Workbook

Sheet Сводная
A1: Период | D1: Итого к перечислению на счет, руб | E1: шт. | H1: Выручка | K1: Себестоимость продаж | L1: Логистика | M1: Комиссия | N1: Хранение | O1: Платная приемка | P1: Штрафы | Q1: Реклама Ozon | R1: Услуги партнёров | S1: Другие услуги и штрафы | T1: Услуги FBO | U1: Компенсировано | V1: Пополнение рекламного кабинета | W1: ЕАЭС | X1: Налог | Y1: Прибыль до вычета налогов | Z1: Прибыль после вычета налогов | AA1: Итог месяц | AB1: % Cебестоимости | AC1: Маржинальность, % | AD1: Рентабельность, % | AE1: Доля рекламы, %
A2: Месяц | B2: Даты | C2: Нед | E2: Заказы | F2: Продажи | G2: Возвраты | H2: Продажи | I2: Возвраты | J2: Общая
A3: Январь | B3: 01-04.01 | C3: 1 | D3: =J3-SUM(L3:T3)+U3+V3 -> 1074.71 | E3: ='Юнит 01-04.01'!K$24 -> 122 | F3: ='Юнит 01-04.01'!P$24 -> 51 | G3: ='Юнит 01-04.01'!Q$24 -> 1 | H3: ='Юнит 01-04.01'!S$24 -> 85937 | I3: ='Юнит 01-04.01'!T$24 -> -1600 | J3: =H3+I3 -> 84337 | K3: ='Юнит 01-04.01'!W$24 -> 6252.96 | L3: ='Юнит 01-04.01'!Z$24 -> 8548.62 | M3: ='Юнит 01-04.01'!X$24 -> 36264.91 | Q3: ='Юнит 01-04.01'!AA$24 -> 36772.95 | R3: 1675.81 | W3: 5252 | X3: =3481.9416*J3/SUM($J$3:$J$7) -> 322.35231 | Y3: =J3-SUM(L3:T3)-K3-V3+U3+W3 -> 73.75 | Z3: =Y3-X3 -> -248.60231 | AA3: =SUM(Z3:Z7) -> 49559.258 | AB3: =K3/J3 -> 0.074142547 | AC3: =Z3/K3 -> -0.039757541 | AD3: =Z3/J3 -> -0.0029477253 | AE3: =Q3/J3 -> 0.43602393
B4: 05-11.01 | C4: 2 | D4: =J4-SUM(L4:T4)+U4+V4 -> 57707.57 | E4: ='Юнит 05-11.01'!K$24 -> 183 | F4: ='Юнит 05-11.01'!P$24 -> 168 | G4: ='Юнит 05-11.01'!Q$24 -> 8 | H4: ='Юнит 05-11.01'!S$24 -> 277715 | I4: ='Юнит 05-11.01'!T$24 -> -13822 | J4: =H4+I4 -> 263893 | K4: ='Юнит 05-11.01'!W$24 -> 20205.96 | L4: ='Юнит 05-11.01'!Z$24 -> 28076.33 | M4: ='Юнит 05-11.01'!X$24 -> 113473.99 | Q4: ='Юнит 05-11.01'!AA$24 -> 56365.38 | R4: 4144.33 | S4: 75 | T4: 4050.4 | X4: =3481.9416*J4/SUM($J$3:$J$7) -> 1008.65 | Y4: =J4-SUM(L4:T4)-K4-V4+U4+W4 -> 37501.61 | Z4: =Y4-X4 -> 36492.96 | AB4: =K4/J4 -> 0.076568761 | AC4: =Z4/K4 -> 1.8060493 | AD4: =Z4/J4 -> 0.13828696 | AE4: =Q4/J4 -> 0.2135918
B5: 12-18.01 | C5: 3 | D5: =J5-SUM(L5:T5)+U5+V5 -> 36064.15 | E5: ='Юнит 12-18.01'!K$24 -> 144 | F5: ='Юнит 12-18.01'!P$24 -> 122 | G5: ='Юнит 12-18.01'!Q$24 -> 2 | H5: ='Юнит 12-18.01'!S$24 -> 211029 | I5: ='Юнит 12-18.01'!T$24 -> -3221 | J5: =H5+I5 -> 207808 | K5: ='Юнит 12-18.01'!W$24 -> 15093.09 | L5: ='Юнит 12-18.01'!Z$24 -> 24172.28 | M5: ='Юнит 12-18.01'!X$24 -> 89357.44 | Q5: ='Юнит 12-18.01'!AA$24 -> 53249.12 | R5: 4025.01 | S5: 0 | T5: 940 | W5: 5135 | X5: =3481.9416*J5/SUM($J$3:$J$7) -> 794.28233 | Y5: =J5-SUM(L5:T5)-K5-V5+U5+W5 -> 26106.06 | Z5: =Y5-X5 -> 25311.778 | AB5: =K5/J5 -> 0.072629976 | AC5: =Z5/K5 -> 1.6770441 | AD5: =Z5/J5 -> 0.12180367 | AE5: =Q5/J5 -> 0.25624192
B6: 19-25.01 | C6: 4 | D6: =J6-SUM(L6:T6)+U6+V6 -> 34413.47 | E6: ='Юнит 19-25.01'!K$24 -> 154 | F6: ='Юнит 19-25.01'!P$24 -> 91 | G6: ='Юнит 19-25.01'!Q$24 -> 2 | H6: ='Юнит 19-25.01'!S$24 -> 161208 | I6: ='Юнит 19-25.01'!T$24 -> -3229 | J6: =H6+I6 -> 157979 | K6: ='Юнит 19-25.01'!W$24 -> 11132.49 | L6: ='Юнит 19-25.01'!Z$24 -> 16989.46 | M6: ='Юнит 19-25.01'!X$24 -> 67930.97 | Q6: ='Юнит 19-25.01'!AA$24 -> 42151.21 | R6: 3468.89 | S6: 25 | V6: 7000 | X6: =3481.9416*J6/SUM($J$3:$J$7) -> 603.82627 | Y6: =J6-SUM(L6:T6)-K6-V6+U6+W6 -> 9280.98 | Z6: =Y6-X6 -> 8677.1537 | AB6: =K6/J6 -> 0.070468163 | AC6: =Z6/K6 -> 0.77944411 | AD6: =Z6/J6 -> 0.054925995 | AE6: =Q6/J6 -> 0.26681527
B7: 26-31.01 | C7: 5 | D7: =J7-SUM(L7:T7)+U7+V7 -> -6034.71 | E7: ='Юнит 26-31.01'!K$24 -> 200 | F7: ='Юнит 26-31.01'!P$24 -> 112 | G7: ='Юнит 26-31.01'!Q$24 -> 2 | H7: ='Юнит 26-31.01'!S$24 -> 200558 | I7: ='Юнит 26-31.01'!T$24 -> -3595 | J7: =H7+I7 -> 196963 | K7: ='Юнит 26-31.01'!W$24 -> 13886.49 | L7: ='Юнит 26-31.01'!Z$24 -> 20843.55 | M7: ='Юнит 26-31.01'!X$24 -> 84694.09 | Q7: ='Юнит 26-31.01'!AA$24 -> 50770.67 | R7: 3661.19 | S7: 150 | T7: 43993.6 | U7: 1115.39 | X7: =3481.9416*J7/SUM($J$3:$J$7) -> 752.83065 | Y7: =J7-SUM(L7:T7)-K7-V7+U7+W7 -> -19921.2 | Z7: =Y7-X7 -> -20674.031 | AB7: =(K7+K8)/(J7+J8) -> 0.070282074 | AC7: =(Z7+Z8)/(K7+K8) -> -0.67605169 | AD7: =(Z7+Z8)/(J7+J8) -> -0.047514315 | AE7: =(Q7+Q8)/(J7+J8) -> 0.25406002
A8: Февраль | B8: 01.02-01.02 | C8: 5 | D8: =J8-SUM(L8:T8)+U8+V8 -> 7323.99 | E8: ='Юнит 01.02'!K$24 -> 36 | F8: ='Юнит 01.02'!P$24 -> 19 | G8: ='Юнит 01.02'!Q$24 -> 1 | H8: ='Юнит 01.02'!S$24 -> 34372 | I8: ='Юнит 01.02'!T$24 -> -1750 | J8: =H8+I8 -> 32622 | K8: ='Юнит 01.02'!W$24 -> 2249.22 | L8: ='Юнит 01.02'!Z$24 -> 3179.52 | M8: ='Юнит 01.02'!X$24 -> 14027.46 | Q8: ='Юнит 01.02'!AA$24 -> 7557.7 | R8: 533.33 | W8: 4831 | X8: =5201.48*J8/SUM($J$8:$J$12) -> 140.3134 | Y8: =J8-SUM(L8:T8)-K8-V8+U8+W8 -> 9905.77 | Z8: =Y8-X8 -> 9765.4566 | AA8: =SUM(Z8:Z12) -> 174317.71
B9: 02.02-08.02 | C9: 6 | D9: =J9-SUM(L9:T9)+U9+V9 -> 40049.95 | E9: ='Юнит 02-08.02'!K$24 -> 225 | F9: ='Юнит 02-08.02'!P$24 -> 167 | G9: ='Юнит 02-08.02'!Q$24 -> 11 | H9: ='Юнит 02-08.02'!S$24 -> 323134 | I9: ='Юнит 02-08.02'!T$24 -> -22524 | J9: =H9+I9 -> 300610 | K9: ='Юнит 02-08.02'!W$24 -> 19848.12 | L9: ='Юнит 02-08.02'!Z$24 -> 31123.53 | M9: ='Юнит 02-08.02'!X$24 -> 129262.3 | Q9: ='Юнит 02-08.02'!AA$24 -> 66736.42 | R9: 5825.9 | T9: 27611.9 | X9: =5201.48*J9/SUM($J$8:$J$12) -> 1292.9806 | Y9: =J9-SUM(L9:T9)-K9-V9+U9+W9 -> 20201.83 | Z9: =Y9-X9 -> 18908.849 | AB9: =K9/J9 -> 0.066026147 | AC9: =Z9/K9 -> 0.9526771 | AD9: =Z9/J9 -> 0.062901598 | AE9: =Q9/J9 -> 0.22200333
B10: 09-15.02 | C10: 7 | D10: =J10-SUM(L10:T10)+U10+V10 -> 62513.5 | E10: ='Юнит 09-15.02'!K$24 -> 240 | F10: ='Юнит 09-15.02'!P$24 -> 125 | G10: ='Юнит 09-15.02'!Q$24 -> 4 | H10: ='Юнит 09-15.02'!S$24 -> 282164 | I10: ='Юнит 09-15.02'!T$24 -> -9000 | J10: =H10+I10 -> 273164 | K10: ='Юнит 09-15.02'!W$24 -> 15306.15 | L10: ='Юнит 09-15.02'!Z$24 -> 24192.27 | M10: ='Юнит 09-15.02'!X$24 -> 117460.52 | Q10: ='Юнит 09-15.02'!AA$24 -> 61070.11 | R10: 5828.6 | S10: 175 | T10: 1924 | X10: =5201.48*J10/SUM($J$8:$J$12) -> 1174.9301 | Y10: =J10-SUM(L10:T10)-K10-V10+U10+W10 -> 47207.35 | Z10: =Y10-X10 -> 46032.42 | AB10: =K10/J10 -> 0.056032823 | AC10: =Z10/K10 -> 3.007446 | AD10: =Z10/J10 -> 0.16851569 | AE10: =Q10/J10 -> 0.22356573
B11: 16-22.02 | C11: 8 | D11: =J11-SUM(L11:T11)+U11+V11 -> 82376.34 | E11: ='Юнит 16-22.02'!K$24 -> 298 | F11: ='Юнит 16-22.02'!P$24 -> 161 | G11: ='Юнит 16-22.02'!Q$24 -> 8 | H11: ='Юнит 16-22.02'!S$24 -> 373392 | I11: ='Юнит 16-22.02'!T$24 -> -18750 | J11: =H11+I11 -> 354642 | K11: ='Юнит 16-22.02'!W$24 -> 19197.06 | L11: ='Юнит 16-22.02'!Z$24 -> 31757.74 | M11: ='Юнит 16-22.02'!X$24 -> 152496.06 | Q11: ='Юнит 16-22.02'!AA$24 -> 79962.77 | R11: 8049.09 | W11: 4347 | X11: =5201.48*J11/SUM($J$8:$J$12) -> 1525.3824 | Y11: =J11-SUM(L11:T11)-K11-V11+U11+W11 -> 67526.28 | Z11: =Y11-X11 -> 66000.898 | AB11: =K11/J11 -> 0.054130814 | AC11: =Z11/K11 -> 3.4380732 | AD11: =Z11/J11 -> 0.1861057 | AE11: =Q11/J11 -> 0.22547462
B12: 23-28.02 | C12: 9 | D12: =J12-SUM(L12:T12)+U12+V12 -> 47866.26 | E12: ='Юнит 23-28.02'!K$24 -> 159 | F12: ='Юнит 23-28.02'!P$24 -> 107 | G12: ='Юнит 23-28.02'!Q$24 -> 6 | H12: ='Юнит 23-28.02'!S$24 -> 262374 | I12: ='Юнит 23-28.02'!T$24 -> -14100 | J12: =H12+I12 -> 248274 | K12: ='Юнит 23-28.02'!W$24 -> 13188.3 | L12: ='Юнит 23-28.02'!Z$24 -> 25365.95 | M12: ='Юнит 23-28.02'!X$24 -> 106757.82 | Q12: ='Юнит 23-28.02'!AA$24 -> 64457.72 | R12: 6407.47 | U12: 2581.22 | X12: =5201.48*J12/SUM($J$8:$J$12) -> 1067.8735 | Y12: =J12-SUM(L12:T12)-K12-V12+U12+W12 -> 34677.96 | Z12: =Y12-X12 -> 33610.086 | AB12: =(K12+K13)/(J12+J13) -> 0.052676864 | AC12: =(Z12+Z13)/(K12+K13) -> 2.4579118 | AD12: =(Z12+Z13)/(J12+J13) -> 0.12947509 | AE12: =(Q12+Q13)/(J12+J13) -> 0.26870709
A13: Март | B13: 46082 | C13: 9 | D13: =J13-SUM(L13:T13)+U13+V13 -> 2695.31 | E13: ='Юнит 01.03'!K$24 -> 36 | F13: ='Юнит 01.03'!P$24 -> 13 | G13: ='Юнит 01.03'!Q$24 -> 1 | H13: ='Юнит 01.03'!S$24 -> 32560 | I13: ='Юнит 01.03'!T$24 -> -2400 | J13: =H13+I13 -> 30160 | K13: ='Юнит 01.03'!W$24 -> 1478.73 | L13: ='Юнит 01.03'!Z$24 -> 3251.78 | M13: ='Юнит 01.03'!X$24 -> 12968.8 | Q13: ='Юнит 01.03'!AA$24 -> 10359.47 | R13: 884.64 | W13: 1350 | X13: ='Юнит 01.03'!$AD$24 -> 126.4 | Y13: =J13-SUM(L13:T13)-K13-V13+U13+W13 -> 2566.58 | Z13: =Y13-X13 -> 2440.18 | AA13: =SUM(Z13:Z18) -> 129879.34
B14: 02.03-08.03 | C14: 10 | D14: =J14-SUM(L14:T14)+U14+V14 -> 31422.07 | E14: ='Юнит 02-08.03'!K$24 -> 179 | F14: ='Юнит 02-08.03'!P$24 -> 93 | G14: ='Юнит 02-08.03'!Q$24 -> 4 | H14: ='Юнит 02-08.03'!S$24 -> 221439 | I14: ='Юнит 02-08.03'!T$24 -> -9910 | J14: =H14+I14 -> 211529 | K14: ='Юнит 02-08.03'!W$24 -> 11497.53 | L14: ='Юнит 02-08.03'!Z$24 -> 18516.49 | M14: ='Юнит 02-08.03'!X$24 -> 90957.47 | Q14: ='Юнит 02-08.03'!AA$24 -> 65685.91 | R14: 4902.06 | S14: 45 | T14: 0 | X14: ='Юнит 02-08.03'!$AD$24 -> 848.57 | Y14: =J14-SUM(L14:T14)-K14-V14+U14+W14 -> 19924.54 | Z14: =Y14-X14 -> 19075.97 | AB14: =(K14+K15)/(J14+J15) -> 0.054517064 | AC14: =(Z14+Z15)/(K14+K15) -> 2.8174678 | AD14: =(Z14+Z15)/(J14+J15) -> 0.15360007 | AE14: =(Q14+Q15)/(J14+J15) -> 0.24591639
B15: 09-15.03 | C15: 11 | D15: =J15-SUM(L15:T15)+U15+V15 -> 61950.07 | E15: ='Юнит 09-15.03'!K$24 -> 156 | F15: ='Юнит 09-15.03'!P$24 -> 97 | G15: ='Юнит 09-15.03'!Q$24 -> 5 | H15: ='Юнит 09-15.03'!S$24 -> 240785 | I15: ='Юнит 09-15.03'!T$24 -> -11873 | J15: =H15+I15 -> 228912 | K15: ='Юнит 09-15.03'!W$24 -> 12514.02 | L15: ='Юнит 09-15.03'!Z$24 -> 20045.39 | M15: ='Юнит 09-15.03'!X$24 -> 98432.16 | Q15: ='Юнит 09-15.03'!AA$24 -> 42625.75 | R15: 5778.63 | S15: 80 | T15: 0 | X15: ='Юнит 09-15.03'!$AD$24 -> 860.25 | Y15: =J15-SUM(L15:T15)-K15-V15+U15+W15 -> 49436.05 | Z15: =Y15-X15 -> 48575.8 | AB15: =(K15+K17)/(J15+J17) -> 0.055790521 | AC15: =(Z15+Z17)/(K15+K17) -> 3.7409589 | AD15: =(Z15+Z17)/(J15+J17) -> 0.20871005 | AE15: =(Q15+Q17)/(J15+J17) -> 0.19505485
B16: 16-22.03 | C16: 12 | D16: =J16-SUM(L16:T16)+U16+V16 -> 41865.51 | E16: ='Юнит 16-22.03'!K$24 -> 109 | F16: ='Юнит 16-22.03'!P$24 -> 61 | G16: ='Юнит 16-22.03'!Q$24 -> 2 | H16: ='Юнит 16-22.03'!S$24 -> 148955 | I16: ='Юнит 16-22.03'!T$24 -> -4939 | J16: =H16+I16 -> 144016 | K16: ='Юнит 16-22.03'!W$24 -> 8173.8 | L16: ='Юнит 16-22.03'!Z$24 -> 13537.32 | M16: ='Юнит 16-22.03'!X$24 -> 61926.88 | Q16: ='Юнит 16-22.03'!AA$24 -> 22870.89 | R16: 3785.4 | S16: 30 | T16: 0 | W16: 1404 | X16: ='Юнит 16-22.03'!$AD$24 -> 662.21 | Y16: =J16-SUM(L16:T16)-K16-V16+U16+W16 -> 35095.71 | Z16: =Y16-X16 -> 34433.5 | AB16: =(K16+K18)/(J16+J18) -> 0.056756194 | AC16: =(Z16+Z18)/(K16+K18) -> 4.2126673 | AD16: =(Z16+Z18)/(J16+J18) -> 0.23909496 | AE16: =(Q16+Q18)/(J16+J18) -> 0.15880798
B17: 23-29.03 | C17: 13 | D17: =J17-SUM(L17:T17)+U17+V17 -> 31815.03 | E17: ='Юнит 23-29.03'!K$24 -> 136 | F17: ='Юнит 23-29.03'!P$24 -> 59 | G17: ='Юнит 23-29.03'!Q$24 -> 5 | H17: ='Юнит 23-29.03'!S$24 -> 135999 | I17: ='Юнит 23-29.03'!T$24 -> -10689 | J17: =H17+I17 -> 125310 | K17: ='Юнит 23-29.03'!W$24 -> 7248.21 | L17: ='Юнит 23-29.03'!Z$24 -> 10759.15 | M17: ='Юнит 23-29.03'!X$24 -> 53883.3 | Q17: ='Юнит 23-29.03'!AA$24 -> 26466.97 | R17: 2330.55 | S17: 55 | T17: 0 | W17: 1404 | X17: ='Юнит 23-29.03'!$AD$24 -> 616.93 | Y17: =J17-SUM(L17:T17)-K17-V17+U17+W17 -> 25970.82 | Z17: =Y17-X17 -> 25353.89
B18: 30-31.03 | C18: 14
A19: Итого | D19: =SUM(D3:D18) -> 533103.22 | E19: =SUM(E3:E18) -> 2377 | F19: =SUM(F3:F18) -> 1446 | G19: =SUM(G3:G18) -> 62 | H19: =SUM(H3:H18) -> 2991621 | I19: =SUM(I3:I18) -> -131402 | J19: =SUM(J3:J18) -> 2860219 | K19: =SUM(K3:K18) -> 177272.13 | ... AA19: =SUM(AA3:AA18) -> 353756.31 | AB19: =K19/J19 -> 0.061978516 | AC19: =Z19/K19 -> 1.9955551 | AD19: =Z19/J19 -> 0.12368155 | AE19: =Q19/J19 -> 0.24022742
H20: % от выручки за весь период
I21: =-I19/H19 -> 0.043923345 | K21: =K19/$J$19 -> 0.061978516 | L21: =L19/$J$19 -> 0.098020249 | M21: =M19/$J$19 -> 0.43 | Q21: =Q19/$J$19 -> 0.24022742 | R21: =R19/$J$19 -> 0.02143224 | S21: =S19/$J$19 -> 0.00022201097 | T21: =T19/$J$19 -> 0.027452408 | U21: =U19/$J$19 -> 0.001292422 | V21: =V19/$J$19 -> 0.002447365 | W21: =W19/$J$19 -> 0.0082941201 | X21: =X19/$J$19 -> 0.0041247826 | Z21: =Z19/K19 -> 1.9955551 | AA21: Маржинальность, % | AB21: =Z19/J19 -> 0.12368155
A23: январь | D23: =SUM(D3:D7) -> 123225.19 | E23: =SUM(E3:E7) -> 803 | F23: =SUM(F3:F7) -> 544 | G23: =SUM(G3:G7) -> 15 | H23: =SUM(H3:H7) -> 936447 | I23: =SUM(I3:I7) -> -25467 | J23: =SUM(J3:J7) -> 910980 | K23: =SUM(K3:K7) -> 66570.99 | ... AA23: =SUM(AA3:AA7) -> 49559.258
I24: =-I23/H23 -> 0.027195346 | K24: =K23/$J$23 -> 0.073076237 | L24: =L23/$J$23 -> 0.10826828 | M24: =M23/$J$23 -> 0.43 | Q24: =Q23/$J$23 -> 0.26269438 | R24: =R23/$J$23 -> 0.018634031 | S24: =S23/$J$23 -> 0.00027442974 | T24: =T23/$J$23 -> 0.053770665 | V24: =V23/$J$23 -> 0.0076840326 | W24: =W23/$J$23 -> 0.011402007 | X24: =X23/$J$23 -> 0.0038221932 | Y24: =Y23/J23 -> 0.05822433 | Z24: =Z23/J23 -> 0.054402137 | AA24: =AA23/J23 -> 0.054402137
A26: 5 неделя | K26: =(K7+K8)/($J$7+$J$8) -> 0.070282074 | L26: =(L7+L8)/($J$7+$J$8) -> 0.10463693 | M26: =(M7+M8)/($J$7+$J$8) -> 0.43 | N26: =(N7+N8)/($J$7+$J$8) -> 0 | O26: =(O7+O8)/($J$7+$J$8) -> 0 | P26: =(P7+P8)/($J$7+$J$8) -> 0 | Q26: =(Q7+Q8)/($J$7+$J$8) -> 0.25406002 | R26: =(R7+S7+T7+R8+S8+T8)/($J$7+$J$8) -> 0.21054564 | U26: =(U7+U8)/($J$7+$J$8) -> 0.0048582878 | V26: =(V7+V8)/($J$7+$J$8) -> 0 | W26: =(W7+W8)/($J$7+$J$8) -> 0.021042315 | X26: =(X7+X8)/($J$7+$J$8) -> 0.0038902544 | Y26: =(Y7+Y8)/($J$7+$J$8) -> -0.043624061 | Z26: =(Z7+Z8)/($J$7+$J$8) -> -0.047514315
A27: 6 неделя | K27: =K9/$J$9 -> 0.066026147 | L27: =L9/$J$9 -> 0.10353458 | M27: =M9/$J$9 -> 0.43 | Q27: =Q9/$J$9 -> 0.22200333 | R27: =(R9+S9+T9)/$J$9 -> 0.11123316 | V27: =V9/$J$9 -> 0 | W27: =W9/$J$9 -> 0 | X27: =X9/$J$9 -> 0.0043011894 | Y27: =Y9/J9 -> 0.067202788 | Z27: =Z9/J9 -> 0.062901598
A28: 7 неделя | K28: =K10/$J$10 -> 0.056032823 | L28: =L10/$J$10 -> 0.088563171 | M28: =M10/$J$10 -> 0.43 | Q28: =Q10/$J$10 -> 0.22356573 | R28: =(R10+S10+T10)/$J$10 -> 0.029021394 | V28: =V10/$J$10 -> 0 | W28: =W10/$J$10 -> 0 | X28: =X10/$J$10 -> 0.0043011894 | Y28: =Y10/J10 -> 0.17281688 | Z28: =Z10/J10 -> 0.16851569
A29: 8 неделя | K29: =K11/$J$11 -> 0.054130814 | L29: =L11/$J$11 -> 0.089548728 | M29: =M11/$J$11 -> 0.43 | Q29: =Q11/$J$11 -> 0.22547462 | R29: =(R11+S11+T11)/$J$11 -> 0.022696381 | V29: =V11/$J$11 -> 0 | W29: =W11/$J$11 -> 0.012257431 | X29: =X11/$J$11 -> 0.0043011894 | Y29: =Y11/J11 -> 0.19040689 | Z29: =Z11/J11 -> 0.1861057
A30: 9 неделя | K30: =(K12+K13)/($J$12+$J$13) -> 0.052676864 | L30: =(L12+L13)/($J$12+$J$13) -> 0.10278102 | M30: =(M12+M13)/($J$12+$J$13) -> 0.43 | N30: =(N12+N13)/($J$12+$J$13) -> 0 | O30: =(O12+O13)/($J$12+$J$13) -> 0 | P30: =(P12+P13)/($J$12+$J$13) -> 0 | Q30: =(Q12+Q13)/($J$12+$J$13) -> 0.26870709 | R30: =(R12+R13)/($J$12+$J$13) -> 0.026189725 | V30: =(V12+V13)/($J$12+$J$13) -> 0 | W30: =(W12+W13)/($J$12+$J$13) -> 0.0048485458 | X30: =(X12+X13)/($J$12+$J$13) -> 0.0042892517 | Y30: =(Y12+Y13)/($J$12+$J$13) -> 0.13376434 | Z30: =(Z12+Z13)/($J$12+$J$13) -> 0.12947509
A32: февраль | D32: =SUM(D8:D12) -> 240130.04 | E32: =SUM(E8:E12) -> 958 | F32: =SUM(F8:F12) -> 579 | G32: =SUM(G8:G12) -> 30 | H32: =SUM(H8:H12) -> 1275436 | I32: =SUM(I8:I12) -> -66124 | J32: =SUM(J8:J12) -> 1209312 | K32: =SUM(K8:K12) -> 69788.85 | ... AA32: =SUM(AA8:AA12) -> 174317.71
A34: март | D34: =SUM(D13:D18) -> 169747.99 | E34: =SUM(E13:E18) -> 616 | F34: =SUM(F13:F18) -> 323 | G34: =SUM(G13:G18) -> 17 | H34: =SUM(H13:H18) -> 779738 | I34: =SUM(I13:I18) -> -39811 | J34: =SUM(J13:J18) -> 739927 | K34: =SUM(K13:K18) -> 40912.29 | ... AA34: =SUM(AA13:AA18) -> 129879.34

Sheet АВС МАРТ
B2: ОЧКИ
C3: Прибыль | D3: % прибыль | E3: Доля | F3: ABC прибыль | G3: ABC кол-во | J3: Кол-во | K3: % кол-во | L3: Доля | M3: ABC кол-во
B4: черные с железкой классика | D4: =C4/C$18 -> #DIV/0! | E4: =D4 -> #DIV/0! | F4: =IF(AND(E4<=0),"C",IF(E4<=0.8,"A",IF(E4<=0.95,"B","C"))) -> #DIV/0! | G4: =VLOOKUP(B$4:B$17,I$4:M$17,5,0) -> #DIV/0! | I4: черные с железкой классика | K4: =J4/J$18 -> #DIV/0! | L4: =K4 -> #DIV/0! | M4: =_xlfn.IFS(L4<80%,"A",L4<=95%,"B",L4>95%,"C") -> #DIV/0!
B5: qs черные | D5: =C5/C$18 -> #DIV/0! | E5: =D5+E4 -> #DIV/0! | F5: =IF(AND(E5<=0),"C",IF(E5<=0.8,"A",IF(E5<=0.95,"B","C"))) -> #DIV/0! | G5: =VLOOKUP(B$4:B$17,I$4:M$17,5,0) -> #DIV/0! | I5: qs черные | K5: =J5/J$18 -> #DIV/0! | L5: =K5+L4 -> #DIV/0! | M5: =_xlfn.IFS(L5<80%,"A",L5<=95%,"B",L5>95%,"C") -> #DIV/0!
B6: qs синие | D6: =C6/C$18 -> #DIV/0! | E6: =D6+E5 -> #DIV/0! | F6: =IF(AND(E6<=0),"C",IF(E6<=0.8,"A",IF(E6<=0.95,"B","C"))) -> #DIV/0! | G6: =VLOOKUP(B$4:B$17,I$4:M$17,5,0) -> #DIV/0! | I6: qs синие | K6: =J6/J$18 -> #DIV/0! | L6: =K6+L5 -> #DIV/0! | M6: =_xlfn.IFS(L6<80%,"A",L6<=95%,"B",L6>95%,"C") -> #DIV/0!
B7: qs желтые | D7: =C7/C$18 -> #DIV/0! | E7: =D7+E6 -> #DIV/0! | F7: =IF(AND(E7<=0),"C",IF(E7<=0.8,"A",IF(E7<=0.95,"B","C"))) -> #DIV/0! | G7: =VLOOKUP(B$4:B$17,I$4:M$17,5,0) -> #DIV/0! | I7: qs желтые | K7: =J7/J$18 -> #DIV/0! | L7: =K7+L6 -> #DIV/0! | M7: =_xlfn.IFS(L7<80%,"A",L7<=95%,"B",L7>95%,"C") -> #DIV/0!
B8: qs коричневые | D8: =C8/C$18 -> #DIV/0! | E8: =D8+E7 -> #DIV/0! | F8: =IF(AND(E8<=0),"C",IF(E8<=0.8,"A",IF(E8<=0.95,"B","C"))) -> #DIV/0! | G8: =VLOOKUP(B$4:B$17,I$4:M$17,5,0) -> #DIV/0! | I8: qs коричневые | K8: =J8/J$18 -> #DIV/0! | L8: =K8+L7 -> #DIV/0! | M8: =_xlfn.IFS(L8<80%,"A",L8<=95%,"B",L8>95%,"C") -> #DIV/0!
B9: MR8854 C2 | D9: =C9/C$18 -> #DIV/0! | E9: =D9+E8 -> #DIV/0! | F9: =IF(AND(E9<=0),"C",IF(E9<=0.8,"A",IF(E9<=0.95,"B","C"))) -> #DIV/0! | G9: =VLOOKUP(B$4:B$17,I$4:M$17,5,0) -> #DIV/0! | I9: MR8854 C2 | K9: =J9/J$18 -> #DIV/0! | L9: =K9+L8 -> #DIV/0! | M9: =_xlfn.IFS(L9<80%,"A",L9<=95%,"B",L9>95%,"C") -> #DIV/0!
B10: th черн | D10: =C10/C$18 -> #DIV/0! | E10: =D10+E9 -> #DIV/0! | F10: =IF(AND(E10<=0),"C",IF(E10<=0.8,"A",IF(E10<=0.95,"B","C"))) -> #DIV/0! | G10: =VLOOKUP(B$4:B$17,I$4:M$17,5,0) -> #DIV/0! | I10: th черн | K10: =J10/J$18 -> #DIV/0! | L10: =K10+L9 -> #DIV/0! | M10: =_xlfn.IFS(L10<80%,"A",L10<=95%,"B",L10>95%,"C") -> #DIV/0!
B11: th син | D11: =C11/C$18 -> #DIV/0! | E11: =D11+E10 -> #DIV/0! | F11: =IF(AND(E11<=0),"C",IF(E11<=0.8,"A",IF(E11<=0.95,"B","C"))) -> #DIV/0! | G11: =VLOOKUP(B$4:B$17,I$4:M$17,5,0) -> #DIV/0! | I11: th син | K11: =J11/J$18 -> #DIV/0! | L11: =K11+L10 -> #DIV/0! | M11: =_xlfn.IFS(L11<80%,"A",L11<=95%,"B",L11>95%,"C") -> #DIV/0!
B12: th желт | D12: =C12/C$18 -> #DIV/0! | E12: =D12+E5 -> #DIV/0! | F12: =IF(AND(E12<=0),"C",IF(E12<=0.8,"A",IF(E12<=0.95,"B","C"))) -> #DIV/0! | G12: =VLOOKUP(B$4:B$17,I$4:M$17,5,0) -> #DIV/0! | I12: th желт | K12: =J12/J$18 -> #DIV/0! | L12: =K12+L5 -> #DIV/0! | M12: =_xlfn.IFS(L12<80%,"A",L12<=95%,"B",L12>95%,"C") -> #DIV/0!
B13: th коричн | D13: =C13/C$18 -> #DIV/0! | E13: =D13+E12 -> #DIV/0! | F13: =IF(AND(E13<=0),"C",IF(E13<=0.8,"A",IF(E13<=0.95,"B","C"))) -> #DIV/0! | G13: =VLOOKUP(B$4:B$17,I$4:M$17,5,0) -> #DIV/0! | I13: th коричн | K13: =J13/J$18 -> #DIV/0! | L13: =K13+L12 -> #DIV/0! | M13: =_xlfn.IFS(L13<80%,"A",L13<=95%,"B",L13>95%,"C") -> #DIV/0!
B14: flip черный | D14: =C14/C$18 -> #DIV/0! | E14: =D14+E13 -> #DIV/0! | F14: =IF(AND(E14<=0),"C",IF(E14<=0.8,"A",IF(E14<=0.95,"B","C"))) -> #DIV/0! | G14: =VLOOKUP(B$4:B$17,I$4:M$17,5,0) -> #DIV/0! | I14: flip черный | K14: =J14/J$18 -> #DIV/0! | L14: =K14+L13 -> #DIV/0! | M14: =_xlfn.IFS(L14<80%,"A",L14<=95%,"B",L14>95%,"C") -> #DIV/0!
B15: flip синий | D15: =C15/C$18 -> #DIV/0! | E15: =D15+E14 -> #DIV/0! | F15: =IF(AND(E15<=0),"C",IF(E15<=0.8,"A",IF(E15<=0.95,"B","C"))) -> #DIV/0! | G15: =VLOOKUP(B$4:B$17,I$4:M$17,5,0) -> #DIV/0! | I15: flip синий | K15: =J15/J$18 -> #DIV/0! | L15: =K15+L14 -> #DIV/0! | M15: =_xlfn.IFS(L15<80%,"A",L15<=95%,"B",L15>95%,"C") -> #DIV/0!
B16: flip жел | D16: =C16/C$18 -> #DIV/0! | E16: =D16+E15 -> #DIV/0! | F16: =IF(AND(E16<=0),"C",IF(E16<=0.8,"A",IF(E16<=0.95,"B","C"))) -> #DIV/0! | G16: =VLOOKUP(B$4:B$17,I$4:M$17,5,0) -> #DIV/0! | I16: flip жел | K16: =J16/J$18 -> #DIV/0! | L16: =K16+L15 -> #DIV/0! | M16: =_xlfn.IFS(L16<80%,"A",L16<=95%,"B",L16>95%,"C") -> #DIV/0!
B17: flip коричневый | D17: =C17/C$18 -> #DIV/0! | E17: =D17+E14 -> #DIV/0! | F17: =IF(AND(E17<=0),"C",IF(E17<=0.8,"A",IF(E17<=0.95,"B","C"))) -> #DIV/0! | G17: =VLOOKUP(B$4:B$17,I$4:M$17,5,0) -> #DIV/0! | I17: flip коричневый | K17: =J17/J$18 -> #DIV/0! | L17: =K17+L14 -> #DIV/0! | M17: =_xlfn.IFS(L17<80%,"A",L17<=95%,"B",L17>95%,"C") -> #DIV/0!
C18: =SUM(C4:C17) -> 0 | D18: =SUM(D4:D17) -> #DIV/0! | J18: =SUM(J4:J17) -> 0 | K18: =SUM(K4:K17) -> #DIV/0!
C21: Прибыль | D21: % прибыль | E21: Доля | F21: ABC прибыль | G21: ABC кол-во | J21: Кол-во | K21: % кол-во | L21: Доля | M21: ABC кол-во
D22: =C22/C$42 -> #DIV/0! | E22: =D22 -> #DIV/0! | F22: =IF(AND(E22<=0),"C",IF(E22<=0.8,"A",IF(E22<=0.95,"B","C"))) -> #DIV/0! | G22: =VLOOKUP(B$22:B$42,I$22:M$42,5,0) -> #N/A | K22: =J22/J$42 -> #DIV/0! | L22: =K22 -> #DIV/0! | M22: =_xlfn.IFS(L22<80%,"A",L22<=95%,"B",L22>95%,"C") -> #DIV/0!
D23: =C23/C$42 -> #DIV/0! | E23: =D23+E22 -> #DIV/0! | F23: =IF(AND(E23<=0),"C",IF(E23<=0.8,"A",IF(E23<=0.95,"B","C"))) -> #DIV/0! | G23: =VLOOKUP(B$22:B$42,I$22:M$42,5,0) -> #N/A | K23: =J23/J$42 -> #DIV/0! | L23: =K23+L22 -> #DIV/0! | M23: =_xlfn.IFS(L23<80%,"A",L23<=95%,"B",L23>95%,"C") -> #DIV/0!
D24: =C24/C$42 -> #DIV/0! | E24: =D24+E23 -> #DIV/0! | F24: =IF(AND(E24<=0),"C",IF(E24<=0.8,"A",IF(E24<=0.95,"B","C"))) -> #DIV/0! | G24: =VLOOKUP(B$22:B$42,I$22:M$42,5,0) -> #N/A | K24: =J24/J$42 -> #DIV/0! | L24: =K24+L23 -> #DIV/0! | M24: =_xlfn.IFS(L24<80%,"A",L24<=95%,"B",L24>95%,"C") -> #DIV/0!
D25: =C25/C$42 -> #DIV/0! | E25: =D25+E24 -> #DIV/0! | F25: =IF(AND(E25<=0),"C",IF(E25<=0.8,"A",IF(E25<=0.95,"B","C"))) -> #DIV/0! | G25: =VLOOKUP(B$22:B$42,I$22:M$42,5,0) -> #N/A | K25: =J25/J$42 -> #DIV/0! | L25: =K25+L24 -> #DIV/0! | M25: =_xlfn.IFS(L25<80%,"A",L25<=95%,"B",L25>95%,"C") -> #DIV/0!
D26: =C26/C$42 -> #DIV/0! | E26: =D26+E25 -> #DIV/0! | F26: =IF(AND(E26<=0),"C",IF(E26<=0.8,"A",IF(E26<=0.95,"B","C"))) -> #DIV/0! | G26: =VLOOKUP(B$22:B$42,I$22:M$42,5,0) -> #N/A | K26: =J26/J$42 -> #DIV/0! | L26: =K26+L25 -> #DIV/0! | M26: =_xlfn.IFS(L26<80%,"A",L26<=95%,"B",L26>95%,"C") -> #DIV/0!
D27: =C27/C$42 -> #DIV/0! | E27: =D27+E26 -> #DIV/0! | F27: =IF(AND(E27<=0),"C",IF(E27<=0.8,"A",IF(E27<=0.95,"B","C"))) -> #DIV/0! | G27: =VLOOKUP(B$22:B$42,I$22:M$42,5,0) -> #N/A | K27: =J27/J$42 -> #DIV/0! | L27: =K27+L26 -> #DIV/0! | M27: =_xlfn.IFS(L27<80%,"A",L27<=95%,"B",L27>95%,"C") -> #DIV/0!
D28: =C28/C$42 -> #DIV/0! | E28: =D28+E27 -> #DIV/0! | F28: =IF(AND(E28<=0),"C",IF(E28<=0.8,"A",IF(E28<=0.95,"B","C"))) -> #DIV/0! | G28: =VLOOKUP(B$22:B$42,I$22:M$42,5,0) -> #N/A | K28: =J28/J$42 -> #DIV/0! | L28: =K28+L27 -> #DIV/0! | M28: =_xlfn.IFS(L28<80%,"A",L28<=95%,"B",L28>95%,"C") -> #DIV/0!
D29: =C29/C$42 -> #DIV/0! | E29: =D29+E28 -> #DIV/0! | F29: =IF(AND(E29<=0),"C",IF(E29<=0.8,"A",IF(E29<=0.95,"B","C"))) -> #DIV/0! | G29: =VLOOKUP(B$22:B$42,I$22:M$42,5,0) -> #N/A | K29: =J29/J$42 -> #DIV/0! | L29: =K29+L28 -> #DIV/0! | M29: =_xlfn.IFS(L29<80%,"A",L29<=95%,"B",L29>95%,"C") -> #DIV/0!
D30: =C30/C$42 -> #DIV/0! | E30: =D30+E29 -> #DIV/0! | F30: =IF(AND(E30<=0),"C",IF(E30<=0.8,"A",IF(E30<=0.95,"B","C"))) -> #DIV/0! | G30: =VLOOKUP(B$22:B$42,I$22:M$42,5,0) -> #N/A | K30: =J30/J$42 -> #DIV/0! | L30: =K30+L29 -> #DIV/0! | M30: =_xlfn.IFS(L30<80%,"A",L30<=95%,"B",L30>95%,"C") -> #DIV/0!
D31: =C31/C$42 -> #DIV/0! | E31: =D31+E30 -> #DIV/0! | F31: =IF(AND(E31<=0),"C",IF(E31<=0.8,"A",IF(E31<=0.95,"B","C"))) -> #DIV/0! | G31: =VLOOKUP(B$22:B$42,I$22:M$42,5,0) -> #N/A | K31: =J31/J$42 -> #DIV/0! | L31: =K31+L30 -> #DIV/0! | M31: =_xlfn.IFS(L31<80%,"A",L31<=95%,"B",L31>95%,"C") -> #DIV/0!
D32: =C32/C$42 -> #DIV/0! | E32: =D32+E31 -> #DIV/0! | F32: =IF(AND(E32<=0),"C",IF(E32<=0.8,"A",IF(E32<=0.95,"B","C"))) -> #DIV/0! | G32: =VLOOKUP(B$22:B$42,I$22:M$42,5,0) -> #N/A | K32: =J32/J$42 -> #DIV/0! | L32: =K32+L31 -> #DIV/0! | M32: =_xlfn.IFS(L32<80%,"A",L32<=95%,"B",L32>95%,"C") -> #DIV/0!
D33: =C33/C$42 -> #DIV/0! | E33: =D33+E32 -> #DIV/0! | F33: =IF(AND(E33<=0),"C",IF(E33<=0.8,"A",IF(E33<=0.95,"B","C"))) -> #DIV/0! | G33: =VLOOKUP(B$22:B$42,I$22:M$42,5,0) -> #N/A | K33: =J33/J$42 -> #DIV/0! | L33: =K33+L32 -> #DIV/0! | M33: =_xlfn.IFS(L33<80%,"A",L33<=95%,"B",L33>95%,"C") -> #DIV/0!
D34: =C34/C$42 -> #DIV/0! | E34: =D34+E33 -> #DIV/0! | F34: =IF(AND(E34<=0),"C",IF(E34<=0.8,"A",IF(E34<=0.95,"B","C"))) -> #DIV/0! | G34: =VLOOKUP(B$22:B$42,I$22:M$42,5,0) -> #N/A | K34: =J34/J$42 -> #DIV/0! | L34: =K34+L33 -> #DIV/0! | M34: =_xlfn.IFS(L34<80%,"A",L34<=95%,"B",L34>95%,"C") -> #DIV/0!
... D41: =C41/C$42 -> #DIV/0! | E41: =D41+E40 -> #DIV/0! | F41: =IF(AND(E41<=0),"C",IF(E41<=0.8,"A",IF(E41<=0.95,"B","C"))) -> #DIV/0! | G41: =VLOOKUP(B$22:B$42,I$22:M$42,5,0) -> #N/A | K41: =J41/J$42 -> #DIV/0! | L41: =K41+L40 -> #DIV/0! | M41: =_xlfn.IFS(L41<80%,"A",L41<=95%,"B",L41>95%,"C") -> #DIV/0!
C42: =SUM(C22:C41) -> 0 | D42: =SUM(D22:D41) -> #DIV/0! | J42: =SUM(J22:J41) -> 0 | K42: =SUM(K22:K41) -> #DIV/0!

Sheet АВС 30-31.03
B2: ОЧКИ
C3: Прибыль | D3: % прибыль | E3: Доля | F3: ABC прибыль | G3: ABC кол-во | J3: Кол-во | K3: % кол-во | L3: Доля | M3: ABC кол-во
B4: черные с железкой классика | D4: =C4/C$18 -> #DIV/0! | E4: =D4 -> #DIV/0! | F4: =IF(AND(E4<=0),"C",IF(E4<=0.8,"A",IF(E4<=0.95,"B","C"))) -> #DIV/0! | G4: =VLOOKUP(B$4:B$17,I$4:M$17,5,0) -> #DIV/0! | I4: черные с железкой классика | K4: =J4/J$18 -> #DIV/0! | L4: =K4 -> #DIV/0! | M4: =_xlfn.IFS(L4<80%,"A",L4<=95%,"B",L4>95%,"C") -> #DIV/0!
B5: qs черные | D5: =C5/C$18 -> #DIV/0! | E5: =D5+E4 -> #DIV/0! | F5: =IF(AND(E5<=0),"C",IF(E5<=0.8,"A",IF(E5<=0.95,"B","C"))) -> #DIV/0! | G5: =VLOOKUP(B$4:B$17,I$4:M$17,5,0) -> #DIV/0! | I5: qs черные | K5: =J5/J$18 -> #DIV/0! | L5: =K5+L4 -> #DIV/0! | M5: =_xlfn.IFS(L5<80%,"A",L5<=95%,"B",L5>95%,"C") -> #DIV/0!
B6: qs синие | D6: =C6/C$18 -> #DIV/0! | E6: =D6+E5 -> #DIV/0! | F6: =IF(AND(E6<=0),"C",IF(E6<=0.8,"A",IF(E6<=0.95,"B","C"))) -> #DIV/0! | G6: =VLOOKUP(B$4:B$17,I$4:M$17,5,0) -> #DIV/0! | I6: qs синие | K6: =J6/J$18 -> #DIV/0! | L6: =K6+L5 -> #DIV/0! | M6: =_xlfn.IFS(L6<80%,"A",L6<=95%,"B",L6>95%,"C") -> #DIV/0!
B7: qs желтые | D7: =C7/C$18 -> #DIV/0! | E7: =D7+E6 -> #DIV/0! | F7: =IF(AND(E7<=0),"C",IF(E7<=0.8,"A",IF(E7<=0.95,"B","C"))) -> #DIV/0! | G7: =VLOOKUP(B$4:B$17,I$4:M$17,5,0) -> #DIV/0! | I7: qs желтые | K7: =J7/J$18 -> #DIV/0! | L7: =K7+L6 -> #DIV/0! | M7: =_xlfn.IFS(L7<80%,"A",L7<=95%,"B",L7>95%,"C") -> #DIV/0!
B8: qs коричневые | D8: =C8/C$18 -> #DIV/0! | E8: =D8+E7 -> #DIV/0! | F8: =IF(AND(E8<=0),"C",IF(E8<=0.8,"A",IF(E8<=0.95,"B","C"))) -> #DIV/0! | G8: =VLOOKUP(B$4:B$17,I$4:M$17,5,0) -> #DIV/0! | I8: qs коричневые | K8: =J8/J$18 -> #DIV/0! | L8: =K8+L7 -> #DIV/0! | M8: =_xlfn.IFS(L8<80%,"A",L8<=95%,"B",L8>95%,"C") -> #DIV/0!
B9: MR8854 C2 | D9: =C9/C$18 -> #DIV/0! | E9: =D9+E8 -> #DIV/0! | F9: =IF(AND(E9<=0),"C",IF(E9<=0.8,"A",IF(E9<=0.95,"B","C"))) -> #DIV/0! | G9: =VLOOKUP(B$4:B$17,I$4:M$17,5,0) -> #DIV/0! | I9: MR8854 C2 | K9: =J9/J$18 -> #DIV/0! | L9: =K9+L8 -> #DIV/0! | M9: =_xlfn.IFS(L9<80%,"A",L9<=95%,"B",L9>95%,"C") -> #DIV/0!
B10: th черн | D10: =C10/C$18 -> #DIV/0! | E10: =D10+E9 -> #DIV/0! | F10: =IF(AND(E10<=0),"C",IF(E10<=0.8,"A",IF(E10<=0.95,"B","C"))) -> #DIV/0! | G10: =VLOOKUP(B$4:B$17,I$4:M$17,5,0) -> #DIV/0! | I10: th черн | K10: =J10/J$18 -> #DIV/0! | L10: =K10+L9 -> #DIV/0! | M10: =_xlfn.IFS(L10<80%,"A",L10<=95%,"B",L10>95%,"C") -> #DIV/0!
B11: th син | D11: =C11/C$18 -> #DIV/0! | E11: =D11+E10 -> #DIV/0! | F11: =IF(AND(E11<=0),"C",IF(E11<=0.8,"A",IF(E11<=0.95,"B","C"))) -> #DIV/0! | G11: =VLOOKUP(B$4:B$17,I$4:M$17,5,0) -> #DIV/0! | I11: th син | K11: =J11/J$18 -> #DIV/0! | L11: =K11+L10 -> #DIV/0! | M11: =_xlfn.IFS(L11<80%,"A",L11<=95%,"B",L11>95%,"C") -> #DIV/0!
B12: th желт | D12: =C12/C$18 -> #DIV/0! | E12: =D12+E5 -> #DIV/0! | F12: =IF(AND(E12<=0),"C",IF(E12<=0.8,"A",IF(E12<=0.95,"B","C"))) -> #DIV/0! | G12: =VLOOKUP(B$4:B$17,I$4:M$17,5,0) -> #DIV/0! | I12: th желт | K12: =J12/J$18 -> #DIV/0! | L12: =K12+L5 -> #DIV/0! | M12: =_xlfn.IFS(L12<80%,"A",L12<=95%,"B",L12>95%,"C") -> #DIV/0!
B13: th коричн | D13: =C13/C$18 -> #DIV/0! | E13: =D13+E12 -> #DIV/0! | F13: =IF(AND(E13<=0),"C",IF(E13<=0.8,"A",IF(E13<=0.95,"B","C"))) -> #DIV/0! | G13: =VLOOKUP(B$4:B$17,I$4:M$17,5,0) -> #DIV/0! | I13: th коричн | K13: =J13/J$18 -> #DIV/0! | L13: =K13+L12 -> #DIV/0! | M13: =_xlfn.IFS(L13<80%,"A",L13<=95%,"B",L13>95%,"C") -> #DIV/0!
B14: flip черный | D14: =C14/C$18 -> #DIV/0! | E14: =D14+E13 -> #DIV/0! | F14: =IF(AND(E14<=0),"C",IF(E14<=0.8,"A",IF(E14<=0.95,"B","C"))) -> #DIV/0! | G14: =VLOOKUP(B$4:B$17,I$4:M$17,5,0) -> #DIV/0! | I14: flip черный | K14: =J14/J$18 -> #DIV/0! | L14: =K14+L13 -> #DIV/0! | M14: =_xlfn.IFS(L14<80%,"A",L14<=95%,"B",L14>95%,"C") -> #DIV/0!
B15: flip синий | D15: =C15/C$18 -> #DIV/0! | E15: =D15+E14 -> #DIV/0! | F15: =IF(AND(E15<=0),"C",IF(E15<=0.8,"A",IF(E15<=0.95,"B","C"))) -> #DIV/0! | G15: =VLOOKUP(B$4:B$17,I$4:M$17,5,0) -> #DIV/0! | I15: flip синий | K15: =J15/J$18 -> #DIV/0! | L15: =K15+L14 -> #DIV/0! | M15: =_xlfn.IFS(L15<80%,"A",L15<=95%,"B",L15>95%,"C") -> #DIV/0!
B16: flip жел | D16: =C16/C$18 -> #DIV/0! | E16: =D16+E15 -> #DIV/0! | F16: =IF(AND(E16<=0),"C",IF(E16<=0.8,"A",IF(E16<=0.95,"B","C"))) -> #DIV/0! | G16: =VLOOKUP(B$4:B$17,I$4:M$17,5,0) -> #DIV/0! | I16: flip жел | K16: =J16/J$18 -> #DIV/0! | L16: =K16+L15 -> #DIV/0! | M16: =_xlfn.IFS(L16<80%,"A",L16<=95%,"B",L16>95%,"C") -> #DIV/0!
B17: flip коричневый | D17: =C17/C$18 -> #DIV/0! | E17: =D17+E14 -> #DIV/0! | F17: =IF(AND(E17<=0),"C",IF(E17<=0.8,"A",IF(E17<=0.95,"B","C"))) -> #DIV/0! | G17: =VLOOKUP(B$4:B$17,I$4:M$17,5,0) -> #DIV/0! | I17: flip коричневый | K17: =J17/J$18 -> #DIV/0! | L17: =K17+L14 -> #DIV/0! | M17: =_xlfn.IFS(L17<80%,"A",L17<=95%,"B",L17>95%,"C") -> #DIV/0!
C18: =SUM(C4:C17) -> 0 | D18: =SUM(D4:D17) -> #DIV/0! | J18: =SUM(J4:J17) -> 0 | K18: =SUM(K4:K17) -> #DIV/0!
C21: Прибыль | D21: % прибыль | E21: Доля | F21: ABC прибыль | G21: ABC кол-во | J21: Кол-во | K21: % кол-во | L21: Доля | M21: ABC кол-во
D22: =C22/C$42 -> #DIV/0! | E22: =D22 -> #DIV/0! | F22: =IF(AND(E22<=0),"C",IF(E22<=0.8,"A",IF(E22<=0.95,"B","C"))) -> #DIV/0! | G22: =VLOOKUP(B$22:B$42,I$22:M$42,5,0) -> #N/A | K22: =J22/J$42 -> #DIV/0! | L22: =K22 -> #DIV/0! | M22: =_xlfn.IFS(L22<80%,"A",L22<=95%,"B",L22>95%,"C") -> #DIV/0!
D23: =C23/C$42 -> #DIV/0! | E23: =D23+E22 -> #DIV/0! | F23: =IF(AND(E23<=0),"C",IF(E23<=0.8,"A",IF(E23<=0.95,"B","C"))) -> #DIV/0! | G23: =VLOOKUP(B$22:B$42,I$22:M$42,5,0) -> #N/A | K23: =J23/J$42 -> #DIV/0! | L23: =K23+L22 -> #DIV/0! | M23: =_xlfn.IFS(L23<80%,"A",L23<=95%,"B",L23>95%,"C") -> #DIV/0!
D24: =C24/C$42 -> #DIV/0! | E24: =D24+E23 -> #DIV/0! | F24: =IF(AND(E24<=0),"C",IF(E24<=0.8,"A",IF(E24<=0.95,"B","C"))) -> #DIV/0! | G24: =VLOOKUP(B$22:B$42,I$22:M$42,5,0) -> #N/A | K24: =J24/J$42 -> #DIV/0! | L24: =K24+L23 -> #DIV/0! | M24: =_xlfn.IFS(L24<80%,"A",L24<=95%,"B",L24>95%,"C") -> #DIV/0!
D25: =C25/C$42 -> #DIV/0! | E25: =D25+E24 -> #DIV/0! | F25: =IF(AND(E25<=0),"C",IF(E25<=0.8,"A",IF(E25<=0.95,"B","C"))) -> #DIV/0! | G25: =VLOOKUP(B$22:B$42,I$22:M$42,5,0) -> #N/A | K25: =J25/J$42 -> #DIV/0! | L25: =K25+L24 -> #DIV/0! | M25: =_xlfn.IFS(L25<80%,"A",L25<=95%,"B",L25>95%,"C") -> #DIV/0!
D26: =C26/C$42 -> #DIV/0! | E26: =D26+E25 -> #DIV/0! | F26: =IF(AND(E26<=0),"C",IF(E26<=0.8,"A",IF(E26<=0.95,"B","C"))) -> #DIV/0! | G26: =VLOOKUP(B$22:B$42,I$22:M$42,5,0) -> #N/A | K26: =J26/J$42 -> #DIV/0! | L26: =K26+L25 -> #DIV/0! | M26: =_xlfn.IFS(L26<80%,"A",L26<=95%,"B",L26>95%,"C") -> #DIV/0!
D27: =C27/C$42 -> #DIV/0! | E27: =D27+E26 -> #DIV/0! | F27: =IF(AND(E27<=0),"C",IF(E27<=0.8,"A",IF(E27<=0.95,"B","C"))) -> #DIV/0! | G27: =VLOOKUP(B$22:B$42,I$22:M$42,5,0) -> #N/A | K27: =J27/J$42 -> #DIV/0! | L27: =K27+L26 -> #DIV/0! | M27: =_xlfn.IFS(L27<80%,"A",L27<=95%,"B",L27>95%,"C") -> #DIV/0!
D28: =C28/C$42 -> #DIV/0! | E28: =D28+E27 -> #DIV/0! | F28: =IF(AND(E28<=0),"C",IF(E28<=0.8,"A",IF(E28<=0.95,"B","C"))) -> #DIV/0! | G28: =VLOOKUP(B$22:B$42,I$22:M$42,5,0) -> #N/A | K28: =J28/J$42 -> #DIV/0! | L28: =K28+L27 -> #DIV/0! | M28: =_xlfn.IFS(L28<80%,"A",L28<=95%,"B",L28>95%,"C") -> #DIV/0!
D29: =C29/C$42 -> #DIV/0! | E29: =D29+E28 -> #DIV/0! | F29: =IF(AND(E29<=0),"C",IF(E29<=0.8,"A",IF(E29<=0.95,"B","C"))) -> #DIV/0! | G29: =VLOOKUP(B$22:B$42,I$22:M$42,5,0) -> #N/A | K29: =J29/J$42 -> #DIV/0! | L29: =K29+L28 -> #DIV/0! | M29: =_xlfn.IFS(L29<80%,"A",L29<=95%,"B",L29>95%,"C") -> #DIV/0!
D30: =C30/C$42 -> #DIV/0! | E30: =D30+E29 -> #DIV/0! | F30: =IF(AND(E30<=0),"C",IF(E30<=0.8,"A",IF(E30<=0.95,"B","C"))) -> #DIV/0! | G30: =VLOOKUP(B$22:B$42,I$22:M$42,5,0) -> #N/A | K30: =J30/J$42 -> #DIV/0! | L30: =K30+L29 -> #DIV/0! | M30: =_xlfn.IFS(L30<80%,"A",L30<=95%,"B",L30>95%,"C") -> #DIV/0!
D31: =C31/C$42 -> #DIV/0! | E31: =D31+E30 -> #DIV/0! | F31: =IF(AND(E31<=0),"C",IF(E31<=0.8,"A",IF(E31<=0.95,"B","C"))) -> #DIV/0! | G31: =VLOOKUP(B$22:B$42,I$22:M$42,5,0) -> #N/A | K31: =J31/J$42 -> #DIV/0! | L31: =K31+L30 -> #DIV/0! | M31: =_xlfn.IFS(L31<80%,"A",L31<=95%,"B",L31>95%,"C") -> #DIV/0!
D32: =C32/C$42 -> #DIV/0! | E32: =D32+E31 -> #DIV/0! | F32: =IF(AND(E32<=0),"C",IF(E32<=0.8,"A",IF(E32<=0.95,"B","C"))) -> #DIV/0! | G32: =VLOOKUP(B$22:B$42,I$22:M$42,5,0) -> #N/A | K32: =J32/J$42 -> #DIV/0! | L32: =K32+L31 -> #DIV/0! | M32: =_xlfn.IFS(L32<80%,"A",L32<=95%,"B",L32>95%,"C") -> #DIV/0!
D33: =C33/C$42 -> #DIV/0! | E33: =D33+E32 -> #DIV/0! | F33: =IF(AND(E33<=0),"C",IF(E33<=0.8,"A",IF(E33<=0.95,"B","C"))) -> #DIV/0! | G33: =VLOOKUP(B$22:B$42,I$22:M$42,5,0) -> #N/A | K33: =J33/J$42 -> #DIV/0! | L33: =K33+L32 -> #DIV/0! | M33: =_xlfn.IFS(L33<80%,"A",L33<=95%,"B",L33>95%,"C") -> #DIV/0!
D34: =C34/C$42 -> #DIV/0! | E34: =D34+E33 -> #DIV/0! | F34: =IF(AND(E34<=0),"C",IF(E34<=0.8,"A",IF(E34<=0.95,"B","C"))) -> #DIV/0! | G34: =VLOOKUP(B$22:B$42,I$22:M$42,5,0) -> #N/A | K34: =J34/J$42 -> #DIV/0! | L34: =K34+L33 -> #DIV/0! | M34: =_xlfn.IFS(L34<80%,"A",L34<=95%,"B",L34>95%,"C") -> #DIV/0!
... D41: =C41/C$42 -> #DIV/0! | E41: =D41+E40 -> #DIV/0! | F41: =IF(AND(E41<=0),"C",IF(E41<=0.8,"A",IF(E41<=0.95,"B","C"))) -> #DIV/0! | G41: =VLOOKUP(B$22:B$42,I$22:M$42,5,0) -> #N/A | K41: =J41/J$42 -> #DIV/0! | L41: =K41+L40 -> #DIV/0! | M41: =_xlfn.IFS(L41<80%,"A",L41<=95%,"B",L41>95%,"C") -> #DIV/0!
C42: =SUM(C22:C41) -> 0 | D42: =SUM(D22:D41) -> #DIV/0! | J42: =SUM(J22:J41) -> 0 | K42: =SUM(K22:K41) -> #DIV/0!

Sheet АВС 23-29.03
B2: ОЧКИ
C3: Прибыль | D3: % прибыль | E3: Доля | F3: ABC прибыль | G3: ABC кол-во | J3: Кол-во | K3: % кол-во | L3: Доля | M3: ABC кол-во
B4: MR8854 C2 | C4: ='Юнит 23-29.03'!AE8 -> 9920.539 | D4: =C4/C$18 -> 0.32860621 | E4: =D4 -> 0.32860621 | F4: =IF(AND(E4<=0),"C",IF(E4<=0.8,"A",IF(E4<=0.95,"B","C"))) -> A | G4: =VLOOKUP(B$4:B$17,I$4:M$17,5,0) -> A | I4: MR8854 C2 | J4: ='Юнит 23-29.03'!R8 -> 14 | K4: =J4/J$18 -> 0.25925926 | L4: =K4 -> 0.25925926 | M4: =_xlfn.IFS(L4<80%,"A",L4<=95%,"B",L4>95%,"C") -> A
B5: flip черный | C5: ='Юнит 23-29.03'!AE13 -> 4886.6796 | D5: =C5/C$18 -> 0.16186553 | E5: =D5+E4 -> 0.49047174 | F5: =IF(AND(E5<=0),"C",IF(E5<=0.8,"A",IF(E5<=0.95,"B","C"))) -> A | G5: =VLOOKUP(B$4:B$17,I$4:M$17,5,0) -> A | I5: flip черный | J5: ='Юнит 23-29.03'!R13 -> 6 | K5: =J5/J$18 -> 0.11111111 | L5: =K5+L4 -> 0.37037037 | M5: =_xlfn.IFS(L5<80%,"A",L5<=95%,"B",L5>95%,"C") -> A
B6: qs синие | C6: ='Юнит 23-29.03'!AE5 -> 3925.109 | D6: =C6/C$18 -> 0.13001463 | E6: =D6+E5 -> 0.62048637 | F6: =IF(AND(E6<=0),"C",IF(E6<=0.8,"A",IF(E6<=0.95,"B","C"))) -> A | G6: =VLOOKUP(B$4:B$17,I$4:M$17,5,0) -> A | I6: flip коричневый | J6: ='Юнит 23-29.03'!R16 -> 6 | K6: =J6/J$18 -> 0.11111111 | L6: =K6+L5 -> 0.48148148 | M6: =_xlfn.IFS(L6<80%,"A",L6<=95%,"B",L6>95%,"C") -> A
B7: flip коричневый | C7: ='Юнит 23-29.03'!AE16 -> 2631.9007 | D7: =C7/C$18 -> 0.087178622 | E7: =D7+E6 -> 0.70766499 | F7: =IF(AND(E7<=0),"C",IF(E7<=0.8,"A",IF(E7<=0.95,"B","C"))) -> A | G7: =VLOOKUP(B$4:B$17,I$4:M$17,5,0) -> A | I7: qs черные | J7: ='Юнит 23-29.03'!R4 -> 5 | K7: =J7/J$18 -> 0.092592593 | L7: =K7+L6 -> 0.57407407 | M7: =_xlfn.IFS(L7<80%,"A",L7<=95%,"B",L7>95%,"C") -> A
B8: qs коричневые | C8: ='Юнит 23-29.03'!AE7 -> 2535.5044 | D8: =C8/C$18 -> 0.083985606 | E8: =D8+E7 -> 0.79165059 | F8: =IF(AND(E8<=0),"C",IF(E8<=0.8,"A",IF(E8<=0.95,"B","C"))) -> A | G8: =VLOOKUP(B$4:B$17,I$4:M$17,5,0) -> B | I8: th желт | J8: ='Юнит 23-29.03'!R11 -> 5 | K8: =J8/J$18 -> 0.092592593 | L8: =K8+L7 -> 0.66666667 | M8: =_xlfn.IFS(L8<80%,"A",L8<=95%,"B",L8>95%,"C") -> A
B9: qs черные | C9: ='Юнит 23-29.03'!AE4 -> 2033.3117 | D9: =C9/C$18 -> 0.067351063 | E9: =D9+E8 -> 0.85900166 | F9: =IF(AND(E9<=0),"C",IF(E9<=0.8,"A",IF(E9<=0.95,"B","C"))) -> B | G9: =VLOOKUP(B$4:B$17,I$4:M$17,5,0) -> A | I9: qs синие | J9: ='Юнит 23-29.03'!R5 -> 4 | K9: =J9/J$18 -> 0.074074074 | L9: =K9+L8 -> 0.74074074 | M9: =_xlfn.IFS(L9<80%,"A",L9<=95%,"B",L9>95%,"C") -> A
B10: th син | C10: ='Юнит 23-29.03'!AE10 -> 1980.0886 | D10: =C10/C$18 -> 0.065588112 | E10: =D10+E9 -> 0.92458977 | F10: =IF(AND(E10<=0),"C",IF(E10<=0.8,"A",IF(E10<=0.95,"B","C"))) -> B | G10: =VLOOKUP(B$4:B$17,I$4:M$17,5,0) -> A | I10: qs коричневые | J10: ='Юнит 23-29.03'!R7 -> 4 | K10: =J10/J$18 -> 0.074074074 | L10: =K10+L9 -> 0.81481481 | M10: =_xlfn.IFS(L10<80%,"A",L10<=95%,"B",L10>95%,"C") -> B
B11: th черн | C11: ='Юнит 23-29.03'!AE9 -> 1951.8173 | D11: =C11/C$18 -> 0.064651656 | E11: =D11+E10 -> 0.98924142 | F11: =IF(AND(E11<=0),"C",IF(E11<=0.8,"A",IF(E11<=0.95,"B","C"))) -> C | G11: =VLOOKUP(B$4:B$17,I$4:M$17,5,0) -> B | I11: th черн | J11: ='Юнит 23-29.03'!R9 -> 2 | K11: =J11/J$18 -> 0.037037037 | L11: =K11+L10 -> 0.85185185 | M11: =_xlfn.IFS(L11<80%,"A",L11<=95%,"B",L11>95%,"C") -> B
B12: flip жел | C12: ='Юнит 23-29.03'!AE15 -> 1845.8299 | D12: =C12/C$18 -> 0.06114095 | E12: =D12+E5 -> 0.55161269 | F12: =IF(AND(E12<=0),"C",IF(E12<=0.8,"A",IF(E12<=0.95,"B","C"))) -> A | G12: =VLOOKUP(B$4:B$17,I$4:M$17,5,0) -> A | I12: th син | J12: ='Юнит 23-29.03'!R10 -> 2 | K12: =J12/J$18 -> 0.037037037 | L12: =K12+L5 -> 0.40740741 | M12: =_xlfn.IFS(L12<80%,"A",L12<=95%,"B",L12>95%,"C") -> A
B13: flip синий | C13: ='Юнит 23-29.03'!AE14 -> 1153.505 | D13: =C13/C$18 -> 0.0382085 | E13: =D13+E12 -> 0.58982119 | F13: =IF(AND(E13<=0),"C",IF(E13<=0.8,"A",IF(E13<=0.95,"B","C"))) -> A | G13: =VLOOKUP(B$4:B$17,I$4:M$17,5,0) -> A | I13: th коричн | J13: ='Юнит 23-29.03'!R12 -> 2 | K13: =J13/J$18 -> 0.037037037 | L13: =K13+L12 -> 0.44444444 | M13: =_xlfn.IFS(L13<80%,"A",L13<=95%,"B",L13>95%,"C") -> A
B14: th желт | C14: ='Юнит 23-29.03'!AE11 -> 993.43114 | D14: =C14/C$18 -> 0.032906241 | E14: =D14+E13 -> 0.62272743 | F14: =IF(AND(E14<=0),"C",IF(E14<=0.8,"A",IF(E14<=0.95,"B","C"))) -> A | G14: =VLOOKUP(B$4:B$17,I$4:M$17,5,0) -> A | I14: flip жел | J14: ='Юнит 23-29.03'!R15 -> 2 | K14: =J14/J$18 -> 0.037037037 | L14: =K14+L13 -> 0.48148148 | M14: =_xlfn.IFS(L14<80%,"A",L14<=95%,"B",L14>95%,"C") -> A
B15: черные с железкой классика | C15: ='Юнит 23-29.03'!AE3 -> -1106.9801 | D15: =C15/C$18 -> -0.036667417 | E15: =D15+E14 -> 0.58606001 | F15: =IF(AND(E15<=0),"C",IF(E15<=0.8,"A",IF(E15<=0.95,"B","C"))) -> A | G15: =VLOOKUP(B$4:B$17,I$4:M$17,5,0) -> A | I15: черные с железкой классика | J15: ='Юнит 23-29.03'!R3 -> 1 | K15: =J15/J$18 -> 0.018518519 | L15: =K15+L14 -> 0.5 | M15: =_xlfn.IFS(L15<80%,"A",L15<=95%,"B",L15>95%,"C") -> A
B16: th коричн | C16: ='Юнит 23-29.03'!AE12 -> -1246.1138 | D16: =C16/C$18 -> -0.041276056 | E16: =D16+E15 -> 0.54478395 | F16: =IF(AND(E16<=0),"C",IF(E16<=0.8,"A",IF(E16<=0.95,"B","C"))) -> A | G16: =VLOOKUP(B$4:B$17,I$4:M$17,5,0) -> A | I16: flip синий | J16: ='Юнит 23-29.03'!R14 -> 1 | K16: =J16/J$18 -> 0.018518519 | L16: =K16+L15 -> 0.51851852 | M16: =_xlfn.IFS(L16<80%,"A",L16<=95%,"B",L16>95%,"C") -> A
B17: qs желтые | C17: ='Юнит 23-29.03'!AE6 -> -1314.8735 | D17: =C17/C$18 -> -0.043553642 | E17: =D17+E14 -> 0.57917379 | F17: =IF(AND(E17<=0),"C",IF(E17<=0.8,"A",IF(E17<=0.95,"B","C"))) -> A | G17: =VLOOKUP(B$4:B$17,I$4:M$17,5,0) -> A | I17: qs желтые | J17: ='Юнит 23-29.03'!R6 -> 0 | K17: =J17/J$18 -> 0 | L17: =K17+L14 -> 0.48148148 | M17: =_xlfn.IFS(L17<80%,"A",L17<=95%,"B",L17>95%,"C") -> A
C18: =SUM(C4:C17) -> 30189.749 | D18: =SUM(D4:D17) -> 1 | J18: =SUM(J4:J17) -> 54 | K18: =SUM(K4:K17) -> 1
C21: Прибыль | D21: % прибыль | E21: Доля | F21: ABC прибыль | G21: ABC кол-во | J21: Кол-во | K21: % кол-во | L21: Доля | M21: ABC кол-во
D22: =C22/C$42 -> #DIV/0! | E22: =D22 -> #DIV/0! | F22: =IF(AND(E22<=0),"C",IF(E22<=0.8,"A",IF(E22<=0.95,"B","C"))) -> #DIV/0! | G22: =VLOOKUP(B$22:B$42,I$22:M$42,5,0) -> #N/A | K22: =J22/J$42 -> #DIV/0! | L22: =K22 -> #DIV/0! | M22: =_xlfn.IFS(L22<80%,"A",L22<=95%,"B",L22>95%,"C") -> #DIV/0!
D23: =C23/C$42 -> #DIV/0! | E23: =D23+E22 -> #DIV/0! | F23: =IF(AND(E23<=0),"C",IF(E23<=0.8,"A",IF(E23<=0.95,"B","C"))) -> #DIV/0! | G23: =VLOOKUP(B$22:B$42,I$22:M$42,5,0) -> #N/A | K23: =J23/J$42 -> #DIV/0! | L23: =K23+L22 -> #DIV/0! | M23: =_xlfn.IFS(L23<80%,"A",L23<=95%,"B",L23>95%,"C") -> #DIV/0!
D24: =C24/C$42 -> #DIV/0! | E24: =D24+E23 -> #DIV/0! | F24: =IF(AND(E24<=0),"C",IF(E24<=0.8,"A",IF(E24<=0.95,"B","C"))) -> #DIV/0! | G24: =VLOOKUP(B$22:B$42,I$22:M$42,5,0) -> #N/A | K24: =J24/J$42 -> #DIV/0! | L24: =K24+L23 -> #DIV/0! | M24: =_xlfn.IFS(L24<80%,"A",L24<=95%,"B",L24>95%,"C") -> #DIV/0!
D25: =C25/C$42 -> #DIV/0! | E25: =D25+E24 -> #DIV/0! | F25: =IF(AND(E25<=0),"C",IF(E25<=0.8,"A",IF(E25<=0.95,"B","C"))) -> #DIV/0! | G25: =VLOOKUP(B$22:B$42,I$22:M$42,5,0) -> #N/A | K25: =J25/J$42 -> #DIV/0! | L25: =K25+L24 -> #DIV/0! | M25: =_xlfn.IFS(L25<80%,"A",L25<=95%,"B",L25>95%,"C") -> #DIV/0!
D26: =C26/C$42 -> #DIV/0! | E26: =D26+E25 -> #DIV/0! | F26: =IF(AND(E26<=0),"C",IF(E26<=0.8,"A",IF(E26<=0.95,"B","C"))) -> #DIV/0! | G26: =VLOOKUP(B$22:B$42,I$22:M$42,5,0) -> #N/A | K26: =J26/J$42 -> #DIV/0! | L26: =K26+L25 -> #DIV/0! | M26: =_xlfn.IFS(L26<80%,"A",L26<=95%,"B",L26>95%,"C") -> #DIV/0!
D27: =C27/C$42 -> #DIV/0! | E27: =D27+E26 -> #DIV/0! | F27: =IF(AND(E27<=0),"C",IF(E27<=0.8,"A",IF(E27<=0.95,"B","C"))) -> #DIV/0! | G27: =VLOOKUP(B$22:B$42,I$22:M$42,5,0) -> #N/A | K27: =J27/J$42 -> #DIV/0! | L27: =K27+L26 -> #DIV/0! | M27: =_xlfn.IFS(L27<80%,"A",L27<=95%,"B",L27>95%,"C") -> #DIV/0!
D28: =C28/C$42 -> #DIV/0! | E28: =D28+E27 -> #DIV/0! | F28: =IF(AND(E28<=0),"C",IF(E28<=0.8,"A",IF(E28<=0.95,"B","C"))) -> #DIV/0! | G28: =VLOOKUP(B$22:B$42,I$22:M$42,5,0) -> #N/A | K28: =J28/J$42 -> #DIV/0! | L28: =K28+L27 -> #DIV/0! | M28: =_xlfn.IFS(L28<80%,"A",L28<=95%,"B",L28>95%,"C") -> #DIV/0!
D29: =C29/C$42 -> #DIV/0! | E29: =D29+E28 -> #DIV/0! | F29: =IF(AND(E29<=0),"C",IF(E29<=0.8,"A",IF(E29<=0.95,"B","C"))) -> #DIV/0! | G29: =VLOOKUP(B$22:B$42,I$22:M$42,5,0) -> #N/A | K29: =J29/J$42 -> #DIV/0! | L29: =K29+L28 -> #DIV/0! | M29: =_xlfn.IFS(L29<80%,"A",L29<=95%,"B",L29>95%,"C") -> #DIV/0!
D30: =C30/C$42 -> #DIV/0! | E30: =D30+E29 -> #DIV/0! | F30: =IF(AND(E30<=0),"C",IF(E30<=0.8,"A",IF(E30<=0.95,"B","C"))) -> #DIV/0! | G30: =VLOOKUP(B$22:B$42,I$22:M$42,5,0) -> #N/A | K30: =J30/J$42 -> #DIV/0! | L30: =K30+L29 -> #DIV/0! | M30: =_xlfn.IFS(L30<80%,"A",L30<=95%,"B",L30>95%,"C") -> #DIV/0!
D31: =C31/C$42 -> #DIV/0! | E31: =D31+E30 -> #DIV/0! | F31: =IF(AND(E31<=0),"C",IF(E31<=0.8,"A",IF(E31<=0.95,"B","C"))) -> #DIV/0! | G31: =VLOOKUP(B$22:B$42,I$22:M$42,5,0) -> #N/A | K31: =J31/J$42 -> #DIV/0! | L31: =K31+L30 -> #DIV/0! | M31: =_xlfn.IFS(L31<80%,"A",L31<=95%,"B",L31>95%,"C") -> #DIV/0!
D32: =C32/C$42 -> #DIV/0! | E32: =D32+E31 -> #DIV/0! | F32: =IF(AND(E32<=0),"C",IF(E32<=0.8,"A",IF(E32<=0.95,"B","C"))) -> #DIV/0! | G32: =VLOOKUP(B$22:B$42,I$22:M$42,5,0) -> #N/A | K32: =J32/J$42 -> #DIV/0! | L32: =K32+L31 -> #DIV/0! | M32: =_xlfn.IFS(L32<80%,"A",L32<=95%,"B",L32>95%,"C") -> #DIV/0!
D33: =C33/C$42 -> #DIV/0! | E33: =D33+E32 -> #DIV/0! | F33: =IF(AND(E33<=0),"C",IF(E33<=0.8,"A",IF(E33<=0.95,"B","C"))) -> #DIV/0! | G33: =VLOOKUP(B$22:B$42,I$22:M$42,5,0) -> #N/A | K33: =J33/J$42 -> #DIV/0! | L33: =K33+L32 -> #DIV/0! | M33: =_xlfn.IFS(L33<80%,"A",L33<=95%,"B",L33>95%,"C") -> #DIV/0!
D34: =C34/C$42 -> #DIV/0! | E34: =D34+E33 -> #DIV/0! | F34: =IF(AND(E34<=0),"C",IF(E34<=0.8,"A",IF(E34<=0.95,"B","C"))) -> #DIV/0! | G34: =VLOOKUP(B$22:B$42,I$22:M$42,5,0) -> #N/A | K34: =J34/J$42 -> #DIV/0! | L34: =K34+L33 -> #DIV/0! | M34: =_xlfn.IFS(L34<80%,"A",L34<=95%,"B",L34>95%,"C") -> #DIV/0!
... D41: =C41/C$42 -> #DIV/0! | E41: =D41+E40 -> #DIV/0! | F41: =IF(AND(E41<=0),"C",IF(E41<=0.8,"A",IF(E41<=0.95,"B","C"))) -> #DIV/0! | G41: =VLOOKUP(B$22:B$42,I$22:M$42,5,0) -> #N/A | K41: =J41/J$42 -> #DIV/0! | L41: =K41+L40 -> #DIV/0! | M41: =_xlfn.IFS(L41<80%,"A",L41<=95%,"B",L41>95%,"C") -> #DIV/0!
C42: =SUM(C22:C41) -> 0 | D42: =SUM(D22:D41) -> #DIV/0! | J42: =SUM(J22:J41) -> 0 | K42: =SUM(K22:K41) -> #DIV/0!

Sheet АВС 16-22.03
B2: ОЧКИ
C3: Прибыль | D3: % прибыль | E3: Доля | F3: ABC прибыль | G3: ABC кол-во | J3: Кол-во | K3: % кол-во | L3: Доля | M3: ABC кол-во
B4: MR8854 C2 | C4: ='Юнит 16-22.03'!AE8 -> 17327.034 | D4: =C4/C$18 -> 0.42309671 | E4: =D4 -> 0.42309671 | F4: =IF(AND(E4<=0),"C",IF(E4<=0.8,"A",IF(E4<=0.95,"B","C"))) -> A | G4: =VLOOKUP(B$4:B$17,I$4:M$17,5,0) -> A | I4: MR8854 C2 | J4: ='Юнит 16-22.03'!R8 -> 21 | K4: =J4/J$18 -> 0.3559322 | L4: =K4 -> 0.3559322 | M4: =_xlfn.IFS(L4<80%,"A",L4<=95%,"B",L4>95%,"C") -> A
B5: flip жел | C5: ='Юнит 16-22.03'!AE15 -> 8577.8162 | D5: =C5/C$18 -> 0.20945569 | E5: =D5+E4 -> 0.63255239 | F5: =IF(AND(E5<=0),"C",IF(E5<=0.8,"A",IF(E5<=0.95,"B","C"))) -> A | G5: =VLOOKUP(B$4:B$17,I$4:M$17,5,0) -> A | I5: flip жел | J5: ='Юнит 16-22.03'!R15 -> 11 | K5: =J5/J$18 -> 0.18644068 | L5: =K5+L4 -> 0.54237288 | M5: =_xlfn.IFS(L5<80%,"A",L5<=95%,"B",L5>95%,"C") -> A
B6: flip коричневый | C6: ='Юнит 16-22.03'!AE16 -> 5015.337 | D6: =C6/C$18 -> 0.122466 | E6: =D6+E5 -> 0.7550184 | F6: =IF(AND(E6<=0),"C",IF(E6<=0.8,"A",IF(E6<=0.95,"B","C"))) -> A | G6: =VLOOKUP(B$4:B$17,I$4:M$17,5,0) -> A | I6: qs коричневые | J6: ='Юнит 16-22.03'!R7 -> 7 | K6: =J6/J$18 -> 0.11864407 | L6: =K6+L5 -> 0.66101695 | M6: =_xlfn.IFS(L6<80%,"A",L6<=95%,"B",L6>95%,"C") -> A
B7: qs коричневые | C7: ='Юнит 16-22.03'!AE7 -> 4914.6606 | D7: =C7/C$18 -> 0.12000766 | E7: =D7+E6 -> 0.87502606 | F7: =IF(AND(E7<=0),"C",IF(E7<=0.8,"A",IF(E7<=0.95,"B","C"))) -> B | G7: =VLOOKUP(B$4:B$17,I$4:M$17,5,0) -> A | I7: flip коричневый | J7: ='Юнит 16-22.03'!R16 -> 6 | K7: =J7/J$18 -> 0.10169492 | L7: =K7+L6 -> 0.76271186 | M7: =_xlfn.IFS(L7<80%,"A",L7<=95%,"B",L7>95%,"C") -> A
B8: qs желтые | C8: ='Юнит 16-22.03'!AE6 -> 3383.0169 | D8: =C8/C$18 -> 0.08260752 | E8: =D8+E7 -> 0.95763358 | F8: =IF(AND(E8<=0),"C",IF(E8<=0.8,"A",IF(E8<=0.95,"B","C"))) -> C | G8: =VLOOKUP(B$4:B$17,I$4:M$17,5,0) -> B | I8: qs желтые | J8: ='Юнит 16-22.03'!R6 -> 5 | K8: =J8/J$18 -> 0.084745763 | L8: =K8+L7 -> 0.84745763 | M8: =_xlfn.IFS(L8<80%,"A",L8<=95%,"B",L8>95%,"C") -> B
B9: flip черный | C9: ='Юнит 16-22.03'!AE13 -> 2165.3465 | D9: =C9/C$18 -> 0.052874079 | E9: =D9+E8 -> 1.0105077 | F9: =IF(AND(E9<=0),"C",IF(E9<=0.8,"A",IF(E9<=0.95,"B","C"))) -> C | G9: =VLOOKUP(B$4:B$17,I$4:M$17,5,0) -> A | I9: th син | J9: ='Юнит 16-22.03'!R10 -> 2 | K9: =J9/J$18 -> 0.033898305 | L9: =K9+L8 -> 0.88135593 | M9: =_xlfn.IFS(L9<80%,"A",L9<=95%,"B",L9>95%,"C") -> B
B10: th коричн | C10: ='Юнит 16-22.03'!AE12 -> 2025.0928 | D10: =C10/C$18 -> 0.049449324 | E10: =D10+E9 -> 1.059957 | F10: =IF(AND(E10<=0),"C",IF(E10<=0.8,"A",IF(E10<=0.95,"B","C"))) -> C | G10: =VLOOKUP(B$4:B$17,I$4:M$17,5,0) -> B | I10: th желт | J10: ='Юнит 16-22.03'!R11 -> 2 | K10: =J10/J$18 -> 0.033898305 | L10: =K10+L9 -> 0.91525424 | M10: =_xlfn.IFS(L10<80%,"A",L10<=95%,"B",L10>95%,"C") -> B
B11: черные с железкой классика | C11: ='Юнит 16-22.03'!AE3 -> 1064.1149 | D11: =C11/C$18 -> 0.025983876 | E11: =D11+E10 -> 1.0859409 | F11: =IF(AND(E11<=0),"C",IF(E11<=0.8,"A",IF(E11<=0.95,"B","C"))) -> C | G11: =VLOOKUP(B$4:B$17,I$4:M$17,5,0) -> A | I11: th коричн | J11: ='Юнит 16-22.03'!R12 -> 2 | K11: =J11/J$18 -> 0.033898305 | L11: =K11+L10 -> 0.94915254 | M11: =_xlfn.IFS(L11<80%,"A",L11<=95%,"B",L11>95%,"C") -> B
B12: th син | C12: ='Юнит 16-22.03'!AE10 -> 487.15649 | D12: =C12/C$18 -> 0.011895533 | E12: =D12+E5 -> 0.64444793 | F12: =IF(AND(E12<=0),"C",IF(E12<=0.8,"A",IF(E12<=0.95,"B","C"))) -> A | G12: =VLOOKUP(B$4:B$17,I$4:M$17,5,0) -> B | I12: flip черный | J12: ='Юнит 16-22.03'!R13 -> 2 | K12: =J12/J$18 -> 0.033898305 | L12: =K12+L5 -> 0.57627119 | M12: =_xlfn.IFS(L12<80%,"A",L12<=95%,"B",L12>95%,"C") -> A
B13: th черн | C13: ='Юнит 16-22.03'!AE9 -> -227.76 | D13: =C13/C$18 -> -0.005561512 | E13: =D13+E12 -> 0.63888642 | F13: =IF(AND(E13<=0),"C",IF(E13<=0.8,"A",IF(E13<=0.95,"B","C"))) -> A | G13: =VLOOKUP(B$4:B$17,I$4:M$17,5,0) -> A | I13: черные с железкой классика | J13: ='Юнит 16-22.03'!R3 -> 1 | K13: =J13/J$18 -> 0.016949153 | L13: =K13+L12 -> 0.59322034 | M13: =_xlfn.IFS(L13<80%,"A",L13<=95%,"B",L13>95%,"C") -> A
B14: flip синий | C14: ='Юнит 16-22.03'!AE14 -> -227.76 | D14: =C14/C$18 -> -0.005561512 | E14: =D14+E13 -> 0.6333249 | F14: =IF(AND(E14<=0),"C",IF(E14<=0.8,"A",IF(E14<=0.95,"B","C"))) -> A | G14: =VLOOKUP(B$4:B$17,I$4:M$17,5,0) -> A | I14: qs черные | J14: ='Юнит 16-22.03'!R4 -> 0 | K14: =J14/J$18 -> 0 | L14: =K14+L13 -> 0.59322034 | M14: =_xlfn.IFS(L14<80%,"A",L14<=95%,"B",L14>95%,"C") -> A
B15: th желт | C15: ='Юнит 16-22.03'!AE11 -> -532.03327 | D15: =C15/C$18 -> -0.012991348 | E15: =D15+E14 -> 0.62033356 | F15: =IF(AND(E15<=0),"C",IF(E15<=0.8,"A",IF(E15<=0.95,"B","C"))) -> A | G15: =VLOOKUP(B$4:B$17,I$4:M$17,5,0) -> B | I15: qs синие | J15: ='Юнит 16-22.03'!R5 -> 0 | K15: =J15/J$18 -> 0 | L15: =K15+L14 -> 0.59322034 | M15: =_xlfn.IFS(L15<80%,"A",L15<=95%,"B",L15>95%,"C") -> A
B16: qs синие | C16: ='Юнит 16-22.03'!AE5 -> -846.19408 | D16: =C16/C$18 -> -0.020662621 | E16: =D16+E15 -> 0.59967094 | F16: =IF(AND(E16<=0),"C",IF(E16<=0.8,"A",IF(E16<=0.95,"B","C"))) -> A | G16: =VLOOKUP(B$4:B$17,I$4:M$17,5,0) -> A | I16: th черн | J16: ='Юнит 16-22.03'!R9 -> 0 | K16: =J16/J$18 -> 0 | L16: =K16+L15 -> 0.59322034 | M16: =_xlfn.IFS(L16<80%,"A",L16<=95%,"B",L16>95%,"C") -> A
B17: qs черные | C17: ='Юнит 16-22.03'!AE4 -> -2172.9357 | D17: =C17/C$18 -> -0.053059395 | E17: =D17+E14 -> 0.58026551 | F17: =IF(AND(E17<=0),"C",IF(E17<=0.8,"A",IF(E17<=0.95,"B","C"))) -> A | G17: =VLOOKUP(B$4:B$17,I$4:M$17,5,0) -> A | I17: flip синий | J17: ='Юнит 16-22.03'!R14 -> 0 | K17: =J17/J$18 -> 0 | L17: =K17+L14 -> 0.59322034 | M17: =_xlfn.IFS(L17<80%,"A",L17<=95%,"B",L17>95%,"C") -> A
C18: =SUM(C4:C17) -> 40952.892 | D18: =SUM(D4:D17) -> 1 | J18: =SUM(J4:J17) -> 59 | K18: =SUM(K4:K17) -> 1
C21: Прибыль | D21: % прибыль | E21: Доля | F21: ABC прибыль | G21: ABC кол-во | J21: Кол-во | K21: % кол-во | L21: Доля | M21: ABC кол-во
D22: =C22/C$42 -> #DIV/0! | E22: =D22 -> #DIV/0! | F22: =IF(AND(E22<=0),"C",IF(E22<=0.8,"A",IF(E22<=0.95,"B","C"))) -> #DIV/0! | G22: =VLOOKUP(B$22:B$42,I$22:M$42,5,0) -> #N/A | K22: =J22/J$42 -> #DIV/0! | L22: =K22 -> #DIV/0! | M22: =_xlfn.IFS(L22<80%,"A",L22<=95%,"B",L22>95%,"C") -> #DIV/0!
D23: =C23/C$42 -> #DIV/0! | E23: =D23+E22 -> #DIV/0! | F23: =IF(AND(E23<=0),"C",IF(E23<=0.8,"A",IF(E23<=0.95,"B","C"))) -> #DIV/0! | G23: =VLOOKUP(B$22:B$42,I$22:M$42,5,0) -> #N/A | K23: =J23/J$42 -> #DIV/0! | L23: =K23+L22 -> #DIV/0! | M23: =_xlfn.IFS(L23<80%,"A",L23<=95%,"B",L23>95%,"C") -> #DIV/0!
D24: =C24/C$42 -> #DIV/0! | E24: =D24+E23 -> #DIV/0! | F24: =IF(AND(E24<=0),"C",IF(E24<=0.8,"A",IF(E24<=0.95,"B","C"))) -> #DIV/0! | G24: =VLOOKUP(B$22:B$42,I$22:M$42,5,0) -> #N/A | K24: =J24/J$42 -> #DIV/0! | L24: =K24+L23 -> #DIV/0! | M24: =_xlfn.IFS(L24<80%,"A",L24<=95%,"B",L24>95%,"C") -> #DIV/0!
D25: =C25/C$42 -> #DIV/0! | E25: =D25+E24 -> #DIV/0! | F25: =IF(AND(E25<=0),"C",IF(E25<=0.8,"A",IF(E25<=0.95,"B","C"))) -> #DIV/0! | G25: =VLOOKUP(B$22:B$42,I$22:M$42,5,0) -> #N/A | K25: =J25/J$42 -> #DIV/0! | L25: =K25+L24 -> #DIV/0! | M25: =_xlfn.IFS(L25<80%,"A",L25<=95%,"B",L25>95%,"C") -> #DIV/0!
D26: =C26/C$42 -> #DIV/0! | E26: =D26+E25 -> #DIV/0! | F26: =IF(AND(E26<=0),"C",IF(E26<=0.8,"A",IF(E26<=0.95,"B","C"))) -> #DIV/0! | G26: =VLOOKUP(B$22:B$42,I$22:M$42,5,0) -> #N/A | K26: =J26/J$42 -> #DIV/0! | L26: =K26+L25 -> #DIV/0! | M26: =_xlfn.IFS(L26<80%,"A",L26<=95%,"B",L26>95%,"C") -> #DIV/0!
D27: =C27/C$42 -> #DIV/0! | E27: =D27+E26 -> #DIV/0! | F27: =IF(AND(E27<=0),"C",IF(E27<=0.8,"A",IF(E27<=0.95,"B","C"))) -> #DIV/0! | G27: =VLOOKUP(B$22:B$42,I$22:M$42,5,0) -> #N/A | K27: =J27/J$42 -> #DIV/0! | L27: =K27+L26 -> #DIV/0! | M27: =_xlfn.IFS(L27<80%,"A",L27<=95%,"B",L27>95%,"C") -> #DIV/0!
D28: =C28/C$42 -> #DIV/0! | E28: =D28+E27 -> #DIV/0! | F28: =IF(AND(E28<=0),"C",IF(E28<=0.8,"A",IF(E28<=0.95,"B","C"))) -> #DIV/0! | G28: =VLOOKUP(B$22:B$42,I$22:M$42,5,0) -> #N/A | K28: =J28/J$42 -> #DIV/0! | L28: =K28+L27 -> #DIV/0! | M28: =_xlfn.IFS(L28<80%,"A",L28<=95%,"B",L28>95%,"C") -> #DIV/0!
D29: =C29/C$42 -> #DIV/0! | E29: =D29+E28 -> #DIV/0! | F29: =IF(AND(E29<=0),"C",IF(E29<=0.8,"A",IF(E29<=0.95,"B","C"))) -> #DIV/0! | G29: =VLOOKUP(B$22:B$42,I$22:M$42,5,0) -> #N/A | K29: =J29/J$42 -> #DIV/0! | L29: =K29+L28 -> #DIV/0! | M29: =_xlfn.IFS(L29<80%,"A",L29<=95%,"B",L29>95%,"C") -> #DIV/0!
D30: =C30/C$42 -> #DIV/0! | E30: =D30+E29 -> #DIV/0! | F30: =IF(AND(E30<=0),"C",IF(E30<=0.8,"A",IF(E30<=0.95,"B","C"))) -> #DIV/0! | G30: =VLOOKUP(B$22:B$42,I$22:M$42,5,0) -> #N/A | K30: =J30/J$42 -> #DIV/0! | L30: =K30+L29 -> #DIV/0! | M30: =_xlfn.IFS(L30<80%,"A",L30<=95%,"B",L30>95%,"C") -> #DIV/0!
D31: =C31/C$42 -> #DIV/0! | E31: =D31+E30 -> #DIV/0! | F31: =IF(AND(E31<=0),"C",IF(E31<=0.8,"A",IF(E31<=0.95,"B","C"))) -> #DIV/0! | G31: =VLOOKUP(B$22:B$42,I$22:M$42,5,0) -> #N/A | K31: =J31/J$42 -> #DIV/0! | L31: =K31+L30 -> #DIV/0! | M31: =_xlfn.IFS(L31<80%,"A",L31<=95%,"B",L31>95%,"C") -> #DIV/0!
D32: =C32/C$42 -> #DIV/0! | E32: =D32+E31 -> #DIV/0! | F32: =IF(AND(E32<=0),"C",IF(E32<=0.8,"A",IF(E32<=0.95,"B","C"))) -> #DIV/0! | G32: =VLOOKUP(B$22:B$42,I$22:M$42,5,0) -> #N/A | K32: =J32/J$42 -> #DIV/0! | L32: =K32+L31 -> #DIV/0! | M32: =_xlfn.IFS(L32<80%,"A",L32<=95%,"B",L32>95%,"C") -> #DIV/0!
D33: =C33/C$42 -> #DIV/0! | E33: =D33+E32 -> #DIV/0! | F33: =IF(AND(E33<=0),"C",IF(E33<=0.8,"A",IF(E33<=0.95,"B","C"))) -> #DIV/0! | G33: =VLOOKUP(B$22:B$42,I$22:M$42,5,0) -> #N/A | K33: =J33/J$42 -> #DIV/0! | L33: =K33+L32 -> #DIV/0! | M33: =_xlfn.IFS(L33<80%,"A",L33<=95%,"B",L33>95%,"C") -> #DIV/0!
D34: =C34/C$42 -> #DIV/0! | E34: =D34+E33 -> #DIV/0! | F34: =IF(AND(E34<=0),"C",IF(E34<=0.8,"A",IF(E34<=0.95,"B","C"))) -> #DIV/0! | G34: =VLOOKUP(B$22:B$42,I$22:M$42,5,0) -> #N/A | K34: =J34/J$42 -> #DIV/0! | L34: =K34+L33 -> #DIV/0! | M34: =_xlfn.IFS(L34<80%,"A",L34<=95%,"B",L34>95%,"C") -> #DIV/0!
... D41: =C41/C$42 -> #DIV/0! | E41: =D41+E40 -> #DIV/0! | F41: =IF(AND(E41<=0),"C",IF(E41<=0.8,"A",IF(E41<=0.95,"B","C"))) -> #DIV/0! | G41: =VLOOKUP(B$22:B$42,I$22:M$42,5,0) -> #N/A | K41: =J41/J$42 -> #DIV/0! | L41: =K41+L40 -> #DIV/0! | M41: =_xlfn.IFS(L41<80%,"A",L41<=95%,"B",L41>95%,"C") -> #DIV/0!
C42: =SUM(C22:C41) -> 0 | D42: =SUM(D22:D41) -> #DIV/0! | J42: =SUM(J22:J41) -> 0 | K42: =SUM(K22:K41) -> #DIV/0!

Sheet АВС 09-15.03
B2: ОЧКИ
C3: Прибыль | D3: % прибыль | E3: Доля | F3: ABC прибыль | G3: ABC кол-во | J3: Кол-во | K3: % кол-во | L3: Доля | M3: ABC кол-во
B4: MR8854 C2 | C4: ='Юнит 09-15.03'!AE8 -> 17647.861 | D4: =C4/C$18 -> 0.31065247 | E4: =D4 -> 0.31065247 | F4: =IF(AND(E4<=0),"C",IF(E4<=0.8,"A",IF(E4<=0.95,"B","C"))) -> A | G4: =VLOOKUP(B$4:B$17,I$4:M$17,5,0) -> A | I4: MR8854 C2 | J4: ='Юнит 09-15.03'!R8 -> 27 | K4: =J4/J$18 -> 0.29347826 | L4: =K4 -> 0.29347826 | M4: =_xlfn.IFS(L4<80%,"A",L4<=95%,"B",L4>95%,"C") -> A
B5: flip черный | C5: ='Юнит 09-15.03'!AE13 -> 8759.325 | D5: =C5/C$18 -> 0.154189 | E5: =D5+E4 -> 0.46484147 | F5: =IF(AND(E5<=0),"C",IF(E5<=0.8,"A",IF(E5<=0.95,"B","C"))) -> A | G5: =VLOOKUP(B$4:B$17,I$4:M$17,5,0) -> A | I5: flip жел | J5: ='Юнит 09-15.03'!R15 -> 13 | K5: =J5/J$18 -> 0.14130435 | L5: =K5+L4 -> 0.43478261 | M5: =_xlfn.IFS(L5<80%,"A",L5<=95%,"B",L5>95%,"C") -> A
B6: flip жел | C6: ='Юнит 09-15.03'!AE15 -> 6988.5675 | D6: =C6/C$18 -> 0.12301863 | E6: =D6+E5 -> 0.5878601 | F6: =IF(AND(E6<=0),"C",IF(E6<=0.8,"A",IF(E6<=0.95,"B","C"))) -> A | G6: =VLOOKUP(B$4:B$17,I$4:M$17,5,0) -> A | I6: qs коричневые | J6: ='Юнит 09-15.03'!R7 -> 12 | K6: =J6/J$18 -> 0.13043478 | L6: =K6+L5 -> 0.56521739 | M6: =_xlfn.IFS(L6<80%,"A",L6<=95%,"B",L6>95%,"C") -> A
B7: qs коричневые | C7: ='Юнит 09-15.03'!AE7 -> 4618.0378 | D7: =C7/C$18 -> 0.08129058 | E7: =D7+E6 -> 0.66915069 | F7: =IF(AND(E7<=0),"C",IF(E7<=0.8,"A",IF(E7<=0.95,"B","C"))) -> A | G7: =VLOOKUP(B$4:B$17,I$4:M$17,5,0) -> A | I7: flip черный | J7: ='Юнит 09-15.03'!R13 -> 10 | K7: =J7/J$18 -> 0.10869565 | L7: =K7+L6 -> 0.67391304 | M7: =_xlfn.IFS(L7<80%,"A",L7<=95%,"B",L7>95%,"C") -> A
B8: qs желтые | C8: ='Юнит 09-15.03'!AE6 -> 3849.3728 | D8: =C8/C$18 -> 0.067759893 | E8: =D8+E7 -> 0.73691058 | F8: =IF(AND(E8<=0),"C",IF(E8<=0.8,"A",IF(E8<=0.95,"B","C"))) -> A | G8: =VLOOKUP(B$4:B$17,I$4:M$17,5,0) -> A | I8: qs желтые | J8: ='Юнит 09-15.03'!R6 -> 7 | K8: =J8/J$18 -> 0.076086957 | L8: =K8+L7 -> 0.75 | M8: =_xlfn.IFS(L8<80%,"A",L8<=95%,"B",L8>95%,"C") -> A
B9: th коричн | C9: ='Юнит 09-15.03'!AE12 -> 3706.648 | D9: =C9/C$18 -> 0.065247531 | E9: =D9+E8 -> 0.80215811 | F9: =IF(AND(E9<=0),"C",IF(E9<=0.8,"A",IF(E9<=0.95,"B","C"))) -> B | G9: =VLOOKUP(B$4:B$17,I$4:M$17,5,0) -> B | I9: flip коричневый | J9: ='Юнит 09-15.03'!R16 -> 6 | K9: =J9/J$18 -> 0.065217391 | L9: =K9+L8 -> 0.81521739 | M9: =_xlfn.IFS(L9<80%,"A",L9<=95%,"B",L9>95%,"C") -> B
B10: qs синие | C10: ='Юнит 09-15.03'!AE5 -> 3561.3402 | D10: =C10/C$18 -> 0.062689702 | E10: =D10+E9 -> 0.86484781 | F10: =IF(AND(E10<=0),"C",IF(E10<=0.8,"A",IF(E10<=0.95,"B","C"))) -> B | G10: =VLOOKUP(B$4:B$17,I$4:M$17,5,0) -> A | I10: th коричн | J10: ='Юнит 09-15.03'!R12 -> 4 | K10: =J10/J$18 -> 0.043478261 | L10: =K10+L9 -> 0.85869565 | M10: =_xlfn.IFS(L10<80%,"A",L10<=95%,"B",L10>95%,"C") -> B
B11: flip коричневый | C11: ='Юнит 09-15.03'!AE16 -> 3184.4268 | D11: =C11/C$18 -> 0.056054956 | E11: =D11+E10 -> 0.92090277 | F11: =IF(AND(E11<=0),"C",IF(E11<=0.8,"A",IF(E11<=0.95,"B","C"))) -> B | G11: =VLOOKUP(B$4:B$17,I$4:M$17,5,0) -> B | I11: черные с железкой классика | J11: ='Юнит 09-15.03'!R3 -> 3 | K11: =J11/J$18 -> 0.032608696 | L11: =K11+L10 -> 0.89130435 | M11: =_xlfn.IFS(L11<80%,"A",L11<=95%,"B",L11>95%,"C") -> B
B12: qs черные | C12: ='Юнит 09-15.03'!AE4 -> 2163.9007 | D12: =C12/C$18 -> 0.038090797 | E12: =D12+E5 -> 0.50293227 | F12: =IF(AND(E12<=0),"C",IF(E12<=0.8,"A",IF(E12<=0.95,"B","C"))) -> A | G12: =VLOOKUP(B$4:B$17,I$4:M$17,5,0) -> A | I12: qs черные | J12: ='Юнит 09-15.03'!R4 -> 3 | K12: =J12/J$18 -> 0.032608696 | L12: =K12+L5 -> 0.4673913 | M12: =_xlfn.IFS(L12<80%,"A",L12<=95%,"B",L12>95%,"C") -> A
B13: черные с железкой классика | C13: ='Юнит 09-15.03'!AE3 -> 1187.0783 | D13: =C13/C$18 -> 0.02089595 | E13: =D13+E12 -> 0.52382822 | F13: =IF(AND(E13<=0),"C",IF(E13<=0.8,"A",IF(E13<=0.95,"B","C"))) -> A | G13: =VLOOKUP(B$4:B$17,I$4:M$17,5,0) -> B | I13: qs синие | J13: ='Юнит 09-15.03'!R5 -> 3 | K13: =J13/J$18 -> 0.032608696 | L13: =K13+L12 -> 0.5 | M13: =_xlfn.IFS(L13<80%,"A",L13<=95%,"B",L13>95%,"C") -> A
B14: th черн | C14: ='Юнит 09-15.03'!AE9 -> 865.64118 | D14: =C14/C$18 -> 0.015237743 | E14: =D14+E13 -> 0.53906596 | F14: =IF(AND(E14<=0),"C",IF(E14<=0.8,"A",IF(E14<=0.95,"B","C"))) -> A | G14: =VLOOKUP(B$4:B$17,I$4:M$17,5,0) -> A | I14: th черн | J14: ='Юнит 09-15.03'!R9 -> 2 | K14: =J14/J$18 -> 0.02173913 | L14: =K14+L13 -> 0.52173913 | M14: =_xlfn.IFS(L14<80%,"A",L14<=95%,"B",L14>95%,"C") -> A
B15: th син | C15: ='Юнит 09-15.03'!AE10 -> 378.06795 | D15: =C15/C$18 -> 0.0066550697 | E15: =D15+E14 -> 0.54572103 | F15: =IF(AND(E15<=0),"C",IF(E15<=0.8,"A",IF(E15<=0.95,"B","C"))) -> A | G15: =VLOOKUP(B$4:B$17,I$4:M$17,5,0) -> A | I15: th син | J15: ='Юнит 09-15.03'!R10 -> 1 | K15: =J15/J$18 -> 0.010869565 | L15: =K15+L14 -> 0.5326087 | M15: =_xlfn.IFS(L15<80%,"A",L15<=95%,"B",L15>95%,"C") -> A
B16: th желт | C16: ='Юнит 09-15.03'!AE11 -> 12.627754 | D16: =C16/C$18 -> 0.00022228433 | E16: =D16+E15 -> 0.54594331 | F16: =IF(AND(E16<=0),"C",IF(E16<=0.8,"A",IF(E16<=0.95,"B","C"))) -> A | G16: =VLOOKUP(B$4:B$17,I$4:M$17,5,0) -> A | I16: th желт | J16: ='Юнит 09-15.03'!R11 -> 1 | K16: =J16/J$18 -> 0.010869565 | L16: =K16+L15 -> 0.54347826 | M16: =_xlfn.IFS(L16<80%,"A",L16<=95%,"B",L16>95%,"C") -> A
B17: flip синий | C17: ='Юнит 09-15.03'!AE14 -> -113.88 | D17: =C17/C$18 -> -0.0020046114 | E17: =D17+E14 -> 0.53706135 | F17: =IF(AND(E17<=0),"C",IF(E17<=0.8,"A",IF(E17<=0.95,"B","C"))) -> A | G17: =VLOOKUP(B$4:B$17,I$4:M$17,5,0) -> A | I17: flip синий | J17: ='Юнит 09-15.03'!R14 -> 0 | K17: =J17/J$18 -> 0 | L17: =K17+L14 -> 0.52173913 | M17: =_xlfn.IFS(L17<80%,"A",L17<=95%,"B",L17>95%,"C") -> A
C18: =SUM(C4:C17) -> 56809.015 | D18: =SUM(D4:D17) -> 1 | J18: =SUM(J4:J17) -> 92 | K18: =SUM(K4:K17) -> 1
C21: Прибыль | D21: % прибыль | E21: Доля | F21: ABC прибыль | G21: ABC кол-во | J21: Кол-во | K21: % кол-во | L21: Доля | M21: ABC кол-во
D22: =C22/C$42 -> #DIV/0! | E22: =D22 -> #DIV/0! | F22: =IF(AND(E22<=0),"C",IF(E22<=0.8,"A",IF(E22<=0.95,"B","C"))) -> #DIV/0! | G22: =VLOOKUP(B$22:B$42,I$22:M$42,5,0) -> #N/A | K22: =J22/J$42 -> #DIV/0! | L22: =K22 -> #DIV/0! | M22: =_xlfn.IFS(L22<80%,"A",L22<=95%,"B",L22>95%,"C") -> #DIV/0!
D23: =C23/C$42 -> #DIV/0! | E23: =D23+E22 -> #DIV/0! | F23: =IF(AND(E23<=0),"C",IF(E23<=0.8,"A",IF(E23<=0.95,"B","C"))) -> #DIV/0! | G23: =VLOOKUP(B$22:B$42,I$22:M$42,5,0) -> #N/A | K23: =J23/J$42 -> #DIV/0! | L23: =K23+L22 -> #DIV/0! | M23: =_xlfn.IFS(L23<80%,"A",L23<=95%,"B",L23>95%,"C") -> #DIV/0!
D24: =C24/C$42 -> #DIV/0! | E24: =D24+E23 -> #DIV/0! | F24: =IF(AND(E24<=0),"C",IF(E24<=0.8,"A",IF(E24<=0.95,"B","C"))) -> #DIV/0! | G24: =VLOOKUP(B$22:B$42,I$22:M$42,5,0) -> #N/A | K24: =J24/J$42 -> #DIV/0! | L24: =K24+L23 -> #DIV/0! | M24: =_xlfn.IFS(L24<80%,"A",L24<=95%,"B",L24>95%,"C") -> #DIV/0!
D25: =C25/C$42 -> #DIV/0! | E25: =D25+E24 -> #DIV/0! | F25: =IF(AND(E25<=0),"C",IF(E25<=0.8,"A",IF(E25<=0.95,"B","C"))) -> #DIV/0! | G25: =VLOOKUP(B$22:B$42,I$22:M$42,5,0) -> #N/A | K25: =J25/J$42 -> #DIV/0! | L25: =K25+L24 -> #DIV/0! | M25: =_xlfn.IFS(L25<80%,"A",L25<=95%,"B",L25>95%,"C") -> #DIV/0!
D26: =C26/C$42 -> #DIV/0! | E26: =D26+E25 -> #DIV/0! | F26: =IF(AND(E26<=0),"C",IF(E26<=0.8,"A",IF(E26<=0.95,"B","C"))) -> #DIV/0! | G26: =VLOOKUP(B$22:B$42,I$22:M$42,5,0) -> #N/A | K26: =J26/J$42 -> #DIV/0! | L26: =K26+L25 -> #DIV/0! | M26: =_xlfn.IFS(L26<80%,"A",L26<=95%,"B",L26>95%,"C") -> #DIV/0!
D27: =C27/C$42 -> #DIV/0! | E27: =D27+E26 -> #DIV/0! | F27: =IF(AND(E27<=0),"C",IF(E27<=0.8,"A",IF(E27<=0.95,"B","C"))) -> #DIV/0! | G27: =VLOOKUP(B$22:B$42,I$22:M$42,5,0) -> #N/A | K27: =J27/J$42 -> #DIV/0! | L27: =K27+L26 -> #DIV/0! | M27: =_xlfn.IFS(L27<80%,"A",L27<=95%,"B",L27>95%,"C") -> #DIV/0!
D28: =C28/C$42 -> #DIV/0! | E28: =D28+E27 -> #DIV/0! | F28: =IF(AND(E28<=0),"C",IF(E28<=0.8,"A",IF(E28<=0.95,"B","C"))) -> #DIV/0! | G28: =VLOOKUP(B$22:B$42,I$22:M$42,5,0) -> #N/A | K28: =J28/J$42 -> #DIV/0! | L28: =K28+L27 -> #DIV/0! | M28: =_xlfn.IFS(L28<80%,"A",L28<=95%,"B",L28>95%,"C") -> #DIV/0!
D29: =C29/C$42 -> #DIV/0! | E29: =D29+E28 -> #DIV/0! | F29: =IF(AND(E29<=0),"C",IF(E29<=0.8,"A",IF(E29<=0.95,"B","C"))) -> #DIV/0! | G29: =VLOOKUP(B$22:B$42,I$22:M$42,5,0) -> #N/A | K29: =J29/J$42 -> #DIV/0! | L29: =K29+L28 -> #DIV/0! | M29: =_xlfn.IFS(L29<80%,"A",L29<=95%,"B",L29>95%,"C") -> #DIV/0!
D30: =C30/C$42 -> #DIV/0! | E30: =D30+E29 -> #DIV/0! | F30: =IF(AND(E30<=0),"C",IF(E30<=0.8,"A",IF(E30<=0.95,"B","C"))) -> #DIV/0! | G30: =VLOOKUP(B$22:B$42,I$22:M$42,5,0) -> #N/A | K30: =J30/J$42 -> #DIV/0! | L30: =K30+L29 -> #DIV/0! | M30: =_xlfn.IFS(L30<80%,"A",L30<=95%,"B",L30>95%,"C") -> #DIV/0!
D31: =C31/C$42 -> #DIV/0! | E31: =D31+E30 -> #DIV/0! | F31: =IF(AND(E31<=0),"C",IF(E31<=0.8,"A",IF(E31<=0.95,"B","C"))) -> #DIV/0! | G31: =VLOOKUP(B$22:B$42,I$22:M$42,5,0) -> #N/A | K31: =J31/J$42 -> #DIV/0! | L31: =K31+L30 -> #DIV/0! | M31: =_xlfn.IFS(L31<80%,"A",L31<=95%,"B",L31>95%,"C") -> #DIV/0!
D32: =C32/C$42 -> #DIV/0! | E32: =D32+E31 -> #DIV/0! | F32: =IF(AND(E32<=0),"C",IF(E32<=0.8,"A",IF(E32<=0.95,"B","C"))) -> #DIV/0! | G32: =VLOOKUP(B$22:B$42,I$22:M$42,5,0) -> #N/A | K32: =J32/J$42 -> #DIV/0! | L32: =K32+L31 -> #DIV/0! | M32: =_xlfn.IFS(L32<80%,"A",L32<=95%,"B",L32>95%,"C") -> #DIV/0!
D33: =C33/C$42 -> #DIV/0! | E33: =D33+E32 -> #DIV/0! | F33: =IF(AND(E33<=0),"C",IF(E33<=0.8,"A",IF(E33<=0.95,"B","C"))) -> #DIV/0! | G33: =VLOOKUP(B$22:B$42,I$22:M$42,5,0) -> #N/A | K33: =J33/J$42 -> #DIV/0! | L33: =K33+L32 -> #DIV/0! | M33: =_xlfn.IFS(L33<80%,"A",L33<=95%,"B",L33>95%,"C") -> #DIV/0!
D34: =C34/C$42 -> #DIV/0! | E34: =D34+E33 -> #DIV/0! | F34: =IF(AND(E34<=0),"C",IF(E34<=0.8,"A",IF(E34<=0.95,"B","C"))) -> #DIV/0! | G34: =VLOOKUP(B$22:B$42,I$22:M$42,5,0) -> #N/A | K34: =J34/J$42 -> #DIV/0! | L34: =K34+L33 -> #DIV/0! | M34: =_xlfn.IFS(L34<80%,"A",L34<=95%,"B",L34>95%,"C") -> #DIV/0!
... D41: =C41/C$42 -> #DIV/0! | E41: =D41+E40 -> #DIV/0! | F41: =IF(AND(E41<=0),"C",IF(E41<=0.8,"A",IF(E41<=0.95,"B","C"))) -> #DIV/0! | G41: =VLOOKUP(B$22:B$42,I$22:M$42,5,0) -> #N/A | K41: =J41/J$42 -> #DIV/0! | L41: =K41+L40 -> #DIV/0! | M41: =_xlfn.IFS(L41<80%,"A",L41<=95%,"B",L41>95%,"C") -> #DIV/0!
C42: =SUM(C22:C41) -> 0 | D42: =SUM(D22:D41) -> #DIV/0! | J42: =SUM(J22:J41) -> 0 | K42: =SUM(K22:K41) -> #DIV/0!

Sheet АВС 02-08.03
B2: ОЧКИ
C3: Прибыль | D3: % прибыль | E3: Доля | F3: ABC прибыль | G3: ABC кол-во | J3: Кол-во | K3: % кол-во | L3: Доля | M3: ABC кол-во
B4: th желт | C4: ='Юнит 02-08.03'!AE11 -> 7184.9577 | D4: =C4/C$18 -> 0.25404898 | E4: =D4 -> 0.25404898 | F4: =IF(AND(E4<=0),"C",IF(E4<=0.8,"A",IF(E4<=0.95,"B","C"))) -> A | G4: =VLOOKUP(B$4:B$17,I$4:M$17,5,0) -> A | I4: MR8854 C2 | J4: ='Юнит 02-08.03'!R8 -> 14 | K4: =J4/J$18 -> 0.15730337 | L4: =K4 -> 0.15730337 | M4: =_xlfn.IFS(L4<80%,"A",L4<=95%,"B",L4>95%,"C") -> A
B5: qs коричневые | C5: ='Юнит 02-08.03'!AE7 -> 5286.3223 | D5: =C5/C$18 -> 0.18691618 | E5: =D5+E4 -> 0.44096516 | F5: =IF(AND(E5<=0),"C",IF(E5<=0.8,"A",IF(E5<=0.95,"B","C"))) -> A | G5: =VLOOKUP(B$4:B$17,I$4:M$17,5,0) -> A | I5: qs коричневые | J5: ='Юнит 02-08.03'!R7 -> 13 | K5: =J5/J$18 -> 0.14606742 | L5: =K5+L4 -> 0.30337079 | M5: =_xlfn.IFS(L5<80%,"A",L5<=95%,"B",L5>95%,"C") -> A
B6: th черн | C6: ='Юнит 02-08.03'!AE9 -> 4879.252 | D6: =C6/C$18 -> 0.1725228 | E6: =D6+E5 -> 0.61348796 | F6: =IF(AND(E6<=0),"C",IF(E6<=0.8,"A",IF(E6<=0.95,"B","C"))) -> A | G6: =VLOOKUP(B$4:B$17,I$4:M$17,5,0) -> B | I6: flip жел | J6: ='Юнит 02-08.03'!R15 -> 12 | K6: =J6/J$18 -> 0.13483146 | L6: =K6+L5 -> 0.43820225 | M6: =_xlfn.IFS(L6<80%,"A",L6<=95%,"B",L6>95%,"C") -> A
B7: MR8854 C2 | C7: ='Юнит 02-08.03'!AE8 -> 3210.7427 | D7: =C7/C$18 -> 0.11352689 | E7: =D7+E6 -> 0.72701485 | F7: =IF(AND(E7<=0),"C",IF(E7<=0.8,"A",IF(E7<=0.95,"B","C"))) -> A | G7: =VLOOKUP(B$4:B$17,I$4:M$17,5,0) -> A | I7: qs желтые | J7: ='Юнит 02-08.03'!R6 -> 8 | K7: =J7/J$18 -> 0.08988764 | L7: =K7+L6 -> 0.52808989 | M7: =_xlfn.IFS(L7<80%,"A",L7<=95%,"B",L7>95%,"C") -> A
B8: flip черный | C8: ='Юнит 02-08.03'!AE13 -> 2905.8291 | D8: =C8/C$18 -> 0.10274562 | E8: =D8+E7 -> 0.82976047 | F8: =IF(AND(E8<=0),"C",IF(E8<=0.8,"A",IF(E8<=0.95,"B","C"))) -> B | G8: =VLOOKUP(B$4:B$17,I$4:M$17,5,0) -> A | I8: th желт | J8: ='Юнит 02-08.03'!R11 -> 8 | K8: =J8/J$18 -> 0.08988764 | L8: =K8+L7 -> 0.61797753 | M8: =_xlfn.IFS(L8<80%,"A",L8<=95%,"B",L8>95%,"C") -> A
B9: flip жел | C9: ='Юнит 02-08.03'!AE15 -> 2790.4321 | D9: =C9/C$18 -> 0.098665363 | E9: =D9+E8 -> 0.92842584 | F9: =IF(AND(E9<=0),"C",IF(E9<=0.8,"A",IF(E9<=0.95,"B","C"))) -> B | G9: =VLOOKUP(B$4:B$17,I$4:M$17,5,0) -> A | I9: flip коричневый | J9: ='Юнит 02-08.03'!R16 -> 8 | K9: =J9/J$18 -> 0.08988764 | L9: =K9+L8 -> 0.70786517 | M9: =_xlfn.IFS(L9<80%,"A",L9<=95%,"B",L9>95%,"C") -> A
B10: qs желтые | C10: ='Юнит 02-08.03'!AE6 -> 2439.4431 | D10: =C10/C$18 -> 0.086254931 | E10: =D10+E9 -> 1.0146808 | F10: =IF(AND(E10<=0),"C",IF(E10<=0.8,"A",IF(E10<=0.95,"B","C"))) -> C | G10: =VLOOKUP(B$4:B$17,I$4:M$17,5,0) -> A | I10: flip черный | J10: ='Юнит 02-08.03'!R13 -> 7 | K10: =J10/J$18 -> 0.078651685 | L10: =K10+L9 -> 0.78651685 | M10: =_xlfn.IFS(L10<80%,"A",L10<=95%,"B",L10>95%,"C") -> A
B11: flip коричневый | C11: ='Юнит 02-08.03'!AE16 -> 2155.6623 | D11: =C11/C$18 -> 0.076220883 | E11: =D11+E10 -> 1.0909017 | F11: =IF(AND(E11<=0),"C",IF(E11<=0.8,"A",IF(E11<=0.95,"B","C"))) -> C | G11: =VLOOKUP(B$4:B$17,I$4:M$17,5,0) -> A | I11: th черн | J11: ='Юнит 02-08.03'!R9 -> 5 | K11: =J11/J$18 -> 0.056179775 | L11: =K11+L10 -> 0.84269663 | M11: =_xlfn.IFS(L11<80%,"A",L11<=95%,"B",L11>95%,"C") -> B
B12: th син | C12: ='Юнит 02-08.03'!AE10 -> 1647.6334 | D12: =C12/C$18 -> 0.058257766 | E12: =D12+E5 -> 0.49922293 | F12: =IF(AND(E12<=0),"C",IF(E12<=0.8,"A",IF(E12<=0.95,"B","C"))) -> A | G12: =VLOOKUP(B$4:B$17,I$4:M$17,5,0) -> A | I12: th син | J12: ='Юнит 02-08.03'!R10 -> 5 | K12: =J12/J$18 -> 0.056179775 | L12: =K12+L5 -> 0.35955056 | M12: =_xlfn.IFS(L12<80%,"A",L12<=95%,"B",L12>95%,"C") -> A
B13: th коричн | C13: ='Юнит 02-08.03'!AE12 -> 1177.2783 | D13: =C13/C$18 -> 0.04162674 | E13: =D13+E12 -> 0.54084967 | F13: =IF(AND(E13<=0),"C",IF(E13<=0.8,"A",IF(E13<=0.95,"B","C"))) -> A | G13: =VLOOKUP(B$4:B$17,I$4:M$17,5,0) -> A | I13: th коричн | J13: ='Юнит 02-08.03'!R12 -> 4 | K13: =J13/J$18 -> 0.04494382 | L13: =K13+L12 -> 0.40449438 | M13: =_xlfn.IFS(L13<80%,"A",L13<=95%,"B",L13>95%,"C") -> A
B14: qs черные | C14: ='Юнит 02-08.03'!AE4 -> 581.43477 | D14: =C14/C$18 -> 0.020558634 | E14: =D14+E13 -> 0.5614083 | F14: =IF(AND(E14<=0),"C",IF(E14<=0.8,"A",IF(E14<=0.95,"B","C"))) -> A | G14: =VLOOKUP(B$4:B$17,I$4:M$17,5,0) -> A | I14: черные с железкой классика | J14: ='Юнит 02-08.03'!R3 -> 2 | K14: =J14/J$18 -> 0.02247191 | L14: =K14+L13 -> 0.42696629 | M14: =_xlfn.IFS(L14<80%,"A",L14<=95%,"B",L14>95%,"C") -> A
B15: qs синие | C15: ='Юнит 02-08.03'!AE5 -> 412.06158 | D15: =C15/C$18 -> 0.01456986 | E15: =D15+E14 -> 0.57597816 | F15: =IF(AND(E15<=0),"C",IF(E15<=0.8,"A",IF(E15<=0.95,"B","C"))) -> A | G15: =VLOOKUP(B$4:B$17,I$4:M$17,5,0) -> A | I15: qs черные | J15: ='Юнит 02-08.03'!R4 -> 2 | K15: =J15/J$18 -> 0.02247191 | L15: =K15+L14 -> 0.4494382 | M15: =_xlfn.IFS(L15<80%,"A",L15<=95%,"B",L15>95%,"C") -> A
B16: flip синий | C16: ='Юнит 02-08.03'!AE14 -> -916.64 | D16: =C16/C$18 -> -0.032410972 | E16: =D16+E15 -> 0.54356719 | F16: =IF(AND(E16<=0),"C",IF(E16<=0.8,"A",IF(E16<=0.95,"B","C"))) -> A | G16: =VLOOKUP(B$4:B$17,I$4:M$17,5,0) -> A | I16: qs синие | J16: ='Юнит 02-08.03'!R5 -> 1 | K16: =J16/J$18 -> 0.011235955 | L16: =K16+L15 -> 0.46067416 | M16: =_xlfn.IFS(L16<80%,"A",L16<=95%,"B",L16>95%,"C") -> A
B17: черные с железкой классика | C17: ='Юнит 02-08.03'!AE3 -> -5472.6286 | D17: =C17/C$18 -> -0.19350368 | E17: =D17+E14 -> 0.36790462 | F17: =IF(AND(E17<=0),"C",IF(E17<=0.8,"A",IF(E17<=0.95,"B","C"))) -> A | G17: =VLOOKUP(B$4:B$17,I$4:M$17,5,0) -> A | I17: flip синий | J17: ='Юнит 02-08.03'!R14 -> 0 | K17: =J17/J$18 -> 0 | L17: =K17+L14 -> 0.42696629 | M17: =_xlfn.IFS(L17<80%,"A",L17<=95%,"B",L17>95%,"C") -> A
C18: =SUM(C4:C17) -> 28281.781 | D18: =SUM(D4:D17) -> 1 | J18: =SUM(J4:J17) -> 89 | K18: =SUM(K4:K17) -> 1
C21: Прибыль | D21: % прибыль | E21: Доля | F21: ABC прибыль | G21: ABC кол-во | J21: Кол-во | K21: % кол-во | L21: Доля | M21: ABC кол-во
D22: =C22/C$42 -> #DIV/0! | E22: =D22 -> #DIV/0! | F22: =IF(AND(E22<=0),"C",IF(E22<=0.8,"A",IF(E22<=0.95,"B","C"))) -> #DIV/0! | G22: =VLOOKUP(B$22:B$42,I$22:M$42,5,0) -> #N/A | K22: =J22/J$42 -> #DIV/0! | L22: =K22 -> #DIV/0! | M22: =_xlfn.IFS(L22<80%,"A",L22<=95%,"B",L22>95%,"C") -> #DIV/0!
D23: =C23/C$42 -> #DIV/0! | E23: =D23+E22 -> #DIV/0! | F23: =IF(AND(E23<=0),"C",IF(E23<=0.8,"A",IF(E23<=0.95,"B","C"))) -> #DIV/0! | G23: =VLOOKUP(B$22:B$42,I$22:M$42,5,0) -> #N/A | K23: =J23/J$42 -> #DIV/0! | L23: =K23+L22 -> #DIV/0! | M23: =_xlfn.IFS(L23<80%,"A",L23<=95%,"B",L23>95%,"C") -> #DIV/0!
D24: =C24/C$42 -> #DIV/0! | E24: =D24+E23 -> #DIV/0! | F24: =IF(AND(E24<=0),"C",IF(E24<=0.8,"A",IF(E24<=0.95,"B","C"))) -> #DIV/0! | G24: =VLOOKUP(B$22:B$42,I$22:M$42,5,0) -> #N/A | K24: =J24/J$42 -> #DIV/0! | L24: =K24+L23 -> #DIV/0! | M24: =_xlfn.IFS(L24<80%,"A",L24<=95%,"B",L24>95%,"C") -> #DIV/0!
D25: =C25/C$42 -> #DIV/0! | E25: =D25+E24 -> #DIV/0! | F25: =IF(AND(E25<=0),"C",IF(E25<=0.8,"A",IF(E25<=0.95,"B","C"))) -> #DIV/0! | G25: =VLOOKUP(B$22:B$42,I$22:M$42,5,0) -> #N/A | K25: =J25/J$42 -> #DIV/0! | L25: =K25+L24 -> #DIV/0! | M25: =_xlfn.IFS(L25<80%,"A",L25<=95%,"B",L25>95%,"C") -> #DIV/0!
D26: =C26/C$42 -> #DIV/0! | E26: =D26+E25 -> #DIV/0! | F26: =IF(AND(E26<=0),"C",IF(E26<=0.8,"A",IF(E26<=0.95,"B","C"))) -> #DIV/0! | G26: =VLOOKUP(B$22:B$42,I$22:M$42,5,0) -> #N/A | K26: =J26/J$42 -> #DIV/0! | L26: =K26+L25 -> #DIV/0! | M26: =_xlfn.IFS(L26<80%,"A",L26<=95%,"B",L26>95%,"C") -> #DIV/0!
D27: =C27/C$42 -> #DIV/0! | E27: =D27+E26 -> #DIV/0! | F27: =IF(AND(E27<=0),"C",IF(E27<=0.8,"A",IF(E27<=0.95,"B","C"))) -> #DIV/0! | G27: =VLOOKUP(B$22:B$42,I$22:M$42,5,0) -> #N/A | K27: =J27/J$42 -> #DIV/0! | L27: =K27+L26 -> #DIV/0! | M27: =_xlfn.IFS(L27<80%,"A",L27<=95%,"B",L27>95%,"C") -> #DIV/0!
D28: =C28/C$42 -> #DIV/0! | E28: =D28+E27 -> #DIV/0! | F28: =IF(AND(E28<=0),"C",IF(E28<=0.8,"A",IF(E28<=0.95,"B","C"))) -> #DIV/0! | G28: =VLOOKUP(B$22:B$42,I$22:M$42,5,0) -> #N/A | K28: =J28/J$42 -> #DIV/0! | L28: =K28+L27 -> #DIV/0! | M28: =_xlfn.IFS(L28<80%,"A",L28<=95%,"B",L28>95%,"C") -> #DIV/0!
D29: =C29/C$42 -> #DIV/0! | E29: =D29+E28 -> #DIV/0! | F29: =IF(AND(E29<=0),"C",IF(E29<=0.8,"A",IF(E29<=0.95,"B","C"))) -> #DIV/0! | G29: =VLOOKUP(B$22:B$42,I$22:M$42,5,0) -> #N/A | K29: =J29/J$42 -> #DIV/0! | L29: =K29+L28 -> #DIV/0! | M29: =_xlfn.IFS(L29<80%,"A",L29<=95%,"B",L29>95%,"C") -> #DIV/0!
D30: =C30/C$42 -> #DIV/0! | E30: =D30+E29 -> #DIV/0! | F30: =IF(AND(E30<=0),"C",IF(E30<=0.8,"A",IF(E30<=0.95,"B","C"))) -> #DIV/0! | G30: =VLOOKUP(B$22:B$42,I$22:M$42,5,0) -> #N/A | K30: =J30/J$42 -> #DIV/0! | L30: =K30+L29 -> #DIV/0! | M30: =_xlfn.IFS(L30<80%,"A",L30<=95%,"B",L30>95%,"C") -> #DIV/0!
D31: =C31/C$42 -> #DIV/0! | E31: =D31+E30 -> #DIV/0! | F31: =IF(AND(E31<=0),"C",IF(E31<=0.8,"A",IF(E31<=0.95,"B","C"))) -> #DIV/0! | G31: =VLOOKUP(B$22:B$42,I$22:M$42,5,0) -> #N/A | K31: =J31/J$42 -> #DIV/0! | L31: =K31+L30 -> #DIV/0! | M31: =_xlfn.IFS(L31<80%,"A",L31<=95%,"B",L31>95%,"C") -> #DIV/0!
D32: =C32/C$42 -> #DIV/0! | E32: =D32+E31 -> #DIV/0! | F32: =IF(AND(E32<=0),"C",IF(E32<=0.8,"A",IF(E32<=0.95,"B","C"))) -> #DIV/0! | G32: =VLOOKUP(B$22:B$42,I$22:M$42,5,0) -> #N/A | K32: =J32/J$42 -> #DIV/0! | L32: =K32+L31 -> #DIV/0! | M32: =_xlfn.IFS(L32<80%,"A",L32<=95%,"B",L32>95%,"C") -> #DIV/0!
D33: =C33/C$42 -> #DIV/0! | E33: =D33+E32 -> #DIV/0! | F33: =IF(AND(E33<=0),"C",IF(E33<=0.8,"A",IF(E33<=0.95,"B","C"))) -> #DIV/0! | G33: =VLOOKUP(B$22:B$42,I$22:M$42,5,0) -> #N/A | K33: =J33/J$42 -> #DIV/0! | L33: =K33+L32 -> #DIV/0! | M33: =_xlfn.IFS(L33<80%,"A",L33<=95%,"B",L33>95%,"C") -> #DIV/0!
D34: =C34/C$42 -> #DIV/0! | E34: =D34+E33 -> #DIV/0! | F34: =IF(AND(E34<=0),"C",IF(E34<=0.8,"A",IF(E34<=0.95,"B","C"))) -> #DIV/0! | G34: =VLOOKUP(B$22:B$42,I$22:M$42,5,0) -> #N/A | K34: =J34/J$42 -> #DIV/0! | L34: =K34+L33 -> #DIV/0! | M34: =_xlfn.IFS(L34<80%,"A",L34<=95%,"B",L34>95%,"C") -> #DIV/0!
... D41: =C41/C$42 -> #DIV/0! | E41: =D41+E40 -> #DIV/0! | F41: =IF(AND(E41<=0),"C",IF(E41<=0.8,"A",IF(E41<=0.95,"B","C"))) -> #DIV/0! | G41: =VLOOKUP(B$22:B$42,I$22:M$42,5,0) -> #N/A | K41: =J41/J$42 -> #DIV/0! | L41: =K41+L40 -> #DIV/0! | M41: =_xlfn.IFS(L41<80%,"A",L41<=95%,"B",L41>95%,"C") -> #DIV/0!
C42: =SUM(C22:C41) -> 0 | D42: =SUM(D22:D41) -> #DIV/0! | J42: =SUM(J22:J41) -> 0 | K42: =SUM(K22:K41) -> #DIV/0!

Sheet АВС ФЕВРАЛЬ
B2: ОЧКИ
C3: Прибыль | D3: % прибыль | E3: Доля | F3: ABC прибыль | G3: ABC кол-во | J3: Кол-во | K3: % кол-во | L3: Доля | M3: ABC кол-во
B4: th желт | C4: =ФЕВРАЛЬ!AE11 -> 46604.635 | D4: =C4/C$18 -> 0.20684727 | E4: =D4 -> 0.20684727 | F4: =IF(AND(E4<=0),"C",IF(E4<=0.8,"A",IF(E4<=0.95,"B","C"))) -> A | G4: =VLOOKUP(B$4:B$17,I$4:M$17,5,0) -> A | I4: th желт | J4: =ФЕВРАЛЬ!R11 -> 105 | K4: =J4/J$18 -> 0.19125683 | L4: =K4 -> 0.19125683 | M4: =_xlfn.IFS(L4<80%,"A",L4<=95%,"B",L4>95%,"C") -> A
B5: flip жел | C5: =ФЕВРАЛЬ!AE15 -> 42795.638 | D5: =C5/C$18 -> 0.18994164 | E5: =D5+E4 -> 0.39678892 | F5: =IF(AND(E5<=0),"C",IF(E5<=0.8,"A",IF(E5<=0.95,"B","C"))) -> A | G5: =VLOOKUP(B$4:B$17,I$4:M$17,5,0) -> A | I5: flip жел | J5: =ФЕВРАЛЬ!R15 -> 91 | K5: =J5/J$18 -> 0.16575592 | L5: =K5+L4 -> 0.35701275 | M5: =_xlfn.IFS(L5<80%,"A",L5<=95%,"B",L5>95%,"C") -> A
B6: MR8854 C2 | C6: =ФЕВРАЛЬ!AE8 -> 27498.912 | D6: =C6/C$18 -> 0.12204956 | E6: =D6+E5 -> 0.51883847 | F6: =IF(AND(E6<=0),"C",IF(E6<=0.8,"A",IF(E6<=0.95,"B","C"))) -> A | G6: =VLOOKUP(B$4:B$17,I$4:M$17,5,0) -> A | I6: qs коричневые | J6: =ФЕВРАЛЬ!R7 -> 64 | K6: =J6/J$18 -> 0.11657559 | L6: =K6+L5 -> 0.47358834 | M6: =_xlfn.IFS(L6<80%,"A",L6<=95%,"B",L6>95%,"C") -> A
B7: qs коричневые | C7: =ФЕВРАЛЬ!AE7 -> 17588.26 | D7: =C7/C$18 -> 0.0780627 | E7: =D7+E6 -> 0.59690117 | F7: =IF(AND(E7<=0),"C",IF(E7<=0.8,"A",IF(E7<=0.95,"B","C"))) -> A | G7: =VLOOKUP(B$4:B$17,I$4:M$17,5,0) -> A | I7: MR8854 C2 | J7: =ФЕВРАЛЬ!R8 -> 58 | K7: =J7/J$18 -> 0.10564663 | L7: =K7+L6 -> 0.57923497 | M7: =_xlfn.IFS(L7<80%,"A",L7<=95%,"B",L7>95%,"C") -> A
B8: qs желтые | C8: =ФЕВРАЛЬ!AE6 -> 15496.897 | D8: =C8/C$18 -> 0.068780519 | E8: =D8+E7 -> 0.66568169 | F8: =IF(AND(E8<=0),"C",IF(E8<=0.8,"A",IF(E8<=0.95,"B","C"))) -> A | G8: =VLOOKUP(B$4:B$17,I$4:M$17,5,0) -> A | I8: flip черный | J8: =ФЕВРАЛЬ!R13 -> 37 | K8: =J8/J$18 -> 0.067395264 | L8: =K8+L7 -> 0.64663024 | M8: =_xlfn.IFS(L8<80%,"A",L8<=95%,"B",L8>95%,"C") -> A
B9: flip коричневый | C9: =ФЕВРАЛЬ!AE16 -> 14713.312 | D9: =C9/C$18 -> 0.0653027 | E9: =D9+E8 -> 0.73098439 | F9: =IF(AND(E9<=0),"C",IF(E9<=0.8,"A",IF(E9<=0.95,"B","C"))) -> A | G9: =VLOOKUP(B$4:B$17,I$4:M$17,5,0) -> A | I9: flip коричневый | J9: =ФЕВРАЛЬ!R16 -> 35 | K9: =J9/J$18 -> 0.063752277 | L9: =K9+L8 -> 0.71038251 | M9: =_xlfn.IFS(L9<80%,"A",L9<=95%,"B",L9>95%,"C") -> A
B10: th син | C10: =ФЕВРАЛЬ!AE10 -> 14356.309 | D10: =C10/C$18 -> 0.063718199 | E10: =D10+E9 -> 0.79470259 | F10: =IF(AND(E10<=0),"C",IF(E10<=0.8,"A",IF(E10<=0.95,"B","C"))) -> A | G10: =VLOOKUP(B$4:B$17,I$4:M$17,5,0) -> B | I10: qs желтые | J10: =ФЕВРАЛЬ!R6 -> 29 | K10: =J10/J$18 -> 0.052823315 | L10: =K10+L9 -> 0.76320583 | M10: =_xlfn.IFS(L10<80%,"A",L10<=95%,"B",L10>95%,"C") -> A
B11: flip черный | C11: =ФЕВРАЛЬ!AE13 -> 13248.471 | D11: =C11/C$18 -> 0.058801237 | E11: =D11+E10 -> 0.85350383 | F11: =IF(AND(E11<=0),"C",IF(E11<=0.8,"A",IF(E11<=0.95,"B","C"))) -> B | G11: =VLOOKUP(B$4:B$17,I$4:M$17,5,0) -> A | I11: th син | J11: =ФЕВРАЛЬ!R10 -> 28 | K11: =J11/J$18 -> 0.051001821 | L11: =K11+L10 -> 0.81420765 | M11: =_xlfn.IFS(L11<80%,"A",L11<=95%,"B",L11>95%,"C") -> B
B12: flip синий | C12: =ФЕВРАЛЬ!AE14 -> 9302.9702 | D12: =C12/C$18 -> 0.041289756 | E12: =D12+E5 -> 0.43807867 | F12: =IF(AND(E12<=0),"C",IF(E12<=0.8,"A",IF(E12<=0.95,"B","C"))) -> A | G12: =VLOOKUP(B$4:B$17,I$4:M$17,5,0) -> A | I12: th коричн | J12: =ФЕВРАЛЬ!R12 -> 24 | K12: =J12/J$18 -> 0.043715847 | L12: =K12+L5 -> 0.4007286 | M12: =_xlfn.IFS(L12<80%,"A",L12<=95%,"B",L12>95%,"C") -> A
B13: qs черные | C13: =ФЕВРАЛЬ!AE4 -> 7968.1985 | D13: =C13/C$18 -> 0.035365584 | E13: =D13+E12 -> 0.47344426 | F13: =IF(AND(E13<=0),"C",IF(E13<=0.8,"A",IF(E13<=0.95,"B","C"))) -> A | G13: =VLOOKUP(B$4:B$17,I$4:M$17,5,0) -> A | I13: flip синий | J13: =ФЕВРАЛЬ!R14 -> 22 | K13: =J13/J$18 -> 0.04007286 | L13: =K13+L12 -> 0.44080146 | M13: =_xlfn.IFS(L13<80%,"A",L13<=95%,"B",L13>95%,"C") -> A
B14: th черн | C14: =ФЕВРАЛЬ!AE9 -> 4092.0496 | D14: =C14/C$18 -> 0.018161912 | E14: =D14+E13 -> 0.49160617 | F14: =IF(AND(E14<=0),"C",IF(E14<=0.8,"A",IF(E14<=0.95,"B","C"))) -> A | G14: =VLOOKUP(B$4:B$17,I$4:M$17,5,0) -> A | I14: qs черные | J14: =ФЕВРАЛЬ!R4 -> 16 | K14: =J14/J$18 -> 0.029143898 | L14: =K14+L13 -> 0.46994536 | M14: =_xlfn.IFS(L14<80%,"A",L14<=95%,"B",L14>95%,"C") -> A
B15: черные с железкой классика | C15: =ФЕВРАЛЬ!AE3 -> 4043.5122 | D15: =C15/C$18 -> 0.017946487 | E15: =D15+E14 -> 0.50955266 | F15: =IF(AND(E15<=0),"C",IF(E15<=0.8,"A",IF(E15<=0.95,"B","C"))) -> A | G15: =VLOOKUP(B$4:B$17,I$4:M$17,5,0) -> A | I15: th черн | J15: =ФЕВРАЛЬ!R9 -> 15 | K15: =J15/J$18 -> 0.027322404 | L15: =K15+L14 -> 0.49726776 | M15: =_xlfn.IFS(L15<80%,"A",L15<=95%,"B",L15>95%,"C") -> A
B16: th коричн | C16: =ФЕВРАЛЬ!AE12 -> 4062.9028 | D16: =C16/C$18 -> 0.018032549 | E16: =D16+E15 -> 0.52758521 | F16: =IF(AND(E16<=0),"C",IF(E16<=0.8,"A",IF(E16<=0.95,"B","C"))) -> A | G16: =VLOOKUP(B$4:B$17,I$4:M$17,5,0) -> A | I16: черные с железкой классика | J16: =ФЕВРАЛЬ!R3 -> 13 | K16: =J16/J$18 -> 0.023679417 | L16: =K16+L15 -> 0.52094718 | M16: =_xlfn.IFS(L16<80%,"A",L16<=95%,"B",L16>95%,"C") -> A
B17: qs синие | C17: =ФЕВРАЛЬ!AE5 -> 3537.3311 | D17: =C17/C$18 -> 0.015699882 | E17: =D17+E14 -> 0.50730605 | F17: =IF(AND(E17<=0),"C",IF(E17<=0.8,"A",IF(E17<=0.95,"B","C"))) -> A | G17: =VLOOKUP(B$4:B$17,I$4:M$17,5,0) -> A | I17: qs синие | J17: =ФЕВРАЛЬ!R5 -> 12 | K17: =J17/J$18 -> 0.021857923 | L17: =K17+L14 -> 0.49180328 | M17: =_xlfn.IFS(L17<80%,"A",L17<=95%,"B",L17>95%,"C") -> A
C18: =SUM(C4:C17) -> 225309.4 | D18: =SUM(D4:D17) -> 1 | J18: =SUM(J4:J17) -> 549 | K18: =SUM(K4:K17) -> 1
C21: Прибыль | D21: % прибыль | E21: Доля | F21: ABC прибыль | G21: ABC кол-во | J21: Кол-во | K21: % кол-во | L21: Доля | M21: ABC кол-во
D22: =C22/C$42 -> #DIV/0! | E22: =D22 -> #DIV/0! | F22: =IF(AND(E22<=0),"C",IF(E22<=0.8,"A",IF(E22<=0.95,"B","C"))) -> #DIV/0! | G22: =VLOOKUP(B$22:B$42,I$22:M$42,5,0) -> #N/A | K22: =J22/J$42 -> #DIV/0! | L22: =K22 -> #DIV/0! | M22: =_xlfn.IFS(L22<80%,"A",L22<=95%,"B",L22>95%,"C") -> #DIV/0!
D23: =C23/C$42 -> #DIV/0! | E23: =D23+E22 -> #DIV/0! | F23: =IF(AND(E23<=0),"C",IF(E23<=0.8,"A",IF(E23<=0.95,"B","C"))) -> #DIV/0! | G23: =VLOOKUP(B$22:B$42,I$22:M$42,5,0) -> #N/A | K23: =J23/J$42 -> #DIV/0! | L23: =K23+L22 -> #DIV/0! | M23: =_xlfn.IFS(L23<80%,"A",L23<=95%,"B",L23>95%,"C") -> #DIV/0!
D24: =C24/C$42 -> #DIV/0! | E24: =D24+E23 -> #DIV/0! | F24: =IF(AND(E24<=0),"C",IF(E24<=0.8,"A",IF(E24<=0.95,"B","C"))) -> #DIV/0! | G24: =VLOOKUP(B$22:B$42,I$22:M$42,5,0) -> #N/A | K24: =J24/J$42 -> #DIV/0! | L24: =K24+L23 -> #DIV/0! | M24: =_xlfn.IFS(L24<80%,"A",L24<=95%,"B",L24>95%,"C") -> #DIV/0!
D25: =C25/C$42 -> #DIV/0! | E25: =D25+E24 -> #DIV/0! | F25: =IF(AND(E25<=0),"C",IF(E25<=0.8,"A",IF(E25<=0.95,"B","C"))) -> #DIV/0! | G25: =VLOOKUP(B$22:B$42,I$22:M$42,5,0) -> #N/A | K25: =J25/J$42 -> #DIV/0! | L25: =K25+L24 -> #DIV/0! | M25: =_xlfn.IFS(L25<80%,"A",L25<=95%,"B",L25>95%,"C") -> #DIV/0!
D26: =C26/C$42 -> #DIV/0! | E26: =D26+E25 -> #DIV/0! | F26: =IF(AND(E26<=0),"C",IF(E26<=0.8,"A",IF(E26<=0.95,"B","C"))) -> #DIV/0! | G26: =VLOOKUP(B$22:B$42,I$22:M$42,5,0) -> #N/A | K26: =J26/J$42 -> #DIV/0! | L26: =K26+L25 -> #DIV/0! | M26: =_xlfn.IFS(L26<80%,"A",L26<=95%,"B",L26>95%,"C") -> #DIV/0!
D27: =C27/C$42 -> #DIV/0! | E27: =D27+E26 -> #DIV/0! | F27: =IF(AND(E27<=0),"C",IF(E27<=0.8,"A",IF(E27<=0.95,"B","C"))) -> #DIV/0! | G27: =VLOOKUP(B$22:B$42,I$22:M$42,5,0) -> #N/A | K27: =J27/J$42 -> #DIV/0! | L27: =K27+L26 -> #DIV/0! | M27: =_xlfn.IFS(L27<80%,"A",L27<=95%,"B",L27>95%,"C") -> #DIV/0!
D28: =C28/C$42 -> #DIV/0! | E28: =D28+E27 -> #DIV/0! | F28: =IF(AND(E28<=0),"C",IF(E28<=0.8,"A",IF(E28<=0.95,"B","C"))) -> #DIV/0! | G28: =VLOOKUP(B$22:B$42,I$22:M$42,5,0) -> #N/A | K28: =J28/J$42 -> #DIV/0! | L28: =K28+L27 -> #DIV/0! | M28: =_xlfn.IFS(L28<80%,"A",L28<=95%,"B",L28>95%,"C") -> #DIV/0!
D29: =C29/C$42 -> #DIV/0! | E29: =D29+E28 -> #DIV/0! | F29: =IF(AND(E29<=0),"C",IF(E29<=0.8,"A",IF(E29<=0.95,"B","C"))) -> #DIV/0! | G29: =VLOOKUP(B$22:B$42,I$22:M$42,5,0) -> #N/A | K29: =J29/J$42 -> #DIV/0! | L29: =K29+L28 -> #DIV/0! | M29: =_xlfn.IFS(L29<80%,"A",L29<=95%,"B",L29>95%,"C") -> #DIV/0!
D30: =C30/C$42 -> #DIV/0! | E30: =D30+E29 -> #DIV/0! | F30: =IF(AND(E30<=0),"C",IF(E30<=0.8,"A",IF(E30<=0.95,"B","C"))) -> #DIV/0! | G30: =VLOOKUP(B$22:B$42,I$22:M$42,5,0) -> #N/A | K30: =J30/J$42 -> #DIV/0! | L30: =K30+L29 -> #DIV/0! | M30: =_xlfn.IFS(L30<80%,"A",L30<=95%,"B",L30>95%,"C") -> #DIV/0!
D31: =C31/C$42 -> #DIV/0! | E31: =D31+E30 -> #DIV/0! | F31: =IF(AND(E31<=0),"C",IF(E31<=0.8,"A",IF(E31<=0.95,"B","C"))) -> #DIV/0! | G31: =VLOOKUP(B$22:B$42,I$22:M$42,5,0) -> #N/A | K31: =J31/J$42 -> #DIV/0! | L31: =K31+L30 -> #DIV/0! | M31: =_xlfn.IFS(L31<80%,"A",L31<=95%,"B",L31>95%,"C") -> #DIV/0!
D32: =C32/C$42 -> #DIV/0! | E32: =D32+E31 -> #DIV/0! | F32: =IF(AND(E32<=0),"C",IF(E32<=0.8,"A",IF(E32<=0.95,"B","C"))) -> #DIV/0! | G32: =VLOOKUP(B$22:B$42,I$22:M$42,5,0) -> #N/A | K32: =J32/J$42 -> #DIV/0! | L32: =K32+L31 -> #DIV/0! | M32: =_xlfn.IFS(L32<80%,"A",L32<=95%,"B",L32>95%,"C") -> #DIV/0!
D33: =C33/C$42 -> #DIV/0! | E33: =D33+E32 -> #DIV/0! | F33: =IF(AND(E33<=0),"C",IF(E33<=0.8,"A",IF(E33<=0.95,"B","C"))) -> #DIV/0! | G33: =VLOOKUP(B$22:B$42,I$22:M$42,5,0) -> #N/A | K33: =J33/J$42 -> #DIV/0! | L33: =K33+L32 -> #DIV/0! | M33: =_xlfn.IFS(L33<80%,"A",L33<=95%,"B",L33>95%,"C") -> #DIV/0!
D34: =C34/C$42 -> #DIV/0! | E34: =D34+E33 -> #DIV/0! | F34: =IF(AND(E34<=0),"C",IF(E34<=0.8,"A",IF(E34<=0.95,"B","C"))) -> #DIV/0! | G34: =VLOOKUP(B$22:B$42,I$22:M$42,5,0) -> #N/A | K34: =J34/J$42 -> #DIV/0! | L34: =K34+L33 -> #DIV/0! | M34: =_xlfn.IFS(L34<80%,"A",L34<=95%,"B",L34>95%,"C") -> #DIV/0!
... D41: =C41/C$42 -> #DIV/0! | E41: =D41+E40 -> #DIV/0! | F41: =IF(AND(E41<=0),"C",IF(E41<=0.8,"A",IF(E41<=0.95,"B","C"))) -> #DIV/0! | G41: =VLOOKUP(B$22:B$42,I$22:M$42,5,0) -> #N/A | K41: =J41/J$42 -> #DIV/0! | L41: =K41+L40 -> #DIV/0! | M41: =_xlfn.IFS(L41<80%,"A",L41<=95%,"B",L41>95%,"C") -> #DIV/0!
C42: =SUM(C22:C41) -> 0 | D42: =SUM(D22:D41) -> #DIV/0! | J42: =SUM(J22:J41) -> 0 | K42: =SUM(K22:K41) -> #DIV/0!

Sheet АВС 23.02-01.03
B2: ОЧКИ
C3: Прибыль | D3: % прибыль | E3: Доля | F3: ABC прибыль | G3: ABC кол-во | J3: Кол-во | K3: % кол-во | L3: Доля | M3: ABC кол-во
B4: MR8854 C2 | C4: ='Юнит 23.02-01.03'!AE8 -> 10426.618 | D4: =C4/C$18 -> 0.23609764 | E4: =D4 -> 0.23609764 | F4: =IF(AND(E4<=0),"C",IF(E4<=0.8,"A",IF(E4<=0.95,"B","C"))) -> A | G4: =VLOOKUP(B$4:B$17,I$4:M$17,5,0) -> A | I4: MR8854 C2 | J4: ='Юнит 23.02-01.03'!R8 -> 17 | K4: =J4/J$18 -> 0.15044248 | L4: =K4 -> 0.15044248 | M4: =_xlfn.IFS(L4<80%,"A",L4<=95%,"B",L4>95%,"C") -> A
B5: flip жел | C5: ='Юнит 23.02-01.03'!AE15 -> 8944.4606 | D5: =C5/C$18 -> 0.20253605 | E5: =D5+E4 -> 0.43863369 | F5: =IF(AND(E5<=0),"C",IF(E5<=0.8,"A",IF(E5<=0.95,"B","C"))) -> A | G5: =VLOOKUP(B$4:B$17,I$4:M$17,5,0) -> A | I5: flip жел | J5: ='Юнит 23.02-01.03'!R15 -> 17 | K5: =J5/J$18 -> 0.15044248 | L5: =K5+L4 -> 0.30088496 | M5: =_xlfn.IFS(L5<80%,"A",L5<=95%,"B",L5>95%,"C") -> A
B6: qs коричневые | C6: ='Юнит 23.02-01.03'!AE7 -> 5980.9182 | D6: =C6/C$18 -> 0.13543036 | E6: =D6+E5 -> 0.57406405 | F6: =IF(AND(E6<=0),"C",IF(E6<=0.8,"A",IF(E6<=0.95,"B","C"))) -> A | G6: =VLOOKUP(B$4:B$17,I$4:M$17,5,0) -> A | I6: qs коричневые | J6: ='Юнит 23.02-01.03'!R7 -> 15 | K6: =J6/J$18 -> 0.13274336 | L6: =K6+L5 -> 0.43362832 | M6: =_xlfn.IFS(L6<80%,"A",L6<=95%,"B",L6>95%,"C") -> A
B7: flip черный | C7: ='Юнит 23.02-01.03'!AE13 -> 4848.254 | D7: =C7/C$18 -> 0.10978261 | E7: =D7+E6 -> 0.68384666 | F7: =IF(AND(E7<=0),"C",IF(E7<=0.8,"A",IF(E7<=0.95,"B","C"))) -> A | G7: =VLOOKUP(B$4:B$17,I$4:M$17,5,0) -> A | I7: flip черный | J7: ='Юнит 23.02-01.03'!R13 -> 12 | K7: =J7/J$18 -> 0.10619469 | L7: =K7+L6 -> 0.53982301 | M7: =_xlfn.IFS(L7<80%,"A",L7<=95%,"B",L7>95%,"C") -> A
B8: qs желтые | C8: ='Юнит 23.02-01.03'!AE6 -> 3930.4352 | D8: =C8/C$18 -> 0.088999757 | E8: =D8+E7 -> 0.77284642 | F8: =IF(AND(E8<=0),"C",IF(E8<=0.8,"A",IF(E8<=0.95,"B","C"))) -> A | G8: =VLOOKUP(B$4:B$17,I$4:M$17,5,0) -> A | I8: flip коричневый | J8: ='Юнит 23.02-01.03'!R16 -> 9 | K8: =J8/J$18 -> 0.079646018 | L8: =K8+L7 -> 0.61946903 | M8: =_xlfn.IFS(L8<80%,"A",L8<=95%,"B",L8>95%,"C") -> A
B9: черные с железкой классика | C9: ='Юнит 23.02-01.03'!AE3 -> 2967.9729 | D9: =C9/C$18 -> 0.06720601 | E9: =D9+E8 -> 0.84005243 | F9: =IF(AND(E9<=0),"C",IF(E9<=0.8,"A",IF(E9<=0.95,"B","C"))) -> B | G9: =VLOOKUP(B$4:B$17,I$4:M$17,5,0) -> A | I9: черные с железкой классика | J9: ='Юнит 23.02-01.03'!R3 -> 7 | K9: =J9/J$18 -> 0.061946903 | L9: =K9+L8 -> 0.68141593 | M9: =_xlfn.IFS(L9<80%,"A",L9<=95%,"B",L9>95%,"C") -> A
B10: th син | C10: ='Юнит 23.02-01.03'!AE10 -> 2677.8258 | D10: =C10/C$18 -> 0.060635993 | E10: =D10+E9 -> 0.90068842 | F10: =IF(AND(E10<=0),"C",IF(E10<=0.8,"A",IF(E10<=0.95,"B","C"))) -> B | G10: =VLOOKUP(B$4:B$17,I$4:M$17,5,0) -> A | I10: qs желтые | J10: ='Юнит 23.02-01.03'!R6 -> 7 | K10: =J10/J$18 -> 0.061946903 | L10: =K10+L9 -> 0.74336283 | M10: =_xlfn.IFS(L10<80%,"A",L10<=95%,"B",L10>95%,"C") -> A
B11: flip коричневый | C11: ='Юнит 23.02-01.03'!AE16 -> 2666.483 | D11: =C11/C$18 -> 0.06037915 | E11: =D11+E10 -> 0.96106757 | F11: =IF(AND(E11<=0),"C",IF(E11<=0.8,"A",IF(E11<=0.95,"B","C"))) -> C | G11: =VLOOKUP(B$4:B$17,I$4:M$17,5,0) -> A | I11: th желт | J11: ='Юнит 23.02-01.03'!R11 -> 7 | K11: =J11/J$18 -> 0.061946903 | L11: =K11+L10 -> 0.80530973 | M11: =_xlfn.IFS(L11<80%,"A",L11<=95%,"B",L11>95%,"C") -> B
B12: flip синий | C12: ='Юнит 23.02-01.03'!AE14 -> 2149.5305 | D12: =C12/C$18 -> 0.048673413 | E12: =D12+E5 -> 0.4873071 | F12: =IF(AND(E12<=0),"C",IF(E12<=0.8,"A",IF(E12<=0.95,"B","C"))) -> A | G12: =VLOOKUP(B$4:B$17,I$4:M$17,5,0) -> A | I12: qs черные | J12: ='Юнит 23.02-01.03'!R4 -> 5 | K12: =J12/J$18 -> 0.044247788 | L12: =K12+L5 -> 0.34513274 | M12: =_xlfn.IFS(L12<80%,"A",L12<=95%,"B",L12>95%,"C") -> A
B13: qs черные | C13: ='Юнит 23.02-01.03'!AE4 -> 1734.179 | D13: =C13/C$18 -> 0.039268299 | E13: =D13+E12 -> 0.5265754 | F13: =IF(AND(E13<=0),"C",IF(E13<=0.8,"A",IF(E13<=0.95,"B","C"))) -> A | G13: =VLOOKUP(B$4:B$17,I$4:M$17,5,0) -> A | I13: th коричн | J13: ='Юнит 23.02-01.03'!R12 -> 5 | K13: =J13/J$18 -> 0.044247788 | L13: =K13+L12 -> 0.38938053 | M13: =_xlfn.IFS(L13<80%,"A",L13<=95%,"B",L13>95%,"C") -> A
B14: qs синие | C14: ='Юнит 23.02-01.03'!AE5 -> 1407.3663 | D14: =C14/C$18 -> 0.031868038 | E14: =D14+E13 -> 0.55844344 | F14: =IF(AND(E14<=0),"C",IF(E14<=0.8,"A",IF(E14<=0.95,"B","C"))) -> A | G14: =VLOOKUP(B$4:B$17,I$4:M$17,5,0) -> A | I14: qs синие | J14: ='Юнит 23.02-01.03'!R5 -> 4 | K14: =J14/J$18 -> 0.03539823 | L14: =K14+L13 -> 0.42477876 | M14: =_xlfn.IFS(L14<80%,"A",L14<=95%,"B",L14>95%,"C") -> A
B15: th желт | C15: ='Юнит 23.02-01.03'!AE11 -> -963.20294 | D15: =C15/C$18 -> -0.021810518 | E15: =D15+E14 -> 0.53663292 | F15: =IF(AND(E15<=0),"C",IF(E15<=0.8,"A",IF(E15<=0.95,"B","C"))) -> A | G15: =VLOOKUP(B$4:B$17,I$4:M$17,5,0) -> B | I15: th син | J15: ='Юнит 23.02-01.03'!R10 -> 4 | K15: =J15/J$18 -> 0.03539823 | L15: =K15+L14 -> 0.46017699 | M15: =_xlfn.IFS(L15<80%,"A",L15<=95%,"B",L15>95%,"C") -> A
B16: th коричн | C16: ='Юнит 23.02-01.03'!AE12 -> -1156.2606 | D16: =C16/C$18 -> -0.026182066 | E16: =D16+E15 -> 0.51045086 | F16: =IF(AND(E16<=0),"C",IF(E16<=0.8,"A",IF(E16<=0.95,"B","C"))) -> A | G16: =VLOOKUP(B$4:B$17,I$4:M$17,5,0) -> A | I16: flip синий | J16: ='Юнит 23.02-01.03'!R14 -> 3 | K16: =J16/J$18 -> 0.026548673 | L16: =K16+L15 -> 0.48672566 | M16: =_xlfn.IFS(L16<80%,"A",L16<=95%,"B",L16>95%,"C") -> A
B17: th черн | C17: ='Юнит 23.02-01.03'!AE9 -> -1452.266 | D17: =C17/C$18 -> -0.032884736 | E17: =D17+E14 -> 0.5255587 | F17: =IF(AND(E17<=0),"C",IF(E17<=0.8,"A",IF(E17<=0.95,"B","C"))) -> A | G17: =VLOOKUP(B$4:B$17,I$4:M$17,5,0) -> A | I17: th черн | J17: ='Юнит 23.02-01.03'!R9 -> 1 | K17: =J17/J$18 -> 0.0088495575 | L17: =K17+L14 -> 0.43362832 | M17: =_xlfn.IFS(L17<80%,"A",L17<=95%,"B",L17>95%,"C") -> A
C18: =SUM(C4:C17) -> 44162.314 | D18: =SUM(D4:D17) -> 1 | J18: =SUM(J4:J17) -> 113 | K18: =SUM(K4:K17) -> 1
C21: Прибыль | D21: % прибыль | E21: Доля | F21: ABC прибыль | G21: ABC кол-во | J21: Кол-во | K21: % кол-во | L21: Доля | M21: ABC кол-во
D22: =C22/C$42 -> #DIV/0! | E22: =D22 -> #DIV/0! | F22: =IF(AND(E22<=0),"C",IF(E22<=0.8,"A",IF(E22<=0.95,"B","C"))) -> #DIV/0! | G22: =VLOOKUP(B$22:B$42,I$22:M$42,5,0) -> #N/A | K22: =J22/J$42 -> #DIV/0! | L22: =K22 -> #DIV/0! | M22: =_xlfn.IFS(L22<80%,"A",L22<=95%,"B",L22>95%,"C") -> #DIV/0!
D23: =C23/C$42 -> #DIV/0! | E23: =D23+E22 -> #DIV/0! | F23: =IF(AND(E23<=0),"C",IF(E23<=0.8,"A",IF(E23<=0.95,"B","C"))) -> #DIV/0! | G23: =VLOOKUP(B$22:B$42,I$22:M$42,5,0) -> #N/A | K23: =J23/J$42 -> #DIV/0! | L23: =K23+L22 -> #DIV/0! | M23: =_xlfn.IFS(L23<80%,"A",L23<=95%,"B",L23>95%,"C") -> #DIV/0!
D24: =C24/C$42 -> #DIV/0! | E24: =D24+E23 -> #DIV/0! | F24: =IF(AND(E24<=0),"C",IF(E24<=0.8,"A",IF(E24<=0.95,"B","C"))) -> #DIV/0! | G24: =VLOOKUP(B$22:B$42,I$22:M$42,5,0) -> #N/A | K24: =J24/J$42 -> #DIV/0! | L24: =K24+L23 -> #DIV/0! | M24: =_xlfn.IFS(L24<80%,"A",L24<=95%,"B",L24>95%,"C") -> #DIV/0!
D25: =C25/C$42 -> #DIV/0! | E25: =D25+E24 -> #DIV/0! | F25: =IF(AND(E25<=0),"C",IF(E25<=0.8,"A",IF(E25<=0.95,"B","C"))) -> #DIV/0! | G25: =VLOOKUP(B$22:B$42,I$22:M$42,5,0) -> #N/A | K25: =J25/J$42 -> #DIV/0! | L25: =K25+L24 -> #DIV/0! | M25: =_xlfn.IFS(L25<80%,"A",L25<=95%,"B",L25>95%,"C") -> #DIV/0!
D26: =C26/C$42 -> #DIV/0! | E26: =D26+E25 -> #DIV/0! | F26: =IF(AND(E26<=0),"C",IF(E26<=0.8,"A",IF(E26<=0.95,"B","C"))) -> #DIV/0! | G26: =VLOOKUP(B$22:B$42,I$22:M$42,5,0) -> #N/A | K26: =J26/J$42 -> #DIV/0! | L26: =K26+L25 -> #DIV/0! | M26: =_xlfn.IFS(L26<80%,"A",L26<=95%,"B",L26>95%,"C") -> #DIV/0!
D27: =C27/C$42 -> #DIV/0! | E27: =D27+E26 -> #DIV/0! | F27: =IF(AND(E27<=0),"C",IF(E27<=0.8,"A",IF(E27<=0.95,"B","C"))) -> #DIV/0! | G27: =VLOOKUP(B$22:B$42,I$22:M$42,5,0) -> #N/A | K27: =J27/J$42 -> #DIV/0! | L27: =K27+L26 -> #DIV/0! | M27: =_xlfn.IFS(L27<80%,"A",L27<=95%,"B",L27>95%,"C") -> #DIV/0!
D28: =C28/C$42 -> #DIV/0! | E28: =D28+E27 -> #DIV/0! | F28: =IF(AND(E28<=0),"C",IF(E28<=0.8,"A",IF(E28<=0.95,"B","C"))) -> #DIV/0! | G28: =VLOOKUP(B$22:B$42,I$22:M$42,5,0) -> #N/A | K28: =J28/J$42 -> #DIV/0! | L28: =K28+L27 -> #DIV/0! | M28: =_xlfn.IFS(L28<80%,"A",L28<=95%,"B",L28>95%,"C") -> #DIV/0!
D29: =C29/C$42 -> #DIV/0! | E29: =D29+E28 -> #DIV/0! | F29: =IF(AND(E29<=0),"C",IF(E29<=0.8,"A",IF(E29<=0.95,"B","C"))) -> #DIV/0! | G29: =VLOOKUP(B$22:B$42,I$22:M$42,5,0) -> #N/A | K29: =J29/J$42 -> #DIV/0! | L29: =K29+L28 -> #DIV/0! | M29: =_xlfn.IFS(L29<80%,"A",L29<=95%,"B",L29>95%,"C") -> #DIV/0!
D30: =C30/C$42 -> #DIV/0! | E30: =D30+E29 -> #DIV/0! | F30: =IF(AND(E30<=0),"C",IF(E30<=0.8,"A",IF(E30<=0.95,"B","C"))) -> #DIV/0! | G30: =VLOOKUP(B$22:B$42,I$22:M$42,5,0) -> #N/A | K30: =J30/J$42 -> #DIV/0! | L30: =K30+L29 -> #DIV/0! | M30: =_xlfn.IFS(L30<80%,"A",L30<=95%,"B",L30>95%,"C") -> #DIV/0!
D31: =C31/C$42 -> #DIV/0! | E31: =D31+E30 -> #DIV/0! | F31: =IF(AND(E31<=0),"C",IF(E31<=0.8,"A",IF(E31<=0.95,"B","C"))) -> #DIV/0! | G31: =VLOOKUP(B$22:B$42,I$22:M$42,5,0) -> #N/A | K31: =J31/J$42 -> #DIV/0! | L31: =K31+L30 -> #DIV/0! | M31: =_xlfn.IFS(L31<80%,"A",L31<=95%,"B",L31>95%,"C") -> #DIV/0!
D32: =C32/C$42 -> #DIV/0! | E32: =D32+E31 -> #DIV/0! | F32: =IF(AND(E32<=0),"C",IF(E32<=0.8,"A",IF(E32<=0.95,"B","C"))) -> #DIV/0! | G32: =VLOOKUP(B$22:B$42,I$22:M$42,5,0) -> #N/A | K32: =J32/J$42 -> #DIV/0! | L32: =K32+L31 -> #DIV/0! | M32: =_xlfn.IFS(L32<80%,"A",L32<=95%,"B",L32>95%,"C") -> #DIV/0!
D33: =C33/C$42 -> #DIV/0! | E33: =D33+E32 -> #DIV/0! | F33: =IF(AND(E33<=0),"C",IF(E33<=0.8,"A",IF(E33<=0.95,"B","C"))) -> #DIV/0! | G33: =VLOOKUP(B$22:B$42,I$22:M$42,5,0) -> #N/A | K33: =J33/J$42 -> #DIV/0! | L33: =K33+L32 -> #DIV/0! | M33: =_xlfn.IFS(L33<80%,"A",L33<=95%,"B",L33>95%,"C") -> #DIV/0!
D34: =C34/C$42 -> #DIV/0! | E34: =D34+E33 -> #DIV/0! | F34: =IF(AND(E34<=0),"C",IF(E34<=0.8,"A",IF(E34<=0.95,"B","C"))) -> #DIV/0! | G34: =VLOOKUP(B$22:B$42,I$22:M$42,5,0) -> #N/A | K34: =J34/J$42 -> #DIV/0! | L34: =K34+L33 -> #DIV/0! | M34: =_xlfn.IFS(L34<80%,"A",L34<=95%,"B",L34>95%,"C") -> #DIV/0!
... D41: =C41/C$42 -> #DIV/0! | E41: =D41+E40 -> #DIV/0! | F41: =IF(AND(E41<=0),"C",IF(E41<=0.8,"A",IF(E41<=0.95,"B","C"))) -> #DIV/0! | G41: =VLOOKUP(B$22:B$42,I$22:M$42,5,0) -> #N/A | K41: =J41/J$42 -> #DIV/0! | L41: =K41+L40 -> #DIV/0! | M41: =_xlfn.IFS(L41<80%,"A",L41<=95%,"B",L41>95%,"C") -> #DIV/0!
C42: =SUM(C22:C41) -> 0 | D42: =SUM(D22:D41) -> #DIV/0! | J42: =SUM(J22:J41) -> 0 | K42: =SUM(K22:K41) -> #DIV/0!

Sheet АВС 16-22.02
B2: ОЧКИ
C3: Прибыль | D3: % прибыль | E3: Доля | F3: ABC прибыль | G3: ABC кол-во | J3: Кол-во | K3: % кол-во | L3: Доля | M3: ABC кол-во
B4: th желт | C4: ='Юнит 16-22.02'!AE11 -> 15588.532 | D4: =C4/C$18 -> 0.22056305 | E4: =D4 -> 0.22056305 | F4: =IF(AND(E4<=0),"C",IF(E4<=0.8,"A",IF(E4<=0.95,"B","C"))) -> A | G4: =VLOOKUP(B$4:B$17,I$4:M$17,5,0) -> A | I4: th желт | J4: ='Юнит 16-22.02'!R11 -> 26 | K4: =J4/J$18 -> 0.16993464 | L4: =K4 -> 0.16993464 | M4: =_xlfn.IFS(L4<80%,"A",L4<=95%,"B",L4>95%,"C") -> A
B5: qs коричневые | C5: ='Юнит 16-22.02'!AE7 -> 13263.624 | D5: =C5/C$18 -> 0.1876678 | E5: =D5+E4 -> 0.40823084 | F5: =IF(AND(E5<=0),"C",IF(E5<=0.8,"A",IF(E5<=0.95,"B","C"))) -> A | G5: =VLOOKUP(B$4:B$17,I$4:M$17,5,0) -> A | I5: qs коричневые | J5: ='Юнит 16-22.02'!R7 -> 25 | K5: =J5/J$18 -> 0.16339869 | L5: =K5+L4 -> 0.33333333 | M5: =_xlfn.IFS(L5<80%,"A",L5<=95%,"B",L5>95%,"C") -> A
B6: flip жел | C6: ='Юнит 16-22.02'!AE15 -> 8708.6634 | D6: =C6/C$18 -> 0.12321939 | E6: =D6+E5 -> 0.53145023 | F6: =IF(AND(E6<=0),"C",IF(E6<=0.8,"A",IF(E6<=0.95,"B","C"))) -> A | G6: =VLOOKUP(B$4:B$17,I$4:M$17,5,0) -> A | I6: flip жел | J6: ='Юнит 16-22.02'!R15 -> 17 | K6: =J6/J$18 -> 0.11111111 | L6: =K6+L5 -> 0.44444444 | M6: =_xlfn.IFS(L6<80%,"A",L6<=95%,"B",L6>95%,"C") -> A
B7: MR8854 C2 | C7: ='Юнит 16-22.02'!AE8 -> 6302.1753 | D7: =C7/C$18 -> 0.089169849 | E7: =D7+E6 -> 0.62062008 | F7: =IF(AND(E7<=0),"C",IF(E7<=0.8,"A",IF(E7<=0.95,"B","C"))) -> A | G7: =VLOOKUP(B$4:B$17,I$4:M$17,5,0) -> A | I7: flip черный | J7: ='Юнит 16-22.02'!R13 -> 14 | K7: =J7/J$18 -> 0.091503268 | L7: =K7+L6 -> 0.53594771 | M7: =_xlfn.IFS(L7<80%,"A",L7<=95%,"B",L7>95%,"C") -> A
B8: th син | C8: ='Юнит 16-22.02'!AE10 -> 5579.1551 | D8: =C8/C$18 -> 0.078939794 | E8: =D8+E7 -> 0.69955988 | F8: =IF(AND(E8<=0),"C",IF(E8<=0.8,"A",IF(E8<=0.95,"B","C"))) -> A | G8: =VLOOKUP(B$4:B$17,I$4:M$17,5,0) -> A | I8: MR8854 C2 | J8: ='Юнит 16-22.02'!R8 -> 12 | K8: =J8/J$18 -> 0.078431373 | L8: =K8+L7 -> 0.61437908 | M8: =_xlfn.IFS(L8<80%,"A",L8<=95%,"B",L8>95%,"C") -> A
B9: flip коричневый | C9: ='Юнит 16-22.02'!AE16 -> 4582.0618 | D9: =C9/C$18 -> 0.064831861 | E9: =D9+E8 -> 0.76439174 | F9: =IF(AND(E9<=0),"C",IF(E9<=0.8,"A",IF(E9<=0.95,"B","C"))) -> A | G9: =VLOOKUP(B$4:B$17,I$4:M$17,5,0) -> A | I9: th син | J9: ='Юнит 16-22.02'!R10 -> 10 | K9: =J9/J$18 -> 0.065359477 | L9: =K9+L8 -> 0.67973856 | M9: =_xlfn.IFS(L9<80%,"A",L9<=95%,"B",L9>95%,"C") -> A
B10: flip синий | C10: ='Юнит 16-22.02'!AE14 -> 3933.2357 | D10: =C10/C$18 -> 0.055651583 | E10: =D10+E9 -> 0.82004332 | F10: =IF(AND(E10<=0),"C",IF(E10<=0.8,"A",IF(E10<=0.95,"B","C"))) -> B | G10: =VLOOKUP(B$4:B$17,I$4:M$17,5,0) -> A | I10: flip коричневый | J10: ='Юнит 16-22.02'!R16 -> 10 | K10: =J10/J$18 -> 0.065359477 | L10: =K10+L9 -> 0.74509804 | M10: =_xlfn.IFS(L10<80%,"A",L10<=95%,"B",L10>95%,"C") -> A
B11: flip черный | C11: ='Юнит 16-22.02'!AE13 -> 3142.7759 | D11: =C11/C$18 -> 0.044467321 | E11: =D11+E10 -> 0.86451064 | F11: =IF(AND(E11<=0),"C",IF(E11<=0.8,"A",IF(E11<=0.95,"B","C"))) -> B | G11: =VLOOKUP(B$4:B$17,I$4:M$17,5,0) -> A | I11: qs желтые | J11: ='Юнит 16-22.02'!R6 -> 8 | K11: =J11/J$18 -> 0.052287582 | L11: =K11+L10 -> 0.79738562 | M11: =_xlfn.IFS(L11<80%,"A",L11<=95%,"B",L11>95%,"C") -> A
B12: qs желтые | C12: ='Юнит 16-22.02'!AE6 -> 3000.4661 | D12: =C12/C$18 -> 0.042453772 | E12: =D12+E5 -> 0.45068462 | F12: =IF(AND(E12<=0),"C",IF(E12<=0.8,"A",IF(E12<=0.95,"B","C"))) -> A | G12: =VLOOKUP(B$4:B$17,I$4:M$17,5,0) -> A | I12: th коричн | J12: ='Юнит 16-22.02'!R12 -> 7 | K12: =J12/J$18 -> 0.045751634 | L12: =K12+L5 -> 0.37908497 | M12: =_xlfn.IFS(L12<80%,"A",L12<=95%,"B",L12>95%,"C") -> A
B13: th черн | C13: ='Юнит 16-22.02'!AE9 -> 2666.4773 | D13: =C13/C$18 -> 0.037728144 | E13: =D13+E12 -> 0.48841276 | F13: =IF(AND(E13<=0),"C",IF(E13<=0.8,"A",IF(E13<=0.95,"B","C"))) -> A | G13: =VLOOKUP(B$4:B$17,I$4:M$17,5,0) -> A | I13: flip синий | J13: ='Юнит 16-22.02'!R14 -> 7 | K13: =J13/J$18 -> 0.045751634 | L13: =K13+L12 -> 0.4248366 | M13: =_xlfn.IFS(L13<80%,"A",L13<=95%,"B",L13>95%,"C") -> A
B14: qs черные | C14: ='Юнит 16-22.02'!AE4 -> 1779.7586 | D14: =C14/C$18 -> 0.025181909 | E14: =D14+E13 -> 0.51359467 | F14: =IF(AND(E14<=0),"C",IF(E14<=0.8,"A",IF(E14<=0.95,"B","C"))) -> A | G14: =VLOOKUP(B$4:B$17,I$4:M$17,5,0) -> A | I14: th черн | J14: ='Юнит 16-22.02'!R9 -> 6 | K14: =J14/J$18 -> 0.039215686 | L14: =K14+L13 -> 0.46405229 | M14: =_xlfn.IFS(L14<80%,"A",L14<=95%,"B",L14>95%,"C") -> A
B15: th коричн | C15: ='Юнит 16-22.02'!AE12 -> 1475.1304 | D15: =C15/C$18 -> 0.020871707 | E15: =D15+E14 -> 0.53446638 | F15: =IF(AND(E15<=0),"C",IF(E15<=0.8,"A",IF(E15<=0.95,"B","C"))) -> A | G15: =VLOOKUP(B$4:B$17,I$4:M$17,5,0) -> A | I15: qs черные | J15: ='Юнит 16-22.02'!R4 -> 5 | K15: =J15/J$18 -> 0.032679739 | L15: =K15+L14 -> 0.49673203 | M15: =_xlfn.IFS(L15<80%,"A",L15<=95%,"B",L15>95%,"C") -> A
B16: qs синие | C16: ='Юнит 16-22.02'!AE5 -> 553.58181 | D16: =C16/C$18 -> 0.0078326616 | E16: =D16+E15 -> 0.54229904 | F16: =IF(AND(E16<=0),"C",IF(E16<=0.8,"A",IF(E16<=0.95,"B","C"))) -> A | G16: =VLOOKUP(B$4:B$17,I$4:M$17,5,0) -> A | I16: черные с железкой классика | J16: ='Юнит 16-22.02'!R3 -> 3 | K16: =J16/J$18 -> 0.019607843 | L16: =K16+L15 -> 0.51633987 | M16: =_xlfn.IFS(L16<80%,"A",L16<=95%,"B",L16>95%,"C") -> A
B17: черные с железкой классика | C17: ='Юнит 16-22.02'!AE3 -> 100.44239 | D17: =C17/C$18 -> 0.0014211653 | E17: =D17+E14 -> 0.51501583 | F17: =IF(AND(E17<=0),"C",IF(E17<=0.8,"A",IF(E17<=0.95,"B","C"))) -> A | G17: =VLOOKUP(B$4:B$17,I$4:M$17,5,0) -> A | I17: qs синие | J17: ='Юнит 16-22.02'!R5 -> 3 | K17: =J17/J$18 -> 0.019607843 | L17: =K17+L14 -> 0.48366013 | M17: =_xlfn.IFS(L17<80%,"A",L17<=95%,"B",L17>95%,"C") -> A
C18: =SUM(C4:C17) -> 70676.079 | D18: =SUM(D4:D17) -> 1 | J18: =SUM(J4:J17) -> 153 | K18: =SUM(K4:K17) -> 1
C21: Прибыль | D21: % прибыль | E21: Доля | F21: ABC прибыль | G21: ABC кол-во | J21: Кол-во | K21: % кол-во | L21: Доля | M21: ABC кол-во
D22: =C22/C$42 -> #DIV/0! | E22: =D22 -> #DIV/0! | F22: =IF(AND(E22<=0),"C",IF(E22<=0.8,"A",IF(E22<=0.95,"B","C"))) -> #DIV/0! | G22: =VLOOKUP(B$22:B$42,I$22:M$42,5,0) -> #N/A | K22: =J22/J$42 -> #DIV/0! | L22: =K22 -> #DIV/0! | M22: =_xlfn.IFS(L22<80%,"A",L22<=95%,"B",L22>95%,"C") -> #DIV/0!
D23: =C23/C$42 -> #DIV/0! | E23: =D23+E22 -> #DIV/0! | F23: =IF(AND(E23<=0),"C",IF(E23<=0.8,"A",IF(E23<=0.95,"B","C"))) -> #DIV/0! | G23: =VLOOKUP(B$22:B$42,I$22:M$42,5,0) -> #N/A | K23: =J23/J$42 -> #DIV/0! | L23: =K23+L22 -> #DIV/0! | M23: =_xlfn.IFS(L23<80%,"A",L23<=95%,"B",L23>95%,"C") -> #DIV/0!
D24: =C24/C$42 -> #DIV/0! | E24: =D24+E23 -> #DIV/0! | F24: =IF(AND(E24<=0),"C",IF(E24<=0.8,"A",IF(E24<=0.95,"B","C"))) -> #DIV/0! | G24: =VLOOKUP(B$22:B$42,I$22:M$42,5,0) -> #N/A | K24: =J24/J$42 -> #DIV/0! | L24: =K24+L23 -> #DIV/0! | M24: =_xlfn.IFS(L24<80%,"A",L24<=95%,"B",L24>95%,"C") -> #DIV/0!
D25: =C25/C$42 -> #DIV/0! | E25: =D25+E24 -> #DIV/0! | F25: =IF(AND(E25<=0),"C",IF(E25<=0.8,"A",IF(E25<=0.95,"B","C"))) -> #DIV/0! | G25: =VLOOKUP(B$22:B$42,I$22:M$42,5,0) -> #N/A | K25: =J25/J$42 -> #DIV/0! | L25: =K25+L24 -> #DIV/0! | M25: =_xlfn.IFS(L25<80%,"A",L25<=95%,"B",L25>95%,"C") -> #DIV/0!
D26: =C26/C$42 -> #DIV/0! | E26: =D26+E25 -> #DIV/0! | F26: =IF(AND(E26<=0),"C",IF(E26<=0.8,"A",IF(E26<=0.95,"B","C"))) -> #DIV/0! | G26: =VLOOKUP(B$22:B$42,I$22:M$42,5,0) -> #N/A | K26: =J26/J$42 -> #DIV/0! | L26: =K26+L25 -> #DIV/0! | M26: =_xlfn.IFS(L26<80%,"A",L26<=95%,"B",L26>95%,"C") -> #DIV/0!
D27: =C27/C$42 -> #DIV/0! | E27: =D27+E26 -> #DIV/0! | F27: =IF(AND(E27<=0),"C",IF(E27<=0.8,"A",IF(E27<=0.95,"B","C"))) -> #DIV/0! | G27: =VLOOKUP(B$22:B$42,I$22:M$42,5,0) -> #N/A | K27: =J27/J$42 -> #DIV/0! | L27: =K27+L26 -> #DIV/0! | M27: =_xlfn.IFS(L27<80%,"A",L27<=95%,"B",L27>95%,"C") -> #DIV/0!
D28: =C28/C$42 -> #DIV/0! | E28: =D28+E27 -> #DIV/0! | F28: =IF(AND(E28<=0),"C",IF(E28<=0.8,"A",IF(E28<=0.95,"B","C"))) -> #DIV/0! | G28: =VLOOKUP(B$22:B$42,I$22:M$42,5,0) -> #N/A | K28: =J28/J$42 -> #DIV/0! | L28: =K28+L27 -> #DIV/0! | M28: =_xlfn.IFS(L28<80%,"A",L28<=95%,"B",L28>95%,"C") -> #DIV/0!
D29: =C29/C$42 -> #DIV/0! | E29: =D29+E28 -> #DIV/0! | F29: =IF(AND(E29<=0),"C",IF(E29<=0.8,"A",IF(E29<=0.95,"B","C"))) -> #DIV/0! | G29: =VLOOKUP(B$22:B$42,I$22:M$42,5,0) -> #N/A | K29: =J29/J$42 -> #DIV/0! | L29: =K29+L28 -> #DIV/0! | M29: =_xlfn.IFS(L29<80%,"A",L29<=95%,"B",L29>95%,"C") -> #DIV/0!
D30: =C30/C$42 -> #DIV/0! | E30: =D30+E29 -> #DIV/0! | F30: =IF(AND(E30<=0),"C",IF(E30<=0.8,"A",IF(E30<=0.95,"B","C"))) -> #DIV/0! | G30: =VLOOKUP(B$22:B$42,I$22:M$42,5,0) -> #N/A | K30: =J30/J$42 -> #DIV/0! | L30: =K30+L29 -> #DIV/0! | M30: =_xlfn.IFS(L30<80%,"A",L30<=95%,"B",L30>95%,"C") -> #DIV/0!
D31: =C31/C$42 -> #DIV/0! | E31: =D31+E30 -> #DIV/0! | F31: =IF(AND(E31<=0),"C",IF(E31<=0.8,"A",IF(E31<=0.95,"B","C"))) -> #DIV/0! | G31: =VLOOKUP(B$22:B$42,I$22:M$42,5,0) -> #N/A | K31: =J31/J$42 -> #DIV/0! | L31: =K31+L30 -> #DIV/0! | M31: =_xlfn.IFS(L31<80%,"A",L31<=95%,"B",L31>95%,"C") -> #DIV/0!
D32: =C32/C$42 -> #DIV/0! | E32: =D32+E31 -> #DIV/0! | F32: =IF(AND(E32<=0),"C",IF(E32<=0.8,"A",IF(E32<=0.95,"B","C"))) -> #DIV/0! | G32: =VLOOKUP(B$22:B$42,I$22:M$42,5,0) -> #N/A | K32: =J32/J$42 -> #DIV/0! | L32: =K32+L31 -> #DIV/0! | M32: =_xlfn.IFS(L32<80%,"A",L32<=95%,"B",L32>95%,"C") -> #DIV/0!
D33: =C33/C$42 -> #DIV/0! | E33: =D33+E32 -> #DIV/0! | F33: =IF(AND(E33<=0),"C",IF(E33<=0.8,"A",IF(E33<=0.95,"B","C"))) -> #DIV/0! | G33: =VLOOKUP(B$22:B$42,I$22:M$42,5,0) -> #N/A | K33: =J33/J$42 -> #DIV/0! | L33: =K33+L32 -> #DIV/0! | M33: =_xlfn.IFS(L33<80%,"A",L33<=95%,"B",L33>95%,"C") -> #DIV/0!
D34: =C34/C$42 -> #DIV/0! | E34: =D34+E33 -> #DIV/0! | F34: =IF(AND(E34<=0),"C",IF(E34<=0.8,"A",IF(E34<=0.95,"B","C"))) -> #DIV/0! | G34: =VLOOKUP(B$22:B$42,I$22:M$42,5,0) -> #N/A | K34: =J34/J$42 -> #DIV/0! | L34: =K34+L33 -> #DIV/0! | M34: =_xlfn.IFS(L34<80%,"A",L34<=95%,"B",L34>95%,"C") -> #DIV/0!
... D41: =C41/C$42 -> #DIV/0! | E41: =D41+E40 -> #DIV/0! | F41: =IF(AND(E41<=0),"C",IF(E41<=0.8,"A",IF(E41<=0.95,"B","C"))) -> #DIV/0! | G41: =VLOOKUP(B$22:B$42,I$22:M$42,5,0) -> #N/A | K41: =J41/J$42 -> #DIV/0! | L41: =K41+L40 -> #DIV/0! | M41: =_xlfn.IFS(L41<80%,"A",L41<=95%,"B",L41>95%,"C") -> #DIV/0!
C42: =SUM(C22:C41) -> 0 | D42: =SUM(D22:D41) -> #DIV/0! | J42: =SUM(J22:J41) -> 0 | K42: =SUM(K22:K41) -> #DIV/0!

Sheet АВС 09-15.02
B2: ОЧКИ
C3: Прибыль | D3: % прибыль | E3: Доля | F3: ABC прибыль | G3: ABC кол-во | J3: Кол-во | K3: % кол-во | L3: Доля | M3: ABC кол-во
B4: черные с железкой классика | D4: =C4/C$18 -> #DIV/0! | E4: =D4 -> #DIV/0! | F4: =IF(AND(E4<=0),"C",IF(E4<=0.8,"A",IF(E4<=0.95,"B","C"))) -> #DIV/0! | G4: =VLOOKUP(B$4:B$17,I$4:M$17,5,0) -> #DIV/0! | I4: черные с железкой классика | K4: =J4/J$18 -> #DIV/0! | L4: =K4 -> #DIV/0! | M4: =_xlfn.IFS(L4<80%,"A",L4<=95%,"B",L4>95%,"C") -> #DIV/0!
B5: qs черные | D5: =C5/C$18 -> #DIV/0! | E5: =D5+E4 -> #DIV/0! | F5: =IF(AND(E5<=0),"C",IF(E5<=0.8,"A",IF(E5<=0.95,"B","C"))) -> #DIV/0! | G5: =VLOOKUP(B$4:B$17,I$4:M$17,5,0) -> #DIV/0! | I5: qs черные | K5: =J5/J$18 -> #DIV/0! | L5: =K5+L4 -> #DIV/0! | M5: =_xlfn.IFS(L5<80%,"A",L5<=95%,"B",L5>95%,"C") -> #DIV/0!
B6: qs синие | D6: =C6/C$18 -> #DIV/0! | E6: =D6+E5 -> #DIV/0! | F6: =IF(AND(E6<=0),"C",IF(E6<=0.8,"A",IF(E6<=0.95,"B","C"))) -> #DIV/0! | G6: =VLOOKUP(B$4:B$17,I$4:M$17,5,0) -> #DIV/0! | I6: qs синие | K6: =J6/J$18 -> #DIV/0! | L6: =K6+L5 -> #DIV/0! | M6: =_xlfn.IFS(L6<80%,"A",L6<=95%,"B",L6>95%,"C") -> #DIV/0!
B7: qs желтые | D7: =C7/C$18 -> #DIV/0! | E7: =D7+E6 -> #DIV/0! | F7: =IF(AND(E7<=0),"C",IF(E7<=0.8,"A",IF(E7<=0.95,"B","C"))) -> #DIV/0! | G7: =VLOOKUP(B$4:B$17,I$4:M$17,5,0) -> #DIV/0! | I7: qs желтые | K7: =J7/J$18 -> #DIV/0! | L7: =K7+L6 -> #DIV/0! | M7: =_xlfn.IFS(L7<80%,"A",L7<=95%,"B",L7>95%,"C") -> #DIV/0!
B8: qs коричневые | D8: =C8/C$18 -> #DIV/0! | E8: =D8+E7 -> #DIV/0! | F8: =IF(AND(E8<=0),"C",IF(E8<=0.8,"A",IF(E8<=0.95,"B","C"))) -> #DIV/0! | G8: =VLOOKUP(B$4:B$17,I$4:M$17,5,0) -> #DIV/0! | I8: qs коричневые | K8: =J8/J$18 -> #DIV/0! | L8: =K8+L7 -> #DIV/0! | M8: =_xlfn.IFS(L8<80%,"A",L8<=95%,"B",L8>95%,"C") -> #DIV/0!
B9: MR8854 C2 | D9: =C9/C$18 -> #DIV/0! | E9: =D9+E8 -> #DIV/0! | F9: =IF(AND(E9<=0),"C",IF(E9<=0.8,"A",IF(E9<=0.95,"B","C"))) -> #DIV/0! | G9: =VLOOKUP(B$4:B$17,I$4:M$17,5,0) -> #DIV/0! | I9: MR8854 C2 | K9: =J9/J$18 -> #DIV/0! | L9: =K9+L8 -> #DIV/0! | M9: =_xlfn.IFS(L9<80%,"A",L9<=95%,"B",L9>95%,"C") -> #DIV/0!
B10: th черн | D10: =C10/C$18 -> #DIV/0! | E10: =D10+E9 -> #DIV/0! | F10: =IF(AND(E10<=0),"C",IF(E10<=0.8,"A",IF(E10<=0.95,"B","C"))) -> #DIV/0! | G10: =VLOOKUP(B$4:B$17,I$4:M$17,5,0) -> #DIV/0! | I10: th черн | K10: =J10/J$18 -> #DIV/0! | L10: =K10+L9 -> #DIV/0! | M10: =_xlfn.IFS(L10<80%,"A",L10<=95%,"B",L10>95%,"C") -> #DIV/0!
B11: th син | D11: =C11/C$18 -> #DIV/0! | E11: =D11+E10 -> #DIV/0! | F11: =IF(AND(E11<=0),"C",IF(E11<=0.8,"A",IF(E11<=0.95,"B","C"))) -> #DIV/0! | G11: =VLOOKUP(B$4:B$17,I$4:M$17,5,0) -> #DIV/0! | I11: th син | K11: =J11/J$18 -> #DIV/0! | L11: =K11+L10 -> #DIV/0! | M11: =_xlfn.IFS(L11<80%,"A",L11<=95%,"B",L11>95%,"C") -> #DIV/0!
B12: th желт | D12: =C12/C$18 -> #DIV/0! | E12: =D12+E5 -> #DIV/0! | F12: =IF(AND(E12<=0),"C",IF(E12<=0.8,"A",IF(E12<=0.95,"B","C"))) -> #DIV/0! | G12: =VLOOKUP(B$4:B$17,I$4:M$17,5,0) -> #DIV/0! | I12: th желт | K12: =J12/J$18 -> #DIV/0! | L12: =K12+L5 -> #DIV/0! | M12: =_xlfn.IFS(L12<80%,"A",L12<=95%,"B",L12>95%,"C") -> #DIV/0!
B13: th коричн | D13: =C13/C$18 -> #DIV/0! | E13: =D13+E12 -> #DIV/0! | F13: =IF(AND(E13<=0),"C",IF(E13<=0.8,"A",IF(E13<=0.95,"B","C"))) -> #DIV/0! | G13: =VLOOKUP(B$4:B$17,I$4:M$17,5,0) -> #DIV/0! | I13: th коричн | K13: =J13/J$18 -> #DIV/0! | L13: =K13+L12 -> #DIV/0! | M13: =_xlfn.IFS(L13<80%,"A",L13<=95%,"B",L13>95%,"C") -> #DIV/0!
B14: flip черный | D14: =C14/C$18 -> #DIV/0! | E14: =D14+E13 -> #DIV/0! | F14: =IF(AND(E14<=0),"C",IF(E14<=0.8,"A",IF(E14<=0.95,"B","C"))) -> #DIV/0! | G14: =VLOOKUP(B$4:B$17,I$4:M$17,5,0) -> #DIV/0! | I14: flip черный | K14: =J14/J$18 -> #DIV/0! | L14: =K14+L13 -> #DIV/0! | M14: =_xlfn.IFS(L14<80%,"A",L14<=95%,"B",L14>95%,"C") -> #DIV/0!
B15: flip синий | D15: =C15/C$18 -> #DIV/0! | E15: =D15+E14 -> #DIV/0! | F15: =IF(AND(E15<=0),"C",IF(E15<=0.8,"A",IF(E15<=0.95,"B","C"))) -> #DIV/0! | G15: =VLOOKUP(B$4:B$17,I$4:M$17,5,0) -> #DIV/0! | I15: flip синий | K15: =J15/J$18 -> #DIV/0! | L15: =K15+L14 -> #DIV/0! | M15: =_xlfn.IFS(L15<80%,"A",L15<=95%,"B",L15>95%,"C") -> #DIV/0!
B16: flip жел | D16: =C16/C$18 -> #DIV/0! | E16: =D16+E15 -> #DIV/0! | F16: =IF(AND(E16<=0),"C",IF(E16<=0.8,"A",IF(E16<=0.95,"B","C"))) -> #DIV/0! | G16: =VLOOKUP(B$4:B$17,I$4:M$17,5,0) -> #DIV/0! | I16: flip жел | K16: =J16/J$18 -> #DIV/0! | L16: =K16+L15 -> #DIV/0! | M16: =_xlfn.IFS(L16<80%,"A",L16<=95%,"B",L16>95%,"C") -> #DIV/0!
B17: flip коричневый | D17: =C17/C$18 -> #DIV/0! | E17: =D17+E14 -> #DIV/0! | F17: =IF(AND(E17<=0),"C",IF(E17<=0.8,"A",IF(E17<=0.95,"B","C"))) -> #DIV/0! | G17: =VLOOKUP(B$4:B$17,I$4:M$17,5,0) -> #DIV/0! | I17: flip коричневый | K17: =J17/J$18 -> #DIV/0! | L17: =K17+L14 -> #DIV/0! | M17: =_xlfn.IFS(L17<80%,"A",L17<=95%,"B",L17>95%,"C") -> #DIV/0!
C18: =SUM(C4:C17) -> 0 | D18: =SUM(D4:D17) -> #DIV/0! | J18: =SUM(J4:J17) -> 0 | K18: =SUM(K4:K17) -> #DIV/0!
C21: Прибыль | D21: % прибыль | E21: Доля | F21: ABC прибыль | G21: ABC кол-во | J21: Кол-во | K21: % кол-во | L21: Доля | M21: ABC кол-во
D22: =C22/C$42 -> #DIV/0! | E22: =D22 -> #DIV/0! | F22: =IF(AND(E22<=0),"C",IF(E22<=0.8,"A",IF(E22<=0.95,"B","C"))) -> #DIV/0! | G22: =VLOOKUP(B$22:B$42,I$22:M$42,5,0) -> #N/A | K22: =J22/J$42 -> #DIV/0! | L22: =K22 -> #DIV/0! | M22: =_xlfn.IFS(L22<80%,"A",L22<=95%,"B",L22>95%,"C") -> #DIV/0!
D23: =C23/C$42 -> #DIV/0! | E23: =D23+E22 -> #DIV/0! | F23: =IF(AND(E23<=0),"C",IF(E23<=0.8,"A",IF(E23<=0.95,"B","C"))) -> #DIV/0! | G23: =VLOOKUP(B$22:B$42,I$22:M$42,5,0) -> #N/A | K23: =J23/J$42 -> #DIV/0! | L23: =K23+L22 -> #DIV/0! | M23: =_xlfn.IFS(L23<80%,"A",L23<=95%,"B",L23>95%,"C") -> #DIV/0!
D24: =C24/C$42 -> #DIV/0! | E24: =D24+E23 -> #DIV/0! | F24: =IF(AND(E24<=0),"C",IF(E24<=0.8,"A",IF(E24<=0.95,"B","C"))) -> #DIV/0! | G24: =VLOOKUP(B$22:B$42,I$22:M$42,5,0) -> #N/A | K24: =J24/J$42 -> #DIV/0! | L24: =K24+L23 -> #DIV/0! | M24: =_xlfn.IFS(L24<80%,"A",L24<=95%,"B",L24>95%,"C") -> #DIV/0!
D25: =C25/C$42 -> #DIV/0! | E25: =D25+E24 -> #DIV/0! | F25: =IF(AND(E25<=0),"C",IF(E25<=0.8,"A",IF(E25<=0.95,"B","C"))) -> #DIV/0! | G25: =VLOOKUP(B$22:B$42,I$22:M$42,5,0) -> #N/A | K25: =J25/J$42 -> #DIV/0! | L25: =K25+L24 -> #DIV/0! | M25: =_xlfn.IFS(L25<80%,"A",L25<=95%,"B",L25>95%,"C") -> #DIV/0!
D26: =C26/C$42 -> #DIV/0! | E26: =D26+E25 -> #DIV/0! | F26: =IF(AND(E26<=0),"C",IF(E26<=0.8,"A",IF(E26<=0.95,"B","C"))) -> #DIV/0! | G26: =VLOOKUP(B$22:B$42,I$22:M$42,5,0) -> #N/A | K26: =J26/J$42 -> #DIV/0! | L26: =K26+L25 -> #DIV/0! | M26: =_xlfn.IFS(L26<80%,"A",L26<=95%,"B",L26>95%,"C") -> #DIV/0!
D27: =C27/C$42 -> #DIV/0! | E27: =D27+E26 -> #DIV/0! | F27: =IF(AND(E27<=0),"C",IF(E27<=0.8,"A",IF(E27<=0.95,"B","C"))) -> #DIV/0! | G27: =VLOOKUP(B$22:B$42,I$22:M$42,5,0) -> #N/A | K27: =J27/J$42 -> #DIV/0! | L27: =K27+L26 -> #DIV/0! | M27: =_xlfn.IFS(L27<80%,"A",L27<=95%,"B",L27>95%,"C") -> #DIV/0!
D28: =C28/C$42 -> #DIV/0! | E28: =D28+E27 -> #DIV/0! | F28: =IF(AND(E28<=0),"C",IF(E28<=0.8,"A",IF(E28<=0.95,"B","C"))) -> #DIV/0! | G28: =VLOOKUP(B$22:B$42,I$22:M$42,5,0) -> #N/A | K28: =J28/J$42 -> #DIV/0! | L28: =K28+L27 -> #DIV/0! | M28: =_xlfn.IFS(L28<80%,"A",L28<=95%,"B",L28>95%,"C") -> #DIV/0!
D29: =C29/C$42 -> #DIV/0! | E29: =D29+E28 -> #DIV/0! | F29: =IF(AND(E29<=0),"C",IF(E29<=0.8,"A",IF(E29<=0.95,"B","C"))) -> #DIV/0! | G29: =VLOOKUP(B$22:B$42,I$22:M$42,5,0) -> #N/A | K29: =J29/J$42 -> #DIV/0! | L29: =K29+L28 -> #DIV/0! | M29: =_xlfn.IFS(L29<80%,"A",L29<=95%,"B",L29>95%,"C") -> #DIV/0!
D30: =C30/C$42 -> #DIV/0! | E30: =D30+E29 -> #DIV/0! | F30: =IF(AND(E30<=0),"C",IF(E30<=0.8,"A",IF(E30<=0.95,"B","C"))) -> #DIV/0! | G30: =VLOOKUP(B$22:B$42,I$22:M$42,5,0) -> #N/A | K30: =J30/J$42 -> #DIV/0! | L30: =K30+L29 -> #DIV/0! | M30: =_xlfn.IFS(L30<80%,"A",L30<=95%,"B",L30>95%,"C") -> #DIV/0!
D31: =C31/C$42 -> #DIV/0! | E31: =D31+E30 -> #DIV/0! | F31: =IF(AND(E31<=0),"C",IF(E31<=0.8,"A",IF(E31<=0.95,"B","C"))) -> #DIV/0! | G31: =VLOOKUP(B$22:B$42,I$22:M$42,5,0) -> #N/A | K31: =J31/J$42 -> #DIV/0! | L31: =K31+L30 -> #DIV/0! | M31: =_xlfn.IFS(L31<80%,"A",L31<=95%,"B",L31>95%,"C") -> #DIV/0!
D32: =C32/C$42 -> #DIV/0! | E32: =D32+E31 -> #DIV/0! | F32: =IF(AND(E32<=0),"C",IF(E32<=0.8,"A",IF(E32<=0.95,"B","C"))) -> #DIV/0! | G32: =VLOOKUP(B$22:B$42,I$22:M$42,5,0) -> #N/A | K32: =J32/J$42 -> #DIV/0! | L32: =K32+L31 -> #DIV/0! | M32: =_xlfn.IFS(L32<80%,"A",L32<=95%,"B",L32>95%,"C") -> #DIV/0!
D33: =C33/C$42 -> #DIV/0! | E33: =D33+E32 -> #DIV/0! | F33: =IF(AND(E33<=0),"C",IF(E33<=0.8,"A",IF(E33<=0.95,"B","C"))) -> #DIV/0! | G33: =VLOOKUP(B$22:B$42,I$22:M$42,5,0) -> #N/A | K33: =J33/J$42 -> #DIV/0! | L33: =K33+L32 -> #DIV/0! | M33: =_xlfn.IFS(L33<80%,"A",L33<=95%,"B",L33>95%,"C") -> #DIV/0!
D34: =C34/C$42 -> #DIV/0! | E34: =D34+E33 -> #DIV/0! | F34: =IF(AND(E34<=0),"C",IF(E34<=0.8,"A",IF(E34<=0.95,"B","C"))) -> #DIV/0! | G34: =VLOOKUP(B$22:B$42,I$22:M$42,5,0) -> #N/A | K34: =J34/J$42 -> #DIV/0! | L34: =K34+L33 -> #DIV/0! | M34: =_xlfn.IFS(L34<80%,"A",L34<=95%,"B",L34>95%,"C") -> #DIV/0!
... D41: =C41/C$42 -> #DIV/0! | E41: =D41+E40 -> #DIV/0! | F41: =IF(AND(E41<=0),"C",IF(E41<=0.8,"A",IF(E41<=0.95,"B","C"))) -> #DIV/0! | G41: =VLOOKUP(B$22:B$42,I$22:M$42,5,0) -> #N/A | K41: =J41/J$42 -> #DIV/0! | L41: =K41+L40 -> #DIV/0! | M41: =_xlfn.IFS(L41<80%,"A",L41<=95%,"B",L41>95%,"C") -> #DIV/0!
C42: =SUM(C22:C41) -> 0 | D42: =SUM(D22:D41) -> #DIV/0! | J42: =SUM(J22:J41) -> 0 | K42: =SUM(K22:K41) -> #DIV/0!

Sheet АВС 02-08.02
B2: ОЧКИ
C3: Прибыль | D3: % прибыль | E3: Доля | F3: ABC прибыль | G3: ABC кол-во | J3: Кол-во | K3: % кол-во | L3: Доля | M3: ABC кол-во
B4: flip жел | C4: ='Юнит 02-08.02'!AE15 -> 18277.046 | D4: =C4/C$18 -> 0.34161491 | E4: =D4 -> 0.34161491 | F4: =IF(AND(E4<=0),"C",IF(E4<=0.8,"A",IF(E4<=0.95,"B","C"))) -> A | G4: =VLOOKUP(B$4:B$17,I$4:M$17,5,0) -> A | I4: th желт | J4: ='Юнит 02-08.02'!R11 -> 42 | K4: =J4/J$18 -> 0.26923077 | L4: =K4 -> 0.26923077 | M4: =_xlfn.IFS(L4<80%,"A",L4<=95%,"B",L4>95%,"C") -> A
B5: th желт | C5: ='Юнит 02-08.02'!AE11 -> 17790.829 | D5: =C5/C$18 -> 0.33252706 | E5: =D5+E4 -> 0.67414197 | F5: =IF(AND(E5<=0),"C",IF(E5<=0.8,"A",IF(E5<=0.95,"B","C"))) -> A | G5: =VLOOKUP(B$4:B$17,I$4:M$17,5,0) -> A | I5: flip жел | J5: ='Юнит 02-08.02'!R15 -> 39 | K5: =J5/J$18 -> 0.25 | L5: =K5+L4 -> 0.51923077 | M5: =_xlfn.IFS(L5<80%,"A",L5<=95%,"B",L5>95%,"C") -> A
B6: MR8854 C2 | C6: ='Юнит 02-08.02'!AE8 -> 6133.4351 | D6: =C6/C$18 -> 0.11463958 | E6: =D6+E5 -> 0.78878155 | F6: =IF(AND(E6<=0),"C",IF(E6<=0.8,"A",IF(E6<=0.95,"B","C"))) -> A | G6: =VLOOKUP(B$4:B$17,I$4:M$17,5,0) -> A | I6: MR8854 C2 | J6: ='Юнит 02-08.02'!R8 -> 16 | K6: =J6/J$18 -> 0.1025641 | L6: =K6+L5 -> 0.62179487 | M6: =_xlfn.IFS(L6<80%,"A",L6<=95%,"B",L6>95%,"C") -> A
B7: qs желтые | C7: ='Юнит 02-08.02'!AE6 -> 4862.3614 | D7: =C7/C$18 -> 0.090882034 | E7: =D7+E6 -> 0.87966358 | F7: =IF(AND(E7<=0),"C",IF(E7<=0.8,"A",IF(E7<=0.95,"B","C"))) -> B | G7: =VLOOKUP(B$4:B$17,I$4:M$17,5,0) -> A | I7: qs коричневые | J7: ='Юнит 02-08.02'!R7 -> 11 | K7: =J7/J$18 -> 0.070512821 | L7: =K7+L6 -> 0.69230769 | M7: =_xlfn.IFS(L7<80%,"A",L7<=95%,"B",L7>95%,"C") -> A
B8: flip синий | C8: ='Юнит 02-08.02'!AE14 -> 2919.034 | D8: =C8/C$18 -> 0.054559447 | E8: =D8+E7 -> 0.93422303 | F8: =IF(AND(E8<=0),"C",IF(E8<=0.8,"A",IF(E8<=0.95,"B","C"))) -> B | G8: =VLOOKUP(B$4:B$17,I$4:M$17,5,0) -> B | I8: qs желтые | J8: ='Юнит 02-08.02'!R6 -> 9 | K8: =J8/J$18 -> 0.057692308 | L8: =K8+L7 -> 0.75 | M8: =_xlfn.IFS(L8<80%,"A",L8<=95%,"B",L8>95%,"C") -> A
B9: th син | C9: ='Юнит 02-08.02'!AE10 -> 2854.5428 | D9: =C9/C$18 -> 0.053354047 | E9: =D9+E8 -> 0.98757708 | F9: =IF(AND(E9<=0),"C",IF(E9<=0.8,"A",IF(E9<=0.95,"B","C"))) -> C | G9: =VLOOKUP(B$4:B$17,I$4:M$17,5,0) -> B | I9: th син | J9: ='Юнит 02-08.02'!R10 -> 9 | K9: =J9/J$18 -> 0.057692308 | L9: =K9+L8 -> 0.80769231 | M9: =_xlfn.IFS(L9<80%,"A",L9<=95%,"B",L9>95%,"C") -> B
B10: qs черные | C10: ='Юнит 02-08.02'!AE4 -> 1679.3861 | D10: =C10/C$18 -> 0.031389281 | E10: =D10+E9 -> 1.0189664 | F10: =IF(AND(E10<=0),"C",IF(E10<=0.8,"A",IF(E10<=0.95,"B","C"))) -> C | G10: =VLOOKUP(B$4:B$17,I$4:M$17,5,0) -> A | I10: flip синий | J10: ='Юнит 02-08.02'!R14 -> 8 | K10: =J10/J$18 -> 0.051282051 | L10: =K10+L9 -> 0.85897436 | M10: =_xlfn.IFS(L10<80%,"A",L10<=95%,"B",L10>95%,"C") -> B
B11: th черн | C11: ='Юнит 02-08.02'!AE9 -> 1483.022 | D11: =C11/C$18 -> 0.027719054 | E11: =D11+E10 -> 1.0466854 | F11: =IF(AND(E11<=0),"C",IF(E11<=0.8,"A",IF(E11<=0.95,"B","C"))) -> C | G11: =VLOOKUP(B$4:B$17,I$4:M$17,5,0) -> B | I11: th черн | J11: ='Юнит 02-08.02'!R9 -> 4 | K11: =J11/J$18 -> 0.025641026 | L11: =K11+L10 -> 0.88461538 | M11: =_xlfn.IFS(L11<80%,"A",L11<=95%,"B",L11>95%,"C") -> B
B12: qs синие | C12: ='Юнит 02-08.02'!AE5 -> 493.8015 | D12: =C12/C$18 -> 0.0092296071 | E12: =D12+E5 -> 0.68337158 | F12: =IF(AND(E12<=0),"C",IF(E12<=0.8,"A",IF(E12<=0.95,"B","C"))) -> A | G12: =VLOOKUP(B$4:B$17,I$4:M$17,5,0) -> A | I12: th коричн | J12: ='Юнит 02-08.02'!R12 -> 4 | K12: =J12/J$18 -> 0.025641026 | L12: =K12+L5 -> 0.54487179 | M12: =_xlfn.IFS(L12<80%,"A",L12<=95%,"B",L12>95%,"C") -> A
B13: flip черный | C13: ='Юнит 02-08.02'!AE13 -> 420.652 | D13: =C13/C$18 -> 0.0078623753 | E13: =D13+E12 -> 0.69123395 | F13: =IF(AND(E13<=0),"C",IF(E13<=0.8,"A",IF(E13<=0.95,"B","C"))) -> A | G13: =VLOOKUP(B$4:B$17,I$4:M$17,5,0) -> A | I13: flip черный | J13: ='Юнит 02-08.02'!R13 -> 4 | K13: =J13/J$18 -> 0.025641026 | L13: =K13+L12 -> 0.57051282 | M13: =_xlfn.IFS(L13<80%,"A",L13<=95%,"B",L13>95%,"C") -> A
B14: flip коричневый | C14: ='Юнит 02-08.02'!AE16 -> 404.65606 | D14: =C14/C$18 -> 0.0075633963 | E14: =D14+E13 -> 0.69879735 | F14: =IF(AND(E14<=0),"C",IF(E14<=0.8,"A",IF(E14<=0.95,"B","C"))) -> A | G14: =VLOOKUP(B$4:B$17,I$4:M$17,5,0) -> A | I14: flip коричневый | J14: ='Юнит 02-08.02'!R16 -> 4 | K14: =J14/J$18 -> 0.025641026 | L14: =K14+L13 -> 0.59615385 | M14: =_xlfn.IFS(L14<80%,"A",L14<=95%,"B",L14>95%,"C") -> A
B15: черные с железкой классика | C15: ='Юнит 02-08.02'!AE3 -> 292.51085 | D15: =C15/C$18 -> 0.0054672985 | E15: =D15+E14 -> 0.70426465 | F15: =IF(AND(E15<=0),"C",IF(E15<=0.8,"A",IF(E15<=0.95,"B","C"))) -> A | G15: =VLOOKUP(B$4:B$17,I$4:M$17,5,0) -> A | I15: qs черные | J15: ='Юнит 02-08.02'!R4 -> 3 | K15: =J15/J$18 -> 0.019230769 | L15: =K15+L14 -> 0.61538462 | M15: =_xlfn.IFS(L15<80%,"A",L15<=95%,"B",L15>95%,"C") -> A
B16: th коричн | C16: ='Юнит 02-08.02'!AE12 -> -724.708 | D16: =C16/C$18 -> -0.013545463 | E16: =D16+E15 -> 0.69071918 | F16: =IF(AND(E16<=0),"C",IF(E16<=0.8,"A",IF(E16<=0.95,"B","C"))) -> A | G16: =VLOOKUP(B$4:B$17,I$4:M$17,5,0) -> A | I16: qs синие | J16: ='Юнит 02-08.02'!R5 -> 2 | K16: =J16/J$18 -> 0.012820513 | L16: =K16+L15 -> 0.62820513 | M16: =_xlfn.IFS(L16<80%,"A",L16<=95%,"B",L16>95%,"C") -> A
B17: qs коричневые | C17: ='Юнит 02-08.02'!AE7 -> -3384.6705 | D17: =C17/C$18 -> -0.063262625 | E17: =D17+E14 -> 0.63553472 | F17: =IF(AND(E17<=0),"C",IF(E17<=0.8,"A",IF(E17<=0.95,"B","C"))) -> A | G17: =VLOOKUP(B$4:B$17,I$4:M$17,5,0) -> A | I17: черные с железкой классика | J17: ='Юнит 02-08.02'!R3 -> 1 | K17: =J17/J$18 -> 0.0064102564 | L17: =K17+L14 -> 0.6025641 | M17: =_xlfn.IFS(L17<80%,"A",L17<=95%,"B",L17>95%,"C") -> A
C18: =SUM(C4:C17) -> 53501.898 | D18: =SUM(D4:D17) -> 1 | J18: =SUM(J4:J17) -> 156 | K18: =SUM(K4:K17) -> 1
C21: Прибыль | D21: % прибыль | E21: Доля | F21: ABC прибыль | G21: ABC кол-во | J21: Кол-во | K21: % кол-во | L21: Доля | M21: ABC кол-во
D22: =C22/C$42 -> #DIV/0! | E22: =D22 -> #DIV/0! | F22: =IF(AND(E22<=0),"C",IF(E22<=0.8,"A",IF(E22<=0.95,"B","C"))) -> #DIV/0! | G22: =VLOOKUP(B$22:B$42,I$22:M$42,5,0) -> #N/A | K22: =J22/J$42 -> #DIV/0! | L22: =K22 -> #DIV/0! | M22: =_xlfn.IFS(L22<80%,"A",L22<=95%,"B",L22>95%,"C") -> #DIV/0!
D23: =C23/C$42 -> #DIV/0! | E23: =D23+E22 -> #DIV/0! | F23: =IF(AND(E23<=0),"C",IF(E23<=0.8,"A",IF(E23<=0.95,"B","C"))) -> #DIV/0! | G23: =VLOOKUP(B$22:B$42,I$22:M$42,5,0) -> #N/A | K23: =J23/J$42 -> #DIV/0! | L23: =K23+L22 -> #DIV/0! | M23: =_xlfn.IFS(L23<80%,"A",L23<=95%,"B",L23>95%,"C") -> #DIV/0!
D24: =C24/C$42 -> #DIV/0! | E24: =D24+E23 -> #DIV/0! | F24: =IF(AND(E24<=0),"C",IF(E24<=0.8,"A",IF(E24<=0.95,"B","C"))) -> #DIV/0! | G24: =VLOOKUP(B$22:B$42,I$22:M$42,5,0) -> #N/A | K24: =J24/J$42 -> #DIV/0! | L24: =K24+L23 -> #DIV/0! | M24: =_xlfn.IFS(L24<80%,"A",L24<=95%,"B",L24>95%,"C") -> #DIV/0!
D25: =C25/C$42 -> #DIV/0! | E25: =D25+E24 -> #DIV/0! | F25: =IF(AND(E25<=0),"C",IF(E25<=0.8,"A",IF(E25<=0.95,"B","C"))) -> #DIV/0! | G25: =VLOOKUP(B$22:B$42,I$22:M$42,5,0) -> #N/A | K25: =J25/J$42 -> #DIV/0! | L25: =K25+L24 -> #DIV/0! | M25: =_xlfn.IFS(L25<80%,"A",L25<=95%,"B",L25>95%,"C") -> #DIV/0!
D26: =C26/C$42 -> #DIV/0! | E26: =D26+E25 -> #DIV/0! | F26: =IF(AND(E26<=0),"C",IF(E26<=0.8,"A",IF(E26<=0.95,"B","C"))) -> #DIV/0! | G26: =VLOOKUP(B$22:B$42,I$22:M$42,5,0) -> #N/A | K26: =J26/J$42 -> #DIV/0! | L26: =K26+L25 -> #DIV/0! | M26: =_xlfn.IFS(L26<80%,"A",L26<=95%,"B",L26>95%,"C") -> #DIV/0!
D27: =C27/C$42 -> #DIV/0! | E27: =D27+E26 -> #DIV/0! | F27: =IF(AND(E27<=0),"C",IF(E27<=0.8,"A",IF(E27<=0.95,"B","C"))) -> #DIV/0! | G27: =VLOOKUP(B$22:B$42,I$22:M$42,5,0) -> #N/A | K27: =J27/J$42 -> #DIV/0! | L27: =K27+L26 -> #DIV/0! | M27: =_xlfn.IFS(L27<80%,"A",L27<=95%,"B",L27>95%,"C") -> #DIV/0!
D28: =C28/C$42 -> #DIV/0! | E28: =D28+E27 -> #DIV/0! | F28: =IF(AND(E28<=0),"C",IF(E28<=0.8,"A",IF(E28<=0.95,"B","C"))) -> #DIV/0! | G28: =VLOOKUP(B$22:B$42,I$22:M$42,5,0) -> #N/A | K28: =J28/J$42 -> #DIV/0! | L28: =K28+L27 -> #DIV/0! | M28: =_xlfn.IFS(L28<80%,"A",L28<=95%,"B",L28>95%,"C") -> #DIV/0!
D29: =C29/C$42 -> #DIV/0! | E29: =D29+E28 -> #DIV/0! | F29: =IF(AND(E29<=0),"C",IF(E29<=0.8,"A",IF(E29<=0.95,"B","C"))) -> #DIV/0! | G29: =VLOOKUP(B$22:B$42,I$22:M$42,5,0) -> #N/A | K29: =J29/J$42 -> #DIV/0! | L29: =K29+L28 -> #DIV/0! | M29: =_xlfn.IFS(L29<80%,"A",L29<=95%,"B",L29>95%,"C") -> #DIV/0!
D30: =C30/C$42 -> #DIV/0! | E30: =D30+E29 -> #DIV/0! | F30: =IF(AND(E30<=0),"C",IF(E30<=0.8,"A",IF(E30<=0.95,"B","C"))) -> #DIV/0! | G30: =VLOOKUP(B$22:B$42,I$22:M$42,5,0) -> #N/A | K30: =J30/J$42 -> #DIV/0! | L30: =K30+L29 -> #DIV/0! | M30: =_xlfn.IFS(L30<80%,"A",L30<=95%,"B",L30>95%,"C") -> #DIV/0!
D31: =C31/C$42 -> #DIV/0! | E31: =D31+E30 -> #DIV/0! | F31: =IF(AND(E31<=0),"C",IF(E31<=0.8,"A",IF(E31<=0.95,"B","C"))) -> #DIV/0! | G31: =VLOOKUP(B$22:B$42,I$22:M$42,5,0) -> #N/A | K31: =J31/J$42 -> #DIV/0! | L31: =K31+L30 -> #DIV/0! | M31: =_xlfn.IFS(L31<80%,"A",L31<=95%,"B",L31>95%,"C") -> #DIV/0!
D32: =C32/C$42 -> #DIV/0! | E32: =D32+E31 -> #DIV/0! | F32: =IF(AND(E32<=0),"C",IF(E32<=0.8,"A",IF(E32<=0.95,"B","C"))) -> #DIV/0! | G32: =VLOOKUP(B$22:B$42,I$22:M$42,5,0) -> #N/A | K32: =J32/J$42 -> #DIV/0! | L32: =K32+L31 -> #DIV/0! | M32: =_xlfn.IFS(L32<80%,"A",L32<=95%,"B",L32>95%,"C") -> #DIV/0!
D33: =C33/C$42 -> #DIV/0! | E33: =D33+E32 -> #DIV/0! | F33: =IF(AND(E33<=0),"C",IF(E33<=0.8,"A",IF(E33<=0.95,"B","C"))) -> #DIV/0! | G33: =VLOOKUP(B$22:B$42,I$22:M$42,5,0) -> #N/A | K33: =J33/J$42 -> #DIV/0! | L33: =K33+L32 -> #DIV/0! | M33: =_xlfn.IFS(L33<80%,"A",L33<=95%,"B",L33>95%,"C") -> #DIV/0!
D34: =C34/C$42 -> #DIV/0! | E34: =D34+E33 -> #DIV/0! | F34: =IF(AND(E34<=0),"C",IF(E34<=0.8,"A",IF(E34<=0.95,"B","C"))) -> #DIV/0! | G34: =VLOOKUP(B$22:B$42,I$22:M$42,5,0) -> #N/A | K34: =J34/J$42 -> #DIV/0! | L34: =K34+L33 -> #DIV/0! | M34: =_xlfn.IFS(L34<80%,"A",L34<=95%,"B",L34>95%,"C") -> #DIV/0!
... D41: =C41/C$42 -> #DIV/0! | E41: =D41+E40 -> #DIV/0! | F41: =IF(AND(E41<=0),"C",IF(E41<=0.8,"A",IF(E41<=0.95,"B","C"))) -> #DIV/0! | G41: =VLOOKUP(B$22:B$42,I$22:M$42,5,0) -> #N/A | K41: =J41/J$42 -> #DIV/0! | L41: =K41+L40 -> #DIV/0! | M41: =_xlfn.IFS(L41<80%,"A",L41<=95%,"B",L41>95%,"C") -> #DIV/0!
C42: =SUM(C22:C41) -> 0 | D42: =SUM(D22:D41) -> #DIV/0! | J42: =SUM(J22:J41) -> 0 | K42: =SUM(K22:K41) -> #DIV/0!

Sheet АВС ЯНВАРЬ
B2: ОЧКИ
C3: Прибыль | D3: % прибыль | E3: Доля | F3: ABC прибыль | G3: ABC кол-во | J3: Кол-во | K3: % кол-во | L3: Доля | M3: ABC кол-во
B4: flip жел | C4: =ЯНВАРЬ!AE15 -> 31976.767 | D4: =C4/C$18 -> 0.2758861 | E4: =D4 -> 0.2758861 | F4: =IF(AND(E4<=0),"C",IF(E4<=0.8,"A",IF(E4<=0.95,"B","C"))) -> A | G4: =VLOOKUP(B$4:B$17,I$4:M$17,5,0) -> A | I4: th желт | J4: =ЯНВАРЬ!R11 -> 165 | K4: =J4/J$18 -> 0.31190926 | L4: =K4 -> 0.31190926 | M4: =_xlfn.IFS(L4<80%,"A",L4<=95%,"B",L4>95%,"C") -> A
B5: th желт | C5: =ЯНВАРЬ!AE11 -> 29547.598 | D5: =C5/C$18 -> 0.25492795 | E5: =D5+E4 -> 0.53081405 | F5: =IF(AND(E5<=0),"C",IF(E5<=0.8,"A",IF(E5<=0.95,"B","C"))) -> A | G5: =VLOOKUP(B$4:B$17,I$4:M$17,5,0) -> A | I5: flip жел | J5: =ЯНВАРЬ!R15 -> 161 | K5: =J5/J$18 -> 0.30434783 | L5: =K5+L4 -> 0.61625709 | M5: =_xlfn.IFS(L5<80%,"A",L5<=95%,"B",L5>95%,"C") -> A
B6: qs желтые | C6: =ЯНВАРЬ!AE6 -> 21761.169 | D6: =C6/C$18 -> 0.18774894 | E6: =D6+E5 -> 0.718563 | F6: =IF(AND(E6<=0),"C",IF(E6<=0.8,"A",IF(E6<=0.95,"B","C"))) -> A | G6: =VLOOKUP(B$4:B$17,I$4:M$17,5,0) -> A | I6: qs желтые | J6: =ЯНВАРЬ!R6 -> 82 | K6: =J6/J$18 -> 0.15500945 | L6: =K6+L5 -> 0.77126654 | M6: =_xlfn.IFS(L6<80%,"A",L6<=95%,"B",L6>95%,"C") -> A
B7: qs черные | C7: =ЯНВАРЬ!AE4 -> 10617.275 | D7: =C7/C$18 -> 0.091602712 | E7: =D7+E6 -> 0.81016571 | F7: =IF(AND(E7<=0),"C",IF(E7<=0.8,"A",IF(E7<=0.95,"B","C"))) -> B | G7: =VLOOKUP(B$4:B$17,I$4:M$17,5,0) -> C | I7: qs коричневые | J7: =ЯНВАРЬ!R7 -> 45 | K7: =J7/J$18 -> 0.085066163 | L7: =K7+L6 -> 0.8563327 | M7: =_xlfn.IFS(L7<80%,"A",L7<=95%,"B",L7>95%,"C") -> B
B8: qs коричневые | C8: =ЯНВАРЬ!AE7 -> 9789.4777 | D8: =C8/C$18 -> 0.084460723 | E8: =D8+E7 -> 0.89462643 | F8: =IF(AND(E8<=0),"C",IF(E8<=0.8,"A",IF(E8<=0.95,"B","C"))) -> B | G8: =VLOOKUP(B$4:B$17,I$4:M$17,5,0) -> B | I8: MR8854 C2 | J8: =ЯНВАРЬ!R8 -> 31 | K8: =J8/J$18 -> 0.058601134 | L8: =K8+L7 -> 0.91493384 | M8: =_xlfn.IFS(L8<80%,"A",L8<=95%,"B",L8>95%,"C") -> B
B9: черные с железкой классика | C9: =ЯНВАРЬ!AE3 -> 6638.0745 | D9: =C9/C$18 -> 0.057271347 | E9: =D9+E8 -> 0.95189778 | F9: =IF(AND(E9<=0),"C",IF(E9<=0.8,"A",IF(E9<=0.95,"B","C"))) -> C | G9: =VLOOKUP(B$4:B$17,I$4:M$17,5,0) -> C | I9: qs черные | J9: =ЯНВАРЬ!R4 -> 19 | K9: =J9/J$18 -> 0.035916824 | L9: =K9+L8 -> 0.95085066 | M9: =_xlfn.IFS(L9<80%,"A",L9<=95%,"B",L9>95%,"C") -> C
B10: qs синие | C10: =ЯНВАРЬ!AE5 -> 4723.2726 | D10: =C10/C$18 -> 0.040751002 | E10: =D10+E9 -> 0.99264878 | F10: =IF(AND(E10<=0),"C",IF(E10<=0.8,"A",IF(E10<=0.95,"B","C"))) -> C | G10: =VLOOKUP(B$4:B$17,I$4:M$17,5,0) -> C | I10: черные с железкой классика | J10: =ЯНВАРЬ!R3 -> 15 | K10: =J10/J$18 -> 0.028355388 | L10: =K10+L9 -> 0.97920605 | M10: =_xlfn.IFS(L10<80%,"A",L10<=95%,"B",L10>95%,"C") -> C
B11: MR8854 C2 | C11: =ЯНВАРЬ!AE8 -> 4340.3483 | D11: =C11/C$18 -> 0.037447243 | E11: =D11+E10 -> 1.030096 | F11: =IF(AND(E11<=0),"C",IF(E11<=0.8,"A",IF(E11<=0.95,"B","C"))) -> C | G11: =VLOOKUP(B$4:B$17,I$4:M$17,5,0) -> B | I11: qs синие | J11: =ЯНВАРЬ!R5 -> 9 | K11: =J11/J$18 -> 0.017013233 | L11: =K11+L10 -> 0.99621928 | M11: =_xlfn.IFS(L11<80%,"A",L11<=95%,"B",L11>95%,"C") -> C
B12: th черн | C12: =ЯНВАРЬ!AE9 -> 296.72616 | D12: =C12/C$18 -> 0.0025600657 | E12: =D12+E5 -> 0.53337412 | F12: =IF(AND(E12<=0),"C",IF(E12<=0.8,"A",IF(E12<=0.95,"B","C"))) -> A | G12: =VLOOKUP(B$4:B$17,I$4:M$17,5,0) -> A | I12: th черн | J12: =ЯНВАРЬ!R9 -> 1 | K12: =J12/J$18 -> 0.0018903592 | L12: =K12+L5 -> 0.61814745 | M12: =_xlfn.IFS(L12<80%,"A",L12<=95%,"B",L12>95%,"C") -> A
B13: flip черный | C13: =ЯНВАРЬ!AE13 -> 220.16156 | D13: =C13/C$18 -> 0.001899489 | E13: =D13+E12 -> 0.53527361 | F13: =IF(AND(E13<=0),"C",IF(E13<=0.8,"A",IF(E13<=0.95,"B","C"))) -> A | G13: =VLOOKUP(B$4:B$17,I$4:M$17,5,0) -> A | I13: flip черный | J13: =ЯНВАРЬ!R13 -> 1 | K13: =J13/J$18 -> 0.0018903592 | L13: =K13+L12 -> 0.62003781 | M13: =_xlfn.IFS(L13<80%,"A",L13<=95%,"B",L13>95%,"C") -> A
B14: th коричн | C14: =ЯНВАРЬ!AE12 -> -555.84386 | D14: =C14/C$18 -> -0.0047956567 | E14: =D14+E13 -> 0.53047795 | F14: =IF(AND(E14<=0),"C",IF(E14<=0.8,"A",IF(E14<=0.95,"B","C"))) -> A | G14: =VLOOKUP(B$4:B$17,I$4:M$17,5,0) -> A | I14: th син | J14: =ЯНВАРЬ!R10 -> 0 | K14: =J14/J$18 -> 0 | L14: =K14+L13 -> 0.62003781 | M14: =_xlfn.IFS(L14<80%,"A",L14<=95%,"B",L14>95%,"C") -> A
B15: flip синий | C15: =ЯНВАРЬ!AE14 -> -607.06546 | D15: =C15/C$18 -> -0.0052375815 | E15: =D15+E14 -> 0.52524037 | F15: =IF(AND(E15<=0),"C",IF(E15<=0.8,"A",IF(E15<=0.95,"B","C"))) -> A | G15: =VLOOKUP(B$4:B$17,I$4:M$17,5,0) -> A | I15: th коричн | J15: =ЯНВАРЬ!R12 -> 0 | K15: =J15/J$18 -> 0 | L15: =K15+L14 -> 0.62003781 | M15: =_xlfn.IFS(L15<80%,"A",L15<=95%,"B",L15>95%,"C") -> A
B16: flip коричневый | C16: =ЯНВАРЬ!AE16 -> -1324.8447 | D16: =C16/C$18 -> -0.011430368 | E16: =D16+E15 -> 0.51381 | F16: =IF(AND(E16<=0),"C",IF(E16<=0.8,"A",IF(E16<=0.95,"B","C"))) -> A | G16: =VLOOKUP(B$4:B$17,I$4:M$17,5,0) -> A | I16: flip синий | J16: =ЯНВАРЬ!R14 -> 0 | K16: =J16/J$18 -> 0 | L16: =K16+L15 -> 0.62003781 | M16: =_xlfn.IFS(L16<80%,"A",L16<=95%,"B",L16>95%,"C") -> A
B17: th син | C17: =ЯНВАРЬ!AE10 -> -1517.4339 | D17: =C17/C$18 -> -0.013091971 | E17: =D17+E14 -> 0.51738598 | F17: =IF(AND(E17<=0),"C",IF(E17<=0.8,"A",IF(E17<=0.95,"B","C"))) -> A | G17: =VLOOKUP(B$4:B$17,I$4:M$17,5,0) -> A | I17: flip коричневый | J17: =ЯНВАРЬ!R16 -> 0 | K17: =J17/J$18 -> 0 | L17: =K17+L14 -> 0.62003781 | M17: =_xlfn.IFS(L17<80%,"A",L17<=95%,"B",L17>95%,"C") -> A
C18: =SUM(C4:C17) -> 115905.68 | D18: =SUM(D4:D17) -> 1 | J18: =SUM(J4:J17) -> 529 | K18: =SUM(K4:K17) -> 1
C21: Прибыль | D21: % прибыль | E21: Доля | F21: ABC прибыль | G21: ABC кол-во | J21: Кол-во | K21: % кол-во | L21: Доля | M21: ABC кол-во
D22: =C22/C$42 -> #DIV/0! | E22: =D22 -> #DIV/0! | F22: =IF(AND(E22<=0),"C",IF(E22<=0.8,"A",IF(E22<=0.95,"B","C"))) -> #DIV/0! | G22: =VLOOKUP(B$22:B$42,I$22:M$42,5,0) -> #N/A | K22: =J22/J$42 -> #DIV/0! | L22: =K22 -> #DIV/0! | M22: =_xlfn.IFS(L22<80%,"A",L22<=95%,"B",L22>95%,"C") -> #DIV/0!
D23: =C23/C$42 -> #DIV/0! | E23: =D23+E22 -> #DIV/0! | F23: =IF(AND(E23<=0),"C",IF(E23<=0.8,"A",IF(E23<=0.95,"B","C"))) -> #DIV/0! | G23: =VLOOKUP(B$22:B$42,I$22:M$42,5,0) -> #N/A | K23: =J23/J$42 -> #DIV/0! | L23: =K23+L22 -> #DIV/0! | M23: =_xlfn.IFS(L23<80%,"A",L23<=95%,"B",L23>95%,"C") -> #DIV/0!
D24: =C24/C$42 -> #DIV/0! | E24: =D24+E23 -> #DIV/0! | F24: =IF(AND(E24<=0),"C",IF(E24<=0.8,"A",IF(E24<=0.95,"B","C"))) -> #DIV/0! | G24: =VLOOKUP(B$22:B$42,I$22:M$42,5,0) -> #N/A | K24: =J24/J$42 -> #DIV/0! | L24: =K24+L23 -> #DIV/0! | M24: =_xlfn.IFS(L24<80%,"A",L24<=95%,"B",L24>95%,"C") -> #DIV/0!
D25: =C25/C$42 -> #DIV/0! | E25: =D25+E24 -> #DIV/0! | F25: =IF(AND(E25<=0),"C",IF(E25<=0.8,"A",IF(E25<=0.95,"B","C"))) -> #DIV/0! | G25: =VLOOKUP(B$22:B$42,I$22:M$42,5,0) -> #N/A | K25: =J25/J$42 -> #DIV/0! | L25: =K25+L24 -> #DIV/0! | M25: =_xlfn.IFS(L25<80%,"A",L25<=95%,"B",L25>95%,"C") -> #DIV/0!
D26: =C26/C$42 -> #DIV/0! | E26: =D26+E25 -> #DIV/0! | F26: =IF(AND(E26<=0),"C",IF(E26<=0.8,"A",IF(E26<=0.95,"B","C"))) -> #DIV/0! | G26: =VLOOKUP(B$22:B$42,I$22:M$42,5,0) -> #N/A | K26: =J26/J$42 -> #DIV/0! | L26: =K26+L25 -> #DIV/0! | M26: =_xlfn.IFS(L26<80%,"A",L26<=95%,"B",L26>95%,"C") -> #DIV/0!
D27: =C27/C$42 -> #DIV/0! | E27: =D27+E26 -> #DIV/0! | F27: =IF(AND(E27<=0),"C",IF(E27<=0.8,"A",IF(E27<=0.95,"B","C"))) -> #DIV/0! | G27: =VLOOKUP(B$22:B$42,I$22:M$42,5,0) -> #N/A | K27: =J27/J$42 -> #DIV/0! | L27: =K27+L26 -> #DIV/0! | M27: =_xlfn.IFS(L27<80%,"A",L27<=95%,"B",L27>95%,"C") -> #DIV/0!
D28: =C28/C$42 -> #DIV/0! | E28: =D28+E27 -> #DIV/0! | F28: =IF(AND(E28<=0),"C",IF(E28<=0.8,"A",IF(E28<=0.95,"B","C"))) -> #DIV/0! | G28: =VLOOKUP(B$22:B$42,I$22:M$42,5,0) -> #N/A | K28: =J28/J$42 -> #DIV/0! | L28: =K28+L27 -> #DIV/0! | M28: =_xlfn.IFS(L28<80%,"A",L28<=95%,"B",L28>95%,"C") -> #DIV/0!
D29: =C29/C$42 -> #DIV/0! | E29: =D29+E28 -> #DIV/0! | F29: =IF(AND(E29<=0),"C",IF(E29<=0.8,"A",IF(E29<=0.95,"B","C"))) -> #DIV/0! | G29: =VLOOKUP(B$22:B$42,I$22:M$42,5,0) -> #N/A | K29: =J29/J$42 -> #DIV/0! | L29: =K29+L28 -> #DIV/0! | M29: =_xlfn.IFS(L29<80%,"A",L29<=95%,"B",L29>95%,"C") -> #DIV/0!
D30: =C30/C$42 -> #DIV/0! | E30: =D30+E29 -> #DIV/0! | F30: =IF(AND(E30<=0),"C",IF(E30<=0.8,"A",IF(E30<=0.95,"B","C"))) -> #DIV/0! | G30: =VLOOKUP(B$22:B$42,I$22:M$42,5,0) -> #N/A | K30: =J30/J$42 -> #DIV/0! | L30: =K30+L29 -> #DIV/0! | M30: =_xlfn.IFS(L30<80%,"A",L30<=95%,"B",L30>95%,"C") -> #DIV/0!
D31: =C31/C$42 -> #DIV/0! | E31: =D31+E30 -> #DIV/0! | F31: =IF(AND(E31<=0),"C",IF(E31<=0.8,"A",IF(E31<=0.95,"B","C"))) -> #DIV/0! | G31: =VLOOKUP(B$22:B$42,I$22:M$42,5,0) -> #N/A | K31: =J31/J$42 -> #DIV/0! | L31: =K31+L30 -> #DIV/0! | M31: =_xlfn.IFS(L31<80%,"A",L31<=95%,"B",L31>95%,"C") -> #DIV/0!
D32: =C32/C$42 -> #DIV/0! | E32: =D32+E31 -> #DIV/0! | F32: =IF(AND(E32<=0),"C",IF(E32<=0.8,"A",IF(E32<=0.95,"B","C"))) -> #DIV/0! | G32: =VLOOKUP(B$22:B$42,I$22:M$42,5,0) -> #N/A | K32: =J32/J$42 -> #DIV/0! | L32: =K32+L31 -> #DIV/0! | M32: =_xlfn.IFS(L32<80%,"A",L32<=95%,"B",L32>95%,"C") -> #DIV/0!
D33: =C33/C$42 -> #DIV/0! | E33: =D33+E32 -> #DIV/0! | F33: =IF(AND(E33<=0),"C",IF(E33<=0.8,"A",IF(E33<=0.95,"B","C"))) -> #DIV/0! | G33: =VLOOKUP(B$22:B$42,I$22:M$42,5,0) -> #N/A | K33: =J33/J$42 -> #DIV/0! | L33: =K33+L32 -> #DIV/0! | M33: =_xlfn.IFS(L33<80%,"A",L33<=95%,"B",L33>95%,"C") -> #DIV/0!
D34: =C34/C$42 -> #DIV/0! | E34: =D34+E33 -> #DIV/0! | F34: =IF(AND(E34<=0),"C",IF(E34<=0.8,"A",IF(E34<=0.95,"B","C"))) -> #DIV/0! | G34: =VLOOKUP(B$22:B$42,I$22:M$42,5,0) -> #N/A | K34: =J34/J$42 -> #DIV/0! | L34: =K34+L33 -> #DIV/0! | M34: =_xlfn.IFS(L34<80%,"A",L34<=95%,"B",L34>95%,"C") -> #DIV/0!
... D41: =C41/C$42 -> #DIV/0! | E41: =D41+E40 -> #DIV/0! | F41: =IF(AND(E41<=0),"C",IF(E41<=0.8,"A",IF(E41<=0.95,"B","C"))) -> #DIV/0! | G41: =VLOOKUP(B$22:B$42,I$22:M$42,5,0) -> #N/A | K41: =J41/J$42 -> #DIV/0! | L41: =K41+L40 -> #DIV/0! | M41: =_xlfn.IFS(L41<80%,"A",L41<=95%,"B",L41>95%,"C") -> #DIV/0!
C42: =SUM(C22:C41) -> 0 | D42: =SUM(D22:D41) -> #DIV/0! | J42: =SUM(J22:J41) -> 0 | K42: =SUM(K22:K41) -> #DIV/0!

Sheet АВС 26.01-01.02
B2: ОЧКИ
C3: Прибыль | D3: % прибыль | E3: Доля | F3: ABC прибыль | G3: ABC кол-во | J3: Кол-во | K3: % кол-во | L3: Доля | M3: ABC кол-во
B4: th желт | C4: ='Юнит 26.01-01.02'!AE11 -> 16111.061 | D4: =C4/C$18 -> 0.51770375 | E4: =D4 -> 0.51770375 | F4: =IF(AND(E4<=0),"C",IF(E4<=0.8,"A",IF(E4<=0.95,"B","C"))) -> A | G4: =VLOOKUP(B$4:B$17,I$4:M$17,5,0) -> A | I4: th желт | J4: ='Юнит 26.01-01.02'!R11 -> 48 | K4: =J4/J$18 -> 0.375 | L4: =K4 -> 0.375 | M4: =_xlfn.IFS(L4<80%,"A",L4<=95%,"B",L4>95%,"C") -> A
B5: flip жел | C5: ='Юнит 26.01-01.02'!AE15 -> 11558.881 | D5: =C5/C$18 -> 0.37142657 | E5: =D5+E4 -> 0.88913032 | F5: =IF(AND(E5<=0),"C",IF(E5<=0.8,"A",IF(E5<=0.95,"B","C"))) -> B | G5: =VLOOKUP(B$4:B$17,I$4:M$17,5,0) -> A | I5: flip жел | J5: ='Юнит 26.01-01.02'!R15 -> 38 | K5: =J5/J$18 -> 0.296875 | L5: =K5+L4 -> 0.671875 | M5: =_xlfn.IFS(L5<80%,"A",L5<=95%,"B",L5>95%,"C") -> A
B6: qs черные | C6: ='Юнит 26.01-01.02'!AE4 -> 3322.05 | D6: =C6/C$18 -> 0.10674888 | E6: =D6+E5 -> 0.9958792 | F6: =IF(AND(E6<=0),"C",IF(E6<=0.8,"A",IF(E6<=0.95,"B","C"))) -> C | G6: =VLOOKUP(B$4:B$17,I$4:M$17,5,0) -> C | I6: qs коричневые | J6: ='Юнит 26.01-01.02'!R7 -> 16 | K6: =J6/J$18 -> 0.125 | L6: =K6+L5 -> 0.796875 | M6: =_xlfn.IFS(L6<80%,"A",L6<=95%,"B",L6>95%,"C") -> A
B7: MR8854 C2 | C7: ='Юнит 26.01-01.02'!AE8 -> 1849.5272 | D7: =C7/C$18 -> 0.059431665 | E7: =D7+E6 -> 1.0553109 | F7: =IF(AND(E7<=0),"C",IF(E7<=0.8,"A",IF(E7<=0.95,"B","C"))) -> C | G7: =VLOOKUP(B$4:B$17,I$4:M$17,5,0) -> B | I7: MR8854 C2 | J7: ='Юнит 26.01-01.02'!R8 -> 10 | K7: =J7/J$18 -> 0.078125 | L7: =K7+L6 -> 0.875 | M7: =_xlfn.IFS(L7<80%,"A",L7<=95%,"B",L7>95%,"C") -> B
B8: qs желтые | C8: ='Юнит 26.01-01.02'!AE6 -> 1191.36 | D8: =C8/C$18 -> 0.038282491 | E8: =D8+E7 -> 1.0935934 | F8: =IF(AND(E8<=0),"C",IF(E8<=0.8,"A",IF(E8<=0.95,"B","C"))) -> C | G8: =VLOOKUP(B$4:B$17,I$4:M$17,5,0) -> B | I8: qs желтые | J8: ='Юнит 26.01-01.02'!R6 -> 6 | K8: =J8/J$18 -> 0.046875 | L8: =K8+L7 -> 0.921875 | M8: =_xlfn.IFS(L8<80%,"A",L8<=95%,"B",L8>95%,"C") -> B
B9: th коричн | C9: ='Юнит 26.01-01.02'!AE12 -> 291.34614 | D9: =C9/C$18 -> 0.0093619527 | E9: =D9+E8 -> 1.1029553 | F9: =IF(AND(E9<=0),"C",IF(E9<=0.8,"A",IF(E9<=0.95,"B","C"))) -> C | G9: =VLOOKUP(B$4:B$17,I$4:M$17,5,0) -> A | I9: qs черные | J9: ='Юнит 26.01-01.02'!R4 -> 5 | K9: =J9/J$18 -> 0.0390625 | L9: =K9+L8 -> 0.9609375 | M9: =_xlfn.IFS(L9<80%,"A",L9<=95%,"B",L9>95%,"C") -> C
B10: th черн | C10: ='Юнит 26.01-01.02'!AE9 -> 284.37054 | D10: =C10/C$18 -> 0.0091378028 | E10: =D10+E9 -> 1.1120931 | F10: =IF(AND(E10<=0),"C",IF(E10<=0.8,"A",IF(E10<=0.95,"B","C"))) -> C | G10: =VLOOKUP(B$4:B$17,I$4:M$17,5,0) -> C | I10: черные с железкой классика | J10: ='Юнит 26.01-01.02'!R3 -> 1 | K10: =J10/J$18 -> 0.0078125 | L10: =K10+L9 -> 0.96875 | M10: =_xlfn.IFS(L10<80%,"A",L10<=95%,"B",L10>95%,"C") -> C
B11: flip черный | C11: ='Юнит 26.01-01.02'!AE13 -> 207.80595 | D11: =C11/C$18 -> 0.0066775192 | E11: =D11+E10 -> 1.1187706 | F11: =IF(AND(E11<=0),"C",IF(E11<=0.8,"A",IF(E11<=0.95,"B","C"))) -> C | G11: =VLOOKUP(B$4:B$17,I$4:M$17,5,0) -> A | I11: th черн | J11: ='Юнит 26.01-01.02'!R9 -> 1 | K11: =J11/J$18 -> 0.0078125 | L11: =K11+L10 -> 0.9765625 | M11: =_xlfn.IFS(L11<80%,"A",L11<=95%,"B",L11>95%,"C") -> C
B12: черные с железкой классика | C12: ='Юнит 26.01-01.02'!AE3 -> 152.11 | D12: =C12/C$18 -> 0.004887817 | E12: =D12+E5 -> 0.89401814 | F12: =IF(AND(E12<=0),"C",IF(E12<=0.8,"A",IF(E12<=0.95,"B","C"))) -> B | G12: =VLOOKUP(B$4:B$17,I$4:M$17,5,0) -> C | I12: th син | J12: ='Юнит 26.01-01.02'!R10 -> 1 | K12: =J12/J$18 -> 0.0078125 | L12: =K12+L5 -> 0.6796875 | M12: =_xlfn.IFS(L12<80%,"A",L12<=95%,"B",L12>95%,"C") -> A
B13: qs синие | C13: ='Юнит 26.01-01.02'!AE5 -> 0 | D13: =C13/C$18 -> 0 | E13: =D13+E12 -> 0.89401814 | F13: =IF(AND(E13<=0),"C",IF(E13<=0.8,"A",IF(E13<=0.95,"B","C"))) -> B | G13: =VLOOKUP(B$4:B$17,I$4:M$17,5,0) -> A | I13: th коричн | J13: ='Юнит 26.01-01.02'!R12 -> 1 | K13: =J13/J$18 -> 0.0078125 | L13: =K13+L12 -> 0.6875 | M13: =_xlfn.IFS(L13<80%,"A",L13<=95%,"B",L13>95%,"C") -> A
B14: qs коричневые | C14: ='Юнит 26.01-01.02'!AE7 -> -472.79957 | D14: =C14/C$18 -> -0.015192675 | E14: =D14+E13 -> 0.87882546 | F14: =IF(AND(E14<=0),"C",IF(E14<=0.8,"A",IF(E14<=0.95,"B","C"))) -> B | G14: =VLOOKUP(B$4:B$17,I$4:M$17,5,0) -> A | I14: flip черный | J14: ='Юнит 26.01-01.02'!R13 -> 1 | K14: =J14/J$18 -> 0.0078125 | L14: =K14+L13 -> 0.6953125 | M14: =_xlfn.IFS(L14<80%,"A",L14<=95%,"B",L14>95%,"C") -> A
B15: flip синий | C15: ='Юнит 26.01-01.02'!AE14 -> -807.06546 | D15: =C15/C$18 -> -0.025933786 | E15: =D15+E14 -> 0.85289167 | F15: =IF(AND(E15<=0),"C",IF(E15<=0.8,"A",IF(E15<=0.95,"B","C"))) -> B | G15: =VLOOKUP(B$4:B$17,I$4:M$17,5,0) -> A | I15: qs синие | J15: ='Юнит 26.01-01.02'!R5 -> 0 | K15: =J15/J$18 -> 0 | L15: =K15+L14 -> 0.6953125 | M15: =_xlfn.IFS(L15<80%,"A",L15<=95%,"B",L15>95%,"C") -> A
B16: th син | C16: ='Юнит 26.01-01.02'!AE10 -> -963.6769 | D16: =C16/C$18 -> -0.03096625 | E16: =D16+E15 -> 0.82192542 | F16: =IF(AND(E16<=0),"C",IF(E16<=0.8,"A",IF(E16<=0.95,"B","C"))) -> B | G16: =VLOOKUP(B$4:B$17,I$4:M$17,5,0) -> A | I16: flip синий | J16: ='Юнит 26.01-01.02'!R14 -> 0 | K16: =J16/J$18 -> 0 | L16: =K16+L15 -> 0.6953125 | M16: =_xlfn.IFS(L16<80%,"A",L16<=95%,"B",L16>95%,"C") -> A
B17: flip коричневый | C17: ='Юнит 26.01-01.02'!AE16 -> -1604.7377 | D17: =C17/C$18 -> -0.051565737 | E17: =D17+E14 -> 0.82725972 | F17: =IF(AND(E17<=0),"C",IF(E17<=0.8,"A",IF(E17<=0.95,"B","C"))) -> B | G17: =VLOOKUP(B$4:B$17,I$4:M$17,5,0) -> A | I17: flip коричневый | J17: ='Юнит 26.01-01.02'!R16 -> 0 | K17: =J17/J$18 -> 0 | L17: =K17+L14 -> 0.6953125 | M17: =_xlfn.IFS(L17<80%,"A",L17<=95%,"B",L17>95%,"C") -> A
C18: =SUM(C4:C17) -> 31120.232 | D18: =SUM(D4:D17) -> 1 | J18: =SUM(J4:J17) -> 128 | K18: =SUM(K4:K17) -> 1
C21: Прибыль | D21: % прибыль | E21: Доля | F21: ABC прибыль | G21: ABC кол-во | J21: Кол-во | K21: % кол-во | L21: Доля | M21: ABC кол-во
D22: =C22/C$42 -> #DIV/0! | E22: =D22 -> #DIV/0! | F22: =IF(AND(E22<=0),"C",IF(E22<=0.8,"A",IF(E22<=0.95,"B","C"))) -> #DIV/0! | G22: =VLOOKUP(B$22:B$42,I$22:M$42,5,0) -> #N/A | K22: =J22/J$42 -> #DIV/0! | L22: =K22 -> #DIV/0! | M22: =_xlfn.IFS(L22<80%,"A",L22<=95%,"B",L22>95%,"C") -> #DIV/0!
D23: =C23/C$42 -> #DIV/0! | E23: =D23+E22 -> #DIV/0! | F23: =IF(AND(E23<=0),"C",IF(E23<=0.8,"A",IF(E23<=0.95,"B","C"))) -> #DIV/0! | G23: =VLOOKUP(B$22:B$42,I$22:M$42,5,0) -> #N/A | K23: =J23/J$42 -> #DIV/0! | L23: =K23+L22 -> #DIV/0! | M23: =_xlfn.IFS(L23<80%,"A",L23<=95%,"B",L23>95%,"C") -> #DIV/0!
D24: =C24/C$42 -> #DIV/0! | E24: =D24+E23 -> #DIV/0! | F24: =IF(AND(E24<=0),"C",IF(E24<=0.8,"A",IF(E24<=0.95,"B","C"))) -> #DIV/0! | G24: =VLOOKUP(B$22:B$42,I$22:M$42,5,0) -> #N/A | K24: =J24/J$42 -> #DIV/0! | L24: =K24+L23 -> #DIV/0! | M24: =_xlfn.IFS(L24<80%,"A",L24<=95%,"B",L24>95%,"C") -> #DIV/0!
D25: =C25/C$42 -> #DIV/0! | E25: =D25+E24 -> #DIV/0! | F25: =IF(AND(E25<=0),"C",IF(E25<=0.8,"A",IF(E25<=0.95,"B","C"))) -> #DIV/0! | G25: =VLOOKUP(B$22:B$42,I$22:M$42,5,0) -> #N/A | K25: =J25/J$42 -> #DIV/0! | L25: =K25+L24 -> #DIV/0! | M25: =_xlfn.IFS(L25<80%,"A",L25<=95%,"B",L25>95%,"C") -> #DIV/0!
D26: =C26/C$42 -> #DIV/0! | E26: =D26+E25 -> #DIV/0! | F26: =IF(AND(E26<=0),"C",IF(E26<=0.8,"A",IF(E26<=0.95,"B","C"))) -> #DIV/0! | G26: =VLOOKUP(B$22:B$42,I$22:M$42,5,0) -> #N/A | K26: =J26/J$42 -> #DIV/0! | L26: =K26+L25 -> #DIV/0! | M26: =_xlfn.IFS(L26<80%,"A",L26<=95%,"B",L26>95%,"C") -> #DIV/0!
D27: =C27/C$42 -> #DIV/0! | E27: =D27+E26 -> #DIV/0! | F27: =IF(AND(E27<=0),"C",IF(E27<=0.8,"A",IF(E27<=0.95,"B","C"))) -> #DIV/0! | G27: =VLOOKUP(B$22:B$42,I$22:M$42,5,0) -> #N/A | K27: =J27/J$42 -> #DIV/0! | L27: =K27+L26 -> #DIV/0! | M27: =_xlfn.IFS(L27<80%,"A",L27<=95%,"B",L27>95%,"C") -> #DIV/0!
D28: =C28/C$42 -> #DIV/0! | E28: =D28+E27 -> #DIV/0! | F28: =IF(AND(E28<=0),"C",IF(E28<=0.8,"A",IF(E28<=0.95,"B","C"))) -> #DIV/0! | G28: =VLOOKUP(B$22:B$42,I$22:M$42,5,0) -> #N/A | K28: =J28/J$42 -> #DIV/0! | L28: =K28+L27 -> #DIV/0! | M28: =_xlfn.IFS(L28<80%,"A",L28<=95%,"B",L28>95%,"C") -> #DIV/0!
D29: =C29/C$42 -> #DIV/0! | E29: =D29+E28 -> #DIV/0! | F29: =IF(AND(E29<=0),"C",IF(E29<=0.8,"A",IF(E29<=0.95,"B","C"))) -> #DIV/0! | G29: =VLOOKUP(B$22:B$42,I$22:M$42,5,0) -> #N/A | K29: =J29/J$42 -> #DIV/0! | L29: =K29+L28 -> #DIV/0! | M29: =_xlfn.IFS(L29<80%,"A",L29<=95%,"B",L29>95%,"C") -> #DIV/0!
D30: =C30/C$42 -> #DIV/0! | E30: =D30+E29 -> #DIV/0! | F30: =IF(AND(E30<=0),"C",IF(E30<=0.8,"A",IF(E30<=0.95,"B","C"))) -> #DIV/0! | G30: =VLOOKUP(B$22:B$42,I$22:M$42,5,0) -> #N/A | K30: =J30/J$42 -> #DIV/0! | L30: =K30+L29 -> #DIV/0! | M30: =_xlfn.IFS(L30<80%,"A",L30<=95%,"B",L30>95%,"C") -> #DIV/0!
D31: =C31/C$42 -> #DIV/0! | E31: =D31+E30 -> #DIV/0! | F31: =IF(AND(E31<=0),"C",IF(E31<=0.8,"A",IF(E31<=0.95,"B","C"))) -> #DIV/0! | G31: =VLOOKUP(B$22:B$42,I$22:M$42,5,0) -> #N/A | K31: =J31/J$42 -> #DIV/0! | L31: =K31+L30 -> #DIV/0! | M31: =_xlfn.IFS(L31<80%,"A",L31<=95%,"B",L31>95%,"C") -> #DIV/0!
D32: =C32/C$42 -> #DIV/0! | E32: =D32+E31 -> #DIV/0! | F32: =IF(AND(E32<=0),"C",IF(E32<=0.8,"A",IF(E32<=0.95,"B","C"))) -> #DIV/0! | G32: =VLOOKUP(B$22:B$42,I$22:M$42,5,0) -> #N/A | K32: =J32/J$42 -> #DIV/0! | L32: =K32+L31 -> #DIV/0! | M32: =_xlfn.IFS(L32<80%,"A",L32<=95%,"B",L32>95%,"C") -> #DIV/0!
D33: =C33/C$42 -> #DIV/0! | E33: =D33+E32 -> #DIV/0! | F33: =IF(AND(E33<=0),"C",IF(E33<=0.8,"A",IF(E33<=0.95,"B","C"))) -> #DIV/0! | G33: =VLOOKUP(B$22:B$42,I$22:M$42,5,0) -> #N/A | K33: =J33/J$42 -> #DIV/0! | L33: =K33+L32 -> #DIV/0! | M33: =_xlfn.IFS(L33<80%,"A",L33<=95%,"B",L33>95%,"C") -> #DIV/0!
D34: =C34/C$42 -> #DIV/0! | E34: =D34+E33 -> #DIV/0! | F34: =IF(AND(E34<=0),"C",IF(E34<=0.8,"A",IF(E34<=0.95,"B","C"))) -> #DIV/0! | G34: =VLOOKUP(B$22:B$42,I$22:M$42,5,0) -> #N/A | K34: =J34/J$42 -> #DIV/0! | L34: =K34+L33 -> #DIV/0! | M34: =_xlfn.IFS(L34<80%,"A",L34<=95%,"B",L34>95%,"C") -> #DIV/0!
... D41: =C41/C$42 -> #DIV/0! | E41: =D41+E40 -> #DIV/0! | F41: =IF(AND(E41<=0),"C",IF(E41<=0.8,"A",IF(E41<=0.95,"B","C"))) -> #DIV/0! | G41: =VLOOKUP(B$22:B$42,I$22:M$42,5,0) -> #N/A | K41: =J41/J$42 -> #DIV/0! | L41: =K41+L40 -> #DIV/0! | M41: =_xlfn.IFS(L41<80%,"A",L41<=95%,"B",L41>95%,"C") -> #DIV/0!
C42: =SUM(C22:C41) -> 0 | D42: =SUM(D22:D41) -> #DIV/0! | J42: =SUM(J22:J41) -> 0 | K42: =SUM(K22:K41) -> #DIV/0!

Sheet АВС 19-25.01
B2: ОЧКИ
C3: Прибыль | D3: % прибыль | E3: Доля | F3: ABC прибыль | G3: ABC кол-во | J3: Кол-во | K3: % кол-во | L3: Доля | M3: ABC кол-во
B4: qs желтые | C4: ='Юнит 19-25.01'!AE6 -> 10158.92 | D4: =C4/C$18 -> 0.52787056 | E4: =D4 -> 0.52787056 | F4: =IF(AND(E4<=0),"C",IF(E4<=0.8,"A",IF(E4<=0.95,"B","C"))) -> A | G4: =VLOOKUP(B$4:B$17,I$4:M$17,5,0) -> A | I4: th желт | J4: ='Юнит 19-25.01'!R11 -> 26 | K4: =J4/J$18 -> 0.29213483 | L4: =K4 -> 0.29213483 | M4: =_xlfn.IFS(L4<80%,"A",L4<=95%,"B",L4>95%,"C") -> A
B5: qs черные | C5: ='Юнит 19-25.01'!AE4 -> 4879.4517 | D5: =C5/C$18 -> 0.25354259 | E5: =D5+E4 -> 0.78141315 | F5: =IF(AND(E5<=0),"C",IF(E5<=0.8,"A",IF(E5<=0.95,"B","C"))) -> A | G5: =VLOOKUP(B$4:B$17,I$4:M$17,5,0) -> B | I5: qs желтые | J5: ='Юнит 19-25.01'!R6 -> 18 | K5: =J5/J$18 -> 0.20224719 | L5: =K5+L4 -> 0.49438202 | M5: =_xlfn.IFS(L5<80%,"A",L5<=95%,"B",L5>95%,"C") -> A
B6: черные с железкой классика | C6: ='Юнит 19-25.01'!AE3 -> 3054.91 | D6: =C6/C$18 -> 0.15873706 | E6: =D6+E5 -> 0.94015021 | F6: =IF(AND(E6<=0),"C",IF(E6<=0.8,"A",IF(E6<=0.95,"B","C"))) -> B | G6: =VLOOKUP(B$4:B$17,I$4:M$17,5,0) -> B | I6: flip жел | J6: ='Юнит 19-25.01'!R15 -> 17 | K6: =J6/J$18 -> 0.19101124 | L6: =K6+L5 -> 0.68539326 | M6: =_xlfn.IFS(L6<80%,"A",L6<=95%,"B",L6>95%,"C") -> A
B7: qs синие | C7: ='Юнит 19-25.01'!AE5 -> 2087.12 | D7: =C7/C$18 -> 0.10844944 | E7: =D7+E6 -> 1.0485997 | F7: =IF(AND(E7<=0),"C",IF(E7<=0.8,"A",IF(E7<=0.95,"B","C"))) -> C | G7: =VLOOKUP(B$4:B$17,I$4:M$17,5,0) -> C | I7: qs коричневые | J7: ='Юнит 19-25.01'!R7 -> 10 | K7: =J7/J$18 -> 0.11235955 | L7: =K7+L6 -> 0.79775281 | M7: =_xlfn.IFS(L7<80%,"A",L7<=95%,"B",L7>95%,"C") -> A
B8: qs коричневые | C8: ='Юнит 19-25.01'!AE7 -> 1636.0082 | D8: =C8/C$18 -> 0.085009092 | E8: =D8+E7 -> 1.1336087 | F8: =IF(AND(E8<=0),"C",IF(E8<=0.8,"A",IF(E8<=0.95,"B","C"))) -> C | G8: =VLOOKUP(B$4:B$17,I$4:M$17,5,0) -> A | I8: qs черные | J8: ='Юнит 19-25.01'!R4 -> 7 | K8: =J8/J$18 -> 0.078651685 | L8: =K8+L7 -> 0.87640449 | M8: =_xlfn.IFS(L8<80%,"A",L8<=95%,"B",L8>95%,"C") -> B
B9: th желт | C9: ='Юнит 19-25.01'!AE11 -> 2661.2441 | D9: =C9/C$18 -> 0.13828167 | E9: =D9+E8 -> 1.2718904 | F9: =IF(AND(E9<=0),"C",IF(E9<=0.8,"A",IF(E9<=0.95,"B","C"))) -> C | G9: =VLOOKUP(B$4:B$17,I$4:M$17,5,0) -> A | I9: черные с железкой классика | J9: ='Юнит 19-25.01'!R3 -> 5 | K9: =J9/J$18 -> 0.056179775 | L9: =K9+L8 -> 0.93258427 | M9: =_xlfn.IFS(L9<80%,"A",L9<=95%,"B",L9>95%,"C") -> B
B10: th черн | C10: ='Юнит 19-25.01'!AE9 -> 0 | D10: =C10/C$18 -> 0 | E10: =D10+E9 -> 1.2718904 | F10: =IF(AND(E10<=0),"C",IF(E10<=0.8,"A",IF(E10<=0.95,"B","C"))) -> C | G10: =VLOOKUP(B$4:B$17,I$4:M$17,5,0) -> A | I10: qs синие | J10: ='Юнит 19-25.01'!R5 -> 3 | K10: =J10/J$18 -> 0.033707865 | L10: =K10+L9 -> 0.96629213 | M10: =_xlfn.IFS(L10<80%,"A",L10<=95%,"B",L10>95%,"C") -> C
B11: th син | C11: ='Юнит 19-25.01'!AE10 -> 0 | D11: =C11/C$18 -> 0 | E11: =D11+E10 -> 1.2718904 | F11: =IF(AND(E11<=0),"C",IF(E11<=0.8,"A",IF(E11<=0.95,"B","C"))) -> C | G11: =VLOOKUP(B$4:B$17,I$4:M$17,5,0) -> A | I11: MR8854 C2 | J11: ='Юнит 19-25.01'!R8 -> 3 | K11: =J11/J$18 -> 0.033707865 | L11: =K11+L10 -> 1 | M11: =_xlfn.IFS(L11<80%,"A",L11<=95%,"B",L11>95%,"C") -> C
B12: th коричн | C12: ='Юнит 19-25.01'!AE12 -> 0 | D12: =C12/C$18 -> 0 | E12: =D12+E5 -> 0.78141315 | F12: =IF(AND(E12<=0),"C",IF(E12<=0.8,"A",IF(E12<=0.95,"B","C"))) -> A | G12: =VLOOKUP(B$4:B$17,I$4:M$17,5,0) -> A | I12: th черн | J12: ='Юнит 19-25.01'!R9 -> 0 | K12: =J12/J$18 -> 0 | L12: =K12+L5 -> 0.49438202 | M12: =_xlfn.IFS(L12<80%,"A",L12<=95%,"B",L12>95%,"C") -> A
B13: flip черный | C13: ='Юнит 19-25.01'!AE13 -> 0 | D13: =C13/C$18 -> 0 | E13: =D13+E12 -> 0.78141315 | F13: =IF(AND(E13<=0),"C",IF(E13<=0.8,"A",IF(E13<=0.95,"B","C"))) -> A | G13: =VLOOKUP(B$4:B$17,I$4:M$17,5,0) -> A | I13: th син | J13: ='Юнит 19-25.01'!R10 -> 0 | K13: =J13/J$18 -> 0 | L13: =K13+L12 -> 0.49438202 | M13: =_xlfn.IFS(L13<80%,"A",L13<=95%,"B",L13>95%,"C") -> A
B14: flip синий | C14: ='Юнит 19-25.01'!AE14 -> 0 | D14: =C14/C$18 -> 0 | E14: =D14+E13 -> 0.78141315 | F14: =IF(AND(E14<=0),"C",IF(E14<=0.8,"A",IF(E14<=0.95,"B","C"))) -> A | G14: =VLOOKUP(B$4:B$17,I$4:M$17,5,0) -> A | I14: th коричн | J14: ='Юнит 19-25.01'!R12 -> 0 | K14: =J14/J$18 -> 0 | L14: =K14+L13 -> 0.49438202 | M14: =_xlfn.IFS(L14<80%,"A",L14<=95%,"B",L14>95%,"C") -> A
B15: flip коричневый | C15: ='Юнит 19-25.01'!AE16 -> 0 | D15: =C15/C$18 -> 0 | E15: =D15+E14 -> 0.78141315 | F15: =IF(AND(E15<=0),"C",IF(E15<=0.8,"A",IF(E15<=0.95,"B","C"))) -> A | G15: =VLOOKUP(B$4:B$17,I$4:M$17,5,0) -> A | I15: flip черный | J15: ='Юнит 19-25.01'!R13 -> 0 | K15: =J15/J$18 -> 0 | L15: =K15+L14 -> 0.49438202 | M15: =_xlfn.IFS(L15<80%,"A",L15<=95%,"B",L15>95%,"C") -> A
B16: MR8854 C2 | C16: ='Юнит 19-25.01'!AE8 -> -789.58498 | D16: =C16/C$18 -> -0.041027852 | E16: =D16+E15 -> 0.7403853 | F16: =IF(AND(E16<=0),"C",IF(E16<=0.8,"A",IF(E16<=0.95,"B","C"))) -> A | G16: =VLOOKUP(B$4:B$17,I$4:M$17,5,0) -> C | I16: flip синий | J16: ='Юнит 19-25.01'!R14 -> 0 | K16: =J16/J$18 -> 0 | L16: =K16+L15 -> 0.49438202 | M16: =_xlfn.IFS(L16<80%,"A",L16<=95%,"B",L16>95%,"C") -> A
B17: flip жел | C17: ='Юнит 19-25.01'!AE15 -> -4442.9723 | D17: =C17/C$18 -> -0.23086256 | E17: =D17+E14 -> 0.55055059 | F17: =IF(AND(E17<=0),"C",IF(E17<=0.8,"A",IF(E17<=0.95,"B","C"))) -> A | G17: =VLOOKUP(B$4:B$17,I$4:M$17,5,0) -> A | I17: flip коричневый | J17: ='Юнит 19-25.01'!R16 -> 0 | K17: =J17/J$18 -> 0 | L17: =K17+L14 -> 0.49438202 | M17: =_xlfn.IFS(L17<80%,"A",L17<=95%,"B",L17>95%,"C") -> A
C18: =SUM(C4:C17) -> 19245.097 | D18: =SUM(D4:D17) -> 1 | J18: =SUM(J4:J17) -> 89 | K18: =SUM(K4:K17) -> 1
C21: Прибыль | D21: % прибыль | E21: Доля | F21: ABC прибыль | G21: ABC кол-во | J21: Кол-во | K21: % кол-во | L21: Доля | M21: ABC кол-во
D22: =C22/C$42 -> #DIV/0! | E22: =D22 -> #DIV/0! | F22: =IF(AND(E22<=0),"C",IF(E22<=0.8,"A",IF(E22<=0.95,"B","C"))) -> #DIV/0! | G22: =VLOOKUP(B$22:B$42,I$22:M$42,5,0) -> #N/A | K22: =J22/J$42 -> #DIV/0! | L22: =K22 -> #DIV/0! | M22: =_xlfn.IFS(L22<80%,"A",L22<=95%,"B",L22>95%,"C") -> #DIV/0!
D23: =C23/C$42 -> #DIV/0! | E23: =D23+E22 -> #DIV/0! | F23: =IF(AND(E23<=0),"C",IF(E23<=0.8,"A",IF(E23<=0.95,"B","C"))) -> #DIV/0! | G23: =VLOOKUP(B$22:B$42,I$22:M$42,5,0) -> #N/A | K23: =J23/J$42 -> #DIV/0! | L23: =K23+L22 -> #DIV/0! | M23: =_xlfn.IFS(L23<80%,"A",L23<=95%,"B",L23>95%,"C") -> #DIV/0!
D24: =C24/C$42 -> #DIV/0! | E24: =D24+E23 -> #DIV/0! | F24: =IF(AND(E24<=0),"C",IF(E24<=0.8,"A",IF(E24<=0.95,"B","C"))) -> #DIV/0! | G24: =VLOOKUP(B$22:B$42,I$22:M$42,5,0) -> #N/A | K24: =J24/J$42 -> #DIV/0! | L24: =K24+L23 -> #DIV/0! | M24: =_xlfn.IFS(L24<80%,"A",L24<=95%,"B",L24>95%,"C") -> #DIV/0!
D25: =C25/C$42 -> #DIV/0! | E25: =D25+E24 -> #DIV/0! | F25: =IF(AND(E25<=0),"C",IF(E25<=0.8,"A",IF(E25<=0.95,"B","C"))) -> #DIV/0! | G25: =VLOOKUP(B$22:B$42,I$22:M$42,5,0) -> #N/A | K25: =J25/J$42 -> #DIV/0! | L25: =K25+L24 -> #DIV/0! | M25: =_xlfn.IFS(L25<80%,"A",L25<=95%,"B",L25>95%,"C") -> #DIV/0!
D26: =C26/C$42 -> #DIV/0! | E26: =D26+E25 -> #DIV/0! | F26: =IF(AND(E26<=0),"C",IF(E26<=0.8,"A",IF(E26<=0.95,"B","C"))) -> #DIV/0! | G26: =VLOOKUP(B$22:B$42,I$22:M$42,5,0) -> #N/A | K26: =J26/J$42 -> #DIV/0! | L26: =K26+L25 -> #DIV/0! | M26: =_xlfn.IFS(L26<80%,"A",L26<=95%,"B",L26>95%,"C") -> #DIV/0!
D27: =C27/C$42 -> #DIV/0! | E27: =D27+E26 -> #DIV/0! | F27: =IF(AND(E27<=0),"C",IF(E27<=0.8,"A",IF(E27<=0.95,"B","C"))) -> #DIV/0! | G27: =VLOOKUP(B$22:B$42,I$22:M$42,5,0) -> #N/A | K27: =J27/J$42 -> #DIV/0! | L27: =K27+L26 -> #DIV/0! | M27: =_xlfn.IFS(L27<80%,"A",L27<=95%,"B",L27>95%,"C") -> #DIV/0!
D28: =C28/C$42 -> #DIV/0! | E28: =D28+E27 -> #DIV/0! | F28: =IF(AND(E28<=0),"C",IF(E28<=0.8,"A",IF(E28<=0.95,"B","C"))) -> #DIV/0! | G28: =VLOOKUP(B$22:B$42,I$22:M$42,5,0) -> #N/A | K28: =J28/J$42 -> #DIV/0! | L28: =K28+L27 -> #DIV/0! | M28: =_xlfn.IFS(L28<80%,"A",L28<=95%,"B",L28>95%,"C") -> #DIV/0!
D29: =C29/C$42 -> #DIV/0! | E29: =D29+E28 -> #DIV/0! | F29: =IF(AND(E29<=0),"C",IF(E29<=0.8,"A",IF(E29<=0.95,"B","C"))) -> #DIV/0! | G29: =VLOOKUP(B$22:B$42,I$22:M$42,5,0) -> #N/A | K29: =J29/J$42 -> #DIV/0! | L29: =K29+L28 -> #DIV/0! | M29: =_xlfn.IFS(L29<80%,"A",L29<=95%,"B",L29>95%,"C") -> #DIV/0!
D30: =C30/C$42 -> #DIV/0! | E30: =D30+E29 -> #DIV/0! | F30: =IF(AND(E30<=0),"C",IF(E30<=0.8,"A",IF(E30<=0.95,"B","C"))) -> #DIV/0! | G30: =VLOOKUP(B$22:B$42,I$22:M$42,5,0) -> #N/A | K30: =J30/J$42 -> #DIV/0! | L30: =K30+L29 -> #DIV/0! | M30: =_xlfn.IFS(L30<80%,"A",L30<=95%,"B",L30>95%,"C") -> #DIV/0!
D31: =C31/C$42 -> #DIV/0! | E31: =D31+E30 -> #DIV/0! | F31: =IF(AND(E31<=0),"C",IF(E31<=0.8,"A",IF(E31<=0.95,"B","C"))) -> #DIV/0! | G31: =VLOOKUP(B$22:B$42,I$22:M$42,5,0) -> #N/A | K31: =J31/J$42 -> #DIV/0! | L31: =K31+L30 -> #DIV/0! | M31: =_xlfn.IFS(L31<80%,"A",L31<=95%,"B",L31>95%,"C") -> #DIV/0!
D32: =C32/C$42 -> #DIV/0! | E32: =D32+E31 -> #DIV/0! | F32: =IF(AND(E32<=0),"C",IF(E32<=0.8,"A",IF(E32<=0.95,"B","C"))) -> #DIV/0! | G32: =VLOOKUP(B$22:B$42,I$22:M$42,5,0) -> #N/A | K32: =J32/J$42 -> #DIV/0! | L32: =K32+L31 -> #DIV/0! | M32: =_xlfn.IFS(L32<80%,"A",L32<=95%,"B",L32>95%,"C") -> #DIV/0!
D33: =C33/C$42 -> #DIV/0! | E33: =D33+E32 -> #DIV/0! | F33: =IF(AND(E33<=0),"C",IF(E33<=0.8,"A",IF(E33<=0.95,"B","C"))) -> #DIV/0! | G33: =VLOOKUP(B$22:B$42,I$22:M$42,5,0) -> #N/A | K33: =J33/J$42 -> #DIV/0! | L33: =K33+L32 -> #DIV/0! | M33: =_xlfn.IFS(L33<80%,"A",L33<=95%,"B",L33>95%,"C") -> #DIV/0!
D34: =C34/C$42 -> #DIV/0! | E34: =D34+E33 -> #DIV/0! | F34: =IF(AND(E34<=0),"C",IF(E34<=0.8,"A",IF(E34<=0.95,"B","C"))) -> #DIV/0! | G34: =VLOOKUP(B$22:B$42,I$22:M$42,5,0) -> #N/A | K34: =J34/J$42 -> #DIV/0! | L34: =K34+L33 -> #DIV/0! | M34: =_xlfn.IFS(L34<80%,"A",L34<=95%,"B",L34>95%,"C") -> #DIV/0!
... D41: =C41/C$42 -> #DIV/0! | E41: =D41+E40 -> #DIV/0! | F41: =IF(AND(E41<=0),"C",IF(E41<=0.8,"A",IF(E41<=0.95,"B","C"))) -> #DIV/0! | G41: =VLOOKUP(B$22:B$42,I$22:M$42,5,0) -> #N/A | K41: =J41/J$42 -> #DIV/0! | L41: =K41+L40 -> #DIV/0! | M41: =_xlfn.IFS(L41<80%,"A",L41<=95%,"B",L41>95%,"C") -> #DIV/0!
C42: =SUM(C22:C41) -> 0 | D42: =SUM(D22:D41) -> #DIV/0! | J42: =SUM(J22:J41) -> 0 | K42: =SUM(K22:K41) -> #DIV/0!

Sheet АВС 12-18.01
B2: ОЧКИ
C3: Прибыль | D3: % прибыль | E3: Доля | F3: ABC прибыль | G3: ABC кол-во | J3: Кол-во | K3: % кол-во | L3: Доля | M3: ABC кол-во
B4: flip жел | C4: ='Юнит 12-18.01'!AE15 -> 7845.5265 | D4: =C4/C$18 -> 0.31497995 | E4: =D4 -> 0.31497995 | F4: =IF(AND(E4<=0),"C",IF(E4<=0.8,"A",IF(E4<=0.95,"B","C"))) -> A | G4: =VLOOKUP(B$4:B$17,I$4:M$17,5,0) -> A | I4: flip жел | J4: ='Юнит 12-18.01'!R15 -> 37 | K4: =J4/J$18 -> 0.30833333 | L4: =K4 -> 0.30833333 | M4: =_xlfn.IFS(L4<80%,"A",L4<=95%,"B",L4>95%,"C") -> A
B5: qs желтые | C5: ='Юнит 12-18.01'!AE6 -> 4986.2704 | D5: =C5/C$18 -> 0.20018736 | E5: =D5+E4 -> 0.51516731 | F5: =IF(AND(E5<=0),"C",IF(E5<=0.8,"A",IF(E5<=0.95,"B","C"))) -> A | G5: =VLOOKUP(B$4:B$17,I$4:M$17,5,0) -> A | I5: th желт | J5: ='Юнит 12-18.01'!R11 -> 35 | K5: =J5/J$18 -> 0.29166667 | L5: =K5+L4 -> 0.6 | M5: =_xlfn.IFS(L5<80%,"A",L5<=95%,"B",L5>95%,"C") -> A
B6: qs коричневые | C6: ='Юнит 12-18.01'!AE7 -> 3808.3998 | D6: =C6/C$18 -> 0.15289854 | E6: =D6+E5 -> 0.66806585 | F6: =IF(AND(E6<=0),"C",IF(E6<=0.8,"A",IF(E6<=0.95,"B","C"))) -> A | G6: =VLOOKUP(B$4:B$17,I$4:M$17,5,0) -> B | I6: qs желтые | J6: ='Юнит 12-18.01'!R6 -> 20 | K6: =J6/J$18 -> 0.16666667 | L6: =K6+L5 -> 0.76666667 | M6: =_xlfn.IFS(L6<80%,"A",L6<=95%,"B",L6>95%,"C") -> A
B7: qs синие | C7: ='Юнит 12-18.01'!AE5 -> 2085.4874 | D7: =C7/C$18 -> 0.083727551 | E7: =D7+E6 -> 0.7517934 | F7: =IF(AND(E7<=0),"C",IF(E7<=0.8,"A",IF(E7<=0.95,"B","C"))) -> A | G7: =VLOOKUP(B$4:B$17,I$4:M$17,5,0) -> C | I7: qs коричневые | J7: ='Юнит 12-18.01'!R7 -> 10 | K7: =J7/J$18 -> 0.083333333 | L7: =K7+L6 -> 0.85 | M7: =_xlfn.IFS(L7<80%,"A",L7<=95%,"B",L7>95%,"C") -> B
B8: черные с железкой классика | C8: ='Юнит 12-18.01'!AE3 -> 1162.1223 | D8: =C8/C$18 -> 0.046656555 | E8: =D8+E7 -> 0.79844996 | F8: =IF(AND(E8<=0),"C",IF(E8<=0.8,"A",IF(E8<=0.95,"B","C"))) -> A | G8: =VLOOKUP(B$4:B$17,I$4:M$17,5,0) -> C | I8: MR8854 C2 | J8: ='Юнит 12-18.01'!R8 -> 7 | K8: =J8/J$18 -> 0.058333333 | L8: =K8+L7 -> 0.90833333 | M8: =_xlfn.IFS(L8<80%,"A",L8<=95%,"B",L8>95%,"C") -> B
B9: th желт | C9: ='Юнит 12-18.01'!AE11 -> 3663.4074 | D9: =C9/C$18 -> 0.14707743 | E9: =D9+E8 -> 0.94552739 | F9: =IF(AND(E9<=0),"C",IF(E9<=0.8,"A",IF(E9<=0.95,"B","C"))) -> B | G9: =VLOOKUP(B$4:B$17,I$4:M$17,5,0) -> A | I9: qs черные | J9: ='Юнит 12-18.01'!R4 -> 4 | K9: =J9/J$18 -> 0.033333333 | L9: =K9+L8 -> 0.94166667 | M9: =_xlfn.IFS(L9<80%,"A",L9<=95%,"B",L9>95%,"C") -> B
B10: qs черные | C10: ='Юнит 12-18.01'!AE4 -> 745.60927 | D10: =C10/C$18 -> 0.029934507 | E10: =D10+E9 -> 0.9754619 | F10: =IF(AND(E10<=0),"C",IF(E10<=0.8,"A",IF(E10<=0.95,"B","C"))) -> C | G10: =VLOOKUP(B$4:B$17,I$4:M$17,5,0) -> B | I10: qs синие | J10: ='Юнит 12-18.01'!R5 -> 4 | K10: =J10/J$18 -> 0.033333333 | L10: =K10+L9 -> 0.975 | M10: =_xlfn.IFS(L10<80%,"A",L10<=95%,"B",L10>95%,"C") -> C
B11: MR8854 C2 | C11: ='Юнит 12-18.01'!AE8 -> 611.19557 | D11: =C11/C$18 -> 0.024538105 | E11: =D11+E10 -> 1 | F11: =IF(AND(E11<=0),"C",IF(E11<=0.8,"A",IF(E11<=0.95,"B","C"))) -> C | G11: =VLOOKUP(B$4:B$17,I$4:M$17,5,0) -> B | I11: черные с железкой классика | J11: ='Юнит 12-18.01'!R3 -> 3 | K11: =J11/J$18 -> 0.025 | L11: =K11+L10 -> 1 | M11: =_xlfn.IFS(L11<80%,"A",L11<=95%,"B",L11>95%,"C") -> C
B12: th черн | C12: ='Юнит 12-18.01'!AE9 -> 0 | D12: =C12/C$18 -> 0 | E12: =D12+E5 -> 0.51516731 | F12: =IF(AND(E12<=0),"C",IF(E12<=0.8,"A",IF(E12<=0.95,"B","C"))) -> A | G12: =VLOOKUP(B$4:B$17,I$4:M$17,5,0) -> A | I12: th черн | J12: ='Юнит 12-18.01'!R9 -> 0 | K12: =J12/J$18 -> 0 | L12: =K12+L5 -> 0.6 | M12: =_xlfn.IFS(L12<80%,"A",L12<=95%,"B",L12>95%,"C") -> A
B13: th син | C13: ='Юнит 12-18.01'!AE10 -> 0 | D13: =C13/C$18 -> 0 | E13: =D13+E12 -> 0.51516731 | F13: =IF(AND(E13<=0),"C",IF(E13<=0.8,"A",IF(E13<=0.95,"B","C"))) -> A | G13: =VLOOKUP(B$4:B$17,I$4:M$17,5,0) -> A | I13: th син | J13: ='Юнит 12-18.01'!R10 -> 0 | K13: =J13/J$18 -> 0 | L13: =K13+L12 -> 0.6 | M13: =_xlfn.IFS(L13<80%,"A",L13<=95%,"B",L13>95%,"C") -> A
B14: th коричн | C14: ='Юнит 12-18.01'!AE12 -> 0 | D14: =C14/C$18 -> 0 | E14: =D14+E13 -> 0.51516731 | F14: =IF(AND(E14<=0),"C",IF(E14<=0.8,"A",IF(E14<=0.95,"B","C"))) -> A | G14: =VLOOKUP(B$4:B$17,I$4:M$17,5,0) -> A | I14: th коричн | J14: ='Юнит 12-18.01'!R12 -> 0 | K14: =J14/J$18 -> 0 | L14: =K14+L13 -> 0.6 | M14: =_xlfn.IFS(L14<80%,"A",L14<=95%,"B",L14>95%,"C") -> A
B15: flip черный | C15: ='Юнит 12-18.01'!AE13 -> 0 | D15: =C15/C$18 -> 0 | E15: =D15+E14 -> 0.51516731 | F15: =IF(AND(E15<=0),"C",IF(E15<=0.8,"A",IF(E15<=0.95,"B","C"))) -> A | G15: =VLOOKUP(B$4:B$17,I$4:M$17,5,0) -> A | I15: flip черный | J15: ='Юнит 12-18.01'!R13 -> 0 | K15: =J15/J$18 -> 0 | L15: =K15+L14 -> 0.6 | M15: =_xlfn.IFS(L15<80%,"A",L15<=95%,"B",L15>95%,"C") -> A
B16: flip синий | C16: ='Юнит 12-18.01'!AE14 -> 0 | D16: =C16/C$18 -> 0 | E16: =D16+E15 -> 0.51516731 | F16: =IF(AND(E16<=0),"C",IF(E16<=0.8,"A",IF(E16<=0.95,"B","C"))) -> A | G16: =VLOOKUP(B$4:B$17,I$4:M$17,5,0) -> A | I16: flip синий | J16: ='Юнит 12-18.01'!R14 -> 0 | K16: =J16/J$18 -> 0 | L16: =K16+L15 -> 0.6 | M16: =_xlfn.IFS(L16<80%,"A",L16<=95%,"B",L16>95%,"C") -> A
B17: flip коричневый | C17: ='Юнит 12-18.01'!AE16 -> 0 | D17: =C17/C$18 -> 0 | E17: =D17+E14 -> 0.51516731 | F17: =IF(AND(E17<=0),"C",IF(E17<=0.8,"A",IF(E17<=0.95,"B","C"))) -> A | G17: =VLOOKUP(B$4:B$17,I$4:M$17,5,0) -> A | I17: flip коричневый | J17: ='Юнит 12-18.01'!R16 -> 0 | K17: =J17/J$18 -> 0 | L17: =K17+L14 -> 0.6 | M17: =_xlfn.IFS(L17<80%,"A",L17<=95%,"B",L17>95%,"C") -> A
C18: =SUM(C4:C17) -> 24908.019 | D18: =SUM(D4:D17) -> 1 | J18: =SUM(J4:J17) -> 120 | K18: =SUM(K4:K17) -> 1
C21: Прибыль | D21: % прибыль | E21: Доля | F21: ABC прибыль | G21: ABC кол-во | J21: Кол-во | K21: % кол-во | L21: Доля | M21: ABC кол-во
D22: =C22/C$42 -> #DIV/0! | E22: =D22 -> #DIV/0! | F22: =IF(AND(E22<=0),"C",IF(E22<=0.8,"A",IF(E22<=0.95,"B","C"))) -> #DIV/0! | G22: =VLOOKUP(B$22:B$42,I$22:M$42,5,0) -> #N/A | K22: =J22/J$42 -> #DIV/0! | L22: =K22 -> #DIV/0! | M22: =_xlfn.IFS(L22<80%,"A",L22<=95%,"B",L22>95%,"C") -> #DIV/0!
D23: =C23/C$42 -> #DIV/0! | E23: =D23+E22 -> #DIV/0! | F23: =IF(AND(E23<=0),"C",IF(E23<=0.8,"A",IF(E23<=0.95,"B","C"))) -> #DIV/0! | G23: =VLOOKUP(B$22:B$42,I$22:M$42,5,0) -> #N/A | K23: =J23/J$42 -> #DIV/0! | L23: =K23+L22 -> #DIV/0! | M23: =_xlfn.IFS(L23<80%,"A",L23<=95%,"B",L23>95%,"C") -> #DIV/0!
D24: =C24/C$42 -> #DIV/0! | E24: =D24+E23 -> #DIV/0! | F24: =IF(AND(E24<=0),"C",IF(E24<=0.8,"A",IF(E24<=0.95,"B","C"))) -> #DIV/0! | G24: =VLOOKUP(B$22:B$42,I$22:M$42,5,0) -> #N/A | K24: =J24/J$42 -> #DIV/0! | L24: =K24+L23 -> #DIV/0! | M24: =_xlfn.IFS(L24<80%,"A",L24<=95%,"B",L24>95%,"C") -> #DIV/0!
D25: =C25/C$42 -> #DIV/0! | E25: =D25+E24 -> #DIV/0! | F25: =IF(AND(E25<=0),"C",IF(E25<=0.8,"A",IF(E25<=0.95,"B","C"))) -> #DIV/0! | G25: =VLOOKUP(B$22:B$42,I$22:M$42,5,0) -> #N/A | K25: =J25/J$42 -> #DIV/0! | L25: =K25+L24 -> #DIV/0! | M25: =_xlfn.IFS(L25<80%,"A",L25<=95%,"B",L25>95%,"C") -> #DIV/0!
D26: =C26/C$42 -> #DIV/0! | E26: =D26+E25 -> #DIV/0! | F26: =IF(AND(E26<=0),"C",IF(E26<=0.8,"A",IF(E26<=0.95,"B","C"))) -> #DIV/0! | G26: =VLOOKUP(B$22:B$42,I$22:M$42,5,0) -> #N/A | K26: =J26/J$42 -> #DIV/0! | L26: =K26+L25 -> #DIV/0! | M26: =_xlfn.IFS(L26<80%,"A",L26<=95%,"B",L26>95%,"C") -> #DIV/0!
D27: =C27/C$42 -> #DIV/0! | E27: =D27+E26 -> #DIV/0! | F27: =IF(AND(E27<=0),"C",IF(E27<=0.8,"A",IF(E27<=0.95,"B","C"))) -> #DIV/0! | G27: =VLOOKUP(B$22:B$42,I$22:M$42,5,0) -> #N/A | K27: =J27/J$42 -> #DIV/0! | L27: =K27+L26 -> #DIV/0! | M27: =_xlfn.IFS(L27<80%,"A",L27<=95%,"B",L27>95%,"C") -> #DIV/0!
D28: =C28/C$42 -> #DIV/0! | E28: =D28+E27 -> #DIV/0! | F28: =IF(AND(E28<=0),"C",IF(E28<=0.8,"A",IF(E28<=0.95,"B","C"))) -> #DIV/0! | G28: =VLOOKUP(B$22:B$42,I$22:M$42,5,0) -> #N/A | K28: =J28/J$42 -> #DIV/0! | L28: =K28+L27 -> #DIV/0! | M28: =_xlfn.IFS(L28<80%,"A",L28<=95%,"B",L28>95%,"C") -> #DIV/0!
D29: =C29/C$42 -> #DIV/0! | E29: =D29+E28 -> #DIV/0! | F29: =IF(AND(E29<=0),"C",IF(E29<=0.8,"A",IF(E29<=0.95,"B","C"))) -> #DIV/0! | G29: =VLOOKUP(B$22:B$42,I$22:M$42,5,0) -> #N/A | K29: =J29/J$42 -> #DIV/0! | L29: =K29+L28 -> #DIV/0! | M29: =_xlfn.IFS(L29<80%,"A",L29<=95%,"B",L29>95%,"C") -> #DIV/0!
D30: =C30/C$42 -> #DIV/0! | E30: =D30+E29 -> #DIV/0! | F30: =IF(AND(E30<=0),"C",IF(E30<=0.8,"A",IF(E30<=0.95,"B","C"))) -> #DIV/0! | G30: =VLOOKUP(B$22:B$42,I$22:M$42,5,0) -> #N/A | K30: =J30/J$42 -> #DIV/0! | L30: =K30+L29 -> #DIV/0! | M30: =_xlfn.IFS(L30<80%,"A",L30<=95%,"B",L30>95%,"C") -> #DIV/0!
D31: =C31/C$42 -> #DIV/0! | E31: =D31+E30 -> #DIV/0! | F31: =IF(AND(E31<=0),"C",IF(E31<=0.8,"A",IF(E31<=0.95,"B","C"))) -> #DIV/0! | G31: =VLOOKUP(B$22:B$42,I$22:M$42,5,0) -> #N/A | K31: =J31/J$42 -> #DIV/0! | L31: =K31+L30 -> #DIV/0! | M31: =_xlfn.IFS(L31<80%,"A",L31<=95%,"B",L31>95%,"C") -> #DIV/0!
D32: =C32/C$42 -> #DIV/0! | E32: =D32+E31 -> #DIV/0! | F32: =IF(AND(E32<=0),"C",IF(E32<=0.8,"A",IF(E32<=0.95,"B","C"))) -> #DIV/0! | G32: =VLOOKUP(B$22:B$42,I$22:M$42,5,0) -> #N/A | K32: =J32/J$42 -> #DIV/0! | L32: =K32+L31 -> #DIV/0! | M32: =_xlfn.IFS(L32<80%,"A",L32<=95%,"B",L32>95%,"C") -> #DIV/0!
D33: =C33/C$42 -> #DIV/0! | E33: =D33+E32 -> #DIV/0! | F33: =IF(AND(E33<=0),"C",IF(E33<=0.8,"A",IF(E33<=0.95,"B","C"))) -> #DIV/0! | G33: =VLOOKUP(B$22:B$42,I$22:M$42,5,0) -> #N/A | K33: =J33/J$42 -> #DIV/0! | L33: =K33+L32 -> #DIV/0! | M33: =_xlfn.IFS(L33<80%,"A",L33<=95%,"B",L33>95%,"C") -> #DIV/0!
D34: =C34/C$42 -> #DIV/0! | E34: =D34+E33 -> #DIV/0! | F34: =IF(AND(E34<=0),"C",IF(E34<=0.8,"A",IF(E34<=0.95,"B","C"))) -> #DIV/0! | G34: =VLOOKUP(B$22:B$42,I$22:M$42,5,0) -> #N/A | K34: =J34/J$42 -> #DIV/0! | L34: =K34+L33 -> #DIV/0! | M34: =_xlfn.IFS(L34<80%,"A",L34<=95%,"B",L34>95%,"C") -> #DIV/0!
... D41: =C41/C$42 -> #DIV/0! | E41: =D41+E40 -> #DIV/0! | F41: =IF(AND(E41<=0),"C",IF(E41<=0.8,"A",IF(E41<=0.95,"B","C"))) -> #DIV/0! | G41: =VLOOKUP(B$22:B$42,I$22:M$42,5,0) -> #N/A | K41: =J41/J$42 -> #DIV/0! | L41: =K41+L40 -> #DIV/0! | M41: =_xlfn.IFS(L41<80%,"A",L41<=95%,"B",L41>95%,"C") -> #DIV/0!
C42: =SUM(C22:C41) -> 0 | D42: =SUM(D22:D41) -> #DIV/0! | J42: =SUM(J22:J41) -> 0 | K42: =SUM(K22:K41) -> #DIV/0!

Sheet АВС 05-11.01
B2: ОЧКИ
C3: Прибыль | D3: % прибыль | E3: Доля | F3: ABC прибыль | G3: ABC кол-во | J3: Кол-во | K3: % кол-во | L3: Доля | M3: ABC кол-во
B4: th желт | C4: ='Юнит 05-11.01'!AE11 -> 14577.679 | D4: =C4/C$18 -> 0.32994497 | E4: =D4 -> 0.32994497 | F4: =IF(AND(E4<=0),"C",IF(E4<=0.8,"A",IF(E4<=0.95,"B","C"))) -> A | G4: =VLOOKUP(B$4:B$17,I$4:M$17,5,0) -> A | I4: th желт | J4: ='Юнит 05-11.01'!R11 -> 52 | K4: =J4/J$18 -> 0.325 | L4: =K4 -> 0.325 | M4: =_xlfn.IFS(L4<80%,"A",L4<=95%,"B",L4>95%,"C") -> A
B5: flip жел | C5: ='Юнит 05-11.01'!AE15 -> 13681.243 | D5: =C5/C$18 -> 0.3096554 | E5: =D5+E4 -> 0.63960037 | F5: =IF(AND(E5<=0),"C",IF(E5<=0.8,"A",IF(E5<=0.95,"B","C"))) -> A | G5: =VLOOKUP(B$4:B$17,I$4:M$17,5,0) -> A | I5: flip жел | J5: ='Юнит 05-11.01'!R15 -> 49 | K5: =J5/J$18 -> 0.30625 | L5: =K5+L4 -> 0.63125 | M5: =_xlfn.IFS(L5<80%,"A",L5<=95%,"B",L5>95%,"C") -> A
B6: qs желтые | C6: ='Юнит 05-11.01'!AE6 -> 6919.0166 | D6: =C6/C$18 -> 0.15660207 | E6: =D6+E5 -> 0.79620244 | F6: =IF(AND(E6<=0),"C",IF(E6<=0.8,"A",IF(E6<=0.95,"B","C"))) -> A | G6: =VLOOKUP(B$4:B$17,I$4:M$17,5,0) -> B | I6: qs желтые | J6: ='Юнит 05-11.01'!R6 -> 31 | K6: =J6/J$18 -> 0.19375 | L6: =K6+L5 -> 0.825 | M6: =_xlfn.IFS(L6<80%,"A",L6<=95%,"B",L6>95%,"C") -> B
B7: qs коричневые | C7: ='Юнит 05-11.01'!AE7 -> 2667.2832 | D7: =C7/C$18 -> 0.060370149 | E7: =D7+E6 -> 0.85657259 | F7: =IF(AND(E7<=0),"C",IF(E7<=0.8,"A",IF(E7<=0.95,"B","C"))) -> B | G7: =VLOOKUP(B$4:B$17,I$4:M$17,5,0) -> B | I7: MR8854 C2 | J7: ='Юнит 05-11.01'!R8 -> 10 | K7: =J7/J$18 -> 0.0625 | L7: =K7+L6 -> 0.8875 | M7: =_xlfn.IFS(L7<80%,"A",L7<=95%,"B",L7>95%,"C") -> B
B8: MR8854 C2 | C8: ='Юнит 05-11.01'!AE8 -> 2517.3576 | D8: =C8/C$18 -> 0.056976798 | E8: =D8+E7 -> 0.91354939 | F8: =IF(AND(E8<=0),"C",IF(E8<=0.8,"A",IF(E8<=0.95,"B","C"))) -> B | G8: =VLOOKUP(B$4:B$17,I$4:M$17,5,0) -> B | I8: qs коричневые | J8: ='Юнит 05-11.01'!R7 -> 8 | K8: =J8/J$18 -> 0.05 | L8: =K8+L7 -> 0.9375 | M8: =_xlfn.IFS(L8<80%,"A",L8<=95%,"B",L8>95%,"C") -> B
B9: черные с железкой классика | C9: ='Юнит 05-11.01'!AE3 -> 1842.5976 | D9: =C9/C$18 -> 0.041704567 | E9: =D9+E8 -> 0.95525396 | F9: =IF(AND(E9<=0),"C",IF(E9<=0.8,"A",IF(E9<=0.95,"B","C"))) -> C | G9: =VLOOKUP(B$4:B$17,I$4:M$17,5,0) -> C | I9: черные с железкой классика | J9: ='Юнит 05-11.01'!R3 -> 5 | K9: =J9/J$18 -> 0.03125 | L9: =K9+L8 -> 0.96875 | M9: =_xlfn.IFS(L9<80%,"A",L9<=95%,"B",L9>95%,"C") -> C
B10: qs черные | C10: ='Юнит 05-11.01'!AE4 -> 1521.1407 | D10: =C10/C$18 -> 0.034428849 | E10: =D10+E9 -> 0.98968281 | F10: =IF(AND(E10<=0),"C",IF(E10<=0.8,"A",IF(E10<=0.95,"B","C"))) -> C | G10: =VLOOKUP(B$4:B$17,I$4:M$17,5,0) -> C | I10: qs черные | J10: ='Юнит 05-11.01'!R4 -> 3 | K10: =J10/J$18 -> 0.01875 | L10: =K10+L9 -> 0.9875 | M10: =_xlfn.IFS(L10<80%,"A",L10<=95%,"B",L10>95%,"C") -> C
B11: qs синие | C11: ='Юнит 05-11.01'!AE5 -> 455.83588 | D11: =C11/C$18 -> 0.010317195 | E11: =D11+E10 -> 1 | F11: =IF(AND(E11<=0),"C",IF(E11<=0.8,"A",IF(E11<=0.95,"B","C"))) -> C | G11: =VLOOKUP(B$4:B$17,I$4:M$17,5,0) -> C | I11: qs синие | J11: ='Юнит 05-11.01'!R5 -> 2 | K11: =J11/J$18 -> 0.0125 | L11: =K11+L10 -> 1 | M11: =_xlfn.IFS(L11<80%,"A",L11<=95%,"B",L11>95%,"C") -> C
B12: th черн | C12: ='Юнит 05-11.01'!AE9 -> 0 | D12: =C12/C$18 -> 0 | E12: =D12+E5 -> 0.63960037 | F12: =IF(AND(E12<=0),"C",IF(E12<=0.8,"A",IF(E12<=0.95,"B","C"))) -> A | G12: =VLOOKUP(B$4:B$17,I$4:M$17,5,0) -> A | I12: th черн | J12: ='Юнит 05-11.01'!R9 -> 0 | K12: =J12/J$18 -> 0 | L12: =K12+L5 -> 0.63125 | M12: =_xlfn.IFS(L12<80%,"A",L12<=95%,"B",L12>95%,"C") -> A
B13: th син | C13: ='Юнит 05-11.01'!AE10 -> 0 | D13: =C13/C$18 -> 0 | E13: =D13+E12 -> 0.63960037 | F13: =IF(AND(E13<=0),"C",IF(E13<=0.8,"A",IF(E13<=0.95,"B","C"))) -> A | G13: =VLOOKUP(B$4:B$17,I$4:M$17,5,0) -> A | I13: th син | J13: ='Юнит 05-11.01'!R10 -> 0 | K13: =J13/J$18 -> 0 | L13: =K13+L12 -> 0.63125 | M13: =_xlfn.IFS(L13<80%,"A",L13<=95%,"B",L13>95%,"C") -> A
B14: th коричн | C14: ='Юнит 05-11.01'!AE12 -> 0 | D14: =C14/C$18 -> 0 | E14: =D14+E13 -> 0.63960037 | F14: =IF(AND(E14<=0),"C",IF(E14<=0.8,"A",IF(E14<=0.95,"B","C"))) -> A | G14: =VLOOKUP(B$4:B$17,I$4:M$17,5,0) -> A | I14: th коричн | J14: ='Юнит 05-11.01'!R12 -> 0 | K14: =J14/J$18 -> 0 | L14: =K14+L13 -> 0.63125 | M14: =_xlfn.IFS(L14<80%,"A",L14<=95%,"B",L14>95%,"C") -> A
B15: flip черный | C15: ='Юнит 05-11.01'!AE13 -> 0 | D15: =C15/C$18 -> 0 | E15: =D15+E14 -> 0.63960037 | F15: =IF(AND(E15<=0),"C",IF(E15<=0.8,"A",IF(E15<=0.95,"B","C"))) -> A | G15: =VLOOKUP(B$4:B$17,I$4:M$17,5,0) -> A | I15: flip черный | J15: ='Юнит 05-11.01'!R13 -> 0 | K15: =J15/J$18 -> 0 | L15: =K15+L14 -> 0.63125 | M15: =_xlfn.IFS(L15<80%,"A",L15<=95%,"B",L15>95%,"C") -> A
B16: flip синий | C16: ='Юнит 05-11.01'!AE14 -> 0 | D16: =C16/C$18 -> 0 | E16: =D16+E15 -> 0.63960037 | F16: =IF(AND(E16<=0),"C",IF(E16<=0.8,"A",IF(E16<=0.95,"B","C"))) -> A | G16: =VLOOKUP(B$4:B$17,I$4:M$17,5,0) -> A | I16: flip синий | J16: ='Юнит 05-11.01'!R14 -> 0 | K16: =J16/J$18 -> 0 | L16: =K16+L15 -> 0.63125 | M16: =_xlfn.IFS(L16<80%,"A",L16<=95%,"B",L16>95%,"C") -> A
B17: flip коричневый | C17: ='Юнит 05-11.01'!AE16 -> 0 | D17: =C17/C$18 -> 0 | E17: =D17+E14 -> 0.63960037 | F17: =IF(AND(E17<=0),"C",IF(E17<=0.8,"A",IF(E17<=0.95,"B","C"))) -> A | G17: =VLOOKUP(B$4:B$17,I$4:M$17,5,0) -> A | I17: flip коричневый | J17: ='Юнит 05-11.01'!R16 -> 0 | K17: =J17/J$18 -> 0 | L17: =K17+L14 -> 0.63125 | M17: =_xlfn.IFS(L17<80%,"A",L17<=95%,"B",L17>95%,"C") -> A
C18: =SUM(C4:C17) -> 44182.154 | D18: =SUM(D4:D17) -> 1 | J18: =SUM(J4:J17) -> 160 | K18: =SUM(K4:K17) -> 1
C21: Прибыль | D21: % прибыль | E21: Доля | F21: ABC прибыль | G21: ABC кол-во | J21: Кол-во | K21: % кол-во | L21: Доля | M21: ABC кол-во
D22: =C22/C$42 -> #DIV/0! | E22: =D22 -> #DIV/0! | F22: =IF(AND(E22<=0),"C",IF(E22<=0.8,"A",IF(E22<=0.95,"B","C"))) -> #DIV/0! | G22: =VLOOKUP(B$22:B$42,I$22:M$42,5,0) -> #N/A | K22: =J22/J$42 -> #DIV/0! | L22: =K22 -> #DIV/0! | M22: =_xlfn.IFS(L22<80%,"A",L22<=95%,"B",L22>95%,"C") -> #DIV/0!
D23: =C23/C$42 -> #DIV/0! | E23: =D23+E22 -> #DIV/0! | F23: =IF(AND(E23<=0),"C",IF(E23<=0.8,"A",IF(E23<=0.95,"B","C"))) -> #DIV/0! | G23: =VLOOKUP(B$22:B$42,I$22:M$42,5,0) -> #N/A | K23: =J23/J$42 -> #DIV/0! | L23: =K23+L22 -> #DIV/0! | M23: =_xlfn.IFS(L23<80%,"A",L23<=95%,"B",L23>95%,"C") -> #DIV/0!
D24: =C24/C$42 -> #DIV/0! | E24: =D24+E23 -> #DIV/0! | F24: =IF(AND(E24<=0),"C",IF(E24<=0.8,"A",IF(E24<=0.95,"B","C"))) -> #DIV/0! | G24: =VLOOKUP(B$22:B$42,I$22:M$42,5,0) -> #N/A | K24: =J24/J$42 -> #DIV/0! | L24: =K24+L23 -> #DIV/0! | M24: =_xlfn.IFS(L24<80%,"A",L24<=95%,"B",L24>95%,"C") -> #DIV/0!
D25: =C25/C$42 -> #DIV/0! | E25: =D25+E24 -> #DIV/0! | F25: =IF(AND(E25<=0),"C",IF(E25<=0.8,"A",IF(E25<=0.95,"B","C"))) -> #DIV/0! | G25: =VLOOKUP(B$22:B$42,I$22:M$42,5,0) -> #N/A | K25: =J25/J$42 -> #DIV/0! | L25: =K25+L24 -> #DIV/0! | M25: =_xlfn.IFS(L25<80%,"A",L25<=95%,"B",L25>95%,"C") -> #DIV/0!
D26: =C26/C$42 -> #DIV/0! | E26: =D26+E25 -> #DIV/0! | F26: =IF(AND(E26<=0),"C",IF(E26<=0.8,"A",IF(E26<=0.95,"B","C"))) -> #DIV/0! | G26: =VLOOKUP(B$22:B$42,I$22:M$42,5,0) -> #N/A | K26: =J26/J$42 -> #DIV/0! | L26: =K26+L25 -> #DIV/0! | M26: =_xlfn.IFS(L26<80%,"A",L26<=95%,"B",L26>95%,"C") -> #DIV/0!
D27: =C27/C$42 -> #DIV/0! | E27: =D27+E26 -> #DIV/0! | F27: =IF(AND(E27<=0),"C",IF(E27<=0.8,"A",IF(E27<=0.95,"B","C"))) -> #DIV/0! | G27: =VLOOKUP(B$22:B$42,I$22:M$42,5,0) -> #N/A | K27: =J27/J$42 -> #DIV/0! | L27: =K27+L26 -> #DIV/0! | M27: =_xlfn.IFS(L27<80%,"A",L27<=95%,"B",L27>95%,"C") -> #DIV/0!
D28: =C28/C$42 -> #DIV/0! | E28: =D28+E27 -> #DIV/0! | F28: =IF(AND(E28<=0),"C",IF(E28<=0.8,"A",IF(E28<=0.95,"B","C"))) -> #DIV/0! | G28: =VLOOKUP(B$22:B$42,I$22:M$42,5,0) -> #N/A | K28: =J28/J$42 -> #DIV/0! | L28: =K28+L27 -> #DIV/0! | M28: =_xlfn.IFS(L28<80%,"A",L28<=95%,"B",L28>95%,"C") -> #DIV/0!
D29: =C29/C$42 -> #DIV/0! | E29: =D29+E28 -> #DIV/0! | F29: =IF(AND(E29<=0),"C",IF(E29<=0.8,"A",IF(E29<=0.95,"B","C"))) -> #DIV/0! | G29: =VLOOKUP(B$22:B$42,I$22:M$42,5,0) -> #N/A | K29: =J29/J$42 -> #DIV/0! | L29: =K29+L28 -> #DIV/0! | M29: =_xlfn.IFS(L29<80%,"A",L29<=95%,"B",L29>95%,"C") -> #DIV/0!
D30: =C30/C$42 -> #DIV/0! | E30: =D30+E29 -> #DIV/0! | F30: =IF(AND(E30<=0),"C",IF(E30<=0.8,"A",IF(E30<=0.95,"B","C"))) -> #DIV/0! | G30: =VLOOKUP(B$22:B$42,I$22:M$42,5,0) -> #N/A | K30: =J30/J$42 -> #DIV/0! | L30: =K30+L29 -> #DIV/0! | M30: =_xlfn.IFS(L30<80%,"A",L30<=95%,"B",L30>95%,"C") -> #DIV/0!
D31: =C31/C$42 -> #DIV/0! | E31: =D31+E30 -> #DIV/0! | F31: =IF(AND(E31<=0),"C",IF(E31<=0.8,"A",IF(E31<=0.95,"B","C"))) -> #DIV/0! | G31: =VLOOKUP(B$22:B$42,I$22:M$42,5,0) -> #N/A | K31: =J31/J$42 -> #DIV/0! | L31: =K31+L30 -> #DIV/0! | M31: =_xlfn.IFS(L31<80%,"A",L31<=95%,"B",L31>95%,"C") -> #DIV/0!
D32: =C32/C$42 -> #DIV/0! | E32: =D32+E31 -> #DIV/0! | F32: =IF(AND(E32<=0),"C",IF(E32<=0.8,"A",IF(E32<=0.95,"B","C"))) -> #DIV/0! | G32: =VLOOKUP(B$22:B$42,I$22:M$42,5,0) -> #N/A | K32: =J32/J$42 -> #DIV/0! | L32: =K32+L31 -> #DIV/0! | M32: =_xlfn.IFS(L32<80%,"A",L32<=95%,"B",L32>95%,"C") -> #DIV/0!
D33: =C33/C$42 -> #DIV/0! | E33: =D33+E32 -> #DIV/0! | F33: =IF(AND(E33<=0),"C",IF(E33<=0.8,"A",IF(E33<=0.95,"B","C"))) -> #DIV/0! | G33: =VLOOKUP(B$22:B$42,I$22:M$42,5,0) -> #N/A | K33: =J33/J$42 -> #DIV/0! | L33: =K33+L32 -> #DIV/0! | M33: =_xlfn.IFS(L33<80%,"A",L33<=95%,"B",L33>95%,"C") -> #DIV/0!
D34: =C34/C$42 -> #DIV/0! | E34: =D34+E33 -> #DIV/0! | F34: =IF(AND(E34<=0),"C",IF(E34<=0.8,"A",IF(E34<=0.95,"B","C"))) -> #DIV/0! | G34: =VLOOKUP(B$22:B$42,I$22:M$42,5,0) -> #N/A | K34: =J34/J$42 -> #DIV/0! | L34: =K34+L33 -> #DIV/0! | M34: =_xlfn.IFS(L34<80%,"A",L34<=95%,"B",L34>95%,"C") -> #DIV/0!
... D41: =C41/C$42 -> #DIV/0! | E41: =D41+E40 -> #DIV/0! | F41: =IF(AND(E41<=0),"C",IF(E41<=0.8,"A",IF(E41<=0.95,"B","C"))) -> #DIV/0! | G41: =VLOOKUP(B$22:B$42,I$22:M$42,5,0) -> #N/A | K41: =J41/J$42 -> #DIV/0! | L41: =K41+L40 -> #DIV/0! | M41: =_xlfn.IFS(L41<80%,"A",L41<=95%,"B",L41>95%,"C") -> #DIV/0!
C42: =SUM(C22:C41) -> 0 | D42: =SUM(D22:D41) -> #DIV/0! | J42: =SUM(J22:J41) -> 0 | K42: =SUM(K22:K41) -> #DIV/0!

Sheet АВС 01-04.01
B2: ОЧКИ
C3: Прибыль | D3: % прибыль | E3: Доля | F3: ABC прибыль | G3: ABC кол-во | J3: Кол-во | K3: % кол-во | L3: Доля | M3: ABC кол-во
B4: flip жел | C4: ='Юнит 01-04.01'!AE15 -> 2923.2652 | D4: =C4/C$18 -> -0.78040933 | E4: =D4 -> -0.78040933 | F4: =IF(AND(E4<=0),"C",IF(E4<=0.8,"A",IF(E4<=0.95,"B","C"))) -> C | G4: =VLOOKUP(B$4:B$17,I$4:M$17,5,0) -> A | I4: flip жел | J4: ='Юнит 01-04.01'!R15 -> 25 | K4: =J4/J$18 -> 0.5 | L4: =K4 -> 0.5 | M4: =_xlfn.IFS(L4<80%,"A",L4<=95%,"B",L4>95%,"C") -> A
B5: qs черные | C5: ='Юнит 01-04.01'!AE4 -> 684.33 | D5: =C5/C$18 -> -0.18269212 | E5: =D5+E4 -> -0.96310145 | F5: =IF(AND(E5<=0),"C",IF(E5<=0.8,"A",IF(E5<=0.95,"B","C"))) -> C | G5: =VLOOKUP(B$4:B$17,I$4:M$17,5,0) -> C | I5: th желт | J5: ='Юнит 01-04.01'!R11 -> 12 | K5: =J5/J$18 -> 0.24 | L5: =K5+L4 -> 0.74 | M5: =_xlfn.IFS(L5<80%,"A",L5<=95%,"B",L5>95%,"C") -> A
B6: qs коричневые | C6: ='Юнит 01-04.01'!AE7 -> 752.97 | D6: =C6/C$18 -> -0.20101659 | E6: =D6+E5 -> -1.164118 | F6: =IF(AND(E6<=0),"C",IF(E6<=0.8,"A",IF(E6<=0.95,"B","C"))) -> C | G6: =VLOOKUP(B$4:B$17,I$4:M$17,5,0) -> B | I6: qs желтые | J6: ='Юнит 01-04.01'!R6 -> 7 | K6: =J6/J$18 -> 0.14 | L6: =K6+L5 -> 0.88 | M6: =_xlfn.IFS(L6<80%,"A",L6<=95%,"B",L6>95%,"C") -> B
B7: черные с железкой классика | C7: ='Юнит 01-04.01'!AE3 -> 277.19 | D7: =C7/C$18 -> -0.074000012 | E7: =D7+E6 -> -1.238118 | F7: =IF(AND(E7<=0),"C",IF(E7<=0.8,"A",IF(E7<=0.95,"B","C"))) -> C | G7: =VLOOKUP(B$4:B$17,I$4:M$17,5,0) -> C | I7: qs коричневые | J7: ='Юнит 01-04.01'!R7 -> 2 | K7: =J7/J$18 -> 0.04 | L7: =K7+L6 -> 0.92 | M7: =_xlfn.IFS(L7<80%,"A",L7<=95%,"B",L7>95%,"C") -> B
B8: qs синие | C8: ='Юнит 01-04.01'!AE5 -> 0 | D8: =C8/C$18 -> 0 | E8: =D8+E7 -> -1.238118 | F8: =IF(AND(E8<=0),"C",IF(E8<=0.8,"A",IF(E8<=0.95,"B","C"))) -> C | G8: =VLOOKUP(B$4:B$17,I$4:M$17,5,0) -> C | I8: MR8854 C2 | J8: ='Юнит 01-04.01'!R8 -> 2 | K8: =J8/J$18 -> 0.04 | L8: =K8+L7 -> 0.96 | M8: =_xlfn.IFS(L8<80%,"A",L8<=95%,"B",L8>95%,"C") -> C
B9: th черн | C9: ='Юнит 01-04.01'!AE9 -> 0 | D9: =C9/C$18 -> 0 | E9: =D9+E8 -> -1.238118 | F9: =IF(AND(E9<=0),"C",IF(E9<=0.8,"A",IF(E9<=0.95,"B","C"))) -> C | G9: =VLOOKUP(B$4:B$17,I$4:M$17,5,0) -> A | I9: черные с железкой классика | J9: ='Юнит 01-04.01'!R3 -> 1 | K9: =J9/J$18 -> 0.02 | L9: =K9+L8 -> 0.98 | M9: =_xlfn.IFS(L9<80%,"A",L9<=95%,"B",L9>95%,"C") -> C
B10: th син | C10: ='Юнит 01-04.01'!AE10 -> 0 | D10: =C10/C$18 -> 0 | E10: =D10+E9 -> -1.238118 | F10: =IF(AND(E10<=0),"C",IF(E10<=0.8,"A",IF(E10<=0.95,"B","C"))) -> C | G10: =VLOOKUP(B$4:B$17,I$4:M$17,5,0) -> A | I10: qs черные | J10: ='Юнит 01-04.01'!R4 -> 1 | K10: =J10/J$18 -> 0.02 | L10: =K10+L9 -> 1 | M10: =_xlfn.IFS(L10<80%,"A",L10<=95%,"B",L10>95%,"C") -> C
B11: th коричн | C11: ='Юнит 01-04.01'!AE12 -> 0 | D11: =C11/C$18 -> 0 | E11: =D11+E10 -> -1.238118 | F11: =IF(AND(E11<=0),"C",IF(E11<=0.8,"A",IF(E11<=0.95,"B","C"))) -> C | G11: =VLOOKUP(B$4:B$17,I$4:M$17,5,0) -> A | I11: qs синие | J11: ='Юнит 01-04.01'!R5 -> 0 | K11: =J11/J$18 -> 0 | L11: =K11+L10 -> 1 | M11: =_xlfn.IFS(L11<80%,"A",L11<=95%,"B",L11>95%,"C") -> C
B12: flip черный | C12: ='Юнит 01-04.01'!AE13 -> 0 | D12: =C12/C$18 -> 0 | E12: =D12+E5 -> -0.96310145 | F12: =IF(AND(E12<=0),"C",IF(E12<=0.8,"A",IF(E12<=0.95,"B","C"))) -> C | G12: =VLOOKUP(B$4:B$17,I$4:M$17,5,0) -> A | I12: th черн | J12: ='Юнит 01-04.01'!R9 -> 0 | K12: =J12/J$18 -> 0 | L12: =K12+L5 -> 0.74 | M12: =_xlfn.IFS(L12<80%,"A",L12<=95%,"B",L12>95%,"C") -> A
B13: flip синий | C13: ='Юнит 01-04.01'!AE14 -> 0 | D13: =C13/C$18 -> 0 | E13: =D13+E12 -> -0.96310145 | F13: =IF(AND(E13<=0),"C",IF(E13<=0.8,"A",IF(E13<=0.95,"B","C"))) -> C | G13: =VLOOKUP(B$4:B$17,I$4:M$17,5,0) -> A | I13: th син | J13: ='Юнит 01-04.01'!R10 -> 0 | K13: =J13/J$18 -> 0 | L13: =K13+L12 -> 0.74 | M13: =_xlfn.IFS(L13<80%,"A",L13<=95%,"B",L13>95%,"C") -> A
B14: flip коричневый | C14: ='Юнит 01-04.01'!AE16 -> 0 | D14: =C14/C$18 -> 0 | E14: =D14+E13 -> -0.96310145 | F14: =IF(AND(E14<=0),"C",IF(E14<=0.8,"A",IF(E14<=0.95,"B","C"))) -> C | G14: =VLOOKUP(B$4:B$17,I$4:M$17,5,0) -> A | I14: th коричн | J14: ='Юнит 01-04.01'!R12 -> 0 | K14: =J14/J$18 -> 0 | L14: =K14+L13 -> 0.74 | M14: =_xlfn.IFS(L14<80%,"A",L14<=95%,"B",L14>95%,"C") -> A
B15: MR8854 C2 | C15: ='Юнит 01-04.01'!AE8 -> -419.23 | D15: =C15/C$18 -> 0.11191971 | E15: =D15+E14 -> -0.85118173 | F15: =IF(AND(E15<=0),"C",IF(E15<=0.8,"A",IF(E15<=0.95,"B","C"))) -> C | G15: =VLOOKUP(B$4:B$17,I$4:M$17,5,0) -> C | I15: flip черный | J15: ='Юнит 01-04.01'!R13 -> 0 | K15: =J15/J$18 -> 0 | L15: =K15+L14 -> 0.74 | M15: =_xlfn.IFS(L15<80%,"A",L15<=95%,"B",L15>95%,"C") -> A
B16: qs желтые | C16: ='Юнит 01-04.01'!AE6 -> -2341.0661 | D16: =C16/C$18 -> 0.62498256 | E16: =D16+E15 -> -0.22619917 | F16: =IF(AND(E16<=0),"C",IF(E16<=0.8,"A",IF(E16<=0.95,"B","C"))) -> C | G16: =VLOOKUP(B$4:B$17,I$4:M$17,5,0) -> B | I16: flip синий | J16: ='Юнит 01-04.01'!R14 -> 0 | K16: =J16/J$18 -> 0 | L16: =K16+L15 -> 0.74 | M16: =_xlfn.IFS(L16<80%,"A",L16<=95%,"B",L16>95%,"C") -> A
B17: th желт | C17: ='Юнит 01-04.01'!AE11 -> -5623.2694 | D17: =C17/C$18 -> 1.5012158 | E17: =D17+E14 -> 0.53811433 | F17: =IF(AND(E17<=0),"C",IF(E17<=0.8,"A",IF(E17<=0.95,"B","C"))) -> A | G17: =VLOOKUP(B$4:B$17,I$4:M$17,5,0) -> A | I17: flip коричневый | J17: ='Юнит 01-04.01'!R16 -> 0 | K17: =J17/J$18 -> 0 | L17: =K17+L14 -> 0.74 | M17: =_xlfn.IFS(L17<80%,"A",L17<=95%,"B",L17>95%,"C") -> A
C18: =SUM(C4:C17) -> -3745.8102 | D18: =SUM(D4:D17) -> 1 | J18: =SUM(J4:J17) -> 50 | K18: =SUM(K4:K17) -> 1
C21: Прибыль | D21: % прибыль | E21: Доля | F21: ABC прибыль | G21: ABC кол-во | J21: Кол-во | K21: % кол-во | L21: Доля | M21: ABC кол-во
D22: =C22/C$42 -> #DIV/0! | E22: =D22 -> #DIV/0! | F22: =IF(AND(E22<=0),"C",IF(E22<=0.8,"A",IF(E22<=0.95,"B","C"))) -> #DIV/0! | G22: =VLOOKUP(B$22:B$42,I$22:M$42,5,0) -> #N/A | K22: =J22/J$42 -> #DIV/0! | L22: =K22 -> #DIV/0! | M22: =_xlfn.IFS(L22<80%,"A",L22<=95%,"B",L22>95%,"C") -> #DIV/0!
D23: =C23/C$42 -> #DIV/0! | E23: =D23+E22 -> #DIV/0! | F23: =IF(AND(E23<=0),"C",IF(E23<=0.8,"A",IF(E23<=0.95,"B","C"))) -> #DIV/0! | G23: =VLOOKUP(B$22:B$42,I$22:M$42,5,0) -> #N/A | K23: =J23/J$42 -> #DIV/0! | L23: =K23+L22 -> #DIV/0! | M23: =_xlfn.IFS(L23<80%,"A",L23<=95%,"B",L23>95%,"C") -> #DIV/0!
D24: =C24/C$42 -> #DIV/0! | E24: =D24+E23 -> #DIV/0! | F24: =IF(AND(E24<=0),"C",IF(E24<=0.8,"A",IF(E24<=0.95,"B","C"))) -> #DIV/0! | G24: =VLOOKUP(B$22:B$42,I$22:M$42,5,0) -> #N/A | K24: =J24/J$42 -> #DIV/0! | L24: =K24+L23 -> #DIV/0! | M24: =_xlfn.IFS(L24<80%,"A",L24<=95%,"B",L24>95%,"C") -> #DIV/0!
D25: =C25/C$42 -> #DIV/0! | E25: =D25+E24 -> #DIV/0! | F25: =IF(AND(E25<=0),"C",IF(E25<=0.8,"A",IF(E25<=0.95,"B","C"))) -> #DIV/0! | G25: =VLOOKUP(B$22:B$42,I$22:M$42,5,0) -> #N/A | K25: =J25/J$42 -> #DIV/0! | L25: =K25+L24 -> #DIV/0! | M25: =_xlfn.IFS(L25<80%,"A",L25<=95%,"B",L25>95%,"C") -> #DIV/0!
D26: =C26/C$42 -> #DIV/0! | E26: =D26+E25 -> #DIV/0! | F26: =IF(AND(E26<=0),"C",IF(E26<=0.8,"A",IF(E26<=0.95,"B","C"))) -> #DIV/0! | G26: =VLOOKUP(B$22:B$42,I$22:M$42,5,0) -> #N/A | K26: =J26/J$42 -> #DIV/0! | L26: =K26+L25 -> #DIV/0! | M26: =_xlfn.IFS(L26<80%,"A",L26<=95%,"B",L26>95%,"C") -> #DIV/0!
D27: =C27/C$42 -> #DIV/0! | E27: =D27+E26 -> #DIV/0! | F27: =IF(AND(E27<=0),"C",IF(E27<=0.8,"A",IF(E27<=0.95,"B","C"))) -> #DIV/0! | G27: =VLOOKUP(B$22:B$42,I$22:M$42,5,0) -> #N/A | K27: =J27/J$42 -> #DIV/0! | L27: =K27+L26 -> #DIV/0! | M27: =_xlfn.IFS(L27<80%,"A",L27<=95%,"B",L27>95%,"C") -> #DIV/0!
D28: =C28/C$42 -> #DIV/0! | E28: =D28+E27 -> #DIV/0! | F28: =IF(AND(E28<=0),"C",IF(E28<=0.8,"A",IF(E28<=0.95,"B","C"))) -> #DIV/0! | G28: =VLOOKUP(B$22:B$42,I$22:M$42,5,0) -> #N/A | K28: =J28/J$42 -> #DIV/0! | L28: =K28+L27 -> #DIV/0! | M28: =_xlfn.IFS(L28<80%,"A",L28<=95%,"B",L28>95%,"C") -> #DIV/0!
D29: =C29/C$42 -> #DIV/0! | E29: =D29+E28 -> #DIV/0! | F29: =IF(AND(E29<=0),"C",IF(E29<=0.8,"A",IF(E29<=0.95,"B","C"))) -> #DIV/0! | G29: =VLOOKUP(B$22:B$42,I$22:M$42,5,0) -> #N/A | K29: =J29/J$42 -> #DIV/0! | L29: =K29+L28 -> #DIV/0! | M29: =_xlfn.IFS(L29<80%,"A",L29<=95%,"B",L29>95%,"C") -> #DIV/0!
D30: =C30/C$42 -> #DIV/0! | E30: =D30+E29 -> #DIV/0! | F30: =IF(AND(E30<=0),"C",IF(E30<=0.8,"A",IF(E30<=0.95,"B","C"))) -> #DIV/0! | G30: =VLOOKUP(B$22:B$42,I$22:M$42,5,0) -> #N/A | K30: =J30/J$42 -> #DIV/0! | L30: =K30+L29 -> #DIV/0! | M30: =_xlfn.IFS(L30<80%,"A",L30<=95%,"B",L30>95%,"C") -> #DIV/0!
D31: =C31/C$42 -> #DIV/0! | E31: =D31+E30 -> #DIV/0! | F31: =IF(AND(E31<=0),"C",IF(E31<=0.8,"A",IF(E31<=0.95,"B","C"))) -> #DIV/0! | G31: =VLOOKUP(B$22:B$42,I$22:M$42,5,0) -> #N/A | K31: =J31/J$42 -> #DIV/0! | L31: =K31+L30 -> #DIV/0! | M31: =_xlfn.IFS(L31<80%,"A",L31<=95%,"B",L31>95%,"C") -> #DIV/0!
D32: =C32/C$42 -> #DIV/0! | E32: =D32+E31 -> #DIV/0! | F32: =IF(AND(E32<=0),"C",IF(E32<=0.8,"A",IF(E32<=0.95,"B","C"))) -> #DIV/0! | G32: =VLOOKUP(B$22:B$42,I$22:M$42,5,0) -> #N/A | K32: =J32/J$42 -> #DIV/0! | L32: =K32+L31 -> #DIV/0! | M32: =_xlfn.IFS(L32<80%,"A",L32<=95%,"B",L32>95%,"C") -> #DIV/0!
D33: =C33/C$42 -> #DIV/0! | E33: =D33+E32 -> #DIV/0! | F33: =IF(AND(E33<=0),"C",IF(E33<=0.8,"A",IF(E33<=0.95,"B","C"))) -> #DIV/0! | G33: =VLOOKUP(B$22:B$42,I$22:M$42,5,0) -> #N/A | K33: =J33/J$42 -> #DIV/0! | L33: =K33+L32 -> #DIV/0! | M33: =_xlfn.IFS(L33<80%,"A",L33<=95%,"B",L33>95%,"C") -> #DIV/0!
D34: =C34/C$42 -> #DIV/0! | E34: =D34+E33 -> #DIV/0! | F34: =IF(AND(E34<=0),"C",IF(E34<=0.8,"A",IF(E34<=0.95,"B","C"))) -> #DIV/0! | G34: =VLOOKUP(B$22:B$42,I$22:M$42,5,0) -> #N/A | K34: =J34/J$42 -> #DIV/0! | L34: =K34+L33 -> #DIV/0! | M34: =_xlfn.IFS(L34<80%,"A",L34<=95%,"B",L34>95%,"C") -> #DIV/0!
... D41: =C41/C$42 -> #DIV/0! | E41: =D41+E40 -> #DIV/0! | F41: =IF(AND(E41<=0),"C",IF(E41<=0.8,"A",IF(E41<=0.95,"B","C"))) -> #DIV/0! | G41: =VLOOKUP(B$22:B$42,I$22:M$42,5,0) -> #N/A | K41: =J41/J$42 -> #DIV/0! | L41: =K41+L40 -> #DIV/0! | M41: =_xlfn.IFS(L41<80%,"A",L41<=95%,"B",L41>95%,"C") -> #DIV/0!
C42: =SUM(C22:C41) -> 0 | D42: =SUM(D22:D41) -> #DIV/0! | J42: =SUM(J22:J41) -> 0 | K42: =SUM(K22:K41) -> #DIV/0!

Sheet 2026
B1: 01-31.03 | N1: Число дней | AG1: на 1 единицу проданного товара
B2: Артикул поставщика | C2: Остаток на | D2: В пути до клиента | E2: В пути от клиента | F2: Итого по складам ВБ | G2: Остаток на нашем складе на 02.09 | H2: Себетоимость на 1 ед на 29.09.25 | I2: Себестоимость остатков | J2: Оборачиваемость, дн | K2: Заказы, шт | L2: Средняя цена, руб (столбец 32, AG) | M2: % выкупа за 7 дней (столбец 23, X) | N2: Скорость заказов | O2: Скорость продаж | P2: Кол-во ПРОДАЖИ | Q2: Кол-во ВОЗВРАТЫ | R2: Кол-во ПРОДАЖИ-ВОЗВРАТЫ | S2: Выручка ПРОДАЖИ | T2: Выручка ВОЗВРАТЫ | U2: Выручка с учетом согласованной скидки ПРОДАЖИ - ВОЗВРАТЫ | V2: Доля выручки, % от общего объема | W2: Себестоимость продаж | X2: Комиссия, руб | Y2: Комиссия, % | Z2: Логистика | AA2: Реклама | AB2: Хранение | AC2: Штрафы | AD2: Налог 1% | AE2: Прибыль | AG2: Выручка на 1 ед (средняя цена продажи со скидкой) | AH2: Себестоимость на 1 ед | AI2: Комиссия на 1 ед | AJ2: Логистика на 1 ед | AK2: Реклама на 1 ед | AL2: Прибыль на 1 ед | AM2: Маржинальность, % | AN2: Рентабельность, % | AP2: Прибыль с остатков
A3: 2676784153 | B3: черные с железкой классика | H3: 142.98 | I3: =C3*H3 -> 0 | K3: =ЯНВАРЬ!K3+ФЕВРАЛЬ!K3+МАРТ!K3 -> 42 | N3: =K3/$O$1 -> #DIV/0! | O3: =R3/$O$1 -> #DIV/0! | P3: =ЯНВАРЬ!P3+ФЕВРАЛЬ!P3+МАРТ!P3 -> 38 | Q3: =ЯНВАРЬ!Q3+ФЕВРАЛЬ!Q3+МАРТ!Q3 -> 2 | R3: =P3-Q3 -> 36 | S3: =ЯНВАРЬ!S3+ФЕВРАЛЬ!S3+МАРТ!S3 -> 78463 | T3: =ЯНВАРЬ!T3+ФЕВРАЛЬ!T3+МАРТ!T3 -> -4800 | U3: =S3+T3 -> 73663 | V3: =U3/$U$24 -> 0.025754322 | W3: =R3*H3 -> 5147.28 | X3: =ЯНВАРЬ!X3+ФЕВРАЛЬ!X3+МАРТ!X3 -> 31675.09 | Y3: =IF(U3=0,0,X3/U3) -> 0.43 | Z3: =ЯНВАРЬ!Z3+ФЕВРАЛЬ!Z3+МАРТ!Z3 -> 8449.75 | AA3: =ЯНВАРЬ!AA3+ФЕВРАЛЬ!AA3+МАРТ!AA3 -> 21287.357 | AD3: =ЯНВАРЬ!AD3+ФЕВРАЛЬ!AD3+МАРТ!AD3 -> 301.77906 | AE3: =U3-W3-X3-Z3-AA3-AB3-AC3-AD3 -> 6801.7436 | AG3: =IF(R3=0,0,U3/R3) -> 2046.1944 | AH3: =H3 -> 142.98 | AI3: =IF(R3=0,0,X3/R3) -> 879.86361 | AJ3: =IF(P3=0,Z3/1,Z3/P3) -> 222.36184 | AK3: =IF(P3=0,0,AA3/P3) -> 560.19362 | AL3: =_xlfn.IFS(R3=0,AE3,R3<0,AE3/-R3,R3>0,AE3/R3) -> 188.93732 | AM3: =IF(AG3=0,0,AL3/AG3) -> 0.092335956 | AN3: =IF(AH3=0,0,AL3/AH3) -> 1.3214248 | AP3: =AL3*C3 -> 0
A4: 2676784638 | B4: qs черные | H4: 123.09 | I4: =C4*H4 -> 0 | K4: =ЯНВАРЬ!K4+ФЕВРАЛЬ!K4+МАРТ!K4 -> 66 | N4: =K4/$O$1 -> #DIV/0! | O4: =R4/$O$1 -> #DIV/0! | P4: =ЯНВАРЬ!P4+ФЕВРАЛЬ!P4+МАРТ!P4 -> 47 | Q4: =ЯНВАРЬ!Q4+ФЕВРАЛЬ!Q4+МАРТ!Q4 -> 2 | R4: =P4-Q4 -> 45 | S4: =ЯНВАРЬ!S4+ФЕВРАЛЬ!S4+МАРТ!S4 -> 95571 | T4: =ЯНВАРЬ!T4+ФЕВРАЛЬ!T4+МАРТ!T4 -> -4677 | U4: =S4+T4 -> 90894 | V4: =U4/$U$24 -> 0.031778685 | W4: =R4*H4 -> 5539.05 | X4: =ЯНВАРЬ!X4+ФЕВРАЛЬ!X4+МАРТ!X4 -> 39084.42 | Y4: =IF(U4=0,0,X4/U4) -> 0.43 | Z4: =ЯНВАРЬ!Z4+ФЕВРАЛЬ!Z4+МАРТ!Z4 -> 8977.36 | AA4: =ЯНВАРЬ!AA4+ФЕВРАЛЬ!AA4+МАРТ!AA4 -> 16179.375 | AD4: =ЯНВАРЬ!AD4+ФЕВРАЛЬ!AD4+МАРТ!AD4 -> 376.66161 | AE4: =U4-W4-X4-Z4-AA4-AB4-AC4-AD4 -> 20737.133 | AG4: =IF(R4=0,0,U4/R4) -> 2019.8667 | AH4: =H4 -> 123.09 | AI4: =IF(R4=0,0,X4/R4) -> 868.54267 | AJ4: =IF(P4=0,Z4/1,Z4/P4) -> 191.00766 | AK4: =IF(P4=0,0,AA4/P4) -> 344.24203 | AL4: {=_xlfn.IFS(R4=0,AE4,R4<0,AE4/-R4,R4>0,AE4/R4)} -> 460.82518 | AM4: =IF(AG4=0,0,AL4/AG4) -> 0.22814634 | AN4: =IF(AH4=0,0,AL4/AH4) -> 3.7438068 | AP4: =AL4*C4 -> 0
A5: 2676784504 | B5: qs синие | H5: 123.09 | I5: =C5*H5 -> 0 | K5: =ЯНВАРЬ!K5+ФЕВРАЛЬ!K5+МАРТ!K5 -> 27 | N5: =K5/$O$1 -> #DIV/0! | O5: =R5/$O$1 -> #DIV/0! | P5: =ЯНВАРЬ!P5+ФЕВРАЛЬ!P5+МАРТ!P5 -> 32 | Q5: =ЯНВАРЬ!Q5+ФЕВРАЛЬ!Q5+МАРТ!Q5 -> 2 | R5: =P5-Q5 -> 30 | S5: =ЯНВАРЬ!S5+ФЕВРАЛЬ!S5+МАРТ!S5 -> 67567 | T5: =ЯНВАРЬ!T5+ФЕВРАЛЬ!T5+МАРТ!T5 -> -4667 | U5: =S5+T5 -> 62900 | V5: =U5/$U$24 -> 0.021991323 | W5: =R5*H5 -> 3692.7 | X5: =ЯНВАРЬ!X5+ФЕВРАЛЬ!X5+МАРТ!X5 -> 27047 | Y5: =IF(U5=0,0,X5/U5) -> 0.43 | Z5: =ЯНВАРЬ!Z5+ФЕВРАЛЬ!Z5+МАРТ!Z5 -> 5062.25 | AA5: =ЯНВАРЬ!AA5+ФЕВРАЛЬ!AA5+МАРТ!AA5 -> 10432.559 | AD5: =ЯНВАРЬ!AD5+ФЕВРАЛЬ!AD5+МАРТ!AD5 -> 263.28825 | AE5: =U5-W5-X5-Z5-AA5-AB5-AC5-AD5 -> 16402.203 | AG5: =IF(R5=0,0,U5/R5) -> 2096.6667 | AH5: =H5 -> 123.09 | AI5: =IF(R5=0,0,X5/R5) -> 901.56667 | AJ5: =IF(P5=0,Z5/1,Z5/P5) -> 158.19531 | AK5: =IF(P5=0,0,AA5/P5) -> 326.01746 | AL5: {=_xlfn.IFS(R5=0,AE5,R5<0,AE5/-R5,R5>0,AE5/R5)} -> 546.7401 | AM5: =IF(AG5=0,0,AL5/AG5) -> 0.26076634 | AN5: =IF(AH5=0,0,AL5/AH5) -> 4.4417914 | AP5: =AL5*C5 -> 0
A6: 2676784514 | B6: qs желтые | H6: 123.09 | I6: =C6*H6 -> 0 | K6: =ЯНВАРЬ!K6+ФЕВРАЛЬ!K6+МАРТ!K6 -> 143 | N6: =K6/$O$1 -> #DIV/0! | O6: =R6/$O$1 -> #DIV/0! | P6: =ЯНВАРЬ!P6+ФЕВРАЛЬ!P6+МАРТ!P6 -> 141 | Q6: =ЯНВАРЬ!Q6+ФЕВРАЛЬ!Q6+МАРТ!Q6 -> 8 | R6: =P6-Q6 -> 133 | S6: =ЯНВАРЬ!S6+ФЕВРАЛЬ!S6+МАРТ!S6 -> 270133 | T6: =ЯНВАРЬ!T6+ФЕВРАЛЬ!T6+МАРТ!T6 -> -15361 | U6: =S6+T6 -> 254772 | V6: =U6/$U$24 -> 0.089074298 | W6: =R6*H6 -> 16370.97 | X6: =ЯНВАРЬ!X6+ФЕВРАЛЬ!X6+МАРТ!X6 -> 109551.96 | Y6: =IF(U6=0,0,X6/U6) -> 0.43 | Z6: =ЯНВАРЬ!Z6+ФЕВРАЛЬ!Z6+МАРТ!Z6 -> 22318.09 | AA6: =ЯНВАРЬ!AA6+ФЕВРАЛЬ!AA6+МАРТ!AA6 -> 57783.919 | AD6: =ЯНВАРЬ!AD6+ФЕВРАЛЬ!AD6+МАРТ!AD6 -> 1018.2592 | AE6: =U6-W6-X6-Z6-AA6-AB6-AC6-AD6 -> 47728.802 | AG6: =IF(R6=0,0,U6/R6) -> 1915.5789 | AH6: =H6 -> 123.09 | AI6: =IF(R6=0,0,X6/R6) -> 823.69895 | AJ6: =IF(P6=0,Z6/1,Z6/P6) -> 158.28433 | AK6: =IF(P6=0,0,AA6/P6) -> 409.81503 | AL6: {=_xlfn.IFS(R6=0,AE6,R6<0,AE6/-R6,R6>0,AE6/R6)} -> 358.86317 | AM6: =IF(AG6=0,0,AL6/AG6) -> 0.18733927 | AN6: =IF(AH6=0,0,AL6/AH6) -> 2.9154535 | AP6: =AL6*C6 -> 0
A7: 2676784181 | B7: qs коричневые | H7: 117.24 | I7: =C7*H7 -> 0 | K7: =ЯНВАРЬ!K7+ФЕВРАЛЬ!K7+МАРТ!K7 -> 165 | N7: =K7/$O$1 -> #DIV/0! | O7: =R7/$O$1 -> #DIV/0! | P7: =ЯНВАРЬ!P7+ФЕВРАЛЬ!P7+МАРТ!P7 -> 154 | Q7: =ЯНВАРЬ!Q7+ФЕВРАЛЬ!Q7+МАРТ!Q7 -> 7 | R7: =P7-Q7 -> 147 | S7: =ЯНВАРЬ!S7+ФЕВРАЛЬ!S7+МАРТ!S7 -> 327803 | T7: =ЯНВАРЬ!T7+ФЕВРАЛЬ!T7+МАРТ!T7 -> -15124 | U7: =S7+T7 -> 312679 | V7: =U7/$U$24 -> 0.10931995 | W7: =R7*H7 -> 17234.28 | X7: =ЯНВАРЬ!X7+ФЕВРАЛЬ!X7+МАРТ!X7 -> 134451.97 | Y7: =IF(U7=0,0,X7/U7) -> 0.43 | Z7: =ЯНВАРЬ!Z7+ФЕВРАЛЬ!Z7+МАРТ!Z7 -> 29128.16 | AA7: =ЯНВАРЬ!AA7+ФЕВРАЛЬ!AA7+МАРТ!AA7 -> 85193.039 | AD7: =ЯНВАРЬ!AD7+ФЕВРАЛЬ!AD7+МАРТ!AD7 -> 1293.3873 | AE7: =U7-W7-X7-Z7-AA7-AB7-AC7-AD7 -> 45378.163 | AG7: =IF(R7=0,0,U7/R7) -> 2127.068 | AH7: =H7 -> 117.24 | AI7: =IF(R7=0,0,X7/R7) -> 914.63925 | AJ7: =IF(P7=0,Z7/1,Z7/P7) -> 189.1439 | AK7: =IF(P7=0,0,AA7/P7) -> 553.20156 | AL7: {=_xlfn.IFS(R7=0,AE7,R7<0,AE7/-R7,R7>0,AE7/R7)} -> 308.69499 | AM7: =IF(AG7=0,0,AL7/AG7) -> 0.14512699 | AN7: =IF(AH7=0,0,AL7/AH7) -> 2.6330176 | AP7: =AL7*C7 -> 0
A8: 2676783005 | B8: MR8854 C2 | H8: 169.89 | I8: =C8*H8 -> 0 | K8: =ЯНВАРЬ!K8+ФЕВРАЛЬ!K8+МАРТ!K8 -> 210 | N8: =K8/$O$1 -> #DIV/0! | O8: =R8/$O$1 -> #DIV/0! | P8: =ЯНВАРЬ!P8+ФЕВРАЛЬ!P8+МАРТ!P8 -> 171 | Q8: =ЯНВАРЬ!Q8+ФЕВРАЛЬ!Q8+МАРТ!Q8 -> 6 | R8: =P8-Q8 -> 165 | S8: =ЯНВАРЬ!S8+ФЕВРАЛЬ!S8+МАРТ!S8 -> 371416 | T8: =ЯНВАРЬ!T8+ФЕВРАЛЬ!T8+МАРТ!T8 -> -12741 | U8: =S8+T8 -> 358675 | V8: =U8/$U$24 -> 0.12540124 | W8: =R8*H8 -> 28031.85 | X8: =ЯНВАРЬ!X8+ФЕВРАЛЬ!X8+МАРТ!X8 -> 154230.25 | Y8: =IF(U8=0,0,X8/U8) -> 0.43 | Z8: =ЯНВАРЬ!Z8+ФЕВРАЛЬ!Z8+МАРТ!Z8 -> 29993.09 | AA8: =ЯНВАРЬ!AA8+ФЕВРАЛЬ!AA8+МАРТ!AA8 -> 65905.821 | AD8: =ЯНВАРЬ!AD8+ФЕВРАЛЬ!AD8+МАРТ!AD8 -> 1510.2843 | AE8: =U8-W8-X8-Z8-AA8-AB8-AC8-AD8 -> 79003.704 | AG8: =IF(R8=0,0,U8/R8) -> 2173.7879 | AH8: =H8 -> 169.89 | AI8: =IF(R8=0,0,X8/R8) -> 934.72879 | AJ8: =IF(P8=0,Z8/1,Z8/P8) -> 175.39819 | AK8: =IF(P8=0,0,AA8/P8) -> 385.41416 | AL8: {=_xlfn.IFS(R8=0,AE8,R8<0,AE8/-R8,R8>0,AE8/R8)} -> 478.81033 | AM8: =IF(AG8=0,0,AL8/AG8) -> 0.22026543 | AN8: =IF(AH8=0,0,AL8/AH8) -> 2.818355 | AP8: =AL8*C8 -> 0
A9: 3405092860 | B9: th черн | H9: 123 | I9: =C9*H9 -> 0 | K9: =ЯНВАРЬ!K9+ФЕВРАЛЬ!K9+МАРТ!K9 -> 29 | N9: =K9/$O$1 -> #DIV/0! | O9: =R9/$O$1 -> #DIV/0! | P9: =ЯНВАРЬ!P9+ФЕВРАЛЬ!P9+МАРТ!P9 -> 28 | Q9: =ЯНВАРЬ!Q9+ФЕВРАЛЬ!Q9+МАРТ!Q9 -> 3 | R9: =P9-Q9 -> 25 | S9: =ЯНВАРЬ!S9+ФЕВРАЛЬ!S9+МАРТ!S9 -> 64081 | T9: =ЯНВАРЬ!T9+ФЕВРАЛЬ!T9+МАРТ!T9 -> -6800 | U9: =S9+T9 -> 57281 | V9: =U9/$U$24 -> 0.020026788 | W9: =R9*H9 -> 3075 | X9: =ЯНВАРЬ!X9+ФЕВРАЛЬ!X9+МАРТ!X9 -> 24630.83 | Y9: =IF(U9=0,0,X9/U9) -> 0.43 | Z9: =ЯНВАРЬ!Z9+ФЕВРАЛЬ!Z9+МАРТ!Z9 -> 8115.92 | AA9: =ЯНВАРЬ!AA9+ФЕВРАЛЬ!AA9+МАРТ!AA9 -> 9515.8467 | AD9: =ЯНВАРЬ!AD9+ФЕВРАЛЬ!AD9+МАРТ!AD9 -> 242.25711 | AE9: =U9-W9-X9-Z9-AA9-AB9-AC9-AD9 -> 11701.146 | AG9: =IF(R9=0,0,U9/R9) -> 2291.24 | AH9: =H9 -> 123 | AI9: =IF(R9=0,0,X9/R9) -> 985.2332 | AJ9: =IF(P9=0,Z9/1,Z9/P9) -> 289.85429 | AK9: =IF(P9=0,0,AA9/P9) -> 339.85167 | AL9: {=_xlfn.IFS(R9=0,AE9,R9<0,AE9/-R9,R9>0,AE9/R9)} -> 468.04585 | AM9: =IF(AG9=0,0,AL9/AG9) -> 0.20427622 | AN9: =IF(AH9=0,0,AL9/AH9) -> 3.8052508 | AP9: =AL9*C9 -> 0
A10: 3405092836 | B10: th син | H10: 123 | I10: =C10*H10 -> 0 | K10: =ЯНВАРЬ!K10+ФЕВРАЛЬ!K10+МАРТ!K10 -> 26 | N10: =K10/$O$1 -> #DIV/0! | O10: =R10/$O$1 -> #DIV/0! | P10: =ЯНВАРЬ!P10+ФЕВРАЛЬ!P10+МАРТ!P10 -> 39 | Q10: =ЯНВАРЬ!Q10+ФЕВРАЛЬ!Q10+МАРТ!Q10 -> 0 | R10: =P10-Q10 -> 39 | S10: =ЯНВАРЬ!S10+ФЕВРАЛЬ!S10+МАРТ!S10 -> 86586 | T10: =ЯНВАРЬ!T10+ФЕВРАЛЬ!T10+МАРТ!T10 -> 0 | U10: =S10+T10 -> 86586 | V10: =U10/$U$24 -> 0.030272507 | W10: =R10*H10 -> 4797 | X10: =ЯНВАРЬ!X10+ФЕВРАЛЬ!X10+МАРТ!X10 -> 37231.98 | Y10: =IF(U10=0,0,X10/U10) -> 0.43 | Z10: =ЯНВАРЬ!Z10+ФЕВРАЛЬ!Z10+МАРТ!Z10 -> 8214.78 | AA10: =ЯНВАРЬ!AA10+ФЕВРАЛЬ!AA10+МАРТ!AA10 -> 17478.823 | AD10: =ЯНВАРЬ!AD10+ФЕВРАЛЬ!AD10+МАРТ!AD10 -> 371.72709 | AE10: =U10-W10-X10-Z10-AA10-AB10-AC10-AD10 -> 18491.69 | AG10: =IF(R10=0,0,U10/R10) -> 2220.1538 | AH10: =H10 -> 123 | AI10: =IF(R10=0,0,X10/R10) -> 954.66615 | AJ10: =IF(P10=0,Z10/1,Z10/P10) -> 210.63538 | AK10: =IF(P10=0,0,AA10/P10) -> 448.17495 | AL10: {=_xlfn.IFS(R10=0,AE10,R10<0,AE10/-R10,R10>0,AE10/R10)} -> 474.1459 | AM10: =IF(AG10=0,0,AL10/AG10) -> 0.21356443 | AN10: =IF(AH10=0,0,AL10/AH10) -> 3.8548447 | AP10: =AL10*C10 -> 0
A11: 3064346962 | B11: th желт | H11: 123 | I11: =C11*H11 -> 0 | K11: =ЯНВАРЬ!K11+ФЕВРАЛЬ!K11+МАРТ!K11 -> 282 | N11: =K11/$O$1 -> #DIV/0! | O11: =R11/$O$1 -> #DIV/0! | P11: =ЯНВАРЬ!P11+ФЕВРАЛЬ!P11+МАРТ!P11 -> 299 | Q11: =ЯНВАРЬ!Q11+ФЕВРАЛЬ!Q11+МАРТ!Q11 -> 10 | R11: =P11-Q11 -> 289 | S11: =ЯНВАРЬ!S11+ФЕВРАЛЬ!S11+МАРТ!S11 -> 568302 | T11: =ЯНВАРЬ!T11+ФЕВРАЛЬ!T11+МАРТ!T11 -> -19758 | U11: =S11+T11 -> 548544 | V11: =U11/$U$24 -> 0.19178392 | W11: =R11*H11 -> 35547 | X11: =ЯНВАРЬ!X11+ФЕВРАЛЬ!X11+МАРТ!X11 -> 235873.92 | Y11: =IF(U11=0,0,X11/U11) -> 0.43 | Z11: =ЯНВАРЬ!Z11+ФЕВРАЛЬ!Z11+МАРТ!Z11 -> 56505.69 | AA11: =ЯНВАРЬ!AA11+ФЕВРАЛЬ!AA11+МАРТ!AA11 -> 132413.63 | AD11: =ЯНВАРЬ!AD11+ФЕВРАЛЬ!AD11+МАРТ!AD11 -> 2224.7925 | AE11: =U11-W11-X11-Z11-AA11-AB11-AC11-AD11 -> 85978.972 | AG11: =IF(R11=0,0,U11/R11) -> 1898.0761 | AH11: =H11 -> 123 | AI11: =IF(R11=0,0,X11/R11) -> 816.17273 | AJ11: =IF(P11=0,Z11/1,Z11/P11) -> 188.98224 | AK11: =IF(P11=0,0,AA11/P11) -> 442.85493 | AL11: {=_xlfn.IFS(R11=0,AE11,R11<0,AE11/-R11,R11>0,AE11/R11)} -> 297.50509 | AM11: =IF(AG11=0,0,AL11/AG11) -> 0.15674034 | AN11: =IF(AH11=0,0,AL11/AH11) -> 2.4187406 | AP11: =AL11*C11 -> 0
A12: 3405092873 | B12: th коричн | H12: 117 | I12: =C12*H12 -> 0 | K12: =ЯНВАРЬ!K12+ФЕВРАЛЬ!K12+МАРТ!K12 -> 30 | N12: =K12/$O$1 -> #DIV/0! | O12: =R12/$O$1 -> #DIV/0! | P12: =ЯНВАРЬ!P12+ФЕВРАЛЬ!P12+МАРТ!P12 -> 37 | Q12: =ЯНВАРЬ!Q12+ФЕВРАЛЬ!Q12+МАРТ!Q12 -> 1 | R12: =P12-Q12 -> 36 | S12: =ЯНВАРЬ!S12+ФЕВРАЛЬ!S12+МАРТ!S12 -> 86013 | T12: =ЯНВАРЬ!T12+ФЕВРАЛЬ!T12+МАРТ!T12 -> -2393 | U12: =S12+T12 -> 83620 | V12: =U12/$U$24 -> 0.029235524 | W12: =R12*H12 -> 4212 | X12: =ЯНВАРЬ!X12+ФЕВРАЛЬ!X12+МАРТ!X12 -> 35956.6 | Y12: =IF(U12=0,0,X12/U12) -> 0.43 | Z12: =ЯНВАРЬ!Z12+ФЕВРАЛЬ!Z12+МАРТ!Z12 -> 8147.35 | AA12: =ЯНВАРЬ!AA12+ФЕВРАЛЬ!AA12+МАРТ!AA12 -> 26302.936 | AD12: =ЯНВАРЬ!AD12+ФЕВРАЛЬ!AD12+МАРТ!AD12 -> 356.15875 | AE12: =U12-W12-X12-Z12-AA12-AB12-AC12-AD12 -> 8644.9553 | AG12: =IF(R12=0,0,U12/R12) -> 2322.7778 | AH12: =H12 -> 117 | AI12: =IF(R12=0,0,X12/R12) -> 998.79444 | AJ12: =IF(P12=0,Z12/1,Z12/P12) -> 220.19865 | AK12: =IF(P12=0,0,AA12/P12) -> 710.89016 | AL12: {=_xlfn.IFS(R12=0,AE12,R12<0,AE12/-R12,R12>0,AE12/R12)} -> 240.13765 | AM12: =IF(AG12=0,0,AL12/AG12) -> 0.10338382 | AN12: =IF(AH12=0,0,AL12/AH12) -> 2.0524585 | AP12: =AL12*C12 -> 0
A13: 3405092993 | B13: flip черный | H13: 123 | I13: =C13*H13 -> 0 | K13: =ЯНВАРЬ!K13+ФЕВРАЛЬ!K13+МАРТ!K13 -> 42 | N13: =K13/$O$1 -> #DIV/0! | O13: =R13/$O$1 -> #DIV/0! | P13: =ЯНВАРЬ!P13+ФЕВРАЛЬ!P13+МАРТ!P13 -> 66 | Q13: =ЯНВАРЬ!Q13+ФЕВРАЛЬ!Q13+МАРТ!Q13 -> 3 | R13: =P13-Q13 -> 63 | S13: =ЯНВАРЬ!S13+ФЕВРАЛЬ!S13+МАРТ!S13 -> 155622 | T13: =ЯНВАРЬ!T13+ФЕВРАЛЬ!T13+МАРТ!T13 -> -7200 | U13: =S13+T13 -> 148422 | V13: =U13/$U$24 -> 0.051891831 | W13: =R13*H13 -> 7749 | X13: =ЯНВАРЬ!X13+ФЕВРАЛЬ!X13+МАРТ!X13 -> 63821.46 | Y13: =IF(U13=0,0,X13/U13) -> 0.43 | Z13: =ЯНВАРЬ!Z13+ФЕВРАЛЬ!Z13+МАРТ!Z13 -> 15006.48 | AA13: =ЯНВАРЬ!AA13+ФЕВРАЛЬ!AA13+МАРТ!AA13 -> 30282.255 | AD13: =ЯНВАРЬ!AD13+ФЕВРАЛЬ!AD13+МАРТ!AD13 -> 629.51585 | AE13: =U13-W13-X13-Z13-AA13-AB13-AC13-AD13 -> 30933.289 | AG13: =IF(R13=0,0,U13/R13) -> 2355.9048 | AH13: =H13 -> 123 | AI13: =IF(R13=0,0,X13/R13) -> 1013.039 | AJ13: =IF(P13=0,Z13/1,Z13/P13) -> 227.37091 | AK13: =IF(P13=0,0,AA13/P13) -> 458.82204 | AL13: {=_xlfn.IFS(R13=0,AE13,R13<0,AE13/-R13,R13>0,AE13/R13)} -> 491.00459 | AM13: =IF(AG13=0,0,AL13/AG13) -> 0.20841445 | AN13: =IF(AH13=0,0,AL13/AH13) -> 3.9919073 | AP13: =AL13*C13 -> 0
