Workbook

Sheet Сводная
A1: Период | D1: Итого к перечислению на счет, руб | E1: шт. | H1: Выручка | K1: Себестоимость продаж | L1: Логистика | M1: Комиссия | N1: Хранение | O1: Платная приемка | P1: Штрафы | Q1: Реклама Ozon | R1: Услуги партнёров | S1: Другие услуги и штрафы | T1: Услуги FBO | U1: Компенсировано | V1: Пополнение рекламного кабинета | W1: ЕАЭС | X1: Налог | Y1: Прибыль до вычета налогов | Z1: Прибыль после вычета налогов | AA1: Итог месяц | AB1: % Cебестоимости | AC1: Маржинальность, % | AD1: Рентабельность, % | AE1: Доля рекламы, %
A2: Месяц | B2: Даты | C2: Нед | E2: Заказы | F2: Продажи | G2: Возвраты | H2: Продажи | I2: Возвраты | J2: Общая
A3: Декабрь | B3: 29-31.12 | C3: 1 | D3: =J3-SUM(L3:T3)+U3+V3 -> 36605.68 | E3: ='Юнит 29-31.12'!K$24 -> 53 | F3: ='Юнит 29-31.12'!P$24 -> 90 | G3: ='Юнит 29-31.12'!Q$24 -> 3 | H3: ='Юнит 29-31.12'!S$24 -> 146316 | I3: ='Юнит 29-31.12'!T$24 -> -4863 | J3: =H3+I3 -> 141453 | K3: ='Юнит 29-31.12'!W$24 -> 10769.4 | L3: ='Юнит 29-31.12'!Z$24 -> 13464.42 | M3: ='Юнит 29-31.12'!X$24 -> 60824.79 | Q3: ='Юнит 29-31.12'!AA$24 -> 26762.42 | R3: 1624.89 | T3: 2170.8 | Y3: =J3-SUM(L3:T3)-K3-V3+U3+W3 -> 25836.28 | Z3: =Y3-X3 -> 25836.28
A4: Январь | B4: 01-04.01 | C4: 1 | D4: =J4-SUM(L4:T4)+U4+V4 -> 1074.71 | E4: ='Юнит 01-04.01'!K$24 -> 122 | F4: ='Юнит 01-04.01'!P$24 -> 51 | G4: ='Юнит 01-04.01'!Q$24 -> 1 | H4: ='Юнит 01-04.01'!S$24 -> 85937 | I4: ='Юнит 01-04.01'!T$24 -> -1600 | J4: =H4+I4 -> 84337 | K4: ='Юнит 01-04.01'!W$24 -> 6252.96 | L4: ='Юнит 01-04.01'!Z$24 -> 8548.62 | M4: ='Юнит 01-04.01'!X$24 -> 36264.91 | Q4: ='Юнит 01-04.01'!AA$24 -> 36772.95 | R4: 1675.81 | W4: 5252 | X4: =3481.9416*J4/SUM($J$4:$J$8) -> 322.35231 | Y4: =J4-SUM(L4:T4)-K4-V4+U4+W4 -> 73.75 | Z4: =Y4-X4 -> -248.60231 | AA4: =SUM(Z4:Z8) -> 49559.258 | AB4: =K4/J4 -> 0.074142547 | AC4: =Z4/K4 -> -0.039757541 | AD4: =Z4/J4 -> -0.0029477253 | AE4: =Q4/J4 -> 0.43602393
B5: 05-11.01 | C5: 2 | D5: =J5-SUM(L5:T5)+U5+V5 -> 57707.57 | E5: ='Юнит 05-11.01'!K$24 -> 183 | F5: ='Юнит 05-11.01'!P$24 -> 168 | G5: ='Юнит 05-11.01'!Q$24 -> 8 | H5: ='Юнит 05-11.01'!S$24 -> 277715 | I5: ='Юнит 05-11.01'!T$24 -> -13822 | J5: =H5+I5 -> 263893 | K5: ='Юнит 05-11.01'!W$24 -> 20205.96 | L5: ='Юнит 05-11.01'!Z$24 -> 28076.33 | M5: ='Юнит 05-11.01'!X$24 -> 113473.99 | Q5: ='Юнит 05-11.01'!AA$24 -> 56365.38 | R5: 4144.33 | S5: 75 | T5: 4050.4 | X5: =3481.9416*J5/SUM($J$4:$J$8) -> 1008.65 | Y5: =J5-SUM(L5:T5)-K5-V5+U5+W5 -> 37501.61 | Z5: =Y5-X5 -> 36492.96 | AB5: =K5/J5 -> 0.076568761 | AC5: =Z5/K5 -> 1.8060493 | AD5: =Z5/J5 -> 0.13828696 | AE5: =Q5/J5 -> 0.2135918
B6: 12-18.01 | C6: 3 | D6: =J6-SUM(L6:T6)+U6+V6 -> 36064.15 | E6: ='Юнит 12-18.01'!K$24 -> 144 | F6: ='Юнит 12-18.01'!P$24 -> 122 | G6: ='Юнит 12-18.01'!Q$24 -> 2 | H6: ='Юнит 12-18.01'!S$24 -> 211029 | I6: ='Юнит 12-18.01'!T$24 -> -3221 | J6: =H6+I6 -> 207808 | K6: ='Юнит 12-18.01'!W$24 -> 15093.09 | L6: ='Юнит 12-18.01'!Z$24 -> 24172.28 | M6: ='Юнит 12-18.01'!X$24 -> 89357.44 | Q6: ='Юнит 12-18.01'!AA$24 -> 53249.12 | R6: 4025.01 | S6: 0 | T6: 940 | W6: 5135 | X6: =3481.9416*J6/SUM($J$4:$J$8) -> 794.28233 | Y6: =J6-SUM(L6:T6)-K6-V6+U6+W6 -> 26106.06 | Z6: =Y6-X6 -> 25311.778 | AB6: =K6/J6 -> 0.072629976 | AC6: =Z6/K6 -> 1.6770441 | AD6: =Z6/J6 -> 0.12180367 | AE6: =Q6/J6 -> 0.25624192
B7: 19-25.01 | C7: 4 | D7: =J7-SUM(L7:T7)+U7+V7 -> 34413.47 | E7: ='Юнит 19-25.01'!K$24 -> 154 | F7: ='Юнит 19-25.01'!P$24 -> 91 | G7: ='Юнит 19-25.01'!Q$24 -> 2 | H7: ='Юнит 19-25.01'!S$24 -> 161208 | I7: ='Юнит 19-25.01'!T$24 -> -3229 | J7: =H7+I7 -> 157979 | K7: ='Юнит 19-25.01'!W$24 -> 11132.49 | L7: ='Юнит 19-25.01'!Z$24 -> 16989.46 | M7: ='Юнит 19-25.01'!X$24 -> 67930.97 | Q7: ='Юнит 19-25.01'!AA$24 -> 42151.21 | R7: 3468.89 | S7: 25 | V7: 7000 | X7: =3481.9416*J7/SUM($J$4:$J$8) -> 603.82627 | Y7: =J7-SUM(L7:T7)-K7-V7+U7+W7 -> 9280.98 | Z7: =Y7-X7 -> 8677.1537 | AB7: =K7/J7 -> 0.070468163 | AC7: =Z7/K7 -> 0.77944411 | AD7: =Z7/J7 -> 0.054925995 | AE7: =Q7/J7 -> 0.26681527
B8: 26-31.01 | C8: 5 | D8: =J8-SUM(L8:T8)+U8+V8 -> -6034.71 | E8: ='Юнит 26-31.01'!K$24 -> 200 | F8: ='Юнит 26-31.01'!P$24 -> 112 | G8: ='Юнит 26-31.01'!Q$24 -> 2 | H8: ='Юнит 26-31.01'!S$24 -> 200558 | I8: ='Юнит 26-31.01'!T$24 -> -3595 | J8: =H8+I8 -> 196963 | K8: ='Юнит 26-31.01'!W$24 -> 13886.49 | L8: ='Юнит 26-31.01'!Z$24 -> 20843.55 | M8: ='Юнит 26-31.01'!X$24 -> 84694.09 | Q8: ='Юнит 26-31.01'!AA$24 -> 50770.67 | R8: 3661.19 | S8: 150 | T8: 43993.6 | U8: 1115.39 | X8: =3481.9416*J8/SUM($J$4:$J$8) -> 752.83065 | Y8: =J8-SUM(L8:T8)-K8-V8+U8+W8 -> -19921.2 | Z8: =Y8-X8 -> -20674.031 | AB8: =(K8+K9)/(J8+J9) -> 0.070282074 | AC8: =(Z8+Z9)/(K8+K9) -> -0.67605169 | AD8: =(Z8+Z9)/(J8+J9) -> -0.047514315 | AE8: =(Q8+Q9)/(J8+J9) -> 0.25406002
A9: Февраль | B9: 01.02-01.02 | C9: 5 | D9: =J9-SUM(L9:T9)+U9+V9 -> 7323.99 | E9: ='Юнит 01.02'!K$24 -> 36 | F9: ='Юнит 01.02'!P$24 -> 19 | G9: ='Юнит 01.02'!Q$24 -> 1 | H9: ='Юнит 01.02'!S$24 -> 34372 | I9: ='Юнит 01.02'!T$24 -> -1750 | J9: =H9+I9 -> 32622 | K9: ='Юнит 01.02'!W$24 -> 2249.22 | L9: ='Юнит 01.02'!Z$24 -> 3179.52 | M9: ='Юнит 01.02'!X$24 -> 14027.46 | Q9: ='Юнит 01.02'!AA$24 -> 7557.7 | R9: 533.33 | W9: 4831 | X9: =5201.48*J9/SUM($J$9:$J$13) -> 140.3134 | Y9: =J9-SUM(L9:T9)-K9-V9+U9+W9 -> 9905.77 | Z9: =Y9-X9 -> 9765.4566 | AA9: =SUM(Z9:Z13) -> 174317.71
B10: 02.02-08.02 | C10: 6 | D10: =J10-SUM(L10:T10)+U10+V10 -> 40049.95 | E10: ='Юнит 02-08.02'!K$24 -> 225 | F10: ='Юнит 02-08.02'!P$24 -> 167 | G10: ='Юнит 02-08.02'!Q$24 -> 11 | H10: ='Юнит 02-08.02'!S$24 -> 323134 | I10: ='Юнит 02-08.02'!T$24 -> -22524 | J10: =H10+I10 -> 300610 | K10: ='Юнит 02-08.02'!W$24 -> 19848.12 | L10: ='Юнит 02-08.02'!Z$24 -> 31123.53 | M10: ='Юнит 02-08.02'!X$24 -> 129262.3 | Q10: ='Юнит 02-08.02'!AA$24 -> 66736.42 | R10: 5825.9 | T10: 27611.9 | X10: =5201.48*J10/SUM($J$9:$J$13) -> 1292.9806 | Y10: =J10-SUM(L10:T10)-K10-V10+U10+W10 -> 20201.83 | Z10: =Y10-X10 -> 18908.849 | AB10: =K10/J10 -> 0.066026147 | AC10: =Z10/K10 -> 0.9526771 | AD10: =Z10/J10 -> 0.062901598 | AE10: =Q10/J10 -> 0.22200333
B11: 09-15.02 | C11: 7 | D11: =J11-SUM(L11:T11)+U11+V11 -> 62513.5 | E11: ='Юнит 09-15.02'!K$24 -> 240 | F11: ='Юнит 09-15.02'!P$24 -> 125 | G11: ='Юнит 09-15.02'!Q$24 -> 4 | H11: ='Юнит 09-15.02'!S$24 -> 282164 | I11: ='Юнит 09-15.02'!T$24 -> -9000 | J11: =H11+I11 -> 273164 | K11: ='Юнит 09-15.02'!W$24 -> 15306.15 | L11: ='Юнит 09-15.02'!Z$24 -> 24192.27 | M11: ='Юнит 09-15.02'!X$24 -> 117460.52 | Q11: ='Юнит 09-15.02'!AA$24 -> 61070.11 | R11: 5828.6 | S11: 175 | T11: 1924 | X11: =5201.48*J11/SUM($J$9:$J$13) -> 1174.9301 | Y11: =J11-SUM(L11:T11)-K11-V11+U11+W11 -> 47207.35 | Z11: =Y11-X11 -> 46032.42 | AB11: =K11/J11 -> 0.056032823 | AC11: =Z11/K11 -> 3.007446 | AD11: =Z11/J11 -> 0.16851569 | AE11: =Q11/J11 -> 0.22356573
B12: 16-22.02 | C12: 8 | D12: =J12-SUM(L12:T12)+U12+V12 -> 82376.34 | E12: ='Юнит 16-22.02'!K$24 -> 298 | F12: ='Юнит 16-22.02'!P$24 -> 161 | G12: ='Юнит 16-22.02'!Q$24 -> 8 | H12: ='Юнит 16-22.02'!S$24 -> 373392 | I12: ='Юнит 16-22.02'!T$24 -> -18750 | J12: =H12+I12 -> 354642 | K12: ='Юнит 16-22.02'!W$24 -> 19197.06 | L12: ='Юнит 16-22.02'!Z$24 -> 31757.74 | M12: ='Юнит 16-22.02'!X$24 -> 152496.06 | Q12: ='Юнит 16-22.02'!AA$24 -> 79962.77 | R12: 8049.09 | W12: 4347 | X12: =5201.48*J12/SUM($J$9:$J$13) -> 1525.3824 | Y12: =J12-SUM(L12:T12)-K12-V12+U12+W12 -> 67526.28 | Z12: =Y12-X12 -> 66000.898 | AB12: =K12/J12 -> 0.054130814 | AC12: =Z12/K12 -> 3.4380732 | AD12: =Z12/J12 -> 0.1861057 | AE12: =Q12/J12 -> 0.22547462
B13: 23-28.02 | C13: 9 | D13: =J13-SUM(L13:T13)+U13+V13 -> 47866.26 | E13: ='Юнит 23-28.02'!K$24 -> 159 | F13: ='Юнит 23-28.02'!P$24 -> 107 | G13: ='Юнит 23-28.02'!Q$24 -> 6 | H13: ='Юнит 23-28.02'!S$24 -> 262374 | I13: ='Юнит 23-28.02'!T$24 -> -14100 | J13: =H13+I13 -> 248274 | K13: ='Юнит 23-28.02'!W$24 -> 13188.3 | L13: ='Юнит 23-28.02'!Z$24 -> 25365.95 | M13: ='Юнит 23-28.02'!X$24 -> 106757.82 | Q13: ='Юнит 23-28.02'!AA$24 -> 64457.72 | R13: 6407.47 | U13: 2581.22 | X13: =5201.48*J13/SUM($J$9:$J$13) -> 1067.8735 | Y13: =J13-SUM(L13:T13)-K13-V13+U13+W13 -> 34677.96 | Z13: =Y13-X13 -> 33610.086 | AB13: =(K13+K14)/(J13+J14) -> 0.052676864 | AC13: =(Z13+Z14)/(K13+K14) -> 2.4578024 | AD13: =(Z13+Z14)/(J13+J14) -> 0.12946932 | AE13: =(Q13+Q14)/(J13+J14) -> 0.26870709
A14: Март | B14: 46082 | C14: 9 | D14: =J14-SUM(L14:T14)+U14+V14 -> 2695.31 | E14: ='Юнит 01.03'!K$24 -> 36 | F14: ='Юнит 01.03'!P$24 -> 13 | G14: ='Юнит 01.03'!Q$24 -> 1 | H14: ='Юнит 01.03'!S$24 -> 32560 | I14: ='Юнит 01.03'!T$24 -> -2400 | J14: =H14+I14 -> 30160 | K14: ='Юнит 01.03'!W$24 -> 1478.73 | L14: ='Юнит 01.03'!Z$24 -> 3251.78 | M14: ='Юнит 01.03'!X$24 -> 12968.8 | Q14: ='Юнит 01.03'!AA$24 -> 10359.47 | R14: 884.64 | W14: 1350 | X14: =3397.77*J14/SUM($J$14:$J$19) -> 128.00473 | Y14: =J14-SUM(L14:T14)-K14-V14+U14+W14 -> 2566.58 | Z14: =Y14-X14 -> 2438.5753 | AA14: =SUM(Z14:Z19) -> 141772.43
B15: 02.03-08.03 | C15: 10 | D15: =J15-SUM(L15:T15)+U15+V15 -> 31422.07 | E15: ='Юнит 02-08.03'!K$24 -> 179 | F15: ='Юнит 02-08.03'!P$24 -> 93 | G15: ='Юнит 02-08.03'!Q$24 -> 4 | H15: ='Юнит 02-08.03'!S$24 -> 221439 | I15: ='Юнит 02-08.03'!T$24 -> -9910 | J15: =H15+I15 -> 211529 | K15: ='Юнит 02-08.03'!W$24 -> 11497.53 | L15: ='Юнит 02-08.03'!Z$24 -> 18516.49 | M15: ='Юнит 02-08.03'!X$24 -> 90957.47 | Q15: ='Юнит 02-08.03'!AA$24 -> 65685.91 | R15: 4902.06 | S15: 45 | T15: 0 | X15: =3397.77*J15/SUM($J$14:$J$19) -> 897.76895 | Y15: =J15-SUM(L15:T15)-K15-V15+U15+W15 -> 19924.54 | Z15: =Y15-X15 -> 19026.771 | AB15: =K15/J15 -> 0.054354391 | AC15: =Z15/K15 -> 1.6548573 | AD15: =Z15/J15 -> 0.089948759 | AE15: =Q15/J15 -> 0.3105291
B16: 09-15.03 | C16: 11 | D16: =J16-SUM(L16:T16)+U16+V16 -> 61950.07 | E16: ='Юнит 09-15.03'!K$24 -> 156 | F16: ='Юнит 09-15.03'!P$24 -> 97 | G16: ='Юнит 09-15.03'!Q$24 -> 5 | H16: ='Юнит 09-15.03'!S$24 -> 240785 | I16: ='Юнит 09-15.03'!T$24 -> -11873 | J16: =H16+I16 -> 228912 | K16: ='Юнит 09-15.03'!W$24 -> 12514.02 | L16: ='Юнит 09-15.03'!Z$24 -> 20045.39 | M16: ='Юнит 09-15.03'!X$24 -> 98432.16 | Q16: ='Юнит 09-15.03'!AA$24 -> 42625.75 | R16: 5778.63 | S16: 80 | T16: 0 | X16: =3397.77*J16/SUM($J$14:$J$19) -> 971.54568 | Y16: =J16-SUM(L16:T16)-K16-V16+U16+W16 -> 49436.05 | Z16: =Y16-X16 -> 48464.504 | AB16: =K16/J16 -> 0.054667383 | AC16: =Z16/K16 -> 3.8728166 | AD16: =Z16/J16 -> 0.21171675 | AE16: =Q16/J16 -> 0.1862102
B17: 16-22.03 | C17: 12 | D17: =J17-SUM(L17:T17)+U17+V17 -> 41865.51 | E17: ='Юнит 16-22.03'!K$24 -> 109 | F17: ='Юнит 16-22.03'!P$24 -> 61 | G17: ='Юнит 16-22.03'!Q$24 -> 2 | H17: ='Юнит 16-22.03'!S$24 -> 148955 | I17: ='Юнит 16-22.03'!T$24 -> -4939 | J17: =H17+I17 -> 144016 | K17: ='Юнит 16-22.03'!W$24 -> 8173.8 | L17: ='Юнит 16-22.03'!Z$24 -> 13537.32 | M17: ='Юнит 16-22.03'!X$24 -> 61926.88 | Q17: ='Юнит 16-22.03'!AA$24 -> 22870.89 | R17: 3785.4 | S17: 30 | T17: 0 | W17: 1404 | X17: =3397.77*J17/SUM($J$14:$J$19) -> 611.23105 | Y17: =J17-SUM(L17:T17)-K17-V17+U17+W17 -> 35095.71 | Z17: =Y17-X17 -> 34484.479 | AB17: =K17/J17 -> 0.056756194 | AC17: =Z17/K17 -> 4.2189042 | AD17: =Z17/J17 -> 0.23944894 | AE17: =Q17/J17 -> 0.15880798
B18: 23-29.03 | C18: 13 | D18: =J18-SUM(L18:T18)+U18+V18 -> 31815.03 | E18: ='Юнит 23-29.03'!K$24 -> 136 | F18: ='Юнит 23-29.03'!P$24 -> 59 | G18: ='Юнит 23-29.03'!Q$24 -> 5 | H18: ='Юнит 23-29.03'!S$24 -> 135999 | I18: ='Юнит 23-29.03'!T$24 -> -10689 | J18: =H18+I18 -> 125310 | K18: ='Юнит 23-29.03'!W$24 -> 7248.21 | L18: ='Юнит 23-29.03'!Z$24 -> 10759.15 | M18: ='Юнит 23-29.03'!X$24 -> 53883.3 | Q18: ='Юнит 23-29.03'!AA$24 -> 26466.97 | R18: 2330.55 | S18: 55 | T18: 0 | X18: =3397.77*J18/SUM($J$14:$J$19) -> 531.83926 | Y18: =J18-SUM(L18:T18)-K18-V18+U18+W18 -> 24566.82 | Z18: =Y18-X18 -> 24034.981 | AB18: =K18/J18 -> 0.057842231 | AC18: =Z18/K18 -> 3.3159885 | AD18: =Z18/J18 -> 0.19180417 | AE18: =Q18/J18 -> 0.21121195
B19: 30-31.03 | C19: 14 | D19: =J19-SUM(L19:T19)+U19+V19 -> 17004.19 | E19: ='Юнит 30-31.03'!K$24 -> 52 | F19: ='Юнит 30-31.03'!P$24 -> 26 | G19: ='Юнит 30-31.03'!Q$24 -> 0 | H19: ='Юнит 30-31.03'!S$24 -> 60643 | I19: ='Юнит 30-31.03'!T$24 -> 0 | J19: =H19+I19 -> 60643 | K19: ='Юнит 30-31.03'!W$24 -> 3423.69 | L19: ='Юнит 30-31.03'!Z$24 -> 4441.24 | M19: ='Юнит 30-31.03'!X$24 -> 26076.49 | Q19: ='Юнит 30-31.03'!AA$24 -> 11946.08 | R19: 1130.4 | S19: 15 | T19: 29.6 | X19: =3397.77*J19/SUM($J$14:$J$19) -> 257.38032 | Y19: =J19-SUM(L19:T19)-K19-V19+U19+W19 -> 13580.5 | Z19: =Y19-X19 -> 13323.12 | AB19: =(K19+K20)/(J19+J20) -> 0.052990653 | AC19: =(Z19+Z20)/(K19+K20) -> 4.2901781 | AD19: =(Z19+Z20)/(J19+J20) -> 0.22733934 | AE19: =(Q19+Q20)/(J19+J20) -> 0.21127753
A20: Апрель | B20: 01.04-05.04 | C20: 14 | D20: =J20-SUM(L20:T20)+U20+V20 -> 34556.54 | E20: ='Юнит 01-05.04'!K$24 -> 93 | F20: ='Юнит 01-05.04'!P$24 -> 52 | G20: ='Юнит 01-05.04'!Q$24 -> 1 | H20: ='Юнит 01-05.04'!S$24 -> 131890 | I20: ='Юнит 01-05.04'!T$24 -> -2103 | J20: =H20+I20 -> 129787 | K20: ='Юнит 01-05.04'!W$24 -> 6667.32 | L20: ='Юнит 01-05.04'!Z$24 -> 8857.02 | M20: ='Юнит 01-05.04'!X$24 -> 55808.41 | Q20: ='Юнит 01-05.04'!AA$24 -> 28287.5 | R20: 2257.53 | S20: 20 | T20: 0 | W20: 2599 | X20: ='Юнит 01-05.04'!$AD$24 -> 519.11 | Y20: =J20-SUM(L20:T20)-K20-V20+U20+W20 -> 30488.22 | Z20: =Y20-X20 -> 29969.11 | AA20: =SUM(Z20:Z31) -> 177191.25
B21: 06.04-12.04 | C21: 15 | D21: =J21-SUM(L21:T21)+U21+V21 -> 36662.16 | E21: ='Юнит 06-12.04'!K$24 -> 161 | F21: ='Юнит 06-12.04'!P$24 -> 84 | G21: ='Юнит 06-12.04'!Q$24 -> 2 | H21: ='Юнит 06-12.04'!S$24 -> 222368 | I21: ='Юнит 06-12.04'!T$24 -> -4950 | J21: =H21+I21 -> 217418 | K21: ='Юнит 06-12.04'!W$24 -> 10463.43 | L21: ='Юнит 06-12.04'!Z$24 -> 16068.74 | M21: ='Юнит 06-12.04'!X$24 -> 100034.39 | Q21: ='Юнит 06-12.04'!AA$24 -> 61249.88 | R21: 3342.83 | S21: 60 | T21: 0 | X21: ='Юнит 06-12.04'!$AD$24 -> 841.64 | Y21: =J21-SUM(L21:T21)-K21-V21+U21+W21 -> 26198.73 | Z21: =Y21-X21 -> 25357.09 | AB21: =K21/J21 -> 0.048125868 | AC21: =Z21/K21 -> 2.4234013 | AD21: =Z21/J21 -> 0.11662829 | AE21: =Q21/J21 -> 0.28171485
B22: 13-19.04 | C22: 16 | D22: =J22-SUM(L22:T22)+U22+V22 -> 25005.01 | E22: ='Юнит 13-19.04'!K$24 -> 107 | F22: ='Юнит 13-19.04'!P$24 -> 60 | G22: ='Юнит 13-19.04'!Q$24 -> 5 | H22: ='Юнит 13-19.04'!S$24 -> 165503 | I22: ='Юнит 13-19.04'!T$24 -> -13500 | J22: =H22+I22 -> 152003 | K22: ='Юнит 13-19.04'!W$24 -> 7010.34 | L22: ='Юнит 13-19.04'!Z$24 -> 17537.62 | M22: ='Юнит 13-19.04'!X$24 -> 72969.29 | Q22: ='Юнит 13-19.04'!AA$24 -> 33345.95 | R22: 3085.13 | S22: 60 | T22: 0 | W22: 1292 | X22: ='Юнит 13-19.04'!$AD$24 -> 593.31 | Y22: =J22-SUM(L22:T22)-K22-V22+U22+W22 -> 19286.67 | Z22: =Y22-X22 -> 18693.36 | AB22: =K22/J22 -> 0.046119748 | AC22: =Z22/K22 -> 2.6665411 | AD22: =Z22/J22 -> 0.1229802 | AE22: =Q22/J22 -> 0.21937692
B23: 20-26.04 | C23: 17 | D23: =J23-SUM(L23:T23)+U23+V23 -> 14054.27 | E23: ='Юнит 20-26.04'!K$24 -> 72 | F23: ='Юнит 20-26.04'!P$24 -> 38 | G23: ='Юнит 20-26.04'!Q$24 -> 2 | H23: ='Юнит 20-26.04'!S$24 -> 106520 | I23: ='Юнит 20-26.04'!T$24 -> -5320 | J23: =H23+I23 -> 101200 | K23: ='Юнит 20-26.04'!W$24 -> 4921.56 | L23: ='Юнит 20-26.04'!Z$24 -> 12223.2 | M23: ='Юнит 20-26.04'!X$24 -> 48451 | Q23: ='Юнит 20-26.04'!AA$24 -> 24263.68 | R23: 2182.85 | S23: 25 | T23: 0 | X23: ='Юнит 20-26.04'!$AD$24 -> 396.25 | Y23: =J23-SUM(L23:T23)-K23-V23+U23+W23 -> 9132.71 | Z23: =Y23-X23 -> 8736.46 | AB23: =K23/J23 -> 0.048632016 | AC23: =Z23/K23 -> 1.7751404 | AD23: =Z23/J23 -> 0.086328656 | AE23: =Q23/J23 -> 0.23975968
B24: 27-30.04 | C24: 18 | D24: =J24-SUM(L24:T24)+U24+V24 -> 7743.67 | E24: ='Юнит 27-30.04'!K$24 -> 45 | F24: ='Юнит 27-30.04'!P$24 -> 24 | G24: ='Юнит 27-30.04'!Q$24 -> 3 | H24: ='Юнит 27-30.04'!S$24 -> 67540 | I24: ='Юнит 27-30.04'!T$24 -> -8460 | J24: =H24+I24 -> 59080 | K24: ='Юнит 27-30.04'!W$24 -> 2781.54 | L24: ='Юнит 27-30.04'!Z$24 -> 5101.96 | M24: ='Юнит 27-30.04'!X$24 -> 28358.4 | Q24: ='Юнит 27-30.04'!AA$24 -> 21519.32 | R24: 996.35 | S24: 100 | T24: 0 | U24: 4739.7 | X24: ='Юнит 27-30.04'!$AD$24 -> 245.4 | Y24: =J24-SUM(L24:T24)-K24-V24+U24+W24 -> 4962.13 | Z24: =Y24-X24 -> 4716.73 | AB24: =(K24+K25)/(J24+J25) -> 0.047392062 | AC24: =(Z24+Z25)/(K24+K25) -> 1.6754438 | AD24: =(Z24+Z25)/(J24+J25) -> 0.079402737 | AE24: =(Q24+Q25)/(J24+J25) -> 0.34100484
A25: Май | B25: 01.05-03.05 | C25: 18 | D25: =J25-SUM(L25:T25)+U25+V25 -> 5199.96 | E25: ='Юнит 01-03.05'!K$24 -> 53 | F25: ='Юнит 01-03.05'!P$24 -> 18 | G25: ='Юнит 01-03.05'!Q$24 -> 0 | H25: ='Юнит 01-03.05'!S$24 -> 50520 | I25: ='Юнит 01-03.05'!T$24 -> 0 | J25: =H25+I25 -> 50520 | K25: ='Юнит 01-03.05'!W$24 -> 2412.63 | L25: ='Юнит 01-03.05'!Z$24 -> 4346.6 | M25: ='Юнит 01-03.05'!X$24 -> 24249.6 | Q25: ='Юнит 01-03.05'!AA$24 -> 15854.81 | R25: 864.03 | S25: 5 | T25: 0 | W25: 1382 | X25: ='Юнит 01-03.05'!$AD$24 -> 183.52 | Y25: =J25-SUM(L25:T25)-K25-V25+U25+W25 -> 4169.33 | Z25: =Y25-X25 -> 3985.81
B26: 04.05-10.05 | C26: 19 | D26: =J26-SUM(L26:T26)+U26+V26 -> 57083.41 | E26: ='Юнит 04-10.05'!K$24 -> 164 | F26: ='Юнит 04-10.05'!P$24 -> 82 | G26: ='Юнит 04-10.05'!Q$24 -> 2 | H26: ='Юнит 04-10.05'!S$24 -> 232090 | I26: ='Юнит 04-10.05'!T$24 -> -5640 | J26: =H26+I26 -> 226450 | K26: ='Юнит 04-10.05'!W$24 -> 10495.77 | L26: ='Юнит 04-10.05'!Z$24 -> 16057.4 | M26: ='Юнит 04-10.05'!X$24 -> 108696 | Q26: ='Юнит 04-10.05'!AA$24 -> 41565.38 | R26: 2902.81 | S26: 0 | T26: 145 | X26: ='Юнит 04-10.05'!$AD$24 -> 800.88 | Y26: =J26-SUM(L26:T26)-K26-V26+U26+W26 -> 46587.64 | Z26: =Y26-X26 -> 45786.76 | AB26: =K26/J26 -> 0.046349172 | AC26: =Z26/K26 -> 4.3624012 | AD26: =Z26/J26 -> 0.20219369 | AE26: =Q26/J26 -> 0.18355213
B27: 11-17.05 | C27: 19 | D27: =J27-SUM(L27:T27)+U27+V27 -> 46234.92 | E27: ='Юнит 11-17.05'!K$24 -> 159 | F27: ='Юнит 11-17.05'!P$24 -> 75 | G27: ='Юнит 11-17.05'!Q$24 -> 1 | H27: ='Юнит 11-17.05'!S$24 -> 212250 | I27: ='Юнит 11-17.05'!T$24 -> -2820 | J27: =H27+I27 -> 209430 | K27: ='Юнит 11-17.05'!W$24 -> 9691.62 | L27: ='Юнит 11-17.05'!Z$24 -> 19222.2 | M27: ='Юнит 11-17.05'!X$24 -> 100526.4 | Q27: ='Юнит 11-17.05'!AA$24 -> 40026.15 | R27: 3370.33 | S27: 50 | T27: 0 | W27: 4145 | X27: ='Юнит 11-17.05'!$AD$24 -> 742.37 | Y27: =J27-SUM(L27:T27)-K27-V27+U27+W27 -> 40688.3 | Z27: =Y27-X27 -> 39945.93 | AB27: =K27/J27 -> 0.046276178 | AC27: =Z27/K27 -> 4.1216979 | AD27: =Z27/J27 -> 0.19073643 | AE27: =Q27/J27 -> 0.19111947
B28: 18-24.05 | C28: 19 | D28: =J28-SUM(L28:T28)+U28+V28 -> 0 | E28: ='Юнит 18-24.05'!K$24 -> 0 | F28: ='Юнит 18-24.05'!P$24 -> 0 | G28: ='Юнит 18-24.05'!Q$24 -> 0 | H28: ='Юнит 18-24.05'!S$24 -> 0 | I28: ='Юнит 18-24.05'!T$24 -> 0 | J28: =H28+I28 -> 0 | K28: ='Юнит 18-24.05'!W$24 -> 0 | L28: ='Юнит 18-24.05'!Z$24 -> 0 | M28: ='Юнит 18-24.05'!X$24 -> 0 | Q28: ='Юнит 18-24.05'!AA$24 -> 0 | X28: ='Юнит 18-24.05'!$AD$24 -> 0 | Y28: =J28-SUM(L28:T28)-K28-V28+U28+W28 -> 0 | Z28: =Y28-X28 -> 0 | AB28: =K28/J28 -> #DIV/0! | AC28: =Z28/K28 -> #DIV/0! | AD28: =Z28/J28 -> #DIV/0! | AE28: =Q28/J28 -> #DIV/0!
B29: 25-31.05 | C29: 19 | D29: =J29-SUM(L29:T29)+U29+V29 -> 0 | E29: ='Юнит 25-31.05'!K$24 -> 0 | F29: ='Юнит 25-31.05'!P$24 -> 0 | G29: ='Юнит 25-31.05'!Q$24 -> 0 | H29: ='Юнит 25-31.05'!S$24 -> 0 | I29: ='Юнит 25-31.05'!T$24 -> 0 | J29: =H29+I29 -> 0 | K29: ='Юнит 25-31.05'!W$24 -> 0 | L29: ='Юнит 25-31.05'!Z$24 -> 0 | M29: ='Юнит 25-31.05'!X$24 -> 0 | Q29: ='Юнит 25-31.05'!AA$24 -> 0 | X29: ='Юнит 25-31.05'!$AD$24 -> 0 | Y29: =J29-SUM(L29:T29)-K29-V29+U29+W29 -> 0 | Z29: =Y29-X29 -> 0 | AB29: =K29/J29 -> #DIV/0! | AC29: =Z29/K29 -> #DIV/0! | AD29: =Z29/J29 -> #DIV/0! | AE29: =Q29/J29 -> #DIV/0!
AB30: =K30/J30 -> #DIV/0! | AC30: =Z30/K30 -> #DIV/0! | AD30: =Z30/J30 -> #DIV/0! | AE30: =Q30/J30 -> #DIV/0!
AB31: =K31/J31 -> #DIV/0! | AC31: =Z31/K31 -> #DIV/0! | AD31: =Z31/J31 -> #DIV/0! | AE31: =Q31/J31 -> #DIV/0!
A32: Итого | D32: =SUM(D4:D19) -> 550107.41 | E32: =SUM(E4:E19) -> 2429 | F32: =SUM(F4:F19) -> 1472 | G32: =SUM(G4:G19) -> 62 | H32: =SUM(H4:H19) -> 3052264 | I32: =SUM(I4:I19) -> -131402 | J32: =SUM(J4:J19) -> 2920862 | K32: =SUM(K4:K19) -> 180695.82 | ... Q32: =SUM(Q4:Q19) -> 699049.12 | R32: =SUM(R4:R21) -> 68031.66 | S32: =SUM(S4:S27) -> 970 | T32: =SUM(T4:T21) -> 78549.5 | U32: =SUM(U4:U19) -> 3696.61 | V32: =SUM(V4:V19) -> 7000 | W32: =SUM(W4:W19) -> 22319 | X32: =SUM(X4:X19) -> 12081.192 | Y32: =SUM(Y4:Y19) -> 377730.59 | Z32: =SUM(Z4:Z19) -> 365649.4 | AA32: =SUM(AA4:AA19) -> 365649.4 | AB32: =K32/J32 -> 0.061863868 | AC32: =Z32/K32 -> 2.0235631 | AD32: =Z32/J32 -> 0.12518544 | AE32: =Q32/J32 -> 0.23932973
H33: % от выручки за весь период
I34: =-I32/H32 -> 0.043050667 | K34: =K32/$J$32 -> 0.061863868 | L34: =L32/$J$32 -> 0.097505675 | M34: =M32/$J$32 -> 0.43 | Q34: =Q32/$J$32 -> 0.23932973 | R34: =R32/$J$32 -> 0.023291638 | S34: =S32/$J$32 -> 0.00033209374 | T34: =T32/$J$32 -> 0.026892575 | U34: =U32/$J$32 -> 0.0012655887 | V34: =V32/$J$32 -> 0.0023965528 | W34: =W32/$J$32 -> 0.0076412374 | X34: =X32/$J$32 -> 0.0041361734 | Z34: =Z32/K32 -> 2.0235631 | AA34: Маржинальность, % | AB34: =Z32/J32 -> 0.12518544
A36: январь | D36: =SUM(D4:D8) -> 123225.19 | E36: =SUM(E4:E8) -> 803 | F36: =SUM(F4:F8) -> 544 | G36: =SUM(G4:G8) -> 15 | H36: =SUM(H4:H8) -> 936447 | I36: =SUM(I4:I8) -> -25467 | J36: =SUM(J4:J8) -> 910980 | K36: =SUM(K4:K8) -> 66570.99 | ... AA36: =SUM(AA4:AA8) -> 49559.258
I37: =-I36/H36 -> 0.027195346 | K37: =K36/$J$36 -> 0.073076237 | L37: =L36/$J$36 -> 0.10826828 | M37: =M36/$J$36 -> 0.43 | Q37: =Q36/$J$36 -> 0.26269438 | R37: =R36/$J$36 -> 0.018634031 | S37: =S36/$J$36 -> 0.00027442974 | T37: =T36/$J$36 -> 0.053770665 | V37: =V36/$J$36 -> 0.0076840326 | W37: =W36/$J$36 -> 0.011402007 | X37: =X36/$J$36 -> 0.0038221932 | Y37: =Y36/J36 -> 0.05822433 | Z37: =Z36/J36 -> 0.054402137 | AA37: =AA36/J36 -> 0.054402137
A39: 5 неделя | K39: =(K8+K9)/($J$8+$J$9) -> 0.070282074 | L39: =(L8+L9)/($J$8+$J$9) -> 0.10463693 | M39: =(M8+M9)/($J$8+$J$9) -> 0.43 | N39: =(N8+N9)/($J$8+$J$9) -> 0 | O39: =(O8+O9)/($J$8+$J$9) -> 0 | P39: =(P8+P9)/($J$8+$J$9) -> 0 | Q39: =(Q8+Q9)/($J$8+$J$9) -> 0.25406002 | R39: =(R8+S8+T8+R9+S9+T9)/($J$8+$J$9) -> 0.21054564 | U39: =(U8+U9)/($J$8+$J$9) -> 0.0048582878 | V39: =(V8+V9)/($J$8+$J$9) -> 0 | W39: =(W8+W9)/($J$8+$J$9) -> 0.021042315 | X39: =(X8+X9)/($J$8+$J$9) -> 0.0038902544 | Y39: =(Y8+Y9)/($J$8+$J$9) -> -0.043624061 | Z39: =(Z8+Z9)/($J$8+$J$9) -> -0.047514315
A40: 6 неделя | K40: =K10/$J$10 -> 0.066026147 | L40: =L10/$J$10 -> 0.10353458 | M40: =M10/$J$10 -> 0.43 | Q40: =Q10/$J$10 -> 0.22200333 | R40: =(R10+S10+T10)/$J$10 -> 0.11123316 | V40: =V10/$J$10 -> 0 | W40: =W10/$J$10 -> 0 | X40: =X10/$J$10 -> 0.0043011894 | Y40: =Y10/J10 -> 0.067202788 | Z40: =Z10/J10 -> 0.062901598
A41: 7 неделя | K41: =K11/$J$11 -> 0.056032823 | L41: =L11/$J$11 -> 0.088563171 | M41: =M11/$J$11 -> 0.43 | Q41: =Q11/$J$11 -> 0.22356573 | R41: =(R11+S11+T11)/$J$11 -> 0.029021394 | V41: =V11/$J$11 -> 0 | W41: =W11/$J$11 -> 0 | X41: =X11/$J$11 -> 0.0043011894 | Y41: =Y11/J11 -> 0.17281688 | Z41: =Z11/J11 -> 0.16851569
A42: 8 неделя | K42: =K12/$J$12 -> 0.054130814 | L42: =L12/$J$12 -> 0.089548728 | M42: =M12/$J$12 -> 0.43 | Q42: =Q12/$J$12 -> 0.22547462 | R42: =(R12+S12+T12)/$J$12 -> 0.022696381 | V42: =V12/$J$12 -> 0 | W42: =W12/$J$12 -> 0.012257431 | X42: =X12/$J$12 -> 0.0043011894 | Y42: =Y12/J12 -> 0.19040689 | Z42: =Z12/J12 -> 0.1861057
A43: 9 неделя | K43: =(K13+K14)/($J$13+$J$14) -> 0.052676864 | L43: =(L13+L14)/($J$13+$J$14) -> 0.10278102 | M43: =(M13+M14)/($J$13+$J$14) -> 0.43 | N43: =(N13+N14)/($J$13+$J$14) -> 0 | O43: =(O13+O14)/($J$13+$J$14) -> 0 | P43: =(P13+P14)/($J$13+$J$14) -> 0 | Q43: =(Q13+Q14)/($J$13+$J$14) -> 0.26870709 | R43: =(R13+R14)/($J$13+$J$14) -> 0.026189725 | V43: =(V13+V14)/($J$13+$J$14) -> 0 | W43: =(W13+W14)/($J$13+$J$14) -> 0.0048485458 | X43: =(X13+X14)/($J$13+$J$14) -> 0.0042950151 | Y43: =(Y13+Y14)/($J$13+$J$14) -> 0.13376434 | Z43: =(Z13+Z14)/($J$13+$J$14) -> 0.12946932
A45: февраль | D45: =SUM(D9:D13) -> 240130.04 | E45: =SUM(E9:E13) -> 958 | F45: =SUM(F9:F13) -> 579 | G45: =SUM(G9:G13) -> 30 | H45: =SUM(H9:H13) -> 1275436 | I45: =SUM(I9:I13) -> -66124 | J45: =SUM(J9:J13) -> 1209312 | K45: =SUM(K9:K13) -> 69788.85 | ... AA45: =SUM(AA9:AA13) -> 174317.71
A47: март | D47: =SUM(D14:D19) -> 186752.18 | E47: =SUM(E14:E19) -> 668 | F47: =SUM(F14:F19) -> 349 | G47: =SUM(G14:G19) -> 17 | H47: =SUM(H14:H19) -> 840381 | I47: =SUM(I14:I19) -> -39811 | J47: =SUM(J14:J19) -> 800570 | K47: =SUM(K14:K19) -> 44335.98 | ... AA47: =SUM(AA14:AA19) -> 141772.43
A49: апрель | D49: =SUM(D20:D24) -> 118021.65 | E49: =SUM(E20:E24) -> 478 | F49: =SUM(F20:F24) -> 258 | G49: =SUM(G20:G24) -> 13 | H49: =SUM(H20:H24) -> 693821 | I49: =SUM(I20:I24) -> -34333 | J49: =SUM(J20:J24) -> 659488 | K49: =SUM(K20:K24) -> 31844.19 | ... AA49: =SUM(AA20:AA24) -> 177191.25
A51: май | D51: =SUM(D25:D29) -> 108518.29 | E51: =SUM(E25:E29) -> 376 | F51: =SUM(F25:F29) -> 175 | G51: =SUM(G25:G29) -> 3 | H51: =SUM(H25:H29) -> 494860 | I51: =SUM(I25:I29) -> -8460 | J51: =SUM(J25:J29) -> 486400 | K51: =SUM(K25:K29) -> 22600.02 | ... AA51: =SUM(AA25:AA29) -> 0
A53: итого | D53: =D36+D45+D47+D49+D51 -> 776647.35 | E53: =E36+E45+E47+E49+E51 -> 3283 | F53: =F36+F45+F47+F49+F51 -> 1905 | G53: =G36+G45+G47+G49+G51 -> 78 | H53: =H36+H45+H47+H49+H51 -> 4240945 | I53: =I36+I45+I47+I49+I51 -> -174195 | J53: =J36+J45+J47+J49+J51 -> 4066750 | K53: =K36+K45+K47+K49+K51 -> 235140.03 | ... AA53: =AA36+AA45+AA47+AA49+AA51 -> 542840.65

Sheet АВС 18-24.05
B2: ОЧКИ
C3: Прибыль | D3: % прибыль | E3: Доля | F3: ABC прибыль | G3: ABC кол-во | J3: Кол-во | K3: % кол-во | L3: Доля | M3: ABC кол-во
B4: черные с железкой классика | D4: =C4/C$18 -> #DIV/0! | E4: =D4 -> #DIV/0! | F4: =IF(AND(E4<=0),"C",IF(E4<=0.8,"A",IF(E4<=0.95,"B","C"))) -> #DIV/0! | G4: =VLOOKUP(B$4:B$17,I$4:M$17,5,0) -> #DIV/0! | I4: черные с железкой классика | K4: =J4/J$18 -> #DIV/0! | L4: =K4 -> #DIV/0! | M4: =_xlfn.IFS(L4<80%,"A",L4<=95%,"B",L4>95%,"C") -> #DIV/0!
B5: qs черные | D5: =C5/C$18 -> #DIV/0! | E5: =D5+E4 -> #DIV/0! | F5: =IF(AND(E5<=0),"C",IF(E5<=0.8,"A",IF(E5<=0.95,"B","C"))) -> #DIV/0! | G5: =VLOOKUP(B$4:B$17,I$4:M$17,5,0) -> #DIV/0! | I5: qs черные | K5: =J5/J$18 -> #DIV/0! | L5: =K5+L4 -> #DIV/0! | M5: =_xlfn.IFS(L5<80%,"A",L5<=95%,"B",L5>95%,"C") -> #DIV/0!
B6: qs синие | D6: =C6/C$18 -> #DIV/0! | E6: =D6+E5 -> #DIV/0! | F6: =IF(AND(E6<=0),"C",IF(E6<=0.8,"A",IF(E6<=0.95,"B","C"))) -> #DIV/0! | G6: =VLOOKUP(B$4:B$17,I$4:M$17,5,0) -> #DIV/0! | I6: qs синие | K6: =J6/J$18 -> #DIV/0! | L6: =K6+L5 -> #DIV/0! | M6: =_xlfn.IFS(L6<80%,"A",L6<=95%,"B",L6>95%,"C") -> #DIV/0!
B7: qs желтые | D7: =C7/C$18 -> #DIV/0! | E7: =D7+E6 -> #DIV/0! | F7: =IF(AND(E7<=0),"C",IF(E7<=0.8,"A",IF(E7<=0.95,"B","C"))) -> #DIV/0! | G7: =VLOOKUP(B$4:B$17,I$4:M$17,5,0) -> #DIV/0! | I7: qs желтые | K7: =J7/J$18 -> #DIV/0! | L7: =K7+L6 -> #DIV/0! | M7: =_xlfn.IFS(L7<80%,"A",L7<=95%,"B",L7>95%,"C") -> #DIV/0!
B8: qs коричневые | D8: =C8/C$18 -> #DIV/0! | E8: =D8+E7 -> #DIV/0! | F8: =IF(AND(E8<=0),"C",IF(E8<=0.8,"A",IF(E8<=0.95,"B","C"))) -> #DIV/0! | G8: =VLOOKUP(B$4:B$17,I$4:M$17,5,0) -> #DIV/0! | I8: qs коричневые | K8: =J8/J$18 -> #DIV/0! | L8: =K8+L7 -> #DIV/0! | M8: =_xlfn.IFS(L8<80%,"A",L8<=95%,"B",L8>95%,"C") -> #DIV/0!
B9: MR8854 C2 | D9: =C9/C$18 -> #DIV/0! | E9: =D9+E8 -> #DIV/0! | F9: =IF(AND(E9<=0),"C",IF(E9<=0.8,"A",IF(E9<=0.95,"B","C"))) -> #DIV/0! | G9: =VLOOKUP(B$4:B$17,I$4:M$17,5,0) -> #DIV/0! | I9: MR8854 C2 | K9: =J9/J$18 -> #DIV/0! | L9: =K9+L8 -> #DIV/0! | M9: =_xlfn.IFS(L9<80%,"A",L9<=95%,"B",L9>95%,"C") -> #DIV/0!
B10: th черн | D10: =C10/C$18 -> #DIV/0! | E10: =D10+E9 -> #DIV/0! | F10: =IF(AND(E10<=0),"C",IF(E10<=0.8,"A",IF(E10<=0.95,"B","C"))) -> #DIV/0! | G10: =VLOOKUP(B$4:B$17,I$4:M$17,5,0) -> #DIV/0! | I10: th черн | K10: =J10/J$18 -> #DIV/0! | L10: =K10+L9 -> #DIV/0! | M10: =_xlfn.IFS(L10<80%,"A",L10<=95%,"B",L10>95%,"C") -> #DIV/0!
B11: th син | D11: =C11/C$18 -> #DIV/0! | E11: =D11+E10 -> #DIV/0! | F11: =IF(AND(E11<=0),"C",IF(E11<=0.8,"A",IF(E11<=0.95,"B","C"))) -> #DIV/0! | G11: =VLOOKUP(B$4:B$17,I$4:M$17,5,0) -> #DIV/0! | I11: th син | K11: =J11/J$18 -> #DIV/0! | L11: =K11+L10 -> #DIV/0! | M11: =_xlfn.IFS(L11<80%,"A",L11<=95%,"B",L11>95%,"C") -> #DIV/0!
B12: th желт | D12: =C12/C$18 -> #DIV/0! | E12: =D12+E5 -> #DIV/0! | F12: =IF(AND(E12<=0),"C",IF(E12<=0.8,"A",IF(E12<=0.95,"B","C"))) -> #DIV/0! | G12: =VLOOKUP(B$4:B$17,I$4:M$17,5,0) -> #DIV/0! | I12: th желт | K12: =J12/J$18 -> #DIV/0! | L12: =K12+L5 -> #DIV/0! | M12: =_xlfn.IFS(L12<80%,"A",L12<=95%,"B",L12>95%,"C") -> #DIV/0!
B13: th коричн | D13: =C13/C$18 -> #DIV/0! | E13: =D13+E12 -> #DIV/0! | F13: =IF(AND(E13<=0),"C",IF(E13<=0.8,"A",IF(E13<=0.95,"B","C"))) -> #DIV/0! | G13: =VLOOKUP(B$4:B$17,I$4:M$17,5,0) -> #DIV/0! | I13: th коричн | K13: =J13/J$18 -> #DIV/0! | L13: =K13+L12 -> #DIV/0! | M13: =_xlfn.IFS(L13<80%,"A",L13<=95%,"B",L13>95%,"C") -> #DIV/0!
B14: flip черный | D14: =C14/C$18 -> #DIV/0! | E14: =D14+E13 -> #DIV/0! | F14: =IF(AND(E14<=0),"C",IF(E14<=0.8,"A",IF(E14<=0.95,"B","C"))) -> #DIV/0! | G14: =VLOOKUP(B$4:B$17,I$4:M$17,5,0) -> #DIV/0! | I14: flip черный | K14: =J14/J$18 -> #DIV/0! | L14: =K14+L13 -> #DIV/0! | M14: =_xlfn.IFS(L14<80%,"A",L14<=95%,"B",L14>95%,"C") -> #DIV/0!
B15: flip синий | D15: =C15/C$18 -> #DIV/0! | E15: =D15+E14 -> #DIV/0! | F15: =IF(AND(E15<=0),"C",IF(E15<=0.8,"A",IF(E15<=0.95,"B","C"))) -> #DIV/0! | G15: =VLOOKUP(B$4:B$17,I$4:M$17,5,0) -> #DIV/0! | I15: flip синий | K15: =J15/J$18 -> #DIV/0! | L15: =K15+L14 -> #DIV/0! | M15: =_xlfn.IFS(L15<80%,"A",L15<=95%,"B",L15>95%,"C") -> #DIV/0!
B16: flip жел | D16: =C16/C$18 -> #DIV/0! | E16: =D16+E15 -> #DIV/0! | F16: =IF(AND(E16<=0),"C",IF(E16<=0.8,"A",IF(E16<=0.95,"B","C"))) -> #DIV/0! | G16: =VLOOKUP(B$4:B$17,I$4:M$17,5,0) -> #DIV/0! | I16: flip жел | K16: =J16/J$18 -> #DIV/0! | L16: =K16+L15 -> #DIV/0! | M16: =_xlfn.IFS(L16<80%,"A",L16<=95%,"B",L16>95%,"C") -> #DIV/0!
B17: flip коричневый | D17: =C17/C$18 -> #DIV/0! | E17: =D17+E14 -> #DIV/0! | F17: =IF(AND(E17<=0),"C",IF(E17<=0.8,"A",IF(E17<=0.95,"B","C"))) -> #DIV/0! | G17: =VLOOKUP(B$4:B$17,I$4:M$17,5,0) -> #DIV/0! | I17: flip коричневый | K17: =J17/J$18 -> #DIV/0! | L17: =K17+L14 -> #DIV/0! | M17: =_xlfn.IFS(L17<80%,"A",L17<=95%,"B",L17>95%,"C") -> #DIV/0!
C18: =SUM(C4:C17) -> 0 | D18: =SUM(D4:D17) -> #DIV/0! | J18: =SUM(J4:J17) -> 0 | K18: =SUM(K4:K17) -> #DIV/0!
C21: Прибыль | D21: % прибыль | E21: Доля | F21: ABC прибыль | G21: ABC кол-во | J21: Кол-во | K21: % кол-во | L21: Доля | M21: ABC кол-во
D22: =C22/C$42 -> #DIV/0! | E22: =D22 -> #DIV/0! | F22: =IF(AND(E22<=0),"C",IF(E22<=0.8,"A",IF(E22<=0.95,"B","C"))) -> #DIV/0! | G22: =VLOOKUP(B$22:B$42,I$22:M$42,5,0) -> #N/A | K22: =J22/J$42 -> #DIV/0! | L22: =K22 -> #DIV/0! | M22: =_xlfn.IFS(L22<80%,"A",L22<=95%,"B",L22>95%,"C") -> #DIV/0!
D23: =C23/C$42 -> #DIV/0! | E23: =D23+E22 -> #DIV/0! | F23: =IF(AND(E23<=0),"C",IF(E23<=0.8,"A",IF(E23<=0.95,"B","C"))) -> #DIV/0! | G23: =VLOOKUP(B$22:B$42,I$22:M$42,5,0) -> #N/A | K23: =J23/J$42 -> #DIV/0! | L23: =K23+L22 -> #DIV/0! | M23: =_xlfn.IFS(L23<80%,"A",L23<=95%,"B",L23>95%,"C") -> #DIV/0!
D24: =C24/C$42 -> #DIV/0! | E24: =D24+E23 -> #DIV/0! | F24: =IF(AND(E24<=0),"C",IF(E24<=0.8,"A",IF(E24<=0.95,"B","C"))) -> #DIV/0! | G24: =VLOOKUP(B$22:B$42,I$22:M$42,5,0) -> #N/A | K24: =J24/J$42 -> #DIV/0! | L24: =K24+L23 -> #DIV/0! | M24: =_xlfn.IFS(L24<80%,"A",L24<=95%,"B",L24>95%,"C") -> #DIV/0!
D25: =C25/C$42 -> #DIV/0! | E25: =D25+E24 -> #DIV/0! | F25: =IF(AND(E25<=0),"C",IF(E25<=0.8,"A",IF(E25<=0.95,"B","C"))) -> #DIV/0! | G25: =VLOOKUP(B$22:B$42,I$22:M$42,5,0) -> #N/A | K25: =J25/J$42 -> #DIV/0! | L25: =K25+L24 -> #DIV/0! | M25: =_xlfn.IFS(L25<80%,"A",L25<=95%,"B",L25>95%,"C") -> #DIV/0!
D26: =C26/C$42 -> #DIV/0! | E26: =D26+E25 -> #DIV/0! | F26: =IF(AND(E26<=0),"C",IF(E26<=0.8,"A",IF(E26<=0.95,"B","C"))) -> #DIV/0! | G26: =VLOOKUP(B$22:B$42,I$22:M$42,5,0) -> #N/A | K26: =J26/J$42 -> #DIV/0! | L26: =K26+L25 -> #DIV/0! | M26: =_xlfn.IFS(L26<80%,"A",L26<=95%,"B",L26>95%,"C") -> #DIV/0!
D27: =C27/C$42 -> #DIV/0! | E27: =D27+E26 -> #DIV/0! | F27: =IF(AND(E27<=0),"C",IF(E27<=0.8,"A",IF(E27<=0.95,"B","C"))) -> #DIV/0! | G27: =VLOOKUP(B$22:B$42,I$22:M$42,5,0) -> #N/A | K27: =J27/J$42 -> #DIV/0! | L27: =K27+L26 -> #DIV/0! | M27: =_xlfn.IFS(L27<80%,"A",L27<=95%,"B",L27>95%,"C") -> #DIV/0!
D28: =C28/C$42 -> #DIV/0! | E28: =D28+E27 -> #DIV/0! | F28: =IF(AND(E28<=0),"C",IF(E28<=0.8,"A",IF(E28<=0.95,"B","C"))) -> #DIV/0! | G28: =VLOOKUP(B$22:B$42,I$22:M$42,5,0) -> #N/A | K28: =J28/J$42 -> #DIV/0! | L28: =K28+L27 -> #DIV/0! | M28: =_xlfn.IFS(L28<80%,"A",L28<=95%,"B",L28>95%,"C") -> #DIV/0!
D29: =C29/C$42 -> #DIV/0! | E29: =D29+E28 -> #DIV/0! | F29: =IF(AND(E29<=0),"C",IF(E29<=0.8,"A",IF(E29<=0.95,"B","C"))) -> #DIV/0! | G29: =VLOOKUP(B$22:B$42,I$22:M$42,5,0) -> #N/A | K29: =J29/J$42 -> #DIV/0! | L29: =K29+L28 -> #DIV/0! | M29: =_xlfn.IFS(L29<80%,"A",L29<=95%,"B",L29>95%,"C") -> #DIV/0!
D30: =C30/C$42 -> #DIV/0! | E30: =D30+E29 -> #DIV/0! | F30: =IF(AND(E30<=0),"C",IF(E30<=0.8,"A",IF(E30<=0.95,"B","C"))) -> #DIV/0! | G30: =VLOOKUP(B$22:B$42,I$22:M$42,5,0) -> #N/A | K30: =J30/J$42 -> #DIV/0! | L30: =K30+L29 -> #DIV/0! | M30: =_xlfn.IFS(L30<80%,"A",L30<=95%,"B",L30>95%,"C") -> #DIV/0!
D31: =C31/C$42 -> #DIV/0! | E31: =D31+E30 -> #DIV/0! | F31: =IF(AND(E31<=0),"C",IF(E31<=0.8,"A",IF(E31<=0.95,"B","C"))) -> #DIV/0! | G31: =VLOOKUP(B$22:B$42,I$22:M$42,5,0) -> #N/A | K31: =J31/J$42 -> #DIV/0! | L31: =K31+L30 -> #DIV/0! | M31: =_xlfn.IFS(L31<80%,"A",L31<=95%,"B",L31>95%,"C") -> #DIV/0!
D32: =C32/C$42 -> #DIV/0! | E32: =D32+E31 -> #DIV/0! | F32: =IF(AND(E32<=0),"C",IF(E32<=0.8,"A",IF(E32<=0.95,"B","C"))) -> #DIV/0! | G32: =VLOOKUP(B$22:B$42,I$22:M$42,5,0) -> #N/A | K32: =J32/J$42 -> #DIV/0! | L32: =K32+L31 -> #DIV/0! | M32: =_xlfn.IFS(L32<80%,"A",L32<=95%,"B",L32>95%,"C") -> #DIV/0!
D33: =C33/C$42 -> #DIV/0! | E33: =D33+E32 -> #DIV/0! | F33: =IF(AND(E33<=0),"C",IF(E33<=0.8,"A",IF(E33<=0.95,"B","C"))) -> #DIV/0! | G33: =VLOOKUP(B$22:B$42,I$22:M$42,5,0) -> #N/A | K33: =J33/J$42 -> #DIV/0! | L33: =K33+L32 -> #DIV/0! | M33: =_xlfn.IFS(L33<80%,"A",L33<=95%,"B",L33>95%,"C") -> #DIV/0!
D34: =C34/C$42 -> #DIV/0! | E34: =D34+E33 -> #DIV/0! | F34: =IF(AND(E34<=0),"C",IF(E34<=0.8,"A",IF(E34<=0.95,"B","C"))) -> #DIV/0! | G34: =VLOOKUP(B$22:B$42,I$22:M$42,5,0) -> #N/A | K34: =J34/J$42 -> #DIV/0! | L34: =K34+L33 -> #DIV/0! | M34: =_xlfn.IFS(L34<80%,"A",L34<=95%,"B",L34>95%,"C") -> #DIV/0!
... D41: =C41/C$42 -> #DIV/0! | E41: =D41+E40 -> #DIV/0! | F41: =IF(AND(E41<=0),"C",IF(E41<=0.8,"A",IF(E41<=0.95,"B","C"))) -> #DIV/0! | G41: =VLOOKUP(B$22:B$42,I$22:M$42,5,0) -> #N/A | K41: =J41/J$42 -> #DIV/0! | L41: =K41+L40 -> #DIV/0! | M41: =_xlfn.IFS(L41<80%,"A",L41<=95%,"B",L41>95%,"C") -> #DIV/0!
C42: =SUM(C22:C41) -> 0 | D42: =SUM(D22:D41) -> #DIV/0! | J42: =SUM(J22:J41) -> 0 | K42: =SUM(K22:K41) -> #DIV/0!

Sheet АВС 11-17.05
B2: ОЧКИ
C3: Прибыль | D3: % прибыль | E3: Доля | F3: ABC прибыль | G3: ABC кол-во | J3: Кол-во | K3: % кол-во | L3: Доля | M3: ABC кол-во
B4: MR8854 C2 | C4: ='Юнит 11-17.05'!AE8 -> 11851.8 | D4: =C4/C$18 -> 0.24132567 | E4: =D4 -> 0.24132567 | F4: =IF(AND(E4<=0),"C",IF(E4<=0.8,"A",IF(E4<=0.95,"B","C"))) -> A | G4: =VLOOKUP(B$4:B$17,I$4:M$17,5,0) -> A | I4: MR8854 C2 | J4: ='Юнит 11-17.05'!R8 -> 15 | K4: =J4/J$18 -> 0.2027027 | L4: =K4 -> 0.2027027 | M4: =_xlfn.IFS(L4<80%,"A",L4<=95%,"B",L4>95%,"C") -> A
B5: th коричн | C5: ='Юнит 11-17.05'!AE12 -> 8967.6723 | D5: =C5/C$18 -> 0.18259923 | E5: =D5+E4 -> 0.4239249 | F5: =IF(AND(E5<=0),"C",IF(E5<=0.8,"A",IF(E5<=0.95,"B","C"))) -> A | G5: =VLOOKUP(B$4:B$17,I$4:M$17,5,0) -> A | I5: th коричн | J5: ='Юнит 11-17.05'!R12 -> 12 | K5: =J5/J$18 -> 0.16216216 | L5: =K5+L4 -> 0.36486486 | M5: =_xlfn.IFS(L5<80%,"A",L5<=95%,"B",L5>95%,"C") -> A
B6: flip черный | C6: ='Юнит 11-17.05'!AE13 -> 6498.3653 | D6: =C6/C$18 -> 0.13231934 | E6: =D6+E5 -> 0.55624425 | F6: =IF(AND(E6<=0),"C",IF(E6<=0.8,"A",IF(E6<=0.95,"B","C"))) -> A | G6: =VLOOKUP(B$4:B$17,I$4:M$17,5,0) -> A | I6: flip черный | J6: ='Юнит 11-17.05'!R13 -> 8 | K6: =J6/J$18 -> 0.10810811 | L6: =K6+L5 -> 0.47297297 | M6: =_xlfn.IFS(L6<80%,"A",L6<=95%,"B",L6>95%,"C") -> A
B7: flip коричневый | C7: ='Юнит 11-17.05'!AE16 -> 5390.0445 | D7: =C7/C$18 -> 0.10975178 | E7: =D7+E6 -> 0.66599602 | F7: =IF(AND(E7<=0),"C",IF(E7<=0.8,"A",IF(E7<=0.95,"B","C"))) -> A | G7: =VLOOKUP(B$4:B$17,I$4:M$17,5,0) -> A | I7: qs коричневые | J7: ='Юнит 11-17.05'!R7 -> 7 | K7: =J7/J$18 -> 0.094594595 | L7: =K7+L6 -> 0.56756757 | M7: =_xlfn.IFS(L7<80%,"A",L7<=95%,"B",L7>95%,"C") -> A
B8: qs коричневые | C8: ='Юнит 11-17.05'!AE7 -> 3414.999 | D8: =C8/C$18 -> 0.069536015 | E8: =D8+E7 -> 0.73553204 | F8: =IF(AND(E8<=0),"C",IF(E8<=0.8,"A",IF(E8<=0.95,"B","C"))) -> A | G8: =VLOOKUP(B$4:B$17,I$4:M$17,5,0) -> A | I8: flip коричневый | J8: ='Юнит 11-17.05'!R16 -> 7 | K8: =J8/J$18 -> 0.094594595 | L8: =K8+L7 -> 0.66216216 | M8: =_xlfn.IFS(L8<80%,"A",L8<=95%,"B",L8>95%,"C") -> A
B9: th черн | C9: ='Юнит 11-17.05'!AE9 -> 3405.7054 | D9: =C9/C$18 -> 0.069346778 | E9: =D9+E8 -> 0.80487882 | F9: =IF(AND(E9<=0),"C",IF(E9<=0.8,"A",IF(E9<=0.95,"B","C"))) -> B | G9: =VLOOKUP(B$4:B$17,I$4:M$17,5,0) -> A | I9: th черн | J9: ='Юнит 11-17.05'!R9 -> 5 | K9: =J9/J$18 -> 0.067567568 | L9: =K9+L8 -> 0.72972973 | M9: =_xlfn.IFS(L9<80%,"A",L9<=95%,"B",L9>95%,"C") -> A
B10: th син | C10: ='Юнит 11-17.05'!AE10 -> 2916.7201 | D10: =C10/C$18 -> 0.059390089 | E10: =D10+E9 -> 0.86426891 | F10: =IF(AND(E10<=0),"C",IF(E10<=0.8,"A",IF(E10<=0.95,"B","C"))) -> B | G10: =VLOOKUP(B$4:B$17,I$4:M$17,5,0) -> A | I10: th желт | J10: ='Юнит 11-17.05'!R11 -> 5 | K10: =J10/J$18 -> 0.067567568 | L10: =K10+L9 -> 0.7972973 | M10: =_xlfn.IFS(L10<80%,"A",L10<=95%,"B",L10>95%,"C") -> A
B11: th желт | C11: ='Юнит 11-17.05'!AE11 -> 2659.9058 | D11: =C11/C$18 -> 0.054160851 | E11: =D11+E10 -> 0.91842976 | F11: =IF(AND(E11<=0),"C",IF(E11<=0.8,"A",IF(E11<=0.95,"B","C"))) -> B | G11: =VLOOKUP(B$4:B$17,I$4:M$17,5,0) -> A | I11: qs черные | J11: ='Юнит 11-17.05'!R4 -> 4 | K11: =J11/J$18 -> 0.054054054 | L11: =K11+L10 -> 0.85135135 | M11: =_xlfn.IFS(L11<80%,"A",L11<=95%,"B",L11>95%,"C") -> B
B12: qs черные | C12: ='Юнит 11-17.05'!AE4 -> 2515.6237 | D12: =C12/C$18 -> 0.051222985 | E12: =D12+E5 -> 0.47514789 | F12: =IF(AND(E12<=0),"C",IF(E12<=0.8,"A",IF(E12<=0.95,"B","C"))) -> A | G12: =VLOOKUP(B$4:B$17,I$4:M$17,5,0) -> B | I12: th син | J12: ='Юнит 11-17.05'!R10 -> 3 | K12: =J12/J$18 -> 0.040540541 | L12: =K12+L5 -> 0.40540541 | M12: =_xlfn.IFS(L12<80%,"A",L12<=95%,"B",L12>95%,"C") -> A
B13: черные с железкой классика | C13: ='Юнит 11-17.05'!AE3 -> 1202.617 | D13: =C13/C$18 -> 0.024487618 | E13: =D13+E12 -> 0.49963551 | F13: =IF(AND(E13<=0),"C",IF(E13<=0.8,"A",IF(E13<=0.95,"B","C"))) -> A | G13: =VLOOKUP(B$4:B$17,I$4:M$17,5,0) -> A | I13: черные с железкой классика | J13: ='Юнит 11-17.05'!R3 -> 2 | K13: =J13/J$18 -> 0.027027027 | L13: =K13+L12 -> 0.43243243 | M13: =_xlfn.IFS(L13<80%,"A",L13<=95%,"B",L13>95%,"C") -> A
B14: qs синие | C14: ='Юнит 11-17.05'!AE5 -> 357.11322 | D14: =C14/C$18 -> 0.007271519 | E14: =D14+E13 -> 0.50690702 | F14: =IF(AND(E14<=0),"C",IF(E14<=0.8,"A",IF(E14<=0.95,"B","C"))) -> A | G14: =VLOOKUP(B$4:B$17,I$4:M$17,5,0) -> A | I14: qs желтые | J14: ='Юнит 11-17.05'!R6 -> 2 | K14: =J14/J$18 -> 0.027027027 | L14: =K14+L13 -> 0.45945946 | M14: =_xlfn.IFS(L14<80%,"A",L14<=95%,"B",L14>95%,"C") -> A
B15: flip синий | C15: ='Юнит 11-17.05'!AE14 -> 353.6152 | D15: =C15/C$18 -> 0.0072002925 | E15: =D15+E14 -> 0.51410732 | F15: =IF(AND(E15<=0),"C",IF(E15<=0.8,"A",IF(E15<=0.95,"B","C"))) -> A | G15: =VLOOKUP(B$4:B$17,I$4:M$17,5,0) -> A | I15: flip жел | J15: ='Юнит 11-17.05'!R15 -> 2 | K15: =J15/J$18 -> 0.027027027 | L15: =K15+L14 -> 0.48648649 | M15: =_xlfn.IFS(L15<80%,"A",L15<=95%,"B",L15>95%,"C") -> A
B16: qs желтые | C16: ='Юнит 11-17.05'!AE6 -> 324.88031 | D16: =C16/C$18 -> 0.0066151944 | E16: =D16+E15 -> 0.52072251 | F16: =IF(AND(E16<=0),"C",IF(E16<=0.8,"A",IF(E16<=0.95,"B","C"))) -> A | G16: =VLOOKUP(B$4:B$17,I$4:M$17,5,0) -> A | I16: qs синие | J16: ='Юнит 11-17.05'!R5 -> 1 | K16: =J16/J$18 -> 0.013513514 | L16: =K16+L15 -> 0.5 | M16: =_xlfn.IFS(L16<80%,"A",L16<=95%,"B",L16>95%,"C") -> A
B17: flip жел | C17: ='Юнит 11-17.05'!AE15 -> -747.83468 | D17: =C17/C$18 -> -0.015227367 | E17: =D17+E14 -> 0.49167966 | F17: =IF(AND(E17<=0),"C",IF(E17<=0.8,"A",IF(E17<=0.95,"B","C"))) -> A | G17: =VLOOKUP(B$4:B$17,I$4:M$17,5,0) -> A | I17: flip синий | J17: ='Юнит 11-17.05'!R14 -> 1 | K17: =J17/J$18 -> 0.013513514 | L17: =K17+L14 -> 0.47297297 | M17: =_xlfn.IFS(L17<80%,"A",L17<=95%,"B",L17>95%,"C") -> A
C18: =SUM(C4:C17) -> 49111.227 | D18: =SUM(D4:D17) -> 1 | J18: =SUM(J4:J17) -> 74 | K18: =SUM(K4:K17) -> 1
C21: Прибыль | D21: % прибыль | E21: Доля | F21: ABC прибыль | G21: ABC кол-во | J21: Кол-во | K21: % кол-во | L21: Доля | M21: ABC кол-во
D22: =C22/C$42 -> #DIV/0! | E22: =D22 -> #DIV/0! | F22: =IF(AND(E22<=0),"C",IF(E22<=0.8,"A",IF(E22<=0.95,"B","C"))) -> #DIV/0! | G22: =VLOOKUP(B$22:B$42,I$22:M$42,5,0) -> #N/A | K22: =J22/J$42 -> #DIV/0! | L22: =K22 -> #DIV/0! | M22: =_xlfn.IFS(L22<80%,"A",L22<=95%,"B",L22>95%,"C") -> #DIV/0!
D23: =C23/C$42 -> #DIV/0! | E23: =D23+E22 -> #DIV/0! | F23: =IF(AND(E23<=0),"C",IF(E23<=0.8,"A",IF(E23<=0.95,"B","C"))) -> #DIV/0! | G23: =VLOOKUP(B$22:B$42,I$22:M$42,5,0) -> #N/A | K23: =J23/J$42 -> #DIV/0! | L23: =K23+L22 -> #DIV/0! | M23: =_xlfn.IFS(L23<80%,"A",L23<=95%,"B",L23>95%,"C") -> #DIV/0!
D24: =C24/C$42 -> #DIV/0! | E24: =D24+E23 -> #DIV/0! | F24: =IF(AND(E24<=0),"C",IF(E24<=0.8,"A",IF(E24<=0.95,"B","C"))) -> #DIV/0! | G24: =VLOOKUP(B$22:B$42,I$22:M$42,5,0) -> #N/A | K24: =J24/J$42 -> #DIV/0! | L24: =K24+L23 -> #DIV/0! | M24: =_xlfn.IFS(L24<80%,"A",L24<=95%,"B",L24>95%,"C") -> #DIV/0!
D25: =C25/C$42 -> #DIV/0! | E25: =D25+E24 -> #DIV/0! | F25: =IF(AND(E25<=0),"C",IF(E25<=0.8,"A",IF(E25<=0.95,"B","C"))) -> #DIV/0! | G25: =VLOOKUP(B$22:B$42,I$22:M$42,5,0) -> #N/A | K25: =J25/J$42 -> #DIV/0! | L25: =K25+L24 -> #DIV/0! | M25: =_xlfn.IFS(L25<80%,"A",L25<=95%,"B",L25>95%,"C") -> #DIV/0!
D26: =C26/C$42 -> #DIV/0! | E26: =D26+E25 -> #DIV/0! | F26: =IF(AND(E26<=0),"C",IF(E26<=0.8,"A",IF(E26<=0.95,"B","C"))) -> #DIV/0! | G26: =VLOOKUP(B$22:B$42,I$22:M$42,5,0) -> #N/A | K26: =J26/J$42 -> #DIV/0! | L26: =K26+L25 -> #DIV/0! | M26: =_xlfn.IFS(L26<80%,"A",L26<=95%,"B",L26>95%,"C") -> #DIV/0!
D27: =C27/C$42 -> #DIV/0! | E27: =D27+E26 -> #DIV/0! | F27: =IF(AND(E27<=0),"C",IF(E27<=0.8,"A",IF(E27<=0.95,"B","C"))) -> #DIV/0! | G27: =VLOOKUP(B$22:B$42,I$22:M$42,5,0) -> #N/A | K27: =J27/J$42 -> #DIV/0! | L27: =K27+L26 -> #DIV/0! | M27: =_xlfn.IFS(L27<80%,"A",L27<=95%,"B",L27>95%,"C") -> #DIV/0!
D28: =C28/C$42 -> #DIV/0! | E28: =D28+E27 -> #DIV/0! | F28: =IF(AND(E28<=0),"C",IF(E28<=0.8,"A",IF(E28<=0.95,"B","C"))) -> #DIV/0! | G28: =VLOOKUP(B$22:B$42,I$22:M$42,5,0) -> #N/A | K28: =J28/J$42 -> #DIV/0! | L28: =K28+L27 -> #DIV/0! | M28: =_xlfn.IFS(L28<80%,"A",L28<=95%,"B",L28>95%,"C") -> #DIV/0!
D29: =C29/C$42 -> #DIV/0! | E29: =D29+E28 -> #DIV/0! | F29: =IF(AND(E29<=0),"C",IF(E29<=0.8,"A",IF(E29<=0.95,"B","C"))) -> #DIV/0! | G29: =VLOOKUP(B$22:B$42,I$22:M$42,5,0) -> #N/A | K29: =J29/J$42 -> #DIV/0! | L29: =K29+L28 -> #DIV/0! | M29: =_xlfn.IFS(L29<80%,"A",L29<=95%,"B",L29>95%,"C") -> #DIV/0!
D30: =C30/C$42 -> #DIV/0! | E30: =D30+E29 -> #DIV/0! | F30: =IF(AND(E30<=0),"C",IF(E30<=0.8,"A",IF(E30<=0.95,"B","C"))) -> #DIV/0! | G30: =VLOOKUP(B$22:B$42,I$22:M$42,5,0) -> #N/A | K30: =J30/J$42 -> #DIV/0! | L30: =K30+L29 -> #DIV/0! | M30: =_xlfn.IFS(L30<80%,"A",L30<=95%,"B",L30>95%,"C") -> #DIV/0!
D31: =C31/C$42 -> #DIV/0! | E31: =D31+E30 -> #DIV/0! | F31: =IF(AND(E31<=0),"C",IF(E31<=0.8,"A",IF(E31<=0.95,"B","C"))) -> #DIV/0! | G31: =VLOOKUP(B$22:B$42,I$22:M$42,5,0) -> #N/A | K31: =J31/J$42 -> #DIV/0! | L31: =K31+L30 -> #DIV/0! | M31: =_xlfn.IFS(L31<80%,"A",L31<=95%,"B",L31>95%,"C") -> #DIV/0!
D32: =C32/C$42 -> #DIV/0! | E32: =D32+E31 -> #DIV/0! | F32: =IF(AND(E32<=0),"C",IF(E32<=0.8,"A",IF(E32<=0.95,"B","C"))) -> #DIV/0! | G32: =VLOOKUP(B$22:B$42,I$22:M$42,5,0) -> #N/A | K32: =J32/J$42 -> #DIV/0! | L32: =K32+L31 -> #DIV/0! | M32: =_xlfn.IFS(L32<80%,"A",L32<=95%,"B",L32>95%,"C") -> #DIV/0!
D33: =C33/C$42 -> #DIV/0! | E33: =D33+E32 -> #DIV/0! | F33: =IF(AND(E33<=0),"C",IF(E33<=0.8,"A",IF(E33<=0.95,"B","C"))) -> #DIV/0! | G33: =VLOOKUP(B$22:B$42,I$22:M$42,5,0) -> #N/A | K33: =J33/J$42 -> #DIV/0! | L33: =K33+L32 -> #DIV/0! | M33: =_xlfn.IFS(L33<80%,"A",L33<=95%,"B",L33>95%,"C") -> #DIV/0!
D34: =C34/C$42 -> #DIV/0! | E34: =D34+E33 -> #DIV/0! | F34: =IF(AND(E34<=0),"C",IF(E34<=0.8,"A",IF(E34<=0.95,"B","C"))) -> #DIV/0! | G34: =VLOOKUP(B$22:B$42,I$22:M$42,5,0) -> #N/A | K34: =J34/J$42 -> #DIV/0! | L34: =K34+L33 -> #DIV/0! | M34: =_xlfn.IFS(L34<80%,"A",L34<=95%,"B",L34>95%,"C") -> #DIV/0!
... D41: =C41/C$42 -> #DIV/0! | E41: =D41+E40 -> #DIV/0! | F41: =IF(AND(E41<=0),"C",IF(E41<=0.8,"A",IF(E41<=0.95,"B","C"))) -> #DIV/0! | G41: =VLOOKUP(B$22:B$42,I$22:M$42,5,0) -> #N/A | K41: =J41/J$42 -> #DIV/0! | L41: =K41+L40 -> #DIV/0! | M41: =_xlfn.IFS(L41<80%,"A",L41<=95%,"B",L41>95%,"C") -> #DIV/0!
C42: =SUM(C22:C41) -> 0 | D42: =SUM(D22:D41) -> #DIV/0! | J42: =SUM(J22:J41) -> 0 | K42: =SUM(K22:K41) -> #DIV/0!

Sheet АВС 04-10.05
B2: ОЧКИ
C3: Прибыль | D3: % прибыль | E3: Доля | F3: ABC прибыль | G3: ABC кол-во | J3: Кол-во | K3: % кол-во | L3: Доля | M3: ABC кол-во
B4: MR8854 C2 | C4: ='Юнит 04-10.05'!AE8 -> 14586.915 | D4: =C4/C$18 -> 0.24652595 | E4: =D4 -> 0.24652595 | F4: =IF(AND(E4<=0),"C",IF(E4<=0.8,"A",IF(E4<=0.95,"B","C"))) -> A | G4: =VLOOKUP(B$4:B$17,I$4:M$17,5,0) -> A | I4: MR8854 C2 | J4: ='Юнит 04-10.05'!R8 -> 17 | K4: =J4/J$18 -> 0.2125 | L4: =K4 -> 0.2125 | M4: =_xlfn.IFS(L4<80%,"A",L4<=95%,"B",L4>95%,"C") -> A
B5: flip черный | C5: ='Юнит 04-10.05'!AE13 -> 7843.3832 | D5: =C5/C$18 -> 0.13255699 | E5: =D5+E4 -> 0.37908294 | F5: =IF(AND(E5<=0),"C",IF(E5<=0.8,"A",IF(E5<=0.95,"B","C"))) -> A | G5: =VLOOKUP(B$4:B$17,I$4:M$17,5,0) -> A | I5: th коричн | J5: ='Юнит 04-10.05'!R12 -> 9 | K5: =J5/J$18 -> 0.1125 | L5: =K5+L4 -> 0.325 | M5: =_xlfn.IFS(L5<80%,"A",L5<=95%,"B",L5>95%,"C") -> A
B6: flip жел | C6: ='Юнит 04-10.05'!AE15 -> 6929.0321 | D6: =C6/C$18 -> 0.11710401 | E6: =D6+E5 -> 0.49618696 | F6: =IF(AND(E6<=0),"C",IF(E6<=0.8,"A",IF(E6<=0.95,"B","C"))) -> A | G6: =VLOOKUP(B$4:B$17,I$4:M$17,5,0) -> A | I6: qs коричневые | J6: ='Юнит 04-10.05'!R7 -> 8 | K6: =J6/J$18 -> 0.1 | L6: =K6+L5 -> 0.425 | M6: =_xlfn.IFS(L6<80%,"A",L6<=95%,"B",L6>95%,"C") -> A
B7: qs коричневые | C7: ='Юнит 04-10.05'!AE7 -> 6857.661 | D7: =C7/C$18 -> 0.1158978 | E7: =D7+E6 -> 0.61208476 | F7: =IF(AND(E7<=0),"C",IF(E7<=0.8,"A",IF(E7<=0.95,"B","C"))) -> A | G7: =VLOOKUP(B$4:B$17,I$4:M$17,5,0) -> A | I7: flip черный | J7: ='Юнит 04-10.05'!R13 -> 8 | K7: =J7/J$18 -> 0.1 | L7: =K7+L6 -> 0.525 | M7: =_xlfn.IFS(L7<80%,"A",L7<=95%,"B",L7>95%,"C") -> A
B8: th коричн | C8: ='Юнит 04-10.05'!AE12 -> 6335.6593 | D8: =C8/C$18 -> 0.10707572 | E8: =D8+E7 -> 0.71916048 | F8: =IF(AND(E8<=0),"C",IF(E8<=0.8,"A",IF(E8<=0.95,"B","C"))) -> A | G8: =VLOOKUP(B$4:B$17,I$4:M$17,5,0) -> A | I8: flip жел | J8: ='Юнит 04-10.05'!R15 -> 8 | K8: =J8/J$18 -> 0.1 | L8: =K8+L7 -> 0.625 | M8: =_xlfn.IFS(L8<80%,"A",L8<=95%,"B",L8>95%,"C") -> A
B9: flip коричневый | C9: ='Юнит 04-10.05'!AE16 -> 5430.7224 | D9: =C9/C$18 -> 0.091781849 | E9: =D9+E8 -> 0.81094233 | F9: =IF(AND(E9<=0),"C",IF(E9<=0.8,"A",IF(E9<=0.95,"B","C"))) -> B | G9: =VLOOKUP(B$4:B$17,I$4:M$17,5,0) -> B | I9: th желт | J9: ='Юнит 04-10.05'!R11 -> 7 | K9: =J9/J$18 -> 0.0875 | L9: =K9+L8 -> 0.7125 | M9: =_xlfn.IFS(L9<80%,"A",L9<=95%,"B",L9>95%,"C") -> A
B10: th желт | C10: ='Юнит 04-10.05'!AE11 -> 5235.0189 | D10: =C10/C$18 -> 0.088474365 | E10: =D10+E9 -> 0.8994167 | F10: =IF(AND(E10<=0),"C",IF(E10<=0.8,"A",IF(E10<=0.95,"B","C"))) -> B | G10: =VLOOKUP(B$4:B$17,I$4:M$17,5,0) -> A | I10: flip коричневый | J10: ='Юнит 04-10.05'!R16 -> 7 | K10: =J10/J$18 -> 0.0875 | L10: =K10+L9 -> 0.8 | M10: =_xlfn.IFS(L10<80%,"A",L10<=95%,"B",L10>95%,"C") -> B
B11: flip синий | C11: ='Юнит 04-10.05'!AE14 -> 3644.9504 | D11: =C11/C$18 -> 0.061601434 | E11: =D11+E10 -> 0.96101813 | F11: =IF(AND(E11<=0),"C",IF(E11<=0.8,"A",IF(E11<=0.95,"B","C"))) -> C | G11: =VLOOKUP(B$4:B$17,I$4:M$17,5,0) -> B | I11: flip синий | J11: ='Юнит 04-10.05'!R14 -> 5 | K11: =J11/J$18 -> 0.0625 | L11: =K11+L10 -> 0.8625 | M11: =_xlfn.IFS(L11<80%,"A",L11<=95%,"B",L11>95%,"C") -> B
B12: qs черные | C12: ='Юнит 04-10.05'!AE4 -> 1664.956 | D12: =C12/C$18 -> 0.028138567 | E12: =D12+E5 -> 0.40722151 | F12: =IF(AND(E12<=0),"C",IF(E12<=0.8,"A",IF(E12<=0.95,"B","C"))) -> A | G12: =VLOOKUP(B$4:B$17,I$4:M$17,5,0) -> A | I12: qs черные | J12: ='Юнит 04-10.05'!R4 -> 4 | K12: =J12/J$18 -> 0.05 | L12: =K12+L5 -> 0.375 | M12: =_xlfn.IFS(L12<80%,"A",L12<=95%,"B",L12>95%,"C") -> A
B13: th черн | C13: ='Юнит 04-10.05'!AE9 -> 1207.7938 | D13: =C13/C$18 -> 0.020412302 | E13: =D13+E12 -> 0.42763381 | F13: =IF(AND(E13<=0),"C",IF(E13<=0.8,"A",IF(E13<=0.95,"B","C"))) -> A | G13: =VLOOKUP(B$4:B$17,I$4:M$17,5,0) -> A | I13: qs синие | J13: ='Юнит 04-10.05'!R5 -> 2 | K13: =J13/J$18 -> 0.025 | L13: =K13+L12 -> 0.4 | M13: =_xlfn.IFS(L13<80%,"A",L13<=95%,"B",L13>95%,"C") -> A
B14: qs желтые | C14: ='Юнит 04-10.05'!AE6 -> 877.47362 | D14: =C14/C$18 -> 0.014829731 | E14: =D14+E13 -> 0.44246354 | F14: =IF(AND(E14<=0),"C",IF(E14<=0.8,"A",IF(E14<=0.95,"B","C"))) -> A | G14: =VLOOKUP(B$4:B$17,I$4:M$17,5,0) -> A | I14: qs желтые | J14: ='Юнит 04-10.05'!R6 -> 2 | K14: =J14/J$18 -> 0.025 | L14: =K14+L13 -> 0.425 | M14: =_xlfn.IFS(L14<80%,"A",L14<=95%,"B",L14>95%,"C") -> A
B15: qs синие | C15: ='Юнит 04-10.05'!AE5 -> 622.1813 | D15: =C15/C$18 -> 0.010515167 | E15: =D15+E14 -> 0.45297871 | F15: =IF(AND(E15<=0),"C",IF(E15<=0.8,"A",IF(E15<=0.95,"B","C"))) -> A | G15: =VLOOKUP(B$4:B$17,I$4:M$17,5,0) -> A | I15: th черн | J15: ='Юнит 04-10.05'!R9 -> 2 | K15: =J15/J$18 -> 0.025 | L15: =K15+L14 -> 0.45 | M15: =_xlfn.IFS(L15<80%,"A",L15<=95%,"B",L15>95%,"C") -> A
B16: th син | C16: ='Юнит 04-10.05'!AE10 -> -876.26724 | D16: =C16/C$18 -> -0.014809342 | E16: =D16+E15 -> 0.43816937 | F16: =IF(AND(E16<=0),"C",IF(E16<=0.8,"A",IF(E16<=0.95,"B","C"))) -> A | G16: =VLOOKUP(B$4:B$17,I$4:M$17,5,0) -> A | I16: th син | J16: ='Юнит 04-10.05'!R10 -> 1 | K16: =J16/J$18 -> 0.0125 | L16: =K16+L15 -> 0.4625 | M16: =_xlfn.IFS(L16<80%,"A",L16<=95%,"B",L16>95%,"C") -> A
B17: черные с железкой классика | C17: ='Юнит 04-10.05'!AE3 -> -1189.5844 | D17: =C17/C$18 -> -0.020104554 | E17: =D17+E14 -> 0.42235899 | F17: =IF(AND(E17<=0),"C",IF(E17<=0.8,"A",IF(E17<=0.95,"B","C"))) -> A | G17: =VLOOKUP(B$4:B$17,I$4:M$17,5,0) -> A | I17: черные с железкой классика | J17: ='Юнит 04-10.05'!R3 -> 0 | K17: =J17/J$18 -> 0 | L17: =K17+L14 -> 0.425 | M17: =_xlfn.IFS(L17<80%,"A",L17<=95%,"B",L17>95%,"C") -> A
C18: =SUM(C4:C17) -> 59169.895 | D18: =SUM(D4:D17) -> 1 | J18: =SUM(J4:J17) -> 80 | K18: =SUM(K4:K17) -> 1
C21: Прибыль | D21: % прибыль | E21: Доля | F21: ABC прибыль | G21: ABC кол-во | J21: Кол-во | K21: % кол-во | L21: Доля | M21: ABC кол-во
D22: =C22/C$42 -> #DIV/0! | E22: =D22 -> #DIV/0! | F22: =IF(AND(E22<=0),"C",IF(E22<=0.8,"A",IF(E22<=0.95,"B","C"))) -> #DIV/0! | G22: =VLOOKUP(B$22:B$42,I$22:M$42,5,0) -> #N/A | K22: =J22/J$42 -> #DIV/0! | L22: =K22 -> #DIV/0! | M22: =_xlfn.IFS(L22<80%,"A",L22<=95%,"B",L22>95%,"C") -> #DIV/0!
D23: =C23/C$42 -> #DIV/0! | E23: =D23+E22 -> #DIV/0! | F23: =IF(AND(E23<=0),"C",IF(E23<=0.8,"A",IF(E23<=0.95,"B","C"))) -> #DIV/0! | G23: =VLOOKUP(B$22:B$42,I$22:M$42,5,0) -> #N/A | K23: =J23/J$42 -> #DIV/0! | L23: =K23+L22 -> #DIV/0! | M23: =_xlfn.IFS(L23<80%,"A",L23<=95%,"B",L23>95%,"C") -> #DIV/0!
D24: =C24/C$42 -> #DIV/0! | E24: =D24+E23 -> #DIV/0! | F24: =IF(AND(E24<=0),"C",IF(E24<=0.8,"A",IF(E24<=0.95,"B","C"))) -> #DIV/0! | G24: =VLOOKUP(B$22:B$42,I$22:M$42,5,0) -> #N/A | K24: =J24/J$42 -> #DIV/0! | L24: =K24+L23 -> #DIV/0! | M24: =_xlfn.IFS(L24<80%,"A",L24<=95%,"B",L24>95%,"C") -> #DIV/0!
D25: =C25/C$42 -> #DIV/0! | E25: =D25+E24 -> #DIV/0! | F25: =IF(AND(E25<=0),"C",IF(E25<=0.8,"A",IF(E25<=0.95,"B","C"))) -> #DIV/0! | G25: =VLOOKUP(B$22:B$42,I$22:M$42,5,0) -> #N/A | K25: =J25/J$42 -> #DIV/0! | L25: =K25+L24 -> #DIV/0! | M25: =_xlfn.IFS(L25<80%,"A",L25<=95%,"B",L25>95%,"C") -> #DIV/0!
D26: =C26/C$42 -> #DIV/0! | E26: =D26+E25 -> #DIV/0! | F26: =IF(AND(E26<=0),"C",IF(E26<=0.8,"A",IF(E26<=0.95,"B","C"))) -> #DIV/0! | G26: =VLOOKUP(B$22:B$42,I$22:M$42,5,0) -> #N/A | K26: =J26/J$42 -> #DIV/0! | L26: =K26+L25 -> #DIV/0! | M26: =_xlfn.IFS(L26<80%,"A",L26<=95%,"B",L26>95%,"C") -> #DIV/0!
D27: =C27/C$42 -> #DIV/0! | E27: =D27+E26 -> #DIV/0! | F27: =IF(AND(E27<=0),"C",IF(E27<=0.8,"A",IF(E27<=0.95,"B","C"))) -> #DIV/0! | G27: =VLOOKUP(B$22:B$42,I$22:M$42,5,0) -> #N/A | K27: =J27/J$42 -> #DIV/0! | L27: =K27+L26 -> #DIV/0! | M27: =_xlfn.IFS(L27<80%,"A",L27<=95%,"B",L27>95%,"C") -> #DIV/0!
D28: =C28/C$42 -> #DIV/0! | E28: =D28+E27 -> #DIV/0! | F28: =IF(AND(E28<=0),"C",IF(E28<=0.8,"A",IF(E28<=0.95,"B","C"))) -> #DIV/0! | G28: =VLOOKUP(B$22:B$42,I$22:M$42,5,0) -> #N/A | K28: =J28/J$42 -> #DIV/0! | L28: =K28+L27 -> #DIV/0! | M28: =_xlfn.IFS(L28<80%,"A",L28<=95%,"B",L28>95%,"C") -> #DIV/0!
D29: =C29/C$42 -> #DIV/0! | E29: =D29+E28 -> #DIV/0! | F29: =IF(AND(E29<=0),"C",IF(E29<=0.8,"A",IF(E29<=0.95,"B","C"))) -> #DIV/0! | G29: =VLOOKUP(B$22:B$42,I$22:M$42,5,0) -> #N/A | K29: =J29/J$42 -> #DIV/0! | L29: =K29+L28 -> #DIV/0! | M29: =_xlfn.IFS(L29<80%,"A",L29<=95%,"B",L29>95%,"C") -> #DIV/0!
D30: =C30/C$42 -> #DIV/0! | E30: =D30+E29 -> #DIV/0! | F30: =IF(AND(E30<=0),"C",IF(E30<=0.8,"A",IF(E30<=0.95,"B","C"))) -> #DIV/0! | G30: =VLOOKUP(B$22:B$42,I$22:M$42,5,0) -> #N/A | K30: =J30/J$42 -> #DIV/0! | L30: =K30+L29 -> #DIV/0! | M30: =_xlfn.IFS(L30<80%,"A",L30<=95%,"B",L30>95%,"C") -> #DIV/0!
D31: =C31/C$42 -> #DIV/0! | E31: =D31+E30 -> #DIV/0! | F31: =IF(AND(E31<=0),"C",IF(E31<=0.8,"A",IF(E31<=0.95,"B","C"))) -> #DIV/0! | G31: =VLOOKUP(B$22:B$42,I$22:M$42,5,0) -> #N/A | K31: =J31/J$42 -> #DIV/0! | L31: =K31+L30 -> #DIV/0! | M31: =_xlfn.IFS(L31<80%,"A",L31<=95%,"B",L31>95%,"C") -> #DIV/0!
D32: =C32/C$42 -> #DIV/0! | E32: =D32+E31 -> #DIV/0! | F32: =IF(AND(E32<=0),"C",IF(E32<=0.8,"A",IF(E32<=0.95,"B","C"))) -> #DIV/0! | G32: =VLOOKUP(B$22:B$42,I$22:M$42,5,0) -> #N/A | K32: =J32/J$42 -> #DIV/0! | L32: =K32+L31 -> #DIV/0! | M32: =_xlfn.IFS(L32<80%,"A",L32<=95%,"B",L32>95%,"C") -> #DIV/0!
D33: =C33/C$42 -> #DIV/0! | E33: =D33+E32 -> #DIV/0! | F33: =IF(AND(E33<=0),"C",IF(E33<=0.8,"A",IF(E33<=0.95,"B","C"))) -> #DIV/0! | G33: =VLOOKUP(B$22:B$42,I$22:M$42,5,0) -> #N/A | K33: =J33/J$42 -> #DIV/0! | L33: =K33+L32 -> #DIV/0! | M33: =_xlfn.IFS(L33<80%,"A",L33<=95%,"B",L33>95%,"C") -> #DIV/0!
D34: =C34/C$42 -> #DIV/0! | E34: =D34+E33 -> #DIV/0! | F34: =IF(AND(E34<=0),"C",IF(E34<=0.8,"A",IF(E34<=0.95,"B","C"))) -> #DIV/0! | G34: =VLOOKUP(B$22:B$42,I$22:M$42,5,0) -> #N/A | K34: =J34/J$42 -> #DIV/0! | L34: =K34+L33 -> #DIV/0! | M34: =_xlfn.IFS(L34<80%,"A",L34<=95%,"B",L34>95%,"C") -> #DIV/0!
... D41: =C41/C$42 -> #DIV/0! | E41: =D41+E40 -> #DIV/0! | F41: =IF(AND(E41<=0),"C",IF(E41<=0.8,"A",IF(E41<=0.95,"B","C"))) -> #DIV/0! | G41: =VLOOKUP(B$22:B$42,I$22:M$42,5,0) -> #N/A | K41: =J41/J$42 -> #DIV/0! | L41: =K41+L40 -> #DIV/0! | M41: =_xlfn.IFS(L41<80%,"A",L41<=95%,"B",L41>95%,"C") -> #DIV/0!
C42: =SUM(C22:C41) -> 0 | D42: =SUM(D22:D41) -> #DIV/0! | J42: =SUM(J22:J41) -> 0 | K42: =SUM(K22:K41) -> #DIV/0!

Sheet АВС АПРЕЛЬ
B2: ОЧКИ
C3: Прибыль | D3: % прибыль | E3: Доля | F3: ABC прибыль | G3: ABC кол-во | J3: Кол-во | K3: % кол-во | L3: Доля | M3: ABC кол-во
B4: MR8854 C2 | C4: =АПРЕЛЬ!AE8 -> 35105.114 | D4: =C4/C$18 -> 0.33019628 | E4: =D4 -> 0.33019628 | F4: =IF(AND(E4<=0),"C",IF(E4<=0.8,"A",IF(E4<=0.95,"B","C"))) -> A | G4: =VLOOKUP(B$4:B$17,I$4:M$17,5,0) -> A | I4: MR8854 C2 | J4: =АПРЕЛЬ!R8 -> 45 | K4: =J4/J$18 -> 0.18367347 | L4: =K4 -> 0.18367347 | M4: =_xlfn.IFS(L4<80%,"A",L4<=95%,"B",L4>95%,"C") -> A
B5: qs коричневые | C5: =АПРЕЛЬ!AE7 -> 14546.256 | D5: =C5/C$18 -> 0.13682108 | E5: =D5+E4 -> 0.46701736 | F5: =IF(AND(E5<=0),"C",IF(E5<=0.8,"A",IF(E5<=0.95,"B","C"))) -> A | G5: =VLOOKUP(B$4:B$17,I$4:M$17,5,0) -> A | I5: flip коричневый | J5: =АПРЕЛЬ!R16 -> 36 | K5: =J5/J$18 -> 0.14693878 | L5: =K5+L4 -> 0.33061224 | M5: =_xlfn.IFS(L5<80%,"A",L5<=95%,"B",L5>95%,"C") -> A
B6: flip коричневый | C6: =АПРЕЛЬ!AE16 -> 13899.136 | D6: =C6/C$18 -> 0.13073431 | E6: =D6+E5 -> 0.59775167 | F6: =IF(AND(E6<=0),"C",IF(E6<=0.8,"A",IF(E6<=0.95,"B","C"))) -> A | G6: =VLOOKUP(B$4:B$17,I$4:M$17,5,0) -> A | I6: th коричн | J6: =АПРЕЛЬ!R12 -> 30 | K6: =J6/J$18 -> 0.12244898 | L6: =K6+L5 -> 0.45306122 | M6: =_xlfn.IFS(L6<80%,"A",L6<=95%,"B",L6>95%,"C") -> A
B7: th коричн | C7: =АПРЕЛЬ!AE12 -> 12107.266 | D7: =C7/C$18 -> 0.11388011 | E7: =D7+E6 -> 0.71163178 | F7: =IF(AND(E7<=0),"C",IF(E7<=0.8,"A",IF(E7<=0.95,"B","C"))) -> A | G7: =VLOOKUP(B$4:B$17,I$4:M$17,5,0) -> A | I7: qs коричневые | J7: =АПРЕЛЬ!R7 -> 29 | K7: =J7/J$18 -> 0.11836735 | L7: =K7+L6 -> 0.57142857 | M7: =_xlfn.IFS(L7<80%,"A",L7<=95%,"B",L7>95%,"C") -> A
B8: flip черный | C8: =АПРЕЛЬ!AE13 -> 10690.46 | D8: =C8/C$18 -> 0.10055373 | E8: =D8+E7 -> 0.81218551 | F8: =IF(AND(E8<=0),"C",IF(E8<=0.8,"A",IF(E8<=0.95,"B","C"))) -> B | G8: =VLOOKUP(B$4:B$17,I$4:M$17,5,0) -> A | I8: flip черный | J8: =АПРЕЛЬ!R13 -> 28 | K8: =J8/J$18 -> 0.11428571 | L8: =K8+L7 -> 0.68571429 | M8: =_xlfn.IFS(L8<80%,"A",L8<=95%,"B",L8>95%,"C") -> A
B9: th желт | C9: =АПРЕЛЬ!AE11 -> 8078.479 | D9: =C9/C$18 -> 0.075985616 | E9: =D9+E8 -> 0.88817113 | F9: =IF(AND(E9<=0),"C",IF(E9<=0.8,"A",IF(E9<=0.95,"B","C"))) -> B | G9: =VLOOKUP(B$4:B$17,I$4:M$17,5,0) -> A | I9: th желт | J9: =АПРЕЛЬ!R11 -> 27 | K9: =J9/J$18 -> 0.11020408 | L9: =K9+L8 -> 0.79591837 | M9: =_xlfn.IFS(L9<80%,"A",L9<=95%,"B",L9>95%,"C") -> A
B10: th син | C10: =АПРЕЛЬ!AE10 -> 4506.226 | D10: =C10/C$18 -> 0.042385251 | E10: =D10+E9 -> 0.93055638 | F10: =IF(AND(E10<=0),"C",IF(E10<=0.8,"A",IF(E10<=0.95,"B","C"))) -> B | G10: =VLOOKUP(B$4:B$17,I$4:M$17,5,0) -> A | I10: qs черные | J10: =АПРЕЛЬ!R4 -> 16 | K10: =J10/J$18 -> 0.065306122 | L10: =K10+L9 -> 0.86122449 | M10: =_xlfn.IFS(L10<80%,"A",L10<=95%,"B",L10>95%,"C") -> B
B11: qs черные | C11: =АПРЕЛЬ!AE4 -> 2967.8152 | D11: =C11/C$18 -> 0.027915065 | E11: =D11+E10 -> 0.95847144 | F11: =IF(AND(E11<=0),"C",IF(E11<=0.8,"A",IF(E11<=0.95,"B","C"))) -> C | G11: =VLOOKUP(B$4:B$17,I$4:M$17,5,0) -> B | I11: черные с железкой классика | J11: =АПРЕЛЬ!R3 -> 8 | K11: =J11/J$18 -> 0.032653061 | L11: =K11+L10 -> 0.89387755 | M11: =_xlfn.IFS(L11<80%,"A",L11<=95%,"B",L11>95%,"C") -> B
B12: flip синий | C12: =АПРЕЛЬ!AE14 -> 2617.7859 | D12: =C12/C$18 -> 0.024622714 | E12: =D12+E5 -> 0.49164007 | F12: =IF(AND(E12<=0),"C",IF(E12<=0.8,"A",IF(E12<=0.95,"B","C"))) -> A | G12: =VLOOKUP(B$4:B$17,I$4:M$17,5,0) -> A | I12: qs синие | J12: =АПРЕЛЬ!R5 -> 5 | K12: =J12/J$18 -> 0.020408163 | L12: =K12+L5 -> 0.35102041 | M12: =_xlfn.IFS(L12<80%,"A",L12<=95%,"B",L12>95%,"C") -> A
B13: черные с железкой классика | C13: =АПРЕЛЬ!AE3 -> 1493.3378 | D13: =C13/C$18 -> 0.014046232 | E13: =D13+E12 -> 0.5056863 | F13: =IF(AND(E13<=0),"C",IF(E13<=0.8,"A",IF(E13<=0.95,"B","C"))) -> A | G13: =VLOOKUP(B$4:B$17,I$4:M$17,5,0) -> B | I13: qs желтые | J13: =АПРЕЛЬ!R6 -> 5 | K13: =J13/J$18 -> 0.020408163 | L13: =K13+L12 -> 0.37142857 | M13: =_xlfn.IFS(L13<80%,"A",L13<=95%,"B",L13>95%,"C") -> A
B14: th черн | C14: =АПРЕЛЬ!AE9 -> 1483.0744 | D14: =C14/C$18 -> 0.013949696 | E14: =D14+E13 -> 0.519636 | F14: =IF(AND(E14<=0),"C",IF(E14<=0.8,"A",IF(E14<=0.95,"B","C"))) -> A | G14: =VLOOKUP(B$4:B$17,I$4:M$17,5,0) -> A | I14: th син | J14: =АПРЕЛЬ!R10 -> 5 | K14: =J14/J$18 -> 0.020408163 | L14: =K14+L13 -> 0.39183673 | M14: =_xlfn.IFS(L14<80%,"A",L14<=95%,"B",L14>95%,"C") -> A
B15: qs синие | C15: =АПРЕЛЬ!AE5 -> 175.21135 | D15: =C15/C$18 -> 0.0016480259 | E15: =D15+E14 -> 0.52128402 | F15: =IF(AND(E15<=0),"C",IF(E15<=0.8,"A",IF(E15<=0.95,"B","C"))) -> A | G15: =VLOOKUP(B$4:B$17,I$4:M$17,5,0) -> A | I15: flip синий | J15: =АПРЕЛЬ!R14 -> 4 | K15: =J15/J$18 -> 0.016326531 | L15: =K15+L14 -> 0.40816327 | M15: =_xlfn.IFS(L15<80%,"A",L15<=95%,"B",L15>95%,"C") -> A
B16: flip жел | C16: =АПРЕЛЬ!AE15 -> -601.84919 | D16: =C16/C$18 -> -0.005660952 | E16: =D16+E15 -> 0.51562307 | F16: =IF(AND(E16<=0),"C",IF(E16<=0.8,"A",IF(E16<=0.95,"B","C"))) -> A | G16: =VLOOKUP(B$4:B$17,I$4:M$17,5,0) -> A | I16: flip жел | J16: =АПРЕЛЬ!R15 -> 4 | K16: =J16/J$18 -> 0.016326531 | L16: =K16+L15 -> 0.4244898 | M16: =_xlfn.IFS(L16<80%,"A",L16<=95%,"B",L16>95%,"C") -> A
B17: qs желтые | C17: =АПРЕЛЬ!AE6 -> -752.41426 | D17: =C17/C$18 -> -0.0070771566 | E17: =D17+E14 -> 0.51255884 | F17: =IF(AND(E17<=0),"C",IF(E17<=0.8,"A",IF(E17<=0.95,"B","C"))) -> A | G17: =VLOOKUP(B$4:B$17,I$4:M$17,5,0) -> A | I17: th черн | J17: =АПРЕЛЬ!R9 -> 3 | K17: =J17/J$18 -> 0.012244898 | L17: =K17+L14 -> 0.40408163 | M17: =_xlfn.IFS(L17<80%,"A",L17<=95%,"B",L17>95%,"C") -> A
C18: =SUM(C4:C17) -> 106315.9 | D18: =SUM(D4:D17) -> 1 | J18: =SUM(J4:J17) -> 245 | K18: =SUM(K4:K17) -> 1
C21: Прибыль | D21: % прибыль | E21: Доля | F21: ABC прибыль | G21: ABC кол-во | J21: Кол-во | K21: % кол-во | L21: Доля | M21: ABC кол-во
D22: =C22/C$42 -> #DIV/0! | E22: =D22 -> #DIV/0! | F22: =IF(AND(E22<=0),"C",IF(E22<=0.8,"A",IF(E22<=0.95,"B","C"))) -> #DIV/0! | G22: =VLOOKUP(B$22:B$42,I$22:M$42,5,0) -> #N/A | K22: =J22/J$42 -> #DIV/0! | L22: =K22 -> #DIV/0! | M22: =_xlfn.IFS(L22<80%,"A",L22<=95%,"B",L22>95%,"C") -> #DIV/0!
D23: =C23/C$42 -> #DIV/0! | E23: =D23+E22 -> #DIV/0! | F23: =IF(AND(E23<=0),"C",IF(E23<=0.8,"A",IF(E23<=0.95,"B","C"))) -> #DIV/0! | G23: =VLOOKUP(B$22:B$42,I$22:M$42,5,0) -> #N/A | K23: =J23/J$42 -> #DIV/0! | L23: =K23+L22 -> #DIV/0! | M23: =_xlfn.IFS(L23<80%,"A",L23<=95%,"B",L23>95%,"C") -> #DIV/0!
D24: =C24/C$42 -> #DIV/0! | E24: =D24+E23 -> #DIV/0! | F24: =IF(AND(E24<=0),"C",IF(E24<=0.8,"A",IF(E24<=0.95,"B","C"))) -> #DIV/0! | G24: =VLOOKUP(B$22:B$42,I$22:M$42,5,0) -> #N/A | K24: =J24/J$42 -> #DIV/0! | L24: =K24+L23 -> #DIV/0! | M24: =_xlfn.IFS(L24<80%,"A",L24<=95%,"B",L24>95%,"C") -> #DIV/0!
D25: =C25/C$42 -> #DIV/0! | E25: =D25+E24 -> #DIV/0! | F25: =IF(AND(E25<=0),"C",IF(E25<=0.8,"A",IF(E25<=0.95,"B","C"))) -> #DIV/0! | G25: =VLOOKUP(B$22:B$42,I$22:M$42,5,0) -> #N/A | K25: =J25/J$42 -> #DIV/0! | L25: =K25+L24 -> #DIV/0! | M25: =_xlfn.IFS(L25<80%,"A",L25<=95%,"B",L25>95%,"C") -> #DIV/0!
D26: =C26/C$42 -> #DIV/0! | E26: =D26+E25 -> #DIV/0! | F26: =IF(AND(E26<=0),"C",IF(E26<=0.8,"A",IF(E26<=0.95,"B","C"))) -> #DIV/0! | G26: =VLOOKUP(B$22:B$42,I$22:M$42,5,0) -> #N/A | K26: =J26/J$42 -> #DIV/0! | L26: =K26+L25 -> #DIV/0! | M26: =_xlfn.IFS(L26<80%,"A",L26<=95%,"B",L26>95%,"C") -> #DIV/0!
D27: =C27/C$42 -> #DIV/0! | E27: =D27+E26 -> #DIV/0! | F27: =IF(AND(E27<=0),"C",IF(E27<=0.8,"A",IF(E27<=0.95,"B","C"))) -> #DIV/0! | G27: =VLOOKUP(B$22:B$42,I$22:M$42,5,0) -> #N/A | K27: =J27/J$42 -> #DIV/0! | L27: =K27+L26 -> #DIV/0! | M27: =_xlfn.IFS(L27<80%,"A",L27<=95%,"B",L27>95%,"C") -> #DIV/0!
D28: =C28/C$42 -> #DIV/0! | E28: =D28+E27 -> #DIV/0! | F28: =IF(AND(E28<=0),"C",IF(E28<=0.8,"A",IF(E28<=0.95,"B","C"))) -> #DIV/0! | G28: =VLOOKUP(B$22:B$42,I$22:M$42,5,0) -> #N/A | K28: =J28/J$42 -> #DIV/0! | L28: =K28+L27 -> #DIV/0! | M28: =_xlfn.IFS(L28<80%,"A",L28<=95%,"B",L28>95%,"C") -> #DIV/0!
D29: =C29/C$42 -> #DIV/0! | E29: =D29+E28 -> #DIV/0! | F29: =IF(AND(E29<=0),"C",IF(E29<=0.8,"A",IF(E29<=0.95,"B","C"))) -> #DIV/0! | G29: =VLOOKUP(B$22:B$42,I$22:M$42,5,0) -> #N/A | K29: =J29/J$42 -> #DIV/0! | L29: =K29+L28 -> #DIV/0! | M29: =_xlfn.IFS(L29<80%,"A",L29<=95%,"B",L29>95%,"C") -> #DIV/0!
D30: =C30/C$42 -> #DIV/0! | E30: =D30+E29 -> #DIV/0! | F30: =IF(AND(E30<=0),"C",IF(E30<=0.8,"A",IF(E30<=0.95,"B","C"))) -> #DIV/0! | G30: =VLOOKUP(B$22:B$42,I$22:M$42,5,0) -> #N/A | K30: =J30/J$42 -> #DIV/0! | L30: =K30+L29 -> #DIV/0! | M30: =_xlfn.IFS(L30<80%,"A",L30<=95%,"B",L30>95%,"C") -> #DIV/0!
D31: =C31/C$42 -> #DIV/0! | E31: =D31+E30 -> #DIV/0! | F31: =IF(AND(E31<=0),"C",IF(E31<=0.8,"A",IF(E31<=0.95,"B","C"))) -> #DIV/0! | G31: =VLOOKUP(B$22:B$42,I$22:M$42,5,0) -> #N/A | K31: =J31/J$42 -> #DIV/0! | L31: =K31+L30 -> #DIV/0! | M31: =_xlfn.IFS(L31<80%,"A",L31<=95%,"B",L31>95%,"C") -> #DIV/0!
D32: =C32/C$42 -> #DIV/0! | E32: =D32+E31 -> #DIV/0! | F32: =IF(AND(E32<=0),"C",IF(E32<=0.8,"A",IF(E32<=0.95,"B","C"))) -> #DIV/0! | G32: =VLOOKUP(B$22:B$42,I$22:M$42,5,0) -> #N/A | K32: =J32/J$42 -> #DIV/0! | L32: =K32+L31 -> #DIV/0! | M32: =_xlfn.IFS(L32<80%,"A",L32<=95%,"B",L32>95%,"C") -> #DIV/0!
D33: =C33/C$42 -> #DIV/0! | E33: =D33+E32 -> #DIV/0! | F33: =IF(AND(E33<=0),"C",IF(E33<=0.8,"A",IF(E33<=0.95,"B","C"))) -> #DIV/0! | G33: =VLOOKUP(B$22:B$42,I$22:M$42,5,0) -> #N/A | K33: =J33/J$42 -> #DIV/0! | L33: =K33+L32 -> #DIV/0! | M33: =_xlfn.IFS(L33<80%,"A",L33<=95%,"B",L33>95%,"C") -> #DIV/0!
D34: =C34/C$42 -> #DIV/0! | E34: =D34+E33 -> #DIV/0! | F34: =IF(AND(E34<=0),"C",IF(E34<=0.8,"A",IF(E34<=0.95,"B","C"))) -> #DIV/0! | G34: =VLOOKUP(B$22:B$42,I$22:M$42,5,0) -> #N/A | K34: =J34/J$42 -> #DIV/0! | L34: =K34+L33 -> #DIV/0! | M34: =_xlfn.IFS(L34<80%,"A",L34<=95%,"B",L34>95%,"C") -> #DIV/0!
... D41: =C41/C$42 -> #DIV/0! | E41: =D41+E40 -> #DIV/0! | F41: =IF(AND(E41<=0),"C",IF(E41<=0.8,"A",IF(E41<=0.95,"B","C"))) -> #DIV/0! | G41: =VLOOKUP(B$22:B$42,I$22:M$42,5,0) -> #N/A | K41: =J41/J$42 -> #DIV/0! | L41: =K41+L40 -> #DIV/0! | M41: =_xlfn.IFS(L41<80%,"A",L41<=95%,"B",L41>95%,"C") -> #DIV/0!
C42: =SUM(C22:C41) -> 0 | D42: =SUM(D22:D41) -> #DIV/0! | J42: =SUM(J22:J41) -> 0 | K42: =SUM(K22:K41) -> #DIV/0!

Sheet АВС 27.04-03.05
B2: ОЧКИ
C3: Прибыль | D3: % прибыль | E3: Доля | F3: ABC прибыль | G3: ABC кол-во | J3: Кол-во | K3: % кол-во | L3: Доля | M3: ABC кол-во
B4: MR8854 C2 | C4: ='Юнит 27.04-03.05'!AE8 -> 7669.0155 | D4: =C4/C$18 -> 0.70327279 | E4: =D4 -> 0.70327279 | F4: =IF(AND(E4<=0),"C",IF(E4<=0.8,"A",IF(E4<=0.95,"B","C"))) -> A | G4: =VLOOKUP(B$4:B$17,I$4:M$17,5,0) -> A | I4: MR8854 C2 | J4: ='Юнит 27.04-03.05'!R8 -> 10 | K4: =J4/J$18 -> 0.25641026 | L4: =K4 -> 0.25641026 | M4: =_xlfn.IFS(L4<80%,"A",L4<=95%,"B",L4>95%,"C") -> A
B5: flip коричневый | C5: ='Юнит 27.04-03.05'!AE16 -> 4329.046 | D5: =C5/C$18 -> 0.3969871 | E5: =D5+E4 -> 1.1002599 | F5: =IF(AND(E5<=0),"C",IF(E5<=0.8,"A",IF(E5<=0.95,"B","C"))) -> C | G5: =VLOOKUP(B$4:B$17,I$4:M$17,5,0) -> A | I5: flip коричневый | J5: ='Юнит 27.04-03.05'!R16 -> 8 | K5: =J5/J$18 -> 0.20512821 | L5: =K5+L4 -> 0.46153846 | M5: =_xlfn.IFS(L5<80%,"A",L5<=95%,"B",L5>95%,"C") -> A
B6: flip черный | C6: ='Юнит 27.04-03.05'!AE13 -> 2163.6437 | D6: =C6/C$18 -> 0.19841291 | E6: =D6+E5 -> 1.2986728 | F6: =IF(AND(E6<=0),"C",IF(E6<=0.8,"A",IF(E6<=0.95,"B","C"))) -> C | G6: =VLOOKUP(B$4:B$17,I$4:M$17,5,0) -> A | I6: th коричн | J6: ='Юнит 27.04-03.05'!R12 -> 4 | K6: =J6/J$18 -> 0.1025641 | L6: =K6+L5 -> 0.56410256 | M6: =_xlfn.IFS(L6<80%,"A",L6<=95%,"B",L6>95%,"C") -> A
B7: flip синий | C7: ='Юнит 27.04-03.05'!AE14 -> 1607.7511 | D7: =C7/C$18 -> 0.14743582 | E7: =D7+E6 -> 1.4461086 | F7: =IF(AND(E7<=0),"C",IF(E7<=0.8,"A",IF(E7<=0.95,"B","C"))) -> C | G7: =VLOOKUP(B$4:B$17,I$4:M$17,5,0) -> A | I7: flip черный | J7: ='Юнит 27.04-03.05'!R13 -> 4 | K7: =J7/J$18 -> 0.1025641 | L7: =K7+L6 -> 0.66666667 | M7: =_xlfn.IFS(L7<80%,"A",L7<=95%,"B",L7>95%,"C") -> A
B8: qs черные | C8: ='Юнит 27.04-03.05'!AE4 -> 1494.0485 | D8: =C8/C$18 -> 0.13700893 | E8: =D8+E7 -> 1.5831176 | F8: =IF(AND(E8<=0),"C",IF(E8<=0.8,"A",IF(E8<=0.95,"B","C"))) -> C | G8: =VLOOKUP(B$4:B$17,I$4:M$17,5,0) -> A | I8: flip синий | J8: ='Юнит 27.04-03.05'!R14 -> 3 | K8: =J8/J$18 -> 0.076923077 | L8: =K8+L7 -> 0.74358974 | M8: =_xlfn.IFS(L8<80%,"A",L8<=95%,"B",L8>95%,"C") -> A
B9: th черн | C9: ='Юнит 27.04-03.05'!AE9 -> 1481.39 | D9: =C9/C$18 -> 0.13584811 | E9: =D9+E8 -> 1.7189657 | F9: =IF(AND(E9<=0),"C",IF(E9<=0.8,"A",IF(E9<=0.95,"B","C"))) -> C | G9: =VLOOKUP(B$4:B$17,I$4:M$17,5,0) -> B | I9: qs черные | J9: ='Юнит 27.04-03.05'!R4 -> 2 | K9: =J9/J$18 -> 0.051282051 | L9: =K9+L8 -> 0.79487179 | M9: =_xlfn.IFS(L9<80%,"A",L9<=95%,"B",L9>95%,"C") -> A
B10: th коричн | C10: ='Юнит 27.04-03.05'!AE12 -> 726.32 | D10: =C10/C$18 -> 0.066605823 | E10: =D10+E9 -> 1.7855715 | F10: =IF(AND(E10<=0),"C",IF(E10<=0.8,"A",IF(E10<=0.95,"B","C"))) -> C | G10: =VLOOKUP(B$4:B$17,I$4:M$17,5,0) -> A | I10: th черн | J10: ='Юнит 27.04-03.05'!R9 -> 2 | K10: =J10/J$18 -> 0.051282051 | L10: =K10+L9 -> 0.84615385 | M10: =_xlfn.IFS(L10<80%,"A",L10<=95%,"B",L10>95%,"C") -> B
B11: th син | C11: ='Юнит 27.04-03.05'!AE10 -> -110.76661 | D11: =C11/C$18 -> -0.010157646 | E11: =D11+E10 -> 1.7754138 | F11: =IF(AND(E11<=0),"C",IF(E11<=0.8,"A",IF(E11<=0.95,"B","C"))) -> C | G11: =VLOOKUP(B$4:B$17,I$4:M$17,5,0) -> A | I11: th желт | J11: ='Юнит 27.04-03.05'!R11 -> 2 | K11: =J11/J$18 -> 0.051282051 | L11: =K11+L10 -> 0.8974359 | M11: =_xlfn.IFS(L11<80%,"A",L11<=95%,"B",L11>95%,"C") -> B
B12: flip жел | C12: ='Юнит 27.04-03.05'!AE15 -> -302.98724 | D12: =C12/C$18 -> -0.027784881 | E12: =D12+E5 -> 1.072475 | F12: =IF(AND(E12<=0),"C",IF(E12<=0.8,"A",IF(E12<=0.95,"B","C"))) -> C | G12: =VLOOKUP(B$4:B$17,I$4:M$17,5,0) -> A | I12: flip жел | J12: ='Юнит 27.04-03.05'!R15 -> 2 | K12: =J12/J$18 -> 0.051282051 | L12: =K12+L5 -> 0.51282051 | M12: =_xlfn.IFS(L12<80%,"A",L12<=95%,"B",L12>95%,"C") -> A
B13: th желт | C13: ='Юнит 27.04-03.05'!AE11 -> -364.19507 | D13: =C13/C$18 -> -0.03339783 | E13: =D13+E12 -> 1.0390772 | F13: =IF(AND(E13<=0),"C",IF(E13<=0.8,"A",IF(E13<=0.95,"B","C"))) -> C | G13: =VLOOKUP(B$4:B$17,I$4:M$17,5,0) -> B | I13: qs синие | J13: ='Юнит 27.04-03.05'!R5 -> 1 | K13: =J13/J$18 -> 0.025641026 | L13: =K13+L12 -> 0.53846154 | M13: =_xlfn.IFS(L13<80%,"A",L13<=95%,"B",L13>95%,"C") -> A
B14: черные с железкой классика | C14: ='Юнит 27.04-03.05'!AE3 -> -1682.1187 | D14: =C14/C$18 -> -0.15425556 | E14: =D14+E13 -> 0.88482162 | F14: =IF(AND(E14<=0),"C",IF(E14<=0.8,"A",IF(E14<=0.95,"B","C"))) -> B | G14: =VLOOKUP(B$4:B$17,I$4:M$17,5,0) -> A | I14: th син | J14: ='Юнит 27.04-03.05'!R10 -> 1 | K14: =J14/J$18 -> 0.025641026 | L14: =K14+L13 -> 0.56410256 | M14: =_xlfn.IFS(L14<80%,"A",L14<=95%,"B",L14>95%,"C") -> A
B15: qs синие | C15: ='Юнит 27.04-03.05'!AE5 -> -1848.952 | D15: =C15/C$18 -> -0.1695547 | E15: =D15+E14 -> 0.71526692 | F15: =IF(AND(E15<=0),"C",IF(E15<=0.8,"A",IF(E15<=0.95,"B","C"))) -> A | G15: =VLOOKUP(B$4:B$17,I$4:M$17,5,0) -> A | I15: черные с железкой классика | J15: ='Юнит 27.04-03.05'!R3 -> 0 | K15: =J15/J$18 -> 0 | L15: =K15+L14 -> 0.56410256 | M15: =_xlfn.IFS(L15<80%,"A",L15<=95%,"B",L15>95%,"C") -> A
B16: qs желтые | C16: ='Юнит 27.04-03.05'!AE6 -> -2099.3921 | D16: =C16/C$18 -> -0.19252084 | E16: =D16+E15 -> 0.52274608 | F16: =IF(AND(E16<=0),"C",IF(E16<=0.8,"A",IF(E16<=0.95,"B","C"))) -> A | G16: =VLOOKUP(B$4:B$17,I$4:M$17,5,0) -> A | I16: qs желтые | J16: ='Юнит 27.04-03.05'!R6 -> 0 | K16: =J16/J$18 -> 0 | L16: =K16+L15 -> 0.56410256 | M16: =_xlfn.IFS(L16<80%,"A",L16<=95%,"B",L16>95%,"C") -> A
B17: qs коричневые | C17: ='Юнит 27.04-03.05'!AE7 -> -2158.0508 | D17: =C17/C$18 -> -0.19790003 | E17: =D17+E14 -> 0.68692158 | F17: =IF(AND(E17<=0),"C",IF(E17<=0.8,"A",IF(E17<=0.95,"B","C"))) -> A | G17: =VLOOKUP(B$4:B$17,I$4:M$17,5,0) -> A | I17: qs коричневые | J17: ='Юнит 27.04-03.05'!R7 -> 0 | K17: =J17/J$18 -> 0 | L17: =K17+L14 -> 0.56410256 | M17: =_xlfn.IFS(L17<80%,"A",L17<=95%,"B",L17>95%,"C") -> A
C18: =SUM(C4:C17) -> 10904.752 | D18: =SUM(D4:D17) -> 1 | J18: =SUM(J4:J17) -> 39 | K18: =SUM(K4:K17) -> 1
C21: Прибыль | D21: % прибыль | E21: Доля | F21: ABC прибыль | G21: ABC кол-во | J21: Кол-во | K21: % кол-во | L21: Доля | M21: ABC кол-во
D22: =C22/C$42 -> #DIV/0! | E22: =D22 -> #DIV/0! | F22: =IF(AND(E22<=0),"C",IF(E22<=0.8,"A",IF(E22<=0.95,"B","C"))) -> #DIV/0! | G22: =VLOOKUP(B$22:B$42,I$22:M$42,5,0) -> #N/A | K22: =J22/J$42 -> #DIV/0! | L22: =K22 -> #DIV/0! | M22: =_xlfn.IFS(L22<80%,"A",L22<=95%,"B",L22>95%,"C") -> #DIV/0!
D23: =C23/C$42 -> #DIV/0! | E23: =D23+E22 -> #DIV/0! | F23: =IF(AND(E23<=0),"C",IF(E23<=0.8,"A",IF(E23<=0.95,"B","C"))) -> #DIV/0! | G23: =VLOOKUP(B$22:B$42,I$22:M$42,5,0) -> #N/A | K23: =J23/J$42 -> #DIV/0! | L23: =K23+L22 -> #DIV/0! | M23: =_xlfn.IFS(L23<80%,"A",L23<=95%,"B",L23>95%,"C") -> #DIV/0!
D24: =C24/C$42 -> #DIV/0! | E24: =D24+E23 -> #DIV/0! | F24: =IF(AND(E24<=0),"C",IF(E24<=0.8,"A",IF(E24<=0.95,"B","C"))) -> #DIV/0! | G24: =VLOOKUP(B$22:B$42,I$22:M$42,5,0) -> #N/A | K24: =J24/J$42 -> #DIV/0! | L24: =K24+L23 -> #DIV/0! | M24: =_xlfn.IFS(L24<80%,"A",L24<=95%,"B",L24>95%,"C") -> #DIV/0!
D25: =C25/C$42 -> #DIV/0! | E25: =D25+E24 -> #DIV/0! | F25: =IF(AND(E25<=0),"C",IF(E25<=0.8,"A",IF(E25<=0.95,"B","C"))) -> #DIV/0! | G25: =VLOOKUP(B$22:B$42,I$22:M$42,5,0) -> #N/A | K25: =J25/J$42 -> #DIV/0! | L25: =K25+L24 -> #DIV/0! | M25: =_xlfn.IFS(L25<80%,"A",L25<=95%,"B",L25>95%,"C") -> #DIV/0!
D26: =C26/C$42 -> #DIV/0! | E26: =D26+E25 -> #DIV/0! | F26: =IF(AND(E26<=0),"C",IF(E26<=0.8,"A",IF(E26<=0.95,"B","C"))) -> #DIV/0! | G26: =VLOOKUP(B$22:B$42,I$22:M$42,5,0) -> #N/A | K26: =J26/J$42 -> #DIV/0! | L26: =K26+L25 -> #DIV/0! | M26: =_xlfn.IFS(L26<80%,"A",L26<=95%,"B",L26>95%,"C") -> #DIV/0!
D27: =C27/C$42 -> #DIV/0! | E27: =D27+E26 -> #DIV/0! | F27: =IF(AND(E27<=0),"C",IF(E27<=0.8,"A",IF(E27<=0.95,"B","C"))) -> #DIV/0! | G27: =VLOOKUP(B$22:B$42,I$22:M$42,5,0) -> #N/A | K27: =J27/J$42 -> #DIV/0! | L27: =K27+L26 -> #DIV/0! | M27: =_xlfn.IFS(L27<80%,"A",L27<=95%,"B",L27>95%,"C") -> #DIV/0!
D28: =C28/C$42 -> #DIV/0! | E28: =D28+E27 -> #DIV/0! | F28: =IF(AND(E28<=0),"C",IF(E28<=0.8,"A",IF(E28<=0.95,"B","C"))) -> #DIV/0! | G28: =VLOOKUP(B$22:B$42,I$22:M$42,5,0) -> #N/A | K28: =J28/J$42 -> #DIV/0! | L28: =K28+L27 -> #DIV/0! | M28: =_xlfn.IFS(L28<80%,"A",L28<=95%,"B",L28>95%,"C") -> #DIV/0!
D29: =C29/C$42 -> #DIV/0! | E29: =D29+E28 -> #DIV/0! | F29: =IF(AND(E29<=0),"C",IF(E29<=0.8,"A",IF(E29<=0.95,"B","C"))) -> #DIV/0! | G29: =VLOOKUP(B$22:B$42,I$22:M$42,5,0) -> #N/A | K29: =J29/J$42 -> #DIV/0! | L29: =K29+L28 -> #DIV/0! | M29: =_xlfn.IFS(L29<80%,"A",L29<=95%,"B",L29>95%,"C") -> #DIV/0!
D30: =C30/C$42 -> #DIV/0! | E30: =D30+E29 -> #DIV/0! | F30: =IF(AND(E30<=0),"C",IF(E30<=0.8,"A",IF(E30<=0.95,"B","C"))) -> #DIV/0! | G30: =VLOOKUP(B$22:B$42,I$22:M$42,5,0) -> #N/A | K30: =J30/J$42 -> #DIV/0! | L30: =K30+L29 -> #DIV/0! | M30: =_xlfn.IFS(L30<80%,"A",L30<=95%,"B",L30>95%,"C") -> #DIV/0!
D31: =C31/C$42 -> #DIV/0! | E31: =D31+E30 -> #DIV/0! | F31: =IF(AND(E31<=0),"C",IF(E31<=0.8,"A",IF(E31<=0.95,"B","C"))) -> #DIV/0! | G31: =VLOOKUP(B$22:B$42,I$22:M$42,5,0) -> #N/A | K31: =J31/J$42 -> #DIV/0! | L31: =K31+L30 -> #DIV/0! | M31: =_xlfn.IFS(L31<80%,"A",L31<=95%,"B",L31>95%,"C") -> #DIV/0!
D32: =C32/C$42 -> #DIV/0! | E32: =D32+E31 -> #DIV/0! | F32: =IF(AND(E32<=0),"C",IF(E32<=0.8,"A",IF(E32<=0.95,"B","C"))) -> #DIV/0! | G32: =VLOOKUP(B$22:B$42,I$22:M$42,5,0) -> #N/A | K32: =J32/J$42 -> #DIV/0! | L32: =K32+L31 -> #DIV/0! | M32: =_xlfn.IFS(L32<80%,"A",L32<=95%,"B",L32>95%,"C") -> #DIV/0!
D33: =C33/C$42 -> #DIV/0! | E33: =D33+E32 -> #DIV/0! | F33: =IF(AND(E33<=0),"C",IF(E33<=0.8,"A",IF(E33<=0.95,"B","C"))) -> #DIV/0! | G33: =VLOOKUP(B$22:B$42,I$22:M$42,5,0) -> #N/A | K33: =J33/J$42 -> #DIV/0! | L33: =K33+L32 -> #DIV/0! | M33: =_xlfn.IFS(L33<80%,"A",L33<=95%,"B",L33>95%,"C") -> #DIV/0!
D34: =C34/C$42 -> #DIV/0! | E34: =D34+E33 -> #DIV/0! | F34: =IF(AND(E34<=0),"C",IF(E34<=0.8,"A",IF(E34<=0.95,"B","C"))) -> #DIV/0! | G34: =VLOOKUP(B$22:B$42,I$22:M$42,5,0) -> #N/A | K34: =J34/J$42 -> #DIV/0! | L34: =K34+L33 -> #DIV/0! | M34: =_xlfn.IFS(L34<80%,"A",L34<=95%,"B",L34>95%,"C") -> #DIV/0!
... D41: =C41/C$42 -> #DIV/0! | E41: =D41+E40 -> #DIV/0! | F41: =IF(AND(E41<=0),"C",IF(E41<=0.8,"A",IF(E41<=0.95,"B","C"))) -> #DIV/0! | G41: =VLOOKUP(B$22:B$42,I$22:M$42,5,0) -> #N/A | K41: =J41/J$42 -> #DIV/0! | L41: =K41+L40 -> #DIV/0! | M41: =_xlfn.IFS(L41<80%,"A",L41<=95%,"B",L41>95%,"C") -> #DIV/0!
C42: =SUM(C22:C41) -> 0 | D42: =SUM(D22:D41) -> #DIV/0! | J42: =SUM(J22:J41) -> 0 | K42: =SUM(K22:K41) -> #DIV/0!

Sheet АВС 20-26.04
B2: ОЧКИ
C3: Прибыль | D3: % прибыль | E3: Доля | F3: ABC прибыль | G3: ABC кол-во | J3: Кол-во | K3: % кол-во | L3: Доля | M3: ABC кол-во
B4: MR8854 C2 | C4: ='Юнит 20-26.04'!AE8 -> 9074.2386 | D4: =C4/C$18 -> 0.57883583 | E4: =D4 -> 0.57883583 | F4: =IF(AND(E4<=0),"C",IF(E4<=0.8,"A",IF(E4<=0.95,"B","C"))) -> A | G4: =VLOOKUP(B$4:B$17,I$4:M$17,5,0) -> A | I4: MR8854 C2 | J4: ='Юнит 20-26.04'!R8 -> 12 | K4: =J4/J$18 -> 0.33333333 | L4: =K4 -> 0.33333333 | M4: =_xlfn.IFS(L4<80%,"A",L4<=95%,"B",L4>95%,"C") -> A
B5: flip коричневый | C5: ='Юнит 20-26.04'!AE16 -> 3982.1712 | D5: =C5/C$18 -> 0.25401838 | E5: =D5+E4 -> 0.8328542 | F5: =IF(AND(E5<=0),"C",IF(E5<=0.8,"A",IF(E5<=0.95,"B","C"))) -> B | G5: =VLOOKUP(B$4:B$17,I$4:M$17,5,0) -> A | I5: flip коричневый | J5: ='Юнит 20-26.04'!R16 -> 7 | K5: =J5/J$18 -> 0.19444444 | L5: =K5+L4 -> 0.52777778 | M5: =_xlfn.IFS(L5<80%,"A",L5<=95%,"B",L5>95%,"C") -> A
B6: qs коричневые | C6: ='Юнит 20-26.04'!AE7 -> 2844.3806 | D6: =C6/C$18 -> 0.18143995 | E6: =D6+E5 -> 1.0142942 | F6: =IF(AND(E6<=0),"C",IF(E6<=0.8,"A",IF(E6<=0.95,"B","C"))) -> C | G6: =VLOOKUP(B$4:B$17,I$4:M$17,5,0) -> A | I6: th коричн | J6: ='Юнит 20-26.04'!R12 -> 5 | K6: =J6/J$18 -> 0.13888889 | L6: =K6+L5 -> 0.66666667 | M6: =_xlfn.IFS(L6<80%,"A",L6<=95%,"B",L6>95%,"C") -> A
B7: th коричн | C7: ='Юнит 20-26.04'!AE12 -> 2346.3737 | D7: =C7/C$18 -> 0.14967263 | E7: =D7+E6 -> 1.1639668 | F7: =IF(AND(E7<=0),"C",IF(E7<=0.8,"A",IF(E7<=0.95,"B","C"))) -> C | G7: =VLOOKUP(B$4:B$17,I$4:M$17,5,0) -> A | I7: qs коричневые | J7: ='Юнит 20-26.04'!R7 -> 3 | K7: =J7/J$18 -> 0.083333333 | L7: =K7+L6 -> 0.75 | M7: =_xlfn.IFS(L7<80%,"A",L7<=95%,"B",L7>95%,"C") -> A
B8: th син | C8: ='Юнит 20-26.04'!AE10 -> 1016.4912 | D8: =C8/C$18 -> 0.064840871 | E8: =D8+E7 -> 1.2288077 | F8: =IF(AND(E8<=0),"C",IF(E8<=0.8,"A",IF(E8<=0.95,"B","C"))) -> C | G8: =VLOOKUP(B$4:B$17,I$4:M$17,5,0) -> A | I8: flip черный | J8: ='Юнит 20-26.04'!R13 -> 3 | K8: =J8/J$18 -> 0.083333333 | L8: =K8+L7 -> 0.83333333 | M8: =_xlfn.IFS(L8<80%,"A",L8<=95%,"B",L8>95%,"C") -> B
B9: th черн | C9: ='Юнит 20-26.04'!AE9 -> 380.08184 | D9: =C9/C$18 -> 0.024245008 | E9: =D9+E8 -> 1.2530527 | F9: =IF(AND(E9<=0),"C",IF(E9<=0.8,"A",IF(E9<=0.95,"B","C"))) -> C | G9: =VLOOKUP(B$4:B$17,I$4:M$17,5,0) -> A | I9: черные с железкой классика | J9: ='Юнит 20-26.04'!R3 -> 1 | K9: =J9/J$18 -> 0.027777778 | L9: =K9+L8 -> 0.86111111 | M9: =_xlfn.IFS(L9<80%,"A",L9<=95%,"B",L9>95%,"C") -> B
B10: flip черный | C10: ='Юнит 20-26.04'!AE13 -> 259.78018 | D10: =C10/C$18 -> 0.016571096 | E10: =D10+E9 -> 1.2696238 | F10: =IF(AND(E10<=0),"C",IF(E10<=0.8,"A",IF(E10<=0.95,"B","C"))) -> C | G10: =VLOOKUP(B$4:B$17,I$4:M$17,5,0) -> B | I10: qs черные | J10: ='Юнит 20-26.04'!R4 -> 1 | K10: =J10/J$18 -> 0.027777778 | L10: =K10+L9 -> 0.88888889 | M10: =_xlfn.IFS(L10<80%,"A",L10<=95%,"B",L10>95%,"C") -> B
B11: черные с железкой классика | C11: ='Юнит 20-26.04'!AE3 -> 145.88777 | D11: =C11/C$18 -> 0.0093060227 | E11: =D11+E10 -> 1.2789298 | F11: =IF(AND(E11<=0),"C",IF(E11<=0.8,"A",IF(E11<=0.95,"B","C"))) -> C | G11: =VLOOKUP(B$4:B$17,I$4:M$17,5,0) -> B | I11: qs синие | J11: ='Юнит 20-26.04'!R5 -> 1 | K11: =J11/J$18 -> 0.027777778 | L11: =K11+L10 -> 0.91666667 | M11: =_xlfn.IFS(L11<80%,"A",L11<=95%,"B",L11>95%,"C") -> B
B12: flip синий | C12: ='Юнит 20-26.04'!AE14 -> -148 | D12: =C12/C$18 -> -0.0094407593 | E12: =D12+E5 -> 0.82341345 | F12: =IF(AND(E12<=0),"C",IF(E12<=0.8,"A",IF(E12<=0.95,"B","C"))) -> B | G12: =VLOOKUP(B$4:B$17,I$4:M$17,5,0) -> A | I12: th черн | J12: ='Юнит 20-26.04'!R9 -> 1 | K12: =J12/J$18 -> 0.027777778 | L12: =K12+L5 -> 0.55555556 | M12: =_xlfn.IFS(L12<80%,"A",L12<=95%,"B",L12>95%,"C") -> A
B13: qs желтые | C13: ='Юнит 20-26.04'!AE6 -> -369.15267 | D13: =C13/C$18 -> -0.023547848 | E13: =D13+E12 -> 0.7998656 | F13: =IF(AND(E13<=0),"C",IF(E13<=0.8,"A",IF(E13<=0.95,"B","C"))) -> A | G13: =VLOOKUP(B$4:B$17,I$4:M$17,5,0) -> A | I13: th син | J13: ='Юнит 20-26.04'!R10 -> 1 | K13: =J13/J$18 -> 0.027777778 | L13: =K13+L12 -> 0.58333333 | M13: =_xlfn.IFS(L13<80%,"A",L13<=95%,"B",L13>95%,"C") -> A
B14: th желт | C14: ='Юнит 20-26.04'!AE11 -> -436.36797 | D14: =C14/C$18 -> -0.027835439 | E14: =D14+E13 -> 0.77203016 | F14: =IF(AND(E14<=0),"C",IF(E14<=0.8,"A",IF(E14<=0.95,"B","C"))) -> A | G14: =VLOOKUP(B$4:B$17,I$4:M$17,5,0) -> A | I14: th желт | J14: ='Юнит 20-26.04'!R11 -> 1 | K14: =J14/J$18 -> 0.027777778 | L14: =K14+L13 -> 0.61111111 | M14: =_xlfn.IFS(L14<80%,"A",L14<=95%,"B",L14>95%,"C") -> A
B15: qs синие | C15: ='Юнит 20-26.04'!AE5 -> -866.40135 | D15: =C15/C$18 -> -0.055266802 | E15: =D15+E14 -> 0.71676336 | F15: =IF(AND(E15<=0),"C",IF(E15<=0.8,"A",IF(E15<=0.95,"B","C"))) -> A | G15: =VLOOKUP(B$4:B$17,I$4:M$17,5,0) -> B | I15: qs желтые | J15: ='Юнит 20-26.04'!R6 -> 0 | K15: =J15/J$18 -> 0 | L15: =K15+L14 -> 0.61111111 | M15: =_xlfn.IFS(L15<80%,"A",L15<=95%,"B",L15>95%,"C") -> A
B16: flip жел | C16: ='Юнит 20-26.04'!AE15 -> -999.75776 | D16: =C16/C$18 -> -0.063773462 | E16: =D16+E15 -> 0.65298989 | F16: =IF(AND(E16<=0),"C",IF(E16<=0.8,"A",IF(E16<=0.95,"B","C"))) -> A | G16: =VLOOKUP(B$4:B$17,I$4:M$17,5,0) -> A | I16: flip синий | J16: ='Юнит 20-26.04'!R14 -> 0 | K16: =J16/J$18 -> 0 | L16: =K16+L15 -> 0.61111111 | M16: =_xlfn.IFS(L16<80%,"A",L16<=95%,"B",L16>95%,"C") -> A
B17: qs черные | C17: ='Юнит 20-26.04'!AE4 -> -1553.0202 | D17: =C17/C$18 -> -0.099065474 | E17: =D17+E14 -> 0.67296468 | F17: =IF(AND(E17<=0),"C",IF(E17<=0.8,"A",IF(E17<=0.95,"B","C"))) -> A | G17: =VLOOKUP(B$4:B$17,I$4:M$17,5,0) -> B | I17: flip жел | J17: ='Юнит 20-26.04'!R15 -> 0 | K17: =J17/J$18 -> 0 | L17: =K17+L14 -> 0.61111111 | M17: =_xlfn.IFS(L17<80%,"A",L17<=95%,"B",L17>95%,"C") -> A
C18: =SUM(C4:C17) -> 15676.705 | D18: =SUM(D4:D17) -> 1 | J18: =SUM(J4:J17) -> 36 | K18: =SUM(K4:K17) -> 1
C21: Прибыль | D21: % прибыль | E21: Доля | F21: ABC прибыль | G21: ABC кол-во | J21: Кол-во | K21: % кол-во | L21: Доля | M21: ABC кол-во
D22: =C22/C$42 -> #DIV/0! | E22: =D22 -> #DIV/0! | F22: =IF(AND(E22<=0),"C",IF(E22<=0.8,"A",IF(E22<=0.95,"B","C"))) -> #DIV/0! | G22: =VLOOKUP(B$22:B$42,I$22:M$42,5,0) -> #N/A | K22: =J22/J$42 -> #DIV/0! | L22: =K22 -> #DIV/0! | M22: =_xlfn.IFS(L22<80%,"A",L22<=95%,"B",L22>95%,"C") -> #DIV/0!
D23: =C23/C$42 -> #DIV/0! | E23: =D23+E22 -> #DIV/0! | F23: =IF(AND(E23<=0),"C",IF(E23<=0.8,"A",IF(E23<=0.95,"B","C"))) -> #DIV/0! | G23: =VLOOKUP(B$22:B$42,I$22:M$42,5,0) -> #N/A | K23: =J23/J$42 -> #DIV/0! | L23: =K23+L22 -> #DIV/0! | M23: =_xlfn.IFS(L23<80%,"A",L23<=95%,"B",L23>95%,"C") -> #DIV/0!
D24: =C24/C$42 -> #DIV/0! | E24: =D24+E23 -> #DIV/0! | F24: =IF(AND(E24<=0),"C",IF(E24<=0.8,"A",IF(E24<=0.95,"B","C"))) -> #DIV/0! | G24: =VLOOKUP(B$22:B$42,I$22:M$42,5,0) -> #N/A | K24: =J24/J$42 -> #DIV/0! | L24: =K24+L23 -> #DIV/0! | M24: =_xlfn.IFS(L24<80%,"A",L24<=95%,"B",L24>95%,"C") -> #DIV/0!
D25: =C25/C$42 -> #DIV/0! | E25: =D25+E24 -> #DIV/0! | F25: =IF(AND(E25<=0),"C",IF(E25<=0.8,"A",IF(E25<=0.95,"B","C"))) -> #DIV/0! | G25: =VLOOKUP(B$22:B$42,I$22:M$42,5,0) -> #N/A | K25: =J25/J$42 -> #DIV/0! | L25: =K25+L24 -> #DIV/0! | M25: =_xlfn.IFS(L25<80%,"A",L25<=95%,"B",L25>95%,"C") -> #DIV/0!
D26: =C26/C$42 -> #DIV/0! | E26: =D26+E25 -> #DIV/0! | F26: =IF(AND(E26<=0),"C",IF(E26<=0.8,"A",IF(E26<=0.95,"B","C"))) -> #DIV/0! | G26: =VLOOKUP(B$22:B$42,I$22:M$42,5,0) -> #N/A | K26: =J26/J$42 -> #DIV/0! | L26: =K26+L25 -> #DIV/0! | M26: =_xlfn.IFS(L26<80%,"A",L26<=95%,"B",L26>95%,"C") -> #DIV/0!
D27: =C27/C$42 -> #DIV/0! | E27: =D27+E26 -> #DIV/0! | F27: =IF(AND(E27<=0),"C",IF(E27<=0.8,"A",IF(E27<=0.95,"B","C"))) -> #DIV/0! | G27: =VLOOKUP(B$22:B$42,I$22:M$42,5,0) -> #N/A | K27: =J27/J$42 -> #DIV/0! | L27: =K27+L26 -> #DIV/0! | M27: =_xlfn.IFS(L27<80%,"A",L27<=95%,"B",L27>95%,"C") -> #DIV/0!
D28: =C28/C$42 -> #DIV/0! | E28: =D28+E27 -> #DIV/0! | F28: =IF(AND(E28<=0),"C",IF(E28<=0.8,"A",IF(E28<=0.95,"B","C"))) -> #DIV/0! | G28: =VLOOKUP(B$22:B$42,I$22:M$42,5,0) -> #N/A | K28: =J28/J$42 -> #DIV/0! | L28: =K28+L27 -> #DIV/0! | M28: =_xlfn.IFS(L28<80%,"A",L28<=95%,"B",L28>95%,"C") -> #DIV/0!
D29: =C29/C$42 -> #DIV/0! | E29: =D29+E28 -> #DIV/0! | F29: =IF(AND(E29<=0),"C",IF(E29<=0.8,"A",IF(E29<=0.95,"B","C"))) -> #DIV/0! | G29: =VLOOKUP(B$22:B$42,I$22:M$42,5,0) -> #N/A | K29: =J29/J$42 -> #DIV/0! | L29: =K29+L28 -> #DIV/0! | M29: =_xlfn.IFS(L29<80%,"A",L29<=95%,"B",L29>95%,"C") -> #DIV/0!
D30: =C30/C$42 -> #DIV/0! | E30: =D30+E29 -> #DIV/0! | F30: =IF(AND(E30<=0),"C",IF(E30<=0.8,"A",IF(E30<=0.95,"B","C"))) -> #DIV/0! | G30: =VLOOKUP(B$22:B$42,I$22:M$42,5,0) -> #N/A | K30: =J30/J$42 -> #DIV/0! | L30: =K30+L29 -> #DIV/0! | M30: =_xlfn.IFS(L30<80%,"A",L30<=95%,"B",L30>95%,"C") -> #DIV/0!
D31: =C31/C$42 -> #DIV/0! | E31: =D31+E30 -> #DIV/0! | F31: =IF(AND(E31<=0),"C",IF(E31<=0.8,"A",IF(E31<=0.95,"B","C"))) -> #DIV/0! | G31: =VLOOKUP(B$22:B$42,I$22:M$42,5,0) -> #N/A | K31: =J31/J$42 -> #DIV/0! | L31: =K31+L30 -> #DIV/0! | M31: =_xlfn.IFS(L31<80%,"A",L31<=95%,"B",L31>95%,"C") -> #DIV/0!
D32: =C32/C$42 -> #DIV/0! | E32: =D32+E31 -> #DIV/0! | F32: =IF(AND(E32<=0),"C",IF(E32<=0.8,"A",IF(E32<=0.95,"B","C"))) -> #DIV/0! | G32: =VLOOKUP(B$22:B$42,I$22:M$42,5,0) -> #N/A | K32: =J32/J$42 -> #DIV/0! | L32: =K32+L31 -> #DIV/0! | M32: =_xlfn.IFS(L32<80%,"A",L32<=95%,"B",L32>95%,"C") -> #DIV/0!
D33: =C33/C$42 -> #DIV/0! | E33: =D33+E32 -> #DIV/0! | F33: =IF(AND(E33<=0),"C",IF(E33<=0.8,"A",IF(E33<=0.95,"B","C"))) -> #DIV/0! | G33: =VLOOKUP(B$22:B$42,I$22:M$42,5,0) -> #N/A | K33: =J33/J$42 -> #DIV/0! | L33: =K33+L32 -> #DIV/0! | M33: =_xlfn.IFS(L33<80%,"A",L33<=95%,"B",L33>95%,"C") -> #DIV/0!
D34: =C34/C$42 -> #DIV/0! | E34: =D34+E33 -> #DIV/0! | F34: =IF(AND(E34<=0),"C",IF(E34<=0.8,"A",IF(E34<=0.95,"B","C"))) -> #DIV/0! | G34: =VLOOKUP(B$22:B$42,I$22:M$42,5,0) -> #N/A | K34: =J34/J$42 -> #DIV/0! | L34: =K34+L33 -> #DIV/0! | M34: =_xlfn.IFS(L34<80%,"A",L34<=95%,"B",L34>95%,"C") -> #DIV/0!
... D41: =C41/C$42 -> #DIV/0! | E41: =D41+E40 -> #DIV/0! | F41: =IF(AND(E41<=0),"C",IF(E41<=0.8,"A",IF(E41<=0.95,"B","C"))) -> #DIV/0! | G41: =VLOOKUP(B$22:B$42,I$22:M$42,5,0) -> #N/A | K41: =J41/J$42 -> #DIV/0! | L41: =K41+L40 -> #DIV/0! | M41: =_xlfn.IFS(L41<80%,"A",L41<=95%,"B",L41>95%,"C") -> #DIV/0!
C42: =SUM(C22:C41) -> 0 | D42: =SUM(D22:D41) -> #DIV/0! | J42: =SUM(J22:J41) -> 0 | K42: =SUM(K22:K41) -> #DIV/0!

Sheet АВС 13-19.04
B2: ОЧКИ
C3: Прибыль | D3: % прибыль | E3: Доля | F3: ABC прибыль | G3: ABC кол-во | J3: Кол-во | K3: % кол-во | L3: Доля | M3: ABC кол-во
B4: qs коричневые | C4: ='Юнит 13-19.04'!AE7 -> 5775.9908 | D4: =C4/C$18 -> 0.24067969 | E4: =D4 -> 0.24067969 | F4: =IF(AND(E4<=0),"C",IF(E4<=0.8,"A",IF(E4<=0.95,"B","C"))) -> A | G4: =VLOOKUP(B$4:B$17,I$4:M$17,5,0) -> A | I4: qs коричневые | J4: ='Юнит 13-19.04'!R7 -> 9 | K4: =J4/J$18 -> 0.16363636 | L4: =K4 -> 0.16363636 | M4: =_xlfn.IFS(L4<80%,"A",L4<=95%,"B",L4>95%,"C") -> A
B5: MR8854 C2 | C5: ='Юнит 13-19.04'!AE8 -> 3187.4615 | D5: =C5/C$18 -> 0.13281829 | E5: =D5+E4 -> 0.37349798 | F5: =IF(AND(E5<=0),"C",IF(E5<=0.8,"A",IF(E5<=0.95,"B","C"))) -> A | G5: =VLOOKUP(B$4:B$17,I$4:M$17,5,0) -> A | I5: MR8854 C2 | J5: ='Юнит 13-19.04'!R8 -> 7 | K5: =J5/J$18 -> 0.12727273 | L5: =K5+L4 -> 0.29090909 | M5: =_xlfn.IFS(L5<80%,"A",L5<=95%,"B",L5>95%,"C") -> A
B6: qs черные | C6: ='Юнит 13-19.04'!AE4 -> 3050.552 | D6: =C6/C$18 -> 0.12711341 | E6: =D6+E5 -> 0.50061139 | F6: =IF(AND(E6<=0),"C",IF(E6<=0.8,"A",IF(E6<=0.95,"B","C"))) -> A | G6: =VLOOKUP(B$4:B$17,I$4:M$17,5,0) -> A | I6: qs черные | J6: ='Юнит 13-19.04'!R4 -> 6 | K6: =J6/J$18 -> 0.10909091 | L6: =K6+L5 -> 0.4 | M6: =_xlfn.IFS(L6<80%,"A",L6<=95%,"B",L6>95%,"C") -> A
B7: flip черный | C7: ='Юнит 13-19.04'!AE13 -> 2998.7956 | D7: =C7/C$18 -> 0.12495678 | E7: =D7+E6 -> 0.62556817 | F7: =IF(AND(E7<=0),"C",IF(E7<=0.8,"A",IF(E7<=0.95,"B","C"))) -> A | G7: =VLOOKUP(B$4:B$17,I$4:M$17,5,0) -> A | I7: th коричн | J7: ='Юнит 13-19.04'!R12 -> 6 | K7: =J7/J$18 -> 0.10909091 | L7: =K7+L6 -> 0.50909091 | M7: =_xlfn.IFS(L7<80%,"A",L7<=95%,"B",L7>95%,"C") -> A
B8: черные с железкой классика | C8: ='Юнит 13-19.04'!AE3 -> 2140.6987 | D8: =C8/C$18 -> 0.089200749 | E8: =D8+E7 -> 0.71476892 | F8: =IF(AND(E8<=0),"C",IF(E8<=0.8,"A",IF(E8<=0.95,"B","C"))) -> A | G8: =VLOOKUP(B$4:B$17,I$4:M$17,5,0) -> A | I8: flip черный | J8: ='Юнит 13-19.04'!R13 -> 6 | K8: =J8/J$18 -> 0.10909091 | L8: =K8+L7 -> 0.61818182 | M8: =_xlfn.IFS(L8<80%,"A",L8<=95%,"B",L8>95%,"C") -> A
B9: qs синие | C9: ='Юнит 13-19.04'!AE5 -> 2047.4787 | D9: =C9/C$18 -> 0.085316366 | E9: =D9+E8 -> 0.80008529 | F9: =IF(AND(E9<=0),"C",IF(E9<=0.8,"A",IF(E9<=0.95,"B","C"))) -> B | G9: =VLOOKUP(B$4:B$17,I$4:M$17,5,0) -> A | I9: flip коричневый | J9: ='Юнит 13-19.04'!R16 -> 6 | K9: =J9/J$18 -> 0.10909091 | L9: =K9+L8 -> 0.72727273 | M9: =_xlfn.IFS(L9<80%,"A",L9<=95%,"B",L9>95%,"C") -> A
B10: flip синий | C10: ='Юнит 13-19.04'!AE14 -> 2041.4836 | D10: =C10/C$18 -> 0.085066555 | E10: =D10+E9 -> 0.88515184 | F10: =IF(AND(E10<=0),"C",IF(E10<=0.8,"A",IF(E10<=0.95,"B","C"))) -> B | G10: =VLOOKUP(B$4:B$17,I$4:M$17,5,0) -> A | I10: th желт | J10: ='Юнит 13-19.04'!R11 -> 4 | K10: =J10/J$18 -> 0.072727273 | L10: =K10+L9 -> 0.8 | M10: =_xlfn.IFS(L10<80%,"A",L10<=95%,"B",L10>95%,"C") -> B
B11: th син | C11: ='Юнит 13-19.04'!AE10 -> 1927.6036 | D11: =C11/C$18 -> 0.080321291 | E11: =D11+E10 -> 0.96547313 | F11: =IF(AND(E11<=0),"C",IF(E11<=0.8,"A",IF(E11<=0.95,"B","C"))) -> C | G11: =VLOOKUP(B$4:B$17,I$4:M$17,5,0) -> A | I11: qs желтые | J11: ='Юнит 13-19.04'!R6 -> 3 | K11: =J11/J$18 -> 0.054545455 | L11: =K11+L10 -> 0.85454545 | M11: =_xlfn.IFS(L11<80%,"A",L11<=95%,"B",L11>95%,"C") -> B
B12: qs желтые | C12: ='Юнит 13-19.04'!AE6 -> 1206.3503 | D12: =C12/C$18 -> 0.050267394 | E12: =D12+E5 -> 0.42376538 | F12: =IF(AND(E12<=0),"C",IF(E12<=0.8,"A",IF(E12<=0.95,"B","C"))) -> A | G12: =VLOOKUP(B$4:B$17,I$4:M$17,5,0) -> B | I12: черные с железкой классика | J12: ='Юнит 13-19.04'!R3 -> 2 | K12: =J12/J$18 -> 0.036363636 | L12: =K12+L5 -> 0.32727273 | M12: =_xlfn.IFS(L12<80%,"A",L12<=95%,"B",L12>95%,"C") -> A
B13: flip коричневый | C13: ='Юнит 13-19.04'!AE16 -> 1128.129 | D13: =C13/C$18 -> 0.047007993 | E13: =D13+E12 -> 0.47077337 | F13: =IF(AND(E13<=0),"C",IF(E13<=0.8,"A",IF(E13<=0.95,"B","C"))) -> A | G13: =VLOOKUP(B$4:B$17,I$4:M$17,5,0) -> A | I13: qs синие | J13: ='Юнит 13-19.04'!R5 -> 2 | K13: =J13/J$18 -> 0.036363636 | L13: =K13+L12 -> 0.36363636 | M13: =_xlfn.IFS(L13<80%,"A",L13<=95%,"B",L13>95%,"C") -> A
B14: th коричн | C14: ='Юнит 13-19.04'!AE12 -> 212.68045 | D14: =C14/C$18 -> 0.0088621792 | E14: =D14+E13 -> 0.47963555 | F14: =IF(AND(E14<=0),"C",IF(E14<=0.8,"A",IF(E14<=0.95,"B","C"))) -> A | G14: =VLOOKUP(B$4:B$17,I$4:M$17,5,0) -> A | I14: th син | J14: ='Юнит 13-19.04'!R10 -> 2 | K14: =J14/J$18 -> 0.036363636 | L14: =K14+L13 -> 0.4 | M14: =_xlfn.IFS(L14<80%,"A",L14<=95%,"B",L14>95%,"C") -> A
B15: flip жел | C15: ='Юнит 13-19.04'!AE15 -> -397.4739 | D15: =C15/C$18 -> -0.016562335 | E15: =D15+E14 -> 0.46307321 | F15: =IF(AND(E15<=0),"C",IF(E15<=0.8,"A",IF(E15<=0.95,"B","C"))) -> A | G15: =VLOOKUP(B$4:B$17,I$4:M$17,5,0) -> A | I15: flip синий | J15: ='Юнит 13-19.04'!R14 -> 2 | K15: =J15/J$18 -> 0.036363636 | L15: =K15+L14 -> 0.43636364 | M15: =_xlfn.IFS(L15<80%,"A",L15<=95%,"B",L15>95%,"C") -> A
B16: th черн | C16: ='Юнит 13-19.04'!AE9 -> -401.88 | D16: =C16/C$18 -> -0.016745933 | E16: =D16+E15 -> 0.44632728 | F16: =IF(AND(E16<=0),"C",IF(E16<=0.8,"A",IF(E16<=0.95,"B","C"))) -> A | G16: =VLOOKUP(B$4:B$17,I$4:M$17,5,0) -> A | I16: th черн | J16: ='Юнит 13-19.04'!R9 -> 0 | K16: =J16/J$18 -> 0 | L16: =K16+L15 -> 0.43636364 | M16: =_xlfn.IFS(L16<80%,"A",L16<=95%,"B",L16>95%,"C") -> A
B17: th желт | C17: ='Юнит 13-19.04'!AE11 -> -919.20717 | D17: =C17/C$18 -> -0.038302432 | E17: =D17+E14 -> 0.44133312 | F17: =IF(AND(E17<=0),"C",IF(E17<=0.8,"A",IF(E17<=0.95,"B","C"))) -> A | G17: =VLOOKUP(B$4:B$17,I$4:M$17,5,0) -> B | I17: flip жел | J17: ='Юнит 13-19.04'!R15 -> 0 | K17: =J17/J$18 -> 0 | L17: =K17+L14 -> 0.4 | M17: =_xlfn.IFS(L17<80%,"A",L17<=95%,"B",L17>95%,"C") -> A
C18: =SUM(C4:C17) -> 23998.663 | D18: =SUM(D4:D17) -> 1 | J18: =SUM(J4:J17) -> 55 | K18: =SUM(K4:K17) -> 1
C21: Прибыль | D21: % прибыль | E21: Доля | F21: ABC прибыль | G21: ABC кол-во | J21: Кол-во | K21: % кол-во | L21: Доля | M21: ABC кол-во
D22: =C22/C$42 -> #DIV/0! | E22: =D22 -> #DIV/0! | F22: =IF(AND(E22<=0),"C",IF(E22<=0.8,"A",IF(E22<=0.95,"B","C"))) -> #DIV/0! | G22: =VLOOKUP(B$22:B$42,I$22:M$42,5,0) -> #N/A | K22: =J22/J$42 -> #DIV/0! | L22: =K22 -> #DIV/0! | M22: =_xlfn.IFS(L22<80%,"A",L22<=95%,"B",L22>95%,"C") -> #DIV/0!
D23: =C23/C$42 -> #DIV/0! | E23: =D23+E22 -> #DIV/0! | F23: =IF(AND(E23<=0),"C",IF(E23<=0.8,"A",IF(E23<=0.95,"B","C"))) -> #DIV/0! | G23: =VLOOKUP(B$22:B$42,I$22:M$42,5,0) -> #N/A | K23: =J23/J$42 -> #DIV/0! | L23: =K23+L22 -> #DIV/0! | M23: =_xlfn.IFS(L23<80%,"A",L23<=95%,"B",L23>95%,"C") -> #DIV/0!
D24: =C24/C$42 -> #DIV/0! | E24: =D24+E23 -> #DIV/0! | F24: =IF(AND(E24<=0),"C",IF(E24<=0.8,"A",IF(E24<=0.95,"B","C"))) -> #DIV/0! | G24: =VLOOKUP(B$22:B$42,I$22:M$42,5,0) -> #N/A | K24: =J24/J$42 -> #DIV/0! | L24: =K24+L23 -> #DIV/0! | M24: =_xlfn.IFS(L24<80%,"A",L24<=95%,"B",L24>95%,"C") -> #DIV/0!
D25: =C25/C$42 -> #DIV/0! | E25: =D25+E24 -> #DIV/0! | F25: =IF(AND(E25<=0),"C",IF(E25<=0.8,"A",IF(E25<=0.95,"B","C"))) -> #DIV/0! | G25: =VLOOKUP(B$22:B$42,I$22:M$42,5,0) -> #N/A | K25: =J25/J$42 -> #DIV/0! | L25: =K25+L24 -> #DIV/0! | M25: =_xlfn.IFS(L25<80%,"A",L25<=95%,"B",L25>95%,"C") -> #DIV/0!
D26: =C26/C$42 -> #DIV/0! | E26: =D26+E25 -> #DIV/0! | F26: =IF(AND(E26<=0),"C",IF(E26<=0.8,"A",IF(E26<=0.95,"B","C"))) -> #DIV/0! | G26: =VLOOKUP(B$22:B$42,I$22:M$42,5,0) -> #N/A | K26: =J26/J$42 -> #DIV/0! | L26: =K26+L25 -> #DIV/0! | M26: =_xlfn.IFS(L26<80%,"A",L26<=95%,"B",L26>95%,"C") -> #DIV/0!
D27: =C27/C$42 -> #DIV/0! | E27: =D27+E26 -> #DIV/0! | F27: =IF(AND(E27<=0),"C",IF(E27<=0.8,"A",IF(E27<=0.95,"B","C"))) -> #DIV/0! | G27: =VLOOKUP(B$22:B$42,I$22:M$42,5,0) -> #N/A | K27: =J27/J$42 -> #DIV/0! | L27: =K27+L26 -> #DIV/0! | M27: =_xlfn.IFS(L27<80%,"A",L27<=95%,"B",L27>95%,"C") -> #DIV/0!
D28: =C28/C$42 -> #DIV/0! | E28: =D28+E27 -> #DIV/0! | F28: =IF(AND(E28<=0),"C",IF(E28<=0.8,"A",IF(E28<=0.95,"B","C"))) -> #DIV/0! | G28: =VLOOKUP(B$22:B$42,I$22:M$42,5,0) -> #N/A | K28: =J28/J$42 -> #DIV/0! | L28: =K28+L27 -> #DIV/0! | M28: =_xlfn.IFS(L28<80%,"A",L28<=95%,"B",L28>95%,"C") -> #DIV/0!
D29: =C29/C$42 -> #DIV/0! | E29: =D29+E28 -> #DIV/0! | F29: =IF(AND(E29<=0),"C",IF(E29<=0.8,"A",IF(E29<=0.95,"B","C"))) -> #DIV/0! | G29: =VLOOKUP(B$22:B$42,I$22:M$42,5,0) -> #N/A | K29: =J29/J$42 -> #DIV/0! | L29: =K29+L28 -> #DIV/0! | M29: =_xlfn.IFS(L29<80%,"A",L29<=95%,"B",L29>95%,"C") -> #DIV/0!
D30: =C30/C$42 -> #DIV/0! | E30: =D30+E29 -> #DIV/0! | F30: =IF(AND(E30<=0),"C",IF(E30<=0.8,"A",IF(E30<=0.95,"B","C"))) -> #DIV/0! | G30: =VLOOKUP(B$22:B$42,I$22:M$42,5,0) -> #N/A | K30: =J30/J$42 -> #DIV/0! | L30: =K30+L29 -> #DIV/0! | M30: =_xlfn.IFS(L30<80%,"A",L30<=95%,"B",L30>95%,"C") -> #DIV/0!
D31: =C31/C$42 -> #DIV/0! | E31: =D31+E30 -> #DIV/0! | F31: =IF(AND(E31<=0),"C",IF(E31<=0.8,"A",IF(E31<=0.95,"B","C"))) -> #DIV/0! | G31: =VLOOKUP(B$22:B$42,I$22:M$42,5,0) -> #N/A | K31: =J31/J$42 -> #DIV/0! | L31: =K31+L30 -> #DIV/0! | M31: =_xlfn.IFS(L31<80%,"A",L31<=95%,"B",L31>95%,"C") -> #DIV/0!
D32: =C32/C$42 -> #DIV/0! | E32: =D32+E31 -> #DIV/0! | F32: =IF(AND(E32<=0),"C",IF(E32<=0.8,"A",IF(E32<=0.95,"B","C"))) -> #DIV/0! | G32: =VLOOKUP(B$22:B$42,I$22:M$42,5,0) -> #N/A | K32: =J32/J$42 -> #DIV/0! | L32: =K32+L31 -> #DIV/0! | M32: =_xlfn.IFS(L32<80%,"A",L32<=95%,"B",L32>95%,"C") -> #DIV/0!
D33: =C33/C$42 -> #DIV/0! | E33: =D33+E32 -> #DIV/0! | F33: =IF(AND(E33<=0),"C",IF(E33<=0.8,"A",IF(E33<=0.95,"B","C"))) -> #DIV/0! | G33: =VLOOKUP(B$22:B$42,I$22:M$42,5,0) -> #N/A | K33: =J33/J$42 -> #DIV/0! | L33: =K33+L32 -> #DIV/0! | M33: =_xlfn.IFS(L33<80%,"A",L33<=95%,"B",L33>95%,"C") -> #DIV/0!
D34: =C34/C$42 -> #DIV/0! | E34: =D34+E33 -> #DIV/0! | F34: =IF(AND(E34<=0),"C",IF(E34<=0.8,"A",IF(E34<=0.95,"B","C"))) -> #DIV/0! | G34: =VLOOKUP(B$22:B$42,I$22:M$42,5,0) -> #N/A | K34: =J34/J$42 -> #DIV/0! | L34: =K34+L33 -> #DIV/0! | M34: =_xlfn.IFS(L34<80%,"A",L34<=95%,"B",L34>95%,"C") -> #DIV/0!
... D41: =C41/C$42 -> #DIV/0! | E41: =D41+E40 -> #DIV/0! | F41: =IF(AND(E41<=0),"C",IF(E41<=0.8,"A",IF(E41<=0.95,"B","C"))) -> #DIV/0! | G41: =VLOOKUP(B$22:B$42,I$22:M$42,5,0) -> #N/A | K41: =J41/J$42 -> #DIV/0! | L41: =K41+L40 -> #DIV/0! | M41: =_xlfn.IFS(L41<80%,"A",L41<=95%,"B",L41>95%,"C") -> #DIV/0!
C42: =SUM(C22:C41) -> 0 | D42: =SUM(D22:D41) -> #DIV/0! | J42: =SUM(J22:J41) -> 0 | K42: =SUM(K22:K41) -> #DIV/0!

Sheet АВС 06-12.04
B2: ОЧКИ
C3: Прибыль | D3: % прибыль | E3: Доля | F3: ABC прибыль | G3: ABC кол-во | J3: Кол-во | K3: % кол-во | L3: Доля | M3: ABC кол-во
B4: MR8854 C2 | C4: ='Юнит 06-12.04'!AE8 -> 10134.919 | D4: =C4/C$18 -> 0.33361767 | E4: =D4 -> 0.33361767 | F4: =IF(AND(E4<=0),"C",IF(E4<=0.8,"A",IF(E4<=0.95,"B","C"))) -> A | G4: =VLOOKUP(B$4:B$17,I$4:M$17,5,0) -> A | I4: flip коричневый | J4: ='Юнит 06-12.04'!R16 -> 15 | K4: =J4/J$18 -> 0.18292683 | L4: =K4 -> 0.18292683 | M4: =_xlfn.IFS(L4<80%,"A",L4<=95%,"B",L4>95%,"C") -> A
B5: th коричн | C5: ='Юнит 06-12.04'!AE12 -> 9483.5035 | D5: =C5/C$18 -> 0.31217461 | E5: =D5+E4 -> 0.64579228 | F5: =IF(AND(E5<=0),"C",IF(E5<=0.8,"A",IF(E5<=0.95,"B","C"))) -> A | G5: =VLOOKUP(B$4:B$17,I$4:M$17,5,0) -> A | I5: th коричн | J5: ='Юнит 06-12.04'!R12 -> 14 | K5: =J5/J$18 -> 0.17073171 | L5: =K5+L4 -> 0.35365854 | M5: =_xlfn.IFS(L5<80%,"A",L5<=95%,"B",L5>95%,"C") -> A
B6: flip коричневый | C6: ='Юнит 06-12.04'!AE16 -> 6610.6235 | D6: =C6/C$18 -> 0.21760616 | E6: =D6+E5 -> 0.86339844 | F6: =IF(AND(E6<=0),"C",IF(E6<=0.8,"A",IF(E6<=0.95,"B","C"))) -> B | G6: =VLOOKUP(B$4:B$17,I$4:M$17,5,0) -> A | I6: MR8854 C2 | J6: ='Юнит 06-12.04'!R8 -> 12 | K6: =J6/J$18 -> 0.14634146 | L6: =K6+L5 -> 0.5 | M6: =_xlfn.IFS(L6<80%,"A",L6<=95%,"B",L6>95%,"C") -> A
B7: th желт | C7: ='Юнит 06-12.04'!AE11 -> 3900.6564 | D7: =C7/C$18 -> 0.12840042 | E7: =D7+E6 -> 0.99179886 | F7: =IF(AND(E7<=0),"C",IF(E7<=0.8,"A",IF(E7<=0.95,"B","C"))) -> C | G7: =VLOOKUP(B$4:B$17,I$4:M$17,5,0) -> A | I7: th желт | J7: ='Юнит 06-12.04'!R11 -> 12 | K7: =J7/J$18 -> 0.14634146 | L7: =K7+L6 -> 0.64634146 | M7: =_xlfn.IFS(L7<80%,"A",L7<=95%,"B",L7>95%,"C") -> A
B8: qs коричневые | C8: ='Юнит 06-12.04'!AE7 -> 1898.8454 | D8: =C8/C$18 -> 0.062505521 | E8: =D8+E7 -> 1.0543044 | F8: =IF(AND(E8<=0),"C",IF(E8<=0.8,"A",IF(E8<=0.95,"B","C"))) -> C | G8: =VLOOKUP(B$4:B$17,I$4:M$17,5,0) -> A | I8: qs коричневые | J8: ='Юнит 06-12.04'!R7 -> 9 | K8: =J8/J$18 -> 0.1097561 | L8: =K8+L7 -> 0.75609756 | M8: =_xlfn.IFS(L8<80%,"A",L8<=95%,"B",L8>95%,"C") -> A
B9: flip черный | C9: ='Юнит 06-12.04'!AE13 -> 1677.1656 | D9: =C9/C$18 -> 0.055208344 | E9: =D9+E8 -> 1.1095127 | F9: =IF(AND(E9<=0),"C",IF(E9<=0.8,"A",IF(E9<=0.95,"B","C"))) -> C | G9: =VLOOKUP(B$4:B$17,I$4:M$17,5,0) -> B | I9: flip черный | J9: ='Юнит 06-12.04'!R13 -> 9 | K9: =J9/J$18 -> 0.1097561 | L9: =K9+L8 -> 0.86585366 | M9: =_xlfn.IFS(L9<80%,"A",L9<=95%,"B",L9>95%,"C") -> B
B10: th черн | C10: ='Юнит 06-12.04'!AE9 -> 970.59456 | D10: =C10/C$18 -> 0.031949688 | E10: =D10+E9 -> 1.1414624 | F10: =IF(AND(E10<=0),"C",IF(E10<=0.8,"A",IF(E10<=0.95,"B","C"))) -> C | G10: =VLOOKUP(B$4:B$17,I$4:M$17,5,0) -> A | I10: qs черные | J10: ='Юнит 06-12.04'!R4 -> 5 | K10: =J10/J$18 -> 0.06097561 | L10: =K10+L9 -> 0.92682927 | M10: =_xlfn.IFS(L10<80%,"A",L10<=95%,"B",L10>95%,"C") -> B
B11: qs черные | C11: ='Юнит 06-12.04'!AE4 -> 68.955823 | D11: =C11/C$18 -> 0.0022698634 | E11: =D11+E10 -> 1.1437323 | F11: =IF(AND(E11<=0),"C",IF(E11<=0.8,"A",IF(E11<=0.95,"B","C"))) -> C | G11: =VLOOKUP(B$4:B$17,I$4:M$17,5,0) -> B | I11: черные с железкой классика | J11: ='Юнит 06-12.04'!R3 -> 2 | K11: =J11/J$18 -> 0.024390244 | L11: =K11+L10 -> 0.95121951 | M11: =_xlfn.IFS(L11<80%,"A",L11<=95%,"B",L11>95%,"C") -> C
B12: th син | C12: ='Юнит 06-12.04'!AE10 -> 0 | D12: =C12/C$18 -> 0 | E12: =D12+E5 -> 0.64579228 | F12: =IF(AND(E12<=0),"C",IF(E12<=0.8,"A",IF(E12<=0.95,"B","C"))) -> A | G12: =VLOOKUP(B$4:B$17,I$4:M$17,5,0) -> A | I12: qs синие | J12: ='Юнит 06-12.04'!R5 -> 1 | K12: =J12/J$18 -> 0.012195122 | L12: =K12+L5 -> 0.36585366 | M12: =_xlfn.IFS(L12<80%,"A",L12<=95%,"B",L12>95%,"C") -> A
B13: flip синий | C13: ='Юнит 06-12.04'!AE14 -> -113.88 | D13: =C13/C$18 -> -0.0037486615 | E13: =D13+E12 -> 0.64204362 | F13: =IF(AND(E13<=0),"C",IF(E13<=0.8,"A",IF(E13<=0.95,"B","C"))) -> A | G13: =VLOOKUP(B$4:B$17,I$4:M$17,5,0) -> A | I13: qs желтые | J13: ='Юнит 06-12.04'!R6 -> 1 | K13: =J13/J$18 -> 0.012195122 | L13: =K13+L12 -> 0.37804878 | M13: =_xlfn.IFS(L13<80%,"A",L13<=95%,"B",L13>95%,"C") -> A
B14: qs синие | C14: ='Юнит 06-12.04'!AE5 -> -839.34842 | D14: =C14/C$18 -> -0.027629374 | E14: =D14+E13 -> 0.61441424 | F14: =IF(AND(E14<=0),"C",IF(E14<=0.8,"A",IF(E14<=0.95,"B","C"))) -> A | G14: =VLOOKUP(B$4:B$17,I$4:M$17,5,0) -> A | I14: th черн | J14: ='Юнит 06-12.04'!R9 -> 1 | K14: =J14/J$18 -> 0.012195122 | L14: =K14+L13 -> 0.3902439 | M14: =_xlfn.IFS(L14<80%,"A",L14<=95%,"B",L14>95%,"C") -> A
B15: flip жел | C15: ='Юнит 06-12.04'!AE15 -> -1084.0032 | D15: =C15/C$18 -> -0.035682834 | E15: =D15+E14 -> 0.57873141 | F15: =IF(AND(E15<=0),"C",IF(E15<=0.8,"A",IF(E15<=0.95,"B","C"))) -> A | G15: =VLOOKUP(B$4:B$17,I$4:M$17,5,0) -> A | I15: flip жел | J15: ='Юнит 06-12.04'!R15 -> 1 | K15: =J15/J$18 -> 0.012195122 | L15: =K15+L14 -> 0.40243902 | M15: =_xlfn.IFS(L15<80%,"A",L15<=95%,"B",L15>95%,"C") -> A
B16: qs желтые | C16: ='Юнит 06-12.04'!AE6 -> -1161.3187 | D16: =C16/C$18 -> -0.038227878 | E16: =D16+E15 -> 0.54050353 | F16: =IF(AND(E16<=0),"C",IF(E16<=0.8,"A",IF(E16<=0.95,"B","C"))) -> A | G16: =VLOOKUP(B$4:B$17,I$4:M$17,5,0) -> A | I16: th син | J16: ='Юнит 06-12.04'!R10 -> 0 | K16: =J16/J$18 -> 0 | L16: =K16+L15 -> 0.40243902 | M16: =_xlfn.IFS(L16<80%,"A",L16<=95%,"B",L16>95%,"C") -> A
B17: черные с железкой классика | C17: ='Юнит 06-12.04'!AE3 -> -1167.8701 | D17: =C17/C$18 -> -0.038443534 | E17: =D17+E14 -> 0.57597071 | F17: =IF(AND(E17<=0),"C",IF(E17<=0.8,"A",IF(E17<=0.95,"B","C"))) -> A | G17: =VLOOKUP(B$4:B$17,I$4:M$17,5,0) -> C | I17: flip синий | J17: ='Юнит 06-12.04'!R14 -> 0 | K17: =J17/J$18 -> 0 | L17: =K17+L14 -> 0.3902439 | M17: =_xlfn.IFS(L17<80%,"A",L17<=95%,"B",L17>95%,"C") -> A
C18: =SUM(C4:C17) -> 30378.843 | D18: =SUM(D4:D17) -> 1 | J18: =SUM(J4:J17) -> 82 | K18: =SUM(K4:K17) -> 1
C21: Прибыль | D21: % прибыль | E21: Доля | F21: ABC прибыль | G21: ABC кол-во | J21: Кол-во | K21: % кол-во | L21: Доля | M21: ABC кол-во
D22: =C22/C$42 -> #DIV/0! | E22: =D22 -> #DIV/0! | F22: =IF(AND(E22<=0),"C",IF(E22<=0.8,"A",IF(E22<=0.95,"B","C"))) -> #DIV/0! | G22: =VLOOKUP(B$22:B$42,I$22:M$42,5,0) -> #N/A | K22: =J22/J$42 -> #DIV/0! | L22: =K22 -> #DIV/0! | M22: =_xlfn.IFS(L22<80%,"A",L22<=95%,"B",L22>95%,"C") -> #DIV/0!
D23: =C23/C$42 -> #DIV/0! | E23: =D23+E22 -> #DIV/0! | F23: =IF(AND(E23<=0),"C",IF(E23<=0.8,"A",IF(E23<=0.95,"B","C"))) -> #DIV/0! | G23: =VLOOKUP(B$22:B$42,I$22:M$42,5,0) -> #N/A | K23: =J23/J$42 -> #DIV/0! | L23: =K23+L22 -> #DIV/0! | M23: =_xlfn.IFS(L23<80%,"A",L23<=95%,"B",L23>95%,"C") -> #DIV/0!
D24: =C24/C$42 -> #DIV/0! | E24: =D24+E23 -> #DIV/0! | F24: =IF(AND(E24<=0),"C",IF(E24<=0.8,"A",IF(E24<=0.95,"B","C"))) -> #DIV/0! | G24: =VLOOKUP(B$22:B$42,I$22:M$42,5,0) -> #N/A | K24: =J24/J$42 -> #DIV/0! | L24: =K24+L23 -> #DIV/0! | M24: =_xlfn.IFS(L24<80%,"A",L24<=95%,"B",L24>95%,"C") -> #DIV/0!
D25: =C25/C$42 -> #DIV/0! | E25: =D25+E24 -> #DIV/0! | F25: =IF(AND(E25<=0),"C",IF(E25<=0.8,"A",IF(E25<=0.95,"B","C"))) -> #DIV/0! | G25: =VLOOKUP(B$22:B$42,I$22:M$42,5,0) -> #N/A | K25: =J25/J$42 -> #DIV/0! | L25: =K25+L24 -> #DIV/0! | M25: =_xlfn.IFS(L25<80%,"A",L25<=95%,"B",L25>95%,"C") -> #DIV/0!
D26: =C26/C$42 -> #DIV/0! | E26: =D26+E25 -> #DIV/0! | F26: =IF(AND(E26<=0),"C",IF(E26<=0.8,"A",IF(E26<=0.95,"B","C"))) -> #DIV/0! | G26: =VLOOKUP(B$22:B$42,I$22:M$42,5,0) -> #N/A | K26: =J26/J$42 -> #DIV/0! | L26: =K26+L25 -> #DIV/0! | M26: =_xlfn.IFS(L26<80%,"A",L26<=95%,"B",L26>95%,"C") -> #DIV/0!
D27: =C27/C$42 -> #DIV/0! | E27: =D27+E26 -> #DIV/0! | F27: =IF(AND(E27<=0),"C",IF(E27<=0.8,"A",IF(E27<=0.95,"B","C"))) -> #DIV/0! | G27: =VLOOKUP(B$22:B$42,I$22:M$42,5,0) -> #N/A | K27: =J27/J$42 -> #DIV/0! | L27: =K27+L26 -> #DIV/0! | M27: =_xlfn.IFS(L27<80%,"A",L27<=95%,"B",L27>95%,"C") -> #DIV/0!
D28: =C28/C$42 -> #DIV/0! | E28: =D28+E27 -> #DIV/0! | F28: =IF(AND(E28<=0),"C",IF(E28<=0.8,"A",IF(E28<=0.95,"B","C"))) -> #DIV/0! | G28: =VLOOKUP(B$22:B$42,I$22:M$42,5,0) -> #N/A | K28: =J28/J$42 -> #DIV/0! | L28: =K28+L27 -> #DIV/0! | M28: =_xlfn.IFS(L28<80%,"A",L28<=95%,"B",L28>95%,"C") -> #DIV/0!
D29: =C29/C$42 -> #DIV/0! | E29: =D29+E28 -> #DIV/0! | F29: =IF(AND(E29<=0),"C",IF(E29<=0.8,"A",IF(E29<=0.95,"B","C"))) -> #DIV/0! | G29: =VLOOKUP(B$22:B$42,I$22:M$42,5,0) -> #N/A | K29: =J29/J$42 -> #DIV/0! | L29: =K29+L28 -> #DIV/0! | M29: =_xlfn.IFS(L29<80%,"A",L29<=95%,"B",L29>95%,"C") -> #DIV/0!
D30: =C30/C$42 -> #DIV/0! | E30: =D30+E29 -> #DIV/0! | F30: =IF(AND(E30<=0),"C",IF(E30<=0.8,"A",IF(E30<=0.95,"B","C"))) -> #DIV/0! | G30: =VLOOKUP(B$22:B$42,I$22:M$42,5,0) -> #N/A | K30: =J30/J$42 -> #DIV/0! | L30: =K30+L29 -> #DIV/0! | M30: =_xlfn.IFS(L30<80%,"A",L30<=95%,"B",L30>95%,"C") -> #DIV/0!
D31: =C31/C$42 -> #DIV/0! | E31: =D31+E30 -> #DIV/0! | F31: =IF(AND(E31<=0),"C",IF(E31<=0.8,"A",IF(E31<=0.95,"B","C"))) -> #DIV/0! | G31: =VLOOKUP(B$22:B$42,I$22:M$42,5,0) -> #N/A | K31: =J31/J$42 -> #DIV/0! | L31: =K31+L30 -> #DIV/0! | M31: =_xlfn.IFS(L31<80%,"A",L31<=95%,"B",L31>95%,"C") -> #DIV/0!
D32: =C32/C$42 -> #DIV/0! | E32: =D32+E31 -> #DIV/0! | F32: =IF(AND(E32<=0),"C",IF(E32<=0.8,"A",IF(E32<=0.95,"B","C"))) -> #DIV/0! | G32: =VLOOKUP(B$22:B$42,I$22:M$42,5,0) -> #N/A | K32: =J32/J$42 -> #DIV/0! | L32: =K32+L31 -> #DIV/0! | M32: =_xlfn.IFS(L32<80%,"A",L32<=95%,"B",L32>95%,"C") -> #DIV/0!
D33: =C33/C$42 -> #DIV/0! | E33: =D33+E32 -> #DIV/0! | F33: =IF(AND(E33<=0),"C",IF(E33<=0.8,"A",IF(E33<=0.95,"B","C"))) -> #DIV/0! | G33: =VLOOKUP(B$22:B$42,I$22:M$42,5,0) -> #N/A | K33: =J33/J$42 -> #DIV/0! | L33: =K33+L32 -> #DIV/0! | M33: =_xlfn.IFS(L33<80%,"A",L33<=95%,"B",L33>95%,"C") -> #DIV/0!
D34: =C34/C$42 -> #DIV/0! | E34: =D34+E33 -> #DIV/0! | F34: =IF(AND(E34<=0),"C",IF(E34<=0.8,"A",IF(E34<=0.95,"B","C"))) -> #DIV/0! | G34: =VLOOKUP(B$22:B$42,I$22:M$42,5,0) -> #N/A | K34: =J34/J$42 -> #DIV/0! | L34: =K34+L33 -> #DIV/0! | M34: =_xlfn.IFS(L34<80%,"A",L34<=95%,"B",L34>95%,"C") -> #DIV/0!
... D41: =C41/C$42 -> #DIV/0! | E41: =D41+E40 -> #DIV/0! | F41: =IF(AND(E41<=0),"C",IF(E41<=0.8,"A",IF(E41<=0.95,"B","C"))) -> #DIV/0! | G41: =VLOOKUP(B$22:B$42,I$22:M$42,5,0) -> #N/A | K41: =J41/J$42 -> #DIV/0! | L41: =K41+L40 -> #DIV/0! | M41: =_xlfn.IFS(L41<80%,"A",L41<=95%,"B",L41>95%,"C") -> #DIV/0!
C42: =SUM(C22:C41) -> 0 | D42: =SUM(D22:D41) -> #DIV/0! | J42: =SUM(J22:J41) -> 0 | K42: =SUM(K22:K41) -> #DIV/0!

Sheet АВС 30.03-05.04
B2: ОЧКИ
C3: Прибыль | D3: % прибыль | E3: Доля | F3: ABC прибыль | G3: ABC кол-во | J3: Кол-во | K3: % кол-во | L3: Доля | M3: ABC кол-во
B4: черные с железкой классика | D4: =C4/C$18 -> #DIV/0! | E4: =D4 -> #DIV/0! | F4: =IF(AND(E4<=0),"C",IF(E4<=0.8,"A",IF(E4<=0.95,"B","C"))) -> #DIV/0! | G4: =VLOOKUP(B$4:B$17,I$4:M$17,5,0) -> #DIV/0! | I4: черные с железкой классика | K4: =J4/J$18 -> #DIV/0! | L4: =K4 -> #DIV/0! | M4: =_xlfn.IFS(L4<80%,"A",L4<=95%,"B",L4>95%,"C") -> #DIV/0!
B5: qs черные | D5: =C5/C$18 -> #DIV/0! | E5: =D5+E4 -> #DIV/0! | F5: =IF(AND(E5<=0),"C",IF(E5<=0.8,"A",IF(E5<=0.95,"B","C"))) -> #DIV/0! | G5: =VLOOKUP(B$4:B$17,I$4:M$17,5,0) -> #DIV/0! | I5: qs черные | K5: =J5/J$18 -> #DIV/0! | L5: =K5+L4 -> #DIV/0! | M5: =_xlfn.IFS(L5<80%,"A",L5<=95%,"B",L5>95%,"C") -> #DIV/0!
B6: qs синие | D6: =C6/C$18 -> #DIV/0! | E6: =D6+E5 -> #DIV/0! | F6: =IF(AND(E6<=0),"C",IF(E6<=0.8,"A",IF(E6<=0.95,"B","C"))) -> #DIV/0! | G6: =VLOOKUP(B$4:B$17,I$4:M$17,5,0) -> #DIV/0! | I6: qs синие | K6: =J6/J$18 -> #DIV/0! | L6: =K6+L5 -> #DIV/0! | M6: =_xlfn.IFS(L6<80%,"A",L6<=95%,"B",L6>95%,"C") -> #DIV/0!
B7: qs желтые | D7: =C7/C$18 -> #DIV/0! | E7: =D7+E6 -> #DIV/0! | F7: =IF(AND(E7<=0),"C",IF(E7<=0.8,"A",IF(E7<=0.95,"B","C"))) -> #DIV/0! | G7: =VLOOKUP(B$4:B$17,I$4:M$17,5,0) -> #DIV/0! | I7: qs желтые | K7: =J7/J$18 -> #DIV/0! | L7: =K7+L6 -> #DIV/0! | M7: =_xlfn.IFS(L7<80%,"A",L7<=95%,"B",L7>95%,"C") -> #DIV/0!
B8: qs коричневые | D8: =C8/C$18 -> #DIV/0! | E8: =D8+E7 -> #DIV/0! | F8: =IF(AND(E8<=0),"C",IF(E8<=0.8,"A",IF(E8<=0.95,"B","C"))) -> #DIV/0! | G8: =VLOOKUP(B$4:B$17,I$4:M$17,5,0) -> #DIV/0! | I8: qs коричневые | K8: =J8/J$18 -> #DIV/0! | L8: =K8+L7 -> #DIV/0! | M8: =_xlfn.IFS(L8<80%,"A",L8<=95%,"B",L8>95%,"C") -> #DIV/0!
B9: MR8854 C2 | D9: =C9/C$18 -> #DIV/0! | E9: =D9+E8 -> #DIV/0! | F9: =IF(AND(E9<=0),"C",IF(E9<=0.8,"A",IF(E9<=0.95,"B","C"))) -> #DIV/0! | G9: =VLOOKUP(B$4:B$17,I$4:M$17,5,0) -> #DIV/0! | I9: MR8854 C2 | K9: =J9/J$18 -> #DIV/0! | L9: =K9+L8 -> #DIV/0! | M9: =_xlfn.IFS(L9<80%,"A",L9<=95%,"B",L9>95%,"C") -> #DIV/0!
B10: th черн | D10: =C10/C$18 -> #DIV/0! | E10: =D10+E9 -> #DIV/0! | F10: =IF(AND(E10<=0),"C",IF(E10<=0.8,"A",IF(E10<=0.95,"B","C"))) -> #DIV/0! | G10: =VLOOKUP(B$4:B$17,I$4:M$17,5,0) -> #DIV/0! | I10: th черн | K10: =J10/J$18 -> #DIV/0! | L10: =K10+L9 -> #DIV/0! | M10: =_xlfn.IFS(L10<80%,"A",L10<=95%,"B",L10>95%,"C") -> #DIV/0!
B11: th син | D11: =C11/C$18 -> #DIV/0! | E11: =D11+E10 -> #DIV/0! | F11: =IF(AND(E11<=0),"C",IF(E11<=0.8,"A",IF(E11<=0.95,"B","C"))) -> #DIV/0! | G11: =VLOOKUP(B$4:B$17,I$4:M$17,5,0) -> #DIV/0! | I11: th син | K11: =J11/J$18 -> #DIV/0! | L11: =K11+L10 -> #DIV/0! | M11: =_xlfn.IFS(L11<80%,"A",L11<=95%,"B",L11>95%,"C") -> #DIV/0!
B12: th желт | D12: =C12/C$18 -> #DIV/0! | E12: =D12+E5 -> #DIV/0! | F12: =IF(AND(E12<=0),"C",IF(E12<=0.8,"A",IF(E12<=0.95,"B","C"))) -> #DIV/0! | G12: =VLOOKUP(B$4:B$17,I$4:M$17,5,0) -> #DIV/0! | I12: th желт | K12: =J12/J$18 -> #DIV/0! | L12: =K12+L5 -> #DIV/0! | M12: =_xlfn.IFS(L12<80%,"A",L12<=95%,"B",L12>95%,"C") -> #DIV/0!
B13: th коричн | D13: =C13/C$18 -> #DIV/0! | E13: =D13+E12 -> #DIV/0! | F13: =IF(AND(E13<=0),"C",IF(E13<=0.8,"A",IF(E13<=0.95,"B","C"))) -> #DIV/0! | G13: =VLOOKUP(B$4:B$17,I$4:M$17,5,0) -> #DIV/0! | I13: th коричн | K13: =J13/J$18 -> #DIV/0! | L13: =K13+L12 -> #DIV/0! | M13: =_xlfn.IFS(L13<80%,"A",L13<=95%,"B",L13>95%,"C") -> #DIV/0!
B14: flip черный | D14: =C14/C$18 -> #DIV/0! | E14: =D14+E13 -> #DIV/0! | F14: =IF(AND(E14<=0),"C",IF(E14<=0.8,"A",IF(E14<=0.95,"B","C"))) -> #DIV/0! | G14: =VLOOKUP(B$4:B$17,I$4:M$17,5,0) -> #DIV/0! | I14: flip черный | K14: =J14/J$18 -> #DIV/0! | L14: =K14+L13 -> #DIV/0! | M14: =_xlfn.IFS(L14<80%,"A",L14<=95%,"B",L14>95%,"C") -> #DIV/0!
B15: flip синий | D15: =C15/C$18 -> #DIV/0! | E15: =D15+E14 -> #DIV/0! | F15: =IF(AND(E15<=0),"C",IF(E15<=0.8,"A",IF(E15<=0.95,"B","C"))) -> #DIV/0! | G15: =VLOOKUP(B$4:B$17,I$4:M$17,5,0) -> #DIV/0! | I15: flip синий | K15: =J15/J$18 -> #DIV/0! | L15: =K15+L14 -> #DIV/0! | M15: =_xlfn.IFS(L15<80%,"A",L15<=95%,"B",L15>95%,"C") -> #DIV/0!
B16: flip жел | D16: =C16/C$18 -> #DIV/0! | E16: =D16+E15 -> #DIV/0! | F16: =IF(AND(E16<=0),"C",IF(E16<=0.8,"A",IF(E16<=0.95,"B","C"))) -> #DIV/0! | G16: =VLOOKUP(B$4:B$17,I$4:M$17,5,0) -> #DIV/0! | I16: flip жел | K16: =J16/J$18 -> #DIV/0! | L16: =K16+L15 -> #DIV/0! | M16: =_xlfn.IFS(L16<80%,"A",L16<=95%,"B",L16>95%,"C") -> #DIV/0!
B17: flip коричневый | D17: =C17/C$18 -> #DIV/0! | E17: =D17+E14 -> #DIV/0! | F17: =IF(AND(E17<=0),"C",IF(E17<=0.8,"A",IF(E17<=0.95,"B","C"))) -> #DIV/0! | G17: =VLOOKUP(B$4:B$17,I$4:M$17,5,0) -> #DIV/0! | I17: flip коричневый | K17: =J17/J$18 -> #DIV/0! | L17: =K17+L14 -> #DIV/0! | M17: =_xlfn.IFS(L17<80%,"A",L17<=95%,"B",L17>95%,"C") -> #DIV/0!
C18: =SUM(C4:C17) -> 0 | D18: =SUM(D4:D17) -> #DIV/0! | J18: =SUM(J4:J17) -> 0 | K18: =SUM(K4:K17) -> #DIV/0!
C21: Прибыль | D21: % прибыль | E21: Доля | F21: ABC прибыль | G21: ABC кол-во | J21: Кол-во | K21: % кол-во | L21: Доля | M21: ABC кол-во
D22: =C22/C$42 -> #DIV/0! | E22: =D22 -> #DIV/0! | F22: =IF(AND(E22<=0),"C",IF(E22<=0.8,"A",IF(E22<=0.95,"B","C"))) -> #DIV/0! | G22: =VLOOKUP(B$22:B$42,I$22:M$42,5,0) -> #N/A | K22: =J22/J$42 -> #DIV/0! | L22: =K22 -> #DIV/0! | M22: =_xlfn.IFS(L22<80%,"A",L22<=95%,"B",L22>95%,"C") -> #DIV/0!
D23: =C23/C$42 -> #DIV/0! | E23: =D23+E22 -> #DIV/0! | F23: =IF(AND(E23<=0),"C",IF(E23<=0.8,"A",IF(E23<=0.95,"B","C"))) -> #DIV/0! | G23: =VLOOKUP(B$22:B$42,I$22:M$42,5,0) -> #N/A | K23: =J23/J$42 -> #DIV/0! | L23: =K23+L22 -> #DIV/0! | M23: =_xlfn.IFS(L23<80%,"A",L23<=95%,"B",L23>95%,"C") -> #DIV/0!
D24: =C24/C$42 -> #DIV/0! | E24: =D24+E23 -> #DIV/0! | F24: =IF(AND(E24<=0),"C",IF(E24<=0.8,"A",IF(E24<=0.95,"B","C"))) -> #DIV/0! | G24: =VLOOKUP(B$22:B$42,I$22:M$42,5,0) -> #N/A | K24: =J24/J$42 -> #DIV/0! | L24: =K24+L23 -> #DIV/0! | M24: =_xlfn.IFS(L24<80%,"A",L24<=95%,"B",L24>95%,"C") -> #DIV/0!
D25: =C25/C$42 -> #DIV/0! | E25: =D25+E24 -> #DIV/0! | F25: =IF(AND(E25<=0),"C",IF(E25<=0.8,"A",IF(E25<=0.95,"B","C"))) -> #DIV/0! | G25: =VLOOKUP(B$22:B$42,I$22:M$42,5,0) -> #N/A | K25: =J25/J$42 -> #DIV/0! | L25: =K25+L24 -> #DIV/0! | M25: =_xlfn.IFS(L25<80%,"A",L25<=95%,"B",L25>95%,"C") -> #DIV/0!
D26: =C26/C$42 -> #DIV/0! | E26: =D26+E25 -> #DIV/0! | F26: =IF(AND(E26<=0),"C",IF(E26<=0.8,"A",IF(E26<=0.95,"B","C"))) -> #DIV/0! | G26: =VLOOKUP(B$22:B$42,I$22:M$42,5,0) -> #N/A | K26: =J26/J$42 -> #DIV/0! | L26: =K26+L25 -> #DIV/0! | M26: =_xlfn.IFS(L26<80%,"A",L26<=95%,"B",L26>95%,"C") -> #DIV/0!
D27: =C27/C$42 -> #DIV/0! | E27: =D27+E26 -> #DIV/0! | F27: =IF(AND(E27<=0),"C",IF(E27<=0.8,"A",IF(E27<=0.95,"B","C"))) -> #DIV/0! | G27: =VLOOKUP(B$22:B$42,I$22:M$42,5,0) -> #N/A | K27: =J27/J$42 -> #DIV/0! | L27: =K27+L26 -> #DIV/0! | M27: =_xlfn.IFS(L27<80%,"A",L27<=95%,"B",L27>95%,"C") -> #DIV/0!
D28: =C28/C$42 -> #DIV/0! | E28: =D28+E27 -> #DIV/0! | F28: =IF(AND(E28<=0),"C",IF(E28<=0.8,"A",IF(E28<=0.95,"B","C"))) -> #DIV/0! | G28: =VLOOKUP(B$22:B$42,I$22:M$42,5,0) -> #N/A | K28: =J28/J$42 -> #DIV/0! | L28: =K28+L27 -> #DIV/0! | M28: =_xlfn.IFS(L28<80%,"A",L28<=95%,"B",L28>95%,"C") -> #DIV/0!
D29: =C29/C$42 -> #DIV/0! | E29: =D29+E28 -> #DIV/0! | F29: =IF(AND(E29<=0),"C",IF(E29<=0.8,"A",IF(E29<=0.95,"B","C"))) -> #DIV/0! | G29: =VLOOKUP(B$22:B$42,I$22:M$42,5,0) -> #N/A | K29: =J29/J$42 -> #DIV/0! | L29: =K29+L28 -> #DIV/0! | M29: =_xlfn.IFS(L29<80%,"A",L29<=95%,"B",L29>95%,"C") -> #DIV/0!
D30: =C30/C$42 -> #DIV/0! | E30: =D30+E29 -> #DIV/0! | F30: =IF(AND(E30<=0),"C",IF(E30<=0.8,"A",IF(E30<=0.95,"B","C"))) -> #DIV/0! | G30: =VLOOKUP(B$22:B$42,I$22:M$42,5,0) -> #N/A | K30: =J30/J$42 -> #DIV/0! | L30: =K30+L29 -> #DIV/0! | M30: =_xlfn.IFS(L30<80%,"A",L30<=95%,"B",L30>95%,"C") -> #DIV/0!
D31: =C31/C$42 -> #DIV/0! | E31: =D31+E30 -> #DIV/0! | F31: =IF(AND(E31<=0),"C",IF(E31<=0.8,"A",IF(E31<=0.95,"B","C"))) -> #DIV/0! | G31: =VLOOKUP(B$22:B$42,I$22:M$42,5,0) -> #N/A | K31: =J31/J$42 -> #DIV/0! | L31: =K31+L30 -> #DIV/0! | M31: =_xlfn.IFS(L31<80%,"A",L31<=95%,"B",L31>95%,"C") -> #DIV/0!
D32: =C32/C$42 -> #DIV/0! | E32: =D32+E31 -> #DIV/0! | F32: =IF(AND(E32<=0),"C",IF(E32<=0.8,"A",IF(E32<=0.95,"B","C"))) -> #DIV/0! | G32: =VLOOKUP(B$22:B$42,I$22:M$42,5,0) -> #N/A | K32: =J32/J$42 -> #DIV/0! | L32: =K32+L31 -> #DIV/0! | M32: =_xlfn.IFS(L32<80%,"A",L32<=95%,"B",L32>95%,"C") -> #DIV/0!
D33: =C33/C$42 -> #DIV/0! | E33: =D33+E32 -> #DIV/0! | F33: =IF(AND(E33<=0),"C",IF(E33<=0.8,"A",IF(E33<=0.95,"B","C"))) -> #DIV/0! | G33: =VLOOKUP(B$22:B$42,I$22:M$42,5,0) -> #N/A | K33: =J33/J$42 -> #DIV/0! | L33: =K33+L32 -> #DIV/0! | M33: =_xlfn.IFS(L33<80%,"A",L33<=95%,"B",L33>95%,"C") -> #DIV/0!
D34: =C34/C$42 -> #DIV/0! | E34: =D34+E33 -> #DIV/0! | F34: =IF(AND(E34<=0),"C",IF(E34<=0.8,"A",IF(E34<=0.95,"B","C"))) -> #DIV/0! | G34: =VLOOKUP(B$22:B$42,I$22:M$42,5,0) -> #N/A | K34: =J34/J$42 -> #DIV/0! | L34: =K34+L33 -> #DIV/0! | M34: =_xlfn.IFS(L34<80%,"A",L34<=95%,"B",L34>95%,"C") -> #DIV/0!
... D41: =C41/C$42 -> #DIV/0! | E41: =D41+E40 -> #DIV/0! | F41: =IF(AND(E41<=0),"C",IF(E41<=0.8,"A",IF(E41<=0.95,"B","C"))) -> #DIV/0! | G41: =VLOOKUP(B$22:B$42,I$22:M$42,5,0) -> #N/A | K41: =J41/J$42 -> #DIV/0! | L41: =K41+L40 -> #DIV/0! | M41: =_xlfn.IFS(L41<80%,"A",L41<=95%,"B",L41>95%,"C") -> #DIV/0!
C42: =SUM(C22:C41) -> 0 | D42: =SUM(D22:D41) -> #DIV/0! | J42: =SUM(J22:J41) -> 0 | K42: =SUM(K22:K41) -> #DIV/0!

Sheet АВС МАРТ
B2: ОЧКИ
C3: Прибыль | D3: % прибыль | E3: Доля | F3: ABC прибыль | G3: ABC кол-во | J3: Кол-во | K3: % кол-во | L3: Доля | M3: ABC кол-во
B4: MR8854 C2 | C4: =МАРТ!AE8 -> 51269.371 | D4: =C4/C$18 -> 0.29166505 | E4: =D4 -> 0.29166505 | F4: =IF(AND(E4<=0),"C",IF(E4<=0.8,"A",IF(E4<=0.95,"B","C"))) -> A | G4: =VLOOKUP(B$4:B$17,I$4:M$17,5,0) -> A | I4: MR8854 C2 | J4: =МАРТ!R8 -> 81 | K4: =J4/J$18 -> 0.2439759 | L4: =K4 -> 0.2439759 | M4: =_xlfn.IFS(L4<80%,"A",L4<=95%,"B",L4>95%,"C") -> A
B5: qs коричневые | C5: =МАРТ!AE7 -> 20625.734 | D5: =C5/C$18 -> 0.11733723 | E5: =D5+E4 -> 0.40900227 | F5: =IF(AND(E5<=0),"C",IF(E5<=0.8,"A",IF(E5<=0.95,"B","C"))) -> A | G5: =VLOOKUP(B$4:B$17,I$4:M$17,5,0) -> A | I5: qs коричневые | J5: =МАРТ!R7 -> 41 | K5: =J5/J$18 -> 0.12349398 | L5: =K5+L4 -> 0.36746988 | M5: =_xlfn.IFS(L5<80%,"A",L5<=95%,"B",L5>95%,"C") -> A
B6: flip черный | C6: =МАРТ!AE13 -> 19840.708 | D6: =C6/C$18 -> 0.11287131 | E6: =D6+E5 -> 0.52187358 | F6: =IF(AND(E6<=0),"C",IF(E6<=0.8,"A",IF(E6<=0.95,"B","C"))) -> A | G6: =VLOOKUP(B$4:B$17,I$4:M$17,5,0) -> A | I6: flip жел | J6: =МАРТ!R15 -> 38 | K6: =J6/J$18 -> 0.11445783 | L6: =K6+L5 -> 0.48192771 | M6: =_xlfn.IFS(L6<80%,"A",L6<=95%,"B",L6>95%,"C") -> A
B7: flip жел | C7: =МАРТ!AE15 -> 18752.445 | D7: =C7/C$18 -> 0.10668032 | E7: =D7+E6 -> 0.6285539 | F7: =IF(AND(E7<=0),"C",IF(E7<=0.8,"A",IF(E7<=0.95,"B","C"))) -> A | G7: =VLOOKUP(B$4:B$17,I$4:M$17,5,0) -> A | I7: flip черный | J7: =МАРТ!R13 -> 28 | K7: =J7/J$18 -> 0.084337349 | L7: =K7+L6 -> 0.56626506 | M7: =_xlfn.IFS(L7<80%,"A",L7<=95%,"B",L7>95%,"C") -> A
B8: flip коричневый | C8: =МАРТ!AE16 -> 12366.329 | D8: =C8/C$18 -> 0.070350504 | E8: =D8+E7 -> 0.6989044 | F8: =IF(AND(E8<=0),"C",IF(E8<=0.8,"A",IF(E8<=0.95,"B","C"))) -> A | G8: =VLOOKUP(B$4:B$17,I$4:M$17,5,0) -> A | I8: flip коричневый | J8: =МАРТ!R16 -> 28 | K8: =J8/J$18 -> 0.084337349 | L8: =K8+L7 -> 0.65060241 | M8: =_xlfn.IFS(L8<80%,"A",L8<=95%,"B",L8>95%,"C") -> A
B9: qs желтые | C9: =МАРТ!AE6 -> 11302.478 | D9: =C9/C$18 -> 0.064298383 | E9: =D9+E8 -> 0.76320278 | F9: =IF(AND(E9<=0),"C",IF(E9<=0.8,"A",IF(E9<=0.95,"B","C"))) -> A | G9: =VLOOKUP(B$4:B$17,I$4:M$17,5,0) -> A | I9: qs желтые | J9: =МАРТ!R6 -> 23 | K9: =J9/J$18 -> 0.069277108 | L9: =K9+L8 -> 0.71987952 | M9: =_xlfn.IFS(L9<80%,"A",L9<=95%,"B",L9>95%,"C") -> A
B10: th желт | C10: =МАРТ!AE11 -> 11208.546 | D10: =C10/C$18 -> 0.063764016 | E10: =D10+E9 -> 0.8269668 | F10: =IF(AND(E10<=0),"C",IF(E10<=0.8,"A",IF(E10<=0.95,"B","C"))) -> B | G10: =VLOOKUP(B$4:B$17,I$4:M$17,5,0) -> A | I10: th желт | J10: =МАРТ!R11 -> 23 | K10: =J10/J$18 -> 0.069277108 | L10: =K10+L9 -> 0.78915663 | M10: =_xlfn.IFS(L10<80%,"A",L10<=95%,"B",L10>95%,"C") -> A
B11: th черн | C11: =МАРТ!AE9 -> 8442.6927 | D11: =C11/C$18 -> 0.048029424 | E11: =D11+E10 -> 0.87499622 | F11: =IF(AND(E11<=0),"C",IF(E11<=0.8,"A",IF(E11<=0.95,"B","C"))) -> B | G11: =VLOOKUP(B$4:B$17,I$4:M$17,5,0) -> A | I11: qs черные | J11: =МАРТ!R4 -> 15 | K11: =J11/J$18 -> 0.045180723 | L11: =K11+L10 -> 0.83433735 | M11: =_xlfn.IFS(L11<80%,"A",L11<=95%,"B",L11>95%,"C") -> B
B12: qs синие | C12: =МАРТ!AE5 -> 8049.3409 | D12: =C12/C$18 -> 0.045791695 | E12: =D12+E5 -> 0.45479397 | F12: =IF(AND(E12<=0),"C",IF(E12<=0.8,"A",IF(E12<=0.95,"B","C"))) -> A | G12: =VLOOKUP(B$4:B$17,I$4:M$17,5,0) -> A | I12: th коричн | J12: =МАРТ!R12 -> 13 | K12: =J12/J$18 -> 0.039156627 | L12: =K12+L5 -> 0.40662651 | M12: =_xlfn.IFS(L12<80%,"A",L12<=95%,"B",L12>95%,"C") -> A
B13: th син | C13: =МАРТ!AE10 -> 6801.883 | D13: =C13/C$18 -> 0.038695063 | E13: =D13+E12 -> 0.49348903 | F13: =IF(AND(E13<=0),"C",IF(E13<=0.8,"A",IF(E13<=0.95,"B","C"))) -> A | G13: =VLOOKUP(B$4:B$17,I$4:M$17,5,0) -> A | I13: th син | J13: =МАРТ!R10 -> 12 | K13: =J13/J$18 -> 0.036144578 | L13: =K13+L12 -> 0.44277108 | M13: =_xlfn.IFS(L13<80%,"A",L13<=95%,"B",L13>95%,"C") -> A
B14: qs черные | C14: =МАРТ!AE4 -> 5615.7015 | D14: =C14/C$18 -> 0.031947024 | E14: =D14+E13 -> 0.52543605 | F14: =IF(AND(E14<=0),"C",IF(E14<=0.8,"A",IF(E14<=0.95,"B","C"))) -> A | G14: =VLOOKUP(B$4:B$17,I$4:M$17,5,0) -> B | I14: th черн | J14: =МАРТ!R9 -> 10 | K14: =J14/J$18 -> 0.030120482 | L14: =K14+L13 -> 0.47289157 | M14: =_xlfn.IFS(L14<80%,"A",L14<=95%,"B",L14>95%,"C") -> A
B15: th коричн | C15: =МАРТ!AE12 -> 4966.3282 | D15: =C15/C$18 -> 0.028252821 | E15: =D15+E14 -> 0.55368888 | F15: =IF(AND(E15<=0),"C",IF(E15<=0.8,"A",IF(E15<=0.95,"B","C"))) -> A | G15: =VLOOKUP(B$4:B$17,I$4:M$17,5,0) -> A | I15: черные с железкой классика | J15: =МАРТ!R3 -> 9 | K15: =J15/J$18 -> 0.027108434 | L15: =K15+L14 -> 0.5 | M15: =_xlfn.IFS(L15<80%,"A",L15<=95%,"B",L15>95%,"C") -> A
B16: flip синий | C16: =МАРТ!AE14 -> 1003.9555 | D16: =C16/C$18 -> 0.0057113772 | E16: =D16+E15 -> 0.55940025 | F16: =IF(AND(E16<=0),"C",IF(E16<=0.8,"A",IF(E16<=0.95,"B","C"))) -> A | G16: =VLOOKUP(B$4:B$17,I$4:M$17,5,0) -> A | I16: qs синие | J16: =МАРТ!R5 -> 9 | K16: =J16/J$18 -> 0.027108434 | L16: =K16+L15 -> 0.52710843 | M16: =_xlfn.IFS(L16<80%,"A",L16<=95%,"B",L16>95%,"C") -> A
B17: черные с железкой классика | C17: =МАРТ!AE3 -> -4463.8355 | D17: =C17/C$18 -> -0.025394203 | E17: =D17+E14 -> 0.50004185 | F17: =IF(AND(E17<=0),"C",IF(E17<=0.8,"A",IF(E17<=0.95,"B","C"))) -> A | G17: =VLOOKUP(B$4:B$17,I$4:M$17,5,0) -> A | I17: flip синий | J17: =МАРТ!R14 -> 2 | K17: =J17/J$18 -> 0.0060240964 | L17: =K17+L14 -> 0.47891566 | M17: =_xlfn.IFS(L17<80%,"A",L17<=95%,"B",L17>95%,"C") -> A
C18: =SUM(C4:C17) -> 175781.68 | D18: =SUM(D4:D17) -> 1 | J18: =SUM(J4:J17) -> 332 | K18: =SUM(K4:K17) -> 1
C21: Прибыль | D21: % прибыль | E21: Доля | F21: ABC прибыль | G21: ABC кол-во | J21: Кол-во | K21: % кол-во | L21: Доля | M21: ABC кол-во
D22: =C22/C$42 -> #DIV/0! | E22: =D22 -> #DIV/0! | F22: =IF(AND(E22<=0),"C",IF(E22<=0.8,"A",IF(E22<=0.95,"B","C"))) -> #DIV/0! | G22: =VLOOKUP(B$22:B$42,I$22:M$42,5,0) -> #N/A | K22: =J22/J$42 -> #DIV/0! | L22: =K22 -> #DIV/0! | M22: =_xlfn.IFS(L22<80%,"A",L22<=95%,"B",L22>95%,"C") -> #DIV/0!
D23: =C23/C$42 -> #DIV/0! | E23: =D23+E22 -> #DIV/0! | F23: =IF(AND(E23<=0),"C",IF(E23<=0.8,"A",IF(E23<=0.95,"B","C"))) -> #DIV/0! | G23: =VLOOKUP(B$22:B$42,I$22:M$42,5,0) -> #N/A | K23: =J23/J$42 -> #DIV/0! | L23: =K23+L22 -> #DIV/0! | M23: =_xlfn.IFS(L23<80%,"A",L23<=95%,"B",L23>95%,"C") -> #DIV/0!
D24: =C24/C$42 -> #DIV/0! | E24: =D24+E23 -> #DIV/0! | F24: =IF(AND(E24<=0),"C",IF(E24<=0.8,"A",IF(E24<=0.95,"B","C"))) -> #DIV/0! | G24: =VLOOKUP(B$22:B$42,I$22:M$42,5,0) -> #N/A | K24: =J24/J$42 -> #DIV/0! | L24: =K24+L23 -> #DIV/0! | M24: =_xlfn.IFS(L24<80%,"A",L24<=95%,"B",L24>95%,"C") -> #DIV/0!
D25: =C25/C$42 -> #DIV/0! | E25: =D25+E24 -> #DIV/0! | F25: =IF(AND(E25<=0),"C",IF(E25<=0.8,"A",IF(E25<=0.95,"B","C"))) -> #DIV/0! | G25: =VLOOKUP(B$22:B$42,I$22:M$42,5,0) -> #N/A | K25: =J25/J$42 -> #DIV/0! | L25: =K25+L24 -> #DIV/0! | M25: =_xlfn.IFS(L25<80%,"A",L25<=95%,"B",L25>95%,"C") -> #DIV/0!
D26: =C26/C$42 -> #DIV/0! | E26: =D26+E25 -> #DIV/0! | F26: =IF(AND(E26<=0),"C",IF(E26<=0.8,"A",IF(E26<=0.95,"B","C"))) -> #DIV/0! | G26: =VLOOKUP(B$22:B$42,I$22:M$42,5,0) -> #N/A | K26: =J26/J$42 -> #DIV/0! | L26: =K26+L25 -> #DIV/0! | M26: =_xlfn.IFS(L26<80%,"A",L26<=95%,"B",L26>95%,"C") -> #DIV/0!
D27: =C27/C$42 -> #DIV/0! | E27: =D27+E26 -> #DIV/0! | F27: =IF(AND(E27<=0),"C",IF(E27<=0.8,"A",IF(E27<=0.95,"B","C"))) -> #DIV/0! | G27: =VLOOKUP(B$22:B$42,I$22:M$42,5,0) -> #N/A | K27: =J27/J$42 -> #DIV/0! | L27: =K27+L26 -> #DIV/0! | M27: =_xlfn.IFS(L27<80%,"A",L27<=95%,"B",L27>95%,"C") -> #DIV/0!
D28: =C28/C$42 -> #DIV/0! | E28: =D28+E27 -> #DIV/0! | F28: =IF(AND(E28<=0),"C",IF(E28<=0.8,"A",IF(E28<=0.95,"B","C"))) -> #DIV/0! | G28: =VLOOKUP(B$22:B$42,I$22:M$42,5,0) -> #N/A | K28: =J28/J$42 -> #DIV/0! | L28: =K28+L27 -> #DIV/0! | M28: =_xlfn.IFS(L28<80%,"A",L28<=95%,"B",L28>95%,"C") -> #DIV/0!
D29: =C29/C$42 -> #DIV/0! | E29: =D29+E28 -> #DIV/0! | F29: =IF(AND(E29<=0),"C",IF(E29<=0.8,"A",IF(E29<=0.95,"B","C"))) -> #DIV/0! | G29: =VLOOKUP(B$22:B$42,I$22:M$42,5,0) -> #N/A | K29: =J29/J$42 -> #DIV/0! | L29: =K29+L28 -> #DIV/0! | M29: =_xlfn.IFS(L29<80%,"A",L29<=95%,"B",L29>95%,"C") -> #DIV/0!
D30: =C30/C$42 -> #DIV/0! | E30: =D30+E29 -> #DIV/0! | F30: =IF(AND(E30<=0),"C",IF(E30<=0.8,"A",IF(E30<=0.95,"B","C"))) -> #DIV/0! | G30: =VLOOKUP(B$22:B$42,I$22:M$42,5,0) -> #N/A | K30: =J30/J$42 -> #DIV/0! | L30: =K30+L29 -> #DIV/0! | M30: =_xlfn.IFS(L30<80%,"A",L30<=95%,"B",L30>95%,"C") -> #DIV/0!
D31: =C31/C$42 -> #DIV/0! | E31: =D31+E30 -> #DIV/0! | F31: =IF(AND(E31<=0),"C",IF(E31<=0.8,"A",IF(E31<=0.95,"B","C"))) -> #DIV/0! | G31: =VLOOKUP(B$22:B$42,I$22:M$42,5,0) -> #N/A | K31: =J31/J$42 -> #DIV/0! | L31: =K31+L30 -> #DIV/0! | M31: =_xlfn.IFS(L31<80%,"A",L31<=95%,"B",L31>95%,"C") -> #DIV/0!
D32: =C32/C$42 -> #DIV/0! | E32: =D32+E31 -> #DIV/0! | F32: =IF(AND(E32<=0),"C",IF(E32<=0.8,"A",IF(E32<=0.95,"B","C"))) -> #DIV/0! | G32: =VLOOKUP(B$22:B$42,I$22:M$42,5,0) -> #N/A | K32: =J32/J$42 -> #DIV/0! | L32: =K32+L31 -> #DIV/0! | M32: =_xlfn.IFS(L32<80%,"A",L32<=95%,"B",L32>95%,"C") -> #DIV/0!
D33: =C33/C$42 -> #DIV/0! | E33: =D33+E32 -> #DIV/0! | F33: =IF(AND(E33<=0),"C",IF(E33<=0.8,"A",IF(E33<=0.95,"B","C"))) -> #DIV/0! | G33: =VLOOKUP(B$22:B$42,I$22:M$42,5,0) -> #N/A | K33: =J33/J$42 -> #DIV/0! | L33: =K33+L32 -> #DIV/0! | M33: =_xlfn.IFS(L33<80%,"A",L33<=95%,"B",L33>95%,"C") -> #DIV/0!
D34: =C34/C$42 -> #DIV/0! | E34: =D34+E33 -> #DIV/0! | F34: =IF(AND(E34<=0),"C",IF(E34<=0.8,"A",IF(E34<=0.95,"B","C"))) -> #DIV/0! | G34: =VLOOKUP(B$22:B$42,I$22:M$42,5,0) -> #N/A | K34: =J34/J$42 -> #DIV/0! | L34: =K34+L33 -> #DIV/0! | M34: =_xlfn.IFS(L34<80%,"A",L34<=95%,"B",L34>95%,"C") -> #DIV/0!
... D41: =C41/C$42 -> #DIV/0! | E41: =D41+E40 -> #DIV/0! | F41: =IF(AND(E41<=0),"C",IF(E41<=0.8,"A",IF(E41<=0.95,"B","C"))) -> #DIV/0! | G41: =VLOOKUP(B$22:B$42,I$22:M$42,5,0) -> #N/A | K41: =J41/J$42 -> #DIV/0! | L41: =K41+L40 -> #DIV/0! | M41: =_xlfn.IFS(L41<80%,"A",L41<=95%,"B",L41>95%,"C") -> #DIV/0!
C42: =SUM(C22:C41) -> 0 | D42: =SUM(D22:D41) -> #DIV/0! | J42: =SUM(J22:J41) -> 0 | K42: =SUM(K22:K41) -> #DIV/0!

Sheet АВС 23-29.03
B2: ОЧКИ
C3: Прибыль | D3: % прибыль | E3: Доля | F3: ABC прибыль | G3: ABC кол-во | J3: Кол-во | K3: % кол-во | L3: Доля | M3: ABC кол-во
B4: MR8854 C2 | C4: ='Юнит 23-29.03'!AE8 -> 9920.539 | D4: =C4/C$18 -> 0.32860621 | E4: =D4 -> 0.32860621 | F4: =IF(AND(E4<=0),"C",IF(E4<=0.8,"A",IF(E4<=0.95,"B","C"))) -> A | G4: =VLOOKUP(B$4:B$17,I$4:M$17,5,0) -> A | I4: MR8854 C2 | J4: ='Юнит 23-29.03'!R8 -> 14 | K4: =J4/J$18 -> 0.25925926 | L4: =K4 -> 0.25925926 | M4: =_xlfn.IFS(L4<80%,"A",L4<=95%,"B",L4>95%,"C") -> A
B5: flip черный | C5: ='Юнит 23-29.03'!AE13 -> 4886.6796 | D5: =C5/C$18 -> 0.16186553 | E5: =D5+E4 -> 0.49047174 | F5: =IF(AND(E5<=0),"C",IF(E5<=0.8,"A",IF(E5<=0.95,"B","C"))) -> A | G5: =VLOOKUP(B$4:B$17,I$4:M$17,5,0) -> A | I5: flip черный | J5: ='Юнит 23-29.03'!R13 -> 6 | K5: =J5/J$18 -> 0.11111111 | L5: =K5+L4 -> 0.37037037 | M5: =_xlfn.IFS(L5<80%,"A",L5<=95%,"B",L5>95%,"C") -> A
B6: qs синие | C6: ='Юнит 23-29.03'!AE5 -> 3925.109 | D6: =C6/C$18 -> 0.13001463 | E6: =D6+E5 -> 0.62048637 | F6: =IF(AND(E6<=0),"C",IF(E6<=0.8,"A",IF(E6<=0.95,"B","C"))) -> A | G6: =VLOOKUP(B$4:B$17,I$4:M$17,5,0) -> A | I6: flip коричневый | J6: ='Юнит 23-29.03'!R16 -> 6 | K6: =J6/J$18 -> 0.11111111 | L6: =K6+L5 -> 0.48148148 | M6: =_xlfn.IFS(L6<80%,"A",L6<=95%,"B",L6>95%,"C") -> A
B7: flip коричневый | C7: ='Юнит 23-29.03'!AE16 -> 2631.9007 | D7: =C7/C$18 -> 0.087178622 | E7: =D7+E6 -> 0.70766499 | F7: =IF(AND(E7<=0),"C",IF(E7<=0.8,"A",IF(E7<=0.95,"B","C"))) -> A | G7: =VLOOKUP(B$4:B$17,I$4:M$17,5,0) -> A | I7: qs черные | J7: ='Юнит 23-29.03'!R4 -> 5 | K7: =J7/J$18 -> 0.092592593 | L7: =K7+L6 -> 0.57407407 | M7: =_xlfn.IFS(L7<80%,"A",L7<=95%,"B",L7>95%,"C") -> A
B8: qs коричневые | C8: ='Юнит 23-29.03'!AE7 -> 2535.5044 | D8: =C8/C$18 -> 0.083985606 | E8: =D8+E7 -> 0.79165059 | F8: =IF(AND(E8<=0),"C",IF(E8<=0.8,"A",IF(E8<=0.95,"B","C"))) -> A | G8: =VLOOKUP(B$4:B$17,I$4:M$17,5,0) -> B | I8: th желт | J8: ='Юнит 23-29.03'!R11 -> 5 | K8: =J8/J$18 -> 0.092592593 | L8: =K8+L7 -> 0.66666667 | M8: =_xlfn.IFS(L8<80%,"A",L8<=95%,"B",L8>95%,"C") -> A
B9: qs черные | C9: ='Юнит 23-29.03'!AE4 -> 2033.3117 | D9: =C9/C$18 -> 0.067351063 | E9: =D9+E8 -> 0.85900166 | F9: =IF(AND(E9<=0),"C",IF(E9<=0.8,"A",IF(E9<=0.95,"B","C"))) -> B | G9: =VLOOKUP(B$4:B$17,I$4:M$17,5,0) -> A | I9: qs синие | J9: ='Юнит 23-29.03'!R5 -> 4 | K9: =J9/J$18 -> 0.074074074 | L9: =K9+L8 -> 0.74074074 | M9: =_xlfn.IFS(L9<80%,"A",L9<=95%,"B",L9>95%,"C") -> A
B10: th син | C10: ='Юнит 23-29.03'!AE10 -> 1980.0886 | D10: =C10/C$18 -> 0.065588112 | E10: =D10+E9 -> 0.92458977 | F10: =IF(AND(E10<=0),"C",IF(E10<=0.8,"A",IF(E10<=0.95,"B","C"))) -> B | G10: =VLOOKUP(B$4:B$17,I$4:M$17,5,0) -> A | I10: qs коричневые | J10: ='Юнит 23-29.03'!R7 -> 4 | K10: =J10/J$18 -> 0.074074074 | L10: =K10+L9 -> 0.81481481 | M10: =_xlfn.IFS(L10<80%,"A",L10<=95%,"B",L10>95%,"C") -> B
B11: th черн | C11: ='Юнит 23-29.03'!AE9 -> 1951.8173 | D11: =C11/C$18 -> 0.064651656 | E11: =D11+E10 -> 0.98924142 | F11: =IF(AND(E11<=0),"C",IF(E11<=0.8,"A",IF(E11<=0.95,"B","C"))) -> C | G11: =VLOOKUP(B$4:B$17,I$4:M$17,5,0) -> B | I11: th черн | J11: ='Юнит 23-29.03'!R9 -> 2 | K11: =J11/J$18 -> 0.037037037 | L11: =K11+L10 -> 0.85185185 | M11: =_xlfn.IFS(L11<80%,"A",L11<=95%,"B",L11>95%,"C") -> B
B12: flip жел | C12: ='Юнит 23-29.03'!AE15 -> 1845.8299 | D12: =C12/C$18 -> 0.06114095 | E12: =D12+E5 -> 0.55161269 | F12: =IF(AND(E12<=0),"C",IF(E12<=0.8,"A",IF(E12<=0.95,"B","C"))) -> A | G12: =VLOOKUP(B$4:B$17,I$4:M$17,5,0) -> A | I12: th син | J12: ='Юнит 23-29.03'!R10 -> 2 | K12: =J12/J$18 -> 0.037037037 | L12: =K12+L5 -> 0.40740741 | M12: =_xlfn.IFS(L12<80%,"A",L12<=95%,"B",L12>95%,"C") -> A
B13: flip синий | C13: ='Юнит 23-29.03'!AE14 -> 1153.505 | D13: =C13/C$18 -> 0.0382085 | E13: =D13+E12 -> 0.58982119 | F13: =IF(AND(E13<=0),"C",IF(E13<=0.8,"A",IF(E13<=0.95,"B","C"))) -> A | G13: =VLOOKUP(B$4:B$17,I$4:M$17,5,0) -> A | I13: th коричн | J13: ='Юнит 23-29.03'!R12 -> 2 | K13: =J13/J$18 -> 0.037037037 | L13: =K13+L12 -> 0.44444444 | M13: =_xlfn.IFS(L13<80%,"A",L13<=95%,"B",L13>95%,"C") -> A
B14: th желт | C14: ='Юнит 23-29.03'!AE11 -> 993.43114 | D14: =C14/C$18 -> 0.032906241 | E14: =D14+E13 -> 0.62272743 | F14: =IF(AND(E14<=0),"C",IF(E14<=0.8,"A",IF(E14<=0.95,"B","C"))) -> A | G14: =VLOOKUP(B$4:B$17,I$4:M$17,5,0) -> A | I14: flip жел | J14: ='Юнит 23-29.03'!R15 -> 2 | K14: =J14/J$18 -> 0.037037037 | L14: =K14+L13 -> 0.48148148 | M14: =_xlfn.IFS(L14<80%,"A",L14<=95%,"B",L14>95%,"C") -> A
B15: черные с железкой классика | C15: ='Юнит 23-29.03'!AE3 -> -1106.9801 | D15: =C15/C$18 -> -0.036667417 | E15: =D15+E14 -> 0.58606001 | F15: =IF(AND(E15<=0),"C",IF(E15<=0.8,"A",IF(E15<=0.95,"B","C"))) -> A | G15: =VLOOKUP(B$4:B$17,I$4:M$17,5,0) -> A | I15: черные с железкой классика | J15: ='Юнит 23-29.03'!R3 -> 1 | K15: =J15/J$18 -> 0.018518519 | L15: =K15+L14 -> 0.5 | M15: =_xlfn.IFS(L15<80%,"A",L15<=95%,"B",L15>95%,"C") -> A
B16: th коричн | C16: ='Юнит 23-29.03'!AE12 -> -1246.1138 | D16: =C16/C$18 -> -0.041276056 | E16: =D16+E15 -> 0.54478395 | F16: =IF(AND(E16<=0),"C",IF(E16<=0.8,"A",IF(E16<=0.95,"B","C"))) -> A | G16: =VLOOKUP(B$4:B$17,I$4:M$17,5,0) -> A | I16: flip синий | J16: ='Юнит 23-29.03'!R14 -> 1 | K16: =J16/J$18 -> 0.018518519 | L16: =K16+L15 -> 0.51851852 | M16: =_xlfn.IFS(L16<80%,"A",L16<=95%,"B",L16>95%,"C") -> A
B17: qs желтые | C17: ='Юнит 23-29.03'!AE6 -> -1314.8735 | D17: =C17/C$18 -> -0.043553642 | E17: =D17+E14 -> 0.57917379 | F17: =IF(AND(E17<=0),"C",IF(E17<=0.8,"A",IF(E17<=0.95,"B","C"))) -> A | G17: =VLOOKUP(B$4:B$17,I$4:M$17,5,0) -> A | I17: qs желтые | J17: ='Юнит 23-29.03'!R6 -> 0 | K17: =J17/J$18 -> 0 | L17: =K17+L14 -> 0.48148148 | M17: =_xlfn.IFS(L17<80%,"A",L17<=95%,"B",L17>95%,"C") -> A
C18: =SUM(C4:C17) -> 30189.749 | D18: =SUM(D4:D17) -> 1 | J18: =SUM(J4:J17) -> 54 | K18: =SUM(K4:K17) -> 1
C21: Прибыль | D21: % прибыль | E21: Доля | F21: ABC прибыль | G21: ABC кол-во | J21: Кол-во | K21: % кол-во | L21: Доля | M21: ABC кол-во
D22: =C22/C$42 -> #DIV/0! | E22: =D22 -> #DIV/0! | F22: =IF(AND(E22<=0),"C",IF(E22<=0.8,"A",IF(E22<=0.95,"B","C"))) -> #DIV/0! | G22: =VLOOKUP(B$22:B$42,I$22:M$42,5,0) -> #N/A | K22: =J22/J$42 -> #DIV/0! | L22: =K22 -> #DIV/0! | M22: =_xlfn.IFS(L22<80%,"A",L22<=95%,"B",L22>95%,"C") -> #DIV/0!
D23: =C23/C$42 -> #DIV/0! | E23: =D23+E22 -> #DIV/0! | F23: =IF(AND(E23<=0),"C",IF(E23<=0.8,"A",IF(E23<=0.95,"B","C"))) -> #DIV/0! | G23: =VLOOKUP(B$22:B$42,I$22:M$42,5,0) -> #N/A | K23: =J23/J$42 -> #DIV/0! | L23: =K23+L22 -> #DIV/0! | M23: =_xlfn.IFS(L23<80%,"A",L23<=95%,"B",L23>95%,"C") -> #DIV/0!
D24: =C24/C$42 -> #DIV/0! | E24: =D24+E23 -> #DIV/0! | F24: =IF(AND(E24<=0),"C",IF(E24<=0.8,"A",IF(E24<=0.95,"B","C"))) -> #DIV/0! | G24: =VLOOKUP(B$22:B$42,I$22:M$42,5,0) -> #N/A | K24: =J24/J$42 -> #DIV/0! | L24: =K24+L23 -> #DIV/0! | M24: =_xlfn.IFS(L24<80%,"A",L24<=95%,"B",L24>95%,"C") -> #DIV/0!
D25: =C25/C$42 -> #DIV/0! | E25: =D25+E24 -> #DIV/0! | F25: =IF(AND(E25<=0),"C",IF(E25<=0.8,"A",IF(E25<=0.95,"B","C"))) -> #DIV/0! | G25: =VLOOKUP(B$22:B$42,I$22:M$42,5,0) -> #N/A | K25: =J25/J$42 -> #DIV/0! | L25: =K25+L24 -> #DIV/0! | M25: =_xlfn.IFS(L25<80%,"A",L25<=95%,"B",L25>95%,"C") -> #DIV/0!
D26: =C26/C$42 -> #DIV/0! | E26: =D26+E25 -> #DIV/0! | F26: =IF(AND(E26<=0),"C",IF(E26<=0.8,"A",IF(E26<=0.95,"B","C"))) -> #DIV/0! | G26: =VLOOKUP(B$22:B$42,I$22:M$42,5,0) -> #N/A | K26: =J26/J$42 -> #DIV/0! | L26: =K26+L25 -> #DIV/0! | M26: =_xlfn.IFS(L26<80%,"A",L26<=95%,"B",L26>95%,"C") -> #DIV/0!
D27: =C27/C$42 -> #DIV/0! | E27: =D27+E26 -> #DIV/0! | F27: =IF(AND(E27<=0),"C",IF(E27<=0.8,"A",IF(E27<=0.95,"B","C"))) -> #DIV/0! | G27: =VLOOKUP(B$22:B$42,I$22:M$42,5,0) -> #N/A | K27: =J27/J$42 -> #DIV/0! | L27: =K27+L26 -> #DIV/0! | M27: =_xlfn.IFS(L27<80%,"A",L27<=95%,"B",L27>95%,"C") -> #DIV/0!
D28: =C28/C$42 -> #DIV/0! | E28: =D28+E27 -> #DIV/0! | F28: =IF(AND(E28<=0),"C",IF(E28<=0.8,"A",IF(E28<=0.95,"B","C"))) -> #DIV/0! | G28: =VLOOKUP(B$22:B$42,I$22:M$42,5,0) -> #N/A | K28: =J28/J$42 -> #DIV/0! | L28: =K28+L27 -> #DIV/0! | M28: =_xlfn.IFS(L28<80%,"A",L28<=95%,"B",L28>95%,"C") -> #DIV/0!
D29: =C29/C$42 -> #DIV/0! | E29: =D29+E28 -> #DIV/0! | F29: =IF(AND(E29<=0),"C",IF(E29<=0.8,"A",IF(E29<=0.95,"B","C"))) -> #DIV/0! | G29: =VLOOKUP(B$22:B$42,I$22:M$42,5,0) -> #N/A | K29: =J29/J$42 -> #DIV/0! | L29: =K29+L28 -> #DIV/0! | M29: =_xlfn.IFS(L29<80%,"A",L29<=95%,"B",L29>95%,"C") -> #DIV/0!
D30: =C30/C$42 -> #DIV/0! | E30: =D30+E29 -> #DIV/0! | F30: =IF(AND(E30<=0),"C",IF(E30<=0.8,"A",IF(E30<=0.95,"B","C"))) -> #DIV/0! | G30: =VLOOKUP(B$22:B$42,I$22:M$42,5,0) -> #N/A | K30: =J30/J$42 -> #DIV/0! | L30: =K30+L29 -> #DIV/0! | M30: =_xlfn.IFS(L30<80%,"A",L30<=95%,"B",L30>95%,"C") -> #DIV/0!
D31: =C31/C$42 -> #DIV/0! | E31: =D31+E30 -> #DIV/0! | F31: =IF(AND(E31<=0),"C",IF(E31<=0.8,"A",IF(E31<=0.95,"B","C"))) -> #DIV/0! | G31: =VLOOKUP(B$22:B$42,I$22:M$42,5,0) -> #N/A | K31: =J31/J$42 -> #DIV/0! | L31: =K31+L30 -> #DIV/0! | M31: =_xlfn.IFS(L31<80%,"A",L31<=95%,"B",L31>95%,"C") -> #DIV/0!
D32: =C32/C$42 -> #DIV/0! | E32: =D32+E31 -> #DIV/0! | F32: =IF(AND(E32<=0),"C",IF(E32<=0.8,"A",IF(E32<=0.95,"B","C"))) -> #DIV/0! | G32: =VLOOKUP(B$22:B$42,I$22:M$42,5,0) -> #N/A | K32: =J32/J$42 -> #DIV/0! | L32: =K32+L31 -> #DIV/0! | M32: =_xlfn.IFS(L32<80%,"A",L32<=95%,"B",L32>95%,"C") -> #DIV/0!
D33: =C33/C$42 -> #DIV/0! | E33: =D33+E32 -> #DIV/0! | F33: =IF(AND(E33<=0),"C",IF(E33<=0.8,"A",IF(E33<=0.95,"B","C"))) -> #DIV/0! | G33: =VLOOKUP(B$22:B$42,I$22:M$42,5,0) -> #N/A | K33: =J33/J$42 -> #DIV/0! | L33: =K33+L32 -> #DIV/0! | M33: =_xlfn.IFS(L33<80%,"A",L33<=95%,"B",L33>95%,"C") -> #DIV/0!
D34: =C34/C$42 -> #DIV/0! | E34: =D34+E33 -> #DIV/0! | F34: =IF(AND(E34<=0),"C",IF(E34<=0.8,"A",IF(E34<=0.95,"B","C"))) -> #DIV/0! | G34: =VLOOKUP(B$22:B$42,I$22:M$42,5,0) -> #N/A | K34: =J34/J$42 -> #DIV/0! | L34: =K34+L33 -> #DIV/0! | M34: =_xlfn.IFS(L34<80%,"A",L34<=95%,"B",L34>95%,"C") -> #DIV/0!
... D41: =C41/C$42 -> #DIV/0! | E41: =D41+E40 -> #DIV/0! | F41: =IF(AND(E41<=0),"C",IF(E41<=0.8,"A",IF(E41<=0.95,"B","C"))) -> #DIV/0! | G41: =VLOOKUP(B$22:B$42,I$22:M$42,5,0) -> #N/A | K41: =J41/J$42 -> #DIV/0! | L41: =K41+L40 -> #DIV/0! | M41: =_xlfn.IFS(L41<80%,"A",L41<=95%,"B",L41>95%,"C") -> #DIV/0!
C42: =SUM(C22:C41) -> 0 | D42: =SUM(D22:D41) -> #DIV/0! | J42: =SUM(J22:J41) -> 0 | K42: =SUM(K22:K41) -> #DIV/0!

Sheet АВС 16-22.03
B2: ОЧКИ
C3: Прибыль | D3: % прибыль | E3: Доля | F3: ABC прибыль | G3: ABC кол-во | J3: Кол-во | K3: % кол-во | L3: Доля | M3: ABC кол-во
B4: MR8854 C2 | C4: ='Юнит 16-22.03'!AE8 -> 17327.034 | D4: =C4/C$18 -> 0.42309671 | E4: =D4 -> 0.42309671 | F4: =IF(AND(E4<=0),"C",IF(E4<=0.8,"A",IF(E4<=0.95,"B","C"))) -> A | G4: =VLOOKUP(B$4:B$17,I$4:M$17,5,0) -> A | I4: MR8854 C2 | J4: ='Юнит 16-22.03'!R8 -> 21 | K4: =J4/J$18 -> 0.3559322 | L4: =K4 -> 0.3559322 | M4: =_xlfn.IFS(L4<80%,"A",L4<=95%,"B",L4>95%,"C") -> A
B5: flip жел | C5: ='Юнит 16-22.03'!AE15 -> 8577.8162 | D5: =C5/C$18 -> 0.20945569 | E5: =D5+E4 -> 0.63255239 | F5: =IF(AND(E5<=0),"C",IF(E5<=0.8,"A",IF(E5<=0.95,"B","C"))) -> A | G5: =VLOOKUP(B$4:B$17,I$4:M$17,5,0) -> A | I5: flip жел | J5: ='Юнит 16-22.03'!R15 -> 11 | K5: =J5/J$18 -> 0.18644068 | L5: =K5+L4 -> 0.54237288 | M5: =_xlfn.IFS(L5<80%,"A",L5<=95%,"B",L5>95%,"C") -> A
B6: flip коричневый | C6: ='Юнит 16-22.03'!AE16 -> 5015.337 | D6: =C6/C$18 -> 0.122466 | E6: =D6+E5 -> 0.7550184 | F6: =IF(AND(E6<=0),"C",IF(E6<=0.8,"A",IF(E6<=0.95,"B","C"))) -> A | G6: =VLOOKUP(B$4:B$17,I$4:M$17,5,0) -> A | I6: qs коричневые | J6: ='Юнит 16-22.03'!R7 -> 7 | K6: =J6/J$18 -> 0.11864407 | L6: =K6+L5 -> 0.66101695 | M6: =_xlfn.IFS(L6<80%,"A",L6<=95%,"B",L6>95%,"C") -> A
B7: qs коричневые | C7: ='Юнит 16-22.03'!AE7 -> 4914.6606 | D7: =C7/C$18 -> 0.12000766 | E7: =D7+E6 -> 0.87502606 | F7: =IF(AND(E7<=0),"C",IF(E7<=0.8,"A",IF(E7<=0.95,"B","C"))) -> B | G7: =VLOOKUP(B$4:B$17,I$4:M$17,5,0) -> A | I7: flip коричневый | J7: ='Юнит 16-22.03'!R16 -> 6 | K7: =J7/J$18 -> 0.10169492 | L7: =K7+L6 -> 0.76271186 | M7: =_xlfn.IFS(L7<80%,"A",L7<=95%,"B",L7>95%,"C") -> A
B8: qs желтые | C8: ='Юнит 16-22.03'!AE6 -> 3383.0169 | D8: =C8/C$18 -> 0.08260752 | E8: =D8+E7 -> 0.95763358 | F8: =IF(AND(E8<=0),"C",IF(E8<=0.8,"A",IF(E8<=0.95,"B","C"))) -> C | G8: =VLOOKUP(B$4:B$17,I$4:M$17,5,0) -> B | I8: qs желтые | J8: ='Юнит 16-22.03'!R6 -> 5 | K8: =J8/J$18 -> 0.084745763 | L8: =K8+L7 -> 0.84745763 | M8: =_xlfn.IFS(L8<80%,"A",L8<=95%,"B",L8>95%,"C") -> B
B9: flip черный | C9: ='Юнит 16-22.03'!AE13 -> 2165.3465 | D9: =C9/C$18 -> 0.052874079 | E9: =D9+E8 -> 1.0105077 | F9: =IF(AND(E9<=0),"C",IF(E9<=0.8,"A",IF(E9<=0.95,"B","C"))) -> C | G9: =VLOOKUP(B$4:B$17,I$4:M$17,5,0) -> A | I9: th син | J9: ='Юнит 16-22.03'!R10 -> 2 | K9: =J9/J$18 -> 0.033898305 | L9: =K9+L8 -> 0.88135593 | M9: =_xlfn.IFS(L9<80%,"A",L9<=95%,"B",L9>95%,"C") -> B
B10: th коричн | C10: ='Юнит 16-22.03'!AE12 -> 2025.0928 | D10: =C10/C$18 -> 0.049449324 | E10: =D10+E9 -> 1.059957 | F10: =IF(AND(E10<=0),"C",IF(E10<=0.8,"A",IF(E10<=0.95,"B","C"))) -> C | G10: =VLOOKUP(B$4:B$17,I$4:M$17,5,0) -> B | I10: th желт | J10: ='Юнит 16-22.03'!R11 -> 2 | K10: =J10/J$18 -> 0.033898305 | L10: =K10+L9 -> 0.91525424 | M10: =_xlfn.IFS(L10<80%,"A",L10<=95%,"B",L10>95%,"C") -> B
B11: черные с железкой классика | C11: ='Юнит 16-22.03'!AE3 -> 1064.1149 | D11: =C11/C$18 -> 0.025983876 | E11: =D11+E10 -> 1.0859409 | F11: =IF(AND(E11<=0),"C",IF(E11<=0.8,"A",IF(E11<=0.95,"B","C"))) -> C | G11: =VLOOKUP(B$4:B$17,I$4:M$17,5,0) -> A | I11: th коричн | J11: ='Юнит 16-22.03'!R12 -> 2 | K11: =J11/J$18 -> 0.033898305 | L11: =K11+L10 -> 0.94915254 | M11: =_xlfn.IFS(L11<80%,"A",L11<=95%,"B",L11>95%,"C") -> B
B12: th син | C12: ='Юнит 16-22.03'!AE10 -> 487.15649 | D12: =C12/C$18 -> 0.011895533 | E12: =D12+E5 -> 0.64444793 | F12: =IF(AND(E12<=0),"C",IF(E12<=0.8,"A",IF(E12<=0.95,"B","C"))) -> A | G12: =VLOOKUP(B$4:B$17,I$4:M$17,5,0) -> B | I12: flip черный | J12: ='Юнит 16-22.03'!R13 -> 2 | K12: =J12/J$18 -> 0.033898305 | L12: =K12+L5 -> 0.57627119 | M12: =_xlfn.IFS(L12<80%,"A",L12<=95%,"B",L12>95%,"C") -> A
B13: th черн | C13: ='Юнит 16-22.03'!AE9 -> -227.76 | D13: =C13/C$18 -> -0.005561512 | E13: =D13+E12 -> 0.63888642 | F13: =IF(AND(E13<=0),"C",IF(E13<=0.8,"A",IF(E13<=0.95,"B","C"))) -> A | G13: =VLOOKUP(B$4:B$17,I$4:M$17,5,0) -> A | I13: черные с железкой классика | J13: ='Юнит 16-22.03'!R3 -> 1 | K13: =J13/J$18 -> 0.016949153 | L13: =K13+L12 -> 0.59322034 | M13: =_xlfn.IFS(L13<80%,"A",L13<=95%,"B",L13>95%,"C") -> A
B14: flip синий | C14: ='Юнит 16-22.03'!AE14 -> -227.76 | D14: =C14/C$18 -> -0.005561512 | E14: =D14+E13 -> 0.6333249 | F14: =IF(AND(E14<=0),"C",IF(E14<=0.8,"A",IF(E14<=0.95,"B","C"))) -> A | G14: =VLOOKUP(B$4:B$17,I$4:M$17,5,0) -> A | I14: qs черные | J14: ='Юнит 16-22.03'!R4 -> 0 | K14: =J14/J$18 -> 0 | L14: =K14+L13 -> 0.59322034 | M14: =_xlfn.IFS(L14<80%,"A",L14<=95%,"B",L14>95%,"C") -> A
B15: th желт | C15: ='Юнит 16-22.03'!AE11 -> -532.03327 | D15: =C15/C$18 -> -0.012991348 | E15: =D15+E14 -> 0.62033356 | F15: =IF(AND(E15<=0),"C",IF(E15<=0.8,"A",IF(E15<=0.95,"B","C"))) -> A | G15: =VLOOKUP(B$4:B$17,I$4:M$17,5,0) -> B | I15: qs синие | J15: ='Юнит 16-22.03'!R5 -> 0 | K15: =J15/J$18 -> 0 | L15: =K15+L14 -> 0.59322034 | M15: =_xlfn.IFS(L15<80%,"A",L15<=95%,"B",L15>95%,"C") -> A
B16: qs синие | C16: ='Юнит 16-22.03'!AE5 -> -846.19408 | D16: =C16/C$18 -> -0.020662621 | E16: =D16+E15 -> 0.59967094 | F16: =IF(AND(E16<=0),"C",IF(E16<=0.8,"A",IF(E16<=0.95,"B","C"))) -> A | G16: =VLOOKUP(B$4:B$17,I$4:M$17,5,0) -> A | I16: th черн | J16: ='Юнит 16-22.03'!R9 -> 0 | K16: =J16/J$18 -> 0 | L16: =K16+L15 -> 0.59322034 | M16: =_xlfn.IFS(L16<80%,"A",L16<=95%,"B",L16>95%,"C") -> A
B17: qs черные | C17: ='Юнит 16-22.03'!AE4 -> -2172.9357 | D17: =C17/C$18 -> -0.053059395 | E17: =D17+E14 -> 0.58026551 | F17: =IF(AND(E17<=0),"C",IF(E17<=0.8,"A",IF(E17<=0.95,"B","C"))) -> A | G17: =VLOOKUP(B$4:B$17,I$4:M$17,5,0) -> A | I17: flip синий | J17: ='Юнит 16-22.03'!R14 -> 0 | K17: =J17/J$18 -> 0 | L17: =K17+L14 -> 0.59322034 | M17: =_xlfn.IFS(L17<80%,"A",L17<=95%,"B",L17>95%,"C") -> A
C18: =SUM(C4:C17) -> 40952.892 | D18: =SUM(D4:D17) -> 1 | J18: =SUM(J4:J17) -> 59 | K18: =SUM(K4:K17) -> 1
C21: Прибыль | D21: % прибыль | E21: Доля | F21: ABC прибыль | G21: ABC кол-во | J21: Кол-во | K21: % кол-во | L21: Доля | M21: ABC кол-во
D22: =C22/C$42 -> #DIV/0! | E22: =D22 -> #DIV/0! | F22: =IF(AND(E22<=0),"C",IF(E22<=0.8,"A",IF(E22<=0.95,"B","C"))) -> #DIV/0! | G22: =VLOOKUP(B$22:B$42,I$22:M$42,5,0) -> #N/A | K22: =J22/J$42 -> #DIV/0! | L22: =K22 -> #DIV/0! | M22: =_xlfn.IFS(L22<80%,"A",L22<=95%,"B",L22>95%,"C") -> #DIV/0!
D23: =C23/C$42 -> #DIV/0! | E23: =D23+E22 -> #DIV/0! | F23: =IF(AND(E23<=0),"C",IF(E23<=0.8,"A",IF(E23<=0.95,"B","C"))) -> #DIV/0! | G23: =VLOOKUP(B$22:B$42,I$22:M$42,5,0) -> #N/A | K23: =J23/J$42 -> #DIV/0! | L23: =K23+L22 -> #DIV/0! | M23: =_xlfn.IFS(L23<80%,"A",L23<=95%,"B",L23>95%,"C") -> #DIV/0!
D24: =C24/C$42 -> #DIV/0! | E24: =D24+E23 -> #DIV/0! | F24: =IF(AND(E24<=0),"C",IF(E24<=0.8,"A",IF(E24<=0.95,"B","C"))) -> #DIV/0! | G24: =VLOOKUP(B$22:B$42,I$22:M$42,5,0) -> #N/A | K24: =J24/J$42 -> #DIV/0! | L24: =K24+L23 -> #DIV/0! | M24: =_xlfn.IFS(L24<80%,"A",L24<=95%,"B",L24>95%,"C") -> #DIV/0!
D25: =C25/C$42 -> #DIV/0! | E25: =D25+E24 -> #DIV/0! | F25: =IF(AND(E25<=0),"C",IF(E25<=0.8,"A",IF(E25<=0.95,"B","C"))) -> #DIV/0! | G25: =VLOOKUP(B$22:B$42,I$22:M$42,5,0) -> #N/A | K25: =J25/J$42 -> #DIV/0! | L25: =K25+L24 -> #DIV/0! | M25: =_xlfn.IFS(L25<80%,"A",L25<=95%,"B",L25>95%,"C") -> #DIV/0!
D26: =C26/C$42 -> #DIV/0! | E26: =D26+E25 -> #DIV/0! | F26: =IF(AND(E26<=0),"C",IF(E26<=0.8,"A",IF(E26<=0.95,"B","C"))) -> #DIV/0! | G26: =VLOOKUP(B$22:B$42,I$22:M$42,5,0) -> #N/A | K26: =J26/J$42 -> #DIV/0! | L26: =K26+L25 -> #DIV/0! | M26: =_xlfn.IFS(L26<80%,"A",L26<=95%,"B",L26>95%,"C") -> #DIV/0!
D27: =C27/C$42 -> #DIV/0! | E27: =D27+E26 -> #DIV/0! | F27: =IF(AND(E27<=0),"C",IF(E27<=0.8,"A",IF(E27<=0.95,"B","C"))) -> #DIV/0! | G27: =VLOOKUP(B$22:B$42,I$22:M$42,5,0) -> #N/A | K27: =J27/J$42 -> #DIV/0! | L27: =K27+L26 -> #DIV/0! | M27: =_xlfn.IFS(L27<80%,"A",L27<=95%,"B",L27>95%,"C") -> #DIV/0!
D28: =C28/C$42 -> #DIV/0! | E28: =D28+E27 -> #DIV/0! | F28: =IF(AND(E28<=0),"C",IF(E28<=0.8,"A",IF(E28<=0.95,"B","C"))) -> #DIV/0! | G28: =VLOOKUP(B$22:B$42,I$22:M$42,5,0) -> #N/A | K28: =J28/J$42 -> #DIV/0! | L28: =K28+L27 -> #DIV/0! | M28: =_xlfn.IFS(L28<80%,"A",L28<=95%,"B",L28>95%,"C") -> #DIV/0!
D29: =C29/C$42 -> #DIV/0! | E29: =D29+E28 -> #DIV/0! | F29: =IF(AND(E29<=0),"C",IF(E29<=0.8,"A",IF(E29<=0.95,"B","C"))) -> #DIV/0! | G29: =VLOOKUP(B$22:B$42,I$22:M$42,5,0) -> #N/A | K29: =J29/J$42 -> #DIV/0! | L29: =K29+L28 -> #DIV/0! | M29: =_xlfn.IFS(L29<80%,"A",L29<=95%,"B",L29>95%,"C") -> #DIV/0!
D30: =C30/C$42 -> #DIV/0! | E30: =D30+E29 -> #DIV/0! | F30: =IF(AND(E30<=0),"C",IF(E30<=0.8,"A",IF(E30<=0.95,"B","C"))) -> #DIV/0! | G30: =VLOOKUP(B$22:B$42,I$22:M$42,5,0) -> #N/A | K30: =J30/J$42 -> #DIV/0! | L30: =K30+L29 -> #DIV/0! | M30: =_xlfn.IFS(L30<80%,"A",L30<=95%,"B",L30>95%,"C") -> #DIV/0!
D31: =C31/C$42 -> #DIV/0! | E31: =D31+E30 -> #DIV/0! | F31: =IF(AND(E31<=0),"C",IF(E31<=0.8,"A",IF(E31<=0.95,"B","C"))) -> #DIV/0! | G31: =VLOOKUP(B$22:B$42,I$22:M$42,5,0) -> #N/A | K31: =J31/J$42 -> #DIV/0! | L31: =K31+L30 -> #DIV/0! | M31: =_xlfn.IFS(L31<80%,"A",L31<=95%,"B",L31>95%,"C") -> #DIV/0!
D32: =C32/C$42 -> #DIV/0! | E32: =D32+E31 -> #DIV/0! | F32: =IF(AND(E32<=0),"C",IF(E32<=0.8,"A",IF(E32<=0.95,"B","C"))) -> #DIV/0! | G32: =VLOOKUP(B$22:B$42,I$22:M$42,5,0) -> #N/A | K32: =J32/J$42 -> #DIV/0! | L32: =K32+L31 -> #DIV/0! | M32: =_xlfn.IFS(L32<80%,"A",L32<=95%,"B",L32>95%,"C") -> #DIV/0!
D33: =C33/C$42 -> #DIV/0! | E33: =D33+E32 -> #DIV/0! | F33: =IF(AND(E33<=0),"C",IF(E33<=0.8,"A",IF(E33<=0.95,"B","C"))) -> #DIV/0! | G33: =VLOOKUP(B$22:B$42,I$22:M$42,5,0) -> #N/A | K33: =J33/J$42 -> #DIV/0! | L33: =K33+L32 -> #DIV/0! | M33: =_xlfn.IFS(L33<80%,"A",L33<=95%,"B",L33>95%,"C") -> #DIV/0!
D34: =C34/C$42 -> #DIV/0! | E34: =D34+E33 -> #DIV/0! | F34: =IF(AND(E34<=0),"C",IF(E34<=0.8,"A",IF(E34<=0.95,"B","C"))) -> #DIV/0! | G34: =VLOOKUP(B$22:B$42,I$22:M$42,5,0) -> #N/A | K34: =J34/J$42 -> #DIV/0! | L34: =K34+L33 -> #DIV/0! | M34: =_xlfn.IFS(L34<80%,"A",L34<=95%,"B",L34>95%,"C") -> #DIV/0!
... D41: =C41/C$42 -> #DIV/0! | E41: =D41+E40 -> #DIV/0! | F41: =IF(AND(E41<=0),"C",IF(E41<=0.8,"A",IF(E41<=0.95,"B","C"))) -> #DIV/0! | G41: =VLOOKUP(B$22:B$42,I$22:M$42,5,0) -> #N/A | K41: =J41/J$42 -> #DIV/0! | L41: =K41+L40 -> #DIV/0! | M41: =_xlfn.IFS(L41<80%,"A",L41<=95%,"B",L41>95%,"C") -> #DIV/0!
C42: =SUM(C22:C41) -> 0 | D42: =SUM(D22:D41) -> #DIV/0! | J42: =SUM(J22:J41) -> 0 | K42: =SUM(K22:K41) -> #DIV/0!

Sheet АВС 09-15.03
B2: ОЧКИ
C3: Прибыль | D3: % прибыль | E3: Доля | F3: ABC прибыль | G3: ABC кол-во | J3: Кол-во | K3: % кол-во | L3: Доля | M3: ABC кол-во
B4: MR8854 C2 | C4: ='Юнит 09-15.03'!AE8 -> 17647.861 | D4: =C4/C$18 -> 0.31065247 | E4: =D4 -> 0.31065247 | F4: =IF(AND(E4<=0),"C",IF(E4<=0.8,"A",IF(E4<=0.95,"B","C"))) -> A | G4: =VLOOKUP(B$4:B$17,I$4:M$17,5,0) -> A | I4: MR8854 C2 | J4: ='Юнит 09-15.03'!R8 -> 27 | K4: =J4/J$18 -> 0.29347826 | L4: =K4 -> 0.29347826 | M4: =_xlfn.IFS(L4<80%,"A",L4<=95%,"B",L4>95%,"C") -> A
B5: flip черный | C5: ='Юнит 09-15.03'!AE13 -> 8759.325 | D5: =C5/C$18 -> 0.154189 | E5: =D5+E4 -> 0.46484147 | F5: =IF(AND(E5<=0),"C",IF(E5<=0.8,"A",IF(E5<=0.95,"B","C"))) -> A | G5: =VLOOKUP(B$4:B$17,I$4:M$17,5,0) -> A | I5: flip жел | J5: ='Юнит 09-15.03'!R15 -> 13 | K5: =J5/J$18 -> 0.14130435 | L5: =K5+L4 -> 0.43478261 | M5: =_xlfn.IFS(L5<80%,"A",L5<=95%,"B",L5>95%,"C") -> A
B6: flip жел | C6: ='Юнит 09-15.03'!AE15 -> 6988.5675 | D6: =C6/C$18 -> 0.12301863 | E6: =D6+E5 -> 0.5878601 | F6: =IF(AND(E6<=0),"C",IF(E6<=0.8,"A",IF(E6<=0.95,"B","C"))) -> A | G6: =VLOOKUP(B$4:B$17,I$4:M$17,5,0) -> A | I6: qs коричневые | J6: ='Юнит 09-15.03'!R7 -> 12 | K6: =J6/J$18 -> 0.13043478 | L6: =K6+L5 -> 0.56521739 | M6: =_xlfn.IFS(L6<80%,"A",L6<=95%,"B",L6>95%,"C") -> A
B7: qs коричневые | C7: ='Юнит 09-15.03'!AE7 -> 4618.0378 | D7: =C7/C$18 -> 0.08129058 | E7: =D7+E6 -> 0.66915069 | F7: =IF(AND(E7<=0),"C",IF(E7<=0.8,"A",IF(E7<=0.95,"B","C"))) -> A | G7: =VLOOKUP(B$4:B$17,I$4:M$17,5,0) -> A | I7: flip черный | J7: ='Юнит 09-15.03'!R13 -> 10 | K7: =J7/J$18 -> 0.10869565 | L7: =K7+L6 -> 0.67391304 | M7: =_xlfn.IFS(L7<80%,"A",L7<=95%,"B",L7>95%,"C") -> A
B8: qs желтые | C8: ='Юнит 09-15.03'!AE6 -> 3849.3728 | D8: =C8/C$18 -> 0.067759893 | E8: =D8+E7 -> 0.73691058 | F8: =IF(AND(E8<=0),"C",IF(E8<=0.8,"A",IF(E8<=0.95,"B","C"))) -> A | G8: =VLOOKUP(B$4:B$17,I$4:M$17,5,0) -> A | I8: qs желтые | J8: ='Юнит 09-15.03'!R6 -> 7 | K8: =J8/J$18 -> 0.076086957 | L8: =K8+L7 -> 0.75 | M8: =_xlfn.IFS(L8<80%,"A",L8<=95%,"B",L8>95%,"C") -> A
B9: th коричн | C9: ='Юнит 09-15.03'!AE12 -> 3706.648 | D9: =C9/C$18 -> 0.065247531 | E9: =D9+E8 -> 0.80215811 | F9: =IF(AND(E9<=0),"C",IF(E9<=0.8,"A",IF(E9<=0.95,"B","C"))) -> B | G9: =VLOOKUP(B$4:B$17,I$4:M$17,5,0) -> B | I9: flip коричневый | J9: ='Юнит 09-15.03'!R16 -> 6 | K9: =J9/J$18 -> 0.065217391 | L9: =K9+L8 -> 0.81521739 | M9: =_xlfn.IFS(L9<80%,"A",L9<=95%,"B",L9>95%,"C") -> B
B10: qs синие | C10: ='Юнит 09-15.03'!AE5 -> 3561.3402 | D10: =C10/C$18 -> 0.062689702 | E10: =D10+E9 -> 0.86484781 | F10: =IF(AND(E10<=0),"C",IF(E10<=0.8,"A",IF(E10<=0.95,"B","C"))) -> B | G10: =VLOOKUP(B$4:B$17,I$4:M$17,5,0) -> A | I10: th коричн | J10: ='Юнит 09-15.03'!R12 -> 4 | K10: =J10/J$18 -> 0.043478261 | L10: =K10+L9 -> 0.85869565 | M10: =_xlfn.IFS(L10<80%,"A",L10<=95%,"B",L10>95%,"C") -> B
B11: flip коричневый | C11: ='Юнит 09-15.03'!AE16 -> 3184.4268 | D11: =C11/C$18 -> 0.056054956 | E11: =D11+E10 -> 0.92090277 | F11: =IF(AND(E11<=0),"C",IF(E11<=0.8,"A",IF(E11<=0.95,"B","C"))) -> B | G11: =VLOOKUP(B$4:B$17,I$4:M$17,5,0) -> B | I11: черные с железкой классика | J11: ='Юнит 09-15.03'!R3 -> 3 | K11: =J11/J$18 -> 0.032608696 | L11: =K11+L10 -> 0.89130435 | M11: =_xlfn.IFS(L11<80%,"A",L11<=95%,"B",L11>95%,"C") -> B
B12: qs черные | C12: ='Юнит 09-15.03'!AE4 -> 2163.9007 | D12: =C12/C$18 -> 0.038090797 | E12: =D12+E5 -> 0.50293227 | F12: =IF(AND(E12<=0),"C",IF(E12<=0.8,"A",IF(E12<=0.95,"B","C"))) -> A | G12: =VLOOKUP(B$4:B$17,I$4:M$17,5,0) -> A | I12: qs черные | J12: ='Юнит 09-15.03'!R4 -> 3 | K12: =J12/J$18 -> 0.032608696 | L12: =K12+L5 -> 0.4673913 | M12: =_xlfn.IFS(L12<80%,"A",L12<=95%,"B",L12>95%,"C") -> A
B13: черные с железкой классика | C13: ='Юнит 09-15.03'!AE3 -> 1187.0783 | D13: =C13/C$18 -> 0.02089595 | E13: =D13+E12 -> 0.52382822 | F13: =IF(AND(E13<=0),"C",IF(E13<=0.8,"A",IF(E13<=0.95,"B","C"))) -> A | G13: =VLOOKUP(B$4:B$17,I$4:M$17,5,0) -> B | I13: qs синие | J13: ='Юнит 09-15.03'!R5 -> 3 | K13: =J13/J$18 -> 0.032608696 | L13: =K13+L12 -> 0.5 | M13: =_xlfn.IFS(L13<80%,"A",L13<=95%,"B",L13>95%,"C") -> A
B14: th черн | C14: ='Юнит 09-15.03'!AE9 -> 865.64118 | D14: =C14/C$18 -> 0.015237743 | E14: =D14+E13 -> 0.53906596 | F14: =IF(AND(E14<=0),"C",IF(E14<=0.8,"A",IF(E14<=0.95,"B","C"))) -> A | G14: =VLOOKUP(B$4:B$17,I$4:M$17,5,0) -> A | I14: th черн | J14: ='Юнит 09-15.03'!R9 -> 2 | K14: =J14/J$18 -> 0.02173913 | L14: =K14+L13 -> 0.52173913 | M14: =_xlfn.IFS(L14<80%,"A",L14<=95%,"B",L14>95%,"C") -> A
B15: th син | C15: ='Юнит 09-15.03'!AE10 -> 378.06795 | D15: =C15/C$18 -> 0.0066550697 | E15: =D15+E14 -> 0.54572103 | F15: =IF(AND(E15<=0),"C",IF(E15<=0.8,"A",IF(E15<=0.95,"B","C"))) -> A | G15: =VLOOKUP(B$4:B$17,I$4:M$17,5,0) -> A | I15: th син | J15: ='Юнит 09-15.03'!R10 -> 1 | K15: =J15/J$18 -> 0.010869565 | L15: =K15+L14 -> 0.5326087 | M15: =_xlfn.IFS(L15<80%,"A",L15<=95%,"B",L15>95%,"C") -> A
B16: th желт | C16: ='Юнит 09-15.03'!AE11 -> 12.627754 | D16: =C16/C$18 -> 0.00022228433 | E16: =D16+E15 -> 0.54594331 | F16: =IF(AND(E16<=0),"C",IF(E16<=0.8,"A",IF(E16<=0.95,"B","C"))) -> A | G16: =VLOOKUP(B$4:B$17,I$4:M$17,5,0) -> A | I16: th желт | J16: ='Юнит 09-15.03'!R11 -> 1 | K16: =J16/J$18 -> 0.010869565 | L16: =K16+L15 -> 0.54347826 | M16: =_xlfn.IFS(L16<80%,"A",L16<=95%,"B",L16>95%,"C") -> A
B17: flip синий | C17: ='Юнит 09-15.03'!AE14 -> -113.88 | D17: =C17/C$18 -> -0.0020046114 | E17: =D17+E14 -> 0.53706135 | F17: =IF(AND(E17<=0),"C",IF(E17<=0.8,"A",IF(E17<=0.95,"B","C"))) -> A | G17: =VLOOKUP(B$4:B$17,I$4:M$17,5,0) -> A | I17: flip синий | J17: ='Юнит 09-15.03'!R14 -> 0 | K17: =J17/J$18 -> 0 | L17: =K17+L14 -> 0.52173913 | M17: =_xlfn.IFS(L17<80%,"A",L17<=95%,"B",L17>95%,"C") -> A
C18: =SUM(C4:C17) -> 56809.015 | D18: =SUM(D4:D17) -> 1 | J18: =SUM(J4:J17) -> 92 | K18: =SUM(K4:K17) -> 1
C21: Прибыль | D21: % прибыль | E21: Доля | F21: ABC прибыль | G21: ABC кол-во | J21: Кол-во | K21: % кол-во | L21: Доля | M21: ABC кол-во
D22: =C22/C$42 -> #DIV/0! | E22: =D22 -> #DIV/0! | F22: =IF(AND(E22<=0),"C",IF(E22<=0.8,"A",IF(E22<=0.95,"B","C"))) -> #DIV/0! | G22: =VLOOKUP(B$22:B$42,I$22:M$42,5,0) -> #N/A | K22: =J22/J$42 -> #DIV/0! | L22: =K22 -> #DIV/0! | M22: =_xlfn.IFS(L22<80%,"A",L22<=95%,"B",L22>95%,"C") -> #DIV/0!
D23: =C23/C$42 -> #DIV/0! | E23: =D23+E22 -> #DIV/0! | F23: =IF(AND(E23<=0),"C",IF(E23<=0.8,"A",IF(E23<=0.95,"B","C"))) -> #DIV/0! | G23: =VLOOKUP(B$22:B$42,I$22:M$42,5,0) -> #N/A | K23: =J23/J$42 -> #DIV/0! | L23: =K23+L22 -> #DIV/0! | M23: =_xlfn.IFS(L23<80%,"A",L23<=95%,"B",L23>95%,"C") -> #DIV/0!
D24: =C24/C$42 -> #DIV/0! | E24: =D24+E23 -> #DIV/0! | F24: =IF(AND(E24<=0),"C",IF(E24<=0.8,"A",IF(E24<=0.95,"B","C"))) -> #DIV/0! | G24: =VLOOKUP(B$22:B$42,I$22:M$42,5,0) -> #N/A | K24: =J24/J$42 -> #DIV/0! | L24: =K24+L23 -> #DIV/0! | M24: =_xlfn.IFS(L24<80%,"A",L24<=95%,"B",L24>95%,"C") -> #DIV/0!
D25: =C25/C$42 -> #DIV/0! | E25: =D25+E24 -> #DIV/0! | F25: =IF(AND(E25<=0),"C",IF(E25<=0.8,"A",IF(E25<=0.95,"B","C"))) -> #DIV/0! | G25: =VLOOKUP(B$22:B$42,I$22:M$42,5,0) -> #N/A | K25: =J25/J$42 -> #DIV/0! | L25: =K25+L24 -> #DIV/0! | M25: =_xlfn.IFS(L25<80%,"A",L25<=95%,"B",L25>95%,"C") -> #DIV/0!
D26: =C26/C$42 -> #DIV/0! | E26: =D26+E25 -> #DIV/0! | F26: =IF(AND(E26<=0),"C",IF(E26<=0.8,"A",IF(E26<=0.95,"B","C"))) -> #DIV/0! | G26: =VLOOKUP(B$22:B$42,I$22:M$42,5,0) -> #N/A | K26: =J26/J$42 -> #DIV/0! | L26: =K26+L25 -> #DIV/0! | M26: =_xlfn.IFS(L26<80%,"A",L26<=95%,"B",L26>95%,"C") -> #DIV/0!
D27: =C27/C$42 -> #DIV/0! | E27: =D27+E26 -> #DIV/0! | F27: =IF(AND(E27<=0),"C",IF(E27<=0.8,"A",IF(E27<=0.95,"B","C"))) -> #DIV/0! | G27: =VLOOKUP(B$22:B$42,I$22:M$42,5,0) -> #N/A | K27: =J27/J$42 -> #DIV/0! | L27: =K27+L26 -> #DIV/0! | M27: =_xlfn.IFS(L27<80%,"A",L27<=95%,"B",L27>95%,"C") -> #DIV/0!
D28: =C28/C$42 -> #DIV/0! | E28: =D28+E27 -> #DIV/0! | F28: =IF(AND(E28<=0),"C",IF(E28<=0.8,"A",IF(E28<=0.95,"B","C"))) -> #DIV/0! | G28: =VLOOKUP(B$22:B$42,I$22:M$42,5,0) -> #N/A | K28: =J28/J$42 -> #DIV/0! | L28: =K28+L27 -> #DIV/0! | M28: =_xlfn.IFS(L28<80%,"A",L28<=95%,"B",L28>95%,"C") -> #DIV/0!
D29: =C29/C$42 -> #DIV/0! | E29: =D29+E28 -> #DIV/0! | F29: =IF(AND(E29<=0),"C",IF(E29<=0.8,"A",IF(E29<=0.95,"B","C"))) -> #DIV/0! | G29: =VLOOKUP(B$22:B$42,I$22:M$42,5,0) -> #N/A | K29: =J29/J$42 -> #DIV/0! | L29: =K29+L28 -> #DIV/0! | M29: =_xlfn.IFS(L29<80%,"A",L29<=95%,"B",L29>95%,"C") -> #DIV/0!
D30: =C30/C$42 -> #DIV/0! | E30: =D30+E29 -> #DIV/0! | F30: =IF(AND(E30<=0),"C",IF(E30<=0.8,"A",IF(E30<=0.95,"B","C"))) -> #DIV/0! | G30: =VLOOKUP(B$22:B$42,I$22:M$42,5,0) -> #N/A | K30: =J30/J$42 -> #DIV/0! | L30: =K30+L29 -> #DIV/0! | M30: =_xlfn.IFS(L30<80%,"A",L30<=95%,"B",L30>95%,"C") -> #DIV/0!
D31: =C31/C$42 -> #DIV/0! | E31: =D31+E30 -> #DIV/0! | F31: =IF(AND(E31<=0),"C",IF(E31<=0.8,"A",IF(E31<=0.95,"B","C"))) -> #DIV/0! | G31: =VLOOKUP(B$22:B$42,I$22:M$42,5,0) -> #N/A | K31: =J31/J$42 -> #DIV/0! | L31: =K31+L30 -> #DIV/0! | M31: =_xlfn.IFS(L31<80%,"A",L31<=95%,"B",L31>95%,"C") -> #DIV/0!
D32: =C32/C$42 -> #DIV/0! | E32: =D32+E31 -> #DIV/0! | F32: =IF(AND(E32<=0),"C",IF(E32<=0.8,"A",IF(E32<=0.95,"B","C"))) -> #DIV/0! | G32: =VLOOKUP(B$22:B$42,I$22:M$42,5,0) -> #N/A | K32: =J32/J$42 -> #DIV/0! | L32: =K32+L31 -> #DIV/0! | M32: =_xlfn.IFS(L32<80%,"A",L32<=95%,"B",L32>95%,"C") -> #DIV/0!
D33: =C33/C$42 -> #DIV/0! | E33: =D33+E32 -> #DIV/0! | F33: =IF(AND(E33<=0),"C",IF(E33<=0.8,"A",IF(E33<=0.95,"B","C"))) -> #DIV/0! | G33: =VLOOKUP(B$22:B$42,I$22:M$42,5,0) -> #N/A | K33: =J33/J$42 -> #DIV/0! | L33: =K33+L32 -> #DIV/0! | M33: =_xlfn.IFS(L33<80%,"A",L33<=95%,"B",L33>95%,"C") -> #DIV/0!
D34: =C34/C$42 -> #DIV/0! | E34: =D34+E33 -> #DIV/0! | F34: =IF(AND(E34<=0),"C",IF(E34<=0.8,"A",IF(E34<=0.95,"B","C"))) -> #DIV/0! | G34: =VLOOKUP(B$22:B$42,I$22:M$42,5,0) -> #N/A | K34: =J34/J$42 -> #DIV/0! | L34: =K34+L33 -> #DIV/0! | M34: =_xlfn.IFS(L34<80%,"A",L34<=95%,"B",L34>95%,"C") -> #DIV/0!
... D41: =C41/C$42 -> #DIV/0! | E41: =D41+E40 -> #DIV/0! | F41: =IF(AND(E41<=0),"C",IF(E41<=0.8,"A",IF(E41<=0.95,"B","C"))) -> #DIV/0! | G41: =VLOOKUP(B$22:B$42,I$22:M$42,5,0) -> #N/A | K41: =J41/J$42 -> #DIV/0! | L41: =K41+L40 -> #DIV/0! | M41: =_xlfn.IFS(L41<80%,"A",L41<=95%,"B",L41>95%,"C") -> #DIV/0!
C42: =SUM(C22:C41) -> 0 | D42: =SUM(D22:D41) -> #DIV/0! | J42: =SUM(J22:J41) -> 0 | K42: =SUM(K22:K41) -> #DIV/0!

Sheet АВС 02-08.03
B2: ОЧКИ
C3: Прибыль | D3: % прибыль | E3: Доля | F3: ABC прибыль | G3: ABC кол-во | J3: Кол-во | K3: % кол-во | L3: Доля | M3: ABC кол-во
B4: th желт | C4: ='Юнит 02-08.03'!AE11 -> 7184.9577 | D4: =C4/C$18 -> 0.25404898 | E4: =D4 -> 0.25404898 | F4: =IF(AND(E4<=0),"C",IF(E4<=0.8,"A",IF(E4<=0.95,"B","C"))) -> A | G4: =VLOOKUP(B$4:B$17,I$4:M$17,5,0) -> A | I4: MR8854 C2 | J4: ='Юнит 02-08.03'!R8 -> 14 | K4: =J4/J$18 -> 0.15730337 | L4: =K4 -> 0.15730337 | M4: =_xlfn.IFS(L4<80%,"A",L4<=95%,"B",L4>95%,"C") -> A
B5: qs коричневые | C5: ='Юнит 02-08.03'!AE7 -> 5286.3223 | D5: =C5/C$18 -> 0.18691618 | E5: =D5+E4 -> 0.44096516 | F5: =IF(AND(E5<=0),"C",IF(E5<=0.8,"A",IF(E5<=0.95,"B","C"))) -> A | G5: =VLOOKUP(B$4:B$17,I$4:M$17,5,0) -> A | I5: qs коричневые | J5: ='Юнит 02-08.03'!R7 -> 13 | K5: =J5/J$18 -> 0.14606742 | L5: =K5+L4 -> 0.30337079 | M5: =_xlfn.IFS(L5<80%,"A",L5<=95%,"B",L5>95%,"C") -> A
B6: th черн | C6: ='Юнит 02-08.03'!AE9 -> 4879.252 | D6: =C6/C$18 -> 0.1725228 | E6: =D6+E5 -> 0.61348796 | F6: =IF(AND(E6<=0),"C",IF(E6<=0.8,"A",IF(E6<=0.95,"B","C"))) -> A | G6: =VLOOKUP(B$4:B$17,I$4:M$17,5,0) -> B | I6: flip жел | J6: ='Юнит 02-08.03'!R15 -> 12 | K6: =J6/J$18 -> 0.13483146 | L6: =K6+L5 -> 0.43820225 | M6: =_xlfn.IFS(L6<80%,"A",L6<=95%,"B",L6>95%,"C") -> A
B7: MR8854 C2 | C7: ='Юнит 02-08.03'!AE8 -> 3210.7427 | D7: =C7/C$18 -> 0.11352689 | E7: =D7+E6 -> 0.72701485 | F7: =IF(AND(E7<=0),"C",IF(E7<=0.8,"A",IF(E7<=0.95,"B","C"))) -> A | G7: =VLOOKUP(B$4:B$17,I$4:M$17,5,0) -> A | I7: qs желтые | J7: ='Юнит 02-08.03'!R6 -> 8 | K7: =J7/J$18 -> 0.08988764 | L7: =K7+L6 -> 0.52808989 | M7: =_xlfn.IFS(L7<80%,"A",L7<=95%,"B",L7>95%,"C") -> A
B8: flip черный | C8: ='Юнит 02-08.03'!AE13 -> 2905.8291 | D8: =C8/C$18 -> 0.10274562 | E8: =D8+E7 -> 0.82976047 | F8: =IF(AND(E8<=0),"C",IF(E8<=0.8,"A",IF(E8<=0.95,"B","C"))) -> B | G8: =VLOOKUP(B$4:B$17,I$4:M$17,5,0) -> A | I8: th желт | J8: ='Юнит 02-08.03'!R11 -> 8 | K8: =J8/J$18 -> 0.08988764 | L8: =K8+L7 -> 0.61797753 | M8: =_xlfn.IFS(L8<80%,"A",L8<=95%,"B",L8>95%,"C") -> A
B9: flip жел | C9: ='Юнит 02-08.03'!AE15 -> 2790.4321 | D9: =C9/C$18 -> 0.098665363 | E9: =D9+E8 -> 0.92842584 | F9: =IF(AND(E9<=0),"C",IF(E9<=0.8,"A",IF(E9<=0.95,"B","C"))) -> B | G9: =VLOOKUP(B$4:B$17,I$4:M$17,5,0) -> A | I9: flip коричневый | J9: ='Юнит 02-08.03'!R16 -> 8 | K9: =J9/J$18 -> 0.08988764 | L9: =K9+L8 -> 0.70786517 | M9: =_xlfn.IFS(L9<80%,"A",L9<=95%,"B",L9>95%,"C") -> A
B10: qs желтые | C10: ='Юнит 02-08.03'!AE6 -> 2439.4431 | D10: =C10/C$18 -> 0.086254931 | E10: =D10+E9 -> 1.0146808 | F10: =IF(AND(E10<=0),"C",IF(E10<=0.8,"A",IF(E10<=0.95,"B","C"))) -> C | G10: =VLOOKUP(B$4:B$17,I$4:M$17,5,0) -> A | I10: flip черный | J10: ='Юнит 02-08.03'!R13 -> 7 | K10: =J10/J$18 -> 0.078651685 | L10: =K10+L9 -> 0.78651685 | M10: =_xlfn.IFS(L10<80%,"A",L10<=95%,"B",L10>95%,"C") -> A
B11: flip коричневый | C11: ='Юнит 02-08.03'!AE16 -> 2155.6623 | D11: =C11/C$18 -> 0.076220883 | E11: =D11+E10 -> 1.0909017 | F11: =IF(AND(E11<=0),"C",IF(E11<=0.8,"A",IF(E11<=0.95,"B","C"))) -> C | G11: =VLOOKUP(B$4:B$17,I$4:M$17,5,0) -> A | I11: th черн | J11: ='Юнит 02-08.03'!R9 -> 5 | K11: =J11/J$18 -> 0.056179775 | L11: =K11+L10 -> 0.84269663 | M11: =_xlfn.IFS(L11<80%,"A",L11<=95%,"B",L11>95%,"C") -> B
B12: th син | C12: ='Юнит 02-08.03'!AE10 -> 1647.6334 | D12: =C12/C$18 -> 0.058257766 | E12: =D12+E5 -> 0.49922293 | F12: =IF(AND(E12<=0),"C",IF(E12<=0.8,"A",IF(E12<=0.95,"B","C"))) -> A | G12: =VLOOKUP(B$4:B$17,I$4:M$17,5,0) -> A | I12: th син | J12: ='Юнит 02-08.03'!R10 -> 5 | K12: =J12/J$18 -> 0.056179775 | L12: =K12+L5 -> 0.35955056 | M12: =_xlfn.IFS(L12<80%,"A",L12<=95%,"B",L12>95%,"C") -> A
B13: th коричн | C13: ='Юнит 02-08.03'!AE12 -> 1177.2783 | D13: =C13/C$18 -> 0.04162674 | E13: =D13+E12 -> 0.54084967 | F13: =IF(AND(E13<=0),"C",IF(E13<=0.8,"A",IF(E13<=0.95,"B","C"))) -> A | G13: =VLOOKUP(B$4:B$17,I$4:M$17,5,0) -> A | I13: th коричн | J13: ='Юнит 02-08.03'!R12 -> 4 | K13: =J13/J$18 -> 0.04494382 | L13: =K13+L12 -> 0.40449438 | M13: =_xlfn.IFS(L13<80%,"A",L13<=95%,"B",L13>95%,"C") -> A
B14: qs черные | C14: ='Юнит 02-08.03'!AE4 -> 581.43477 | D14: =C14/C$18 -> 0.020558634 | E14: =D14+E13 -> 0.5614083 | F14: =IF(AND(E14<=0),"C",IF(E14<=0.8,"A",IF(E14<=0.95,"B","C"))) -> A | G14: =VLOOKUP(B$4:B$17,I$4:M$17,5,0) -> A | I14: черные с железкой классика | J14: ='Юнит 02-08.03'!R3 -> 2 | K14: =J14/J$18 -> 0.02247191 | L14: =K14+L13 -> 0.42696629 | M14: =_xlfn.IFS(L14<80%,"A",L14<=95%,"B",L14>95%,"C") -> A
B15: qs синие | C15: ='Юнит 02-08.03'!AE5 -> 412.06158 | D15: =C15/C$18 -> 0.01456986 | E15: =D15+E14 -> 0.57597816 | F15: =IF(AND(E15<=0),"C",IF(E15<=0.8,"A",IF(E15<=0.95,"B","C"))) -> A | G15: =VLOOKUP(B$4:B$17,I$4:M$17,5,0) -> A | I15: qs черные | J15: ='Юнит 02-08.03'!R4 -> 2 | K15: =J15/J$18 -> 0.02247191 | L15: =K15+L14 -> 0.4494382 | M15: =_xlfn.IFS(L15<80%,"A",L15<=95%,"B",L15>95%,"C") -> A
B16: flip синий | C16: ='Юнит 02-08.03'!AE14 -> -916.64 | D16: =C16/C$18 -> -0.032410972 | E16: =D16+E15 -> 0.54356719 | F16: =IF(AND(E16<=0),"C",IF(E16<=0.8,"A",IF(E16<=0.95,"B","C"))) -> A | G16: =VLOOKUP(B$4:B$17,I$4:M$17,5,0) -> A | I16: qs синие | J16: ='Юнит 02-08.03'!R5 -> 1 | K16: =J16/J$18 -> 0.011235955 | L16: =K16+L15 -> 0.46067416 | M16: =_xlfn.IFS(L16<80%,"A",L16<=95%,"B",L16>95%,"C") -> A
B17: черные с железкой классика | C17: ='Юнит 02-08.03'!AE3 -> -5472.6286 | D17: =C17/C$18 -> -0.19350368 | E17: =D17+E14 -> 0.36790462 | F17: =IF(AND(E17<=0),"C",IF(E17<=0.8,"A",IF(E17<=0.95,"B","C"))) -> A | G17: =VLOOKUP(B$4:B$17,I$4:M$17,5,0) -> A | I17: flip синий | J17: ='Юнит 02-08.03'!R14 -> 0 | K17: =J17/J$18 -> 0 | L17: =K17+L14 -> 0.42696629 | M17: =_xlfn.IFS(L17<80%,"A",L17<=95%,"B",L17>95%,"C") -> A
C18: =SUM(C4:C17) -> 28281.781 | D18: =SUM(D4:D17) -> 1 | J18: =SUM(J4:J17) -> 89 | K18: =SUM(K4:K17) -> 1
C21: Прибыль | D21: % прибыль | E21: Доля | F21: ABC прибыль | G21: ABC кол-во | J21: Кол-во | K21: % кол-во | L21: Доля | M21: ABC кол-во
D22: =C22/C$42 -> #DIV/0! | E22: =D22 -> #DIV/0! | F22: =IF(AND(E22<=0),"C",IF(E22<=0.8,"A",IF(E22<=0.95,"B","C"))) -> #DIV/0! | G22: =VLOOKUP(B$22:B$42,I$22:M$42,5,0) -> #N/A | K22: =J22/J$42 -> #DIV/0! | L22: =K22 -> #DIV/0! | M22: =_xlfn.IFS(L22<80%,"A",L22<=95%,"B",L22>95%,"C") -> #DIV/0!
D23: =C23/C$42 -> #DIV/0! | E23: =D23+E22 -> #DIV/0! | F23: =IF(AND(E23<=0),"C",IF(E23<=0.8,"A",IF(E23<=0.95,"B","C"))) -> #DIV/0! | G23: =VLOOKUP(B$22:B$42,I$22:M$42,5,0) -> #N/A | K23: =J23/J$42 -> #DIV/0! | L23: =K23+L22 -> #DIV/0! | M23: =_xlfn.IFS(L23<80%,"A",L23<=95%,"B",L23>95%,"C") -> #DIV/0!
D24: =C24/C$42 -> #DIV/0! | E24: =D24+E23 -> #DIV/0! | F24: =IF(AND(E24<=0),"C",IF(E24<=0.8,"A",IF(E24<=0.95,"B","C"))) -> #DIV/0! | G24: =VLOOKUP(B$22:B$42,I$22:M$42,5,0) -> #N/A | K24: =J24/J$42 -> #DIV/0! | L24: =K24+L23 -> #DIV/0! | M24: =_xlfn.IFS(L24<80%,"A",L24<=95%,"B",L24>95%,"C") -> #DIV/0!
D25: =C25/C$42 -> #DIV/0! | E25: =D25+E24 -> #DIV/0! | F25: =IF(AND(E25<=0),"C",IF(E25<=0.8,"A",IF(E25<=0.95,"B","C"))) -> #DIV/0! | G25: =VLOOKUP(B$22:B$42,I$22:M$42,5,0) -> #N/A | K25: =J25/J$42 -> #DIV/0! | L25: =K25+L24 -> #DIV/0! | M25: =_xlfn.IFS(L25<80%,"A",L25<=95%,"B",L25>95%,"C") -> #DIV/0!
D26: =C26/C$42 -> #DIV/0! | E26: =D26+E25 -> #DIV/0! | F26: =IF(AND(E26<=0),"C",IF(E26<=0.8,"A",IF(E26<=0.95,"B","C"))) -> #DIV/0! | G26: =VLOOKUP(B$22:B$42,I$22:M$42,5,0) -> #N/A | K26: =J26/J$42 -> #DIV/0! | L26: =K26+L25 -> #DIV/0! | M26: =_xlfn.IFS(L26<80%,"A",L26<=95%,"B",L26>95%,"C") -> #DIV/0!
D27: =C27/C$42 -> #DIV/0! | E27: =D27+E26 -> #DIV/0! | F27: =IF(AND(E27<=0),"C",IF(E27<=0.8,"A",IF(E27<=0.95,"B","C"))) -> #DIV/0! | G27: =VLOOKUP(B$22:B$42,I$22:M$42,5,0) -> #N/A | K27: =J27/J$42 -> #DIV/0! | L27: =K27+L26 -> #DIV/0! | M27: =_xlfn.IFS(L27<80%,"A",L27<=95%,"B",L27>95%,"C") -> #DIV/0!
D28: =C28/C$42 -> #DIV/0! | E28: =D28+E27 -> #DIV/0! | F28: =IF(AND(E28<=0),"C",IF(E28<=0.8,"A",IF(E28<=0.95,"B","C"))) -> #DIV/0! | G28: =VLOOKUP(B$22:B$42,I$22:M$42,5,0) -> #N/A | K28: =J28/J$42 -> #DIV/0! | L28: =K28+L27 -> #DIV/0! | M28: =_xlfn.IFS(L28<80%,"A",L28<=95%,"B",L28>95%,"C") -> #DIV/0!
D29: =C29/C$42 -> #DIV/0! | E29: =D29+E28 -> #DIV/0! | F29: =IF(AND(E29<=0),"C",IF(E29<=0.8,"A",IF(E29<=0.95,"B","C"))) -> #DIV/0! | G29: =VLOOKUP(B$22:B$42,I$22:M$42,5,0) -> #N/A | K29: =J29/J$42 -> #DIV/0! | L29: =K29+L28 -> #DIV/0! | M29: =_xlfn.IFS(L29<80%,"A",L29<=95%,"B",L29>95%,"C") -> #DIV/0!
D30: =C30/C$42 -> #DIV/0! | E30: =D30+E29 -> #DIV/0! | F30: =IF(AND(E30<=0),"C",IF(E30<=0.8,"A",IF(E30<=0.95,"B","C"))) -> #DIV/0! | G30: =VLOOKUP(B$22:B$42,I$22:M$42,5,0) -> #N/A | K30: =J30/J$42 -> #DIV/0! | L30: =K30+L29 -> #DIV/0! | M30: =_xlfn.IFS(L30<80%,"A",L30<=95%,"B",L30>95%,"C") -> #DIV/0!
D31: =C31/C$42 -> #DIV/0! | E31: =D31+E30 -> #DIV/0! | F31: =IF(AND(E31<=0),"C",IF(E31<=0.8,"A",IF(E31<=0.95,"B","C"))) -> #DIV/0! | G31: =VLOOKUP(B$22:B$42,I$22:M$42,5,0) -> #N/A | K31: =J31/J$42 -> #DIV/0! | L31: =K31+L30 -> #DIV/0! | M31: =_xlfn.IFS(L31<80%,"A",L31<=95%,"B",L31>95%,"C") -> #DIV/0!
D32: =C32/C$42 -> #DIV/0! | E32: =D32+E31 -> #DIV/0! | F32: =IF(AND(E32<=0),"C",IF(E32<=0.8,"A",IF(E32<=0.95,"B","C"))) -> #DIV/0! | G32: =VLOOKUP(B$22:B$42,I$22:M$42,5,0) -> #N/A | K32: =J32/J$42 -> #DIV/0! | L32: =K32+L31 -> #DIV/0! | M32: =_xlfn.IFS(L32<80%,"A",L32<=95%,"B",L32>95%,"C") -> #DIV/0!
D33: =C33/C$42 -> #DIV/0! | E33: =D33+E32 -> #DIV/0! | F33: =IF(AND(E33<=0),"C",IF(E33<=0.8,"A",IF(E33<=0.95,"B","C"))) -> #DIV/0! | G33: =VLOOKUP(B$22:B$42,I$22:M$42,5,0) -> #N/A | K33: =J33/J$42 -> #DIV/0! | L33: =K33+L32 -> #DIV/0! | M33: =_xlfn.IFS(L33<80%,"A",L33<=95%,"B",L33>95%,"C") -> #DIV/0!
D34: =C34/C$42 -> #DIV/0! | E34: =D34+E33 -> #DIV/0! | F34: =IF(AND(E34<=0),"C",IF(E34<=0.8,"A",IF(E34<=0.95,"B","C"))) -> #DIV/0! | G34: =VLOOKUP(B$22:B$42,I$22:M$42,5,0) -> #N/A | K34: =J34/J$42 -> #DIV/0! | L34: =K34+L33 -> #DIV/0! | M34: =_xlfn.IFS(L34<80%,"A",L34<=95%,"B",L34>95%,"C") -> #DIV/0!
... D41: =C41/C$42 -> #DIV/0! | E41: =D41+E40 -> #DIV/0! | F41: =IF(AND(E41<=0),"C",IF(E41<=0.8,"A",IF(E41<=0.95,"B","C"))) -> #DIV/0! | G41: =VLOOKUP(B$22:B$42,I$22:M$42,5,0) -> #N/A | K41: =J41/J$42 -> #DIV/0! | L41: =K41+L40 -> #DIV/0! | M41: =_xlfn.IFS(L41<80%,"A",L41<=95%,"B",L41>95%,"C") -> #DIV/0!
C42: =SUM(C22:C41) -> 0 | D42: =SUM(D22:D41) -> #DIV/0! | J42: =SUM(J22:J41) -> 0 | K42: =SUM(K22:K41) -> #DIV/0!

Sheet АВС ФЕВРАЛЬ
B2: ОЧКИ
C3: Прибыль | D3: % прибыль | E3: Доля | F3: ABC прибыль | G3: ABC кол-во | J3: Кол-во | K3: % кол-во | L3: Доля | M3: ABC кол-во
B4: th желт | C4: =ФЕВРАЛЬ!AE11 -> 46604.635 | D4: =C4/C$18 -> 0.20684727 | E4: =D4 -> 0.20684727 | F4: =IF(AND(E4<=0),"C",IF(E4<=0.8,"A",IF(E4<=0.95,"B","C"))) -> A | G4: =VLOOKUP(B$4:B$17,I$4:M$17,5,0) -> A | I4: th желт | J4: =ФЕВРАЛЬ!R11 -> 105 | K4: =J4/J$18 -> 0.19125683 | L4: =K4 -> 0.19125683 | M4: =_xlfn.IFS(L4<80%,"A",L4<=95%,"B",L4>95%,"C") -> A
B5: flip жел | C5: =ФЕВРАЛЬ!AE15 -> 42795.638 | D5: =C5/C$18 -> 0.18994164 | E5: =D5+E4 -> 0.39678892 | F5: =IF(AND(E5<=0),"C",IF(E5<=0.8,"A",IF(E5<=0.95,"B","C"))) -> A | G5: =VLOOKUP(B$4:B$17,I$4:M$17,5,0) -> A | I5: flip жел | J5: =ФЕВРАЛЬ!R15 -> 91 | K5: =J5/J$18 -> 0.16575592 | L5: =K5+L4 -> 0.35701275 | M5: =_xlfn.IFS(L5<80%,"A",L5<=95%,"B",L5>95%,"C") -> A
B6: MR8854 C2 | C6: =ФЕВРАЛЬ!AE8 -> 27498.912 | D6: =C6/C$18 -> 0.12204956 | E6: =D6+E5 -> 0.51883847 | F6: =IF(AND(E6<=0),"C",IF(E6<=0.8,"A",IF(E6<=0.95,"B","C"))) -> A | G6: =VLOOKUP(B$4:B$17,I$4:M$17,5,0) -> A | I6: qs коричневые | J6: =ФЕВРАЛЬ!R7 -> 64 | K6: =J6/J$18 -> 0.11657559 | L6: =K6+L5 -> 0.47358834 | M6: =_xlfn.IFS(L6<80%,"A",L6<=95%,"B",L6>95%,"C") -> A
B7: qs коричневые | C7: =ФЕВРАЛЬ!AE7 -> 17588.26 | D7: =C7/C$18 -> 0.0780627 | E7: =D7+E6 -> 0.59690117 | F7: =IF(AND(E7<=0),"C",IF(E7<=0.8,"A",IF(E7<=0.95,"B","C"))) -> A | G7: =VLOOKUP(B$4:B$17,I$4:M$17,5,0) -> A | I7: MR8854 C2 | J7: =ФЕВРАЛЬ!R8 -> 58 | K7: =J7/J$18 -> 0.10564663 | L7: =K7+L6 -> 0.57923497 | M7: =_xlfn.IFS(L7<80%,"A",L7<=95%,"B",L7>95%,"C") -> A
B8: qs желтые | C8: =ФЕВРАЛЬ!AE6 -> 15496.897 | D8: =C8/C$18 -> 0.068780519 | E8: =D8+E7 -> 0.66568169 | F8: =IF(AND(E8<=0),"C",IF(E8<=0.8,"A",IF(E8<=0.95,"B","C"))) -> A | G8: =VLOOKUP(B$4:B$17,I$4:M$17,5,0) -> A | I8: flip черный | J8: =ФЕВРАЛЬ!R13 -> 37 | K8: =J8/J$18 -> 0.067395264 | L8: =K8+L7 -> 0.64663024 | M8: =_xlfn.IFS(L8<80%,"A",L8<=95%,"B",L8>95%,"C") -> A
B9: flip коричневый | C9: =ФЕВРАЛЬ!AE16 -> 14713.312 | D9: =C9/C$18 -> 0.0653027 | E9: =D9+E8 -> 0.73098439 | F9: =IF(AND(E9<=0),"C",IF(E9<=0.8,"A",IF(E9<=0.95,"B","C"))) -> A | G9: =VLOOKUP(B$4:B$17,I$4:M$17,5,0) -> A | I9: flip коричневый | J9: =ФЕВРАЛЬ!R16 -> 35 | K9: =J9/J$18 -> 0.063752277 | L9: =K9+L8 -> 0.71038251 | M9: =_xlfn.IFS(L9<80%,"A",L9<=95%,"B",L9>95%,"C") -> A
B10: th син | C10: =ФЕВРАЛЬ!AE10 -> 14356.309 | D10: =C10/C$18 -> 0.063718199 | E10: =D10+E9 -> 0.79470259 | F10: =IF(AND(E10<=0),"C",IF(E10<=0.8,"A",IF(E10<=0.95,"B","C"))) -> A | G10: =VLOOKUP(B$4:B$17,I$4:M$17,5,0) -> B | I10: qs желтые | J10: =ФЕВРАЛЬ!R6 -> 29 | K10: =J10/J$18 -> 0.052823315 | L10: =K10+L9 -> 0.76320583 | M10: =_xlfn.IFS(L10<80%,"A",L10<=95%,"B",L10>95%,"C") -> A
B11: flip черный | C11: =ФЕВРАЛЬ!AE13 -> 13248.471 | D11: =C11/C$18 -> 0.058801237 | E11: =D11+E10 -> 0.85350383 | F11: =IF(AND(E11<=0),"C",IF(E11<=0.8,"A",IF(E11<=0.95,"B","C"))) -> B | G11: =VLOOKUP(B$4:B$17,I$4:M$17,5,0) -> A | I11: th син | J11: =ФЕВРАЛЬ!R10 -> 28 | K11: =J11/J$18 -> 0.051001821 | L11: =K11+L10 -> 0.81420765 | M11: =_xlfn.IFS(L11<80%,"A",L11<=95%,"B",L11>95%,"C") -> B
B12: flip синий | C12: =ФЕВРАЛЬ!AE14 -> 9302.9702 | D12: =C12/C$18 -> 0.041289756 | E12: =D12+E5 -> 0.43807867 | F12: =IF(AND(E12<=0),"C",IF(E12<=0.8,"A",IF(E12<=0.95,"B","C"))) -> A | G12: =VLOOKUP(B$4:B$17,I$4:M$17,5,0) -> A | I12: th коричн | J12: =ФЕВРАЛЬ!R12 -> 24 | K12: =J12/J$18 -> 0.043715847 | L12: =K12+L5 -> 0.4007286 | M12: =_xlfn.IFS(L12<80%,"A",L12<=95%,"B",L12>95%,"C") -> A
B13: qs черные | C13: =ФЕВРАЛЬ!AE4 -> 7968.1985 | D13: =C13/C$18 -> 0.035365584 | E13: =D13+E12 -> 0.47344426 | F13: =IF(AND(E13<=0),"C",IF(E13<=0.8,"A",IF(E13<=0.95,"B","C"))) -> A | G13: =VLOOKUP(B$4:B$17,I$4:M$17,5,0) -> A | I13: flip синий | J13: =ФЕВРАЛЬ!R14 -> 22 | K13: =J13/J$18 -> 0.04007286 | L13: =K13+L12 -> 0.44080146 | M13: =_xlfn.IFS(L13<80%,"A",L13<=95%,"B",L13>95%,"C") -> A
B14: th черн | C14: =ФЕВРАЛЬ!AE9 -> 4092.0496 | D14: =C14/C$18 -> 0.018161912 | E14: =D14+E13 -> 0.49160617 | F14: =IF(AND(E14<=0),"C",IF(E14<=0.8,"A",IF(E14<=0.95,"B","C"))) -> A | G14: =VLOOKUP(B$4:B$17,I$4:M$17,5,0) -> A | I14: qs черные | J14: =ФЕВРАЛЬ!R4 -> 16 | K14: =J14/J$18 -> 0.029143898 | L14: =K14+L13 -> 0.46994536 | M14: =_xlfn.IFS(L14<80%,"A",L14<=95%,"B",L14>95%,"C") -> A
B15: черные с железкой классика | C15: =ФЕВРАЛЬ!AE3 -> 4043.5122 | D15: =C15/C$18 -> 0.017946487 | E15: =D15+E14 -> 0.50955266 | F15: =IF(AND(E15<=0),"C",IF(E15<=0.8,"A",IF(E15<=0.95,"B","C"))) -> A | G15: =VLOOKUP(B$4:B$17,I$4:M$17,5,0) -> A | I15: th черн | J15: =ФЕВРАЛЬ!R9 -> 15 | K15: =J15/J$18 -> 0.027322404 | L15: =K15+L14 -> 0.49726776 | M15: =_xlfn.IFS(L15<80%,"A",L15<=95%,"B",L15>95%,"C") -> A
B16: th коричн | C16: =ФЕВРАЛЬ!AE12 -> 4062.9028 | D16: =C16/C$18 -> 0.018032549 | E16: =D16+E15 -> 0.52758521 | F16: =IF(AND(E16<=0),"C",IF(E16<=0.8,"A",IF(E16<=0.95,"B","C"))) -> A | G16: =VLOOKUP(B$4:B$17,I$4:M$17,5,0) -> A | I16: черные с железкой классика | J16: =ФЕВРАЛЬ!R3 -> 13 | K16: =J16/J$18 -> 0.023679417 | L16: =K16+L15 -> 0.52094718 | M16: =_xlfn.IFS(L16<80%,"A",L16<=95%,"B",L16>95%,"C") -> A
B17: qs синие | C17: =ФЕВРАЛЬ!AE5 -> 3537.3311 | D17: =C17/C$18 -> 0.015699882 | E17: =D17+E14 -> 0.50730605 | F17: =IF(AND(E17<=0),"C",IF(E17<=0.8,"A",IF(E17<=0.95,"B","C"))) -> A | G17: =VLOOKUP(B$4:B$17,I$4:M$17,5,0) -> A | I17: qs синие | J17: =ФЕВРАЛЬ!R5 -> 12 | K17: =J17/J$18 -> 0.021857923 | L17: =K17+L14 -> 0.49180328 | M17: =_xlfn.IFS(L17<80%,"A",L17<=95%,"B",L17>95%,"C") -> A
C18: =SUM(C4:C17) -> 225309.4 | D18: =SUM(D4:D17) -> 1 | J18: =SUM(J4:J17) -> 549 | K18: =SUM(K4:K17) -> 1
C21: Прибыль | D21: % прибыль | E21: Доля | F21: ABC прибыль | G21: ABC кол-во | J21: Кол-во | K21: % кол-во | L21: Доля | M21: ABC кол-во
D22: =C22/C$42 -> #DIV/0! | E22: =D22 -> #DIV/0! | F22: =IF(AND(E22<=0),"C",IF(E22<=0.8,"A",IF(E22<=0.95,"B","C"))) -> #DIV/0! | G22: =VLOOKUP(B$22:B$42,I$22:M$42,5,0) -> #N/A | K22: =J22/J$42 -> #DIV/0! | L22: =K22 -> #DIV/0! | M22: =_xlfn.IFS(L22<80%,"A",L22<=95%,"B",L22>95%,"C") -> #DIV/0!
D23: =C23/C$42 -> #DIV/0! | E23: =D23+E22 -> #DIV/0! | F23: =IF(AND(E23<=0),"C",IF(E23<=0.8,"A",IF(E23<=0.95,"B","C"))) -> #DIV/0! | G23: =VLOOKUP(B$22:B$42,I$22:M$42,5,0) -> #N/A | K23: =J23/J$42 -> #DIV/0! | L23: =K23+L22 -> #DIV/0! | M23: =_xlfn.IFS(L23<80%,"A",L23<=95%,"B",L23>95%,"C") -> #DIV/0!
D24: =C24/C$42 -> #DIV/0! | E24: =D24+E23 -> #DIV/0! | F24: =IF(AND(E24<=0),"C",IF(E24<=0.8,"A",IF(E24<=0.95,"B","C"))) -> #DIV/0! | G24: =VLOOKUP(B$22:B$42,I$22:M$42,5,0) -> #N/A | K24: =J24/J$42 -> #DIV/0! | L24: =K24+L23 -> #DIV/0! | M24: =_xlfn.IFS(L24<80%,"A",L24<=95%,"B",L24>95%,"C") -> #DIV/0!
D25: =C25/C$42 -> #DIV/0! | E25: =D25+E24 -> #DIV/0! | F25: =IF(AND(E25<=0),"C",IF(E25<=0.8,"A",IF(E25<=0.95,"B","C"))) -> #DIV/0! | G25: =VLOOKUP(B$22:B$42,I$22:M$42,5,0) -> #N/A | K25: =J25/J$42 -> #DIV/0! | L25: =K25+L24 -> #DIV/0! | M25: =_xlfn.IFS(L25<80%,"A",L25<=95%,"B",L25>95%,"C") -> #DIV/0!
D26: =C26/C$42 -> #DIV/0! | E26: =D26+E25 -> #DIV/0! | F26: =IF(AND(E26<=0),"C",IF(E26<=0.8,"A",IF(E26<=0.95,"B","C"))) -> #DIV/0! | G26: =VLOOKUP(B$22:B$42,I$22:M$42,5,0) -> #N/A | K26: =J26/J$42 -> #DIV/0! | L26: =K26+L25 -> #DIV/0! | M26: =_xlfn.IFS(L26<80%,"A",L26<=95%,"B",L26>95%,"C") -> #DIV/0!
D27: =C27/C$42 -> #DIV/0! | E27: =D27+E26 -> #DIV/0! | F27: =IF(AND(E27<=0),"C",IF(E27<=0.8,"A",IF(E27<=0.95,"B","C"))) -> #DIV/0! | G27: =VLOOKUP(B$22:B$42,I$22:M$42,5,0) -> #N/A | K27: =J27/J$42 -> #DIV/0! | L27: =K27+L26 -> #DIV/0! | M27: =_xlfn.IFS(L27<80%,"A",L27<=95%,"B",L27>95%,"C") -> #DIV/0!
D28: =C28/C$42 -> #DIV/0! | E28: =D28+E27 -> #DIV/0! | F28: =IF(AND(E28<=0),"C",IF(E28<=0.8,"A",IF(E28<=0.95,"B","C"))) -> #DIV/0! | G28: =VLOOKUP(B$22:B$42,I$22:M$42,5,0) -> #N/A | K28: =J28/J$42 -> #DIV/0! | L28: =K28+L27 -> #DIV/0! | M28: =_xlfn.IFS(L28<80%,"A",L28<=95%,"B",L28>95%,"C") -> #DIV/0!
D29: =C29/C$42 -> #DIV/0! | E29: =D29+E28 -> #DIV/0! | F29: =IF(AND(E29<=0),"C",IF(E29<=0.8,"A",IF(E29<=0.95,"B","C"))) -> #DIV/0! | G29: =VLOOKUP(B$22:B$42,I$22:M$42,5,0) -> #N/A | K29: =J29/J$42 -> #DIV/0! | L29: =K29+L28 -> #DIV/0! | M29: =_xlfn.IFS(L29<80%,"A",L29<=95%,"B",L29>95%,"C") -> #DIV/0!
D30: =C30/C$42 -> #DIV/0! | E30: =D30+E29 -> #DIV/0! | F30: =IF(AND(E30<=0),"C",IF(E30<=0.8,"A",IF(E30<=0.95,"B","C"))) -> #DIV/0! | G30: =VLOOKUP(B$22:B$42,I$22:M$42,5,0) -> #N/A | K30: =J30/J$42 -> #DIV/0! | L30: =K30+L29 -> #DIV/0! | M30: =_xlfn.IFS(L30<80%,"A",L30<=95%,"B",L30>95%,"C") -> #DIV/0!
D31: =C31/C$42 -> #DIV/0! | E31: =D31+E30 -> #DIV/0! | F31: =IF(AND(E31<=0),"C",IF(E31<=0.8,"A",IF(E31<=0.95,"B","C"))) -> #DIV/0! | G31: =VLOOKUP(B$22:B$42,I$22:M$42,5,0) -> #N/A | K31: =J31/J$42 -> #DIV/0! | L31: =K31+L30 -> #DIV/0! | M31: =_xlfn.IFS(L31<80%,"A",L31<=95%,"B",L31>95%,"C") -> #DIV/0!
D32: =C32/C$42 -> #DIV/0! | E32: =D32+E31 -> #DIV/0! | F32: =IF(AND(E32<=0),"C",IF(E32<=0.8,"A",IF(E32<=0.95,"B","C"))) -> #DIV/0! | G32: =VLOOKUP(B$22:B$42,I$22:M$42,5,0) -> #N/A | K32: =J32/J$42 -> #DIV/0! | L32: =K32+L31 -> #DIV/0! | M32: =_xlfn.IFS(L32<80%,"A",L32<=95%,"B",L32>95%,"C") -> #DIV/0!
D33: =C33/C$42 -> #DIV/0! | E33: =D33+E32 -> #DIV/0! | F33: =IF(AND(E33<=0),"C",IF(E33<=0.8,"A",IF(E33<=0.95,"B","C"))) -> #DIV/0! | G33: =VLOOKUP(B$22:B$42,I$22:M$42,5,0) -> #N/A | K33: =J33/J$42 -> #DIV/0! | L33: =K33+L32 -> #DIV/0! | M33: =_xlfn.IFS(L33<80%,"A",L33<=95%,"B",L33>95%,"C") -> #DIV/0!
D34: =C34/C$42 -> #DIV/0! | E34: =D34+E33 -> #DIV/0! | F34: =IF(AND(E34<=0),"C",IF(E34<=0.8,"A",IF(E34<=0.95,"B","C"))) -> #DIV/0! | G34: =VLOOKUP(B$22:B$42,I$22:M$42,5,0) -> #N/A | K34: =J34/J$42 -> #DIV/0! | L34: =K34+L33 -> #DIV/0! | M34: =_xlfn.IFS(L34<80%,"A",L34<=95%,"B",L34>95%,"C") -> #DIV/0!
... D41: =C41/C$42 -> #DIV/0! | E41: =D41+E40 -> #DIV/0! | F41: =IF(AND(E41<=0),"C",IF(E41<=0.8,"A",IF(E41<=0.95,"B","C"))) -> #DIV/0! | G41: =VLOOKUP(B$22:B$42,I$22:M$42,5,0) -> #N/A | K41: =J41/J$42 -> #DIV/0! | L41: =K41+L40 -> #DIV/0! | M41: =_xlfn.IFS(L41<80%,"A",L41<=95%,"B",L41>95%,"C") -> #DIV/0!
C42: =SUM(C22:C41) -> 0 | D42: =SUM(D22:D41) -> #DIV/0! | J42: =SUM(J22:J41) -> 0 | K42: =SUM(K22:K41) -> #DIV/0!

Sheet АВС 23.02-01.03
B2: ОЧКИ
C3: Прибыль | D3: % прибыль | E3: Доля | F3: ABC прибыль | G3: ABC кол-во | J3: Кол-во | K3: % кол-во | L3: Доля | M3: ABC кол-во
B4: MR8854 C2 | C4: ='Юнит 23.02-01.03'!AE8 -> 10426.618 | D4: =C4/C$18 -> 0.23609764 | E4: =D4 -> 0.23609764 | F4: =IF(AND(E4<=0),"C",IF(E4<=0.8,"A",IF(E4<=0.95,"B","C"))) -> A | G4: =VLOOKUP(B$4:B$17,I$4:M$17,5,0) -> A | I4: MR8854 C2 | J4: ='Юнит 23.02-01.03'!R8 -> 17 | K4: =J4/J$18 -> 0.15044248 | L4: =K4 -> 0.15044248 | M4: =_xlfn.IFS(L4<80%,"A",L4<=95%,"B",L4>95%,"C") -> A
B5: flip жел | C5: ='Юнит 23.02-01.03'!AE15 -> 8944.4606 | D5: =C5/C$18 -> 0.20253605 | E5: =D5+E4 -> 0.43863369 | F5: =IF(AND(E5<=0),"C",IF(E5<=0.8,"A",IF(E5<=0.95,"B","C"))) -> A | G5: =VLOOKUP(B$4:B$17,I$4:M$17,5,0) -> A | I5: flip жел | J5: ='Юнит 23.02-01.03'!R15 -> 17 | K5: =J5/J$18 -> 0.15044248 | L5: =K5+L4 -> 0.30088496 | M5: =_xlfn.IFS(L5<80%,"A",L5<=95%,"B",L5>95%,"C") -> A
B6: qs коричневые | C6: ='Юнит 23.02-01.03'!AE7 -> 5980.9182 | D6: =C6/C$18 -> 0.13543036 | E6: =D6+E5 -> 0.57406405 | F6: =IF(AND(E6<=0),"C",IF(E6<=0.8,"A",IF(E6<=0.95,"B","C"))) -> A | G6: =VLOOKUP(B$4:B$17,I$4:M$17,5,0) -> A | I6: qs коричневые | J6: ='Юнит 23.02-01.03'!R7 -> 15 | K6: =J6/J$18 -> 0.13274336 | L6: =K6+L5 -> 0.43362832 | M6: =_xlfn.IFS(L6<80%,"A",L6<=95%,"B",L6>95%,"C") -> A
B7: flip черный | C7: ='Юнит 23.02-01.03'!AE13 -> 4848.254 | D7: =C7/C$18 -> 0.10978261 | E7: =D7+E6 -> 0.68384666 | F7: =IF(AND(E7<=0),"C",IF(E7<=0.8,"A",IF(E7<=0.95,"B","C"))) -> A | G7: =VLOOKUP(B$4:B$17,I$4:M$17,5,0) -> A | I7: flip черный | J7: ='Юнит 23.02-01.03'!R13 -> 12 | K7: =J7/J$18 -> 0.10619469 | L7: =K7+L6 -> 0.53982301 | M7: =_xlfn.IFS(L7<80%,"A",L7<=95%,"B",L7>95%,"C") -> A
B8: qs желтые | C8: ='Юнит 23.02-01.03'!AE6 -> 3930.4352 | D8: =C8/C$18 -> 0.088999757 | E8: =D8+E7 -> 0.77284642 | F8: =IF(AND(E8<=0),"C",IF(E8<=0.8,"A",IF(E8<=0.95,"B","C"))) -> A | G8: =VLOOKUP(B$4:B$17,I$4:M$17,5,0) -> A | I8: flip коричневый | J8: ='Юнит 23.02-01.03'!R16 -> 9 | K8: =J8/J$18 -> 0.079646018 | L8: =K8+L7 -> 0.61946903 | M8: =_xlfn.IFS(L8<80%,"A",L8<=95%,"B",L8>95%,"C") -> A
B9: черные с железкой классика | C9: ='Юнит 23.02-01.03'!AE3 -> 2967.9729 | D9: =C9/C$18 -> 0.06720601 | E9: =D9+E8 -> 0.84005243 | F9: =IF(AND(E9<=0),"C",IF(E9<=0.8,"A",IF(E9<=0.95,"B","C"))) -> B | G9: =VLOOKUP(B$4:B$17,I$4:M$17,5,0) -> A | I9: черные с железкой классика | J9: ='Юнит 23.02-01.03'!R3 -> 7 | K9: =J9/J$18 -> 0.061946903 | L9: =K9+L8 -> 0.68141593 | M9: =_xlfn.IFS(L9<80%,"A",L9<=95%,"B",L9>95%,"C") -> A
B10: th син | C10: ='Юнит 23.02-01.03'!AE10 -> 2677.8258 | D10: =C10/C$18 -> 0.060635993 | E10: =D10+E9 -> 0.90068842 | F10: =IF(AND(E10<=0),"C",IF(E10<=0.8,"A",IF(E10<=0.95,"B","C"))) -> B | G10: =VLOOKUP(B$4:B$17,I$4:M$17,5,0) -> A | I10: qs желтые | J10: ='Юнит 23.02-01.03'!R6 -> 7 | K10: =J10/J$18 -> 0.061946903 | L10: =K10+L9 -> 0.74336283 | M10: =_xlfn.IFS(L10<80%,"A",L10<=95%,"B",L10>95%,"C") -> A
B11: flip коричневый | C11: ='Юнит 23.02-01.03'!AE16 -> 2666.483 | D11: =C11/C$18 -> 0.06037915 | E11: =D11+E10 -> 0.96106757 | F11: =IF(AND(E11<=0),"C",IF(E11<=0.8,"A",IF(E11<=0.95,"B","C"))) -> C | G11: =VLOOKUP(B$4:B$17,I$4:M$17,5,0) -> A | I11: th желт | J11: ='Юнит 23.02-01.03'!R11 -> 7 | K11: =J11/J$18 -> 0.061946903 | L11: =K11+L10 -> 0.80530973 | M11: =_xlfn.IFS(L11<80%,"A",L11<=95%,"B",L11>95%,"C") -> B
B12: flip синий | C12: ='Юнит 23.02-01.03'!AE14 -> 2149.5305 | D12: =C12/C$18 -> 0.048673413 | E12: =D12+E5 -> 0.4873071 | F12: =IF(AND(E12<=0),"C",IF(E12<=0.8,"A",IF(E12<=0.95,"B","C"))) -> A | G12: =VLOOKUP(B$4:B$17,I$4:M$17,5,0) -> A | I12: qs черные | J12: ='Юнит 23.02-01.03'!R4 -> 5 | K12: =J12/J$18 -> 0.044247788 | L12: =K12+L5 -> 0.34513274 | M12: =_xlfn.IFS(L12<80%,"A",L12<=95%,"B",L12>95%,"C") -> A
B13: qs черные | C13: ='Юнит 23.02-01.03'!AE4 -> 1734.179 | D13: =C13/C$18 -> 0.039268299 | E13: =D13+E12 -> 0.5265754 | F13: =IF(AND(E13<=0),"C",IF(E13<=0.8,"A",IF(E13<=0.95,"B","C"))) -> A | G13: =VLOOKUP(B$4:B$17,I$4:M$17,5,0) -> A | I13: th коричн | J13: ='Юнит 23.02-01.03'!R12 -> 5 | K13: =J13/J$18 -> 0.044247788 | L13: =K13+L12 -> 0.38938053 | M13: =_xlfn.IFS(L13<80%,"A",L13<=95%,"B",L13>95%,"C") -> A
B14: qs синие | C14: ='Юнит 23.02-01.03'!AE5 -> 1407.3663 | D14: =C14/C$18 -> 0.031868038 | E14: =D14+E13 -> 0.55844344 | F14: =IF(AND(E14<=0),"C",IF(E14<=0.8,"A",IF(E14<=0.95,"B","C"))) -> A | G14: =VLOOKUP(B$4:B$17,I$4:M$17,5,0) -> A | I14: qs синие | J14: ='Юнит 23.02-01.03'!R5 -> 4 | K14: =J14/J$18 -> 0.03539823 | L14: =K14+L13 -> 0.42477876 | M14: =_xlfn.IFS(L14<80%,"A",L14<=95%,"B",L14>95%,"C") -> A
B15: th желт | C15: ='Юнит 23.02-01.03'!AE11 -> -963.20294 | D15: =C15/C$18 -> -0.021810518 | E15: =D15+E14 -> 0.53663292 | F15: =IF(AND(E15<=0),"C",IF(E15<=0.8,"A",IF(E15<=0.95,"B","C"))) -> A | G15: =VLOOKUP(B$4:B$17,I$4:M$17,5,0) -> B | I15: th син | J15: ='Юнит 23.02-01.03'!R10 -> 4 | K15: =J15/J$18 -> 0.03539823 | L15: =K15+L14 -> 0.46017699 | M15: =_xlfn.IFS(L15<80%,"A",L15<=95%,"B",L15>95%,"C") -> A
B16: th коричн | C16: ='Юнит 23.02-01.03'!AE12 -> -1156.2606 | D16: =C16/C$18 -> -0.026182066 | E16: =D16+E15 -> 0.51045086 | F16: =IF(AND(E16<=0),"C",IF(E16<=0.8,"A",IF(E16<=0.95,"B","C"))) -> A | G16: =VLOOKUP(B$4:B$17,I$4:M$17,5,0) -> A | I16: flip синий | J16: ='Юнит 23.02-01.03'!R14 -> 3 | K16: =J16/J$18 -> 0.026548673 | L16: =K16+L15 -> 0.48672566 | M16: =_xlfn.IFS(L16<80%,"A",L16<=95%,"B",L16>95%,"C") -> A
B17: th черн | C17: ='Юнит 23.02-01.03'!AE9 -> -1452.266 | D17: =C17/C$18 -> -0.032884736 | E17: =D17+E14 -> 0.5255587 | F17: =IF(AND(E17<=0),"C",IF(E17<=0.8,"A",IF(E17<=0.95,"B","C"))) -> A | G17: =VLOOKUP(B$4:B$17,I$4:M$17,5,0) -> A | I17: th черн | J17: ='Юнит 23.02-01.03'!R9 -> 1 | K17: =J17/J$18 -> 0.0088495575 | L17: =K17+L14 -> 0.43362832 | M17: =_xlfn.IFS(L17<80%,"A",L17<=95%,"B",L17>95%,"C") -> A
C18: =SUM(C4:C17) -> 44162.314 | D18: =SUM(D4:D17) -> 1 | J18: =SUM(J4:J17) -> 113 | K18: =SUM(K4:K17) -> 1
C21: Прибыль | D21: % прибыль | E21: Доля | F21: ABC прибыль | G21: ABC кол-во | J21: Кол-во | K21: % кол-во | L21: Доля | M21: ABC кол-во
D22: =C22/C$42 -> #DIV/0! | E22: =D22 -> #DIV/0! | F22: =IF(AND(E22<=0),"C",IF(E22<=0.8,"A",IF(E22<=0.95,"B","C"))) -> #DIV/0! | G22: =VLOOKUP(B$22:B$42,I$22:M$42,5,0) -> #N/A | K22: =J22/J$42 -> #DIV/0! | L22: =K22 -> #DIV/0! | M22: =_xlfn.IFS(L22<80%,"A",L22<=95%,"B",L22>95%,"C") -> #DIV/0!
D23: =C23/C$42 -> #DIV/0! | E23: =D23+E22 -> #DIV/0! | F23: =IF(AND(E23<=0),"C",IF(E23<=0.8,"A",IF(E23<=0.95,"B","C"))) -> #DIV/0! | G23: =VLOOKUP(B$22:B$42,I$22:M$42,5,0) -> #N/A | K23: =J23/J$42 -> #DIV/0! | L23: =K23+L22 -> #DIV/0! | M23: =_xlfn.IFS(L23<80%,"A",L23<=95%,"B",L23>95%,"C") -> #DIV/0!
D24: =C24/C$42 -> #DIV/0! | E24: =D24+E23 -> #DIV/0! | F24: =IF(AND(E24<=0),"C",IF(E24<=0.8,"A",IF(E24<=0.95,"B","C"))) -> #DIV/0! | G24: =VLOOKUP(B$22:B$42,I$22:M$42,5,0) -> #N/A | K24: =J24/J$42 -> #DIV/0! | L24: =K24+L23 -> #DIV/0! | M24: =_xlfn.IFS(L24<80%,"A",L24<=95%,"B",L24>95%,"C") -> #DIV/0!
D25: =C25/C$42 -> #DIV/0! | E25: =D25+E24 -> #DIV/0! | F25: =IF(AND(E25<=0),"C",IF(E25<=0.8,"A",IF(E25<=0.95,"B","C"))) -> #DIV/0! | G25: =VLOOKUP(B$22:B$42,I$22:M$42,5,0) -> #N/A | K25: =J25/J$42 -> #DIV/0! | L25: =K25+L24 -> #DIV/0! | M25: =_xlfn.IFS(L25<80%,"A",L25<=95%,"B",L25>95%,"C") -> #DIV/0!
D26: =C26/C$42 -> #DIV/0! | E26: =D26+E25 -> #DIV/0! | F26: =IF(AND(E26<=0),"C",IF(E26<=0.8,"A",IF(E26<=0.95,"B","C"))) -> #DIV/0! | G26: =VLOOKUP(B$22:B$42,I$22:M$42,5,0) -> #N/A | K26: =J26/J$42 -> #DIV/0! | L26: =K26+L25 -> #DIV/0! | M26: =_xlfn.IFS(L26<80%,"A",L26<=95%,"B",L26>95%,"C") -> #DIV/0!
D27: =C27/C$42 -> #DIV/0! | E27: =D27+E26 -> #DIV/0! | F27: =IF(AND(E27<=0),"C",IF(E27<=0.8,"A",IF(E27<=0.95,"B","C"))) -> #DIV/0! | G27: =VLOOKUP(B$22:B$42,I$22:M$42,5,0) -> #N/A | K27: =J27/J$42 -> #DIV/0! | L27: =K27+L26 -> #DIV/0! | M27: =_xlfn.IFS(L27<80%,"A",L27<=95%,"B",L27>95%,"C") -> #DIV/0!
D28: =C28/C$42 -> #DIV/0! | E28: =D28+E27 -> #DIV/0! | F28: =IF(AND(E28<=0),"C",IF(E28<=0.8,"A",IF(E28<=0.95,"B","C"))) -> #DIV/0! | G28: =VLOOKUP(B$22:B$42,I$22:M$42,5,0) -> #N/A | K28: =J28/J$42 -> #DIV/0! | L28: =K28+L27 -> #DIV/0! | M28: =_xlfn.IFS(L28<80%,"A",L28<=95%,"B",L28>95%,"C") -> #DIV/0!
D29: =C29/C$42 -> #DIV/0! | E29: =D29+E28 -> #DIV/0! | F29: =IF(AND(E29<=0),"C",IF(E29<=0.8,"A",IF(E29<=0.95,"B","C"))) -> #DIV/0! | G29: =VLOOKUP(B$22:B$42,I$22:M$42,5,0) -> #N/A | K29: =J29/J$42 -> #DIV/0! | L29: =K29+L28 -> #DIV/0! | M29: =_xlfn.IFS(L29<80%,"A",L29<=95%,"B",L29>95%,"C") -> #DIV/0!
D30: =C30/C$42 -> #DIV/0! | E30: =D30+E29 -> #DIV/0! | F30: =IF(AND(E30<=0),"C",IF(E30<=0.8,"A",IF(E30<=0.95,"B","C"))) -> #DIV/0! | G30: =VLOOKUP(B$22:B$42,I$22:M$42,5,0) -> #N/A | K30: =J30/J$42 -> #DIV/0! | L30: =K30+L29 -> #DIV/0! | M30: =_xlfn.IFS(L30<80%,"A",L30<=95%,"B",L30>95%,"C") -> #DIV/0!
D31: =C31/C$42 -> #DIV/0! | E31: =D31+E30 -> #DIV/0! | F31: =IF(AND(E31<=0),"C",IF(E31<=0.8,"A",IF(E31<=0.95,"B","C"))) -> #DIV/0! | G31: =VLOOKUP(B$22:B$42,I$22:M$42,5,0) -> #N/A | K31: =J31/J$42 -> #DIV/0! | L31: =K31+L30 -> #DIV/0! | M31: =_xlfn.IFS(L31<80%,"A",L31<=95%,"B",L31>95%,"C") -> #DIV/0!
D32: =C32/C$42 -> #DIV/0! | E32: =D32+E31 -> #DIV/0! | F32: =IF(AND(E32<=0),"C",IF(E32<=0.8,"A",IF(E32<=0.95,"B","C"))) -> #DIV/0! | G32: =VLOOKUP(B$22:B$42,I$22:M$42,5,0) -> #N/A | K32: =J32/J$42 -> #DIV/0! | L32: =K32+L31 -> #DIV/0! | M32: =_xlfn.IFS(L32<80%,"A",L32<=95%,"B",L32>95%,"C") -> #DIV/0!
D33: =C33/C$42 -> #DIV/0! | E33: =D33+E32 -> #DIV/0! | F33: =IF(AND(E33<=0),"C",IF(E33<=0.8,"A",IF(E33<=0.95,"B","C"))) -> #DIV/0! | G33: =VLOOKUP(B$22:B$42,I$22:M$42,5,0) -> #N/A | K33: =J33/J$42 -> #DIV/0! | L33: =K33+L32 -> #DIV/0! | M33: =_xlfn.IFS(L33<80%,"A",L33<=95%,"B",L33>95%,"C") -> #DIV/0!
D34: =C34/C$42 -> #DIV/0! | E34: =D34+E33 -> #DIV/0! | F34: =IF(AND(E34<=0),"C",IF(E34<=0.8,"A",IF(E34<=0.95,"B","C"))) -> #DIV/0! | G34: =VLOOKUP(B$22:B$42,I$22:M$42,5,0) -> #N/A | K34: =J34/J$42 -> #DIV/0! | L34: =K34+L33 -> #DIV/0! | M34: =_xlfn.IFS(L34<80%,"A",L34<=95%,"B",L34>95%,"C") -> #DIV/0!
... D41: =C41/C$42 -> #DIV/0! | E41: =D41+E40 -> #DIV/0! | F41: =IF(AND(E41<=0),"C",IF(E41<=0.8,"A",IF(E41<=0.95,"B","C"))) -> #DIV/0! | G41: =VLOOKUP(B$22:B$42,I$22:M$42,5,0) -> #N/A | K41: =J41/J$42 -> #DIV/0! | L41: =K41+L40 -> #DIV/0! | M41: =_xlfn.IFS(L41<80%,"A",L41<=95%,"B",L41>95%,"C") -> #DIV/0!
C42: =SUM(C22:C41) -> 0 | D42: =SUM(D22:D41) -> #DIV/0! | J42: =SUM(J22:J41) -> 0 | K42: =SUM(K22:K41) -> #DIV/0!

Sheet АВС 16-22.02
B2: ОЧКИ
C3: Прибыль | D3: % прибыль | E3: Доля | F3: ABC прибыль | G3: ABC кол-во | J3: Кол-во | K3: % кол-во | L3: Доля | M3: ABC кол-во
B4: th желт | C4: ='Юнит 16-22.02'!AE11 -> 15588.532 | D4: =C4/C$18 -> 0.22056305 | E4: =D4 -> 0.22056305 | F4: =IF(AND(E4<=0),"C",IF(E4<=0.8,"A",IF(E4<=0.95,"B","C"))) -> A | G4: =VLOOKUP(B$4:B$17,I$4:M$17,5,0) -> A | I4: th желт | J4: ='Юнит 16-22.02'!R11 -> 26 | K4: =J4/J$18 -> 0.16993464 | L4: =K4 -> 0.16993464 | M4: =_xlfn.IFS(L4<80%,"A",L4<=95%,"B",L4>95%,"C") -> A
B5: qs коричневые | C5: ='Юнит 16-22.02'!AE7 -> 13263.624 | D5: =C5/C$18 -> 0.1876678 | E5: =D5+E4 -> 0.40823084 | F5: =IF(AND(E5<=0),"C",IF(E5<=0.8,"A",IF(E5<=0.95,"B","C"))) -> A | G5: =VLOOKUP(B$4:B$17,I$4:M$17,5,0) -> A | I5: qs коричневые | J5: ='Юнит 16-22.02'!R7 -> 25 | K5: =J5/J$18 -> 0.16339869 | L5: =K5+L4 -> 0.33333333 | M5: =_xlfn.IFS(L5<80%,"A",L5<=95%,"B",L5>95%,"C") -> A
B6: flip жел | C6: ='Юнит 16-22.02'!AE15 -> 8708.6634 | D6: =C6/C$18 -> 0.12321939 | E6: =D6+E5 -> 0.53145023 | F6: =IF(AND(E6<=0),"C",IF(E6<=0.8,"A",IF(E6<=0.95,"B","C"))) -> A | G6: =VLOOKUP(B$4:B$17,I$4:M$17,5,0) -> A | I6: flip жел | J6: ='Юнит 16-22.02'!R15 -> 17 | K6: =J6/J$18 -> 0.11111111 | L6: =K6+L5 -> 0.44444444 | M6: =_xlfn.IFS(L6<80%,"A",L6<=95%,"B",L6>95%,"C") -> A
B7: MR8854 C2 | C7: ='Юнит 16-22.02'!AE8 -> 6302.1753 | D7: =C7/C$18 -> 0.089169849 | E7: =D7+E6 -> 0.62062008 | F7: =IF(AND(E7<=0),"C",IF(E7<=0.8,"A",IF(E7<=0.95,"B","C"))) -> A | G7: =VLOOKUP(B$4:B$17,I$4:M$17,5,0) -> A | I7: flip черный | J7: ='Юнит 16-22.02'!R13 -> 14 | K7: =J7/J$18 -> 0.091503268 | L7: =K7+L6 -> 0.53594771 | M7: =_xlfn.IFS(L7<80%,"A",L7<=95%,"B",L7>95%,"C") -> A
B8: th син | C8: ='Юнит 16-22.02'!AE10 -> 5579.1551 | D8: =C8/C$18 -> 0.078939794 | E8: =D8+E7 -> 0.69955988 | F8: =IF(AND(E8<=0),"C",IF(E8<=0.8,"A",IF(E8<=0.95,"B","C"))) -> A | G8: =VLOOKUP(B$4:B$17,I$4:M$17,5,0) -> A | I8: MR8854 C2 | J8: ='Юнит 16-22.02'!R8 -> 12 | K8: =J8/J$18 -> 0.078431373 | L8: =K8+L7 -> 0.61437908 | M8: =_xlfn.IFS(L8<80%,"A",L8<=95%,"B",L8>95%,"C") -> A
B9: flip коричневый | C9: ='Юнит 16-22.02'!AE16 -> 4582.0618 | D9: =C9/C$18 -> 0.064831861 | E9: =D9+E8 -> 0.76439174 | F9: =IF(AND(E9<=0),"C",IF(E9<=0.8,"A",IF(E9<=0.95,"B","C"))) -> A | G9: =VLOOKUP(B$4:B$17,I$4:M$17,5,0) -> A | I9: th син | J9: ='Юнит 16-22.02'!R10 -> 10 | K9: =J9/J$18 -> 0.065359477 | L9: =K9+L8 -> 0.67973856 | M9: =_xlfn.IFS(L9<80%,"A",L9<=95%,"B",L9>95%,"C") -> A
B10: flip синий | C10: ='Юнит 16-22.02'!AE14 -> 3933.2357 | D10: =C10/C$18 -> 0.055651583 | E10: =D10+E9 -> 0.82004332 | F10: =IF(AND(E10<=0),"C",IF(E10<=0.8,"A",IF(E10<=0.95,"B","C"))) -> B | G10: =VLOOKUP(B$4:B$17,I$4:M$17,5,0) -> A | I10: flip коричневый | J10: ='Юнит 16-22.02'!R16 -> 10 | K10: =J10/J$18 -> 0.065359477 | L10: =K10+L9 -> 0.74509804 | M10: =_xlfn.IFS(L10<80%,"A",L10<=95%,"B",L10>95%,"C") -> A
B11: flip черный | C11: ='Юнит 16-22.02'!AE13 -> 3142.7759 | D11: =C11/C$18 -> 0.044467321 | E11: =D11+E10 -> 0.86451064 | F11: =IF(AND(E11<=0),"C",IF(E11<=0.8,"A",IF(E11<=0.95,"B","C"))) -> B | G11: =VLOOKUP(B$4:B$17,I$4:M$17,5,0) -> A | I11: qs желтые | J11: ='Юнит 16-22.02'!R6 -> 8 | K11: =J11/J$18 -> 0.052287582 | L11: =K11+L10 -> 0.79738562 | M11: =_xlfn.IFS(L11<80%,"A",L11<=95%,"B",L11>95%,"C") -> A
B12: qs желтые | C12: ='Юнит 16-22.02'!AE6 -> 3000.4661 | D12: =C12/C$18 -> 0.042453772 | E12: =D12+E5 -> 0.45068462 | F12: =IF(AND(E12<=0),"C",IF(E12<=0.8,"A",IF(E12<=0.95,"B","C"))) -> A | G12: =VLOOKUP(B$4:B$17,I$4:M$17,5,0) -> A | I12: th коричн | J12: ='Юнит 16-22.02'!R12 -> 7 | K12: =J12/J$18 -> 0.045751634 | L12: =K12+L5 -> 0.37908497 | M12: =_xlfn.IFS(L12<80%,"A",L12<=95%,"B",L12>95%,"C") -> A
B13: th черн | C13: ='Юнит 16-22.02'!AE9 -> 2666.4773 | D13: =C13/C$18 -> 0.037728144 | E13: =D13+E12 -> 0.48841276 | F13: =IF(AND(E13<=0),"C",IF(E13<=0.8,"A",IF(E13<=0.95,"B","C"))) -> A | G13: =VLOOKUP(B$4:B$17,I$4:M$17,5,0) -> A | I13: flip синий | J13: ='Юнит 16-22.02'!R14 -> 7 | K13: =J13/J$18 -> 0.045751634 | L13: =K13+L12 -> 0.4248366 | M13: =_xlfn.IFS(L13<80%,"A",L13<=95%,"B",L13>95%,"C") -> A
B14: qs черные | C14: ='Юнит 16-22.02'!AE4 -> 1779.7586 | D14: =C14/C$18 -> 0.025181909 | E14: =D14+E13 -> 0.51359467 | F14: =IF(AND(E14<=0),"C",IF(E14<=0.8,"A",IF(E14<=0.95,"B","C"))) -> A | G14: =VLOOKUP(B$4:B$17,I$4:M$17,5,0) -> A | I14: th черн | J14: ='Юнит 16-22.02'!R9 -> 6 | K14: =J14/J$18 -> 0.039215686 | L14: =K14+L13 -> 0.46405229 | M14: =_xlfn.IFS(L14<80%,"A",L14<=95%,"B",L14>95%,"C") -> A
B15: th коричн | C15: ='Юнит 16-22.02'!AE12 -> 1475.1304 | D15: =C15/C$18 -> 0.020871707 | E15: =D15+E14 -> 0.53446638 | F15: =IF(AND(E15<=0),"C",IF(E15<=0.8,"A",IF(E15<=0.95,"B","C"))) -> A | G15: =VLOOKUP(B$4:B$17,I$4:M$17,5,0) -> A | I15: qs черные | J15: ='Юнит 16-22.02'!R4 -> 5 | K15: =J15/J$18 -> 0.032679739 | L15: =K15+L14 -> 0.49673203 | M15: =_xlfn.IFS(L15<80%,"A",L15<=95%,"B",L15>95%,"C") -> A
B16: qs синие | C16: ='Юнит 16-22.02'!AE5 -> 553.58181 | D16: =C16/C$18 -> 0.0078326616 | E16: =D16+E15 -> 0.54229904 | F16: =IF(AND(E16<=0),"C",IF(E16<=0.8,"A",IF(E16<=0.95,"B","C"))) -> A | G16: =VLOOKUP(B$4:B$17,I$4:M$17,5,0) -> A | I16: черные с железкой классика | J16: ='Юнит 16-22.02'!R3 -> 3 | K16: =J16/J$18 -> 0.019607843 | L16: =K16+L15 -> 0.51633987 | M16: =_xlfn.IFS(L16<80%,"A",L16<=95%,"B",L16>95%,"C") -> A
B17: черные с железкой классика | C17: ='Юнит 16-22.02'!AE3 -> 100.44239 | D17: =C17/C$18 -> 0.0014211653 | E17: =D17+E14 -> 0.51501583 | F17: =IF(AND(E17<=0),"C",IF(E17<=0.8,"A",IF(E17<=0.95,"B","C"))) -> A | G17: =VLOOKUP(B$4:B$17,I$4:M$17,5,0) -> A | I17: qs синие | J17: ='Юнит 16-22.02'!R5 -> 3 | K17: =J17/J$18 -> 0.019607843 | L17: =K17+L14 -> 0.48366013 | M17: =_xlfn.IFS(L17<80%,"A",L17<=95%,"B",L17>95%,"C") -> A
C18: =SUM(C4:C17) -> 70676.079 | D18: =SUM(D4:D17) -> 1 | J18: =SUM(J4:J17) -> 153 | K18: =SUM(K4:K17) -> 1
C21: Прибыль | D21: % прибыль | E21: Доля | F21: ABC прибыль | G21: ABC кол-во | J21: Кол-во | K21: % кол-во | L21: Доля | M21: ABC кол-во
D22: =C22/C$42 -> #DIV/0! | E22: =D22 -> #DIV/0! | F22: =IF(AND(E22<=0),"C",IF(E22<=0.8,"A",IF(E22<=0.95,"B","C"))) -> #DIV/0! | G22: =VLOOKUP(B$22:B$42,I$22:M$42,5,0) -> #N/A | K22: =J22/J$42 -> #DIV/0! | L22: =K22 -> #DIV/0! | M22: =_xlfn.IFS(L22<80%,"A",L22<=95%,"B",L22>95%,"C") -> #DIV/0!
D23: =C23/C$42 -> #DIV/0! | E23: =D23+E22 -> #DIV/0! | F23: =IF(AND(E23<=0),"C",IF(E23<=0.8,"A",IF(E23<=0.95,"B","C"))) -> #DIV/0! | G23: =VLOOKUP(B$22:B$42,I$22:M$42,5,0) -> #N/A | K23: =J23/J$42 -> #DIV/0! | L23: =K23+L22 -> #DIV/0! | M23: =_xlfn.IFS(L23<80%,"A",L23<=95%,"B",L23>95%,"C") -> #DIV/0!
D24: =C24/C$42 -> #DIV/0! | E24: =D24+E23 -> #DIV/0! | F24: =IF(AND(E24<=0),"C",IF(E24<=0.8,"A",IF(E24<=0.95,"B","C"))) -> #DIV/0! | G24: =VLOOKUP(B$22:B$42,I$22:M$42,5,0) -> #N/A | K24: =J24/J$42 -> #DIV/0! | L24: =K24+L23 -> #DIV/0! | M24: =_xlfn.IFS(L24<80%,"A",L24<=95%,"B",L24>95%,"C") -> #DIV/0!
D25: =C25/C$42 -> #DIV/0! | E25: =D25+E24 -> #DIV/0! | F25: =IF(AND(E25<=0),"C",IF(E25<=0.8,"A",IF(E25<=0.95,"B","C"))) -> #DIV/0! | G25: =VLOOKUP(B$22:B$42,I$22:M$42,5,0) -> #N/A | K25: =J25/J$42 -> #DIV/0! | L25: =K25+L24 -> #DIV/0! | M25: =_xlfn.IFS(L25<80%,"A",L25<=95%,"B",L25>95%,"C") -> #DIV/0!
D26: =C26/C$42 -> #DIV/0! | E26: =D26+E25 -> #DIV/0! | F26: =IF(AND(E26<=0),"C",IF(E26<=0.8,"A",IF(E26<=0.95,"B","C"))) -> #DIV/0! | G26: =VLOOKUP(B$22:B$42,I$22:M$42,5,0) -> #N/A | K26: =J26/J$42 -> #DIV/0! | L26: =K26+L25 -> #DIV/0! | M26: =_xlfn.IFS(L26<80%,"A",L26<=95%,"B",L26>95%,"C") -> #DIV/0!
D27: =C27/C$42 -> #DIV/0! | E27: =D27+E26 -> #DIV/0! | F27: =IF(AND(E27<=0),"C",IF(E27<=0.8,"A",IF(E27<=0.95,"B","C"))) -> #DIV/0! | G27: =VLOOKUP(B$22:B$42,I$22:M$42,5,0) -> #N/A | K27: =J27/J$42 -> #DIV/0! | L27: =K27+L26 -> #DIV/0! | M27: =_xlfn.IFS(L27<80%,"A",L27<=95%,"B",L27>95%,"C") -> #DIV/0!
D28: =C28/C$42 -> #DIV/0! | E28: =D28+E27 -> #DIV/0! | F28: =IF(AND(E28<=0),"C",IF(E28<=0.8,"A",IF(E28<=0.95,"B","C"))) -> #DIV/0! | G28: =VLOOKUP(B$22:B$42,I$22:M$42,5,0) -> #N/A | K28: =J28/J$42 -> #DIV/0! | L28: =K28+L27 -> #DIV/0! | M28: =_xlfn.IFS(L28<80%,"A",L28<=95%,"B",L28>95%,"C") -> #DIV/0!
D29: =C29/C$42 -> #DIV/0! | E29: =D29+E28 -> #DIV/0! | F29: =IF(AND(E29<=0),"C",IF(E29<=0.8,"A",IF(E29<=0.95,"B","C"))) -> #DIV/0! | G29: =VLOOKUP(B$22:B$42,I$22:M$42,5,0) -> #N/A | K29: =J29/J$42 -> #DIV/0! | L29: =K29+L28 -> #DIV/0! | M29: =_xlfn.IFS(L29<80%,"A",L29<=95%,"B",L29>95%,"C") -> #DIV/0!
D30: =C30/C$42 -> #DIV/0! | E30: =D30+E29 -> #DIV/0! | F30: =IF(AND(E30<=0),"C",IF(E30<=0.8,"A",IF(E30<=0.95,"B","C"))) -> #DIV/0! | G30: =VLOOKUP(B$22:B$42,I$22:M$42,5,0) -> #N/A | K30: =J30/J$42 -> #DIV/0! | L30: =K30+L29 -> #DIV/0! | M30: =_xlfn.IFS(L30<80%,"A",L30<=95%,"B",L30>95%,"C") -> #DIV/0!
D31: =C31/C$42 -> #DIV/0! | E31: =D31+E30 -> #DIV/0! | F31: =IF(AND(E31<=0),"C",IF(E31<=0.8,"A",IF(E31<=0.95,"B","C"))) -> #DIV/0! | G31: =VLOOKUP(B$22:B$42,I$22:M$42,5,0) -> #N/A | K31: =J31/J$42 -> #DIV/0! | L31: =K31+L30 -> #DIV/0! | M31: =_xlfn.IFS(L31<80%,"A",L31<=95%,"B",L31>95%,"C") -> #DIV/0!
D32: =C32/C$42 -> #DIV/0! | E32: =D32+E31 -> #DIV/0! | F32: =IF(AND(E32<=0),"C",IF(E32<=0.8,"A",IF(E32<=0.95,"B","C"))) -> #DIV/0! | G32: =VLOOKUP(B$22:B$42,I$22:M$42,5,0) -> #N/A | K32: =J32/J$42 -> #DIV/0! | L32: =K32+L31 -> #DIV/0! | M32: =_xlfn.IFS(L32<80%,"A",L32<=95%,"B",L32>95%,"C") -> #DIV/0!
D33: =C33/C$42 -> #DIV/0! | E33: =D33+E32 -> #DIV/0! | F33: =IF(AND(E33<=0),"C",IF(E33<=0.8,"A",IF(E33<=0.95,"B","C"))) -> #DIV/0! | G33: =VLOOKUP(B$22:B$42,I$22:M$42,5,0) -> #N/A | K33: =J33/J$42 -> #DIV/0! | L33: =K33+L32 -> #DIV/0! | M33: =_xlfn.IFS(L33<80%,"A",L33<=95%,"B",L33>95%,"C") -> #DIV/0!
D34: =C34/C$42 -> #DIV/0! | E34: =D34+E33 -> #DIV/0! | F34: =IF(AND(E34<=0),"C",IF(E34<=0.8,"A",IF(E34<=0.95,"B","C"))) -> #DIV/0! | G34: =VLOOKUP(B$22:B$42,I$22:M$42,5,0) -> #N/A | K34: =J34/J$42 -> #DIV/0! | L34: =K34+L33 -> #DIV/0! | M34: =_xlfn.IFS(L34<80%,"A",L34<=95%,"B",L34>95%,"C") -> #DIV/0!
... D41: =C41/C$42 -> #DIV/0! | E41: =D41+E40 -> #DIV/0! | F41: =IF(AND(E41<=0),"C",IF(E41<=0.8,"A",IF(E41<=0.95,"B","C"))) -> #DIV/0! | G41: =VLOOKUP(B$22:B$42,I$22:M$42,5,0) -> #N/A | K41: =J41/J$42 -> #DIV/0! | L41: =K41+L40 -> #DIV/0! | M41: =_xlfn.IFS(L41<80%,"A",L41<=95%,"B",L41>95%,"C") -> #DIV/0!
C42: =SUM(C22:C41) -> 0 | D42: =SUM(D22:D41) -> #DIV/0! | J42: =SUM(J22:J41) -> 0 | K42: =SUM(K22:K41) -> #DIV/0!

Sheet АВС 09-15.02
B2: ОЧКИ
C3: Прибыль | D3: % прибыль | E3: Доля | F3: ABC прибыль | G3: ABC кол-во | J3: Кол-во | K3: % кол-во | L3: Доля | M3: ABC кол-во
B4: черные с железкой классика | D4: =C4/C$18 -> #DIV/0! | E4: =D4 -> #DIV/0! | F4: =IF(AND(E4<=0),"C",IF(E4<=0.8,"A",IF(E4<=0.95,"B","C"))) -> #DIV/0! | G4: =VLOOKUP(B$4:B$17,I$4:M$17,5,0) -> #DIV/0! | I4: черные с железкой классика | K4: =J4/J$18 -> #DIV/0! | L4: =K4 -> #DIV/0! | M4: =_xlfn.IFS(L4<80%,"A",L4<=95%,"B",L4>95%,"C") -> #DIV/0!
B5: qs черные | D5: =C5/C$18 -> #DIV/0! | E5: =D5+E4 -> #DIV/0! | F5: =IF(AND(E5<=0),"C",IF(E5<=0.8,"A",IF(E5<=0.95,"B","C"))) -> #DIV/0! | G5: =VLOOKUP(B$4:B$17,I$4:M$17,5,0) -> #DIV/0! | I5: qs черные | K5: =J5/J$18 -> #DIV/0! | L5: =K5+L4 -> #DIV/0! | M5: =_xlfn.IFS(L5<80%,"A",L5<=95%,"B",L5>95%,"C") -> #DIV/0!
B6: qs синие | D6: =C6/C$18 -> #DIV/0! | E6: =D6+E5 -> #DIV/0! | F6: =IF(AND(E6<=0),"C",IF(E6<=0.8,"A",IF(E6<=0.95,"B","C"))) -> #DIV/0! | G6: =VLOOKUP(B$4:B$17,I$4:M$17,5,0) -> #DIV/0! | I6: qs синие | K6: =J6/J$18 -> #DIV/0! | L6: =K6+L5 -> #DIV/0! | M6: =_xlfn.IFS(L6<80%,"A",L6<=95%,"B",L6>95%,"C") -> #DIV/0!
B7: qs желтые | D7: =C7/C$18 -> #DIV/0! | E7: =D7+E6 -> #DIV/0! | F7: =IF(AND(E7<=0),"C",IF(E7<=0.8,"A",IF(E7<=0.95,"B","C"))) -> #DIV/0! | G7: =VLOOKUP(B$4:B$17,I$4:M$17,5,0) -> #DIV/0! | I7: qs желтые | K7: =J7/J$18 -> #DIV/0! | L7: =K7+L6 -> #DIV/0! | M7: =_xlfn.IFS(L7<80%,"A",L7<=95%,"B",L7>95%,"C") -> #DIV/0!
B8: qs коричневые | D8: =C8/C$18 -> #DIV/0! | E8: =D8+E7 -> #DIV/0! | F8: =IF(AND(E8<=0),"C",IF(E8<=0.8,"A",IF(E8<=0.95,"B","C"))) -> #DIV/0! | G8: =VLOOKUP(B$4:B$17,I$4:M$17,5,0) -> #DIV/0! | I8: qs коричневые | K8: =J8/J$18 -> #DIV/0! | L8: =K8+L7 -> #DIV/0! | M8: =_xlfn.IFS(L8<80%,"A",L8<=95%,"B",L8>95%,"C") -> #DIV/0!
