Workbook

Sheet Налоги
B2: Месяц | C2: Отчет о реализации 5+6-13-14 | D2: Отчет о компенсации | E2: Отчет о выкупленных товарах/Выплаты | F2: Итого | G2: УСН 1%
B3: январь | C3: 337112.53 | D3: 1115.39 | E3: =5135.4+4830.84 -> 9966.24 | F3: =C3+D3+E3 -> 348194.16 | G3: =F3*1% -> 3481.9416

Sheet Сводная
A1: Период | D1: Итого к перечислению на счет, руб | E1: шт. | H1: Выручка | K1: Себестоимость продаж | L1: Логистика | M1: Комиссия | N1: Хранение | O1: Платная приемка | P1: Штрафы | Q1: Реклама Ozon | R1: Услуги агентов | S1: Другие услуги и штрафы | T1: Услуги FBO | U1: Компенсировано | V1: Пополнение рекламного кабинета | W1: ЕАЭС | X1: Налог | Y1: Прибыль до вычета налогов | Z1: Прибыль после вычета налогов | AA1: Итог месяц | AB1: % Cебестоимости | AC1: Маржинальность, % | AD1: Рентабельность, % | AE1: Доля рекламы, %
A2: Месяц | B2: Даты | C2: Нед | E2: Заказы | F2: Продажи | G2: Возвраты | H2: Продажи | I2: Возвраты | J2: Общая
A3: Январь | B3: 01-04.01 | C3: 1 | D3: =J3-SUM(L3:T3)+U3+V3 -> 1074.71 | E3: ='Юнит 01-04.01'!K$24 -> 122 | F3: ='Юнит 01-04.01'!P$24 -> 51 | G3: ='Юнит 01-04.01'!Q$24 -> 1 | H3: ='Юнит 01-04.01'!S$24 -> 85937 | I3: ='Юнит 01-04.01'!T$24 -> -1600 | J3: =H3+I3 -> 84337 | K3: ='Юнит 01-04.01'!W$24 -> 6252.96 | L3: ='Юнит 01-04.01'!Z$24 -> 8548.62 | M3: ='Юнит 01-04.01'!X$24 -> 36264.91 | Q3: ='Юнит 01-04.01'!AA$24 -> 36772.95 | R3: 1675.81 | W3: 5252 | X3: =3481.9416*J3/SUM($J$3:$J$7) -> 322.35231 | Y3: =J3-SUM(L3:T3)-K3-V3+U3+W3 -> 73.75 | Z3: =Y3-X3 -> -248.60231 | AA3: =SUM(Z3:Z7) -> 49559.258 | AB3: =K3/J3 -> 0.074142547 | AC3: =Z3/K3 -> -0.039757541 | AD3: =Z3/J3 -> -0.0029477253 | AE3: =Q3/J3 -> 0.43602393
B4: 05-11.01 | C4: 2 | D4: =J4-SUM(L4:T4)+U4+V4 -> 57707.57 | E4: ='Юнит 05-11.01'!K$24 -> 183 | F4: ='Юнит 05-11.01'!P$24 -> 168 | G4: ='Юнит 05-11.01'!Q$24 -> 8 | H4: ='Юнит 05-11.01'!S$24 -> 277715 | I4: ='Юнит 05-11.01'!T$24 -> -13822 | J4: =H4+I4 -> 263893 | K4: ='Юнит 05-11.01'!W$24 -> 20205.96 | L4: ='Юнит 05-11.01'!Z$24 -> 28076.33 | M4: ='Юнит 05-11.01'!X$24 -> 113473.99 | Q4: ='Юнит 05-11.01'!AA$24 -> 56365.38 | R4: 4144.33 | S4: 75 | T4: 4050.4 | X4: =3481.9416*J4/SUM($J$3:$J$7) -> 1008.65 | Y4: =J4-SUM(L4:T4)-K4-V4+U4+W4 -> 37501.61 | Z4: =Y4-X4 -> 36492.96 | AB4: =K4/J4 -> 0.076568761 | AC4: =Z4/K4 -> 1.8060493 | AD4: =Z4/J4 -> 0.13828696 | AE4: =Q4/J4 -> 0.2135918
B5: 12-18.01 | C5: 3 | D5: =J5-SUM(L5:T5)+U5+V5 -> 36064.15 | E5: ='Юнит 12-18.01'!K$24 -> 144 | F5: ='Юнит 12-18.01'!P$24 -> 122 | G5: ='Юнит 12-18.01'!Q$24 -> 2 | H5: ='Юнит 12-18.01'!S$24 -> 211029 | I5: ='Юнит 12-18.01'!T$24 -> -3221 | J5: =H5+I5 -> 207808 | K5: ='Юнит 12-18.01'!W$24 -> 15093.09 | L5: ='Юнит 12-18.01'!Z$24 -> 24172.28 | M5: ='Юнит 12-18.01'!X$24 -> 89357.44 | Q5: ='Юнит 12-18.01'!AA$24 -> 53249.12 | R5: 4025.01 | S5: 0 | T5: 940 | W5: 5135 | X5: =3481.9416*J5/SUM($J$3:$J$7) -> 794.28233 | Y5: =J5-SUM(L5:T5)-K5-V5+U5+W5 -> 26106.06 | Z5: =Y5-X5 -> 25311.778 | AB5: =K5/J5 -> 0.072629976 | AC5: =Z5/K5 -> 1.6770441 | AD5: =Z5/J5 -> 0.12180367 | AE5: =Q5/J5 -> 0.25624192
B6: 19-25.01 | C6: 4 | D6: =J6-SUM(L6:T6)+U6+V6 -> 34413.47 | E6: ='Юнит 19-25.01'!K$24 -> 154 | F6: ='Юнит 19-25.01'!P$24 -> 91 | G6: ='Юнит 19-25.01'!Q$24 -> 2 | H6: ='Юнит 19-25.01'!S$24 -> 161208 | I6: ='Юнит 19-25.01'!T$24 -> -3229 | J6: =H6+I6 -> 157979 | K6: ='Юнит 19-25.01'!W$24 -> 11132.49 | L6: ='Юнит 19-25.01'!Z$24 -> 16989.46 | M6: ='Юнит 19-25.01'!X$24 -> 67930.97 | Q6: ='Юнит 19-25.01'!AA$24 -> 42151.21 | R6: 3468.89 | S6: 25 | V6: 7000 | X6: =3481.9416*J6/SUM($J$3:$J$7) -> 603.82627 | Y6: =J6-SUM(L6:T6)-K6-V6+U6+W6 -> 9280.98 | Z6: =Y6-X6 -> 8677.1537 | AB6: =K6/J6 -> 0.070468163 | AC6: =Z6/K6 -> 0.77944411 | AD6: =Z6/J6 -> 0.054925995 | AE6: =Q6/J6 -> 0.26681527
B7: 26-31.01 | C7: 5 | D7: =J7-SUM(L7:T7)+U7+V7 -> -6034.71 | E7: ='Юнит 26-31.01'!K$24 -> 200 | F7: ='Юнит 26-31.01'!P$24 -> 112 | G7: ='Юнит 26-31.01'!Q$24 -> 2 | H7: ='Юнит 26-31.01'!S$24 -> 200558 | I7: ='Юнит 26-31.01'!T$24 -> -3595 | J7: =H7+I7 -> 196963 | K7: ='Юнит 26-31.01'!W$24 -> 13886.49 | L7: ='Юнит 26-31.01'!Z$24 -> 20843.55 | M7: ='Юнит 26-31.01'!X$24 -> 84694.09 | Q7: ='Юнит 26-31.01'!AA$24 -> 50770.67 | R7: 3661.19 | S7: 150 | T7: 43993.6 | U7: 1115.39 | X7: =3481.9416*J7/SUM($J$3:$J$7) -> 752.83065 | Y7: =J7-SUM(L7:T7)-K7-V7+U7+W7 -> -19921.2 | Z7: =Y7-X7 -> -20674.031 | AB7: =(K7+K8)/(J7+J8) -> 0.070282074 | AC7: =(Z7+Z8)/(K7+K8) -> -0.67496445 | AD7: =(Z7+Z8)/(J7+J8) -> -0.047437902 | AE7: =(Q7+Q8)/(J7+J8) -> 0.25406002
A8: Февраль | B8: 01.02-01.02 | C8: 5 | D8: =J8-SUM(L8:T8)+U8+V8 -> 7323.99 | E8: ='Юнит 01.02'!K$24 -> 36 | F8: ='Юнит 01.02'!P$24 -> 19 | G8: ='Юнит 01.02'!Q$24 -> 1 | H8: ='Юнит 01.02'!S$24 -> 34372 | I8: ='Юнит 01.02'!T$24 -> -1750 | J8: =H8+I8 -> 32622 | K8: ='Юнит 01.02'!W$24 -> 2249.22 | L8: ='Юнит 01.02'!Z$24 -> 3179.52 | M8: ='Юнит 01.02'!X$24 -> 14027.46 | Q8: ='Юнит 01.02'!AA$24 -> 7557.7 | R8: 533.33 | W8: 4831 | X8: ='Юнит 01.02'!AD24 -> 122.77 | Y8: =J8-SUM(L8:T8)-K8-V8+U8+W8 -> 9905.77 | Z8: =Y8-X8 -> 9783 | AA8: =SUM(Z8:Z12) -> 171819.28
B9: 02.02-08.02 | C9: 6 | D9: =J9-SUM(L9:T9)+U9+V9 -> 40049.95 | E9: ='Юнит 02-08.02'!K$24 -> 225 | F9: ='Юнит 02-08.02'!P$24 -> 167 | G9: ='Юнит 02-08.02'!Q$24 -> 11 | H9: ='Юнит 02-08.02'!S$24 -> 323134 | I9: ='Юнит 02-08.02'!T$24 -> -22524 | J9: =H9+I9 -> 300610 | K9: ='Юнит 02-08.02'!W$24 -> 19848.12 | L9: ='Юнит 02-08.02'!Z$24 -> 31123.53 | M9: ='Юнит 02-08.02'!X$24 -> 129262.3 | Q9: ='Юнит 02-08.02'!AA$24 -> 66736.42 | R9: 5825.9 | T9: 27611.9 | X9: ='Юнит 02-08.02'!AD24 -> 1187.71 | Y9: =J9-SUM(L9:T9)-K9-V9+U9+W9 -> 20201.83 | Z9: =Y9-X9 -> 19014.12 | AB9: =K9/J9 -> 0.066026147 | AC9: =Z9/K9 -> 0.95798091 | AD9: =Z9/J9 -> 0.063251788 | AE9: =Q9/J9 -> 0.22200333
B10: 09-15.02 | C10: 7 | D10: =J10-SUM(L10:T10)+U10+V10 -> 62513.5 | E10: ='Юнит 09-15.02'!K$24 -> 240 | F10: ='Юнит 09-15.02'!P$24 -> 125 | G10: ='Юнит 09-15.02'!Q$24 -> 4 | H10: ='Юнит 09-15.02'!S$24 -> 282164 | I10: ='Юнит 09-15.02'!T$24 -> -9000 | J10: =H10+I10 -> 273164 | K10: ='Юнит 09-15.02'!W$24 -> 15306.15 | L10: ='Юнит 09-15.02'!Z$24 -> 24192.27 | M10: ='Юнит 09-15.02'!X$24 -> 117460.52 | Q10: ='Юнит 09-15.02'!AA$24 -> 61070.11 | R10: 5828.6 | S10: 175 | T10: 1924 | X10: ='Юнит 09-15.02'!AD24 -> 1179.57 | Y10: =J10-SUM(L10:T10)-K10-V10+U10+W10 -> 47207.35 | Z10: =Y10-X10 -> 46027.78 | AB10: =K10/J10 -> 0.056032823 | AC10: =Z10/K10 -> 3.0071429 | AD10: =Z10/J10 -> 0.1684987 | AE10: =Q10/J10 -> 0.22356573
B11: 16-22.02 | C11: 8 | D11: =J11-SUM(L11:T11)+U11+V11 -> 82376.34 | E11: ='Юнит 16-22.02'!K$24 -> 298 | F11: ='Юнит 16-22.02'!P$24 -> 161 | G11: ='Юнит 16-22.02'!Q$24 -> 8 | H11: ='Юнит 16-22.02'!S$24 -> 373392 | I11: ='Юнит 16-22.02'!T$24 -> -18750 | J11: =H11+I11 -> 354642 | K11: ='Юнит 16-22.02'!W$24 -> 19197.06 | L11: ='Юнит 16-22.02'!Z$24 -> 31757.74 | M11: ='Юнит 16-22.02'!X$24 -> 152496.06 | Q11: ='Юнит 16-22.02'!AA$24 -> 79962.77 | R11: 8049.09 | W11: 4347 | X11: ='Юнит 16-22.02'!$AD$24 -> 1601.92 | Y11: =J11-SUM(L11:T11)-K11-V11+U11+W11 -> 67526.28 | Z11: =Y11-X11 -> 65924.36 | AB11: =K11/J11 -> 0.054130814 | AC11: =Z11/K11 -> 3.4340863 | AD11: =Z11/J11 -> 0.18588988 | AE11: =Q11/J11 -> 0.22547462
B12: 23-28.02 | C12: 9 | D12: =J12-SUM(L12:T12)+U12+V12 -> 45285.04 | E12: ='Юнит 23-28.02'!K$24 -> 159 | F12: ='Юнит 23-28.02'!P$24 -> 107 | G12: ='Юнит 23-28.02'!Q$24 -> 6 | H12: ='Юнит 23-28.02'!S$24 -> 262374 | I12: ='Юнит 23-28.02'!T$24 -> -14100 | J12: =H12+I12 -> 248274 | K12: ='Юнит 23-28.02'!W$24 -> 13188.3 | L12: ='Юнит 23-28.02'!Z$24 -> 25365.95 | M12: ='Юнит 23-28.02'!X$24 -> 106757.82 | Q12: ='Юнит 23-28.02'!AA$24 -> 64457.72 | R12: 6407.47 | X12: ='Юнит 23-28.02'!$AD$24 -> 1026.72 | Y12: =J12-SUM(L12:T12)-K12-V12+U12+W12 -> 32096.74 | Z12: =Y12-X12 -> 31070.02 | AB12: =(K12+K13)/(J12+J13) -> 0.052676864 | AC12: =(Z12+Z13)/(K12+K13) -> 2.2847298 | AD12: =(Z12+Z13)/(J12+J13) -> 0.1203524 | AE12: =(Q12+Q13)/(J12+J13) -> 0.26870709
A13: Март | B13: 46082 | C13: 9 | D13: =J13-SUM(L13:T13)+U13+V13 -> 2695.31 | E13: ='Юнит 01.03'!K$24 -> 36 | F13: ='Юнит 01.03'!P$24 -> 13 | G13: ='Юнит 01.03'!Q$24 -> 1 | H13: ='Юнит 01.03'!S$24 -> 32560 | I13: ='Юнит 01.03'!T$24 -> -2400 | J13: =H13+I13 -> 30160 | K13: ='Юнит 01.03'!W$24 -> 1478.73 | L13: ='Юнит 01.03'!Z$24 -> 3251.78 | M13: ='Юнит 01.03'!X$24 -> 12968.8 | Q13: ='Юнит 01.03'!AA$24 -> 10359.47 | R13: 884.64 | W13: 1350 | X13: ='Юнит 01.03'!$AD$24 -> 126.4 | Y13: =J13-SUM(L13:T13)-K13-V13+U13+W13 -> 2566.58 | Z13: =Y13-X13 -> 2440.18
Y17: =J17-SUM(L17:T17)-K17-V17+U17+W17 -> 0 | Z17: =Y17-X17 -> 0 | AB17: =K17/J17 -> #DIV/0! | AC17: =Z17/K17 -> #DIV/0! | AD17: =Z17/J17 -> #DIV/0! | AE17: =Q17/J17 -> #DIV/0!
A18: Итого | D18: =SUM(D3:D17) -> 363469.32 | E18: =SUM(E3:E17) -> 1797 | F18: =SUM(F3:F17) -> 1136 | G18: =SUM(G3:G17) -> 46 | H18: =SUM(H3:H17) -> 2244443 | I18: =SUM(I3:I17) -> -93991 | J18: =SUM(J3:J17) -> 2150452 | K18: =SUM(K3:K17) -> 137838.57 | ... AA18: =SUM(AA3:AA17) -> 221378.54 | AB18: =K18/J18 -> 0.064097487 | AC18: =Z18/K18 -> 1.6237742 | AD18: =Z18/J18 -> 0.10407985 | AE18: =Q18/J18 -> 0.24620569
H19: % от выручки за весь период
I20: =-I18/H18 -> 0.041877205 | K20: =K18/$J$18 -> 0.064097487 | L20: =L18/$J$18 -> 0.10114201 | M20: =M18/$J$18 -> 0.43 | Q20: =Q18/$J$18 -> 0.24620569 | R20: =R18/$J$18 -> 0.020695305 | S20: =S18/$J$18 -> 0.00019763287 | T20: =T18/$J$18 -> 0.036513207 | U20: =U18/$J$18 -> 0.000518677 | V20: =V18/$J$18 -> 0.0032551296 | W20: =W18/$J$18 -> 0.0097258623 | X20: =X18/$J$18 -> 0.0040582313 | Z20: =Z18/K18 -> 1.6237742 | AA20: Маржинальность, % | AB20: =Z18/J18 -> 0.10407985
A22: январь | D22: =SUM(D3:D7) -> 123225.19 | E22: =SUM(E3:E7) -> 803 | F22: =SUM(F3:F7) -> 544 | G22: =SUM(G3:G7) -> 15 | H22: =SUM(H3:H7) -> 936447 | I22: =SUM(I3:I7) -> -25467 | J22: =SUM(J3:J7) -> 910980 | K22: =SUM(K3:K7) -> 66570.99 | ... AA22: =SUM(AA3:AA7) -> 49559.258
I23: =-I22/H22 -> 0.027195346 | K23: =K22/$J$22 -> 0.073076237 | L23: =L22/$J$22 -> 0.10826828 | M23: =M22/$J$22 -> 0.43 | Q23: =Q22/$J$22 -> 0.26269438 | R23: =R22/$J$22 -> 0.018634031 | S23: =S22/$J$22 -> 0.00027442974 | T23: =T22/$J$22 -> 0.053770665 | V23: =V22/$J$22 -> 0.0076840326 | W23: =W22/$J$22 -> 0.011402007 | X23: =X22/$J$22 -> 0.0038221932 | Y23: =Y22/J22 -> 0.05822433 | Z23: =Z22/J22 -> 0.054402137 | AA23: =AA22/J22 -> 0.054402137
A25: 5 неделя | K25: =(K7+K8)/($J$7+$J$8) -> 0.070282074 | L25: =(L7+L8)/($J$7+$J$8) -> 0.10463693 | M25: =(M7+M8)/($J$7+$J$8) -> 0.43 | N25: =(N7+N8)/($J$7+$J$8) -> 0 | O25: =(O7+O8)/($J$7+$J$8) -> 0 | P25: =(P7+P8)/($J$7+$J$8) -> 0 | Q25: =(Q7+Q8)/($J$7+$J$8) -> 0.25406002 | R25: =(R7+S7+T7+R8+S8+T8)/($J$7+$J$8) -> 0.21054564 | U25: =(U7+U8)/($J$7+$J$8) -> 0.0048582878 | V25: =(V7+V8)/($J$7+$J$8) -> 0 | W25: =(W7+W8)/($J$7+$J$8) -> 0.021042315 | X25: =(X7+X8)/($J$7+$J$8) -> 0.0038138408 | Y25: =(Y7+Y8)/($J$7+$J$8) -> -0.043624061 | Z25: =(Z7+Z8)/($J$7+$J$8) -> -0.047437902
A26: 6 неделя | K26: =K9/$J$9 -> 0.066026147 | L26: =L9/$J$9 -> 0.10353458 | M26: =M9/$J$9 -> 0.43 | Q26: =Q9/$J$9 -> 0.22200333 | R26: =(R9+S9+T9)/$J$9 -> 0.11123316 | V26: =V9/$J$9 -> 0 | W26: =W9/$J$9 -> 0 | X26: =X9/$J$9 -> 0.0039509996 | Y26: =Y9/J9 -> 0.067202788 | Z26: =Z9/J9 -> 0.063251788
A27: 7 неделя | K27: =K10/$J$10 -> 0.056032823 | L27: =L10/$J$10 -> 0.088563171 | M27: =M10/$J$10 -> 0.43 | Q27: =Q10/$J$10 -> 0.22356573 | R27: =(R10+S10+T10)/$J$10 -> 0.029021394 | V27: =V10/$J$10 -> 0 | W27: =W10/$J$10 -> 0 | X27: =X10/$J$10 -> 0.0043181752 | Y27: =Y10/J10 -> 0.17281688 | Z27: =Z10/J10 -> 0.1684987
A28: 8 неделя | K28: =K11/$J$11 -> 0.054130814 | L28: =L11/$J$11 -> 0.089548728 | M28: =M11/$J$11 -> 0.43 | Q28: =Q11/$J$11 -> 0.22547462 | R28: =(R11+S11+T11)/$J$11 -> 0.022696381 | V28: =V11/$J$11 -> 0 | W28: =W11/$J$11 -> 0.012257431 | X28: =X11/$J$11 -> 0.0045170059 | Y28: =Y11/J11 -> 0.19040689 | Z28: =Z11/J11 -> 0.18588988
A29: 9 неделя | K29: =(K12+K13)/($J$12+$J$13) -> 0.052676864 | L29: =(L12+L13)/($J$12+$J$13) -> 0.10278102 | M29: =(M12+M13)/($J$12+$J$13) -> 0.43 | N29: =(N12+N13)/($J$12+$J$13) -> 0 | O29: =(O12+O13)/($J$12+$J$13) -> 0 | P29: =(P12+P13)/($J$12+$J$13) -> 0 | Q29: =(Q12+Q13)/($J$12+$J$13) -> 0.26870709 | R29: =(R12+R13)/($J$12+$J$13) -> 0.026189725 | V29: =(V12+V13)/($J$12+$J$13) -> 0 | W29: =(W12+W13)/($J$12+$J$13) -> 0.0048485458 | X29: =(X12+X13)/($J$12+$J$13) -> 0.0041414482 | Y29: =(Y12+Y13)/($J$12+$J$13) -> 0.12449385 | Z29: =(Z12+Z13)/($J$12+$J$13) -> 0.1203524
A31: февраль | D31: =SUM(D8:D12) -> 237548.82 | E31: =SUM(E8:E12) -> 958 | F31: =SUM(F8:F12) -> 579 | G31: =SUM(G8:G12) -> 30 | H31: =SUM(H8:H12) -> 1275436 | I31: =SUM(I8:I12) -> -66124 | J31: =SUM(J8:J12) -> 1209312 | K31: =SUM(K8:K12) -> 69788.85 | ... AA31: =SUM(AA8:AA12) -> 171819.28

Sheet АВС 02-08.03
B2: ОЧКИ
C3: Прибыль | D3: % прибыль | E3: Доля | F3: ABC прибыль | G3: ABC кол-во | J3: Кол-во | K3: % кол-во | L3: Доля | M3: ABC кол-во
B4: черные с железкой классика | D4: =C4/C$18 -> #DIV/0! | E4: =D4 -> #DIV/0! | F4: =IF(AND(E4<=0),"C",IF(E4<=0.8,"A",IF(E4<=0.95,"B","C"))) -> #DIV/0! | G4: =VLOOKUP(B$4:B$17,I$4:M$17,5,0) -> #DIV/0! | I4: черные с железкой классика | K4: =J4/J$18 -> #DIV/0! | L4: =K4 -> #DIV/0! | M4: =_xlfn.IFS(L4<80%,"A",L4<=95%,"B",L4>95%,"C") -> #DIV/0!
B5: qs черные | D5: =C5/C$18 -> #DIV/0! | E5: =D5+E4 -> #DIV/0! | F5: =IF(AND(E5<=0),"C",IF(E5<=0.8,"A",IF(E5<=0.95,"B","C"))) -> #DIV/0! | G5: =VLOOKUP(B$4:B$17,I$4:M$17,5,0) -> #DIV/0! | I5: qs черные | K5: =J5/J$18 -> #DIV/0! | L5: =K5+L4 -> #DIV/0! | M5: =_xlfn.IFS(L5<80%,"A",L5<=95%,"B",L5>95%,"C") -> #DIV/0!
B6: qs синие | D6: =C6/C$18 -> #DIV/0! | E6: =D6+E5 -> #DIV/0! | F6: =IF(AND(E6<=0),"C",IF(E6<=0.8,"A",IF(E6<=0.95,"B","C"))) -> #DIV/0! | G6: =VLOOKUP(B$4:B$17,I$4:M$17,5,0) -> #DIV/0! | I6: qs синие | K6: =J6/J$18 -> #DIV/0! | L6: =K6+L5 -> #DIV/0! | M6: =_xlfn.IFS(L6<80%,"A",L6<=95%,"B",L6>95%,"C") -> #DIV/0!
B7: qs желтые | D7: =C7/C$18 -> #DIV/0! | E7: =D7+E6 -> #DIV/0! | F7: =IF(AND(E7<=0),"C",IF(E7<=0.8,"A",IF(E7<=0.95,"B","C"))) -> #DIV/0! | G7: =VLOOKUP(B$4:B$17,I$4:M$17,5,0) -> #DIV/0! | I7: qs желтые | K7: =J7/J$18 -> #DIV/0! | L7: =K7+L6 -> #DIV/0! | M7: =_xlfn.IFS(L7<80%,"A",L7<=95%,"B",L7>95%,"C") -> #DIV/0!
B8: qs коричневые | D8: =C8/C$18 -> #DIV/0! | E8: =D8+E7 -> #DIV/0! | F8: =IF(AND(E8<=0),"C",IF(E8<=0.8,"A",IF(E8<=0.95,"B","C"))) -> #DIV/0! | G8: =VLOOKUP(B$4:B$17,I$4:M$17,5,0) -> #DIV/0! | I8: qs коричневые | K8: =J8/J$18 -> #DIV/0! | L8: =K8+L7 -> #DIV/0! | M8: =_xlfn.IFS(L8<80%,"A",L8<=95%,"B",L8>95%,"C") -> #DIV/0!
B9: MR8854 C2 | D9: =C9/C$18 -> #DIV/0! | E9: =D9+E8 -> #DIV/0! | F9: =IF(AND(E9<=0),"C",IF(E9<=0.8,"A",IF(E9<=0.95,"B","C"))) -> #DIV/0! | G9: =VLOOKUP(B$4:B$17,I$4:M$17,5,0) -> #DIV/0! | I9: MR8854 C2 | K9: =J9/J$18 -> #DIV/0! | L9: =K9+L8 -> #DIV/0! | M9: =_xlfn.IFS(L9<80%,"A",L9<=95%,"B",L9>95%,"C") -> #DIV/0!
B10: th черн | D10: =C10/C$18 -> #DIV/0! | E10: =D10+E9 -> #DIV/0! | F10: =IF(AND(E10<=0),"C",IF(E10<=0.8,"A",IF(E10<=0.95,"B","C"))) -> #DIV/0! | G10: =VLOOKUP(B$4:B$17,I$4:M$17,5,0) -> #DIV/0! | I10: th черн | K10: =J10/J$18 -> #DIV/0! | L10: =K10+L9 -> #DIV/0! | M10: =_xlfn.IFS(L10<80%,"A",L10<=95%,"B",L10>95%,"C") -> #DIV/0!
B11: th син | D11: =C11/C$18 -> #DIV/0! | E11: =D11+E10 -> #DIV/0! | F11: =IF(AND(E11<=0),"C",IF(E11<=0.8,"A",IF(E11<=0.95,"B","C"))) -> #DIV/0! | G11: =VLOOKUP(B$4:B$17,I$4:M$17,5,0) -> #DIV/0! | I11: th син | K11: =J11/J$18 -> #DIV/0! | L11: =K11+L10 -> #DIV/0! | M11: =_xlfn.IFS(L11<80%,"A",L11<=95%,"B",L11>95%,"C") -> #DIV/0!
B12: th желт | D12: =C12/C$18 -> #DIV/0! | E12: =D12+E5 -> #DIV/0! | F12: =IF(AND(E12<=0),"C",IF(E12<=0.8,"A",IF(E12<=0.95,"B","C"))) -> #DIV/0! | G12: =VLOOKUP(B$4:B$17,I$4:M$17,5,0) -> #DIV/0! | I12: th желт | K12: =J12/J$18 -> #DIV/0! | L12: =K12+L5 -> #DIV/0! | M12: =_xlfn.IFS(L12<80%,"A",L12<=95%,"B",L12>95%,"C") -> #DIV/0!
B13: th коричн | D13: =C13/C$18 -> #DIV/0! | E13: =D13+E12 -> #DIV/0! | F13: =IF(AND(E13<=0),"C",IF(E13<=0.8,"A",IF(E13<=0.95,"B","C"))) -> #DIV/0! | G13: =VLOOKUP(B$4:B$17,I$4:M$17,5,0) -> #DIV/0! | I13: th коричн | K13: =J13/J$18 -> #DIV/0! | L13: =K13+L12 -> #DIV/0! | M13: =_xlfn.IFS(L13<80%,"A",L13<=95%,"B",L13>95%,"C") -> #DIV/0!
B14: flip черный | D14: =C14/C$18 -> #DIV/0! | E14: =D14+E13 -> #DIV/0! | F14: =IF(AND(E14<=0),"C",IF(E14<=0.8,"A",IF(E14<=0.95,"B","C"))) -> #DIV/0! | G14: =VLOOKUP(B$4:B$17,I$4:M$17,5,0) -> #DIV/0! | I14: flip черный | K14: =J14/J$18 -> #DIV/0! | L14: =K14+L13 -> #DIV/0! | M14: =_xlfn.IFS(L14<80%,"A",L14<=95%,"B",L14>95%,"C") -> #DIV/0!
B15: flip синий | D15: =C15/C$18 -> #DIV/0! | E15: =D15+E14 -> #DIV/0! | F15: =IF(AND(E15<=0),"C",IF(E15<=0.8,"A",IF(E15<=0.95,"B","C"))) -> #DIV/0! | G15: =VLOOKUP(B$4:B$17,I$4:M$17,5,0) -> #DIV/0! | I15: flip синий | K15: =J15/J$18 -> #DIV/0! | L15: =K15+L14 -> #DIV/0! | M15: =_xlfn.IFS(L15<80%,"A",L15<=95%,"B",L15>95%,"C") -> #DIV/0!
B16: flip жел | D16: =C16/C$18 -> #DIV/0! | E16: =D16+E15 -> #DIV/0! | F16: =IF(AND(E16<=0),"C",IF(E16<=0.8,"A",IF(E16<=0.95,"B","C"))) -> #DIV/0! | G16: =VLOOKUP(B$4:B$17,I$4:M$17,5,0) -> #DIV/0! | I16: flip жел | K16: =J16/J$18 -> #DIV/0! | L16: =K16+L15 -> #DIV/0! | M16: =_xlfn.IFS(L16<80%,"A",L16<=95%,"B",L16>95%,"C") -> #DIV/0!
B17: flip коричневый | D17: =C17/C$18 -> #DIV/0! | E17: =D17+E14 -> #DIV/0! | F17: =IF(AND(E17<=0),"C",IF(E17<=0.8,"A",IF(E17<=0.95,"B","C"))) -> #DIV/0! | G17: =VLOOKUP(B$4:B$17,I$4:M$17,5,0) -> #DIV/0! | I17: flip коричневый | K17: =J17/J$18 -> #DIV/0! | L17: =K17+L14 -> #DIV/0! | M17: =_xlfn.IFS(L17<80%,"A",L17<=95%,"B",L17>95%,"C") -> #DIV/0!
C18: =SUM(C4:C17) -> 0 | D18: =SUM(D4:D17) -> #DIV/0! | J18: =SUM(J4:J17) -> 0 | K18: =SUM(K4:K17) -> #DIV/0!
C21: Прибыль | D21: % прибыль | E21: Доля | F21: ABC прибыль | G21: ABC кол-во | J21: Кол-во | K21: % кол-во | L21: Доля | M21: ABC кол-во
D22: =C22/C$42 -> #DIV/0! | E22: =D22 -> #DIV/0! | F22: =IF(AND(E22<=0),"C",IF(E22<=0.8,"A",IF(E22<=0.95,"B","C"))) -> #DIV/0! | G22: =VLOOKUP(B$22:B$42,I$22:M$42,5,0) -> #N/A | K22: =J22/J$42 -> #DIV/0! | L22: =K22 -> #DIV/0! | M22: =_xlfn.IFS(L22<80%,"A",L22<=95%,"B",L22>95%,"C") -> #DIV/0!
D23: =C23/C$42 -> #DIV/0! | E23: =D23+E22 -> #DIV/0! | F23: =IF(AND(E23<=0),"C",IF(E23<=0.8,"A",IF(E23<=0.95,"B","C"))) -> #DIV/0! | G23: =VLOOKUP(B$22:B$42,I$22:M$42,5,0) -> #N/A | K23: =J23/J$42 -> #DIV/0! | L23: =K23+L22 -> #DIV/0! | M23: =_xlfn.IFS(L23<80%,"A",L23<=95%,"B",L23>95%,"C") -> #DIV/0!
D24: =C24/C$42 -> #DIV/0! | E24: =D24+E23 -> #DIV/0! | F24: =IF(AND(E24<=0),"C",IF(E24<=0.8,"A",IF(E24<=0.95,"B","C"))) -> #DIV/0! | G24: =VLOOKUP(B$22:B$42,I$22:M$42,5,0) -> #N/A | K24: =J24/J$42 -> #DIV/0! | L24: =K24+L23 -> #DIV/0! | M24: =_xlfn.IFS(L24<80%,"A",L24<=95%,"B",L24>95%,"C") -> #DIV/0!
D25: =C25/C$42 -> #DIV/0! | E25: =D25+E24 -> #DIV/0! | F25: =IF(AND(E25<=0),"C",IF(E25<=0.8,"A",IF(E25<=0.95,"B","C"))) -> #DIV/0! | G25: =VLOOKUP(B$22:B$42,I$22:M$42,5,0) -> #N/A | K25: =J25/J$42 -> #DIV/0! | L25: =K25+L24 -> #DIV/0! | M25: =_xlfn.IFS(L25<80%,"A",L25<=95%,"B",L25>95%,"C") -> #DIV/0!
D26: =C26/C$42 -> #DIV/0! | E26: =D26+E25 -> #DIV/0! | F26: =IF(AND(E26<=0),"C",IF(E26<=0.8,"A",IF(E26<=0.95,"B","C"))) -> #DIV/0! | G26: =VLOOKUP(B$22:B$42,I$22:M$42,5,0) -> #N/A | K26: =J26/J$42 -> #DIV/0! | L26: =K26+L25 -> #DIV/0! | M26: =_xlfn.IFS(L26<80%,"A",L26<=95%,"B",L26>95%,"C") -> #DIV/0!
D27: =C27/C$42 -> #DIV/0! | E27: =D27+E26 -> #DIV/0! | F27: =IF(AND(E27<=0),"C",IF(E27<=0.8,"A",IF(E27<=0.95,"B","C"))) -> #DIV/0! | G27: =VLOOKUP(B$22:B$42,I$22:M$42,5,0) -> #N/A | K27: =J27/J$42 -> #DIV/0! | L27: =K27+L26 -> #DIV/0! | M27: =_xlfn.IFS(L27<80%,"A",L27<=95%,"B",L27>95%,"C") -> #DIV/0!
D28: =C28/C$42 -> #DIV/0! | E28: =D28+E27 -> #DIV/0! | F28: =IF(AND(E28<=0),"C",IF(E28<=0.8,"A",IF(E28<=0.95,"B","C"))) -> #DIV/0! | G28: =VLOOKUP(B$22:B$42,I$22:M$42,5,0) -> #N/A | K28: =J28/J$42 -> #DIV/0! | L28: =K28+L27 -> #DIV/0! | M28: =_xlfn.IFS(L28<80%,"A",L28<=95%,"B",L28>95%,"C") -> #DIV/0!
D29: =C29/C$42 -> #DIV/0! | E29: =D29+E28 -> #DIV/0! | F29: =IF(AND(E29<=0),"C",IF(E29<=0.8,"A",IF(E29<=0.95,"B","C"))) -> #DIV/0! | G29: =VLOOKUP(B$22:B$42,I$22:M$42,5,0) -> #N/A | K29: =J29/J$42 -> #DIV/0! | L29: =K29+L28 -> #DIV/0! | M29: =_xlfn.IFS(L29<80%,"A",L29<=95%,"B",L29>95%,"C") -> #DIV/0!
D30: =C30/C$42 -> #DIV/0! | E30: =D30+E29 -> #DIV/0! | F30: =IF(AND(E30<=0),"C",IF(E30<=0.8,"A",IF(E30<=0.95,"B","C"))) -> #DIV/0! | G30: =VLOOKUP(B$22:B$42,I$22:M$42,5,0) -> #N/A | K30: =J30/J$42 -> #DIV/0! | L30: =K30+L29 -> #DIV/0! | M30: =_xlfn.IFS(L30<80%,"A",L30<=95%,"B",L30>95%,"C") -> #DIV/0!
D31: =C31/C$42 -> #DIV/0! | E31: =D31+E30 -> #DIV/0! | F31: =IF(AND(E31<=0),"C",IF(E31<=0.8,"A",IF(E31<=0.95,"B","C"))) -> #DIV/0! | G31: =VLOOKUP(B$22:B$42,I$22:M$42,5,0) -> #N/A | K31: =J31/J$42 -> #DIV/0! | L31: =K31+L30 -> #DIV/0! | M31: =_xlfn.IFS(L31<80%,"A",L31<=95%,"B",L31>95%,"C") -> #DIV/0!
D32: =C32/C$42 -> #DIV/0! | E32: =D32+E31 -> #DIV/0! | F32: =IF(AND(E32<=0),"C",IF(E32<=0.8,"A",IF(E32<=0.95,"B","C"))) -> #DIV/0! | G32: =VLOOKUP(B$22:B$42,I$22:M$42,5,0) -> #N/A | K32: =J32/J$42 -> #DIV/0! | L32: =K32+L31 -> #DIV/0! | M32: =_xlfn.IFS(L32<80%,"A",L32<=95%,"B",L32>95%,"C") -> #DIV/0!
D33: =C33/C$42 -> #DIV/0! | E33: =D33+E32 -> #DIV/0! | F33: =IF(AND(E33<=0),"C",IF(E33<=0.8,"A",IF(E33<=0.95,"B","C"))) -> #DIV/0! | G33: =VLOOKUP(B$22:B$42,I$22:M$42,5,0) -> #N/A | K33: =J33/J$42 -> #DIV/0! | L33: =K33+L32 -> #DIV/0! | M33: =_xlfn.IFS(L33<80%,"A",L33<=95%,"B",L33>95%,"C") -> #DIV/0!
D34: =C34/C$42 -> #DIV/0! | E34: =D34+E33 -> #DIV/0! | F34: =IF(AND(E34<=0),"C",IF(E34<=0.8,"A",IF(E34<=0.95,"B","C"))) -> #DIV/0! | G34: =VLOOKUP(B$22:B$42,I$22:M$42,5,0) -> #N/A | K34: =J34/J$42 -> #DIV/0! | L34: =K34+L33 -> #DIV/0! | M34: =_xlfn.IFS(L34<80%,"A",L34<=95%,"B",L34>95%,"C") -> #DIV/0!
... D41: =C41/C$42 -> #DIV/0! | E41: =D41+E40 -> #DIV/0! | F41: =IF(AND(E41<=0),"C",IF(E41<=0.8,"A",IF(E41<=0.95,"B","C"))) -> #DIV/0! | G41: =VLOOKUP(B$22:B$42,I$22:M$42,5,0) -> #N/A | K41: =J41/J$42 -> #DIV/0! | L41: =K41+L40 -> #DIV/0! | M41: =_xlfn.IFS(L41<80%,"A",L41<=95%,"B",L41>95%,"C") -> #DIV/0!
C42: =SUM(C22:C41) -> 0 | D42: =SUM(D22:D41) -> #DIV/0! | J42: =SUM(J22:J41) -> 0 | K42: =SUM(K22:K41) -> #DIV/0!

Sheet АВС ФЕВРАЛЬ
B2: ОЧКИ
C3: Прибыль | D3: % прибыль | E3: Доля | F3: ABC прибыль | G3: ABC кол-во | J3: Кол-во | K3: % кол-во | L3: Доля | M3: ABC кол-во
B4: th желт | C4: =ФЕВРАЛЬ!AE11 -> 46628.355 | D4: =C4/C$18 -> 0.20687654 | E4: =D4 -> 0.20687654 | F4: =IF(AND(E4<=0),"C",IF(E4<=0.8,"A",IF(E4<=0.95,"B","C"))) -> A | G4: =VLOOKUP(B$4:B$17,I$4:M$17,5,0) -> A | I4: th желт | J4: =ФЕВРАЛЬ!R11 -> 105 | K4: =J4/J$18 -> 0.19125683 | L4: =K4 -> 0.19125683 | M4: =_xlfn.IFS(L4<80%,"A",L4<=95%,"B",L4>95%,"C") -> A
B5: flip жел | C5: =ФЕВРАЛЬ!AE15 -> 42824.912 | D5: =C5/C$18 -> 0.19000176 | E5: =D5+E4 -> 0.39687829 | F5: =IF(AND(E5<=0),"C",IF(E5<=0.8,"A",IF(E5<=0.95,"B","C"))) -> A | G5: =VLOOKUP(B$4:B$17,I$4:M$17,5,0) -> A | I5: flip жел | J5: =ФЕВРАЛЬ!R15 -> 91 | K5: =J5/J$18 -> 0.16575592 | L5: =K5+L4 -> 0.35701275 | M5: =_xlfn.IFS(L5<80%,"A",L5<=95%,"B",L5>95%,"C") -> A
B6: MR8854 C2 | C6: =ФЕВРАЛЬ!AE8 -> 27510.868 | D6: =C6/C$18 -> 0.12205777 | E6: =D6+E5 -> 0.51893606 | F6: =IF(AND(E6<=0),"C",IF(E6<=0.8,"A",IF(E6<=0.95,"B","C"))) -> A | G6: =VLOOKUP(B$4:B$17,I$4:M$17,5,0) -> A | I6: qs коричневые | J6: =ФЕВРАЛЬ!R7 -> 64 | K6: =J6/J$18 -> 0.11657559 | L6: =K6+L5 -> 0.47358834 | M6: =_xlfn.IFS(L6<80%,"A",L6<=95%,"B",L6>95%,"C") -> A
B7: qs коричневые | C7: =ФЕВРАЛЬ!AE7 -> 17588.555 | D7: =C7/C$18 -> 0.078035333 | E7: =D7+E6 -> 0.59697139 | F7: =IF(AND(E7<=0),"C",IF(E7<=0.8,"A",IF(E7<=0.95,"B","C"))) -> A | G7: =VLOOKUP(B$4:B$17,I$4:M$17,5,0) -> A | I7: MR8854 C2 | J7: =ФЕВРАЛЬ!R8 -> 58 | K7: =J7/J$18 -> 0.10564663 | L7: =K7+L6 -> 0.57923497 | M7: =_xlfn.IFS(L7<80%,"A",L7<=95%,"B",L7>95%,"C") -> A
B8: qs желтые | C8: =ФЕВРАЛЬ!AE6 -> 15500.323 | D8: =C8/C$18 -> 0.068770454 | E8: =D8+E7 -> 0.66574185 | F8: =IF(AND(E8<=0),"C",IF(E8<=0.8,"A",IF(E8<=0.95,"B","C"))) -> A | G8: =VLOOKUP(B$4:B$17,I$4:M$17,5,0) -> A | I8: flip черный | J8: =ФЕВРАЛЬ!R13 -> 37 | K8: =J8/J$18 -> 0.067395264 | L8: =K8+L7 -> 0.64663024 | M8: =_xlfn.IFS(L8<80%,"A",L8<=95%,"B",L8>95%,"C") -> A
B9: flip коричневый | C9: =ФЕВРАЛЬ!AE16 -> 14713.909 | D9: =C9/C$18 -> 0.065281363 | E9: =D9+E8 -> 0.73102321 | F9: =IF(AND(E9<=0),"C",IF(E9<=0.8,"A",IF(E9<=0.95,"B","C"))) -> A | G9: =VLOOKUP(B$4:B$17,I$4:M$17,5,0) -> A | I9: flip коричневый | J9: =ФЕВРАЛЬ!R16 -> 35 | K9: =J9/J$18 -> 0.063752277 | L9: =K9+L8 -> 0.71038251 | M9: =_xlfn.IFS(L9<80%,"A",L9<=95%,"B",L9>95%,"C") -> A
B10: th син | C10: =ФЕВРАЛЬ!AE10 -> 14360.07 | D10: =C10/C$18 -> 0.063711478 | E10: =D10+E9 -> 0.79473469 | F10: =IF(AND(E10<=0),"C",IF(E10<=0.8,"A",IF(E10<=0.95,"B","C"))) -> A | G10: =VLOOKUP(B$4:B$17,I$4:M$17,5,0) -> B | I10: qs желтые | J10: =ФЕВРАЛЬ!R6 -> 29 | K10: =J10/J$18 -> 0.052823315 | L10: =K10+L9 -> 0.76320583 | M10: =_xlfn.IFS(L10<80%,"A",L10<=95%,"B",L10>95%,"C") -> A
B11: flip черный | C11: =ФЕВРАЛЬ!AE13 -> 13248.86 | D11: =C11/C$18 -> 0.058781364 | E11: =D11+E10 -> 0.85351605 | F11: =IF(AND(E11<=0),"C",IF(E11<=0.8,"A",IF(E11<=0.95,"B","C"))) -> B | G11: =VLOOKUP(B$4:B$17,I$4:M$17,5,0) -> A | I11: th син | J11: =ФЕВРАЛЬ!R10 -> 28 | K11: =J11/J$18 -> 0.051001821 | L11: =K11+L10 -> 0.81420765 | M11: =_xlfn.IFS(L11<80%,"A",L11<=95%,"B",L11>95%,"C") -> B
B12: flip синий | C12: =ФЕВРАЛЬ!AE14 -> 9305.9105 | D12: =C12/C$18 -> 0.041287635 | E12: =D12+E5 -> 0.43816593 | F12: =IF(AND(E12<=0),"C",IF(E12<=0.8,"A",IF(E12<=0.95,"B","C"))) -> A | G12: =VLOOKUP(B$4:B$17,I$4:M$17,5,0) -> A | I12: th коричн | J12: =ФЕВРАЛЬ!R12 -> 24 | K12: =J12/J$18 -> 0.043715847 | L12: =K12+L5 -> 0.4007286 | M12: =_xlfn.IFS(L12<80%,"A",L12<=95%,"B",L12>95%,"C") -> A
B13: qs черные | C13: =ФЕВРАЛЬ!AE4 -> 7970.474 | D13: =C13/C$18 -> 0.035362689 | E13: =D13+E12 -> 0.47352862 | F13: =IF(AND(E13<=0),"C",IF(E13<=0.8,"A",IF(E13<=0.95,"B","C"))) -> A | G13: =VLOOKUP(B$4:B$17,I$4:M$17,5,0) -> A | I13: flip синий | J13: =ФЕВРАЛЬ!R14 -> 22 | K13: =J13/J$18 -> 0.04007286 | L13: =K13+L12 -> 0.44080146 | M13: =_xlfn.IFS(L13<80%,"A",L13<=95%,"B",L13>95%,"C") -> A
B14: th черн | C14: =ФЕВРАЛЬ!AE9 -> 4092.066 | D14: =C14/C$18 -> 0.018155314 | E14: =D14+E13 -> 0.49168393 | F14: =IF(AND(E14<=0),"C",IF(E14<=0.8,"A",IF(E14<=0.95,"B","C"))) -> A | G14: =VLOOKUP(B$4:B$17,I$4:M$17,5,0) -> A | I14: qs черные | J14: =ФЕВРАЛЬ!R4 -> 16 | K14: =J14/J$18 -> 0.029143898 | L14: =K14+L13 -> 0.46994536 | M14: =_xlfn.IFS(L14<80%,"A",L14<=95%,"B",L14>95%,"C") -> A
B15: черные с железкой классика | C15: =ФЕВРАЛЬ!AE3 -> 4044.8307 | D15: =C15/C$18 -> 0.017945745 | E15: =D15+E14 -> 0.50962968 | F15: =IF(AND(E15<=0),"C",IF(E15<=0.8,"A",IF(E15<=0.95,"B","C"))) -> A | G15: =VLOOKUP(B$4:B$17,I$4:M$17,5,0) -> A | I15: th черн | J15: =ФЕВРАЛЬ!R9 -> 15 | K15: =J15/J$18 -> 0.027322404 | L15: =K15+L14 -> 0.49726776 | M15: =_xlfn.IFS(L15<80%,"A",L15<=95%,"B",L15>95%,"C") -> A
B16: th коричн | C16: =ФЕВРАЛЬ!AE12 -> 4064.9459 | D16: =C16/C$18 -> 0.01803499 | E16: =D16+E15 -> 0.52766467 | F16: =IF(AND(E16<=0),"C",IF(E16<=0.8,"A",IF(E16<=0.95,"B","C"))) -> A | G16: =VLOOKUP(B$4:B$17,I$4:M$17,5,0) -> A | I16: черные с железкой классика | J16: =ФЕВРАЛЬ!R3 -> 13 | K16: =J16/J$18 -> 0.023679417 | L16: =K16+L15 -> 0.52094718 | M16: =_xlfn.IFS(L16<80%,"A",L16<=95%,"B",L16>95%,"C") -> A
B17: qs синие | C17: =ФЕВРАЛЬ!AE5 -> 3538.1108 | D17: =C17/C$18 -> 0.015697575 | E17: =D17+E14 -> 0.50738151 | F17: =IF(AND(E17<=0),"C",IF(E17<=0.8,"A",IF(E17<=0.95,"B","C"))) -> A | G17: =VLOOKUP(B$4:B$17,I$4:M$17,5,0) -> A | I17: qs синие | J17: =ФЕВРАЛЬ!R5 -> 12 | K17: =J17/J$18 -> 0.021857923 | L17: =K17+L14 -> 0.49180328 | M17: =_xlfn.IFS(L17<80%,"A",L17<=95%,"B",L17>95%,"C") -> A
C18: =SUM(C4:C17) -> 225392.19 | D18: =SUM(D4:D17) -> 1 | J18: =SUM(J4:J17) -> 549 | K18: =SUM(K4:K17) -> 1
C21: Прибыль | D21: % прибыль | E21: Доля | F21: ABC прибыль | G21: ABC кол-во | J21: Кол-во | K21: % кол-во | L21: Доля | M21: ABC кол-во
D22: =C22/C$42 -> #DIV/0! | E22: =D22 -> #DIV/0! | F22: =IF(AND(E22<=0),"C",IF(E22<=0.8,"A",IF(E22<=0.95,"B","C"))) -> #DIV/0! | G22: =VLOOKUP(B$22:B$42,I$22:M$42,5,0) -> #N/A | K22: =J22/J$42 -> #DIV/0! | L22: =K22 -> #DIV/0! | M22: =_xlfn.IFS(L22<80%,"A",L22<=95%,"B",L22>95%,"C") -> #DIV/0!
D23: =C23/C$42 -> #DIV/0! | E23: =D23+E22 -> #DIV/0! | F23: =IF(AND(E23<=0),"C",IF(E23<=0.8,"A",IF(E23<=0.95,"B","C"))) -> #DIV/0! | G23: =VLOOKUP(B$22:B$42,I$22:M$42,5,0) -> #N/A | K23: =J23/J$42 -> #DIV/0! | L23: =K23+L22 -> #DIV/0! | M23: =_xlfn.IFS(L23<80%,"A",L23<=95%,"B",L23>95%,"C") -> #DIV/0!
D24: =C24/C$42 -> #DIV/0! | E24: =D24+E23 -> #DIV/0! | F24: =IF(AND(E24<=0),"C",IF(E24<=0.8,"A",IF(E24<=0.95,"B","C"))) -> #DIV/0! | G24: =VLOOKUP(B$22:B$42,I$22:M$42,5,0) -> #N/A | K24: =J24/J$42 -> #DIV/0! | L24: =K24+L23 -> #DIV/0! | M24: =_xlfn.IFS(L24<80%,"A",L24<=95%,"B",L24>95%,"C") -> #DIV/0!
D25: =C25/C$42 -> #DIV/0! | E25: =D25+E24 -> #DIV/0! | F25: =IF(AND(E25<=0),"C",IF(E25<=0.8,"A",IF(E25<=0.95,"B","C"))) -> #DIV/0! | G25: =VLOOKUP(B$22:B$42,I$22:M$42,5,0) -> #N/A | K25: =J25/J$42 -> #DIV/0! | L25: =K25+L24 -> #DIV/0! | M25: =_xlfn.IFS(L25<80%,"A",L25<=95%,"B",L25>95%,"C") -> #DIV/0!
D26: =C26/C$42 -> #DIV/0! | E26: =D26+E25 -> #DIV/0! | F26: =IF(AND(E26<=0),"C",IF(E26<=0.8,"A",IF(E26<=0.95,"B","C"))) -> #DIV/0! | G26: =VLOOKUP(B$22:B$42,I$22:M$42,5,0) -> #N/A | K26: =J26/J$42 -> #DIV/0! | L26: =K26+L25 -> #DIV/0! | M26: =_xlfn.IFS(L26<80%,"A",L26<=95%,"B",L26>95%,"C") -> #DIV/0!
D27: =C27/C$42 -> #DIV/0! | E27: =D27+E26 -> #DIV/0! | F27: =IF(AND(E27<=0),"C",IF(E27<=0.8,"A",IF(E27<=0.95,"B","C"))) -> #DIV/0! | G27: =VLOOKUP(B$22:B$42,I$22:M$42,5,0) -> #N/A | K27: =J27/J$42 -> #DIV/0! | L27: =K27+L26 -> #DIV/0! | M27: =_xlfn.IFS(L27<80%,"A",L27<=95%,"B",L27>95%,"C") -> #DIV/0!
D28: =C28/C$42 -> #DIV/0! | E28: =D28+E27 -> #DIV/0! | F28: =IF(AND(E28<=0),"C",IF(E28<=0.8,"A",IF(E28<=0.95,"B","C"))) -> #DIV/0! | G28: =VLOOKUP(B$22:B$42,I$22:M$42,5,0) -> #N/A | K28: =J28/J$42 -> #DIV/0! | L28: =K28+L27 -> #DIV/0! | M28: =_xlfn.IFS(L28<80%,"A",L28<=95%,"B",L28>95%,"C") -> #DIV/0!
D29: =C29/C$42 -> #DIV/0! | E29: =D29+E28 -> #DIV/0! | F29: =IF(AND(E29<=0),"C",IF(E29<=0.8,"A",IF(E29<=0.95,"B","C"))) -> #DIV/0! | G29: =VLOOKUP(B$22:B$42,I$22:M$42,5,0) -> #N/A | K29: =J29/J$42 -> #DIV/0! | L29: =K29+L28 -> #DIV/0! | M29: =_xlfn.IFS(L29<80%,"A",L29<=95%,"B",L29>95%,"C") -> #DIV/0!
D30: =C30/C$42 -> #DIV/0! | E30: =D30+E29 -> #DIV/0! | F30: =IF(AND(E30<=0),"C",IF(E30<=0.8,"A",IF(E30<=0.95,"B","C"))) -> #DIV/0! | G30: =VLOOKUP(B$22:B$42,I$22:M$42,5,0) -> #N/A | K30: =J30/J$42 -> #DIV/0! | L30: =K30+L29 -> #DIV/0! | M30: =_xlfn.IFS(L30<80%,"A",L30<=95%,"B",L30>95%,"C") -> #DIV/0!
D31: =C31/C$42 -> #DIV/0! | E31: =D31+E30 -> #DIV/0! | F31: =IF(AND(E31<=0),"C",IF(E31<=0.8,"A",IF(E31<=0.95,"B","C"))) -> #DIV/0! | G31: =VLOOKUP(B$22:B$42,I$22:M$42,5,0) -> #N/A | K31: =J31/J$42 -> #DIV/0! | L31: =K31+L30 -> #DIV/0! | M31: =_xlfn.IFS(L31<80%,"A",L31<=95%,"B",L31>95%,"C") -> #DIV/0!
D32: =C32/C$42 -> #DIV/0! | E32: =D32+E31 -> #DIV/0! | F32: =IF(AND(E32<=0),"C",IF(E32<=0.8,"A",IF(E32<=0.95,"B","C"))) -> #DIV/0! | G32: =VLOOKUP(B$22:B$42,I$22:M$42,5,0) -> #N/A | K32: =J32/J$42 -> #DIV/0! | L32: =K32+L31 -> #DIV/0! | M32: =_xlfn.IFS(L32<80%,"A",L32<=95%,"B",L32>95%,"C") -> #DIV/0!
D33: =C33/C$42 -> #DIV/0! | E33: =D33+E32 -> #DIV/0! | F33: =IF(AND(E33<=0),"C",IF(E33<=0.8,"A",IF(E33<=0.95,"B","C"))) -> #DIV/0! | G33: =VLOOKUP(B$22:B$42,I$22:M$42,5,0) -> #N/A | K33: =J33/J$42 -> #DIV/0! | L33: =K33+L32 -> #DIV/0! | M33: =_xlfn.IFS(L33<80%,"A",L33<=95%,"B",L33>95%,"C") -> #DIV/0!
D34: =C34/C$42 -> #DIV/0! | E34: =D34+E33 -> #DIV/0! | F34: =IF(AND(E34<=0),"C",IF(E34<=0.8,"A",IF(E34<=0.95,"B","C"))) -> #DIV/0! | G34: =VLOOKUP(B$22:B$42,I$22:M$42,5,0) -> #N/A | K34: =J34/J$42 -> #DIV/0! | L34: =K34+L33 -> #DIV/0! | M34: =_xlfn.IFS(L34<80%,"A",L34<=95%,"B",L34>95%,"C") -> #DIV/0!
... D41: =C41/C$42 -> #DIV/0! | E41: =D41+E40 -> #DIV/0! | F41: =IF(AND(E41<=0),"C",IF(E41<=0.8,"A",IF(E41<=0.95,"B","C"))) -> #DIV/0! | G41: =VLOOKUP(B$22:B$42,I$22:M$42,5,0) -> #N/A | K41: =J41/J$42 -> #DIV/0! | L41: =K41+L40 -> #DIV/0! | M41: =_xlfn.IFS(L41<80%,"A",L41<=95%,"B",L41>95%,"C") -> #DIV/0!
C42: =SUM(C22:C41) -> 0 | D42: =SUM(D22:D41) -> #DIV/0! | J42: =SUM(J22:J41) -> 0 | K42: =SUM(K22:K41) -> #DIV/0!

Sheet АВС 23.02-01.03
B2: ОЧКИ
C3: Прибыль | D3: % прибыль | E3: Доля | F3: ABC прибыль | G3: ABC кол-во | J3: Кол-во | K3: % кол-во | L3: Доля | M3: ABC кол-во
B4: MR8854 C2 | C4: ='Юнит 23.02-01.03'!AE8 -> 10426.618 | D4: =C4/C$18 -> 0.23609764 | E4: =D4 -> 0.23609764 | F4: =IF(AND(E4<=0),"C",IF(E4<=0.8,"A",IF(E4<=0.95,"B","C"))) -> A | G4: =VLOOKUP(B$4:B$17,I$4:M$17,5,0) -> A | I4: MR8854 C2 | J4: ='Юнит 23.02-01.03'!R8 -> 17 | K4: =J4/J$18 -> 0.15044248 | L4: =K4 -> 0.15044248 | M4: =_xlfn.IFS(L4<80%,"A",L4<=95%,"B",L4>95%,"C") -> A
B5: flip жел | C5: ='Юнит 23.02-01.03'!AE15 -> 8944.4606 | D5: =C5/C$18 -> 0.20253605 | E5: =D5+E4 -> 0.43863369 | F5: =IF(AND(E5<=0),"C",IF(E5<=0.8,"A",IF(E5<=0.95,"B","C"))) -> A | G5: =VLOOKUP(B$4:B$17,I$4:M$17,5,0) -> A | I5: flip жел | J5: ='Юнит 23.02-01.03'!R15 -> 17 | K5: =J5/J$18 -> 0.15044248 | L5: =K5+L4 -> 0.30088496 | M5: =_xlfn.IFS(L5<80%,"A",L5<=95%,"B",L5>95%,"C") -> A
B6: qs коричневые | C6: ='Юнит 23.02-01.03'!AE7 -> 5980.9182 | D6: =C6/C$18 -> 0.13543036 | E6: =D6+E5 -> 0.57406405 | F6: =IF(AND(E6<=0),"C",IF(E6<=0.8,"A",IF(E6<=0.95,"B","C"))) -> A | G6: =VLOOKUP(B$4:B$17,I$4:M$17,5,0) -> A | I6: qs коричневые | J6: ='Юнит 23.02-01.03'!R7 -> 15 | K6: =J6/J$18 -> 0.13274336 | L6: =K6+L5 -> 0.43362832 | M6: =_xlfn.IFS(L6<80%,"A",L6<=95%,"B",L6>95%,"C") -> A
B7: flip черный | C7: ='Юнит 23.02-01.03'!AE13 -> 4848.254 | D7: =C7/C$18 -> 0.10978261 | E7: =D7+E6 -> 0.68384666 | F7: =IF(AND(E7<=0),"C",IF(E7<=0.8,"A",IF(E7<=0.95,"B","C"))) -> A | G7: =VLOOKUP(B$4:B$17,I$4:M$17,5,0) -> A | I7: flip черный | J7: ='Юнит 23.02-01.03'!R13 -> 12 | K7: =J7/J$18 -> 0.10619469 | L7: =K7+L6 -> 0.53982301 | M7: =_xlfn.IFS(L7<80%,"A",L7<=95%,"B",L7>95%,"C") -> A
B8: qs желтые | C8: ='Юнит 23.02-01.03'!AE6 -> 3930.4352 | D8: =C8/C$18 -> 0.088999757 | E8: =D8+E7 -> 0.77284642 | F8: =IF(AND(E8<=0),"C",IF(E8<=0.8,"A",IF(E8<=0.95,"B","C"))) -> A | G8: =VLOOKUP(B$4:B$17,I$4:M$17,5,0) -> A | I8: flip коричневый | J8: ='Юнит 23.02-01.03'!R16 -> 9 | K8: =J8/J$18 -> 0.079646018 | L8: =K8+L7 -> 0.61946903 | M8: =_xlfn.IFS(L8<80%,"A",L8<=95%,"B",L8>95%,"C") -> A
B9: черные с железкой классика | C9: ='Юнит 23.02-01.03'!AE3 -> 2967.9729 | D9: =C9/C$18 -> 0.06720601 | E9: =D9+E8 -> 0.84005243 | F9: =IF(AND(E9<=0),"C",IF(E9<=0.8,"A",IF(E9<=0.95,"B","C"))) -> B | G9: =VLOOKUP(B$4:B$17,I$4:M$17,5,0) -> A | I9: черные с железкой классика | J9: ='Юнит 23.02-01.03'!R3 -> 7 | K9: =J9/J$18 -> 0.061946903 | L9: =K9+L8 -> 0.68141593 | M9: =_xlfn.IFS(L9<80%,"A",L9<=95%,"B",L9>95%,"C") -> A
B10: th син | C10: ='Юнит 23.02-01.03'!AE10 -> 2677.8258 | D10: =C10/C$18 -> 0.060635993 | E10: =D10+E9 -> 0.90068842 | F10: =IF(AND(E10<=0),"C",IF(E10<=0.8,"A",IF(E10<=0.95,"B","C"))) -> B | G10: =VLOOKUP(B$4:B$17,I$4:M$17,5,0) -> A | I10: qs желтые | J10: ='Юнит 23.02-01.03'!R6 -> 7 | K10: =J10/J$18 -> 0.061946903 | L10: =K10+L9 -> 0.74336283 | M10: =_xlfn.IFS(L10<80%,"A",L10<=95%,"B",L10>95%,"C") -> A
B11: flip коричневый | C11: ='Юнит 23.02-01.03'!AE16 -> 2666.483 | D11: =C11/C$18 -> 0.06037915 | E11: =D11+E10 -> 0.96106757 | F11: =IF(AND(E11<=0),"C",IF(E11<=0.8,"A",IF(E11<=0.95,"B","C"))) -> C | G11: =VLOOKUP(B$4:B$17,I$4:M$17,5,0) -> A | I11: th желт | J11: ='Юнит 23.02-01.03'!R11 -> 7 | K11: =J11/J$18 -> 0.061946903 | L11: =K11+L10 -> 0.80530973 | M11: =_xlfn.IFS(L11<80%,"A",L11<=95%,"B",L11>95%,"C") -> B
B12: flip синий | C12: ='Юнит 23.02-01.03'!AE14 -> 2149.5305 | D12: =C12/C$18 -> 0.048673413 | E12: =D12+E5 -> 0.4873071 | F12: =IF(AND(E12<=0),"C",IF(E12<=0.8,"A",IF(E12<=0.95,"B","C"))) -> A | G12: =VLOOKUP(B$4:B$17,I$4:M$17,5,0) -> A | I12: qs черные | J12: ='Юнит 23.02-01.03'!R4 -> 5 | K12: =J12/J$18 -> 0.044247788 | L12: =K12+L5 -> 0.34513274 | M12: =_xlfn.IFS(L12<80%,"A",L12<=95%,"B",L12>95%,"C") -> A
B13: qs черные | C13: ='Юнит 23.02-01.03'!AE4 -> 1734.179 | D13: =C13/C$18 -> 0.039268299 | E13: =D13+E12 -> 0.5265754 | F13: =IF(AND(E13<=0),"C",IF(E13<=0.8,"A",IF(E13<=0.95,"B","C"))) -> A | G13: =VLOOKUP(B$4:B$17,I$4:M$17,5,0) -> A | I13: th коричн | J13: ='Юнит 23.02-01.03'!R12 -> 5 | K13: =J13/J$18 -> 0.044247788 | L13: =K13+L12 -> 0.38938053 | M13: =_xlfn.IFS(L13<80%,"A",L13<=95%,"B",L13>95%,"C") -> A
B14: qs синие | C14: ='Юнит 23.02-01.03'!AE5 -> 1407.3663 | D14: =C14/C$18 -> 0.031868038 | E14: =D14+E13 -> 0.55844344 | F14: =IF(AND(E14<=0),"C",IF(E14<=0.8,"A",IF(E14<=0.95,"B","C"))) -> A | G14: =VLOOKUP(B$4:B$17,I$4:M$17,5,0) -> A | I14: qs синие | J14: ='Юнит 23.02-01.03'!R5 -> 4 | K14: =J14/J$18 -> 0.03539823 | L14: =K14+L13 -> 0.42477876 | M14: =_xlfn.IFS(L14<80%,"A",L14<=95%,"B",L14>95%,"C") -> A
B15: th желт | C15: ='Юнит 23.02-01.03'!AE11 -> -963.20294 | D15: =C15/C$18 -> -0.021810518 | E15: =D15+E14 -> 0.53663292 | F15: =IF(AND(E15<=0),"C",IF(E15<=0.8,"A",IF(E15<=0.95,"B","C"))) -> A | G15: =VLOOKUP(B$4:B$17,I$4:M$17,5,0) -> B | I15: th син | J15: ='Юнит 23.02-01.03'!R10 -> 4 | K15: =J15/J$18 -> 0.03539823 | L15: =K15+L14 -> 0.46017699 | M15: =_xlfn.IFS(L15<80%,"A",L15<=95%,"B",L15>95%,"C") -> A
B16: th коричн | C16: ='Юнит 23.02-01.03'!AE12 -> -1156.2606 | D16: =C16/C$18 -> -0.026182066 | E16: =D16+E15 -> 0.51045086 | F16: =IF(AND(E16<=0),"C",IF(E16<=0.8,"A",IF(E16<=0.95,"B","C"))) -> A | G16: =VLOOKUP(B$4:B$17,I$4:M$17,5,0) -> A | I16: flip синий | J16: ='Юнит 23.02-01.03'!R14 -> 3 | K16: =J16/J$18 -> 0.026548673 | L16: =K16+L15 -> 0.48672566 | M16: =_xlfn.IFS(L16<80%,"A",L16<=95%,"B",L16>95%,"C") -> A
B17: th черн | C17: ='Юнит 23.02-01.03'!AE9 -> -1452.266 | D17: =C17/C$18 -> -0.032884736 | E17: =D17+E14 -> 0.5255587 | F17: =IF(AND(E17<=0),"C",IF(E17<=0.8,"A",IF(E17<=0.95,"B","C"))) -> A | G17: =VLOOKUP(B$4:B$17,I$4:M$17,5,0) -> A | I17: th черн | J17: ='Юнит 23.02-01.03'!R9 -> 1 | K17: =J17/J$18 -> 0.0088495575 | L17: =K17+L14 -> 0.43362832 | M17: =_xlfn.IFS(L17<80%,"A",L17<=95%,"B",L17>95%,"C") -> A
C18: =SUM(C4:C17) -> 44162.314 | D18: =SUM(D4:D17) -> 1 | J18: =SUM(J4:J17) -> 113 | K18: =SUM(K4:K17) -> 1
C21: Прибыль | D21: % прибыль | E21: Доля | F21: ABC прибыль | G21: ABC кол-во | J21: Кол-во | K21: % кол-во | L21: Доля | M21: ABC кол-во
D22: =C22/C$42 -> #DIV/0! | E22: =D22 -> #DIV/0! | F22: =IF(AND(E22<=0),"C",IF(E22<=0.8,"A",IF(E22<=0.95,"B","C"))) -> #DIV/0! | G22: =VLOOKUP(B$22:B$42,I$22:M$42,5,0) -> #N/A | K22: =J22/J$42 -> #DIV/0! | L22: =K22 -> #DIV/0! | M22: =_xlfn.IFS(L22<80%,"A",L22<=95%,"B",L22>95%,"C") -> #DIV/0!
D23: =C23/C$42 -> #DIV/0! | E23: =D23+E22 -> #DIV/0! | F23: =IF(AND(E23<=0),"C",IF(E23<=0.8,"A",IF(E23<=0.95,"B","C"))) -> #DIV/0! | G23: =VLOOKUP(B$22:B$42,I$22:M$42,5,0) -> #N/A | K23: =J23/J$42 -> #DIV/0! | L23: =K23+L22 -> #DIV/0! | M23: =_xlfn.IFS(L23<80%,"A",L23<=95%,"B",L23>95%,"C") -> #DIV/0!
D24: =C24/C$42 -> #DIV/0! | E24: =D24+E23 -> #DIV/0! | F24: =IF(AND(E24<=0),"C",IF(E24<=0.8,"A",IF(E24<=0.95,"B","C"))) -> #DIV/0! | G24: =VLOOKUP(B$22:B$42,I$22:M$42,5,0) -> #N/A | K24: =J24/J$42 -> #DIV/0! | L24: =K24+L23 -> #DIV/0! | M24: =_xlfn.IFS(L24<80%,"A",L24<=95%,"B",L24>95%,"C") -> #DIV/0!
D25: =C25/C$42 -> #DIV/0! | E25: =D25+E24 -> #DIV/0! | F25: =IF(AND(E25<=0),"C",IF(E25<=0.8,"A",IF(E25<=0.95,"B","C"))) -> #DIV/0! | G25: =VLOOKUP(B$22:B$42,I$22:M$42,5,0) -> #N/A | K25: =J25/J$42 -> #DIV/0! | L25: =K25+L24 -> #DIV/0! | M25: =_xlfn.IFS(L25<80%,"A",L25<=95%,"B",L25>95%,"C") -> #DIV/0!
D26: =C26/C$42 -> #DIV/0! | E26: =D26+E25 -> #DIV/0! | F26: =IF(AND(E26<=0),"C",IF(E26<=0.8,"A",IF(E26<=0.95,"B","C"))) -> #DIV/0! | G26: =VLOOKUP(B$22:B$42,I$22:M$42,5,0) -> #N/A | K26: =J26/J$42 -> #DIV/0! | L26: =K26+L25 -> #DIV/0! | M26: =_xlfn.IFS(L26<80%,"A",L26<=95%,"B",L26>95%,"C") -> #DIV/0!
D27: =C27/C$42 -> #DIV/0! | E27: =D27+E26 -> #DIV/0! | F27: =IF(AND(E27<=0),"C",IF(E27<=0.8,"A",IF(E27<=0.95,"B","C"))) -> #DIV/0! | G27: =VLOOKUP(B$22:B$42,I$22:M$42,5,0) -> #N/A | K27: =J27/J$42 -> #DIV/0! | L27: =K27+L26 -> #DIV/0! | M27: =_xlfn.IFS(L27<80%,"A",L27<=95%,"B",L27>95%,"C") -> #DIV/0!
D28: =C28/C$42 -> #DIV/0! | E28: =D28+E27 -> #DIV/0! | F28: =IF(AND(E28<=0),"C",IF(E28<=0.8,"A",IF(E28<=0.95,"B","C"))) -> #DIV/0! | G28: =VLOOKUP(B$22:B$42,I$22:M$42,5,0) -> #N/A | K28: =J28/J$42 -> #DIV/0! | L28: =K28+L27 -> #DIV/0! | M28: =_xlfn.IFS(L28<80%,"A",L28<=95%,"B",L28>95%,"C") -> #DIV/0!
D29: =C29/C$42 -> #DIV/0! | E29: =D29+E28 -> #DIV/0! | F29: =IF(AND(E29<=0),"C",IF(E29<=0.8,"A",IF(E29<=0.95,"B","C"))) -> #DIV/0! | G29: =VLOOKUP(B$22:B$42,I$22:M$42,5,0) -> #N/A | K29: =J29/J$42 -> #DIV/0! | L29: =K29+L28 -> #DIV/0! | M29: =_xlfn.IFS(L29<80%,"A",L29<=95%,"B",L29>95%,"C") -> #DIV/0!
D30: =C30/C$42 -> #DIV/0! | E30: =D30+E29 -> #DIV/0! | F30: =IF(AND(E30<=0),"C",IF(E30<=0.8,"A",IF(E30<=0.95,"B","C"))) -> #DIV/0! | G30: =VLOOKUP(B$22:B$42,I$22:M$42,5,0) -> #N/A | K30: =J30/J$42 -> #DIV/0! | L30: =K30+L29 -> #DIV/0! | M30: =_xlfn.IFS(L30<80%,"A",L30<=95%,"B",L30>95%,"C") -> #DIV/0!
D31: =C31/C$42 -> #DIV/0! | E31: =D31+E30 -> #DIV/0! | F31: =IF(AND(E31<=0),"C",IF(E31<=0.8,"A",IF(E31<=0.95,"B","C"))) -> #DIV/0! | G31: =VLOOKUP(B$22:B$42,I$22:M$42,5,0) -> #N/A | K31: =J31/J$42 -> #DIV/0! | L31: =K31+L30 -> #DIV/0! | M31: =_xlfn.IFS(L31<80%,"A",L31<=95%,"B",L31>95%,"C") -> #DIV/0!
D32: =C32/C$42 -> #DIV/0! | E32: =D32+E31 -> #DIV/0! | F32: =IF(AND(E32<=0),"C",IF(E32<=0.8,"A",IF(E32<=0.95,"B","C"))) -> #DIV/0! | G32: =VLOOKUP(B$22:B$42,I$22:M$42,5,0) -> #N/A | K32: =J32/J$42 -> #DIV/0! | L32: =K32+L31 -> #DIV/0! | M32: =_xlfn.IFS(L32<80%,"A",L32<=95%,"B",L32>95%,"C") -> #DIV/0!
D33: =C33/C$42 -> #DIV/0! | E33: =D33+E32 -> #DIV/0! | F33: =IF(AND(E33<=0),"C",IF(E33<=0.8,"A",IF(E33<=0.95,"B","C"))) -> #DIV/0! | G33: =VLOOKUP(B$22:B$42,I$22:M$42,5,0) -> #N/A | K33: =J33/J$42 -> #DIV/0! | L33: =K33+L32 -> #DIV/0! | M33: =_xlfn.IFS(L33<80%,"A",L33<=95%,"B",L33>95%,"C") -> #DIV/0!
D34: =C34/C$42 -> #DIV/0! | E34: =D34+E33 -> #DIV/0! | F34: =IF(AND(E34<=0),"C",IF(E34<=0.8,"A",IF(E34<=0.95,"B","C"))) -> #DIV/0! | G34: =VLOOKUP(B$22:B$42,I$22:M$42,5,0) -> #N/A | K34: =J34/J$42 -> #DIV/0! | L34: =K34+L33 -> #DIV/0! | M34: =_xlfn.IFS(L34<80%,"A",L34<=95%,"B",L34>95%,"C") -> #DIV/0!
... D41: =C41/C$42 -> #DIV/0! | E41: =D41+E40 -> #DIV/0! | F41: =IF(AND(E41<=0),"C",IF(E41<=0.8,"A",IF(E41<=0.95,"B","C"))) -> #DIV/0! | G41: =VLOOKUP(B$22:B$42,I$22:M$42,5,0) -> #N/A | K41: =J41/J$42 -> #DIV/0! | L41: =K41+L40 -> #DIV/0! | M41: =_xlfn.IFS(L41<80%,"A",L41<=95%,"B",L41>95%,"C") -> #DIV/0!
C42: =SUM(C22:C41) -> 0 | D42: =SUM(D22:D41) -> #DIV/0! | J42: =SUM(J22:J41) -> 0 | K42: =SUM(K22:K41) -> #DIV/0!

Sheet АВС 16-22.02
B2: ОЧКИ
C3: Прибыль | D3: % прибыль | E3: Доля | F3: ABC прибыль | G3: ABC кол-во | J3: Кол-во | K3: % кол-во | L3: Доля | M3: ABC кол-во
B4: th желт | C4: ='Юнит 16-22.02'!AE11 -> 15588.532 | D4: =C4/C$18 -> 0.22056305 | E4: =D4 -> 0.22056305 | F4: =IF(AND(E4<=0),"C",IF(E4<=0.8,"A",IF(E4<=0.95,"B","C"))) -> A | G4: =VLOOKUP(B$4:B$17,I$4:M$17,5,0) -> A | I4: th желт | J4: ='Юнит 16-22.02'!R11 -> 26 | K4: =J4/J$18 -> 0.16993464 | L4: =K4 -> 0.16993464 | M4: =_xlfn.IFS(L4<80%,"A",L4<=95%,"B",L4>95%,"C") -> A
B5: qs коричневые | C5: ='Юнит 16-22.02'!AE7 -> 13263.624 | D5: =C5/C$18 -> 0.1876678 | E5: =D5+E4 -> 0.40823084 | F5: =IF(AND(E5<=0),"C",IF(E5<=0.8,"A",IF(E5<=0.95,"B","C"))) -> A | G5: =VLOOKUP(B$4:B$17,I$4:M$17,5,0) -> A | I5: qs коричневые | J5: ='Юнит 16-22.02'!R7 -> 25 | K5: =J5/J$18 -> 0.16339869 | L5: =K5+L4 -> 0.33333333 | M5: =_xlfn.IFS(L5<80%,"A",L5<=95%,"B",L5>95%,"C") -> A
B6: flip жел | C6: ='Юнит 16-22.02'!AE15 -> 8708.6634 | D6: =C6/C$18 -> 0.12321939 | E6: =D6+E5 -> 0.53145023 | F6: =IF(AND(E6<=0),"C",IF(E6<=0.8,"A",IF(E6<=0.95,"B","C"))) -> A | G6: =VLOOKUP(B$4:B$17,I$4:M$17,5,0) -> A | I6: flip жел | J6: ='Юнит 16-22.02'!R15 -> 17 | K6: =J6/J$18 -> 0.11111111 | L6: =K6+L5 -> 0.44444444 | M6: =_xlfn.IFS(L6<80%,"A",L6<=95%,"B",L6>95%,"C") -> A
B7: MR8854 C2 | C7: ='Юнит 16-22.02'!AE8 -> 6302.1753 | D7: =C7/C$18 -> 0.089169849 | E7: =D7+E6 -> 0.62062008 | F7: =IF(AND(E7<=0),"C",IF(E7<=0.8,"A",IF(E7<=0.95,"B","C"))) -> A | G7: =VLOOKUP(B$4:B$17,I$4:M$17,5,0) -> A | I7: flip черный | J7: ='Юнит 16-22.02'!R13 -> 14 | K7: =J7/J$18 -> 0.091503268 | L7: =K7+L6 -> 0.53594771 | M7: =_xlfn.IFS(L7<80%,"A",L7<=95%,"B",L7>95%,"C") -> A
B8: th син | C8: ='Юнит 16-22.02'!AE10 -> 5579.1551 | D8: =C8/C$18 -> 0.078939794 | E8: =D8+E7 -> 0.69955988 | F8: =IF(AND(E8<=0),"C",IF(E8<=0.8,"A",IF(E8<=0.95,"B","C"))) -> A | G8: =VLOOKUP(B$4:B$17,I$4:M$17,5,0) -> A | I8: MR8854 C2 | J8: ='Юнит 16-22.02'!R8 -> 12 | K8: =J8/J$18 -> 0.078431373 | L8: =K8+L7 -> 0.61437908 | M8: =_xlfn.IFS(L8<80%,"A",L8<=95%,"B",L8>95%,"C") -> A
B9: flip коричневый | C9: ='Юнит 16-22.02'!AE16 -> 4582.0618 | D9: =C9/C$18 -> 0.064831861 | E9: =D9+E8 -> 0.76439174 | F9: =IF(AND(E9<=0),"C",IF(E9<=0.8,"A",IF(E9<=0.95,"B","C"))) -> A | G9: =VLOOKUP(B$4:B$17,I$4:M$17,5,0) -> A | I9: th син | J9: ='Юнит 16-22.02'!R10 -> 10 | K9: =J9/J$18 -> 0.065359477 | L9: =K9+L8 -> 0.67973856 | M9: =_xlfn.IFS(L9<80%,"A",L9<=95%,"B",L9>95%,"C") -> A
B10: flip синий | C10: ='Юнит 16-22.02'!AE14 -> 3933.2357 | D10: =C10/C$18 -> 0.055651583 | E10: =D10+E9 -> 0.82004332 | F10: =IF(AND(E10<=0),"C",IF(E10<=0.8,"A",IF(E10<=0.95,"B","C"))) -> B | G10: =VLOOKUP(B$4:B$17,I$4:M$17,5,0) -> A | I10: flip коричневый | J10: ='Юнит 16-22.02'!R16 -> 10 | K10: =J10/J$18 -> 0.065359477 | L10: =K10+L9 -> 0.74509804 | M10: =_xlfn.IFS(L10<80%,"A",L10<=95%,"B",L10>95%,"C") -> A
B11: flip черный | C11: ='Юнит 16-22.02'!AE13 -> 3142.7759 | D11: =C11/C$18 -> 0.044467321 | E11: =D11+E10 -> 0.86451064 | F11: =IF(AND(E11<=0),"C",IF(E11<=0.8,"A",IF(E11<=0.95,"B","C"))) -> B | G11: =VLOOKUP(B$4:B$17,I$4:M$17,5,0) -> A | I11: qs желтые | J11: ='Юнит 16-22.02'!R6 -> 8 | K11: =J11/J$18 -> 0.052287582 | L11: =K11+L10 -> 0.79738562 | M11: =_xlfn.IFS(L11<80%,"A",L11<=95%,"B",L11>95%,"C") -> A
B12: qs желтые | C12: ='Юнит 16-22.02'!AE6 -> 3000.4661 | D12: =C12/C$18 -> 0.042453772 | E12: =D12+E5 -> 0.45068462 | F12: =IF(AND(E12<=0),"C",IF(E12<=0.8,"A",IF(E12<=0.95,"B","C"))) -> A | G12: =VLOOKUP(B$4:B$17,I$4:M$17,5,0) -> A | I12: th коричн | J12: ='Юнит 16-22.02'!R12 -> 7 | K12: =J12/J$18 -> 0.045751634 | L12: =K12+L5 -> 0.37908497 | M12: =_xlfn.IFS(L12<80%,"A",L12<=95%,"B",L12>95%,"C") -> A
B13: th черн | C13: ='Юнит 16-22.02'!AE9 -> 2666.4773 | D13: =C13/C$18 -> 0.037728144 | E13: =D13+E12 -> 0.48841276 | F13: =IF(AND(E13<=0),"C",IF(E13<=0.8,"A",IF(E13<=0.95,"B","C"))) -> A | G13: =VLOOKUP(B$4:B$17,I$4:M$17,5,0) -> A | I13: flip синий | J13: ='Юнит 16-22.02'!R14 -> 7 | K13: =J13/J$18 -> 0.045751634 | L13: =K13+L12 -> 0.4248366 | M13: =_xlfn.IFS(L13<80%,"A",L13<=95%,"B",L13>95%,"C") -> A
B14: qs черные | C14: ='Юнит 16-22.02'!AE4 -> 1779.7586 | D14: =C14/C$18 -> 0.025181909 | E14: =D14+E13 -> 0.51359467 | F14: =IF(AND(E14<=0),"C",IF(E14<=0.8,"A",IF(E14<=0.95,"B","C"))) -> A | G14: =VLOOKUP(B$4:B$17,I$4:M$17,5,0) -> A | I14: th черн | J14: ='Юнит 16-22.02'!R9 -> 6 | K14: =J14/J$18 -> 0.039215686 | L14: =K14+L13 -> 0.46405229 | M14: =_xlfn.IFS(L14<80%,"A",L14<=95%,"B",L14>95%,"C") -> A
B15: th коричн | C15: ='Юнит 16-22.02'!AE12 -> 1475.1304 | D15: =C15/C$18 -> 0.020871707 | E15: =D15+E14 -> 0.53446638 | F15: =IF(AND(E15<=0),"C",IF(E15<=0.8,"A",IF(E15<=0.95,"B","C"))) -> A | G15: =VLOOKUP(B$4:B$17,I$4:M$17,5,0) -> A | I15: qs черные | J15: ='Юнит 16-22.02'!R4 -> 5 | K15: =J15/J$18 -> 0.032679739 | L15: =K15+L14 -> 0.49673203 | M15: =_xlfn.IFS(L15<80%,"A",L15<=95%,"B",L15>95%,"C") -> A
B16: qs синие | C16: ='Юнит 16-22.02'!AE5 -> 553.58181 | D16: =C16/C$18 -> 0.0078326616 | E16: =D16+E15 -> 0.54229904 | F16: =IF(AND(E16<=0),"C",IF(E16<=0.8,"A",IF(E16<=0.95,"B","C"))) -> A | G16: =VLOOKUP(B$4:B$17,I$4:M$17,5,0) -> A | I16: черные с железкой классика | J16: ='Юнит 16-22.02'!R3 -> 3 | K16: =J16/J$18 -> 0.019607843 | L16: =K16+L15 -> 0.51633987 | M16: =_xlfn.IFS(L16<80%,"A",L16<=95%,"B",L16>95%,"C") -> A
B17: черные с железкой классика | C17: ='Юнит 16-22.02'!AE3 -> 100.44239 | D17: =C17/C$18 -> 0.0014211653 | E17: =D17+E14 -> 0.51501583 | F17: =IF(AND(E17<=0),"C",IF(E17<=0.8,"A",IF(E17<=0.95,"B","C"))) -> A | G17: =VLOOKUP(B$4:B$17,I$4:M$17,5,0) -> A | I17: qs синие | J17: ='Юнит 16-22.02'!R5 -> 3 | K17: =J17/J$18 -> 0.019607843 | L17: =K17+L14 -> 0.48366013 | M17: =_xlfn.IFS(L17<80%,"A",L17<=95%,"B",L17>95%,"C") -> A
C18: =SUM(C4:C17) -> 70676.079 | D18: =SUM(D4:D17) -> 1 | J18: =SUM(J4:J17) -> 153 | K18: =SUM(K4:K17) -> 1
C21: Прибыль | D21: % прибыль | E21: Доля | F21: ABC прибыль | G21: ABC кол-во | J21: Кол-во | K21: % кол-во | L21: Доля | M21: ABC кол-во
D22: =C22/C$42 -> #DIV/0! | E22: =D22 -> #DIV/0! | F22: =IF(AND(E22<=0),"C",IF(E22<=0.8,"A",IF(E22<=0.95,"B","C"))) -> #DIV/0! | G22: =VLOOKUP(B$22:B$42,I$22:M$42,5,0) -> #N/A | K22: =J22/J$42 -> #DIV/0! | L22: =K22 -> #DIV/0! | M22: =_xlfn.IFS(L22<80%,"A",L22<=95%,"B",L22>95%,"C") -> #DIV/0!
D23: =C23/C$42 -> #DIV/0! | E23: =D23+E22 -> #DIV/0! | F23: =IF(AND(E23<=0),"C",IF(E23<=0.8,"A",IF(E23<=0.95,"B","C"))) -> #DIV/0! | G23: =VLOOKUP(B$22:B$42,I$22:M$42,5,0) -> #N/A | K23: =J23/J$42 -> #DIV/0! | L23: =K23+L22 -> #DIV/0! | M23: =_xlfn.IFS(L23<80%,"A",L23<=95%,"B",L23>95%,"C") -> #DIV/0!
D24: =C24/C$42 -> #DIV/0! | E24: =D24+E23 -> #DIV/0! | F24: =IF(AND(E24<=0),"C",IF(E24<=0.8,"A",IF(E24<=0.95,"B","C"))) -> #DIV/0! | G24: =VLOOKUP(B$22:B$42,I$22:M$42,5,0) -> #N/A | K24: =J24/J$42 -> #DIV/0! | L24: =K24+L23 -> #DIV/0! | M24: =_xlfn.IFS(L24<80%,"A",L24<=95%,"B",L24>95%,"C") -> #DIV/0!
D25: =C25/C$42 -> #DIV/0! | E25: =D25+E24 -> #DIV/0! | F25: =IF(AND(E25<=0),"C",IF(E25<=0.8,"A",IF(E25<=0.95,"B","C"))) -> #DIV/0! | G25: =VLOOKUP(B$22:B$42,I$22:M$42,5,0) -> #N/A | K25: =J25/J$42 -> #DIV/0! | L25: =K25+L24 -> #DIV/0! | M25: =_xlfn.IFS(L25<80%,"A",L25<=95%,"B",L25>95%,"C") -> #DIV/0!
D26: =C26/C$42 -> #DIV/0! | E26: =D26+E25 -> #DIV/0! | F26: =IF(AND(E26<=0),"C",IF(E26<=0.8,"A",IF(E26<=0.95,"B","C"))) -> #DIV/0! | G26: =VLOOKUP(B$22:B$42,I$22:M$42,5,0) -> #N/A | K26: =J26/J$42 -> #DIV/0! | L26: =K26+L25 -> #DIV/0! | M26: =_xlfn.IFS(L26<80%,"A",L26<=95%,"B",L26>95%,"C") -> #DIV/0!
D27: =C27/C$42 -> #DIV/0! | E27: =D27+E26 -> #DIV/0! | F27: =IF(AND(E27<=0),"C",IF(E27<=0.8,"A",IF(E27<=0.95,"B","C"))) -> #DIV/0! | G27: =VLOOKUP(B$22:B$42,I$22:M$42,5,0) -> #N/A | K27: =J27/J$42 -> #DIV/0! | L27: =K27+L26 -> #DIV/0! | M27: =_xlfn.IFS(L27<80%,"A",L27<=95%,"B",L27>95%,"C") -> #DIV/0!
D28: =C28/C$42 -> #DIV/0! | E28: =D28+E27 -> #DIV/0! | F28: =IF(AND(E28<=0),"C",IF(E28<=0.8,"A",IF(E28<=0.95,"B","C"))) -> #DIV/0! | G28: =VLOOKUP(B$22:B$42,I$22:M$42,5,0) -> #N/A | K28: =J28/J$42 -> #DIV/0! | L28: =K28+L27 -> #DIV/0! | M28: =_xlfn.IFS(L28<80%,"A",L28<=95%,"B",L28>95%,"C") -> #DIV/0!
D29: =C29/C$42 -> #DIV/0! | E29: =D29+E28 -> #DIV/0! | F29: =IF(AND(E29<=0),"C",IF(E29<=0.8,"A",IF(E29<=0.95,"B","C"))) -> #DIV/0! | G29: =VLOOKUP(B$22:B$42,I$22:M$42,5,0) -> #N/A | K29: =J29/J$42 -> #DIV/0! | L29: =K29+L28 -> #DIV/0! | M29: =_xlfn.IFS(L29<80%,"A",L29<=95%,"B",L29>95%,"C") -> #DIV/0!
D30: =C30/C$42 -> #DIV/0! | E30: =D30+E29 -> #DIV/0! | F30: =IF(AND(E30<=0),"C",IF(E30<=0.8,"A",IF(E30<=0.95,"B","C"))) -> #DIV/0! | G30: =VLOOKUP(B$22:B$42,I$22:M$42,5,0) -> #N/A | K30: =J30/J$42 -> #DIV/0! | L30: =K30+L29 -> #DIV/0! | M30: =_xlfn.IFS(L30<80%,"A",L30<=95%,"B",L30>95%,"C") -> #DIV/0!
D31: =C31/C$42 -> #DIV/0! | E31: =D31+E30 -> #DIV/0! | F31: =IF(AND(E31<=0),"C",IF(E31<=0.8,"A",IF(E31<=0.95,"B","C"))) -> #DIV/0! | G31: =VLOOKUP(B$22:B$42,I$22:M$42,5,0) -> #N/A | K31: =J31/J$42 -> #DIV/0! | L31: =K31+L30 -> #DIV/0! | M31: =_xlfn.IFS(L31<80%,"A",L31<=95%,"B",L31>95%,"C") -> #DIV/0!
D32: =C32/C$42 -> #DIV/0! | E32: =D32+E31 -> #DIV/0! | F32: =IF(AND(E32<=0),"C",IF(E32<=0.8,"A",IF(E32<=0.95,"B","C"))) -> #DIV/0! | G32: =VLOOKUP(B$22:B$42,I$22:M$42,5,0) -> #N/A | K32: =J32/J$42 -> #DIV/0! | L32: =K32+L31 -> #DIV/0! | M32: =_xlfn.IFS(L32<80%,"A",L32<=95%,"B",L32>95%,"C") -> #DIV/0!
D33: =C33/C$42 -> #DIV/0! | E33: =D33+E32 -> #DIV/0! | F33: =IF(AND(E33<=0),"C",IF(E33<=0.8,"A",IF(E33<=0.95,"B","C"))) -> #DIV/0! | G33: =VLOOKUP(B$22:B$42,I$22:M$42,5,0) -> #N/A | K33: =J33/J$42 -> #DIV/0! | L33: =K33+L32 -> #DIV/0! | M33: =_xlfn.IFS(L33<80%,"A",L33<=95%,"B",L33>95%,"C") -> #DIV/0!
D34: =C34/C$42 -> #DIV/0! | E34: =D34+E33 -> #DIV/0! | F34: =IF(AND(E34<=0),"C",IF(E34<=0.8,"A",IF(E34<=0.95,"B","C"))) -> #DIV/0! | G34: =VLOOKUP(B$22:B$42,I$22:M$42,5,0) -> #N/A | K34: =J34/J$42 -> #DIV/0! | L34: =K34+L33 -> #DIV/0! | M34: =_xlfn.IFS(L34<80%,"A",L34<=95%,"B",L34>95%,"C") -> #DIV/0!
... D41: =C41/C$42 -> #DIV/0! | E41: =D41+E40 -> #DIV/0! | F41: =IF(AND(E41<=0),"C",IF(E41<=0.8,"A",IF(E41<=0.95,"B","C"))) -> #DIV/0! | G41: =VLOOKUP(B$22:B$42,I$22:M$42,5,0) -> #N/A | K41: =J41/J$42 -> #DIV/0! | L41: =K41+L40 -> #DIV/0! | M41: =_xlfn.IFS(L41<80%,"A",L41<=95%,"B",L41>95%,"C") -> #DIV/0!
C42: =SUM(C22:C41) -> 0 | D42: =SUM(D22:D41) -> #DIV/0! | J42: =SUM(J22:J41) -> 0 | K42: =SUM(K22:K41) -> #DIV/0!

Sheet АВС 09-15.02
B2: ОЧКИ
C3: Прибыль | D3: % прибыль | E3: Доля | F3: ABC прибыль | G3: ABC кол-во | J3: Кол-во | K3: % кол-во | L3: Доля | M3: ABC кол-во
B4: черные с железкой классика | D4: =C4/C$18 -> #DIV/0! | E4: =D4 -> #DIV/0! | F4: =IF(AND(E4<=0),"C",IF(E4<=0.8,"A",IF(E4<=0.95,"B","C"))) -> #DIV/0! | G4: =VLOOKUP(B$4:B$17,I$4:M$17,5,0) -> #DIV/0! | I4: черные с железкой классика | K4: =J4/J$18 -> #DIV/0! | L4: =K4 -> #DIV/0! | M4: =_xlfn.IFS(L4<80%,"A",L4<=95%,"B",L4>95%,"C") -> #DIV/0!
B5: qs черные | D5: =C5/C$18 -> #DIV/0! | E5: =D5+E4 -> #DIV/0! | F5: =IF(AND(E5<=0),"C",IF(E5<=0.8,"A",IF(E5<=0.95,"B","C"))) -> #DIV/0! | G5: =VLOOKUP(B$4:B$17,I$4:M$17,5,0) -> #DIV/0! | I5: qs черные | K5: =J5/J$18 -> #DIV/0! | L5: =K5+L4 -> #DIV/0! | M5: =_xlfn.IFS(L5<80%,"A",L5<=95%,"B",L5>95%,"C") -> #DIV/0!
B6: qs синие | D6: =C6/C$18 -> #DIV/0! | E6: =D6+E5 -> #DIV/0! | F6: =IF(AND(E6<=0),"C",IF(E6<=0.8,"A",IF(E6<=0.95,"B","C"))) -> #DIV/0! | G6: =VLOOKUP(B$4:B$17,I$4:M$17,5,0) -> #DIV/0! | I6: qs синие | K6: =J6/J$18 -> #DIV/0! | L6: =K6+L5 -> #DIV/0! | M6: =_xlfn.IFS(L6<80%,"A",L6<=95%,"B",L6>95%,"C") -> #DIV/0!
B7: qs желтые | D7: =C7/C$18 -> #DIV/0! | E7: =D7+E6 -> #DIV/0! | F7: =IF(AND(E7<=0),"C",IF(E7<=0.8,"A",IF(E7<=0.95,"B","C"))) -> #DIV/0! | G7: =VLOOKUP(B$4:B$17,I$4:M$17,5,0) -> #DIV/0! | I7: qs желтые | K7: =J7/J$18 -> #DIV/0! | L7: =K7+L6 -> #DIV/0! | M7: =_xlfn.IFS(L7<80%,"A",L7<=95%,"B",L7>95%,"C") -> #DIV/0!
B8: qs коричневые | D8: =C8/C$18 -> #DIV/0! | E8: =D8+E7 -> #DIV/0! | F8: =IF(AND(E8<=0),"C",IF(E8<=0.8,"A",IF(E8<=0.95,"B","C"))) -> #DIV/0! | G8: =VLOOKUP(B$4:B$17,I$4:M$17,5,0) -> #DIV/0! | I8: qs коричневые | K8: =J8/J$18 -> #DIV/0! | L8: =K8+L7 -> #DIV/0! | M8: =_xlfn.IFS(L8<80%,"A",L8<=95%,"B",L8>95%,"C") -> #DIV/0!
B9: MR8854 C2 | D9: =C9/C$18 -> #DIV/0! | E9: =D9+E8 -> #DIV/0! | F9: =IF(AND(E9<=0),"C",IF(E9<=0.8,"A",IF(E9<=0.95,"B","C"))) -> #DIV/0! | G9: =VLOOKUP(B$4:B$17,I$4:M$17,5,0) -> #DIV/0! | I9: MR8854 C2 | K9: =J9/J$18 -> #DIV/0! | L9: =K9+L8 -> #DIV/0! | M9: =_xlfn.IFS(L9<80%,"A",L9<=95%,"B",L9>95%,"C") -> #DIV/0!
B10: th черн | D10: =C10/C$18 -> #DIV/0! | E10: =D10+E9 -> #DIV/0! | F10: =IF(AND(E10<=0),"C",IF(E10<=0.8,"A",IF(E10<=0.95,"B","C"))) -> #DIV/0! | G10: =VLOOKUP(B$4:B$17,I$4:M$17,5,0) -> #DIV/0! | I10: th черн | K10: =J10/J$18 -> #DIV/0! | L10: =K10+L9 -> #DIV/0! | M10: =_xlfn.IFS(L10<80%,"A",L10<=95%,"B",L10>95%,"C") -> #DIV/0!
B11: th син | D11: =C11/C$18 -> #DIV/0! | E11: =D11+E10 -> #DIV/0! | F11: =IF(AND(E11<=0),"C",IF(E11<=0.8,"A",IF(E11<=0.95,"B","C"))) -> #DIV/0! | G11: =VLOOKUP(B$4:B$17,I$4:M$17,5,0) -> #DIV/0! | I11: th син | K11: =J11/J$18 -> #DIV/0! | L11: =K11+L10 -> #DIV/0! | M11: =_xlfn.IFS(L11<80%,"A",L11<=95%,"B",L11>95%,"C") -> #DIV/0!
B12: th желт | D12: =C12/C$18 -> #DIV/0! | E12: =D12+E5 -> #DIV/0! | F12: =IF(AND(E12<=0),"C",IF(E12<=0.8,"A",IF(E12<=0.95,"B","C"))) -> #DIV/0! | G12: =VLOOKUP(B$4:B$17,I$4:M$17,5,0) -> #DIV/0! | I12: th желт | K12: =J12/J$18 -> #DIV/0! | L12: =K12+L5 -> #DIV/0! | M12: =_xlfn.IFS(L12<80%,"A",L12<=95%,"B",L12>95%,"C") -> #DIV/0!
B13: th коричн | D13: =C13/C$18 -> #DIV/0! | E13: =D13+E12 -> #DIV/0! | F13: =IF(AND(E13<=0),"C",IF(E13<=0.8,"A",IF(E13<=0.95,"B","C"))) -> #DIV/0! | G13: =VLOOKUP(B$4:B$17,I$4:M$17,5,0) -> #DIV/0! | I13: th коричн | K13: =J13/J$18 -> #DIV/0! | L13: =K13+L12 -> #DIV/0! | M13: =_xlfn.IFS(L13<80%,"A",L13<=95%,"B",L13>95%,"C") -> #DIV/0!
B14: flip черный | D14: =C14/C$18 -> #DIV/0! | E14: =D14+E13 -> #DIV/0! | F14: =IF(AND(E14<=0),"C",IF(E14<=0.8,"A",IF(E14<=0.95,"B","C"))) -> #DIV/0! | G14: =VLOOKUP(B$4:B$17,I$4:M$17,5,0) -> #DIV/0! | I14: flip черный | K14: =J14/J$18 -> #DIV/0! | L14: =K14+L13 -> #DIV/0! | M14: =_xlfn.IFS(L14<80%,"A",L14<=95%,"B",L14>95%,"C") -> #DIV/0!
B15: flip синий | D15: =C15/C$18 -> #DIV/0! | E15: =D15+E14 -> #DIV/0! | F15: =IF(AND(E15<=0),"C",IF(E15<=0.8,"A",IF(E15<=0.95,"B","C"))) -> #DIV/0! | G15: =VLOOKUP(B$4:B$17,I$4:M$17,5,0) -> #DIV/0! | I15: flip синий | K15: =J15/J$18 -> #DIV/0! | L15: =K15+L14 -> #DIV/0! | M15: =_xlfn.IFS(L15<80%,"A",L15<=95%,"B",L15>95%,"C") -> #DIV/0!
B16: flip жел | D16: =C16/C$18 -> #DIV/0! | E16: =D16+E15 -> #DIV/0! | F16: =IF(AND(E16<=0),"C",IF(E16<=0.8,"A",IF(E16<=0.95,"B","C"))) -> #DIV/0! | G16: =VLOOKUP(B$4:B$17,I$4:M$17,5,0) -> #DIV/0! | I16: flip жел | K16: =J16/J$18 -> #DIV/0! | L16: =K16+L15 -> #DIV/0! | M16: =_xlfn.IFS(L16<80%,"A",L16<=95%,"B",L16>95%,"C") -> #DIV/0!
B17: flip коричневый | D17: =C17/C$18 -> #DIV/0! | E17: =D17+E14 -> #DIV/0! | F17: =IF(AND(E17<=0),"C",IF(E17<=0.8,"A",IF(E17<=0.95,"B","C"))) -> #DIV/0! | G17: =VLOOKUP(B$4:B$17,I$4:M$17,5,0) -> #DIV/0! | I17: flip коричневый | K17: =J17/J$18 -> #DIV/0! | L17: =K17+L14 -> #DIV/0! | M17: =_xlfn.IFS(L17<80%,"A",L17<=95%,"B",L17>95%,"C") -> #DIV/0!
C18: =SUM(C4:C17) -> 0 | D18: =SUM(D4:D17) -> #DIV/0! | J18: =SUM(J4:J17) -> 0 | K18: =SUM(K4:K17) -> #DIV/0!
C21: Прибыль | D21: % прибыль | E21: Доля | F21: ABC прибыль | G21: ABC кол-во | J21: Кол-во | K21: % кол-во | L21: Доля | M21: ABC кол-во
D22: =C22/C$42 -> #DIV/0! | E22: =D22 -> #DIV/0! | F22: =IF(AND(E22<=0),"C",IF(E22<=0.8,"A",IF(E22<=0.95,"B","C"))) -> #DIV/0! | G22: =VLOOKUP(B$22:B$42,I$22:M$42,5,0) -> #N/A | K22: =J22/J$42 -> #DIV/0! | L22: =K22 -> #DIV/0! | M22: =_xlfn.IFS(L22<80%,"A",L22<=95%,"B",L22>95%,"C") -> #DIV/0!
D23: =C23/C$42 -> #DIV/0! | E23: =D23+E22 -> #DIV/0! | F23: =IF(AND(E23<=0),"C",IF(E23<=0.8,"A",IF(E23<=0.95,"B","C"))) -> #DIV/0! | G23: =VLOOKUP(B$22:B$42,I$22:M$42,5,0) -> #N/A | K23: =J23/J$42 -> #DIV/0! | L23: =K23+L22 -> #DIV/0! | M23: =_xlfn.IFS(L23<80%,"A",L23<=95%,"B",L23>95%,"C") -> #DIV/0!
D24: =C24/C$42 -> #DIV/0! | E24: =D24+E23 -> #DIV/0! | F24: =IF(AND(E24<=0),"C",IF(E24<=0.8,"A",IF(E24<=0.95,"B","C"))) -> #DIV/0! | G24: =VLOOKUP(B$22:B$42,I$22:M$42,5,0) -> #N/A | K24: =J24/J$42 -> #DIV/0! | L24: =K24+L23 -> #DIV/0! | M24: =_xlfn.IFS(L24<80%,"A",L24<=95%,"B",L24>95%,"C") -> #DIV/0!
D25: =C25/C$42 -> #DIV/0! | E25: =D25+E24 -> #DIV/0! | F25: =IF(AND(E25<=0),"C",IF(E25<=0.8,"A",IF(E25<=0.95,"B","C"))) -> #DIV/0! | G25: =VLOOKUP(B$22:B$42,I$22:M$42,5,0) -> #N/A | K25: =J25/J$42 -> #DIV/0! | L25: =K25+L24 -> #DIV/0! | M25: =_xlfn.IFS(L25<80%,"A",L25<=95%,"B",L25>95%,"C") -> #DIV/0!
D26: =C26/C$42 -> #DIV/0! | E26: =D26+E25 -> #DIV/0! | F26: =IF(AND(E26<=0),"C",IF(E26<=0.8,"A",IF(E26<=0.95,"B","C"))) -> #DIV/0! | G26: =VLOOKUP(B$22:B$42,I$22:M$42,5,0) -> #N/A | K26: =J26/J$42 -> #DIV/0! | L26: =K26+L25 -> #DIV/0! | M26: =_xlfn.IFS(L26<80%,"A",L26<=95%,"B",L26>95%,"C") -> #DIV/0!
D27: =C27/C$42 -> #DIV/0! | E27: =D27+E26 -> #DIV/0! | F27: =IF(AND(E27<=0),"C",IF(E27<=0.8,"A",IF(E27<=0.95,"B","C"))) -> #DIV/0! | G27: =VLOOKUP(B$22:B$42,I$22:M$42,5,0) -> #N/A | K27: =J27/J$42 -> #DIV/0! | L27: =K27+L26 -> #DIV/0! | M27: =_xlfn.IFS(L27<80%,"A",L27<=95%,"B",L27>95%,"C") -> #DIV/0!
D28: =C28/C$42 -> #DIV/0! | E28: =D28+E27 -> #DIV/0! | F28: =IF(AND(E28<=0),"C",IF(E28<=0.8,"A",IF(E28<=0.95,"B","C"))) -> #DIV/0! | G28: =VLOOKUP(B$22:B$42,I$22:M$42,5,0) -> #N/A | K28: =J28/J$42 -> #DIV/0! | L28: =K28+L27 -> #DIV/0! | M28: =_xlfn.IFS(L28<80%,"A",L28<=95%,"B",L28>95%,"C") -> #DIV/0!
D29: =C29/C$42 -> #DIV/0! | E29: =D29+E28 -> #DIV/0! | F29: =IF(AND(E29<=0),"C",IF(E29<=0.8,"A",IF(E29<=0.95,"B","C"))) -> #DIV/0! | G29: =VLOOKUP(B$22:B$42,I$22:M$42,5,0) -> #N/A | K29: =J29/J$42 -> #DIV/0! | L29: =K29+L28 -> #DIV/0! | M29: =_xlfn.IFS(L29<80%,"A",L29<=95%,"B",L29>95%,"C") -> #DIV/0!
D30: =C30/C$42 -> #DIV/0! | E30: =D30+E29 -> #DIV/0! | F30: =IF(AND(E30<=0),"C",IF(E30<=0.8,"A",IF(E30<=0.95,"B","C"))) -> #DIV/0! | G30: =VLOOKUP(B$22:B$42,I$22:M$42,5,0) -> #N/A | K30: =J30/J$42 -> #DIV/0! | L30: =K30+L29 -> #DIV/0! | M30: =_xlfn.IFS(L30<80%,"A",L30<=95%,"B",L30>95%,"C") -> #DIV/0!
D31: =C31/C$42 -> #DIV/0! | E31: =D31+E30 -> #DIV/0! | F31: =IF(AND(E31<=0),"C",IF(E31<=0.8,"A",IF(E31<=0.95,"B","C"))) -> #DIV/0! | G31: =VLOOKUP(B$22:B$42,I$22:M$42,5,0) -> #N/A | K31: =J31/J$42 -> #DIV/0! | L31: =K31+L30 -> #DIV/0! | M31: =_xlfn.IFS(L31<80%,"A",L31<=95%,"B",L31>95%,"C") -> #DIV/0!
D32: =C32/C$42 -> #DIV/0! | E32: =D32+E31 -> #DIV/0! | F32: =IF(AND(E32<=0),"C",IF(E32<=0.8,"A",IF(E32<=0.95,"B","C"))) -> #DIV/0! | G32: =VLOOKUP(B$22:B$42,I$22:M$42,5,0) -> #N/A | K32: =J32/J$42 -> #DIV/0! | L32: =K32+L31 -> #DIV/0! | M32: =_xlfn.IFS(L32<80%,"A",L32<=95%,"B",L32>95%,"C") -> #DIV/0!
D33: =C33/C$42 -> #DIV/0! | E33: =D33+E32 -> #DIV/0! | F33: =IF(AND(E33<=0),"C",IF(E33<=0.8,"A",IF(E33<=0.95,"B","C"))) -> #DIV/0! | G33: =VLOOKUP(B$22:B$42,I$22:M$42,5,0) -> #N/A | K33: =J33/J$42 -> #DIV/0! | L33: =K33+L32 -> #DIV/0! | M33: =_xlfn.IFS(L33<80%,"A",L33<=95%,"B",L33>95%,"C") -> #DIV/0!
D34: =C34/C$42 -> #DIV/0! | E34: =D34+E33 -> #DIV/0! | F34: =IF(AND(E34<=0),"C",IF(E34<=0.8,"A",IF(E34<=0.95,"B","C"))) -> #DIV/0! | G34: =VLOOKUP(B$22:B$42,I$22:M$42,5,0) -> #N/A | K34: =J34/J$42 -> #DIV/0! | L34: =K34+L33 -> #DIV/0! | M34: =_xlfn.IFS(L34<80%,"A",L34<=95%,"B",L34>95%,"C") -> #DIV/0!
... D41: =C41/C$42 -> #DIV/0! | E41: =D41+E40 -> #DIV/0! | F41: =IF(AND(E41<=0),"C",IF(E41<=0.8,"A",IF(E41<=0.95,"B","C"))) -> #DIV/0! | G41: =VLOOKUP(B$22:B$42,I$22:M$42,5,0) -> #N/A | K41: =J41/J$42 -> #DIV/0! | L41: =K41+L40 -> #DIV/0! | M41: =_xlfn.IFS(L41<80%,"A",L41<=95%,"B",L41>95%,"C") -> #DIV/0!
C42: =SUM(C22:C41) -> 0 | D42: =SUM(D22:D41) -> #DIV/0! | J42: =SUM(J22:J41) -> 0 | K42: =SUM(K22:K41) -> #DIV/0!

Sheet АВС 02-08.02
B2: ОЧКИ
C3: Прибыль | D3: % прибыль | E3: Доля | F3: ABC прибыль | G3: ABC кол-во | J3: Кол-во | K3: % кол-во | L3: Доля | M3: ABC кол-во
B4: flip жел | C4: ='Юнит 02-08.02'!AE15 -> 18277.046 | D4: =C4/C$18 -> 0.34161491 | E4: =D4 -> 0.34161491 | F4: =IF(AND(E4<=0),"C",IF(E4<=0.8,"A",IF(E4<=0.95,"B","C"))) -> A | G4: =VLOOKUP(B$4:B$17,I$4:M$17,5,0) -> A | I4: th желт | J4: ='Юнит 02-08.02'!R11 -> 42 | K4: =J4/J$18 -> 0.26923077 | L4: =K4 -> 0.26923077 | M4: =_xlfn.IFS(L4<80%,"A",L4<=95%,"B",L4>95%,"C") -> A
B5: th желт | C5: ='Юнит 02-08.02'!AE11 -> 17790.829 | D5: =C5/C$18 -> 0.33252706 | E5: =D5+E4 -> 0.67414197 | F5: =IF(AND(E5<=0),"C",IF(E5<=0.8,"A",IF(E5<=0.95,"B","C"))) -> A | G5: =VLOOKUP(B$4:B$17,I$4:M$17,5,0) -> A | I5: flip жел | J5: ='Юнит 02-08.02'!R15 -> 39 | K5: =J5/J$18 -> 0.25 | L5: =K5+L4 -> 0.51923077 | M5: =_xlfn.IFS(L5<80%,"A",L5<=95%,"B",L5>95%,"C") -> A
B6: MR8854 C2 | C6: ='Юнит 02-08.02'!AE8 -> 6133.4351 | D6: =C6/C$18 -> 0.11463958 | E6: =D6+E5 -> 0.78878155 | F6: =IF(AND(E6<=0),"C",IF(E6<=0.8,"A",IF(E6<=0.95,"B","C"))) -> A | G6: =VLOOKUP(B$4:B$17,I$4:M$17,5,0) -> A | I6: MR8854 C2 | J6: ='Юнит 02-08.02'!R8 -> 16 | K6: =J6/J$18 -> 0.1025641 | L6: =K6+L5 -> 0.62179487 | M6: =_xlfn.IFS(L6<80%,"A",L6<=95%,"B",L6>95%,"C") -> A
B7: qs желтые | C7: ='Юнит 02-08.02'!AE6 -> 4862.3614 | D7: =C7/C$18 -> 0.090882034 | E7: =D7+E6 -> 0.87966358 | F7: =IF(AND(E7<=0),"C",IF(E7<=0.8,"A",IF(E7<=0.95,"B","C"))) -> B | G7: =VLOOKUP(B$4:B$17,I$4:M$17,5,0) -> A | I7: qs коричневые | J7: ='Юнит 02-08.02'!R7 -> 11 | K7: =J7/J$18 -> 0.070512821 | L7: =K7+L6 -> 0.69230769 | M7: =_xlfn.IFS(L7<80%,"A",L7<=95%,"B",L7>95%,"C") -> A
B8: flip синий | C8: ='Юнит 02-08.02'!AE14 -> 2919.034 | D8: =C8/C$18 -> 0.054559447 | E8: =D8+E7 -> 0.93422303 | F8: =IF(AND(E8<=0),"C",IF(E8<=0.8,"A",IF(E8<=0.95,"B","C"))) -> B | G8: =VLOOKUP(B$4:B$17,I$4:M$17,5,0) -> B | I8: qs желтые | J8: ='Юнит 02-08.02'!R6 -> 9 | K8: =J8/J$18 -> 0.057692308 | L8: =K8+L7 -> 0.75 | M8: =_xlfn.IFS(L8<80%,"A",L8<=95%,"B",L8>95%,"C") -> A
B9: th син | C9: ='Юнит 02-08.02'!AE10 -> 2854.5428 | D9: =C9/C$18 -> 0.053354047 | E9: =D9+E8 -> 0.98757708 | F9: =IF(AND(E9<=0),"C",IF(E9<=0.8,"A",IF(E9<=0.95,"B","C"))) -> C | G9: =VLOOKUP(B$4:B$17,I$4:M$17,5,0) -> B | I9: th син | J9: ='Юнит 02-08.02'!R10 -> 9 | K9: =J9/J$18 -> 0.057692308 | L9: =K9+L8 -> 0.80769231 | M9: =_xlfn.IFS(L9<80%,"A",L9<=95%,"B",L9>95%,"C") -> B
B10: qs черные | C10: ='Юнит 02-08.02'!AE4 -> 1679.3861 | D10: =C10/C$18 -> 0.031389281 | E10: =D10+E9 -> 1.0189664 | F10: =IF(AND(E10<=0),"C",IF(E10<=0.8,"A",IF(E10<=0.95,"B","C"))) -> C | G10: =VLOOKUP(B$4:B$17,I$4:M$17,5,0) -> A | I10: flip синий | J10: ='Юнит 02-08.02'!R14 -> 8 | K10: =J10/J$18 -> 0.051282051 | L10: =K10+L9 -> 0.85897436 | M10: =_xlfn.IFS(L10<80%,"A",L10<=95%,"B",L10>95%,"C") -> B
B11: th черн | C11: ='Юнит 02-08.02'!AE9 -> 1483.022 | D11: =C11/C$18 -> 0.027719054 | E11: =D11+E10 -> 1.0466854 | F11: =IF(AND(E11<=0),"C",IF(E11<=0.8,"A",IF(E11<=0.95,"B","C"))) -> C | G11: =VLOOKUP(B$4:B$17,I$4:M$17,5,0) -> B | I11: th черн | J11: ='Юнит 02-08.02'!R9 -> 4 | K11: =J11/J$18 -> 0.025641026 | L11: =K11+L10 -> 0.88461538 | M11: =_xlfn.IFS(L11<80%,"A",L11<=95%,"B",L11>95%,"C") -> B
B12: qs синие | C12: ='Юнит 02-08.02'!AE5 -> 493.8015 | D12: =C12/C$18 -> 0.0092296071 | E12: =D12+E5 -> 0.68337158 | F12: =IF(AND(E12<=0),"C",IF(E12<=0.8,"A",IF(E12<=0.95,"B","C"))) -> A | G12: =VLOOKUP(B$4:B$17,I$4:M$17,5,0) -> A | I12: th коричн | J12: ='Юнит 02-08.02'!R12 -> 4 | K12: =J12/J$18 -> 0.025641026 | L12: =K12+L5 -> 0.54487179 | M12: =_xlfn.IFS(L12<80%,"A",L12<=95%,"B",L12>95%,"C") -> A
B13: flip черный | C13: ='Юнит 02-08.02'!AE13 -> 420.652 | D13: =C13/C$18 -> 0.0078623753 | E13: =D13+E12 -> 0.69123395 | F13: =IF(AND(E13<=0),"C",IF(E13<=0.8,"A",IF(E13<=0.95,"B","C"))) -> A | G13: =VLOOKUP(B$4:B$17,I$4:M$17,5,0) -> A | I13: flip черный | J13: ='Юнит 02-08.02'!R13 -> 4 | K13: =J13/J$18 -> 0.025641026 | L13: =K13+L12 -> 0.57051282 | M13: =_xlfn.IFS(L13<80%,"A",L13<=95%,"B",L13>95%,"C") -> A
B14: flip коричневый | C14: ='Юнит 02-08.02'!AE16 -> 404.65606 | D14: =C14/C$18 -> 0.0075633963 | E14: =D14+E13 -> 0.69879735 | F14: =IF(AND(E14<=0),"C",IF(E14<=0.8,"A",IF(E14<=0.95,"B","C"))) -> A | G14: =VLOOKUP(B$4:B$17,I$4:M$17,5,0) -> A | I14: flip коричневый | J14: ='Юнит 02-08.02'!R16 -> 4 | K14: =J14/J$18 -> 0.025641026 | L14: =K14+L13 -> 0.59615385 | M14: =_xlfn.IFS(L14<80%,"A",L14<=95%,"B",L14>95%,"C") -> A
B15: черные с железкой классика | C15: ='Юнит 02-08.02'!AE3 -> 292.51085 | D15: =C15/C$18 -> 0.0054672985 | E15: =D15+E14 -> 0.70426465 | F15: =IF(AND(E15<=0),"C",IF(E15<=0.8,"A",IF(E15<=0.95,"B","C"))) -> A | G15: =VLOOKUP(B$4:B$17,I$4:M$17,5,0) -> A | I15: qs черные | J15: ='Юнит 02-08.02'!R4 -> 3 | K15: =J15/J$18 -> 0.019230769 | L15: =K15+L14 -> 0.61538462 | M15: =_xlfn.IFS(L15<80%,"A",L15<=95%,"B",L15>95%,"C") -> A
B16: th коричн | C16: ='Юнит 02-08.02'!AE12 -> -724.708 | D16: =C16/C$18 -> -0.013545463 | E16: =D16+E15 -> 0.69071918 | F16: =IF(AND(E16<=0),"C",IF(E16<=0.8,"A",IF(E16<=0.95,"B","C"))) -> A | G16: =VLOOKUP(B$4:B$17,I$4:M$17,5,0) -> A | I16: qs синие | J16: ='Юнит 02-08.02'!R5 -> 2 | K16: =J16/J$18 -> 0.012820513 | L16: =K16+L15 -> 0.62820513 | M16: =_xlfn.IFS(L16<80%,"A",L16<=95%,"B",L16>95%,"C") -> A
B17: qs коричневые | C17: ='Юнит 02-08.02'!AE7 -> -3384.6705 | D17: =C17/C$18 -> -0.063262625 | E17: =D17+E14 -> 0.63553472 | F17: =IF(AND(E17<=0),"C",IF(E17<=0.8,"A",IF(E17<=0.95,"B","C"))) -> A | G17: =VLOOKUP(B$4:B$17,I$4:M$17,5,0) -> A | I17: черные с железкой классика | J17: ='Юнит 02-08.02'!R3 -> 1 | K17: =J17/J$18 -> 0.0064102564 | L17: =K17+L14 -> 0.6025641 | M17: =_xlfn.IFS(L17<80%,"A",L17<=95%,"B",L17>95%,"C") -> A
C18: =SUM(C4:C17) -> 53501.898 | D18: =SUM(D4:D17) -> 1 | J18: =SUM(J4:J17) -> 156 | K18: =SUM(K4:K17) -> 1
C21: Прибыль | D21: % прибыль | E21: Доля | F21: ABC прибыль | G21: ABC кол-во | J21: Кол-во | K21: % кол-во | L21: Доля | M21: ABC кол-во
D22: =C22/C$42 -> #DIV/0! | E22: =D22 -> #DIV/0! | F22: =IF(AND(E22<=0),"C",IF(E22<=0.8,"A",IF(E22<=0.95,"B","C"))) -> #DIV/0! | G22: =VLOOKUP(B$22:B$42,I$22:M$42,5,0) -> #N/A | K22: =J22/J$42 -> #DIV/0! | L22: =K22 -> #DIV/0! | M22: =_xlfn.IFS(L22<80%,"A",L22<=95%,"B",L22>95%,"C") -> #DIV/0!
D23: =C23/C$42 -> #DIV/0! | E23: =D23+E22 -> #DIV/0! | F23: =IF(AND(E23<=0),"C",IF(E23<=0.8,"A",IF(E23<=0.95,"B","C"))) -> #DIV/0! | G23: =VLOOKUP(B$22:B$42,I$22:M$42,5,0) -> #N/A | K23: =J23/J$42 -> #DIV/0! | L23: =K23+L22 -> #DIV/0! | M23: =_xlfn.IFS(L23<80%,"A",L23<=95%,"B",L23>95%,"C") -> #DIV/0!
D24: =C24/C$42 -> #DIV/0! | E24: =D24+E23 -> #DIV/0! | F24: =IF(AND(E24<=0),"C",IF(E24<=0.8,"A",IF(E24<=0.95,"B","C"))) -> #DIV/0! | G24: =VLOOKUP(B$22:B$42,I$22:M$42,5,0) -> #N/A | K24: =J24/J$42 -> #DIV/0! | L24: =K24+L23 -> #DIV/0! | M24: =_xlfn.IFS(L24<80%,"A",L24<=95%,"B",L24>95%,"C") -> #DIV/0!
D25: =C25/C$42 -> #DIV/0! | E25: =D25+E24 -> #DIV/0! | F25: =IF(AND(E25<=0),"C",IF(E25<=0.8,"A",IF(E25<=0.95,"B","C"))) -> #DIV/0! | G25: =VLOOKUP(B$22:B$42,I$22:M$42,5,0) -> #N/A | K25: =J25/J$42 -> #DIV/0! | L25: =K25+L24 -> #DIV/0! | M25: =_xlfn.IFS(L25<80%,"A",L25<=95%,"B",L25>95%,"C") -> #DIV/0!
D26: =C26/C$42 -> #DIV/0! | E26: =D26+E25 -> #DIV/0! | F26: =IF(AND(E26<=0),"C",IF(E26<=0.8,"A",IF(E26<=0.95,"B","C"))) -> #DIV/0! | G26: =VLOOKUP(B$22:B$42,I$22:M$42,5,0) -> #N/A | K26: =J26/J$42 -> #DIV/0! | L26: =K26+L25 -> #DIV/0! | M26: =_xlfn.IFS(L26<80%,"A",L26<=95%,"B",L26>95%,"C") -> #DIV/0!
D27: =C27/C$42 -> #DIV/0! | E27: =D27+E26 -> #DIV/0! | F27: =IF(AND(E27<=0),"C",IF(E27<=0.8,"A",IF(E27<=0.95,"B","C"))) -> #DIV/0! | G27: =VLOOKUP(B$22:B$42,I$22:M$42,5,0) -> #N/A | K27: =J27/J$42 -> #DIV/0! | L27: =K27+L26 -> #DIV/0! | M27: =_xlfn.IFS(L27<80%,"A",L27<=95%,"B",L27>95%,"C") -> #DIV/0!
D28: =C28/C$42 -> #DIV/0! | E28: =D28+E27 -> #DIV/0! | F28: =IF(AND(E28<=0),"C",IF(E28<=0.8,"A",IF(E28<=0.95,"B","C"))) -> #DIV/0! | G28: =VLOOKUP(B$22:B$42,I$22:M$42,5,0) -> #N/A | K28: =J28/J$42 -> #DIV/0! | L28: =K28+L27 -> #DIV/0! | M28: =_xlfn.IFS(L28<80%,"A",L28<=95%,"B",L28>95%,"C") -> #DIV/0!
D29: =C29/C$42 -> #DIV/0! | E29: =D29+E28 -> #DIV/0! | F29: =IF(AND(E29<=0),"C",IF(E29<=0.8,"A",IF(E29<=0.95,"B","C"))) -> #DIV/0! | G29: =VLOOKUP(B$22:B$42,I$22:M$42,5,0) -> #N/A | K29: =J29/J$42 -> #DIV/0! | L29: =K29+L28 -> #DIV/0! | M29: =_xlfn.IFS(L29<80%,"A",L29<=95%,"B",L29>95%,"C") -> #DIV/0!
D30: =C30/C$42 -> #DIV/0! | E30: =D30+E29 -> #DIV/0! | F30: =IF(AND(E30<=0),"C",IF(E30<=0.8,"A",IF(E30<=0.95,"B","C"))) -> #DIV/0! | G30: =VLOOKUP(B$22:B$42,I$22:M$42,5,0) -> #N/A | K30: =J30/J$42 -> #DIV/0! | L30: =K30+L29 -> #DIV/0! | M30: =_xlfn.IFS(L30<80%,"A",L30<=95%,"B",L30>95%,"C") -> #DIV/0!
D31: =C31/C$42 -> #DIV/0! | E31: =D31+E30 -> #DIV/0! | F31: =IF(AND(E31<=0),"C",IF(E31<=0.8,"A",IF(E31<=0.95,"B","C"))) -> #DIV/0! | G31: =VLOOKUP(B$22:B$42,I$22:M$42,5,0) -> #N/A | K31: =J31/J$42 -> #DIV/0! | L31: =K31+L30 -> #DIV/0! | M31: =_xlfn.IFS(L31<80%,"A",L31<=95%,"B",L31>95%,"C") -> #DIV/0!
D32: =C32/C$42 -> #DIV/0! | E32: =D32+E31 -> #DIV/0! | F32: =IF(AND(E32<=0),"C",IF(E32<=0.8,"A",IF(E32<=0.95,"B","C"))) -> #DIV/0! | G32: =VLOOKUP(B$22:B$42,I$22:M$42,5,0) -> #N/A | K32: =J32/J$42 -> #DIV/0! | L32: =K32+L31 -> #DIV/0! | M32: =_xlfn.IFS(L32<80%,"A",L32<=95%,"B",L32>95%,"C") -> #DIV/0!
D33: =C33/C$42 -> #DIV/0! | E33: =D33+E32 -> #DIV/0! | F33: =IF(AND(E33<=0),"C",IF(E33<=0.8,"A",IF(E33<=0.95,"B","C"))) -> #DIV/0! | G33: =VLOOKUP(B$22:B$42,I$22:M$42,5,0) -> #N/A | K33: =J33/J$42 -> #DIV/0! | L33: =K33+L32 -> #DIV/0! | M33: =_xlfn.IFS(L33<80%,"A",L33<=95%,"B",L33>95%,"C") -> #DIV/0!
D34: =C34/C$42 -> #DIV/0! | E34: =D34+E33 -> #DIV/0! | F34: =IF(AND(E34<=0),"C",IF(E34<=0.8,"A",IF(E34<=0.95,"B","C"))) -> #DIV/0! | G34: =VLOOKUP(B$22:B$42,I$22:M$42,5,0) -> #N/A | K34: =J34/J$42 -> #DIV/0! | L34: =K34+L33 -> #DIV/0! | M34: =_xlfn.IFS(L34<80%,"A",L34<=95%,"B",L34>95%,"C") -> #DIV/0!
... D41: =C41/C$42 -> #DIV/0! | E41: =D41+E40 -> #DIV/0! | F41: =IF(AND(E41<=0),"C",IF(E41<=0.8,"A",IF(E41<=0.95,"B","C"))) -> #DIV/0! | G41: =VLOOKUP(B$22:B$42,I$22:M$42,5,0) -> #N/A | K41: =J41/J$42 -> #DIV/0! | L41: =K41+L40 -> #DIV/0! | M41: =_xlfn.IFS(L41<80%,"A",L41<=95%,"B",L41>95%,"C") -> #DIV/0!
C42: =SUM(C22:C41) -> 0 | D42: =SUM(D22:D41) -> #DIV/0! | J42: =SUM(J22:J41) -> 0 | K42: =SUM(K22:K41) -> #DIV/0!

Sheet АВС ЯНВАРЬ
B2: ОЧКИ
C3: Прибыль | D3: % прибыль | E3: Доля | F3: ABC прибыль | G3: ABC кол-во | J3: Кол-во | K3: % кол-во | L3: Доля | M3: ABC кол-во
B4: flip жел | C4: =ЯНВАРЬ!AE15 -> 31976.767 | D4: =C4/C$18 -> 0.2758861 | E4: =D4 -> 0.2758861 | F4: =IF(AND(E4<=0),"C",IF(E4<=0.8,"A",IF(E4<=0.95,"B","C"))) -> A | G4: =VLOOKUP(B$4:B$17,I$4:M$17,5,0) -> A | I4: th желт | J4: =ЯНВАРЬ!R11 -> 165 | K4: =J4/J$18 -> 0.31190926 | L4: =K4 -> 0.31190926 | M4: =_xlfn.IFS(L4<80%,"A",L4<=95%,"B",L4>95%,"C") -> A
B5: th желт | C5: =ЯНВАРЬ!AE11 -> 29547.598 | D5: =C5/C$18 -> 0.25492795 | E5: =D5+E4 -> 0.53081405 | F5: =IF(AND(E5<=0),"C",IF(E5<=0.8,"A",IF(E5<=0.95,"B","C"))) -> A | G5: =VLOOKUP(B$4:B$17,I$4:M$17,5,0) -> A | I5: flip жел | J5: =ЯНВАРЬ!R15 -> 161 | K5: =J5/J$18 -> 0.30434783 | L5: =K5+L4 -> 0.61625709 | M5: =_xlfn.IFS(L5<80%,"A",L5<=95%,"B",L5>95%,"C") -> A
B6: qs желтые | C6: =ЯНВАРЬ!AE6 -> 21761.169 | D6: =C6/C$18 -> 0.18774894 | E6: =D6+E5 -> 0.718563 | F6: =IF(AND(E6<=0),"C",IF(E6<=0.8,"A",IF(E6<=0.95,"B","C"))) -> A | G6: =VLOOKUP(B$4:B$17,I$4:M$17,5,0) -> A | I6: qs желтые | J6: =ЯНВАРЬ!R6 -> 82 | K6: =J6/J$18 -> 0.15500945 | L6: =K6+L5 -> 0.77126654 | M6: =_xlfn.IFS(L6<80%,"A",L6<=95%,"B",L6>95%,"C") -> A
B7: qs черные | C7: =ЯНВАРЬ!AE4 -> 10617.275 | D7: =C7/C$18 -> 0.091602712 | E7: =D7+E6 -> 0.81016571 | F7: =IF(AND(E7<=0),"C",IF(E7<=0.8,"A",IF(E7<=0.95,"B","C"))) -> B | G7: =VLOOKUP(B$4:B$17,I$4:M$17,5,0) -> C | I7: qs коричневые | J7: =ЯНВАРЬ!R7 -> 45 | K7: =J7/J$18 -> 0.085066163 | L7: =K7+L6 -> 0.8563327 | M7: =_xlfn.IFS(L7<80%,"A",L7<=95%,"B",L7>95%,"C") -> B
B8: qs коричневые | C8: =ЯНВАРЬ!AE7 -> 9789.4777 | D8: =C8/C$18 -> 0.084460723 | E8: =D8+E7 -> 0.89462643 | F8: =IF(AND(E8<=0),"C",IF(E8<=0.8,"A",IF(E8<=0.95,"B","C"))) -> B | G8: =VLOOKUP(B$4:B$17,I$4:M$17,5,0) -> B | I8: MR8854 C2 | J8: =ЯНВАРЬ!R8 -> 31 | K8: =J8/J$18 -> 0.058601134 | L8: =K8+L7 -> 0.91493384 | M8: =_xlfn.IFS(L8<80%,"A",L8<=95%,"B",L8>95%,"C") -> B
B9: черные с железкой классика | C9: =ЯНВАРЬ!AE3 -> 6638.0745 | D9: =C9/C$18 -> 0.057271347 | E9: =D9+E8 -> 0.95189778 | F9: =IF(AND(E9<=0),"C",IF(E9<=0.8,"A",IF(E9<=0.95,"B","C"))) -> C | G9: =VLOOKUP(B$4:B$17,I$4:M$17,5,0) -> C | I9: qs черные | J9: =ЯНВАРЬ!R4 -> 19 | K9: =J9/J$18 -> 0.035916824 | L9: =K9+L8 -> 0.95085066 | M9: =_xlfn.IFS(L9<80%,"A",L9<=95%,"B",L9>95%,"C") -> C
B10: qs синие | C10: =ЯНВАРЬ!AE5 -> 4723.2726 | D10: =C10/C$18 -> 0.040751002 | E10: =D10+E9 -> 0.99264878 | F10: =IF(AND(E10<=0),"C",IF(E10<=0.8,"A",IF(E10<=0.95,"B","C"))) -> C | G10: =VLOOKUP(B$4:B$17,I$4:M$17,5,0) -> C | I10: черные с железкой классика | J10: =ЯНВАРЬ!R3 -> 15 | K10: =J10/J$18 -> 0.028355388 | L10: =K10+L9 -> 0.97920605 | M10: =_xlfn.IFS(L10<80%,"A",L10<=95%,"B",L10>95%,"C") -> C
B11: MR8854 C2 | C11: =ЯНВАРЬ!AE8 -> 4340.3483 | D11: =C11/C$18 -> 0.037447243 | E11: =D11+E10 -> 1.030096 | F11: =IF(AND(E11<=0),"C",IF(E11<=0.8,"A",IF(E11<=0.95,"B","C"))) -> C | G11: =VLOOKUP(B$4:B$17,I$4:M$17,5,0) -> B | I11: qs синие | J11: =ЯНВАРЬ!R5 -> 9 | K11: =J11/J$18 -> 0.017013233 | L11: =K11+L10 -> 0.99621928 | M11: =_xlfn.IFS(L11<80%,"A",L11<=95%,"B",L11>95%,"C") -> C
B12: th черн | C12: =ЯНВАРЬ!AE9 -> 296.72616 | D12: =C12/C$18 -> 0.0025600657 | E12: =D12+E5 -> 0.53337412 | F12: =IF(AND(E12<=0),"C",IF(E12<=0.8,"A",IF(E12<=0.95,"B","C"))) -> A | G12: =VLOOKUP(B$4:B$17,I$4:M$17,5,0) -> A | I12: th черн | J12: =ЯНВАРЬ!R9 -> 1 | K12: =J12/J$18 -> 0.0018903592 | L12: =K12+L5 -> 0.61814745 | M12: =_xlfn.IFS(L12<80%,"A",L12<=95%,"B",L12>95%,"C") -> A
B13: flip черный | C13: =ЯНВАРЬ!AE13 -> 220.16156 | D13: =C13/C$18 -> 0.001899489 | E13: =D13+E12 -> 0.53527361 | F13: =IF(AND(E13<=0),"C",IF(E13<=0.8,"A",IF(E13<=0.95,"B","C"))) -> A | G13: =VLOOKUP(B$4:B$17,I$4:M$17,5,0) -> A | I13: flip черный | J13: =ЯНВАРЬ!R13 -> 1 | K13: =J13/J$18 -> 0.0018903592 | L13: =K13+L12 -> 0.62003781 | M13: =_xlfn.IFS(L13<80%,"A",L13<=95%,"B",L13>95%,"C") -> A
B14: th коричн | C14: =ЯНВАРЬ!AE12 -> -555.84386 | D14: =C14/C$18 -> -0.0047956567 | E14: =D14+E13 -> 0.53047795 | F14: =IF(AND(E14<=0),"C",IF(E14<=0.8,"A",IF(E14<=0.95,"B","C"))) -> A | G14: =VLOOKUP(B$4:B$17,I$4:M$17,5,0) -> A | I14: th син | J14: =ЯНВАРЬ!R10 -> 0 | K14: =J14/J$18 -> 0 | L14: =K14+L13 -> 0.62003781 | M14: =_xlfn.IFS(L14<80%,"A",L14<=95%,"B",L14>95%,"C") -> A
B15: flip синий | C15: =ЯНВАРЬ!AE14 -> -607.06546 | D15: =C15/C$18 -> -0.0052375815 | E15: =D15+E14 -> 0.52524037 | F15: =IF(AND(E15<=0),"C",IF(E15<=0.8,"A",IF(E15<=0.95,"B","C"))) -> A | G15: =VLOOKUP(B$4:B$17,I$4:M$17,5,0) -> A | I15: th коричн | J15: =ЯНВАРЬ!R12 -> 0 | K15: =J15/J$18 -> 0 | L15: =K15+L14 -> 0.62003781 | M15: =_xlfn.IFS(L15<80%,"A",L15<=95%,"B",L15>95%,"C") -> A
B16: flip коричневый | C16: =ЯНВАРЬ!AE16 -> -1324.8447 | D16: =C16/C$18 -> -0.011430368 | E16: =D16+E15 -> 0.51381 | F16: =IF(AND(E16<=0),"C",IF(E16<=0.8,"A",IF(E16<=0.95,"B","C"))) -> A | G16: =VLOOKUP(B$4:B$17,I$4:M$17,5,0) -> A | I16: flip синий | J16: =ЯНВАРЬ!R14 -> 0 | K16: =J16/J$18 -> 0 | L16: =K16+L15 -> 0.62003781 | M16: =_xlfn.IFS(L16<80%,"A",L16<=95%,"B",L16>95%,"C") -> A
B17: th син | C17: =ЯНВАРЬ!AE10 -> -1517.4339 | D17: =C17/C$18 -> -0.013091971 | E17: =D17+E14 -> 0.51738598 | F17: =IF(AND(E17<=0),"C",IF(E17<=0.8,"A",IF(E17<=0.95,"B","C"))) -> A | G17: =VLOOKUP(B$4:B$17,I$4:M$17,5,0) -> A | I17: flip коричневый | J17: =ЯНВАРЬ!R16 -> 0 | K17: =J17/J$18 -> 0 | L17: =K17+L14 -> 0.62003781 | M17: =_xlfn.IFS(L17<80%,"A",L17<=95%,"B",L17>95%,"C") -> A
C18: =SUM(C4:C17) -> 115905.68 | D18: =SUM(D4:D17) -> 1 | J18: =SUM(J4:J17) -> 529 | K18: =SUM(K4:K17) -> 1
C21: Прибыль | D21: % прибыль | E21: Доля | F21: ABC прибыль | G21: ABC кол-во | J21: Кол-во | K21: % кол-во | L21: Доля | M21: ABC кол-во
D22: =C22/C$42 -> #DIV/0! | E22: =D22 -> #DIV/0! | F22: =IF(AND(E22<=0),"C",IF(E22<=0.8,"A",IF(E22<=0.95,"B","C"))) -> #DIV/0! | G22: =VLOOKUP(B$22:B$42,I$22:M$42,5,0) -> #N/A | K22: =J22/J$42 -> #DIV/0! | L22: =K22 -> #DIV/0! | M22: =_xlfn.IFS(L22<80%,"A",L22<=95%,"B",L22>95%,"C") -> #DIV/0!
D23: =C23/C$42 -> #DIV/0! | E23: =D23+E22 -> #DIV/0! | F23: =IF(AND(E23<=0),"C",IF(E23<=0.8,"A",IF(E23<=0.95,"B","C"))) -> #DIV/0! | G23: =VLOOKUP(B$22:B$42,I$22:M$42,5,0) -> #N/A | K23: =J23/J$42 -> #DIV/0! | L23: =K23+L22 -> #DIV/0! | M23: =_xlfn.IFS(L23<80%,"A",L23<=95%,"B",L23>95%,"C") -> #DIV/0!
D24: =C24/C$42 -> #DIV/0! | E24: =D24+E23 -> #DIV/0! | F24: =IF(AND(E24<=0),"C",IF(E24<=0.8,"A",IF(E24<=0.95,"B","C"))) -> #DIV/0! | G24: =VLOOKUP(B$22:B$42,I$22:M$42,5,0) -> #N/A | K24: =J24/J$42 -> #DIV/0! | L24: =K24+L23 -> #DIV/0! | M24: =_xlfn.IFS(L24<80%,"A",L24<=95%,"B",L24>95%,"C") -> #DIV/0!
D25: =C25/C$42 -> #DIV/0! | E25: =D25+E24 -> #DIV/0! | F25: =IF(AND(E25<=0),"C",IF(E25<=0.8,"A",IF(E25<=0.95,"B","C"))) -> #DIV/0! | G25: =VLOOKUP(B$22:B$42,I$22:M$42,5,0) -> #N/A | K25: =J25/J$42 -> #DIV/0! | L25: =K25+L24 -> #DIV/0! | M25: =_xlfn.IFS(L25<80%,"A",L25<=95%,"B",L25>95%,"C") -> #DIV/0!
D26: =C26/C$42 -> #DIV/0! | E26: =D26+E25 -> #DIV/0! | F26: =IF(AND(E26<=0),"C",IF(E26<=0.8,"A",IF(E26<=0.95,"B","C"))) -> #DIV/0! | G26: =VLOOKUP(B$22:B$42,I$22:M$42,5,0) -> #N/A | K26: =J26/J$42 -> #DIV/0! | L26: =K26+L25 -> #DIV/0! | M26: =_xlfn.IFS(L26<80%,"A",L26<=95%,"B",L26>95%,"C") -> #DIV/0!
D27: =C27/C$42 -> #DIV/0! | E27: =D27+E26 -> #DIV/0! | F27: =IF(AND(E27<=0),"C",IF(E27<=0.8,"A",IF(E27<=0.95,"B","C"))) -> #DIV/0! | G27: =VLOOKUP(B$22:B$42,I$22:M$42,5,0) -> #N/A | K27: =J27/J$42 -> #DIV/0! | L27: =K27+L26 -> #DIV/0! | M27: =_xlfn.IFS(L27<80%,"A",L27<=95%,"B",L27>95%,"C") -> #DIV/0!
D28: =C28/C$42 -> #DIV/0! | E28: =D28+E27 -> #DIV/0! | F28: =IF(AND(E28<=0),"C",IF(E28<=0.8,"A",IF(E28<=0.95,"B","C"))) -> #DIV/0! | G28: =VLOOKUP(B$22:B$42,I$22:M$42,5,0) -> #N/A | K28: =J28/J$42 -> #DIV/0! | L28: =K28+L27 -> #DIV/0! | M28: =_xlfn.IFS(L28<80%,"A",L28<=95%,"B",L28>95%,"C") -> #DIV/0!
D29: =C29/C$42 -> #DIV/0! | E29: =D29+E28 -> #DIV/0! | F29: =IF(AND(E29<=0),"C",IF(E29<=0.8,"A",IF(E29<=0.95,"B","C"))) -> #DIV/0! | G29: =VLOOKUP(B$22:B$42,I$22:M$42,5,0) -> #N/A | K29: =J29/J$42 -> #DIV/0! | L29: =K29+L28 -> #DIV/0! | M29: =_xlfn.IFS(L29<80%,"A",L29<=95%,"B",L29>95%,"C") -> #DIV/0!
D30: =C30/C$42 -> #DIV/0! | E30: =D30+E29 -> #DIV/0! | F30: =IF(AND(E30<=0),"C",IF(E30<=0.8,"A",IF(E30<=0.95,"B","C"))) -> #DIV/0! | G30: =VLOOKUP(B$22:B$42,I$22:M$42,5,0) -> #N/A | K30: =J30/J$42 -> #DIV/0! | L30: =K30+L29 -> #DIV/0! | M30: =_xlfn.IFS(L30<80%,"A",L30<=95%,"B",L30>95%,"C") -> #DIV/0!
D31: =C31/C$42 -> #DIV/0! | E31: =D31+E30 -> #DIV/0! | F31: =IF(AND(E31<=0),"C",IF(E31<=0.8,"A",IF(E31<=0.95,"B","C"))) -> #DIV/0! | G31: =VLOOKUP(B$22:B$42,I$22:M$42,5,0) -> #N/A | K31: =J31/J$42 -> #DIV/0! | L31: =K31+L30 -> #DIV/0! | M31: =_xlfn.IFS(L31<80%,"A",L31<=95%,"B",L31>95%,"C") -> #DIV/0!
D32: =C32/C$42 -> #DIV/0! | E32: =D32+E31 -> #DIV/0! | F32: =IF(AND(E32<=0),"C",IF(E32<=0.8,"A",IF(E32<=0.95,"B","C"))) -> #DIV/0! | G32: =VLOOKUP(B$22:B$42,I$22:M$42,5,0) -> #N/A | K32: =J32/J$42 -> #DIV/0! | L32: =K32+L31 -> #DIV/0! | M32: =_xlfn.IFS(L32<80%,"A",L32<=95%,"B",L32>95%,"C") -> #DIV/0!
D33: =C33/C$42 -> #DIV/0! | E33: =D33+E32 -> #DIV/0! | F33: =IF(AND(E33<=0),"C",IF(E33<=0.8,"A",IF(E33<=0.95,"B","C"))) -> #DIV/0! | G33: =VLOOKUP(B$22:B$42,I$22:M$42,5,0) -> #N/A | K33: =J33/J$42 -> #DIV/0! | L33: =K33+L32 -> #DIV/0! | M33: =_xlfn.IFS(L33<80%,"A",L33<=95%,"B",L33>95%,"C") -> #DIV/0!
D34: =C34/C$42 -> #DIV/0! | E34: =D34+E33 -> #DIV/0! | F34: =IF(AND(E34<=0),"C",IF(E34<=0.8,"A",IF(E34<=0.95,"B","C"))) -> #DIV/0! | G34: =VLOOKUP(B$22:B$42,I$22:M$42,5,0) -> #N/A | K34: =J34/J$42 -> #DIV/0! | L34: =K34+L33 -> #DIV/0! | M34: =_xlfn.IFS(L34<80%,"A",L34<=95%,"B",L34>95%,"C") -> #DIV/0!
... D41: =C41/C$42 -> #DIV/0! | E41: =D41+E40 -> #DIV/0! | F41: =IF(AND(E41<=0),"C",IF(E41<=0.8,"A",IF(E41<=0.95,"B","C"))) -> #DIV/0! | G41: =VLOOKUP(B$22:B$42,I$22:M$42,5,0) -> #N/A | K41: =J41/J$42 -> #DIV/0! | L41: =K41+L40 -> #DIV/0! | M41: =_xlfn.IFS(L41<80%,"A",L41<=95%,"B",L41>95%,"C") -> #DIV/0!
C42: =SUM(C22:C41) -> 0 | D42: =SUM(D22:D41) -> #DIV/0! | J42: =SUM(J22:J41) -> 0 | K42: =SUM(K22:K41) -> #DIV/0!

Sheet АВС 26.01-01.02
B2: ОЧКИ
C3: Прибыль | D3: % прибыль | E3: Доля | F3: ABC прибыль | G3: ABC кол-во | J3: Кол-во | K3: % кол-во | L3: Доля | M3: ABC кол-во
B4: th желт | C4: ='Юнит 26.01-01.02'!AE11 -> 16111.061 | D4: =C4/C$18 -> 0.51770375 | E4: =D4 -> 0.51770375 | F4: =IF(AND(E4<=0),"C",IF(E4<=0.8,"A",IF(E4<=0.95,"B","C"))) -> A | G4: =VLOOKUP(B$4:B$17,I$4:M$17,5,0) -> A | I4: th желт | J4: ='Юнит 26.01-01.02'!R11 -> 48 | K4: =J4/J$18 -> 0.375 | L4: =K4 -> 0.375 | M4: =_xlfn.IFS(L4<80%,"A",L4<=95%,"B",L4>95%,"C") -> A
B5: flip жел | C5: ='Юнит 26.01-01.02'!AE15 -> 11558.881 | D5: =C5/C$18 -> 0.37142657 | E5: =D5+E4 -> 0.88913032 | F5: =IF(AND(E5<=0),"C",IF(E5<=0.8,"A",IF(E5<=0.95,"B","C"))) -> B | G5: =VLOOKUP(B$4:B$17,I$4:M$17,5,0) -> A | I5: flip жел | J5: ='Юнит 26.01-01.02'!R15 -> 38 | K5: =J5/J$18 -> 0.296875 | L5: =K5+L4 -> 0.671875 | M5: =_xlfn.IFS(L5<80%,"A",L5<=95%,"B",L5>95%,"C") -> A
B6: qs черные | C6: ='Юнит 26.01-01.02'!AE4 -> 3322.05 | D6: =C6/C$18 -> 0.10674888 | E6: =D6+E5 -> 0.9958792 | F6: =IF(AND(E6<=0),"C",IF(E6<=0.8,"A",IF(E6<=0.95,"B","C"))) -> C | G6: =VLOOKUP(B$4:B$17,I$4:M$17,5,0) -> C | I6: qs коричневые | J6: ='Юнит 26.01-01.02'!R7 -> 16 | K6: =J6/J$18 -> 0.125 | L6: =K6+L5 -> 0.796875 | M6: =_xlfn.IFS(L6<80%,"A",L6<=95%,"B",L6>95%,"C") -> A
B7: MR8854 C2 | C7: ='Юнит 26.01-01.02'!AE8 -> 1849.5272 | D7: =C7/C$18 -> 0.059431665 | E7: =D7+E6 -> 1.0553109 | F7: =IF(AND(E7<=0),"C",IF(E7<=0.8,"A",IF(E7<=0.95,"B","C"))) -> C | G7: =VLOOKUP(B$4:B$17,I$4:M$17,5,0) -> B | I7: MR8854 C2 | J7: ='Юнит 26.01-01.02'!R8 -> 10 | K7: =J7/J$18 -> 0.078125 | L7: =K7+L6 -> 0.875 | M7: =_xlfn.IFS(L7<80%,"A",L7<=95%,"B",L7>95%,"C") -> B
B8: qs желтые | C8: ='Юнит 26.01-01.02'!AE6 -> 1191.36 | D8: =C8/C$18 -> 0.038282491 | E8: =D8+E7 -> 1.0935934 | F8: =IF(AND(E8<=0),"C",IF(E8<=0.8,"A",IF(E8<=0.95,"B","C"))) -> C | G8: =VLOOKUP(B$4:B$17,I$4:M$17,5,0) -> B | I8: qs желтые | J8: ='Юнит 26.01-01.02'!R6 -> 6 | K8: =J8/J$18 -> 0.046875 | L8: =K8+L7 -> 0.921875 | M8: =_xlfn.IFS(L8<80%,"A",L8<=95%,"B",L8>95%,"C") -> B
B9: th коричн | C9: ='Юнит 26.01-01.02'!AE12 -> 291.34614 | D9: =C9/C$18 -> 0.0093619527 | E9: =D9+E8 -> 1.1029553 | F9: =IF(AND(E9<=0),"C",IF(E9<=0.8,"A",IF(E9<=0.95,"B","C"))) -> C | G9: =VLOOKUP(B$4:B$17,I$4:M$17,5,0) -> A | I9: qs черные | J9: ='Юнит 26.01-01.02'!R4 -> 5 | K9: =J9/J$18 -> 0.0390625 | L9: =K9+L8 -> 0.9609375 | M9: =_xlfn.IFS(L9<80%,"A",L9<=95%,"B",L9>95%,"C") -> C
B10: th черн | C10: ='Юнит 26.01-01.02'!AE9 -> 284.37054 | D10: =C10/C$18 -> 0.0091378028 | E10: =D10+E9 -> 1.1120931 | F10: =IF(AND(E10<=0),"C",IF(E10<=0.8,"A",IF(E10<=0.95,"B","C"))) -> C | G10: =VLOOKUP(B$4:B$17,I$4:M$17,5,0) -> C | I10: черные с железкой классика | J10: ='Юнит 26.01-01.02'!R3 -> 1 | K10: =J10/J$18 -> 0.0078125 | L10: =K10+L9 -> 0.96875 | M10: =_xlfn.IFS(L10<80%,"A",L10<=95%,"B",L10>95%,"C") -> C
B11: flip черный | C11: ='Юнит 26.01-01.02'!AE13 -> 207.80595 | D11: =C11/C$18 -> 0.0066775192 | E11: =D11+E10 -> 1.1187706 | F11: =IF(AND(E11<=0),"C",IF(E11<=0.8,"A",IF(E11<=0.95,"B","C"))) -> C | G11: =VLOOKUP(B$4:B$17,I$4:M$17,5,0) -> A | I11: th черн | J11: ='Юнит 26.01-01.02'!R9 -> 1 | K11: =J11/J$18 -> 0.0078125 | L11: =K11+L10 -> 0.9765625 | M11: =_xlfn.IFS(L11<80%,"A",L11<=95%,"B",L11>95%,"C") -> C
B12: черные с железкой классика | C12: ='Юнит 26.01-01.02'!AE3 -> 152.11 | D12: =C12/C$18 -> 0.004887817 | E12: =D12+E5 -> 0.89401814 | F12: =IF(AND(E12<=0),"C",IF(E12<=0.8,"A",IF(E12<=0.95,"B","C"))) -> B | G12: =VLOOKUP(B$4:B$17,I$4:M$17,5,0) -> C | I12: th син | J12: ='Юнит 26.01-01.02'!R10 -> 1 | K12: =J12/J$18 -> 0.0078125 | L12: =K12+L5 -> 0.6796875 | M12: =_xlfn.IFS(L12<80%,"A",L12<=95%,"B",L12>95%,"C") -> A
B13: qs синие | C13: ='Юнит 26.01-01.02'!AE5 -> 0 | D13: =C13/C$18 -> 0 | E13: =D13+E12 -> 0.89401814 | F13: =IF(AND(E13<=0),"C",IF(E13<=0.8,"A",IF(E13<=0.95,"B","C"))) -> B | G13: =VLOOKUP(B$4:B$17,I$4:M$17,5,0) -> A | I13: th коричн | J13: ='Юнит 26.01-01.02'!R12 -> 1 | K13: =J13/J$18 -> 0.0078125 | L13: =K13+L12 -> 0.6875 | M13: =_xlfn.IFS(L13<80%,"A",L13<=95%,"B",L13>95%,"C") -> A
B14: qs коричневые | C14: ='Юнит 26.01-01.02'!AE7 -> -472.79957 | D14: =C14/C$18 -> -0.015192675 | E14: =D14+E13 -> 0.87882546 | F14: =IF(AND(E14<=0),"C",IF(E14<=0.8,"A",IF(E14<=0.95,"B","C"))) -> B | G14: =VLOOKUP(B$4:B$17,I$4:M$17,5,0) -> A | I14: flip черный | J14: ='Юнит 26.01-01.02'!R13 -> 1 | K14: =J14/J$18 -> 0.0078125 | L14: =K14+L13 -> 0.6953125 | M14: =_xlfn.IFS(L14<80%,"A",L14<=95%,"B",L14>95%,"C") -> A
B15: flip синий | C15: ='Юнит 26.01-01.02'!AE14 -> -807.06546 | D15: =C15/C$18 -> -0.025933786 | E15: =D15+E14 -> 0.85289167 | F15: =IF(AND(E15<=0),"C",IF(E15<=0.8,"A",IF(E15<=0.95,"B","C"))) -> B | G15: =VLOOKUP(B$4:B$17,I$4:M$17,5,0) -> A | I15: qs синие | J15: ='Юнит 26.01-01.02'!R5 -> 0 | K15: =J15/J$18 -> 0 | L15: =K15+L14 -> 0.6953125 | M15: =_xlfn.IFS(L15<80%,"A",L15<=95%,"B",L15>95%,"C") -> A
B16: th син | C16: ='Юнит 26.01-01.02'!AE10 -> -963.6769 | D16: =C16/C$18 -> -0.03096625 | E16: =D16+E15 -> 0.82192542 | F16: =IF(AND(E16<=0),"C",IF(E16<=0.8,"A",IF(E16<=0.95,"B","C"))) -> B | G16: =VLOOKUP(B$4:B$17,I$4:M$17,5,0) -> A | I16: flip синий | J16: ='Юнит 26.01-01.02'!R14 -> 0 | K16: =J16/J$18 -> 0 | L16: =K16+L15 -> 0.6953125 | M16: =_xlfn.IFS(L16<80%,"A",L16<=95%,"B",L16>95%,"C") -> A
B17: flip коричневый | C17: ='Юнит 26.01-01.02'!AE16 -> -1604.7377 | D17: =C17/C$18 -> -0.051565737 | E17: =D17+E14 -> 0.82725972 | F17: =IF(AND(E17<=0),"C",IF(E17<=0.8,"A",IF(E17<=0.95,"B","C"))) -> B | G17: =VLOOKUP(B$4:B$17,I$4:M$17,5,0) -> A | I17: flip коричневый | J17: ='Юнит 26.01-01.02'!R16 -> 0 | K17: =J17/J$18 -> 0 | L17: =K17+L14 -> 0.6953125 | M17: =_xlfn.IFS(L17<80%,"A",L17<=95%,"B",L17>95%,"C") -> A
C18: =SUM(C4:C17) -> 31120.232 | D18: =SUM(D4:D17) -> 1 | J18: =SUM(J4:J17) -> 128 | K18: =SUM(K4:K17) -> 1
C21: Прибыль | D21: % прибыль | E21: Доля | F21: ABC прибыль | G21: ABC кол-во | J21: Кол-во | K21: % кол-во | L21: Доля | M21: ABC кол-во
D22: =C22/C$42 -> #DIV/0! | E22: =D22 -> #DIV/0! | F22: =IF(AND(E22<=0),"C",IF(E22<=0.8,"A",IF(E22<=0.95,"B","C"))) -> #DIV/0! | G22: =VLOOKUP(B$22:B$42,I$22:M$42,5,0) -> #N/A | K22: =J22/J$42 -> #DIV/0! | L22: =K22 -> #DIV/0! | M22: =_xlfn.IFS(L22<80%,"A",L22<=95%,"B",L22>95%,"C") -> #DIV/0!
D23: =C23/C$42 -> #DIV/0! | E23: =D23+E22 -> #DIV/0! | F23: =IF(AND(E23<=0),"C",IF(E23<=0.8,"A",IF(E23<=0.95,"B","C"))) -> #DIV/0! | G23: =VLOOKUP(B$22:B$42,I$22:M$42,5,0) -> #N/A | K23: =J23/J$42 -> #DIV/0! | L23: =K23+L22 -> #DIV/0! | M23: =_xlfn.IFS(L23<80%,"A",L23<=95%,"B",L23>95%,"C") -> #DIV/0!
D24: =C24/C$42 -> #DIV/0! | E24: =D24+E23 -> #DIV/0! | F24: =IF(AND(E24<=0),"C",IF(E24<=0.8,"A",IF(E24<=0.95,"B","C"))) -> #DIV/0! | G24: =VLOOKUP(B$22:B$42,I$22:M$42,5,0) -> #N/A | K24: =J24/J$42 -> #DIV/0! | L24: =K24+L23 -> #DIV/0! | M24: =_xlfn.IFS(L24<80%,"A",L24<=95%,"B",L24>95%,"C") -> #DIV/0!
D25: =C25/C$42 -> #DIV/0! | E25: =D25+E24 -> #DIV/0! | F25: =IF(AND(E25<=0),"C",IF(E25<=0.8,"A",IF(E25<=0.95,"B","C"))) -> #DIV/0! | G25: =VLOOKUP(B$22:B$42,I$22:M$42,5,0) -> #N/A | K25: =J25/J$42 -> #DIV/0! | L25: =K25+L24 -> #DIV/0! | M25: =_xlfn.IFS(L25<80%,"A",L25<=95%,"B",L25>95%,"C") -> #DIV/0!
D26: =C26/C$42 -> #DIV/0! | E26: =D26+E25 -> #DIV/0! | F26: =IF(AND(E26<=0),"C",IF(E26<=0.8,"A",IF(E26<=0.95,"B","C"))) -> #DIV/0! | G26: =VLOOKUP(B$22:B$42,I$22:M$42,5,0) -> #N/A | K26: =J26/J$42 -> #DIV/0! | L26: =K26+L25 -> #DIV/0! | M26: =_xlfn.IFS(L26<80%,"A",L26<=95%,"B",L26>95%,"C") -> #DIV/0!
D27: =C27/C$42 -> #DIV/0! | E27: =D27+E26 -> #DIV/0! | F27: =IF(AND(E27<=0),"C",IF(E27<=0.8,"A",IF(E27<=0.95,"B","C"))) -> #DIV/0! | G27: =VLOOKUP(B$22:B$42,I$22:M$42,5,0) -> #N/A | K27: =J27/J$42 -> #DIV/0! | L27: =K27+L26 -> #DIV/0! | M27: =_xlfn.IFS(L27<80%,"A",L27<=95%,"B",L27>95%,"C") -> #DIV/0!
D28: =C28/C$42 -> #DIV/0! | E28: =D28+E27 -> #DIV/0! | F28: =IF(AND(E28<=0),"C",IF(E28<=0.8,"A",IF(E28<=0.95,"B","C"))) -> #DIV/0! | G28: =VLOOKUP(B$22:B$42,I$22:M$42,5,0) -> #N/A | K28: =J28/J$42 -> #DIV/0! | L28: =K28+L27 -> #DIV/0! | M28: =_xlfn.IFS(L28<80%,"A",L28<=95%,"B",L28>95%,"C") -> #DIV/0!
D29: =C29/C$42 -> #DIV/0! | E29: =D29+E28 -> #DIV/0! | F29: =IF(AND(E29<=0),"C",IF(E29<=0.8,"A",IF(E29<=0.95,"B","C"))) -> #DIV/0! | G29: =VLOOKUP(B$22:B$42,I$22:M$42,5,0) -> #N/A | K29: =J29/J$42 -> #DIV/0! | L29: =K29+L28 -> #DIV/0! | M29: =_xlfn.IFS(L29<80%,"A",L29<=95%,"B",L29>95%,"C") -> #DIV/0!
D30: =C30/C$42 -> #DIV/0! | E30: =D30+E29 -> #DIV/0! | F30: =IF(AND(E30<=0),"C",IF(E30<=0.8,"A",IF(E30<=0.95,"B","C"))) -> #DIV/0! | G30: =VLOOKUP(B$22:B$42,I$22:M$42,5,0) -> #N/A | K30: =J30/J$42 -> #DIV/0! | L30: =K30+L29 -> #DIV/0! | M30: =_xlfn.IFS(L30<80%,"A",L30<=95%,"B",L30>95%,"C") -> #DIV/0!
D31: =C31/C$42 -> #DIV/0! | E31: =D31+E30 -> #DIV/0! | F31: =IF(AND(E31<=0),"C",IF(E31<=0.8,"A",IF(E31<=0.95,"B","C"))) -> #DIV/0! | G31: =VLOOKUP(B$22:B$42,I$22:M$42,5,0) -> #N/A | K31: =J31/J$42 -> #DIV/0! | L31: =K31+L30 -> #DIV/0! | M31: =_xlfn.IFS(L31<80%,"A",L31<=95%,"B",L31>95%,"C") -> #DIV/0!
D32: =C32/C$42 -> #DIV/0! | E32: =D32+E31 -> #DIV/0! | F32: =IF(AND(E32<=0),"C",IF(E32<=0.8,"A",IF(E32<=0.95,"B","C"))) -> #DIV/0! | G32: =VLOOKUP(B$22:B$42,I$22:M$42,5,0) -> #N/A | K32: =J32/J$42 -> #DIV/0! | L32: =K32+L31 -> #DIV/0! | M32: =_xlfn.IFS(L32<80%,"A",L32<=95%,"B",L32>95%,"C") -> #DIV/0!
D33: =C33/C$42 -> #DIV/0! | E33: =D33+E32 -> #DIV/0! | F33: =IF(AND(E33<=0),"C",IF(E33<=0.8,"A",IF(E33<=0.95,"B","C"))) -> #DIV/0! | G33: =VLOOKUP(B$22:B$42,I$22:M$42,5,0) -> #N/A | K33: =J33/J$42 -> #DIV/0! | L33: =K33+L32 -> #DIV/0! | M33: =_xlfn.IFS(L33<80%,"A",L33<=95%,"B",L33>95%,"C") -> #DIV/0!
D34: =C34/C$42 -> #DIV/0! | E34: =D34+E33 -> #DIV/0! | F34: =IF(AND(E34<=0),"C",IF(E34<=0.8,"A",IF(E34<=0.95,"B","C"))) -> #DIV/0! | G34: =VLOOKUP(B$22:B$42,I$22:M$42,5,0) -> #N/A | K34: =J34/J$42 -> #DIV/0! | L34: =K34+L33 -> #DIV/0! | M34: =_xlfn.IFS(L34<80%,"A",L34<=95%,"B",L34>95%,"C") -> #DIV/0!
... D41: =C41/C$42 -> #DIV/0! | E41: =D41+E40 -> #DIV/0! | F41: =IF(AND(E41<=0),"C",IF(E41<=0.8,"A",IF(E41<=0.95,"B","C"))) -> #DIV/0! | G41: =VLOOKUP(B$22:B$42,I$22:M$42,5,0) -> #N/A | K41: =J41/J$42 -> #DIV/0! | L41: =K41+L40 -> #DIV/0! | M41: =_xlfn.IFS(L41<80%,"A",L41<=95%,"B",L41>95%,"C") -> #DIV/0!
C42: =SUM(C22:C41) -> 0 | D42: =SUM(D22:D41) -> #DIV/0! | J42: =SUM(J22:J41) -> 0 | K42: =SUM(K22:K41) -> #DIV/0!

Sheet АВС 19-25.01
B2: ОЧКИ
C3: Прибыль | D3: % прибыль | E3: Доля | F3: ABC прибыль | G3: ABC кол-во | J3: Кол-во | K3: % кол-во | L3: Доля | M3: ABC кол-во
B4: qs желтые | C4: ='Юнит 19-25.01'!AE6 -> 10158.92 | D4: =C4/C$18 -> 0.52787056 | E4: =D4 -> 0.52787056 | F4: =IF(AND(E4<=0),"C",IF(E4<=0.8,"A",IF(E4<=0.95,"B","C"))) -> A | G4: =VLOOKUP(B$4:B$17,I$4:M$17,5,0) -> A | I4: th желт | J4: ='Юнит 19-25.01'!R11 -> 26 | K4: =J4/J$18 -> 0.29213483 | L4: =K4 -> 0.29213483 | M4: =_xlfn.IFS(L4<80%,"A",L4<=95%,"B",L4>95%,"C") -> A
B5: qs черные | C5: ='Юнит 19-25.01'!AE4 -> 4879.4517 | D5: =C5/C$18 -> 0.25354259 | E5: =D5+E4 -> 0.78141315 | F5: =IF(AND(E5<=0),"C",IF(E5<=0.8,"A",IF(E5<=0.95,"B","C"))) -> A | G5: =VLOOKUP(B$4:B$17,I$4:M$17,5,0) -> B | I5: qs желтые | J5: ='Юнит 19-25.01'!R6 -> 18 | K5: =J5/J$18 -> 0.20224719 | L5: =K5+L4 -> 0.49438202 | M5: =_xlfn.IFS(L5<80%,"A",L5<=95%,"B",L5>95%,"C") -> A
B6: черные с железкой классика | C6: ='Юнит 19-25.01'!AE3 -> 3054.91 | D6: =C6/C$18 -> 0.15873706 | E6: =D6+E5 -> 0.94015021 | F6: =IF(AND(E6<=0),"C",IF(E6<=0.8,"A",IF(E6<=0.95,"B","C"))) -> B | G6: =VLOOKUP(B$4:B$17,I$4:M$17,5,0) -> B | I6: flip жел | J6: ='Юнит 19-25.01'!R15 -> 17 | K6: =J6/J$18 -> 0.19101124 | L6: =K6+L5 -> 0.68539326 | M6: =_xlfn.IFS(L6<80%,"A",L6<=95%,"B",L6>95%,"C") -> A
B7: qs синие | C7: ='Юнит 19-25.01'!AE5 -> 2087.12 | D7: =C7/C$18 -> 0.10844944 | E7: =D7+E6 -> 1.0485997 | F7: =IF(AND(E7<=0),"C",IF(E7<=0.8,"A",IF(E7<=0.95,"B","C"))) -> C | G7: =VLOOKUP(B$4:B$17,I$4:M$17,5,0) -> C | I7: qs коричневые | J7: ='Юнит 19-25.01'!R7 -> 10 | K7: =J7/J$18 -> 0.11235955 | L7: =K7+L6 -> 0.79775281 | M7: =_xlfn.IFS(L7<80%,"A",L7<=95%,"B",L7>95%,"C") -> A
B8: qs коричневые | C8: ='Юнит 19-25.01'!AE7 -> 1636.0082 | D8: =C8/C$18 -> 0.085009092 | E8: =D8+E7 -> 1.1336087 | F8: =IF(AND(E8<=0),"C",IF(E8<=0.8,"A",IF(E8<=0.95,"B","C"))) -> C | G8: =VLOOKUP(B$4:B$17,I$4:M$17,5,0) -> A | I8: qs черные | J8: ='Юнит 19-25.01'!R4 -> 7 | K8: =J8/J$18 -> 0.078651685 | L8: =K8+L7 -> 0.87640449 | M8: =_xlfn.IFS(L8<80%,"A",L8<=95%,"B",L8>95%,"C") -> B
B9: th желт | C9: ='Юнит 19-25.01'!AE11 -> 2661.2441 | D9: =C9/C$18 -> 0.13828167 | E9: =D9+E8 -> 1.2718904 | F9: =IF(AND(E9<=0),"C",IF(E9<=0.8,"A",IF(E9<=0.95,"B","C"))) -> C | G9: =VLOOKUP(B$4:B$17,I$4:M$17,5,0) -> A | I9: черные с железкой классика | J9: ='Юнит 19-25.01'!R3 -> 5 | K9: =J9/J$18 -> 0.056179775 | L9: =K9+L8 -> 0.93258427 | M9: =_xlfn.IFS(L9<80%,"A",L9<=95%,"B",L9>95%,"C") -> B
B10: th черн | C10: ='Юнит 19-25.01'!AE9 -> 0 | D10: =C10/C$18 -> 0 | E10: =D10+E9 -> 1.2718904 | F10: =IF(AND(E10<=0),"C",IF(E10<=0.8,"A",IF(E10<=0.95,"B","C"))) -> C | G10: =VLOOKUP(B$4:B$17,I$4:M$17,5,0) -> A | I10: qs синие | J10: ='Юнит 19-25.01'!R5 -> 3 | K10: =J10/J$18 -> 0.033707865 | L10: =K10+L9 -> 0.96629213 | M10: =_xlfn.IFS(L10<80%,"A",L10<=95%,"B",L10>95%,"C") -> C
B11: th син | C11: ='Юнит 19-25.01'!AE10 -> 0 | D11: =C11/C$18 -> 0 | E11: =D11+E10 -> 1.2718904 | F11: =IF(AND(E11<=0),"C",IF(E11<=0.8,"A",IF(E11<=0.95,"B","C"))) -> C | G11: =VLOOKUP(B$4:B$17,I$4:M$17,5,0) -> A | I11: MR8854 C2 | J11: ='Юнит 19-25.01'!R8 -> 3 | K11: =J11/J$18 -> 0.033707865 | L11: =K11+L10 -> 1 | M11: =_xlfn.IFS(L11<80%,"A",L11<=95%,"B",L11>95%,"C") -> C
B12: th коричн | C12: ='Юнит 19-25.01'!AE12 -> 0 | D12: =C12/C$18 -> 0 | E12: =D12+E5 -> 0.78141315 | F12: =IF(AND(E12<=0),"C",IF(E12<=0.8,"A",IF(E12<=0.95,"B","C"))) -> A | G12: =VLOOKUP(B$4:B$17,I$4:M$17,5,0) -> A | I12: th черн | J12: ='Юнит 19-25.01'!R9 -> 0 | K12: =J12/J$18 -> 0 | L12: =K12+L5 -> 0.49438202 | M12: =_xlfn.IFS(L12<80%,"A",L12<=95%,"B",L12>95%,"C") -> A
B13: flip черный | C13: ='Юнит 19-25.01'!AE13 -> 0 | D13: =C13/C$18 -> 0 | E13: =D13+E12 -> 0.78141315 | F13: =IF(AND(E13<=0),"C",IF(E13<=0.8,"A",IF(E13<=0.95,"B","C"))) -> A | G13: =VLOOKUP(B$4:B$17,I$4:M$17,5,0) -> A | I13: th син | J13: ='Юнит 19-25.01'!R10 -> 0 | K13: =J13/J$18 -> 0 | L13: =K13+L12 -> 0.49438202 | M13: =_xlfn.IFS(L13<80%,"A",L13<=95%,"B",L13>95%,"C") -> A
B14: flip синий | C14: ='Юнит 19-25.01'!AE14 -> 0 | D14: =C14/C$18 -> 0 | E14: =D14+E13 -> 0.78141315 | F14: =IF(AND(E14<=0),"C",IF(E14<=0.8,"A",IF(E14<=0.95,"B","C"))) -> A | G14: =VLOOKUP(B$4:B$17,I$4:M$17,5,0) -> A | I14: th коричн | J14: ='Юнит 19-25.01'!R12 -> 0 | K14: =J14/J$18 -> 0 | L14: =K14+L13 -> 0.49438202 | M14: =_xlfn.IFS(L14<80%,"A",L14<=95%,"B",L14>95%,"C") -> A
B15: flip коричневый | C15: ='Юнит 19-25.01'!AE16 -> 0 | D15: =C15/C$18 -> 0 | E15: =D15+E14 -> 0.78141315 | F15: =IF(AND(E15<=0),"C",IF(E15<=0.8,"A",IF(E15<=0.95,"B","C"))) -> A | G15: =VLOOKUP(B$4:B$17,I$4:M$17,5,0) -> A | I15: flip черный | J15: ='Юнит 19-25.01'!R13 -> 0 | K15: =J15/J$18 -> 0 | L15: =K15+L14 -> 0.49438202 | M15: =_xlfn.IFS(L15<80%,"A",L15<=95%,"B",L15>95%,"C") -> A
B16: MR8854 C2 | C16: ='Юнит 19-25.01'!AE8 -> -789.58498 | D16: =C16/C$18 -> -0.041027852 | E16: =D16+E15 -> 0.7403853 | F16: =IF(AND(E16<=0),"C",IF(E16<=0.8,"A",IF(E16<=0.95,"B","C"))) -> A | G16: =VLOOKUP(B$4:B$17,I$4:M$17,5,0) -> C | I16: flip синий | J16: ='Юнит 19-25.01'!R14 -> 0 | K16: =J16/J$18 -> 0 | L16: =K16+L15 -> 0.49438202 | M16: =_xlfn.IFS(L16<80%,"A",L16<=95%,"B",L16>95%,"C") -> A
B17: flip жел | C17: ='Юнит 19-25.01'!AE15 -> -4442.9723 | D17: =C17/C$18 -> -0.23086256 | E17: =D17+E14 -> 0.55055059 | F17: =IF(AND(E17<=0),"C",IF(E17<=0.8,"A",IF(E17<=0.95,"B","C"))) -> A | G17: =VLOOKUP(B$4:B$17,I$4:M$17,5,0) -> A | I17: flip коричневый | J17: ='Юнит 19-25.01'!R16 -> 0 | K17: =J17/J$18 -> 0 | L17: =K17+L14 -> 0.49438202 | M17: =_xlfn.IFS(L17<80%,"A",L17<=95%,"B",L17>95%,"C") -> A
C18: =SUM(C4:C17) -> 19245.097 | D18: =SUM(D4:D17) -> 1 | J18: =SUM(J4:J17) -> 89 | K18: =SUM(K4:K17) -> 1
C21: Прибыль | D21: % прибыль | E21: Доля | F21: ABC прибыль | G21: ABC кол-во | J21: Кол-во | K21: % кол-во | L21: Доля | M21: ABC кол-во
D22: =C22/C$42 -> #DIV/0! | E22: =D22 -> #DIV/0! | F22: =IF(AND(E22<=0),"C",IF(E22<=0.8,"A",IF(E22<=0.95,"B","C"))) -> #DIV/0! | G22: =VLOOKUP(B$22:B$42,I$22:M$42,5,0) -> #N/A | K22: =J22/J$42 -> #DIV/0! | L22: =K22 -> #DIV/0! | M22: =_xlfn.IFS(L22<80%,"A",L22<=95%,"B",L22>95%,"C") -> #DIV/0!
D23: =C23/C$42 -> #DIV/0! | E23: =D23+E22 -> #DIV/0! | F23: =IF(AND(E23<=0),"C",IF(E23<=0.8,"A",IF(E23<=0.95,"B","C"))) -> #DIV/0! | G23: =VLOOKUP(B$22:B$42,I$22:M$42,5,0) -> #N/A | K23: =J23/J$42 -> #DIV/0! | L23: =K23+L22 -> #DIV/0! | M23: =_xlfn.IFS(L23<80%,"A",L23<=95%,"B",L23>95%,"C") -> #DIV/0!
D24: =C24/C$42 -> #DIV/0! | E24: =D24+E23 -> #DIV/0! | F24: =IF(AND(E24<=0),"C",IF(E24<=0.8,"A",IF(E24<=0.95,"B","C"))) -> #DIV/0! | G24: =VLOOKUP(B$22:B$42,I$22:M$42,5,0) -> #N/A | K24: =J24/J$42 -> #DIV/0! | L24: =K24+L23 -> #DIV/0! | M24: =_xlfn.IFS(L24<80%,"A",L24<=95%,"B",L24>95%,"C") -> #DIV/0!
D25: =C25/C$42 -> #DIV/0! | E25: =D25+E24 -> #DIV/0! | F25: =IF(AND(E25<=0),"C",IF(E25<=0.8,"A",IF(E25<=0.95,"B","C"))) -> #DIV/0! | G25: =VLOOKUP(B$22:B$42,I$22:M$42,5,0) -> #N/A | K25: =J25/J$42 -> #DIV/0! | L25: =K25+L24 -> #DIV/0! | M25: =_xlfn.IFS(L25<80%,"A",L25<=95%,"B",L25>95%,"C") -> #DIV/0!
D26: =C26/C$42 -> #DIV/0! | E26: =D26+E25 -> #DIV/0! | F26: =IF(AND(E26<=0),"C",IF(E26<=0.8,"A",IF(E26<=0.95,"B","C"))) -> #DIV/0! | G26: =VLOOKUP(B$22:B$42,I$22:M$42,5,0) -> #N/A | K26: =J26/J$42 -> #DIV/0! | L26: =K26+L25 -> #DIV/0! | M26: =_xlfn.IFS(L26<80%,"A",L26<=95%,"B",L26>95%,"C") -> #DIV/0!
D27: =C27/C$42 -> #DIV/0! | E27: =D27+E26 -> #DIV/0! | F27: =IF(AND(E27<=0),"C",IF(E27<=0.8,"A",IF(E27<=0.95,"B","C"))) -> #DIV/0! | G27: =VLOOKUP(B$22:B$42,I$22:M$42,5,0) -> #N/A | K27: =J27/J$42 -> #DIV/0! | L27: =K27+L26 -> #DIV/0! | M27: =_xlfn.IFS(L27<80%,"A",L27<=95%,"B",L27>95%,"C") -> #DIV/0!
D28: =C28/C$42 -> #DIV/0! | E28: =D28+E27 -> #DIV/0! | F28: =IF(AND(E28<=0),"C",IF(E28<=0.8,"A",IF(E28<=0.95,"B","C"))) -> #DIV/0! | G28: =VLOOKUP(B$22:B$42,I$22:M$42,5,0) -> #N/A | K28: =J28/J$42 -> #DIV/0! | L28: =K28+L27 -> #DIV/0! | M28: =_xlfn.IFS(L28<80%,"A",L28<=95%,"B",L28>95%,"C") -> #DIV/0!
D29: =C29/C$42 -> #DIV/0! | E29: =D29+E28 -> #DIV/0! | F29: =IF(AND(E29<=0),"C",IF(E29<=0.8,"A",IF(E29<=0.95,"B","C"))) -> #DIV/0! | G29: =VLOOKUP(B$22:B$42,I$22:M$42,5,0) -> #N/A | K29: =J29/J$42 -> #DIV/0! | L29: =K29+L28 -> #DIV/0! | M29: =_xlfn.IFS(L29<80%,"A",L29<=95%,"B",L29>95%,"C") -> #DIV/0!
D30: =C30/C$42 -> #DIV/0! | E30: =D30+E29 -> #DIV/0! | F30: =IF(AND(E30<=0),"C",IF(E30<=0.8,"A",IF(E30<=0.95,"B","C"))) -> #DIV/0! | G30: =VLOOKUP(B$22:B$42,I$22:M$42,5,0) -> #N/A | K30: =J30/J$42 -> #DIV/0! | L30: =K30+L29 -> #DIV/0! | M30: =_xlfn.IFS(L30<80%,"A",L30<=95%,"B",L30>95%,"C") -> #DIV/0!
D31: =C31/C$42 -> #DIV/0! | E31: =D31+E30 -> #DIV/0! | F31: =IF(AND(E31<=0),"C",IF(E31<=0.8,"A",IF(E31<=0.95,"B","C"))) -> #DIV/0! | G31: =VLOOKUP(B$22:B$42,I$22:M$42,5,0) -> #N/A | K31: =J31/J$42 -> #DIV/0! | L31: =K31+L30 -> #DIV/0! | M31: =_xlfn.IFS(L31<80%,"A",L31<=95%,"B",L31>95%,"C") -> #DIV/0!
D32: =C32/C$42 -> #DIV/0! | E32: =D32+E31 -> #DIV/0! | F32: =IF(AND(E32<=0),"C",IF(E32<=0.8,"A",IF(E32<=0.95,"B","C"))) -> #DIV/0! | G32: =VLOOKUP(B$22:B$42,I$22:M$42,5,0) -> #N/A | K32: =J32/J$42 -> #DIV/0! | L32: =K32+L31 -> #DIV/0! | M32: =_xlfn.IFS(L32<80%,"A",L32<=95%,"B",L32>95%,"C") -> #DIV/0!
D33: =C33/C$42 -> #DIV/0! | E33: =D33+E32 -> #DIV/0! | F33: =IF(AND(E33<=0),"C",IF(E33<=0.8,"A",IF(E33<=0.95,"B","C"))) -> #DIV/0! | G33: =VLOOKUP(B$22:B$42,I$22:M$42,5,0) -> #N/A | K33: =J33/J$42 -> #DIV/0! | L33: =K33+L32 -> #DIV/0! | M33: =_xlfn.IFS(L33<80%,"A",L33<=95%,"B",L33>95%,"C") -> #DIV/0!
D34: =C34/C$42 -> #DIV/0! | E34: =D34+E33 -> #DIV/0! | F34: =IF(AND(E34<=0),"C",IF(E34<=0.8,"A",IF(E34<=0.95,"B","C"))) -> #DIV/0! | G34: =VLOOKUP(B$22:B$42,I$22:M$42,5,0) -> #N/A | K34: =J34/J$42 -> #DIV/0! | L34: =K34+L33 -> #DIV/0! | M34: =_xlfn.IFS(L34<80%,"A",L34<=95%,"B",L34>95%,"C") -> #DIV/0!
... D41: =C41/C$42 -> #DIV/0! | E41: =D41+E40 -> #DIV/0! | F41: =IF(AND(E41<=0),"C",IF(E41<=0.8,"A",IF(E41<=0.95,"B","C"))) -> #DIV/0! | G41: =VLOOKUP(B$22:B$42,I$22:M$42,5,0) -> #N/A | K41: =J41/J$42 -> #DIV/0! | L41: =K41+L40 -> #DIV/0! | M41: =_xlfn.IFS(L41<80%,"A",L41<=95%,"B",L41>95%,"C") -> #DIV/0!
C42: =SUM(C22:C41) -> 0 | D42: =SUM(D22:D41) -> #DIV/0! | J42: =SUM(J22:J41) -> 0 | K42: =SUM(K22:K41) -> #DIV/0!

Sheet АВС 12-18.01
B2: ОЧКИ
C3: Прибыль | D3: % прибыль | E3: Доля | F3: ABC прибыль | G3: ABC кол-во | J3: Кол-во | K3: % кол-во | L3: Доля | M3: ABC кол-во
B4: flip жел | C4: ='Юнит 12-18.01'!AE15 -> 7845.5265 | D4: =C4/C$18 -> 0.31497995 | E4: =D4 -> 0.31497995 | F4: =IF(AND(E4<=0),"C",IF(E4<=0.8,"A",IF(E4<=0.95,"B","C"))) -> A | G4: =VLOOKUP(B$4:B$17,I$4:M$17,5,0) -> A | I4: flip жел | J4: ='Юнит 12-18.01'!R15 -> 37 | K4: =J4/J$18 -> 0.30833333 | L4: =K4 -> 0.30833333 | M4: =_xlfn.IFS(L4<80%,"A",L4<=95%,"B",L4>95%,"C") -> A
B5: qs желтые | C5: ='Юнит 12-18.01'!AE6 -> 4986.2704 | D5: =C5/C$18 -> 0.20018736 | E5: =D5+E4 -> 0.51516731 | F5: =IF(AND(E5<=0),"C",IF(E5<=0.8,"A",IF(E5<=0.95,"B","C"))) -> A | G5: =VLOOKUP(B$4:B$17,I$4:M$17,5,0) -> A | I5: th желт | J5: ='Юнит 12-18.01'!R11 -> 35 | K5: =J5/J$18 -> 0.29166667 | L5: =K5+L4 -> 0.6 | M5: =_xlfn.IFS(L5<80%,"A",L5<=95%,"B",L5>95%,"C") -> A
B6: qs коричневые | C6: ='Юнит 12-18.01'!AE7 -> 3808.3998 | D6: =C6/C$18 -> 0.15289854 | E6: =D6+E5 -> 0.66806585 | F6: =IF(AND(E6<=0),"C",IF(E6<=0.8,"A",IF(E6<=0.95,"B","C"))) -> A | G6: =VLOOKUP(B$4:B$17,I$4:M$17,5,0) -> B | I6: qs желтые | J6: ='Юнит 12-18.01'!R6 -> 20 | K6: =J6/J$18 -> 0.16666667 | L6: =K6+L5 -> 0.76666667 | M6: =_xlfn.IFS(L6<80%,"A",L6<=95%,"B",L6>95%,"C") -> A
B7: qs синие | C7: ='Юнит 12-18.01'!AE5 -> 2085.4874 | D7: =C7/C$18 -> 0.083727551 | E7: =D7+E6 -> 0.7517934 | F7: =IF(AND(E7<=0),"C",IF(E7<=0.8,"A",IF(E7<=0.95,"B","C"))) -> A | G7: =VLOOKUP(B$4:B$17,I$4:M$17,5,0) -> C | I7: qs коричневые | J7: ='Юнит 12-18.01'!R7 -> 10 | K7: =J7/J$18 -> 0.083333333 | L7: =K7+L6 -> 0.85 | M7: =_xlfn.IFS(L7<80%,"A",L7<=95%,"B",L7>95%,"C") -> B
B8: черные с железкой классика | C8: ='Юнит 12-18.01'!AE3 -> 1162.1223 | D8: =C8/C$18 -> 0.046656555 | E8: =D8+E7 -> 0.79844996 | F8: =IF(AND(E8<=0),"C",IF(E8<=0.8,"A",IF(E8<=0.95,"B","C"))) -> A | G8: =VLOOKUP(B$4:B$17,I$4:M$17,5,0) -> C | I8: MR8854 C2 | J8: ='Юнит 12-18.01'!R8 -> 7 | K8: =J8/J$18 -> 0.058333333 | L8: =K8+L7 -> 0.90833333 | M8: =_xlfn.IFS(L8<80%,"A",L8<=95%,"B",L8>95%,"C") -> B
B9: th желт | C9: ='Юнит 12-18.01'!AE11 -> 3663.4074 | D9: =C9/C$18 -> 0.14707743 | E9: =D9+E8 -> 0.94552739 | F9: =IF(AND(E9<=0),"C",IF(E9<=0.8,"A",IF(E9<=0.95,"B","C"))) -> B | G9: =VLOOKUP(B$4:B$17,I$4:M$17,5,0) -> A | I9: qs черные | J9: ='Юнит 12-18.01'!R4 -> 4 | K9: =J9/J$18 -> 0.033333333 | L9: =K9+L8 -> 0.94166667 | M9: =_xlfn.IFS(L9<80%,"A",L9<=95%,"B",L9>95%,"C") -> B
B10: qs черные | C10: ='Юнит 12-18.01'!AE4 -> 745.60927 | D10: =C10/C$18 -> 0.029934507 | E10: =D10+E9 -> 0.9754619 | F10: =IF(AND(E10<=0),"C",IF(E10<=0.8,"A",IF(E10<=0.95,"B","C"))) -> C | G10: =VLOOKUP(B$4:B$17,I$4:M$17,5,0) -> B | I10: qs синие | J10: ='Юнит 12-18.01'!R5 -> 4 | K10: =J10/J$18 -> 0.033333333 | L10: =K10+L9 -> 0.975 | M10: =_xlfn.IFS(L10<80%,"A",L10<=95%,"B",L10>95%,"C") -> C
B11: MR8854 C2 | C11: ='Юнит 12-18.01'!AE8 -> 611.19557 | D11: =C11/C$18 -> 0.024538105 | E11: =D11+E10 -> 1 | F11: =IF(AND(E11<=0),"C",IF(E11<=0.8,"A",IF(E11<=0.95,"B","C"))) -> C | G11: =VLOOKUP(B$4:B$17,I$4:M$17,5,0) -> B | I11: черные с железкой классика | J11: ='Юнит 12-18.01'!R3 -> 3 | K11: =J11/J$18 -> 0.025 | L11: =K11+L10 -> 1 | M11: =_xlfn.IFS(L11<80%,"A",L11<=95%,"B",L11>95%,"C") -> C
B12: th черн | C12: ='Юнит 12-18.01'!AE9 -> 0 | D12: =C12/C$18 -> 0 | E12: =D12+E5 -> 0.51516731 | F12: =IF(AND(E12<=0),"C",IF(E12<=0.8,"A",IF(E12<=0.95,"B","C"))) -> A | G12: =VLOOKUP(B$4:B$17,I$4:M$17,5,0) -> A | I12: th черн | J12: ='Юнит 12-18.01'!R9 -> 0 | K12: =J12/J$18 -> 0 | L12: =K12+L5 -> 0.6 | M12: =_xlfn.IFS(L12<80%,"A",L12<=95%,"B",L12>95%,"C") -> A
B13: th син | C13: ='Юнит 12-18.01'!AE10 -> 0 | D13: =C13/C$18 -> 0 | E13: =D13+E12 -> 0.51516731 | F13: =IF(AND(E13<=0),"C",IF(E13<=0.8,"A",IF(E13<=0.95,"B","C"))) -> A | G13: =VLOOKUP(B$4:B$17,I$4:M$17,5,0) -> A | I13: th син | J13: ='Юнит 12-18.01'!R10 -> 0 | K13: =J13/J$18 -> 0 | L13: =K13+L12 -> 0.6 | M13: =_xlfn.IFS(L13<80%,"A",L13<=95%,"B",L13>95%,"C") -> A
B14: th коричн | C14: ='Юнит 12-18.01'!AE12 -> 0 | D14: =C14/C$18 -> 0 | E14: =D14+E13 -> 0.51516731 | F14: =IF(AND(E14<=0),"C",IF(E14<=0.8,"A",IF(E14<=0.95,"B","C"))) -> A | G14: =VLOOKUP(B$4:B$17,I$4:M$17,5,0) -> A | I14: th коричн | J14: ='Юнит 12-18.01'!R12 -> 0 | K14: =J14/J$18 -> 0 | L14: =K14+L13 -> 0.6 | M14: =_xlfn.IFS(L14<80%,"A",L14<=95%,"B",L14>95%,"C") -> A
B15: flip черный | C15: ='Юнит 12-18.01'!AE13 -> 0 | D15: =C15/C$18 -> 0 | E15: =D15+E14 -> 0.51516731 | F15: =IF(AND(E15<=0),"C",IF(E15<=0.8,"A",IF(E15<=0.95,"B","C"))) -> A | G15: =VLOOKUP(B$4:B$17,I$4:M$17,5,0) -> A | I15: flip черный | J15: ='Юнит 12-18.01'!R13 -> 0 | K15: =J15/J$18 -> 0 | L15: =K15+L14 -> 0.6 | M15: =_xlfn.IFS(L15<80%,"A",L15<=95%,"B",L15>95%,"C") -> A
B16: flip синий | C16: ='Юнит 12-18.01'!AE14 -> 0 | D16: =C16/C$18 -> 0 | E16: =D16+E15 -> 0.51516731 | F16: =IF(AND(E16<=0),"C",IF(E16<=0.8,"A",IF(E16<=0.95,"B","C"))) -> A | G16: =VLOOKUP(B$4:B$17,I$4:M$17,5,0) -> A | I16: flip синий | J16: ='Юнит 12-18.01'!R14 -> 0 | K16: =J16/J$18 -> 0 | L16: =K16+L15 -> 0.6 | M16: =_xlfn.IFS(L16<80%,"A",L16<=95%,"B",L16>95%,"C") -> A
B17: flip коричневый | C17: ='Юнит 12-18.01'!AE16 -> 0 | D17: =C17/C$18 -> 0 | E17: =D17+E14 -> 0.51516731 | F17: =IF(AND(E17<=0),"C",IF(E17<=0.8,"A",IF(E17<=0.95,"B","C"))) -> A | G17: =VLOOKUP(B$4:B$17,I$4:M$17,5,0) -> A | I17: flip коричневый | J17: ='Юнит 12-18.01'!R16 -> 0 | K17: =J17/J$18 -> 0 | L17: =K17+L14 -> 0.6 | M17: =_xlfn.IFS(L17<80%,"A",L17<=95%,"B",L17>95%,"C") -> A
C18: =SUM(C4:C17) -> 24908.019 | D18: =SUM(D4:D17) -> 1 | J18: =SUM(J4:J17) -> 120 | K18: =SUM(K4:K17) -> 1
C21: Прибыль | D21: % прибыль | E21: Доля | F21: ABC прибыль | G21: ABC кол-во | J21: Кол-во | K21: % кол-во | L21: Доля | M21: ABC кол-во
D22: =C22/C$42 -> #DIV/0! | E22: =D22 -> #DIV/0! | F22: =IF(AND(E22<=0),"C",IF(E22<=0.8,"A",IF(E22<=0.95,"B","C"))) -> #DIV/0! | G22: =VLOOKUP(B$22:B$42,I$22:M$42,5,0) -> #N/A | K22: =J22/J$42 -> #DIV/0! | L22: =K22 -> #DIV/0! | M22: =_xlfn.IFS(L22<80%,"A",L22<=95%,"B",L22>95%,"C") -> #DIV/0!
D23: =C23/C$42 -> #DIV/0! | E23: =D23+E22 -> #DIV/0! | F23: =IF(AND(E23<=0),"C",IF(E23<=0.8,"A",IF(E23<=0.95,"B","C"))) -> #DIV/0! | G23: =VLOOKUP(B$22:B$42,I$22:M$42,5,0) -> #N/A | K23: =J23/J$42 -> #DIV/0! | L23: =K23+L22 -> #DIV/0! | M23: =_xlfn.IFS(L23<80%,"A",L23<=95%,"B",L23>95%,"C") -> #DIV/0!
D24: =C24/C$42 -> #DIV/0! | E24: =D24+E23 -> #DIV/0! | F24: =IF(AND(E24<=0),"C",IF(E24<=0.8,"A",IF(E24<=0.95,"B","C"))) -> #DIV/0! | G24: =VLOOKUP(B$22:B$42,I$22:M$42,5,0) -> #N/A | K24: =J24/J$42 -> #DIV/0! | L24: =K24+L23 -> #DIV/0! | M24: =_xlfn.IFS(L24<80%,"A",L24<=95%,"B",L24>95%,"C") -> #DIV/0!
D25: =C25/C$42 -> #DIV/0! | E25: =D25+E24 -> #DIV/0! | F25: =IF(AND(E25<=0),"C",IF(E25<=0.8,"A",IF(E25<=0.95,"B","C"))) -> #DIV/0! | G25: =VLOOKUP(B$22:B$42,I$22:M$42,5,0) -> #N/A | K25: =J25/J$42 -> #DIV/0! | L25: =K25+L24 -> #DIV/0! | M25: =_xlfn.IFS(L25<80%,"A",L25<=95%,"B",L25>95%,"C") -> #DIV/0!
D26: =C26/C$42 -> #DIV/0! | E26: =D26+E25 -> #DIV/0! | F26: =IF(AND(E26<=0),"C",IF(E26<=0.8,"A",IF(E26<=0.95,"B","C"))) -> #DIV/0! | G26: =VLOOKUP(B$22:B$42,I$22:M$42,5,0) -> #N/A | K26: =J26/J$42 -> #DIV/0! | L26: =K26+L25 -> #DIV/0! | M26: =_xlfn.IFS(L26<80%,"A",L26<=95%,"B",L26>95%,"C") -> #DIV/0!
D27: =C27/C$42 -> #DIV/0! | E27: =D27+E26 -> #DIV/0! | F27: =IF(AND(E27<=0),"C",IF(E27<=0.8,"A",IF(E27<=0.95,"B","C"))) -> #DIV/0! | G27: =VLOOKUP(B$22:B$42,I$22:M$42,5,0) -> #N/A | K27: =J27/J$42 -> #DIV/0! | L27: =K27+L26 -> #DIV/0! | M27: =_xlfn.IFS(L27<80%,"A",L27<=95%,"B",L27>95%,"C") -> #DIV/0!
D28: =C28/C$42 -> #DIV/0! | E28: =D28+E27 -> #DIV/0! | F28: =IF(AND(E28<=0),"C",IF(E28<=0.8,"A",IF(E28<=0.95,"B","C"))) -> #DIV/0! | G28: =VLOOKUP(B$22:B$42,I$22:M$42,5,0) -> #N/A | K28: =J28/J$42 -> #DIV/0! | L28: =K28+L27 -> #DIV/0! | M28: =_xlfn.IFS(L28<80%,"A",L28<=95%,"B",L28>95%,"C") -> #DIV/0!
D29: =C29/C$42 -> #DIV/0! | E29: =D29+E28 -> #DIV/0! | F29: =IF(AND(E29<=0),"C",IF(E29<=0.8,"A",IF(E29<=0.95,"B","C"))) -> #DIV/0! | G29: =VLOOKUP(B$22:B$42,I$22:M$42,5,0) -> #N/A | K29: =J29/J$42 -> #DIV/0! | L29: =K29+L28 -> #DIV/0! | M29: =_xlfn.IFS(L29<80%,"A",L29<=95%,"B",L29>95%,"C") -> #DIV/0!
D30: =C30/C$42 -> #DIV/0! | E30: =D30+E29 -> #DIV/0! | F30: =IF(AND(E30<=0),"C",IF(E30<=0.8,"A",IF(E30<=0.95,"B","C"))) -> #DIV/0! | G30: =VLOOKUP(B$22:B$42,I$22:M$42,5,0) -> #N/A | K30: =J30/J$42 -> #DIV/0! | L30: =K30+L29 -> #DIV/0! | M30: =_xlfn.IFS(L30<80%,"A",L30<=95%,"B",L30>95%,"C") -> #DIV/0!
D31: =C31/C$42 -> #DIV/0! | E31: =D31+E30 -> #DIV/0! | F31: =IF(AND(E31<=0),"C",IF(E31<=0.8,"A",IF(E31<=0.95,"B","C"))) -> #DIV/0! | G31: =VLOOKUP(B$22:B$42,I$22:M$42,5,0) -> #N/A | K31: =J31/J$42 -> #DIV/0! | L31: =K31+L30 -> #DIV/0! | M31: =_xlfn.IFS(L31<80%,"A",L31<=95%,"B",L31>95%,"C") -> #DIV/0!
D32: =C32/C$42 -> #DIV/0! | E32: =D32+E31 -> #DIV/0! | F32: =IF(AND(E32<=0),"C",IF(E32<=0.8,"A",IF(E32<=0.95,"B","C"))) -> #DIV/0! | G32: =VLOOKUP(B$22:B$42,I$22:M$42,5,0) -> #N/A | K32: =J32/J$42 -> #DIV/0! | L32: =K32+L31 -> #DIV/0! | M32: =_xlfn.IFS(L32<80%,"A",L32<=95%,"B",L32>95%,"C") -> #DIV/0!
D33: =C33/C$42 -> #DIV/0! | E33: =D33+E32 -> #DIV/0! | F33: =IF(AND(E33<=0),"C",IF(E33<=0.8,"A",IF(E33<=0.95,"B","C"))) -> #DIV/0! | G33: =VLOOKUP(B$22:B$42,I$22:M$42,5,0) -> #N/A | K33: =J33/J$42 -> #DIV/0! | L33: =K33+L32 -> #DIV/0! | M33: =_xlfn.IFS(L33<80%,"A",L33<=95%,"B",L33>95%,"C") -> #DIV/0!
D34: =C34/C$42 -> #DIV/0! | E34: =D34+E33 -> #DIV/0! | F34: =IF(AND(E34<=0),"C",IF(E34<=0.8,"A",IF(E34<=0.95,"B","C"))) -> #DIV/0! | G34: =VLOOKUP(B$22:B$42,I$22:M$42,5,0) -> #N/A | K34: =J34/J$42 -> #DIV/0! | L34: =K34+L33 -> #DIV/0! | M34: =_xlfn.IFS(L34<80%,"A",L34<=95%,"B",L34>95%,"C") -> #DIV/0!
... D41: =C41/C$42 -> #DIV/0! | E41: =D41+E40 -> #DIV/0! | F41: =IF(AND(E41<=0),"C",IF(E41<=0.8,"A",IF(E41<=0.95,"B","C"))) -> #DIV/0! | G41: =VLOOKUP(B$22:B$42,I$22:M$42,5,0) -> #N/A | K41: =J41/J$42 -> #DIV/0! | L41: =K41+L40 -> #DIV/0! | M41: =_xlfn.IFS(L41<80%,"A",L41<=95%,"B",L41>95%,"C") -> #DIV/0!
C42: =SUM(C22:C41) -> 0 | D42: =SUM(D22:D41) -> #DIV/0! | J42: =SUM(J22:J41) -> 0 | K42: =SUM(K22:K41) -> #DIV/0!

Sheet АВС 05-11.01
B2: ОЧКИ
C3: Прибыль | D3: % прибыль | E3: Доля | F3: ABC прибыль | G3: ABC кол-во | J3: Кол-во | K3: % кол-во | L3: Доля | M3: ABC кол-во
B4: th желт | C4: ='Юнит 05-11.01'!AE11 -> 14577.679 | D4: =C4/C$18 -> 0.32994497 | E4: =D4 -> 0.32994497 | F4: =IF(AND(E4<=0),"C",IF(E4<=0.8,"A",IF(E4<=0.95,"B","C"))) -> A | G4: =VLOOKUP(B$4:B$17,I$4:M$17,5,0) -> A | I4: th желт | J4: ='Юнит 05-11.01'!R11 -> 52 | K4: =J4/J$18 -> 0.325 | L4: =K4 -> 0.325 | M4: =_xlfn.IFS(L4<80%,"A",L4<=95%,"B",L4>95%,"C") -> A
B5: flip жел | C5: ='Юнит 05-11.01'!AE15 -> 13681.243 | D5: =C5/C$18 -> 0.3096554 | E5: =D5+E4 -> 0.63960037 | F5: =IF(AND(E5<=0),"C",IF(E5<=0.8,"A",IF(E5<=0.95,"B","C"))) -> A | G5: =VLOOKUP(B$4:B$17,I$4:M$17,5,0) -> A | I5: flip жел | J5: ='Юнит 05-11.01'!R15 -> 49 | K5: =J5/J$18 -> 0.30625 | L5: =K5+L4 -> 0.63125 | M5: =_xlfn.IFS(L5<80%,"A",L5<=95%,"B",L5>95%,"C") -> A
B6: qs желтые | C6: ='Юнит 05-11.01'!AE6 -> 6919.0166 | D6: =C6/C$18 -> 0.15660207 | E6: =D6+E5 -> 0.79620244 | F6: =IF(AND(E6<=0),"C",IF(E6<=0.8,"A",IF(E6<=0.95,"B","C"))) -> A | G6: =VLOOKUP(B$4:B$17,I$4:M$17,5,0) -> B | I6: qs желтые | J6: ='Юнит 05-11.01'!R6 -> 31 | K6: =J6/J$18 -> 0.19375 | L6: =K6+L5 -> 0.825 | M6: =_xlfn.IFS(L6<80%,"A",L6<=95%,"B",L6>95%,"C") -> B
B7: qs коричневые | C7: ='Юнит 05-11.01'!AE7 -> 2667.2832 | D7: =C7/C$18 -> 0.060370149 | E7: =D7+E6 -> 0.85657259 | F7: =IF(AND(E7<=0),"C",IF(E7<=0.8,"A",IF(E7<=0.95,"B","C"))) -> B | G7: =VLOOKUP(B$4:B$17,I$4:M$17,5,0) -> B | I7: MR8854 C2 | J7: ='Юнит 05-11.01'!R8 -> 10 | K7: =J7/J$18 -> 0.0625 | L7: =K7+L6 -> 0.8875 | M7: =_xlfn.IFS(L7<80%,"A",L7<=95%,"B",L7>95%,"C") -> B
B8: MR8854 C2 | C8: ='Юнит 05-11.01'!AE8 -> 2517.3576 | D8: =C8/C$18 -> 0.056976798 | E8: =D8+E7 -> 0.91354939 | F8: =IF(AND(E8<=0),"C",IF(E8<=0.8,"A",IF(E8<=0.95,"B","C"))) -> B | G8: =VLOOKUP(B$4:B$17,I$4:M$17,5,0) -> B | I8: qs коричневые | J8: ='Юнит 05-11.01'!R7 -> 8 | K8: =J8/J$18 -> 0.05 | L8: =K8+L7 -> 0.9375 | M8: =_xlfn.IFS(L8<80%,"A",L8<=95%,"B",L8>95%,"C") -> B
B9: черные с железкой классика | C9: ='Юнит 05-11.01'!AE3 -> 1842.5976 | D9: =C9/C$18 -> 0.041704567 | E9: =D9+E8 -> 0.95525396 | F9: =IF(AND(E9<=0),"C",IF(E9<=0.8,"A",IF(E9<=0.95,"B","C"))) -> C | G9: =VLOOKUP(B$4:B$17,I$4:M$17,5,0) -> C | I9: черные с железкой классика | J9: ='Юнит 05-11.01'!R3 -> 5 | K9: =J9/J$18 -> 0.03125 | L9: =K9+L8 -> 0.96875 | M9: =_xlfn.IFS(L9<80%,"A",L9<=95%,"B",L9>95%,"C") -> C
B10: qs черные | C10: ='Юнит 05-11.01'!AE4 -> 1521.1407 | D10: =C10/C$18 -> 0.034428849 | E10: =D10+E9 -> 0.98968281 | F10: =IF(AND(E10<=0),"C",IF(E10<=0.8,"A",IF(E10<=0.95,"B","C"))) -> C | G10: =VLOOKUP(B$4:B$17,I$4:M$17,5,0) -> C | I10: qs черные | J10: ='Юнит 05-11.01'!R4 -> 3 | K10: =J10/J$18 -> 0.01875 | L10: =K10+L9 -> 0.9875 | M10: =_xlfn.IFS(L10<80%,"A",L10<=95%,"B",L10>95%,"C") -> C
B11: qs синие | C11: ='Юнит 05-11.01'!AE5 -> 455.83588 | D11: =C11/C$18 -> 0.010317195 | E11: =D11+E10 -> 1 | F11: =IF(AND(E11<=0),"C",IF(E11<=0.8,"A",IF(E11<=0.95,"B","C"))) -> C | G11: =VLOOKUP(B$4:B$17,I$4:M$17,5,0) -> C | I11: qs синие | J11: ='Юнит 05-11.01'!R5 -> 2 | K11: =J11/J$18 -> 0.0125 | L11: =K11+L10 -> 1 | M11: =_xlfn.IFS(L11<80%,"A",L11<=95%,"B",L11>95%,"C") -> C
B12: th черн | C12: ='Юнит 05-11.01'!AE9 -> 0 | D12: =C12/C$18 -> 0 | E12: =D12+E5 -> 0.63960037 | F12: =IF(AND(E12<=0),"C",IF(E12<=0.8,"A",IF(E12<=0.95,"B","C"))) -> A | G12: =VLOOKUP(B$4:B$17,I$4:M$17,5,0) -> A | I12: th черн | J12: ='Юнит 05-11.01'!R9 -> 0 | K12: =J12/J$18 -> 0 | L12: =K12+L5 -> 0.63125 | M12: =_xlfn.IFS(L12<80%,"A",L12<=95%,"B",L12>95%,"C") -> A
B13: th син | C13: ='Юнит 05-11.01'!AE10 -> 0 | D13: =C13/C$18 -> 0 | E13: =D13+E12 -> 0.63960037 | F13: =IF(AND(E13<=0),"C",IF(E13<=0.8,"A",IF(E13<=0.95,"B","C"))) -> A | G13: =VLOOKUP(B$4:B$17,I$4:M$17,5,0) -> A | I13: th син | J13: ='Юнит 05-11.01'!R10 -> 0 | K13: =J13/J$18 -> 0 | L13: =K13+L12 -> 0.63125 | M13: =_xlfn.IFS(L13<80%,"A",L13<=95%,"B",L13>95%,"C") -> A
B14: th коричн | C14: ='Юнит 05-11.01'!AE12 -> 0 | D14: =C14/C$18 -> 0 | E14: =D14+E13 -> 0.63960037 | F14: =IF(AND(E14<=0),"C",IF(E14<=0.8,"A",IF(E14<=0.95,"B","C"))) -> A | G14: =VLOOKUP(B$4:B$17,I$4:M$17,5,0) -> A | I14: th коричн | J14: ='Юнит 05-11.01'!R12 -> 0 | K14: =J14/J$18 -> 0 | L14: =K14+L13 -> 0.63125 | M14: =_xlfn.IFS(L14<80%,"A",L14<=95%,"B",L14>95%,"C") -> A
B15: flip черный | C15: ='Юнит 05-11.01'!AE13 -> 0 | D15: =C15/C$18 -> 0 | E15: =D15+E14 -> 0.63960037 | F15: =IF(AND(E15<=0),"C",IF(E15<=0.8,"A",IF(E15<=0.95,"B","C"))) -> A | G15: =VLOOKUP(B$4:B$17,I$4:M$17,5,0) -> A | I15: flip черный | J15: ='Юнит 05-11.01'!R13 -> 0 | K15: =J15/J$18 -> 0 | L15: =K15+L14 -> 0.63125 | M15: =_xlfn.IFS(L15<80%,"A",L15<=95%,"B",L15>95%,"C") -> A
B16: flip синий | C16: ='Юнит 05-11.01'!AE14 -> 0 | D16: =C16/C$18 -> 0 | E16: =D16+E15 -> 0.63960037 | F16: =IF(AND(E16<=0),"C",IF(E16<=0.8,"A",IF(E16<=0.95,"B","C"))) -> A | G16: =VLOOKUP(B$4:B$17,I$4:M$17,5,0) -> A | I16: flip синий | J16: ='Юнит 05-11.01'!R14 -> 0 | K16: =J16/J$18 -> 0 | L16: =K16+L15 -> 0.63125 | M16: =_xlfn.IFS(L16<80%,"A",L16<=95%,"B",L16>95%,"C") -> A
B17: flip коричневый | C17: ='Юнит 05-11.01'!AE16 -> 0 | D17: =C17/C$18 -> 0 | E17: =D17+E14 -> 0.63960037 | F17: =IF(AND(E17<=0),"C",IF(E17<=0.8,"A",IF(E17<=0.95,"B","C"))) -> A | G17: =VLOOKUP(B$4:B$17,I$4:M$17,5,0) -> A | I17: flip коричневый | J17: ='Юнит 05-11.01'!R16 -> 0 | K17: =J17/J$18 -> 0 | L17: =K17+L14 -> 0.63125 | M17: =_xlfn.IFS(L17<80%,"A",L17<=95%,"B",L17>95%,"C") -> A
C18: =SUM(C4:C17) -> 44182.154 | D18: =SUM(D4:D17) -> 1 | J18: =SUM(J4:J17) -> 160 | K18: =SUM(K4:K17) -> 1
C21: Прибыль | D21: % прибыль | E21: Доля | F21: ABC прибыль | G21: ABC кол-во | J21: Кол-во | K21: % кол-во | L21: Доля | M21: ABC кол-во
D22: =C22/C$42 -> #DIV/0! | E22: =D22 -> #DIV/0! | F22: =IF(AND(E22<=0),"C",IF(E22<=0.8,"A",IF(E22<=0.95,"B","C"))) -> #DIV/0! | G22: =VLOOKUP(B$22:B$42,I$22:M$42,5,0) -> #N/A | K22: =J22/J$42 -> #DIV/0! | L22: =K22 -> #DIV/0! | M22: =_xlfn.IFS(L22<80%,"A",L22<=95%,"B",L22>95%,"C") -> #DIV/0!
D23: =C23/C$42 -> #DIV/0! | E23: =D23+E22 -> #DIV/0! | F23: =IF(AND(E23<=0),"C",IF(E23<=0.8,"A",IF(E23<=0.95,"B","C"))) -> #DIV/0! | G23: =VLOOKUP(B$22:B$42,I$22:M$42,5,0) -> #N/A | K23: =J23/J$42 -> #DIV/0! | L23: =K23+L22 -> #DIV/0! | M23: =_xlfn.IFS(L23<80%,"A",L23<=95%,"B",L23>95%,"C") -> #DIV/0!
D24: =C24/C$42 -> #DIV/0! | E24: =D24+E23 -> #DIV/0! | F24: =IF(AND(E24<=0),"C",IF(E24<=0.8,"A",IF(E24<=0.95,"B","C"))) -> #DIV/0! | G24: =VLOOKUP(B$22:B$42,I$22:M$42,5,0) -> #N/A | K24: =J24/J$42 -> #DIV/0! | L24: =K24+L23 -> #DIV/0! | M24: =_xlfn.IFS(L24<80%,"A",L24<=95%,"B",L24>95%,"C") -> #DIV/0!
D25: =C25/C$42 -> #DIV/0! | E25: =D25+E24 -> #DIV/0! | F25: =IF(AND(E25<=0),"C",IF(E25<=0.8,"A",IF(E25<=0.95,"B","C"))) -> #DIV/0! | G25: =VLOOKUP(B$22:B$42,I$22:M$42,5,0) -> #N/A | K25: =J25/J$42 -> #DIV/0! | L25: =K25+L24 -> #DIV/0! | M25: =_xlfn.IFS(L25<80%,"A",L25<=95%,"B",L25>95%,"C") -> #DIV/0!
D26: =C26/C$42 -> #DIV/0! | E26: =D26+E25 -> #DIV/0! | F26: =IF(AND(E26<=0),"C",IF(E26<=0.8,"A",IF(E26<=0.95,"B","C"))) -> #DIV/0! | G26: =VLOOKUP(B$22:B$42,I$22:M$42,5,0) -> #N/A | K26: =J26/J$42 -> #DIV/0! | L26: =K26+L25 -> #DIV/0! | M26: =_xlfn.IFS(L26<80%,"A",L26<=95%,"B",L26>95%,"C") -> #DIV/0!
D27: =C27/C$42 -> #DIV/0! | E27: =D27+E26 -> #DIV/0! | F27: =IF(AND(E27<=0),"C",IF(E27<=0.8,"A",IF(E27<=0.95,"B","C"))) -> #DIV/0! | G27: =VLOOKUP(B$22:B$42,I$22:M$42,5,0) -> #N/A | K27: =J27/J$42 -> #DIV/0! | L27: =K27+L26 -> #DIV/0! | M27: =_xlfn.IFS(L27<80%,"A",L27<=95%,"B",L27>95%,"C") -> #DIV/0!
D28: =C28/C$42 -> #DIV/0! | E28: =D28+E27 -> #DIV/0! | F28: =IF(AND(E28<=0),"C",IF(E28<=0.8,"A",IF(E28<=0.95,"B","C"))) -> #DIV/0! | G28: =VLOOKUP(B$22:B$42,I$22:M$42,5,0) -> #N/A | K28: =J28/J$42 -> #DIV/0! | L28: =K28+L27 -> #DIV/0! | M28: =_xlfn.IFS(L28<80%,"A",L28<=95%,"B",L28>95%,"C") -> #DIV/0!
D29: =C29/C$42 -> #DIV/0! | E29: =D29+E28 -> #DIV/0! | F29: =IF(AND(E29<=0),"C",IF(E29<=0.8,"A",IF(E29<=0.95,"B","C"))) -> #DIV/0! | G29: =VLOOKUP(B$22:B$42,I$22:M$42,5,0) -> #N/A | K29: =J29/J$42 -> #DIV/0! | L29: =K29+L28 -> #DIV/0! | M29: =_xlfn.IFS(L29<80%,"A",L29<=95%,"B",L29>95%,"C") -> #DIV/0!
D30: =C30/C$42 -> #DIV/0! | E30: =D30+E29 -> #DIV/0! | F30: =IF(AND(E30<=0),"C",IF(E30<=0.8,"A",IF(E30<=0.95,"B","C"))) -> #DIV/0! | G30: =VLOOKUP(B$22:B$42,I$22:M$42,5,0) -> #N/A | K30: =J30/J$42 -> #DIV/0! | L30: =K30+L29 -> #DIV/0! | M30: =_xlfn.IFS(L30<80%,"A",L30<=95%,"B",L30>95%,"C") -> #DIV/0!
D31: =C31/C$42 -> #DIV/0! | E31: =D31+E30 -> #DIV/0! | F31: =IF(AND(E31<=0),"C",IF(E31<=0.8,"A",IF(E31<=0.95,"B","C"))) -> #DIV/0! | G31: =VLOOKUP(B$22:B$42,I$22:M$42,5,0) -> #N/A | K31: =J31/J$42 -> #DIV/0! | L31: =K31+L30 -> #DIV/0! | M31: =_xlfn.IFS(L31<80%,"A",L31<=95%,"B",L31>95%,"C") -> #DIV/0!
D32: =C32/C$42 -> #DIV/0! | E32: =D32+E31 -> #DIV/0! | F32: =IF(AND(E32<=0),"C",IF(E32<=0.8,"A",IF(E32<=0.95,"B","C"))) -> #DIV/0! | G32: =VLOOKUP(B$22:B$42,I$22:M$42,5,0) -> #N/A | K32: =J32/J$42 -> #DIV/0! | L32: =K32+L31 -> #DIV/0! | M32: =_xlfn.IFS(L32<80%,"A",L32<=95%,"B",L32>95%,"C") -> #DIV/0!
D33: =C33/C$42 -> #DIV/0! | E33: =D33+E32 -> #DIV/0! | F33: =IF(AND(E33<=0),"C",IF(E33<=0.8,"A",IF(E33<=0.95,"B","C"))) -> #DIV/0! | G33: =VLOOKUP(B$22:B$42,I$22:M$42,5,0) -> #N/A | K33: =J33/J$42 -> #DIV/0! | L33: =K33+L32 -> #DIV/0! | M33: =_xlfn.IFS(L33<80%,"A",L33<=95%,"B",L33>95%,"C") -> #DIV/0!
D34: =C34/C$42 -> #DIV/0! | E34: =D34+E33 -> #DIV/0! | F34: =IF(AND(E34<=0),"C",IF(E34<=0.8,"A",IF(E34<=0.95,"B","C"))) -> #DIV/0! | G34: =VLOOKUP(B$22:B$42,I$22:M$42,5,0) -> #N/A | K34: =J34/J$42 -> #DIV/0! | L34: =K34+L33 -> #DIV/0! | M34: =_xlfn.IFS(L34<80%,"A",L34<=95%,"B",L34>95%,"C") -> #DIV/0!
... D41: =C41/C$42 -> #DIV/0! | E41: =D41+E40 -> #DIV/0! | F41: =IF(AND(E41<=0),"C",IF(E41<=0.8,"A",IF(E41<=0.95,"B","C"))) -> #DIV/0! | G41: =VLOOKUP(B$22:B$42,I$22:M$42,5,0) -> #N/A | K41: =J41/J$42 -> #DIV/0! | L41: =K41+L40 -> #DIV/0! | M41: =_xlfn.IFS(L41<80%,"A",L41<=95%,"B",L41>95%,"C") -> #DIV/0!
C42: =SUM(C22:C41) -> 0 | D42: =SUM(D22:D41) -> #DIV/0! | J42: =SUM(J22:J41) -> 0 | K42: =SUM(K22:K41) -> #DIV/0!

Sheet АВС 01-04.01
B2: ОЧКИ
C3: Прибыль | D3: % прибыль | E3: Доля | F3: ABC прибыль | G3: ABC кол-во | J3: Кол-во | K3: % кол-во | L3: Доля | M3: ABC кол-во
B4: flip жел | C4: ='Юнит 01-04.01'!AE15 -> 2923.2652 | D4: =C4/C$18 -> -0.78040933 | E4: =D4 -> -0.78040933 | F4: =IF(AND(E4<=0),"C",IF(E4<=0.8,"A",IF(E4<=0.95,"B","C"))) -> C | G4: =VLOOKUP(B$4:B$17,I$4:M$17,5,0) -> A | I4: flip жел | J4: ='Юнит 01-04.01'!R15 -> 25 | K4: =J4/J$18 -> 0.5 | L4: =K4 -> 0.5 | M4: =_xlfn.IFS(L4<80%,"A",L4<=95%,"B",L4>95%,"C") -> A
B5: qs черные | C5: ='Юнит 01-04.01'!AE4 -> 684.33 | D5: =C5/C$18 -> -0.18269212 | E5: =D5+E4 -> -0.96310145 | F5: =IF(AND(E5<=0),"C",IF(E5<=0.8,"A",IF(E5<=0.95,"B","C"))) -> C | G5: =VLOOKUP(B$4:B$17,I$4:M$17,5,0) -> C | I5: th желт | J5: ='Юнит 01-04.01'!R11 -> 12 | K5: =J5/J$18 -> 0.24 | L5: =K5+L4 -> 0.74 | M5: =_xlfn.IFS(L5<80%,"A",L5<=95%,"B",L5>95%,"C") -> A
B6: qs коричневые | C6: ='Юнит 01-04.01'!AE7 -> 752.97 | D6: =C6/C$18 -> -0.20101659 | E6: =D6+E5 -> -1.164118 | F6: =IF(AND(E6<=0),"C",IF(E6<=0.8,"A",IF(E6<=0.95,"B","C"))) -> C | G6: =VLOOKUP(B$4:B$17,I$4:M$17,5,0) -> B | I6: qs желтые | J6: ='Юнит 01-04.01'!R6 -> 7 | K6: =J6/J$18 -> 0.14 | L6: =K6+L5 -> 0.88 | M6: =_xlfn.IFS(L6<80%,"A",L6<=95%,"B",L6>95%,"C") -> B
B7: черные с железкой классика | C7: ='Юнит 01-04.01'!AE3 -> 277.19 | D7: =C7/C$18 -> -0.074000012 | E7: =D7+E6 -> -1.238118 | F7: =IF(AND(E7<=0),"C",IF(E7<=0.8,"A",IF(E7<=0.95,"B","C"))) -> C | G7: =VLOOKUP(B$4:B$17,I$4:M$17,5,0) -> C | I7: qs коричневые | J7: ='Юнит 01-04.01'!R7 -> 2 | K7: =J7/J$18 -> 0.04 | L7: =K7+L6 -> 0.92 | M7: =_xlfn.IFS(L7<80%,"A",L7<=95%,"B",L7>95%,"C") -> B
B8: qs синие | C8: ='Юнит 01-04.01'!AE5 -> 0 | D8: =C8/C$18 -> 0 | E8: =D8+E7 -> -1.238118 | F8: =IF(AND(E8<=0),"C",IF(E8<=0.8,"A",IF(E8<=0.95,"B","C"))) -> C | G8: =VLOOKUP(B$4:B$17,I$4:M$17,5,0) -> C | I8: MR8854 C2 | J8: ='Юнит 01-04.01'!R8 -> 2 | K8: =J8/J$18 -> 0.04 | L8: =K8+L7 -> 0.96 | M8: =_xlfn.IFS(L8<80%,"A",L8<=95%,"B",L8>95%,"C") -> C
B9: th черн | C9: ='Юнит 01-04.01'!AE9 -> 0 | D9: =C9/C$18 -> 0 | E9: =D9+E8 -> -1.238118 | F9: =IF(AND(E9<=0),"C",IF(E9<=0.8,"A",IF(E9<=0.95,"B","C"))) -> C | G9: =VLOOKUP(B$4:B$17,I$4:M$17,5,0) -> A | I9: черные с железкой классика | J9: ='Юнит 01-04.01'!R3 -> 1 | K9: =J9/J$18 -> 0.02 | L9: =K9+L8 -> 0.98 | M9: =_xlfn.IFS(L9<80%,"A",L9<=95%,"B",L9>95%,"C") -> C
B10: th син | C10: ='Юнит 01-04.01'!AE10 -> 0 | D10: =C10/C$18 -> 0 | E10: =D10+E9 -> -1.238118 | F10: =IF(AND(E10<=0),"C",IF(E10<=0.8,"A",IF(E10<=0.95,"B","C"))) -> C | G10: =VLOOKUP(B$4:B$17,I$4:M$17,5,0) -> A | I10: qs черные | J10: ='Юнит 01-04.01'!R4 -> 1 | K10: =J10/J$18 -> 0.02 | L10: =K10+L9 -> 1 | M10: =_xlfn.IFS(L10<80%,"A",L10<=95%,"B",L10>95%,"C") -> C
B11: th коричн | C11: ='Юнит 01-04.01'!AE12 -> 0 | D11: =C11/C$18 -> 0 | E11: =D11+E10 -> -1.238118 | F11: =IF(AND(E11<=0),"C",IF(E11<=0.8,"A",IF(E11<=0.95,"B","C"))) -> C | G11: =VLOOKUP(B$4:B$17,I$4:M$17,5,0) -> A | I11: qs синие | J11: ='Юнит 01-04.01'!R5 -> 0 | K11: =J11/J$18 -> 0 | L11: =K11+L10 -> 1 | M11: =_xlfn.IFS(L11<80%,"A",L11<=95%,"B",L11>95%,"C") -> C
B12: flip черный | C12: ='Юнит 01-04.01'!AE13 -> 0 | D12: =C12/C$18 -> 0 | E12: =D12+E5 -> -0.96310145 | F12: =IF(AND(E12<=0),"C",IF(E12<=0.8,"A",IF(E12<=0.95,"B","C"))) -> C | G12: =VLOOKUP(B$4:B$17,I$4:M$17,5,0) -> A | I12: th черн | J12: ='Юнит 01-04.01'!R9 -> 0 | K12: =J12/J$18 -> 0 | L12: =K12+L5 -> 0.74 | M12: =_xlfn.IFS(L12<80%,"A",L12<=95%,"B",L12>95%,"C") -> A
B13: flip синий | C13: ='Юнит 01-04.01'!AE14 -> 0 | D13: =C13/C$18 -> 0 | E13: =D13+E12 -> -0.96310145 | F13: =IF(AND(E13<=0),"C",IF(E13<=0.8,"A",IF(E13<=0.95,"B","C"))) -> C | G13: =VLOOKUP(B$4:B$17,I$4:M$17,5,0) -> A | I13: th син | J13: ='Юнит 01-04.01'!R10 -> 0 | K13: =J13/J$18 -> 0 | L13: =K13+L12 -> 0.74 | M13: =_xlfn.IFS(L13<80%,"A",L13<=95%,"B",L13>95%,"C") -> A
B14: flip коричневый | C14: ='Юнит 01-04.01'!AE16 -> 0 | D14: =C14/C$18 -> 0 | E14: =D14+E13 -> -0.96310145 | F14: =IF(AND(E14<=0),"C",IF(E14<=0.8,"A",IF(E14<=0.95,"B","C"))) -> C | G14: =VLOOKUP(B$4:B$17,I$4:M$17,5,0) -> A | I14: th коричн | J14: ='Юнит 01-04.01'!R12 -> 0 | K14: =J14/J$18 -> 0 | L14: =K14+L13 -> 0.74 | M14: =_xlfn.IFS(L14<80%,"A",L14<=95%,"B",L14>95%,"C") -> A
B15: MR8854 C2 | C15: ='Юнит 01-04.01'!AE8 -> -419.23 | D15: =C15/C$18 -> 0.11191971 | E15: =D15+E14 -> -0.85118173 | F15: =IF(AND(E15<=0),"C",IF(E15<=0.8,"A",IF(E15<=0.95,"B","C"))) -> C | G15: =VLOOKUP(B$4:B$17,I$4:M$17,5,0) -> C | I15: flip черный | J15: ='Юнит 01-04.01'!R13 -> 0 | K15: =J15/J$18 -> 0 | L15: =K15+L14 -> 0.74 | M15: =_xlfn.IFS(L15<80%,"A",L15<=95%,"B",L15>95%,"C") -> A
B16: qs желтые | C16: ='Юнит 01-04.01'!AE6 -> -2341.0661 | D16: =C16/C$18 -> 0.62498256 | E16: =D16+E15 -> -0.22619917 | F16: =IF(AND(E16<=0),"C",IF(E16<=0.8,"A",IF(E16<=0.95,"B","C"))) -> C | G16: =VLOOKUP(B$4:B$17,I$4:M$17,5,0) -> B | I16: flip синий | J16: ='Юнит 01-04.01'!R14 -> 0 | K16: =J16/J$18 -> 0 | L16: =K16+L15 -> 0.74 | M16: =_xlfn.IFS(L16<80%,"A",L16<=95%,"B",L16>95%,"C") -> A
B17: th желт | C17: ='Юнит 01-04.01'!AE11 -> -5623.2694 | D17: =C17/C$18 -> 1.5012158 | E17: =D17+E14 -> 0.53811433 | F17: =IF(AND(E17<=0),"C",IF(E17<=0.8,"A",IF(E17<=0.95,"B","C"))) -> A | G17: =VLOOKUP(B$4:B$17,I$4:M$17,5,0) -> A | I17: flip коричневый | J17: ='Юнит 01-04.01'!R16 -> 0 | K17: =J17/J$18 -> 0 | L17: =K17+L14 -> 0.74 | M17: =_xlfn.IFS(L17<80%,"A",L17<=95%,"B",L17>95%,"C") -> A
C18: =SUM(C4:C17) -> -3745.8102 | D18: =SUM(D4:D17) -> 1 | J18: =SUM(J4:J17) -> 50 | K18: =SUM(K4:K17) -> 1
C21: Прибыль | D21: % прибыль | E21: Доля | F21: ABC прибыль | G21: ABC кол-во | J21: Кол-во | K21: % кол-во | L21: Доля | M21: ABC кол-во
D22: =C22/C$42 -> #DIV/0! | E22: =D22 -> #DIV/0! | F22: =IF(AND(E22<=0),"C",IF(E22<=0.8,"A",IF(E22<=0.95,"B","C"))) -> #DIV/0! | G22: =VLOOKUP(B$22:B$42,I$22:M$42,5,0) -> #N/A | K22: =J22/J$42 -> #DIV/0! | L22: =K22 -> #DIV/0! | M22: =_xlfn.IFS(L22<80%,"A",L22<=95%,"B",L22>95%,"C") -> #DIV/0!
D23: =C23/C$42 -> #DIV/0! | E23: =D23+E22 -> #DIV/0! | F23: =IF(AND(E23<=0),"C",IF(E23<=0.8,"A",IF(E23<=0.95,"B","C"))) -> #DIV/0! | G23: =VLOOKUP(B$22:B$42,I$22:M$42,5,0) -> #N/A | K23: =J23/J$42 -> #DIV/0! | L23: =K23+L22 -> #DIV/0! | M23: =_xlfn.IFS(L23<80%,"A",L23<=95%,"B",L23>95%,"C") -> #DIV/0!
D24: =C24/C$42 -> #DIV/0! | E24: =D24+E23 -> #DIV/0! | F24: =IF(AND(E24<=0),"C",IF(E24<=0.8,"A",IF(E24<=0.95,"B","C"))) -> #DIV/0! | G24: =VLOOKUP(B$22:B$42,I$22:M$42,5,0) -> #N/A | K24: =J24/J$42 -> #DIV/0! | L24: =K24+L23 -> #DIV/0! | M24: =_xlfn.IFS(L24<80%,"A",L24<=95%,"B",L24>95%,"C") -> #DIV/0!
D25: =C25/C$42 -> #DIV/0! | E25: =D25+E24 -> #DIV/0! | F25: =IF(AND(E25<=0),"C",IF(E25<=0.8,"A",IF(E25<=0.95,"B","C"))) -> #DIV/0! | G25: =VLOOKUP(B$22:B$42,I$22:M$42,5,0) -> #N/A | K25: =J25/J$42 -> #DIV/0! | L25: =K25+L24 -> #DIV/0! | M25: =_xlfn.IFS(L25<80%,"A",L25<=95%,"B",L25>95%,"C") -> #DIV/0!
D26: =C26/C$42 -> #DIV/0! | E26: =D26+E25 -> #DIV/0! | F26: =IF(AND(E26<=0),"C",IF(E26<=0.8,"A",IF(E26<=0.95,"B","C"))) -> #DIV/0! | G26: =VLOOKUP(B$22:B$42,I$22:M$42,5,0) -> #N/A | K26: =J26/J$42 -> #DIV/0! | L26: =K26+L25 -> #DIV/0! | M26: =_xlfn.IFS(L26<80%,"A",L26<=95%,"B",L26>95%,"C") -> #DIV/0!
D27: =C27/C$42 -> #DIV/0! | E27: =D27+E26 -> #DIV/0! | F27: =IF(AND(E27<=0),"C",IF(E27<=0.8,"A",IF(E27<=0.95,"B","C"))) -> #DIV/0! | G27: =VLOOKUP(B$22:B$42,I$22:M$42,5,0) -> #N/A | K27: =J27/J$42 -> #DIV/0! | L27: =K27+L26 -> #DIV/0! | M27: =_xlfn.IFS(L27<80%,"A",L27<=95%,"B",L27>95%,"C") -> #DIV/0!
D28: =C28/C$42 -> #DIV/0! | E28: =D28+E27 -> #DIV/0! | F28: =IF(AND(E28<=0),"C",IF(E28<=0.8,"A",IF(E28<=0.95,"B","C"))) -> #DIV/0! | G28: =VLOOKUP(B$22:B$42,I$22:M$42,5,0) -> #N/A | K28: =J28/J$42 -> #DIV/0! | L28: =K28+L27 -> #DIV/0! | M28: =_xlfn.IFS(L28<80%,"A",L28<=95%,"B",L28>95%,"C") -> #DIV/0!
D29: =C29/C$42 -> #DIV/0! | E29: =D29+E28 -> #DIV/0! | F29: =IF(AND(E29<=0),"C",IF(E29<=0.8,"A",IF(E29<=0.95,"B","C"))) -> #DIV/0! | G29: =VLOOKUP(B$22:B$42,I$22:M$42,5,0) -> #N/A | K29: =J29/J$42 -> #DIV/0! | L29: =K29+L28 -> #DIV/0! | M29: =_xlfn.IFS(L29<80%,"A",L29<=95%,"B",L29>95%,"C") -> #DIV/0!
D30: =C30/C$42 -> #DIV/0! | E30: =D30+E29 -> #DIV/0! | F30: =IF(AND(E30<=0),"C",IF(E30<=0.8,"A",IF(E30<=0.95,"B","C"))) -> #DIV/0! | G30: =VLOOKUP(B$22:B$42,I$22:M$42,5,0) -> #N/A | K30: =J30/J$42 -> #DIV/0! | L30: =K30+L29 -> #DIV/0! | M30: =_xlfn.IFS(L30<80%,"A",L30<=95%,"B",L30>95%,"C") -> #DIV/0!
D31: =C31/C$42 -> #DIV/0! | E31: =D31+E30 -> #DIV/0! | F31: =IF(AND(E31<=0),"C",IF(E31<=0.8,"A",IF(E31<=0.95,"B","C"))) -> #DIV/0! | G31: =VLOOKUP(B$22:B$42,I$22:M$42,5,0) -> #N/A | K31: =J31/J$42 -> #DIV/0! | L31: =K31+L30 -> #DIV/0! | M31: =_xlfn.IFS(L31<80%,"A",L31<=95%,"B",L31>95%,"C") -> #DIV/0!
D32: =C32/C$42 -> #DIV/0! | E32: =D32+E31 -> #DIV/0! | F32: =IF(AND(E32<=0),"C",IF(E32<=0.8,"A",IF(E32<=0.95,"B","C"))) -> #DIV/0! | G32: =VLOOKUP(B$22:B$42,I$22:M$42,5,0) -> #N/A | K32: =J32/J$42 -> #DIV/0! | L32: =K32+L31 -> #DIV/0! | M32: =_xlfn.IFS(L32<80%,"A",L32<=95%,"B",L32>95%,"C") -> #DIV/0!
D33: =C33/C$42 -> #DIV/0! | E33: =D33+E32 -> #DIV/0! | F33: =IF(AND(E33<=0),"C",IF(E33<=0.8,"A",IF(E33<=0.95,"B","C"))) -> #DIV/0! | G33: =VLOOKUP(B$22:B$42,I$22:M$42,5,0) -> #N/A | K33: =J33/J$42 -> #DIV/0! | L33: =K33+L32 -> #DIV/0! | M33: =_xlfn.IFS(L33<80%,"A",L33<=95%,"B",L33>95%,"C") -> #DIV/0!
D34: =C34/C$42 -> #DIV/0! | E34: =D34+E33 -> #DIV/0! | F34: =IF(AND(E34<=0),"C",IF(E34<=0.8,"A",IF(E34<=0.95,"B","C"))) -> #DIV/0! | G34: =VLOOKUP(B$22:B$42,I$22:M$42,5,0) -> #N/A | K34: =J34/J$42 -> #DIV/0! | L34: =K34+L33 -> #DIV/0! | M34: =_xlfn.IFS(L34<80%,"A",L34<=95%,"B",L34>95%,"C") -> #DIV/0!
... D41: =C41/C$42 -> #DIV/0! | E41: =D41+E40 -> #DIV/0! | F41: =IF(AND(E41<=0),"C",IF(E41<=0.8,"A",IF(E41<=0.95,"B","C"))) -> #DIV/0! | G41: =VLOOKUP(B$22:B$42,I$22:M$42,5,0) -> #N/A | K41: =J41/J$42 -> #DIV/0! | L41: =K41+L40 -> #DIV/0! | M41: =_xlfn.IFS(L41<80%,"A",L41<=95%,"B",L41>95%,"C") -> #DIV/0!
C42: =SUM(C22:C41) -> 0 | D42: =SUM(D22:D41) -> #DIV/0! | J42: =SUM(J22:J41) -> 0 | K42: =SUM(K22:K41) -> #DIV/0!

Sheet Юнит 02-08.03
B1: 02-08.03 | N1: Число дней | O1: 1 | AA1: Примерная налогооблагаемая база | AE1: =U24/AD1 -> #DIV/0! | AG1: на 1 единицу проданного товара
B2: Артикул поставщика | C2: Остаток на 09.03 | D2: В пути до клиента | E2: В пути от клиента | F2: Итого по складам ВБ | G2: Остаток на нашем складе на 02.09 | H2: Себетоимость на 1 ед на 29.09.25 | I2: Себестоимость остатков | J2: Оборачиваемость, дн | K2: Заказы, шт 01.03 | L2: Средняя цена, руб (столбец 32, AG) | M2: % выкупа за 7 дней (столбец 23, X) | N2: Скорость заказов | O2: Скорость продаж | P2: Кол-во ПРОДАЖИ | Q2: Кол-во ВОЗВРАТЫ | R2: Кол-во ПРОДАЖИ-ВОЗВРАТЫ | S2: Выручка ПРОДАЖИ | T2: Выручка ВОЗВРАТЫ | U2: Выручка с учетом согласованной скидки ПРОДАЖИ - ВОЗВРАТЫ | V2: Доля выручки, % от общего объема | W2: Себестоимость продаж | X2: Комиссия, руб | Y2: Комиссия, % | Z2: Логистика | AA2: Реклама | AB2: Хранение | AC2: Штрафы | AD2: Налог 1% | AE2: Прибыль | AG2: Выручка на 1 ед (средняя цена продажи со скидкой) | AH2: Себестоимость на 1 ед | AI2: Комиссия на 1 ед | AJ2: Логистика на 1 ед | AK2: Реклама на 1 ед | AL2: Прибыль на 1 ед | AM2: Маржинальность, % | AN2: Рентабельность, % | AP2: Прибыль с остатков
A3: 2676784153 | B3: черные с железкой классика | H3: 142.98 | I3: =C3*H3 -> 0 | N3: =K3/$O$1 -> 0 | O3: =R3/$O$1 -> 0 | P3: =SUMIFS('Отчет 02-08.03'!H:H,'Отчет 02-08.03'!D:D,"Выручка",'Отчет 02-08.03'!E:E,B3) -> 0 | Q3: =SUMIFS('Отчет 02-08.03'!H:H,'Отчет 02-08.03'!D:D,"Возврат выручки",'Отчет 02-08.03'!E:E,B3) -> 0 | R3: =P3-Q3 -> 0 | S3: =SUMIFS('Отчет 02-08.03'!P:P,'Отчет 02-08.03'!C:C,"Продажи",'Отчет 02-08.03'!E:E,B3) -> 0 | T3: =SUMIFS('Отчет 02-08.03'!P:P,'Отчет 02-08.03'!C:C,"Возвраты",'Отчет 02-08.03'!E:E,B3) -> 0 | U3: =S3+T3 -> 0 | V3: =U3/$U$24 -> #DIV/0! | W3: =R3*H3 -> 0 | X3: =-SUMIFS('Отчет 02-08.03'!P:P,'Отчет 02-08.03'!C:C,"Вознаграждение Ozon",'Отчет 02-08.03'!E:E,B3) -> 0 | Y3: =IF(U3=0,0,X3/U3) -> 0 | Z3: =-SUMIFS('Отчет 02-08.03'!P:P,'Отчет 02-08.03'!C:C,"Услуги доставки",'Отчет 02-08.03'!E:E,B3) -> 0 | AD3: =U3*1%/$AE$1 -> #DIV/0! | AE3: =U3-W3-X3-Z3-AA3-AB3-AC3-AD3 -> #DIV/0! | AG3: =IF(R3=0,0,U3/R3) -> 0 | AH3: =H3 -> 142.98 | AI3: =IF(R3=0,0,X3/R3) -> 0 | AJ3: =IF(P3=0,Z3/1,Z3/P3) -> 0 | AK3: =IF(P3=0,0,AA3/P3) -> 0 | AL3: =_xlfn.IFS(R3=0,AE3,R3<0,AE3/-R3,R3>0,AE3/R3) -> #DIV/0! | AM3: =IF(AG3=0,0,AL3/AG3) -> 0 | AN3: =IF(AH3=0,0,AL3/AH3) -> #DIV/0! | AP3: =AL3*C3 -> #DIV/0!
A4: 2676784638 | B4: qs черные | H4: 123.09 | I4: =C4*H4 -> 0 | N4: =K4/$O$1 -> 0 | O4: =R4/$O$1 -> 0 | P4: =SUMIFS('Отчет 02-08.03'!H:H,'Отчет 02-08.03'!D:D,"Выручка",'Отчет 02-08.03'!E:E,B4) -> 0 | Q4: =SUMIFS('Отчет 02-08.03'!H:H,'Отчет 02-08.03'!D:D,"Возврат выручки",'Отчет 02-08.03'!E:E,B4) -> 0 | R4: =P4-Q4 -> 0 | S4: =SUMIFS('Отчет 02-08.03'!P:P,'Отчет 02-08.03'!C:C,"Продажи",'Отчет 02-08.03'!E:E,B4) -> 0 | T4: =SUMIFS('Отчет 02-08.03'!P:P,'Отчет 02-08.03'!C:C,"Возвраты",'Отчет 02-08.03'!E:E,B4) -> 0 | U4: =S4+T4 -> 0 | V4: =U4/$U$24 -> #DIV/0! | W4: =R4*H4 -> 0 | X4: =-SUMIFS('Отчет 02-08.03'!P:P,'Отчет 02-08.03'!C:C,"Вознаграждение Ozon",'Отчет 02-08.03'!E:E,B4) -> 0 | Y4: =IF(U4=0,0,X4/U4) -> 0 | Z4: =-SUMIFS('Отчет 02-08.03'!P:P,'Отчет 02-08.03'!C:C,"Услуги доставки",'Отчет 02-08.03'!E:E,B4) -> 0 | AD4: =U4*1%/$AE$1 -> #DIV/0! | AE4: =U4-W4-X4-Z4-AA4-AB4-AC4-AD4 -> #DIV/0! | AG4: =IF(R4=0,0,U4/R4) -> 0 | AH4: =H4 -> 123.09 | AI4: =IF(R4=0,0,X4/R4) -> 0 | AJ4: =IF(P4=0,Z4/1,Z4/P4) -> 0 | AK4: =IF(P4=0,0,AA4/P4) -> 0 | AL4: {=_xlfn.IFS(R4=0,AE4,R4<0,AE4/-R4,R4>0,AE4/R4)} -> #DIV/0! | AM4: =IF(AG4=0,0,AL4/AG4) -> 0 | AN4: =IF(AH4=0,0,AL4/AH4) -> #DIV/0! | AP4: =AL4*C4 -> #DIV/0!
A5: 2676784504 | B5: qs синие | H5: 123.09 | I5: =C5*H5 -> 0 | N5: =K5/$O$1 -> 0 | O5: =R5/$O$1 -> 0 | P5: =SUMIFS('Отчет 02-08.03'!H:H,'Отчет 02-08.03'!D:D,"Выручка",'Отчет 02-08.03'!E:E,B5) -> 0 | Q5: =SUMIFS('Отчет 02-08.03'!H:H,'Отчет 02-08.03'!D:D,"Возврат выручки",'Отчет 02-08.03'!E:E,B5) -> 0 | R5: =P5-Q5 -> 0 | S5: =SUMIFS('Отчет 02-08.03'!P:P,'Отчет 02-08.03'!C:C,"Продажи",'Отчет 02-08.03'!E:E,B5) -> 0 | T5: =SUMIFS('Отчет 02-08.03'!P:P,'Отчет 02-08.03'!C:C,"Возвраты",'Отчет 02-08.03'!E:E,B5) -> 0 | U5: =S5+T5 -> 0 | V5: =U5/$U$24 -> #DIV/0! | W5: =R5*H5 -> 0 | X5: =-SUMIFS('Отчет 02-08.03'!P:P,'Отчет 02-08.03'!C:C,"Вознаграждение Ozon",'Отчет 02-08.03'!E:E,B5) -> 0 | Y5: =IF(U5=0,0,X5/U5) -> 0 | Z5: =-SUMIFS('Отчет 02-08.03'!P:P,'Отчет 02-08.03'!C:C,"Услуги доставки",'Отчет 02-08.03'!E:E,B5) -> 0 | AD5: =U5*1%/$AE$1 -> #DIV/0! | AE5: =U5-W5-X5-Z5-AA5-AB5-AC5-AD5 -> #DIV/0! | AG5: =IF(R5=0,0,U5/R5) -> 0 | AH5: =H5 -> 123.09 | AI5: =IF(R5=0,0,X5/R5) -> 0 | AJ5: =IF(P5=0,Z5/1,Z5/P5) -> 0 | AK5: =IF(P5=0,0,AA5/P5) -> 0 | AL5: {=_xlfn.IFS(R5=0,AE5,R5<0,AE5/-R5,R5>0,AE5/R5)} -> #DIV/0! | AM5: =IF(AG5=0,0,AL5/AG5) -> 0 | AN5: =IF(AH5=0,0,AL5/AH5) -> #DIV/0! | AP5: =AL5*C5 -> #DIV/0!
A6: 2676784514 | B6: qs желтые | H6: 123.09 | I6: =C6*H6 -> 0 | N6: =K6/$O$1 -> 0 | O6: =R6/$O$1 -> 0 | P6: =SUMIFS('Отчет 02-08.03'!H:H,'Отчет 02-08.03'!D:D,"Выручка",'Отчет 02-08.03'!E:E,B6) -> 0 | Q6: =SUMIFS('Отчет 02-08.03'!H:H,'Отчет 02-08.03'!D:D,"Возврат выручки",'Отчет 02-08.03'!E:E,B6) -> 0 | R6: =P6-Q6 -> 0 | S6: =SUMIFS('Отчет 02-08.03'!P:P,'Отчет 02-08.03'!C:C,"Продажи",'Отчет 02-08.03'!E:E,B6) -> 0 | T6: =SUMIFS('Отчет 02-08.03'!P:P,'Отчет 02-08.03'!C:C,"Возвраты",'Отчет 02-08.03'!E:E,B6) -> 0 | U6: =S6+T6 -> 0 | V6: =U6/$U$24 -> #DIV/0! | W6: =R6*H6 -> 0 | X6: =-SUMIFS('Отчет 02-08.03'!P:P,'Отчет 02-08.03'!C:C,"Вознаграждение Ozon",'Отчет 02-08.03'!E:E,B6) -> 0 | Y6: =IF(U6=0,0,X6/U6) -> 0 | Z6: =-SUMIFS('Отчет 02-08.03'!P:P,'Отчет 02-08.03'!C:C,"Услуги доставки",'Отчет 02-08.03'!E:E,B6) -> 0 | AD6: =U6*1%/$AE$1 -> #DIV/0! | AE6: =U6-W6-X6-Z6-AA6-AB6-AC6-AD6 -> #DIV/0! | AG6: =IF(R6=0,0,U6/R6) -> 0 | AH6: =H6 -> 123.09 | AI6: =IF(R6=0,0,X6/R6) -> 0 | AJ6: =IF(P6=0,Z6/1,Z6/P6) -> 0 | AK6: =IF(P6=0,0,AA6/P6) -> 0 | AL6: {=_xlfn.IFS(R6=0,AE6,R6<0,AE6/-R6,R6>0,AE6/R6)} -> #DIV/0! | AM6: =IF(AG6=0,0,AL6/AG6) -> 0 | AN6: =IF(AH6=0,0,AL6/AH6) -> #DIV/0! | AP6: =AL6*C6 -> #DIV/0!
A7: 2676784181 | B7: qs коричневые | H7: 117.24 | I7: =C7*H7 -> 0 | N7: =K7/$O$1 -> 0 | O7: =R7/$O$1 -> 0 | P7: =SUMIFS('Отчет 02-08.03'!H:H,'Отчет 02-08.03'!D:D,"Выручка",'Отчет 02-08.03'!E:E,B7) -> 0 | Q7: =SUMIFS('Отчет 02-08.03'!H:H,'Отчет 02-08.03'!D:D,"Возврат выручки",'Отчет 02-08.03'!E:E,B7) -> 0 | R7: =P7-Q7 -> 0 | S7: =SUMIFS('Отчет 02-08.03'!P:P,'Отчет 02-08.03'!C:C,"Продажи",'Отчет 02-08.03'!E:E,B7) -> 0 | T7: =SUMIFS('Отчет 02-08.03'!P:P,'Отчет 02-08.03'!C:C,"Возвраты",'Отчет 02-08.03'!E:E,B7) -> 0 | U7: =S7+T7 -> 0 | V7: =U7/$U$24 -> #DIV/0! | W7: =R7*H7 -> 0 | X7: =-SUMIFS('Отчет 02-08.03'!P:P,'Отчет 02-08.03'!C:C,"Вознаграждение Ozon",'Отчет 02-08.03'!E:E,B7) -> 0 | Y7: =IF(U7=0,0,X7/U7) -> 0 | Z7: =-SUMIFS('Отчет 02-08.03'!P:P,'Отчет 02-08.03'!C:C,"Услуги доставки",'Отчет 02-08.03'!E:E,B7) -> 0 | AD7: =U7*1%/$AE$1 -> #DIV/0! | AE7: =U7-W7-X7-Z7-AA7-AB7-AC7-AD7 -> #DIV/0! | AG7: =IF(R7=0,0,U7/R7) -> 0 | AH7: =H7 -> 117.24 | AI7: =IF(R7=0,0,X7/R7) -> 0 | AJ7: =IF(P7=0,Z7/1,Z7/P7) -> 0 | AK7: =IF(P7=0,0,AA7/P7) -> 0 | AL7: {=_xlfn.IFS(R7=0,AE7,R7<0,AE7/-R7,R7>0,AE7/R7)} -> #DIV/0! | AM7: =IF(AG7=0,0,AL7/AG7) -> 0 | AN7: =IF(AH7=0,0,AL7/AH7) -> #DIV/0! | AP7: =AL7*C7 -> #DIV/0!
A8: 2676783005 | B8: MR8854 C2 | H8: 169.89 | I8: =C8*H8 -> 0 | N8: =K8/$O$1 -> 0 | O8: =R8/$O$1 -> 0 | P8: =SUMIFS('Отчет 02-08.03'!H:H,'Отчет 02-08.03'!D:D,"Выручка",'Отчет 02-08.03'!E:E,B8) -> 0 | Q8: =SUMIFS('Отчет 02-08.03'!H:H,'Отчет 02-08.03'!D:D,"Возврат выручки",'Отчет 02-08.03'!E:E,B8) -> 0 | R8: =P8-Q8 -> 0 | S8: =SUMIFS('Отчет 02-08.03'!P:P,'Отчет 02-08.03'!C:C,"Продажи",'Отчет 02-08.03'!E:E,B8) -> 0 | T8: =SUMIFS('Отчет 02-08.03'!P:P,'Отчет 02-08.03'!C:C,"Возвраты",'Отчет 02-08.03'!E:E,B8) -> 0 | U8: =S8+T8 -> 0 | V8: =U8/$U$24 -> #DIV/0! | W8: =R8*H8 -> 0 | X8: =-SUMIFS('Отчет 02-08.03'!P:P,'Отчет 02-08.03'!C:C,"Вознаграждение Ozon",'Отчет 02-08.03'!E:E,B8) -> 0 | Y8: =IF(U8=0,0,X8/U8) -> 0 | Z8: =-SUMIFS('Отчет 02-08.03'!P:P,'Отчет 02-08.03'!C:C,"Услуги доставки",'Отчет 02-08.03'!E:E,B8) -> 0 | AD8: =U8*1%/$AE$1 -> #DIV/0! | AE8: =U8-W8-X8-Z8-AA8-AB8-AC8-AD8 -> #DIV/0! | AG8: =IF(R8=0,0,U8/R8) -> 0 | AH8: =H8 -> 169.89 | AI8: =IF(R8=0,0,X8/R8) -> 0 | AJ8: =IF(P8=0,Z8/1,Z8/P8) -> 0 | AK8: =IF(P8=0,0,AA8/P8) -> 0 | AL8: {=_xlfn.IFS(R8=0,AE8,R8<0,AE8/-R8,R8>0,AE8/R8)} -> #DIV/0! | AM8: =IF(AG8=0,0,AL8/AG8) -> 0 | AN8: =IF(AH8=0,0,AL8/AH8) -> #DIV/0! | AP8: =AL8*C8 -> #DIV/0!
A9: 3405092860 | B9: th черн | H9: 123 | I9: =C9*H9 -> 0 | N9: =K9/$O$1 -> 0 | O9: =R9/$O$1 -> 0 | P9: =SUMIFS('Отчет 02-08.03'!H:H,'Отчет 02-08.03'!D:D,"Выручка",'Отчет 02-08.03'!E:E,B9) -> 0 | Q9: =SUMIFS('Отчет 02-08.03'!H:H,'Отчет 02-08.03'!D:D,"Возврат выручки",'Отчет 02-08.03'!E:E,B9) -> 0 | R9: =P9-Q9 -> 0 | S9: =SUMIFS('Отчет 02-08.03'!P:P,'Отчет 02-08.03'!C:C,"Продажи",'Отчет 02-08.03'!E:E,B9) -> 0 | T9: =SUMIFS('Отчет 02-08.03'!P:P,'Отчет 02-08.03'!C:C,"Возвраты",'Отчет 02-08.03'!E:E,B9) -> 0 | U9: =S9+T9 -> 0 | V9: =U9/$U$24 -> #DIV/0! | W9: =R9*H9 -> 0 | X9: =-SUMIFS('Отчет 02-08.03'!P:P,'Отчет 02-08.03'!C:C,"Вознаграждение Ozon",'Отчет 02-08.03'!E:E,B9) -> 0 | Y9: =IF(U9=0,0,X9/U9) -> 0 | Z9: =-SUMIFS('Отчет 02-08.03'!P:P,'Отчет 02-08.03'!C:C,"Услуги доставки",'Отчет 02-08.03'!E:E,B9) -> 0 | AD9: =U9*1%/$AE$1 -> #DIV/0! | AE9: =U9-W9-X9-Z9-AA9-AB9-AC9-AD9 -> #DIV/0! | AG9: =IF(R9=0,0,U9/R9) -> 0 | AH9: =H9 -> 123 | AI9: =IF(R9=0,0,X9/R9) -> 0 | AJ9: =IF(P9=0,Z9/1,Z9/P9) -> 0 | AK9: =IF(P9=0,0,AA9/P9) -> 0 | AL9: {=_xlfn.IFS(R9=0,AE9,R9<0,AE9/-R9,R9>0,AE9/R9)} -> #DIV/0! | AM9: =IF(AG9=0,0,AL9/AG9) -> 0 | AN9: =IF(AH9=0,0,AL9/AH9) -> #DIV/0! | AP9: =AL9*C9 -> #DIV/0!
A10: 3405092836 | B10: th син | H10: 123 | I10: =C10*H10 -> 0 | N10: =K10/$O$1 -> 0 | O10: =R10/$O$1 -> 0 | P10: =SUMIFS('Отчет 02-08.03'!H:H,'Отчет 02-08.03'!D:D,"Выручка",'Отчет 02-08.03'!E:E,B10) -> 0 | Q10: =SUMIFS('Отчет 02-08.03'!H:H,'Отчет 02-08.03'!D:D,"Возврат выручки",'Отчет 02-08.03'!E:E,B10) -> 0 | R10: =P10-Q10 -> 0 | S10: =SUMIFS('Отчет 02-08.03'!P:P,'Отчет 02-08.03'!C:C,"Продажи",'Отчет 02-08.03'!E:E,B10) -> 0 | T10: =SUMIFS('Отчет 02-08.03'!P:P,'Отчет 02-08.03'!C:C,"Возвраты",'Отчет 02-08.03'!E:E,B10) -> 0 | U10: =S10+T10 -> 0 | V10: =U10/$U$24 -> #DIV/0! | W10: =R10*H10 -> 0 | X10: =-SUMIFS('Отчет 02-08.03'!P:P,'Отчет 02-08.03'!C:C,"Вознаграждение Ozon",'Отчет 02-08.03'!E:E,B10) -> 0 | Y10: =IF(U10=0,0,X10/U10) -> 0 | Z10: =-SUMIFS('Отчет 02-08.03'!P:P,'Отчет 02-08.03'!C:C,"Услуги доставки",'Отчет 02-08.03'!E:E,B10) -> 0 | AD10: =U10*1%/$AE$1 -> #DIV/0! | AE10: =U10-W10-X10-Z10-AA10-AB10-AC10-AD10 -> #DIV/0! | AG10: =IF(R10=0,0,U10/R10) -> 0 | AH10: =H10 -> 123 | AI10: =IF(R10=0,0,X10/R10) -> 0 | AJ10: =IF(P10=0,Z10/1,Z10/P10) -> 0 | AK10: =IF(P10=0,0,AA10/P10) -> 0 | AL10: {=_xlfn.IFS(R10=0,AE10,R10<0,AE10/-R10,R10>0,AE10/R10)} -> #DIV/0! | AM10: =IF(AG10=0,0,AL10/AG10) -> 0 | AN10: =IF(AH10=0,0,AL10/AH10) -> #DIV/0! | AP10: =AL10*C10 -> #DIV/0!
A11: 3064346962 | B11: th желт | H11: 123 | I11: =C11*H11 -> 0 | N11: =K11/$O$1 -> 0 | O11: =R11/$O$1 -> 0 | P11: =SUMIFS('Отчет 02-08.03'!H:H,'Отчет 02-08.03'!D:D,"Выручка",'Отчет 02-08.03'!E:E,B11) -> 0 | Q11: =SUMIFS('Отчет 02-08.03'!H:H,'Отчет 02-08.03'!D:D,"Возврат выручки",'Отчет 02-08.03'!E:E,B11) -> 0 | R11: =P11-Q11 -> 0 | S11: =SUMIFS('Отчет 02-08.03'!P:P,'Отчет 02-08.03'!C:C,"Продажи",'Отчет 02-08.03'!E:E,B11) -> 0 | T11: =SUMIFS('Отчет 02-08.03'!P:P,'Отчет 02-08.03'!C:C,"Возвраты",'Отчет 02-08.03'!E:E,B11) -> 0 | U11: =S11+T11 -> 0 | V11: =U11/$U$24 -> #DIV/0! | W11: =R11*H11 -> 0 | X11: =-SUMIFS('Отчет 02-08.03'!P:P,'Отчет 02-08.03'!C:C,"Вознаграждение Ozon",'Отчет 02-08.03'!E:E,B11) -> 0 | Y11: =IF(U11=0,0,X11/U11) -> 0 | Z11: =-SUMIFS('Отчет 02-08.03'!P:P,'Отчет 02-08.03'!C:C,"Услуги доставки",'Отчет 02-08.03'!E:E,B11) -> 0 | AD11: =U11*1%/$AE$1 -> #DIV/0! | AE11: =U11-W11-X11-Z11-AA11-AB11-AC11-AD11 -> #DIV/0! | AG11: =IF(R11=0,0,U11/R11) -> 0 | AH11: =H11 -> 123 | AI11: =IF(R11=0,0,X11/R11) -> 0 | AJ11: =IF(P11=0,Z11/1,Z11/P11) -> 0 | AK11: =IF(P11=0,0,AA11/P11) -> 0 | AL11: {=_xlfn.IFS(R11=0,AE11,R11<0,AE11/-R11,R11>0,AE11/R11)} -> #DIV/0! | AM11: =IF(AG11=0,0,AL11/AG11) -> 0 | AN11: =IF(AH11=0,0,AL11/AH11) -> #DIV/0! | AP11: =AL11*C11 -> #DIV/0!
A12: 3405092873 | B12: th коричн | H12: 117 | I12: =C12*H12 -> 0 | N12: =K12/$O$1 -> 0 | O12: =R12/$O$1 -> 0 | P12: =SUMIFS('Отчет 02-08.03'!H:H,'Отчет 02-08.03'!D:D,"Выручка",'Отчет 02-08.03'!E:E,B12) -> 0 | Q12: =SUMIFS('Отчет 02-08.03'!H:H,'Отчет 02-08.03'!D:D,"Возврат выручки",'Отчет 02-08.03'!E:E,B12) -> 0 | R12: =P12-Q12 -> 0 | S12: =SUMIFS('Отчет 02-08.03'!P:P,'Отчет 02-08.03'!C:C,"Продажи",'Отчет 02-08.03'!E:E,B12) -> 0 | T12: =SUMIFS('Отчет 02-08.03'!P:P,'Отчет 02-08.03'!C:C,"Возвраты",'Отчет 02-08.03'!E:E,B12) -> 0 | U12: =S12+T12 -> 0 | V12: =U12/$U$24 -> #DIV/0! | W12: =R12*H12 -> 0 | X12: =-SUMIFS('Отчет 02-08.03'!P:P,'Отчет 02-08.03'!C:C,"Вознаграждение Ozon",'Отчет 02-08.03'!E:E,B12) -> 0 | Y12: =IF(U12=0,0,X12/U12) -> 0 | Z12: =-SUMIFS('Отчет 02-08.03'!P:P,'Отчет 02-08.03'!C:C,"Услуги доставки",'Отчет 02-08.03'!E:E,B12) -> 0 | AD12: =U12*1%/$AE$1 -> #DIV/0! | AE12: =U12-W12-X12-Z12-AA12-AB12-AC12-AD12 -> #DIV/0! | AG12: =IF(R12=0,0,U12/R12) -> 0 | AH12: =H12 -> 117 | AI12: =IF(R12=0,0,X12/R12) -> 0 | AJ12: =IF(P12=0,Z12/1,Z12/P12) -> 0 | AK12: =IF(P12=0,0,AA12/P12) -> 0 | AL12: {=_xlfn.IFS(R12=0,AE12,R12<0,AE12/-R12,R12>0,AE12/R12)} -> #DIV/0! | AM12: =IF(AG12=0,0,AL12/AG12) -> 0 | AN12: =IF(AH12=0,0,AL12/AH12) -> #DIV/0! | AP12: =AL12*C12 -> #DIV/0!
A13: 3405092993 | B13: flip черный | H13: 123 | I13: =C13*H13 -> 0 | N13: =K13/$O$1 -> 0 | O13: =R13/$O$1 -> 0 | P13: =SUMIFS('Отчет 02-08.03'!H:H,'Отчет 02-08.03'!D:D,"Выручка",'Отчет 02-08.03'!E:E,B13) -> 0 | Q13: =SUMIFS('Отчет 02-08.03'!H:H,'Отчет 02-08.03'!D:D,"Возврат выручки",'Отчет 02-08.03'!E:E,B13) -> 0 | R13: =P13-Q13 -> 0 | S13: =SUMIFS('Отчет 02-08.03'!P:P,'Отчет 02-08.03'!C:C,"Продажи",'Отчет 02-08.03'!E:E,B13) -> 0 | T13: =SUMIFS('Отчет 02-08.03'!P:P,'Отчет 02-08.03'!C:C,"Возвраты",'Отчет 02-08.03'!E:E,B13) -> 0 | U13: =S13+T13 -> 0 | V13: =U13/$U$24 -> #DIV/0! | W13: =R13*H13 -> 0 | X13: =-SUMIFS('Отчет 02-08.03'!P:P,'Отчет 02-08.03'!C:C,"Вознаграждение Ozon",'Отчет 02-08.03'!E:E,B13) -> 0 | Y13: =IF(U13=0,0,X13/U13) -> 0 | Z13: =-SUMIFS('Отчет 02-08.03'!P:P,'Отчет 02-08.03'!C:C,"Услуги доставки",'Отчет 02-08.03'!E:E,B13) -> 0 | AD13: =U13*1%/$AE$1 -> #DIV/0! | AE13: =U13-W13-X13-Z13-AA13-AB13-AC13-AD13 -> #DIV/0! | AG13: =IF(R13=0,0,U13/R13) -> 0 | AH13: =H13 -> 123 | AI13: =IF(R13=0,0,X13/R13) -> 0 | AJ13: =IF(P13=0,Z13/1,Z13/P13) -> 0 | AK13: =IF(P13=0,0,AA13/P13) -> 0 | AL13: {=_xlfn.IFS(R13=0,AE13,R13<0,AE13/-R13,R13>0,AE13/R13)} -> #DIV/0! | AM13: =IF(AG13=0,0,AL13/AG13) -> 0 | AN13: =IF(AH13=0,0,AL13/AH13) -> #DIV/0! | AP13: =AL13*C13 -> #DIV/0!
A14: 3405092868 | B14: flip синий | H14: 123 | I14: =C14*H14 -> 0 | N14: =K14/$O$1 -> 0 | O14: =R14/$O$1 -> 0 | P14: =SUMIFS('Отчет 02-08.03'!H:H,'Отчет 02-08.03'!D:D,"Выручка",'Отчет 02-08.03'!E:E,B14) -> 0 | Q14: =SUMIFS('Отчет 02-08.03'!H:H,'Отчет 02-08.03'!D:D,"Возврат выручки",'Отчет 02-08.03'!E:E,B14) -> 0 | R14: =P14-Q14 -> 0 | S14: =SUMIFS('Отчет 02-08.03'!P:P,'Отчет 02-08.03'!C:C,"Продажи",'Отчет 02-08.03'!E:E,B14) -> 0 | T14: =SUMIFS('Отчет 02-08.03'!P:P,'Отчет 02-08.03'!C:C,"Возвраты",'Отчет 02-08.03'!E:E,B14) -> 0 | U14: =S14+T14 -> 0 | V14: =U14/$U$24 -> #DIV/0! | W14: =R14*H14 -> 0 | X14: =-SUMIFS('Отчет 02-08.03'!P:P,'Отчет 02-08.03'!C:C,"Вознаграждение Ozon",'Отчет 02-08.03'!E:E,B14) -> 0 | Y14: =IF(U14=0,0,X14/U14) -> 0 | Z14: =-SUMIFS('Отчет 02-08.03'!P:P,'Отчет 02-08.03'!C:C,"Услуги доставки",'Отчет 02-08.03'!E:E,B14) -> 0 | AD14: =U14*1%/$AE$1 -> #DIV/0! | AE14: =U14-W14-X14-Z14-AA14-AB14-AC14-AD14 -> #DIV/0! | AG14: =IF(R14=0,0,U14/R14) -> 0 | AH14: =H14 -> 123 | AI14: =IF(R14=0,0,X14/R14) -> 0 | AJ14: =IF(P14=0,Z14/1,Z14/P14) -> 0 | AK14: =IF(P14=0,0,AA14/P14) -> 0 | AL14: {=_xlfn.IFS(R14=0,AE14,R14<0,AE14/-R14,R14>0,AE14/R14)} -> #DIV/0! | AM14: =IF(AG14=0,0,AL14/AG14) -> 0 | AN14: =IF(AH14=0,0,AL14/AH14) -> #DIV/0! | AP14: =AL14*C14 -> #DIV/0!
A15: 3064346642 | B15: flip жел | H15: 123 | I15: =C15*H15 -> 0 | N15: =K15/$O$1 -> 0 | O15: =R15/$O$1 -> 0 | P15: =SUMIFS('Отчет 02-08.03'!H:H,'Отчет 02-08.03'!D:D,"Выручка",'Отчет 02-08.03'!E:E,B15) -> 0 | Q15: =SUMIFS('Отчет 02-08.03'!H:H,'Отчет 02-08.03'!D:D,"Возврат выручки",'Отчет 02-08.03'!E:E,B15) -> 0 | R15: =P15-Q15 -> 0 | S15: =SUMIFS('Отчет 02-08.03'!P:P,'Отчет 02-08.03'!C:C,"Продажи",'Отчет 02-08.03'!E:E,B15) -> 0 | T15: =SUMIFS('Отчет 02-08.03'!P:P,'Отчет 02-08.03'!C:C,"Возвраты",'Отчет 02-08.03'!E:E,B15) -> 0 | U15: =S15+T15 -> 0 | V15: =U15/$U$24 -> #DIV/0! | W15: =R15*H15 -> 0 | X15: =-SUMIFS('Отчет 02-08.03'!P:P,'Отчет 02-08.03'!C:C,"Вознаграждение Ozon",'Отчет 02-08.03'!E:E,B15) -> 0 | Y15: =IF(U15=0,0,X15/U15) -> 0 | Z15: =-SUMIFS('Отчет 02-08.03'!P:P,'Отчет 02-08.03'!C:C,"Услуги доставки",'Отчет 02-08.03'!E:E,B15) -> 0 | AD15: =U15*1%/$AE$1 -> #DIV/0! | AE15: =U15-W15-X15-Z15-AA15-AB15-AC15-AD15 -> #DIV/0! | AG15: =IF(R15=0,0,U15/R15) -> 0 | AH15: =H15 -> 123 | AI15: =IF(R15=0,0,X15/R15) -> 0 | AJ15: =IF(P15=0,Z15/1,Z15/P15) -> 0 | AK15: =IF(P15=0,0,AA15/P15) -> 0 | AL15: {=_xlfn.IFS(R15=0,AE15,R15<0,AE15/-R15,R15>0,AE15/R15)} -> #DIV/0! | AM15: =IF(AG15=0,0,AL15/AG15) -> 0 | AN15: =IF(AH15=0,0,AL15/AH15) -> #DIV/0! | AP15: =AL15*C15 -> #DIV/0!
A16: 3405092287 | B16: flip коричневый | H16: 117 | I16: =C16*H16 -> 0 | N16: =K16/$O$1 -> 0 | O16: =R16/$O$1 -> 0 | P16: =SUMIFS('Отчет 02-08.03'!H:H,'Отчет 02-08.03'!D:D,"Выручка",'Отчет 02-08.03'!E:E,B16) -> 0 | Q16: =SUMIFS('Отчет 02-08.03'!H:H,'Отчет 02-08.03'!D:D,"Возврат выручки",'Отчет 02-08.03'!E:E,B16) -> 0 | R16: =P16-Q16 -> 0 | S16: =SUMIFS('Отчет 02-08.03'!P:P,'Отчет 02-08.03'!C:C,"Продажи",'Отчет 02-08.03'!E:E,B16) -> 0 | T16: =SUMIFS('Отчет 02-08.03'!P:P,'Отчет 02-08.03'!C:C,"Возвраты",'Отчет 02-08.03'!E:E,B16) -> 0 | U16: =S16+T16 -> 0 | V16: =U16/$U$24 -> #DIV/0! | W16: =R16*H16 -> 0 | X16: =-SUMIFS('Отчет 02-08.03'!P:P,'Отчет 02-08.03'!C:C,"Вознаграждение Ozon",'Отчет 02-08.03'!E:E,B16) -> 0 | Y16: =IF(U16=0,0,X16/U16) -> 0 | Z16: =-SUMIFS('Отчет 02-08.03'!P:P,'Отчет 02-08.03'!C:C,"Услуги доставки",'Отчет 02-08.03'!E:E,B16) -> 0 | AD16: =U16*1%/$AE$1 -> #DIV/0! | AE16: =U16-W16-X16-Z16-AA16-AB16-AC16-AD16 -> #DIV/0! | AG16: =IF(R16=0,0,U16/R16) -> 0 | AH16: =H16 -> 117 | AI16: =IF(R16=0,0,X16/R16) -> 0 | AJ16: =IF(P16=0,Z16/1,Z16/P16) -> 0 | AK16: =IF(P16=0,0,AA16/P16) -> 0 | AL16: {=_xlfn.IFS(R16=0,AE16,R16<0,AE16/-R16,R16>0,AE16/R16)} -> #DIV/0! | AM16: =IF(AG16=0,0,AL16/AG16) -> 0 | AN16: =IF(AH16=0,0,AL16/AH16) -> #DIV/0! | AP16: =AL16*C16 -> #DIV/0!
AG17: =AVERAGEIF(AG3:AG15,"<>0",AG3:AG15) -> #DIV/0! | AH17: =AVERAGEIF(AH3:AH15,"<>0",AH3:AH15) -> 127.26 | AI17: =AVERAGEIF(AI3:AI15,"<>0",AI3:AI15) -> #DIV/0! | AJ17: =AVERAGEIF(AJ3:AJ15,"<>0",AJ3:AJ15) -> #DIV/0! | AK17: =AVERAGEIF(AK3:AK15,"<>0",AK3:AK15) -> #DIV/0! | AL17: =AVERAGEIF(AL3:AL15,"<>0",AL3:AL15) -> #DIV/0! | AM17: =AVERAGEIF(AM3:AM15,"<>0",AM3:AM15) -> #DIV/0! | AN17: =AVERAGEIF(AN3:AN15,"<>0",AN3:AN15) -> #DIV/0!
A18: Итого очки | C18: =SUM(C3:C16) -> 0 | E18: 108496 | F18: 597 | G18: 295 | I18: =SUM(I3:I16) -> 0 | K18: =SUM(K3:K16) -> 0 | P18: =SUM(P3:P16) -> 0 | Q18: =SUM(Q3:Q16) -> 0 | R18: =SUM(R3:R16) -> 0 | S18: =SUM(S3:S16) -> 0 | T18: =SUM(T3:T16) -> 0 | U18: =SUM(U3:U16) -> 0 | V18: =SUM(V3:V16) -> #DIV/0! | W18: =SUM(W3:W16) -> 0 | X18: =SUM(X3:X16) -> 0 | Y18: =IF(U18=0,0,X18/U18) -> 0 | Z18: =SUM(Z3:Z16) -> 0 | AA18: =IFERROR(P18*AA24/P24,0) -> 0 | AB18: =SUM(AB3:AB16) -> 0 | AC18: =SUM(AC3:AC16) -> 0 | AD18: =SUM(AD3:AD16) -> #DIV/0! | AE18: =SUM(AE3:AE16) -> #DIV/0! | AP18: =SUM(AP3:AP16) -> #DIV/0! | AZ18: 18592777
AG21: =AVERAGEIF(AG20:AG20,"<>0",AG20:AG20) -> #DIV/0! | AH21: =AVERAGEIF(AH20:AH20,"<>0",AH20:AH20) -> #DIV/0! | AI21: =AVERAGEIF(AI20:AI20,"<>0",AI20:AI20) -> #DIV/0! | AJ21: =AVERAGEIF(AJ20:AJ20,"<>0",AJ20:AJ20) -> #DIV/0! | AK21: =AVERAGEIF(AK20:AK20,"<>0",AK20:AK20) -> #DIV/0! | AL21: =AVERAGEIF(AL20:AL20,"<>0",AL20:AL20) -> #DIV/0! | AM21: =AVERAGEIF(AM20:AM20,"<>0",AM20:AM20) -> #DIV/0! | AN21: =AVERAGEIF(AN20:AN20,"<>0",AN20:AN20) -> #DIV/0!
C22: =SUM(C20:C20) -> 0 | I22: =SUM(I20:I20) -> 0 | K22: =SUM(K20:K20) -> 0 | P22: =SUM(P20:P20) -> 0 | Q22: =SUM(Q20:Q20) -> 0 | R22: =SUM(R20:R20) -> 0 | S22: =SUM(S20:S20) -> 0 | T22: =SUM(T20:T20) -> 0 | U22: =SUM(U20:U20) -> 0 | V22: =SUM(V20:V20) -> 0 | W22: =SUM(W20:W20) -> 0 | X22: =SUM(X20:X20) -> 0 | Y22: =IF(U22=0,0,X22/U22) -> 0 | Z22: =SUM(Z20:Z20) -> 0 | AB22: =SUM(AB20:AB20) -> 0 | AC22: =SUM(AC20:AC20) -> 0 | AD22: =SUM(AD20:AD20) -> 0 | AE22: =SUM(AE20:AE20) -> 0 | AP22: =SUM(AP20:AP20) -> 0
A24: ИТОГО | C24: =C18+C22 -> 0 | D24: =SUM(D3:D20) -> 0 | E24: =SUM(E3:E20) -> 108496 | F24: =SUM(F3:F20) -> 597 | G24: =SUM(G3:G20) -> 295 | I24: =I18+I22 -> 0 | J24: =J18+J22 -> 0 | K24: =K18+K22 -> 0 | P24: =P18+P22 -> 0 | Q24: =Q18+Q22 -> 0 | R24: =R18-R22 -> 0 | S24: =S18+S22 -> 0 | T24: =T18+T22 -> 0 | U24: =U18+U22 -> 0 | V24: =V18+V22 -> #DIV/0! | W24: =W18+W22 -> 0 | X24: =X18+X22 -> 0 | Y24: =X24/U24 -> #DIV/0! | Z24: =Z18+Z22 -> 0 | AC24: =SUM(AC3:AC20) -> 0 | AD24: =AD18+AD22 -> #DIV/0! | AE24: =AE18+AE22 -> #DIV/0! | AK24: =AA25/P24 -> #DIV/0! | AP24: =SUM(AP3:AP20) -> #DIV/0!
AA25: =SUM(AA3:AA16) -> 0
AD26: Закрепление отзыва
AD27: Баллы за отзывы
I29: Себестоимость остатков | K29: Прибыль с остатков | L29: Рентабельность товарных остатков
H31: до 60 дн | I31: =SUMIF(J3:J20,"<60",I3:I20) -> 0 | J31: =I31/I24 -> #DIV/0! | K31: =SUMIF(J3:J20,"<60",AP3:AP20) -> 0 | L31: =K31/I31 -> #DIV/0!
H32: 60-120 дн | I32: =I24-I33-I31 -> 0 | J32: =I32/I24 -> #DIV/0! | K32: =AP24-K31-K33 -> #DIV/0! | L32: =K32/I32 -> #DIV/0!
H33: > 120 дн | I33: =SUMIF(J3:J20,">120",I3:I20) -> 0 | J33: =I33/I24 -> #DIV/0! | K33: =SUMIF(J3:J20,">120",AP3:AP20) -> 0 | L33: =K33/I33 -> #DIV/0!
H35: Если товар на сайте менее 30 дней - оборачиваемость 0

Sheet Юнит 01.03
B1: 01.03 | N1: Число дней | O1: 1 | AA1: Примерная налогооблагаемая база | AD1: =12549+91 -> 12640 | AE1: =U24/AD1 -> 2.3860759 | AG1: на 1 единицу проданного товара
B2: Артикул поставщика | C2: Остаток на 02.03 | D2: В пути до клиента | E2: В пути от клиента | F2: Итого по складам ВБ | G2: Остаток на нашем складе на 02.09 | H2: Себетоимость на 1 ед на 29.09.25 | I2: Себестоимость остатков | J2: Оборачиваемость, дн | K2: Заказы, шт 01.03 | L2: Средняя цена, руб (столбец 32, AG) | M2: % выкупа за 7 дней (столбец 23, X) | N2: Скорость заказов | O2: Скорость продаж | P2: Кол-во ПРОДАЖИ | Q2: Кол-во ВОЗВРАТЫ | R2: Кол-во ПРОДАЖИ-ВОЗВРАТЫ | S2: Выручка ПРОДАЖИ | T2: Выручка ВОЗВРАТЫ | U2: Выручка с учетом согласованной скидки ПРОДАЖИ - ВОЗВРАТЫ | V2: Доля выручки, % от общего объема | W2: Себестоимость продаж | X2: Комиссия, руб | Y2: Комиссия, % | Z2: Логистика | AA2: Реклама | AB2: Хранение | AC2: Штрафы | AD2: Налог 1% | AE2: Прибыль | AG2: Выручка на 1 ед (средняя цена продажи со скидкой) | AH2: Себестоимость на 1 ед | AI2: Комиссия на 1 ед | AJ2: Логистика на 1 ед | AK2: Реклама на 1 ед | AL2: Прибыль на 1 ед | AM2: Маржинальность, % | AN2: Рентабельность, % | AP2: Прибыль с остатков
A3: 2676784153 | B3: черные с железкой классика | H3: 142.98 | I3: =C3*H3 -> 0 | K3: 1 | N3: =K3/$O$1 -> 1 | O3: =R3/$O$1 -> 1 | P3: =SUMIFS('Отчет 01.03'!H:H,'Отчет 01.03'!D:D,"Выручка",'Отчет 01.03'!E:E,B3) -> 1 | Q3: =SUMIFS('Отчет 01.03'!H:H,'Отчет 01.03'!D:D,"Возврат выручки",'Отчет 01.03'!E:E,B3) -> 0 | R3: =P3-Q3 -> 1 | S3: =SUMIFS('Отчет 01.03'!P:P,'Отчет 01.03'!C:C,"Продажи",'Отчет 01.03'!E:E,B3) -> 2450 | T3: =SUMIFS('Отчет 01.03'!P:P,'Отчет 01.03'!C:C,"Возвраты",'Отчет 01.03'!E:E,B3) -> 0 | U3: =S3+T3 -> 2450 | V3: =U3/$U$24 -> 0.081233422 | W3: =R3*H3 -> 142.98 | X3: =-SUMIFS('Отчет 01.03'!P:P,'Отчет 01.03'!C:C,"Вознаграждение Ozon",'Отчет 01.03'!E:E,B3) -> 1053.5 | Y3: =IF(U3=0,0,X3/U3) -> 0.43 | Z3: =-SUMIFS('Отчет 01.03'!P:P,'Отчет 01.03'!C:C,"Услуги доставки",'Отчет 01.03'!E:E,B3) -> 107.71 | AA3: 686.96977 | AD3: =U3*1%/$AE$1 -> 10.267905 | AE3: =U3-W3-X3-Z3-AA3-AB3-AC3-AD3 -> 448.57232 | AG3: =IF(R3=0,0,U3/R3) -> 2450 | AH3: =H3 -> 142.98 | AI3: =IF(R3=0,0,X3/R3) -> 1053.5 | AJ3: =IF(P3=0,Z3/1,Z3/P3) -> 107.71 | AK3: =IF(P3=0,0,AA3/P3) -> 686.96977 | AL3: =_xlfn.IFS(R3=0,AE3,R3<0,AE3/-R3,R3>0,AE3/R3) -> 448.57232 | AM3: =IF(AG3=0,0,AL3/AG3) -> 0.18309074 | AN3: =IF(AH3=0,0,AL3/AH3) -> 3.1373082 | AP3: =AL3*C3 -> 0
A4: 2676784638 | B4: qs черные | H4: 123.09 | I4: =C4*H4 -> 0 | K4: 3 | N4: =K4/$O$1 -> 3 | O4: =R4/$O$1 -> 0 | P4: =SUMIFS('Отчет 01.03'!H:H,'Отчет 01.03'!D:D,"Выручка",'Отчет 01.03'!E:E,B4) -> 0 | Q4: =SUMIFS('Отчет 01.03'!H:H,'Отчет 01.03'!D:D,"Возврат выручки",'Отчет 01.03'!E:E,B4) -> 0 | R4: =P4-Q4 -> 0 | S4: =SUMIFS('Отчет 01.03'!P:P,'Отчет 01.03'!C:C,"Продажи",'Отчет 01.03'!E:E,B4) -> 0 | T4: =SUMIFS('Отчет 01.03'!P:P,'Отчет 01.03'!C:C,"Возвраты",'Отчет 01.03'!E:E,B4) -> 0 | U4: =S4+T4 -> 0 | V4: =U4/$U$24 -> 0 | W4: =R4*H4 -> 0 | X4: =-SUMIFS('Отчет 01.03'!P:P,'Отчет 01.03'!C:C,"Вознаграждение Ozon",'Отчет 01.03'!E:E,B4) -> 0 | Y4: =IF(U4=0,0,X4/U4) -> 0 | Z4: =-SUMIFS('Отчет 01.03'!P:P,'Отчет 01.03'!C:C,"Услуги доставки",'Отчет 01.03'!E:E,B4) -> 93.54 | AA4: 360.51165 | AD4: =U4*1%/$AE$1 -> 0 | AE4: =U4-W4-X4-Z4-AA4-AB4-AC4-AD4 -> -454.05165 | AG4: =IF(R4=0,0,U4/R4) -> 0 | AH4: =H4 -> 123.09 | AI4: =IF(R4=0,0,X4/R4) -> 0 | AJ4: =IF(P4=0,Z4/1,Z4/P4) -> 93.54 | AK4: =IF(P4=0,0,AA4/P4) -> 0 | AL4: {=_xlfn.IFS(R4=0,AE4,R4<0,AE4/-R4,R4>0,AE4/R4)} -> -454.05165 | AM4: =IF(AG4=0,0,AL4/AG4) -> 0 | AN4: =IF(AH4=0,0,AL4/AH4) -> -3.6887778 | AP4: =AL4*C4 -> 0
A5: 2676784504 | B5: qs синие | H5: 123.09 | I5: =C5*H5 -> 0 | K5: 1 | N5: =K5/$O$1 -> 1 | O5: =R5/$O$1 -> 1 | P5: =SUMIFS('Отчет 01.03'!H:H,'Отчет 01.03'!D:D,"Выручка",'Отчет 01.03'!E:E,B5) -> 1 | Q5: =SUMIFS('Отчет 01.03'!H:H,'Отчет 01.03'!D:D,"Возврат выручки",'Отчет 01.03'!E:E,B5) -> 0 | R5: =P5-Q5 -> 1 | S5: =SUMIFS('Отчет 01.03'!P:P,'Отчет 01.03'!C:C,"Продажи",'Отчет 01.03'!E:E,B5) -> 2500 | T5: =SUMIFS('Отчет 01.03'!P:P,'Отчет 01.03'!C:C,"Возвраты",'Отчет 01.03'!E:E,B5) -> 0 | U5: =S5+T5 -> 2500 | V5: =U5/$U$24 -> 0.082891247 | W5: =R5*H5 -> 123.09 | X5: =-SUMIFS('Отчет 01.03'!P:P,'Отчет 01.03'!C:C,"Вознаграждение Ozon",'Отчет 01.03'!E:E,B5) -> 1075 | Y5: =IF(U5=0,0,X5/U5) -> 0.43 | Z5: =-SUMIFS('Отчет 01.03'!P:P,'Отчет 01.03'!C:C,"Услуги доставки",'Отчет 01.03'!E:E,B5) -> 202.15 | AA5: 0 | AD5: =U5*1%/$AE$1 -> 10.477454 | AE5: =U5-W5-X5-Z5-AA5-AB5-AC5-AD5 -> 1089.2825 | AG5: =IF(R5=0,0,U5/R5) -> 2500 | AH5: =H5 -> 123.09 | AI5: =IF(R5=0,0,X5/R5) -> 1075 | AJ5: =IF(P5=0,Z5/1,Z5/P5) -> 202.15 | AK5: =IF(P5=0,0,AA5/P5) -> 0 | AL5: {=_xlfn.IFS(R5=0,AE5,R5<0,AE5/-R5,R5>0,AE5/R5)} -> 1089.2825 | AM5: =IF(AG5=0,0,AL5/AG5) -> 0.43571302 | AN5: =IF(AH5=0,0,AL5/AH5) -> 8.8494804 | AP5: =AL5*C5 -> 0
A6: 2676784514 | B6: qs желтые | H6: 123.09 | I6: =C6*H6 -> 0 | K6: 2 | N6: =K6/$O$1 -> 2 | O6: =R6/$O$1 -> 2 | P6: =SUMIFS('Отчет 01.03'!H:H,'Отчет 01.03'!D:D,"Выручка",'Отчет 01.03'!E:E,B6) -> 2 | Q6: =SUMIFS('Отчет 01.03'!H:H,'Отчет 01.03'!D:D,"Возврат выручки",'Отчет 01.03'!E:E,B6) -> 0 | R6: =P6-Q6 -> 2 | S6: =SUMIFS('Отчет 01.03'!P:P,'Отчет 01.03'!C:C,"Продажи",'Отчет 01.03'!E:E,B6) -> 5200 | T6: =SUMIFS('Отчет 01.03'!P:P,'Отчет 01.03'!C:C,"Возвраты",'Отчет 01.03'!E:E,B6) -> 0 | U6: =S6+T6 -> 5200 | V6: =U6/$U$24 -> 0.17241379 | W6: =R6*H6 -> 246.18 | X6: =-SUMIFS('Отчет 01.03'!P:P,'Отчет 01.03'!C:C,"Вознаграждение Ozon",'Отчет 01.03'!E:E,B6) -> 2236 | Y6: =IF(U6=0,0,X6/U6) -> 0.43 | Z6: =-SUMIFS('Отчет 01.03'!P:P,'Отчет 01.03'!C:C,"Услуги доставки",'Отчет 01.03'!E:E,B6) -> 220.82 | AA6: 361.43133 | AD6: =U6*1%/$AE$1 -> 21.793103 | AE6: =U6-W6-X6-Z6-AA6-AB6-AC6-AD6 -> 2113.7756 | AG6: =IF(R6=0,0,U6/R6) -> 2600 | AH6: =H6 -> 123.09 | AI6: =IF(R6=0,0,X6/R6) -> 1118 | AJ6: =IF(P6=0,Z6/1,Z6/P6) -> 110.41 | AK6: =IF(P6=0,0,AA6/P6) -> 180.71566 | AL6: {=_xlfn.IFS(R6=0,AE6,R6<0,AE6/-R6,R6>0,AE6/R6)} -> 1056.8878 | AM6: =IF(AG6=0,0,AL6/AG6) -> 0.4064953 | AN6: =IF(AH6=0,0,AL6/AH6) -> 8.5863009 | AP6: =AL6*C6 -> 0
A7: 2676784181 | B7: qs коричневые | H7: 117.24 | I7: =C7*H7 -> 0 | K7: 4 | N7: =K7/$O$1 -> 4 | O7: =R7/$O$1 -> 2 | P7: =SUMIFS('Отчет 01.03'!H:H,'Отчет 01.03'!D:D,"Выручка",'Отчет 01.03'!E:E,B7) -> 2 | Q7: =SUMIFS('Отчет 01.03'!H:H,'Отчет 01.03'!D:D,"Возврат выручки",'Отчет 01.03'!E:E,B7) -> 0 | R7: =P7-Q7 -> 2 | S7: =SUMIFS('Отчет 01.03'!P:P,'Отчет 01.03'!C:C,"Продажи",'Отчет 01.03'!E:E,B7) -> 5070 | T7: =SUMIFS('Отчет 01.03'!P:P,'Отчет 01.03'!C:C,"Возвраты",'Отчет 01.03'!E:E,B7) -> 0 | U7: =S7+T7 -> 5070 | V7: =U7/$U$24 -> 0.16810345 | W7: =R7*H7 -> 234.48 | X7: =-SUMIFS('Отчет 01.03'!P:P,'Отчет 01.03'!C:C,"Вознаграждение Ozon",'Отчет 01.03'!E:E,B7) -> 2180.1 | Y7: =IF(U7=0,0,X7/U7) -> 0.43 | Z7: =-SUMIFS('Отчет 01.03'!P:P,'Отчет 01.03'!C:C,"Услуги доставки",'Отчет 01.03'!E:E,B7) -> 485.22 | AA7: 1503.0513 | AD7: =U7*1%/$AE$1 -> 21.248276 | AE7: =U7-W7-X7-Z7-AA7-AB7-AC7-AD7 -> 645.9004 | AG7: =IF(R7=0,0,U7/R7) -> 2535 | AH7: =H7 -> 117.24 | AI7: =IF(R7=0,0,X7/R7) -> 1090.05 | AJ7: =IF(P7=0,Z7/1,Z7/P7) -> 242.61 | AK7: =IF(P7=0,0,AA7/P7) -> 751.52566 | AL7: {=_xlfn.IFS(R7=0,AE7,R7<0,AE7/-R7,R7>0,AE7/R7)} -> 322.9502 | AM7: =IF(AG7=0,0,AL7/AG7) -> 0.12739653 | AN7: =IF(AH7=0,0,AL7/AH7) -> 2.7546076 | AP7: =AL7*C7 -> 0
A8: 2676783005 | B8: MR8854 C2 | H8: 169.89 | I8: =C8*H8 -> 0 | K8: 3 | N8: =K8/$O$1 -> 3 | O8: =R8/$O$1 -> 0 | P8: =SUMIFS('Отчет 01.03'!H:H,'Отчет 01.03'!D:D,"Выручка",'Отчет 01.03'!E:E,B8) -> 0 | Q8: =SUMIFS('Отчет 01.03'!H:H,'Отчет 01.03'!D:D,"Возврат выручки",'Отчет 01.03'!E:E,B8) -> 0 | R8: =P8-Q8 -> 0 | S8: =SUMIFS('Отчет 01.03'!P:P,'Отчет 01.03'!C:C,"Продажи",'Отчет 01.03'!E:E,B8) -> 0 | T8: =SUMIFS('Отчет 01.03'!P:P,'Отчет 01.03'!C:C,"Возвраты",'Отчет 01.03'!E:E,B8) -> 0 | U8: =S8+T8 -> 0 | V8: =U8/$U$24 -> 0 | W8: =R8*H8 -> 0 | X8: =-SUMIFS('Отчет 01.03'!P:P,'Отчет 01.03'!C:C,"Вознаграждение Ozon",'Отчет 01.03'!E:E,B8) -> 0 | Y8: =IF(U8=0,0,X8/U8) -> 0 | Z8: =-SUMIFS('Отчет 01.03'!P:P,'Отчет 01.03'!C:C,"Услуги доставки",'Отчет 01.03'!E:E,B8) -> 0 | AA8: 941.73276 | AD8: =U8*1%/$AE$1 -> 0 | AE8: =U8-W8-X8-Z8-AA8-AB8-AC8-AD8 -> -941.73276 | AG8: =IF(R8=0,0,U8/R8) -> 0 | AH8: =H8 -> 169.89 | AI8: =IF(R8=0,0,X8/R8) -> 0 | AJ8: =IF(P8=0,Z8/1,Z8/P8) -> 0 | AK8: =IF(P8=0,0,AA8/P8) -> 0 | AL8: {=_xlfn.IFS(R8=0,AE8,R8<0,AE8/-R8,R8>0,AE8/R8)} -> -941.73276 | AM8: =IF(AG8=0,0,AL8/AG8) -> 0 | AN8: =IF(AH8=0,0,AL8/AH8) -> -5.5431912 | AP8: =AL8*C8 -> 0
A9: 3405092860 | B9: th черн | H9: 123 | I9: =C9*H9 -> 0 | K9: 2 | N9: =K9/$O$1 -> 2 | O9: =R9/$O$1 -> 0 | P9: =SUMIFS('Отчет 01.03'!H:H,'Отчет 01.03'!D:D,"Выручка",'Отчет 01.03'!E:E,B9) -> 0 | Q9: =SUMIFS('Отчет 01.03'!H:H,'Отчет 01.03'!D:D,"Возврат выручки",'Отчет 01.03'!E:E,B9) -> 0 | R9: =P9-Q9 -> 0 | S9: =SUMIFS('Отчет 01.03'!P:P,'Отчет 01.03'!C:C,"Продажи",'Отчет 01.03'!E:E,B9) -> 0 | T9: =SUMIFS('Отчет 01.03'!P:P,'Отчет 01.03'!C:C,"Возвраты",'Отчет 01.03'!E:E,B9) -> 0 | U9: =S9+T9 -> 0 | V9: =U9/$U$24 -> 0 | W9: =R9*H9 -> 0 | X9: =-SUMIFS('Отчет 01.03'!P:P,'Отчет 01.03'!C:C,"Вознаграждение Ozon",'Отчет 01.03'!E:E,B9) -> 0 | Y9: =IF(U9=0,0,X9/U9) -> 0 | Z9: =-SUMIFS('Отчет 01.03'!P:P,'Отчет 01.03'!C:C,"Услуги доставки",'Отчет 01.03'!E:E,B9) -> 156.58 | AA9: 0 | AD9: =U9*1%/$AE$1 -> 0 | AE9: =U9-W9-X9-Z9-AA9-AB9-AC9-AD9 -> -156.58 | AG9: =IF(R9=0,0,U9/R9) -> 0 | AH9: =H9 -> 123 | AI9: =IF(R9=0,0,X9/R9) -> 0 | AJ9: =IF(P9=0,Z9/1,Z9/P9) -> 156.58 | AK9: =IF(P9=0,0,AA9/P9) -> 0 | AL9: {=_xlfn.IFS(R9=0,AE9,R9<0,AE9/-R9,R9>0,AE9/R9)} -> -156.58 | AM9: =IF(AG9=0,0,AL9/AG9) -> 0 | AN9: =IF(AH9=0,0,AL9/AH9) -> -1.2730081 | AP9: =AL9*C9 -> 0
A10: 3405092836 | B10: th син | H10: 123 | I10: =C10*H10 -> 0 | K10: 2 | N10: =K10/$O$1 -> 2 | O10: =R10/$O$1 -> 1 | P10: =SUMIFS('Отчет 01.03'!H:H,'Отчет 01.03'!D:D,"Выручка",'Отчет 01.03'!E:E,B10) -> 1 | Q10: =SUMIFS('Отчет 01.03'!H:H,'Отчет 01.03'!D:D,"Возврат выручки",'Отчет 01.03'!E:E,B10) -> 0 | R10: =P10-Q10 -> 1 | S10: =SUMIFS('Отчет 01.03'!P:P,'Отчет 01.03'!C:C,"Продажи",'Отчет 01.03'!E:E,B10) -> 2470 | T10: =SUMIFS('Отчет 01.03'!P:P,'Отчет 01.03'!C:C,"Возвраты",'Отчет 01.03'!E:E,B10) -> 0 | U10: =S10+T10 -> 2470 | V10: =U10/$U$24 -> 0.081896552 | W10: =R10*H10 -> 123 | X10: =-SUMIFS('Отчет 01.03'!P:P,'Отчет 01.03'!C:C,"Вознаграждение Ozon",'Отчет 01.03'!E:E,B10) -> 1062.1 | Y10: =IF(U10=0,0,X10/U10) -> 0.43 | Z10: =-SUMIFS('Отчет 01.03'!P:P,'Отчет 01.03'!C:C,"Услуги доставки",'Отчет 01.03'!E:E,B10) -> 114.68 | AA10: 0 | AD10: =U10*1%/$AE$1 -> 10.351724 | AE10: =U10-W10-X10-Z10-AA10-AB10-AC10-AD10 -> 1159.8683 | AG10: =IF(R10=0,0,U10/R10) -> 2470 | AH10: =H10 -> 123 | AI10: =IF(R10=0,0,X10/R10) -> 1062.1 | AJ10: =IF(P10=0,Z10/1,Z10/P10) -> 114.68 | AK10: =IF(P10=0,0,AA10/P10) -> 0 | AL10: {=_xlfn.IFS(R10=0,AE10,R10<0,AE10/-R10,R10>0,AE10/R10)} -> 1159.8683 | AM10: =IF(AG10=0,0,AL10/AG10) -> 0.4695823 | AN10: =IF(AH10=0,0,AL10/AH10) -> 9.4298234 | AP10: =AL10*C10 -> 0
A11: 3064346962 | B11: th желт | H11: 123 | I11: =C11*H11 -> 0 | K11: 3 | N11: =K11/$O$1 -> 3 | O11: =R11/$O$1 -> 3 | P11: =SUMIFS('Отчет 01.03'!H:H,'Отчет 01.03'!D:D,"Выручка",'Отчет 01.03'!E:E,B11) -> 3 | Q11: =SUMIFS('Отчет 01.03'!H:H,'Отчет 01.03'!D:D,"Возврат выручки",'Отчет 01.03'!E:E,B11) -> 0 | R11: =P11-Q11 -> 3 | S11: =SUMIFS('Отчет 01.03'!P:P,'Отчет 01.03'!C:C,"Продажи",'Отчет 01.03'!E:E,B11) -> 7570 | T11: =SUMIFS('Отчет 01.03'!P:P,'Отчет 01.03'!C:C,"Возвраты",'Отчет 01.03'!E:E,B11) -> 0 | U11: =S11+T11 -> 7570 | V11: =U11/$U$24 -> 0.25099469 | W11: =R11*H11 -> 369 | X11: =-SUMIFS('Отчет 01.03'!P:P,'Отчет 01.03'!C:C,"Вознаграждение Ozon",'Отчет 01.03'!E:E,B11) -> 3255.1 | Y11: =IF(U11=0,0,X11/U11) -> 0.43 | Z11: =-SUMIFS('Отчет 01.03'!P:P,'Отчет 01.03'!C:C,"Услуги доставки",'Отчет 01.03'!E:E,B11) -> 802.64 | AA11: 943.7781 | AD11: =U11*1%/$AE$1 -> 31.725729 | AE11: =U11-W11-X11-Z11-AA11-AB11-AC11-AD11 -> 2167.7562 | AG11: =IF(R11=0,0,U11/R11) -> 2523.3333 | AH11: =H11 -> 123 | AI11: =IF(R11=0,0,X11/R11) -> 1085.0333 | AJ11: =IF(P11=0,Z11/1,Z11/P11) -> 267.54667 | AK11: =IF(P11=0,0,AA11/P11) -> 314.5927 | AL11: {=_xlfn.IFS(R11=0,AE11,R11<0,AE11/-R11,R11>0,AE11/R11)} -> 722.58539 | AM11: =IF(AG11=0,0,AL11/AG11) -> 0.28636145 | AN11: =IF(AH11=0,0,AL11/AH11) -> 5.874678 | AP11: =AL11*C11 -> 0
A12: 3405092873 | B12: th коричн | H12: 117 | I12: =C12*H12 -> 0 | K12: 1 | N12: =K12/$O$1 -> 1 | O12: =R12/$O$1 -> 0 | P12: =SUMIFS('Отчет 01.03'!H:H,'Отчет 01.03'!D:D,"Выручка",'Отчет 01.03'!E:E,B12) -> 0 | Q12: =SUMIFS('Отчет 01.03'!H:H,'Отчет 01.03'!D:D,"Возврат выручки",'Отчет 01.03'!E:E,B12) -> 0 | R12: =P12-Q12 -> 0 | S12: =SUMIFS('Отчет 01.03'!P:P,'Отчет 01.03'!C:C,"Продажи",'Отчет 01.03'!E:E,B12) -> 0 | T12: =SUMIFS('Отчет 01.03'!P:P,'Отчет 01.03'!C:C,"Возвраты",'Отчет 01.03'!E:E,B12) -> 0 | U12: =S12+T12 -> 0 | V12: =U12/$U$24 -> 0 | W12: =R12*H12 -> 0 | X12: =-SUMIFS('Отчет 01.03'!P:P,'Отчет 01.03'!C:C,"Вознаграждение Ozon",'Отчет 01.03'!E:E,B12) -> 0 | Y12: =IF(U12=0,0,X12/U12) -> 0 | Z12: =-SUMIFS('Отчет 01.03'!P:P,'Отчет 01.03'!C:C,"Услуги доставки",'Отчет 01.03'!E:E,B12) -> 113.88 | AA12: 411.12899 | AD12: =U12*1%/$AE$1 -> 0 | AE12: =U12-W12-X12-Z12-AA12-AB12-AC12-AD12 -> -525.00899 | AG12: =IF(R12=0,0,U12/R12) -> 0 | AH12: =H12 -> 117 | AI12: =IF(R12=0,0,X12/R12) -> 0 | AJ12: =IF(P12=0,Z12/1,Z12/P12) -> 113.88 | AK12: =IF(P12=0,0,AA12/P12) -> 0 | AL12: {=_xlfn.IFS(R12=0,AE12,R12<0,AE12/-R12,R12>0,AE12/R12)} -> -525.00899 | AM12: =IF(AG12=0,0,AL12/AG12) -> 0 | AN12: =IF(AH12=0,0,AL12/AH12) -> -4.4872563 | AP12: =AL12*C12 -> 0
A13: 3405092993 | B13: flip черный | H13: 123 | I13: =C13*H13 -> 0 | K13: 4 | N13: =K13/$O$1 -> 4 | O13: =R13/$O$1 -> 0 | P13: =SUMIFS('Отчет 01.03'!H:H,'Отчет 01.03'!D:D,"Выручка",'Отчет 01.03'!E:E,B13) -> 1 | Q13: =SUMIFS('Отчет 01.03'!H:H,'Отчет 01.03'!D:D,"Возврат выручки",'Отчет 01.03'!E:E,B13) -> 1 | R13: =P13-Q13 -> 0 | S13: =SUMIFS('Отчет 01.03'!P:P,'Отчет 01.03'!C:C,"Продажи",'Отчет 01.03'!E:E,B13) -> 2400 | T13: =SUMIFS('Отчет 01.03'!P:P,'Отчет 01.03'!C:C,"Возвраты",'Отчет 01.03'!E:E,B13) -> -2400 | U13: =S13+T13 -> 0 | V13: =U13/$U$24 -> 0 | W13: =R13*H13 -> 0 | X13: =-SUMIFS('Отчет 01.03'!P:P,'Отчет 01.03'!C:C,"Вознаграждение Ozon",'Отчет 01.03'!E:E,B13) -> 0 | Y13: =IF(U13=0,0,X13/U13) -> 0 | Z13: =-SUMIFS('Отчет 01.03'!P:P,'Отчет 01.03'!C:C,"Услуги доставки",'Отчет 01.03'!E:E,B13) -> 241.6 | AA13: 1010.9237 | AD13: =U13*1%/$AE$1 -> 0 | AE13: =U13-W13-X13-Z13-AA13-AB13-AC13-AD13 -> -1252.5237 | AG13: =IF(R13=0,0,U13/R13) -> 0 | AH13: =H13 -> 123 | AI13: =IF(R13=0,0,X13/R13) -> 0 | AJ13: =IF(P13=0,Z13/1,Z13/P13) -> 241.6 | AK13: =IF(P13=0,0,AA13/P13) -> 1010.9237 | AL13: {=_xlfn.IFS(R13=0,AE13,R13<0,AE13/-R13,R13>0,AE13/R13)} -> -1252.5237 | AM13: =IF(AG13=0,0,AL13/AG13) -> 0 | AN13: =IF(AH13=0,0,AL13/AH13) -> -10.18312 | AP13: =AL13*C13 -> 0
A14: 3405092868 | B14: flip синий | H14: 123 | I14: =C14*H14 -> 0 | K14: 0 | N14: =K14/$O$1 -> 0 | O14: =R14/$O$1 -> 1 | P14: =SUMIFS('Отчет 01.03'!H:H,'Отчет 01.03'!D:D,"Выручка",'Отчет 01.03'!E:E,B14) -> 1 | Q14: =SUMIFS('Отчет 01.03'!H:H,'Отчет 01.03'!D:D,"Возврат выручки",'Отчет 01.03'!E:E,B14) -> 0 | R14: =P14-Q14 -> 1 | S14: =SUMIFS('Отчет 01.03'!P:P,'Отчет 01.03'!C:C,"Продажи",'Отчет 01.03'!E:E,B14) -> 2400 | T14: =SUMIFS('Отчет 01.03'!P:P,'Отчет 01.03'!C:C,"Возвраты",'Отчет 01.03'!E:E,B14) -> 0 | U14: =S14+T14 -> 2400 | V14: =U14/$U$24 -> 0.079575597 | W14: =R14*H14 -> 123 | X14: =-SUMIFS('Отчет 01.03'!P:P,'Отчет 01.03'!C:C,"Вознаграждение Ozon",'Отчет 01.03'!E:E,B14) -> 1032 | Y14: =IF(U14=0,0,X14/U14) -> 0.43 | Z14: =-SUMIFS('Отчет 01.03'!P:P,'Отчет 01.03'!C:C,"Услуги доставки",'Отчет 01.03'!E:E,B14) -> 127.72 | AA14: 0 | AD14: =U14*1%/$AE$1 -> 10.058355 | AE14: =U14-W14-X14-Z14-AA14-AB14-AC14-AD14 -> 1107.2216 | AG14: =IF(R14=0,0,U14/R14) -> 2400 | AH14: =H14 -> 123 | AI14: =IF(R14=0,0,X14/R14) -> 1032 | AJ14: =IF(P14=0,Z14/1,Z14/P14) -> 127.72 | AK14: =IF(P14=0,0,AA14/P14) -> 0 | AL14: {=_xlfn.IFS(R14=0,AE14,R14<0,AE14/-R14,R14>0,AE14/R14)} -> 1107.2216 | AM14: =IF(AG14=0,0,AL14/AG14) -> 0.46134235 | AN14: =IF(AH14=0,0,AL14/AH14) -> 9.001802 | AP14: =AL14*C14 -> 0
A15: 3064346642 | B15: flip жел | H15: 123 | I15: =C15*H15 -> 0 | K15: 9 | N15: =K15/$O$1 -> 9 | O15: =R15/$O$1 -> 0 | P15: =SUMIFS('Отчет 01.03'!H:H,'Отчет 01.03'!D:D,"Выручка",'Отчет 01.03'!E:E,B15) -> 0 | Q15: =SUMIFS('Отчет 01.03'!H:H,'Отчет 01.03'!D:D,"Возврат выручки",'Отчет 01.03'!E:E,B15) -> 0 | R15: =P15-Q15 -> 0 | S15: =SUMIFS('Отчет 01.03'!P:P,'Отчет 01.03'!C:C,"Продажи",'Отчет 01.03'!E:E,B15) -> 0 | T15: =SUMIFS('Отчет 01.03'!P:P,'Отчет 01.03'!C:C,"Возвраты",'Отчет 01.03'!E:E,B15) -> 0 | U15: =S15+T15 -> 0 | V15: =U15/$U$24 -> 0 | W15: =R15*H15 -> 0 | X15: =-SUMIFS('Отчет 01.03'!P:P,'Отчет 01.03'!C:C,"Вознаграждение Ozon",'Отчет 01.03'!E:E,B15) -> 0 | Y15: =IF(U15=0,0,X15/U15) -> 0 | Z15: =-SUMIFS('Отчет 01.03'!P:P,'Отчет 01.03'!C:C,"Услуги доставки",'Отчет 01.03'!E:E,B15) -> 227.76 | AA15: 1212.4027 | AD15: =U15*1%/$AE$1 -> 0 | AE15: =U15-W15-X15-Z15-AA15-AB15-AC15-AD15 -> -1440.1627 | AG15: =IF(R15=0,0,U15/R15) -> 0 | AH15: =H15 -> 123 | AI15: =IF(R15=0,0,X15/R15) -> 0 | AJ15: =IF(P15=0,Z15/1,Z15/P15) -> 227.76 | AK15: =IF(P15=0,0,AA15/P15) -> 0 | AL15: {=_xlfn.IFS(R15=0,AE15,R15<0,AE15/-R15,R15>0,AE15/R15)} -> -1440.1627 | AM15: =IF(AG15=0,0,AL15/AG15) -> 0 | AN15: =IF(AH15=0,0,AL15/AH15) -> -11.70864 | AP15: =AL15*C15 -> 0
A16: 3405092287 | B16: flip коричневый | H16: 117 | I16: =C16*H16 -> 0 | K16: 1 | N16: =K16/$O$1 -> 1 | O16: =R16/$O$1 -> 1 | P16: =SUMIFS('Отчет 01.03'!H:H,'Отчет 01.03'!D:D,"Выручка",'Отчет 01.03'!E:E,B16) -> 1 | Q16: =SUMIFS('Отчет 01.03'!H:H,'Отчет 01.03'!D:D,"Возврат выручки",'Отчет 01.03'!E:E,B16) -> 0 | R16: =P16-Q16 -> 1 | S16: =SUMIFS('Отчет 01.03'!P:P,'Отчет 01.03'!C:C,"Продажи",'Отчет 01.03'!E:E,B16) -> 2500 | T16: =SUMIFS('Отчет 01.03'!P:P,'Отчет 01.03'!C:C,"Возвраты",'Отчет 01.03'!E:E,B16) -> 0 | U16: =S16+T16 -> 2500 | V16: =U16/$U$24 -> 0.082891247 | W16: =R16*H16 -> 117 | X16: =-SUMIFS('Отчет 01.03'!P:P,'Отчет 01.03'!C:C,"Вознаграждение Ozon",'Отчет 01.03'!E:E,B16) -> 1075 | Y16: =IF(U16=0,0,X16/U16) -> 0.43 | Z16: =-SUMIFS('Отчет 01.03'!P:P,'Отчет 01.03'!C:C,"Услуги доставки",'Отчет 01.03'!E:E,B16) -> 357.48 | AA16: 1313.5545 | AD16: =U16*1%/$AE$1 -> 10.477454 | AE16: =U16-W16-X16-Z16-AA16-AB16-AC16-AD16 -> -373.512 | AG16: =IF(R16=0,0,U16/R16) -> 2500 | AH16: =H16 -> 117 | AI16: =IF(R16=0,0,X16/R16) -> 1075 | AJ16: =IF(P16=0,Z16/1,Z16/P16) -> 357.48 | AK16: =IF(P16=0,0,AA16/P16) -> 1313.5545 | AL16: {=_xlfn.IFS(R16=0,AE16,R16<0,AE16/-R16,R16>0,AE16/R16)} -> -373.512 | AM16: =IF(AG16=0,0,AL16/AG16) -> -0.1494048 | AN16: =IF(AH16=0,0,AL16/AH16) -> -3.1924103 | AP16: =AL16*C16 -> 0
AG17: =AVERAGEIF(AG3:AG15,"<>0",AG3:AG15) -> 2496.9048 | AH17: =AVERAGEIF(AH3:AH15,"<>0",AH3:AH15) -> 127.26 | AI17: =AVERAGEIF(AI3:AI15,"<>0",AI3:AI15) -> 1073.669 | AJ17: =AVERAGEIF(AJ3:AJ15,"<>0",AJ3:AJ15) -> 167.18222 | AK17: =AVERAGEIF(AK3:AK15,"<>0",AK3:AK15) -> 588.94551 | AL17: =AVERAGEIF(AL3:AL15,"<>0",AL3:AL15) -> 87.485255 | AM17: =AVERAGEIF(AM3:AM15,"<>0",AM3:AM15) -> 0.33856881 | AN17: =AVERAGEIF(AN3:AN15,"<>0",AN3:AN15) -> 0.82692364
A18: Итого очки | C18: =SUM(C3:C16) -> 0 | E18: 108496 | F18: 597 | G18: 295 | I18: =SUM(I3:I16) -> 0 | K18: =SUM(K3:K16) -> 36 | P18: =SUM(P3:P16) -> 13 | Q18: =SUM(Q3:Q16) -> 1 | R18: =SUM(R3:R16) -> 12 | S18: =SUM(S3:S16) -> 32560 | T18: =SUM(T3:T16) -> -2400 | U18: =SUM(U3:U16) -> 30160 | V18: =SUM(V3:V16) -> 1 | W18: =SUM(W3:W16) -> 1478.73 | X18: =SUM(X3:X16) -> 12968.8 | Y18: =IF(U18=0,0,X18/U18) -> 0.43 | Z18: =SUM(Z3:Z16) -> 3251.78 | AA18: =IFERROR(P18*AA24/P24,0) -> 10359.47 | AB18: =SUM(AB3:AB16) -> 0 | AC18: =SUM(AC3:AC16) -> 0 | AD18: =SUM(AD3:AD16) -> 126.4 | AE18: =SUM(AE3:AE16) -> 3588.8051 | AP18: =SUM(AP3:AP16) -> 0 | AZ18: 18592777
AG21: =AVERAGEIF(AG20:AG20,"<>0",AG20:AG20) -> #DIV/0! | AH21: =AVERAGEIF(AH20:AH20,"<>0",AH20:AH20) -> #DIV/0! | AI21: =AVERAGEIF(AI20:AI20,"<>0",AI20:AI20) -> #DIV/0! | AJ21: =AVERAGEIF(AJ20:AJ20,"<>0",AJ20:AJ20) -> #DIV/0! | AK21: =AVERAGEIF(AK20:AK20,"<>0",AK20:AK20) -> #DIV/0! | AL21: =AVERAGEIF(AL20:AL20,"<>0",AL20:AL20) -> #DIV/0! | AM21: =AVERAGEIF(AM20:AM20,"<>0",AM20:AM20) -> #DIV/0! | AN21: =AVERAGEIF(AN20:AN20,"<>0",AN20:AN20) -> #DIV/0!
C22: =SUM(C20:C20) -> 0 | I22: =SUM(I20:I20) -> 0 | K22: =SUM(K20:K20) -> 0 | P22: =SUM(P20:P20) -> 0 | Q22: =SUM(Q20:Q20) -> 0 | R22: =SUM(R20:R20) -> 0 | S22: =SUM(S20:S20) -> 0 | T22: =SUM(T20:T20) -> 0 | U22: =SUM(U20:U20) -> 0 | V22: =SUM(V20:V20) -> 0 | W22: =SUM(W20:W20) -> 0 | X22: =SUM(X20:X20) -> 0 | Y22: =IF(U22=0,0,X22/U22) -> 0 | Z22: =SUM(Z20:Z20) -> 0 | AA22: =IFERROR(P22*AA24/P24,0) -> 0 | AB22: =SUM(AB20:AB20) -> 0 | AC22: =SUM(AC20:AC20) -> 0 | AD22: =SUM(AD20:AD20) -> 0 | AE22: =SUM(AE20:AE20) -> 0 | AP22: =SUM(AP20:AP20) -> 0
AA23: =SUM(AA20:AA20) -> 0
A24: ИТОГО | C24: =C18+C22 -> 0 | D24: =SUM(D3:D20) -> 0 | E24: =SUM(E3:E20) -> 108496 | F24: =SUM(F3:F20) -> 597 | G24: =SUM(G3:G20) -> 295 | I24: =I18+I22 -> 0 | J24: =J18+J22 -> 0 | K24: =K18+K22 -> 36 | P24: =P18+P22 -> 13 | Q24: =Q18+Q22 -> 1 | R24: =R18-R22 -> 12 | S24: =S18+S22 -> 32560 | T24: =T18+T22 -> -2400 | U24: =U18+U22 -> 30160 | V24: =V18+V22 -> 1 | W24: =W18+W22 -> 1478.73 | X24: =X18+X22 -> 12968.8 | Y24: =X24/U24 -> 0.43 | Z24: =Z18+Z22 -> 3251.78 | AA24: 10359.47 | AC24: =SUM(AC3:AC20) -> 0 | AD24: =AD18+AD22 -> 126.4 | AE24: =AE18+AE22 -> 3588.8051 | AK24: =AA25/P24 -> 672.72961 | AP24: =SUM(AP3:AP20) -> 0
AA25: =SUM(AA3:AA16) -> 8745.4849
AA26: 150 | AD26: Закрепление отзыва
AA27: 1464 | AD27: Баллы за отзывы

Sheet ФЕВРАЛЬ
B1: 01-28.02 | AG1: на 1 единицу проданного товара
B2: Артикул поставщика | C2: Остаток на | D2: В пути до клиента | E2: В пути от клиента | F2: Итого по складам ВБ | G2: Остаток на нашем складе на 02.09 | H2: Себетоимость на 1 ед на 29.09.25 | I2: Себестоимость остатков | J2: Оборачиваемость, дн | K2: Заказы, шт 7 дней | L2: Средняя цена, руб (столбец 32, AG) | M2: % выкупа за 7 дней (столбец 23, X) | N2: Скорость заказов | O2: Скорость продаж | P2: Кол-во ПРОДАЖИ | Q2: Кол-во ВОЗВРАТЫ | R2: Кол-во ПРОДАЖИ-ВОЗВРАТЫ | S2: Выручка ПРОДАЖИ | T2: Выручка ВОЗВРАТЫ | U2: Выручка с учетом согласованной скидки ПРОДАЖИ - ВОЗВРАТЫ | V2: Доля выручки, % от общего объема | W2: Себестоимость продаж | X2: Комиссия, руб | Y2: Комиссия, % | Z2: Логистика | AA2: Реклама | AB2: Хранение | AC2: Штрафы | AD2: Налог 1% | AE2: Прибыль | AG2: Выручка на 1 ед (средняя цена продажи со скидкой) | AH2: Себестоимость на 1 ед | AI2: Комиссия на 1 ед | AJ2: Логистика на 1 ед | AK2: Реклама на 1 ед | AL2: Прибыль на 1 ед | AM2: Маржинальность, % | AN2: Рентабельность, % | AP2: Прибыль с остатков
A3: 2676784153 | B3: черные с железкой классика | H3: 142.98 | I3: =C3*H3 -> 0 | N3: =K3/7 -> 0 | O3: =R3/7 -> 1.8571429 | P3: ='Юнит 01.02'!P3+'Юнит 02-08.02'!P3+'Юнит 09-15.02'!P3+'Юнит 16-22.02'!P3+'Юнит 23-28.02'!P3 -> 15 | Q3: ='Юнит 01.02'!Q3+'Юнит 02-08.02'!Q3+'Юнит 09-15.02'!Q3+'Юнит 16-22.02'!Q3+'Юнит 23-28.02'!Q3 -> 2 | R3: =P3-Q3 -> 13 | S3: ='Юнит 01.02'!S3+'Юнит 02-08.02'!S3+'Юнит 09-15.02'!S3+'Юнит 16-22.02'!S3+'Юнит 23-28.02'!S3 -> 35150 | T3: ='Юнит 01.02'!T3+'Юнит 02-08.02'!T3+'Юнит 09-15.02'!T3+'Юнит 16-22.02'!T3+'Юнит 23-28.02'!T3 -> -4800 | U3: =S3+T3 -> 30350 | V3: =U3/$U$24 -> 0.025096915 | W3: =R3*H3 -> 1858.74 | X3: ='Юнит 01.02'!X3+'Юнит 02-08.02'!X3+'Юнит 09-15.02'!X3+'Юнит 16-22.02'!X3+'Юнит 23-28.02'!X3 -> 13050.5 | Y3: =IF(U3=0,0,X3/U3) -> 0.43 | Z3: ='Юнит 01.02'!Z3+'Юнит 02-08.02'!Z3+'Юнит 09-15.02'!Z3+'Юнит 16-22.02'!Z3+'Юнит 23-28.02'!Z3 -> 3642.16 | AA3: ='Юнит 01.02'!AA3+'Юнит 02-08.02'!AA3+'Юнит 09-15.02'!AA3+'Юнит 16-22.02'!AA3+'Юнит 23-28.02'!AA3 -> 7624.5467 | AB3: ='Юнит 01.02'!AB3+'Юнит 02-08.02'!AB3+'Юнит 09-15.02'!AB3+'Юнит 16-22.02'!AB3+'Юнит 23-28.02'!AB3 -> 0 | AC3: ='Юнит 01.02'!AC3+'Юнит 02-08.02'!AC3+'Юнит 09-15.02'!AC3+'Юнит 16-22.02'!AC3+'Юнит 23-28.02'!AC3 -> 0 | AD3: ='Юнит 01.02'!AD3+'Юнит 02-08.02'!AD3+'Юнит 09-15.02'!AD3+'Юнит 16-22.02'!AD3+'Юнит 23-28.02'!AD3 -> 129.22263 | AE3: =U3-W3-X3-Z3-AA3-AB3-AC3-AD3 -> 4044.8307 | AG3: =IF(R3=0,0,U3/R3) -> 2334.6154 | AH3: =H3 -> 142.98 | AI3: =IF(R3=0,0,X3/R3) -> 1003.8846 | AJ3: =IF(P3=0,Z3/1,Z3/P3) -> 242.81067 | AK3: =IF(P3=0,0,AA3/P3) -> 508.30311 | AL3: =_xlfn.IFS(R3=0,AE3,R3<0,AE3/-R3,R3>0,AE3/R3) -> 311.14082 | AM3: =IF(AG3=0,0,AL3/AG3) -> 0.13327284 | AN3: =IF(AH3=0,0,AL3/AH3) -> 2.1761143 | AP3: =AL3*C3 -> 0
A4: 2676784638 | B4: qs черные | H4: 123.09 | I4: =C4*H4 -> 0 | N4: =K4/7 -> 0 | O4: =R4/7 -> 2.2857143 | P4: ='Юнит 01.02'!P4+'Юнит 02-08.02'!P4+'Юнит 09-15.02'!P4+'Юнит 16-22.02'!P4+'Юнит 23-28.02'!P4 -> 17 | Q4: ='Юнит 01.02'!Q4+'Юнит 02-08.02'!Q4+'Юнит 09-15.02'!Q4+'Юнит 16-22.02'!Q4+'Юнит 23-28.02'!Q4 -> 1 | R4: =P4-Q4 -> 16 | S4: ='Юнит 01.02'!S4+'Юнит 02-08.02'!S4+'Юнит 09-15.02'!S4+'Юнит 16-22.02'!S4+'Юнит 23-28.02'!S4 -> 37606 | T4: ='Юнит 01.02'!T4+'Юнит 02-08.02'!T4+'Юнит 09-15.02'!T4+'Юнит 16-22.02'!T4+'Юнит 23-28.02'!T4 -> -2350 | U4: =S4+T4 -> 35256 | V4: =U4/$U$24 -> 0.029153767 | W4: =R4*H4 -> 1969.44 | X4: ='Юнит 01.02'!X4+'Юнит 02-08.02'!X4+'Юнит 09-15.02'!X4+'Юнит 16-22.02'!X4+'Юнит 23-28.02'!X4 -> 15160.08 | Y4: =IF(U4=0,0,X4/U4) -> 0.43 | Z4: ='Юнит 01.02'!Z4+'Юнит 02-08.02'!Z4+'Юнит 09-15.02'!Z4+'Юнит 16-22.02'!Z4+'Юнит 23-28.02'!Z4 -> 2950.66 | AA4: ='Юнит 01.02'!AA4+'Юнит 02-08.02'!AA4+'Юнит 09-15.02'!AA4+'Юнит 16-22.02'!AA4+'Юнит 23-28.02'!AA4 -> 7055.9788 | AB4: ='Юнит 01.02'!AB4+'Юнит 02-08.02'!AB4+'Юнит 09-15.02'!AB4+'Юнит 16-22.02'!AB4+'Юнит 23-28.02'!AB4 -> 0 | AC4: ='Юнит 01.02'!AC4+'Юнит 02-08.02'!AC4+'Юнит 09-15.02'!AC4+'Юнит 16-22.02'!AC4+'Юнит 23-28.02'!AC4 -> 0 | AD4: ='Юнит 01.02'!AD4+'Юнит 02-08.02'!AD4+'Юнит 09-15.02'!AD4+'Юнит 16-22.02'!AD4+'Юнит 23-28.02'!AD4 -> 149.36726 | AE4: =U4-W4-X4-Z4-AA4-AB4-AC4-AD4 -> 7970.474 | AG4: =IF(R4=0,0,U4/R4) -> 2203.5 | AH4: =H4 -> 123.09 | AI4: =IF(R4=0,0,X4/R4) -> 947.505 | AJ4: =IF(P4=0,Z4/1,Z4/P4) -> 173.56824 | AK4: =IF(P4=0,0,AA4/P4) -> 415.05757 | AL4: {=_xlfn.IFS(R4=0,AE4,R4<0,AE4/-R4,R4>0,AE4/R4)} -> 498.15462 | AM4: =IF(AG4=0,0,AL4/AG4) -> 0.22607426 | AN4: =IF(AH4=0,0,AL4/AH4) -> 4.0470763 | AP4: =AL4*C4 -> 0
A5: 2676784504 | B5: qs синие | H5: 123.09 | I5: =C5*H5 -> 0 | N5: =K5/7 -> 0 | O5: =R5/7 -> 1.7142857 | P5: ='Юнит 01.02'!P5+'Юнит 02-08.02'!P5+'Юнит 09-15.02'!P5+'Юнит 16-22.02'!P5+'Юнит 23-28.02'!P5 -> 13 | Q5: ='Юнит 01.02'!Q5+'Юнит 02-08.02'!Q5+'Юнит 09-15.02'!Q5+'Юнит 16-22.02'!Q5+'Юнит 23-28.02'!Q5 -> 1 | R5: =P5-Q5 -> 12 | S5: ='Юнит 01.02'!S5+'Юнит 02-08.02'!S5+'Юнит 09-15.02'!S5+'Юнит 16-22.02'!S5+'Юнит 23-28.02'!S5 -> 28900 | T5: ='Юнит 01.02'!T5+'Юнит 02-08.02'!T5+'Юнит 09-15.02'!T5+'Юнит 16-22.02'!T5+'Юнит 23-28.02'!T5 -> -2150 | U5: =S5+T5 -> 26750 | V5: =U5/$U$24 -> 0.022120015 | W5: =R5*H5 -> 1477.08 | X5: ='Юнит 01.02'!X5+'Юнит 02-08.02'!X5+'Юнит 09-15.02'!X5+'Юнит 16-22.02'!X5+'Юнит 23-28.02'!X5 -> 11502.5 | Y5: =IF(U5=0,0,X5/U5) -> 0.43 | Z5: ='Юнит 01.02'!Z5+'Юнит 02-08.02'!Z5+'Юнит 09-15.02'!Z5+'Юнит 16-22.02'!Z5+'Юнит 23-28.02'!Z5 -> 2265.81 | AA5: ='Юнит 01.02'!AA5+'Юнит 02-08.02'!AA5+'Юнит 09-15.02'!AA5+'Юнит 16-22.02'!AA5+'Юнит 23-28.02'!AA5 -> 7852.2221 | AB5: ='Юнит 01.02'!AB5+'Юнит 02-08.02'!AB5+'Юнит 09-15.02'!AB5+'Юнит 16-22.02'!AB5+'Юнит 23-28.02'!AB5 -> 0 | AC5: ='Юнит 01.02'!AC5+'Юнит 02-08.02'!AC5+'Юнит 09-15.02'!AC5+'Юнит 16-22.02'!AC5+'Юнит 23-28.02'!AC5 -> 0 | AD5: ='Юнит 01.02'!AD5+'Юнит 02-08.02'!AD5+'Юнит 09-15.02'!AD5+'Юнит 16-22.02'!AD5+'Юнит 23-28.02'!AD5 -> 114.27713 | AE5: =U5-W5-X5-Z5-AA5-AB5-AC5-AD5 -> 3538.1108 | AG5: =IF(R5=0,0,U5/R5) -> 2229.1667 | AH5: =H5 -> 123.09 | AI5: =IF(R5=0,0,X5/R5) -> 958.54167 | AJ5: =IF(P5=0,Z5/1,Z5/P5) -> 174.29308 | AK5: =IF(P5=0,0,AA5/P5) -> 604.01709 | AL5: {=_xlfn.IFS(R5=0,AE5,R5<0,AE5/-R5,R5>0,AE5/R5)} -> 294.84256 | AM5: =IF(AG5=0,0,AL5/AG5) -> 0.13226582 | AN5: =IF(AH5=0,0,AL5/AH5) -> 2.3953413 | AP5: =AL5*C5 -> 0
A6: 2676784514 | B6: qs желтые | H6: 123.09 | I6: =C6*H6 -> 0 | N6: =K6/7 -> 0 | O6: =R6/7 -> 4.1428571 | P6: ='Юнит 01.02'!P6+'Юнит 02-08.02'!P6+'Юнит 09-15.02'!P6+'Юнит 16-22.02'!P6+'Юнит 23-28.02'!P6 -> 31 | Q6: ='Юнит 01.02'!Q6+'Юнит 02-08.02'!Q6+'Юнит 09-15.02'!Q6+'Юнит 16-22.02'!Q6+'Юнит 23-28.02'!Q6 -> 2 | R6: =P6-Q6 -> 29 | S6: ='Юнит 01.02'!S6+'Юнит 02-08.02'!S6+'Юнит 09-15.02'!S6+'Юнит 16-22.02'!S6+'Юнит 23-28.02'!S6 -> 68150 | T6: ='Юнит 01.02'!T6+'Юнит 02-08.02'!T6+'Юнит 09-15.02'!T6+'Юнит 16-22.02'!T6+'Юнит 23-28.02'!T6 -> -4500 | U6: =S6+T6 -> 63650 | V6: =U6/$U$24 -> 0.052633233 | W6: =R6*H6 -> 3569.61 | X6: ='Юнит 01.02'!X6+'Юнит 02-08.02'!X6+'Юнит 09-15.02'!X6+'Юнит 16-22.02'!X6+'Юнит 23-28.02'!X6 -> 27369.5 | Y6: =IF(U6=0,0,X6/U6) -> 0.43 | Z6: ='Юнит 01.02'!Z6+'Юнит 02-08.02'!Z6+'Юнит 09-15.02'!Z6+'Юнит 16-22.02'!Z6+'Юнит 23-28.02'!Z6 -> 5027.52 | AA6: ='Юнит 01.02'!AA6+'Юнит 02-08.02'!AA6+'Юнит 09-15.02'!AA6+'Юнит 16-22.02'!AA6+'Юнит 23-28.02'!AA6 -> 11912.702 | AB6: ='Юнит 01.02'!AB6+'Юнит 02-08.02'!AB6+'Юнит 09-15.02'!AB6+'Юнит 16-22.02'!AB6+'Юнит 23-28.02'!AB6 -> 0 | AC6: ='Юнит 01.02'!AC6+'Юнит 02-08.02'!AC6+'Юнит 09-15.02'!AC6+'Юнит 16-22.02'!AC6+'Юнит 23-28.02'!AC6 -> 0 | AD6: ='Юнит 01.02'!AD6+'Юнит 02-08.02'!AD6+'Юнит 09-15.02'!AD6+'Юнит 16-22.02'!AD6+'Юнит 23-28.02'!AD6 -> 270.34505 | AE6: =U6-W6-X6-Z6-AA6-AB6-AC6-AD6 -> 15500.323 | AG6: =IF(R6=0,0,U6/R6) -> 2194.8276 | AH6: =H6 -> 123.09 | AI6: =IF(R6=0,0,X6/R6) -> 943.77586 | AJ6: =IF(P6=0,Z6/1,Z6/P6) -> 162.17806 | AK6: =IF(P6=0,0,AA6/P6) -> 384.2807 | AL6: {=_xlfn.IFS(R6=0,AE6,R6<0,AE6/-R6,R6>0,AE6/R6)} -> 534.4939 | AM6: =IF(AG6=0,0,AL6/AG6) -> 0.24352432 | AN6: =IF(AH6=0,0,AL6/AH6) -> 4.3423016 | AP6: =AL6*C6 -> 0
A7: 2676784181 | B7: qs коричневые | H7: 117.24 | I7: =C7*H7 -> 0 | N7: =K7/7 -> 0 | O7: =R7/7 -> 9.1428571 | P7: ='Юнит 01.02'!P7+'Юнит 02-08.02'!P7+'Юнит 09-15.02'!P7+'Юнит 16-22.02'!P7+'Юнит 23-28.02'!P7 -> 67 | Q7: ='Юнит 01.02'!Q7+'Юнит 02-08.02'!Q7+'Юнит 09-15.02'!Q7+'Юнит 16-22.02'!Q7+'Юнит 23-28.02'!Q7 -> 3 | R7: =P7-Q7 -> 64 | S7: ='Юнит 01.02'!S7+'Юнит 02-08.02'!S7+'Юнит 09-15.02'!S7+'Юнит 16-22.02'!S7+'Юнит 23-28.02'!S7 -> 148954 | T7: ='Юнит 01.02'!T7+'Юнит 02-08.02'!T7+'Юнит 09-15.02'!T7+'Юнит 16-22.02'!T7+'Юнит 23-28.02'!T7 -> -6250 | U7: =S7+T7 -> 142704 | V7: =U7/$U$24 -> 0.11800429 | W7: =R7*H7 -> 7503.36 | X7: ='Юнит 01.02'!X7+'Юнит 02-08.02'!X7+'Юнит 09-15.02'!X7+'Юнит 16-22.02'!X7+'Юнит 23-28.02'!X7 -> 61362.72 | Y7: =IF(U7=0,0,X7/U7) -> 0.43 | Z7: ='Юнит 01.02'!Z7+'Юнит 02-08.02'!Z7+'Юнит 09-15.02'!Z7+'Юнит 16-22.02'!Z7+'Юнит 23-28.02'!Z7 -> 12409.9 | AA7: ='Юнит 01.02'!AA7+'Юнит 02-08.02'!AA7+'Юнит 09-15.02'!AA7+'Юнит 16-22.02'!AA7+'Юнит 23-28.02'!AA7 -> 43225.963 | AB7: ='Юнит 01.02'!AB7+'Юнит 02-08.02'!AB7+'Юнит 09-15.02'!AB7+'Юнит 16-22.02'!AB7+'Юнит 23-28.02'!AB7 -> 0 | AC7: ='Юнит 01.02'!AC7+'Юнит 02-08.02'!AC7+'Юнит 09-15.02'!AC7+'Юнит 16-22.02'!AC7+'Юнит 23-28.02'!AC7 -> 0 | AD7: ='Юнит 01.02'!AD7+'Юнит 02-08.02'!AD7+'Юнит 09-15.02'!AD7+'Юнит 16-22.02'!AD7+'Юнит 23-28.02'!AD7 -> 613.50245 | AE7: =U7-W7-X7-Z7-AA7-AB7-AC7-AD7 -> 17588.555 | AG7: =IF(R7=0,0,U7/R7) -> 2229.75 | AH7: =H7 -> 117.24 | AI7: =IF(R7=0,0,X7/R7) -> 958.7925 | AJ7: =IF(P7=0,Z7/1,Z7/P7) -> 185.22239 | AK7: =IF(P7=0,0,AA7/P7) -> 645.16363 | AL7: {=_xlfn.IFS(R7=0,AE7,R7<0,AE7/-R7,R7>0,AE7/R7)} -> 274.82117 | AM7: =IF(AG7=0,0,AL7/AG7) -> 0.12325201 | AN7: =IF(AH7=0,0,AL7/AH7) -> 2.3440905 | AP7: =AL7*C7 -> 0
A8: 2676783005 | B8: MR8854 C2 | H8: 169.89 | I8: =C8*H8 -> 0 | N8: =K8/7 -> 0 | O8: =R8/7 -> 8.2857143 | P8: ='Юнит 01.02'!P8+'Юнит 02-08.02'!P8+'Юнит 09-15.02'!P8+'Юнит 16-22.02'!P8+'Юнит 23-28.02'!P8 -> 61 | Q8: ='Юнит 01.02'!Q8+'Юнит 02-08.02'!Q8+'Юнит 09-15.02'!Q8+'Юнит 16-22.02'!Q8+'Юнит 23-28.02'!Q8 -> 3 | R8: =P8-Q8 -> 58 | S8: ='Юнит 01.02'!S8+'Юнит 02-08.02'!S8+'Юнит 09-15.02'!S8+'Юнит 16-22.02'!S8+'Юнит 23-28.02'!S8 -> 136400 | T8: ='Юнит 01.02'!T8+'Юнит 02-08.02'!T8+'Юнит 09-15.02'!T8+'Юнит 16-22.02'!T8+'Юнит 23-28.02'!T8 -> -7000 | U8: =S8+T8 -> 129400 | V8: =U8/$U$24 -> 0.10700299 | W8: =R8*H8 -> 9853.62 | X8: ='Юнит 01.02'!X8+'Юнит 02-08.02'!X8+'Юнит 09-15.02'!X8+'Юнит 16-22.02'!X8+'Юнит 23-28.02'!X8 -> 55642 | Y8: =IF(U8=0,0,X8/U8) -> 0.43 | Z8: ='Юнит 01.02'!Z8+'Юнит 02-08.02'!Z8+'Юнит 09-15.02'!Z8+'Юнит 16-22.02'!Z8+'Юнит 23-28.02'!Z8 -> 10936.04 | AA8: ='Юнит 01.02'!AA8+'Юнит 02-08.02'!AA8+'Юнит 09-15.02'!AA8+'Юнит 16-22.02'!AA8+'Юнит 23-28.02'!AA8 -> 24912.854 | AB8: ='Юнит 01.02'!AB8+'Юнит 02-08.02'!AB8+'Юнит 09-15.02'!AB8+'Юнит 16-22.02'!AB8+'Юнит 23-28.02'!AB8 -> 0 | AC8: ='Юнит 01.02'!AC8+'Юнит 02-08.02'!AC8+'Юнит 09-15.02'!AC8+'Юнит 16-22.02'!AC8+'Юнит 23-28.02'!AC8 -> 0 | AD8: ='Юнит 01.02'!AD8+'Юнит 02-08.02'!AD8+'Юнит 09-15.02'!AD8+'Юнит 16-22.02'!AD8+'Юнит 23-28.02'!AD8 -> 544.61876 | AE8: =U8-W8-X8-Z8-AA8-AB8-AC8-AD8 -> 27510.868 | AG8: =IF(R8=0,0,U8/R8) -> 2231.0345 | AH8: =H8 -> 169.89 | AI8: =IF(R8=0,0,X8/R8) -> 959.34483 | AJ8: =IF(P8=0,Z8/1,Z8/P8) -> 179.27934 | AK8: =IF(P8=0,0,AA8/P8) -> 408.40744 | AL8: {=_xlfn.IFS(R8=0,AE8,R8<0,AE8/-R8,R8>0,AE8/R8)} -> 474.3253 | AM8: =IF(AG8=0,0,AL8/AG8) -> 0.2126033 | AN8: =IF(AH8=0,0,AL8/AH8) -> 2.7919554 | AP8: =AL8*C8 -> 0
A9: 3405092860 | B9: th черн | H9: 123 | I9: =C9*H9 -> 0 | N9: =K9/7 -> 0 | O9: =R9/7 -> 2.1428571 | P9: ='Юнит 01.02'!P9+'Юнит 02-08.02'!P9+'Юнит 09-15.02'!P9+'Юнит 16-22.02'!P9+'Юнит 23-28.02'!P9 -> 18 | Q9: ='Юнит 01.02'!Q9+'Юнит 02-08.02'!Q9+'Юнит 09-15.02'!Q9+'Юнит 16-22.02'!Q9+'Юнит 23-28.02'!Q9 -> 3 | R9: =P9-Q9 -> 15 | S9: ='Юнит 01.02'!S9+'Юнит 02-08.02'!S9+'Юнит 09-15.02'!S9+'Юнит 16-22.02'!S9+'Юнит 23-28.02'!S9 -> 40424 | T9: ='Юнит 01.02'!T9+'Юнит 02-08.02'!T9+'Юнит 09-15.02'!T9+'Юнит 16-22.02'!T9+'Юнит 23-28.02'!T9 -> -6800 | U9: =S9+T9 -> 33624 | V9: =U9/$U$24 -> 0.027804239 | W9: =R9*H9 -> 1845 | X9: ='Юнит 01.02'!X9+'Юнит 02-08.02'!X9+'Юнит 09-15.02'!X9+'Юнит 16-22.02'!X9+'Юнит 23-28.02'!X9 -> 14458.32 | Y9: =IF(U9=0,0,X9/U9) -> 0.43 | Z9: ='Юнит 01.02'!Z9+'Юнит 02-08.02'!Z9+'Юнит 09-15.02'!Z9+'Юнит 16-22.02'!Z9+'Юнит 23-28.02'!Z9 -> 5177.92 | AA9: ='Юнит 01.02'!AA9+'Юнит 02-08.02'!AA9+'Юнит 09-15.02'!AA9+'Юнит 16-22.02'!AA9+'Юнит 23-28.02'!AA9 -> 7906.0872 | AB9: ='Юнит 01.02'!AB9+'Юнит 02-08.02'!AB9+'Юнит 09-15.02'!AB9+'Юнит 16-22.02'!AB9+'Юнит 23-28.02'!AB9 -> 0 | AC9: ='Юнит 01.02'!AC9+'Юнит 02-08.02'!AC9+'Юнит 09-15.02'!AC9+'Юнит 16-22.02'!AC9+'Юнит 23-28.02'!AC9 -> 0 | AD9: ='Юнит 01.02'!AD9+'Юнит 02-08.02'!AD9+'Юнит 09-15.02'!AD9+'Юнит 16-22.02'!AD9+'Юнит 23-28.02'!AD9 -> 144.60673 | AE9: =U9-W9-X9-Z9-AA9-AB9-AC9-AD9 -> 4092.066 | AG9: =IF(R9=0,0,U9/R9) -> 2241.6 | AH9: =H9 -> 123 | AI9: =IF(R9=0,0,X9/R9) -> 963.888 | AJ9: =IF(P9=0,Z9/1,Z9/P9) -> 287.66222 | AK9: =IF(P9=0,0,AA9/P9) -> 439.22707 | AL9: {=_xlfn.IFS(R9=0,AE9,R9<0,AE9/-R9,R9>0,AE9/R9)} -> 272.8044 | AM9: =IF(AG9=0,0,AL9/AG9) -> 0.12170075 | AN9: =IF(AH9=0,0,AL9/AH9) -> 2.217922 | AP9: =AL9*C9 -> 0
A10: 3405092836 | B10: th син | H10: 123 | I10: =C10*H10 -> 0 | N10: =K10/7 -> 0 | O10: =R10/7 -> 4 | P10: ='Юнит 01.02'!P10+'Юнит 02-08.02'!P10+'Юнит 09-15.02'!P10+'Юнит 16-22.02'!P10+'Юнит 23-28.02'!P10 -> 28 | Q10: ='Юнит 01.02'!Q10+'Юнит 02-08.02'!Q10+'Юнит 09-15.02'!Q10+'Юнит 16-22.02'!Q10+'Юнит 23-28.02'!Q10 -> 0 | R10: =P10-Q10 -> 28 | S10: ='Юнит 01.02'!S10+'Юнит 02-08.02'!S10+'Юнит 09-15.02'!S10+'Юнит 16-22.02'!S10+'Юнит 23-28.02'!S10 -> 60184 | T10: ='Юнит 01.02'!T10+'Юнит 02-08.02'!T10+'Юнит 09-15.02'!T10+'Юнит 16-22.02'!T10+'Юнит 23-28.02'!T10 -> 0 | U10: =S10+T10 -> 60184 | V10: =U10/$U$24 -> 0.04976714 | W10: =R10*H10 -> 3444 | X10: ='Юнит 01.02'!X10+'Юнит 02-08.02'!X10+'Юнит 09-15.02'!X10+'Юнит 16-22.02'!X10+'Юнит 23-28.02'!X10 -> 25879.12 | Y10: =IF(U10=0,0,X10/U10) -> 0.43 | Z10: ='Юнит 01.02'!Z10+'Юнит 02-08.02'!Z10+'Юнит 09-15.02'!Z10+'Юнит 16-22.02'!Z10+'Юнит 23-28.02'!Z10 -> 5669.79 | AA10: ='Юнит 01.02'!AA10+'Юнит 02-08.02'!AA10+'Юнит 09-15.02'!AA10+'Юнит 16-22.02'!AA10+'Юнит 23-28.02'!AA10 -> 10575.918 | AB10: ='Юнит 01.02'!AB10+'Юнит 02-08.02'!AB10+'Юнит 09-15.02'!AB10+'Юнит 16-22.02'!AB10+'Юнит 23-28.02'!AB10 -> 0 | AC10: ='Юнит 01.02'!AC10+'Юнит 02-08.02'!AC10+'Юнит 09-15.02'!AC10+'Юнит 16-22.02'!AC10+'Юнит 23-28.02'!AC10 -> 0 | AD10: ='Юнит 01.02'!AD10+'Юнит 02-08.02'!AD10+'Юнит 09-15.02'!AD10+'Юнит 16-22.02'!AD10+'Юнит 23-28.02'!AD10 -> 255.1024 | AE10: =U10-W10-X10-Z10-AA10-AB10-AC10-AD10 -> 14360.07 | AG10: =IF(R10=0,0,U10/R10) -> 2149.4286 | AH10: =H10 -> 123 | AI10: =IF(R10=0,0,X10/R10) -> 924.25429 | AJ10: =IF(P10=0,Z10/1,Z10/P10) -> 202.4925 | AK10: =IF(P10=0,0,AA10/P10) -> 377.71136 | AL10: {=_xlfn.IFS(R10=0,AE10,R10<0,AE10/-R10,R10>0,AE10/R10)} -> 512.85963 | AM10: =IF(AG10=0,0,AL10/AG10) -> 0.23860278 | AN10: =IF(AH10=0,0,AL10/AH10) -> 4.1695905 | AP10: =AL10*C10 -> 0
A11: 3064346962 | B11: th желт | H11: 123 | I11: =C11*H11 -> 0 | N11: =K11/7 -> 0 | O11: =R11/7 -> 15 | P11: ='Юнит 01.02'!P11+'Юнит 02-08.02'!P11+'Юнит 09-15.02'!P11+'Юнит 16-22.02'!P11+'Юнит 23-28.02'!P11 -> 109 | Q11: ='Юнит 01.02'!Q11+'Юнит 02-08.02'!Q11+'Юнит 09-15.02'!Q11+'Юнит 16-22.02'!Q11+'Юнит 23-28.02'!Q11 -> 4 | R11: =P11-Q11 -> 105 | S11: ='Юнит 01.02'!S11+'Юнит 02-08.02'!S11+'Юнит 09-15.02'!S11+'Юнит 16-22.02'!S11+'Юнит 23-28.02'!S11 -> 232120 | T11: ='Юнит 01.02'!T11+'Юнит 02-08.02'!T11+'Юнит 09-15.02'!T11+'Юнит 16-22.02'!T11+'Юнит 23-28.02'!T11 -> -8650 | U11: =S11+T11 -> 223470 | V11: =U11/$U$24 -> 0.18479102 | W11: =R11*H11 -> 12915 | X11: ='Юнит 01.02'!X11+'Юнит 02-08.02'!X11+'Юнит 09-15.02'!X11+'Юнит 16-22.02'!X11+'Юнит 23-28.02'!X11 -> 96092.1 | Y11: =IF(U11=0,0,X11/U11) -> 0.43 | Z11: ='Юнит 01.02'!Z11+'Юнит 02-08.02'!Z11+'Юнит 09-15.02'!Z11+'Юнит 16-22.02'!Z11+'Юнит 23-28.02'!Z11 -> 21306.63 | AA11: ='Юнит 01.02'!AA11+'Юнит 02-08.02'!AA11+'Юнит 09-15.02'!AA11+'Юнит 16-22.02'!AA11+'Юнит 23-28.02'!AA11 -> 45590.448 | AB11: ='Юнит 01.02'!AB11+'Юнит 02-08.02'!AB11+'Юнит 09-15.02'!AB11+'Юнит 16-22.02'!AB11+'Юнит 23-28.02'!AB11 -> 0 | AC11: ='Юнит 01.02'!AC11+'Юнит 02-08.02'!AC11+'Юнит 09-15.02'!AC11+'Юнит 16-22.02'!AC11+'Юнит 23-28.02'!AC11 -> 0 | AD11: ='Юнит 01.02'!AD11+'Юнит 02-08.02'!AD11+'Юнит 09-15.02'!AD11+'Юнит 16-22.02'!AD11+'Юнит 23-28.02'!AD11 -> 937.46644 | AE11: =U11-W11-X11-Z11-AA11-AB11-AC11-AD11 -> 46628.355 | AG11: =IF(R11=0,0,U11/R11) -> 2128.2857 | AH11: =H11 -> 123 | AI11: =IF(R11=0,0,X11/R11) -> 915.16286 | AJ11: =IF(P11=0,Z11/1,Z11/P11) -> 195.47367 | AK11: =IF(P11=0,0,AA11/P11) -> 418.26099 | AL11: {=_xlfn.IFS(R11=0,AE11,R11<0,AE11/-R11,R11>0,AE11/R11)} -> 444.07957 | AM11: =IF(AG11=0,0,AL11/AG11) -> 0.208656 | AN11: =IF(AH11=0,0,AL11/AH11) -> 3.610403 | AP11: =AL11*C11 -> 0
A12: 3405092873 | B12: th коричн | H12: 117 | I12: =C12*H12 -> 0 | N12: =K12/7 -> 0 | O12: =R12/7 -> 3.4285714 | P12: ='Юнит 01.02'!P12+'Юнит 02-08.02'!P12+'Юнит 09-15.02'!P12+'Юнит 16-22.02'!P12+'Юнит 23-28.02'!P12 -> 24 | Q12: ='Юнит 01.02'!Q12+'Юнит 02-08.02'!Q12+'Юнит 09-15.02'!Q12+'Юнит 16-22.02'!Q12+'Юнит 23-28.02'!Q12 -> 0 | R12: =P12-Q12 -> 24 | S12: ='Юнит 01.02'!S12+'Юнит 02-08.02'!S12+'Юнит 09-15.02'!S12+'Юнит 16-22.02'!S12+'Юнит 23-28.02'!S12 -> 54824 | T12: ='Юнит 01.02'!T12+'Юнит 02-08.02'!T12+'Юнит 09-15.02'!T12+'Юнит 16-22.02'!T12+'Юнит 23-28.02'!T12 -> 0 | U12: =S12+T12 -> 54824 | V12: =U12/$U$24 -> 0.045334868 | W12: =R12*H12 -> 2808 | X12: ='Юнит 01.02'!X12+'Юнит 02-08.02'!X12+'Юнит 09-15.02'!X12+'Юнит 16-22.02'!X12+'Юнит 23-28.02'!X12 -> 23574.32 | Y12: =IF(U12=0,0,X12/U12) -> 0.43 | Z12: ='Юнит 01.02'!Z12+'Юнит 02-08.02'!Z12+'Юнит 09-15.02'!Z12+'Юнит 16-22.02'!Z12+'Юнит 23-28.02'!Z12 -> 5507.28 | AA12: ='Юнит 01.02'!AA12+'Юнит 02-08.02'!AA12+'Юнит 09-15.02'!AA12+'Юнит 16-22.02'!AA12+'Юнит 23-28.02'!AA12 -> 18635.689 | AB12: ='Юнит 01.02'!AB12+'Юнит 02-08.02'!AB12+'Юнит 09-15.02'!AB12+'Юнит 16-22.02'!AB12+'Юнит 23-28.02'!AB12 -> 0 | AC12: ='Юнит 01.02'!AC12+'Юнит 02-08.02'!AC12+'Юнит 09-15.02'!AC12+'Юнит 16-22.02'!AC12+'Юнит 23-28.02'!AC12 -> 0 | AD12: ='Юнит 01.02'!AD12+'Юнит 02-08.02'!AD12+'Юнит 09-15.02'!AD12+'Юнит 16-22.02'!AD12+'Юнит 23-28.02'!AD12 -> 233.76537 | AE12: =U12-W12-X12-Z12-AA12-AB12-AC12-AD12 -> 4064.9459 | AG12: =IF(R12=0,0,U12/R12) -> 2284.3333 | AH12: =H12 -> 117 | AI12: =IF(R12=0,0,X12/R12) -> 982.26333 | AJ12: =IF(P12=0,Z12/1,Z12/P12) -> 229.47 | AK12: =IF(P12=0,0,AA12/P12) -> 776.48703 | AL12: {=_xlfn.IFS(R12=0,AE12,R12<0,AE12/-R12,R12>0,AE12/R12)} -> 169.37274 | AM12: =IF(AG12=0,0,AL12/AG12) -> 0.074145372 | AN12: =IF(AH12=0,0,AL12/AH12) -> 1.4476303 | AP12: =AL12*C12 -> 0
A13: 3405092993 | B13: flip черный | H13: 123 | I13: =C13*H13 -> 0 | N13: =K13/7 -> 0 | O13: =R13/7 -> 5.2857143 | P13: ='Юнит 01.02'!P13+'Юнит 02-08.02'!P13+'Юнит 09-15.02'!P13+'Юнит 16-22.02'!P13+'Юнит 23-28.02'!P13 -> 39 | Q13: ='Юнит 01.02'!Q13+'Юнит 02-08.02'!Q13+'Юнит 09-15.02'!Q13+'Юнит 16-22.02'!Q13+'Юнит 23-28.02'!Q13 -> 2 | R13: =P13-Q13 -> 37 | S13: ='Юнит 01.02'!S13+'Юнит 02-08.02'!S13+'Юнит 09-15.02'!S13+'Юнит 16-22.02'!S13+'Юнит 23-28.02'!S13 -> 89712 | T13: ='Юнит 01.02'!T13+'Юнит 02-08.02'!T13+'Юнит 09-15.02'!T13+'Юнит 16-22.02'!T13+'Юнит 23-28.02'!T13 -> -4800 | U13: =S13+T13 -> 84912 | V13: =U13/$U$24 -> 0.070215131 | W13: =R13*H13 -> 4551 | X13: ='Юнит 01.02'!X13+'Юнит 02-08.02'!X13+'Юнит 09-15.02'!X13+'Юнит 16-22.02'!X13+'Юнит 23-28.02'!X13 -> 36512.16 | Y13: =IF(U13=0,0,X13/U13) -> 0.43 | Z13: ='Юнит 01.02'!Z13+'Юнит 02-08.02'!Z13+'Юнит 09-15.02'!Z13+'Юнит 16-22.02'!Z13+'Юнит 23-28.02'!Z13 -> 9929.82 | AA13: ='Юнит 01.02'!AA13+'Юнит 02-08.02'!AA13+'Юнит 09-15.02'!AA13+'Юнит 16-22.02'!AA13+'Юнит 23-28.02'!AA13 -> 20305.326 | AB13: ='Юнит 01.02'!AB13+'Юнит 02-08.02'!AB13+'Юнит 09-15.02'!AB13+'Юнит 16-22.02'!AB13+'Юнит 23-28.02'!AB13 -> 0 | AC13: ='Юнит 01.02'!AC13+'Юнит 02-08.02'!AC13+'Юнит 09-15.02'!AC13+'Юнит 16-22.02'!AC13+'Юнит 23-28.02'!AC13 -> 0 | AD13: ='Юнит 01.02'!AD13+'Юнит 02-08.02'!AD13+'Юнит 09-15.02'!AD13+'Юнит 16-22.02'!AD13+'Юнит 23-28.02'!AD13 -> 364.83371 | AE13: =U13-W13-X13-Z13-AA13-AB13-AC13-AD13 -> 13248.86 | AG13: =IF(R13=0,0,U13/R13) -> 2294.9189 | AH13: =H13 -> 123 | AI13: =IF(R13=0,0,X13/R13) -> 986.81514 | AJ13: =IF(P13=0,Z13/1,Z13/P13) -> 254.61077 | AK13: =IF(P13=0,0,AA13/P13) -> 520.64939 | AL13: {=_xlfn.IFS(R13=0,AE13,R13<0,AE13/-R13,R13>0,AE13/R13)} -> 358.0773 | AM13: =IF(AG13=0,0,AL13/AG13) -> 0.15603048 | AN13: =IF(AH13=0,0,AL13/AH13) -> 2.9111976 | AP13: =AL13*C13 -> 0
A14: 3405092868 | B14: flip синий | H14: 123 | I14: =C14*H14 -> 0 | N14: =K14/7 -> 0 | O14: =R14/7 -> 3.1428571 | P14: ='Юнит 01.02'!P14+'Юнит 02-08.02'!P14+'Юнит 09-15.02'!P14+'Юнит 16-22.02'!P14+'Юнит 23-28.02'!P14 -> 23 | Q14: ='Юнит 01.02'!Q14+'Юнит 02-08.02'!Q14+'Юнит 09-15.02'!Q14+'Юнит 16-22.02'!Q14+'Юнит 23-28.02'!Q14 -> 1 | R14: =P14-Q14 -> 22 | S14: ='Юнит 01.02'!S14+'Юнит 02-08.02'!S14+'Юнит 09-15.02'!S14+'Юнит 16-22.02'!S14+'Юнит 23-28.02'!S14 -> 49880 | T14: ='Юнит 01.02'!T14+'Юнит 02-08.02'!T14+'Юнит 09-15.02'!T14+'Юнит 16-22.02'!T14+'Юнит 23-28.02'!T14 -> -2000 | U14: =S14+T14 -> 47880 | V14: =U14/$U$24 -> 0.03959276 | W14: =R14*H14 -> 2706 | X14: ='Юнит 01.02'!X14+'Юнит 02-08.02'!X14+'Юнит 09-15.02'!X14+'Юнит 16-22.02'!X14+'Юнит 23-28.02'!X14 -> 20588.4 | Y14: =IF(U14=0,0,X14/U14) -> 0.43 | Z14: ='Юнит 01.02'!Z14+'Юнит 02-08.02'!Z14+'Юнит 09-15.02'!Z14+'Юнит 16-22.02'!Z14+'Юнит 23-28.02'!Z14 -> 4060.76 | AA14: ='Юнит 01.02'!AA14+'Юнит 02-08.02'!AA14+'Юнит 09-15.02'!AA14+'Юнит 16-22.02'!AA14+'Юнит 23-28.02'!AA14 -> 11015.929 | AB14: ='Юнит 01.02'!AB14+'Юнит 02-08.02'!AB14+'Юнит 09-15.02'!AB14+'Юнит 16-22.02'!AB14+'Юнит 23-28.02'!AB14 -> 0 | AC14: ='Юнит 01.02'!AC14+'Юнит 02-08.02'!AC14+'Юнит 09-15.02'!AC14+'Юнит 16-22.02'!AC14+'Юнит 23-28.02'!AC14 -> 0 | AD14: ='Юнит 01.02'!AD14+'Юнит 02-08.02'!AD14+'Юнит 09-15.02'!AD14+'Юнит 16-22.02'!AD14+'Юнит 23-28.02'!AD14 -> 203.00061 | AE14: =U14-W14-X14-Z14-AA14-AB14-AC14-AD14 -> 9305.9105 | AG14: =IF(R14=0,0,U14/R14) -> 2176.3636 | AH14: =H14 -> 123 | AI14: =IF(R14=0,0,X14/R14) -> 935.83636 | AJ14: =IF(P14=0,Z14/1,Z14/P14) -> 176.55478 | AK14: =IF(P14=0,0,AA14/P14) -> 478.95343 | AL14: {=_xlfn.IFS(R14=0,AE14,R14<0,AE14/-R14,R14>0,AE14/R14)} -> 422.99593 | AM14: =IF(AG14=0,0,AL14/AG14) -> 0.19435903 | AN14: =IF(AH14=0,0,AL14/AH14) -> 3.4389913 | AP14: =AL14*C14 -> 0
