Workbook

Sheet Сводная
A1: Период | D1: Дата поступления дс | E1: Итого к перечислению на счет, руб | F1: шт. | I1: Выручка | L1: Себестоимость продаж | M1: Логистика | N1: Комиссия | O1: Хранение | P1: Платная приемка | Q1: Штрафы | R1: Реклама Ozon | S1: Прочее | T1: Доп. услуги | U1: Услуги FBO | V1: Компенсировано | W1: Прочие начисления | X1: Налог | Y1: Итого | Z1: Итог месяц | AA1: % Cебестоимости | AB1: Маржинальность, % | AC1: Рентабельность, % | AD1: Доля рекламы, %
A2: Месяц | B2: Даты | C2: Нед | F2: Заказы | G2: Продажи | H2: Возвраты | I2: Продажи | J2: Возвраты | K2: Общая
A3: Январь | B3: 01-04.01 | E3: =K3-SUM(M3:U3)+V3+W3 -> 1074.71 | F3: ='Юнит 01-04.01'!K24 -> 122 | G3: ='Юнит 01-04.01'!P$24 -> 51 | H3: ='Юнит 01-04.01'!Q$24 -> 1 | I3: ='Юнит 01-04.01'!S$24 -> 85937 | J3: ='Юнит 01-04.01'!T$24 -> -1600 | K3: =I3+J3 -> 84337 | L3: ='Юнит 01-04.01'!W$24 -> 6252.96 | M3: ='Юнит 01-04.01'!Z$24 -> 8548.62 | N3: ='Юнит 01-04.01'!X$24 -> 36264.91 | R3: ='Юнит 01-04.01'!AA$24 -> 36772.95 | S3: 1675.81 | T3: 0 | U3: 0 | X3: =(K3)*0.0571 -> 4815.6427 | Y3: =K3-SUM(M3:U3)-L3-X3+V3+W3 -> -9993.8927 | Z3: =SUM(Y3:Y7) -> 35805.029 | AA3: =L3/K3 -> 0.074142547 | AB3: =Y3/L3 -> -1.5982659 | AC3: =Y3/K3 -> -0.1184995 | AD3: =R3/K3 -> 0.43602393
B4: 05-11.01 | E4: =K4-SUM(M4:U4)+V4+W4 -> 57707.57 | F4: ='Юнит 05-11.01'!K$24 -> 183 | G4: ='Юнит 05-11.01'!P$24 -> 168 | H4: ='Юнит 05-11.01'!Q$24 -> 8 | I4: ='Юнит 05-11.01'!S$24 -> 277715 | J4: ='Юнит 05-11.01'!T$24 -> -13822 | K4: =I4+J4 -> 263893 | L4: ='Юнит 05-11.01'!W$24 -> 20205.96 | M4: ='Юнит 05-11.01'!Z$24 -> 28076.33 | N4: ='Юнит 05-11.01'!X$24 -> 113473.99 | R4: ='Юнит 05-11.01'!AA$24 -> 56365.38 | S4: 4144.33 | T4: 75 | U4: 4050.4 | X4: =(K4)*0.0571 -> 15068.29 | Y4: =K4-SUM(M4:U4)-L4-X4+V4+W4 -> 22433.32 | AA4: =L4/K4 -> 0.076568761 | AB4: =Y4/L4 -> 1.1102328 | AC4: =Y4/K4 -> 0.08500915 | AD4: =R4/K4 -> 0.2135918
B5: 12-18.01 | E5: =K5-SUM(M5:U5)+V5+W5 -> 36064.15 | F5: ='Юнит 12-18.01'!K$24 -> 144 | G5: ='Юнит 12-18.01'!P$24 -> 122 | H5: ='Юнит 12-18.01'!Q$24 -> 2 | I5: ='Юнит 12-18.01'!S$24 -> 211029 | J5: ='Юнит 12-18.01'!T$24 -> -3221 | K5: =I5+J5 -> 207808 | L5: ='Юнит 12-18.01'!W$24 -> 15093.09 | M5: ='Юнит 12-18.01'!Z$24 -> 24172.28 | N5: ='Юнит 12-18.01'!X$24 -> 89357.44 | R5: ='Юнит 12-18.01'!AA$24 -> 53249.12 | S5: 4025.01 | T5: 0 | U5: 940 | X5: =(K5)*0.0571 -> 11865.837 | Y5: =K5-SUM(M5:U5)-L5-X5+V5+W5 -> 9105.2232 | AA5: =L5/K5 -> 0.072629976 | AB5: =Y5/L5 -> 0.60327098 | AC5: =Y5/K5 -> 0.043815557 | AD5: =R5/K5 -> 0.25624192
B6: 19-25.01 | E6: =K6-SUM(M6:U6)+V6+W6 -> 34413.47 | F6: ='Юнит 19-25.01'!K$24 -> 154 | G6: ='Юнит 19-25.01'!P$24 -> 91 | H6: ='Юнит 19-25.01'!Q$24 -> 2 | I6: ='Юнит 19-25.01'!S$24 -> 161208 | J6: ='Юнит 19-25.01'!T$24 -> -3229 | K6: =I6+J6 -> 157979 | L6: ='Юнит 19-25.01'!W$24 -> 11132.49 | M6: ='Юнит 19-25.01'!Z$24 -> 16989.46 | N6: ='Юнит 19-25.01'!X$24 -> 67930.97 | R6: ='Юнит 19-25.01'!AA$24 -> 42151.21 | S6: 3468.89 | T6: 25 | U6: 0 | W6: 7000 | X6: =(K6)*0.0571 -> 9020.6009 | Y6: =K6-SUM(M6:U6)-L6-X6+V6+W6 -> 14260.379 | AA6: =L6/K6 -> 0.070468163 | AB6: =Y6/L6 -> 1.2809694 | AC6: =Y6/K6 -> 0.090267562 | AD6: =R6/K6 -> 0.26681527
B7: 24-31.01 | E7: =K7-SUM(M7:U7)+V7+W7 -> 0 | F7: ='Юнит 26-31.01'!K$24 -> 0 | G7: ='Юнит 26-31.01'!P$24 -> 0 | H7: ='Юнит 26-31.01'!Q$24 -> 0 | I7: ='Юнит 26-31.01'!S$24 -> 0 | J7: ='Юнит 26-31.01'!T$24 -> 0 | K7: =I7+J7 -> 0 | L7: ='Юнит 26-31.01'!W$24 -> 0 | M7: ='Юнит 26-31.01'!Z$24 -> 0 | N7: ='Юнит 26-31.01'!X$24 -> 0 | R7: ='Юнит 26-31.01'!AA$24 -> 0 | X7: =(K7)*0.0571 -> 0 | Y7: =K7-SUM(M7:U7)-L7-X7+V7+W7 -> 0 | AA7: =L7/K7 -> #DIV/0! | AB7: =Y7/L7 -> #DIV/0! | AC7: =Y7/K7 -> #DIV/0! | AD7: =R7/K7 -> #DIV/0!
A8: Итого | E8: =SUM(E3:E7) -> 129259.9 | F8: =SUM(F3:F7) -> 603 | G8: =SUM(G3:G7) -> 432 | H8: =SUM(H3:H7) -> 13 | I8: =SUM(I3:I7) -> 735889 | J8: =SUM(J3:J7) -> -21872 | K8: =SUM(K3:K7) -> 714017 | L8: =SUM(L3:L7) -> 52684.5 | ... Z8: =SUM(Z3:Z7) -> 35805.029 | AA8: =L8/K8 -> 0.073786058 | AB8: =Y8/L8 -> 0.67961221 | AC8: =Y8/K8 -> 0.050145906 | AD8: =R8/K8 -> 0.26405346
I9: % от выручки за весь период
J10: =-J8/I8 -> 0.029721874 | K10: 0 | L10: =L8/$K$8 -> 0.073786058 | M10: =M8/$K$8 -> 0.10894235 | N10: =N8/$K$8 -> 0.43 | R10: =R8/$K$8 -> 0.26405346 | X10: =X8/$K$8 -> 0.0571 | Y10: =Y8/L8 -> 0.67961221 | Z10: Маржинальность, %

Sheet АВС 01.02
B2: ОЧКИ
C3: Прибыль | D3: % прибыль | E3: Доля | F3: ABC прибыль | G3: ABC кол-во | J3: Кол-во | K3: % кол-во | L3: Доля | M3: ABC кол-во
B4: черные с железкой классика | D4: =C4/C$18 -> #DIV/0! | E4: =D4 -> #DIV/0! | F4: =IF(AND(E4<=0),"C",IF(E4<=0.8,"A",IF(E4<=0.95,"B","C"))) -> #DIV/0! | G4: =VLOOKUP(B$4:B$17,I$4:M$17,5,0) -> #DIV/0! | I4: черные с железкой классика | K4: =J4/J$18 -> #DIV/0! | L4: =K4 -> #DIV/0! | M4: =_xlfn.IFS(L4<80%,"A",L4<=95%,"B",L4>95%,"C") -> #DIV/0!
B5: qs черные | D5: =C5/C$18 -> #DIV/0! | E5: =D5+E4 -> #DIV/0! | F5: =IF(AND(E5<=0),"C",IF(E5<=0.8,"A",IF(E5<=0.95,"B","C"))) -> #DIV/0! | G5: =VLOOKUP(B$4:B$17,I$4:M$17,5,0) -> #DIV/0! | I5: qs черные | K5: =J5/J$18 -> #DIV/0! | L5: =K5+L4 -> #DIV/0! | M5: =_xlfn.IFS(L5<80%,"A",L5<=95%,"B",L5>95%,"C") -> #DIV/0!
B6: qs синие | D6: =C6/C$18 -> #DIV/0! | E6: =D6+E5 -> #DIV/0! | F6: =IF(AND(E6<=0),"C",IF(E6<=0.8,"A",IF(E6<=0.95,"B","C"))) -> #DIV/0! | G6: =VLOOKUP(B$4:B$17,I$4:M$17,5,0) -> #DIV/0! | I6: qs синие | K6: =J6/J$18 -> #DIV/0! | L6: =K6+L5 -> #DIV/0! | M6: =_xlfn.IFS(L6<80%,"A",L6<=95%,"B",L6>95%,"C") -> #DIV/0!
B7: qs желтые | D7: =C7/C$18 -> #DIV/0! | E7: =D7+E6 -> #DIV/0! | F7: =IF(AND(E7<=0),"C",IF(E7<=0.8,"A",IF(E7<=0.95,"B","C"))) -> #DIV/0! | G7: =VLOOKUP(B$4:B$17,I$4:M$17,5,0) -> #DIV/0! | I7: qs желтые | K7: =J7/J$18 -> #DIV/0! | L7: =K7+L6 -> #DIV/0! | M7: =_xlfn.IFS(L7<80%,"A",L7<=95%,"B",L7>95%,"C") -> #DIV/0!
B8: qs коричневые | D8: =C8/C$18 -> #DIV/0! | E8: =D8+E7 -> #DIV/0! | F8: =IF(AND(E8<=0),"C",IF(E8<=0.8,"A",IF(E8<=0.95,"B","C"))) -> #DIV/0! | G8: =VLOOKUP(B$4:B$17,I$4:M$17,5,0) -> #DIV/0! | I8: qs коричневые | K8: =J8/J$18 -> #DIV/0! | L8: =K8+L7 -> #DIV/0! | M8: =_xlfn.IFS(L8<80%,"A",L8<=95%,"B",L8>95%,"C") -> #DIV/0!
B9: MR8854 C2 | D9: =C9/C$18 -> #DIV/0! | E9: =D9+E8 -> #DIV/0! | F9: =IF(AND(E9<=0),"C",IF(E9<=0.8,"A",IF(E9<=0.95,"B","C"))) -> #DIV/0! | G9: =VLOOKUP(B$4:B$17,I$4:M$17,5,0) -> #DIV/0! | I9: MR8854 C2 | K9: =J9/J$18 -> #DIV/0! | L9: =K9+L8 -> #DIV/0! | M9: =_xlfn.IFS(L9<80%,"A",L9<=95%,"B",L9>95%,"C") -> #DIV/0!
B10: th черн | D10: =C10/C$18 -> #DIV/0! | E10: =D10+E9 -> #DIV/0! | F10: =IF(AND(E10<=0),"C",IF(E10<=0.8,"A",IF(E10<=0.95,"B","C"))) -> #DIV/0! | G10: =VLOOKUP(B$4:B$17,I$4:M$17,5,0) -> #DIV/0! | I10: th черн | K10: =J10/J$18 -> #DIV/0! | L10: =K10+L9 -> #DIV/0! | M10: =_xlfn.IFS(L10<80%,"A",L10<=95%,"B",L10>95%,"C") -> #DIV/0!
B11: th син | D11: =C11/C$18 -> #DIV/0! | E11: =D11+E10 -> #DIV/0! | F11: =IF(AND(E11<=0),"C",IF(E11<=0.8,"A",IF(E11<=0.95,"B","C"))) -> #DIV/0! | G11: =VLOOKUP(B$4:B$17,I$4:M$17,5,0) -> #DIV/0! | I11: th син | K11: =J11/J$18 -> #DIV/0! | L11: =K11+L10 -> #DIV/0! | M11: =_xlfn.IFS(L11<80%,"A",L11<=95%,"B",L11>95%,"C") -> #DIV/0!
B12: th желт | D12: =C12/C$18 -> #DIV/0! | E12: =D12+E5 -> #DIV/0! | F12: =IF(AND(E12<=0),"C",IF(E12<=0.8,"A",IF(E12<=0.95,"B","C"))) -> #DIV/0! | G12: =VLOOKUP(B$4:B$17,I$4:M$17,5,0) -> #DIV/0! | I12: th желт | K12: =J12/J$18 -> #DIV/0! | L12: =K12+L5 -> #DIV/0! | M12: =_xlfn.IFS(L12<80%,"A",L12<=95%,"B",L12>95%,"C") -> #DIV/0!
B13: th коричн | D13: =C13/C$18 -> #DIV/0! | E13: =D13+E12 -> #DIV/0! | F13: =IF(AND(E13<=0),"C",IF(E13<=0.8,"A",IF(E13<=0.95,"B","C"))) -> #DIV/0! | G13: =VLOOKUP(B$4:B$17,I$4:M$17,5,0) -> #DIV/0! | I13: th коричн | K13: =J13/J$18 -> #DIV/0! | L13: =K13+L12 -> #DIV/0! | M13: =_xlfn.IFS(L13<80%,"A",L13<=95%,"B",L13>95%,"C") -> #DIV/0!
B14: flip черный | D14: =C14/C$18 -> #DIV/0! | E14: =D14+E13 -> #DIV/0! | F14: =IF(AND(E14<=0),"C",IF(E14<=0.8,"A",IF(E14<=0.95,"B","C"))) -> #DIV/0! | G14: =VLOOKUP(B$4:B$17,I$4:M$17,5,0) -> #DIV/0! | I14: flip черный | K14: =J14/J$18 -> #DIV/0! | L14: =K14+L13 -> #DIV/0! | M14: =_xlfn.IFS(L14<80%,"A",L14<=95%,"B",L14>95%,"C") -> #DIV/0!
B15: flip синий | D15: =C15/C$18 -> #DIV/0! | E15: =D15+E14 -> #DIV/0! | F15: =IF(AND(E15<=0),"C",IF(E15<=0.8,"A",IF(E15<=0.95,"B","C"))) -> #DIV/0! | G15: =VLOOKUP(B$4:B$17,I$4:M$17,5,0) -> #DIV/0! | I15: flip синий | K15: =J15/J$18 -> #DIV/0! | L15: =K15+L14 -> #DIV/0! | M15: =_xlfn.IFS(L15<80%,"A",L15<=95%,"B",L15>95%,"C") -> #DIV/0!
B16: flip жел | D16: =C16/C$18 -> #DIV/0! | E16: =D16+E15 -> #DIV/0! | F16: =IF(AND(E16<=0),"C",IF(E16<=0.8,"A",IF(E16<=0.95,"B","C"))) -> #DIV/0! | G16: =VLOOKUP(B$4:B$17,I$4:M$17,5,0) -> #DIV/0! | I16: flip жел | K16: =J16/J$18 -> #DIV/0! | L16: =K16+L15 -> #DIV/0! | M16: =_xlfn.IFS(L16<80%,"A",L16<=95%,"B",L16>95%,"C") -> #DIV/0!
B17: flip коричневый | D17: =C17/C$18 -> #DIV/0! | E17: =D17+E14 -> #DIV/0! | F17: =IF(AND(E17<=0),"C",IF(E17<=0.8,"A",IF(E17<=0.95,"B","C"))) -> #DIV/0! | G17: =VLOOKUP(B$4:B$17,I$4:M$17,5,0) -> #DIV/0! | I17: flip коричневый | K17: =J17/J$18 -> #DIV/0! | L17: =K17+L14 -> #DIV/0! | M17: =_xlfn.IFS(L17<80%,"A",L17<=95%,"B",L17>95%,"C") -> #DIV/0!
C18: =SUM(C4:C17) -> 0 | D18: =SUM(D4:D17) -> #DIV/0! | J18: =SUM(J4:J17) -> 0 | K18: =SUM(K4:K17) -> #DIV/0!
C21: Прибыль | D21: % прибыль | E21: Доля | F21: ABC прибыль | G21: ABC кол-во | J21: Кол-во | K21: % кол-во | L21: Доля | M21: ABC кол-во
D22: =C22/C$42 -> #DIV/0! | E22: =D22 -> #DIV/0! | F22: =IF(AND(E22<=0),"C",IF(E22<=0.8,"A",IF(E22<=0.95,"B","C"))) -> #DIV/0! | G22: =VLOOKUP(B$22:B$42,I$22:M$42,5,0) -> #N/A | K22: =J22/J$42 -> #DIV/0! | L22: =K22 -> #DIV/0! | M22: =_xlfn.IFS(L22<80%,"A",L22<=95%,"B",L22>95%,"C") -> #DIV/0!
D23: =C23/C$42 -> #DIV/0! | E23: =D23+E22 -> #DIV/0! | F23: =IF(AND(E23<=0),"C",IF(E23<=0.8,"A",IF(E23<=0.95,"B","C"))) -> #DIV/0! | G23: =VLOOKUP(B$22:B$42,I$22:M$42,5,0) -> #N/A | K23: =J23/J$42 -> #DIV/0! | L23: =K23+L22 -> #DIV/0! | M23: =_xlfn.IFS(L23<80%,"A",L23<=95%,"B",L23>95%,"C") -> #DIV/0!
D24: =C24/C$42 -> #DIV/0! | E24: =D24+E23 -> #DIV/0! | F24: =IF(AND(E24<=0),"C",IF(E24<=0.8,"A",IF(E24<=0.95,"B","C"))) -> #DIV/0! | G24: =VLOOKUP(B$22:B$42,I$22:M$42,5,0) -> #N/A | K24: =J24/J$42 -> #DIV/0! | L24: =K24+L23 -> #DIV/0! | M24: =_xlfn.IFS(L24<80%,"A",L24<=95%,"B",L24>95%,"C") -> #DIV/0!
D25: =C25/C$42 -> #DIV/0! | E25: =D25+E24 -> #DIV/0! | F25: =IF(AND(E25<=0),"C",IF(E25<=0.8,"A",IF(E25<=0.95,"B","C"))) -> #DIV/0! | G25: =VLOOKUP(B$22:B$42,I$22:M$42,5,0) -> #N/A | K25: =J25/J$42 -> #DIV/0! | L25: =K25+L24 -> #DIV/0! | M25: =_xlfn.IFS(L25<80%,"A",L25<=95%,"B",L25>95%,"C") -> #DIV/0!
D26: =C26/C$42 -> #DIV/0! | E26: =D26+E25 -> #DIV/0! | F26: =IF(AND(E26<=0),"C",IF(E26<=0.8,"A",IF(E26<=0.95,"B","C"))) -> #DIV/0! | G26: =VLOOKUP(B$22:B$42,I$22:M$42,5,0) -> #N/A | K26: =J26/J$42 -> #DIV/0! | L26: =K26+L25 -> #DIV/0! | M26: =_xlfn.IFS(L26<80%,"A",L26<=95%,"B",L26>95%,"C") -> #DIV/0!
D27: =C27/C$42 -> #DIV/0! | E27: =D27+E26 -> #DIV/0! | F27: =IF(AND(E27<=0),"C",IF(E27<=0.8,"A",IF(E27<=0.95,"B","C"))) -> #DIV/0! | G27: =VLOOKUP(B$22:B$42,I$22:M$42,5,0) -> #N/A | K27: =J27/J$42 -> #DIV/0! | L27: =K27+L26 -> #DIV/0! | M27: =_xlfn.IFS(L27<80%,"A",L27<=95%,"B",L27>95%,"C") -> #DIV/0!
D28: =C28/C$42 -> #DIV/0! | E28: =D28+E27 -> #DIV/0! | F28: =IF(AND(E28<=0),"C",IF(E28<=0.8,"A",IF(E28<=0.95,"B","C"))) -> #DIV/0! | G28: =VLOOKUP(B$22:B$42,I$22:M$42,5,0) -> #N/A | K28: =J28/J$42 -> #DIV/0! | L28: =K28+L27 -> #DIV/0! | M28: =_xlfn.IFS(L28<80%,"A",L28<=95%,"B",L28>95%,"C") -> #DIV/0!
D29: =C29/C$42 -> #DIV/0! | E29: =D29+E28 -> #DIV/0! | F29: =IF(AND(E29<=0),"C",IF(E29<=0.8,"A",IF(E29<=0.95,"B","C"))) -> #DIV/0! | G29: =VLOOKUP(B$22:B$42,I$22:M$42,5,0) -> #N/A | K29: =J29/J$42 -> #DIV/0! | L29: =K29+L28 -> #DIV/0! | M29: =_xlfn.IFS(L29<80%,"A",L29<=95%,"B",L29>95%,"C") -> #DIV/0!
D30: =C30/C$42 -> #DIV/0! | E30: =D30+E29 -> #DIV/0! | F30: =IF(AND(E30<=0),"C",IF(E30<=0.8,"A",IF(E30<=0.95,"B","C"))) -> #DIV/0! | G30: =VLOOKUP(B$22:B$42,I$22:M$42,5,0) -> #N/A | K30: =J30/J$42 -> #DIV/0! | L30: =K30+L29 -> #DIV/0! | M30: =_xlfn.IFS(L30<80%,"A",L30<=95%,"B",L30>95%,"C") -> #DIV/0!
D31: =C31/C$42 -> #DIV/0! | E31: =D31+E30 -> #DIV/0! | F31: =IF(AND(E31<=0),"C",IF(E31<=0.8,"A",IF(E31<=0.95,"B","C"))) -> #DIV/0! | G31: =VLOOKUP(B$22:B$42,I$22:M$42,5,0) -> #N/A | K31: =J31/J$42 -> #DIV/0! | L31: =K31+L30 -> #DIV/0! | M31: =_xlfn.IFS(L31<80%,"A",L31<=95%,"B",L31>95%,"C") -> #DIV/0!
D32: =C32/C$42 -> #DIV/0! | E32: =D32+E31 -> #DIV/0! | F32: =IF(AND(E32<=0),"C",IF(E32<=0.8,"A",IF(E32<=0.95,"B","C"))) -> #DIV/0! | G32: =VLOOKUP(B$22:B$42,I$22:M$42,5,0) -> #N/A | K32: =J32/J$42 -> #DIV/0! | L32: =K32+L31 -> #DIV/0! | M32: =_xlfn.IFS(L32<80%,"A",L32<=95%,"B",L32>95%,"C") -> #DIV/0!
D33: =C33/C$42 -> #DIV/0! | E33: =D33+E32 -> #DIV/0! | F33: =IF(AND(E33<=0),"C",IF(E33<=0.8,"A",IF(E33<=0.95,"B","C"))) -> #DIV/0! | G33: =VLOOKUP(B$22:B$42,I$22:M$42,5,0) -> #N/A | K33: =J33/J$42 -> #DIV/0! | L33: =K33+L32 -> #DIV/0! | M33: =_xlfn.IFS(L33<80%,"A",L33<=95%,"B",L33>95%,"C") -> #DIV/0!
D34: =C34/C$42 -> #DIV/0! | E34: =D34+E33 -> #DIV/0! | F34: =IF(AND(E34<=0),"C",IF(E34<=0.8,"A",IF(E34<=0.95,"B","C"))) -> #DIV/0! | G34: =VLOOKUP(B$22:B$42,I$22:M$42,5,0) -> #N/A | K34: =J34/J$42 -> #DIV/0! | L34: =K34+L33 -> #DIV/0! | M34: =_xlfn.IFS(L34<80%,"A",L34<=95%,"B",L34>95%,"C") -> #DIV/0!
... D41: =C41/C$42 -> #DIV/0! | E41: =D41+E40 -> #DIV/0! | F41: =IF(AND(E41<=0),"C",IF(E41<=0.8,"A",IF(E41<=0.95,"B","C"))) -> #DIV/0! | G41: =VLOOKUP(B$22:B$42,I$22:M$42,5,0) -> #N/A | K41: =J41/J$42 -> #DIV/0! | L41: =K41+L40 -> #DIV/0! | M41: =_xlfn.IFS(L41<80%,"A",L41<=95%,"B",L41>95%,"C") -> #DIV/0!
C42: =SUM(C22:C41) -> 0 | D42: =SUM(D22:D41) -> #DIV/0! | J42: =SUM(J22:J41) -> 0 | K42: =SUM(K22:K41) -> #DIV/0!

Sheet АВС ЯНВАРЬ
B2: ОЧКИ
C3: Прибыль | D3: % прибыль | E3: Доля | F3: ABC прибыль | G3: ABC кол-во | J3: Кол-во | K3: % кол-во | L3: Доля | M3: ABC кол-во
B4: черные с железкой классика | D4: =C4/C$18 -> #DIV/0! | E4: =D4 -> #DIV/0! | F4: =IF(AND(E4<=0),"C",IF(E4<=0.8,"A",IF(E4<=0.95,"B","C"))) -> #DIV/0! | G4: =VLOOKUP(B$4:B$17,I$4:M$17,5,0) -> #DIV/0! | I4: черные с железкой классика | K4: =J4/J$18 -> #DIV/0! | L4: =K4 -> #DIV/0! | M4: =_xlfn.IFS(L4<80%,"A",L4<=95%,"B",L4>95%,"C") -> #DIV/0!
B5: qs черные | D5: =C5/C$18 -> #DIV/0! | E5: =D5+E4 -> #DIV/0! | F5: =IF(AND(E5<=0),"C",IF(E5<=0.8,"A",IF(E5<=0.95,"B","C"))) -> #DIV/0! | G5: =VLOOKUP(B$4:B$17,I$4:M$17,5,0) -> #DIV/0! | I5: qs черные | K5: =J5/J$18 -> #DIV/0! | L5: =K5+L4 -> #DIV/0! | M5: =_xlfn.IFS(L5<80%,"A",L5<=95%,"B",L5>95%,"C") -> #DIV/0!
B6: qs синие | D6: =C6/C$18 -> #DIV/0! | E6: =D6+E5 -> #DIV/0! | F6: =IF(AND(E6<=0),"C",IF(E6<=0.8,"A",IF(E6<=0.95,"B","C"))) -> #DIV/0! | G6: =VLOOKUP(B$4:B$17,I$4:M$17,5,0) -> #DIV/0! | I6: qs синие | K6: =J6/J$18 -> #DIV/0! | L6: =K6+L5 -> #DIV/0! | M6: =_xlfn.IFS(L6<80%,"A",L6<=95%,"B",L6>95%,"C") -> #DIV/0!
B7: qs желтые | D7: =C7/C$18 -> #DIV/0! | E7: =D7+E6 -> #DIV/0! | F7: =IF(AND(E7<=0),"C",IF(E7<=0.8,"A",IF(E7<=0.95,"B","C"))) -> #DIV/0! | G7: =VLOOKUP(B$4:B$17,I$4:M$17,5,0) -> #DIV/0! | I7: qs желтые | K7: =J7/J$18 -> #DIV/0! | L7: =K7+L6 -> #DIV/0! | M7: =_xlfn.IFS(L7<80%,"A",L7<=95%,"B",L7>95%,"C") -> #DIV/0!
B8: qs коричневые | D8: =C8/C$18 -> #DIV/0! | E8: =D8+E7 -> #DIV/0! | F8: =IF(AND(E8<=0),"C",IF(E8<=0.8,"A",IF(E8<=0.95,"B","C"))) -> #DIV/0! | G8: =VLOOKUP(B$4:B$17,I$4:M$17,5,0) -> #DIV/0! | I8: qs коричневые | K8: =J8/J$18 -> #DIV/0! | L8: =K8+L7 -> #DIV/0! | M8: =_xlfn.IFS(L8<80%,"A",L8<=95%,"B",L8>95%,"C") -> #DIV/0!
B9: MR8854 C2 | D9: =C9/C$18 -> #DIV/0! | E9: =D9+E8 -> #DIV/0! | F9: =IF(AND(E9<=0),"C",IF(E9<=0.8,"A",IF(E9<=0.95,"B","C"))) -> #DIV/0! | G9: =VLOOKUP(B$4:B$17,I$4:M$17,5,0) -> #DIV/0! | I9: MR8854 C2 | K9: =J9/J$18 -> #DIV/0! | L9: =K9+L8 -> #DIV/0! | M9: =_xlfn.IFS(L9<80%,"A",L9<=95%,"B",L9>95%,"C") -> #DIV/0!
B10: th черн | D10: =C10/C$18 -> #DIV/0! | E10: =D10+E9 -> #DIV/0! | F10: =IF(AND(E10<=0),"C",IF(E10<=0.8,"A",IF(E10<=0.95,"B","C"))) -> #DIV/0! | G10: =VLOOKUP(B$4:B$17,I$4:M$17,5,0) -> #DIV/0! | I10: th черн | K10: =J10/J$18 -> #DIV/0! | L10: =K10+L9 -> #DIV/0! | M10: =_xlfn.IFS(L10<80%,"A",L10<=95%,"B",L10>95%,"C") -> #DIV/0!
B11: th син | D11: =C11/C$18 -> #DIV/0! | E11: =D11+E10 -> #DIV/0! | F11: =IF(AND(E11<=0),"C",IF(E11<=0.8,"A",IF(E11<=0.95,"B","C"))) -> #DIV/0! | G11: =VLOOKUP(B$4:B$17,I$4:M$17,5,0) -> #DIV/0! | I11: th син | K11: =J11/J$18 -> #DIV/0! | L11: =K11+L10 -> #DIV/0! | M11: =_xlfn.IFS(L11<80%,"A",L11<=95%,"B",L11>95%,"C") -> #DIV/0!
B12: th желт | D12: =C12/C$18 -> #DIV/0! | E12: =D12+E5 -> #DIV/0! | F12: =IF(AND(E12<=0),"C",IF(E12<=0.8,"A",IF(E12<=0.95,"B","C"))) -> #DIV/0! | G12: =VLOOKUP(B$4:B$17,I$4:M$17,5,0) -> #DIV/0! | I12: th желт | K12: =J12/J$18 -> #DIV/0! | L12: =K12+L5 -> #DIV/0! | M12: =_xlfn.IFS(L12<80%,"A",L12<=95%,"B",L12>95%,"C") -> #DIV/0!
B13: th коричн | D13: =C13/C$18 -> #DIV/0! | E13: =D13+E12 -> #DIV/0! | F13: =IF(AND(E13<=0),"C",IF(E13<=0.8,"A",IF(E13<=0.95,"B","C"))) -> #DIV/0! | G13: =VLOOKUP(B$4:B$17,I$4:M$17,5,0) -> #DIV/0! | I13: th коричн | K13: =J13/J$18 -> #DIV/0! | L13: =K13+L12 -> #DIV/0! | M13: =_xlfn.IFS(L13<80%,"A",L13<=95%,"B",L13>95%,"C") -> #DIV/0!
B14: flip черный | D14: =C14/C$18 -> #DIV/0! | E14: =D14+E13 -> #DIV/0! | F14: =IF(AND(E14<=0),"C",IF(E14<=0.8,"A",IF(E14<=0.95,"B","C"))) -> #DIV/0! | G14: =VLOOKUP(B$4:B$17,I$4:M$17,5,0) -> #DIV/0! | I14: flip черный | K14: =J14/J$18 -> #DIV/0! | L14: =K14+L13 -> #DIV/0! | M14: =_xlfn.IFS(L14<80%,"A",L14<=95%,"B",L14>95%,"C") -> #DIV/0!
B15: flip синий | D15: =C15/C$18 -> #DIV/0! | E15: =D15+E14 -> #DIV/0! | F15: =IF(AND(E15<=0),"C",IF(E15<=0.8,"A",IF(E15<=0.95,"B","C"))) -> #DIV/0! | G15: =VLOOKUP(B$4:B$17,I$4:M$17,5,0) -> #DIV/0! | I15: flip синий | K15: =J15/J$18 -> #DIV/0! | L15: =K15+L14 -> #DIV/0! | M15: =_xlfn.IFS(L15<80%,"A",L15<=95%,"B",L15>95%,"C") -> #DIV/0!
B16: flip жел | D16: =C16/C$18 -> #DIV/0! | E16: =D16+E15 -> #DIV/0! | F16: =IF(AND(E16<=0),"C",IF(E16<=0.8,"A",IF(E16<=0.95,"B","C"))) -> #DIV/0! | G16: =VLOOKUP(B$4:B$17,I$4:M$17,5,0) -> #DIV/0! | I16: flip жел | K16: =J16/J$18 -> #DIV/0! | L16: =K16+L15 -> #DIV/0! | M16: =_xlfn.IFS(L16<80%,"A",L16<=95%,"B",L16>95%,"C") -> #DIV/0!
B17: flip коричневый | D17: =C17/C$18 -> #DIV/0! | E17: =D17+E14 -> #DIV/0! | F17: =IF(AND(E17<=0),"C",IF(E17<=0.8,"A",IF(E17<=0.95,"B","C"))) -> #DIV/0! | G17: =VLOOKUP(B$4:B$17,I$4:M$17,5,0) -> #DIV/0! | I17: flip коричневый | K17: =J17/J$18 -> #DIV/0! | L17: =K17+L14 -> #DIV/0! | M17: =_xlfn.IFS(L17<80%,"A",L17<=95%,"B",L17>95%,"C") -> #DIV/0!
C18: =SUM(C4:C17) -> 0 | D18: =SUM(D4:D17) -> #DIV/0! | J18: =SUM(J4:J17) -> 0 | K18: =SUM(K4:K17) -> #DIV/0!
C21: Прибыль | D21: % прибыль | E21: Доля | F21: ABC прибыль | G21: ABC кол-во | J21: Кол-во | K21: % кол-во | L21: Доля | M21: ABC кол-во
D22: =C22/C$42 -> #DIV/0! | E22: =D22 -> #DIV/0! | F22: =IF(AND(E22<=0),"C",IF(E22<=0.8,"A",IF(E22<=0.95,"B","C"))) -> #DIV/0! | G22: =VLOOKUP(B$22:B$42,I$22:M$42,5,0) -> #N/A | K22: =J22/J$42 -> #DIV/0! | L22: =K22 -> #DIV/0! | M22: =_xlfn.IFS(L22<80%,"A",L22<=95%,"B",L22>95%,"C") -> #DIV/0!
D23: =C23/C$42 -> #DIV/0! | E23: =D23+E22 -> #DIV/0! | F23: =IF(AND(E23<=0),"C",IF(E23<=0.8,"A",IF(E23<=0.95,"B","C"))) -> #DIV/0! | G23: =VLOOKUP(B$22:B$42,I$22:M$42,5,0) -> #N/A | K23: =J23/J$42 -> #DIV/0! | L23: =K23+L22 -> #DIV/0! | M23: =_xlfn.IFS(L23<80%,"A",L23<=95%,"B",L23>95%,"C") -> #DIV/0!
D24: =C24/C$42 -> #DIV/0! | E24: =D24+E23 -> #DIV/0! | F24: =IF(AND(E24<=0),"C",IF(E24<=0.8,"A",IF(E24<=0.95,"B","C"))) -> #DIV/0! | G24: =VLOOKUP(B$22:B$42,I$22:M$42,5,0) -> #N/A | K24: =J24/J$42 -> #DIV/0! | L24: =K24+L23 -> #DIV/0! | M24: =_xlfn.IFS(L24<80%,"A",L24<=95%,"B",L24>95%,"C") -> #DIV/0!
D25: =C25/C$42 -> #DIV/0! | E25: =D25+E24 -> #DIV/0! | F25: =IF(AND(E25<=0),"C",IF(E25<=0.8,"A",IF(E25<=0.95,"B","C"))) -> #DIV/0! | G25: =VLOOKUP(B$22:B$42,I$22:M$42,5,0) -> #N/A | K25: =J25/J$42 -> #DIV/0! | L25: =K25+L24 -> #DIV/0! | M25: =_xlfn.IFS(L25<80%,"A",L25<=95%,"B",L25>95%,"C") -> #DIV/0!
D26: =C26/C$42 -> #DIV/0! | E26: =D26+E25 -> #DIV/0! | F26: =IF(AND(E26<=0),"C",IF(E26<=0.8,"A",IF(E26<=0.95,"B","C"))) -> #DIV/0! | G26: =VLOOKUP(B$22:B$42,I$22:M$42,5,0) -> #N/A | K26: =J26/J$42 -> #DIV/0! | L26: =K26+L25 -> #DIV/0! | M26: =_xlfn.IFS(L26<80%,"A",L26<=95%,"B",L26>95%,"C") -> #DIV/0!
D27: =C27/C$42 -> #DIV/0! | E27: =D27+E26 -> #DIV/0! | F27: =IF(AND(E27<=0),"C",IF(E27<=0.8,"A",IF(E27<=0.95,"B","C"))) -> #DIV/0! | G27: =VLOOKUP(B$22:B$42,I$22:M$42,5,0) -> #N/A | K27: =J27/J$42 -> #DIV/0! | L27: =K27+L26 -> #DIV/0! | M27: =_xlfn.IFS(L27<80%,"A",L27<=95%,"B",L27>95%,"C") -> #DIV/0!
D28: =C28/C$42 -> #DIV/0! | E28: =D28+E27 -> #DIV/0! | F28: =IF(AND(E28<=0),"C",IF(E28<=0.8,"A",IF(E28<=0.95,"B","C"))) -> #DIV/0! | G28: =VLOOKUP(B$22:B$42,I$22:M$42,5,0) -> #N/A | K28: =J28/J$42 -> #DIV/0! | L28: =K28+L27 -> #DIV/0! | M28: =_xlfn.IFS(L28<80%,"A",L28<=95%,"B",L28>95%,"C") -> #DIV/0!
D29: =C29/C$42 -> #DIV/0! | E29: =D29+E28 -> #DIV/0! | F29: =IF(AND(E29<=0),"C",IF(E29<=0.8,"A",IF(E29<=0.95,"B","C"))) -> #DIV/0! | G29: =VLOOKUP(B$22:B$42,I$22:M$42,5,0) -> #N/A | K29: =J29/J$42 -> #DIV/0! | L29: =K29+L28 -> #DIV/0! | M29: =_xlfn.IFS(L29<80%,"A",L29<=95%,"B",L29>95%,"C") -> #DIV/0!
D30: =C30/C$42 -> #DIV/0! | E30: =D30+E29 -> #DIV/0! | F30: =IF(AND(E30<=0),"C",IF(E30<=0.8,"A",IF(E30<=0.95,"B","C"))) -> #DIV/0! | G30: =VLOOKUP(B$22:B$42,I$22:M$42,5,0) -> #N/A | K30: =J30/J$42 -> #DIV/0! | L30: =K30+L29 -> #DIV/0! | M30: =_xlfn.IFS(L30<80%,"A",L30<=95%,"B",L30>95%,"C") -> #DIV/0!
D31: =C31/C$42 -> #DIV/0! | E31: =D31+E30 -> #DIV/0! | F31: =IF(AND(E31<=0),"C",IF(E31<=0.8,"A",IF(E31<=0.95,"B","C"))) -> #DIV/0! | G31: =VLOOKUP(B$22:B$42,I$22:M$42,5,0) -> #N/A | K31: =J31/J$42 -> #DIV/0! | L31: =K31+L30 -> #DIV/0! | M31: =_xlfn.IFS(L31<80%,"A",L31<=95%,"B",L31>95%,"C") -> #DIV/0!
D32: =C32/C$42 -> #DIV/0! | E32: =D32+E31 -> #DIV/0! | F32: =IF(AND(E32<=0),"C",IF(E32<=0.8,"A",IF(E32<=0.95,"B","C"))) -> #DIV/0! | G32: =VLOOKUP(B$22:B$42,I$22:M$42,5,0) -> #N/A | K32: =J32/J$42 -> #DIV/0! | L32: =K32+L31 -> #DIV/0! | M32: =_xlfn.IFS(L32<80%,"A",L32<=95%,"B",L32>95%,"C") -> #DIV/0!
D33: =C33/C$42 -> #DIV/0! | E33: =D33+E32 -> #DIV/0! | F33: =IF(AND(E33<=0),"C",IF(E33<=0.8,"A",IF(E33<=0.95,"B","C"))) -> #DIV/0! | G33: =VLOOKUP(B$22:B$42,I$22:M$42,5,0) -> #N/A | K33: =J33/J$42 -> #DIV/0! | L33: =K33+L32 -> #DIV/0! | M33: =_xlfn.IFS(L33<80%,"A",L33<=95%,"B",L33>95%,"C") -> #DIV/0!
D34: =C34/C$42 -> #DIV/0! | E34: =D34+E33 -> #DIV/0! | F34: =IF(AND(E34<=0),"C",IF(E34<=0.8,"A",IF(E34<=0.95,"B","C"))) -> #DIV/0! | G34: =VLOOKUP(B$22:B$42,I$22:M$42,5,0) -> #N/A | K34: =J34/J$42 -> #DIV/0! | L34: =K34+L33 -> #DIV/0! | M34: =_xlfn.IFS(L34<80%,"A",L34<=95%,"B",L34>95%,"C") -> #DIV/0!
... D41: =C41/C$42 -> #DIV/0! | E41: =D41+E40 -> #DIV/0! | F41: =IF(AND(E41<=0),"C",IF(E41<=0.8,"A",IF(E41<=0.95,"B","C"))) -> #DIV/0! | G41: =VLOOKUP(B$22:B$42,I$22:M$42,5,0) -> #N/A | K41: =J41/J$42 -> #DIV/0! | L41: =K41+L40 -> #DIV/0! | M41: =_xlfn.IFS(L41<80%,"A",L41<=95%,"B",L41>95%,"C") -> #DIV/0!
C42: =SUM(C22:C41) -> 0 | D42: =SUM(D22:D41) -> #DIV/0! | J42: =SUM(J22:J41) -> 0 | K42: =SUM(K22:K41) -> #DIV/0!

Sheet АВС 26-31.01
B2: ОЧКИ
C3: Прибыль | D3: % прибыль | E3: Доля | F3: ABC прибыль | G3: ABC кол-во | J3: Кол-во | K3: % кол-во | L3: Доля | M3: ABC кол-во
B4: черные с железкой классика | D4: =C4/C$18 -> #DIV/0! | E4: =D4 -> #DIV/0! | F4: =IF(AND(E4<=0),"C",IF(E4<=0.8,"A",IF(E4<=0.95,"B","C"))) -> #DIV/0! | G4: =VLOOKUP(B$4:B$17,I$4:M$17,5,0) -> #DIV/0! | I4: черные с железкой классика | K4: =J4/J$18 -> #DIV/0! | L4: =K4 -> #DIV/0! | M4: =_xlfn.IFS(L4<80%,"A",L4<=95%,"B",L4>95%,"C") -> #DIV/0!
B5: qs черные | D5: =C5/C$18 -> #DIV/0! | E5: =D5+E4 -> #DIV/0! | F5: =IF(AND(E5<=0),"C",IF(E5<=0.8,"A",IF(E5<=0.95,"B","C"))) -> #DIV/0! | G5: =VLOOKUP(B$4:B$17,I$4:M$17,5,0) -> #DIV/0! | I5: qs черные | K5: =J5/J$18 -> #DIV/0! | L5: =K5+L4 -> #DIV/0! | M5: =_xlfn.IFS(L5<80%,"A",L5<=95%,"B",L5>95%,"C") -> #DIV/0!
B6: qs синие | D6: =C6/C$18 -> #DIV/0! | E6: =D6+E5 -> #DIV/0! | F6: =IF(AND(E6<=0),"C",IF(E6<=0.8,"A",IF(E6<=0.95,"B","C"))) -> #DIV/0! | G6: =VLOOKUP(B$4:B$17,I$4:M$17,5,0) -> #DIV/0! | I6: qs синие | K6: =J6/J$18 -> #DIV/0! | L6: =K6+L5 -> #DIV/0! | M6: =_xlfn.IFS(L6<80%,"A",L6<=95%,"B",L6>95%,"C") -> #DIV/0!
B7: qs желтые | D7: =C7/C$18 -> #DIV/0! | E7: =D7+E6 -> #DIV/0! | F7: =IF(AND(E7<=0),"C",IF(E7<=0.8,"A",IF(E7<=0.95,"B","C"))) -> #DIV/0! | G7: =VLOOKUP(B$4:B$17,I$4:M$17,5,0) -> #DIV/0! | I7: qs желтые | K7: =J7/J$18 -> #DIV/0! | L7: =K7+L6 -> #DIV/0! | M7: =_xlfn.IFS(L7<80%,"A",L7<=95%,"B",L7>95%,"C") -> #DIV/0!
B8: qs коричневые | D8: =C8/C$18 -> #DIV/0! | E8: =D8+E7 -> #DIV/0! | F8: =IF(AND(E8<=0),"C",IF(E8<=0.8,"A",IF(E8<=0.95,"B","C"))) -> #DIV/0! | G8: =VLOOKUP(B$4:B$17,I$4:M$17,5,0) -> #DIV/0! | I8: qs коричневые | K8: =J8/J$18 -> #DIV/0! | L8: =K8+L7 -> #DIV/0! | M8: =_xlfn.IFS(L8<80%,"A",L8<=95%,"B",L8>95%,"C") -> #DIV/0!
B9: MR8854 C2 | D9: =C9/C$18 -> #DIV/0! | E9: =D9+E8 -> #DIV/0! | F9: =IF(AND(E9<=0),"C",IF(E9<=0.8,"A",IF(E9<=0.95,"B","C"))) -> #DIV/0! | G9: =VLOOKUP(B$4:B$17,I$4:M$17,5,0) -> #DIV/0! | I9: MR8854 C2 | K9: =J9/J$18 -> #DIV/0! | L9: =K9+L8 -> #DIV/0! | M9: =_xlfn.IFS(L9<80%,"A",L9<=95%,"B",L9>95%,"C") -> #DIV/0!
B10: th черн | D10: =C10/C$18 -> #DIV/0! | E10: =D10+E9 -> #DIV/0! | F10: =IF(AND(E10<=0),"C",IF(E10<=0.8,"A",IF(E10<=0.95,"B","C"))) -> #DIV/0! | G10: =VLOOKUP(B$4:B$17,I$4:M$17,5,0) -> #DIV/0! | I10: th черн | K10: =J10/J$18 -> #DIV/0! | L10: =K10+L9 -> #DIV/0! | M10: =_xlfn.IFS(L10<80%,"A",L10<=95%,"B",L10>95%,"C") -> #DIV/0!
B11: th син | D11: =C11/C$18 -> #DIV/0! | E11: =D11+E10 -> #DIV/0! | F11: =IF(AND(E11<=0),"C",IF(E11<=0.8,"A",IF(E11<=0.95,"B","C"))) -> #DIV/0! | G11: =VLOOKUP(B$4:B$17,I$4:M$17,5,0) -> #DIV/0! | I11: th син | K11: =J11/J$18 -> #DIV/0! | L11: =K11+L10 -> #DIV/0! | M11: =_xlfn.IFS(L11<80%,"A",L11<=95%,"B",L11>95%,"C") -> #DIV/0!
B12: th желт | D12: =C12/C$18 -> #DIV/0! | E12: =D12+E5 -> #DIV/0! | F12: =IF(AND(E12<=0),"C",IF(E12<=0.8,"A",IF(E12<=0.95,"B","C"))) -> #DIV/0! | G12: =VLOOKUP(B$4:B$17,I$4:M$17,5,0) -> #DIV/0! | I12: th желт | K12: =J12/J$18 -> #DIV/0! | L12: =K12+L5 -> #DIV/0! | M12: =_xlfn.IFS(L12<80%,"A",L12<=95%,"B",L12>95%,"C") -> #DIV/0!
B13: th коричн | D13: =C13/C$18 -> #DIV/0! | E13: =D13+E12 -> #DIV/0! | F13: =IF(AND(E13<=0),"C",IF(E13<=0.8,"A",IF(E13<=0.95,"B","C"))) -> #DIV/0! | G13: =VLOOKUP(B$4:B$17,I$4:M$17,5,0) -> #DIV/0! | I13: th коричн | K13: =J13/J$18 -> #DIV/0! | L13: =K13+L12 -> #DIV/0! | M13: =_xlfn.IFS(L13<80%,"A",L13<=95%,"B",L13>95%,"C") -> #DIV/0!
B14: flip черный | D14: =C14/C$18 -> #DIV/0! | E14: =D14+E13 -> #DIV/0! | F14: =IF(AND(E14<=0),"C",IF(E14<=0.8,"A",IF(E14<=0.95,"B","C"))) -> #DIV/0! | G14: =VLOOKUP(B$4:B$17,I$4:M$17,5,0) -> #DIV/0! | I14: flip черный | K14: =J14/J$18 -> #DIV/0! | L14: =K14+L13 -> #DIV/0! | M14: =_xlfn.IFS(L14<80%,"A",L14<=95%,"B",L14>95%,"C") -> #DIV/0!
B15: flip синий | D15: =C15/C$18 -> #DIV/0! | E15: =D15+E14 -> #DIV/0! | F15: =IF(AND(E15<=0),"C",IF(E15<=0.8,"A",IF(E15<=0.95,"B","C"))) -> #DIV/0! | G15: =VLOOKUP(B$4:B$17,I$4:M$17,5,0) -> #DIV/0! | I15: flip синий | K15: =J15/J$18 -> #DIV/0! | L15: =K15+L14 -> #DIV/0! | M15: =_xlfn.IFS(L15<80%,"A",L15<=95%,"B",L15>95%,"C") -> #DIV/0!
B16: flip жел | D16: =C16/C$18 -> #DIV/0! | E16: =D16+E15 -> #DIV/0! | F16: =IF(AND(E16<=0),"C",IF(E16<=0.8,"A",IF(E16<=0.95,"B","C"))) -> #DIV/0! | G16: =VLOOKUP(B$4:B$17,I$4:M$17,5,0) -> #DIV/0! | I16: flip жел | K16: =J16/J$18 -> #DIV/0! | L16: =K16+L15 -> #DIV/0! | M16: =_xlfn.IFS(L16<80%,"A",L16<=95%,"B",L16>95%,"C") -> #DIV/0!
B17: flip коричневый | D17: =C17/C$18 -> #DIV/0! | E17: =D17+E14 -> #DIV/0! | F17: =IF(AND(E17<=0),"C",IF(E17<=0.8,"A",IF(E17<=0.95,"B","C"))) -> #DIV/0! | G17: =VLOOKUP(B$4:B$17,I$4:M$17,5,0) -> #DIV/0! | I17: flip коричневый | K17: =J17/J$18 -> #DIV/0! | L17: =K17+L14 -> #DIV/0! | M17: =_xlfn.IFS(L17<80%,"A",L17<=95%,"B",L17>95%,"C") -> #DIV/0!
C18: =SUM(C4:C17) -> 0 | D18: =SUM(D4:D17) -> #DIV/0! | J18: =SUM(J4:J17) -> 0 | K18: =SUM(K4:K17) -> #DIV/0!
C21: Прибыль | D21: % прибыль | E21: Доля | F21: ABC прибыль | G21: ABC кол-во | J21: Кол-во | K21: % кол-во | L21: Доля | M21: ABC кол-во
D22: =C22/C$42 -> #DIV/0! | E22: =D22 -> #DIV/0! | F22: =IF(AND(E22<=0),"C",IF(E22<=0.8,"A",IF(E22<=0.95,"B","C"))) -> #DIV/0! | G22: =VLOOKUP(B$22:B$42,I$22:M$42,5,0) -> #N/A | K22: =J22/J$42 -> #DIV/0! | L22: =K22 -> #DIV/0! | M22: =_xlfn.IFS(L22<80%,"A",L22<=95%,"B",L22>95%,"C") -> #DIV/0!
D23: =C23/C$42 -> #DIV/0! | E23: =D23+E22 -> #DIV/0! | F23: =IF(AND(E23<=0),"C",IF(E23<=0.8,"A",IF(E23<=0.95,"B","C"))) -> #DIV/0! | G23: =VLOOKUP(B$22:B$42,I$22:M$42,5,0) -> #N/A | K23: =J23/J$42 -> #DIV/0! | L23: =K23+L22 -> #DIV/0! | M23: =_xlfn.IFS(L23<80%,"A",L23<=95%,"B",L23>95%,"C") -> #DIV/0!
D24: =C24/C$42 -> #DIV/0! | E24: =D24+E23 -> #DIV/0! | F24: =IF(AND(E24<=0),"C",IF(E24<=0.8,"A",IF(E24<=0.95,"B","C"))) -> #DIV/0! | G24: =VLOOKUP(B$22:B$42,I$22:M$42,5,0) -> #N/A | K24: =J24/J$42 -> #DIV/0! | L24: =K24+L23 -> #DIV/0! | M24: =_xlfn.IFS(L24<80%,"A",L24<=95%,"B",L24>95%,"C") -> #DIV/0!
D25: =C25/C$42 -> #DIV/0! | E25: =D25+E24 -> #DIV/0! | F25: =IF(AND(E25<=0),"C",IF(E25<=0.8,"A",IF(E25<=0.95,"B","C"))) -> #DIV/0! | G25: =VLOOKUP(B$22:B$42,I$22:M$42,5,0) -> #N/A | K25: =J25/J$42 -> #DIV/0! | L25: =K25+L24 -> #DIV/0! | M25: =_xlfn.IFS(L25<80%,"A",L25<=95%,"B",L25>95%,"C") -> #DIV/0!
D26: =C26/C$42 -> #DIV/0! | E26: =D26+E25 -> #DIV/0! | F26: =IF(AND(E26<=0),"C",IF(E26<=0.8,"A",IF(E26<=0.95,"B","C"))) -> #DIV/0! | G26: =VLOOKUP(B$22:B$42,I$22:M$42,5,0) -> #N/A | K26: =J26/J$42 -> #DIV/0! | L26: =K26+L25 -> #DIV/0! | M26: =_xlfn.IFS(L26<80%,"A",L26<=95%,"B",L26>95%,"C") -> #DIV/0!
D27: =C27/C$42 -> #DIV/0! | E27: =D27+E26 -> #DIV/0! | F27: =IF(AND(E27<=0),"C",IF(E27<=0.8,"A",IF(E27<=0.95,"B","C"))) -> #DIV/0! | G27: =VLOOKUP(B$22:B$42,I$22:M$42,5,0) -> #N/A | K27: =J27/J$42 -> #DIV/0! | L27: =K27+L26 -> #DIV/0! | M27: =_xlfn.IFS(L27<80%,"A",L27<=95%,"B",L27>95%,"C") -> #DIV/0!
D28: =C28/C$42 -> #DIV/0! | E28: =D28+E27 -> #DIV/0! | F28: =IF(AND(E28<=0),"C",IF(E28<=0.8,"A",IF(E28<=0.95,"B","C"))) -> #DIV/0! | G28: =VLOOKUP(B$22:B$42,I$22:M$42,5,0) -> #N/A | K28: =J28/J$42 -> #DIV/0! | L28: =K28+L27 -> #DIV/0! | M28: =_xlfn.IFS(L28<80%,"A",L28<=95%,"B",L28>95%,"C") -> #DIV/0!
D29: =C29/C$42 -> #DIV/0! | E29: =D29+E28 -> #DIV/0! | F29: =IF(AND(E29<=0),"C",IF(E29<=0.8,"A",IF(E29<=0.95,"B","C"))) -> #DIV/0! | G29: =VLOOKUP(B$22:B$42,I$22:M$42,5,0) -> #N/A | K29: =J29/J$42 -> #DIV/0! | L29: =K29+L28 -> #DIV/0! | M29: =_xlfn.IFS(L29<80%,"A",L29<=95%,"B",L29>95%,"C") -> #DIV/0!
D30: =C30/C$42 -> #DIV/0! | E30: =D30+E29 -> #DIV/0! | F30: =IF(AND(E30<=0),"C",IF(E30<=0.8,"A",IF(E30<=0.95,"B","C"))) -> #DIV/0! | G30: =VLOOKUP(B$22:B$42,I$22:M$42,5,0) -> #N/A | K30: =J30/J$42 -> #DIV/0! | L30: =K30+L29 -> #DIV/0! | M30: =_xlfn.IFS(L30<80%,"A",L30<=95%,"B",L30>95%,"C") -> #DIV/0!
D31: =C31/C$42 -> #DIV/0! | E31: =D31+E30 -> #DIV/0! | F31: =IF(AND(E31<=0),"C",IF(E31<=0.8,"A",IF(E31<=0.95,"B","C"))) -> #DIV/0! | G31: =VLOOKUP(B$22:B$42,I$22:M$42,5,0) -> #N/A | K31: =J31/J$42 -> #DIV/0! | L31: =K31+L30 -> #DIV/0! | M31: =_xlfn.IFS(L31<80%,"A",L31<=95%,"B",L31>95%,"C") -> #DIV/0!
D32: =C32/C$42 -> #DIV/0! | E32: =D32+E31 -> #DIV/0! | F32: =IF(AND(E32<=0),"C",IF(E32<=0.8,"A",IF(E32<=0.95,"B","C"))) -> #DIV/0! | G32: =VLOOKUP(B$22:B$42,I$22:M$42,5,0) -> #N/A | K32: =J32/J$42 -> #DIV/0! | L32: =K32+L31 -> #DIV/0! | M32: =_xlfn.IFS(L32<80%,"A",L32<=95%,"B",L32>95%,"C") -> #DIV/0!
D33: =C33/C$42 -> #DIV/0! | E33: =D33+E32 -> #DIV/0! | F33: =IF(AND(E33<=0),"C",IF(E33<=0.8,"A",IF(E33<=0.95,"B","C"))) -> #DIV/0! | G33: =VLOOKUP(B$22:B$42,I$22:M$42,5,0) -> #N/A | K33: =J33/J$42 -> #DIV/0! | L33: =K33+L32 -> #DIV/0! | M33: =_xlfn.IFS(L33<80%,"A",L33<=95%,"B",L33>95%,"C") -> #DIV/0!
D34: =C34/C$42 -> #DIV/0! | E34: =D34+E33 -> #DIV/0! | F34: =IF(AND(E34<=0),"C",IF(E34<=0.8,"A",IF(E34<=0.95,"B","C"))) -> #DIV/0! | G34: =VLOOKUP(B$22:B$42,I$22:M$42,5,0) -> #N/A | K34: =J34/J$42 -> #DIV/0! | L34: =K34+L33 -> #DIV/0! | M34: =_xlfn.IFS(L34<80%,"A",L34<=95%,"B",L34>95%,"C") -> #DIV/0!
... D41: =C41/C$42 -> #DIV/0! | E41: =D41+E40 -> #DIV/0! | F41: =IF(AND(E41<=0),"C",IF(E41<=0.8,"A",IF(E41<=0.95,"B","C"))) -> #DIV/0! | G41: =VLOOKUP(B$22:B$42,I$22:M$42,5,0) -> #N/A | K41: =J41/J$42 -> #DIV/0! | L41: =K41+L40 -> #DIV/0! | M41: =_xlfn.IFS(L41<80%,"A",L41<=95%,"B",L41>95%,"C") -> #DIV/0!
C42: =SUM(C22:C41) -> 0 | D42: =SUM(D22:D41) -> #DIV/0! | J42: =SUM(J22:J41) -> 0 | K42: =SUM(K22:K41) -> #DIV/0!

Sheet АВС 19-25.01
B2: ОЧКИ
C3: Прибыль | D3: % прибыль | E3: Доля | F3: ABC прибыль | G3: ABC кол-во | J3: Кол-во | K3: % кол-во | L3: Доля | M3: ABC кол-во
B4: qs желтые | C4: ='Юнит 19-25.01'!AE6 -> 8682.335 | D4: =C4/C$18 -> 0.73552395 | E4: =D4 -> 0.73552395 | F4: =IF(AND(E4<=0),"C",IF(E4<=0.8,"A",IF(E4<=0.95,"B","C"))) -> A | G4: =VLOOKUP(B$4:B$17,I$4:M$17,5,0) -> A | I4: th желт | J4: ='Юнит 19-25.01'!R11 -> 26 | K4: =J4/J$18 -> 0.29213483 | L4: =K4 -> 0.29213483 | M4: =_xlfn.IFS(L4<80%,"A",L4<=95%,"B",L4>95%,"C") -> A
B5: qs черные | C5: ='Юнит 19-25.01'!AE4 -> 4302.4767 | D5: =C5/C$18 -> 0.36448429 | E5: =D5+E4 -> 1.1000082 | F5: =IF(AND(E5<=0),"C",IF(E5<=0.8,"A",IF(E5<=0.95,"B","C"))) -> C | G5: =VLOOKUP(B$4:B$17,I$4:M$17,5,0) -> B | I5: qs желтые | J5: ='Юнит 19-25.01'!R6 -> 18 | K5: =J5/J$18 -> 0.20224719 | L5: =K5+L4 -> 0.49438202 | M5: =_xlfn.IFS(L5<80%,"A",L5<=95%,"B",L5>95%,"C") -> A
B6: черные с железкой классика | C6: ='Юнит 19-25.01'!AE3 -> 2675.9434 | D6: =C6/C$18 -> 0.22669253 | E6: =D6+E5 -> 1.3267008 | F6: =IF(AND(E6<=0),"C",IF(E6<=0.8,"A",IF(E6<=0.95,"B","C"))) -> C | G6: =VLOOKUP(B$4:B$17,I$4:M$17,5,0) -> B | I6: flip жел | J6: ='Юнит 19-25.01'!R15 -> 17 | K6: =J6/J$18 -> 0.19101124 | L6: =K6+L5 -> 0.68539326 | M6: =_xlfn.IFS(L6<80%,"A",L6<=95%,"B",L6>95%,"C") -> A
B7: qs синие | C7: ='Юнит 19-25.01'!AE5 -> 1839.845 | D7: =C7/C$18 -> 0.15586246 | E7: =D7+E6 -> 1.4825632 | F7: =IF(AND(E7<=0),"C",IF(E7<=0.8,"A",IF(E7<=0.95,"B","C"))) -> C | G7: =VLOOKUP(B$4:B$17,I$4:M$17,5,0) -> C | I7: qs коричневые | J7: ='Юнит 19-25.01'!R7 -> 10 | K7: =J7/J$18 -> 0.11235955 | L7: =K7+L6 -> 0.79775281 | M7: =_xlfn.IFS(L7<80%,"A",L7<=95%,"B",L7>95%,"C") -> A
B8: qs коричневые | C8: ='Юнит 19-25.01'!AE7 -> 811.7582 | D8: =C8/C$18 -> 0.06876809 | E8: =D8+E7 -> 1.5513313 | F8: =IF(AND(E8<=0),"C",IF(E8<=0.8,"A",IF(E8<=0.95,"B","C"))) -> C | G8: =VLOOKUP(B$4:B$17,I$4:M$17,5,0) -> A | I8: qs черные | J8: ='Юнит 19-25.01'!R4 -> 7 | K8: =J8/J$18 -> 0.078651685 | L8: =K8+L7 -> 0.87640449 | M8: =_xlfn.IFS(L8<80%,"A",L8<=95%,"B",L8>95%,"C") -> B
B9: th желт | C9: ='Юнит 19-25.01'!AE11 -> 470.19917 | D9: =C9/C$18 -> 0.03983292 | E9: =D9+E8 -> 1.5911642 | F9: =IF(AND(E9<=0),"C",IF(E9<=0.8,"A",IF(E9<=0.95,"B","C"))) -> C | G9: =VLOOKUP(B$4:B$17,I$4:M$17,5,0) -> A | I9: черные с железкой классика | J9: ='Юнит 19-25.01'!R3 -> 5 | K9: =J9/J$18 -> 0.056179775 | L9: =K9+L8 -> 0.93258427 | M9: =_xlfn.IFS(L9<80%,"A",L9<=95%,"B",L9>95%,"C") -> B
B10: th черн | C10: ='Юнит 19-25.01'!AE9 -> 0 | D10: =C10/C$18 -> 0 | E10: =D10+E9 -> 1.5911642 | F10: =IF(AND(E10<=0),"C",IF(E10<=0.8,"A",IF(E10<=0.95,"B","C"))) -> C | G10: =VLOOKUP(B$4:B$17,I$4:M$17,5,0) -> A | I10: qs синие | J10: ='Юнит 19-25.01'!R5 -> 3 | K10: =J10/J$18 -> 0.033707865 | L10: =K10+L9 -> 0.96629213 | M10: =_xlfn.IFS(L10<80%,"A",L10<=95%,"B",L10>95%,"C") -> C
B11: th син | C11: ='Юнит 19-25.01'!AE10 -> 0 | D11: =C11/C$18 -> 0 | E11: =D11+E10 -> 1.5911642 | F11: =IF(AND(E11<=0),"C",IF(E11<=0.8,"A",IF(E11<=0.95,"B","C"))) -> C | G11: =VLOOKUP(B$4:B$17,I$4:M$17,5,0) -> A | I11: MR8854 C2 | J11: ='Юнит 19-25.01'!R8 -> 3 | K11: =J11/J$18 -> 0.033707865 | L11: =K11+L10 -> 1 | M11: =_xlfn.IFS(L11<80%,"A",L11<=95%,"B",L11>95%,"C") -> C
B12: th коричн | C12: ='Юнит 19-25.01'!AE12 -> 0 | D12: =C12/C$18 -> 0 | E12: =D12+E5 -> 1.1000082 | F12: =IF(AND(E12<=0),"C",IF(E12<=0.8,"A",IF(E12<=0.95,"B","C"))) -> C | G12: =VLOOKUP(B$4:B$17,I$4:M$17,5,0) -> A | I12: th черн | J12: ='Юнит 19-25.01'!R9 -> 0 | K12: =J12/J$18 -> 0 | L12: =K12+L5 -> 0.49438202 | M12: =_xlfn.IFS(L12<80%,"A",L12<=95%,"B",L12>95%,"C") -> A
B13: flip черный | C13: ='Юнит 19-25.01'!AE13 -> 0 | D13: =C13/C$18 -> 0 | E13: =D13+E12 -> 1.1000082 | F13: =IF(AND(E13<=0),"C",IF(E13<=0.8,"A",IF(E13<=0.95,"B","C"))) -> C | G13: =VLOOKUP(B$4:B$17,I$4:M$17,5,0) -> A | I13: th син | J13: ='Юнит 19-25.01'!R10 -> 0 | K13: =J13/J$18 -> 0 | L13: =K13+L12 -> 0.49438202 | M13: =_xlfn.IFS(L13<80%,"A",L13<=95%,"B",L13>95%,"C") -> A
B14: flip синий | C14: ='Юнит 19-25.01'!AE14 -> 0 | D14: =C14/C$18 -> 0 | E14: =D14+E13 -> 1.1000082 | F14: =IF(AND(E14<=0),"C",IF(E14<=0.8,"A",IF(E14<=0.95,"B","C"))) -> C | G14: =VLOOKUP(B$4:B$17,I$4:M$17,5,0) -> A | I14: th коричн | J14: ='Юнит 19-25.01'!R12 -> 0 | K14: =J14/J$18 -> 0 | L14: =K14+L13 -> 0.49438202 | M14: =_xlfn.IFS(L14<80%,"A",L14<=95%,"B",L14>95%,"C") -> A
B15: flip коричневый | C15: ='Юнит 19-25.01'!AE16 -> 0 | D15: =C15/C$18 -> 0 | E15: =D15+E14 -> 1.1000082 | F15: =IF(AND(E15<=0),"C",IF(E15<=0.8,"A",IF(E15<=0.95,"B","C"))) -> C | G15: =VLOOKUP(B$4:B$17,I$4:M$17,5,0) -> A | I15: flip черный | J15: ='Юнит 19-25.01'!R13 -> 0 | K15: =J15/J$18 -> 0 | L15: =K15+L14 -> 0.49438202 | M15: =_xlfn.IFS(L15<80%,"A",L15<=95%,"B",L15>95%,"C") -> A
B16: MR8854 C2 | C16: ='Юнит 19-25.01'!AE8 -> -1062.6708 | D16: =C16/C$18 -> -0.090024148 | E16: =D16+E15 -> 1.0099841 | F16: =IF(AND(E16<=0),"C",IF(E16<=0.8,"A",IF(E16<=0.95,"B","C"))) -> C | G16: =VLOOKUP(B$4:B$17,I$4:M$17,5,0) -> C | I16: flip синий | J16: ='Юнит 19-25.01'!R14 -> 0 | K16: =J16/J$18 -> 0 | L16: =K16+L15 -> 0.49438202 | M16: =_xlfn.IFS(L16<80%,"A",L16<=95%,"B",L16>95%,"C") -> A
B17: flip жел | C17: ='Юнит 19-25.01'!AE15 -> -5915.6009 | D17: =C17/C$18 -> -0.50114009 | E17: =D17+E14 -> 0.59886815 | F17: =IF(AND(E17<=0),"C",IF(E17<=0.8,"A",IF(E17<=0.95,"B","C"))) -> A | G17: =VLOOKUP(B$4:B$17,I$4:M$17,5,0) -> A | I17: flip коричневый | J17: ='Юнит 19-25.01'!R16 -> 0 | K17: =J17/J$18 -> 0 | L17: =K17+L14 -> 0.49438202 | M17: =_xlfn.IFS(L17<80%,"A",L17<=95%,"B",L17>95%,"C") -> A
C18: =SUM(C4:C17) -> 11804.286 | D18: =SUM(D4:D17) -> 1 | J18: =SUM(J4:J17) -> 89 | K18: =SUM(K4:K17) -> 1
C21: Прибыль | D21: % прибыль | E21: Доля | F21: ABC прибыль | G21: ABC кол-во | J21: Кол-во | K21: % кол-во | L21: Доля | M21: ABC кол-во
D22: =C22/C$42 -> #DIV/0! | E22: =D22 -> #DIV/0! | F22: =IF(AND(E22<=0),"C",IF(E22<=0.8,"A",IF(E22<=0.95,"B","C"))) -> #DIV/0! | G22: =VLOOKUP(B$22:B$42,I$22:M$42,5,0) -> #N/A | K22: =J22/J$42 -> #DIV/0! | L22: =K22 -> #DIV/0! | M22: =_xlfn.IFS(L22<80%,"A",L22<=95%,"B",L22>95%,"C") -> #DIV/0!
D23: =C23/C$42 -> #DIV/0! | E23: =D23+E22 -> #DIV/0! | F23: =IF(AND(E23<=0),"C",IF(E23<=0.8,"A",IF(E23<=0.95,"B","C"))) -> #DIV/0! | G23: =VLOOKUP(B$22:B$42,I$22:M$42,5,0) -> #N/A | K23: =J23/J$42 -> #DIV/0! | L23: =K23+L22 -> #DIV/0! | M23: =_xlfn.IFS(L23<80%,"A",L23<=95%,"B",L23>95%,"C") -> #DIV/0!
D24: =C24/C$42 -> #DIV/0! | E24: =D24+E23 -> #DIV/0! | F24: =IF(AND(E24<=0),"C",IF(E24<=0.8,"A",IF(E24<=0.95,"B","C"))) -> #DIV/0! | G24: =VLOOKUP(B$22:B$42,I$22:M$42,5,0) -> #N/A | K24: =J24/J$42 -> #DIV/0! | L24: =K24+L23 -> #DIV/0! | M24: =_xlfn.IFS(L24<80%,"A",L24<=95%,"B",L24>95%,"C") -> #DIV/0!
D25: =C25/C$42 -> #DIV/0! | E25: =D25+E24 -> #DIV/0! | F25: =IF(AND(E25<=0),"C",IF(E25<=0.8,"A",IF(E25<=0.95,"B","C"))) -> #DIV/0! | G25: =VLOOKUP(B$22:B$42,I$22:M$42,5,0) -> #N/A | K25: =J25/J$42 -> #DIV/0! | L25: =K25+L24 -> #DIV/0! | M25: =_xlfn.IFS(L25<80%,"A",L25<=95%,"B",L25>95%,"C") -> #DIV/0!
D26: =C26/C$42 -> #DIV/0! | E26: =D26+E25 -> #DIV/0! | F26: =IF(AND(E26<=0),"C",IF(E26<=0.8,"A",IF(E26<=0.95,"B","C"))) -> #DIV/0! | G26: =VLOOKUP(B$22:B$42,I$22:M$42,5,0) -> #N/A | K26: =J26/J$42 -> #DIV/0! | L26: =K26+L25 -> #DIV/0! | M26: =_xlfn.IFS(L26<80%,"A",L26<=95%,"B",L26>95%,"C") -> #DIV/0!
D27: =C27/C$42 -> #DIV/0! | E27: =D27+E26 -> #DIV/0! | F27: =IF(AND(E27<=0),"C",IF(E27<=0.8,"A",IF(E27<=0.95,"B","C"))) -> #DIV/0! | G27: =VLOOKUP(B$22:B$42,I$22:M$42,5,0) -> #N/A | K27: =J27/J$42 -> #DIV/0! | L27: =K27+L26 -> #DIV/0! | M27: =_xlfn.IFS(L27<80%,"A",L27<=95%,"B",L27>95%,"C") -> #DIV/0!
D28: =C28/C$42 -> #DIV/0! | E28: =D28+E27 -> #DIV/0! | F28: =IF(AND(E28<=0),"C",IF(E28<=0.8,"A",IF(E28<=0.95,"B","C"))) -> #DIV/0! | G28: =VLOOKUP(B$22:B$42,I$22:M$42,5,0) -> #N/A | K28: =J28/J$42 -> #DIV/0! | L28: =K28+L27 -> #DIV/0! | M28: =_xlfn.IFS(L28<80%,"A",L28<=95%,"B",L28>95%,"C") -> #DIV/0!
D29: =C29/C$42 -> #DIV/0! | E29: =D29+E28 -> #DIV/0! | F29: =IF(AND(E29<=0),"C",IF(E29<=0.8,"A",IF(E29<=0.95,"B","C"))) -> #DIV/0! | G29: =VLOOKUP(B$22:B$42,I$22:M$42,5,0) -> #N/A | K29: =J29/J$42 -> #DIV/0! | L29: =K29+L28 -> #DIV/0! | M29: =_xlfn.IFS(L29<80%,"A",L29<=95%,"B",L29>95%,"C") -> #DIV/0!
D30: =C30/C$42 -> #DIV/0! | E30: =D30+E29 -> #DIV/0! | F30: =IF(AND(E30<=0),"C",IF(E30<=0.8,"A",IF(E30<=0.95,"B","C"))) -> #DIV/0! | G30: =VLOOKUP(B$22:B$42,I$22:M$42,5,0) -> #N/A | K30: =J30/J$42 -> #DIV/0! | L30: =K30+L29 -> #DIV/0! | M30: =_xlfn.IFS(L30<80%,"A",L30<=95%,"B",L30>95%,"C") -> #DIV/0!
D31: =C31/C$42 -> #DIV/0! | E31: =D31+E30 -> #DIV/0! | F31: =IF(AND(E31<=0),"C",IF(E31<=0.8,"A",IF(E31<=0.95,"B","C"))) -> #DIV/0! | G31: =VLOOKUP(B$22:B$42,I$22:M$42,5,0) -> #N/A | K31: =J31/J$42 -> #DIV/0! | L31: =K31+L30 -> #DIV/0! | M31: =_xlfn.IFS(L31<80%,"A",L31<=95%,"B",L31>95%,"C") -> #DIV/0!
D32: =C32/C$42 -> #DIV/0! | E32: =D32+E31 -> #DIV/0! | F32: =IF(AND(E32<=0),"C",IF(E32<=0.8,"A",IF(E32<=0.95,"B","C"))) -> #DIV/0! | G32: =VLOOKUP(B$22:B$42,I$22:M$42,5,0) -> #N/A | K32: =J32/J$42 -> #DIV/0! | L32: =K32+L31 -> #DIV/0! | M32: =_xlfn.IFS(L32<80%,"A",L32<=95%,"B",L32>95%,"C") -> #DIV/0!
D33: =C33/C$42 -> #DIV/0! | E33: =D33+E32 -> #DIV/0! | F33: =IF(AND(E33<=0),"C",IF(E33<=0.8,"A",IF(E33<=0.95,"B","C"))) -> #DIV/0! | G33: =VLOOKUP(B$22:B$42,I$22:M$42,5,0) -> #N/A | K33: =J33/J$42 -> #DIV/0! | L33: =K33+L32 -> #DIV/0! | M33: =_xlfn.IFS(L33<80%,"A",L33<=95%,"B",L33>95%,"C") -> #DIV/0!
D34: =C34/C$42 -> #DIV/0! | E34: =D34+E33 -> #DIV/0! | F34: =IF(AND(E34<=0),"C",IF(E34<=0.8,"A",IF(E34<=0.95,"B","C"))) -> #DIV/0! | G34: =VLOOKUP(B$22:B$42,I$22:M$42,5,0) -> #N/A | K34: =J34/J$42 -> #DIV/0! | L34: =K34+L33 -> #DIV/0! | M34: =_xlfn.IFS(L34<80%,"A",L34<=95%,"B",L34>95%,"C") -> #DIV/0!
... D41: =C41/C$42 -> #DIV/0! | E41: =D41+E40 -> #DIV/0! | F41: =IF(AND(E41<=0),"C",IF(E41<=0.8,"A",IF(E41<=0.95,"B","C"))) -> #DIV/0! | G41: =VLOOKUP(B$22:B$42,I$22:M$42,5,0) -> #N/A | K41: =J41/J$42 -> #DIV/0! | L41: =K41+L40 -> #DIV/0! | M41: =_xlfn.IFS(L41<80%,"A",L41<=95%,"B",L41>95%,"C") -> #DIV/0!
C42: =SUM(C22:C41) -> 0 | D42: =SUM(D22:D41) -> #DIV/0! | J42: =SUM(J22:J41) -> 0 | K42: =SUM(K22:K41) -> #DIV/0!

Sheet АВС 12-18.01
B2: ОЧКИ
C3: Прибыль | D3: % прибыль | E3: Доля | F3: ABC прибыль | G3: ABC кол-во | J3: Кол-во | K3: % кол-во | L3: Доля | M3: ABC кол-во
B4: flip жел | C4: ='Юнит 12-18.01'!AE15 -> 4630.245 | D4: =C4/C$18 -> 0.30622783 | E4: =D4 -> 0.30622783 | F4: =IF(AND(E4<=0),"C",IF(E4<=0.8,"A",IF(E4<=0.95,"B","C"))) -> A | G4: =VLOOKUP(B$4:B$17,I$4:M$17,5,0) -> A | I4: flip жел | J4: ='Юнит 12-18.01'!R15 -> 37 | K4: =J4/J$18 -> 0.30833333 | L4: =K4 -> 0.30833333 | M4: =_xlfn.IFS(L4<80%,"A",L4<=95%,"B",L4>95%,"C") -> A
B5: qs желтые | C5: ='Юнит 12-18.01'!AE6 -> 3366.0304 | D5: =C5/C$18 -> 0.2226172 | E5: =D5+E4 -> 0.52884503 | F5: =IF(AND(E5<=0),"C",IF(E5<=0.8,"A",IF(E5<=0.95,"B","C"))) -> A | G5: =VLOOKUP(B$4:B$17,I$4:M$17,5,0) -> A | I5: th желт | J5: ='Юнит 12-18.01'!R11 -> 35 | K5: =J5/J$18 -> 0.29166667 | L5: =K5+L4 -> 0.6 | M5: =_xlfn.IFS(L5<80%,"A",L5<=95%,"B",L5>95%,"C") -> A
B6: qs коричневые | C6: ='Юнит 12-18.01'!AE7 -> 3012.4098 | D6: =C6/C$18 -> 0.19923 | E6: =D6+E5 -> 0.72807504 | F6: =IF(AND(E6<=0),"C",IF(E6<=0.8,"A",IF(E6<=0.95,"B","C"))) -> A | G6: =VLOOKUP(B$4:B$17,I$4:M$17,5,0) -> B | I6: qs желтые | J6: ='Юнит 12-18.01'!R6 -> 20 | K6: =J6/J$18 -> 0.16666667 | L6: =K6+L5 -> 0.76666667 | M6: =_xlfn.IFS(L6<80%,"A",L6<=95%,"B",L6>95%,"C") -> A
B7: qs синие | C7: ='Юнит 12-18.01'!AE5 -> 1765.2074 | D7: =C7/C$18 -> 0.1167445 | E7: =D7+E6 -> 0.84481954 | F7: =IF(AND(E7<=0),"C",IF(E7<=0.8,"A",IF(E7<=0.95,"B","C"))) -> B | G7: =VLOOKUP(B$4:B$17,I$4:M$17,5,0) -> C | I7: qs коричневые | J7: ='Юнит 12-18.01'!R7 -> 10 | K7: =J7/J$18 -> 0.083333333 | L7: =K7+L6 -> 0.85 | M7: =_xlfn.IFS(L7<80%,"A",L7<=95%,"B",L7>95%,"C") -> B
B8: черные с железкой классика | C8: ='Юнит 12-18.01'!AE3 -> 924.26734 | D8: =C8/C$18 -> 0.061127734 | E8: =D8+E7 -> 0.90594727 | F8: =IF(AND(E8<=0),"C",IF(E8<=0.8,"A",IF(E8<=0.95,"B","C"))) -> B | G8: =VLOOKUP(B$4:B$17,I$4:M$17,5,0) -> C | I8: MR8854 C2 | J8: ='Юнит 12-18.01'!R8 -> 7 | K8: =J8/J$18 -> 0.058333333 | L8: =K8+L7 -> 0.90833333 | M8: =_xlfn.IFS(L8<80%,"A",L8<=95%,"B",L8>95%,"C") -> B
B9: th желт | C9: ='Юнит 12-18.01'!AE11 -> 889.82966 | D9: =C9/C$18 -> 0.058850149 | E9: =D9+E8 -> 0.96479742 | F9: =IF(AND(E9<=0),"C",IF(E9<=0.8,"A",IF(E9<=0.95,"B","C"))) -> C | G9: =VLOOKUP(B$4:B$17,I$4:M$17,5,0) -> A | I9: qs черные | J9: ='Юнит 12-18.01'!R4 -> 4 | K9: =J9/J$18 -> 0.033333333 | L9: =K9+L8 -> 0.94166667 | M9: =_xlfn.IFS(L9<80%,"A",L9<=95%,"B",L9>95%,"C") -> B
B10: qs черные | C10: ='Юнит 12-18.01'!AE4 -> 420.61927 | D10: =C10/C$18 -> 0.027818253 | E10: =D10+E9 -> 0.99261567 | F10: =IF(AND(E10<=0),"C",IF(E10<=0.8,"A",IF(E10<=0.95,"B","C"))) -> C | G10: =VLOOKUP(B$4:B$17,I$4:M$17,5,0) -> B | I10: qs синие | J10: ='Юнит 12-18.01'!R5 -> 4 | K10: =J10/J$18 -> 0.033333333 | L10: =K10+L9 -> 0.975 | M10: =_xlfn.IFS(L10<80%,"A",L10<=95%,"B",L10>95%,"C") -> C
B11: MR8854 C2 | C11: ='Юнит 12-18.01'!AE8 -> 111.65297 | D11: =C11/C$18 -> 0.0073843277 | E11: =D11+E10 -> 1 | F11: =IF(AND(E11<=0),"C",IF(E11<=0.8,"A",IF(E11<=0.95,"B","C"))) -> C | G11: =VLOOKUP(B$4:B$17,I$4:M$17,5,0) -> B | I11: черные с железкой классика | J11: ='Юнит 12-18.01'!R3 -> 3 | K11: =J11/J$18 -> 0.025 | L11: =K11+L10 -> 1 | M11: =_xlfn.IFS(L11<80%,"A",L11<=95%,"B",L11>95%,"C") -> C
B12: th черн | C12: ='Юнит 12-18.01'!AE9 -> 0 | D12: =C12/C$18 -> 0 | E12: =D12+E5 -> 0.52884503 | F12: =IF(AND(E12<=0),"C",IF(E12<=0.8,"A",IF(E12<=0.95,"B","C"))) -> A | G12: =VLOOKUP(B$4:B$17,I$4:M$17,5,0) -> A | I12: th черн | J12: ='Юнит 12-18.01'!R9 -> 0 | K12: =J12/J$18 -> 0 | L12: =K12+L5 -> 0.6 | M12: =_xlfn.IFS(L12<80%,"A",L12<=95%,"B",L12>95%,"C") -> A
B13: th син | C13: ='Юнит 12-18.01'!AE10 -> 0 | D13: =C13/C$18 -> 0 | E13: =D13+E12 -> 0.52884503 | F13: =IF(AND(E13<=0),"C",IF(E13<=0.8,"A",IF(E13<=0.95,"B","C"))) -> A | G13: =VLOOKUP(B$4:B$17,I$4:M$17,5,0) -> A | I13: th син | J13: ='Юнит 12-18.01'!R10 -> 0 | K13: =J13/J$18 -> 0 | L13: =K13+L12 -> 0.6 | M13: =_xlfn.IFS(L13<80%,"A",L13<=95%,"B",L13>95%,"C") -> A
B14: th коричн | C14: ='Юнит 12-18.01'!AE12 -> 0 | D14: =C14/C$18 -> 0 | E14: =D14+E13 -> 0.52884503 | F14: =IF(AND(E14<=0),"C",IF(E14<=0.8,"A",IF(E14<=0.95,"B","C"))) -> A | G14: =VLOOKUP(B$4:B$17,I$4:M$17,5,0) -> A | I14: th коричн | J14: ='Юнит 12-18.01'!R12 -> 0 | K14: =J14/J$18 -> 0 | L14: =K14+L13 -> 0.6 | M14: =_xlfn.IFS(L14<80%,"A",L14<=95%,"B",L14>95%,"C") -> A
B15: flip черный | C15: ='Юнит 12-18.01'!AE13 -> 0 | D15: =C15/C$18 -> 0 | E15: =D15+E14 -> 0.52884503 | F15: =IF(AND(E15<=0),"C",IF(E15<=0.8,"A",IF(E15<=0.95,"B","C"))) -> A | G15: =VLOOKUP(B$4:B$17,I$4:M$17,5,0) -> A | I15: flip черный | J15: ='Юнит 12-18.01'!R13 -> 0 | K15: =J15/J$18 -> 0 | L15: =K15+L14 -> 0.6 | M15: =_xlfn.IFS(L15<80%,"A",L15<=95%,"B",L15>95%,"C") -> A
B16: flip синий | C16: ='Юнит 12-18.01'!AE14 -> 0 | D16: =C16/C$18 -> 0 | E16: =D16+E15 -> 0.52884503 | F16: =IF(AND(E16<=0),"C",IF(E16<=0.8,"A",IF(E16<=0.95,"B","C"))) -> A | G16: =VLOOKUP(B$4:B$17,I$4:M$17,5,0) -> A | I16: flip синий | J16: ='Юнит 12-18.01'!R14 -> 0 | K16: =J16/J$18 -> 0 | L16: =K16+L15 -> 0.6 | M16: =_xlfn.IFS(L16<80%,"A",L16<=95%,"B",L16>95%,"C") -> A
B17: flip коричневый | C17: ='Юнит 12-18.01'!AE16 -> 0 | D17: =C17/C$18 -> 0 | E17: =D17+E14 -> 0.52884503 | F17: =IF(AND(E17<=0),"C",IF(E17<=0.8,"A",IF(E17<=0.95,"B","C"))) -> A | G17: =VLOOKUP(B$4:B$17,I$4:M$17,5,0) -> A | I17: flip коричневый | J17: ='Юнит 12-18.01'!R16 -> 0 | K17: =J17/J$18 -> 0 | L17: =K17+L14 -> 0.6 | M17: =_xlfn.IFS(L17<80%,"A",L17<=95%,"B",L17>95%,"C") -> A
C18: =SUM(C4:C17) -> 15120.262 | D18: =SUM(D4:D17) -> 1 | J18: =SUM(J4:J17) -> 120 | K18: =SUM(K4:K17) -> 1
C21: Прибыль | D21: % прибыль | E21: Доля | F21: ABC прибыль | G21: ABC кол-во | J21: Кол-во | K21: % кол-во | L21: Доля | M21: ABC кол-во
D22: =C22/C$42 -> #DIV/0! | E22: =D22 -> #DIV/0! | F22: =IF(AND(E22<=0),"C",IF(E22<=0.8,"A",IF(E22<=0.95,"B","C"))) -> #DIV/0! | G22: =VLOOKUP(B$22:B$42,I$22:M$42,5,0) -> #N/A | K22: =J22/J$42 -> #DIV/0! | L22: =K22 -> #DIV/0! | M22: =_xlfn.IFS(L22<80%,"A",L22<=95%,"B",L22>95%,"C") -> #DIV/0!
D23: =C23/C$42 -> #DIV/0! | E23: =D23+E22 -> #DIV/0! | F23: =IF(AND(E23<=0),"C",IF(E23<=0.8,"A",IF(E23<=0.95,"B","C"))) -> #DIV/0! | G23: =VLOOKUP(B$22:B$42,I$22:M$42,5,0) -> #N/A | K23: =J23/J$42 -> #DIV/0! | L23: =K23+L22 -> #DIV/0! | M23: =_xlfn.IFS(L23<80%,"A",L23<=95%,"B",L23>95%,"C") -> #DIV/0!
D24: =C24/C$42 -> #DIV/0! | E24: =D24+E23 -> #DIV/0! | F24: =IF(AND(E24<=0),"C",IF(E24<=0.8,"A",IF(E24<=0.95,"B","C"))) -> #DIV/0! | G24: =VLOOKUP(B$22:B$42,I$22:M$42,5,0) -> #N/A | K24: =J24/J$42 -> #DIV/0! | L24: =K24+L23 -> #DIV/0! | M24: =_xlfn.IFS(L24<80%,"A",L24<=95%,"B",L24>95%,"C") -> #DIV/0!
D25: =C25/C$42 -> #DIV/0! | E25: =D25+E24 -> #DIV/0! | F25: =IF(AND(E25<=0),"C",IF(E25<=0.8,"A",IF(E25<=0.95,"B","C"))) -> #DIV/0! | G25: =VLOOKUP(B$22:B$42,I$22:M$42,5,0) -> #N/A | K25: =J25/J$42 -> #DIV/0! | L25: =K25+L24 -> #DIV/0! | M25: =_xlfn.IFS(L25<80%,"A",L25<=95%,"B",L25>95%,"C") -> #DIV/0!
D26: =C26/C$42 -> #DIV/0! | E26: =D26+E25 -> #DIV/0! | F26: =IF(AND(E26<=0),"C",IF(E26<=0.8,"A",IF(E26<=0.95,"B","C"))) -> #DIV/0! | G26: =VLOOKUP(B$22:B$42,I$22:M$42,5,0) -> #N/A | K26: =J26/J$42 -> #DIV/0! | L26: =K26+L25 -> #DIV/0! | M26: =_xlfn.IFS(L26<80%,"A",L26<=95%,"B",L26>95%,"C") -> #DIV/0!
D27: =C27/C$42 -> #DIV/0! | E27: =D27+E26 -> #DIV/0! | F27: =IF(AND(E27<=0),"C",IF(E27<=0.8,"A",IF(E27<=0.95,"B","C"))) -> #DIV/0! | G27: =VLOOKUP(B$22:B$42,I$22:M$42,5,0) -> #N/A | K27: =J27/J$42 -> #DIV/0! | L27: =K27+L26 -> #DIV/0! | M27: =_xlfn.IFS(L27<80%,"A",L27<=95%,"B",L27>95%,"C") -> #DIV/0!
D28: =C28/C$42 -> #DIV/0! | E28: =D28+E27 -> #DIV/0! | F28: =IF(AND(E28<=0),"C",IF(E28<=0.8,"A",IF(E28<=0.95,"B","C"))) -> #DIV/0! | G28: =VLOOKUP(B$22:B$42,I$22:M$42,5,0) -> #N/A | K28: =J28/J$42 -> #DIV/0! | L28: =K28+L27 -> #DIV/0! | M28: =_xlfn.IFS(L28<80%,"A",L28<=95%,"B",L28>95%,"C") -> #DIV/0!
D29: =C29/C$42 -> #DIV/0! | E29: =D29+E28 -> #DIV/0! | F29: =IF(AND(E29<=0),"C",IF(E29<=0.8,"A",IF(E29<=0.95,"B","C"))) -> #DIV/0! | G29: =VLOOKUP(B$22:B$42,I$22:M$42,5,0) -> #N/A | K29: =J29/J$42 -> #DIV/0! | L29: =K29+L28 -> #DIV/0! | M29: =_xlfn.IFS(L29<80%,"A",L29<=95%,"B",L29>95%,"C") -> #DIV/0!
D30: =C30/C$42 -> #DIV/0! | E30: =D30+E29 -> #DIV/0! | F30: =IF(AND(E30<=0),"C",IF(E30<=0.8,"A",IF(E30<=0.95,"B","C"))) -> #DIV/0! | G30: =VLOOKUP(B$22:B$42,I$22:M$42,5,0) -> #N/A | K30: =J30/J$42 -> #DIV/0! | L30: =K30+L29 -> #DIV/0! | M30: =_xlfn.IFS(L30<80%,"A",L30<=95%,"B",L30>95%,"C") -> #DIV/0!
D31: =C31/C$42 -> #DIV/0! | E31: =D31+E30 -> #DIV/0! | F31: =IF(AND(E31<=0),"C",IF(E31<=0.8,"A",IF(E31<=0.95,"B","C"))) -> #DIV/0! | G31: =VLOOKUP(B$22:B$42,I$22:M$42,5,0) -> #N/A | K31: =J31/J$42 -> #DIV/0! | L31: =K31+L30 -> #DIV/0! | M31: =_xlfn.IFS(L31<80%,"A",L31<=95%,"B",L31>95%,"C") -> #DIV/0!
D32: =C32/C$42 -> #DIV/0! | E32: =D32+E31 -> #DIV/0! | F32: =IF(AND(E32<=0),"C",IF(E32<=0.8,"A",IF(E32<=0.95,"B","C"))) -> #DIV/0! | G32: =VLOOKUP(B$22:B$42,I$22:M$42,5,0) -> #N/A | K32: =J32/J$42 -> #DIV/0! | L32: =K32+L31 -> #DIV/0! | M32: =_xlfn.IFS(L32<80%,"A",L32<=95%,"B",L32>95%,"C") -> #DIV/0!
D33: =C33/C$42 -> #DIV/0! | E33: =D33+E32 -> #DIV/0! | F33: =IF(AND(E33<=0),"C",IF(E33<=0.8,"A",IF(E33<=0.95,"B","C"))) -> #DIV/0! | G33: =VLOOKUP(B$22:B$42,I$22:M$42,5,0) -> #N/A | K33: =J33/J$42 -> #DIV/0! | L33: =K33+L32 -> #DIV/0! | M33: =_xlfn.IFS(L33<80%,"A",L33<=95%,"B",L33>95%,"C") -> #DIV/0!
D34: =C34/C$42 -> #DIV/0! | E34: =D34+E33 -> #DIV/0! | F34: =IF(AND(E34<=0),"C",IF(E34<=0.8,"A",IF(E34<=0.95,"B","C"))) -> #DIV/0! | G34: =VLOOKUP(B$22:B$42,I$22:M$42,5,0) -> #N/A | K34: =J34/J$42 -> #DIV/0! | L34: =K34+L33 -> #DIV/0! | M34: =_xlfn.IFS(L34<80%,"A",L34<=95%,"B",L34>95%,"C") -> #DIV/0!
... D41: =C41/C$42 -> #DIV/0! | E41: =D41+E40 -> #DIV/0! | F41: =IF(AND(E41<=0),"C",IF(E41<=0.8,"A",IF(E41<=0.95,"B","C"))) -> #DIV/0! | G41: =VLOOKUP(B$22:B$42,I$22:M$42,5,0) -> #N/A | K41: =J41/J$42 -> #DIV/0! | L41: =K41+L40 -> #DIV/0! | M41: =_xlfn.IFS(L41<80%,"A",L41<=95%,"B",L41>95%,"C") -> #DIV/0!
C42: =SUM(C22:C41) -> 0 | D42: =SUM(D22:D41) -> #DIV/0! | J42: =SUM(J22:J41) -> 0 | K42: =SUM(K22:K41) -> #DIV/0!

Sheet АВС 05-11.01
B2: ОЧКИ
C3: Прибыль | D3: % прибыль | E3: Доля | F3: ABC прибыль | G3: ABC кол-во | J3: Кол-во | K3: % кол-во | L3: Доля | M3: ABC кол-во
B4: th желт | C4: ='Юнит 05-11.01'!AE11 -> 10607.526 | D4: =C4/C$18 -> 0.33406592 | E4: =D4 -> 0.33406592 | F4: =IF(AND(E4<=0),"C",IF(E4<=0.8,"A",IF(E4<=0.95,"B","C"))) -> A | G4: =VLOOKUP(B$4:B$17,I$4:M$17,5,0) -> A | I4: th желт | J4: ='Юнит 05-11.01'!R11 -> 52 | K4: =J4/J$18 -> 0.325 | L4: =K4 -> 0.325 | M4: =_xlfn.IFS(L4<80%,"A",L4<=95%,"B",L4>95%,"C") -> A
B5: flip жел | C5: ='Юнит 05-11.01'!AE15 -> 9475.9191 | D5: =C5/C$18 -> 0.29842789 | E5: =D5+E4 -> 0.63249381 | F5: =IF(AND(E5<=0),"C",IF(E5<=0.8,"A",IF(E5<=0.95,"B","C"))) -> A | G5: =VLOOKUP(B$4:B$17,I$4:M$17,5,0) -> A | I5: flip жел | J5: ='Юнит 05-11.01'!R15 -> 49 | K5: =J5/J$18 -> 0.30625 | L5: =K5+L4 -> 0.63125 | M5: =_xlfn.IFS(L5<80%,"A",L5<=95%,"B",L5>95%,"C") -> A
B6: qs желтые | C6: ='Юнит 05-11.01'!AE6 -> 4582.8566 | D6: =C6/C$18 -> 0.14432924 | E6: =D6+E5 -> 0.77682306 | F6: =IF(AND(E6<=0),"C",IF(E6<=0.8,"A",IF(E6<=0.95,"B","C"))) -> A | G6: =VLOOKUP(B$4:B$17,I$4:M$17,5,0) -> B | I6: qs желтые | J6: ='Юнит 05-11.01'!R6 -> 31 | K6: =J6/J$18 -> 0.19375 | L6: =K6+L5 -> 0.825 | M6: =_xlfn.IFS(L6<80%,"A",L6<=95%,"B",L6>95%,"C") -> B
B7: qs коричневые | C7: ='Юнит 05-11.01'!AE7 -> 2064.4032 | D7: =C7/C$18 -> 0.065014854 | E7: =D7+E6 -> 0.84183791 | F7: =IF(AND(E7<=0),"C",IF(E7<=0.8,"A",IF(E7<=0.95,"B","C"))) -> B | G7: =VLOOKUP(B$4:B$17,I$4:M$17,5,0) -> B | I7: MR8854 C2 | J7: ='Юнит 05-11.01'!R8 -> 10 | K7: =J7/J$18 -> 0.0625 | L7: =K7+L6 -> 0.8875 | M7: =_xlfn.IFS(L7<80%,"A",L7<=95%,"B",L7>95%,"C") -> B
B8: MR8854 C2 | C8: ='Юнит 05-11.01'!AE8 -> 1951.2156 | D8: =C8/C$18 -> 0.061450204 | E8: =D8+E7 -> 0.90328811 | F8: =IF(AND(E8<=0),"C",IF(E8<=0.8,"A",IF(E8<=0.95,"B","C"))) -> B | G8: =VLOOKUP(B$4:B$17,I$4:M$17,5,0) -> B | I8: qs коричневые | J8: ='Юнит 05-11.01'!R7 -> 8 | K8: =J8/J$18 -> 0.05 | L8: =K8+L7 -> 0.9375 | M8: =_xlfn.IFS(L8<80%,"A",L8<=95%,"B",L8>95%,"C") -> B
B9: черные с железкой классика | C9: ='Юнит 05-11.01'!AE3 -> 1482.471 | D9: =C9/C$18 -> 0.046687892 | E9: =D9+E8 -> 0.94997601 | F9: =IF(AND(E9<=0),"C",IF(E9<=0.8,"A",IF(E9<=0.95,"B","C"))) -> B | G9: =VLOOKUP(B$4:B$17,I$4:M$17,5,0) -> C | I9: черные с железкой классика | J9: ='Юнит 05-11.01'!R3 -> 5 | K9: =J9/J$18 -> 0.03125 | L9: =K9+L8 -> 0.96875 | M9: =_xlfn.IFS(L9<80%,"A",L9<=95%,"B",L9>95%,"C") -> C
B10: qs черные | C10: ='Юнит 05-11.01'!AE4 -> 1287.9957 | D10: =C10/C$18 -> 0.040563225 | E10: =D10+E9 -> 0.99053923 | F10: =IF(AND(E10<=0),"C",IF(E10<=0.8,"A",IF(E10<=0.95,"B","C"))) -> C | G10: =VLOOKUP(B$4:B$17,I$4:M$17,5,0) -> C | I10: qs черные | J10: ='Юнит 05-11.01'!R4 -> 3 | K10: =J10/J$18 -> 0.01875 | L10: =K10+L9 -> 0.9875 | M10: =_xlfn.IFS(L10<80%,"A",L10<=95%,"B",L10>95%,"C") -> C
B11: qs синие | C11: ='Юнит 05-11.01'!AE5 -> 300.40588 | D11: =C11/C$18 -> 0.0094607701 | E11: =D11+E10 -> 1 | F11: =IF(AND(E11<=0),"C",IF(E11<=0.8,"A",IF(E11<=0.95,"B","C"))) -> C | G11: =VLOOKUP(B$4:B$17,I$4:M$17,5,0) -> C | I11: qs синие | J11: ='Юнит 05-11.01'!R5 -> 2 | K11: =J11/J$18 -> 0.0125 | L11: =K11+L10 -> 1 | M11: =_xlfn.IFS(L11<80%,"A",L11<=95%,"B",L11>95%,"C") -> C
B12: th черн | C12: ='Юнит 05-11.01'!AE9 -> 0 | D12: =C12/C$18 -> 0 | E12: =D12+E5 -> 0.63249381 | F12: =IF(AND(E12<=0),"C",IF(E12<=0.8,"A",IF(E12<=0.95,"B","C"))) -> A | G12: =VLOOKUP(B$4:B$17,I$4:M$17,5,0) -> A | I12: th черн | J12: ='Юнит 05-11.01'!R9 -> 0 | K12: =J12/J$18 -> 0 | L12: =K12+L5 -> 0.63125 | M12: =_xlfn.IFS(L12<80%,"A",L12<=95%,"B",L12>95%,"C") -> A
B13: th син | C13: ='Юнит 05-11.01'!AE10 -> 0 | D13: =C13/C$18 -> 0 | E13: =D13+E12 -> 0.63249381 | F13: =IF(AND(E13<=0),"C",IF(E13<=0.8,"A",IF(E13<=0.95,"B","C"))) -> A | G13: =VLOOKUP(B$4:B$17,I$4:M$17,5,0) -> A | I13: th син | J13: ='Юнит 05-11.01'!R10 -> 0 | K13: =J13/J$18 -> 0 | L13: =K13+L12 -> 0.63125 | M13: =_xlfn.IFS(L13<80%,"A",L13<=95%,"B",L13>95%,"C") -> A
B14: th коричн | C14: ='Юнит 05-11.01'!AE12 -> 0 | D14: =C14/C$18 -> 0 | E14: =D14+E13 -> 0.63249381 | F14: =IF(AND(E14<=0),"C",IF(E14<=0.8,"A",IF(E14<=0.95,"B","C"))) -> A | G14: =VLOOKUP(B$4:B$17,I$4:M$17,5,0) -> A | I14: th коричн | J14: ='Юнит 05-11.01'!R12 -> 0 | K14: =J14/J$18 -> 0 | L14: =K14+L13 -> 0.63125 | M14: =_xlfn.IFS(L14<80%,"A",L14<=95%,"B",L14>95%,"C") -> A
B15: flip черный | C15: ='Юнит 05-11.01'!AE13 -> 0 | D15: =C15/C$18 -> 0 | E15: =D15+E14 -> 0.63249381 | F15: =IF(AND(E15<=0),"C",IF(E15<=0.8,"A",IF(E15<=0.95,"B","C"))) -> A | G15: =VLOOKUP(B$4:B$17,I$4:M$17,5,0) -> A | I15: flip черный | J15: ='Юнит 05-11.01'!R13 -> 0 | K15: =J15/J$18 -> 0 | L15: =K15+L14 -> 0.63125 | M15: =_xlfn.IFS(L15<80%,"A",L15<=95%,"B",L15>95%,"C") -> A
B16: flip синий | C16: ='Юнит 05-11.01'!AE14 -> 0 | D16: =C16/C$18 -> 0 | E16: =D16+E15 -> 0.63249381 | F16: =IF(AND(E16<=0),"C",IF(E16<=0.8,"A",IF(E16<=0.95,"B","C"))) -> A | G16: =VLOOKUP(B$4:B$17,I$4:M$17,5,0) -> A | I16: flip синий | J16: ='Юнит 05-11.01'!R14 -> 0 | K16: =J16/J$18 -> 0 | L16: =K16+L15 -> 0.63125 | M16: =_xlfn.IFS(L16<80%,"A",L16<=95%,"B",L16>95%,"C") -> A
B17: flip коричневый | C17: ='Юнит 05-11.01'!AE16 -> 0 | D17: =C17/C$18 -> 0 | E17: =D17+E14 -> 0.63249381 | F17: =IF(AND(E17<=0),"C",IF(E17<=0.8,"A",IF(E17<=0.95,"B","C"))) -> A | G17: =VLOOKUP(B$4:B$17,I$4:M$17,5,0) -> A | I17: flip коричневый | J17: ='Юнит 05-11.01'!R16 -> 0 | K17: =J17/J$18 -> 0 | L17: =K17+L14 -> 0.63125 | M17: =_xlfn.IFS(L17<80%,"A",L17<=95%,"B",L17>95%,"C") -> A
C18: =SUM(C4:C17) -> 31752.793 | D18: =SUM(D4:D17) -> 1 | J18: =SUM(J4:J17) -> 160 | K18: =SUM(K4:K17) -> 1
C21: Прибыль | D21: % прибыль | E21: Доля | F21: ABC прибыль | G21: ABC кол-во | J21: Кол-во | K21: % кол-во | L21: Доля | M21: ABC кол-во
D22: =C22/C$42 -> #DIV/0! | E22: =D22 -> #DIV/0! | F22: =IF(AND(E22<=0),"C",IF(E22<=0.8,"A",IF(E22<=0.95,"B","C"))) -> #DIV/0! | G22: =VLOOKUP(B$22:B$42,I$22:M$42,5,0) -> #N/A | K22: =J22/J$42 -> #DIV/0! | L22: =K22 -> #DIV/0! | M22: =_xlfn.IFS(L22<80%,"A",L22<=95%,"B",L22>95%,"C") -> #DIV/0!
D23: =C23/C$42 -> #DIV/0! | E23: =D23+E22 -> #DIV/0! | F23: =IF(AND(E23<=0),"C",IF(E23<=0.8,"A",IF(E23<=0.95,"B","C"))) -> #DIV/0! | G23: =VLOOKUP(B$22:B$42,I$22:M$42,5,0) -> #N/A | K23: =J23/J$42 -> #DIV/0! | L23: =K23+L22 -> #DIV/0! | M23: =_xlfn.IFS(L23<80%,"A",L23<=95%,"B",L23>95%,"C") -> #DIV/0!
D24: =C24/C$42 -> #DIV/0! | E24: =D24+E23 -> #DIV/0! | F24: =IF(AND(E24<=0),"C",IF(E24<=0.8,"A",IF(E24<=0.95,"B","C"))) -> #DIV/0! | G24: =VLOOKUP(B$22:B$42,I$22:M$42,5,0) -> #N/A | K24: =J24/J$42 -> #DIV/0! | L24: =K24+L23 -> #DIV/0! | M24: =_xlfn.IFS(L24<80%,"A",L24<=95%,"B",L24>95%,"C") -> #DIV/0!
D25: =C25/C$42 -> #DIV/0! | E25: =D25+E24 -> #DIV/0! | F25: =IF(AND(E25<=0),"C",IF(E25<=0.8,"A",IF(E25<=0.95,"B","C"))) -> #DIV/0! | G25: =VLOOKUP(B$22:B$42,I$22:M$42,5,0) -> #N/A | K25: =J25/J$42 -> #DIV/0! | L25: =K25+L24 -> #DIV/0! | M25: =_xlfn.IFS(L25<80%,"A",L25<=95%,"B",L25>95%,"C") -> #DIV/0!
D26: =C26/C$42 -> #DIV/0! | E26: =D26+E25 -> #DIV/0! | F26: =IF(AND(E26<=0),"C",IF(E26<=0.8,"A",IF(E26<=0.95,"B","C"))) -> #DIV/0! | G26: =VLOOKUP(B$22:B$42,I$22:M$42,5,0) -> #N/A | K26: =J26/J$42 -> #DIV/0! | L26: =K26+L25 -> #DIV/0! | M26: =_xlfn.IFS(L26<80%,"A",L26<=95%,"B",L26>95%,"C") -> #DIV/0!
D27: =C27/C$42 -> #DIV/0! | E27: =D27+E26 -> #DIV/0! | F27: =IF(AND(E27<=0),"C",IF(E27<=0.8,"A",IF(E27<=0.95,"B","C"))) -> #DIV/0! | G27: =VLOOKUP(B$22:B$42,I$22:M$42,5,0) -> #N/A | K27: =J27/J$42 -> #DIV/0! | L27: =K27+L26 -> #DIV/0! | M27: =_xlfn.IFS(L27<80%,"A",L27<=95%,"B",L27>95%,"C") -> #DIV/0!
D28: =C28/C$42 -> #DIV/0! | E28: =D28+E27 -> #DIV/0! | F28: =IF(AND(E28<=0),"C",IF(E28<=0.8,"A",IF(E28<=0.95,"B","C"))) -> #DIV/0! | G28: =VLOOKUP(B$22:B$42,I$22:M$42,5,0) -> #N/A | K28: =J28/J$42 -> #DIV/0! | L28: =K28+L27 -> #DIV/0! | M28: =_xlfn.IFS(L28<80%,"A",L28<=95%,"B",L28>95%,"C") -> #DIV/0!
D29: =C29/C$42 -> #DIV/0! | E29: =D29+E28 -> #DIV/0! | F29: =IF(AND(E29<=0),"C",IF(E29<=0.8,"A",IF(E29<=0.95,"B","C"))) -> #DIV/0! | G29: =VLOOKUP(B$22:B$42,I$22:M$42,5,0) -> #N/A | K29: =J29/J$42 -> #DIV/0! | L29: =K29+L28 -> #DIV/0! | M29: =_xlfn.IFS(L29<80%,"A",L29<=95%,"B",L29>95%,"C") -> #DIV/0!
D30: =C30/C$42 -> #DIV/0! | E30: =D30+E29 -> #DIV/0! | F30: =IF(AND(E30<=0),"C",IF(E30<=0.8,"A",IF(E30<=0.95,"B","C"))) -> #DIV/0! | G30: =VLOOKUP(B$22:B$42,I$22:M$42,5,0) -> #N/A | K30: =J30/J$42 -> #DIV/0! | L30: =K30+L29 -> #DIV/0! | M30: =_xlfn.IFS(L30<80%,"A",L30<=95%,"B",L30>95%,"C") -> #DIV/0!
D31: =C31/C$42 -> #DIV/0! | E31: =D31+E30 -> #DIV/0! | F31: =IF(AND(E31<=0),"C",IF(E31<=0.8,"A",IF(E31<=0.95,"B","C"))) -> #DIV/0! | G31: =VLOOKUP(B$22:B$42,I$22:M$42,5,0) -> #N/A | K31: =J31/J$42 -> #DIV/0! | L31: =K31+L30 -> #DIV/0! | M31: =_xlfn.IFS(L31<80%,"A",L31<=95%,"B",L31>95%,"C") -> #DIV/0!
D32: =C32/C$42 -> #DIV/0! | E32: =D32+E31 -> #DIV/0! | F32: =IF(AND(E32<=0),"C",IF(E32<=0.8,"A",IF(E32<=0.95,"B","C"))) -> #DIV/0! | G32: =VLOOKUP(B$22:B$42,I$22:M$42,5,0) -> #N/A | K32: =J32/J$42 -> #DIV/0! | L32: =K32+L31 -> #DIV/0! | M32: =_xlfn.IFS(L32<80%,"A",L32<=95%,"B",L32>95%,"C") -> #DIV/0!
D33: =C33/C$42 -> #DIV/0! | E33: =D33+E32 -> #DIV/0! | F33: =IF(AND(E33<=0),"C",IF(E33<=0.8,"A",IF(E33<=0.95,"B","C"))) -> #DIV/0! | G33: =VLOOKUP(B$22:B$42,I$22:M$42,5,0) -> #N/A | K33: =J33/J$42 -> #DIV/0! | L33: =K33+L32 -> #DIV/0! | M33: =_xlfn.IFS(L33<80%,"A",L33<=95%,"B",L33>95%,"C") -> #DIV/0!
D34: =C34/C$42 -> #DIV/0! | E34: =D34+E33 -> #DIV/0! | F34: =IF(AND(E34<=0),"C",IF(E34<=0.8,"A",IF(E34<=0.95,"B","C"))) -> #DIV/0! | G34: =VLOOKUP(B$22:B$42,I$22:M$42,5,0) -> #N/A | K34: =J34/J$42 -> #DIV/0! | L34: =K34+L33 -> #DIV/0! | M34: =_xlfn.IFS(L34<80%,"A",L34<=95%,"B",L34>95%,"C") -> #DIV/0!
... D41: =C41/C$42 -> #DIV/0! | E41: =D41+E40 -> #DIV/0! | F41: =IF(AND(E41<=0),"C",IF(E41<=0.8,"A",IF(E41<=0.95,"B","C"))) -> #DIV/0! | G41: =VLOOKUP(B$22:B$42,I$22:M$42,5,0) -> #N/A | K41: =J41/J$42 -> #DIV/0! | L41: =K41+L40 -> #DIV/0! | M41: =_xlfn.IFS(L41<80%,"A",L41<=95%,"B",L41>95%,"C") -> #DIV/0!
C42: =SUM(C22:C41) -> 0 | D42: =SUM(D22:D41) -> #DIV/0! | J42: =SUM(J22:J41) -> 0 | K42: =SUM(K22:K41) -> #DIV/0!

Sheet АВС 01-04.01
B2: ОЧКИ
C3: Прибыль | D3: % прибыль | E3: Доля | F3: ABC прибыль | G3: ABC кол-во | J3: Кол-во | K3: % кол-во | L3: Доля | M3: ABC кол-во
B4: flip жел | C4: ='Юнит 01-04.01'!AE15 -> 814.08013 | D4: =C4/C$18 -> -0.10547699 | E4: =D4 -> -0.10547699 | F4: =IF(AND(E4<=0),"C",IF(E4<=0.8,"A",IF(E4<=0.95,"B","C"))) -> C | G4: =VLOOKUP(B$4:B$17,I$4:M$17,5,0) -> A | I4: flip жел | J4: ='Юнит 01-04.01'!R15 -> 25 | K4: =J4/J$18 -> 0.5 | L4: =K4 -> 0.5 | M4: =_xlfn.IFS(L4<80%,"A",L4<=95%,"B",L4>95%,"C") -> A
B5: qs черные | C5: ='Юнит 01-04.01'!AE4 -> 606.615 | D5: =C5/C$18 -> -0.07859659 | E5: =D5+E4 -> -0.18407358 | F5: =IF(AND(E5<=0),"C",IF(E5<=0.8,"A",IF(E5<=0.95,"B","C"))) -> C | G5: =VLOOKUP(B$4:B$17,I$4:M$17,5,0) -> C | I5: th желт | J5: ='Юнит 01-04.01'!R11 -> 12 | K5: =J5/J$18 -> 0.24 | L5: =K5+L4 -> 0.74 | M5: =_xlfn.IFS(L5<80%,"A",L5<=95%,"B",L5>95%,"C") -> A
B6: qs коричневые | C6: ='Юнит 01-04.01'!AE7 -> 602.25 | D6: =C6/C$18 -> -0.078031035 | E6: =D6+E5 -> -0.26210461 | F6: =IF(AND(E6<=0),"C",IF(E6<=0.8,"A",IF(E6<=0.95,"B","C"))) -> C | G6: =VLOOKUP(B$4:B$17,I$4:M$17,5,0) -> B | I6: qs желтые | J6: ='Юнит 01-04.01'!R6 -> 7 | K6: =J6/J$18 -> 0.14 | L6: =K6+L5 -> 0.88 | M6: =_xlfn.IFS(L6<80%,"A",L6<=95%,"B",L6>95%,"C") -> B
B7: черные с железкой классика | C7: ='Юнит 01-04.01'!AE3 -> 199.475 | D7: =C7/C$18 -> -0.025845149 | E7: =D7+E6 -> -0.28794976 | F7: =IF(AND(E7<=0),"C",IF(E7<=0.8,"A",IF(E7<=0.95,"B","C"))) -> C | G7: =VLOOKUP(B$4:B$17,I$4:M$17,5,0) -> C | I7: qs коричневые | J7: ='Юнит 01-04.01'!R7 -> 2 | K7: =J7/J$18 -> 0.04 | L7: =K7+L6 -> 0.92 | M7: =_xlfn.IFS(L7<80%,"A",L7<=95%,"B",L7>95%,"C") -> B
B8: qs синие | C8: ='Юнит 01-04.01'!AE5 -> 0 | D8: =C8/C$18 -> 0 | E8: =D8+E7 -> -0.28794976 | F8: =IF(AND(E8<=0),"C",IF(E8<=0.8,"A",IF(E8<=0.95,"B","C"))) -> C | G8: =VLOOKUP(B$4:B$17,I$4:M$17,5,0) -> C | I8: MR8854 C2 | J8: ='Юнит 01-04.01'!R8 -> 2 | K8: =J8/J$18 -> 0.04 | L8: =K8+L7 -> 0.96 | M8: =_xlfn.IFS(L8<80%,"A",L8<=95%,"B",L8>95%,"C") -> C
B9: th черн | C9: ='Юнит 01-04.01'!AE9 -> 0 | D9: =C9/C$18 -> 0 | E9: =D9+E8 -> -0.28794976 | F9: =IF(AND(E9<=0),"C",IF(E9<=0.8,"A",IF(E9<=0.95,"B","C"))) -> C | G9: =VLOOKUP(B$4:B$17,I$4:M$17,5,0) -> A | I9: черные с железкой классика | J9: ='Юнит 01-04.01'!R3 -> 1 | K9: =J9/J$18 -> 0.02 | L9: =K9+L8 -> 0.98 | M9: =_xlfn.IFS(L9<80%,"A",L9<=95%,"B",L9>95%,"C") -> C
B10: th син | C10: ='Юнит 01-04.01'!AE10 -> 0 | D10: =C10/C$18 -> 0 | E10: =D10+E9 -> -0.28794976 | F10: =IF(AND(E10<=0),"C",IF(E10<=0.8,"A",IF(E10<=0.95,"B","C"))) -> C | G10: =VLOOKUP(B$4:B$17,I$4:M$17,5,0) -> A | I10: qs черные | J10: ='Юнит 01-04.01'!R4 -> 1 | K10: =J10/J$18 -> 0.02 | L10: =K10+L9 -> 1 | M10: =_xlfn.IFS(L10<80%,"A",L10<=95%,"B",L10>95%,"C") -> C
B11: th коричн | C11: ='Юнит 01-04.01'!AE12 -> 0 | D11: =C11/C$18 -> 0 | E11: =D11+E10 -> -0.28794976 | F11: =IF(AND(E11<=0),"C",IF(E11<=0.8,"A",IF(E11<=0.95,"B","C"))) -> C | G11: =VLOOKUP(B$4:B$17,I$4:M$17,5,0) -> A | I11: qs синие | J11: ='Юнит 01-04.01'!R5 -> 0 | K11: =J11/J$18 -> 0 | L11: =K11+L10 -> 1 | M11: =_xlfn.IFS(L11<80%,"A",L11<=95%,"B",L11>95%,"C") -> C
B12: flip черный | C12: ='Юнит 01-04.01'!AE13 -> 0 | D12: =C12/C$18 -> 0 | E12: =D12+E5 -> -0.18407358 | F12: =IF(AND(E12<=0),"C",IF(E12<=0.8,"A",IF(E12<=0.95,"B","C"))) -> C | G12: =VLOOKUP(B$4:B$17,I$4:M$17,5,0) -> A | I12: th черн | J12: ='Юнит 01-04.01'!R9 -> 0 | K12: =J12/J$18 -> 0 | L12: =K12+L5 -> 0.74 | M12: =_xlfn.IFS(L12<80%,"A",L12<=95%,"B",L12>95%,"C") -> A
B13: flip синий | C13: ='Юнит 01-04.01'!AE14 -> 0 | D13: =C13/C$18 -> 0 | E13: =D13+E12 -> -0.18407358 | F13: =IF(AND(E13<=0),"C",IF(E13<=0.8,"A",IF(E13<=0.95,"B","C"))) -> C | G13: =VLOOKUP(B$4:B$17,I$4:M$17,5,0) -> A | I13: th син | J13: ='Юнит 01-04.01'!R10 -> 0 | K13: =J13/J$18 -> 0 | L13: =K13+L12 -> 0.74 | M13: =_xlfn.IFS(L13<80%,"A",L13<=95%,"B",L13>95%,"C") -> A
B14: flip коричневый | C14: ='Юнит 01-04.01'!AE16 -> 0 | D14: =C14/C$18 -> 0 | E14: =D14+E13 -> -0.18407358 | F14: =IF(AND(E14<=0),"C",IF(E14<=0.8,"A",IF(E14<=0.95,"B","C"))) -> C | G14: =VLOOKUP(B$4:B$17,I$4:M$17,5,0) -> A | I14: th коричн | J14: ='Юнит 01-04.01'!R12 -> 0 | K14: =J14/J$18 -> 0 | L14: =K14+L13 -> 0.74 | M14: =_xlfn.IFS(L14<80%,"A",L14<=95%,"B",L14>95%,"C") -> A
B15: MR8854 C2 | C15: ='Юнит 01-04.01'!AE8 -> -532.4584 | D15: =C15/C$18 -> 0.068988427 | E15: =D15+E14 -> -0.11508515 | F15: =IF(AND(E15<=0),"C",IF(E15<=0.8,"A",IF(E15<=0.95,"B","C"))) -> C | G15: =VLOOKUP(B$4:B$17,I$4:M$17,5,0) -> C | I15: flip черный | J15: ='Юнит 01-04.01'!R13 -> 0 | K15: =J15/J$18 -> 0 | L15: =K15+L14 -> 0.74 | M15: =_xlfn.IFS(L15<80%,"A",L15<=95%,"B",L15>95%,"C") -> A
B16: qs желтые | C16: ='Юнит 01-04.01'!AE6 -> -2868.5861 | D16: =C16/C$18 -> 0.3716708 | E16: =D16+E15 -> 0.25658565 | F16: =IF(AND(E16<=0),"C",IF(E16<=0.8,"A",IF(E16<=0.95,"B","C"))) -> A | G16: =VLOOKUP(B$4:B$17,I$4:M$17,5,0) -> B | I16: flip синий | J16: ='Юнит 01-04.01'!R14 -> 0 | K16: =J16/J$18 -> 0 | L16: =K16+L15 -> 0.74 | M16: =_xlfn.IFS(L16<80%,"A",L16<=95%,"B",L16>95%,"C") -> A
B17: th желт | C17: ='Юнит 01-04.01'!AE11 -> -6539.4586 | D17: =C17/C$18 -> 0.84729053 | E17: =D17+E14 -> 0.66321695 | F17: =IF(AND(E17<=0),"C",IF(E17<=0.8,"A",IF(E17<=0.95,"B","C"))) -> A | G17: =VLOOKUP(B$4:B$17,I$4:M$17,5,0) -> A | I17: flip коричневый | J17: ='Юнит 01-04.01'!R16 -> 0 | K17: =J17/J$18 -> 0 | L17: =K17+L14 -> 0.74 | M17: =_xlfn.IFS(L17<80%,"A",L17<=95%,"B",L17>95%,"C") -> A
C18: =SUM(C4:C17) -> -7718.0829 | D18: =SUM(D4:D17) -> 1 | J18: =SUM(J4:J17) -> 50 | K18: =SUM(K4:K17) -> 1
C21: Прибыль | D21: % прибыль | E21: Доля | F21: ABC прибыль | G21: ABC кол-во | J21: Кол-во | K21: % кол-во | L21: Доля | M21: ABC кол-во
D22: =C22/C$42 -> #DIV/0! | E22: =D22 -> #DIV/0! | F22: =IF(AND(E22<=0),"C",IF(E22<=0.8,"A",IF(E22<=0.95,"B","C"))) -> #DIV/0! | G22: =VLOOKUP(B$22:B$42,I$22:M$42,5,0) -> #N/A | K22: =J22/J$42 -> #DIV/0! | L22: =K22 -> #DIV/0! | M22: =_xlfn.IFS(L22<80%,"A",L22<=95%,"B",L22>95%,"C") -> #DIV/0!
D23: =C23/C$42 -> #DIV/0! | E23: =D23+E22 -> #DIV/0! | F23: =IF(AND(E23<=0),"C",IF(E23<=0.8,"A",IF(E23<=0.95,"B","C"))) -> #DIV/0! | G23: =VLOOKUP(B$22:B$42,I$22:M$42,5,0) -> #N/A | K23: =J23/J$42 -> #DIV/0! | L23: =K23+L22 -> #DIV/0! | M23: =_xlfn.IFS(L23<80%,"A",L23<=95%,"B",L23>95%,"C") -> #DIV/0!
D24: =C24/C$42 -> #DIV/0! | E24: =D24+E23 -> #DIV/0! | F24: =IF(AND(E24<=0),"C",IF(E24<=0.8,"A",IF(E24<=0.95,"B","C"))) -> #DIV/0! | G24: =VLOOKUP(B$22:B$42,I$22:M$42,5,0) -> #N/A | K24: =J24/J$42 -> #DIV/0! | L24: =K24+L23 -> #DIV/0! | M24: =_xlfn.IFS(L24<80%,"A",L24<=95%,"B",L24>95%,"C") -> #DIV/0!
D25: =C25/C$42 -> #DIV/0! | E25: =D25+E24 -> #DIV/0! | F25: =IF(AND(E25<=0),"C",IF(E25<=0.8,"A",IF(E25<=0.95,"B","C"))) -> #DIV/0! | G25: =VLOOKUP(B$22:B$42,I$22:M$42,5,0) -> #N/A | K25: =J25/J$42 -> #DIV/0! | L25: =K25+L24 -> #DIV/0! | M25: =_xlfn.IFS(L25<80%,"A",L25<=95%,"B",L25>95%,"C") -> #DIV/0!
D26: =C26/C$42 -> #DIV/0! | E26: =D26+E25 -> #DIV/0! | F26: =IF(AND(E26<=0),"C",IF(E26<=0.8,"A",IF(E26<=0.95,"B","C"))) -> #DIV/0! | G26: =VLOOKUP(B$22:B$42,I$22:M$42,5,0) -> #N/A | K26: =J26/J$42 -> #DIV/0! | L26: =K26+L25 -> #DIV/0! | M26: =_xlfn.IFS(L26<80%,"A",L26<=95%,"B",L26>95%,"C") -> #DIV/0!
D27: =C27/C$42 -> #DIV/0! | E27: =D27+E26 -> #DIV/0! | F27: =IF(AND(E27<=0),"C",IF(E27<=0.8,"A",IF(E27<=0.95,"B","C"))) -> #DIV/0! | G27: =VLOOKUP(B$22:B$42,I$22:M$42,5,0) -> #N/A | K27: =J27/J$42 -> #DIV/0! | L27: =K27+L26 -> #DIV/0! | M27: =_xlfn.IFS(L27<80%,"A",L27<=95%,"B",L27>95%,"C") -> #DIV/0!
D28: =C28/C$42 -> #DIV/0! | E28: =D28+E27 -> #DIV/0! | F28: =IF(AND(E28<=0),"C",IF(E28<=0.8,"A",IF(E28<=0.95,"B","C"))) -> #DIV/0! | G28: =VLOOKUP(B$22:B$42,I$22:M$42,5,0) -> #N/A | K28: =J28/J$42 -> #DIV/0! | L28: =K28+L27 -> #DIV/0! | M28: =_xlfn.IFS(L28<80%,"A",L28<=95%,"B",L28>95%,"C") -> #DIV/0!
D29: =C29/C$42 -> #DIV/0! | E29: =D29+E28 -> #DIV/0! | F29: =IF(AND(E29<=0),"C",IF(E29<=0.8,"A",IF(E29<=0.95,"B","C"))) -> #DIV/0! | G29: =VLOOKUP(B$22:B$42,I$22:M$42,5,0) -> #N/A | K29: =J29/J$42 -> #DIV/0! | L29: =K29+L28 -> #DIV/0! | M29: =_xlfn.IFS(L29<80%,"A",L29<=95%,"B",L29>95%,"C") -> #DIV/0!
D30: =C30/C$42 -> #DIV/0! | E30: =D30+E29 -> #DIV/0! | F30: =IF(AND(E30<=0),"C",IF(E30<=0.8,"A",IF(E30<=0.95,"B","C"))) -> #DIV/0! | G30: =VLOOKUP(B$22:B$42,I$22:M$42,5,0) -> #N/A | K30: =J30/J$42 -> #DIV/0! | L30: =K30+L29 -> #DIV/0! | M30: =_xlfn.IFS(L30<80%,"A",L30<=95%,"B",L30>95%,"C") -> #DIV/0!
D31: =C31/C$42 -> #DIV/0! | E31: =D31+E30 -> #DIV/0! | F31: =IF(AND(E31<=0),"C",IF(E31<=0.8,"A",IF(E31<=0.95,"B","C"))) -> #DIV/0! | G31: =VLOOKUP(B$22:B$42,I$22:M$42,5,0) -> #N/A | K31: =J31/J$42 -> #DIV/0! | L31: =K31+L30 -> #DIV/0! | M31: =_xlfn.IFS(L31<80%,"A",L31<=95%,"B",L31>95%,"C") -> #DIV/0!
D32: =C32/C$42 -> #DIV/0! | E32: =D32+E31 -> #DIV/0! | F32: =IF(AND(E32<=0),"C",IF(E32<=0.8,"A",IF(E32<=0.95,"B","C"))) -> #DIV/0! | G32: =VLOOKUP(B$22:B$42,I$22:M$42,5,0) -> #N/A | K32: =J32/J$42 -> #DIV/0! | L32: =K32+L31 -> #DIV/0! | M32: =_xlfn.IFS(L32<80%,"A",L32<=95%,"B",L32>95%,"C") -> #DIV/0!
D33: =C33/C$42 -> #DIV/0! | E33: =D33+E32 -> #DIV/0! | F33: =IF(AND(E33<=0),"C",IF(E33<=0.8,"A",IF(E33<=0.95,"B","C"))) -> #DIV/0! | G33: =VLOOKUP(B$22:B$42,I$22:M$42,5,0) -> #N/A | K33: =J33/J$42 -> #DIV/0! | L33: =K33+L32 -> #DIV/0! | M33: =_xlfn.IFS(L33<80%,"A",L33<=95%,"B",L33>95%,"C") -> #DIV/0!
D34: =C34/C$42 -> #DIV/0! | E34: =D34+E33 -> #DIV/0! | F34: =IF(AND(E34<=0),"C",IF(E34<=0.8,"A",IF(E34<=0.95,"B","C"))) -> #DIV/0! | G34: =VLOOKUP(B$22:B$42,I$22:M$42,5,0) -> #N/A | K34: =J34/J$42 -> #DIV/0! | L34: =K34+L33 -> #DIV/0! | M34: =_xlfn.IFS(L34<80%,"A",L34<=95%,"B",L34>95%,"C") -> #DIV/0!
... D41: =C41/C$42 -> #DIV/0! | E41: =D41+E40 -> #DIV/0! | F41: =IF(AND(E41<=0),"C",IF(E41<=0.8,"A",IF(E41<=0.95,"B","C"))) -> #DIV/0! | G41: =VLOOKUP(B$22:B$42,I$22:M$42,5,0) -> #N/A | K41: =J41/J$42 -> #DIV/0! | L41: =K41+L40 -> #DIV/0! | M41: =_xlfn.IFS(L41<80%,"A",L41<=95%,"B",L41>95%,"C") -> #DIV/0!
C42: =SUM(C22:C41) -> 0 | D42: =SUM(D22:D41) -> #DIV/0! | J42: =SUM(J22:J41) -> 0 | K42: =SUM(K22:K41) -> #DIV/0!

Sheet Юнит 01.02
B1: 01.02 | AG1: на 1 единицу проданного товара
B2: Артикул поставщика | C2: Остаток на | D2: В пути до клиента | E2: В пути от клиента | F2: Итого по складам ВБ | G2: Остаток на нашем складе на 02.09 | H2: Себетоимость на 1 ед на 29.09.25 | I2: Себестоимость остатков | J2: Оборачиваемость, дн | K2: Заказы, шт 7 дней | L2: Средняя цена, руб (столбец 32, AG) | M2: % выкупа за 7 дней (столбец 23, X) | N2: Скорость заказов | O2: Скорость продаж | P2: Кол-во ПРОДАЖИ | Q2: Кол-во ВОЗВРАТЫ | R2: Кол-во ПРОДАЖИ-ВОЗВРАТЫ | S2: Выручка ПРОДАЖИ | T2: Выручка ВОЗВРАТЫ | U2: Выручка с учетом согласованной скидки ПРОДАЖИ - ВОЗВРАТЫ | V2: Доля выручки, % от общего объема | W2: Себестоимость продаж | X2: Комиссия, руб | Y2: Комиссия, % | Z2: Логистика | AA2: Реклама | AB2: Хранение | AC2: Штрафы | AD2: Налог 1%+ НДС 5% | AE2: Прибыль | AG2: Выручка на 1 ед (средняя цена продажи со скидкой) | AH2: Себестоимость на 1 ед | AI2: Комиссия на 1 ед | AJ2: Логистика на 1 ед | AK2: Реклама на 1 ед | AL2: Прибыль на 1 ед | AM2: Маржинальность, % | AN2: Рентабельность, % | AP2: Прибыль с остатков
A3: 2676784153 | B3: черные с железкой классика | H3: 142.98 | I3: =C3*H3 -> 0 | N3: =K3/7 -> 0 | O3: =R3/7 -> 0 | P3: =SUMIFS('Отчет 01.02'!H:H,'Отчет 01.02'!D:D,"Выручка",'Отчет 01.02'!E:E,B3) -> 0 | Q3: =SUMIFS('Отчет 01.02'!H:H,'Отчет 01.02'!D:D,"Возврат выручки",'Отчет 01.02'!E:E,B3) -> 0 | R3: =P3-Q3 -> 0 | S3: =SUMIFS('Отчет 01.02'!P:P,'Отчет 01.02'!C:C,"Продажи",'Отчет 01.02'!E:E,B3) -> 0 | T3: =SUMIFS('Отчет 01.02'!P:P,'Отчет 01.02'!C:C,"Возвраты",'Отчет 01.02'!E:E,B3) -> 0 | U3: =S3+T3 -> 0 | V3: =U3/$U$24 -> #DIV/0! | W3: =R3*H3 -> 0 | X3: =-SUMIFS('Отчет 01.02'!P:P,'Отчет 01.02'!C:C,"Вознаграждение Ozon",'Отчет 01.02'!E:E,B3) -> 0 | Y3: =IF(U3=0,0,X3/U3) -> 0 | Z3: =-SUMIFS('Отчет 01.02'!P:P,'Отчет 01.02'!C:C,"Услуги доставки",'Отчет 01.02'!E:E,B3) -> 0 | AD3: =U3*5.71% -> 0 | AE3: =U3-W3-X3-Z3-AA3-AB3-AC3-AD3 -> 0 | AG3: =IF(R3=0,0,U3/R3) -> 0 | AH3: =H3 -> 142.98 | AI3: =IF(R3=0,0,X3/R3) -> 0 | AJ3: =IF(P3=0,Z3/1,Z3/P3) -> 0 | AK3: =IF(P3=0,0,AA3/P3) -> 0 | AL3: =_xlfn.IFS(R3=0,AE3,R3<0,AE3/-R3,R3>0,AE3/R3) -> 0 | AM3: =IF(AG3=0,0,AL3/AG3) -> 0 | AN3: =IF(AH3=0,0,AL3/AH3) -> 0 | AP3: =AL3*C3 -> 0
A4: 2676784638 | B4: qs черные | H4: 123.09 | I4: =C4*H4 -> 0 | N4: =K4/7 -> 0 | O4: =R4/7 -> 0 | P4: =SUMIFS('Отчет 01.02'!H:H,'Отчет 01.02'!D:D,"Выручка",'Отчет 01.02'!E:E,B4) -> 0 | Q4: =SUMIFS('Отчет 01.02'!H:H,'Отчет 01.02'!D:D,"Возврат выручки",'Отчет 01.02'!E:E,B4) -> 0 | R4: =P4-Q4 -> 0 | S4: =SUMIFS('Отчет 01.02'!P:P,'Отчет 01.02'!C:C,"Продажи",'Отчет 01.02'!E:E,B4) -> 0 | T4: =SUMIFS('Отчет 01.02'!P:P,'Отчет 01.02'!C:C,"Возвраты",'Отчет 01.02'!E:E,B4) -> 0 | U4: =S4+T4 -> 0 | V4: =U4/$U$24 -> #DIV/0! | W4: =R4*H4 -> 0 | X4: =-SUMIFS('Отчет 01.02'!P:P,'Отчет 01.02'!C:C,"Вознаграждение Ozon",'Отчет 01.02'!E:E,B4) -> 0 | Y4: =IF(U4=0,0,X4/U4) -> 0 | Z4: =-SUMIFS('Отчет 01.02'!P:P,'Отчет 01.02'!C:C,"Услуги доставки",'Отчет 01.02'!E:E,B4) -> 0 | AD4: =U4*5.71% -> 0 | AE4: =U4-W4-X4-Z4-AA4-AB4-AC4-AD4 -> 0 | AG4: =IF(R4=0,0,U4/R4) -> 0 | AH4: =H4 -> 123.09 | AI4: =IF(R4=0,0,X4/R4) -> 0 | AJ4: =IF(P4=0,Z4/1,Z4/P4) -> 0 | AK4: =IF(P4=0,0,AA4/P4) -> 0 | AL4: {=_xlfn.IFS(R4=0,AE4,R4<0,AE4/-R4,R4>0,AE4/R4)} -> 0 | AM4: =IF(AG4=0,0,AL4/AG4) -> 0 | AN4: =IF(AH4=0,0,AL4/AH4) -> 0 | AP4: =AL4*C4 -> 0
A5: 2676784504 | B5: qs синие | H5: 123.09 | I5: =C5*H5 -> 0 | N5: =K5/7 -> 0 | O5: =R5/7 -> 0 | P5: =SUMIFS('Отчет 01.02'!H:H,'Отчет 01.02'!D:D,"Выручка",'Отчет 01.02'!E:E,B5) -> 0 | Q5: =SUMIFS('Отчет 01.02'!H:H,'Отчет 01.02'!D:D,"Возврат выручки",'Отчет 01.02'!E:E,B5) -> 0 | R5: =P5-Q5 -> 0 | S5: =SUMIFS('Отчет 01.02'!P:P,'Отчет 01.02'!C:C,"Продажи",'Отчет 01.02'!E:E,B5) -> 0 | T5: =SUMIFS('Отчет 01.02'!P:P,'Отчет 01.02'!C:C,"Возвраты",'Отчет 01.02'!E:E,B5) -> 0 | U5: =S5+T5 -> 0 | V5: =U5/$U$24 -> #DIV/0! | W5: =R5*H5 -> 0 | X5: =-SUMIFS('Отчет 01.02'!P:P,'Отчет 01.02'!C:C,"Вознаграждение Ozon",'Отчет 01.02'!E:E,B5) -> 0 | Y5: =IF(U5=0,0,X5/U5) -> 0 | Z5: =-SUMIFS('Отчет 01.02'!P:P,'Отчет 01.02'!C:C,"Услуги доставки",'Отчет 01.02'!E:E,B5) -> 0 | AD5: =U5*5.71% -> 0 | AE5: =U5-W5-X5-Z5-AA5-AB5-AC5-AD5 -> 0 | AG5: =IF(R5=0,0,U5/R5) -> 0 | AH5: =H5 -> 123.09 | AI5: =IF(R5=0,0,X5/R5) -> 0 | AJ5: =IF(P5=0,Z5/1,Z5/P5) -> 0 | AK5: =IF(P5=0,0,AA5/P5) -> 0 | AL5: {=_xlfn.IFS(R5=0,AE5,R5<0,AE5/-R5,R5>0,AE5/R5)} -> 0 | AM5: =IF(AG5=0,0,AL5/AG5) -> 0 | AN5: =IF(AH5=0,0,AL5/AH5) -> 0 | AP5: =AL5*C5 -> 0
A6: 2676784514 | B6: qs желтые | H6: 123.09 | I6: =C6*H6 -> 0 | N6: =K6/7 -> 0 | O6: =R6/7 -> 0 | P6: =SUMIFS('Отчет 01.02'!H:H,'Отчет 01.02'!D:D,"Выручка",'Отчет 01.02'!E:E,B6) -> 0 | Q6: =SUMIFS('Отчет 01.02'!H:H,'Отчет 01.02'!D:D,"Возврат выручки",'Отчет 01.02'!E:E,B6) -> 0 | R6: =P6-Q6 -> 0 | S6: =SUMIFS('Отчет 01.02'!P:P,'Отчет 01.02'!C:C,"Продажи",'Отчет 01.02'!E:E,B6) -> 0 | T6: =SUMIFS('Отчет 01.02'!P:P,'Отчет 01.02'!C:C,"Возвраты",'Отчет 01.02'!E:E,B6) -> 0 | U6: =S6+T6 -> 0 | V6: =U6/$U$24 -> #DIV/0! | W6: =R6*H6 -> 0 | X6: =-SUMIFS('Отчет 01.02'!P:P,'Отчет 01.02'!C:C,"Вознаграждение Ozon",'Отчет 01.02'!E:E,B6) -> 0 | Y6: =IF(U6=0,0,X6/U6) -> 0 | Z6: =-SUMIFS('Отчет 01.02'!P:P,'Отчет 01.02'!C:C,"Услуги доставки",'Отчет 01.02'!E:E,B6) -> 0 | AD6: =U6*5.71% -> 0 | AE6: =U6-W6-X6-Z6-AA6-AB6-AC6-AD6 -> 0 | AG6: =IF(R6=0,0,U6/R6) -> 0 | AH6: =H6 -> 123.09 | AI6: =IF(R6=0,0,X6/R6) -> 0 | AJ6: =IF(P6=0,Z6/1,Z6/P6) -> 0 | AK6: =IF(P6=0,0,AA6/P6) -> 0 | AL6: {=_xlfn.IFS(R6=0,AE6,R6<0,AE6/-R6,R6>0,AE6/R6)} -> 0 | AM6: =IF(AG6=0,0,AL6/AG6) -> 0 | AN6: =IF(AH6=0,0,AL6/AH6) -> 0 | AP6: =AL6*C6 -> 0
A7: 2676784181 | B7: qs коричневые | H7: 117.24 | I7: =C7*H7 -> 0 | N7: =K7/7 -> 0 | O7: =R7/7 -> 0 | P7: =SUMIFS('Отчет 01.02'!H:H,'Отчет 01.02'!D:D,"Выручка",'Отчет 01.02'!E:E,B7) -> 0 | Q7: =SUMIFS('Отчет 01.02'!H:H,'Отчет 01.02'!D:D,"Возврат выручки",'Отчет 01.02'!E:E,B7) -> 0 | R7: =P7-Q7 -> 0 | S7: =SUMIFS('Отчет 01.02'!P:P,'Отчет 01.02'!C:C,"Продажи",'Отчет 01.02'!E:E,B7) -> 0 | T7: =SUMIFS('Отчет 01.02'!P:P,'Отчет 01.02'!C:C,"Возвраты",'Отчет 01.02'!E:E,B7) -> 0 | U7: =S7+T7 -> 0 | V7: =U7/$U$24 -> #DIV/0! | W7: =R7*H7 -> 0 | X7: =-SUMIFS('Отчет 01.02'!P:P,'Отчет 01.02'!C:C,"Вознаграждение Ozon",'Отчет 01.02'!E:E,B7) -> 0 | Y7: =IF(U7=0,0,X7/U7) -> 0 | Z7: =-SUMIFS('Отчет 01.02'!P:P,'Отчет 01.02'!C:C,"Услуги доставки",'Отчет 01.02'!E:E,B7) -> 0 | AD7: =U7*5.71% -> 0 | AE7: =U7-W7-X7-Z7-AA7-AB7-AC7-AD7 -> 0 | AG7: =IF(R7=0,0,U7/R7) -> 0 | AH7: =H7 -> 117.24 | AI7: =IF(R7=0,0,X7/R7) -> 0 | AJ7: =IF(P7=0,Z7/1,Z7/P7) -> 0 | AK7: =IF(P7=0,0,AA7/P7) -> 0 | AL7: {=_xlfn.IFS(R7=0,AE7,R7<0,AE7/-R7,R7>0,AE7/R7)} -> 0 | AM7: =IF(AG7=0,0,AL7/AG7) -> 0 | AN7: =IF(AH7=0,0,AL7/AH7) -> 0 | AP7: =AL7*C7 -> 0
A8: 2676783005 | B8: MR8854 C2 | H8: 169.89 | I8: =C8*H8 -> 0 | N8: =K8/7 -> 0 | O8: =R8/7 -> 0 | P8: =SUMIFS('Отчет 01.02'!H:H,'Отчет 01.02'!D:D,"Выручка",'Отчет 01.02'!E:E,B8) -> 0 | Q8: =SUMIFS('Отчет 01.02'!H:H,'Отчет 01.02'!D:D,"Возврат выручки",'Отчет 01.02'!E:E,B8) -> 0 | R8: =P8-Q8 -> 0 | S8: =SUMIFS('Отчет 01.02'!P:P,'Отчет 01.02'!C:C,"Продажи",'Отчет 01.02'!E:E,B8) -> 0 | T8: =SUMIFS('Отчет 01.02'!P:P,'Отчет 01.02'!C:C,"Возвраты",'Отчет 01.02'!E:E,B8) -> 0 | U8: =S8+T8 -> 0 | V8: =U8/$U$24 -> #DIV/0! | W8: =R8*H8 -> 0 | X8: =-SUMIFS('Отчет 01.02'!P:P,'Отчет 01.02'!C:C,"Вознаграждение Ozon",'Отчет 01.02'!E:E,B8) -> 0 | Y8: =IF(U8=0,0,X8/U8) -> 0 | Z8: =-SUMIFS('Отчет 01.02'!P:P,'Отчет 01.02'!C:C,"Услуги доставки",'Отчет 01.02'!E:E,B8) -> 0 | AD8: =U8*5.71% -> 0 | AE8: =U8-W8-X8-Z8-AA8-AB8-AC8-AD8 -> 0 | AG8: =IF(R8=0,0,U8/R8) -> 0 | AH8: =H8 -> 169.89 | AI8: =IF(R8=0,0,X8/R8) -> 0 | AJ8: =IF(P8=0,Z8/1,Z8/P8) -> 0 | AK8: =IF(P8=0,0,AA8/P8) -> 0 | AL8: {=_xlfn.IFS(R8=0,AE8,R8<0,AE8/-R8,R8>0,AE8/R8)} -> 0 | AM8: =IF(AG8=0,0,AL8/AG8) -> 0 | AN8: =IF(AH8=0,0,AL8/AH8) -> 0 | AP8: =AL8*C8 -> 0
A9: 3405092860 | B9: th черн | H9: 123 | I9: =C9*H9 -> 0 | N9: =K9/7 -> 0 | O9: =R9/7 -> 0 | P9: =SUMIFS('Отчет 01.02'!H:H,'Отчет 01.02'!D:D,"Выручка",'Отчет 01.02'!E:E,B9) -> 0 | Q9: =SUMIFS('Отчет 01.02'!H:H,'Отчет 01.02'!D:D,"Возврат выручки",'Отчет 01.02'!E:E,B9) -> 0 | R9: =P9-Q9 -> 0 | S9: =SUMIFS('Отчет 01.02'!P:P,'Отчет 01.02'!C:C,"Продажи",'Отчет 01.02'!E:E,B9) -> 0 | T9: =SUMIFS('Отчет 01.02'!P:P,'Отчет 01.02'!C:C,"Возвраты",'Отчет 01.02'!E:E,B9) -> 0 | U9: =S9+T9 -> 0 | V9: =U9/$U$24 -> #DIV/0! | W9: =R9*H9 -> 0 | X9: =-SUMIFS('Отчет 01.02'!P:P,'Отчет 01.02'!C:C,"Вознаграждение Ozon",'Отчет 01.02'!E:E,B9) -> 0 | Y9: =IF(U9=0,0,X9/U9) -> 0 | Z9: =-SUMIFS('Отчет 01.02'!P:P,'Отчет 01.02'!C:C,"Услуги доставки",'Отчет 01.02'!E:E,B9) -> 0 | AD9: =U9*5.71% -> 0 | AE9: =U9-W9-X9-Z9-AA9-AB9-AC9-AD9 -> 0 | AG9: =IF(R9=0,0,U9/R9) -> 0 | AH9: =H9 -> 123 | AI9: =IF(R9=0,0,X9/R9) -> 0 | AJ9: =IF(P9=0,Z9/1,Z9/P9) -> 0 | AK9: =IF(P9=0,0,AA9/P9) -> 0 | AL9: {=_xlfn.IFS(R9=0,AE9,R9<0,AE9/-R9,R9>0,AE9/R9)} -> 0 | AM9: =IF(AG9=0,0,AL9/AG9) -> 0 | AN9: =IF(AH9=0,0,AL9/AH9) -> 0 | AP9: =AL9*C9 -> 0
A10: 3405092836 | B10: th син | H10: 123 | I10: =C10*H10 -> 0 | N10: =K10/7 -> 0 | O10: =R10/7 -> 0 | P10: =SUMIFS('Отчет 01.02'!H:H,'Отчет 01.02'!D:D,"Выручка",'Отчет 01.02'!E:E,B10) -> 0 | Q10: =SUMIFS('Отчет 01.02'!H:H,'Отчет 01.02'!D:D,"Возврат выручки",'Отчет 01.02'!E:E,B10) -> 0 | R10: =P10-Q10 -> 0 | S10: =SUMIFS('Отчет 01.02'!P:P,'Отчет 01.02'!C:C,"Продажи",'Отчет 01.02'!E:E,B10) -> 0 | T10: =SUMIFS('Отчет 01.02'!P:P,'Отчет 01.02'!C:C,"Возвраты",'Отчет 01.02'!E:E,B10) -> 0 | U10: =S10+T10 -> 0 | V10: =U10/$U$24 -> #DIV/0! | W10: =R10*H10 -> 0 | X10: =-SUMIFS('Отчет 01.02'!P:P,'Отчет 01.02'!C:C,"Вознаграждение Ozon",'Отчет 01.02'!E:E,B10) -> 0 | Y10: =IF(U10=0,0,X10/U10) -> 0 | Z10: =-SUMIFS('Отчет 01.02'!P:P,'Отчет 01.02'!C:C,"Услуги доставки",'Отчет 01.02'!E:E,B10) -> 0 | AD10: =U10*5.71% -> 0 | AE10: =U10-W10-X10-Z10-AA10-AB10-AC10-AD10 -> 0 | AG10: =IF(R10=0,0,U10/R10) -> 0 | AH10: =H10 -> 123 | AI10: =IF(R10=0,0,X10/R10) -> 0 | AJ10: =IF(P10=0,Z10/1,Z10/P10) -> 0 | AK10: =IF(P10=0,0,AA10/P10) -> 0 | AL10: {=_xlfn.IFS(R10=0,AE10,R10<0,AE10/-R10,R10>0,AE10/R10)} -> 0 | AM10: =IF(AG10=0,0,AL10/AG10) -> 0 | AN10: =IF(AH10=0,0,AL10/AH10) -> 0 | AP10: =AL10*C10 -> 0
A11: 3064346962 | B11: th желт | H11: 123 | I11: =C11*H11 -> 0 | N11: =K11/7 -> 0 | O11: =R11/7 -> 0 | P11: =SUMIFS('Отчет 01.02'!H:H,'Отчет 01.02'!D:D,"Выручка",'Отчет 01.02'!E:E,B11) -> 0 | Q11: =SUMIFS('Отчет 01.02'!H:H,'Отчет 01.02'!D:D,"Возврат выручки",'Отчет 01.02'!E:E,B11) -> 0 | R11: =P11-Q11 -> 0 | S11: =SUMIFS('Отчет 01.02'!P:P,'Отчет 01.02'!C:C,"Продажи",'Отчет 01.02'!E:E,B11) -> 0 | T11: =SUMIFS('Отчет 01.02'!P:P,'Отчет 01.02'!C:C,"Возвраты",'Отчет 01.02'!E:E,B11) -> 0 | U11: =S11+T11 -> 0 | V11: =U11/$U$24 -> #DIV/0! | W11: =R11*H11 -> 0 | X11: =-SUMIFS('Отчет 01.02'!P:P,'Отчет 01.02'!C:C,"Вознаграждение Ozon",'Отчет 01.02'!E:E,B11) -> 0 | Y11: =IF(U11=0,0,X11/U11) -> 0 | Z11: =-SUMIFS('Отчет 01.02'!P:P,'Отчет 01.02'!C:C,"Услуги доставки",'Отчет 01.02'!E:E,B11) -> 0 | AD11: =U11*5.71% -> 0 | AE11: =U11-W11-X11-Z11-AA11-AB11-AC11-AD11 -> 0 | AG11: =IF(R11=0,0,U11/R11) -> 0 | AH11: =H11 -> 123 | AI11: =IF(R11=0,0,X11/R11) -> 0 | AJ11: =IF(P11=0,Z11/1,Z11/P11) -> 0 | AK11: =IF(P11=0,0,AA11/P11) -> 0 | AL11: {=_xlfn.IFS(R11=0,AE11,R11<0,AE11/-R11,R11>0,AE11/R11)} -> 0 | AM11: =IF(AG11=0,0,AL11/AG11) -> 0 | AN11: =IF(AH11=0,0,AL11/AH11) -> 0 | AP11: =AL11*C11 -> 0
A12: 3405092873 | B12: th коричн | H12: 117 | I12: =C12*H12 -> 0 | N12: =K12/7 -> 0 | O12: =R12/7 -> 0 | P12: =SUMIFS('Отчет 01.02'!H:H,'Отчет 01.02'!D:D,"Выручка",'Отчет 01.02'!E:E,B12) -> 0 | Q12: =SUMIFS('Отчет 01.02'!H:H,'Отчет 01.02'!D:D,"Возврат выручки",'Отчет 01.02'!E:E,B12) -> 0 | R12: =P12-Q12 -> 0 | S12: =SUMIFS('Отчет 01.02'!P:P,'Отчет 01.02'!C:C,"Продажи",'Отчет 01.02'!E:E,B12) -> 0 | T12: =SUMIFS('Отчет 01.02'!P:P,'Отчет 01.02'!C:C,"Возвраты",'Отчет 01.02'!E:E,B12) -> 0 | U12: =S12+T12 -> 0 | V12: =U12/$U$24 -> #DIV/0! | W12: =R12*H12 -> 0 | X12: =-SUMIFS('Отчет 01.02'!P:P,'Отчет 01.02'!C:C,"Вознаграждение Ozon",'Отчет 01.02'!E:E,B12) -> 0 | Y12: =IF(U12=0,0,X12/U12) -> 0 | Z12: =-SUMIFS('Отчет 01.02'!P:P,'Отчет 01.02'!C:C,"Услуги доставки",'Отчет 01.02'!E:E,B12) -> 0 | AD12: =U12*5.71% -> 0 | AE12: =U12-W12-X12-Z12-AA12-AB12-AC12-AD12 -> 0 | AG12: =IF(R12=0,0,U12/R12) -> 0 | AH12: =H12 -> 117 | AI12: =IF(R12=0,0,X12/R12) -> 0 | AJ12: =IF(P12=0,Z12/1,Z12/P12) -> 0 | AK12: =IF(P12=0,0,AA12/P12) -> 0 | AL12: {=_xlfn.IFS(R12=0,AE12,R12<0,AE12/-R12,R12>0,AE12/R12)} -> 0 | AM12: =IF(AG12=0,0,AL12/AG12) -> 0 | AN12: =IF(AH12=0,0,AL12/AH12) -> 0 | AP12: =AL12*C12 -> 0
A13: 3405092993 | B13: flip черный | H13: 123 | I13: =C13*H13 -> 0 | N13: =K13/7 -> 0 | O13: =R13/7 -> 0 | P13: =SUMIFS('Отчет 01.02'!H:H,'Отчет 01.02'!D:D,"Выручка",'Отчет 01.02'!E:E,B13) -> 0 | Q13: =SUMIFS('Отчет 01.02'!H:H,'Отчет 01.02'!D:D,"Возврат выручки",'Отчет 01.02'!E:E,B13) -> 0 | R13: =P13-Q13 -> 0 | S13: =SUMIFS('Отчет 01.02'!P:P,'Отчет 01.02'!C:C,"Продажи",'Отчет 01.02'!E:E,B13) -> 0 | T13: =SUMIFS('Отчет 01.02'!P:P,'Отчет 01.02'!C:C,"Возвраты",'Отчет 01.02'!E:E,B13) -> 0 | U13: =S13+T13 -> 0 | V13: =U13/$U$24 -> #DIV/0! | W13: =R13*H13 -> 0 | X13: =-SUMIFS('Отчет 01.02'!P:P,'Отчет 01.02'!C:C,"Вознаграждение Ozon",'Отчет 01.02'!E:E,B13) -> 0 | Y13: =IF(U13=0,0,X13/U13) -> 0 | Z13: =-SUMIFS('Отчет 01.02'!P:P,'Отчет 01.02'!C:C,"Услуги доставки",'Отчет 01.02'!E:E,B13) -> 0 | AD13: =U13*5.71% -> 0 | AE13: =U13-W13-X13-Z13-AA13-AB13-AC13-AD13 -> 0 | AG13: =IF(R13=0,0,U13/R13) -> 0 | AH13: =H13 -> 123 | AI13: =IF(R13=0,0,X13/R13) -> 0 | AJ13: =IF(P13=0,Z13/1,Z13/P13) -> 0 | AK13: =IF(P13=0,0,AA13/P13) -> 0 | AL13: {=_xlfn.IFS(R13=0,AE13,R13<0,AE13/-R13,R13>0,AE13/R13)} -> 0 | AM13: =IF(AG13=0,0,AL13/AG13) -> 0 | AN13: =IF(AH13=0,0,AL13/AH13) -> 0 | AP13: =AL13*C13 -> 0
A14: 3405092868 | B14: flip синий | H14: 123 | I14: =C14*H14 -> 0 | N14: =K14/7 -> 0 | O14: =R14/7 -> 0 | P14: =SUMIFS('Отчет 01.02'!H:H,'Отчет 01.02'!D:D,"Выручка",'Отчет 01.02'!E:E,B14) -> 0 | Q14: =SUMIFS('Отчет 01.02'!H:H,'Отчет 01.02'!D:D,"Возврат выручки",'Отчет 01.02'!E:E,B14) -> 0 | R14: =P14-Q14 -> 0 | S14: =SUMIFS('Отчет 01.02'!P:P,'Отчет 01.02'!C:C,"Продажи",'Отчет 01.02'!E:E,B14) -> 0 | T14: =SUMIFS('Отчет 01.02'!P:P,'Отчет 01.02'!C:C,"Возвраты",'Отчет 01.02'!E:E,B14) -> 0 | U14: =S14+T14 -> 0 | V14: =U14/$U$24 -> #DIV/0! | W14: =R14*H14 -> 0 | X14: =-SUMIFS('Отчет 01.02'!P:P,'Отчет 01.02'!C:C,"Вознаграждение Ozon",'Отчет 01.02'!E:E,B14) -> 0 | Y14: =IF(U14=0,0,X14/U14) -> 0 | Z14: =-SUMIFS('Отчет 01.02'!P:P,'Отчет 01.02'!C:C,"Услуги доставки",'Отчет 01.02'!E:E,B14) -> 0 | AD14: =U14*5.71% -> 0 | AE14: =U14-W14-X14-Z14-AA14-AB14-AC14-AD14 -> 0 | AG14: =IF(R14=0,0,U14/R14) -> 0 | AH14: =H14 -> 123 | AI14: =IF(R14=0,0,X14/R14) -> 0 | AJ14: =IF(P14=0,Z14/1,Z14/P14) -> 0 | AK14: =IF(P14=0,0,AA14/P14) -> 0 | AL14: {=_xlfn.IFS(R14=0,AE14,R14<0,AE14/-R14,R14>0,AE14/R14)} -> 0 | AM14: =IF(AG14=0,0,AL14/AG14) -> 0 | AN14: =IF(AH14=0,0,AL14/AH14) -> 0 | AP14: =AL14*C14 -> 0
A15: 3064346642 | B15: flip жел | H15: 123 | I15: =C15*H15 -> 0 | N15: =K15/7 -> 0 | O15: =R15/7 -> 0 | P15: =SUMIFS('Отчет 01.02'!H:H,'Отчет 01.02'!D:D,"Выручка",'Отчет 01.02'!E:E,B15) -> 0 | Q15: =SUMIFS('Отчет 01.02'!H:H,'Отчет 01.02'!D:D,"Возврат выручки",'Отчет 01.02'!E:E,B15) -> 0 | R15: =P15-Q15 -> 0 | S15: =SUMIFS('Отчет 01.02'!P:P,'Отчет 01.02'!C:C,"Продажи",'Отчет 01.02'!E:E,B15) -> 0 | T15: =SUMIFS('Отчет 01.02'!P:P,'Отчет 01.02'!C:C,"Возвраты",'Отчет 01.02'!E:E,B15) -> 0 | U15: =S15+T15 -> 0 | V15: =U15/$U$24 -> #DIV/0! | W15: =R15*H15 -> 0 | X15: =-SUMIFS('Отчет 01.02'!P:P,'Отчет 01.02'!C:C,"Вознаграждение Ozon",'Отчет 01.02'!E:E,B15) -> 0 | Y15: =IF(U15=0,0,X15/U15) -> 0 | Z15: =-SUMIFS('Отчет 01.02'!P:P,'Отчет 01.02'!C:C,"Услуги доставки",'Отчет 01.02'!E:E,B15) -> 0 | AD15: =U15*5.71% -> 0 | AE15: =U15-W15-X15-Z15-AA15-AB15-AC15-AD15 -> 0 | AG15: =IF(R15=0,0,U15/R15) -> 0 | AH15: =H15 -> 123 | AI15: =IF(R15=0,0,X15/R15) -> 0 | AJ15: =IF(P15=0,Z15/1,Z15/P15) -> 0 | AK15: =IF(P15=0,0,AA15/P15) -> 0 | AL15: {=_xlfn.IFS(R15=0,AE15,R15<0,AE15/-R15,R15>0,AE15/R15)} -> 0 | AM15: =IF(AG15=0,0,AL15/AG15) -> 0 | AN15: =IF(AH15=0,0,AL15/AH15) -> 0 | AP15: =AL15*C15 -> 0
A16: 3405092287 | B16: flip коричневый | H16: 117 | I16: =C16*H16 -> 0 | N16: =K16/7 -> 0 | O16: =R16/7 -> 0 | P16: =SUMIFS('Отчет 01.02'!H:H,'Отчет 01.02'!D:D,"Выручка",'Отчет 01.02'!E:E,B16) -> 0 | Q16: =SUMIFS('Отчет 01.02'!H:H,'Отчет 01.02'!D:D,"Возврат выручки",'Отчет 01.02'!E:E,B16) -> 0 | R16: =P16-Q16 -> 0 | S16: =SUMIFS('Отчет 01.02'!P:P,'Отчет 01.02'!C:C,"Продажи",'Отчет 01.02'!E:E,B16) -> 0 | T16: =SUMIFS('Отчет 01.02'!P:P,'Отчет 01.02'!C:C,"Возвраты",'Отчет 01.02'!E:E,B16) -> 0 | U16: =S16+T16 -> 0 | V16: =U16/$U$24 -> #DIV/0! | W16: =R16*H16 -> 0 | X16: =-SUMIFS('Отчет 01.02'!P:P,'Отчет 01.02'!C:C,"Вознаграждение Ozon",'Отчет 01.02'!E:E,B16) -> 0 | Y16: =IF(U16=0,0,X16/U16) -> 0 | Z16: =-SUMIFS('Отчет 01.02'!P:P,'Отчет 01.02'!C:C,"Услуги доставки",'Отчет 01.02'!E:E,B16) -> 0 | AD16: =U16*5.71% -> 0 | AE16: =U16-W16-X16-Z16-AA16-AB16-AC16-AD16 -> 0 | AG16: =IF(R16=0,0,U16/R16) -> 0 | AH16: =H16 -> 117 | AI16: =IF(R16=0,0,X16/R16) -> 0 | AJ16: =IF(P16=0,Z16/1,Z16/P16) -> 0 | AK16: =IF(P16=0,0,AA16/P16) -> 0 | AL16: {=_xlfn.IFS(R16=0,AE16,R16<0,AE16/-R16,R16>0,AE16/R16)} -> 0 | AM16: =IF(AG16=0,0,AL16/AG16) -> 0 | AN16: =IF(AH16=0,0,AL16/AH16) -> 0 | AP16: =AL16*C16 -> 0
AG17: =AVERAGEIF(AG3:AG15,"<>0",AG3:AG15) -> #DIV/0! | AH17: =AVERAGEIF(AH3:AH15,"<>0",AH3:AH15) -> 127.26 | AI17: =AVERAGEIF(AI3:AI15,"<>0",AI3:AI15) -> #DIV/0! | AJ17: =AVERAGEIF(AJ3:AJ15,"<>0",AJ3:AJ15) -> #DIV/0! | AK17: =AVERAGEIF(AK3:AK15,"<>0",AK3:AK15) -> #DIV/0! | AL17: =AVERAGEIF(AL3:AL15,"<>0",AL3:AL15) -> #DIV/0! | AM17: =AVERAGEIF(AM3:AM15,"<>0",AM3:AM15) -> #DIV/0! | AN17: =AVERAGEIF(AN3:AN15,"<>0",AN3:AN15) -> #DIV/0!
A18: Итого очки | C18: =SUM(C3:C16) -> 0 | E18: 108496 | F18: 597 | G18: 295 | I18: =SUM(I3:I16) -> 0 | K18: =SUM(K3:K16) -> 0 | P18: =SUM(P3:P16) -> 0 | Q18: =SUM(Q3:Q16) -> 0 | R18: =SUM(R3:R16) -> 0 | S18: =SUM(S3:S16) -> 0 | T18: =SUM(T3:T16) -> 0 | U18: =SUM(U3:U16) -> 0 | V18: =SUM(V3:V16) -> #DIV/0! | W18: =SUM(W3:W16) -> 0 | X18: =SUM(X3:X16) -> 0 | Y18: =IF(U18=0,0,X18/U18) -> 0 | Z18: =SUM(Z3:Z16) -> 0 | AA18: =IFERROR(P18*AA24/P24,0) -> 0 | AB18: =SUM(AB3:AB16) -> 0 | AC18: =SUM(AC3:AC16) -> 0 | AD18: =SUM(AD3:AD16) -> 0 | AE18: =SUM(AE3:AE16) -> 0 | AP18: =SUM(AP3:AP16) -> 0 | AZ18: 18592777
AA19: =SUM(AA3:AA15) -> 0
AG21: =AVERAGEIF(AG20:AG20,"<>0",AG20:AG20) -> #DIV/0! | AH21: =AVERAGEIF(AH20:AH20,"<>0",AH20:AH20) -> #DIV/0! | AI21: =AVERAGEIF(AI20:AI20,"<>0",AI20:AI20) -> #DIV/0! | AJ21: =AVERAGEIF(AJ20:AJ20,"<>0",AJ20:AJ20) -> #DIV/0! | AK21: =AVERAGEIF(AK20:AK20,"<>0",AK20:AK20) -> #DIV/0! | AL21: =AVERAGEIF(AL20:AL20,"<>0",AL20:AL20) -> #DIV/0! | AM21: =AVERAGEIF(AM20:AM20,"<>0",AM20:AM20) -> #DIV/0! | AN21: =AVERAGEIF(AN20:AN20,"<>0",AN20:AN20) -> #DIV/0!
C22: =SUM(C20:C20) -> 0 | I22: =SUM(I20:I20) -> 0 | K22: =SUM(K20:K20) -> 0 | P22: =SUM(P20:P20) -> 0 | Q22: =SUM(Q20:Q20) -> 0 | R22: =SUM(R20:R20) -> 0 | S22: =SUM(S20:S20) -> 0 | T22: =SUM(T20:T20) -> 0 | U22: =SUM(U20:U20) -> 0 | V22: =SUM(V20:V20) -> 0 | W22: =SUM(W20:W20) -> 0 | X22: =SUM(X20:X20) -> 0 | Y22: =IF(U22=0,0,X22/U22) -> 0 | Z22: =SUM(Z20:Z20) -> 0 | AA22: =IFERROR(P22*AA24/P24,0) -> 0 | AB22: =SUM(AB20:AB20) -> 0 | AC22: =SUM(AC20:AC20) -> 0 | AD22: =SUM(AD20:AD20) -> 0 | AE22: =SUM(AE20:AE20) -> 0 | AP22: =SUM(AP20:AP20) -> 0
AA23: =SUM(AA20:AA20) -> 0
A24: ИТОГО | C24: =C18+C22 -> 0 | D24: =SUM(D3:D20) -> 0 | E24: =SUM(E3:E20) -> 108496 | F24: =SUM(F3:F20) -> 597 | G24: =SUM(G3:G20) -> 295 | I24: =I18+I22 -> 0 | J24: =J18+J22 -> 0 | K24: =K18+K22 -> 0 | P24: =P18+P22 -> 0 | Q24: =Q18+Q22 -> 0 | R24: =R18-R22 -> 0 | S24: =S18+S22 -> 0 | T24: =T18+T22 -> 0 | U24: =U18+U22 -> 0 | V24: =V18+V22 -> #DIV/0! | W24: =W18+W22 -> 0 | X24: =X18+X22 -> 0 | Y24: =X24/U24 -> #DIV/0! | Z24: =Z18+Z22 -> 0 | AC24: =SUM(AC3:AC20) -> 0 | AD24: =AD18+AD22 -> 0 | AE24: =AE18+AE22 -> 0 | AK24: =AA25/P24 -> #DIV/0! | AP24: =SUM(AP3:AP20) -> 0
AA25: =AA18+AA22 -> 0
AA26: =AA19+AA23 -> 0
I29: Себестоимость остатков | K29: Прибыль с остатков | L29: Рентабельность товарных остатков
H31: до 60 дн | I31: =SUMIF(J3:J20,"<60",I3:I20) -> 0 | J31: =I31/I24 -> #DIV/0! | K31: =SUMIF(J3:J20,"<60",AP3:AP20) -> 0 | L31: =K31/I31 -> #DIV/0!
H32: 60-120 дн | I32: =I24-I33-I31 -> 0 | J32: =I32/I24 -> #DIV/0! | K32: =AP24-K31-K33 -> 0 | L32: =K32/I32 -> #DIV/0!
H33: > 120 дн | I33: =SUMIF(J3:J20,">120",I3:I20) -> 0 | J33: =I33/I24 -> #DIV/0! | K33: =SUMIF(J3:J20,">120",AP3:AP20) -> 0 | L33: =K33/I33 -> #DIV/0!
H35: Если товар на сайте менее 30 дней - оборачиваемость 0

Sheet ЯНВАРЬ
B1: 01-31.01 | AG1: на 1 единицу проданного товара
B2: Артикул поставщика | C2: Остаток на 01.02 | D2: В пути до клиента | E2: В пути от клиента | F2: Итого по складам ВБ | G2: Остаток на нашем складе на 02.09 | H2: Себетоимость на 1 ед на 29.09.25 | I2: Себестоимость остатков | J2: Оборачиваемость, дн | K2: Заказы, шт 31 день | L2: Средняя цена, руб (столбец 32, AG) | M2: % выкупа за 7 дней (столбец 23, X) | N2: Скорость заказов | O2: Скорость продаж | P2: Кол-во ПРОДАЖИ | Q2: Кол-во ВОЗВРАТЫ | R2: Кол-во ПРОДАЖИ-ВОЗВРАТЫ | S2: Выручка ПРОДАЖИ | T2: Выручка ВОЗВРАТЫ | U2: Выручка с учетом согласованной скидки ПРОДАЖИ - ВОЗВРАТЫ | V2: Доля выручки, % от общего объема | W2: Себестоимость продаж | X2: Комиссия, руб | Y2: Комиссия, % | Z2: Логистика | AA2: Реклама | AB2: Хранение | AC2: Штрафы | AD2: Налог 1%+ НДС 5% | AE2: Прибыль | AG2: Выручка на 1 ед (средняя цена продажи со скидкой) | AH2: Себестоимость на 1 ед | AI2: Комиссия на 1 ед | AJ2: Логистика на 1 ед | AK2: Реклама на 1 ед | AL2: Прибыль на 1 ед | AM2: Маржинальность, % | AN2: Рентабельность, % | AP2: Прибыль с остатков
A3: 2676784153 | B3: черные с железкой классика | C3: ='Юнит 26-31.01'!C3 -> 0 | H3: 142.98 | I3: =C3*H3 -> 0 | K3: ='Юнит 01-04.01'!K3+'Юнит 05-11.01'!K3+'Юнит 12-18.01'!K3+'Юнит 19-25.01'!K3+'Юнит 26-31.01'!K3 -> 17 | N3: =K3/31 -> 0.5483871 | O3: =R3/31 -> 0.4516129 | P3: ='Юнит 01-04.01'!P3+'Юнит 05-11.01'!P3+'Юнит 12-18.01'!P3+'Юнит 19-25.01'!P3+'Юнит 26-31.01'!P3 -> 14 | Q3: ='Юнит 01-04.01'!Q3+'Юнит 05-11.01'!Q3+'Юнит 12-18.01'!Q3+'Юнит 19-25.01'!Q3+'Юнит 26-31.01'!Q3 -> 0 | R3: =P3-Q3 -> 14 | S3: ='Юнит 01-04.01'!S3+'Юнит 05-11.01'!S3+'Юнит 12-18.01'!S3+'Юнит 19-25.01'!S3+'Юнит 26-31.01'!S3 -> 22392 | T3: ='Юнит 01-04.01'!T3+'Юнит 05-11.01'!T3+'Юнит 12-18.01'!T3+'Юнит 19-25.01'!T3+'Юнит 26-31.01'!T3 -> 0 | U3: =S3+T3 -> 22392 | V3: =U3/$U$24 -> 0.031360598 | W3: =R3*H3 -> 2001.72 | X3: ='Юнит 01-04.01'!X3+'Юнит 05-11.01'!X3+'Юнит 12-18.01'!X3+'Юнит 19-25.01'!X3+'Юнит 26-31.01'!X3 -> 9628.56 | Y3: =IF(U3=0,0,X3/U3) -> 0.43 | Z3: ='Юнит 01-04.01'!Z3+'Юнит 05-11.01'!Z3+'Юнит 12-18.01'!Z3+'Юнит 19-25.01'!Z3+'Юнит 26-31.01'!Z3 -> 2332.29 | AA3: ='Юнит 01-04.01'!AA3+'Юнит 05-11.01'!AA3+'Юнит 12-18.01'!AA3+'Юнит 19-25.01'!AA3+'Юнит 26-31.01'!AA3 -> 1868.6901 | AD3: =U3*5.71% -> 1278.5832 | AE3: =U3-W3-X3-Z3-AA3-AB3-AC3-AD3 -> 5282.1567 | AG3: =IF(R3=0,0,U3/R3) -> 1599.4286 | AH3: =H3 -> 142.98 | AI3: =IF(R3=0,0,X3/R3) -> 687.75429 | AJ3: =IF(P3=0,Z3/1,Z3/P3) -> 166.59214 | AK3: =IF(P3=0,0,AA3/P3) -> 133.47786 | AL3: =_xlfn.IFS(R3=0,AE3,R3<0,AE3/-R3,R3>0,AE3/R3) -> 377.29691 | AM3: =IF(AG3=0,0,AL3/AG3) -> 0.23589482 | AN3: =IF(AH3=0,0,AL3/AH3) -> 2.638809 | AP3: =AL3*C3 -> 0
A4: 2676784638 | B4: qs черные | C4: ='Юнит 26-31.01'!C4 -> 0 | H4: 123.09 | I4: =C4*H4 -> 0 | K4: ='Юнит 01-04.01'!K4+'Юнит 05-11.01'!K4+'Юнит 12-18.01'!K4+'Юнит 19-25.01'!K4+'Юнит 26-31.01'!K4 -> 23 | N4: =K4/31 -> 0.74193548 | O4: =R4/31 -> 0.48387097 | P4: ='Юнит 01-04.01'!P4+'Юнит 05-11.01'!P4+'Юнит 12-18.01'!P4+'Юнит 19-25.01'!P4+'Юнит 26-31.01'!P4 -> 15 | Q4: ='Юнит 01-04.01'!Q4+'Юнит 05-11.01'!Q4+'Юнит 12-18.01'!Q4+'Юнит 19-25.01'!Q4+'Юнит 26-31.01'!Q4 -> 0 | R4: =P4-Q4 -> 15 | S4: ='Юнит 01-04.01'!S4+'Юнит 05-11.01'!S4+'Юнит 12-18.01'!S4+'Юнит 19-25.01'!S4+'Юнит 26-31.01'!S4 -> 25750 | T4: ='Юнит 01-04.01'!T4+'Юнит 05-11.01'!T4+'Юнит 12-18.01'!T4+'Юнит 19-25.01'!T4+'Юнит 26-31.01'!T4 -> 0 | U4: =S4+T4 -> 25750 | V4: =U4/$U$24 -> 0.036063567 | W4: =R4*H4 -> 1846.35 | X4: ='Юнит 01-04.01'!X4+'Юнит 05-11.01'!X4+'Юнит 12-18.01'!X4+'Юнит 19-25.01'!X4+'Юнит 26-31.01'!X4 -> 11072.5 | Y4: =IF(U4=0,0,X4/U4) -> 0.43 | Z4: ='Юнит 01-04.01'!Z4+'Юнит 05-11.01'!Z4+'Юнит 12-18.01'!Z4+'Юнит 19-25.01'!Z4+'Юнит 26-31.01'!Z4 -> 2132.85 | AA4: ='Юнит 01-04.01'!AA4+'Юнит 05-11.01'!AA4+'Юнит 12-18.01'!AA4+'Юнит 19-25.01'!AA4+'Юнит 26-31.01'!AA4 -> 2610.2683 | AD4: =U4*5.71% -> 1470.325 | AE4: =U4-W4-X4-Z4-AA4-AB4-AC4-AD4 -> 6617.7067 | AG4: =IF(R4=0,0,U4/R4) -> 1716.6667 | AH4: =H4 -> 123.09 | AI4: =IF(R4=0,0,X4/R4) -> 738.16667 | AJ4: =IF(P4=0,Z4/1,Z4/P4) -> 142.19 | AK4: =IF(P4=0,0,AA4/P4) -> 174.01789 | AL4: {=_xlfn.IFS(R4=0,AE4,R4<0,AE4/-R4,R4>0,AE4/R4)} -> 441.18045 | AM4: =IF(AG4=0,0,AL4/AG4) -> 0.25699832 | AN4: =IF(AH4=0,0,AL4/AH4) -> 3.5842103 | AP4: =AL4*C4 -> 0
A5: 2676784504 | B5: qs синие | C5: ='Юнит 26-31.01'!C5 -> 0 | H5: 123.09 | I5: =C5*H5 -> 0 | K5: ='Юнит 01-04.01'!K5+'Юнит 05-11.01'!K5+'Юнит 12-18.01'!K5+'Юнит 19-25.01'!K5+'Юнит 26-31.01'!K5 -> 11 | N5: =K5/31 -> 0.35483871 | O5: =R5/31 -> 0.29032258 | P5: ='Юнит 01-04.01'!P5+'Юнит 05-11.01'!P5+'Юнит 12-18.01'!P5+'Юнит 19-25.01'!P5+'Юнит 26-31.01'!P5 -> 9 | Q5: ='Юнит 01-04.01'!Q5+'Юнит 05-11.01'!Q5+'Юнит 12-18.01'!Q5+'Юнит 19-25.01'!Q5+'Юнит 26-31.01'!Q5 -> 0 | R5: =P5-Q5 -> 9 | S5: ='Юнит 01-04.01'!S5+'Юнит 05-11.01'!S5+'Юнит 12-18.01'!S5+'Юнит 19-25.01'!S5+'Юнит 26-31.01'!S5 -> 15350 | T5: ='Юнит 01-04.01'!T5+'Юнит 05-11.01'!T5+'Юнит 12-18.01'!T5+'Юнит 19-25.01'!T5+'Юнит 26-31.01'!T5 -> 0 | U5: =S5+T5 -> 15350 | V5: =U5/$U$24 -> 0.021498088 | W5: =R5*H5 -> 1107.81 | X5: ='Юнит 01-04.01'!X5+'Юнит 05-11.01'!X5+'Юнит 12-18.01'!X5+'Юнит 19-25.01'!X5+'Юнит 26-31.01'!X5 -> 6600.5 | Y5: =IF(U5=0,0,X5/U5) -> 0.43 | Z5: ='Юнит 01-04.01'!Z5+'Юнит 05-11.01'!Z5+'Юнит 12-18.01'!Z5+'Юнит 19-25.01'!Z5+'Юнит 26-31.01'!Z5 -> 1336.49 | AA5: ='Юнит 01-04.01'!AA5+'Юнит 05-11.01'!AA5+'Юнит 12-18.01'!AA5+'Юнит 19-25.01'!AA5+'Юнит 26-31.01'!AA5 -> 1523.2567 | AD5: =U5*5.71% -> 876.485 | AE5: =U5-W5-X5-Z5-AA5-AB5-AC5-AD5 -> 3905.4583 | AG5: =IF(R5=0,0,U5/R5) -> 1705.5556 | AH5: =H5 -> 123.09 | AI5: =IF(R5=0,0,X5/R5) -> 733.38889 | AJ5: =IF(P5=0,Z5/1,Z5/P5) -> 148.49889 | AK5: =IF(P5=0,0,AA5/P5) -> 169.25075 | AL5: {=_xlfn.IFS(R5=0,AE5,R5<0,AE5/-R5,R5>0,AE5/R5)} -> 433.93981 | AM5: =IF(AG5=0,0,AL5/AG5) -> 0.25442725 | AN5: =IF(AH5=0,0,AL5/AH5) -> 3.5253864 | AP5: =AL5*C5 -> 0
A6: 2676784514 | B6: qs желтые | C6: ='Юнит 26-31.01'!C6 -> 0 | H6: 123.09 | I6: =C6*H6 -> 0 | K6: ='Юнит 01-04.01'!K6+'Юнит 05-11.01'!K6+'Юнит 12-18.01'!K6+'Юнит 19-25.01'!K6+'Юнит 26-31.01'!K6 -> 96 | N6: =K6/31 -> 3.0967742 | O6: =R6/31 -> 2.4516129 | P6: ='Юнит 01-04.01'!P6+'Юнит 05-11.01'!P6+'Юнит 12-18.01'!P6+'Юнит 19-25.01'!P6+'Юнит 26-31.01'!P6 -> 80 | Q6: ='Юнит 01-04.01'!Q6+'Юнит 05-11.01'!Q6+'Юнит 12-18.01'!Q6+'Юнит 19-25.01'!Q6+'Юнит 26-31.01'!Q6 -> 4 | R6: =P6-Q6 -> 76 | S6: ='Юнит 01-04.01'!S6+'Юнит 05-11.01'!S6+'Юнит 12-18.01'!S6+'Юнит 19-25.01'!S6+'Юнит 26-31.01'!S6 -> 132950 | T6: ='Юнит 01-04.01'!T6+'Юнит 05-11.01'!T6+'Юнит 12-18.01'!T6+'Юнит 19-25.01'!T6+'Юнит 26-31.01'!T6 -> -6400 | U6: =S6+T6 -> 126550 | V6: =U6/$U$24 -> 0.17723668 | W6: =R6*H6 -> 9354.84 | X6: ='Юнит 01-04.01'!X6+'Юнит 05-11.01'!X6+'Юнит 12-18.01'!X6+'Юнит 19-25.01'!X6+'Юнит 26-31.01'!X6 -> 54416.5 | Y6: =IF(U6=0,0,X6/U6) -> 0.43 | Z6: ='Юнит 01-04.01'!Z6+'Юнит 05-11.01'!Z6+'Юнит 12-18.01'!Z6+'Юнит 19-25.01'!Z6+'Юнит 26-31.01'!Z6 -> 12454.16 | AA6: ='Юнит 01-04.01'!AA6+'Юнит 05-11.01'!AA6+'Юнит 12-18.01'!AA6+'Юнит 19-25.01'!AA6+'Юнит 26-31.01'!AA6 -> 29335.859 | AD6: =U6*5.71% -> 7226.005 | AE6: =U6-W6-X6-Z6-AA6-AB6-AC6-AD6 -> 13762.636 | AG6: =IF(R6=0,0,U6/R6) -> 1665.1316 | AH6: =H6 -> 123.09 | AI6: =IF(R6=0,0,X6/R6) -> 716.00658 | AJ6: =IF(P6=0,Z6/1,Z6/P6) -> 155.677 | AK6: =IF(P6=0,0,AA6/P6) -> 366.69824 | AL6: {=_xlfn.IFS(R6=0,AE6,R6<0,AE6/-R6,R6>0,AE6/R6)} -> 181.08732 | AM6: =IF(AG6=0,0,AL6/AG6) -> 0.10875256 | AN6: =IF(AH6=0,0,AL6/AH6) -> 1.4711781 | AP6: =AL6*C6 -> 0
A7: 2676784181 | B7: qs коричневые | C7: ='Юнит 26-31.01'!C7 -> 0 | H7: 117.24 | I7: =C7*H7 -> 0 | K7: ='Юнит 01-04.01'!K7+'Юнит 05-11.01'!K7+'Юнит 12-18.01'!K7+'Юнит 19-25.01'!K7+'Юнит 26-31.01'!K7 -> 57 | N7: =K7/31 -> 1.8387097 | O7: =R7/31 -> 0.96774194 | P7: ='Юнит 01-04.01'!P7+'Юнит 05-11.01'!P7+'Юнит 12-18.01'!P7+'Юнит 19-25.01'!P7+'Юнит 26-31.01'!P7 -> 30 | Q7: ='Юнит 01-04.01'!Q7+'Юнит 05-11.01'!Q7+'Юнит 12-18.01'!Q7+'Юнит 19-25.01'!Q7+'Юнит 26-31.01'!Q7 -> 0 | R7: =P7-Q7 -> 30 | S7: ='Юнит 01-04.01'!S7+'Юнит 05-11.01'!S7+'Юнит 12-18.01'!S7+'Юнит 19-25.01'!S7+'Юнит 26-31.01'!S7 -> 50400 | T7: ='Юнит 01-04.01'!T7+'Юнит 05-11.01'!T7+'Юнит 12-18.01'!T7+'Юнит 19-25.01'!T7+'Юнит 26-31.01'!T7 -> 0 | U7: =S7+T7 -> 50400 | V7: =U7/$U$24 -> 0.070586555 | W7: =R7*H7 -> 3517.2 | X7: ='Юнит 01-04.01'!X7+'Юнит 05-11.01'!X7+'Юнит 12-18.01'!X7+'Юнит 19-25.01'!X7+'Юнит 26-31.01'!X7 -> 21672 | Y7: =IF(U7=0,0,X7/U7) -> 0.43 | Z7: ='Юнит 01-04.01'!Z7+'Юнит 05-11.01'!Z7+'Юнит 12-18.01'!Z7+'Юнит 19-25.01'!Z7+'Юнит 26-31.01'!Z7 -> 4720.84 | AA7: ='Юнит 01-04.01'!AA7+'Юнит 05-11.01'!AA7+'Юнит 12-18.01'!AA7+'Юнит 19-25.01'!AA7+'Юнит 26-31.01'!AA7 -> 11121.299 | AD7: =U7*5.71% -> 2877.84 | AE7: =U7-W7-X7-Z7-AA7-AB7-AC7-AD7 -> 6490.8212 | AG7: =IF(R7=0,0,U7/R7) -> 1680 | AH7: =H7 -> 117.24 | AI7: =IF(R7=0,0,X7/R7) -> 722.4 | AJ7: =IF(P7=0,Z7/1,Z7/P7) -> 157.36133 | AK7: =IF(P7=0,0,AA7/P7) -> 370.70996 | AL7: {=_xlfn.IFS(R7=0,AE7,R7<0,AE7/-R7,R7>0,AE7/R7)} -> 216.36071 | AM7: =IF(AG7=0,0,AL7/AG7) -> 0.12878614 | AN7: =IF(AH7=0,0,AL7/AH7) -> 1.8454513 | AP7: =AL7*C7 -> 0
A8: 2676783005 | B8: MR8854 C2 | C8: ='Юнит 26-31.01'!C8 -> 0 | H8: 169.89 | I8: =C8*H8 -> 0 | K8: ='Юнит 01-04.01'!K8+'Юнит 05-11.01'!K8+'Юнит 12-18.01'!K8+'Юнит 19-25.01'!K8+'Юнит 26-31.01'!K8 -> 33 | N8: =K8/31 -> 1.0645161 | O8: =R8/31 -> 0.70967742 | P8: ='Юнит 01-04.01'!P8+'Юнит 05-11.01'!P8+'Юнит 12-18.01'!P8+'Юнит 19-25.01'!P8+'Юнит 26-31.01'!P8 -> 23 | Q8: ='Юнит 01-04.01'!Q8+'Юнит 05-11.01'!Q8+'Юнит 12-18.01'!Q8+'Юнит 19-25.01'!Q8+'Юнит 26-31.01'!Q8 -> 1 | R8: =P8-Q8 -> 22 | S8: ='Юнит 01-04.01'!S8+'Юнит 05-11.01'!S8+'Юнит 12-18.01'!S8+'Юнит 19-25.01'!S8+'Юнит 26-31.01'!S8 -> 32030 | T8: ='Юнит 01-04.01'!T8+'Юнит 05-11.01'!T8+'Юнит 12-18.01'!T8+'Юнит 19-25.01'!T8+'Юнит 26-31.01'!T8 -> -1202 | U8: =S8+T8 -> 30828 | V8: =U8/$U$24 -> 0.043175443 | W8: =R8*H8 -> 3737.58 | X8: ='Юнит 01-04.01'!X8+'Юнит 05-11.01'!X8+'Юнит 12-18.01'!X8+'Юнит 19-25.01'!X8+'Юнит 26-31.01'!X8 -> 13256.04 | Y8: =IF(U8=0,0,X8/U8) -> 0.43 | Z8: ='Юнит 01-04.01'!Z8+'Юнит 05-11.01'!Z8+'Юнит 12-18.01'!Z8+'Юнит 19-25.01'!Z8+'Юнит 26-31.01'!Z8 -> 3351.83 | AA8: ='Юнит 01-04.01'!AA8+'Юнит 05-11.01'!AA8+'Юнит 12-18.01'!AA8+'Юнит 19-25.01'!AA8+'Юнит 26-31.01'!AA8 -> 8254.5318 | AD8: =U8*5.71% -> 1760.2788 | AE8: =U8-W8-X8-Z8-AA8-AB8-AC8-AD8 -> 467.73943 | AG8: =IF(R8=0,0,U8/R8) -> 1401.2727 | AH8: =H8 -> 169.89 | AI8: =IF(R8=0,0,X8/R8) -> 602.54727 | AJ8: =IF(P8=0,Z8/1,Z8/P8) -> 145.73174 | AK8: =IF(P8=0,0,AA8/P8) -> 358.89269 | AL8: {=_xlfn.IFS(R8=0,AE8,R8<0,AE8/-R8,R8>0,AE8/R8)} -> 21.260883 | AM8: =IF(AG8=0,0,AL8/AG8) -> 0.015172552 | AN8: =IF(AH8=0,0,AL8/AH8) -> 0.125145 | AP8: =AL8*C8 -> 0
A9: 3405092860 | B9: th черн | C9: ='Юнит 26-31.01'!C9 -> 0 | H9: 123 | I9: =C9*H9 -> 0 | K9: ='Юнит 01-04.01'!K9+'Юнит 05-11.01'!K9+'Юнит 12-18.01'!K9+'Юнит 19-25.01'!K9+'Юнит 26-31.01'!K9 -> 0 | N9: =K9/31 -> 0 | O9: =R9/31 -> 0 | P9: ='Юнит 01-04.01'!P9+'Юнит 05-11.01'!P9+'Юнит 12-18.01'!P9+'Юнит 19-25.01'!P9+'Юнит 26-31.01'!P9 -> 0 | Q9: ='Юнит 01-04.01'!Q9+'Юнит 05-11.01'!Q9+'Юнит 12-18.01'!Q9+'Юнит 19-25.01'!Q9+'Юнит 26-31.01'!Q9 -> 0 | R9: =P9-Q9 -> 0 | S9: ='Юнит 01-04.01'!S9+'Юнит 05-11.01'!S9+'Юнит 12-18.01'!S9+'Юнит 19-25.01'!S9+'Юнит 26-31.01'!S9 -> 0 | T9: ='Юнит 01-04.01'!T9+'Юнит 05-11.01'!T9+'Юнит 12-18.01'!T9+'Юнит 19-25.01'!T9+'Юнит 26-31.01'!T9 -> 0 | U9: =S9+T9 -> 0 | V9: =U9/$U$24 -> 0 | W9: =R9*H9 -> 0 | X9: ='Юнит 01-04.01'!X9+'Юнит 05-11.01'!X9+'Юнит 12-18.01'!X9+'Юнит 19-25.01'!X9+'Юнит 26-31.01'!X9 -> 0 | Y9: =IF(U9=0,0,X9/U9) -> 0 | Z9: ='Юнит 01-04.01'!Z9+'Юнит 05-11.01'!Z9+'Юнит 12-18.01'!Z9+'Юнит 19-25.01'!Z9+'Юнит 26-31.01'!Z9 -> 0 | AA9: ='Юнит 01-04.01'!AA9+'Юнит 05-11.01'!AA9+'Юнит 12-18.01'!AA9+'Юнит 19-25.01'!AA9+'Юнит 26-31.01'!AA9 -> 0 | AD9: =U9*5.71% -> 0 | AE9: =U9-W9-X9-Z9-AA9-AB9-AC9-AD9 -> 0 | AG9: =IF(R9=0,0,U9/R9) -> 0 | AH9: =H9 -> 123 | AI9: =IF(R9=0,0,X9/R9) -> 0 | AJ9: =IF(P9=0,Z9/1,Z9/P9) -> 0 | AK9: =IF(P9=0,0,AA9/P9) -> 0 | AL9: {=_xlfn.IFS(R9=0,AE9,R9<0,AE9/-R9,R9>0,AE9/R9)} -> 0 | AM9: =IF(AG9=0,0,AL9/AG9) -> 0 | AN9: =IF(AH9=0,0,AL9/AH9) -> 0 | AP9: =AL9*C9 -> 0
A10: 3405092836 | B10: th син | C10: ='Юнит 26-31.01'!C10 -> 0 | H10: 123 | I10: =C10*H10 -> 0 | K10: ='Юнит 01-04.01'!K10+'Юнит 05-11.01'!K10+'Юнит 12-18.01'!K10+'Юнит 19-25.01'!K10+'Юнит 26-31.01'!K10 -> 0 | N10: =K10/31 -> 0 | O10: =R10/31 -> 0 | P10: ='Юнит 01-04.01'!P10+'Юнит 05-11.01'!P10+'Юнит 12-18.01'!P10+'Юнит 19-25.01'!P10+'Юнит 26-31.01'!P10 -> 0 | Q10: ='Юнит 01-04.01'!Q10+'Юнит 05-11.01'!Q10+'Юнит 12-18.01'!Q10+'Юнит 19-25.01'!Q10+'Юнит 26-31.01'!Q10 -> 0 | R10: =P10-Q10 -> 0 | S10: ='Юнит 01-04.01'!S10+'Юнит 05-11.01'!S10+'Юнит 12-18.01'!S10+'Юнит 19-25.01'!S10+'Юнит 26-31.01'!S10 -> 0 | T10: ='Юнит 01-04.01'!T10+'Юнит 05-11.01'!T10+'Юнит 12-18.01'!T10+'Юнит 19-25.01'!T10+'Юнит 26-31.01'!T10 -> 0 | U10: =S10+T10 -> 0 | V10: =U10/$U$24 -> 0 | W10: =R10*H10 -> 0 | X10: ='Юнит 01-04.01'!X10+'Юнит 05-11.01'!X10+'Юнит 12-18.01'!X10+'Юнит 19-25.01'!X10+'Юнит 26-31.01'!X10 -> 0 | Y10: =IF(U10=0,0,X10/U10) -> 0 | Z10: ='Юнит 01-04.01'!Z10+'Юнит 05-11.01'!Z10+'Юнит 12-18.01'!Z10+'Юнит 19-25.01'!Z10+'Юнит 26-31.01'!Z10 -> 0 | AA10: ='Юнит 01-04.01'!AA10+'Юнит 05-11.01'!AA10+'Юнит 12-18.01'!AA10+'Юнит 19-25.01'!AA10+'Юнит 26-31.01'!AA10 -> 0 | AD10: =U10*5.71% -> 0 | AE10: =U10-W10-X10-Z10-AA10-AB10-AC10-AD10 -> 0 | AG10: =IF(R10=0,0,U10/R10) -> 0 | AH10: =H10 -> 123 | AI10: =IF(R10=0,0,X10/R10) -> 0 | AJ10: =IF(P10=0,Z10/1,Z10/P10) -> 0 | AK10: =IF(P10=0,0,AA10/P10) -> 0 | AL10: {=_xlfn.IFS(R10=0,AE10,R10<0,AE10/-R10,R10>0,AE10/R10)} -> 0 | AM10: =IF(AG10=0,0,AL10/AG10) -> 0 | AN10: =IF(AH10=0,0,AL10/AH10) -> 0 | AP10: =AL10*C10 -> 0
A11: 3064346962 | B11: th желт | C11: ='Юнит 26-31.01'!C11 -> 0 | H11: 123 | I11: =C11*H11 -> 0 | K11: ='Юнит 01-04.01'!K11+'Юнит 05-11.01'!K11+'Юнит 12-18.01'!K11+'Юнит 19-25.01'!K11+'Юнит 26-31.01'!K11 -> 182 | N11: =K11/31 -> 5.8709677 | O11: =R11/31 -> 4.0322581 | P11: ='Юнит 01-04.01'!P11+'Юнит 05-11.01'!P11+'Юнит 12-18.01'!P11+'Юнит 19-25.01'!P11+'Юнит 26-31.01'!P11 -> 129 | Q11: ='Юнит 01-04.01'!Q11+'Юнит 05-11.01'!Q11+'Юнит 12-18.01'!Q11+'Юнит 19-25.01'!Q11+'Юнит 26-31.01'!Q11 -> 4 | R11: =P11-Q11 -> 125 | S11: ='Юнит 01-04.01'!S11+'Юнит 05-11.01'!S11+'Юнит 12-18.01'!S11+'Юнит 19-25.01'!S11+'Юнит 26-31.01'!S11 -> 216040 | T11: ='Юнит 01-04.01'!T11+'Юнит 05-11.01'!T11+'Юнит 12-18.01'!T11+'Юнит 19-25.01'!T11+'Юнит 26-31.01'!T11 -> -6890 | U11: =S11+T11 -> 209150 | V11: =U11/$U$24 -> 0.2929202 | W11: =R11*H11 -> 15375 | X11: ='Юнит 01-04.01'!X11+'Юнит 05-11.01'!X11+'Юнит 12-18.01'!X11+'Юнит 19-25.01'!X11+'Юнит 26-31.01'!X11 -> 89934.5 | Y11: =IF(U11=0,0,X11/U11) -> 0.43 | Z11: ='Юнит 01-04.01'!Z11+'Юнит 05-11.01'!Z11+'Юнит 12-18.01'!Z11+'Юнит 19-25.01'!Z11+'Юнит 26-31.01'!Z11 -> 23434.17 | AA11: ='Юнит 01-04.01'!AA11+'Юнит 05-11.01'!AA11+'Юнит 12-18.01'!AA11+'Юнит 19-25.01'!AA11+'Юнит 26-31.01'!AA11 -> 63035.769 | AD11: =U11*5.71% -> 11942.465 | AE11: =U11-W11-X11-Z11-AA11-AB11-AC11-AD11 -> 5428.0965 | AG11: =IF(R11=0,0,U11/R11) -> 1673.2 | AH11: =H11 -> 123 | AI11: =IF(R11=0,0,X11/R11) -> 719.476 | AJ11: =IF(P11=0,Z11/1,Z11/P11) -> 181.66023 | AK11: =IF(P11=0,0,AA11/P11) -> 488.64937 | AL11: {=_xlfn.IFS(R11=0,AE11,R11<0,AE11/-R11,R11>0,AE11/R11)} -> 43.424772 | AM11: =IF(AG11=0,0,AL11/AG11) -> 0.025953127 | AN11: =IF(AH11=0,0,AL11/AH11) -> 0.35304693 | AP11: =AL11*C11 -> 0
A12: 3405092873 | B12: th коричн | C12: ='Юнит 26-31.01'!C12 -> 0 | H12: 117 | I12: =C12*H12 -> 0 | K12: ='Юнит 01-04.01'!K12+'Юнит 05-11.01'!K12+'Юнит 12-18.01'!K12+'Юнит 19-25.01'!K12+'Юнит 26-31.01'!K12 -> 0 | N12: =K12/31 -> 0 | O12: =R12/31 -> 0 | P12: ='Юнит 01-04.01'!P12+'Юнит 05-11.01'!P12+'Юнит 12-18.01'!P12+'Юнит 19-25.01'!P12+'Юнит 26-31.01'!P12 -> 0 | Q12: ='Юнит 01-04.01'!Q12+'Юнит 05-11.01'!Q12+'Юнит 12-18.01'!Q12+'Юнит 19-25.01'!Q12+'Юнит 26-31.01'!Q12 -> 0 | R12: =P12-Q12 -> 0 | S12: ='Юнит 01-04.01'!S12+'Юнит 05-11.01'!S12+'Юнит 12-18.01'!S12+'Юнит 19-25.01'!S12+'Юнит 26-31.01'!S12 -> 0 | T12: ='Юнит 01-04.01'!T12+'Юнит 05-11.01'!T12+'Юнит 12-18.01'!T12+'Юнит 19-25.01'!T12+'Юнит 26-31.01'!T12 -> 0 | U12: =S12+T12 -> 0 | V12: =U12/$U$24 -> 0 | W12: =R12*H12 -> 0 | X12: ='Юнит 01-04.01'!X12+'Юнит 05-11.01'!X12+'Юнит 12-18.01'!X12+'Юнит 19-25.01'!X12+'Юнит 26-31.01'!X12 -> 0 | Y12: =IF(U12=0,0,X12/U12) -> 0 | Z12: ='Юнит 01-04.01'!Z12+'Юнит 05-11.01'!Z12+'Юнит 12-18.01'!Z12+'Юнит 19-25.01'!Z12+'Юнит 26-31.01'!Z12 -> 0 | AA12: ='Юнит 01-04.01'!AA12+'Юнит 05-11.01'!AA12+'Юнит 12-18.01'!AA12+'Юнит 19-25.01'!AA12+'Юнит 26-31.01'!AA12 -> 0 | AD12: =U12*5.71% -> 0 | AE12: =U12-W12-X12-Z12-AA12-AB12-AC12-AD12 -> 0 | AG12: =IF(R12=0,0,U12/R12) -> 0 | AH12: =H12 -> 117 | AI12: =IF(R12=0,0,X12/R12) -> 0 | AJ12: =IF(P12=0,Z12/1,Z12/P12) -> 0 | AK12: =IF(P12=0,0,AA12/P12) -> 0 | AL12: {=_xlfn.IFS(R12=0,AE12,R12<0,AE12/-R12,R12>0,AE12/R12)} -> 0 | AM12: =IF(AG12=0,0,AL12/AG12) -> 0 | AN12: =IF(AH12=0,0,AL12/AH12) -> 0 | AP12: =AL12*C12 -> 0
A13: 3405092993 | B13: flip черный | C13: ='Юнит 26-31.01'!C13 -> 0 | H13: 123 | I13: =C13*H13 -> 0 | K13: ='Юнит 01-04.01'!K13+'Юнит 05-11.01'!K13+'Юнит 12-18.01'!K13+'Юнит 19-25.01'!K13+'Юнит 26-31.01'!K13 -> 0 | N13: =K13/31 -> 0 | O13: =R13/31 -> 0 | P13: ='Юнит 01-04.01'!P13+'Юнит 05-11.01'!P13+'Юнит 12-18.01'!P13+'Юнит 19-25.01'!P13+'Юнит 26-31.01'!P13 -> 0 | Q13: ='Юнит 01-04.01'!Q13+'Юнит 05-11.01'!Q13+'Юнит 12-18.01'!Q13+'Юнит 19-25.01'!Q13+'Юнит 26-31.01'!Q13 -> 0 | R13: =P13-Q13 -> 0 | S13: ='Юнит 01-04.01'!S13+'Юнит 05-11.01'!S13+'Юнит 12-18.01'!S13+'Юнит 19-25.01'!S13+'Юнит 26-31.01'!S13 -> 0 | T13: ='Юнит 01-04.01'!T13+'Юнит 05-11.01'!T13+'Юнит 12-18.01'!T13+'Юнит 19-25.01'!T13+'Юнит 26-31.01'!T13 -> 0 | U13: =S13+T13 -> 0 | V13: =U13/$U$24 -> 0 | W13: =R13*H13 -> 0 | X13: ='Юнит 01-04.01'!X13+'Юнит 05-11.01'!X13+'Юнит 12-18.01'!X13+'Юнит 19-25.01'!X13+'Юнит 26-31.01'!X13 -> 0 | Y13: =IF(U13=0,0,X13/U13) -> 0 | Z13: ='Юнит 01-04.01'!Z13+'Юнит 05-11.01'!Z13+'Юнит 12-18.01'!Z13+'Юнит 19-25.01'!Z13+'Юнит 26-31.01'!Z13 -> 0 | AA13: ='Юнит 01-04.01'!AA13+'Юнит 05-11.01'!AA13+'Юнит 12-18.01'!AA13+'Юнит 19-25.01'!AA13+'Юнит 26-31.01'!AA13 -> 0 | AD13: =U13*5.71% -> 0 | AE13: =U13-W13-X13-Z13-AA13-AB13-AC13-AD13 -> 0 | AG13: =IF(R13=0,0,U13/R13) -> 0 | AH13: =H13 -> 123 | AI13: =IF(R13=0,0,X13/R13) -> 0 | AJ13: =IF(P13=0,Z13/1,Z13/P13) -> 0 | AK13: =IF(P13=0,0,AA13/P13) -> 0 | AL13: {=_xlfn.IFS(R13=0,AE13,R13<0,AE13/-R13,R13>0,AE13/R13)} -> 0 | AM13: =IF(AG13=0,0,AL13/AG13) -> 0 | AN13: =IF(AH13=0,0,AL13/AH13) -> 0 | AP13: =AL13*C13 -> 0
A14: 3405092868 | B14: flip синий | C14: ='Юнит 26-31.01'!C14 -> 0 | H14: 123 | I14: =C14*H14 -> 0 | K14: ='Юнит 01-04.01'!K14+'Юнит 05-11.01'!K14+'Юнит 12-18.01'!K14+'Юнит 19-25.01'!K14+'Юнит 26-31.01'!K14 -> 0 | N14: =K14/31 -> 0 | O14: =R14/31 -> 0 | P14: ='Юнит 01-04.01'!P14+'Юнит 05-11.01'!P14+'Юнит 12-18.01'!P14+'Юнит 19-25.01'!P14+'Юнит 26-31.01'!P14 -> 0 | Q14: ='Юнит 01-04.01'!Q14+'Юнит 05-11.01'!Q14+'Юнит 12-18.01'!Q14+'Юнит 19-25.01'!Q14+'Юнит 26-31.01'!Q14 -> 0 | R14: =P14-Q14 -> 0 | S14: ='Юнит 01-04.01'!S14+'Юнит 05-11.01'!S14+'Юнит 12-18.01'!S14+'Юнит 19-25.01'!S14+'Юнит 26-31.01'!S14 -> 0 | T14: ='Юнит 01-04.01'!T14+'Юнит 05-11.01'!T14+'Юнит 12-18.01'!T14+'Юнит 19-25.01'!T14+'Юнит 26-31.01'!T14 -> 0 | U14: =S14+T14 -> 0 | V14: =U14/$U$24 -> 0 | W14: =R14*H14 -> 0 | X14: ='Юнит 01-04.01'!X14+'Юнит 05-11.01'!X14+'Юнит 12-18.01'!X14+'Юнит 19-25.01'!X14+'Юнит 26-31.01'!X14 -> 0 | Y14: =IF(U14=0,0,X14/U14) -> 0 | Z14: ='Юнит 01-04.01'!Z14+'Юнит 05-11.01'!Z14+'Юнит 12-18.01'!Z14+'Юнит 19-25.01'!Z14+'Юнит 26-31.01'!Z14 -> 0 | AA14: ='Юнит 01-04.01'!AA14+'Юнит 05-11.01'!AA14+'Юнит 12-18.01'!AA14+'Юнит 19-25.01'!AA14+'Юнит 26-31.01'!AA14 -> 0 | AD14: =U14*5.71% -> 0 | AE14: =U14-W14-X14-Z14-AA14-AB14-AC14-AD14 -> 0 | AG14: =IF(R14=0,0,U14/R14) -> 0 | AH14: =H14 -> 123 | AI14: =IF(R14=0,0,X14/R14) -> 0 | AJ14: =IF(P14=0,Z14/1,Z14/P14) -> 0 | AK14: =IF(P14=0,0,AA14/P14) -> 0 | AL14: {=_xlfn.IFS(R14=0,AE14,R14<0,AE14/-R14,R14>0,AE14/R14)} -> 0 | AM14: =IF(AG14=0,0,AL14/AG14) -> 0 | AN14: =IF(AH14=0,0,AL14/AH14) -> 0 | AP14: =AL14*C14 -> 0
A15: 3064346642 | B15: flip жел | C15: ='Юнит 26-31.01'!C15 -> 0 | H15: 123 | I15: =C15*H15 -> 0 | K15: ='Юнит 01-04.01'!K15+'Юнит 05-11.01'!K15+'Юнит 12-18.01'!K15+'Юнит 19-25.01'!K15+'Юнит 26-31.01'!K15 -> 184 | N15: =K15/31 -> 5.9354839 | O15: =R15/31 -> 4.1290323 | P15: ='Юнит 01-04.01'!P15+'Юнит 05-11.01'!P15+'Юнит 12-18.01'!P15+'Юнит 19-25.01'!P15+'Юнит 26-31.01'!P15 -> 132 | Q15: ='Юнит 01-04.01'!Q15+'Юнит 05-11.01'!Q15+'Юнит 12-18.01'!Q15+'Юнит 19-25.01'!Q15+'Юнит 26-31.01'!Q15 -> 4 | R15: =P15-Q15 -> 128 | S15: ='Юнит 01-04.01'!S15+'Юнит 05-11.01'!S15+'Юнит 12-18.01'!S15+'Юнит 19-25.01'!S15+'Юнит 26-31.01'!S15 -> 240977 | T15: ='Юнит 01-04.01'!T15+'Юнит 05-11.01'!T15+'Юнит 12-18.01'!T15+'Юнит 19-25.01'!T15+'Юнит 26-31.01'!T15 -> -7380 | U15: =S15+T15 -> 233597 | V15: =U15/$U$24 -> 0.32715888 | W15: =R15*H15 -> 15744 | X15: ='Юнит 01-04.01'!X15+'Юнит 05-11.01'!X15+'Юнит 12-18.01'!X15+'Юнит 19-25.01'!X15+'Юнит 26-31.01'!X15 -> 100446.71 | Y15: =IF(U15=0,0,X15/U15) -> 0.43 | Z15: ='Юнит 01-04.01'!Z15+'Юнит 05-11.01'!Z15+'Юнит 12-18.01'!Z15+'Юнит 19-25.01'!Z15+'Юнит 26-31.01'!Z15 -> 28024.06 | AA15: ='Юнит 01-04.01'!AA15+'Юнит 05-11.01'!AA15+'Юнит 12-18.01'!AA15+'Юнит 19-25.01'!AA15+'Юнит 26-31.01'!AA15 -> 67039.198 | AD15: =U15*5.71% -> 13338.389 | AE15: =U15-W15-X15-Z15-AA15-AB15-AC15-AD15 -> 9004.6434 | AG15: =IF(R15=0,0,U15/R15) -> 1824.9766 | AH15: =H15 -> 123 | AI15: =IF(R15=0,0,X15/R15) -> 784.73992 | AJ15: =IF(P15=0,Z15/1,Z15/P15) -> 212.30348 | AK15: =IF(P15=0,0,AA15/P15) -> 507.87271 | AL15: {=_xlfn.IFS(R15=0,AE15,R15<0,AE15/-R15,R15>0,AE15/R15)} -> 70.348777 | AM15: =IF(AG15=0,0,AL15/AG15) -> 0.03854777 | AN15: =IF(AH15=0,0,AL15/AH15) -> 0.57194127 | AP15: =AL15*C15 -> 0
A16: 3405092287 | B16: flip коричневый | C16: ='Юнит 26-31.01'!C16 -> 0 | H16: 117 | I16: =C16*H16 -> 0 | K16: ='Юнит 01-04.01'!K16+'Юнит 05-11.01'!K16+'Юнит 12-18.01'!K16+'Юнит 19-25.01'!K16+'Юнит 26-31.01'!K16 -> 0 | N16: =K16/31 -> 0 | O16: =R16/31 -> 0 | P16: ='Юнит 01-04.01'!P16+'Юнит 05-11.01'!P16+'Юнит 12-18.01'!P16+'Юнит 19-25.01'!P16+'Юнит 26-31.01'!P16 -> 0 | Q16: ='Юнит 01-04.01'!Q16+'Юнит 05-11.01'!Q16+'Юнит 12-18.01'!Q16+'Юнит 19-25.01'!Q16+'Юнит 26-31.01'!Q16 -> 0 | R16: =P16-Q16 -> 0 | S16: ='Юнит 01-04.01'!S16+'Юнит 05-11.01'!S16+'Юнит 12-18.01'!S16+'Юнит 19-25.01'!S16+'Юнит 26-31.01'!S16 -> 0 | T16: ='Юнит 01-04.01'!T16+'Юнит 05-11.01'!T16+'Юнит 12-18.01'!T16+'Юнит 19-25.01'!T16+'Юнит 26-31.01'!T16 -> 0 | U16: =S16+T16 -> 0 | V16: =U16/$U$24 -> 0 | W16: =R16*H16 -> 0 | X16: ='Юнит 01-04.01'!X16+'Юнит 05-11.01'!X16+'Юнит 12-18.01'!X16+'Юнит 19-25.01'!X16+'Юнит 26-31.01'!X16 -> 0 | Y16: =IF(U16=0,0,X16/U16) -> 0 | Z16: ='Юнит 01-04.01'!Z16+'Юнит 05-11.01'!Z16+'Юнит 12-18.01'!Z16+'Юнит 19-25.01'!Z16+'Юнит 26-31.01'!Z16 -> 0 | AA16: ='Юнит 01-04.01'!AA16+'Юнит 05-11.01'!AA16+'Юнит 12-18.01'!AA16+'Юнит 19-25.01'!AA16+'Юнит 26-31.01'!AA16 -> 0 | AD16: =U16*5.71% -> 0 | AE16: =U16-W16-X16-Z16-AA16-AB16-AC16-AD16 -> 0 | AG16: =IF(R16=0,0,U16/R16) -> 0 | AH16: =H16 -> 117 | AI16: =IF(R16=0,0,X16/R16) -> 0 | AJ16: =IF(P16=0,Z16/1,Z16/P16) -> 0 | AK16: =IF(P16=0,0,AA16/P16) -> 0 | AL16: {=_xlfn.IFS(R16=0,AE16,R16<0,AE16/-R16,R16>0,AE16/R16)} -> 0 | AM16: =IF(AG16=0,0,AL16/AG16) -> 0 | AN16: =IF(AH16=0,0,AL16/AH16) -> 0 | AP16: =AL16*C16 -> 0
AG17: =AVERAGEIF(AG3:AG15,"<>0",AG3:AG15) -> 1658.279 | AH17: =AVERAGEIF(AH3:AH15,"<>0",AH3:AH15) -> 127.26 | AI17: =AVERAGEIF(AI3:AI15,"<>0",AI3:AI15) -> 713.05995 | AJ17: =AVERAGEIF(AJ3:AJ15,"<>0",AJ3:AJ15) -> 163.75185 | AK17: =AVERAGEIF(AK3:AK15,"<>0",AK3:AK15) -> 321.19618 | AL17: =AVERAGEIF(AL3:AL15,"<>0",AL3:AL15) -> 223.11245 | AM17: =AVERAGEIF(AM3:AM15,"<>0",AM3:AM15) -> 0.13306657 | AN17: =AVERAGEIF(AN3:AN15,"<>0",AN3:AN15) -> 1.764396
A18: Итого очки | C18: =SUM(C3:C16) -> 0 | E18: 108496 | F18: 597 | G18: 295 | I18: =SUM(I3:I16) -> 0 | K18: =SUM(K3:K16) -> 603 | P18: =SUM(P3:P16) -> 432 | Q18: =SUM(Q3:Q16) -> 13 | R18: =SUM(R3:R16) -> 419 | S18: =SUM(S3:S16) -> 735889 | T18: =SUM(T3:T16) -> -21872 | U18: =SUM(U3:U16) -> 714017 | V18: =SUM(V3:V16) -> 1 | W18: =SUM(W3:W16) -> 52684.5 | X18: =SUM(X3:X16) -> 307027.31 | Y18: =IF(U18=0,0,X18/U18) -> 0.43 | Z18: =SUM(Z3:Z16) -> 77786.69 | AA18: =IFERROR(P18*AA24/P24,0) -> 188538.66 | AB18: =SUM(AB3:AB16) -> 0 | AC18: =SUM(AC3:AC16) -> 0 | AD18: =SUM(AD3:AD16) -> 40770.371 | AE18: =SUM(AE3:AE16) -> 50959.258 | AP18: =SUM(AP3:AP16) -> 0 | AZ18: 18592777
AA19: =SUM(AA3:AA15) -> 184788.87
AG21: =AVERAGEIF(AG20:AG20,"<>0",AG20:AG20) -> #DIV/0! | AH21: =AVERAGEIF(AH20:AH20,"<>0",AH20:AH20) -> #DIV/0! | AI21: =AVERAGEIF(AI20:AI20,"<>0",AI20:AI20) -> #DIV/0! | AJ21: =AVERAGEIF(AJ20:AJ20,"<>0",AJ20:AJ20) -> #DIV/0! | AK21: =AVERAGEIF(AK20:AK20,"<>0",AK20:AK20) -> #DIV/0! | AL21: =AVERAGEIF(AL20:AL20,"<>0",AL20:AL20) -> #DIV/0! | AM21: =AVERAGEIF(AM20:AM20,"<>0",AM20:AM20) -> #DIV/0! | AN21: =AVERAGEIF(AN20:AN20,"<>0",AN20:AN20) -> #DIV/0!
C22: =SUM(C20:C20) -> 0 | I22: =SUM(I20:I20) -> 0 | K22: =SUM(K20:K20) -> 0 | P22: =SUM(P20:P20) -> 0 | Q22: =SUM(Q20:Q20) -> 0 | R22: =SUM(R20:R20) -> 0 | S22: =SUM(S20:S20) -> 0 | T22: =SUM(T20:T20) -> 0 | U22: =SUM(U20:U20) -> 0 | V22: =SUM(V20:V20) -> 0 | W22: =SUM(W20:W20) -> 0 | X22: =SUM(X20:X20) -> 0 | Y22: =IF(U22=0,0,X22/U22) -> 0 | Z22: =SUM(Z20:Z20) -> 0 | AA22: =IFERROR(P22*AA24/P24,0) -> 0 | AB22: =SUM(AB20:AB20) -> 0 | AC22: =SUM(AC20:AC20) -> 0 | AD22: =SUM(AD20:AD20) -> 0 | AE22: =SUM(AE20:AE20) -> 0 | AP22: =SUM(AP20:AP20) -> 0
AA23: =SUM(AA20:AA20) -> 0
A24: ИТОГО | C24: =C18+C22 -> 0 | D24: =SUM(D3:D20) -> 0 | E24: =SUM(E3:E20) -> 108496 | F24: =SUM(F3:F20) -> 597 | G24: =SUM(G3:G20) -> 295 | I24: =I18+I22 -> 0 | J24: =J18+J22 -> 0 | K24: =K18+K22 -> 603 | P24: =P18+P22 -> 432 | Q24: =Q18+Q22 -> 13 | R24: =R18-R22 -> 419 | S24: =S18+S22 -> 735889 | T24: =T18+T22 -> -21872 | U24: =U18+U22 -> 714017 | V24: =V18+V22 -> 1 | W24: =W18+W22 -> 52684.5 | X24: =X18+X22 -> 307027.31 | Y24: =X24/U24 -> 0.43 | Z24: =Z18+Z22 -> 77786.69 | AA24: ='Юнит 01-04.01'!AA24+'Юнит 05-11.01'!AA24+'Юнит 12-18.01'!AA24+'Юнит 19-25.01'!AA24+'Юнит 26-31.01'!AA24 -> 188538.66 | AC24: =SUM(AC3:AC20) -> 0 | AD24: =AD18+AD22 -> 40770.371 | AE24: =AE18+AE22 -> 50959.258 | AK24: =AA25/P24 -> 436.43208 | AP24: =SUM(AP3:AP20) -> 0
AA25: =AA18+AA22 -> 188538.66 | AE25: =Сводная!Y8+Сводная!S8+Сводная!T8+Сводная!U8-Сводная!V8-Сводная!W8-(AA26-AA25) -> 50959.258
AA26: =AA19+AA23 -> 184788.87
I29: Себестоимость остатков | K29: Прибыль с остатков | L29: Рентабельность товарных остатков
H31: до 60 дн | I31: =SUMIF(J3:J20,"<60",I3:I20) -> 0 | J31: =I31/I24 -> #DIV/0! | K31: =SUMIF(J3:J20,"<60",AP3:AP20) -> 0 | L31: =K31/I31 -> #DIV/0!
H32: 60-120 дн | I32: =I24-I33-I31 -> 0 | J32: =I32/I24 -> #DIV/0! | K32: =AP24-K31-K33 -> 0 | L32: =K32/I32 -> #DIV/0!
H33: > 120 дн | I33: =SUMIF(J3:J20,">120",I3:I20) -> 0 | J33: =I33/I24 -> #DIV/0! | K33: =SUMIF(J3:J20,">120",AP3:AP20) -> 0 | L33: =K33/I33 -> #DIV/0!
H35: Если товар на сайте менее 30 дней - оборачиваемость 0

Sheet Юнит 26-31.01
B1: 26-31.01 | AG1: на 1 единицу проданного товара
B2: Артикул поставщика | C2: Остаток на 01.02 | D2: В пути до клиента | E2: В пути от клиента | F2: Итого по складам ВБ | G2: Остаток на нашем складе на 02.09 | H2: Себетоимость на 1 ед на 29.09.25 | I2: Себестоимость остатков | J2: Оборачиваемость, дн | K2: Заказы, шт 7 дней | L2: Средняя цена, руб (столбец 32, AG) | M2: % выкупа за 7 дней (столбец 23, X) | N2: Скорость заказов | O2: Скорость продаж | P2: Кол-во ПРОДАЖИ | Q2: Кол-во ВОЗВРАТЫ | R2: Кол-во ПРОДАЖИ-ВОЗВРАТЫ | S2: Выручка ПРОДАЖИ | T2: Выручка ВОЗВРАТЫ | U2: Выручка с учетом согласованной скидки ПРОДАЖИ - ВОЗВРАТЫ | V2: Доля выручки, % от общего объема | W2: Себестоимость продаж | X2: Комиссия, руб | Y2: Комиссия, % | Z2: Логистика | AA2: Реклама | AB2: Хранение | AC2: Штрафы | AD2: Налог 1%+ НДС 5% | AE2: Прибыль | AG2: Выручка на 1 ед (средняя цена продажи со скидкой) | AH2: Себестоимость на 1 ед | AI2: Комиссия на 1 ед | AJ2: Логистика на 1 ед | AK2: Реклама на 1 ед | AL2: Прибыль на 1 ед | AM2: Маржинальность, % | AN2: Рентабельность, % | AP2: Прибыль с остатков
A3: 2676784153 | B3: черные с железкой классика | H3: 142.98 | I3: =C3*H3 -> 0 | N3: =K3/7 -> 0 | O3: =R3/7 -> 0 | P3: =SUMIFS('Отчет 26-31.01'!H:H,'Отчет 26-31.01'!D:D,"Выручка",'Отчет 26-31.01'!E:E,B3) -> 0 | Q3: =SUMIFS('Отчет 26-31.01'!H:H,'Отчет 26-31.01'!D:D,"Возврат выручки",'Отчет 26-31.01'!E:E,B3) -> 0 | R3: =P3-Q3 -> 0 | S3: =SUMIFS('Отчет 26-31.01'!P:P,'Отчет 26-31.01'!C:C,"Продажи",'Отчет 26-31.01'!E:E,B3) -> 0 | T3: =SUMIFS('Отчет 26-31.01'!P:P,'Отчет 26-31.01'!C:C,"Возвраты",'Отчет 26-31.01'!E:E,B3) -> 0 | U3: =S3+T3 -> 0 | V3: =U3/$U$24 -> #DIV/0! | W3: =R3*H3 -> 0 | X3: =-SUMIFS('Отчет 26-31.01'!P:P,'Отчет 26-31.01'!C:C,"Вознаграждение Ozon",'Отчет 26-31.01'!E:E,B3) -> 0 | Y3: =IF(U3=0,0,X3/U3) -> 0 | Z3: =-SUMIFS('Отчет 26-31.01'!P:P,'Отчет 26-31.01'!C:C,"Услуги доставки",'Отчет 26-31.01'!E:E,B3) -> 0 | AD3: =U3*5.71% -> 0 | AE3: =U3-W3-X3-Z3-AA3-AB3-AC3-AD3 -> 0 | AG3: =IF(R3=0,0,U3/R3) -> 0 | AH3: =H3 -> 142.98 | AI3: =IF(R3=0,0,X3/R3) -> 0 | AJ3: =IF(P3=0,Z3/1,Z3/P3) -> 0 | AK3: =IF(P3=0,0,AA3/P3) -> 0 | AL3: =_xlfn.IFS(R3=0,AE3,R3<0,AE3/-R3,R3>0,AE3/R3) -> 0 | AM3: =IF(AG3=0,0,AL3/AG3) -> 0 | AN3: =IF(AH3=0,0,AL3/AH3) -> 0 | AP3: =AL3*C3 -> 0
A4: 2676784638 | B4: qs черные | H4: 123.09 | I4: =C4*H4 -> 0 | N4: =K4/7 -> 0 | O4: =R4/7 -> 0 | P4: =SUMIFS('Отчет 26-31.01'!H:H,'Отчет 26-31.01'!D:D,"Выручка",'Отчет 26-31.01'!E:E,B4) -> 0 | Q4: =SUMIFS('Отчет 26-31.01'!H:H,'Отчет 26-31.01'!D:D,"Возврат выручки",'Отчет 26-31.01'!E:E,B4) -> 0 | R4: =P4-Q4 -> 0 | S4: =SUMIFS('Отчет 26-31.01'!P:P,'Отчет 26-31.01'!C:C,"Продажи",'Отчет 26-31.01'!E:E,B4) -> 0 | T4: =SUMIFS('Отчет 26-31.01'!P:P,'Отчет 26-31.01'!C:C,"Возвраты",'Отчет 26-31.01'!E:E,B4) -> 0 | U4: =S4+T4 -> 0 | V4: =U4/$U$24 -> #DIV/0! | W4: =R4*H4 -> 0 | X4: =-SUMIFS('Отчет 26-31.01'!P:P,'Отчет 26-31.01'!C:C,"Вознаграждение Ozon",'Отчет 26-31.01'!E:E,B4) -> 0 | Y4: =IF(U4=0,0,X4/U4) -> 0 | Z4: =-SUMIFS('Отчет 26-31.01'!P:P,'Отчет 26-31.01'!C:C,"Услуги доставки",'Отчет 26-31.01'!E:E,B4) -> 0 | AD4: =U4*5.71% -> 0 | AE4: =U4-W4-X4-Z4-AA4-AB4-AC4-AD4 -> 0 | AG4: =IF(R4=0,0,U4/R4) -> 0 | AH4: =H4 -> 123.09 | AI4: =IF(R4=0,0,X4/R4) -> 0 | AJ4: =IF(P4=0,Z4/1,Z4/P4) -> 0 | AK4: =IF(P4=0,0,AA4/P4) -> 0 | AL4: {=_xlfn.IFS(R4=0,AE4,R4<0,AE4/-R4,R4>0,AE4/R4)} -> 0 | AM4: =IF(AG4=0,0,AL4/AG4) -> 0 | AN4: =IF(AH4=0,0,AL4/AH4) -> 0 | AP4: =AL4*C4 -> 0
A5: 2676784504 | B5: qs синие | H5: 123.09 | I5: =C5*H5 -> 0 | N5: =K5/7 -> 0 | O5: =R5/7 -> 0 | P5: =SUMIFS('Отчет 26-31.01'!H:H,'Отчет 26-31.01'!D:D,"Выручка",'Отчет 26-31.01'!E:E,B5) -> 0 | Q5: =SUMIFS('Отчет 26-31.01'!H:H,'Отчет 26-31.01'!D:D,"Возврат выручки",'Отчет 26-31.01'!E:E,B5) -> 0 | R5: =P5-Q5 -> 0 | S5: =SUMIFS('Отчет 26-31.01'!P:P,'Отчет 26-31.01'!C:C,"Продажи",'Отчет 26-31.01'!E:E,B5) -> 0 | T5: =SUMIFS('Отчет 26-31.01'!P:P,'Отчет 26-31.01'!C:C,"Возвраты",'Отчет 26-31.01'!E:E,B5) -> 0 | U5: =S5+T5 -> 0 | V5: =U5/$U$24 -> #DIV/0! | W5: =R5*H5 -> 0 | X5: =-SUMIFS('Отчет 26-31.01'!P:P,'Отчет 26-31.01'!C:C,"Вознаграждение Ozon",'Отчет 26-31.01'!E:E,B5) -> 0 | Y5: =IF(U5=0,0,X5/U5) -> 0 | Z5: =-SUMIFS('Отчет 26-31.01'!P:P,'Отчет 26-31.01'!C:C,"Услуги доставки",'Отчет 26-31.01'!E:E,B5) -> 0 | AD5: =U5*5.71% -> 0 | AE5: =U5-W5-X5-Z5-AA5-AB5-AC5-AD5 -> 0 | AG5: =IF(R5=0,0,U5/R5) -> 0 | AH5: =H5 -> 123.09 | AI5: =IF(R5=0,0,X5/R5) -> 0 | AJ5: =IF(P5=0,Z5/1,Z5/P5) -> 0 | AK5: =IF(P5=0,0,AA5/P5) -> 0 | AL5: {=_xlfn.IFS(R5=0,AE5,R5<0,AE5/-R5,R5>0,AE5/R5)} -> 0 | AM5: =IF(AG5=0,0,AL5/AG5) -> 0 | AN5: =IF(AH5=0,0,AL5/AH5) -> 0 | AP5: =AL5*C5 -> 0
A6: 2676784514 | B6: qs желтые | H6: 123.09 | I6: =C6*H6 -> 0 | N6: =K6/7 -> 0 | O6: =R6/7 -> 0 | P6: =SUMIFS('Отчет 26-31.01'!H:H,'Отчет 26-31.01'!D:D,"Выручка",'Отчет 26-31.01'!E:E,B6) -> 0 | Q6: =SUMIFS('Отчет 26-31.01'!H:H,'Отчет 26-31.01'!D:D,"Возврат выручки",'Отчет 26-31.01'!E:E,B6) -> 0 | R6: =P6-Q6 -> 0 | S6: =SUMIFS('Отчет 26-31.01'!P:P,'Отчет 26-31.01'!C:C,"Продажи",'Отчет 26-31.01'!E:E,B6) -> 0 | T6: =SUMIFS('Отчет 26-31.01'!P:P,'Отчет 26-31.01'!C:C,"Возвраты",'Отчет 26-31.01'!E:E,B6) -> 0 | U6: =S6+T6 -> 0 | V6: =U6/$U$24 -> #DIV/0! | W6: =R6*H6 -> 0 | X6: =-SUMIFS('Отчет 26-31.01'!P:P,'Отчет 26-31.01'!C:C,"Вознаграждение Ozon",'Отчет 26-31.01'!E:E,B6) -> 0 | Y6: =IF(U6=0,0,X6/U6) -> 0 | Z6: =-SUMIFS('Отчет 26-31.01'!P:P,'Отчет 26-31.01'!C:C,"Услуги доставки",'Отчет 26-31.01'!E:E,B6) -> 0 | AD6: =U6*5.71% -> 0 | AE6: =U6-W6-X6-Z6-AA6-AB6-AC6-AD6 -> 0 | AG6: =IF(R6=0,0,U6/R6) -> 0 | AH6: =H6 -> 123.09 | AI6: =IF(R6=0,0,X6/R6) -> 0 | AJ6: =IF(P6=0,Z6/1,Z6/P6) -> 0 | AK6: =IF(P6=0,0,AA6/P6) -> 0 | AL6: {=_xlfn.IFS(R6=0,AE6,R6<0,AE6/-R6,R6>0,AE6/R6)} -> 0 | AM6: =IF(AG6=0,0,AL6/AG6) -> 0 | AN6: =IF(AH6=0,0,AL6/AH6) -> 0 | AP6: =AL6*C6 -> 0
A7: 2676784181 | B7: qs коричневые | H7: 117.24 | I7: =C7*H7 -> 0 | N7: =K7/7 -> 0 | O7: =R7/7 -> 0 | P7: =SUMIFS('Отчет 26-31.01'!H:H,'Отчет 26-31.01'!D:D,"Выручка",'Отчет 26-31.01'!E:E,B7) -> 0 | Q7: =SUMIFS('Отчет 26-31.01'!H:H,'Отчет 26-31.01'!D:D,"Возврат выручки",'Отчет 26-31.01'!E:E,B7) -> 0 | R7: =P7-Q7 -> 0 | S7: =SUMIFS('Отчет 26-31.01'!P:P,'Отчет 26-31.01'!C:C,"Продажи",'Отчет 26-31.01'!E:E,B7) -> 0 | T7: =SUMIFS('Отчет 26-31.01'!P:P,'Отчет 26-31.01'!C:C,"Возвраты",'Отчет 26-31.01'!E:E,B7) -> 0 | U7: =S7+T7 -> 0 | V7: =U7/$U$24 -> #DIV/0! | W7: =R7*H7 -> 0 | X7: =-SUMIFS('Отчет 26-31.01'!P:P,'Отчет 26-31.01'!C:C,"Вознаграждение Ozon",'Отчет 26-31.01'!E:E,B7) -> 0 | Y7: =IF(U7=0,0,X7/U7) -> 0 | Z7: =-SUMIFS('Отчет 26-31.01'!P:P,'Отчет 26-31.01'!C:C,"Услуги доставки",'Отчет 26-31.01'!E:E,B7) -> 0 | AD7: =U7*5.71% -> 0 | AE7: =U7-W7-X7-Z7-AA7-AB7-AC7-AD7 -> 0 | AG7: =IF(R7=0,0,U7/R7) -> 0 | AH7: =H7 -> 117.24 | AI7: =IF(R7=0,0,X7/R7) -> 0 | AJ7: =IF(P7=0,Z7/1,Z7/P7) -> 0 | AK7: =IF(P7=0,0,AA7/P7) -> 0 | AL7: {=_xlfn.IFS(R7=0,AE7,R7<0,AE7/-R7,R7>0,AE7/R7)} -> 0 | AM7: =IF(AG7=0,0,AL7/AG7) -> 0 | AN7: =IF(AH7=0,0,AL7/AH7) -> 0 | AP7: =AL7*C7 -> 0
A8: 2676783005 | B8: MR8854 C2 | H8: 169.89 | I8: =C8*H8 -> 0 | N8: =K8/7 -> 0 | O8: =R8/7 -> 0 | P8: =SUMIFS('Отчет 26-31.01'!H:H,'Отчет 26-31.01'!D:D,"Выручка",'Отчет 26-31.01'!E:E,B8) -> 0 | Q8: =SUMIFS('Отчет 26-31.01'!H:H,'Отчет 26-31.01'!D:D,"Возврат выручки",'Отчет 26-31.01'!E:E,B8) -> 0 | R8: =P8-Q8 -> 0 | S8: =SUMIFS('Отчет 26-31.01'!P:P,'Отчет 26-31.01'!C:C,"Продажи",'Отчет 26-31.01'!E:E,B8) -> 0 | T8: =SUMIFS('Отчет 26-31.01'!P:P,'Отчет 26-31.01'!C:C,"Возвраты",'Отчет 26-31.01'!E:E,B8) -> 0 | U8: =S8+T8 -> 0 | V8: =U8/$U$24 -> #DIV/0! | W8: =R8*H8 -> 0 | X8: =-SUMIFS('Отчет 26-31.01'!P:P,'Отчет 26-31.01'!C:C,"Вознаграждение Ozon",'Отчет 26-31.01'!E:E,B8) -> 0 | Y8: =IF(U8=0,0,X8/U8) -> 0 | Z8: =-SUMIFS('Отчет 26-31.01'!P:P,'Отчет 26-31.01'!C:C,"Услуги доставки",'Отчет 26-31.01'!E:E,B8) -> 0 | AD8: =U8*5.71% -> 0 | AE8: =U8-W8-X8-Z8-AA8-AB8-AC8-AD8 -> 0 | AG8: =IF(R8=0,0,U8/R8) -> 0 | AH8: =H8 -> 169.89 | AI8: =IF(R8=0,0,X8/R8) -> 0 | AJ8: =IF(P8=0,Z8/1,Z8/P8) -> 0 | AK8: =IF(P8=0,0,AA8/P8) -> 0 | AL8: {=_xlfn.IFS(R8=0,AE8,R8<0,AE8/-R8,R8>0,AE8/R8)} -> 0 | AM8: =IF(AG8=0,0,AL8/AG8) -> 0 | AN8: =IF(AH8=0,0,AL8/AH8) -> 0 | AP8: =AL8*C8 -> 0
A9: 3405092860 | B9: th черн | H9: 123 | I9: =C9*H9 -> 0 | N9: =K9/7 -> 0 | O9: =R9/7 -> 0 | P9: =SUMIFS('Отчет 26-31.01'!H:H,'Отчет 26-31.01'!D:D,"Выручка",'Отчет 26-31.01'!E:E,B9) -> 0 | Q9: =SUMIFS('Отчет 26-31.01'!H:H,'Отчет 26-31.01'!D:D,"Возврат выручки",'Отчет 26-31.01'!E:E,B9) -> 0 | R9: =P9-Q9 -> 0 | S9: =SUMIFS('Отчет 26-31.01'!P:P,'Отчет 26-31.01'!C:C,"Продажи",'Отчет 26-31.01'!E:E,B9) -> 0 | T9: =SUMIFS('Отчет 26-31.01'!P:P,'Отчет 26-31.01'!C:C,"Возвраты",'Отчет 26-31.01'!E:E,B9) -> 0 | U9: =S9+T9 -> 0 | V9: =U9/$U$24 -> #DIV/0! | W9: =R9*H9 -> 0 | X9: =-SUMIFS('Отчет 26-31.01'!P:P,'Отчет 26-31.01'!C:C,"Вознаграждение Ozon",'Отчет 26-31.01'!E:E,B9) -> 0 | Y9: =IF(U9=0,0,X9/U9) -> 0 | Z9: =-SUMIFS('Отчет 26-31.01'!P:P,'Отчет 26-31.01'!C:C,"Услуги доставки",'Отчет 26-31.01'!E:E,B9) -> 0 | AD9: =U9*5.71% -> 0 | AE9: =U9-W9-X9-Z9-AA9-AB9-AC9-AD9 -> 0 | AG9: =IF(R9=0,0,U9/R9) -> 0 | AH9: =H9 -> 123 | AI9: =IF(R9=0,0,X9/R9) -> 0 | AJ9: =IF(P9=0,Z9/1,Z9/P9) -> 0 | AK9: =IF(P9=0,0,AA9/P9) -> 0 | AL9: {=_xlfn.IFS(R9=0,AE9,R9<0,AE9/-R9,R9>0,AE9/R9)} -> 0 | AM9: =IF(AG9=0,0,AL9/AG9) -> 0 | AN9: =IF(AH9=0,0,AL9/AH9) -> 0 | AP9: =AL9*C9 -> 0
A10: 3405092836 | B10: th син | H10: 123 | I10: =C10*H10 -> 0 | N10: =K10/7 -> 0 | O10: =R10/7 -> 0 | P10: =SUMIFS('Отчет 26-31.01'!H:H,'Отчет 26-31.01'!D:D,"Выручка",'Отчет 26-31.01'!E:E,B10) -> 0 | Q10: =SUMIFS('Отчет 26-31.01'!H:H,'Отчет 26-31.01'!D:D,"Возврат выручки",'Отчет 26-31.01'!E:E,B10) -> 0 | R10: =P10-Q10 -> 0 | S10: =SUMIFS('Отчет 26-31.01'!P:P,'Отчет 26-31.01'!C:C,"Продажи",'Отчет 26-31.01'!E:E,B10) -> 0 | T10: =SUMIFS('Отчет 26-31.01'!P:P,'Отчет 26-31.01'!C:C,"Возвраты",'Отчет 26-31.01'!E:E,B10) -> 0 | U10: =S10+T10 -> 0 | V10: =U10/$U$24 -> #DIV/0! | W10: =R10*H10 -> 0 | X10: =-SUMIFS('Отчет 26-31.01'!P:P,'Отчет 26-31.01'!C:C,"Вознаграждение Ozon",'Отчет 26-31.01'!E:E,B10) -> 0 | Y10: =IF(U10=0,0,X10/U10) -> 0 | Z10: =-SUMIFS('Отчет 26-31.01'!P:P,'Отчет 26-31.01'!C:C,"Услуги доставки",'Отчет 26-31.01'!E:E,B10) -> 0 | AD10: =U10*5.71% -> 0 | AE10: =U10-W10-X10-Z10-AA10-AB10-AC10-AD10 -> 0 | AG10: =IF(R10=0,0,U10/R10) -> 0 | AH10: =H10 -> 123 | AI10: =IF(R10=0,0,X10/R10) -> 0 | AJ10: =IF(P10=0,Z10/1,Z10/P10) -> 0 | AK10: =IF(P10=0,0,AA10/P10) -> 0 | AL10: {=_xlfn.IFS(R10=0,AE10,R10<0,AE10/-R10,R10>0,AE10/R10)} -> 0 | AM10: =IF(AG10=0,0,AL10/AG10) -> 0 | AN10: =IF(AH10=0,0,AL10/AH10) -> 0 | AP10: =AL10*C10 -> 0
A11: 3064346962 | B11: th желт | H11: 123 | I11: =C11*H11 -> 0 | N11: =K11/7 -> 0 | O11: =R11/7 -> 0 | P11: =SUMIFS('Отчет 26-31.01'!H:H,'Отчет 26-31.01'!D:D,"Выручка",'Отчет 26-31.01'!E:E,B11) -> 0 | Q11: =SUMIFS('Отчет 26-31.01'!H:H,'Отчет 26-31.01'!D:D,"Возврат выручки",'Отчет 26-31.01'!E:E,B11) -> 0 | R11: =P11-Q11 -> 0 | S11: =SUMIFS('Отчет 26-31.01'!P:P,'Отчет 26-31.01'!C:C,"Продажи",'Отчет 26-31.01'!E:E,B11) -> 0 | T11: =SUMIFS('Отчет 26-31.01'!P:P,'Отчет 26-31.01'!C:C,"Возвраты",'Отчет 26-31.01'!E:E,B11) -> 0 | U11: =S11+T11 -> 0 | V11: =U11/$U$24 -> #DIV/0! | W11: =R11*H11 -> 0 | X11: =-SUMIFS('Отчет 26-31.01'!P:P,'Отчет 26-31.01'!C:C,"Вознаграждение Ozon",'Отчет 26-31.01'!E:E,B11) -> 0 | Y11: =IF(U11=0,0,X11/U11) -> 0 | Z11: =-SUMIFS('Отчет 26-31.01'!P:P,'Отчет 26-31.01'!C:C,"Услуги доставки",'Отчет 26-31.01'!E:E,B11) -> 0 | AD11: =U11*5.71% -> 0 | AE11: =U11-W11-X11-Z11-AA11-AB11-AC11-AD11 -> 0 | AG11: =IF(R11=0,0,U11/R11) -> 0 | AH11: =H11 -> 123 | AI11: =IF(R11=0,0,X11/R11) -> 0 | AJ11: =IF(P11=0,Z11/1,Z11/P11) -> 0 | AK11: =IF(P11=0,0,AA11/P11) -> 0 | AL11: {=_xlfn.IFS(R11=0,AE11,R11<0,AE11/-R11,R11>0,AE11/R11)} -> 0 | AM11: =IF(AG11=0,0,AL11/AG11) -> 0 | AN11: =IF(AH11=0,0,AL11/AH11) -> 0 | AP11: =AL11*C11 -> 0
A12: 3405092873 | B12: th коричн | H12: 117 | I12: =C12*H12 -> 0 | N12: =K12/7 -> 0 | O12: =R12/7 -> 0 | P12: =SUMIFS('Отчет 26-31.01'!H:H,'Отчет 26-31.01'!D:D,"Выручка",'Отчет 26-31.01'!E:E,B12) -> 0 | Q12: =SUMIFS('Отчет 26-31.01'!H:H,'Отчет 26-31.01'!D:D,"Возврат выручки",'Отчет 26-31.01'!E:E,B12) -> 0 | R12: =P12-Q12 -> 0 | S12: =SUMIFS('Отчет 26-31.01'!P:P,'Отчет 26-31.01'!C:C,"Продажи",'Отчет 26-31.01'!E:E,B12) -> 0 | T12: =SUMIFS('Отчет 26-31.01'!P:P,'Отчет 26-31.01'!C:C,"Возвраты",'Отчет 26-31.01'!E:E,B12) -> 0 | U12: =S12+T12 -> 0 | V12: =U12/$U$24 -> #DIV/0! | W12: =R12*H12 -> 0 | X12: =-SUMIFS('Отчет 26-31.01'!P:P,'Отчет 26-31.01'!C:C,"Вознаграждение Ozon",'Отчет 26-31.01'!E:E,B12) -> 0 | Y12: =IF(U12=0,0,X12/U12) -> 0 | Z12: =-SUMIFS('Отчет 26-31.01'!P:P,'Отчет 26-31.01'!C:C,"Услуги доставки",'Отчет 26-31.01'!E:E,B12) -> 0 | AD12: =U12*5.71% -> 0 | AE12: =U12-W12-X12-Z12-AA12-AB12-AC12-AD12 -> 0 | AG12: =IF(R12=0,0,U12/R12) -> 0 | AH12: =H12 -> 117 | AI12: =IF(R12=0,0,X12/R12) -> 0 | AJ12: =IF(P12=0,Z12/1,Z12/P12) -> 0 | AK12: =IF(P12=0,0,AA12/P12) -> 0 | AL12: {=_xlfn.IFS(R12=0,AE12,R12<0,AE12/-R12,R12>0,AE12/R12)} -> 0 | AM12: =IF(AG12=0,0,AL12/AG12) -> 0 | AN12: =IF(AH12=0,0,AL12/AH12) -> 0 | AP12: =AL12*C12 -> 0
A13: 3405092993 | B13: flip черный | H13: 123 | I13: =C13*H13 -> 0 | N13: =K13/7 -> 0 | O13: =R13/7 -> 0 | P13: =SUMIFS('Отчет 26-31.01'!H:H,'Отчет 26-31.01'!D:D,"Выручка",'Отчет 26-31.01'!E:E,B13) -> 0 | Q13: =SUMIFS('Отчет 26-31.01'!H:H,'Отчет 26-31.01'!D:D,"Возврат выручки",'Отчет 26-31.01'!E:E,B13) -> 0 | R13: =P13-Q13 -> 0 | S13: =SUMIFS('Отчет 26-31.01'!P:P,'Отчет 26-31.01'!C:C,"Продажи",'Отчет 26-31.01'!E:E,B13) -> 0 | T13: =SUMIFS('Отчет 26-31.01'!P:P,'Отчет 26-31.01'!C:C,"Возвраты",'Отчет 26-31.01'!E:E,B13) -> 0 | U13: =S13+T13 -> 0 | V13: =U13/$U$24 -> #DIV/0! | W13: =R13*H13 -> 0 | X13: =-SUMIFS('Отчет 26-31.01'!P:P,'Отчет 26-31.01'!C:C,"Вознаграждение Ozon",'Отчет 26-31.01'!E:E,B13) -> 0 | Y13: =IF(U13=0,0,X13/U13) -> 0 | Z13: =-SUMIFS('Отчет 26-31.01'!P:P,'Отчет 26-31.01'!C:C,"Услуги доставки",'Отчет 26-31.01'!E:E,B13) -> 0 | AD13: =U13*5.71% -> 0 | AE13: =U13-W13-X13-Z13-AA13-AB13-AC13-AD13 -> 0 | AG13: =IF(R13=0,0,U13/R13) -> 0 | AH13: =H13 -> 123 | AI13: =IF(R13=0,0,X13/R13) -> 0 | AJ13: =IF(P13=0,Z13/1,Z13/P13) -> 0 | AK13: =IF(P13=0,0,AA13/P13) -> 0 | AL13: {=_xlfn.IFS(R13=0,AE13,R13<0,AE13/-R13,R13>0,AE13/R13)} -> 0 | AM13: =IF(AG13=0,0,AL13/AG13) -> 0 | AN13: =IF(AH13=0,0,AL13/AH13) -> 0 | AP13: =AL13*C13 -> 0
A14: 3405092868 | B14: flip синий | H14: 123 | I14: =C14*H14 -> 0 | N14: =K14/7 -> 0 | O14: =R14/7 -> 0 | P14: =SUMIFS('Отчет 26-31.01'!H:H,'Отчет 26-31.01'!D:D,"Выручка",'Отчет 26-31.01'!E:E,B14) -> 0 | Q14: =SUMIFS('Отчет 26-31.01'!H:H,'Отчет 26-31.01'!D:D,"Возврат выручки",'Отчет 26-31.01'!E:E,B14) -> 0 | R14: =P14-Q14 -> 0 | S14: =SUMIFS('Отчет 26-31.01'!P:P,'Отчет 26-31.01'!C:C,"Продажи",'Отчет 26-31.01'!E:E,B14) -> 0 | T14: =SUMIFS('Отчет 26-31.01'!P:P,'Отчет 26-31.01'!C:C,"Возвраты",'Отчет 26-31.01'!E:E,B14) -> 0 | U14: =S14+T14 -> 0 | V14: =U14/$U$24 -> #DIV/0! | W14: =R14*H14 -> 0 | X14: =-SUMIFS('Отчет 26-31.01'!P:P,'Отчет 26-31.01'!C:C,"Вознаграждение Ozon",'Отчет 26-31.01'!E:E,B14) -> 0 | Y14: =IF(U14=0,0,X14/U14) -> 0 | Z14: =-SUMIFS('Отчет 26-31.01'!P:P,'Отчет 26-31.01'!C:C,"Услуги доставки",'Отчет 26-31.01'!E:E,B14) -> 0 | AD14: =U14*5.71% -> 0 | AE14: =U14-W14-X14-Z14-AA14-AB14-AC14-AD14 -> 0 | AG14: =IF(R14=0,0,U14/R14) -> 0 | AH14: =H14 -> 123 | AI14: =IF(R14=0,0,X14/R14) -> 0 | AJ14: =IF(P14=0,Z14/1,Z14/P14) -> 0 | AK14: =IF(P14=0,0,AA14/P14) -> 0 | AL14: {=_xlfn.IFS(R14=0,AE14,R14<0,AE14/-R14,R14>0,AE14/R14)} -> 0 | AM14: =IF(AG14=0,0,AL14/AG14) -> 0 | AN14: =IF(AH14=0,0,AL14/AH14) -> 0 | AP14: =AL14*C14 -> 0
A15: 3064346642 | B15: flip жел | H15: 123 | I15: =C15*H15 -> 0 | N15: =K15/7 -> 0 | O15: =R15/7 -> 0 | P15: =SUMIFS('Отчет 26-31.01'!H:H,'Отчет 26-31.01'!D:D,"Выручка",'Отчет 26-31.01'!E:E,B15) -> 0 | Q15: =SUMIFS('Отчет 26-31.01'!H:H,'Отчет 26-31.01'!D:D,"Возврат выручки",'Отчет 26-31.01'!E:E,B15) -> 0 | R15: =P15-Q15 -> 0 | S15: =SUMIFS('Отчет 26-31.01'!P:P,'Отчет 26-31.01'!C:C,"Продажи",'Отчет 26-31.01'!E:E,B15) -> 0 | T15: =SUMIFS('Отчет 26-31.01'!P:P,'Отчет 26-31.01'!C:C,"Возвраты",'Отчет 26-31.01'!E:E,B15) -> 0 | U15: =S15+T15 -> 0 | V15: =U15/$U$24 -> #DIV/0! | W15: =R15*H15 -> 0 | X15: =-SUMIFS('Отчет 26-31.01'!P:P,'Отчет 26-31.01'!C:C,"Вознаграждение Ozon",'Отчет 26-31.01'!E:E,B15) -> 0 | Y15: =IF(U15=0,0,X15/U15) -> 0 | Z15: =-SUMIFS('Отчет 26-31.01'!P:P,'Отчет 26-31.01'!C:C,"Услуги доставки",'Отчет 26-31.01'!E:E,B15) -> 0 | AD15: =U15*5.71% -> 0 | AE15: =U15-W15-X15-Z15-AA15-AB15-AC15-AD15 -> 0 | AG15: =IF(R15=0,0,U15/R15) -> 0 | AH15: =H15 -> 123 | AI15: =IF(R15=0,0,X15/R15) -> 0 | AJ15: =IF(P15=0,Z15/1,Z15/P15) -> 0 | AK15: =IF(P15=0,0,AA15/P15) -> 0 | AL15: {=_xlfn.IFS(R15=0,AE15,R15<0,AE15/-R15,R15>0,AE15/R15)} -> 0 | AM15: =IF(AG15=0,0,AL15/AG15) -> 0 | AN15: =IF(AH15=0,0,AL15/AH15) -> 0 | AP15: =AL15*C15 -> 0
A16: 3405092287 | B16: flip коричневый | H16: 117 | I16: =C16*H16 -> 0 | N16: =K16/7 -> 0 | O16: =R16/7 -> 0 | P16: =SUMIFS('Отчет 26-31.01'!H:H,'Отчет 26-31.01'!D:D,"Выручка",'Отчет 26-31.01'!E:E,B16) -> 0 | Q16: =SUMIFS('Отчет 26-31.01'!H:H,'Отчет 26-31.01'!D:D,"Возврат выручки",'Отчет 26-31.01'!E:E,B16) -> 0 | R16: =P16-Q16 -> 0 | S16: =SUMIFS('Отчет 26-31.01'!P:P,'Отчет 26-31.01'!C:C,"Продажи",'Отчет 26-31.01'!E:E,B16) -> 0 | T16: =SUMIFS('Отчет 26-31.01'!P:P,'Отчет 26-31.01'!C:C,"Возвраты",'Отчет 26-31.01'!E:E,B16) -> 0 | U16: =S16+T16 -> 0 | V16: =U16/$U$24 -> #DIV/0! | W16: =R16*H16 -> 0 | X16: =-SUMIFS('Отчет 26-31.01'!P:P,'Отчет 26-31.01'!C:C,"Вознаграждение Ozon",'Отчет 26-31.01'!E:E,B16) -> 0 | Y16: =IF(U16=0,0,X16/U16) -> 0 | Z16: =-SUMIFS('Отчет 26-31.01'!P:P,'Отчет 26-31.01'!C:C,"Услуги доставки",'Отчет 26-31.01'!E:E,B16) -> 0 | AD16: =U16*5.71% -> 0 | AE16: =U16-W16-X16-Z16-AA16-AB16-AC16-AD16 -> 0 | AG16: =IF(R16=0,0,U16/R16) -> 0 | AH16: =H16 -> 117 | AI16: =IF(R16=0,0,X16/R16) -> 0 | AJ16: =IF(P16=0,Z16/1,Z16/P16) -> 0 | AK16: =IF(P16=0,0,AA16/P16) -> 0 | AL16: {=_xlfn.IFS(R16=0,AE16,R16<0,AE16/-R16,R16>0,AE16/R16)} -> 0 | AM16: =IF(AG16=0,0,AL16/AG16) -> 0 | AN16: =IF(AH16=0,0,AL16/AH16) -> 0 | AP16: =AL16*C16 -> 0
AG17: =AVERAGEIF(AG3:AG15,"<>0",AG3:AG15) -> #DIV/0! | AH17: =AVERAGEIF(AH3:AH15,"<>0",AH3:AH15) -> 127.26 | AI17: =AVERAGEIF(AI3:AI15,"<>0",AI3:AI15) -> #DIV/0! | AJ17: =AVERAGEIF(AJ3:AJ15,"<>0",AJ3:AJ15) -> #DIV/0! | AK17: =AVERAGEIF(AK3:AK15,"<>0",AK3:AK15) -> #DIV/0! | AL17: =AVERAGEIF(AL3:AL15,"<>0",AL3:AL15) -> #DIV/0! | AM17: =AVERAGEIF(AM3:AM15,"<>0",AM3:AM15) -> #DIV/0! | AN17: =AVERAGEIF(AN3:AN15,"<>0",AN3:AN15) -> #DIV/0!
A18: Итого очки | C18: =SUM(C3:C16) -> 0 | E18: 108496 | F18: 597 | G18: 295 | I18: =SUM(I3:I16) -> 0 | K18: =SUM(K3:K16) -> 0 | P18: =SUM(P3:P16) -> 0 | Q18: =SUM(Q3:Q16) -> 0 | R18: =SUM(R3:R16) -> 0 | S18: =SUM(S3:S16) -> 0 | T18: =SUM(T3:T16) -> 0 | U18: =SUM(U3:U16) -> 0 | V18: =SUM(V3:V16) -> #DIV/0! | W18: =SUM(W3:W16) -> 0 | X18: =SUM(X3:X16) -> 0 | Y18: =IF(U18=0,0,X18/U18) -> 0 | Z18: =SUM(Z3:Z16) -> 0 | AA18: =IFERROR(P18*AA24/P24,0) -> 0 | AB18: =SUM(AB3:AB16) -> 0 | AC18: =SUM(AC3:AC16) -> 0 | AD18: =SUM(AD3:AD16) -> 0 | AE18: =SUM(AE3:AE16) -> 0 | AP18: =SUM(AP3:AP16) -> 0 | AZ18: 18592777
AA19: =SUM(AA3:AA15) -> 0
AG21: =AVERAGEIF(AG20:AG20,"<>0",AG20:AG20) -> #DIV/0! | AH21: =AVERAGEIF(AH20:AH20,"<>0",AH20:AH20) -> #DIV/0! | AI21: =AVERAGEIF(AI20:AI20,"<>0",AI20:AI20) -> #DIV/0! | AJ21: =AVERAGEIF(AJ20:AJ20,"<>0",AJ20:AJ20) -> #DIV/0! | AK21: =AVERAGEIF(AK20:AK20,"<>0",AK20:AK20) -> #DIV/0! | AL21: =AVERAGEIF(AL20:AL20,"<>0",AL20:AL20) -> #DIV/0! | AM21: =AVERAGEIF(AM20:AM20,"<>0",AM20:AM20) -> #DIV/0! | AN21: =AVERAGEIF(AN20:AN20,"<>0",AN20:AN20) -> #DIV/0!
C22: =SUM(C20:C20) -> 0 | I22: =SUM(I20:I20) -> 0 | K22: =SUM(K20:K20) -> 0 | P22: =SUM(P20:P20) -> 0 | Q22: =SUM(Q20:Q20) -> 0 | R22: =SUM(R20:R20) -> 0 | S22: =SUM(S20:S20) -> 0 | T22: =SUM(T20:T20) -> 0 | U22: =SUM(U20:U20) -> 0 | V22: =SUM(V20:V20) -> 0 | W22: =SUM(W20:W20) -> 0 | X22: =SUM(X20:X20) -> 0 | Y22: =IF(U22=0,0,X22/U22) -> 0 | Z22: =SUM(Z20:Z20) -> 0 | AA22: =IFERROR(P22*AA24/P24,0) -> 0 | AB22: =SUM(AB20:AB20) -> 0 | AC22: =SUM(AC20:AC20) -> 0 | AD22: =SUM(AD20:AD20) -> 0 | AE22: =SUM(AE20:AE20) -> 0 | AP22: =SUM(AP20:AP20) -> 0
AA23: =SUM(AA20:AA20) -> 0
A24: ИТОГО | C24: =C18+C22 -> 0 | D24: =SUM(D3:D20) -> 0 | E24: =SUM(E3:E20) -> 108496 | F24: =SUM(F3:F20) -> 597 | G24: =SUM(G3:G20) -> 295 | I24: =I18+I22 -> 0 | J24: =J18+J22 -> 0 | K24: =K18+K22 -> 0 | P24: =P18+P22 -> 0 | Q24: =Q18+Q22 -> 0 | R24: =R18-R22 -> 0 | S24: =S18+S22 -> 0 | T24: =T18+T22 -> 0 | U24: =U18+U22 -> 0 | V24: =V18+V22 -> #DIV/0! | W24: =W18+W22 -> 0 | X24: =X18+X22 -> 0 | Y24: =X24/U24 -> #DIV/0! | Z24: =Z18+Z22 -> 0 | AC24: =SUM(AC3:AC20) -> 0 | AD24: =AD18+AD22 -> 0 | AE24: =AE18+AE22 -> 0 | AK24: =AA25/P24 -> #DIV/0! | AP24: =SUM(AP3:AP20) -> 0
AA25: =AA18+AA22 -> 0
AA26: =AA19+AA23 -> 0
I29: Себестоимость остатков | K29: Прибыль с остатков | L29: Рентабельность товарных остатков
H31: до 60 дн | I31: =SUMIF(J3:J20,"<60",I3:I20) -> 0 | J31: =I31/I24 -> #DIV/0! | K31: =SUMIF(J3:J20,"<60",AP3:AP20) -> 0 | L31: =K31/I31 -> #DIV/0!
H32: 60-120 дн | I32: =I24-I33-I31 -> 0 | J32: =I32/I24 -> #DIV/0! | K32: =AP24-K31-K33 -> 0 | L32: =K32/I32 -> #DIV/0!
H33: > 120 дн | I33: =SUMIF(J3:J20,">120",I3:I20) -> 0 | J33: =I33/I24 -> #DIV/0! | K33: =SUMIF(J3:J20,">120",AP3:AP20) -> 0 | L33: =K33/I33 -> #DIV/0!
H35: Если товар на сайте менее 30 дней - оборачиваемость 0

Sheet Юнит 19-25.01
B1: 19-25.01 | AG1: на 1 единицу проданного товара
B2: Артикул поставщика | C2: Остаток на 26.01 | D2: В пути до клиента | E2: В пути от клиента | F2: Итого по складам ВБ | G2: Остаток на нашем складе на 02.09 | H2: Себетоимость на 1 ед на 29.09.25 | I2: Себестоимость остатков | J2: Оборачиваемость, дн | K2: Заказы, шт 7 дней | L2: Средняя цена, руб (столбец 32, AG) | M2: % выкупа за 7 дней (столбец 23, X) | N2: Скорость заказов | O2: Скорость продаж | P2: Кол-во ПРОДАЖИ | Q2: Кол-во ВОЗВРАТЫ | R2: Кол-во ПРОДАЖИ-ВОЗВРАТЫ | S2: Выручка ПРОДАЖИ | T2: Выручка ВОЗВРАТЫ | U2: Выручка с учетом согласованной скидки ПРОДАЖИ - ВОЗВРАТЫ | V2: Доля выручки, % от общего объема | W2: Себестоимость продаж | X2: Комиссия, руб | Y2: Комиссия, % | Z2: Логистика | AA2: Реклама | AB2: Хранение | AC2: Штрафы | AD2: Налог 1%+ НДС 5% | AE2: Прибыль | AG2: Выручка на 1 ед (средняя цена продажи со скидкой) | AH2: Себестоимость на 1 ед | AI2: Комиссия на 1 ед | AJ2: Логистика на 1 ед | AK2: Реклама на 1 ед | AL2: Прибыль на 1 ед | AM2: Маржинальность, % | AN2: Рентабельность, % | AP2: Прибыль с остатков
A3: 2676784153 | B3: черные с железкой классика | C3: 370 | H3: 142.98 | I3: =C3*H3 -> 52902.6 | K3: 3 | N3: =K3/7 -> 0.42857143 | O3: =R3/7 -> 0.71428571 | P3: =SUMIFS('Отчет 19-25.01'!H:H,'Отчет 19-25.01'!D:D,"Выручка",'Отчет 19-25.01'!E:E,B3) -> 5 | Q3: =SUMIFS('Отчет 19-25.01'!H:H,'Отчет 19-25.01'!D:D,"Возврат выручки",'Отчет 19-25.01'!E:E,B3) -> 0 | R3: =P3-Q3 -> 5 | S3: =SUMIFS('Отчет 19-25.01'!P:P,'Отчет 19-25.01'!C:C,"Продажи",'Отчет 19-25.01'!E:E,B3) -> 8046 | T3: =SUMIFS('Отчет 19-25.01'!P:P,'Отчет 19-25.01'!C:C,"Возвраты",'Отчет 19-25.01'!E:E,B3) -> 0 | U3: =S3+T3 -> 8046 | V3: =U3/$U$24 -> 0.05093082 | W3: =R3*H3 -> 714.9 | X3: =-SUMIFS('Отчет 19-25.01'!P:P,'Отчет 19-25.01'!C:C,"Вознаграждение Ozon",'Отчет 19-25.01'!E:E,B3) -> 3459.78 | Y3: =IF(U3=0,0,X3/U3) -> 0.43 | Z3: =-SUMIFS('Отчет 19-25.01'!P:P,'Отчет 19-25.01'!C:C,"Услуги доставки",'Отчет 19-25.01'!E:E,B3) -> 735.95 | AA3: 0 | AD3: =U3*5.71% -> 459.4266 | AE3: =U3-W3-X3-Z3-AA3-AB3-AC3-AD3 -> 2675.9434 | AG3: =IF(R3=0,0,U3/R3) -> 1609.2 | AH3: =H3 -> 142.98 | AI3: =IF(R3=0,0,X3/R3) -> 691.956 | AJ3: =IF(P3=0,Z3/1,Z3/P3) -> 147.19 | AK3: =IF(P3=0,0,AA3/P3) -> 0 | AL3: =_xlfn.IFS(R3=0,AE3,R3<0,AE3/-R3,R3>0,AE3/R3) -> 535.18868 | AM3: =IF(AG3=0,0,AL3/AG3) -> 0.33258059 | AN3: =IF(AH3=0,0,AL3/AH3) -> 3.7431017 | AP3: =AL3*C3 -> 198019.81
A4: 2676784638 | B4: qs черные | C4: 368 | H4: 123.09 | I4: =C4*H4 -> 45297.12 | K4: 10 | N4: =K4/7 -> 1.4285714 | O4: =R4/7 -> 1 | P4: =SUMIFS('Отчет 19-25.01'!H:H,'Отчет 19-25.01'!D:D,"Выручка",'Отчет 19-25.01'!E:E,B4) -> 7 | Q4: =SUMIFS('Отчет 19-25.01'!H:H,'Отчет 19-25.01'!D:D,"Возврат выручки",'Отчет 19-25.01'!E:E,B4) -> 0 | R4: =P4-Q4 -> 7 | S4: =SUMIFS('Отчет 19-25.01'!P:P,'Отчет 19-25.01'!C:C,"Продажи",'Отчет 19-25.01'!E:E,B4) -> 12250 | T4: =SUMIFS('Отчет 19-25.01'!P:P,'Отчет 19-25.01'!C:C,"Возвраты",'Отчет 19-25.01'!E:E,B4) -> 0 | U4: =S4+T4 -> 12250 | V4: =U4/$U$24 -> 0.077541952 | W4: =R4*H4 -> 861.63 | X4: =-SUMIFS('Отчет 19-25.01'!P:P,'Отчет 19-25.01'!C:C,"Вознаграждение Ozon",'Отчет 19-25.01'!E:E,B4) -> 5267.5 | Y4: =IF(U4=0,0,X4/U4) -> 0.43 | Z4: =-SUMIFS('Отчет 19-25.01'!P:P,'Отчет 19-25.01'!C:C,"Услуги доставки",'Отчет 19-25.01'!E:E,B4) -> 1015.78 | AA4: 103.13827 | AD4: =U4*5.71% -> 699.475 | AE4: =U4-W4-X4-Z4-AA4-AB4-AC4-AD4 -> 4302.4767 | AG4: =IF(R4=0,0,U4/R4) -> 1750 | AH4: =H4 -> 123.09 | AI4: =IF(R4=0,0,X4/R4) -> 752.5 | AJ4: =IF(P4=0,Z4/1,Z4/P4) -> 145.11143 | AK4: =IF(P4=0,0,AA4/P4) -> 14.734039 | AL4: {=_xlfn.IFS(R4=0,AE4,R4<0,AE4/-R4,R4>0,AE4/R4)} -> 614.63953 | AM4: =IF(AG4=0,0,AL4/AG4) -> 0.35122259 | AN4: =IF(AH4=0,0,AL4/AH4) -> 4.9934157 | AP4: =AL4*C4 -> 226187.35
A5: 2676784504 | B5: qs синие | C5: 379 | H5: 123.09 | I5: =C5*H5 -> 46651.11 | K5: 1 | N5: =K5/7 -> 0.14285714 | O5: =R5/7 -> 0.42857143 | P5: =SUMIFS('Отчет 19-25.01'!H:H,'Отчет 19-25.01'!D:D,"Выручка",'Отчет 19-25.01'!E:E,B5) -> 3 | Q5: =SUMIFS('Отчет 19-25.01'!H:H,'Отчет 19-25.01'!D:D,"Возврат выручки",'Отчет 19-25.01'!E:E,B5) -> 0 | R5: =P5-Q5 -> 3 | S5: =SUMIFS('Отчет 19-25.01'!P:P,'Отчет 19-25.01'!C:C,"Продажи",'Отчет 19-25.01'!E:E,B5) -> 5250 | T5: =SUMIFS('Отчет 19-25.01'!P:P,'Отчет 19-25.01'!C:C,"Возвраты",'Отчет 19-25.01'!E:E,B5) -> 0 | U5: =S5+T5 -> 5250 | V5: =U5/$U$24 -> 0.033232265 | W5: =R5*H5 -> 369.27 | X5: =-SUMIFS('Отчет 19-25.01'!P:P,'Отчет 19-25.01'!C:C,"Вознаграждение Ozon",'Отчет 19-25.01'!E:E,B5) -> 2257.5 | Y5: =IF(U5=0,0,X5/U5) -> 0.43 | Z5: =-SUMIFS('Отчет 19-25.01'!P:P,'Отчет 19-25.01'!C:C,"Услуги доставки",'Отчет 19-25.01'!E:E,B5) -> 483.61 | AA5: 0 | AD5: =U5*5.71% -> 299.775 | AE5: =U5-W5-X5-Z5-AA5-AB5-AC5-AD5 -> 1839.845 | AG5: =IF(R5=0,0,U5/R5) -> 1750 | AH5: =H5 -> 123.09 | AI5: =IF(R5=0,0,X5/R5) -> 752.5 | AJ5: =IF(P5=0,Z5/1,Z5/P5) -> 161.20333 | AK5: =IF(P5=0,0,AA5/P5) -> 0 | AL5: {=_xlfn.IFS(R5=0,AE5,R5<0,AE5/-R5,R5>0,AE5/R5)} -> 613.28167 | AM5: =IF(AG5=0,0,AL5/AG5) -> 0.35044667 | AN5: =IF(AH5=0,0,AL5/AH5) -> 4.9823842 | AP5: =AL5*C5 -> 232433.75
A6: 2676784514 | B6: qs желтые | C6: 687 | H6: 123.09 | I6: =C6*H6 -> 84562.83 | K6: 17 | N6: =K6/7 -> 2.4285714 | O6: =R6/7 -> 2.5714286 | P6: =SUMIFS('Отчет 19-25.01'!H:H,'Отчет 19-25.01'!D:D,"Выручка",'Отчет 19-25.01'!E:E,B6) -> 18 | Q6: =SUMIFS('Отчет 19-25.01'!H:H,'Отчет 19-25.01'!D:D,"Возврат выручки",'Отчет 19-25.01'!E:E,B6) -> 0 | R6: =P6-Q6 -> 18 | S6: =SUMIFS('Отчет 19-25.01'!P:P,'Отчет 19-25.01'!C:C,"Продажи",'Отчет 19-25.01'!E:E,B6) -> 31350 | T6: =SUMIFS('Отчет 19-25.01'!P:P,'Отчет 19-25.01'!C:C,"Возвраты",'Отчет 19-25.01'!E:E,B6) -> 0 | U6: =S6+T6 -> 31350 | V6: =U6/$U$24 -> 0.1984441 | W6: =R6*H6 -> 2215.62 | X6: =-SUMIFS('Отчет 19-25.01'!P:P,'Отчет 19-25.01'!C:C,"Вознаграждение Ozon",'Отчет 19-25.01'!E:E,B6) -> 13480.5 | Y6: =IF(U6=0,0,X6/U6) -> 0.43 | Z6: =-SUMIFS('Отчет 19-25.01'!P:P,'Отчет 19-25.01'!C:C,"Услуги доставки",'Отчет 19-25.01'!E:E,B6) -> 2736.46 | AA6: 2445 | AD6: =U6*5.71% -> 1790.085 | AE6: =U6-W6-X6-Z6-AA6-AB6-AC6-AD6 -> 8682.335 | AG6: =IF(R6=0,0,U6/R6) -> 1741.6667 | AH6: =H6 -> 123.09 | AI6: =IF(R6=0,0,X6/R6) -> 748.91667 | AJ6: =IF(P6=0,Z6/1,Z6/P6) -> 152.02556 | AK6: =IF(P6=0,0,AA6/P6) -> 135.83333 | AL6: {=_xlfn.IFS(R6=0,AE6,R6<0,AE6/-R6,R6>0,AE6/R6)} -> 482.35194 | AM6: =IF(AG6=0,0,AL6/AG6) -> 0.27694848 | AN6: =IF(AH6=0,0,AL6/AH6) -> 3.9186932 | AP6: =AL6*C6 -> 331375.79
A7: 2676784181 | B7: qs коричневые | C7: 700 | H7: 117.24 | I7: =C7*H7 -> 82068 | K7: 28 | N7: =K7/7 -> 4 | O7: =R7/7 -> 1.4285714 | P7: =SUMIFS('Отчет 19-25.01'!H:H,'Отчет 19-25.01'!D:D,"Выручка",'Отчет 19-25.01'!E:E,B7) -> 10 | Q7: =SUMIFS('Отчет 19-25.01'!H:H,'Отчет 19-25.01'!D:D,"Возврат выручки",'Отчет 19-25.01'!E:E,B7) -> 0 | R7: =P7-Q7 -> 10 | S7: =SUMIFS('Отчет 19-25.01'!P:P,'Отчет 19-25.01'!C:C,"Продажи",'Отчет 19-25.01'!E:E,B7) -> 17500 | T7: =SUMIFS('Отчет 19-25.01'!P:P,'Отчет 19-25.01'!C:C,"Возвраты",'Отчет 19-25.01'!E:E,B7) -> 0 | U7: =S7+T7 -> 17500 | V7: =U7/$U$24 -> 0.11077422 | W7: =R7*H7 -> 1172.4 | X7: =-SUMIFS('Отчет 19-25.01'!P:P,'Отчет 19-25.01'!C:C,"Вознаграждение Ozon",'Отчет 19-25.01'!E:E,B7) -> 7525 | Y7: =IF(U7=0,0,X7/U7) -> 0.43 | Z7: =-SUMIFS('Отчет 19-25.01'!P:P,'Отчет 19-25.01'!C:C,"Услуги доставки",'Отчет 19-25.01'!E:E,B7) -> 1468.48 | AA7: 5523.1118 | AD7: =U7*5.71% -> 999.25 | AE7: =U7-W7-X7-Z7-AA7-AB7-AC7-AD7 -> 811.7582 | AG7: =IF(R7=0,0,U7/R7) -> 1750 | AH7: =H7 -> 117.24 | AI7: =IF(R7=0,0,X7/R7) -> 752.5 | AJ7: =IF(P7=0,Z7/1,Z7/P7) -> 146.848 | AK7: =IF(P7=0,0,AA7/P7) -> 552.31118 | AL7: {=_xlfn.IFS(R7=0,AE7,R7<0,AE7/-R7,R7>0,AE7/R7)} -> 81.17582 | AM7: =IF(AG7=0,0,AL7/AG7) -> 0.046386183 | AN7: =IF(AH7=0,0,AL7/AH7) -> 0.69239014 | AP7: =AL7*C7 -> 56823.074
A8: 2676783005 | B8: MR8854 C2 | C8: 356 | H8: 169.89 | I8: =C8*H8 -> 60480.84 | K8: 8 | N8: =K8/7 -> 1.1428571 | O8: =R8/7 -> 0.42857143 | P8: =SUMIFS('Отчет 19-25.01'!H:H,'Отчет 19-25.01'!D:D,"Выручка",'Отчет 19-25.01'!E:E,B8) -> 4 | Q8: =SUMIFS('Отчет 19-25.01'!H:H,'Отчет 19-25.01'!D:D,"Возврат выручки",'Отчет 19-25.01'!E:E,B8) -> 1 | R8: =P8-Q8 -> 3 | S8: =SUMIFS('Отчет 19-25.01'!P:P,'Отчет 19-25.01'!C:C,"Продажи",'Отчет 19-25.01'!E:E,B8) -> 7000 | T8: =SUMIFS('Отчет 19-25.01'!P:P,'Отчет 19-25.01'!C:C,"Возвраты",'Отчет 19-25.01'!E:E,B8) -> -1202 | U8: =S8+T8 -> 5798 | V8: =U8/$U$24 -> 0.036701081 | W8: =R8*H8 -> 509.67 | X8: =-SUMIFS('Отчет 19-25.01'!P:P,'Отчет 19-25.01'!C:C,"Вознаграждение Ozon",'Отчет 19-25.01'!E:E,B8) -> 2493.14 | Y8: =IF(U8=0,0,X8/U8) -> 0.43 | Z8: =-SUMIFS('Отчет 19-25.01'!P:P,'Отчет 19-25.01'!C:C,"Услуги доставки",'Отчет 19-25.01'!E:E,B8) -> 598.84 | AA8: 2927.955 | AD8: =U8*5.71% -> 331.0658 | AE8: =U8-W8-X8-Z8-AA8-AB8-AC8-AD8 -> -1062.6708 | AG8: =IF(R8=0,0,U8/R8) -> 1932.6667 | AH8: =H8 -> 169.89 | AI8: =IF(R8=0,0,X8/R8) -> 831.04667 | AJ8: =IF(P8=0,Z8/1,Z8/P8) -> 149.71 | AK8: =IF(P8=0,0,AA8/P8) -> 731.98874 | AL8: {=_xlfn.IFS(R8=0,AE8,R8<0,AE8/-R8,R8>0,AE8/R8)} -> -354.22359 | AM8: =IF(AG8=0,0,AL8/AG8) -> -0.1832823 | AN8: =IF(AH8=0,0,AL8/AH8) -> -2.0850173 | AP8: =AL8*C8 -> -126103.6
A9: 3405092860 | B9: th черн | C9: 0 | H9: 123 | I9: =C9*H9 -> 0 | K9: 0 | N9: =K9/7 -> 0 | O9: =R9/7 -> 0 | P9: =SUMIFS('Отчет 19-25.01'!H:H,'Отчет 19-25.01'!D:D,"Выручка",'Отчет 19-25.01'!E:E,B9) -> 0 | Q9: =SUMIFS('Отчет 19-25.01'!H:H,'Отчет 19-25.01'!D:D,"Возврат выручки",'Отчет 19-25.01'!E:E,B9) -> 0 | R9: =P9-Q9 -> 0 | S9: =SUMIFS('Отчет 19-25.01'!P:P,'Отчет 19-25.01'!C:C,"Продажи",'Отчет 19-25.01'!E:E,B9) -> 0 | T9: =SUMIFS('Отчет 19-25.01'!P:P,'Отчет 19-25.01'!C:C,"Возвраты",'Отчет 19-25.01'!E:E,B9) -> 0 | U9: =S9+T9 -> 0 | V9: =U9/$U$24 -> 0 | W9: =R9*H9 -> 0 | X9: =-SUMIFS('Отчет 19-25.01'!P:P,'Отчет 19-25.01'!C:C,"Вознаграждение Ozon",'Отчет 19-25.01'!E:E,B9) -> 0 | Y9: =IF(U9=0,0,X9/U9) -> 0 | Z9: =-SUMIFS('Отчет 19-25.01'!P:P,'Отчет 19-25.01'!C:C,"Услуги доставки",'Отчет 19-25.01'!E:E,B9) -> 0 | AA9: 0 | AD9: =U9*5.71% -> 0 | AE9: =U9-W9-X9-Z9-AA9-AB9-AC9-AD9 -> 0 | AG9: =IF(R9=0,0,U9/R9) -> 0 | AH9: =H9 -> 123 | AI9: =IF(R9=0,0,X9/R9) -> 0 | AJ9: =IF(P9=0,Z9/1,Z9/P9) -> 0 | AK9: =IF(P9=0,0,AA9/P9) -> 0 | AL9: {=_xlfn.IFS(R9=0,AE9,R9<0,AE9/-R9,R9>0,AE9/R9)} -> 0 | AM9: =IF(AG9=0,0,AL9/AG9) -> 0 | AN9: =IF(AH9=0,0,AL9/AH9) -> 0 | AP9: =AL9*C9 -> 0
A10: 3405092836 | B10: th син | C10: 0 | H10: 123 | I10: =C10*H10 -> 0 | K10: 0 | N10: =K10/7 -> 0 | O10: =R10/7 -> 0 | P10: =SUMIFS('Отчет 19-25.01'!H:H,'Отчет 19-25.01'!D:D,"Выручка",'Отчет 19-25.01'!E:E,B10) -> 0 | Q10: =SUMIFS('Отчет 19-25.01'!H:H,'Отчет 19-25.01'!D:D,"Возврат выручки",'Отчет 19-25.01'!E:E,B10) -> 0 | R10: =P10-Q10 -> 0 | S10: =SUMIFS('Отчет 19-25.01'!P:P,'Отчет 19-25.01'!C:C,"Продажи",'Отчет 19-25.01'!E:E,B10) -> 0 | T10: =SUMIFS('Отчет 19-25.01'!P:P,'Отчет 19-25.01'!C:C,"Возвраты",'Отчет 19-25.01'!E:E,B10) -> 0 | U10: =S10+T10 -> 0 | V10: =U10/$U$24 -> 0 | W10: =R10*H10 -> 0 | X10: =-SUMIFS('Отчет 19-25.01'!P:P,'Отчет 19-25.01'!C:C,"Вознаграждение Ozon",'Отчет 19-25.01'!E:E,B10) -> 0 | Y10: =IF(U10=0,0,X10/U10) -> 0 | Z10: =-SUMIFS('Отчет 19-25.01'!P:P,'Отчет 19-25.01'!C:C,"Услуги доставки",'Отчет 19-25.01'!E:E,B10) -> 0 | AA10: 0 | AD10: =U10*5.71% -> 0 | AE10: =U10-W10-X10-Z10-AA10-AB10-AC10-AD10 -> 0 | AG10: =IF(R10=0,0,U10/R10) -> 0 | AH10: =H10 -> 123 | AI10: =IF(R10=0,0,X10/R10) -> 0 | AJ10: =IF(P10=0,Z10/1,Z10/P10) -> 0 | AK10: =IF(P10=0,0,AA10/P10) -> 0 | AL10: {=_xlfn.IFS(R10=0,AE10,R10<0,AE10/-R10,R10>0,AE10/R10)} -> 0 | AM10: =IF(AG10=0,0,AL10/AG10) -> 0 | AN10: =IF(AH10=0,0,AL10/AH10) -> 0 | AP10: =AL10*C10 -> 0
A11: 3064346962 | B11: th желт | C11: 243 | H11: 123 | I11: =C11*H11 -> 29889 | K11: 42 | N11: =K11/7 -> 6 | O11: =R11/7 -> 3.7142857 | P11: =SUMIFS('Отчет 19-25.01'!H:H,'Отчет 19-25.01'!D:D,"Выручка",'Отчет 19-25.01'!E:E,B11) -> 27 | Q11: =SUMIFS('Отчет 19-25.01'!H:H,'Отчет 19-25.01'!D:D,"Возврат выручки",'Отчет 19-25.01'!E:E,B11) -> 1 | R11: =P11-Q11 -> 26 | S11: =SUMIFS('Отчет 19-25.01'!P:P,'Отчет 19-25.01'!C:C,"Продажи",'Отчет 19-25.01'!E:E,B11) -> 48546 | T11: =SUMIFS('Отчет 19-25.01'!P:P,'Отчет 19-25.01'!C:C,"Возвраты",'Отчет 19-25.01'!E:E,B11) -> -2027 | U11: =S11+T11 -> 46519 | V11: =U11/$U$24 -> 0.29446319 | W11: =R11*H11 -> 3198 | X11: =-SUMIFS('Отчет 19-25.01'!P:P,'Отчет 19-25.01'!C:C,"Вознаграждение Ozon",'Отчет 19-25.01'!E:E,B11) -> 20003.17 | Y11: =IF(U11=0,0,X11/U11) -> 0.43 | Z11: =-SUMIFS('Отчет 19-25.01'!P:P,'Отчет 19-25.01'!C:C,"Услуги доставки",'Отчет 19-25.01'!E:E,B11) -> 5471.21 | AA11: 14720.186 | AD11: =U11*5.71% -> 2656.2349 | AE11: =U11-W11-X11-Z11-AA11-AB11-AC11-AD11 -> 470.19917 | AG11: =IF(R11=0,0,U11/R11) -> 1789.1923 | AH11: =H11 -> 123 | AI11: =IF(R11=0,0,X11/R11) -> 769.35269 | AJ11: =IF(P11=0,Z11/1,Z11/P11) -> 202.63741 | AK11: =IF(P11=0,0,AA11/P11) -> 545.19207 | AL11: {=_xlfn.IFS(R11=0,AE11,R11<0,AE11/-R11,R11>0,AE11/R11)} -> 18.084584 | AM11: =IF(AG11=0,0,AL11/AG11) -> 0.01010768 | AN11: =IF(AH11=0,0,AL11/AH11) -> 0.14702913 | AP11: =AL11*C11 -> 4394.5538
A12: 3405092873 | B12: th коричн | C12: 0 | H12: 117 | I12: =C12*H12 -> 0 | K12: 0 | N12: =K12/7 -> 0 | O12: =R12/7 -> 0 | P12: =SUMIFS('Отчет 19-25.01'!H:H,'Отчет 19-25.01'!D:D,"Выручка",'Отчет 19-25.01'!E:E,B12) -> 0 | Q12: =SUMIFS('Отчет 19-25.01'!H:H,'Отчет 19-25.01'!D:D,"Возврат выручки",'Отчет 19-25.01'!E:E,B12) -> 0 | R12: =P12-Q12 -> 0 | S12: =SUMIFS('Отчет 19-25.01'!P:P,'Отчет 19-25.01'!C:C,"Продажи",'Отчет 19-25.01'!E:E,B12) -> 0 | T12: =SUMIFS('Отчет 19-25.01'!P:P,'Отчет 19-25.01'!C:C,"Возвраты",'Отчет 19-25.01'!E:E,B12) -> 0 | U12: =S12+T12 -> 0 | V12: =U12/$U$24 -> 0 | W12: =R12*H12 -> 0 | X12: =-SUMIFS('Отчет 19-25.01'!P:P,'Отчет 19-25.01'!C:C,"Вознаграждение Ozon",'Отчет 19-25.01'!E:E,B12) -> 0 | Y12: =IF(U12=0,0,X12/U12) -> 0 | Z12: =-SUMIFS('Отчет 19-25.01'!P:P,'Отчет 19-25.01'!C:C,"Услуги доставки",'Отчет 19-25.01'!E:E,B12) -> 0 | AA12: 0 | AD12: =U12*5.71% -> 0 | AE12: =U12-W12-X12-Z12-AA12-AB12-AC12-AD12 -> 0 | AG12: =IF(R12=0,0,U12/R12) -> 0 | AH12: =H12 -> 117 | AI12: =IF(R12=0,0,X12/R12) -> 0 | AJ12: =IF(P12=0,Z12/1,Z12/P12) -> 0 | AK12: =IF(P12=0,0,AA12/P12) -> 0 | AL12: {=_xlfn.IFS(R12=0,AE12,R12<0,AE12/-R12,R12>0,AE12/R12)} -> 0 | AM12: =IF(AG12=0,0,AL12/AG12) -> 0 | AN12: =IF(AH12=0,0,AL12/AH12) -> 0 | AP12: =AL12*C12 -> 0
A13: 3405092993 | B13: flip черный | C13: 0 | H13: 123 | I13: =C13*H13 -> 0 | K13: 0 | N13: =K13/7 -> 0 | O13: =R13/7 -> 0 | P13: =SUMIFS('Отчет 19-25.01'!H:H,'Отчет 19-25.01'!D:D,"Выручка",'Отчет 19-25.01'!E:E,B13) -> 0 | Q13: =SUMIFS('Отчет 19-25.01'!H:H,'Отчет 19-25.01'!D:D,"Возврат выручки",'Отчет 19-25.01'!E:E,B13) -> 0 | R13: =P13-Q13 -> 0 | S13: =SUMIFS('Отчет 19-25.01'!P:P,'Отчет 19-25.01'!C:C,"Продажи",'Отчет 19-25.01'!E:E,B13) -> 0 | T13: =SUMIFS('Отчет 19-25.01'!P:P,'Отчет 19-25.01'!C:C,"Возвраты",'Отчет 19-25.01'!E:E,B13) -> 0 | U13: =S13+T13 -> 0 | V13: =U13/$U$24 -> 0 | W13: =R13*H13 -> 0 | X13: =-SUMIFS('Отчет 19-25.01'!P:P,'Отчет 19-25.01'!C:C,"Вознаграждение Ozon",'Отчет 19-25.01'!E:E,B13) -> 0 | Y13: =IF(U13=0,0,X13/U13) -> 0 | Z13: =-SUMIFS('Отчет 19-25.01'!P:P,'Отчет 19-25.01'!C:C,"Услуги доставки",'Отчет 19-25.01'!E:E,B13) -> 0 | AA13: 0 | AD13: =U13*5.71% -> 0 | AE13: =U13-W13-X13-Z13-AA13-AB13-AC13-AD13 -> 0 | AG13: =IF(R13=0,0,U13/R13) -> 0 | AH13: =H13 -> 123 | AI13: =IF(R13=0,0,X13/R13) -> 0 | AJ13: =IF(P13=0,Z13/1,Z13/P13) -> 0 | AK13: =IF(P13=0,0,AA13/P13) -> 0 | AL13: {=_xlfn.IFS(R13=0,AE13,R13<0,AE13/-R13,R13>0,AE13/R13)} -> 0 | AM13: =IF(AG13=0,0,AL13/AG13) -> 0 | AN13: =IF(AH13=0,0,AL13/AH13) -> 0 | AP13: =AL13*C13 -> 0
A14: 3405092868 | B14: flip синий | C14: 0 | H14: 123 | I14: =C14*H14 -> 0 | K14: 0 | N14: =K14/7 -> 0 | O14: =R14/7 -> 0 | P14: =SUMIFS('Отчет 19-25.01'!H:H,'Отчет 19-25.01'!D:D,"Выручка",'Отчет 19-25.01'!E:E,B14) -> 0 | Q14: =SUMIFS('Отчет 19-25.01'!H:H,'Отчет 19-25.01'!D:D,"Возврат выручки",'Отчет 19-25.01'!E:E,B14) -> 0 | R14: =P14-Q14 -> 0 | S14: =SUMIFS('Отчет 19-25.01'!P:P,'Отчет 19-25.01'!C:C,"Продажи",'Отчет 19-25.01'!E:E,B14) -> 0 | T14: =SUMIFS('Отчет 19-25.01'!P:P,'Отчет 19-25.01'!C:C,"Возвраты",'Отчет 19-25.01'!E:E,B14) -> 0 | U14: =S14+T14 -> 0 | V14: =U14/$U$24 -> 0 | W14: =R14*H14 -> 0 | X14: =-SUMIFS('Отчет 19-25.01'!P:P,'Отчет 19-25.01'!C:C,"Вознаграждение Ozon",'Отчет 19-25.01'!E:E,B14) -> 0 | Y14: =IF(U14=0,0,X14/U14) -> 0 | Z14: =-SUMIFS('Отчет 19-25.01'!P:P,'Отчет 19-25.01'!C:C,"Услуги доставки",'Отчет 19-25.01'!E:E,B14) -> 0 | AA14: 0 | AD14: =U14*5.71% -> 0 | AE14: =U14-W14-X14-Z14-AA14-AB14-AC14-AD14 -> 0 | AG14: =IF(R14=0,0,U14/R14) -> 0 | AH14: =H14 -> 123 | AI14: =IF(R14=0,0,X14/R14) -> 0 | AJ14: =IF(P14=0,Z14/1,Z14/P14) -> 0 | AK14: =IF(P14=0,0,AA14/P14) -> 0 | AL14: {=_xlfn.IFS(R14=0,AE14,R14<0,AE14/-R14,R14>0,AE14/R14)} -> 0 | AM14: =IF(AG14=0,0,AL14/AG14) -> 0 | AN14: =IF(AH14=0,0,AL14/AH14) -> 0 | AP14: =AL14*C14 -> 0
A15: 3064346642 | B15: flip жел | C15: 141 | H15: 123 | I15: =C15*H15 -> 17343 | K15: 45 | N15: =K15/7 -> 6.4285714 | O15: =R15/7 -> 2.4285714 | P15: =SUMIFS('Отчет 19-25.01'!H:H,'Отчет 19-25.01'!D:D,"Выручка",'Отчет 19-25.01'!E:E,B15) -> 17 | Q15: =SUMIFS('Отчет 19-25.01'!H:H,'Отчет 19-25.01'!D:D,"Возврат выручки",'Отчет 19-25.01'!E:E,B15) -> 0 | R15: =P15-Q15 -> 17 | S15: =SUMIFS('Отчет 19-25.01'!P:P,'Отчет 19-25.01'!C:C,"Продажи",'Отчет 19-25.01'!E:E,B15) -> 31266 | T15: =SUMIFS('Отчет 19-25.01'!P:P,'Отчет 19-25.01'!C:C,"Возвраты",'Отчет 19-25.01'!E:E,B15) -> 0 | U15: =S15+T15 -> 31266 | V15: =U15/$U$24 -> 0.19791238 | W15: =R15*H15 -> 2091 | X15: =-SUMIFS('Отчет 19-25.01'!P:P,'Отчет 19-25.01'!C:C,"Вознаграждение Ozon",'Отчет 19-25.01'!E:E,B15) -> 13444.38 | Y15: =IF(U15=0,0,X15/U15) -> 0.43 | Z15: =-SUMIFS('Отчет 19-25.01'!P:P,'Отчет 19-25.01'!C:C,"Услуги доставки",'Отчет 19-25.01'!E:E,B15) -> 4479.13 | AA15: 15381.802 | AD15: =U15*5.71% -> 1785.2886 | AE15: =U15-W15-X15-Z15-AA15-AB15-AC15-AD15 -> -5915.6009 | AG15: =IF(R15=0,0,U15/R15) -> 1839.1765 | AH15: =H15 -> 123 | AI15: =IF(R15=0,0,X15/R15) -> 790.84588 | AJ15: =IF(P15=0,Z15/1,Z15/P15) -> 263.47824 | AK15: =IF(P15=0,0,AA15/P15) -> 904.8119 | AL15: {=_xlfn.IFS(R15=0,AE15,R15<0,AE15/-R15,R15>0,AE15/R15)} -> -347.97652 | AM15: =IF(AG15=0,0,AL15/AG15) -> -0.18920236 | AN15: =IF(AH15=0,0,AL15/AH15) -> -2.8290774 | AP15: =AL15*C15 -> -49064.689
A16: 3405092287 | B16: flip коричневый | C16: 0 | H16: 117 | I16: =C16*H16 -> 0 | K16: 0 | N16: =K16/7 -> 0 | O16: =R16/7 -> 0 | P16: =SUMIFS('Отчет 19-25.01'!H:H,'Отчет 19-25.01'!D:D,"Выручка",'Отчет 19-25.01'!E:E,B16) -> 0 | Q16: =SUMIFS('Отчет 19-25.01'!H:H,'Отчет 19-25.01'!D:D,"Возврат выручки",'Отчет 19-25.01'!E:E,B16) -> 0 | R16: =P16-Q16 -> 0 | S16: =SUMIFS('Отчет 19-25.01'!P:P,'Отчет 19-25.01'!C:C,"Продажи",'Отчет 19-25.01'!E:E,B16) -> 0 | T16: =SUMIFS('Отчет 19-25.01'!P:P,'Отчет 19-25.01'!C:C,"Возвраты",'Отчет 19-25.01'!E:E,B16) -> 0 | U16: =S16+T16 -> 0 | V16: =U16/$U$24 -> 0 | W16: =R16*H16 -> 0 | X16: =-SUMIFS('Отчет 19-25.01'!P:P,'Отчет 19-25.01'!C:C,"Вознаграждение Ozon",'Отчет 19-25.01'!E:E,B16) -> 0 | Y16: =IF(U16=0,0,X16/U16) -> 0 | Z16: =-SUMIFS('Отчет 19-25.01'!P:P,'Отчет 19-25.01'!C:C,"Услуги доставки",'Отчет 19-25.01'!E:E,B16) -> 0 | AA16: 0 | AD16: =U16*5.71% -> 0 | AE16: =U16-W16-X16-Z16-AA16-AB16-AC16-AD16 -> 0 | AG16: =IF(R16=0,0,U16/R16) -> 0 | AH16: =H16 -> 117 | AI16: =IF(R16=0,0,X16/R16) -> 0 | AJ16: =IF(P16=0,Z16/1,Z16/P16) -> 0 | AK16: =IF(P16=0,0,AA16/P16) -> 0 | AL16: {=_xlfn.IFS(R16=0,AE16,R16<0,AE16/-R16,R16>0,AE16/R16)} -> 0 | AM16: =IF(AG16=0,0,AL16/AG16) -> 0 | AN16: =IF(AH16=0,0,AL16/AH16) -> 0 | AP16: =AL16*C16 -> 0
AG17: =AVERAGEIF(AG3:AG15,"<>0",AG3:AG15) -> 1770.2378 | AH17: =AVERAGEIF(AH3:AH15,"<>0",AH3:AH15) -> 127.26 | AI17: =AVERAGEIF(AI3:AI15,"<>0",AI3:AI15) -> 761.20224 | AJ17: =AVERAGEIF(AJ3:AJ15,"<>0",AJ3:AJ15) -> 171.0255 | AK17: =AVERAGEIF(AK3:AK15,"<>0",AK3:AK15) -> 480.81188 | AL17: =AVERAGEIF(AL3:AL15,"<>0",AL3:AL15) -> 205.31526 | AM17: =AVERAGEIF(AM3:AM15,"<>0",AM3:AM15) -> 0.12440094 | AN17: =AVERAGEIF(AN3:AN15,"<>0",AN3:AN15) -> 1.6953649
A18: Итого очки | C18: =SUM(C3:C16) -> 3244 | E18: 108496 | F18: 597 | G18: 295 | I18: =SUM(I3:I16) -> 419194.5 | K18: =SUM(K3:K16) -> 154 | P18: =SUM(P3:P16) -> 91 | Q18: =SUM(Q3:Q16) -> 2 | R18: =SUM(R3:R16) -> 89 | S18: =SUM(S3:S16) -> 161208 | T18: =SUM(T3:T16) -> -3229 | U18: =SUM(U3:U16) -> 157979 | V18: =SUM(V3:V16) -> 1 | W18: =SUM(W3:W16) -> 11132.49 | X18: =SUM(X3:X16) -> 67930.97 | Y18: =IF(U18=0,0,X18/U18) -> 0.43 | Z18: =SUM(Z3:Z16) -> 16989.46 | AA18: =IFERROR(P18*AA24/P24,0) -> 42151.21 | AB18: =SUM(AB3:AB16) -> 0 | AC18: =SUM(AC3:AC16) -> 0 | AD18: =SUM(AD3:AD16) -> 9020.6009 | AE18: =SUM(AE3:AE16) -> 11804.286 | AP18: =SUM(AP3:AP16) -> 874066.04 | AZ18: 18592777
AA19: =SUM(AA3:AA15) -> 41101.193
AG21: =AVERAGEIF(AG20:AG20,"<>0",AG20:AG20) -> #DIV/0! | AH21: =AVERAGEIF(AH20:AH20,"<>0",AH20:AH20) -> #DIV/0! | AI21: =AVERAGEIF(AI20:AI20,"<>0",AI20:AI20) -> #DIV/0! | AJ21: =AVERAGEIF(AJ20:AJ20,"<>0",AJ20:AJ20) -> #DIV/0! | AK21: =AVERAGEIF(AK20:AK20,"<>0",AK20:AK20) -> #DIV/0! | AL21: =AVERAGEIF(AL20:AL20,"<>0",AL20:AL20) -> #DIV/0! | AM21: =AVERAGEIF(AM20:AM20,"<>0",AM20:AM20) -> #DIV/0! | AN21: =AVERAGEIF(AN20:AN20,"<>0",AN20:AN20) -> #DIV/0!
C22: =SUM(C20:C20) -> 0 | I22: =SUM(I20:I20) -> 0 | K22: =SUM(K20:K20) -> 0 | P22: =SUM(P20:P20) -> 0 | Q22: =SUM(Q20:Q20) -> 0 | R22: =SUM(R20:R20) -> 0 | S22: =SUM(S20:S20) -> 0 | T22: =SUM(T20:T20) -> 0 | U22: =SUM(U20:U20) -> 0 | V22: =SUM(V20:V20) -> 0 | W22: =SUM(W20:W20) -> 0 | X22: =SUM(X20:X20) -> 0 | Y22: =IF(U22=0,0,X22/U22) -> 0 | Z22: =SUM(Z20:Z20) -> 0 | AA22: =IFERROR(P22*AA24/P24,0) -> 0 | AB22: =SUM(AB20:AB20) -> 0 | AC22: =SUM(AC20:AC20) -> 0 | AD22: =SUM(AD20:AD20) -> 0 | AE22: =SUM(AE20:AE20) -> 0 | AP22: =SUM(AP20:AP20) -> 0
AA23: =SUM(AA20:AA20) -> 0
A24: ИТОГО | C24: =C18+C22 -> 3244 | D24: =SUM(D3:D20) -> 0 | E24: =SUM(E3:E20) -> 108496 | F24: =SUM(F3:F20) -> 597 | G24: =SUM(G3:G20) -> 295 | I24: =I18+I22 -> 419194.5 | J24: =J18+J22 -> 0 | K24: =K18+K22 -> 154 | P24: =P18+P22 -> 91 | Q24: =Q18+Q22 -> 2 | R24: =R18-R22 -> 89 | S24: =S18+S22 -> 161208 | T24: =T18+T22 -> -3229 | U24: =U18+U22 -> 157979 | V24: =V18+V22 -> 1 | W24: =W18+W22 -> 11132.49 | X24: =X18+X22 -> 67930.97 | Y24: =X24/U24 -> 0.43 | Z24: =Z18+Z22 -> 16989.46 | AA24: 42151.21 | AC24: =SUM(AC3:AC20) -> 0 | AD24: =AD18+AD22 -> 9020.6009 | AE24: =AE18+AE22 -> 11804.286 | AK24: =AA25/P24 -> 463.20011 | AP24: =SUM(AP3:AP20) -> 1748132.1
AA25: =AA18+AA22 -> 42151.21
AA26: =AA19+AA23 -> 41101.193
I29: Себестоимость остатков | K29: Прибыль с остатков | L29: Рентабельность товарных остатков
H31: до 60 дн | I31: =SUMIF(J3:J20,"<60",I3:I20) -> 0 | J31: =I31/I24 -> 0 | K31: =SUMIF(J3:J20,"<60",AP3:AP20) -> 0 | L31: =K31/I31 -> #DIV/0!
H32: 60-120 дн | I32: =I24-I33-I31 -> 419194.5 | J32: =I32/I24 -> 1 | K32: =AP24-K31-K33 -> 1748132.1 | L32: =K32/I32 -> 4.1702171
H33: > 120 дн | I33: =SUMIF(J3:J20,">120",I3:I20) -> 0 | J33: =I33/I24 -> 0 | K33: =SUMIF(J3:J20,">120",AP3:AP20) -> 0 | L33: =K33/I33 -> #DIV/0!
H35: Если товар на сайте менее 30 дней - оборачиваемость 0

Sheet Юнит 12-18.01
B1: 12-18.01 | AG1: на 1 единицу проданного товара
B2: Артикул поставщика | C2: Остаток на 19.01 | D2: В пути до клиента | E2: В пути от клиента | F2: Итого по складам ВБ | G2: Остаток на нашем складе на 02.09 | H2: Себетоимость на 1 ед на 29.09.25 | I2: Себестоимость остатков | J2: Оборачиваемость, дн | K2: Заказы, шт 7 дней | L2: Средняя цена, руб (столбец 32, AG) | M2: % выкупа за 7 дней (столбец 23, X) | N2: Скорость заказов | O2: Скорость продаж | P2: Кол-во ПРОДАЖИ | Q2: Кол-во ВОЗВРАТЫ | R2: Кол-во ПРОДАЖИ-ВОЗВРАТЫ | S2: Выручка ПРОДАЖИ | T2: Выручка ВОЗВРАТЫ | U2: Выручка с учетом согласованной скидки ПРОДАЖИ - ВОЗВРАТЫ | V2: Доля выручки, % от общего объема | W2: Себестоимость продаж | X2: Комиссия, руб | Y2: Комиссия, % | Z2: Логистика | AA2: Реклама | AB2: Хранение | AC2: Штрафы | AD2: Налог 1%+ НДС 5% | AE2: Прибыль | AG2: Выручка на 1 ед (средняя цена продажи со скидкой) | AH2: Себестоимость на 1 ед | AI2: Комиссия на 1 ед | AJ2: Логистика на 1 ед | AK2: Реклама на 1 ед | AL2: Прибыль на 1 ед | AM2: Маржинальность, % | AN2: Рентабельность, % | AP2: Прибыль с остатков
A3: 2676784153 | B3: черные с железкой классика | C3: 373 | H3: 142.98 | I3: =C3*H3 -> 53331.54 | K3: 3 | N3: =K3/7 -> 0.42857143 | O3: =R3/7 -> 0.42857143 | P3: =SUMIFS('Отчет 12-18.01'!H:H,'Отчет 12-18.01'!D:D,"Выручка",'Отчет 12-18.01'!E:E,B3) -> 3 | Q3: =SUMIFS('Отчет 12-18.01'!H:H,'Отчет 12-18.01'!D:D,"Возврат выручки",'Отчет 12-18.01'!E:E,B3) -> 0 | R3: =P3-Q3 -> 3 | S3: =SUMIFS('Отчет 12-18.01'!P:P,'Отчет 12-18.01'!C:C,"Продажи",'Отчет 12-18.01'!E:E,B3) -> 5050 | T3: =SUMIFS('Отчет 12-18.01'!P:P,'Отчет 12-18.01'!C:C,"Возвраты",'Отчет 12-18.01'!E:E,B3) -> 0 | U3: =S3+T3 -> 5050 | V3: =U3/$U$24 -> 0.024301278 | W3: =R3*H3 -> 428.94 | X3: =-SUMIFS('Отчет 12-18.01'!P:P,'Отчет 12-18.01'!C:C,"Вознаграждение Ozon",'Отчет 12-18.01'!E:E,B3) -> 2171.5 | Y3: =IF(U3=0,0,X3/U3) -> 0.43 | Z3: =-SUMIFS('Отчет 12-18.01'!P:P,'Отчет 12-18.01'!C:C,"Услуги доставки",'Отчет 12-18.01'!E:E,B3) -> 559.51 | AA3: 677.42766 | AD3: =U3*5.71% -> 288.355 | AE3: =U3-W3-X3-Z3-AA3-AB3-AC3-AD3 -> 924.26734 | AG3: =IF(R3=0,0,U3/R3) -> 1683.3333 | AH3: =H3 -> 142.98 | AI3: =IF(R3=0,0,X3/R3) -> 723.83333 | AJ3: =IF(P3=0,Z3/1,Z3/P3) -> 186.50333 | AK3: =IF(P3=0,0,AA3/P3) -> 225.80922 | AL3: =_xlfn.IFS(R3=0,AE3,R3<0,AE3/-R3,R3>0,AE3/R3) -> 308.08911 | AM3: =IF(AG3=0,0,AL3/AG3) -> 0.18302324 | AN3: =IF(AH3=0,0,AL3/AH3) -> 2.1547707 | AP3: =AL3*C3 -> 114917.24
A4: 2676784638 | B4: qs черные | C4: 379 | H4: 123.09 | I4: =C4*H4 -> 46651.11 | K4: 8 | N4: =K4/7 -> 1.1428571 | O4: =R4/7 -> 0.57142857 | P4: =SUMIFS('Отчет 12-18.01'!H:H,'Отчет 12-18.01'!D:D,"Выручка",'Отчет 12-18.01'!E:E,B4) -> 4 | Q4: =SUMIFS('Отчет 12-18.01'!H:H,'Отчет 12-18.01'!D:D,"Возврат выручки",'Отчет 12-18.01'!E:E,B4) -> 0 | R4: =P4-Q4 -> 4 | S4: =SUMIFS('Отчет 12-18.01'!P:P,'Отчет 12-18.01'!C:C,"Продажи",'Отчет 12-18.01'!E:E,B4) -> 6900 | T4: =SUMIFS('Отчет 12-18.01'!P:P,'Отчет 12-18.01'!C:C,"Возвраты",'Отчет 12-18.01'!E:E,B4) -> 0 | U4: =S4+T4 -> 6900 | V4: =U4/$U$24 -> 0.033203727 | W4: =R4*H4 -> 492.36 | X4: =-SUMIFS('Отчет 12-18.01'!P:P,'Отчет 12-18.01'!C:C,"Вознаграждение Ozon",'Отчет 12-18.01'!E:E,B4) -> 2967 | Y4: =IF(U4=0,0,X4/U4) -> 0.43 | Z4: =-SUMIFS('Отчет 12-18.01'!P:P,'Отчет 12-18.01'!C:C,"Услуги доставки",'Отчет 12-18.01'!E:E,B4) -> 514.55 | AA4: 2111.4807 | AD4: =U4*5.71% -> 393.99 | AE4: =U4-W4-X4-Z4-AA4-AB4-AC4-AD4 -> 420.61927 | AG4: =IF(R4=0,0,U4/R4) -> 1725 | AH4: =H4 -> 123.09 | AI4: =IF(R4=0,0,X4/R4) -> 741.75 | AJ4: =IF(P4=0,Z4/1,Z4/P4) -> 128.6375 | AK4: =IF(P4=0,0,AA4/P4) -> 527.87018 | AL4: {=_xlfn.IFS(R4=0,AE4,R4<0,AE4/-R4,R4>0,AE4/R4)} -> 105.15482 | AM4: =IF(AG4=0,0,AL4/AG4) -> 0.060959314 | AN4: =IF(AH4=0,0,AL4/AH4) -> 0.85429212 | AP4: =AL4*C4 -> 39853.676
A5: 2676784504 | B5: qs синие | C5: 379 | H5: 123.09 | I5: =C5*H5 -> 46651.11 | K5: 4 | N5: =K5/7 -> 0.57142857 | O5: =R5/7 -> 0.57142857 | P5: =SUMIFS('Отчет 12-18.01'!H:H,'Отчет 12-18.01'!D:D,"Выручка",'Отчет 12-18.01'!E:E,B5) -> 4 | Q5: =SUMIFS('Отчет 12-18.01'!H:H,'Отчет 12-18.01'!D:D,"Возврат выручки",'Отчет 12-18.01'!E:E,B5) -> 0 | R5: =P5-Q5 -> 4 | S5: =SUMIFS('Отчет 12-18.01'!P:P,'Отчет 12-18.01'!C:C,"Продажи",'Отчет 12-18.01'!E:E,B5) -> 6800 | T5: =SUMIFS('Отчет 12-18.01'!P:P,'Отчет 12-18.01'!C:C,"Возвраты",'Отчет 12-18.01'!E:E,B5) -> 0 | U5: =S5+T5 -> 6800 | V5: =U5/$U$24 -> 0.032722513 | W5: =R5*H5 -> 492.36 | X5: =-SUMIFS('Отчет 12-18.01'!P:P,'Отчет 12-18.01'!C:C,"Вознаграждение Ozon",'Отчет 12-18.01'!E:E,B5) -> 2924 | Y5: =IF(U5=0,0,X5/U5) -> 0.43 | Z5: =-SUMIFS('Отчет 12-18.01'!P:P,'Отчет 12-18.01'!C:C,"Услуги доставки",'Отчет 12-18.01'!E:E,B5) -> 518.42 | AA5: 711.73259 | AD5: =U5*5.71% -> 388.28 | AE5: =U5-W5-X5-Z5-AA5-AB5-AC5-AD5 -> 1765.2074 | AG5: =IF(R5=0,0,U5/R5) -> 1700 | AH5: =H5 -> 123.09 | AI5: =IF(R5=0,0,X5/R5) -> 731 | AJ5: =IF(P5=0,Z5/1,Z5/P5) -> 129.605 | AK5: =IF(P5=0,0,AA5/P5) -> 177.93315 | AL5: {=_xlfn.IFS(R5=0,AE5,R5<0,AE5/-R5,R5>0,AE5/R5)} -> 441.30185 | AM5: =IF(AG5=0,0,AL5/AG5) -> 0.25958933 | AN5: =IF(AH5=0,0,AL5/AH5) -> 3.5851966 | AP5: =AL5*C5 -> 167253.4
A6: 2676784514 | B6: qs желтые | C6: 696 | H6: 123.09 | I6: =C6*H6 -> 85670.64 | K6: 26 | N6: =K6/7 -> 3.7142857 | O6: =R6/7 -> 2.8571429 | P6: =SUMIFS('Отчет 12-18.01'!H:H,'Отчет 12-18.01'!D:D,"Выручка",'Отчет 12-18.01'!E:E,B6) -> 21 | Q6: =SUMIFS('Отчет 12-18.01'!H:H,'Отчет 12-18.01'!D:D,"Возврат выручки",'Отчет 12-18.01'!E:E,B6) -> 1 | R6: =P6-Q6 -> 20 | S6: =SUMIFS('Отчет 12-18.01'!P:P,'Отчет 12-18.01'!C:C,"Продажи",'Отчет 12-18.01'!E:E,B6) -> 36000 | T6: =SUMIFS('Отчет 12-18.01'!P:P,'Отчет 12-18.01'!C:C,"Возвраты",'Отчет 12-18.01'!E:E,B6) -> -1600 | U6: =S6+T6 -> 34400 | V6: =U6/$U$24 -> 0.16553742 | W6: =R6*H6 -> 2461.8 | X6: =-SUMIFS('Отчет 12-18.01'!P:P,'Отчет 12-18.01'!C:C,"Вознаграждение Ozon",'Отчет 12-18.01'!E:E,B6) -> 14792 | Y6: =IF(U6=0,0,X6/U6) -> 0.43 | Z6: =-SUMIFS('Отчет 12-18.01'!P:P,'Отчет 12-18.01'!C:C,"Услуги доставки",'Отчет 12-18.01'!E:E,B6) -> 3963.63 | AA6: 7852.2996 | AD6: =U6*5.71% -> 1964.24 | AE6: =U6-W6-X6-Z6-AA6-AB6-AC6-AD6 -> 3366.0304 | AG6: =IF(R6=0,0,U6/R6) -> 1720 | AH6: =H6 -> 123.09 | AI6: =IF(R6=0,0,X6/R6) -> 739.6 | AJ6: =IF(P6=0,Z6/1,Z6/P6) -> 188.74429 | AK6: =IF(P6=0,0,AA6/P6) -> 373.91903 | AL6: {=_xlfn.IFS(R6=0,AE6,R6<0,AE6/-R6,R6>0,AE6/R6)} -> 168.30152 | AM6: =IF(AG6=0,0,AL6/AG6) -> 0.097849721 | AN6: =IF(AH6=0,0,AL6/AH6) -> 1.3673046 | AP6: =AL6*C6 -> 117137.86
A7: 2676784181 | B7: qs коричневые | C7: 722 | H7: 117.24 | I7: =C7*H7 -> 84647.28 | K7: 11 | N7: =K7/7 -> 1.5714286 | O7: =R7/7 -> 1.4285714 | P7: =SUMIFS('Отчет 12-18.01'!H:H,'Отчет 12-18.01'!D:D,"Выручка",'Отчет 12-18.01'!E:E,B7) -> 10 | Q7: =SUMIFS('Отчет 12-18.01'!H:H,'Отчет 12-18.01'!D:D,"Возврат выручки",'Отчет 12-18.01'!E:E,B7) -> 0 | R7: =P7-Q7 -> 10 | S7: =SUMIFS('Отчет 12-18.01'!P:P,'Отчет 12-18.01'!C:C,"Продажи",'Отчет 12-18.01'!E:E,B7) -> 16900 | T7: =SUMIFS('Отчет 12-18.01'!P:P,'Отчет 12-18.01'!C:C,"Возвраты",'Отчет 12-18.01'!E:E,B7) -> 0 | U7: =S7+T7 -> 16900 | V7: =U7/$U$24 -> 0.081325069 | W7: =R7*H7 -> 1172.4 | X7: =-SUMIFS('Отчет 12-18.01'!P:P,'Отчет 12-18.01'!C:C,"Вознаграждение Ozon",'Отчет 12-18.01'!E:E,B7) -> 7267 | Y7: =IF(U7=0,0,X7/U7) -> 0.43 | Z7: =-SUMIFS('Отчет 12-18.01'!P:P,'Отчет 12-18.01'!C:C,"Услуги доставки",'Отчет 12-18.01'!E:E,B7) -> 1556.33 | AA7: 2926.8702 | AD7: =U7*5.71% -> 964.99 | AE7: =U7-W7-X7-Z7-AA7-AB7-AC7-AD7 -> 3012.4098 | AG7: =IF(R7=0,0,U7/R7) -> 1690 | AH7: =H7 -> 117.24 | AI7: =IF(R7=0,0,X7/R7) -> 726.7 | AJ7: =IF(P7=0,Z7/1,Z7/P7) -> 155.633 | AK7: =IF(P7=0,0,AA7/P7) -> 292.68702 | AL7: {=_xlfn.IFS(R7=0,AE7,R7<0,AE7/-R7,R7>0,AE7/R7)} -> 301.24098 | AM7: =IF(AG7=0,0,AL7/AG7) -> 0.1782491 | AN7: =IF(AH7=0,0,AL7/AH7) -> 2.5694386 | AP7: =AL7*C7 -> 217495.99
A8: 2676783005 | B8: MR8854 C2 | C8: 362 | H8: 169.89 | I8: =C8*H8 -> 61500.18 | K8: 4 | N8: =K8/7 -> 0.57142857 | O8: =R8/7 -> 1 | P8: =SUMIFS('Отчет 12-18.01'!H:H,'Отчет 12-18.01'!D:D,"Выручка",'Отчет 12-18.01'!E:E,B8) -> 7 | Q8: =SUMIFS('Отчет 12-18.01'!H:H,'Отчет 12-18.01'!D:D,"Возврат выручки",'Отчет 12-18.01'!E:E,B8) -> 0 | R8: =P8-Q8 -> 7 | S8: =SUMIFS('Отчет 12-18.01'!P:P,'Отчет 12-18.01'!C:C,"Продажи",'Отчет 12-18.01'!E:E,B8) -> 10606 | T8: =SUMIFS('Отчет 12-18.01'!P:P,'Отчет 12-18.01'!C:C,"Возвраты",'Отчет 12-18.01'!E:E,B8) -> 0 | U8: =S8+T8 -> 10606 | V8: =U8/$U$24 -> 0.051037496 | W8: =R8*H8 -> 1189.23 | X8: =-SUMIFS('Отчет 12-18.01'!P:P,'Отчет 12-18.01'!C:C,"Вознаграждение Ozon",'Отчет 12-18.01'!E:E,B8) -> 4560.58 | Y8: =IF(U8=0,0,X8/U8) -> 0.43 | Z8: =-SUMIFS('Отчет 12-18.01'!P:P,'Отчет 12-18.01'!C:C,"Услуги доставки",'Отчет 12-18.01'!E:E,B8) -> 1308.17 | AA8: 2830.7644 | AD8: =U8*5.71% -> 605.6026 | AE8: =U8-W8-X8-Z8-AA8-AB8-AC8-AD8 -> 111.65297 | AG8: =IF(R8=0,0,U8/R8) -> 1515.1429 | AH8: =H8 -> 169.89 | AI8: =IF(R8=0,0,X8/R8) -> 651.51143 | AJ8: =IF(P8=0,Z8/1,Z8/P8) -> 186.88143 | AK8: =IF(P8=0,0,AA8/P8) -> 404.39492 | AL8: {=_xlfn.IFS(R8=0,AE8,R8<0,AE8/-R8,R8>0,AE8/R8)} -> 15.950424 | AM8: =IF(AG8=0,0,AL8/AG8) -> 0.01052734 | AN8: =IF(AH8=0,0,AL8/AH8) -> 0.093886774 | AP8: =AL8*C8 -> 5774.0535
A9: 3405092860 | B9: th черн | C9: 0 | H9: 123 | I9: =C9*H9 -> 0 | K9: 0 | N9: =K9/7 -> 0 | O9: =R9/7 -> 0 | P9: =SUMIFS('Отчет 12-18.01'!H:H,'Отчет 12-18.01'!D:D,"Выручка",'Отчет 12-18.01'!E:E,B9) -> 0 | Q9: =SUMIFS('Отчет 12-18.01'!H:H,'Отчет 12-18.01'!D:D,"Возврат выручки",'Отчет 12-18.01'!E:E,B9) -> 0 | R9: =P9-Q9 -> 0 | S9: =SUMIFS('Отчет 12-18.01'!P:P,'Отчет 12-18.01'!C:C,"Продажи",'Отчет 12-18.01'!E:E,B9) -> 0 | T9: =SUMIFS('Отчет 12-18.01'!P:P,'Отчет 12-18.01'!C:C,"Возвраты",'Отчет 12-18.01'!E:E,B9) -> 0 | U9: =S9+T9 -> 0 | V9: =U9/$U$24 -> 0 | W9: =R9*H9 -> 0 | X9: =-SUMIFS('Отчет 12-18.01'!P:P,'Отчет 12-18.01'!C:C,"Вознаграждение Ozon",'Отчет 12-18.01'!E:E,B9) -> 0 | Y9: =IF(U9=0,0,X9/U9) -> 0 | Z9: =-SUMIFS('Отчет 12-18.01'!P:P,'Отчет 12-18.01'!C:C,"Услуги доставки",'Отчет 12-18.01'!E:E,B9) -> 0 | AA9: 0 | AD9: =U9*5.71% -> 0 | AE9: =U9-W9-X9-Z9-AA9-AB9-AC9-AD9 -> 0 | AG9: =IF(R9=0,0,U9/R9) -> 0 | AH9: =H9 -> 123 | AI9: =IF(R9=0,0,X9/R9) -> 0 | AJ9: =IF(P9=0,Z9/1,Z9/P9) -> 0 | AK9: =IF(P9=0,0,AA9/P9) -> 0 | AL9: {=_xlfn.IFS(R9=0,AE9,R9<0,AE9/-R9,R9>0,AE9/R9)} -> 0 | AM9: =IF(AG9=0,0,AL9/AG9) -> 0 | AN9: =IF(AH9=0,0,AL9/AH9) -> 0 | AP9: =AL9*C9 -> 0
A10: 3405092836 | B10: th син | C10: 0 | H10: 123 | I10: =C10*H10 -> 0 | K10: 0 | N10: =K10/7 -> 0 | O10: =R10/7 -> 0 | P10: =SUMIFS('Отчет 12-18.01'!H:H,'Отчет 12-18.01'!D:D,"Выручка",'Отчет 12-18.01'!E:E,B10) -> 0 | Q10: =SUMIFS('Отчет 12-18.01'!H:H,'Отчет 12-18.01'!D:D,"Возврат выручки",'Отчет 12-18.01'!E:E,B10) -> 0 | R10: =P10-Q10 -> 0 | S10: =SUMIFS('Отчет 12-18.01'!P:P,'Отчет 12-18.01'!C:C,"Продажи",'Отчет 12-18.01'!E:E,B10) -> 0 | T10: =SUMIFS('Отчет 12-18.01'!P:P,'Отчет 12-18.01'!C:C,"Возвраты",'Отчет 12-18.01'!E:E,B10) -> 0 | U10: =S10+T10 -> 0 | V10: =U10/$U$24 -> 0 | W10: =R10*H10 -> 0 | X10: =-SUMIFS('Отчет 12-18.01'!P:P,'Отчет 12-18.01'!C:C,"Вознаграждение Ozon",'Отчет 12-18.01'!E:E,B10) -> 0 | Y10: =IF(U10=0,0,X10/U10) -> 0 | Z10: =-SUMIFS('Отчет 12-18.01'!P:P,'Отчет 12-18.01'!C:C,"Услуги доставки",'Отчет 12-18.01'!E:E,B10) -> 0 | AA10: 0 | AD10: =U10*5.71% -> 0 | AE10: =U10-W10-X10-Z10-AA10-AB10-AC10-AD10 -> 0 | AG10: =IF(R10=0,0,U10/R10) -> 0 | AH10: =H10 -> 123 | AI10: =IF(R10=0,0,X10/R10) -> 0 | AJ10: =IF(P10=0,Z10/1,Z10/P10) -> 0 | AK10: =IF(P10=0,0,AA10/P10) -> 0 | AL10: {=_xlfn.IFS(R10=0,AE10,R10<0,AE10/-R10,R10>0,AE10/R10)} -> 0 | AM10: =IF(AG10=0,0,AL10/AG10) -> 0 | AN10: =IF(AH10=0,0,AL10/AH10) -> 0 | AP10: =AL10*C10 -> 0
A11: 3064346962 | B11: th желт | C11: 278 | H11: 123 | I11: =C11*H11 -> 34194 | K11: 48 | N11: =K11/7 -> 6.8571429 | O11: =R11/7 -> 5 | P11: =SUMIFS('Отчет 12-18.01'!H:H,'Отчет 12-18.01'!D:D,"Выручка",'Отчет 12-18.01'!E:E,B11) -> 36 | Q11: =SUMIFS('Отчет 12-18.01'!H:H,'Отчет 12-18.01'!D:D,"Возврат выручки",'Отчет 12-18.01'!E:E,B11) -> 1 | R11: =P11-Q11 -> 35 | S11: =SUMIFS('Отчет 12-18.01'!P:P,'Отчет 12-18.01'!C:C,"Продажи",'Отчет 12-18.01'!E:E,B11) -> 60508 | T11: =SUMIFS('Отчет 12-18.01'!P:P,'Отчет 12-18.01'!C:C,"Возвраты",'Отчет 12-18.01'!E:E,B11) -> -1621 | U11: =S11+T11 -> 58887 | V11: =U11/$U$24 -> 0.28337215 | W11: =R11*H11 -> 4305 | X11: =-SUMIFS('Отчет 12-18.01'!P:P,'Отчет 12-18.01'!C:C,"Вознаграждение Ozon",'Отчет 12-18.01'!E:E,B11) -> 25321.41 | Y11: =IF(U11=0,0,X11/U11) -> 0.43 | Z11: =-SUMIFS('Отчет 12-18.01'!P:P,'Отчет 12-18.01'!C:C,"Услуги доставки",'Отчет 12-18.01'!E:E,B11) -> 7286.05 | AA11: 17722.263 | AD11: =U11*5.71% -> 3362.4477 | AE11: =U11-W11-X11-Z11-AA11-AB11-AC11-AD11 -> 889.82966 | AG11: =IF(R11=0,0,U11/R11) -> 1682.4857 | AH11: =H11 -> 123 | AI11: =IF(R11=0,0,X11/R11) -> 723.46886 | AJ11: =IF(P11=0,Z11/1,Z11/P11) -> 202.39028 | AK11: =IF(P11=0,0,AA11/P11) -> 492.28507 | AL11: {=_xlfn.IFS(R11=0,AE11,R11<0,AE11/-R11,R11>0,AE11/R11)} -> 25.423705 | AM11: =IF(AG11=0,0,AL11/AG11) -> 0.0151108 | AN11: =IF(AH11=0,0,AL11/AH11) -> 0.20669679 | AP11: =AL11*C11 -> 7067.7899
A12: 3405092873 | B12: th коричн | C12: 0 | H12: 117 | I12: =C12*H12 -> 0 | K12: 0 | N12: =K12/7 -> 0 | O12: =R12/7 -> 0 | P12: =SUMIFS('Отчет 12-18.01'!H:H,'Отчет 12-18.01'!D:D,"Выручка",'Отчет 12-18.01'!E:E,B12) -> 0 | Q12: =SUMIFS('Отчет 12-18.01'!H:H,'Отчет 12-18.01'!D:D,"Возврат выручки",'Отчет 12-18.01'!E:E,B12) -> 0 | R12: =P12-Q12 -> 0 | S12: =SUMIFS('Отчет 12-18.01'!P:P,'Отчет 12-18.01'!C:C,"Продажи",'Отчет 12-18.01'!E:E,B12) -> 0 | T12: =SUMIFS('Отчет 12-18.01'!P:P,'Отчет 12-18.01'!C:C,"Возвраты",'Отчет 12-18.01'!E:E,B12) -> 0 | U12: =S12+T12 -> 0 | V12: =U12/$U$24 -> 0 | W12: =R12*H12 -> 0 | X12: =-SUMIFS('Отчет 12-18.01'!P:P,'Отчет 12-18.01'!C:C,"Вознаграждение Ozon",'Отчет 12-18.01'!E:E,B12) -> 0 | Y12: =IF(U12=0,0,X12/U12) -> 0 | Z12: =-SUMIFS('Отчет 12-18.01'!P:P,'Отчет 12-18.01'!C:C,"Услуги доставки",'Отчет 12-18.01'!E:E,B12) -> 0 | AA12: 0 | AD12: =U12*5.71% -> 0 | AE12: =U12-W12-X12-Z12-AA12-AB12-AC12-AD12 -> 0 | AG12: =IF(R12=0,0,U12/R12) -> 0 | AH12: =H12 -> 117 | AI12: =IF(R12=0,0,X12/R12) -> 0 | AJ12: =IF(P12=0,Z12/1,Z12/P12) -> 0 | AK12: =IF(P12=0,0,AA12/P12) -> 0 | AL12: {=_xlfn.IFS(R12=0,AE12,R12<0,AE12/-R12,R12>0,AE12/R12)} -> 0 | AM12: =IF(AG12=0,0,AL12/AG12) -> 0 | AN12: =IF(AH12=0,0,AL12/AH12) -> 0 | AP12: =AL12*C12 -> 0
A13: 3405092993 | B13: flip черный | C13: 0 | H13: 123 | I13: =C13*H13 -> 0 | K13: 0 | N13: =K13/7 -> 0 | O13: =R13/7 -> 0 | P13: =SUMIFS('Отчет 12-18.01'!H:H,'Отчет 12-18.01'!D:D,"Выручка",'Отчет 12-18.01'!E:E,B13) -> 0 | Q13: =SUMIFS('Отчет 12-18.01'!H:H,'Отчет 12-18.01'!D:D,"Возврат выручки",'Отчет 12-18.01'!E:E,B13) -> 0 | R13: =P13-Q13 -> 0 | S13: =SUMIFS('Отчет 12-18.01'!P:P,'Отчет 12-18.01'!C:C,"Продажи",'Отчет 12-18.01'!E:E,B13) -> 0 | T13: =SUMIFS('Отчет 12-18.01'!P:P,'Отчет 12-18.01'!C:C,"Возвраты",'Отчет 12-18.01'!E:E,B13) -> 0 | U13: =S13+T13 -> 0 | V13: =U13/$U$24 -> 0 | W13: =R13*H13 -> 0 | X13: =-SUMIFS('Отчет 12-18.01'!P:P,'Отчет 12-18.01'!C:C,"Вознаграждение Ozon",'Отчет 12-18.01'!E:E,B13) -> 0 | Y13: =IF(U13=0,0,X13/U13) -> 0 | Z13: =-SUMIFS('Отчет 12-18.01'!P:P,'Отчет 12-18.01'!C:C,"Услуги доставки",'Отчет 12-18.01'!E:E,B13) -> 0 | AA13: 0 | AD13: =U13*5.71% -> 0 | AE13: =U13-W13-X13-Z13-AA13-AB13-AC13-AD13 -> 0 | AG13: =IF(R13=0,0,U13/R13) -> 0 | AH13: =H13 -> 123 | AI13: =IF(R13=0,0,X13/R13) -> 0 | AJ13: =IF(P13=0,Z13/1,Z13/P13) -> 0 | AK13: =IF(P13=0,0,AA13/P13) -> 0 | AL13: {=_xlfn.IFS(R13=0,AE13,R13<0,AE13/-R13,R13>0,AE13/R13)} -> 0 | AM13: =IF(AG13=0,0,AL13/AG13) -> 0 | AN13: =IF(AH13=0,0,AL13/AH13) -> 0 | AP13: =AL13*C13 -> 0
A14: 3405092868 | B14: flip синий | C14: 0 | H14: 123 | I14: =C14*H14 -> 0 | K14: 0 | N14: =K14/7 -> 0 | O14: =R14/7 -> 0 | P14: =SUMIFS('Отчет 12-18.01'!H:H,'Отчет 12-18.01'!D:D,"Выручка",'Отчет 12-18.01'!E:E,B14) -> 0 | Q14: =SUMIFS('Отчет 12-18.01'!H:H,'Отчет 12-18.01'!D:D,"Возврат выручки",'Отчет 12-18.01'!E:E,B14) -> 0 | R14: =P14-Q14 -> 0 | S14: =SUMIFS('Отчет 12-18.01'!P:P,'Отчет 12-18.01'!C:C,"Продажи",'Отчет 12-18.01'!E:E,B14) -> 0 | T14: =SUMIFS('Отчет 12-18.01'!P:P,'Отчет 12-18.01'!C:C,"Возвраты",'Отчет 12-18.01'!E:E,B14) -> 0 | U14: =S14+T14 -> 0 | V14: =U14/$U$24 -> 0 | W14: =R14*H14 -> 0 | X14: =-SUMIFS('Отчет 12-18.01'!P:P,'Отчет 12-18.01'!C:C,"Вознаграждение Ozon",'Отчет 12-18.01'!E:E,B14) -> 0 | Y14: =IF(U14=0,0,X14/U14) -> 0 | Z14: =-SUMIFS('Отчет 12-18.01'!P:P,'Отчет 12-18.01'!C:C,"Услуги доставки",'Отчет 12-18.01'!E:E,B14) -> 0 | AA14: 0 | AD14: =U14*5.71% -> 0 | AE14: =U14-W14-X14-Z14-AA14-AB14-AC14-AD14 -> 0 | AG14: =IF(R14=0,0,U14/R14) -> 0 | AH14: =H14 -> 123 | AI14: =IF(R14=0,0,X14/R14) -> 0 | AJ14: =IF(P14=0,Z14/1,Z14/P14) -> 0 | AK14: =IF(P14=0,0,AA14/P14) -> 0 | AL14: {=_xlfn.IFS(R14=0,AE14,R14<0,AE14/-R14,R14>0,AE14/R14)} -> 0 | AM14: =IF(AG14=0,0,AL14/AG14) -> 0 | AN14: =IF(AH14=0,0,AL14/AH14) -> 0 | AP14: =AL14*C14 -> 0
A15: 3064346642 | B15: flip жел | C15: 172 | H15: 123 | I15: =C15*H15 -> 21156 | K15: 40 | N15: =K15/7 -> 5.7142857 | O15: =R15/7 -> 5.2857143 | P15: =SUMIFS('Отчет 12-18.01'!H:H,'Отчет 12-18.01'!D:D,"Выручка",'Отчет 12-18.01'!E:E,B15) -> 37 | Q15: =SUMIFS('Отчет 12-18.01'!H:H,'Отчет 12-18.01'!D:D,"Возврат выручки",'Отчет 12-18.01'!E:E,B15) -> 0 | R15: =P15-Q15 -> 37 | S15: =SUMIFS('Отчет 12-18.01'!P:P,'Отчет 12-18.01'!C:C,"Продажи",'Отчет 12-18.01'!E:E,B15) -> 68265 | T15: =SUMIFS('Отчет 12-18.01'!P:P,'Отчет 12-18.01'!C:C,"Возвраты",'Отчет 12-18.01'!E:E,B15) -> 0 | U15: =S15+T15 -> 68265 | V15: =U15/$U$24 -> 0.32850035 | W15: =R15*H15 -> 4551 | X15: =-SUMIFS('Отчет 12-18.01'!P:P,'Отчет 12-18.01'!C:C,"Вознаграждение Ozon",'Отчет 12-18.01'!E:E,B15) -> 29353.95 | Y15: =IF(U15=0,0,X15/U15) -> 0.43 | Z15: =-SUMIFS('Отчет 12-18.01'!P:P,'Отчет 12-18.01'!C:C,"Услуги доставки",'Отчет 12-18.01'!E:E,B15) -> 8465.62 | AA15: 17366.253 | AD15: =U15*5.71% -> 3897.9315 | AE15: =U15-W15-X15-Z15-AA15-AB15-AC15-AD15 -> 4630.245 | AG15: =IF(R15=0,0,U15/R15) -> 1845 | AH15: =H15 -> 123 | AI15: =IF(R15=0,0,X15/R15) -> 793.35 | AJ15: =IF(P15=0,Z15/1,Z15/P15) -> 228.80054 | AK15: =IF(P15=0,0,AA15/P15) -> 469.3582 | AL15: {=_xlfn.IFS(R15=0,AE15,R15<0,AE15/-R15,R15>0,AE15/R15)} -> 125.14176 | AM15: =IF(AG15=0,0,AL15/AG15) -> 0.06782751 | AN15: =IF(AH15=0,0,AL15/AH15) -> 1.0174127 | AP15: =AL15*C15 -> 21524.382
A16: 3405092287 | B16: flip коричневый | C16: 0 | H16: 117 | I16: =C16*H16 -> 0 | K16: 0 | N16: =K16/7 -> 0 | O16: =R16/7 -> 0 | P16: =SUMIFS('Отчет 12-18.01'!H:H,'Отчет 12-18.01'!D:D,"Выручка",'Отчет 12-18.01'!E:E,B16) -> 0 | Q16: =SUMIFS('Отчет 12-18.01'!H:H,'Отчет 12-18.01'!D:D,"Возврат выручки",'Отчет 12-18.01'!E:E,B16) -> 0 | R16: =P16-Q16 -> 0 | S16: =SUMIFS('Отчет 12-18.01'!P:P,'Отчет 12-18.01'!C:C,"Продажи",'Отчет 12-18.01'!E:E,B16) -> 0 | T16: =SUMIFS('Отчет 12-18.01'!P:P,'Отчет 12-18.01'!C:C,"Возвраты",'Отчет 12-18.01'!E:E,B16) -> 0 | U16: =S16+T16 -> 0 | V16: =U16/$U$24 -> 0 | W16: =R16*H16 -> 0 | X16: =-SUMIFS('Отчет 12-18.01'!P:P,'Отчет 12-18.01'!C:C,"Вознаграждение Ozon",'Отчет 12-18.01'!E:E,B16) -> 0 | Y16: =IF(U16=0,0,X16/U16) -> 0 | Z16: =-SUMIFS('Отчет 12-18.01'!P:P,'Отчет 12-18.01'!C:C,"Услуги доставки",'Отчет 12-18.01'!E:E,B16) -> 0 | AA16: 0 | AD16: =U16*5.71% -> 0 | AE16: =U16-W16-X16-Z16-AA16-AB16-AC16-AD16 -> 0 | AG16: =IF(R16=0,0,U16/R16) -> 0 | AH16: =H16 -> 117 | AI16: =IF(R16=0,0,X16/R16) -> 0 | AJ16: =IF(P16=0,Z16/1,Z16/P16) -> 0 | AK16: =IF(P16=0,0,AA16/P16) -> 0 | AL16: {=_xlfn.IFS(R16=0,AE16,R16<0,AE16/-R16,R16>0,AE16/R16)} -> 0 | AM16: =IF(AG16=0,0,AL16/AG16) -> 0 | AN16: =IF(AH16=0,0,AL16/AH16) -> 0 | AP16: =AL16*C16 -> 0
AG17: =AVERAGEIF(AG3:AG15,"<>0",AG3:AG15) -> 1695.1202 | AH17: =AVERAGEIF(AH3:AH15,"<>0",AH3:AH15) -> 127.26 | AI17: =AVERAGEIF(AI3:AI15,"<>0",AI3:AI15) -> 728.9017 | AJ17: =AVERAGEIF(AJ3:AJ15,"<>0",AJ3:AJ15) -> 175.89942 | AK17: =AVERAGEIF(AK3:AK15,"<>0",AK3:AK15) -> 370.5321 | AL17: =AVERAGEIF(AL3:AL15,"<>0",AL3:AL15) -> 186.32552 | AM17: =AVERAGEIF(AM3:AM15,"<>0",AM3:AM15) -> 0.10914204 | AN17: =AVERAGEIF(AN3:AN15,"<>0",AN3:AN15) -> 1.4811249
A18: Итого очки | C18: =SUM(C3:C16) -> 3361 | E18: 108496 | F18: 597 | G18: 295 | I18: =SUM(I3:I16) -> 433801.86 | K18: =SUM(K3:K16) -> 144 | P18: =SUM(P3:P16) -> 122 | Q18: =SUM(Q3:Q16) -> 2 | R18: =SUM(R3:R16) -> 120 | S18: =SUM(S3:S16) -> 211029 | T18: =SUM(T3:T16) -> -3221 | U18: =SUM(U3:U16) -> 207808 | V18: =SUM(V3:V16) -> 1 | W18: =SUM(W3:W16) -> 15093.09 | X18: =SUM(X3:X16) -> 89357.44 | Y18: =IF(U18=0,0,X18/U18) -> 0.43 | Z18: =SUM(Z3:Z16) -> 24172.28 | AA18: =IFERROR(P18*AA24/P24,0) -> 53249.12 | AB18: =SUM(AB3:AB16) -> 0 | AC18: =SUM(AC3:AC16) -> 0 | AD18: =SUM(AD3:AD16) -> 11865.837 | AE18: =SUM(AE3:AE16) -> 15120.262 | AP18: =SUM(AP3:AP16) -> 691024.39 | AZ18: 18592777
AA19: =SUM(AA3:AA15) -> 52199.091
AG21: =AVERAGEIF(AG20:AG20,"<>0",AG20:AG20) -> #DIV/0! | AH21: =AVERAGEIF(AH20:AH20,"<>0",AH20:AH20) -> #DIV/0! | AI21: =AVERAGEIF(AI20:AI20,"<>0",AI20:AI20) -> #DIV/0! | AJ21: =AVERAGEIF(AJ20:AJ20,"<>0",AJ20:AJ20) -> #DIV/0! | AK21: =AVERAGEIF(AK20:AK20,"<>0",AK20:AK20) -> #DIV/0! | AL21: =AVERAGEIF(AL20:AL20,"<>0",AL20:AL20) -> #DIV/0! | AM21: =AVERAGEIF(AM20:AM20,"<>0",AM20:AM20) -> #DIV/0! | AN21: =AVERAGEIF(AN20:AN20,"<>0",AN20:AN20) -> #DIV/0!
C22: =SUM(C20:C20) -> 0 | I22: =SUM(I20:I20) -> 0 | K22: =SUM(K20:K20) -> 0 | P22: =SUM(P20:P20) -> 0 | Q22: =SUM(Q20:Q20) -> 0 | R22: =SUM(R20:R20) -> 0 | S22: =SUM(S20:S20) -> 0 | T22: =SUM(T20:T20) -> 0 | U22: =SUM(U20:U20) -> 0 | V22: =SUM(V20:V20) -> 0 | W22: =SUM(W20:W20) -> 0 | X22: =SUM(X20:X20) -> 0 | Y22: =IF(U22=0,0,X22/U22) -> 0 | Z22: =SUM(Z20:Z20) -> 0 | AA22: =IFERROR(P22*AA24/P24,0) -> 0 | AB22: =SUM(AB20:AB20) -> 0 | AC22: =SUM(AC20:AC20) -> 0 | AD22: =SUM(AD20:AD20) -> 0 | AE22: =SUM(AE20:AE20) -> 0 | AP22: =SUM(AP20:AP20) -> 0
AA23: =SUM(AA20:AA20) -> 0
A24: ИТОГО | C24: =C18+C22 -> 3361 | D24: =SUM(D3:D20) -> 0 | E24: =SUM(E3:E20) -> 108496 | F24: =SUM(F3:F20) -> 597 | G24: =SUM(G3:G20) -> 295 | I24: =I18+I22 -> 433801.86 | J24: =J18+J22 -> 0 | K24: =K18+K22 -> 144 | P24: =P18+P22 -> 122 | Q24: =Q18+Q22 -> 2 | R24: =R18-R22 -> 120 | S24: =S18+S22 -> 211029 | T24: =T18+T22 -> -3221 | U24: =U18+U22 -> 207808 | V24: =V18+V22 -> 1 | W24: =W18+W22 -> 15093.09 | X24: =X18+X22 -> 89357.44 | Y24: =X24/U24 -> 0.43 | Z24: =Z18+Z22 -> 24172.28 | AA24: 53249.12 | AC24: =SUM(AC3:AC20) -> 0 | AD24: =AD18+AD22 -> 11865.837 | AE24: =AE18+AE22 -> 15120.262 | AK24: =AA25/P24 -> 436.4682 | AP24: =SUM(AP3:AP20) -> 1382048.8
AA25: =AA18+AA22 -> 53249.12
AA26: =AA19+AA23 -> 52199.091
I29: Себестоимость остатков | K29: Прибыль с остатков | L29: Рентабельность товарных остатков
H31: до 60 дн | I31: =SUMIF(J3:J20,"<60",I3:I20) -> 0 | J31: =I31/I24 -> 0 | K31: =SUMIF(J3:J20,"<60",AP3:AP20) -> 0 | L31: =K31/I31 -> #DIV/0!
H32: 60-120 дн | I32: =I24-I33-I31 -> 433801.86 | J32: =I32/I24 -> 1 | K32: =AP24-K31-K33 -> 1382048.8 | L32: =K32/I32 -> 3.1858987
H33: > 120 дн | I33: =SUMIF(J3:J20,">120",I3:I20) -> 0 | J33: =I33/I24 -> 0 | K33: =SUMIF(J3:J20,">120",AP3:AP20) -> 0 | L33: =K33/I33 -> #DIV/0!
H35: Если товар на сайте менее 30 дней - оборачиваемость 0

Sheet Отчет 01.02

Sheet Отчет 26-31.01

Sheet Юнит 05-11.01
B1: 05-11.01 | AG1: на 1 единицу проданного товара
B2: Артикул поставщика | C2: Остаток на | D2: В пути до клиента | E2: В пути от клиента | F2: Итого по складам ВБ | G2: Остаток на нашем складе на 02.09 | H2: Себетоимость на 1 ед на 29.09.25 | I2: Себестоимость остатков | J2: Оборачиваемость, дн | K2: Заказы, шт 7 дней | L2: Средняя цена, руб (столбец 32, AG) | M2: % выкупа за 7 дней (столбец 23, X) | N2: Скорость заказов | O2: Скорость продаж | P2: Кол-во ПРОДАЖИ | Q2: Кол-во ВОЗВРАТЫ | R2: Кол-во ПРОДАЖИ-ВОЗВРАТЫ | S2: Выручка ПРОДАЖИ | T2: Выручка ВОЗВРАТЫ | U2: Выручка с учетом согласованной скидки ПРОДАЖИ - ВОЗВРАТЫ | V2: Доля выручки, % от общего объема | W2: Себестоимость продаж | X2: Комиссия, руб | Y2: Комиссия, % | Z2: Логистика | AA2: Реклама | AB2: Хранение | AC2: Штрафы | AD2: Налог 1%+ НДС 5% | AE2: Прибыль | AG2: Выручка на 1 ед (средняя цена продажи со скидкой) | AH2: Себестоимость на 1 ед | AI2: Комиссия на 1 ед | AJ2: Логистика на 1 ед | AK2: Реклама на 1 ед | AL2: Прибыль на 1 ед | AM2: Маржинальность, % | AN2: Рентабельность, % | AP2: Прибыль с остатков
A3: 2676784153 | B3: черные с железкой классика | H3: 142.98 | I3: =C3*H3 -> 0 | K3: 7 | N3: =K3/7 -> 1 | O3: =R3/7 -> 0.71428571 | P3: =SUMIFS('Отчет 05-11.01'!H:H,'Отчет 05-11.01'!D:D,"Выручка",'Отчет 05-11.01'!E:E,B3) -> 5 | Q3: =SUMIFS('Отчет 05-11.01'!H:H,'Отчет 05-11.01'!D:D,"Возврат выручки",'Отчет 05-11.01'!E:E,B3) -> 0 | R3: =P3-Q3 -> 5 | S3: =SUMIFS('Отчет 05-11.01'!P:P,'Отчет 05-11.01'!C:C,"Продажи",'Отчет 05-11.01'!E:E,B3) -> 7646 | T3: =SUMIFS('Отчет 05-11.01'!P:P,'Отчет 05-11.01'!C:C,"Возвраты",'Отчет 05-11.01'!E:E,B3) -> 0 | U3: =S3+T3 -> 7646 | V3: =U3/$U$24 -> 0.028973864 | W3: =R3*H3 -> 714.9 | X3: =-SUMIFS('Отчет 05-11.01'!P:P,'Отчет 05-11.01'!C:C,"Вознаграждение Ozon",'Отчет 05-11.01'!E:E,B3) -> 3287.78 | Y3: =IF(U3=0,0,X3/U3) -> 0.43 | Z3: =-SUMIFS('Отчет 05-11.01'!P:P,'Отчет 05-11.01'!C:C,"Услуги доставки",'Отчет 05-11.01'!E:E,B3) -> 912.5 | AA3: 811.7624 | AD3: =U3*5.71% -> 436.5866 | AE3: =U3-W3-X3-Z3-AA3-AB3-AC3-AD3 -> 1482.471 | AG3: =IF(R3=0,0,U3/R3) -> 1529.2 | AH3: =H3 -> 142.98 | AI3: =IF(R3=0,0,X3/R3) -> 657.556 | AJ3: =IF(P3=0,Z3/1,Z3/P3) -> 182.5 | AK3: =IF(P3=0,0,AA3/P3) -> 162.35248 | AL3: =_xlfn.IFS(R3=0,AE3,R3<0,AE3/-R3,R3>0,AE3/R3) -> 296.4942 | AM3: =IF(AG3=0,0,AL3/AG3) -> 0.19388844 | AN3: =IF(AH3=0,0,AL3/AH3) -> 2.073676 | AP3: =AL3*C3 -> 0
A4: 2676784638 | B4: qs черные | H4: 123.09 | I4: =C4*H4 -> 0 | K4: 1 | N4: =K4/7 -> 0.14285714 | O4: =R4/7 -> 0.42857143 | P4: =SUMIFS('Отчет 05-11.01'!H:H,'Отчет 05-11.01'!D:D,"Выручка",'Отчет 05-11.01'!E:E,B4) -> 3 | Q4: =SUMIFS('Отчет 05-11.01'!H:H,'Отчет 05-11.01'!D:D,"Возврат выручки",'Отчет 05-11.01'!E:E,B4) -> 0 | R4: =P4-Q4 -> 3 | S4: =SUMIFS('Отчет 05-11.01'!P:P,'Отчет 05-11.01'!C:C,"Продажи",'Отчет 05-11.01'!E:E,B4) -> 4950 | T4: =SUMIFS('Отчет 05-11.01'!P:P,'Отчет 05-11.01'!C:C,"Возвраты",'Отчет 05-11.01'!E:E,B4) -> 0 | U4: =S4+T4 -> 4950 | V4: =U4/$U$24 -> 0.018757603 | W4: =R4*H4 -> 369.27 | X4: =-SUMIFS('Отчет 05-11.01'!P:P,'Отчет 05-11.01'!C:C,"Вознаграждение Ozon",'Отчет 05-11.01'!E:E,B4) -> 2128.5 | Y4: =IF(U4=0,0,X4/U4) -> 0.43 | Z4: =-SUMIFS('Отчет 05-11.01'!P:P,'Отчет 05-11.01'!C:C,"Услуги доставки",'Отчет 05-11.01'!E:E,B4) -> 485.94 | AA4: 395.64931 | AD4: =U4*5.71% -> 282.645 | AE4: =U4-W4-X4-Z4-AA4-AB4-AC4-AD4 -> 1287.9957 | AG4: =IF(R4=0,0,U4/R4) -> 1650 | AH4: =H4 -> 123.09 | AI4: =IF(R4=0,0,X4/R4) -> 709.5 | AJ4: =IF(P4=0,Z4/1,Z4/P4) -> 161.98 | AK4: =IF(P4=0,0,AA4/P4) -> 131.8831 | AL4: {=_xlfn.IFS(R4=0,AE4,R4<0,AE4/-R4,R4>0,AE4/R4)} -> 429.3319 | AM4: =IF(AG4=0,0,AL4/AG4) -> 0.26020115 | AN4: =IF(AH4=0,0,AL4/AH4) -> 3.4879511 | AP4: =AL4*C4 -> 0
A5: 2676784504 | B5: qs синие | H5: 123.09 | I5: =C5*H5 -> 0 | K5: 3 | N5: =K5/7 -> 0.42857143 | O5: =R5/7 -> 0.28571429 | P5: =SUMIFS('Отчет 05-11.01'!H:H,'Отчет 05-11.01'!D:D,"Выручка",'Отчет 05-11.01'!E:E,B5) -> 2 | Q5: =SUMIFS('Отчет 05-11.01'!H:H,'Отчет 05-11.01'!D:D,"Возврат выручки",'Отчет 05-11.01'!E:E,B5) -> 0 | R5: =P5-Q5 -> 2 | S5: =SUMIFS('Отчет 05-11.01'!P:P,'Отчет 05-11.01'!C:C,"Продажи",'Отчет 05-11.01'!E:E,B5) -> 3300 | T5: =SUMIFS('Отчет 05-11.01'!P:P,'Отчет 05-11.01'!C:C,"Возвраты",'Отчет 05-11.01'!E:E,B5) -> 0 | U5: =S5+T5 -> 3300 | V5: =U5/$U$24 -> 0.012505068 | W5: =R5*H5 -> 246.18 | X5: =-SUMIFS('Отчет 05-11.01'!P:P,'Отчет 05-11.01'!C:C,"Вознаграждение Ozon",'Отчет 05-11.01'!E:E,B5) -> 1419 | Y5: =IF(U5=0,0,X5/U5) -> 0.43 | Z5: =-SUMIFS('Отчет 05-11.01'!P:P,'Отчет 05-11.01'!C:C,"Услуги доставки",'Отчет 05-11.01'!E:E,B5) -> 334.46 | AA5: 811.52412 | AD5: =U5*5.71% -> 188.43 | AE5: =U5-W5-X5-Z5-AA5-AB5-AC5-AD5 -> 300.40588 | AG5: =IF(R5=0,0,U5/R5) -> 1650 | AH5: =H5 -> 123.09 | AI5: =IF(R5=0,0,X5/R5) -> 709.5 | AJ5: =IF(P5=0,Z5/1,Z5/P5) -> 167.23 | AK5: =IF(P5=0,0,AA5/P5) -> 405.76206 | AL5: {=_xlfn.IFS(R5=0,AE5,R5<0,AE5/-R5,R5>0,AE5/R5)} -> 150.20294 | AM5: =IF(AG5=0,0,AL5/AG5) -> 0.091032084 | AN5: =IF(AH5=0,0,AL5/AH5) -> 1.2202692 | AP5: =AL5*C5 -> 0
A6: 2676784514 | B6: qs желтые | H6: 123.09 | I6: =C6*H6 -> 0 | K6: 38 | N6: =K6/7 -> 5.4285714 | O6: =R6/7 -> 4.4285714 | P6: =SUMIFS('Отчет 05-11.01'!H:H,'Отчет 05-11.01'!D:D,"Выручка",'Отчет 05-11.01'!E:E,B6) -> 33 | Q6: =SUMIFS('Отчет 05-11.01'!H:H,'Отчет 05-11.01'!D:D,"Возврат выручки",'Отчет 05-11.01'!E:E,B6) -> 2 | R6: =P6-Q6 -> 31 | S6: =SUMIFS('Отчет 05-11.01'!P:P,'Отчет 05-11.01'!C:C,"Продажи",'Отчет 05-11.01'!E:E,B6) -> 52800 | T6: =SUMIFS('Отчет 05-11.01'!P:P,'Отчет 05-11.01'!C:C,"Возвраты",'Отчет 05-11.01'!E:E,B6) -> -3200 | U6: =S6+T6 -> 49600 | V6: =U6/$U$24 -> 0.18795497 | W6: =R6*H6 -> 3815.79 | X6: =-SUMIFS('Отчет 05-11.01'!P:P,'Отчет 05-11.01'!C:C,"Вознаграждение Ozon",'Отчет 05-11.01'!E:E,B6) -> 21328 | Y6: =IF(U6=0,0,X6/U6) -> 0.43 | Z6: =-SUMIFS('Отчет 05-11.01'!P:P,'Отчет 05-11.01'!C:C,"Услуги доставки",'Отчет 05-11.01'!E:E,B6) -> 4679.14 | AA6: 12362.053 | AD6: =U6*5.71% -> 2832.16 | AE6: =U6-W6-X6-Z6-AA6-AB6-AC6-AD6 -> 4582.8566 | AG6: =IF(R6=0,0,U6/R6) -> 1600 | AH6: =H6 -> 123.09 | AI6: =IF(R6=0,0,X6/R6) -> 688 | AJ6: =IF(P6=0,Z6/1,Z6/P6) -> 141.79212 | AK6: =IF(P6=0,0,AA6/P6) -> 374.60768 | AL6: {=_xlfn.IFS(R6=0,AE6,R6<0,AE6/-R6,R6>0,AE6/R6)} -> 147.83408 | AM6: =IF(AG6=0,0,AL6/AG6) -> 0.092396302 | AN6: =IF(AH6=0,0,AL6/AH6) -> 1.2010243 | AP6: =AL6*C6 -> 0
A7: 2676784181 | B7: qs коричневые | H7: 117.24 | I7: =C7*H7 -> 0 | K7: 14 | N7: =K7/7 -> 2 | O7: =R7/7 -> 1.1428571 | P7: =SUMIFS('Отчет 05-11.01'!H:H,'Отчет 05-11.01'!D:D,"Выручка",'Отчет 05-11.01'!E:E,B7) -> 8 | Q7: =SUMIFS('Отчет 05-11.01'!H:H,'Отчет 05-11.01'!D:D,"Возврат выручки",'Отчет 05-11.01'!E:E,B7) -> 0 | R7: =P7-Q7 -> 8 | S7: =SUMIFS('Отчет 05-11.01'!P:P,'Отчет 05-11.01'!C:C,"Продажи",'Отчет 05-11.01'!E:E,B7) -> 12800 | T7: =SUMIFS('Отчет 05-11.01'!P:P,'Отчет 05-11.01'!C:C,"Возвраты",'Отчет 05-11.01'!E:E,B7) -> 0 | U7: =S7+T7 -> 12800 | V7: =U7/$U$24 -> 0.048504508 | W7: =R7*H7 -> 937.92 | X7: =-SUMIFS('Отчет 05-11.01'!P:P,'Отчет 05-11.01'!C:C,"Вознаграждение Ozon",'Отчет 05-11.01'!E:E,B7) -> 5504 | Y7: =IF(U7=0,0,X7/U7) -> 0.43 | Z7: =-SUMIFS('Отчет 05-11.01'!P:P,'Отчет 05-11.01'!C:C,"Услуги доставки",'Отчет 05-11.01'!E:E,B7) -> 1259.48 | AA7: 2303.3168 | AD7: =U7*5.71% -> 730.88 | AE7: =U7-W7-X7-Z7-AA7-AB7-AC7-AD7 -> 2064.4032 | AG7: =IF(R7=0,0,U7/R7) -> 1600 | AH7: =H7 -> 117.24 | AI7: =IF(R7=0,0,X7/R7) -> 688 | AJ7: =IF(P7=0,Z7/1,Z7/P7) -> 157.435 | AK7: =IF(P7=0,0,AA7/P7) -> 287.9146 | AL7: {=_xlfn.IFS(R7=0,AE7,R7<0,AE7/-R7,R7>0,AE7/R7)} -> 258.0504 | AM7: =IF(AG7=0,0,AL7/AG7) -> 0.1612815 | AN7: =IF(AH7=0,0,AL7/AH7) -> 2.201044 | AP7: =AL7*C7 -> 0
A8: 2676783005 | B8: MR8854 C2 | H8: 169.89 | I8: =C8*H8 -> 0 | K8: 11 | N8: =K8/7 -> 1.5714286 | O8: =R8/7 -> 1.4285714 | P8: =SUMIFS('Отчет 05-11.01'!H:H,'Отчет 05-11.01'!D:D,"Выручка",'Отчет 05-11.01'!E:E,B8) -> 10 | Q8: =SUMIFS('Отчет 05-11.01'!H:H,'Отчет 05-11.01'!D:D,"Возврат выручки",'Отчет 05-11.01'!E:E,B8) -> 0 | R8: =P8-Q8 -> 10 | S8: =SUMIFS('Отчет 05-11.01'!P:P,'Отчет 05-11.01'!C:C,"Продажи",'Отчет 05-11.01'!E:E,B8) -> 12020 | T8: =SUMIFS('Отчет 05-11.01'!P:P,'Отчет 05-11.01'!C:C,"Возвраты",'Отчет 05-11.01'!E:E,B8) -> 0 | U8: =S8+T8 -> 12020 | V8: =U8/$U$24 -> 0.045548764 | W8: =R8*H8 -> 1698.9 | X8: =-SUMIFS('Отчет 05-11.01'!P:P,'Отчет 05-11.01'!C:C,"Вознаграждение Ozon",'Отчет 05-11.01'!E:E,B8) -> 5168.6 | Y8: =IF(U8=0,0,X8/U8) -> 0.43 | Z8: =-SUMIFS('Отчет 05-11.01'!P:P,'Отчет 05-11.01'!C:C,"Услуги доставки",'Отчет 05-11.01'!E:E,B8) -> 1124.97 | AA8: 1389.9724 | AD8: =U8*5.71% -> 686.342 | AE8: =U8-W8-X8-Z8-AA8-AB8-AC8-AD8 -> 1951.2156 | AG8: =IF(R8=0,0,U8/R8) -> 1202 | AH8: =H8 -> 169.89 | AI8: =IF(R8=0,0,X8/R8) -> 516.86 | AJ8: =IF(P8=0,Z8/1,Z8/P8) -> 112.497 | AK8: =IF(P8=0,0,AA8/P8) -> 138.99724 | AL8: {=_xlfn.IFS(R8=0,AE8,R8<0,AE8/-R8,R8>0,AE8/R8)} -> 195.12156 | AM8: =IF(AG8=0,0,AL8/AG8) -> 0.16233075 | AN8: =IF(AH8=0,0,AL8/AH8) -> 1.1485171 | AP8: =AL8*C8 -> 0
A9: 3405092860 | B9: th черн | H9: 123 | I9: =C9*H9 -> 0 | K9: 0 | N9: =K9/7 -> 0 | O9: =R9/7 -> 0 | P9: =SUMIFS('Отчет 05-11.01'!H:H,'Отчет 05-11.01'!D:D,"Выручка",'Отчет 05-11.01'!E:E,B9) -> 0 | Q9: =SUMIFS('Отчет 05-11.01'!H:H,'Отчет 05-11.01'!D:D,"Возврат выручки",'Отчет 05-11.01'!E:E,B9) -> 0 | R9: =P9-Q9 -> 0 | S9: =SUMIFS('Отчет 05-11.01'!P:P,'Отчет 05-11.01'!C:C,"Продажи",'Отчет 05-11.01'!E:E,B9) -> 0 | T9: =SUMIFS('Отчет 05-11.01'!P:P,'Отчет 05-11.01'!C:C,"Возвраты",'Отчет 05-11.01'!E:E,B9) -> 0 | U9: =S9+T9 -> 0 | V9: =U9/$U$24 -> 0 | W9: =R9*H9 -> 0 | X9: =-SUMIFS('Отчет 05-11.01'!P:P,'Отчет 05-11.01'!C:C,"Вознаграждение Ozon",'Отчет 05-11.01'!E:E,B9) -> 0 | Y9: =IF(U9=0,0,X9/U9) -> 0 | Z9: =-SUMIFS('Отчет 05-11.01'!P:P,'Отчет 05-11.01'!C:C,"Услуги доставки",'Отчет 05-11.01'!E:E,B9) -> 0 | AA9: 0 | AD9: =U9*5.71% -> 0 | AE9: =U9-W9-X9-Z9-AA9-AB9-AC9-AD9 -> 0 | AG9: =IF(R9=0,0,U9/R9) -> 0 | AH9: =H9 -> 123 | AI9: =IF(R9=0,0,X9/R9) -> 0 | AJ9: =IF(P9=0,Z9/1,Z9/P9) -> 0 | AK9: =IF(P9=0,0,AA9/P9) -> 0 | AL9: {=_xlfn.IFS(R9=0,AE9,R9<0,AE9/-R9,R9>0,AE9/R9)} -> 0 | AM9: =IF(AG9=0,0,AL9/AG9) -> 0 | AN9: =IF(AH9=0,0,AL9/AH9) -> 0 | AP9: =AL9*C9 -> 0
A10: 3405092836 | B10: th син | H10: 123 | I10: =C10*H10 -> 0 | K10: 0 | N10: =K10/7 -> 0 | O10: =R10/7 -> 0 | P10: =SUMIFS('Отчет 05-11.01'!H:H,'Отчет 05-11.01'!D:D,"Выручка",'Отчет 05-11.01'!E:E,B10) -> 0 | Q10: =SUMIFS('Отчет 05-11.01'!H:H,'Отчет 05-11.01'!D:D,"Возврат выручки",'Отчет 05-11.01'!E:E,B10) -> 0 | R10: =P10-Q10 -> 0 | S10: =SUMIFS('Отчет 05-11.01'!P:P,'Отчет 05-11.01'!C:C,"Продажи",'Отчет 05-11.01'!E:E,B10) -> 0 | T10: =SUMIFS('Отчет 05-11.01'!P:P,'Отчет 05-11.01'!C:C,"Возвраты",'Отчет 05-11.01'!E:E,B10) -> 0 | U10: =S10+T10 -> 0 | V10: =U10/$U$24 -> 0 | W10: =R10*H10 -> 0 | X10: =-SUMIFS('Отчет 05-11.01'!P:P,'Отчет 05-11.01'!C:C,"Вознаграждение Ozon",'Отчет 05-11.01'!E:E,B10) -> 0 | Y10: =IF(U10=0,0,X10/U10) -> 0 | Z10: =-SUMIFS('Отчет 05-11.01'!P:P,'Отчет 05-11.01'!C:C,"Услуги доставки",'Отчет 05-11.01'!E:E,B10) -> 0 | AA10: 0 | AD10: =U10*5.71% -> 0 | AE10: =U10-W10-X10-Z10-AA10-AB10-AC10-AD10 -> 0 | AG10: =IF(R10=0,0,U10/R10) -> 0 | AH10: =H10 -> 123 | AI10: =IF(R10=0,0,X10/R10) -> 0 | AJ10: =IF(P10=0,Z10/1,Z10/P10) -> 0 | AK10: =IF(P10=0,0,AA10/P10) -> 0 | AL10: {=_xlfn.IFS(R10=0,AE10,R10<0,AE10/-R10,R10>0,AE10/R10)} -> 0 | AM10: =IF(AG10=0,0,AL10/AG10) -> 0 | AN10: =IF(AH10=0,0,AL10/AH10) -> 0 | AP10: =AL10*C10 -> 0
