Workbook

Sheet Сводная
A1: Период | D1: Итого к перечислению на счет, руб | E1: шт. | H1: Выручка | K1: Себестоимость продаж | L1: Логистика | M1: Комиссия | N1: Хранение | O1: Платная приемка | P1: Штрафы | Q1: Реклама Ozon | R1: Прочее | S1: Доп. услуги | T1: Услуги FBO | U1: Компенсировано | V1: Пополнение рекламного кабинета | W1: ЕАЭС | X1: Налог | Y1: Итого | Z1: Итог месяц | AA1: % Cебестоимости | AB1: Маржинальность, % | AC1: Рентабельность, % | AD1: Доля рекламы, %
A2: Месяц | B2: Даты | C2: Нед | E2: Заказы | F2: Продажи | G2: Возвраты | H2: Продажи | I2: Возвраты | J2: Общая
A3: Январь | B3: 01-04.01 | D3: =J3-SUM(L3:T3)+U3+V3 -> 1074.71 | E3: ='Юнит 01-04.01'!K$24 -> 122 | F3: ='Юнит 01-04.01'!P$24 -> 51 | G3: ='Юнит 01-04.01'!Q$24 -> 1 | H3: ='Юнит 01-04.01'!S$24 -> 85937 | I3: ='Юнит 01-04.01'!T$24 -> -1600 | J3: =H3+I3 -> 84337 | K3: ='Юнит 01-04.01'!W$24 -> 6252.96 | L3: ='Юнит 01-04.01'!Z$24 -> 8548.62 | M3: ='Юнит 01-04.01'!X$24 -> 36264.91 | Q3: ='Юнит 01-04.01'!AA$24 -> 36772.95 | R3: 1675.81 | S3: 0 | T3: 0 | W3: 5252 | X3: =(J3)*0.01 -> 843.37 | Y3: =J3-SUM(L3:T3)-K3-X3+U3-V3+W3 -> -769.62 | Z3: =SUM(Y3:Y7) -> 43931.01 | AA3: =K3/J3 -> 0.074142547 | AB3: =Y3/K3 -> -0.12308091 | AC3: =Y3/J3 -> -0.0091255321 | AD3: =Q3/J3 -> 0.43602393
B4: 05-11.01 | D4: =J4-SUM(L4:T4)+U4+V4 -> 57707.57 | E4: ='Юнит 05-11.01'!K$24 -> 183 | F4: ='Юнит 05-11.01'!P$24 -> 168 | G4: ='Юнит 05-11.01'!Q$24 -> 8 | H4: ='Юнит 05-11.01'!S$24 -> 277715 | I4: ='Юнит 05-11.01'!T$24 -> -13822 | J4: =H4+I4 -> 263893 | K4: ='Юнит 05-11.01'!W$24 -> 20205.96 | L4: ='Юнит 05-11.01'!Z$24 -> 28076.33 | M4: ='Юнит 05-11.01'!X$24 -> 113473.99 | Q4: ='Юнит 05-11.01'!AA$24 -> 56365.38 | R4: 4144.33 | S4: 75 | T4: 4050.4 | X4: =(J4)*0.01 -> 2638.93 | Y4: =J4-SUM(L4:T4)-K4-X4+U4-V4+W4 -> 34862.68 | AA4: =K4/J4 -> 0.076568761 | AB4: =Y4/K4 -> 1.7253662 | AC4: =Y4/J4 -> 0.13210915 | AD4: =Q4/J4 -> 0.2135918
B5: 12-18.01 | D5: =J5-SUM(L5:T5)+U5+V5 -> 36064.15 | E5: ='Юнит 12-18.01'!K$24 -> 144 | F5: ='Юнит 12-18.01'!P$24 -> 122 | G5: ='Юнит 12-18.01'!Q$24 -> 2 | H5: ='Юнит 12-18.01'!S$24 -> 211029 | I5: ='Юнит 12-18.01'!T$24 -> -3221 | J5: =H5+I5 -> 207808 | K5: ='Юнит 12-18.01'!W$24 -> 15093.09 | L5: ='Юнит 12-18.01'!Z$24 -> 24172.28 | M5: ='Юнит 12-18.01'!X$24 -> 89357.44 | Q5: ='Юнит 12-18.01'!AA$24 -> 53249.12 | R5: 4025.01 | S5: 0 | T5: 940 | W5: 5135 | X5: =(J5)*0.01 -> 2078.08 | Y5: =J5-SUM(L5:T5)-K5-X5+U5-V5+W5 -> 24027.98 | AA5: =K5/J5 -> 0.072629976 | AB5: =Y5/K5 -> 1.5919855 | AC5: =Y5/J5 -> 0.11562587 | AD5: =Q5/J5 -> 0.25624192
B6: 19-25.01 | D6: =J6-SUM(L6:T6)+U6+V6 -> 34413.47 | E6: ='Юнит 19-25.01'!K$24 -> 154 | F6: ='Юнит 19-25.01'!P$24 -> 91 | G6: ='Юнит 19-25.01'!Q$24 -> 2 | H6: ='Юнит 19-25.01'!S$24 -> 161208 | I6: ='Юнит 19-25.01'!T$24 -> -3229 | J6: =H6+I6 -> 157979 | K6: ='Юнит 19-25.01'!W$24 -> 11132.49 | L6: ='Юнит 19-25.01'!Z$24 -> 16989.46 | M6: ='Юнит 19-25.01'!X$24 -> 67930.97 | Q6: ='Юнит 19-25.01'!AA$24 -> 42151.21 | R6: 3468.89 | S6: 25 | T6: 0 | V6: 7000 | X6: =(J6)*0.01 -> 1579.79 | Y6: =J6-SUM(L6:T6)-K6-X6+U6-V6+W6 -> 7701.19 | AA6: =K6/J6 -> 0.070468163 | AB6: =Y6/K6 -> 0.69177605 | AC6: =Y6/J6 -> 0.048748188 | AD6: =Q6/J6 -> 0.26681527
B7: 26-31.01 | D7: =J7-SUM(L7:T7)+U7+V7 -> -6035.1 | E7: ='Юнит 26-31.01'!K$24 -> 200 | F7: ='Юнит 26-31.01'!P$24 -> 112 | G7: ='Юнит 26-31.01'!Q$24 -> 2 | H7: ='Юнит 26-31.01'!S$24 -> 200558 | I7: ='Юнит 26-31.01'!T$24 -> -3595 | J7: =H7+I7 -> 196963 | K7: ='Юнит 26-31.01'!W$24 -> 13886.49 | L7: ='Юнит 26-31.01'!Z$24 -> 20843.55 | M7: ='Юнит 26-31.01'!X$24 -> 84694.09 | Q7: ='Юнит 26-31.01'!AA$24 -> 50770.67 | R7: 3661.19 | S7: 150 | T7: 43993.6 | U7: 1115 | X7: =(J7)*0.01 -> 1969.63 | Y7: =J7-SUM(L7:T7)-K7-X7+U7-V7+W7 -> -21891.22 | AA7: =(K7+K8)/(J7+J8) -> 0.070282074 | AB7: =(Y7+Y8)/(K7+K8) -> -0.76300764 | AC7: =(Y7+Y8)/(J7+J8) -> -0.05362576 | AD7: =(Q7+Q8)/(J7+J8) -> 0.25406002
B8: 01.02-01.02 | D8: =J8-SUM(L8:T8)+U8+V8 -> 7323.99 | E8: ='Юнит 01.02'!K$24 -> 36 | F8: ='Юнит 01.02'!P$24 -> 19 | G8: ='Юнит 01.02'!Q$24 -> 1 | H8: ='Юнит 01.02'!S$24 -> 34372 | I8: ='Юнит 01.02'!T$24 -> -1750 | J8: =H8+I8 -> 32622 | K8: ='Юнит 01.02'!W$24 -> 2249.22 | L8: ='Юнит 01.02'!Z$24 -> 3179.52 | M8: ='Юнит 01.02'!X$24 -> 14027.46 | Q8: ='Юнит 01.02'!AA$24 -> 7557.7 | R8: 533.33 | W8: 4831 | X8: =(J8)*0.01 -> 326.22 | Y8: =J8-SUM(L8:T8)-K8-X8+U8-V8+W8 -> 9579.55 | Z8: =SUM(Y8:Y12) -> 9579.55
B9: 02.02-08.02 | AA9: =K9/J9 -> #DIV/0! | AB9: =Y9/K9 -> #DIV/0! | AC9: =Y9/J9 -> #DIV/0! | AD9: =Q9/J9 -> #DIV/0!
B10: 09-15.02 | AA10: =K10/J10 -> #DIV/0! | AB10: =Y10/K10 -> #DIV/0! | AC10: =Y10/J10 -> #DIV/0! | AD10: =Q10/J10 -> #DIV/0!
B11: 16-22.02 | AA11: =K11/J11 -> #DIV/0! | AB11: =Y11/K11 -> #DIV/0! | AC11: =Y11/J11 -> #DIV/0! | AD11: =Q11/J11 -> #DIV/0!
B12: 23-28.02 | AA12: =K12/J12 -> #DIV/0! | AB12: =Y12/K12 -> #DIV/0! | AC12: =Y12/J12 -> #DIV/0! | AD12: =Q12/J12 -> #DIV/0!
A13: Итого | D13: =SUM(D3:D12) -> 130548.79 | E13: =SUM(E3:E12) -> 839 | F13: =SUM(F3:F12) -> 563 | G13: =SUM(G3:G12) -> 16 | H13: =SUM(H3:H12) -> 970819 | I13: =SUM(I3:I12) -> -27217 | J13: =SUM(J3:J12) -> 943602 | K13: =SUM(K3:K12) -> 68820.21 | ... Z13: =SUM(Z3:Z12) -> 53510.56 | AA13: =K13/J13 -> 0.072933514 | AB13: =Y13/K13 -> 0.77754136 | AC13: =Y13/J13 -> 0.056708824 | AD13: =Q13/J13 -> 0.26162199
H14: % от выручки за весь период
I15: =-I13/H13 -> 0.028035092 | J15: 0 | K15: =K13/$J$13 -> 0.072933514 | L15: =L13/$J$13 -> 0.10789481 | M15: =M13/$J$13 -> 0.43 | Q15: =Q13/$J$13 -> 0.26162199 | R15: =R13/$J$13 -> 0.018555026 | S15: =S13/$J$13 -> 0.00026494221 | T15: =T13/$J$13 -> 0.051911717 | U15: =U13/$J$13 -> 0.0011816423 | V15: =V13/$J$13 -> 0.0074183819 | X15: =X13/$J$13 -> 0.01 | Y15: =Y13/K13 -> 0.77754136 | Z15: Маржинальность, % | AA15: =Y13/J13 -> 0.056708824
A17: январь | D17: =SUM(D3:D7) -> 123224.8 | E17: =SUM(E3:E7) -> 803 | F17: =SUM(F3:F7) -> 544 | G17: =SUM(G3:G7) -> 15 | H17: =SUM(H3:H7) -> 936447 | I17: =SUM(I3:I7) -> -25467 | J17: =SUM(J3:J7) -> 910980 | K17: =SUM(K3:K7) -> 66570.99 | ... Z17: =SUM(Z3:Z7) -> 43931.01

Sheet АВС 02-08.02
B2: ОЧКИ
C3: Прибыль | D3: % прибыль | E3: Доля | F3: ABC прибыль | G3: ABC кол-во | J3: Кол-во | K3: % кол-во | L3: Доля | M3: ABC кол-во
B4: черные с железкой классика | D4: =C4/C$18 -> #DIV/0! | E4: =D4 -> #DIV/0! | F4: =IF(AND(E4<=0),"C",IF(E4<=0.8,"A",IF(E4<=0.95,"B","C"))) -> #DIV/0! | G4: =VLOOKUP(B$4:B$17,I$4:M$17,5,0) -> #DIV/0! | I4: черные с железкой классика | K4: =J4/J$18 -> #DIV/0! | L4: =K4 -> #DIV/0! | M4: =_xlfn.IFS(L4<80%,"A",L4<=95%,"B",L4>95%,"C") -> #DIV/0!
B5: qs черные | D5: =C5/C$18 -> #DIV/0! | E5: =D5+E4 -> #DIV/0! | F5: =IF(AND(E5<=0),"C",IF(E5<=0.8,"A",IF(E5<=0.95,"B","C"))) -> #DIV/0! | G5: =VLOOKUP(B$4:B$17,I$4:M$17,5,0) -> #DIV/0! | I5: qs черные | K5: =J5/J$18 -> #DIV/0! | L5: =K5+L4 -> #DIV/0! | M5: =_xlfn.IFS(L5<80%,"A",L5<=95%,"B",L5>95%,"C") -> #DIV/0!
B6: qs синие | D6: =C6/C$18 -> #DIV/0! | E6: =D6+E5 -> #DIV/0! | F6: =IF(AND(E6<=0),"C",IF(E6<=0.8,"A",IF(E6<=0.95,"B","C"))) -> #DIV/0! | G6: =VLOOKUP(B$4:B$17,I$4:M$17,5,0) -> #DIV/0! | I6: qs синие | K6: =J6/J$18 -> #DIV/0! | L6: =K6+L5 -> #DIV/0! | M6: =_xlfn.IFS(L6<80%,"A",L6<=95%,"B",L6>95%,"C") -> #DIV/0!
B7: qs желтые | D7: =C7/C$18 -> #DIV/0! | E7: =D7+E6 -> #DIV/0! | F7: =IF(AND(E7<=0),"C",IF(E7<=0.8,"A",IF(E7<=0.95,"B","C"))) -> #DIV/0! | G7: =VLOOKUP(B$4:B$17,I$4:M$17,5,0) -> #DIV/0! | I7: qs желтые | K7: =J7/J$18 -> #DIV/0! | L7: =K7+L6 -> #DIV/0! | M7: =_xlfn.IFS(L7<80%,"A",L7<=95%,"B",L7>95%,"C") -> #DIV/0!
B8: qs коричневые | D8: =C8/C$18 -> #DIV/0! | E8: =D8+E7 -> #DIV/0! | F8: =IF(AND(E8<=0),"C",IF(E8<=0.8,"A",IF(E8<=0.95,"B","C"))) -> #DIV/0! | G8: =VLOOKUP(B$4:B$17,I$4:M$17,5,0) -> #DIV/0! | I8: qs коричневые | K8: =J8/J$18 -> #DIV/0! | L8: =K8+L7 -> #DIV/0! | M8: =_xlfn.IFS(L8<80%,"A",L8<=95%,"B",L8>95%,"C") -> #DIV/0!
B9: MR8854 C2 | D9: =C9/C$18 -> #DIV/0! | E9: =D9+E8 -> #DIV/0! | F9: =IF(AND(E9<=0),"C",IF(E9<=0.8,"A",IF(E9<=0.95,"B","C"))) -> #DIV/0! | G9: =VLOOKUP(B$4:B$17,I$4:M$17,5,0) -> #DIV/0! | I9: MR8854 C2 | K9: =J9/J$18 -> #DIV/0! | L9: =K9+L8 -> #DIV/0! | M9: =_xlfn.IFS(L9<80%,"A",L9<=95%,"B",L9>95%,"C") -> #DIV/0!
B10: th черн | D10: =C10/C$18 -> #DIV/0! | E10: =D10+E9 -> #DIV/0! | F10: =IF(AND(E10<=0),"C",IF(E10<=0.8,"A",IF(E10<=0.95,"B","C"))) -> #DIV/0! | G10: =VLOOKUP(B$4:B$17,I$4:M$17,5,0) -> #DIV/0! | I10: th черн | K10: =J10/J$18 -> #DIV/0! | L10: =K10+L9 -> #DIV/0! | M10: =_xlfn.IFS(L10<80%,"A",L10<=95%,"B",L10>95%,"C") -> #DIV/0!
B11: th син | D11: =C11/C$18 -> #DIV/0! | E11: =D11+E10 -> #DIV/0! | F11: =IF(AND(E11<=0),"C",IF(E11<=0.8,"A",IF(E11<=0.95,"B","C"))) -> #DIV/0! | G11: =VLOOKUP(B$4:B$17,I$4:M$17,5,0) -> #DIV/0! | I11: th син | K11: =J11/J$18 -> #DIV/0! | L11: =K11+L10 -> #DIV/0! | M11: =_xlfn.IFS(L11<80%,"A",L11<=95%,"B",L11>95%,"C") -> #DIV/0!
B12: th желт | D12: =C12/C$18 -> #DIV/0! | E12: =D12+E5 -> #DIV/0! | F12: =IF(AND(E12<=0),"C",IF(E12<=0.8,"A",IF(E12<=0.95,"B","C"))) -> #DIV/0! | G12: =VLOOKUP(B$4:B$17,I$4:M$17,5,0) -> #DIV/0! | I12: th желт | K12: =J12/J$18 -> #DIV/0! | L12: =K12+L5 -> #DIV/0! | M12: =_xlfn.IFS(L12<80%,"A",L12<=95%,"B",L12>95%,"C") -> #DIV/0!
B13: th коричн | D13: =C13/C$18 -> #DIV/0! | E13: =D13+E12 -> #DIV/0! | F13: =IF(AND(E13<=0),"C",IF(E13<=0.8,"A",IF(E13<=0.95,"B","C"))) -> #DIV/0! | G13: =VLOOKUP(B$4:B$17,I$4:M$17,5,0) -> #DIV/0! | I13: th коричн | K13: =J13/J$18 -> #DIV/0! | L13: =K13+L12 -> #DIV/0! | M13: =_xlfn.IFS(L13<80%,"A",L13<=95%,"B",L13>95%,"C") -> #DIV/0!
B14: flip черный | D14: =C14/C$18 -> #DIV/0! | E14: =D14+E13 -> #DIV/0! | F14: =IF(AND(E14<=0),"C",IF(E14<=0.8,"A",IF(E14<=0.95,"B","C"))) -> #DIV/0! | G14: =VLOOKUP(B$4:B$17,I$4:M$17,5,0) -> #DIV/0! | I14: flip черный | K14: =J14/J$18 -> #DIV/0! | L14: =K14+L13 -> #DIV/0! | M14: =_xlfn.IFS(L14<80%,"A",L14<=95%,"B",L14>95%,"C") -> #DIV/0!
B15: flip синий | D15: =C15/C$18 -> #DIV/0! | E15: =D15+E14 -> #DIV/0! | F15: =IF(AND(E15<=0),"C",IF(E15<=0.8,"A",IF(E15<=0.95,"B","C"))) -> #DIV/0! | G15: =VLOOKUP(B$4:B$17,I$4:M$17,5,0) -> #DIV/0! | I15: flip синий | K15: =J15/J$18 -> #DIV/0! | L15: =K15+L14 -> #DIV/0! | M15: =_xlfn.IFS(L15<80%,"A",L15<=95%,"B",L15>95%,"C") -> #DIV/0!
B16: flip жел | D16: =C16/C$18 -> #DIV/0! | E16: =D16+E15 -> #DIV/0! | F16: =IF(AND(E16<=0),"C",IF(E16<=0.8,"A",IF(E16<=0.95,"B","C"))) -> #DIV/0! | G16: =VLOOKUP(B$4:B$17,I$4:M$17,5,0) -> #DIV/0! | I16: flip жел | K16: =J16/J$18 -> #DIV/0! | L16: =K16+L15 -> #DIV/0! | M16: =_xlfn.IFS(L16<80%,"A",L16<=95%,"B",L16>95%,"C") -> #DIV/0!
B17: flip коричневый | D17: =C17/C$18 -> #DIV/0! | E17: =D17+E14 -> #DIV/0! | F17: =IF(AND(E17<=0),"C",IF(E17<=0.8,"A",IF(E17<=0.95,"B","C"))) -> #DIV/0! | G17: =VLOOKUP(B$4:B$17,I$4:M$17,5,0) -> #DIV/0! | I17: flip коричневый | K17: =J17/J$18 -> #DIV/0! | L17: =K17+L14 -> #DIV/0! | M17: =_xlfn.IFS(L17<80%,"A",L17<=95%,"B",L17>95%,"C") -> #DIV/0!
C18: =SUM(C4:C17) -> 0 | D18: =SUM(D4:D17) -> #DIV/0! | J18: =SUM(J4:J17) -> 0 | K18: =SUM(K4:K17) -> #DIV/0!
C21: Прибыль | D21: % прибыль | E21: Доля | F21: ABC прибыль | G21: ABC кол-во | J21: Кол-во | K21: % кол-во | L21: Доля | M21: ABC кол-во
D22: =C22/C$42 -> #DIV/0! | E22: =D22 -> #DIV/0! | F22: =IF(AND(E22<=0),"C",IF(E22<=0.8,"A",IF(E22<=0.95,"B","C"))) -> #DIV/0! | G22: =VLOOKUP(B$22:B$42,I$22:M$42,5,0) -> #N/A | K22: =J22/J$42 -> #DIV/0! | L22: =K22 -> #DIV/0! | M22: =_xlfn.IFS(L22<80%,"A",L22<=95%,"B",L22>95%,"C") -> #DIV/0!
D23: =C23/C$42 -> #DIV/0! | E23: =D23+E22 -> #DIV/0! | F23: =IF(AND(E23<=0),"C",IF(E23<=0.8,"A",IF(E23<=0.95,"B","C"))) -> #DIV/0! | G23: =VLOOKUP(B$22:B$42,I$22:M$42,5,0) -> #N/A | K23: =J23/J$42 -> #DIV/0! | L23: =K23+L22 -> #DIV/0! | M23: =_xlfn.IFS(L23<80%,"A",L23<=95%,"B",L23>95%,"C") -> #DIV/0!
D24: =C24/C$42 -> #DIV/0! | E24: =D24+E23 -> #DIV/0! | F24: =IF(AND(E24<=0),"C",IF(E24<=0.8,"A",IF(E24<=0.95,"B","C"))) -> #DIV/0! | G24: =VLOOKUP(B$22:B$42,I$22:M$42,5,0) -> #N/A | K24: =J24/J$42 -> #DIV/0! | L24: =K24+L23 -> #DIV/0! | M24: =_xlfn.IFS(L24<80%,"A",L24<=95%,"B",L24>95%,"C") -> #DIV/0!
D25: =C25/C$42 -> #DIV/0! | E25: =D25+E24 -> #DIV/0! | F25: =IF(AND(E25<=0),"C",IF(E25<=0.8,"A",IF(E25<=0.95,"B","C"))) -> #DIV/0! | G25: =VLOOKUP(B$22:B$42,I$22:M$42,5,0) -> #N/A | K25: =J25/J$42 -> #DIV/0! | L25: =K25+L24 -> #DIV/0! | M25: =_xlfn.IFS(L25<80%,"A",L25<=95%,"B",L25>95%,"C") -> #DIV/0!
D26: =C26/C$42 -> #DIV/0! | E26: =D26+E25 -> #DIV/0! | F26: =IF(AND(E26<=0),"C",IF(E26<=0.8,"A",IF(E26<=0.95,"B","C"))) -> #DIV/0! | G26: =VLOOKUP(B$22:B$42,I$22:M$42,5,0) -> #N/A | K26: =J26/J$42 -> #DIV/0! | L26: =K26+L25 -> #DIV/0! | M26: =_xlfn.IFS(L26<80%,"A",L26<=95%,"B",L26>95%,"C") -> #DIV/0!
D27: =C27/C$42 -> #DIV/0! | E27: =D27+E26 -> #DIV/0! | F27: =IF(AND(E27<=0),"C",IF(E27<=0.8,"A",IF(E27<=0.95,"B","C"))) -> #DIV/0! | G27: =VLOOKUP(B$22:B$42,I$22:M$42,5,0) -> #N/A | K27: =J27/J$42 -> #DIV/0! | L27: =K27+L26 -> #DIV/0! | M27: =_xlfn.IFS(L27<80%,"A",L27<=95%,"B",L27>95%,"C") -> #DIV/0!
D28: =C28/C$42 -> #DIV/0! | E28: =D28+E27 -> #DIV/0! | F28: =IF(AND(E28<=0),"C",IF(E28<=0.8,"A",IF(E28<=0.95,"B","C"))) -> #DIV/0! | G28: =VLOOKUP(B$22:B$42,I$22:M$42,5,0) -> #N/A | K28: =J28/J$42 -> #DIV/0! | L28: =K28+L27 -> #DIV/0! | M28: =_xlfn.IFS(L28<80%,"A",L28<=95%,"B",L28>95%,"C") -> #DIV/0!
D29: =C29/C$42 -> #DIV/0! | E29: =D29+E28 -> #DIV/0! | F29: =IF(AND(E29<=0),"C",IF(E29<=0.8,"A",IF(E29<=0.95,"B","C"))) -> #DIV/0! | G29: =VLOOKUP(B$22:B$42,I$22:M$42,5,0) -> #N/A | K29: =J29/J$42 -> #DIV/0! | L29: =K29+L28 -> #DIV/0! | M29: =_xlfn.IFS(L29<80%,"A",L29<=95%,"B",L29>95%,"C") -> #DIV/0!
D30: =C30/C$42 -> #DIV/0! | E30: =D30+E29 -> #DIV/0! | F30: =IF(AND(E30<=0),"C",IF(E30<=0.8,"A",IF(E30<=0.95,"B","C"))) -> #DIV/0! | G30: =VLOOKUP(B$22:B$42,I$22:M$42,5,0) -> #N/A | K30: =J30/J$42 -> #DIV/0! | L30: =K30+L29 -> #DIV/0! | M30: =_xlfn.IFS(L30<80%,"A",L30<=95%,"B",L30>95%,"C") -> #DIV/0!
D31: =C31/C$42 -> #DIV/0! | E31: =D31+E30 -> #DIV/0! | F31: =IF(AND(E31<=0),"C",IF(E31<=0.8,"A",IF(E31<=0.95,"B","C"))) -> #DIV/0! | G31: =VLOOKUP(B$22:B$42,I$22:M$42,5,0) -> #N/A | K31: =J31/J$42 -> #DIV/0! | L31: =K31+L30 -> #DIV/0! | M31: =_xlfn.IFS(L31<80%,"A",L31<=95%,"B",L31>95%,"C") -> #DIV/0!
D32: =C32/C$42 -> #DIV/0! | E32: =D32+E31 -> #DIV/0! | F32: =IF(AND(E32<=0),"C",IF(E32<=0.8,"A",IF(E32<=0.95,"B","C"))) -> #DIV/0! | G32: =VLOOKUP(B$22:B$42,I$22:M$42,5,0) -> #N/A | K32: =J32/J$42 -> #DIV/0! | L32: =K32+L31 -> #DIV/0! | M32: =_xlfn.IFS(L32<80%,"A",L32<=95%,"B",L32>95%,"C") -> #DIV/0!
D33: =C33/C$42 -> #DIV/0! | E33: =D33+E32 -> #DIV/0! | F33: =IF(AND(E33<=0),"C",IF(E33<=0.8,"A",IF(E33<=0.95,"B","C"))) -> #DIV/0! | G33: =VLOOKUP(B$22:B$42,I$22:M$42,5,0) -> #N/A | K33: =J33/J$42 -> #DIV/0! | L33: =K33+L32 -> #DIV/0! | M33: =_xlfn.IFS(L33<80%,"A",L33<=95%,"B",L33>95%,"C") -> #DIV/0!
D34: =C34/C$42 -> #DIV/0! | E34: =D34+E33 -> #DIV/0! | F34: =IF(AND(E34<=0),"C",IF(E34<=0.8,"A",IF(E34<=0.95,"B","C"))) -> #DIV/0! | G34: =VLOOKUP(B$22:B$42,I$22:M$42,5,0) -> #N/A | K34: =J34/J$42 -> #DIV/0! | L34: =K34+L33 -> #DIV/0! | M34: =_xlfn.IFS(L34<80%,"A",L34<=95%,"B",L34>95%,"C") -> #DIV/0!
... D41: =C41/C$42 -> #DIV/0! | E41: =D41+E40 -> #DIV/0! | F41: =IF(AND(E41<=0),"C",IF(E41<=0.8,"A",IF(E41<=0.95,"B","C"))) -> #DIV/0! | G41: =VLOOKUP(B$22:B$42,I$22:M$42,5,0) -> #N/A | K41: =J41/J$42 -> #DIV/0! | L41: =K41+L40 -> #DIV/0! | M41: =_xlfn.IFS(L41<80%,"A",L41<=95%,"B",L41>95%,"C") -> #DIV/0!
C42: =SUM(C22:C41) -> 0 | D42: =SUM(D22:D41) -> #DIV/0! | J42: =SUM(J22:J41) -> 0 | K42: =SUM(K22:K41) -> #DIV/0!

Sheet АВС ЯНВАРЬ
B2: ОЧКИ
C3: Прибыль | D3: % прибыль | E3: Доля | F3: ABC прибыль | G3: ABC кол-во | J3: Кол-во | K3: % кол-во | L3: Доля | M3: ABC кол-во
B4: flip жел | C4: =ЯНВАРЬ!AE15 -> 30164.137 | D4: =C4/C$18 -> 0.27352858 | E4: =D4 -> 0.27352858 | F4: =IF(AND(E4<=0),"C",IF(E4<=0.8,"A",IF(E4<=0.95,"B","C"))) -> A | G4: =VLOOKUP(B$4:B$17,I$4:M$17,5,0) -> A | I4: th желт | J4: =ЯНВАРЬ!R11 -> 165 | K4: =J4/J$18 -> 0.31190926 | L4: =K4 -> 0.31190926 | M4: =_xlfn.IFS(L4<80%,"A",L4<=95%,"B",L4>95%,"C") -> A
B5: th желт | C5: =ЯНВАРЬ!AE11 -> 27810.244 | D5: =C5/C$18 -> 0.25218347 | E5: =D5+E4 -> 0.52571205 | F5: =IF(AND(E5<=0),"C",IF(E5<=0.8,"A",IF(E5<=0.95,"B","C"))) -> A | G5: =VLOOKUP(B$4:B$17,I$4:M$17,5,0) -> A | I5: flip жел | J5: =ЯНВАРЬ!R15 -> 161 | K5: =J5/J$18 -> 0.30434783 | L5: =K5+L4 -> 0.61625709 | M5: =_xlfn.IFS(L5<80%,"A",L5<=95%,"B",L5>95%,"C") -> A
B6: qs желтые | C6: =ЯНВАРЬ!AE6 -> 20914.501 | D6: =C6/C$18 -> 0.18965283 | E6: =D6+E5 -> 0.71536488 | F6: =IF(AND(E6<=0),"C",IF(E6<=0.8,"A",IF(E6<=0.95,"B","C"))) -> A | G6: =VLOOKUP(B$4:B$17,I$4:M$17,5,0) -> A | I6: qs желтые | J6: =ЯНВАРЬ!R6 -> 82 | K6: =J6/J$18 -> 0.15500945 | L6: =K6+L5 -> 0.77126654 | M6: =_xlfn.IFS(L6<80%,"A",L6<=95%,"B",L6>95%,"C") -> A
B7: qs черные | C7: =ЯНВАРЬ!AE4 -> 10414.952 | D7: =C7/C$18 -> 0.094442848 | E7: =D7+E6 -> 0.80980772 | F7: =IF(AND(E7<=0),"C",IF(E7<=0.8,"A",IF(E7<=0.95,"B","C"))) -> B | G7: =VLOOKUP(B$4:B$17,I$4:M$17,5,0) -> C | I7: qs коричневые | J7: =ЯНВАРЬ!R7 -> 45 | K7: =J7/J$18 -> 0.085066163 | L7: =K7+L6 -> 0.8563327 | M7: =_xlfn.IFS(L7<80%,"A",L7<=95%,"B",L7>95%,"C") -> B
B8: qs коричневые | C8: =ЯНВАРЬ!AE7 -> 9317.0299 | D8: =C8/C$18 -> 0.084486886 | E8: =D8+E7 -> 0.89429461 | F8: =IF(AND(E8<=0),"C",IF(E8<=0.8,"A",IF(E8<=0.95,"B","C"))) -> B | G8: =VLOOKUP(B$4:B$17,I$4:M$17,5,0) -> B | I8: MR8854 C2 | J8: =ЯНВАРЬ!R8 -> 31 | K8: =J8/J$18 -> 0.058601134 | L8: =K8+L7 -> 0.91493384 | M8: =_xlfn.IFS(L8<80%,"A",L8<=95%,"B",L8>95%,"C") -> B
B9: черные с железкой классика | C9: =ЯНВАРЬ!AE3 -> 6488.9299 | D9: =C9/C$18 -> 0.058841658 | E9: =D9+E8 -> 0.95313627 | F9: =IF(AND(E9<=0),"C",IF(E9<=0.8,"A",IF(E9<=0.95,"B","C"))) -> C | G9: =VLOOKUP(B$4:B$17,I$4:M$17,5,0) -> C | I9: qs черные | J9: =ЯНВАРЬ!R4 -> 19 | K9: =J9/J$18 -> 0.035916824 | L9: =K9+L8 -> 0.95085066 | M9: =_xlfn.IFS(L9<80%,"A",L9<=95%,"B",L9>95%,"C") -> C
B10: qs синие | C10: =ЯНВАРЬ!AE5 -> 4628.4433 | D10: =C10/C$18 -> 0.041970753 | E10: =D10+E9 -> 0.99510702 | F10: =IF(AND(E10<=0),"C",IF(E10<=0.8,"A",IF(E10<=0.95,"B","C"))) -> C | G10: =VLOOKUP(B$4:B$17,I$4:M$17,5,0) -> C | I10: черные с железкой классика | J10: =ЯНВАРЬ!R3 -> 15 | K10: =J10/J$18 -> 0.028355388 | L10: =K10+L9 -> 0.97920605 | M10: =_xlfn.IFS(L10<80%,"A",L10<=95%,"B",L10>95%,"C") -> C
B11: MR8854 C2 | C11: =ЯНВАРЬ!AE8 -> 4052.5984 | D11: =C11/C$18 -> 0.036748988 | E11: =D11+E10 -> 1.031856 | F11: =IF(AND(E11<=0),"C",IF(E11<=0.8,"A",IF(E11<=0.95,"B","C"))) -> C | G11: =VLOOKUP(B$4:B$17,I$4:M$17,5,0) -> B | I11: qs синие | J11: =ЯНВАРЬ!R5 -> 9 | K11: =J11/J$18 -> 0.017013233 | L11: =K11+L10 -> 0.99621928 | M11: =_xlfn.IFS(L11<80%,"A",L11<=95%,"B",L11>95%,"C") -> C
B12: th черн | C12: =ЯНВАРЬ!AE9 -> 284.37054 | D12: =C12/C$18 -> 0.0025786739 | E12: =D12+E5 -> 0.52829072 | F12: =IF(AND(E12<=0),"C",IF(E12<=0.8,"A",IF(E12<=0.95,"B","C"))) -> A | G12: =VLOOKUP(B$4:B$17,I$4:M$17,5,0) -> A | I12: th черн | J12: =ЯНВАРЬ!R9 -> 1 | K12: =J12/J$18 -> 0.0018903592 | L12: =K12+L5 -> 0.61814745 | M12: =_xlfn.IFS(L12<80%,"A",L12<=95%,"B",L12>95%,"C") -> A
B13: flip черный | C13: =ЯНВАРЬ!AE13 -> 207.80595 | D13: =C13/C$18 -> 0.0018843857 | E13: =D13+E12 -> 0.53017511 | F13: =IF(AND(E13<=0),"C",IF(E13<=0.8,"A",IF(E13<=0.95,"B","C"))) -> A | G13: =VLOOKUP(B$4:B$17,I$4:M$17,5,0) -> A | I13: flip черный | J13: =ЯНВАРЬ!R13 -> 1 | K13: =J13/J$18 -> 0.0018903592 | L13: =K13+L12 -> 0.62003781 | M13: =_xlfn.IFS(L13<80%,"A",L13<=95%,"B",L13>95%,"C") -> A
B14: th коричн | C14: =ЯНВАРЬ!AE12 -> -555.84386 | D14: =C14/C$18 -> -0.0050403956 | E14: =D14+E13 -> 0.52513471 | F14: =IF(AND(E14<=0),"C",IF(E14<=0.8,"A",IF(E14<=0.95,"B","C"))) -> A | G14: =VLOOKUP(B$4:B$17,I$4:M$17,5,0) -> A | I14: th син | J14: =ЯНВАРЬ!R10 -> 0 | K14: =J14/J$18 -> 0 | L14: =K14+L13 -> 0.62003781 | M14: =_xlfn.IFS(L14<80%,"A",L14<=95%,"B",L14>95%,"C") -> A
B15: flip синий | C15: =ЯНВАРЬ!AE14 -> -607.06546 | D15: =C15/C$18 -> -0.0055048734 | E15: =D15+E14 -> 0.51962984 | F15: =IF(AND(E15<=0),"C",IF(E15<=0.8,"A",IF(E15<=0.95,"B","C"))) -> A | G15: =VLOOKUP(B$4:B$17,I$4:M$17,5,0) -> A | I15: th коричн | J15: =ЯНВАРЬ!R12 -> 0 | K15: =J15/J$18 -> 0 | L15: =K15+L14 -> 0.62003781 | M15: =_xlfn.IFS(L15<80%,"A",L15<=95%,"B",L15>95%,"C") -> A
B16: flip коричневый | C16: =ЯНВАРЬ!AE16 -> -1324.8447 | D16: =C16/C$18 -> -0.0120137 | E16: =D16+E15 -> 0.50761614 | F16: =IF(AND(E16<=0),"C",IF(E16<=0.8,"A",IF(E16<=0.95,"B","C"))) -> A | G16: =VLOOKUP(B$4:B$17,I$4:M$17,5,0) -> A | I16: flip синий | J16: =ЯНВАРЬ!R14 -> 0 | K16: =J16/J$18 -> 0 | L16: =K16+L15 -> 0.62003781 | M16: =_xlfn.IFS(L16<80%,"A",L16<=95%,"B",L16>95%,"C") -> A
B17: th син | C17: =ЯНВАРЬ!AE10 -> -1517.4339 | D17: =C17/C$18 -> -0.0137601 | E17: =D17+E14 -> 0.51137461 | F17: =IF(AND(E17<=0),"C",IF(E17<=0.8,"A",IF(E17<=0.95,"B","C"))) -> A | G17: =VLOOKUP(B$4:B$17,I$4:M$17,5,0) -> A | I17: flip коричневый | J17: =ЯНВАРЬ!R16 -> 0 | K17: =J17/J$18 -> 0 | L17: =K17+L14 -> 0.62003781 | M17: =_xlfn.IFS(L17<80%,"A",L17<=95%,"B",L17>95%,"C") -> A
C18: =SUM(C4:C17) -> 110277.82 | D18: =SUM(D4:D17) -> 1 | J18: =SUM(J4:J17) -> 529 | K18: =SUM(K4:K17) -> 1
C21: Прибыль | D21: % прибыль | E21: Доля | F21: ABC прибыль | G21: ABC кол-во | J21: Кол-во | K21: % кол-во | L21: Доля | M21: ABC кол-во
D22: =C22/C$42 -> #DIV/0! | E22: =D22 -> #DIV/0! | F22: =IF(AND(E22<=0),"C",IF(E22<=0.8,"A",IF(E22<=0.95,"B","C"))) -> #DIV/0! | G22: =VLOOKUP(B$22:B$42,I$22:M$42,5,0) -> #N/A | K22: =J22/J$42 -> #DIV/0! | L22: =K22 -> #DIV/0! | M22: =_xlfn.IFS(L22<80%,"A",L22<=95%,"B",L22>95%,"C") -> #DIV/0!
D23: =C23/C$42 -> #DIV/0! | E23: =D23+E22 -> #DIV/0! | F23: =IF(AND(E23<=0),"C",IF(E23<=0.8,"A",IF(E23<=0.95,"B","C"))) -> #DIV/0! | G23: =VLOOKUP(B$22:B$42,I$22:M$42,5,0) -> #N/A | K23: =J23/J$42 -> #DIV/0! | L23: =K23+L22 -> #DIV/0! | M23: =_xlfn.IFS(L23<80%,"A",L23<=95%,"B",L23>95%,"C") -> #DIV/0!
D24: =C24/C$42 -> #DIV/0! | E24: =D24+E23 -> #DIV/0! | F24: =IF(AND(E24<=0),"C",IF(E24<=0.8,"A",IF(E24<=0.95,"B","C"))) -> #DIV/0! | G24: =VLOOKUP(B$22:B$42,I$22:M$42,5,0) -> #N/A | K24: =J24/J$42 -> #DIV/0! | L24: =K24+L23 -> #DIV/0! | M24: =_xlfn.IFS(L24<80%,"A",L24<=95%,"B",L24>95%,"C") -> #DIV/0!
D25: =C25/C$42 -> #DIV/0! | E25: =D25+E24 -> #DIV/0! | F25: =IF(AND(E25<=0),"C",IF(E25<=0.8,"A",IF(E25<=0.95,"B","C"))) -> #DIV/0! | G25: =VLOOKUP(B$22:B$42,I$22:M$42,5,0) -> #N/A | K25: =J25/J$42 -> #DIV/0! | L25: =K25+L24 -> #DIV/0! | M25: =_xlfn.IFS(L25<80%,"A",L25<=95%,"B",L25>95%,"C") -> #DIV/0!
D26: =C26/C$42 -> #DIV/0! | E26: =D26+E25 -> #DIV/0! | F26: =IF(AND(E26<=0),"C",IF(E26<=0.8,"A",IF(E26<=0.95,"B","C"))) -> #DIV/0! | G26: =VLOOKUP(B$22:B$42,I$22:M$42,5,0) -> #N/A | K26: =J26/J$42 -> #DIV/0! | L26: =K26+L25 -> #DIV/0! | M26: =_xlfn.IFS(L26<80%,"A",L26<=95%,"B",L26>95%,"C") -> #DIV/0!
D27: =C27/C$42 -> #DIV/0! | E27: =D27+E26 -> #DIV/0! | F27: =IF(AND(E27<=0),"C",IF(E27<=0.8,"A",IF(E27<=0.95,"B","C"))) -> #DIV/0! | G27: =VLOOKUP(B$22:B$42,I$22:M$42,5,0) -> #N/A | K27: =J27/J$42 -> #DIV/0! | L27: =K27+L26 -> #DIV/0! | M27: =_xlfn.IFS(L27<80%,"A",L27<=95%,"B",L27>95%,"C") -> #DIV/0!
D28: =C28/C$42 -> #DIV/0! | E28: =D28+E27 -> #DIV/0! | F28: =IF(AND(E28<=0),"C",IF(E28<=0.8,"A",IF(E28<=0.95,"B","C"))) -> #DIV/0! | G28: =VLOOKUP(B$22:B$42,I$22:M$42,5,0) -> #N/A | K28: =J28/J$42 -> #DIV/0! | L28: =K28+L27 -> #DIV/0! | M28: =_xlfn.IFS(L28<80%,"A",L28<=95%,"B",L28>95%,"C") -> #DIV/0!
D29: =C29/C$42 -> #DIV/0! | E29: =D29+E28 -> #DIV/0! | F29: =IF(AND(E29<=0),"C",IF(E29<=0.8,"A",IF(E29<=0.95,"B","C"))) -> #DIV/0! | G29: =VLOOKUP(B$22:B$42,I$22:M$42,5,0) -> #N/A | K29: =J29/J$42 -> #DIV/0! | L29: =K29+L28 -> #DIV/0! | M29: =_xlfn.IFS(L29<80%,"A",L29<=95%,"B",L29>95%,"C") -> #DIV/0!
D30: =C30/C$42 -> #DIV/0! | E30: =D30+E29 -> #DIV/0! | F30: =IF(AND(E30<=0),"C",IF(E30<=0.8,"A",IF(E30<=0.95,"B","C"))) -> #DIV/0! | G30: =VLOOKUP(B$22:B$42,I$22:M$42,5,0) -> #N/A | K30: =J30/J$42 -> #DIV/0! | L30: =K30+L29 -> #DIV/0! | M30: =_xlfn.IFS(L30<80%,"A",L30<=95%,"B",L30>95%,"C") -> #DIV/0!
D31: =C31/C$42 -> #DIV/0! | E31: =D31+E30 -> #DIV/0! | F31: =IF(AND(E31<=0),"C",IF(E31<=0.8,"A",IF(E31<=0.95,"B","C"))) -> #DIV/0! | G31: =VLOOKUP(B$22:B$42,I$22:M$42,5,0) -> #N/A | K31: =J31/J$42 -> #DIV/0! | L31: =K31+L30 -> #DIV/0! | M31: =_xlfn.IFS(L31<80%,"A",L31<=95%,"B",L31>95%,"C") -> #DIV/0!
D32: =C32/C$42 -> #DIV/0! | E32: =D32+E31 -> #DIV/0! | F32: =IF(AND(E32<=0),"C",IF(E32<=0.8,"A",IF(E32<=0.95,"B","C"))) -> #DIV/0! | G32: =VLOOKUP(B$22:B$42,I$22:M$42,5,0) -> #N/A | K32: =J32/J$42 -> #DIV/0! | L32: =K32+L31 -> #DIV/0! | M32: =_xlfn.IFS(L32<80%,"A",L32<=95%,"B",L32>95%,"C") -> #DIV/0!
D33: =C33/C$42 -> #DIV/0! | E33: =D33+E32 -> #DIV/0! | F33: =IF(AND(E33<=0),"C",IF(E33<=0.8,"A",IF(E33<=0.95,"B","C"))) -> #DIV/0! | G33: =VLOOKUP(B$22:B$42,I$22:M$42,5,0) -> #N/A | K33: =J33/J$42 -> #DIV/0! | L33: =K33+L32 -> #DIV/0! | M33: =_xlfn.IFS(L33<80%,"A",L33<=95%,"B",L33>95%,"C") -> #DIV/0!
D34: =C34/C$42 -> #DIV/0! | E34: =D34+E33 -> #DIV/0! | F34: =IF(AND(E34<=0),"C",IF(E34<=0.8,"A",IF(E34<=0.95,"B","C"))) -> #DIV/0! | G34: =VLOOKUP(B$22:B$42,I$22:M$42,5,0) -> #N/A | K34: =J34/J$42 -> #DIV/0! | L34: =K34+L33 -> #DIV/0! | M34: =_xlfn.IFS(L34<80%,"A",L34<=95%,"B",L34>95%,"C") -> #DIV/0!
... D41: =C41/C$42 -> #DIV/0! | E41: =D41+E40 -> #DIV/0! | F41: =IF(AND(E41<=0),"C",IF(E41<=0.8,"A",IF(E41<=0.95,"B","C"))) -> #DIV/0! | G41: =VLOOKUP(B$22:B$42,I$22:M$42,5,0) -> #N/A | K41: =J41/J$42 -> #DIV/0! | L41: =K41+L40 -> #DIV/0! | M41: =_xlfn.IFS(L41<80%,"A",L41<=95%,"B",L41>95%,"C") -> #DIV/0!
C42: =SUM(C22:C41) -> 0 | D42: =SUM(D22:D41) -> #DIV/0! | J42: =SUM(J22:J41) -> 0 | K42: =SUM(K22:K41) -> #DIV/0!

Sheet АВС 26.01-01.02
B2: ОЧКИ
C3: Прибыль | D3: % прибыль | E3: Доля | F3: ABC прибыль | G3: ABC кол-во | J3: Кол-во | K3: % кол-во | L3: Доля | M3: ABC кол-во
B4: th желт | C4: ='Юнит 26.01-01.02'!AE11 -> 16111.061 | D4: =C4/C$18 -> 0.51770375 | E4: =D4 -> 0.51770375 | F4: =IF(AND(E4<=0),"C",IF(E4<=0.8,"A",IF(E4<=0.95,"B","C"))) -> A | G4: =VLOOKUP(B$4:B$17,I$4:M$17,5,0) -> A | I4: th желт | J4: ='Юнит 26.01-01.02'!R11 -> 48 | K4: =J4/J$18 -> 0.375 | L4: =K4 -> 0.375 | M4: =_xlfn.IFS(L4<80%,"A",L4<=95%,"B",L4>95%,"C") -> A
B5: flip жел | C5: ='Юнит 26.01-01.02'!AE15 -> 11558.881 | D5: =C5/C$18 -> 0.37142657 | E5: =D5+E4 -> 0.88913032 | F5: =IF(AND(E5<=0),"C",IF(E5<=0.8,"A",IF(E5<=0.95,"B","C"))) -> B | G5: =VLOOKUP(B$4:B$17,I$4:M$17,5,0) -> A | I5: flip жел | J5: ='Юнит 26.01-01.02'!R15 -> 38 | K5: =J5/J$18 -> 0.296875 | L5: =K5+L4 -> 0.671875 | M5: =_xlfn.IFS(L5<80%,"A",L5<=95%,"B",L5>95%,"C") -> A
B6: qs черные | C6: ='Юнит 26.01-01.02'!AE4 -> 3322.05 | D6: =C6/C$18 -> 0.10674888 | E6: =D6+E5 -> 0.9958792 | F6: =IF(AND(E6<=0),"C",IF(E6<=0.8,"A",IF(E6<=0.95,"B","C"))) -> C | G6: =VLOOKUP(B$4:B$17,I$4:M$17,5,0) -> C | I6: qs коричневые | J6: ='Юнит 26.01-01.02'!R7 -> 16 | K6: =J6/J$18 -> 0.125 | L6: =K6+L5 -> 0.796875 | M6: =_xlfn.IFS(L6<80%,"A",L6<=95%,"B",L6>95%,"C") -> A
B7: MR8854 C2 | C7: ='Юнит 26.01-01.02'!AE8 -> 1849.5272 | D7: =C7/C$18 -> 0.059431665 | E7: =D7+E6 -> 1.0553109 | F7: =IF(AND(E7<=0),"C",IF(E7<=0.8,"A",IF(E7<=0.95,"B","C"))) -> C | G7: =VLOOKUP(B$4:B$17,I$4:M$17,5,0) -> B | I7: MR8854 C2 | J7: ='Юнит 26.01-01.02'!R8 -> 10 | K7: =J7/J$18 -> 0.078125 | L7: =K7+L6 -> 0.875 | M7: =_xlfn.IFS(L7<80%,"A",L7<=95%,"B",L7>95%,"C") -> B
B8: qs желтые | C8: ='Юнит 26.01-01.02'!AE6 -> 1191.36 | D8: =C8/C$18 -> 0.038282491 | E8: =D8+E7 -> 1.0935934 | F8: =IF(AND(E8<=0),"C",IF(E8<=0.8,"A",IF(E8<=0.95,"B","C"))) -> C | G8: =VLOOKUP(B$4:B$17,I$4:M$17,5,0) -> B | I8: qs желтые | J8: ='Юнит 26.01-01.02'!R6 -> 6 | K8: =J8/J$18 -> 0.046875 | L8: =K8+L7 -> 0.921875 | M8: =_xlfn.IFS(L8<80%,"A",L8<=95%,"B",L8>95%,"C") -> B
B9: th коричн | C9: ='Юнит 26.01-01.02'!AE12 -> 291.34614 | D9: =C9/C$18 -> 0.0093619527 | E9: =D9+E8 -> 1.1029553 | F9: =IF(AND(E9<=0),"C",IF(E9<=0.8,"A",IF(E9<=0.95,"B","C"))) -> C | G9: =VLOOKUP(B$4:B$17,I$4:M$17,5,0) -> A | I9: qs черные | J9: ='Юнит 26.01-01.02'!R4 -> 5 | K9: =J9/J$18 -> 0.0390625 | L9: =K9+L8 -> 0.9609375 | M9: =_xlfn.IFS(L9<80%,"A",L9<=95%,"B",L9>95%,"C") -> C
B10: th черн | C10: ='Юнит 26.01-01.02'!AE9 -> 284.37054 | D10: =C10/C$18 -> 0.0091378028 | E10: =D10+E9 -> 1.1120931 | F10: =IF(AND(E10<=0),"C",IF(E10<=0.8,"A",IF(E10<=0.95,"B","C"))) -> C | G10: =VLOOKUP(B$4:B$17,I$4:M$17,5,0) -> C | I10: черные с железкой классика | J10: ='Юнит 26.01-01.02'!R3 -> 1 | K10: =J10/J$18 -> 0.0078125 | L10: =K10+L9 -> 0.96875 | M10: =_xlfn.IFS(L10<80%,"A",L10<=95%,"B",L10>95%,"C") -> C
B11: flip черный | C11: ='Юнит 26.01-01.02'!AE13 -> 207.80595 | D11: =C11/C$18 -> 0.0066775192 | E11: =D11+E10 -> 1.1187706 | F11: =IF(AND(E11<=0),"C",IF(E11<=0.8,"A",IF(E11<=0.95,"B","C"))) -> C | G11: =VLOOKUP(B$4:B$17,I$4:M$17,5,0) -> A | I11: th черн | J11: ='Юнит 26.01-01.02'!R9 -> 1 | K11: =J11/J$18 -> 0.0078125 | L11: =K11+L10 -> 0.9765625 | M11: =_xlfn.IFS(L11<80%,"A",L11<=95%,"B",L11>95%,"C") -> C
B12: черные с железкой классика | C12: ='Юнит 26.01-01.02'!AE3 -> 152.11 | D12: =C12/C$18 -> 0.004887817 | E12: =D12+E5 -> 0.89401814 | F12: =IF(AND(E12<=0),"C",IF(E12<=0.8,"A",IF(E12<=0.95,"B","C"))) -> B | G12: =VLOOKUP(B$4:B$17,I$4:M$17,5,0) -> C | I12: th син | J12: ='Юнит 26.01-01.02'!R10 -> 1 | K12: =J12/J$18 -> 0.0078125 | L12: =K12+L5 -> 0.6796875 | M12: =_xlfn.IFS(L12<80%,"A",L12<=95%,"B",L12>95%,"C") -> A
B13: qs синие | C13: ='Юнит 26.01-01.02'!AE5 -> 0 | D13: =C13/C$18 -> 0 | E13: =D13+E12 -> 0.89401814 | F13: =IF(AND(E13<=0),"C",IF(E13<=0.8,"A",IF(E13<=0.95,"B","C"))) -> B | G13: =VLOOKUP(B$4:B$17,I$4:M$17,5,0) -> A | I13: th коричн | J13: ='Юнит 26.01-01.02'!R12 -> 1 | K13: =J13/J$18 -> 0.0078125 | L13: =K13+L12 -> 0.6875 | M13: =_xlfn.IFS(L13<80%,"A",L13<=95%,"B",L13>95%,"C") -> A
B14: qs коричневые | C14: ='Юнит 26.01-01.02'!AE7 -> -472.79957 | D14: =C14/C$18 -> -0.015192675 | E14: =D14+E13 -> 0.87882546 | F14: =IF(AND(E14<=0),"C",IF(E14<=0.8,"A",IF(E14<=0.95,"B","C"))) -> B | G14: =VLOOKUP(B$4:B$17,I$4:M$17,5,0) -> A | I14: flip черный | J14: ='Юнит 26.01-01.02'!R13 -> 1 | K14: =J14/J$18 -> 0.0078125 | L14: =K14+L13 -> 0.6953125 | M14: =_xlfn.IFS(L14<80%,"A",L14<=95%,"B",L14>95%,"C") -> A
B15: flip синий | C15: ='Юнит 26.01-01.02'!AE14 -> -807.06546 | D15: =C15/C$18 -> -0.025933786 | E15: =D15+E14 -> 0.85289167 | F15: =IF(AND(E15<=0),"C",IF(E15<=0.8,"A",IF(E15<=0.95,"B","C"))) -> B | G15: =VLOOKUP(B$4:B$17,I$4:M$17,5,0) -> A | I15: qs синие | J15: ='Юнит 26.01-01.02'!R5 -> 0 | K15: =J15/J$18 -> 0 | L15: =K15+L14 -> 0.6953125 | M15: =_xlfn.IFS(L15<80%,"A",L15<=95%,"B",L15>95%,"C") -> A
B16: th син | C16: ='Юнит 26.01-01.02'!AE10 -> -963.6769 | D16: =C16/C$18 -> -0.03096625 | E16: =D16+E15 -> 0.82192542 | F16: =IF(AND(E16<=0),"C",IF(E16<=0.8,"A",IF(E16<=0.95,"B","C"))) -> B | G16: =VLOOKUP(B$4:B$17,I$4:M$17,5,0) -> A | I16: flip синий | J16: ='Юнит 26.01-01.02'!R14 -> 0 | K16: =J16/J$18 -> 0 | L16: =K16+L15 -> 0.6953125 | M16: =_xlfn.IFS(L16<80%,"A",L16<=95%,"B",L16>95%,"C") -> A
B17: flip коричневый | C17: ='Юнит 26.01-01.02'!AE16 -> -1604.7377 | D17: =C17/C$18 -> -0.051565737 | E17: =D17+E14 -> 0.82725972 | F17: =IF(AND(E17<=0),"C",IF(E17<=0.8,"A",IF(E17<=0.95,"B","C"))) -> B | G17: =VLOOKUP(B$4:B$17,I$4:M$17,5,0) -> A | I17: flip коричневый | J17: ='Юнит 26.01-01.02'!R16 -> 0 | K17: =J17/J$18 -> 0 | L17: =K17+L14 -> 0.6953125 | M17: =_xlfn.IFS(L17<80%,"A",L17<=95%,"B",L17>95%,"C") -> A
C18: =SUM(C4:C17) -> 31120.232 | D18: =SUM(D4:D17) -> 1 | J18: =SUM(J4:J17) -> 128 | K18: =SUM(K4:K17) -> 1
C21: Прибыль | D21: % прибыль | E21: Доля | F21: ABC прибыль | G21: ABC кол-во | J21: Кол-во | K21: % кол-во | L21: Доля | M21: ABC кол-во
D22: =C22/C$42 -> #DIV/0! | E22: =D22 -> #DIV/0! | F22: =IF(AND(E22<=0),"C",IF(E22<=0.8,"A",IF(E22<=0.95,"B","C"))) -> #DIV/0! | G22: =VLOOKUP(B$22:B$42,I$22:M$42,5,0) -> #N/A | K22: =J22/J$42 -> #DIV/0! | L22: =K22 -> #DIV/0! | M22: =_xlfn.IFS(L22<80%,"A",L22<=95%,"B",L22>95%,"C") -> #DIV/0!
D23: =C23/C$42 -> #DIV/0! | E23: =D23+E22 -> #DIV/0! | F23: =IF(AND(E23<=0),"C",IF(E23<=0.8,"A",IF(E23<=0.95,"B","C"))) -> #DIV/0! | G23: =VLOOKUP(B$22:B$42,I$22:M$42,5,0) -> #N/A | K23: =J23/J$42 -> #DIV/0! | L23: =K23+L22 -> #DIV/0! | M23: =_xlfn.IFS(L23<80%,"A",L23<=95%,"B",L23>95%,"C") -> #DIV/0!
D24: =C24/C$42 -> #DIV/0! | E24: =D24+E23 -> #DIV/0! | F24: =IF(AND(E24<=0),"C",IF(E24<=0.8,"A",IF(E24<=0.95,"B","C"))) -> #DIV/0! | G24: =VLOOKUP(B$22:B$42,I$22:M$42,5,0) -> #N/A | K24: =J24/J$42 -> #DIV/0! | L24: =K24+L23 -> #DIV/0! | M24: =_xlfn.IFS(L24<80%,"A",L24<=95%,"B",L24>95%,"C") -> #DIV/0!
D25: =C25/C$42 -> #DIV/0! | E25: =D25+E24 -> #DIV/0! | F25: =IF(AND(E25<=0),"C",IF(E25<=0.8,"A",IF(E25<=0.95,"B","C"))) -> #DIV/0! | G25: =VLOOKUP(B$22:B$42,I$22:M$42,5,0) -> #N/A | K25: =J25/J$42 -> #DIV/0! | L25: =K25+L24 -> #DIV/0! | M25: =_xlfn.IFS(L25<80%,"A",L25<=95%,"B",L25>95%,"C") -> #DIV/0!
D26: =C26/C$42 -> #DIV/0! | E26: =D26+E25 -> #DIV/0! | F26: =IF(AND(E26<=0),"C",IF(E26<=0.8,"A",IF(E26<=0.95,"B","C"))) -> #DIV/0! | G26: =VLOOKUP(B$22:B$42,I$22:M$42,5,0) -> #N/A | K26: =J26/J$42 -> #DIV/0! | L26: =K26+L25 -> #DIV/0! | M26: =_xlfn.IFS(L26<80%,"A",L26<=95%,"B",L26>95%,"C") -> #DIV/0!
D27: =C27/C$42 -> #DIV/0! | E27: =D27+E26 -> #DIV/0! | F27: =IF(AND(E27<=0),"C",IF(E27<=0.8,"A",IF(E27<=0.95,"B","C"))) -> #DIV/0! | G27: =VLOOKUP(B$22:B$42,I$22:M$42,5,0) -> #N/A | K27: =J27/J$42 -> #DIV/0! | L27: =K27+L26 -> #DIV/0! | M27: =_xlfn.IFS(L27<80%,"A",L27<=95%,"B",L27>95%,"C") -> #DIV/0!
D28: =C28/C$42 -> #DIV/0! | E28: =D28+E27 -> #DIV/0! | F28: =IF(AND(E28<=0),"C",IF(E28<=0.8,"A",IF(E28<=0.95,"B","C"))) -> #DIV/0! | G28: =VLOOKUP(B$22:B$42,I$22:M$42,5,0) -> #N/A | K28: =J28/J$42 -> #DIV/0! | L28: =K28+L27 -> #DIV/0! | M28: =_xlfn.IFS(L28<80%,"A",L28<=95%,"B",L28>95%,"C") -> #DIV/0!
D29: =C29/C$42 -> #DIV/0! | E29: =D29+E28 -> #DIV/0! | F29: =IF(AND(E29<=0),"C",IF(E29<=0.8,"A",IF(E29<=0.95,"B","C"))) -> #DIV/0! | G29: =VLOOKUP(B$22:B$42,I$22:M$42,5,0) -> #N/A | K29: =J29/J$42 -> #DIV/0! | L29: =K29+L28 -> #DIV/0! | M29: =_xlfn.IFS(L29<80%,"A",L29<=95%,"B",L29>95%,"C") -> #DIV/0!
D30: =C30/C$42 -> #DIV/0! | E30: =D30+E29 -> #DIV/0! | F30: =IF(AND(E30<=0),"C",IF(E30<=0.8,"A",IF(E30<=0.95,"B","C"))) -> #DIV/0! | G30: =VLOOKUP(B$22:B$42,I$22:M$42,5,0) -> #N/A | K30: =J30/J$42 -> #DIV/0! | L30: =K30+L29 -> #DIV/0! | M30: =_xlfn.IFS(L30<80%,"A",L30<=95%,"B",L30>95%,"C") -> #DIV/0!
D31: =C31/C$42 -> #DIV/0! | E31: =D31+E30 -> #DIV/0! | F31: =IF(AND(E31<=0),"C",IF(E31<=0.8,"A",IF(E31<=0.95,"B","C"))) -> #DIV/0! | G31: =VLOOKUP(B$22:B$42,I$22:M$42,5,0) -> #N/A | K31: =J31/J$42 -> #DIV/0! | L31: =K31+L30 -> #DIV/0! | M31: =_xlfn.IFS(L31<80%,"A",L31<=95%,"B",L31>95%,"C") -> #DIV/0!
D32: =C32/C$42 -> #DIV/0! | E32: =D32+E31 -> #DIV/0! | F32: =IF(AND(E32<=0),"C",IF(E32<=0.8,"A",IF(E32<=0.95,"B","C"))) -> #DIV/0! | G32: =VLOOKUP(B$22:B$42,I$22:M$42,5,0) -> #N/A | K32: =J32/J$42 -> #DIV/0! | L32: =K32+L31 -> #DIV/0! | M32: =_xlfn.IFS(L32<80%,"A",L32<=95%,"B",L32>95%,"C") -> #DIV/0!
D33: =C33/C$42 -> #DIV/0! | E33: =D33+E32 -> #DIV/0! | F33: =IF(AND(E33<=0),"C",IF(E33<=0.8,"A",IF(E33<=0.95,"B","C"))) -> #DIV/0! | G33: =VLOOKUP(B$22:B$42,I$22:M$42,5,0) -> #N/A | K33: =J33/J$42 -> #DIV/0! | L33: =K33+L32 -> #DIV/0! | M33: =_xlfn.IFS(L33<80%,"A",L33<=95%,"B",L33>95%,"C") -> #DIV/0!
D34: =C34/C$42 -> #DIV/0! | E34: =D34+E33 -> #DIV/0! | F34: =IF(AND(E34<=0),"C",IF(E34<=0.8,"A",IF(E34<=0.95,"B","C"))) -> #DIV/0! | G34: =VLOOKUP(B$22:B$42,I$22:M$42,5,0) -> #N/A | K34: =J34/J$42 -> #DIV/0! | L34: =K34+L33 -> #DIV/0! | M34: =_xlfn.IFS(L34<80%,"A",L34<=95%,"B",L34>95%,"C") -> #DIV/0!
... D41: =C41/C$42 -> #DIV/0! | E41: =D41+E40 -> #DIV/0! | F41: =IF(AND(E41<=0),"C",IF(E41<=0.8,"A",IF(E41<=0.95,"B","C"))) -> #DIV/0! | G41: =VLOOKUP(B$22:B$42,I$22:M$42,5,0) -> #N/A | K41: =J41/J$42 -> #DIV/0! | L41: =K41+L40 -> #DIV/0! | M41: =_xlfn.IFS(L41<80%,"A",L41<=95%,"B",L41>95%,"C") -> #DIV/0!
C42: =SUM(C22:C41) -> 0 | D42: =SUM(D22:D41) -> #DIV/0! | J42: =SUM(J22:J41) -> 0 | K42: =SUM(K22:K41) -> #DIV/0!

Sheet АВС 19-25.01
B2: ОЧКИ
C3: Прибыль | D3: % прибыль | E3: Доля | F3: ABC прибыль | G3: ABC кол-во | J3: Кол-во | K3: % кол-во | L3: Доля | M3: ABC кол-во
B4: qs желтые | C4: ='Юнит 19-25.01'!AE6 -> 10158.92 | D4: =C4/C$18 -> 0.52787056 | E4: =D4 -> 0.52787056 | F4: =IF(AND(E4<=0),"C",IF(E4<=0.8,"A",IF(E4<=0.95,"B","C"))) -> A | G4: =VLOOKUP(B$4:B$17,I$4:M$17,5,0) -> A | I4: th желт | J4: ='Юнит 19-25.01'!R11 -> 26 | K4: =J4/J$18 -> 0.29213483 | L4: =K4 -> 0.29213483 | M4: =_xlfn.IFS(L4<80%,"A",L4<=95%,"B",L4>95%,"C") -> A
B5: qs черные | C5: ='Юнит 19-25.01'!AE4 -> 4879.4517 | D5: =C5/C$18 -> 0.25354259 | E5: =D5+E4 -> 0.78141315 | F5: =IF(AND(E5<=0),"C",IF(E5<=0.8,"A",IF(E5<=0.95,"B","C"))) -> A | G5: =VLOOKUP(B$4:B$17,I$4:M$17,5,0) -> B | I5: qs желтые | J5: ='Юнит 19-25.01'!R6 -> 18 | K5: =J5/J$18 -> 0.20224719 | L5: =K5+L4 -> 0.49438202 | M5: =_xlfn.IFS(L5<80%,"A",L5<=95%,"B",L5>95%,"C") -> A
B6: черные с железкой классика | C6: ='Юнит 19-25.01'!AE3 -> 3054.91 | D6: =C6/C$18 -> 0.15873706 | E6: =D6+E5 -> 0.94015021 | F6: =IF(AND(E6<=0),"C",IF(E6<=0.8,"A",IF(E6<=0.95,"B","C"))) -> B | G6: =VLOOKUP(B$4:B$17,I$4:M$17,5,0) -> B | I6: flip жел | J6: ='Юнит 19-25.01'!R15 -> 17 | K6: =J6/J$18 -> 0.19101124 | L6: =K6+L5 -> 0.68539326 | M6: =_xlfn.IFS(L6<80%,"A",L6<=95%,"B",L6>95%,"C") -> A
B7: qs синие | C7: ='Юнит 19-25.01'!AE5 -> 2087.12 | D7: =C7/C$18 -> 0.10844944 | E7: =D7+E6 -> 1.0485997 | F7: =IF(AND(E7<=0),"C",IF(E7<=0.8,"A",IF(E7<=0.95,"B","C"))) -> C | G7: =VLOOKUP(B$4:B$17,I$4:M$17,5,0) -> C | I7: qs коричневые | J7: ='Юнит 19-25.01'!R7 -> 10 | K7: =J7/J$18 -> 0.11235955 | L7: =K7+L6 -> 0.79775281 | M7: =_xlfn.IFS(L7<80%,"A",L7<=95%,"B",L7>95%,"C") -> A
B8: qs коричневые | C8: ='Юнит 19-25.01'!AE7 -> 1636.0082 | D8: =C8/C$18 -> 0.085009092 | E8: =D8+E7 -> 1.1336087 | F8: =IF(AND(E8<=0),"C",IF(E8<=0.8,"A",IF(E8<=0.95,"B","C"))) -> C | G8: =VLOOKUP(B$4:B$17,I$4:M$17,5,0) -> A | I8: qs черные | J8: ='Юнит 19-25.01'!R4 -> 7 | K8: =J8/J$18 -> 0.078651685 | L8: =K8+L7 -> 0.87640449 | M8: =_xlfn.IFS(L8<80%,"A",L8<=95%,"B",L8>95%,"C") -> B
B9: th желт | C9: ='Юнит 19-25.01'!AE11 -> 2661.2441 | D9: =C9/C$18 -> 0.13828167 | E9: =D9+E8 -> 1.2718904 | F9: =IF(AND(E9<=0),"C",IF(E9<=0.8,"A",IF(E9<=0.95,"B","C"))) -> C | G9: =VLOOKUP(B$4:B$17,I$4:M$17,5,0) -> A | I9: черные с железкой классика | J9: ='Юнит 19-25.01'!R3 -> 5 | K9: =J9/J$18 -> 0.056179775 | L9: =K9+L8 -> 0.93258427 | M9: =_xlfn.IFS(L9<80%,"A",L9<=95%,"B",L9>95%,"C") -> B
B10: th черн | C10: ='Юнит 19-25.01'!AE9 -> 0 | D10: =C10/C$18 -> 0 | E10: =D10+E9 -> 1.2718904 | F10: =IF(AND(E10<=0),"C",IF(E10<=0.8,"A",IF(E10<=0.95,"B","C"))) -> C | G10: =VLOOKUP(B$4:B$17,I$4:M$17,5,0) -> A | I10: qs синие | J10: ='Юнит 19-25.01'!R5 -> 3 | K10: =J10/J$18 -> 0.033707865 | L10: =K10+L9 -> 0.96629213 | M10: =_xlfn.IFS(L10<80%,"A",L10<=95%,"B",L10>95%,"C") -> C
B11: th син | C11: ='Юнит 19-25.01'!AE10 -> 0 | D11: =C11/C$18 -> 0 | E11: =D11+E10 -> 1.2718904 | F11: =IF(AND(E11<=0),"C",IF(E11<=0.8,"A",IF(E11<=0.95,"B","C"))) -> C | G11: =VLOOKUP(B$4:B$17,I$4:M$17,5,0) -> A | I11: MR8854 C2 | J11: ='Юнит 19-25.01'!R8 -> 3 | K11: =J11/J$18 -> 0.033707865 | L11: =K11+L10 -> 1 | M11: =_xlfn.IFS(L11<80%,"A",L11<=95%,"B",L11>95%,"C") -> C
B12: th коричн | C12: ='Юнит 19-25.01'!AE12 -> 0 | D12: =C12/C$18 -> 0 | E12: =D12+E5 -> 0.78141315 | F12: =IF(AND(E12<=0),"C",IF(E12<=0.8,"A",IF(E12<=0.95,"B","C"))) -> A | G12: =VLOOKUP(B$4:B$17,I$4:M$17,5,0) -> A | I12: th черн | J12: ='Юнит 19-25.01'!R9 -> 0 | K12: =J12/J$18 -> 0 | L12: =K12+L5 -> 0.49438202 | M12: =_xlfn.IFS(L12<80%,"A",L12<=95%,"B",L12>95%,"C") -> A
B13: flip черный | C13: ='Юнит 19-25.01'!AE13 -> 0 | D13: =C13/C$18 -> 0 | E13: =D13+E12 -> 0.78141315 | F13: =IF(AND(E13<=0),"C",IF(E13<=0.8,"A",IF(E13<=0.95,"B","C"))) -> A | G13: =VLOOKUP(B$4:B$17,I$4:M$17,5,0) -> A | I13: th син | J13: ='Юнит 19-25.01'!R10 -> 0 | K13: =J13/J$18 -> 0 | L13: =K13+L12 -> 0.49438202 | M13: =_xlfn.IFS(L13<80%,"A",L13<=95%,"B",L13>95%,"C") -> A
B14: flip синий | C14: ='Юнит 19-25.01'!AE14 -> 0 | D14: =C14/C$18 -> 0 | E14: =D14+E13 -> 0.78141315 | F14: =IF(AND(E14<=0),"C",IF(E14<=0.8,"A",IF(E14<=0.95,"B","C"))) -> A | G14: =VLOOKUP(B$4:B$17,I$4:M$17,5,0) -> A | I14: th коричн | J14: ='Юнит 19-25.01'!R12 -> 0 | K14: =J14/J$18 -> 0 | L14: =K14+L13 -> 0.49438202 | M14: =_xlfn.IFS(L14<80%,"A",L14<=95%,"B",L14>95%,"C") -> A
B15: flip коричневый | C15: ='Юнит 19-25.01'!AE16 -> 0 | D15: =C15/C$18 -> 0 | E15: =D15+E14 -> 0.78141315 | F15: =IF(AND(E15<=0),"C",IF(E15<=0.8,"A",IF(E15<=0.95,"B","C"))) -> A | G15: =VLOOKUP(B$4:B$17,I$4:M$17,5,0) -> A | I15: flip черный | J15: ='Юнит 19-25.01'!R13 -> 0 | K15: =J15/J$18 -> 0 | L15: =K15+L14 -> 0.49438202 | M15: =_xlfn.IFS(L15<80%,"A",L15<=95%,"B",L15>95%,"C") -> A
B16: MR8854 C2 | C16: ='Юнит 19-25.01'!AE8 -> -789.58498 | D16: =C16/C$18 -> -0.041027852 | E16: =D16+E15 -> 0.7403853 | F16: =IF(AND(E16<=0),"C",IF(E16<=0.8,"A",IF(E16<=0.95,"B","C"))) -> A | G16: =VLOOKUP(B$4:B$17,I$4:M$17,5,0) -> C | I16: flip синий | J16: ='Юнит 19-25.01'!R14 -> 0 | K16: =J16/J$18 -> 0 | L16: =K16+L15 -> 0.49438202 | M16: =_xlfn.IFS(L16<80%,"A",L16<=95%,"B",L16>95%,"C") -> A
B17: flip жел | C17: ='Юнит 19-25.01'!AE15 -> -4442.9723 | D17: =C17/C$18 -> -0.23086256 | E17: =D17+E14 -> 0.55055059 | F17: =IF(AND(E17<=0),"C",IF(E17<=0.8,"A",IF(E17<=0.95,"B","C"))) -> A | G17: =VLOOKUP(B$4:B$17,I$4:M$17,5,0) -> A | I17: flip коричневый | J17: ='Юнит 19-25.01'!R16 -> 0 | K17: =J17/J$18 -> 0 | L17: =K17+L14 -> 0.49438202 | M17: =_xlfn.IFS(L17<80%,"A",L17<=95%,"B",L17>95%,"C") -> A
C18: =SUM(C4:C17) -> 19245.097 | D18: =SUM(D4:D17) -> 1 | J18: =SUM(J4:J17) -> 89 | K18: =SUM(K4:K17) -> 1
C21: Прибыль | D21: % прибыль | E21: Доля | F21: ABC прибыль | G21: ABC кол-во | J21: Кол-во | K21: % кол-во | L21: Доля | M21: ABC кол-во
D22: =C22/C$42 -> #DIV/0! | E22: =D22 -> #DIV/0! | F22: =IF(AND(E22<=0),"C",IF(E22<=0.8,"A",IF(E22<=0.95,"B","C"))) -> #DIV/0! | G22: =VLOOKUP(B$22:B$42,I$22:M$42,5,0) -> #N/A | K22: =J22/J$42 -> #DIV/0! | L22: =K22 -> #DIV/0! | M22: =_xlfn.IFS(L22<80%,"A",L22<=95%,"B",L22>95%,"C") -> #DIV/0!
D23: =C23/C$42 -> #DIV/0! | E23: =D23+E22 -> #DIV/0! | F23: =IF(AND(E23<=0),"C",IF(E23<=0.8,"A",IF(E23<=0.95,"B","C"))) -> #DIV/0! | G23: =VLOOKUP(B$22:B$42,I$22:M$42,5,0) -> #N/A | K23: =J23/J$42 -> #DIV/0! | L23: =K23+L22 -> #DIV/0! | M23: =_xlfn.IFS(L23<80%,"A",L23<=95%,"B",L23>95%,"C") -> #DIV/0!
D24: =C24/C$42 -> #DIV/0! | E24: =D24+E23 -> #DIV/0! | F24: =IF(AND(E24<=0),"C",IF(E24<=0.8,"A",IF(E24<=0.95,"B","C"))) -> #DIV/0! | G24: =VLOOKUP(B$22:B$42,I$22:M$42,5,0) -> #N/A | K24: =J24/J$42 -> #DIV/0! | L24: =K24+L23 -> #DIV/0! | M24: =_xlfn.IFS(L24<80%,"A",L24<=95%,"B",L24>95%,"C") -> #DIV/0!
D25: =C25/C$42 -> #DIV/0! | E25: =D25+E24 -> #DIV/0! | F25: =IF(AND(E25<=0),"C",IF(E25<=0.8,"A",IF(E25<=0.95,"B","C"))) -> #DIV/0! | G25: =VLOOKUP(B$22:B$42,I$22:M$42,5,0) -> #N/A | K25: =J25/J$42 -> #DIV/0! | L25: =K25+L24 -> #DIV/0! | M25: =_xlfn.IFS(L25<80%,"A",L25<=95%,"B",L25>95%,"C") -> #DIV/0!
D26: =C26/C$42 -> #DIV/0! | E26: =D26+E25 -> #DIV/0! | F26: =IF(AND(E26<=0),"C",IF(E26<=0.8,"A",IF(E26<=0.95,"B","C"))) -> #DIV/0! | G26: =VLOOKUP(B$22:B$42,I$22:M$42,5,0) -> #N/A | K26: =J26/J$42 -> #DIV/0! | L26: =K26+L25 -> #DIV/0! | M26: =_xlfn.IFS(L26<80%,"A",L26<=95%,"B",L26>95%,"C") -> #DIV/0!
D27: =C27/C$42 -> #DIV/0! | E27: =D27+E26 -> #DIV/0! | F27: =IF(AND(E27<=0),"C",IF(E27<=0.8,"A",IF(E27<=0.95,"B","C"))) -> #DIV/0! | G27: =VLOOKUP(B$22:B$42,I$22:M$42,5,0) -> #N/A | K27: =J27/J$42 -> #DIV/0! | L27: =K27+L26 -> #DIV/0! | M27: =_xlfn.IFS(L27<80%,"A",L27<=95%,"B",L27>95%,"C") -> #DIV/0!
D28: =C28/C$42 -> #DIV/0! | E28: =D28+E27 -> #DIV/0! | F28: =IF(AND(E28<=0),"C",IF(E28<=0.8,"A",IF(E28<=0.95,"B","C"))) -> #DIV/0! | G28: =VLOOKUP(B$22:B$42,I$22:M$42,5,0) -> #N/A | K28: =J28/J$42 -> #DIV/0! | L28: =K28+L27 -> #DIV/0! | M28: =_xlfn.IFS(L28<80%,"A",L28<=95%,"B",L28>95%,"C") -> #DIV/0!
D29: =C29/C$42 -> #DIV/0! | E29: =D29+E28 -> #DIV/0! | F29: =IF(AND(E29<=0),"C",IF(E29<=0.8,"A",IF(E29<=0.95,"B","C"))) -> #DIV/0! | G29: =VLOOKUP(B$22:B$42,I$22:M$42,5,0) -> #N/A | K29: =J29/J$42 -> #DIV/0! | L29: =K29+L28 -> #DIV/0! | M29: =_xlfn.IFS(L29<80%,"A",L29<=95%,"B",L29>95%,"C") -> #DIV/0!
D30: =C30/C$42 -> #DIV/0! | E30: =D30+E29 -> #DIV/0! | F30: =IF(AND(E30<=0),"C",IF(E30<=0.8,"A",IF(E30<=0.95,"B","C"))) -> #DIV/0! | G30: =VLOOKUP(B$22:B$42,I$22:M$42,5,0) -> #N/A | K30: =J30/J$42 -> #DIV/0! | L30: =K30+L29 -> #DIV/0! | M30: =_xlfn.IFS(L30<80%,"A",L30<=95%,"B",L30>95%,"C") -> #DIV/0!
D31: =C31/C$42 -> #DIV/0! | E31: =D31+E30 -> #DIV/0! | F31: =IF(AND(E31<=0),"C",IF(E31<=0.8,"A",IF(E31<=0.95,"B","C"))) -> #DIV/0! | G31: =VLOOKUP(B$22:B$42,I$22:M$42,5,0) -> #N/A | K31: =J31/J$42 -> #DIV/0! | L31: =K31+L30 -> #DIV/0! | M31: =_xlfn.IFS(L31<80%,"A",L31<=95%,"B",L31>95%,"C") -> #DIV/0!
D32: =C32/C$42 -> #DIV/0! | E32: =D32+E31 -> #DIV/0! | F32: =IF(AND(E32<=0),"C",IF(E32<=0.8,"A",IF(E32<=0.95,"B","C"))) -> #DIV/0! | G32: =VLOOKUP(B$22:B$42,I$22:M$42,5,0) -> #N/A | K32: =J32/J$42 -> #DIV/0! | L32: =K32+L31 -> #DIV/0! | M32: =_xlfn.IFS(L32<80%,"A",L32<=95%,"B",L32>95%,"C") -> #DIV/0!
D33: =C33/C$42 -> #DIV/0! | E33: =D33+E32 -> #DIV/0! | F33: =IF(AND(E33<=0),"C",IF(E33<=0.8,"A",IF(E33<=0.95,"B","C"))) -> #DIV/0! | G33: =VLOOKUP(B$22:B$42,I$22:M$42,5,0) -> #N/A | K33: =J33/J$42 -> #DIV/0! | L33: =K33+L32 -> #DIV/0! | M33: =_xlfn.IFS(L33<80%,"A",L33<=95%,"B",L33>95%,"C") -> #DIV/0!
D34: =C34/C$42 -> #DIV/0! | E34: =D34+E33 -> #DIV/0! | F34: =IF(AND(E34<=0),"C",IF(E34<=0.8,"A",IF(E34<=0.95,"B","C"))) -> #DIV/0! | G34: =VLOOKUP(B$22:B$42,I$22:M$42,5,0) -> #N/A | K34: =J34/J$42 -> #DIV/0! | L34: =K34+L33 -> #DIV/0! | M34: =_xlfn.IFS(L34<80%,"A",L34<=95%,"B",L34>95%,"C") -> #DIV/0!
... D41: =C41/C$42 -> #DIV/0! | E41: =D41+E40 -> #DIV/0! | F41: =IF(AND(E41<=0),"C",IF(E41<=0.8,"A",IF(E41<=0.95,"B","C"))) -> #DIV/0! | G41: =VLOOKUP(B$22:B$42,I$22:M$42,5,0) -> #N/A | K41: =J41/J$42 -> #DIV/0! | L41: =K41+L40 -> #DIV/0! | M41: =_xlfn.IFS(L41<80%,"A",L41<=95%,"B",L41>95%,"C") -> #DIV/0!
C42: =SUM(C22:C41) -> 0 | D42: =SUM(D22:D41) -> #DIV/0! | J42: =SUM(J22:J41) -> 0 | K42: =SUM(K22:K41) -> #DIV/0!

Sheet АВС 12-18.01
B2: ОЧКИ
C3: Прибыль | D3: % прибыль | E3: Доля | F3: ABC прибыль | G3: ABC кол-во | J3: Кол-во | K3: % кол-во | L3: Доля | M3: ABC кол-во
B4: flip жел | C4: ='Юнит 12-18.01'!AE15 -> 7845.5265 | D4: =C4/C$18 -> 0.31497995 | E4: =D4 -> 0.31497995 | F4: =IF(AND(E4<=0),"C",IF(E4<=0.8,"A",IF(E4<=0.95,"B","C"))) -> A | G4: =VLOOKUP(B$4:B$17,I$4:M$17,5,0) -> A | I4: flip жел | J4: ='Юнит 12-18.01'!R15 -> 37 | K4: =J4/J$18 -> 0.30833333 | L4: =K4 -> 0.30833333 | M4: =_xlfn.IFS(L4<80%,"A",L4<=95%,"B",L4>95%,"C") -> A
B5: qs желтые | C5: ='Юнит 12-18.01'!AE6 -> 4986.2704 | D5: =C5/C$18 -> 0.20018736 | E5: =D5+E4 -> 0.51516731 | F5: =IF(AND(E5<=0),"C",IF(E5<=0.8,"A",IF(E5<=0.95,"B","C"))) -> A | G5: =VLOOKUP(B$4:B$17,I$4:M$17,5,0) -> A | I5: th желт | J5: ='Юнит 12-18.01'!R11 -> 35 | K5: =J5/J$18 -> 0.29166667 | L5: =K5+L4 -> 0.6 | M5: =_xlfn.IFS(L5<80%,"A",L5<=95%,"B",L5>95%,"C") -> A
B6: qs коричневые | C6: ='Юнит 12-18.01'!AE7 -> 3808.3998 | D6: =C6/C$18 -> 0.15289854 | E6: =D6+E5 -> 0.66806585 | F6: =IF(AND(E6<=0),"C",IF(E6<=0.8,"A",IF(E6<=0.95,"B","C"))) -> A | G6: =VLOOKUP(B$4:B$17,I$4:M$17,5,0) -> B | I6: qs желтые | J6: ='Юнит 12-18.01'!R6 -> 20 | K6: =J6/J$18 -> 0.16666667 | L6: =K6+L5 -> 0.76666667 | M6: =_xlfn.IFS(L6<80%,"A",L6<=95%,"B",L6>95%,"C") -> A
B7: qs синие | C7: ='Юнит 12-18.01'!AE5 -> 2085.4874 | D7: =C7/C$18 -> 0.083727551 | E7: =D7+E6 -> 0.7517934 | F7: =IF(AND(E7<=0),"C",IF(E7<=0.8,"A",IF(E7<=0.95,"B","C"))) -> A | G7: =VLOOKUP(B$4:B$17,I$4:M$17,5,0) -> C | I7: qs коричневые | J7: ='Юнит 12-18.01'!R7 -> 10 | K7: =J7/J$18 -> 0.083333333 | L7: =K7+L6 -> 0.85 | M7: =_xlfn.IFS(L7<80%,"A",L7<=95%,"B",L7>95%,"C") -> B
B8: черные с железкой классика | C8: ='Юнит 12-18.01'!AE3 -> 1162.1223 | D8: =C8/C$18 -> 0.046656555 | E8: =D8+E7 -> 0.79844996 | F8: =IF(AND(E8<=0),"C",IF(E8<=0.8,"A",IF(E8<=0.95,"B","C"))) -> A | G8: =VLOOKUP(B$4:B$17,I$4:M$17,5,0) -> C | I8: MR8854 C2 | J8: ='Юнит 12-18.01'!R8 -> 7 | K8: =J8/J$18 -> 0.058333333 | L8: =K8+L7 -> 0.90833333 | M8: =_xlfn.IFS(L8<80%,"A",L8<=95%,"B",L8>95%,"C") -> B
B9: th желт | C9: ='Юнит 12-18.01'!AE11 -> 3663.4074 | D9: =C9/C$18 -> 0.14707743 | E9: =D9+E8 -> 0.94552739 | F9: =IF(AND(E9<=0),"C",IF(E9<=0.8,"A",IF(E9<=0.95,"B","C"))) -> B | G9: =VLOOKUP(B$4:B$17,I$4:M$17,5,0) -> A | I9: qs черные | J9: ='Юнит 12-18.01'!R4 -> 4 | K9: =J9/J$18 -> 0.033333333 | L9: =K9+L8 -> 0.94166667 | M9: =_xlfn.IFS(L9<80%,"A",L9<=95%,"B",L9>95%,"C") -> B
B10: qs черные | C10: ='Юнит 12-18.01'!AE4 -> 745.60927 | D10: =C10/C$18 -> 0.029934507 | E10: =D10+E9 -> 0.9754619 | F10: =IF(AND(E10<=0),"C",IF(E10<=0.8,"A",IF(E10<=0.95,"B","C"))) -> C | G10: =VLOOKUP(B$4:B$17,I$4:M$17,5,0) -> B | I10: qs синие | J10: ='Юнит 12-18.01'!R5 -> 4 | K10: =J10/J$18 -> 0.033333333 | L10: =K10+L9 -> 0.975 | M10: =_xlfn.IFS(L10<80%,"A",L10<=95%,"B",L10>95%,"C") -> C
B11: MR8854 C2 | C11: ='Юнит 12-18.01'!AE8 -> 611.19557 | D11: =C11/C$18 -> 0.024538105 | E11: =D11+E10 -> 1 | F11: =IF(AND(E11<=0),"C",IF(E11<=0.8,"A",IF(E11<=0.95,"B","C"))) -> C | G11: =VLOOKUP(B$4:B$17,I$4:M$17,5,0) -> B | I11: черные с железкой классика | J11: ='Юнит 12-18.01'!R3 -> 3 | K11: =J11/J$18 -> 0.025 | L11: =K11+L10 -> 1 | M11: =_xlfn.IFS(L11<80%,"A",L11<=95%,"B",L11>95%,"C") -> C
B12: th черн | C12: ='Юнит 12-18.01'!AE9 -> 0 | D12: =C12/C$18 -> 0 | E12: =D12+E5 -> 0.51516731 | F12: =IF(AND(E12<=0),"C",IF(E12<=0.8,"A",IF(E12<=0.95,"B","C"))) -> A | G12: =VLOOKUP(B$4:B$17,I$4:M$17,5,0) -> A | I12: th черн | J12: ='Юнит 12-18.01'!R9 -> 0 | K12: =J12/J$18 -> 0 | L12: =K12+L5 -> 0.6 | M12: =_xlfn.IFS(L12<80%,"A",L12<=95%,"B",L12>95%,"C") -> A
B13: th син | C13: ='Юнит 12-18.01'!AE10 -> 0 | D13: =C13/C$18 -> 0 | E13: =D13+E12 -> 0.51516731 | F13: =IF(AND(E13<=0),"C",IF(E13<=0.8,"A",IF(E13<=0.95,"B","C"))) -> A | G13: =VLOOKUP(B$4:B$17,I$4:M$17,5,0) -> A | I13: th син | J13: ='Юнит 12-18.01'!R10 -> 0 | K13: =J13/J$18 -> 0 | L13: =K13+L12 -> 0.6 | M13: =_xlfn.IFS(L13<80%,"A",L13<=95%,"B",L13>95%,"C") -> A
B14: th коричн | C14: ='Юнит 12-18.01'!AE12 -> 0 | D14: =C14/C$18 -> 0 | E14: =D14+E13 -> 0.51516731 | F14: =IF(AND(E14<=0),"C",IF(E14<=0.8,"A",IF(E14<=0.95,"B","C"))) -> A | G14: =VLOOKUP(B$4:B$17,I$4:M$17,5,0) -> A | I14: th коричн | J14: ='Юнит 12-18.01'!R12 -> 0 | K14: =J14/J$18 -> 0 | L14: =K14+L13 -> 0.6 | M14: =_xlfn.IFS(L14<80%,"A",L14<=95%,"B",L14>95%,"C") -> A
B15: flip черный | C15: ='Юнит 12-18.01'!AE13 -> 0 | D15: =C15/C$18 -> 0 | E15: =D15+E14 -> 0.51516731 | F15: =IF(AND(E15<=0),"C",IF(E15<=0.8,"A",IF(E15<=0.95,"B","C"))) -> A | G15: =VLOOKUP(B$4:B$17,I$4:M$17,5,0) -> A | I15: flip черный | J15: ='Юнит 12-18.01'!R13 -> 0 | K15: =J15/J$18 -> 0 | L15: =K15+L14 -> 0.6 | M15: =_xlfn.IFS(L15<80%,"A",L15<=95%,"B",L15>95%,"C") -> A
B16: flip синий | C16: ='Юнит 12-18.01'!AE14 -> 0 | D16: =C16/C$18 -> 0 | E16: =D16+E15 -> 0.51516731 | F16: =IF(AND(E16<=0),"C",IF(E16<=0.8,"A",IF(E16<=0.95,"B","C"))) -> A | G16: =VLOOKUP(B$4:B$17,I$4:M$17,5,0) -> A | I16: flip синий | J16: ='Юнит 12-18.01'!R14 -> 0 | K16: =J16/J$18 -> 0 | L16: =K16+L15 -> 0.6 | M16: =_xlfn.IFS(L16<80%,"A",L16<=95%,"B",L16>95%,"C") -> A
B17: flip коричневый | C17: ='Юнит 12-18.01'!AE16 -> 0 | D17: =C17/C$18 -> 0 | E17: =D17+E14 -> 0.51516731 | F17: =IF(AND(E17<=0),"C",IF(E17<=0.8,"A",IF(E17<=0.95,"B","C"))) -> A | G17: =VLOOKUP(B$4:B$17,I$4:M$17,5,0) -> A | I17: flip коричневый | J17: ='Юнит 12-18.01'!R16 -> 0 | K17: =J17/J$18 -> 0 | L17: =K17+L14 -> 0.6 | M17: =_xlfn.IFS(L17<80%,"A",L17<=95%,"B",L17>95%,"C") -> A
C18: =SUM(C4:C17) -> 24908.019 | D18: =SUM(D4:D17) -> 1 | J18: =SUM(J4:J17) -> 120 | K18: =SUM(K4:K17) -> 1
C21: Прибыль | D21: % прибыль | E21: Доля | F21: ABC прибыль | G21: ABC кол-во | J21: Кол-во | K21: % кол-во | L21: Доля | M21: ABC кол-во
D22: =C22/C$42 -> #DIV/0! | E22: =D22 -> #DIV/0! | F22: =IF(AND(E22<=0),"C",IF(E22<=0.8,"A",IF(E22<=0.95,"B","C"))) -> #DIV/0! | G22: =VLOOKUP(B$22:B$42,I$22:M$42,5,0) -> #N/A | K22: =J22/J$42 -> #DIV/0! | L22: =K22 -> #DIV/0! | M22: =_xlfn.IFS(L22<80%,"A",L22<=95%,"B",L22>95%,"C") -> #DIV/0!
D23: =C23/C$42 -> #DIV/0! | E23: =D23+E22 -> #DIV/0! | F23: =IF(AND(E23<=0),"C",IF(E23<=0.8,"A",IF(E23<=0.95,"B","C"))) -> #DIV/0! | G23: =VLOOKUP(B$22:B$42,I$22:M$42,5,0) -> #N/A | K23: =J23/J$42 -> #DIV/0! | L23: =K23+L22 -> #DIV/0! | M23: =_xlfn.IFS(L23<80%,"A",L23<=95%,"B",L23>95%,"C") -> #DIV/0!
D24: =C24/C$42 -> #DIV/0! | E24: =D24+E23 -> #DIV/0! | F24: =IF(AND(E24<=0),"C",IF(E24<=0.8,"A",IF(E24<=0.95,"B","C"))) -> #DIV/0! | G24: =VLOOKUP(B$22:B$42,I$22:M$42,5,0) -> #N/A | K24: =J24/J$42 -> #DIV/0! | L24: =K24+L23 -> #DIV/0! | M24: =_xlfn.IFS(L24<80%,"A",L24<=95%,"B",L24>95%,"C") -> #DIV/0!
D25: =C25/C$42 -> #DIV/0! | E25: =D25+E24 -> #DIV/0! | F25: =IF(AND(E25<=0),"C",IF(E25<=0.8,"A",IF(E25<=0.95,"B","C"))) -> #DIV/0! | G25: =VLOOKUP(B$22:B$42,I$22:M$42,5,0) -> #N/A | K25: =J25/J$42 -> #DIV/0! | L25: =K25+L24 -> #DIV/0! | M25: =_xlfn.IFS(L25<80%,"A",L25<=95%,"B",L25>95%,"C") -> #DIV/0!
D26: =C26/C$42 -> #DIV/0! | E26: =D26+E25 -> #DIV/0! | F26: =IF(AND(E26<=0),"C",IF(E26<=0.8,"A",IF(E26<=0.95,"B","C"))) -> #DIV/0! | G26: =VLOOKUP(B$22:B$42,I$22:M$42,5,0) -> #N/A | K26: =J26/J$42 -> #DIV/0! | L26: =K26+L25 -> #DIV/0! | M26: =_xlfn.IFS(L26<80%,"A",L26<=95%,"B",L26>95%,"C") -> #DIV/0!
D27: =C27/C$42 -> #DIV/0! | E27: =D27+E26 -> #DIV/0! | F27: =IF(AND(E27<=0),"C",IF(E27<=0.8,"A",IF(E27<=0.95,"B","C"))) -> #DIV/0! | G27: =VLOOKUP(B$22:B$42,I$22:M$42,5,0) -> #N/A | K27: =J27/J$42 -> #DIV/0! | L27: =K27+L26 -> #DIV/0! | M27: =_xlfn.IFS(L27<80%,"A",L27<=95%,"B",L27>95%,"C") -> #DIV/0!
D28: =C28/C$42 -> #DIV/0! | E28: =D28+E27 -> #DIV/0! | F28: =IF(AND(E28<=0),"C",IF(E28<=0.8,"A",IF(E28<=0.95,"B","C"))) -> #DIV/0! | G28: =VLOOKUP(B$22:B$42,I$22:M$42,5,0) -> #N/A | K28: =J28/J$42 -> #DIV/0! | L28: =K28+L27 -> #DIV/0! | M28: =_xlfn.IFS(L28<80%,"A",L28<=95%,"B",L28>95%,"C") -> #DIV/0!
D29: =C29/C$42 -> #DIV/0! | E29: =D29+E28 -> #DIV/0! | F29: =IF(AND(E29<=0),"C",IF(E29<=0.8,"A",IF(E29<=0.95,"B","C"))) -> #DIV/0! | G29: =VLOOKUP(B$22:B$42,I$22:M$42,5,0) -> #N/A | K29: =J29/J$42 -> #DIV/0! | L29: =K29+L28 -> #DIV/0! | M29: =_xlfn.IFS(L29<80%,"A",L29<=95%,"B",L29>95%,"C") -> #DIV/0!
D30: =C30/C$42 -> #DIV/0! | E30: =D30+E29 -> #DIV/0! | F30: =IF(AND(E30<=0),"C",IF(E30<=0.8,"A",IF(E30<=0.95,"B","C"))) -> #DIV/0! | G30: =VLOOKUP(B$22:B$42,I$22:M$42,5,0) -> #N/A | K30: =J30/J$42 -> #DIV/0! | L30: =K30+L29 -> #DIV/0! | M30: =_xlfn.IFS(L30<80%,"A",L30<=95%,"B",L30>95%,"C") -> #DIV/0!
D31: =C31/C$42 -> #DIV/0! | E31: =D31+E30 -> #DIV/0! | F31: =IF(AND(E31<=0),"C",IF(E31<=0.8,"A",IF(E31<=0.95,"B","C"))) -> #DIV/0! | G31: =VLOOKUP(B$22:B$42,I$22:M$42,5,0) -> #N/A | K31: =J31/J$42 -> #DIV/0! | L31: =K31+L30 -> #DIV/0! | M31: =_xlfn.IFS(L31<80%,"A",L31<=95%,"B",L31>95%,"C") -> #DIV/0!
D32: =C32/C$42 -> #DIV/0! | E32: =D32+E31 -> #DIV/0! | F32: =IF(AND(E32<=0),"C",IF(E32<=0.8,"A",IF(E32<=0.95,"B","C"))) -> #DIV/0! | G32: =VLOOKUP(B$22:B$42,I$22:M$42,5,0) -> #N/A | K32: =J32/J$42 -> #DIV/0! | L32: =K32+L31 -> #DIV/0! | M32: =_xlfn.IFS(L32<80%,"A",L32<=95%,"B",L32>95%,"C") -> #DIV/0!
D33: =C33/C$42 -> #DIV/0! | E33: =D33+E32 -> #DIV/0! | F33: =IF(AND(E33<=0),"C",IF(E33<=0.8,"A",IF(E33<=0.95,"B","C"))) -> #DIV/0! | G33: =VLOOKUP(B$22:B$42,I$22:M$42,5,0) -> #N/A | K33: =J33/J$42 -> #DIV/0! | L33: =K33+L32 -> #DIV/0! | M33: =_xlfn.IFS(L33<80%,"A",L33<=95%,"B",L33>95%,"C") -> #DIV/0!
D34: =C34/C$42 -> #DIV/0! | E34: =D34+E33 -> #DIV/0! | F34: =IF(AND(E34<=0),"C",IF(E34<=0.8,"A",IF(E34<=0.95,"B","C"))) -> #DIV/0! | G34: =VLOOKUP(B$22:B$42,I$22:M$42,5,0) -> #N/A | K34: =J34/J$42 -> #DIV/0! | L34: =K34+L33 -> #DIV/0! | M34: =_xlfn.IFS(L34<80%,"A",L34<=95%,"B",L34>95%,"C") -> #DIV/0!
... D41: =C41/C$42 -> #DIV/0! | E41: =D41+E40 -> #DIV/0! | F41: =IF(AND(E41<=0),"C",IF(E41<=0.8,"A",IF(E41<=0.95,"B","C"))) -> #DIV/0! | G41: =VLOOKUP(B$22:B$42,I$22:M$42,5,0) -> #N/A | K41: =J41/J$42 -> #DIV/0! | L41: =K41+L40 -> #DIV/0! | M41: =_xlfn.IFS(L41<80%,"A",L41<=95%,"B",L41>95%,"C") -> #DIV/0!
C42: =SUM(C22:C41) -> 0 | D42: =SUM(D22:D41) -> #DIV/0! | J42: =SUM(J22:J41) -> 0 | K42: =SUM(K22:K41) -> #DIV/0!

Sheet АВС 05-11.01
B2: ОЧКИ
C3: Прибыль | D3: % прибыль | E3: Доля | F3: ABC прибыль | G3: ABC кол-во | J3: Кол-во | K3: % кол-во | L3: Доля | M3: ABC кол-во
B4: th желт | C4: ='Юнит 05-11.01'!AE11 -> 14577.679 | D4: =C4/C$18 -> 0.32994497 | E4: =D4 -> 0.32994497 | F4: =IF(AND(E4<=0),"C",IF(E4<=0.8,"A",IF(E4<=0.95,"B","C"))) -> A | G4: =VLOOKUP(B$4:B$17,I$4:M$17,5,0) -> A | I4: th желт | J4: ='Юнит 05-11.01'!R11 -> 52 | K4: =J4/J$18 -> 0.325 | L4: =K4 -> 0.325 | M4: =_xlfn.IFS(L4<80%,"A",L4<=95%,"B",L4>95%,"C") -> A
B5: flip жел | C5: ='Юнит 05-11.01'!AE15 -> 13681.243 | D5: =C5/C$18 -> 0.3096554 | E5: =D5+E4 -> 0.63960037 | F5: =IF(AND(E5<=0),"C",IF(E5<=0.8,"A",IF(E5<=0.95,"B","C"))) -> A | G5: =VLOOKUP(B$4:B$17,I$4:M$17,5,0) -> A | I5: flip жел | J5: ='Юнит 05-11.01'!R15 -> 49 | K5: =J5/J$18 -> 0.30625 | L5: =K5+L4 -> 0.63125 | M5: =_xlfn.IFS(L5<80%,"A",L5<=95%,"B",L5>95%,"C") -> A
B6: qs желтые | C6: ='Юнит 05-11.01'!AE6 -> 6919.0166 | D6: =C6/C$18 -> 0.15660207 | E6: =D6+E5 -> 0.79620244 | F6: =IF(AND(E6<=0),"C",IF(E6<=0.8,"A",IF(E6<=0.95,"B","C"))) -> A | G6: =VLOOKUP(B$4:B$17,I$4:M$17,5,0) -> B | I6: qs желтые | J6: ='Юнит 05-11.01'!R6 -> 31 | K6: =J6/J$18 -> 0.19375 | L6: =K6+L5 -> 0.825 | M6: =_xlfn.IFS(L6<80%,"A",L6<=95%,"B",L6>95%,"C") -> B
B7: qs коричневые | C7: ='Юнит 05-11.01'!AE7 -> 2667.2832 | D7: =C7/C$18 -> 0.060370149 | E7: =D7+E6 -> 0.85657259 | F7: =IF(AND(E7<=0),"C",IF(E7<=0.8,"A",IF(E7<=0.95,"B","C"))) -> B | G7: =VLOOKUP(B$4:B$17,I$4:M$17,5,0) -> B | I7: MR8854 C2 | J7: ='Юнит 05-11.01'!R8 -> 10 | K7: =J7/J$18 -> 0.0625 | L7: =K7+L6 -> 0.8875 | M7: =_xlfn.IFS(L7<80%,"A",L7<=95%,"B",L7>95%,"C") -> B
B8: MR8854 C2 | C8: ='Юнит 05-11.01'!AE8 -> 2517.3576 | D8: =C8/C$18 -> 0.056976798 | E8: =D8+E7 -> 0.91354939 | F8: =IF(AND(E8<=0),"C",IF(E8<=0.8,"A",IF(E8<=0.95,"B","C"))) -> B | G8: =VLOOKUP(B$4:B$17,I$4:M$17,5,0) -> B | I8: qs коричневые | J8: ='Юнит 05-11.01'!R7 -> 8 | K8: =J8/J$18 -> 0.05 | L8: =K8+L7 -> 0.9375 | M8: =_xlfn.IFS(L8<80%,"A",L8<=95%,"B",L8>95%,"C") -> B
B9: черные с железкой классика | C9: ='Юнит 05-11.01'!AE3 -> 1842.5976 | D9: =C9/C$18 -> 0.041704567 | E9: =D9+E8 -> 0.95525396 | F9: =IF(AND(E9<=0),"C",IF(E9<=0.8,"A",IF(E9<=0.95,"B","C"))) -> C | G9: =VLOOKUP(B$4:B$17,I$4:M$17,5,0) -> C | I9: черные с железкой классика | J9: ='Юнит 05-11.01'!R3 -> 5 | K9: =J9/J$18 -> 0.03125 | L9: =K9+L8 -> 0.96875 | M9: =_xlfn.IFS(L9<80%,"A",L9<=95%,"B",L9>95%,"C") -> C
B10: qs черные | C10: ='Юнит 05-11.01'!AE4 -> 1521.1407 | D10: =C10/C$18 -> 0.034428849 | E10: =D10+E9 -> 0.98968281 | F10: =IF(AND(E10<=0),"C",IF(E10<=0.8,"A",IF(E10<=0.95,"B","C"))) -> C | G10: =VLOOKUP(B$4:B$17,I$4:M$17,5,0) -> C | I10: qs черные | J10: ='Юнит 05-11.01'!R4 -> 3 | K10: =J10/J$18 -> 0.01875 | L10: =K10+L9 -> 0.9875 | M10: =_xlfn.IFS(L10<80%,"A",L10<=95%,"B",L10>95%,"C") -> C
B11: qs синие | C11: ='Юнит 05-11.01'!AE5 -> 455.83588 | D11: =C11/C$18 -> 0.010317195 | E11: =D11+E10 -> 1 | F11: =IF(AND(E11<=0),"C",IF(E11<=0.8,"A",IF(E11<=0.95,"B","C"))) -> C | G11: =VLOOKUP(B$4:B$17,I$4:M$17,5,0) -> C | I11: qs синие | J11: ='Юнит 05-11.01'!R5 -> 2 | K11: =J11/J$18 -> 0.0125 | L11: =K11+L10 -> 1 | M11: =_xlfn.IFS(L11<80%,"A",L11<=95%,"B",L11>95%,"C") -> C
B12: th черн | C12: ='Юнит 05-11.01'!AE9 -> 0 | D12: =C12/C$18 -> 0 | E12: =D12+E5 -> 0.63960037 | F12: =IF(AND(E12<=0),"C",IF(E12<=0.8,"A",IF(E12<=0.95,"B","C"))) -> A | G12: =VLOOKUP(B$4:B$17,I$4:M$17,5,0) -> A | I12: th черн | J12: ='Юнит 05-11.01'!R9 -> 0 | K12: =J12/J$18 -> 0 | L12: =K12+L5 -> 0.63125 | M12: =_xlfn.IFS(L12<80%,"A",L12<=95%,"B",L12>95%,"C") -> A
B13: th син | C13: ='Юнит 05-11.01'!AE10 -> 0 | D13: =C13/C$18 -> 0 | E13: =D13+E12 -> 0.63960037 | F13: =IF(AND(E13<=0),"C",IF(E13<=0.8,"A",IF(E13<=0.95,"B","C"))) -> A | G13: =VLOOKUP(B$4:B$17,I$4:M$17,5,0) -> A | I13: th син | J13: ='Юнит 05-11.01'!R10 -> 0 | K13: =J13/J$18 -> 0 | L13: =K13+L12 -> 0.63125 | M13: =_xlfn.IFS(L13<80%,"A",L13<=95%,"B",L13>95%,"C") -> A
B14: th коричн | C14: ='Юнит 05-11.01'!AE12 -> 0 | D14: =C14/C$18 -> 0 | E14: =D14+E13 -> 0.63960037 | F14: =IF(AND(E14<=0),"C",IF(E14<=0.8,"A",IF(E14<=0.95,"B","C"))) -> A | G14: =VLOOKUP(B$4:B$17,I$4:M$17,5,0) -> A | I14: th коричн | J14: ='Юнит 05-11.01'!R12 -> 0 | K14: =J14/J$18 -> 0 | L14: =K14+L13 -> 0.63125 | M14: =_xlfn.IFS(L14<80%,"A",L14<=95%,"B",L14>95%,"C") -> A
B15: flip черный | C15: ='Юнит 05-11.01'!AE13 -> 0 | D15: =C15/C$18 -> 0 | E15: =D15+E14 -> 0.63960037 | F15: =IF(AND(E15<=0),"C",IF(E15<=0.8,"A",IF(E15<=0.95,"B","C"))) -> A | G15: =VLOOKUP(B$4:B$17,I$4:M$17,5,0) -> A | I15: flip черный | J15: ='Юнит 05-11.01'!R13 -> 0 | K15: =J15/J$18 -> 0 | L15: =K15+L14 -> 0.63125 | M15: =_xlfn.IFS(L15<80%,"A",L15<=95%,"B",L15>95%,"C") -> A
B16: flip синий | C16: ='Юнит 05-11.01'!AE14 -> 0 | D16: =C16/C$18 -> 0 | E16: =D16+E15 -> 0.63960037 | F16: =IF(AND(E16<=0),"C",IF(E16<=0.8,"A",IF(E16<=0.95,"B","C"))) -> A | G16: =VLOOKUP(B$4:B$17,I$4:M$17,5,0) -> A | I16: flip синий | J16: ='Юнит 05-11.01'!R14 -> 0 | K16: =J16/J$18 -> 0 | L16: =K16+L15 -> 0.63125 | M16: =_xlfn.IFS(L16<80%,"A",L16<=95%,"B",L16>95%,"C") -> A
B17: flip коричневый | C17: ='Юнит 05-11.01'!AE16 -> 0 | D17: =C17/C$18 -> 0 | E17: =D17+E14 -> 0.63960037 | F17: =IF(AND(E17<=0),"C",IF(E17<=0.8,"A",IF(E17<=0.95,"B","C"))) -> A | G17: =VLOOKUP(B$4:B$17,I$4:M$17,5,0) -> A | I17: flip коричневый | J17: ='Юнит 05-11.01'!R16 -> 0 | K17: =J17/J$18 -> 0 | L17: =K17+L14 -> 0.63125 | M17: =_xlfn.IFS(L17<80%,"A",L17<=95%,"B",L17>95%,"C") -> A
C18: =SUM(C4:C17) -> 44182.154 | D18: =SUM(D4:D17) -> 1 | J18: =SUM(J4:J17) -> 160 | K18: =SUM(K4:K17) -> 1
C21: Прибыль | D21: % прибыль | E21: Доля | F21: ABC прибыль | G21: ABC кол-во | J21: Кол-во | K21: % кол-во | L21: Доля | M21: ABC кол-во
D22: =C22/C$42 -> #DIV/0! | E22: =D22 -> #DIV/0! | F22: =IF(AND(E22<=0),"C",IF(E22<=0.8,"A",IF(E22<=0.95,"B","C"))) -> #DIV/0! | G22: =VLOOKUP(B$22:B$42,I$22:M$42,5,0) -> #N/A | K22: =J22/J$42 -> #DIV/0! | L22: =K22 -> #DIV/0! | M22: =_xlfn.IFS(L22<80%,"A",L22<=95%,"B",L22>95%,"C") -> #DIV/0!
D23: =C23/C$42 -> #DIV/0! | E23: =D23+E22 -> #DIV/0! | F23: =IF(AND(E23<=0),"C",IF(E23<=0.8,"A",IF(E23<=0.95,"B","C"))) -> #DIV/0! | G23: =VLOOKUP(B$22:B$42,I$22:M$42,5,0) -> #N/A | K23: =J23/J$42 -> #DIV/0! | L23: =K23+L22 -> #DIV/0! | M23: =_xlfn.IFS(L23<80%,"A",L23<=95%,"B",L23>95%,"C") -> #DIV/0!
D24: =C24/C$42 -> #DIV/0! | E24: =D24+E23 -> #DIV/0! | F24: =IF(AND(E24<=0),"C",IF(E24<=0.8,"A",IF(E24<=0.95,"B","C"))) -> #DIV/0! | G24: =VLOOKUP(B$22:B$42,I$22:M$42,5,0) -> #N/A | K24: =J24/J$42 -> #DIV/0! | L24: =K24+L23 -> #DIV/0! | M24: =_xlfn.IFS(L24<80%,"A",L24<=95%,"B",L24>95%,"C") -> #DIV/0!
D25: =C25/C$42 -> #DIV/0! | E25: =D25+E24 -> #DIV/0! | F25: =IF(AND(E25<=0),"C",IF(E25<=0.8,"A",IF(E25<=0.95,"B","C"))) -> #DIV/0! | G25: =VLOOKUP(B$22:B$42,I$22:M$42,5,0) -> #N/A | K25: =J25/J$42 -> #DIV/0! | L25: =K25+L24 -> #DIV/0! | M25: =_xlfn.IFS(L25<80%,"A",L25<=95%,"B",L25>95%,"C") -> #DIV/0!
D26: =C26/C$42 -> #DIV/0! | E26: =D26+E25 -> #DIV/0! | F26: =IF(AND(E26<=0),"C",IF(E26<=0.8,"A",IF(E26<=0.95,"B","C"))) -> #DIV/0! | G26: =VLOOKUP(B$22:B$42,I$22:M$42,5,0) -> #N/A | K26: =J26/J$42 -> #DIV/0! | L26: =K26+L25 -> #DIV/0! | M26: =_xlfn.IFS(L26<80%,"A",L26<=95%,"B",L26>95%,"C") -> #DIV/0!
D27: =C27/C$42 -> #DIV/0! | E27: =D27+E26 -> #DIV/0! | F27: =IF(AND(E27<=0),"C",IF(E27<=0.8,"A",IF(E27<=0.95,"B","C"))) -> #DIV/0! | G27: =VLOOKUP(B$22:B$42,I$22:M$42,5,0) -> #N/A | K27: =J27/J$42 -> #DIV/0! | L27: =K27+L26 -> #DIV/0! | M27: =_xlfn.IFS(L27<80%,"A",L27<=95%,"B",L27>95%,"C") -> #DIV/0!
D28: =C28/C$42 -> #DIV/0! | E28: =D28+E27 -> #DIV/0! | F28: =IF(AND(E28<=0),"C",IF(E28<=0.8,"A",IF(E28<=0.95,"B","C"))) -> #DIV/0! | G28: =VLOOKUP(B$22:B$42,I$22:M$42,5,0) -> #N/A | K28: =J28/J$42 -> #DIV/0! | L28: =K28+L27 -> #DIV/0! | M28: =_xlfn.IFS(L28<80%,"A",L28<=95%,"B",L28>95%,"C") -> #DIV/0!
D29: =C29/C$42 -> #DIV/0! | E29: =D29+E28 -> #DIV/0! | F29: =IF(AND(E29<=0),"C",IF(E29<=0.8,"A",IF(E29<=0.95,"B","C"))) -> #DIV/0! | G29: =VLOOKUP(B$22:B$42,I$22:M$42,5,0) -> #N/A | K29: =J29/J$42 -> #DIV/0! | L29: =K29+L28 -> #DIV/0! | M29: =_xlfn.IFS(L29<80%,"A",L29<=95%,"B",L29>95%,"C") -> #DIV/0!
D30: =C30/C$42 -> #DIV/0! | E30: =D30+E29 -> #DIV/0! | F30: =IF(AND(E30<=0),"C",IF(E30<=0.8,"A",IF(E30<=0.95,"B","C"))) -> #DIV/0! | G30: =VLOOKUP(B$22:B$42,I$22:M$42,5,0) -> #N/A | K30: =J30/J$42 -> #DIV/0! | L30: =K30+L29 -> #DIV/0! | M30: =_xlfn.IFS(L30<80%,"A",L30<=95%,"B",L30>95%,"C") -> #DIV/0!
D31: =C31/C$42 -> #DIV/0! | E31: =D31+E30 -> #DIV/0! | F31: =IF(AND(E31<=0),"C",IF(E31<=0.8,"A",IF(E31<=0.95,"B","C"))) -> #DIV/0! | G31: =VLOOKUP(B$22:B$42,I$22:M$42,5,0) -> #N/A | K31: =J31/J$42 -> #DIV/0! | L31: =K31+L30 -> #DIV/0! | M31: =_xlfn.IFS(L31<80%,"A",L31<=95%,"B",L31>95%,"C") -> #DIV/0!
D32: =C32/C$42 -> #DIV/0! | E32: =D32+E31 -> #DIV/0! | F32: =IF(AND(E32<=0),"C",IF(E32<=0.8,"A",IF(E32<=0.95,"B","C"))) -> #DIV/0! | G32: =VLOOKUP(B$22:B$42,I$22:M$42,5,0) -> #N/A | K32: =J32/J$42 -> #DIV/0! | L32: =K32+L31 -> #DIV/0! | M32: =_xlfn.IFS(L32<80%,"A",L32<=95%,"B",L32>95%,"C") -> #DIV/0!
D33: =C33/C$42 -> #DIV/0! | E33: =D33+E32 -> #DIV/0! | F33: =IF(AND(E33<=0),"C",IF(E33<=0.8,"A",IF(E33<=0.95,"B","C"))) -> #DIV/0! | G33: =VLOOKUP(B$22:B$42,I$22:M$42,5,0) -> #N/A | K33: =J33/J$42 -> #DIV/0! | L33: =K33+L32 -> #DIV/0! | M33: =_xlfn.IFS(L33<80%,"A",L33<=95%,"B",L33>95%,"C") -> #DIV/0!
D34: =C34/C$42 -> #DIV/0! | E34: =D34+E33 -> #DIV/0! | F34: =IF(AND(E34<=0),"C",IF(E34<=0.8,"A",IF(E34<=0.95,"B","C"))) -> #DIV/0! | G34: =VLOOKUP(B$22:B$42,I$22:M$42,5,0) -> #N/A | K34: =J34/J$42 -> #DIV/0! | L34: =K34+L33 -> #DIV/0! | M34: =_xlfn.IFS(L34<80%,"A",L34<=95%,"B",L34>95%,"C") -> #DIV/0!
... D41: =C41/C$42 -> #DIV/0! | E41: =D41+E40 -> #DIV/0! | F41: =IF(AND(E41<=0),"C",IF(E41<=0.8,"A",IF(E41<=0.95,"B","C"))) -> #DIV/0! | G41: =VLOOKUP(B$22:B$42,I$22:M$42,5,0) -> #N/A | K41: =J41/J$42 -> #DIV/0! | L41: =K41+L40 -> #DIV/0! | M41: =_xlfn.IFS(L41<80%,"A",L41<=95%,"B",L41>95%,"C") -> #DIV/0!
C42: =SUM(C22:C41) -> 0 | D42: =SUM(D22:D41) -> #DIV/0! | J42: =SUM(J22:J41) -> 0 | K42: =SUM(K22:K41) -> #DIV/0!

Sheet АВС 01-04.01
B2: ОЧКИ
C3: Прибыль | D3: % прибыль | E3: Доля | F3: ABC прибыль | G3: ABC кол-во | J3: Кол-во | K3: % кол-во | L3: Доля | M3: ABC кол-во
B4: flip жел | C4: ='Юнит 01-04.01'!AE15 -> 2923.2652 | D4: =C4/C$18 -> -0.78040933 | E4: =D4 -> -0.78040933 | F4: =IF(AND(E4<=0),"C",IF(E4<=0.8,"A",IF(E4<=0.95,"B","C"))) -> C | G4: =VLOOKUP(B$4:B$17,I$4:M$17,5,0) -> A | I4: flip жел | J4: ='Юнит 01-04.01'!R15 -> 25 | K4: =J4/J$18 -> 0.5 | L4: =K4 -> 0.5 | M4: =_xlfn.IFS(L4<80%,"A",L4<=95%,"B",L4>95%,"C") -> A
B5: qs черные | C5: ='Юнит 01-04.01'!AE4 -> 684.33 | D5: =C5/C$18 -> -0.18269212 | E5: =D5+E4 -> -0.96310145 | F5: =IF(AND(E5<=0),"C",IF(E5<=0.8,"A",IF(E5<=0.95,"B","C"))) -> C | G5: =VLOOKUP(B$4:B$17,I$4:M$17,5,0) -> C | I5: th желт | J5: ='Юнит 01-04.01'!R11 -> 12 | K5: =J5/J$18 -> 0.24 | L5: =K5+L4 -> 0.74 | M5: =_xlfn.IFS(L5<80%,"A",L5<=95%,"B",L5>95%,"C") -> A
B6: qs коричневые | C6: ='Юнит 01-04.01'!AE7 -> 752.97 | D6: =C6/C$18 -> -0.20101659 | E6: =D6+E5 -> -1.164118 | F6: =IF(AND(E6<=0),"C",IF(E6<=0.8,"A",IF(E6<=0.95,"B","C"))) -> C | G6: =VLOOKUP(B$4:B$17,I$4:M$17,5,0) -> B | I6: qs желтые | J6: ='Юнит 01-04.01'!R6 -> 7 | K6: =J6/J$18 -> 0.14 | L6: =K6+L5 -> 0.88 | M6: =_xlfn.IFS(L6<80%,"A",L6<=95%,"B",L6>95%,"C") -> B
B7: черные с железкой классика | C7: ='Юнит 01-04.01'!AE3 -> 277.19 | D7: =C7/C$18 -> -0.074000012 | E7: =D7+E6 -> -1.238118 | F7: =IF(AND(E7<=0),"C",IF(E7<=0.8,"A",IF(E7<=0.95,"B","C"))) -> C | G7: =VLOOKUP(B$4:B$17,I$4:M$17,5,0) -> C | I7: qs коричневые | J7: ='Юнит 01-04.01'!R7 -> 2 | K7: =J7/J$18 -> 0.04 | L7: =K7+L6 -> 0.92 | M7: =_xlfn.IFS(L7<80%,"A",L7<=95%,"B",L7>95%,"C") -> B
B8: qs синие | C8: ='Юнит 01-04.01'!AE5 -> 0 | D8: =C8/C$18 -> 0 | E8: =D8+E7 -> -1.238118 | F8: =IF(AND(E8<=0),"C",IF(E8<=0.8,"A",IF(E8<=0.95,"B","C"))) -> C | G8: =VLOOKUP(B$4:B$17,I$4:M$17,5,0) -> C | I8: MR8854 C2 | J8: ='Юнит 01-04.01'!R8 -> 2 | K8: =J8/J$18 -> 0.04 | L8: =K8+L7 -> 0.96 | M8: =_xlfn.IFS(L8<80%,"A",L8<=95%,"B",L8>95%,"C") -> C
B9: th черн | C9: ='Юнит 01-04.01'!AE9 -> 0 | D9: =C9/C$18 -> 0 | E9: =D9+E8 -> -1.238118 | F9: =IF(AND(E9<=0),"C",IF(E9<=0.8,"A",IF(E9<=0.95,"B","C"))) -> C | G9: =VLOOKUP(B$4:B$17,I$4:M$17,5,0) -> A | I9: черные с железкой классика | J9: ='Юнит 01-04.01'!R3 -> 1 | K9: =J9/J$18 -> 0.02 | L9: =K9+L8 -> 0.98 | M9: =_xlfn.IFS(L9<80%,"A",L9<=95%,"B",L9>95%,"C") -> C
B10: th син | C10: ='Юнит 01-04.01'!AE10 -> 0 | D10: =C10/C$18 -> 0 | E10: =D10+E9 -> -1.238118 | F10: =IF(AND(E10<=0),"C",IF(E10<=0.8,"A",IF(E10<=0.95,"B","C"))) -> C | G10: =VLOOKUP(B$4:B$17,I$4:M$17,5,0) -> A | I10: qs черные | J10: ='Юнит 01-04.01'!R4 -> 1 | K10: =J10/J$18 -> 0.02 | L10: =K10+L9 -> 1 | M10: =_xlfn.IFS(L10<80%,"A",L10<=95%,"B",L10>95%,"C") -> C
B11: th коричн | C11: ='Юнит 01-04.01'!AE12 -> 0 | D11: =C11/C$18 -> 0 | E11: =D11+E10 -> -1.238118 | F11: =IF(AND(E11<=0),"C",IF(E11<=0.8,"A",IF(E11<=0.95,"B","C"))) -> C | G11: =VLOOKUP(B$4:B$17,I$4:M$17,5,0) -> A | I11: qs синие | J11: ='Юнит 01-04.01'!R5 -> 0 | K11: =J11/J$18 -> 0 | L11: =K11+L10 -> 1 | M11: =_xlfn.IFS(L11<80%,"A",L11<=95%,"B",L11>95%,"C") -> C
B12: flip черный | C12: ='Юнит 01-04.01'!AE13 -> 0 | D12: =C12/C$18 -> 0 | E12: =D12+E5 -> -0.96310145 | F12: =IF(AND(E12<=0),"C",IF(E12<=0.8,"A",IF(E12<=0.95,"B","C"))) -> C | G12: =VLOOKUP(B$4:B$17,I$4:M$17,5,0) -> A | I12: th черн | J12: ='Юнит 01-04.01'!R9 -> 0 | K12: =J12/J$18 -> 0 | L12: =K12+L5 -> 0.74 | M12: =_xlfn.IFS(L12<80%,"A",L12<=95%,"B",L12>95%,"C") -> A
B13: flip синий | C13: ='Юнит 01-04.01'!AE14 -> 0 | D13: =C13/C$18 -> 0 | E13: =D13+E12 -> -0.96310145 | F13: =IF(AND(E13<=0),"C",IF(E13<=0.8,"A",IF(E13<=0.95,"B","C"))) -> C | G13: =VLOOKUP(B$4:B$17,I$4:M$17,5,0) -> A | I13: th син | J13: ='Юнит 01-04.01'!R10 -> 0 | K13: =J13/J$18 -> 0 | L13: =K13+L12 -> 0.74 | M13: =_xlfn.IFS(L13<80%,"A",L13<=95%,"B",L13>95%,"C") -> A
B14: flip коричневый | C14: ='Юнит 01-04.01'!AE16 -> 0 | D14: =C14/C$18 -> 0 | E14: =D14+E13 -> -0.96310145 | F14: =IF(AND(E14<=0),"C",IF(E14<=0.8,"A",IF(E14<=0.95,"B","C"))) -> C | G14: =VLOOKUP(B$4:B$17,I$4:M$17,5,0) -> A | I14: th коричн | J14: ='Юнит 01-04.01'!R12 -> 0 | K14: =J14/J$18 -> 0 | L14: =K14+L13 -> 0.74 | M14: =_xlfn.IFS(L14<80%,"A",L14<=95%,"B",L14>95%,"C") -> A
B15: MR8854 C2 | C15: ='Юнит 01-04.01'!AE8 -> -419.23 | D15: =C15/C$18 -> 0.11191971 | E15: =D15+E14 -> -0.85118173 | F15: =IF(AND(E15<=0),"C",IF(E15<=0.8,"A",IF(E15<=0.95,"B","C"))) -> C | G15: =VLOOKUP(B$4:B$17,I$4:M$17,5,0) -> C | I15: flip черный | J15: ='Юнит 01-04.01'!R13 -> 0 | K15: =J15/J$18 -> 0 | L15: =K15+L14 -> 0.74 | M15: =_xlfn.IFS(L15<80%,"A",L15<=95%,"B",L15>95%,"C") -> A
B16: qs желтые | C16: ='Юнит 01-04.01'!AE6 -> -2341.0661 | D16: =C16/C$18 -> 0.62498256 | E16: =D16+E15 -> -0.22619917 | F16: =IF(AND(E16<=0),"C",IF(E16<=0.8,"A",IF(E16<=0.95,"B","C"))) -> C | G16: =VLOOKUP(B$4:B$17,I$4:M$17,5,0) -> B | I16: flip синий | J16: ='Юнит 01-04.01'!R14 -> 0 | K16: =J16/J$18 -> 0 | L16: =K16+L15 -> 0.74 | M16: =_xlfn.IFS(L16<80%,"A",L16<=95%,"B",L16>95%,"C") -> A
B17: th желт | C17: ='Юнит 01-04.01'!AE11 -> -5623.2694 | D17: =C17/C$18 -> 1.5012158 | E17: =D17+E14 -> 0.53811433 | F17: =IF(AND(E17<=0),"C",IF(E17<=0.8,"A",IF(E17<=0.95,"B","C"))) -> A | G17: =VLOOKUP(B$4:B$17,I$4:M$17,5,0) -> A | I17: flip коричневый | J17: ='Юнит 01-04.01'!R16 -> 0 | K17: =J17/J$18 -> 0 | L17: =K17+L14 -> 0.74 | M17: =_xlfn.IFS(L17<80%,"A",L17<=95%,"B",L17>95%,"C") -> A
C18: =SUM(C4:C17) -> -3745.8102 | D18: =SUM(D4:D17) -> 1 | J18: =SUM(J4:J17) -> 50 | K18: =SUM(K4:K17) -> 1
C21: Прибыль | D21: % прибыль | E21: Доля | F21: ABC прибыль | G21: ABC кол-во | J21: Кол-во | K21: % кол-во | L21: Доля | M21: ABC кол-во
D22: =C22/C$42 -> #DIV/0! | E22: =D22 -> #DIV/0! | F22: =IF(AND(E22<=0),"C",IF(E22<=0.8,"A",IF(E22<=0.95,"B","C"))) -> #DIV/0! | G22: =VLOOKUP(B$22:B$42,I$22:M$42,5,0) -> #N/A | K22: =J22/J$42 -> #DIV/0! | L22: =K22 -> #DIV/0! | M22: =_xlfn.IFS(L22<80%,"A",L22<=95%,"B",L22>95%,"C") -> #DIV/0!
D23: =C23/C$42 -> #DIV/0! | E23: =D23+E22 -> #DIV/0! | F23: =IF(AND(E23<=0),"C",IF(E23<=0.8,"A",IF(E23<=0.95,"B","C"))) -> #DIV/0! | G23: =VLOOKUP(B$22:B$42,I$22:M$42,5,0) -> #N/A | K23: =J23/J$42 -> #DIV/0! | L23: =K23+L22 -> #DIV/0! | M23: =_xlfn.IFS(L23<80%,"A",L23<=95%,"B",L23>95%,"C") -> #DIV/0!
D24: =C24/C$42 -> #DIV/0! | E24: =D24+E23 -> #DIV/0! | F24: =IF(AND(E24<=0),"C",IF(E24<=0.8,"A",IF(E24<=0.95,"B","C"))) -> #DIV/0! | G24: =VLOOKUP(B$22:B$42,I$22:M$42,5,0) -> #N/A | K24: =J24/J$42 -> #DIV/0! | L24: =K24+L23 -> #DIV/0! | M24: =_xlfn.IFS(L24<80%,"A",L24<=95%,"B",L24>95%,"C") -> #DIV/0!
D25: =C25/C$42 -> #DIV/0! | E25: =D25+E24 -> #DIV/0! | F25: =IF(AND(E25<=0),"C",IF(E25<=0.8,"A",IF(E25<=0.95,"B","C"))) -> #DIV/0! | G25: =VLOOKUP(B$22:B$42,I$22:M$42,5,0) -> #N/A | K25: =J25/J$42 -> #DIV/0! | L25: =K25+L24 -> #DIV/0! | M25: =_xlfn.IFS(L25<80%,"A",L25<=95%,"B",L25>95%,"C") -> #DIV/0!
D26: =C26/C$42 -> #DIV/0! | E26: =D26+E25 -> #DIV/0! | F26: =IF(AND(E26<=0),"C",IF(E26<=0.8,"A",IF(E26<=0.95,"B","C"))) -> #DIV/0! | G26: =VLOOKUP(B$22:B$42,I$22:M$42,5,0) -> #N/A | K26: =J26/J$42 -> #DIV/0! | L26: =K26+L25 -> #DIV/0! | M26: =_xlfn.IFS(L26<80%,"A",L26<=95%,"B",L26>95%,"C") -> #DIV/0!
D27: =C27/C$42 -> #DIV/0! | E27: =D27+E26 -> #DIV/0! | F27: =IF(AND(E27<=0),"C",IF(E27<=0.8,"A",IF(E27<=0.95,"B","C"))) -> #DIV/0! | G27: =VLOOKUP(B$22:B$42,I$22:M$42,5,0) -> #N/A | K27: =J27/J$42 -> #DIV/0! | L27: =K27+L26 -> #DIV/0! | M27: =_xlfn.IFS(L27<80%,"A",L27<=95%,"B",L27>95%,"C") -> #DIV/0!
D28: =C28/C$42 -> #DIV/0! | E28: =D28+E27 -> #DIV/0! | F28: =IF(AND(E28<=0),"C",IF(E28<=0.8,"A",IF(E28<=0.95,"B","C"))) -> #DIV/0! | G28: =VLOOKUP(B$22:B$42,I$22:M$42,5,0) -> #N/A | K28: =J28/J$42 -> #DIV/0! | L28: =K28+L27 -> #DIV/0! | M28: =_xlfn.IFS(L28<80%,"A",L28<=95%,"B",L28>95%,"C") -> #DIV/0!
D29: =C29/C$42 -> #DIV/0! | E29: =D29+E28 -> #DIV/0! | F29: =IF(AND(E29<=0),"C",IF(E29<=0.8,"A",IF(E29<=0.95,"B","C"))) -> #DIV/0! | G29: =VLOOKUP(B$22:B$42,I$22:M$42,5,0) -> #N/A | K29: =J29/J$42 -> #DIV/0! | L29: =K29+L28 -> #DIV/0! | M29: =_xlfn.IFS(L29<80%,"A",L29<=95%,"B",L29>95%,"C") -> #DIV/0!
D30: =C30/C$42 -> #DIV/0! | E30: =D30+E29 -> #DIV/0! | F30: =IF(AND(E30<=0),"C",IF(E30<=0.8,"A",IF(E30<=0.95,"B","C"))) -> #DIV/0! | G30: =VLOOKUP(B$22:B$42,I$22:M$42,5,0) -> #N/A | K30: =J30/J$42 -> #DIV/0! | L30: =K30+L29 -> #DIV/0! | M30: =_xlfn.IFS(L30<80%,"A",L30<=95%,"B",L30>95%,"C") -> #DIV/0!
D31: =C31/C$42 -> #DIV/0! | E31: =D31+E30 -> #DIV/0! | F31: =IF(AND(E31<=0),"C",IF(E31<=0.8,"A",IF(E31<=0.95,"B","C"))) -> #DIV/0! | G31: =VLOOKUP(B$22:B$42,I$22:M$42,5,0) -> #N/A | K31: =J31/J$42 -> #DIV/0! | L31: =K31+L30 -> #DIV/0! | M31: =_xlfn.IFS(L31<80%,"A",L31<=95%,"B",L31>95%,"C") -> #DIV/0!
D32: =C32/C$42 -> #DIV/0! | E32: =D32+E31 -> #DIV/0! | F32: =IF(AND(E32<=0),"C",IF(E32<=0.8,"A",IF(E32<=0.95,"B","C"))) -> #DIV/0! | G32: =VLOOKUP(B$22:B$42,I$22:M$42,5,0) -> #N/A | K32: =J32/J$42 -> #DIV/0! | L32: =K32+L31 -> #DIV/0! | M32: =_xlfn.IFS(L32<80%,"A",L32<=95%,"B",L32>95%,"C") -> #DIV/0!
D33: =C33/C$42 -> #DIV/0! | E33: =D33+E32 -> #DIV/0! | F33: =IF(AND(E33<=0),"C",IF(E33<=0.8,"A",IF(E33<=0.95,"B","C"))) -> #DIV/0! | G33: =VLOOKUP(B$22:B$42,I$22:M$42,5,0) -> #N/A | K33: =J33/J$42 -> #DIV/0! | L33: =K33+L32 -> #DIV/0! | M33: =_xlfn.IFS(L33<80%,"A",L33<=95%,"B",L33>95%,"C") -> #DIV/0!
D34: =C34/C$42 -> #DIV/0! | E34: =D34+E33 -> #DIV/0! | F34: =IF(AND(E34<=0),"C",IF(E34<=0.8,"A",IF(E34<=0.95,"B","C"))) -> #DIV/0! | G34: =VLOOKUP(B$22:B$42,I$22:M$42,5,0) -> #N/A | K34: =J34/J$42 -> #DIV/0! | L34: =K34+L33 -> #DIV/0! | M34: =_xlfn.IFS(L34<80%,"A",L34<=95%,"B",L34>95%,"C") -> #DIV/0!
... D41: =C41/C$42 -> #DIV/0! | E41: =D41+E40 -> #DIV/0! | F41: =IF(AND(E41<=0),"C",IF(E41<=0.8,"A",IF(E41<=0.95,"B","C"))) -> #DIV/0! | G41: =VLOOKUP(B$22:B$42,I$22:M$42,5,0) -> #N/A | K41: =J41/J$42 -> #DIV/0! | L41: =K41+L40 -> #DIV/0! | M41: =_xlfn.IFS(L41<80%,"A",L41<=95%,"B",L41>95%,"C") -> #DIV/0!
C42: =SUM(C22:C41) -> 0 | D42: =SUM(D22:D41) -> #DIV/0! | J42: =SUM(J22:J41) -> 0 | K42: =SUM(K22:K41) -> #DIV/0!

Sheet Юнит 02-08.02
B1: 02-08.02 | AG1: на 1 единицу проданного товара
B2: Артикул поставщика | C2: Остаток на | D2: В пути до клиента | E2: В пути от клиента | F2: Итого по складам ВБ | G2: Остаток на нашем складе на 02.09 | H2: Себетоимость на 1 ед на 29.09.25 | I2: Себестоимость остатков | J2: Оборачиваемость, дн | K2: Заказы, шт 7 дней | L2: Средняя цена, руб (столбец 32, AG) | M2: % выкупа за 7 дней (столбец 23, X) | N2: Скорость заказов | O2: Скорость продаж | P2: Кол-во ПРОДАЖИ | Q2: Кол-во ВОЗВРАТЫ | R2: Кол-во ПРОДАЖИ-ВОЗВРАТЫ | S2: Выручка ПРОДАЖИ | T2: Выручка ВОЗВРАТЫ | U2: Выручка с учетом согласованной скидки ПРОДАЖИ - ВОЗВРАТЫ | V2: Доля выручки, % от общего объема | W2: Себестоимость продаж | X2: Комиссия, руб | Y2: Комиссия, % | Z2: Логистика | AA2: Реклама | AB2: Хранение | AC2: Штрафы | AD2: Налог 1% | AE2: Прибыль | AG2: Выручка на 1 ед (средняя цена продажи со скидкой) | AH2: Себестоимость на 1 ед | AI2: Комиссия на 1 ед | AJ2: Логистика на 1 ед | AK2: Реклама на 1 ед | AL2: Прибыль на 1 ед | AM2: Маржинальность, % | AN2: Рентабельность, % | AP2: Прибыль с остатков
A3: 2676784153 | B3: черные с железкой классика | H3: 142.98 | I3: =C3*H3 -> 0 | N3: =K3/7 -> 0 | O3: =R3/7 -> 0 | P3: =SUMIFS('Отчет 01.02'!H:H,'Отчет 01.02'!D:D,"Выручка",'Отчет 01.02'!E:E,B3) -> 0 | Q3: =SUMIFS('Отчет 01.02'!H:H,'Отчет 01.02'!D:D,"Возврат выручки",'Отчет 01.02'!E:E,B3) -> 0 | R3: =P3-Q3 -> 0 | S3: =SUMIFS('Отчет 01.02'!P:P,'Отчет 01.02'!C:C,"Продажи",'Отчет 01.02'!E:E,B3) -> 0 | T3: =SUMIFS('Отчет 01.02'!P:P,'Отчет 01.02'!C:C,"Возвраты",'Отчет 01.02'!E:E,B3) -> 0 | U3: =S3+T3 -> 0 | V3: =U3/$U$24 -> 0 | W3: =R3*H3 -> 0 | X3: =-SUMIFS('Отчет 01.02'!P:P,'Отчет 01.02'!C:C,"Вознаграждение Ozon",'Отчет 01.02'!E:E,B3) -> 0 | Y3: =IF(U3=0,0,X3/U3) -> 0 | Z3: =-SUMIFS('Отчет 01.02'!P:P,'Отчет 01.02'!C:C,"Услуги доставки",'Отчет 01.02'!E:E,B3) -> 0 | AD3: =U3*1% -> 0 | AE3: =U3-W3-X3-Z3-AA3-AB3-AC3-AD3 -> 0 | AG3: =IF(R3=0,0,U3/R3) -> 0 | AH3: =H3 -> 142.98 | AI3: =IF(R3=0,0,X3/R3) -> 0 | AJ3: =IF(P3=0,Z3/1,Z3/P3) -> 0 | AK3: =IF(P3=0,0,AA3/P3) -> 0 | AL3: =_xlfn.IFS(R3=0,AE3,R3<0,AE3/-R3,R3>0,AE3/R3) -> 0 | AM3: =IF(AG3=0,0,AL3/AG3) -> 0 | AN3: =IF(AH3=0,0,AL3/AH3) -> 0 | AP3: =AL3*C3 -> 0
A4: 2676784638 | B4: qs черные | H4: 123.09 | I4: =C4*H4 -> 0 | N4: =K4/7 -> 0 | O4: =R4/7 -> 0.14285714 | P4: =SUMIFS('Отчет 01.02'!H:H,'Отчет 01.02'!D:D,"Выручка",'Отчет 01.02'!E:E,B4) -> 1 | Q4: =SUMIFS('Отчет 01.02'!H:H,'Отчет 01.02'!D:D,"Возврат выручки",'Отчет 01.02'!E:E,B4) -> 0 | R4: =P4-Q4 -> 1 | S4: =SUMIFS('Отчет 01.02'!P:P,'Отчет 01.02'!C:C,"Продажи",'Отчет 01.02'!E:E,B4) -> 1750 | T4: =SUMIFS('Отчет 01.02'!P:P,'Отчет 01.02'!C:C,"Возвраты",'Отчет 01.02'!E:E,B4) -> 0 | U4: =S4+T4 -> 1750 | V4: =U4/$U$24 -> 0.05364478 | W4: =R4*H4 -> 123.09 | X4: =-SUMIFS('Отчет 01.02'!P:P,'Отчет 01.02'!C:C,"Вознаграждение Ozon",'Отчет 01.02'!E:E,B4) -> 752.5 | Y4: =IF(U4=0,0,X4/U4) -> 0.43 | Z4: =-SUMIFS('Отчет 01.02'!P:P,'Отчет 01.02'!C:C,"Услуги доставки",'Отчет 01.02'!E:E,B4) -> 119.28 | AD4: =U4*1% -> 17.5 | AE4: =U4-W4-X4-Z4-AA4-AB4-AC4-AD4 -> 737.63 | AG4: =IF(R4=0,0,U4/R4) -> 1750 | AH4: =H4 -> 123.09 | AI4: =IF(R4=0,0,X4/R4) -> 752.5 | AJ4: =IF(P4=0,Z4/1,Z4/P4) -> 119.28 | AK4: =IF(P4=0,0,AA4/P4) -> 0 | AL4: {=_xlfn.IFS(R4=0,AE4,R4<0,AE4/-R4,R4>0,AE4/R4)} -> 737.63 | AM4: =IF(AG4=0,0,AL4/AG4) -> 0.42150286 | AN4: =IF(AH4=0,0,AL4/AH4) -> 5.992607 | AP4: =AL4*C4 -> 0
A5: 2676784504 | B5: qs синие | H5: 123.09 | I5: =C5*H5 -> 0 | N5: =K5/7 -> 0 | O5: =R5/7 -> 0 | P5: =SUMIFS('Отчет 01.02'!H:H,'Отчет 01.02'!D:D,"Выручка",'Отчет 01.02'!E:E,B5) -> 0 | Q5: =SUMIFS('Отчет 01.02'!H:H,'Отчет 01.02'!D:D,"Возврат выручки",'Отчет 01.02'!E:E,B5) -> 0 | R5: =P5-Q5 -> 0 | S5: =SUMIFS('Отчет 01.02'!P:P,'Отчет 01.02'!C:C,"Продажи",'Отчет 01.02'!E:E,B5) -> 0 | T5: =SUMIFS('Отчет 01.02'!P:P,'Отчет 01.02'!C:C,"Возвраты",'Отчет 01.02'!E:E,B5) -> 0 | U5: =S5+T5 -> 0 | V5: =U5/$U$24 -> 0 | W5: =R5*H5 -> 0 | X5: =-SUMIFS('Отчет 01.02'!P:P,'Отчет 01.02'!C:C,"Вознаграждение Ozon",'Отчет 01.02'!E:E,B5) -> 0 | Y5: =IF(U5=0,0,X5/U5) -> 0 | Z5: =-SUMIFS('Отчет 01.02'!P:P,'Отчет 01.02'!C:C,"Услуги доставки",'Отчет 01.02'!E:E,B5) -> 0 | AD5: =U5*1% -> 0 | AE5: =U5-W5-X5-Z5-AA5-AB5-AC5-AD5 -> 0 | AG5: =IF(R5=0,0,U5/R5) -> 0 | AH5: =H5 -> 123.09 | AI5: =IF(R5=0,0,X5/R5) -> 0 | AJ5: =IF(P5=0,Z5/1,Z5/P5) -> 0 | AK5: =IF(P5=0,0,AA5/P5) -> 0 | AL5: {=_xlfn.IFS(R5=0,AE5,R5<0,AE5/-R5,R5>0,AE5/R5)} -> 0 | AM5: =IF(AG5=0,0,AL5/AG5) -> 0 | AN5: =IF(AH5=0,0,AL5/AH5) -> 0 | AP5: =AL5*C5 -> 0
A6: 2676784514 | B6: qs желтые | H6: 123.09 | I6: =C6*H6 -> 0 | N6: =K6/7 -> 0 | O6: =R6/7 -> 0 | P6: =SUMIFS('Отчет 01.02'!H:H,'Отчет 01.02'!D:D,"Выручка",'Отчет 01.02'!E:E,B6) -> 0 | Q6: =SUMIFS('Отчет 01.02'!H:H,'Отчет 01.02'!D:D,"Возврат выручки",'Отчет 01.02'!E:E,B6) -> 0 | R6: =P6-Q6 -> 0 | S6: =SUMIFS('Отчет 01.02'!P:P,'Отчет 01.02'!C:C,"Продажи",'Отчет 01.02'!E:E,B6) -> 0 | T6: =SUMIFS('Отчет 01.02'!P:P,'Отчет 01.02'!C:C,"Возвраты",'Отчет 01.02'!E:E,B6) -> 0 | U6: =S6+T6 -> 0 | V6: =U6/$U$24 -> 0 | W6: =R6*H6 -> 0 | X6: =-SUMIFS('Отчет 01.02'!P:P,'Отчет 01.02'!C:C,"Вознаграждение Ozon",'Отчет 01.02'!E:E,B6) -> 0 | Y6: =IF(U6=0,0,X6/U6) -> 0 | Z6: =-SUMIFS('Отчет 01.02'!P:P,'Отчет 01.02'!C:C,"Услуги доставки",'Отчет 01.02'!E:E,B6) -> 0 | AD6: =U6*1% -> 0 | AE6: =U6-W6-X6-Z6-AA6-AB6-AC6-AD6 -> 0 | AG6: =IF(R6=0,0,U6/R6) -> 0 | AH6: =H6 -> 123.09 | AI6: =IF(R6=0,0,X6/R6) -> 0 | AJ6: =IF(P6=0,Z6/1,Z6/P6) -> 0 | AK6: =IF(P6=0,0,AA6/P6) -> 0 | AL6: {=_xlfn.IFS(R6=0,AE6,R6<0,AE6/-R6,R6>0,AE6/R6)} -> 0 | AM6: =IF(AG6=0,0,AL6/AG6) -> 0 | AN6: =IF(AH6=0,0,AL6/AH6) -> 0 | AP6: =AL6*C6 -> 0
A7: 2676784181 | B7: qs коричневые | H7: 117.24 | I7: =C7*H7 -> 0 | N7: =K7/7 -> 0 | O7: =R7/7 -> 0.14285714 | P7: =SUMIFS('Отчет 01.02'!H:H,'Отчет 01.02'!D:D,"Выручка",'Отчет 01.02'!E:E,B7) -> 2 | Q7: =SUMIFS('Отчет 01.02'!H:H,'Отчет 01.02'!D:D,"Возврат выручки",'Отчет 01.02'!E:E,B7) -> 1 | R7: =P7-Q7 -> 1 | S7: =SUMIFS('Отчет 01.02'!P:P,'Отчет 01.02'!C:C,"Продажи",'Отчет 01.02'!E:E,B7) -> 3500 | T7: =SUMIFS('Отчет 01.02'!P:P,'Отчет 01.02'!C:C,"Возвраты",'Отчет 01.02'!E:E,B7) -> -1750 | U7: =S7+T7 -> 1750 | V7: =U7/$U$24 -> 0.05364478 | W7: =R7*H7 -> 117.24 | X7: =-SUMIFS('Отчет 01.02'!P:P,'Отчет 01.02'!C:C,"Вознаграждение Ozon",'Отчет 01.02'!E:E,B7) -> 752.5 | Y7: =IF(U7=0,0,X7/U7) -> 0.43 | Z7: =-SUMIFS('Отчет 01.02'!P:P,'Отчет 01.02'!C:C,"Услуги доставки",'Отчет 01.02'!E:E,B7) -> 262.74 | AD7: =U7*1% -> 17.5 | AE7: =U7-W7-X7-Z7-AA7-AB7-AC7-AD7 -> 600.02 | AG7: =IF(R7=0,0,U7/R7) -> 1750 | AH7: =H7 -> 117.24 | AI7: =IF(R7=0,0,X7/R7) -> 752.5 | AJ7: =IF(P7=0,Z7/1,Z7/P7) -> 131.37 | AK7: =IF(P7=0,0,AA7/P7) -> 0 | AL7: {=_xlfn.IFS(R7=0,AE7,R7<0,AE7/-R7,R7>0,AE7/R7)} -> 600.02 | AM7: =IF(AG7=0,0,AL7/AG7) -> 0.34286857 | AN7: =IF(AH7=0,0,AL7/AH7) -> 5.1178779 | AP7: =AL7*C7 -> 0
A8: 2676783005 | B8: MR8854 C2 | H8: 169.89 | I8: =C8*H8 -> 0 | N8: =K8/7 -> 0 | O8: =R8/7 -> 0.14285714 | P8: =SUMIFS('Отчет 01.02'!H:H,'Отчет 01.02'!D:D,"Выручка",'Отчет 01.02'!E:E,B8) -> 1 | Q8: =SUMIFS('Отчет 01.02'!H:H,'Отчет 01.02'!D:D,"Возврат выручки",'Отчет 01.02'!E:E,B8) -> 0 | R8: =P8-Q8 -> 1 | S8: =SUMIFS('Отчет 01.02'!P:P,'Отчет 01.02'!C:C,"Продажи",'Отчет 01.02'!E:E,B8) -> 1750 | T8: =SUMIFS('Отчет 01.02'!P:P,'Отчет 01.02'!C:C,"Возвраты",'Отчет 01.02'!E:E,B8) -> 0 | U8: =S8+T8 -> 1750 | V8: =U8/$U$24 -> 0.05364478 | W8: =R8*H8 -> 169.89 | X8: =-SUMIFS('Отчет 01.02'!P:P,'Отчет 01.02'!C:C,"Вознаграждение Ozon",'Отчет 01.02'!E:E,B8) -> 752.5 | Y8: =IF(U8=0,0,X8/U8) -> 0.43 | Z8: =-SUMIFS('Отчет 01.02'!P:P,'Отчет 01.02'!C:C,"Услуги доставки",'Отчет 01.02'!E:E,B8) -> 131.37 | AD8: =U8*1% -> 17.5 | AE8: =U8-W8-X8-Z8-AA8-AB8-AC8-AD8 -> 678.74 | AG8: =IF(R8=0,0,U8/R8) -> 1750 | AH8: =H8 -> 169.89 | AI8: =IF(R8=0,0,X8/R8) -> 752.5 | AJ8: =IF(P8=0,Z8/1,Z8/P8) -> 131.37 | AK8: =IF(P8=0,0,AA8/P8) -> 0 | AL8: {=_xlfn.IFS(R8=0,AE8,R8<0,AE8/-R8,R8>0,AE8/R8)} -> 678.74 | AM8: =IF(AG8=0,0,AL8/AG8) -> 0.38785143 | AN8: =IF(AH8=0,0,AL8/AH8) -> 3.9951733 | AP8: =AL8*C8 -> 0
A9: 3405092860 | B9: th черн | H9: 123 | I9: =C9*H9 -> 0 | N9: =K9/7 -> 0 | O9: =R9/7 -> 0 | P9: =SUMIFS('Отчет 01.02'!H:H,'Отчет 01.02'!D:D,"Выручка",'Отчет 01.02'!E:E,B9) -> 0 | Q9: =SUMIFS('Отчет 01.02'!H:H,'Отчет 01.02'!D:D,"Возврат выручки",'Отчет 01.02'!E:E,B9) -> 0 | R9: =P9-Q9 -> 0 | S9: =SUMIFS('Отчет 01.02'!P:P,'Отчет 01.02'!C:C,"Продажи",'Отчет 01.02'!E:E,B9) -> 0 | T9: =SUMIFS('Отчет 01.02'!P:P,'Отчет 01.02'!C:C,"Возвраты",'Отчет 01.02'!E:E,B9) -> 0 | U9: =S9+T9 -> 0 | V9: =U9/$U$24 -> 0 | W9: =R9*H9 -> 0 | X9: =-SUMIFS('Отчет 01.02'!P:P,'Отчет 01.02'!C:C,"Вознаграждение Ozon",'Отчет 01.02'!E:E,B9) -> 0 | Y9: =IF(U9=0,0,X9/U9) -> 0 | Z9: =-SUMIFS('Отчет 01.02'!P:P,'Отчет 01.02'!C:C,"Услуги доставки",'Отчет 01.02'!E:E,B9) -> 0 | AD9: =U9*1% -> 0 | AE9: =U9-W9-X9-Z9-AA9-AB9-AC9-AD9 -> 0 | AG9: =IF(R9=0,0,U9/R9) -> 0 | AH9: =H9 -> 123 | AI9: =IF(R9=0,0,X9/R9) -> 0 | AJ9: =IF(P9=0,Z9/1,Z9/P9) -> 0 | AK9: =IF(P9=0,0,AA9/P9) -> 0 | AL9: {=_xlfn.IFS(R9=0,AE9,R9<0,AE9/-R9,R9>0,AE9/R9)} -> 0 | AM9: =IF(AG9=0,0,AL9/AG9) -> 0 | AN9: =IF(AH9=0,0,AL9/AH9) -> 0 | AP9: =AL9*C9 -> 0
A10: 3405092836 | B10: th син | H10: 123 | I10: =C10*H10 -> 0 | N10: =K10/7 -> 0 | O10: =R10/7 -> 0.14285714 | P10: =SUMIFS('Отчет 01.02'!H:H,'Отчет 01.02'!D:D,"Выручка",'Отчет 01.02'!E:E,B10) -> 1 | Q10: =SUMIFS('Отчет 01.02'!H:H,'Отчет 01.02'!D:D,"Возврат выручки",'Отчет 01.02'!E:E,B10) -> 0 | R10: =P10-Q10 -> 1 | S10: =SUMIFS('Отчет 01.02'!P:P,'Отчет 01.02'!C:C,"Продажи",'Отчет 01.02'!E:E,B10) -> 2000 | T10: =SUMIFS('Отчет 01.02'!P:P,'Отчет 01.02'!C:C,"Возвраты",'Отчет 01.02'!E:E,B10) -> 0 | U10: =S10+T10 -> 2000 | V10: =U10/$U$24 -> 0.06130832 | W10: =R10*H10 -> 123 | X10: =-SUMIFS('Отчет 01.02'!P:P,'Отчет 01.02'!C:C,"Вознаграждение Ozon",'Отчет 01.02'!E:E,B10) -> 860 | Y10: =IF(U10=0,0,X10/U10) -> 0.43 | Z10: =-SUMIFS('Отчет 01.02'!P:P,'Отчет 01.02'!C:C,"Услуги доставки",'Отчет 01.02'!E:E,B10) -> 155.81 | AD10: =U10*1% -> 20 | AE10: =U10-W10-X10-Z10-AA10-AB10-AC10-AD10 -> 841.19 | AG10: =IF(R10=0,0,U10/R10) -> 2000 | AH10: =H10 -> 123 | AI10: =IF(R10=0,0,X10/R10) -> 860 | AJ10: =IF(P10=0,Z10/1,Z10/P10) -> 155.81 | AK10: =IF(P10=0,0,AA10/P10) -> 0 | AL10: {=_xlfn.IFS(R10=0,AE10,R10<0,AE10/-R10,R10>0,AE10/R10)} -> 841.19 | AM10: =IF(AG10=0,0,AL10/AG10) -> 0.420595 | AN10: =IF(AH10=0,0,AL10/AH10) -> 6.8389431 | AP10: =AL10*C10 -> 0
A11: 3064346962 | B11: th желт | H11: 123 | I11: =C11*H11 -> 0 | N11: =K11/7 -> 0 | O11: =R11/7 -> 1.1428571 | P11: =SUMIFS('Отчет 01.02'!H:H,'Отчет 01.02'!D:D,"Выручка",'Отчет 01.02'!E:E,B11) -> 8 | Q11: =SUMIFS('Отчет 01.02'!H:H,'Отчет 01.02'!D:D,"Возврат выручки",'Отчет 01.02'!E:E,B11) -> 0 | R11: =P11-Q11 -> 8 | S11: =SUMIFS('Отчет 01.02'!P:P,'Отчет 01.02'!C:C,"Продажи",'Отчет 01.02'!E:E,B11) -> 14312 | T11: =SUMIFS('Отчет 01.02'!P:P,'Отчет 01.02'!C:C,"Возвраты",'Отчет 01.02'!E:E,B11) -> 0 | U11: =S11+T11 -> 14312 | V11: =U11/$U$24 -> 0.43872233 | W11: =R11*H11 -> 984 | X11: =-SUMIFS('Отчет 01.02'!P:P,'Отчет 01.02'!C:C,"Вознаграждение Ozon",'Отчет 01.02'!E:E,B11) -> 6154.16 | Y11: =IF(U11=0,0,X11/U11) -> 0.43 | Z11: =-SUMIFS('Отчет 01.02'!P:P,'Отчет 01.02'!C:C,"Услуги доставки",'Отчет 01.02'!E:E,B11) -> 1379.34 | AD11: =U11*1% -> 143.12 | AE11: =U11-W11-X11-Z11-AA11-AB11-AC11-AD11 -> 5651.38 | AG11: =IF(R11=0,0,U11/R11) -> 1789 | AH11: =H11 -> 123 | AI11: =IF(R11=0,0,X11/R11) -> 769.27 | AJ11: =IF(P11=0,Z11/1,Z11/P11) -> 172.4175 | AK11: =IF(P11=0,0,AA11/P11) -> 0 | AL11: {=_xlfn.IFS(R11=0,AE11,R11<0,AE11/-R11,R11>0,AE11/R11)} -> 706.4225 | AM11: =IF(AG11=0,0,AL11/AG11) -> 0.39487004 | AN11: =IF(AH11=0,0,AL11/AH11) -> 5.7432724 | AP11: =AL11*C11 -> 0
A12: 3405092873 | B12: th коричн | H12: 117 | I12: =C12*H12 -> 0 | N12: =K12/7 -> 0 | O12: =R12/7 -> 0.14285714 | P12: =SUMIFS('Отчет 01.02'!H:H,'Отчет 01.02'!D:D,"Выручка",'Отчет 01.02'!E:E,B12) -> 1 | Q12: =SUMIFS('Отчет 01.02'!H:H,'Отчет 01.02'!D:D,"Возврат выручки",'Отчет 01.02'!E:E,B12) -> 0 | R12: =P12-Q12 -> 1 | S12: =SUMIFS('Отчет 01.02'!P:P,'Отчет 01.02'!C:C,"Продажи",'Отчет 01.02'!E:E,B12) -> 2000 | T12: =SUMIFS('Отчет 01.02'!P:P,'Отчет 01.02'!C:C,"Возвраты",'Отчет 01.02'!E:E,B12) -> 0 | U12: =S12+T12 -> 2000 | V12: =U12/$U$24 -> 0.06130832 | W12: =R12*H12 -> 117 | X12: =-SUMIFS('Отчет 01.02'!P:P,'Отчет 01.02'!C:C,"Вознаграждение Ozon",'Отчет 01.02'!E:E,B12) -> 860 | Y12: =IF(U12=0,0,X12/U12) -> 0.43 | Z12: =-SUMIFS('Отчет 01.02'!P:P,'Отчет 01.02'!C:C,"Услуги доставки",'Отчет 01.02'!E:E,B12) -> 155.81 | AD12: =U12*1% -> 20 | AE12: =U12-W12-X12-Z12-AA12-AB12-AC12-AD12 -> 847.19 | AG12: =IF(R12=0,0,U12/R12) -> 2000 | AH12: =H12 -> 117 | AI12: =IF(R12=0,0,X12/R12) -> 860 | AJ12: =IF(P12=0,Z12/1,Z12/P12) -> 155.81 | AK12: =IF(P12=0,0,AA12/P12) -> 0 | AL12: {=_xlfn.IFS(R12=0,AE12,R12<0,AE12/-R12,R12>0,AE12/R12)} -> 847.19 | AM12: =IF(AG12=0,0,AL12/AG12) -> 0.423595 | AN12: =IF(AH12=0,0,AL12/AH12) -> 7.2409402 | AP12: =AL12*C12 -> 0
A13: 3405092993 | B13: flip черный | H13: 123 | I13: =C13*H13 -> 0 | N13: =K13/7 -> 0 | O13: =R13/7 -> 0 | P13: =SUMIFS('Отчет 01.02'!H:H,'Отчет 01.02'!D:D,"Выручка",'Отчет 01.02'!E:E,B13) -> 0 | Q13: =SUMIFS('Отчет 01.02'!H:H,'Отчет 01.02'!D:D,"Возврат выручки",'Отчет 01.02'!E:E,B13) -> 0 | R13: =P13-Q13 -> 0 | S13: =SUMIFS('Отчет 01.02'!P:P,'Отчет 01.02'!C:C,"Продажи",'Отчет 01.02'!E:E,B13) -> 0 | T13: =SUMIFS('Отчет 01.02'!P:P,'Отчет 01.02'!C:C,"Возвраты",'Отчет 01.02'!E:E,B13) -> 0 | U13: =S13+T13 -> 0 | V13: =U13/$U$24 -> 0 | W13: =R13*H13 -> 0 | X13: =-SUMIFS('Отчет 01.02'!P:P,'Отчет 01.02'!C:C,"Вознаграждение Ozon",'Отчет 01.02'!E:E,B13) -> 0 | Y13: =IF(U13=0,0,X13/U13) -> 0 | Z13: =-SUMIFS('Отчет 01.02'!P:P,'Отчет 01.02'!C:C,"Услуги доставки",'Отчет 01.02'!E:E,B13) -> 0 | AD13: =U13*1% -> 0 | AE13: =U13-W13-X13-Z13-AA13-AB13-AC13-AD13 -> 0 | AG13: =IF(R13=0,0,U13/R13) -> 0 | AH13: =H13 -> 123 | AI13: =IF(R13=0,0,X13/R13) -> 0 | AJ13: =IF(P13=0,Z13/1,Z13/P13) -> 0 | AK13: =IF(P13=0,0,AA13/P13) -> 0 | AL13: {=_xlfn.IFS(R13=0,AE13,R13<0,AE13/-R13,R13>0,AE13/R13)} -> 0 | AM13: =IF(AG13=0,0,AL13/AG13) -> 0 | AN13: =IF(AH13=0,0,AL13/AH13) -> 0 | AP13: =AL13*C13 -> 0
A14: 3405092868 | B14: flip синий | H14: 123 | I14: =C14*H14 -> 0 | N14: =K14/7 -> 0 | O14: =R14/7 -> 0 | P14: =SUMIFS('Отчет 01.02'!H:H,'Отчет 01.02'!D:D,"Выручка",'Отчет 01.02'!E:E,B14) -> 0 | Q14: =SUMIFS('Отчет 01.02'!H:H,'Отчет 01.02'!D:D,"Возврат выручки",'Отчет 01.02'!E:E,B14) -> 0 | R14: =P14-Q14 -> 0 | S14: =SUMIFS('Отчет 01.02'!P:P,'Отчет 01.02'!C:C,"Продажи",'Отчет 01.02'!E:E,B14) -> 0 | T14: =SUMIFS('Отчет 01.02'!P:P,'Отчет 01.02'!C:C,"Возвраты",'Отчет 01.02'!E:E,B14) -> 0 | U14: =S14+T14 -> 0 | V14: =U14/$U$24 -> 0 | W14: =R14*H14 -> 0 | X14: =-SUMIFS('Отчет 01.02'!P:P,'Отчет 01.02'!C:C,"Вознаграждение Ozon",'Отчет 01.02'!E:E,B14) -> 0 | Y14: =IF(U14=0,0,X14/U14) -> 0 | Z14: =-SUMIFS('Отчет 01.02'!P:P,'Отчет 01.02'!C:C,"Услуги доставки",'Отчет 01.02'!E:E,B14) -> 0 | AD14: =U14*1% -> 0 | AE14: =U14-W14-X14-Z14-AA14-AB14-AC14-AD14 -> 0 | AG14: =IF(R14=0,0,U14/R14) -> 0 | AH14: =H14 -> 123 | AI14: =IF(R14=0,0,X14/R14) -> 0 | AJ14: =IF(P14=0,Z14/1,Z14/P14) -> 0 | AK14: =IF(P14=0,0,AA14/P14) -> 0 | AL14: {=_xlfn.IFS(R14=0,AE14,R14<0,AE14/-R14,R14>0,AE14/R14)} -> 0 | AM14: =IF(AG14=0,0,AL14/AG14) -> 0 | AN14: =IF(AH14=0,0,AL14/AH14) -> 0 | AP14: =AL14*C14 -> 0
A15: 3064346642 | B15: flip жел | H15: 123 | I15: =C15*H15 -> 0 | N15: =K15/7 -> 0 | O15: =R15/7 -> 0.71428571 | P15: =SUMIFS('Отчет 01.02'!H:H,'Отчет 01.02'!D:D,"Выручка",'Отчет 01.02'!E:E,B15) -> 5 | Q15: =SUMIFS('Отчет 01.02'!H:H,'Отчет 01.02'!D:D,"Возврат выручки",'Отчет 01.02'!E:E,B15) -> 0 | R15: =P15-Q15 -> 5 | S15: =SUMIFS('Отчет 01.02'!P:P,'Отчет 01.02'!C:C,"Продажи",'Отчет 01.02'!E:E,B15) -> 9060 | T15: =SUMIFS('Отчет 01.02'!P:P,'Отчет 01.02'!C:C,"Возвраты",'Отчет 01.02'!E:E,B15) -> 0 | U15: =S15+T15 -> 9060 | V15: =U15/$U$24 -> 0.27772669 | W15: =R15*H15 -> 615 | X15: =-SUMIFS('Отчет 01.02'!P:P,'Отчет 01.02'!C:C,"Вознаграждение Ozon",'Отчет 01.02'!E:E,B15) -> 3895.8 | Y15: =IF(U15=0,0,X15/U15) -> 0.43 | Z15: =-SUMIFS('Отчет 01.02'!P:P,'Отчет 01.02'!C:C,"Услуги доставки",'Отчет 01.02'!E:E,B15) -> 975.17 | AD15: =U15*1% -> 90.6 | AE15: =U15-W15-X15-Z15-AA15-AB15-AC15-AD15 -> 3483.43 | AG15: =IF(R15=0,0,U15/R15) -> 1812 | AH15: =H15 -> 123 | AI15: =IF(R15=0,0,X15/R15) -> 779.16 | AJ15: =IF(P15=0,Z15/1,Z15/P15) -> 195.034 | AK15: =IF(P15=0,0,AA15/P15) -> 0 | AL15: {=_xlfn.IFS(R15=0,AE15,R15<0,AE15/-R15,R15>0,AE15/R15)} -> 696.686 | AM15: =IF(AG15=0,0,AL15/AG15) -> 0.38448455 | AN15: =IF(AH15=0,0,AL15/AH15) -> 5.6641138 | AP15: =AL15*C15 -> 0
A16: 3405092287 | B16: flip коричневый | H16: 117 | I16: =C16*H16 -> 0 | N16: =K16/7 -> 0 | O16: =R16/7 -> 0 | P16: =SUMIFS('Отчет 01.02'!H:H,'Отчет 01.02'!D:D,"Выручка",'Отчет 01.02'!E:E,B16) -> 0 | Q16: =SUMIFS('Отчет 01.02'!H:H,'Отчет 01.02'!D:D,"Возврат выручки",'Отчет 01.02'!E:E,B16) -> 0 | R16: =P16-Q16 -> 0 | S16: =SUMIFS('Отчет 01.02'!P:P,'Отчет 01.02'!C:C,"Продажи",'Отчет 01.02'!E:E,B16) -> 0 | T16: =SUMIFS('Отчет 01.02'!P:P,'Отчет 01.02'!C:C,"Возвраты",'Отчет 01.02'!E:E,B16) -> 0 | U16: =S16+T16 -> 0 | V16: =U16/$U$24 -> 0 | W16: =R16*H16 -> 0 | X16: =-SUMIFS('Отчет 01.02'!P:P,'Отчет 01.02'!C:C,"Вознаграждение Ozon",'Отчет 01.02'!E:E,B16) -> 0 | Y16: =IF(U16=0,0,X16/U16) -> 0 | Z16: =-SUMIFS('Отчет 01.02'!P:P,'Отчет 01.02'!C:C,"Услуги доставки",'Отчет 01.02'!E:E,B16) -> 0 | AD16: =U16*1% -> 0 | AE16: =U16-W16-X16-Z16-AA16-AB16-AC16-AD16 -> 0 | AG16: =IF(R16=0,0,U16/R16) -> 0 | AH16: =H16 -> 117 | AI16: =IF(R16=0,0,X16/R16) -> 0 | AJ16: =IF(P16=0,Z16/1,Z16/P16) -> 0 | AK16: =IF(P16=0,0,AA16/P16) -> 0 | AL16: {=_xlfn.IFS(R16=0,AE16,R16<0,AE16/-R16,R16>0,AE16/R16)} -> 0 | AM16: =IF(AG16=0,0,AL16/AG16) -> 0 | AN16: =IF(AH16=0,0,AL16/AH16) -> 0 | AP16: =AL16*C16 -> 0
AG17: =AVERAGEIF(AG3:AG15,"<>0",AG3:AG15) -> 1835.8571 | AH17: =AVERAGEIF(AH3:AH15,"<>0",AH3:AH15) -> 127.26 | AI17: =AVERAGEIF(AI3:AI15,"<>0",AI3:AI15) -> 789.41857 | AJ17: =AVERAGEIF(AJ3:AJ15,"<>0",AJ3:AJ15) -> 151.5845 | AK17: =AVERAGEIF(AK3:AK15,"<>0",AK3:AK15) -> #DIV/0! | AL17: =AVERAGEIF(AL3:AL15,"<>0",AL3:AL15) -> 729.69693 | AM17: =AVERAGEIF(AM3:AM15,"<>0",AM3:AM15) -> 0.39653821 | AN17: =AVERAGEIF(AN3:AN15,"<>0",AN3:AN15) -> 5.7989897
A18: Итого очки | C18: =SUM(C3:C16) -> 0 | E18: 108496 | F18: 597 | G18: 295 | I18: =SUM(I3:I16) -> 0 | K18: =SUM(K3:K16) -> 0 | P18: =SUM(P3:P16) -> 19 | Q18: =SUM(Q3:Q16) -> 1 | R18: =SUM(R3:R16) -> 18 | S18: =SUM(S3:S16) -> 34372 | T18: =SUM(T3:T16) -> -1750 | U18: =SUM(U3:U16) -> 32622 | V18: =SUM(V3:V16) -> 1 | W18: =SUM(W3:W16) -> 2249.22 | X18: =SUM(X3:X16) -> 14027.46 | Y18: =IF(U18=0,0,X18/U18) -> 0.43 | Z18: =SUM(Z3:Z16) -> 3179.52 | AA18: =IFERROR(P18*AA24/P24,0) -> 0 | AB18: =SUM(AB3:AB16) -> 0 | AC18: =SUM(AC3:AC16) -> 0 | AD18: =SUM(AD3:AD16) -> 326.22 | AE18: =SUM(AE3:AE16) -> 12839.58 | AP18: =SUM(AP3:AP16) -> 0 | AZ18: 18592777
AA19: =SUM(AA3:AA16) -> 0
AG21: =AVERAGEIF(AG20:AG20,"<>0",AG20:AG20) -> #DIV/0! | AH21: =AVERAGEIF(AH20:AH20,"<>0",AH20:AH20) -> #DIV/0! | AI21: =AVERAGEIF(AI20:AI20,"<>0",AI20:AI20) -> #DIV/0! | AJ21: =AVERAGEIF(AJ20:AJ20,"<>0",AJ20:AJ20) -> #DIV/0! | AK21: =AVERAGEIF(AK20:AK20,"<>0",AK20:AK20) -> #DIV/0! | AL21: =AVERAGEIF(AL20:AL20,"<>0",AL20:AL20) -> #DIV/0! | AM21: =AVERAGEIF(AM20:AM20,"<>0",AM20:AM20) -> #DIV/0! | AN21: =AVERAGEIF(AN20:AN20,"<>0",AN20:AN20) -> #DIV/0!
C22: =SUM(C20:C20) -> 0 | I22: =SUM(I20:I20) -> 0 | K22: =SUM(K20:K20) -> 0 | P22: =SUM(P20:P20) -> 0 | Q22: =SUM(Q20:Q20) -> 0 | R22: =SUM(R20:R20) -> 0 | S22: =SUM(S20:S20) -> 0 | T22: =SUM(T20:T20) -> 0 | U22: =SUM(U20:U20) -> 0 | V22: =SUM(V20:V20) -> 0 | W22: =SUM(W20:W20) -> 0 | X22: =SUM(X20:X20) -> 0 | Y22: =IF(U22=0,0,X22/U22) -> 0 | Z22: =SUM(Z20:Z20) -> 0 | AA22: =IFERROR(P22*AA24/P24,0) -> 0 | AB22: =SUM(AB20:AB20) -> 0 | AC22: =SUM(AC20:AC20) -> 0 | AD22: =SUM(AD20:AD20) -> 0 | AE22: =SUM(AE20:AE20) -> 0 | AP22: =SUM(AP20:AP20) -> 0
AA23: =SUM(AA20:AA20) -> 0
A24: ИТОГО | C24: =C18+C22 -> 0 | D24: =SUM(D3:D20) -> 0 | E24: =SUM(E3:E20) -> 108496 | F24: =SUM(F3:F20) -> 597 | G24: =SUM(G3:G20) -> 295 | I24: =I18+I22 -> 0 | J24: =J18+J22 -> 0 | K24: =K18+K22 -> 0 | P24: =P18+P22 -> 19 | Q24: =Q18+Q22 -> 1 | R24: =R18-R22 -> 18 | S24: =S18+S22 -> 34372 | T24: =T18+T22 -> -1750 | U24: =U18+U22 -> 32622 | V24: =V18+V22 -> 1 | W24: =W18+W22 -> 2249.22 | X24: =X18+X22 -> 14027.46 | Y24: =X24/U24 -> 0.43 | Z24: =Z18+Z22 -> 3179.52 | AC24: =SUM(AC3:AC20) -> 0 | AD24: =AD18+AD22 -> 326.22 | AE24: =AE18+AE22 -> 12839.58 | AK24: =AA25/P24 -> 0 | AP24: =SUM(AP3:AP20) -> 0
AA25: =AA18+AA22 -> 0
AA26: =AA19+AA23 -> 0
I29: Себестоимость остатков | K29: Прибыль с остатков | L29: Рентабельность товарных остатков
H31: до 60 дн | I31: =SUMIF(J3:J20,"<60",I3:I20) -> 0 | J31: =I31/I24 -> #DIV/0! | K31: =SUMIF(J3:J20,"<60",AP3:AP20) -> 0 | L31: =K31/I31 -> #DIV/0!
H32: 60-120 дн | I32: =I24-I33-I31 -> 0 | J32: =I32/I24 -> #DIV/0! | K32: =AP24-K31-K33 -> 0 | L32: =K32/I32 -> #DIV/0!
H33: > 120 дн | I33: =SUMIF(J3:J20,">120",I3:I20) -> 0 | J33: =I33/I24 -> #DIV/0! | K33: =SUMIF(J3:J20,">120",AP3:AP20) -> 0 | L33: =K33/I33 -> #DIV/0!
H35: Если товар на сайте менее 30 дней - оборачиваемость 0

Sheet Юнит 01.02
B1: 01.02 | N1: число дней | O1: 1 | AG1: на 1 единицу проданного товара
B2: Артикул поставщика | C2: Остаток на 02.02 | D2: В пути до клиента | E2: В пути от клиента | F2: Итого по складам ВБ | G2: Остаток на нашем складе на 02.09 | H2: Себетоимость на 1 ед на 29.09.25 | I2: Себестоимость остатков | J2: Оборачиваемость, дн | K2: Заказы, шт 01.02 | L2: Средняя цена, руб (столбец 32, AG) | M2: % выкупа за 7 дней (столбец 23, X) | N2: Скорость заказов | O2: Скорость продаж | P2: Кол-во ПРОДАЖИ | Q2: Кол-во ВОЗВРАТЫ | R2: Кол-во ПРОДАЖИ-ВОЗВРАТЫ | S2: Выручка ПРОДАЖИ | T2: Выручка ВОЗВРАТЫ | U2: Выручка с учетом согласованной скидки ПРОДАЖИ - ВОЗВРАТЫ | V2: Доля выручки, % от общего объема | W2: Себестоимость продаж | X2: Комиссия, руб | Y2: Комиссия, % | Z2: Логистика | AA2: Реклама | AB2: Хранение | AC2: Штрафы | AD2: Налог 1% | AE2: Прибыль | AG2: Выручка на 1 ед (средняя цена продажи со скидкой) | AH2: Себестоимость на 1 ед | AI2: Комиссия на 1 ед | AJ2: Логистика на 1 ед | AK2: Реклама на 1 ед | AL2: Прибыль на 1 ед | AM2: Маржинальность, % | AN2: Рентабельность, % | AP2: Прибыль с остатков
A3: 2676784153 | B3: черные с железкой классика | C3: 362 | H3: 142.98 | I3: =C3*H3 -> 51758.76 | K3: 1 | N3: =K3/$O$1 -> 1 | O3: =R3/$O$1 -> 0 | P3: =SUMIFS('Отчет 01.02'!H:H,'Отчет 01.02'!D:D,"Выручка",'Отчет 01.02'!E:E,B3) -> 0 | Q3: =SUMIFS('Отчет 01.02'!H:H,'Отчет 01.02'!D:D,"Возврат выручки",'Отчет 01.02'!E:E,B3) -> 0 | R3: =P3-Q3 -> 0 | S3: =SUMIFS('Отчет 01.02'!P:P,'Отчет 01.02'!C:C,"Продажи",'Отчет 01.02'!E:E,B3) -> 0 | T3: =SUMIFS('Отчет 01.02'!P:P,'Отчет 01.02'!C:C,"Возвраты",'Отчет 01.02'!E:E,B3) -> 0 | U3: =S3+T3 -> 0 | V3: =U3/$U$24 -> 0 | W3: =R3*H3 -> 0 | X3: =-SUMIFS('Отчет 01.02'!P:P,'Отчет 01.02'!C:C,"Вознаграждение Ozon",'Отчет 01.02'!E:E,B3) -> 0 | Y3: =IF(U3=0,0,X3/U3) -> 0 | Z3: =-SUMIFS('Отчет 01.02'!P:P,'Отчет 01.02'!C:C,"Услуги доставки",'Отчет 01.02'!E:E,B3) -> 0 | AA3: 0 | AD3: =U3*1% -> 0 | AE3: =U3-W3-X3-Z3-AA3-AB3-AC3-AD3 -> 0 | AG3: =IF(R3=0,0,U3/R3) -> 0 | AH3: =H3 -> 142.98 | AI3: =IF(R3=0,0,X3/R3) -> 0 | AJ3: =IF(P3=0,Z3/1,Z3/P3) -> 0 | AK3: =IF(P3=0,0,AA3/P3) -> 0 | AL3: =_xlfn.IFS(R3=0,AE3,R3<0,AE3/-R3,R3>0,AE3/R3) -> 0 | AM3: =IF(AG3=0,0,AL3/AG3) -> 0 | AN3: =IF(AH3=0,0,AL3/AH3) -> 0 | AP3: =AL3*C3 -> 0
A4: 2676784638 | B4: qs черные | C4: 368 | H4: 123.09 | I4: =C4*H4 -> 45297.12 | K4: 0 | N4: =K4/$O$1 -> 0 | O4: =R4/$O$1 -> 1 | P4: =SUMIFS('Отчет 01.02'!H:H,'Отчет 01.02'!D:D,"Выручка",'Отчет 01.02'!E:E,B4) -> 1 | Q4: =SUMIFS('Отчет 01.02'!H:H,'Отчет 01.02'!D:D,"Возврат выручки",'Отчет 01.02'!E:E,B4) -> 0 | R4: =P4-Q4 -> 1 | S4: =SUMIFS('Отчет 01.02'!P:P,'Отчет 01.02'!C:C,"Продажи",'Отчет 01.02'!E:E,B4) -> 1750 | T4: =SUMIFS('Отчет 01.02'!P:P,'Отчет 01.02'!C:C,"Возвраты",'Отчет 01.02'!E:E,B4) -> 0 | U4: =S4+T4 -> 1750 | V4: =U4/$U$24 -> 0.05364478 | W4: =R4*H4 -> 123.09 | X4: =-SUMIFS('Отчет 01.02'!P:P,'Отчет 01.02'!C:C,"Вознаграждение Ozon",'Отчет 01.02'!E:E,B4) -> 752.5 | Y4: =IF(U4=0,0,X4/U4) -> 0.43 | Z4: =-SUMIFS('Отчет 01.02'!P:P,'Отчет 01.02'!C:C,"Услуги доставки",'Отчет 01.02'!E:E,B4) -> 119.28 | AA4: 0 | AD4: =U4*1% -> 17.5 | AE4: =U4-W4-X4-Z4-AA4-AB4-AC4-AD4 -> 737.63 | AG4: =IF(R4=0,0,U4/R4) -> 1750 | AH4: =H4 -> 123.09 | AI4: =IF(R4=0,0,X4/R4) -> 752.5 | AJ4: =IF(P4=0,Z4/1,Z4/P4) -> 119.28 | AK4: =IF(P4=0,0,AA4/P4) -> 0 | AL4: {=_xlfn.IFS(R4=0,AE4,R4<0,AE4/-R4,R4>0,AE4/R4)} -> 737.63 | AM4: =IF(AG4=0,0,AL4/AG4) -> 0.42150286 | AN4: =IF(AH4=0,0,AL4/AH4) -> 5.992607 | AP4: =AL4*C4 -> 271447.84
A5: 2676784504 | B5: qs синие | C5: 378 | H5: 123.09 | I5: =C5*H5 -> 46528.02 | K5: 0 | N5: =K5/$O$1 -> 0 | O5: =R5/$O$1 -> 0 | P5: =SUMIFS('Отчет 01.02'!H:H,'Отчет 01.02'!D:D,"Выручка",'Отчет 01.02'!E:E,B5) -> 0 | Q5: =SUMIFS('Отчет 01.02'!H:H,'Отчет 01.02'!D:D,"Возврат выручки",'Отчет 01.02'!E:E,B5) -> 0 | R5: =P5-Q5 -> 0 | S5: =SUMIFS('Отчет 01.02'!P:P,'Отчет 01.02'!C:C,"Продажи",'Отчет 01.02'!E:E,B5) -> 0 | T5: =SUMIFS('Отчет 01.02'!P:P,'Отчет 01.02'!C:C,"Возвраты",'Отчет 01.02'!E:E,B5) -> 0 | U5: =S5+T5 -> 0 | V5: =U5/$U$24 -> 0 | W5: =R5*H5 -> 0 | X5: =-SUMIFS('Отчет 01.02'!P:P,'Отчет 01.02'!C:C,"Вознаграждение Ozon",'Отчет 01.02'!E:E,B5) -> 0 | Y5: =IF(U5=0,0,X5/U5) -> 0 | Z5: =-SUMIFS('Отчет 01.02'!P:P,'Отчет 01.02'!C:C,"Услуги доставки",'Отчет 01.02'!E:E,B5) -> 0 | AA5: 0 | AD5: =U5*1% -> 0 | AE5: =U5-W5-X5-Z5-AA5-AB5-AC5-AD5 -> 0 | AG5: =IF(R5=0,0,U5/R5) -> 0 | AH5: =H5 -> 123.09 | AI5: =IF(R5=0,0,X5/R5) -> 0 | AJ5: =IF(P5=0,Z5/1,Z5/P5) -> 0 | AK5: =IF(P5=0,0,AA5/P5) -> 0 | AL5: {=_xlfn.IFS(R5=0,AE5,R5<0,AE5/-R5,R5>0,AE5/R5)} -> 0 | AM5: =IF(AG5=0,0,AL5/AG5) -> 0 | AN5: =IF(AH5=0,0,AL5/AH5) -> 0 | AP5: =AL5*C5 -> 0
A6: 2676784514 | B6: qs желтые | C6: 680 | H6: 123.09 | I6: =C6*H6 -> 83701.2 | K6: 1 | N6: =K6/$O$1 -> 1 | O6: =R6/$O$1 -> 0 | P6: =SUMIFS('Отчет 01.02'!H:H,'Отчет 01.02'!D:D,"Выручка",'Отчет 01.02'!E:E,B6) -> 0 | Q6: =SUMIFS('Отчет 01.02'!H:H,'Отчет 01.02'!D:D,"Возврат выручки",'Отчет 01.02'!E:E,B6) -> 0 | R6: =P6-Q6 -> 0 | S6: =SUMIFS('Отчет 01.02'!P:P,'Отчет 01.02'!C:C,"Продажи",'Отчет 01.02'!E:E,B6) -> 0 | T6: =SUMIFS('Отчет 01.02'!P:P,'Отчет 01.02'!C:C,"Возвраты",'Отчет 01.02'!E:E,B6) -> 0 | U6: =S6+T6 -> 0 | V6: =U6/$U$24 -> 0 | W6: =R6*H6 -> 0 | X6: =-SUMIFS('Отчет 01.02'!P:P,'Отчет 01.02'!C:C,"Вознаграждение Ozon",'Отчет 01.02'!E:E,B6) -> 0 | Y6: =IF(U6=0,0,X6/U6) -> 0 | Z6: =-SUMIFS('Отчет 01.02'!P:P,'Отчет 01.02'!C:C,"Услуги доставки",'Отчет 01.02'!E:E,B6) -> 0 | AA6: 0 | AD6: =U6*1% -> 0 | AE6: =U6-W6-X6-Z6-AA6-AB6-AC6-AD6 -> 0 | AG6: =IF(R6=0,0,U6/R6) -> 0 | AH6: =H6 -> 123.09 | AI6: =IF(R6=0,0,X6/R6) -> 0 | AJ6: =IF(P6=0,Z6/1,Z6/P6) -> 0 | AK6: =IF(P6=0,0,AA6/P6) -> 0 | AL6: {=_xlfn.IFS(R6=0,AE6,R6<0,AE6/-R6,R6>0,AE6/R6)} -> 0 | AM6: =IF(AG6=0,0,AL6/AG6) -> 0 | AN6: =IF(AH6=0,0,AL6/AH6) -> 0 | AP6: =AL6*C6 -> 0
A7: 2676784181 | B7: qs коричневые | C7: 675 | H7: 117.24 | I7: =C7*H7 -> 79137 | K7: 4 | N7: =K7/$O$1 -> 4 | O7: =R7/$O$1 -> 1 | P7: =SUMIFS('Отчет 01.02'!H:H,'Отчет 01.02'!D:D,"Выручка",'Отчет 01.02'!E:E,B7) -> 2 | Q7: =SUMIFS('Отчет 01.02'!H:H,'Отчет 01.02'!D:D,"Возврат выручки",'Отчет 01.02'!E:E,B7) -> 1 | R7: =P7-Q7 -> 1 | S7: =SUMIFS('Отчет 01.02'!P:P,'Отчет 01.02'!C:C,"Продажи",'Отчет 01.02'!E:E,B7) -> 3500 | T7: =SUMIFS('Отчет 01.02'!P:P,'Отчет 01.02'!C:C,"Возвраты",'Отчет 01.02'!E:E,B7) -> -1750 | U7: =S7+T7 -> 1750 | V7: =U7/$U$24 -> 0.05364478 | W7: =R7*H7 -> 117.24 | X7: =-SUMIFS('Отчет 01.02'!P:P,'Отчет 01.02'!C:C,"Вознаграждение Ozon",'Отчет 01.02'!E:E,B7) -> 752.5 | Y7: =IF(U7=0,0,X7/U7) -> 0.43 | Z7: =-SUMIFS('Отчет 01.02'!P:P,'Отчет 01.02'!C:C,"Услуги доставки",'Отчет 01.02'!E:E,B7) -> 262.74 | AA7: 1525.1883 | AD7: =U7*1% -> 17.5 | AE7: =U7-W7-X7-Z7-AA7-AB7-AC7-AD7 -> -925.16826 | AG7: =IF(R7=0,0,U7/R7) -> 1750 | AH7: =H7 -> 117.24 | AI7: =IF(R7=0,0,X7/R7) -> 752.5 | AJ7: =IF(P7=0,Z7/1,Z7/P7) -> 131.37 | AK7: =IF(P7=0,0,AA7/P7) -> 762.59413 | AL7: {=_xlfn.IFS(R7=0,AE7,R7<0,AE7/-R7,R7>0,AE7/R7)} -> -925.16826 | AM7: =IF(AG7=0,0,AL7/AG7) -> -0.52866758 | AN7: =IF(AH7=0,0,AL7/AH7) -> -7.8912339 | AP7: =AL7*C7 -> -624488.57
A8: 2676783005 | B8: MR8854 C2 | C8: 335 | H8: 169.89 | I8: =C8*H8 -> 56913.15 | K8: 8 | N8: =K8/$O$1 -> 8 | O8: =R8/$O$1 -> 1 | P8: =SUMIFS('Отчет 01.02'!H:H,'Отчет 01.02'!D:D,"Выручка",'Отчет 01.02'!E:E,B8) -> 1 | Q8: =SUMIFS('Отчет 01.02'!H:H,'Отчет 01.02'!D:D,"Возврат выручки",'Отчет 01.02'!E:E,B8) -> 0 | R8: =P8-Q8 -> 1 | S8: =SUMIFS('Отчет 01.02'!P:P,'Отчет 01.02'!C:C,"Продажи",'Отчет 01.02'!E:E,B8) -> 1750 | T8: =SUMIFS('Отчет 01.02'!P:P,'Отчет 01.02'!C:C,"Возвраты",'Отчет 01.02'!E:E,B8) -> 0 | U8: =S8+T8 -> 1750 | V8: =U8/$U$24 -> 0.05364478 | W8: =R8*H8 -> 169.89 | X8: =-SUMIFS('Отчет 01.02'!P:P,'Отчет 01.02'!C:C,"Вознаграждение Ozon",'Отчет 01.02'!E:E,B8) -> 752.5 | Y8: =IF(U8=0,0,X8/U8) -> 0.43 | Z8: =-SUMIFS('Отчет 01.02'!P:P,'Отчет 01.02'!C:C,"Услуги доставки",'Отчет 01.02'!E:E,B8) -> 131.37 | AA8: 962.07295 | AD8: =U8*1% -> 17.5 | AE8: =U8-W8-X8-Z8-AA8-AB8-AC8-AD8 -> -283.33294 | AG8: =IF(R8=0,0,U8/R8) -> 1750 | AH8: =H8 -> 169.89 | AI8: =IF(R8=0,0,X8/R8) -> 752.5 | AJ8: =IF(P8=0,Z8/1,Z8/P8) -> 131.37 | AK8: =IF(P8=0,0,AA8/P8) -> 962.07295 | AL8: {=_xlfn.IFS(R8=0,AE8,R8<0,AE8/-R8,R8>0,AE8/R8)} -> -283.33294 | AM8: =IF(AG8=0,0,AL8/AG8) -> -0.16190454 | AN8: =IF(AH8=0,0,AL8/AH8) -> -1.6677435 | AP8: =AL8*C8 -> -94916.537
A9: 3405092860 | B9: th черн | C9: 393 | H9: 123 | I9: =C9*H9 -> 48339 | K9: 2 | N9: =K9/$O$1 -> 2 | O9: =R9/$O$1 -> 0 | P9: =SUMIFS('Отчет 01.02'!H:H,'Отчет 01.02'!D:D,"Выручка",'Отчет 01.02'!E:E,B9) -> 0 | Q9: =SUMIFS('Отчет 01.02'!H:H,'Отчет 01.02'!D:D,"Возврат выручки",'Отчет 01.02'!E:E,B9) -> 0 | R9: =P9-Q9 -> 0 | S9: =SUMIFS('Отчет 01.02'!P:P,'Отчет 01.02'!C:C,"Продажи",'Отчет 01.02'!E:E,B9) -> 0 | T9: =SUMIFS('Отчет 01.02'!P:P,'Отчет 01.02'!C:C,"Возвраты",'Отчет 01.02'!E:E,B9) -> 0 | U9: =S9+T9 -> 0 | V9: =U9/$U$24 -> 0 | W9: =R9*H9 -> 0 | X9: =-SUMIFS('Отчет 01.02'!P:P,'Отчет 01.02'!C:C,"Вознаграждение Ozon",'Отчет 01.02'!E:E,B9) -> 0 | Y9: =IF(U9=0,0,X9/U9) -> 0 | Z9: =-SUMIFS('Отчет 01.02'!P:P,'Отчет 01.02'!C:C,"Услуги доставки",'Отчет 01.02'!E:E,B9) -> 0 | AA9: 0 | AD9: =U9*1% -> 0 | AE9: =U9-W9-X9-Z9-AA9-AB9-AC9-AD9 -> 0 | AG9: =IF(R9=0,0,U9/R9) -> 0 | AH9: =H9 -> 123 | AI9: =IF(R9=0,0,X9/R9) -> 0 | AJ9: =IF(P9=0,Z9/1,Z9/P9) -> 0 | AK9: =IF(P9=0,0,AA9/P9) -> 0 | AL9: {=_xlfn.IFS(R9=0,AE9,R9<0,AE9/-R9,R9>0,AE9/R9)} -> 0 | AM9: =IF(AG9=0,0,AL9/AG9) -> 0 | AN9: =IF(AH9=0,0,AL9/AH9) -> 0 | AP9: =AL9*C9 -> 0
A10: 3405092836 | B10: th син | C10: 391 | H10: 123 | I10: =C10*H10 -> 48093 | K10: 2 | N10: =K10/$O$1 -> 2 | O10: =R10/$O$1 -> 1 | P10: =SUMIFS('Отчет 01.02'!H:H,'Отчет 01.02'!D:D,"Выручка",'Отчет 01.02'!E:E,B10) -> 1 | Q10: =SUMIFS('Отчет 01.02'!H:H,'Отчет 01.02'!D:D,"Возврат выручки",'Отчет 01.02'!E:E,B10) -> 0 | R10: =P10-Q10 -> 1 | S10: =SUMIFS('Отчет 01.02'!P:P,'Отчет 01.02'!C:C,"Продажи",'Отчет 01.02'!E:E,B10) -> 2000 | T10: =SUMIFS('Отчет 01.02'!P:P,'Отчет 01.02'!C:C,"Возвраты",'Отчет 01.02'!E:E,B10) -> 0 | U10: =S10+T10 -> 2000 | V10: =U10/$U$24 -> 0.06130832 | W10: =R10*H10 -> 123 | X10: =-SUMIFS('Отчет 01.02'!P:P,'Отчет 01.02'!C:C,"Вознаграждение Ozon",'Отчет 01.02'!E:E,B10) -> 860 | Y10: =IF(U10=0,0,X10/U10) -> 0.43 | Z10: =-SUMIFS('Отчет 01.02'!P:P,'Отчет 01.02'!C:C,"Услуги доставки",'Отчет 01.02'!E:E,B10) -> 155.81 | AA10: 287.43303 | AD10: =U10*1% -> 20 | AE10: =U10-W10-X10-Z10-AA10-AB10-AC10-AD10 -> 553.75697 | AG10: =IF(R10=0,0,U10/R10) -> 2000 | AH10: =H10 -> 123 | AI10: =IF(R10=0,0,X10/R10) -> 860 | AJ10: =IF(P10=0,Z10/1,Z10/P10) -> 155.81 | AK10: =IF(P10=0,0,AA10/P10) -> 287.43303 | AL10: {=_xlfn.IFS(R10=0,AE10,R10<0,AE10/-R10,R10>0,AE10/R10)} -> 553.75697 | AM10: =IF(AG10=0,0,AL10/AG10) -> 0.27687848 | AN10: =IF(AH10=0,0,AL10/AH10) -> 4.5020892 | AP10: =AL10*C10 -> 216518.97
A11: 3064346962 | B11: th желт | C11: 705 | H11: 123 | I11: =C11*H11 -> 86715 | K11: 8 | N11: =K11/$O$1 -> 8 | O11: =R11/$O$1 -> 8 | P11: =SUMIFS('Отчет 01.02'!H:H,'Отчет 01.02'!D:D,"Выручка",'Отчет 01.02'!E:E,B11) -> 8 | Q11: =SUMIFS('Отчет 01.02'!H:H,'Отчет 01.02'!D:D,"Возврат выручки",'Отчет 01.02'!E:E,B11) -> 0 | R11: =P11-Q11 -> 8 | S11: =SUMIFS('Отчет 01.02'!P:P,'Отчет 01.02'!C:C,"Продажи",'Отчет 01.02'!E:E,B11) -> 14312 | T11: =SUMIFS('Отчет 01.02'!P:P,'Отчет 01.02'!C:C,"Возвраты",'Отчет 01.02'!E:E,B11) -> 0 | U11: =S11+T11 -> 14312 | V11: =U11/$U$24 -> 0.43872233 | W11: =R11*H11 -> 984 | X11: =-SUMIFS('Отчет 01.02'!P:P,'Отчет 01.02'!C:C,"Вознаграждение Ozon",'Отчет 01.02'!E:E,B11) -> 6154.16 | Y11: =IF(U11=0,0,X11/U11) -> 0.43 | Z11: =-SUMIFS('Отчет 01.02'!P:P,'Отчет 01.02'!C:C,"Услуги доставки",'Отчет 01.02'!E:E,B11) -> 1379.34 | AA11: 2071.5017 | AD11: =U11*1% -> 143.12 | AE11: =U11-W11-X11-Z11-AA11-AB11-AC11-AD11 -> 3579.8783 | AG11: =IF(R11=0,0,U11/R11) -> 1789 | AH11: =H11 -> 123 | AI11: =IF(R11=0,0,X11/R11) -> 769.27 | AJ11: =IF(P11=0,Z11/1,Z11/P11) -> 172.4175 | AK11: =IF(P11=0,0,AA11/P11) -> 258.93771 | AL11: {=_xlfn.IFS(R11=0,AE11,R11<0,AE11/-R11,R11>0,AE11/R11)} -> 447.48479 | AM11: =IF(AG11=0,0,AL11/AG11) -> 0.25013124 | AN11: =IF(AH11=0,0,AL11/AH11) -> 3.6380877 | AP11: =AL11*C11 -> 315476.78
A12: 3405092873 | B12: th коричн | C12: 356 | H12: 117 | I12: =C12*H12 -> 41652 | K12: 0 | N12: =K12/$O$1 -> 0 | O12: =R12/$O$1 -> 1 | P12: =SUMIFS('Отчет 01.02'!H:H,'Отчет 01.02'!D:D,"Выручка",'Отчет 01.02'!E:E,B12) -> 1 | Q12: =SUMIFS('Отчет 01.02'!H:H,'Отчет 01.02'!D:D,"Возврат выручки",'Отчет 01.02'!E:E,B12) -> 0 | R12: =P12-Q12 -> 1 | S12: =SUMIFS('Отчет 01.02'!P:P,'Отчет 01.02'!C:C,"Продажи",'Отчет 01.02'!E:E,B12) -> 2000 | T12: =SUMIFS('Отчет 01.02'!P:P,'Отчет 01.02'!C:C,"Возвраты",'Отчет 01.02'!E:E,B12) -> 0 | U12: =S12+T12 -> 2000 | V12: =U12/$U$24 -> 0.06130832 | W12: =R12*H12 -> 117 | X12: =-SUMIFS('Отчет 01.02'!P:P,'Отчет 01.02'!C:C,"Вознаграждение Ozon",'Отчет 01.02'!E:E,B12) -> 860 | Y12: =IF(U12=0,0,X12/U12) -> 0.43 | Z12: =-SUMIFS('Отчет 01.02'!P:P,'Отчет 01.02'!C:C,"Услуги доставки",'Отчет 01.02'!E:E,B12) -> 155.81 | AA12: 0 | AD12: =U12*1% -> 20 | AE12: =U12-W12-X12-Z12-AA12-AB12-AC12-AD12 -> 847.19 | AG12: =IF(R12=0,0,U12/R12) -> 2000 | AH12: =H12 -> 117 | AI12: =IF(R12=0,0,X12/R12) -> 860 | AJ12: =IF(P12=0,Z12/1,Z12/P12) -> 155.81 | AK12: =IF(P12=0,0,AA12/P12) -> 0 | AL12: {=_xlfn.IFS(R12=0,AE12,R12<0,AE12/-R12,R12>0,AE12/R12)} -> 847.19 | AM12: =IF(AG12=0,0,AL12/AG12) -> 0.423595 | AN12: =IF(AH12=0,0,AL12/AH12) -> 7.2409402 | AP12: =AL12*C12 -> 301599.64
A13: 3405092993 | B13: flip черный | C13: 336 | H13: 123 | I13: =C13*H13 -> 41328 | K13: 2 | N13: =K13/$O$1 -> 2 | O13: =R13/$O$1 -> 0 | P13: =SUMIFS('Отчет 01.02'!H:H,'Отчет 01.02'!D:D,"Выручка",'Отчет 01.02'!E:E,B13) -> 0 | Q13: =SUMIFS('Отчет 01.02'!H:H,'Отчет 01.02'!D:D,"Возврат выручки",'Отчет 01.02'!E:E,B13) -> 0 | R13: =P13-Q13 -> 0 | S13: =SUMIFS('Отчет 01.02'!P:P,'Отчет 01.02'!C:C,"Продажи",'Отчет 01.02'!E:E,B13) -> 0 | T13: =SUMIFS('Отчет 01.02'!P:P,'Отчет 01.02'!C:C,"Возвраты",'Отчет 01.02'!E:E,B13) -> 0 | U13: =S13+T13 -> 0 | V13: =U13/$U$24 -> 0 | W13: =R13*H13 -> 0 | X13: =-SUMIFS('Отчет 01.02'!P:P,'Отчет 01.02'!C:C,"Вознаграждение Ozon",'Отчет 01.02'!E:E,B13) -> 0 | Y13: =IF(U13=0,0,X13/U13) -> 0 | Z13: =-SUMIFS('Отчет 01.02'!P:P,'Отчет 01.02'!C:C,"Услуги доставки",'Отчет 01.02'!E:E,B13) -> 0 | AA13: 0 | AD13: =U13*1% -> 0 | AE13: =U13-W13-X13-Z13-AA13-AB13-AC13-AD13 -> 0 | AG13: =IF(R13=0,0,U13/R13) -> 0 | AH13: =H13 -> 123 | AI13: =IF(R13=0,0,X13/R13) -> 0 | AJ13: =IF(P13=0,Z13/1,Z13/P13) -> 0 | AK13: =IF(P13=0,0,AA13/P13) -> 0 | AL13: {=_xlfn.IFS(R13=0,AE13,R13<0,AE13/-R13,R13>0,AE13/R13)} -> 0 | AM13: =IF(AG13=0,0,AL13/AG13) -> 0 | AN13: =IF(AH13=0,0,AL13/AH13) -> 0 | AP13: =AL13*C13 -> 0
A14: 3405092868 | B14: flip синий | C14: 318 | H14: 123 | I14: =C14*H14 -> 39114 | K14: 1 | N14: =K14/$O$1 -> 1 | O14: =R14/$O$1 -> 0 | P14: =SUMIFS('Отчет 01.02'!H:H,'Отчет 01.02'!D:D,"Выручка",'Отчет 01.02'!E:E,B14) -> 0 | Q14: =SUMIFS('Отчет 01.02'!H:H,'Отчет 01.02'!D:D,"Возврат выручки",'Отчет 01.02'!E:E,B14) -> 0 | R14: =P14-Q14 -> 0 | S14: =SUMIFS('Отчет 01.02'!P:P,'Отчет 01.02'!C:C,"Продажи",'Отчет 01.02'!E:E,B14) -> 0 | T14: =SUMIFS('Отчет 01.02'!P:P,'Отчет 01.02'!C:C,"Возвраты",'Отчет 01.02'!E:E,B14) -> 0 | U14: =S14+T14 -> 0 | V14: =U14/$U$24 -> 0 | W14: =R14*H14 -> 0 | X14: =-SUMIFS('Отчет 01.02'!P:P,'Отчет 01.02'!C:C,"Вознаграждение Ozon",'Отчет 01.02'!E:E,B14) -> 0 | Y14: =IF(U14=0,0,X14/U14) -> 0 | Z14: =-SUMIFS('Отчет 01.02'!P:P,'Отчет 01.02'!C:C,"Услуги доставки",'Отчет 01.02'!E:E,B14) -> 0 | AA14: 200 | AD14: =U14*1% -> 0 | AE14: =U14-W14-X14-Z14-AA14-AB14-AC14-AD14 -> -200 | AG14: =IF(R14=0,0,U14/R14) -> 0 | AH14: =H14 -> 123 | AI14: =IF(R14=0,0,X14/R14) -> 0 | AJ14: =IF(P14=0,Z14/1,Z14/P14) -> 0 | AK14: =IF(P14=0,0,AA14/P14) -> 0 | AL14: {=_xlfn.IFS(R14=0,AE14,R14<0,AE14/-R14,R14>0,AE14/R14)} -> -200 | AM14: =IF(AG14=0,0,AL14/AG14) -> 0 | AN14: =IF(AH14=0,0,AL14/AH14) -> -1.6260163 | AP14: =AL14*C14 -> -63600
A15: 3064346642 | B15: flip жел | C15: 616 | H15: 123 | I15: =C15*H15 -> 75768 | K15: 7 | N15: =K15/$O$1 -> 7 | O15: =R15/$O$1 -> 5 | P15: =SUMIFS('Отчет 01.02'!H:H,'Отчет 01.02'!D:D,"Выручка",'Отчет 01.02'!E:E,B15) -> 5 | Q15: =SUMIFS('Отчет 01.02'!H:H,'Отчет 01.02'!D:D,"Возврат выручки",'Отчет 01.02'!E:E,B15) -> 0 | R15: =P15-Q15 -> 5 | S15: =SUMIFS('Отчет 01.02'!P:P,'Отчет 01.02'!C:C,"Продажи",'Отчет 01.02'!E:E,B15) -> 9060 | T15: =SUMIFS('Отчет 01.02'!P:P,'Отчет 01.02'!C:C,"Возвраты",'Отчет 01.02'!E:E,B15) -> 0 | U15: =S15+T15 -> 9060 | V15: =U15/$U$24 -> 0.27772669 | W15: =R15*H15 -> 615 | X15: =-SUMIFS('Отчет 01.02'!P:P,'Отчет 01.02'!C:C,"Вознаграждение Ozon",'Отчет 01.02'!E:E,B15) -> 3895.8 | Y15: =IF(U15=0,0,X15/U15) -> 0.43 | Z15: =-SUMIFS('Отчет 01.02'!P:P,'Отчет 01.02'!C:C,"Услуги доставки",'Отчет 01.02'!E:E,B15) -> 975.17 | AA15: 2081.6234 | AD15: =U15*1% -> 90.6 | AE15: =U15-W15-X15-Z15-AA15-AB15-AC15-AD15 -> 1401.8066 | AG15: =IF(R15=0,0,U15/R15) -> 1812 | AH15: =H15 -> 123 | AI15: =IF(R15=0,0,X15/R15) -> 779.16 | AJ15: =IF(P15=0,Z15/1,Z15/P15) -> 195.034 | AK15: =IF(P15=0,0,AA15/P15) -> 416.32469 | AL15: {=_xlfn.IFS(R15=0,AE15,R15<0,AE15/-R15,R15>0,AE15/R15)} -> 280.36131 | AM15: =IF(AG15=0,0,AL15/AG15) -> 0.15472479 | AN15: =IF(AH15=0,0,AL15/AH15) -> 2.2793602 | AP15: =AL15*C15 -> 172702.57
A16: 3405092287 | B16: flip коричневый | C16: 336 | H16: 117 | I16: =C16*H16 -> 39312 | K16: 0 | N16: =K16/$O$1 -> 0 | O16: =R16/$O$1 -> 0 | P16: =SUMIFS('Отчет 01.02'!H:H,'Отчет 01.02'!D:D,"Выручка",'Отчет 01.02'!E:E,B16) -> 0 | Q16: =SUMIFS('Отчет 01.02'!H:H,'Отчет 01.02'!D:D,"Возврат выручки",'Отчет 01.02'!E:E,B16) -> 0 | R16: =P16-Q16 -> 0 | S16: =SUMIFS('Отчет 01.02'!P:P,'Отчет 01.02'!C:C,"Продажи",'Отчет 01.02'!E:E,B16) -> 0 | T16: =SUMIFS('Отчет 01.02'!P:P,'Отчет 01.02'!C:C,"Возвраты",'Отчет 01.02'!E:E,B16) -> 0 | U16: =S16+T16 -> 0 | V16: =U16/$U$24 -> 0 | W16: =R16*H16 -> 0 | X16: =-SUMIFS('Отчет 01.02'!P:P,'Отчет 01.02'!C:C,"Вознаграждение Ozon",'Отчет 01.02'!E:E,B16) -> 0 | Y16: =IF(U16=0,0,X16/U16) -> 0 | Z16: =-SUMIFS('Отчет 01.02'!P:P,'Отчет 01.02'!C:C,"Услуги доставки",'Отчет 01.02'!E:E,B16) -> 0 | AA16: 279.89307 | AD16: =U16*1% -> 0 | AE16: =U16-W16-X16-Z16-AA16-AB16-AC16-AD16 -> -279.89307 | AG16: =IF(R16=0,0,U16/R16) -> 0 | AH16: =H16 -> 117 | AI16: =IF(R16=0,0,X16/R16) -> 0 | AJ16: =IF(P16=0,Z16/1,Z16/P16) -> 0 | AK16: =IF(P16=0,0,AA16/P16) -> 0 | AL16: {=_xlfn.IFS(R16=0,AE16,R16<0,AE16/-R16,R16>0,AE16/R16)} -> -279.89307 | AM16: =IF(AG16=0,0,AL16/AG16) -> 0 | AN16: =IF(AH16=0,0,AL16/AH16) -> -2.3922485 | AP16: =AL16*C16 -> -94044.072
AG17: =AVERAGEIF(AG3:AG15,"<>0",AG3:AG15) -> 1835.8571 | AH17: =AVERAGEIF(AH3:AH15,"<>0",AH3:AH15) -> 127.26 | AI17: =AVERAGEIF(AI3:AI15,"<>0",AI3:AI15) -> 789.41857 | AJ17: =AVERAGEIF(AJ3:AJ15,"<>0",AJ3:AJ15) -> 151.5845 | AK17: =AVERAGEIF(AK3:AK15,"<>0",AK3:AK15) -> 537.4725 | AL17: =AVERAGEIF(AL3:AL15,"<>0",AL3:AL15) -> 182.24023 | AM17: =AVERAGEIF(AM3:AM15,"<>0",AM3:AM15) -> 0.11946575 | AN17: =AVERAGEIF(AN3:AN15,"<>0",AN3:AN15) -> 1.5585113
A18: Итого очки | C18: =SUM(C3:C16) -> 6249 | E18: 108496 | F18: 597 | G18: 295 | I18: =SUM(I3:I16) -> 783656.25 | K18: =SUM(K3:K16) -> 36 | P18: =SUM(P3:P16) -> 19 | Q18: =SUM(Q3:Q16) -> 1 | R18: =SUM(R3:R16) -> 18 | S18: =SUM(S3:S16) -> 34372 | T18: =SUM(T3:T16) -> -1750 | U18: =SUM(U3:U16) -> 32622 | V18: =SUM(V3:V16) -> 1 | W18: =SUM(W3:W16) -> 2249.22 | X18: =SUM(X3:X16) -> 14027.46 | Y18: =IF(U18=0,0,X18/U18) -> 0.43 | Z18: =SUM(Z3:Z16) -> 3179.52 | AA18: =IFERROR(P18*AA24/P24,0) -> 7557.7 | AB18: =SUM(AB3:AB16) -> 0 | AC18: =SUM(AC3:AC16) -> 0 | AD18: =SUM(AD3:AD16) -> 326.22 | AE18: =SUM(AE3:AE16) -> 5431.8676 | AP18: =SUM(AP3:AP16) -> 400696.62 | AZ18: 18592777
AA19: =SUM(AA3:AA16) -> 7407.7124
AG21: =AVERAGEIF(AG20:AG20,"<>0",AG20:AG20) -> #DIV/0! | AH21: =AVERAGEIF(AH20:AH20,"<>0",AH20:AH20) -> #DIV/0! | AI21: =AVERAGEIF(AI20:AI20,"<>0",AI20:AI20) -> #DIV/0! | AJ21: =AVERAGEIF(AJ20:AJ20,"<>0",AJ20:AJ20) -> #DIV/0! | AK21: =AVERAGEIF(AK20:AK20,"<>0",AK20:AK20) -> #DIV/0! | AL21: =AVERAGEIF(AL20:AL20,"<>0",AL20:AL20) -> #DIV/0! | AM21: =AVERAGEIF(AM20:AM20,"<>0",AM20:AM20) -> #DIV/0! | AN21: =AVERAGEIF(AN20:AN20,"<>0",AN20:AN20) -> #DIV/0!
C22: =SUM(C20:C20) -> 0 | I22: =SUM(I20:I20) -> 0 | K22: =SUM(K20:K20) -> 0 | P22: =SUM(P20:P20) -> 0 | Q22: =SUM(Q20:Q20) -> 0 | R22: =SUM(R20:R20) -> 0 | S22: =SUM(S20:S20) -> 0 | T22: =SUM(T20:T20) -> 0 | U22: =SUM(U20:U20) -> 0 | V22: =SUM(V20:V20) -> 0 | W22: =SUM(W20:W20) -> 0 | X22: =SUM(X20:X20) -> 0 | Y22: =IF(U22=0,0,X22/U22) -> 0 | Z22: =SUM(Z20:Z20) -> 0 | AA22: =IFERROR(P22*AA24/P24,0) -> 0 | AB22: =SUM(AB20:AB20) -> 0 | AC22: =SUM(AC20:AC20) -> 0 | AD22: =SUM(AD20:AD20) -> 0 | AE22: =SUM(AE20:AE20) -> 0 | AP22: =SUM(AP20:AP20) -> 0
AA23: =SUM(AA20:AA20) -> 0
A24: ИТОГО | C24: =C18+C22 -> 6249 | D24: =SUM(D3:D20) -> 0 | E24: =SUM(E3:E20) -> 108496 | F24: =SUM(F3:F20) -> 597 | G24: =SUM(G3:G20) -> 295 | I24: =I18+I22 -> 783656.25 | J24: =J18+J22 -> 0 | K24: =K18+K22 -> 36 | P24: =P18+P22 -> 19 | Q24: =Q18+Q22 -> 1 | R24: =R18-R22 -> 18 | S24: =S18+S22 -> 34372 | T24: =T18+T22 -> -1750 | U24: =U18+U22 -> 32622 | V24: =V18+V22 -> 1 | W24: =W18+W22 -> 2249.22 | X24: =X18+X22 -> 14027.46 | Y24: =X24/U24 -> 0.43 | Z24: =Z18+Z22 -> 3179.52 | AA24: 7557.7 | AC24: =SUM(AC3:AC20) -> 0 | AD24: =AD18+AD22 -> 326.22 | AE24: =AE18+AE22 -> 5431.8676 | AK24: =AA25/P24 -> 397.77368 | AP24: =SUM(AP3:AP20) -> 801393.23
AA25: =AA18+AA22 -> 7557.7
AA26: =AA19+AA23 -> 7407.7124
I29: Себестоимость остатков | K29: Прибыль с остатков | L29: Рентабельность товарных остатков
H31: до 60 дн | I31: =SUMIF(J3:J20,"<60",I3:I20) -> 0 | J31: =I31/I24 -> 0 | K31: =SUMIF(J3:J20,"<60",AP3:AP20) -> 0 | L31: =K31/I31 -> #DIV/0!
H32: 60-120 дн | I32: =I24-I33-I31 -> 783656.25 | J32: =I32/I24 -> 1 | K32: =AP24-K31-K33 -> 801393.23 | L32: =K32/I32 -> 1.0226336
H33: > 120 дн | I33: =SUMIF(J3:J20,">120",I3:I20) -> 0 | J33: =I33/I24 -> 0 | K33: =SUMIF(J3:J20,">120",AP3:AP20) -> 0 | L33: =K33/I33 -> #DIV/0!
H35: Если товар на сайте менее 30 дней - оборачиваемость 0

Sheet ЯНВАРЬ
B1: 01-31.01 | AG1: на 1 единицу проданного товара
B2: Артикул поставщика | C2: Остаток на 01.02 | D2: В пути до клиента | E2: В пути от клиента | F2: Итого по складам ВБ | G2: Остаток на нашем складе на 02.09 | H2: Себетоимость на 1 ед на 29.09.25 | I2: Себестоимость остатков | J2: Оборачиваемость, дн | K2: Заказы, шт 31 день | L2: Средняя цена, руб (столбец 32, AG) | M2: % выкупа за 7 дней (столбец 23, X) | N2: Скорость заказов | O2: Скорость продаж | P2: Кол-во ПРОДАЖИ | Q2: Кол-во ВОЗВРАТЫ | R2: Кол-во ПРОДАЖИ-ВОЗВРАТЫ | S2: Выручка ПРОДАЖИ | T2: Выручка ВОЗВРАТЫ | U2: Выручка с учетом согласованной скидки ПРОДАЖИ - ВОЗВРАТЫ | V2: Доля выручки, % от общего объема | W2: Себестоимость продаж | X2: Комиссия, руб | Y2: Комиссия, % | Z2: Логистика | AA2: Реклама | AB2: Хранение | AC2: Штрафы | AD2: Налог 1% | AE2: Прибыль | AG2: Выручка на 1 ед (средняя цена продажи со скидкой) | AH2: Себестоимость на 1 ед | AI2: Комиссия на 1 ед | AJ2: Логистика на 1 ед | AK2: Реклама на 1 ед | AL2: Прибыль на 1 ед | AM2: Маржинальность, % | AN2: Рентабельность, % | AP2: Прибыль с остатков
A3: 2676784153 | B3: черные с железкой классика | C3: ='Юнит 26-31.01'!C3 -> 0 | H3: 142.98 | I3: =C3*H3 -> 0 | K3: ='Юнит 01-04.01'!K3+'Юнит 05-11.01'!K3+'Юнит 12-18.01'!K3+'Юнит 19-25.01'!K3+'Юнит 26-31.01'!K3 -> 21 | N3: =K3/31 -> 0.67741935 | O3: =R3/31 -> 0.48387097 | P3: ='Юнит 01-04.01'!P3+'Юнит 05-11.01'!P3+'Юнит 12-18.01'!P3+'Юнит 19-25.01'!P3+'Юнит 26-31.01'!P3 -> 15 | Q3: ='Юнит 01-04.01'!Q3+'Юнит 05-11.01'!Q3+'Юнит 12-18.01'!Q3+'Юнит 19-25.01'!Q3+'Юнит 26-31.01'!Q3 -> 0 | R3: =P3-Q3 -> 15 | S3: ='Юнит 01-04.01'!S3+'Юнит 05-11.01'!S3+'Юнит 12-18.01'!S3+'Юнит 19-25.01'!S3+'Юнит 26-31.01'!S3 -> 24142 | T3: ='Юнит 01-04.01'!T3+'Юнит 05-11.01'!T3+'Юнит 12-18.01'!T3+'Юнит 19-25.01'!T3+'Юнит 26-31.01'!T3 -> 0 | U3: =S3+T3 -> 24142 | V3: =U3/$U$24 -> 0.026501131 | W3: =R3*H3 -> 2144.7 | X3: ='Юнит 01-04.01'!X3+'Юнит 05-11.01'!X3+'Юнит 12-18.01'!X3+'Юнит 19-25.01'!X3+'Юнит 26-31.01'!X3 -> 10381.06 | Y3: =IF(U3=0,0,X3/U3) -> 0.43 | Z3: ='Юнит 01-04.01'!Z3+'Юнит 05-11.01'!Z3+'Юнит 12-18.01'!Z3+'Юнит 19-25.01'!Z3+'Юнит 26-31.01'!Z3 -> 2557.2 | AA3: ='Юнит 01-04.01'!AA3+'Юнит 05-11.01'!AA3+'Юнит 12-18.01'!AA3+'Юнит 19-25.01'!AA3+'Юнит 26-31.01'!AA3 -> 2328.6901 | AD3: =U3*1% -> 241.42 | AE3: =U3-W3-X3-Z3-AA3-AB3-AC3-AD3 -> 6488.9299 | AG3: =IF(R3=0,0,U3/R3) -> 1609.4667 | AH3: =H3 -> 142.98 | AI3: =IF(R3=0,0,X3/R3) -> 692.07067 | AJ3: =IF(P3=0,Z3/1,Z3/P3) -> 170.48 | AK3: =IF(P3=0,0,AA3/P3) -> 155.246 | AL3: =_xlfn.IFS(R3=0,AE3,R3<0,AE3/-R3,R3>0,AE3/R3) -> 432.59533 | AM3: =IF(AG3=0,0,AL3/AG3) -> 0.26878179 | AN3: =IF(AH3=0,0,AL3/AH3) -> 3.0255653 | AP3: =AL3*C3 -> 0
A4: 2676784638 | B4: qs черные | C4: ='Юнит 26-31.01'!C4 -> 0 | H4: 123.09 | I4: =C4*H4 -> 0 | K4: ='Юнит 01-04.01'!K4+'Юнит 05-11.01'!K4+'Юнит 12-18.01'!K4+'Юнит 19-25.01'!K4+'Юнит 26-31.01'!K4 -> 27 | N4: =K4/31 -> 0.87096774 | O4: =R4/31 -> 0.61290323 | P4: ='Юнит 01-04.01'!P4+'Юнит 05-11.01'!P4+'Юнит 12-18.01'!P4+'Юнит 19-25.01'!P4+'Юнит 26-31.01'!P4 -> 19 | Q4: ='Юнит 01-04.01'!Q4+'Юнит 05-11.01'!Q4+'Юнит 12-18.01'!Q4+'Юнит 19-25.01'!Q4+'Юнит 26-31.01'!Q4 -> 0 | R4: =P4-Q4 -> 19 | S4: ='Юнит 01-04.01'!S4+'Юнит 05-11.01'!S4+'Юнит 12-18.01'!S4+'Юнит 19-25.01'!S4+'Юнит 26-31.01'!S4 -> 32750 | T4: ='Юнит 01-04.01'!T4+'Юнит 05-11.01'!T4+'Юнит 12-18.01'!T4+'Юнит 19-25.01'!T4+'Юнит 26-31.01'!T4 -> 0 | U4: =S4+T4 -> 32750 | V4: =U4/$U$24 -> 0.035950295 | W4: =R4*H4 -> 2338.71 | X4: ='Юнит 01-04.01'!X4+'Юнит 05-11.01'!X4+'Юнит 12-18.01'!X4+'Юнит 19-25.01'!X4+'Юнит 26-31.01'!X4 -> 14082.5 | Y4: =IF(U4=0,0,X4/U4) -> 0.43 | Z4: ='Юнит 01-04.01'!Z4+'Юнит 05-11.01'!Z4+'Юнит 12-18.01'!Z4+'Юнит 19-25.01'!Z4+'Юнит 26-31.01'!Z4 -> 2801.07 | AA4: ='Юнит 01-04.01'!AA4+'Юнит 05-11.01'!AA4+'Юнит 12-18.01'!AA4+'Юнит 19-25.01'!AA4+'Юнит 26-31.01'!AA4 -> 2785.2683 | AD4: =U4*1% -> 327.5 | AE4: =U4-W4-X4-Z4-AA4-AB4-AC4-AD4 -> 10414.952 | AG4: =IF(R4=0,0,U4/R4) -> 1723.6842 | AH4: =H4 -> 123.09 | AI4: =IF(R4=0,0,X4/R4) -> 741.18421 | AJ4: =IF(P4=0,Z4/1,Z4/P4) -> 147.42474 | AK4: =IF(P4=0,0,AA4/P4) -> 146.59307 | AL4: {=_xlfn.IFS(R4=0,AE4,R4<0,AE4/-R4,R4>0,AE4/R4)} -> 548.15535 | AM4: =IF(AG4=0,0,AL4/AG4) -> 0.31801379 | AN4: =IF(AH4=0,0,AL4/AH4) -> 4.4532891 | AP4: =AL4*C4 -> 0
A5: 2676784504 | B5: qs синие | C5: ='Юнит 26-31.01'!C5 -> 0 | H5: 123.09 | I5: =C5*H5 -> 0 | K5: ='Юнит 01-04.01'!K5+'Юнит 05-11.01'!K5+'Юнит 12-18.01'!K5+'Юнит 19-25.01'!K5+'Юнит 26-31.01'!K5 -> 12 | N5: =K5/31 -> 0.38709677 | O5: =R5/31 -> 0.29032258 | P5: ='Юнит 01-04.01'!P5+'Юнит 05-11.01'!P5+'Юнит 12-18.01'!P5+'Юнит 19-25.01'!P5+'Юнит 26-31.01'!P5 -> 9 | Q5: ='Юнит 01-04.01'!Q5+'Юнит 05-11.01'!Q5+'Юнит 12-18.01'!Q5+'Юнит 19-25.01'!Q5+'Юнит 26-31.01'!Q5 -> 0 | R5: =P5-Q5 -> 9 | S5: ='Юнит 01-04.01'!S5+'Юнит 05-11.01'!S5+'Юнит 12-18.01'!S5+'Юнит 19-25.01'!S5+'Юнит 26-31.01'!S5 -> 15350 | T5: ='Юнит 01-04.01'!T5+'Юнит 05-11.01'!T5+'Юнит 12-18.01'!T5+'Юнит 19-25.01'!T5+'Юнит 26-31.01'!T5 -> 0 | U5: =S5+T5 -> 15350 | V5: =U5/$U$24 -> 0.016849986 | W5: =R5*H5 -> 1107.81 | X5: ='Юнит 01-04.01'!X5+'Юнит 05-11.01'!X5+'Юнит 12-18.01'!X5+'Юнит 19-25.01'!X5+'Юнит 26-31.01'!X5 -> 6600.5 | Y5: =IF(U5=0,0,X5/U5) -> 0.43 | Z5: ='Юнит 01-04.01'!Z5+'Юнит 05-11.01'!Z5+'Юнит 12-18.01'!Z5+'Юнит 19-25.01'!Z5+'Юнит 26-31.01'!Z5 -> 1336.49 | AA5: ='Юнит 01-04.01'!AA5+'Юнит 05-11.01'!AA5+'Юнит 12-18.01'!AA5+'Юнит 19-25.01'!AA5+'Юнит 26-31.01'!AA5 -> 1523.2567 | AD5: =U5*1% -> 153.5 | AE5: =U5-W5-X5-Z5-AA5-AB5-AC5-AD5 -> 4628.4433 | AG5: =IF(R5=0,0,U5/R5) -> 1705.5556 | AH5: =H5 -> 123.09 | AI5: =IF(R5=0,0,X5/R5) -> 733.38889 | AJ5: =IF(P5=0,Z5/1,Z5/P5) -> 148.49889 | AK5: =IF(P5=0,0,AA5/P5) -> 169.25075 | AL5: {=_xlfn.IFS(R5=0,AE5,R5<0,AE5/-R5,R5>0,AE5/R5)} -> 514.27148 | AM5: =IF(AG5=0,0,AL5/AG5) -> 0.30152725 | AN5: =IF(AH5=0,0,AL5/AH5) -> 4.1780118 | AP5: =AL5*C5 -> 0
A6: 2676784514 | B6: qs желтые | C6: ='Юнит 26-31.01'!C6 -> 0 | H6: 123.09 | I6: =C6*H6 -> 0 | K6: ='Юнит 01-04.01'!K6+'Юнит 05-11.01'!K6+'Юнит 12-18.01'!K6+'Юнит 19-25.01'!K6+'Юнит 26-31.01'!K6 -> 107 | N6: =K6/31 -> 3.4516129 | O6: =R6/31 -> 2.6451613 | P6: ='Юнит 01-04.01'!P6+'Юнит 05-11.01'!P6+'Юнит 12-18.01'!P6+'Юнит 19-25.01'!P6+'Юнит 26-31.01'!P6 -> 86 | Q6: ='Юнит 01-04.01'!Q6+'Юнит 05-11.01'!Q6+'Юнит 12-18.01'!Q6+'Юнит 19-25.01'!Q6+'Юнит 26-31.01'!Q6 -> 4 | R6: =P6-Q6 -> 82 | S6: ='Юнит 01-04.01'!S6+'Юнит 05-11.01'!S6+'Юнит 12-18.01'!S6+'Юнит 19-25.01'!S6+'Юнит 26-31.01'!S6 -> 143450 | T6: ='Юнит 01-04.01'!T6+'Юнит 05-11.01'!T6+'Юнит 12-18.01'!T6+'Юнит 19-25.01'!T6+'Юнит 26-31.01'!T6 -> -6400 | U6: =S6+T6 -> 137050 | V6: =U6/$U$24 -> 0.15044238 | W6: =R6*H6 -> 10093.38 | X6: ='Юнит 01-04.01'!X6+'Юнит 05-11.01'!X6+'Юнит 12-18.01'!X6+'Юнит 19-25.01'!X6+'Юнит 26-31.01'!X6 -> 58931.5 | Y6: =IF(U6=0,0,X6/U6) -> 0.43 | Z6: ='Юнит 01-04.01'!Z6+'Юнит 05-11.01'!Z6+'Юнит 12-18.01'!Z6+'Юнит 19-25.01'!Z6+'Юнит 26-31.01'!Z6 -> 13586.76 | AA6: ='Юнит 01-04.01'!AA6+'Юнит 05-11.01'!AA6+'Юнит 12-18.01'!AA6+'Юнит 19-25.01'!AA6+'Юнит 26-31.01'!AA6 -> 32153.359 | AD6: =U6*1% -> 1370.5 | AE6: =U6-W6-X6-Z6-AA6-AB6-AC6-AD6 -> 20914.501 | AG6: =IF(R6=0,0,U6/R6) -> 1671.3415 | AH6: =H6 -> 123.09 | AI6: =IF(R6=0,0,X6/R6) -> 718.67683 | AJ6: =IF(P6=0,Z6/1,Z6/P6) -> 157.98558 | AK6: =IF(P6=0,0,AA6/P6) -> 373.87627 | AL6: {=_xlfn.IFS(R6=0,AE6,R6<0,AE6/-R6,R6>0,AE6/R6)} -> 255.05489 | AM6: =IF(AG6=0,0,AL6/AG6) -> 0.1526049 | AN6: =IF(AH6=0,0,AL6/AH6) -> 2.0721008 | AP6: =AL6*C6 -> 0
A7: 2676784181 | B7: qs коричневые | C7: ='Юнит 26-31.01'!C7 -> 0 | H7: 117.24 | I7: =C7*H7 -> 0 | K7: ='Юнит 01-04.01'!K7+'Юнит 05-11.01'!K7+'Юнит 12-18.01'!K7+'Юнит 19-25.01'!K7+'Юнит 26-31.01'!K7 -> 87 | N7: =K7/31 -> 2.8064516 | O7: =R7/31 -> 1.4516129 | P7: ='Юнит 01-04.01'!P7+'Юнит 05-11.01'!P7+'Юнит 12-18.01'!P7+'Юнит 19-25.01'!P7+'Юнит 26-31.01'!P7 -> 46 | Q7: ='Юнит 01-04.01'!Q7+'Юнит 05-11.01'!Q7+'Юнит 12-18.01'!Q7+'Юнит 19-25.01'!Q7+'Юнит 26-31.01'!Q7 -> 1 | R7: =P7-Q7 -> 45 | S7: ='Юнит 01-04.01'!S7+'Юнит 05-11.01'!S7+'Юнит 12-18.01'!S7+'Юнит 19-25.01'!S7+'Юнит 26-31.01'!S7 -> 78225 | T7: ='Юнит 01-04.01'!T7+'Юнит 05-11.01'!T7+'Юнит 12-18.01'!T7+'Юнит 19-25.01'!T7+'Юнит 26-31.01'!T7 -> -1750 | U7: =S7+T7 -> 76475 | V7: =U7/$U$24 -> 0.083948056 | W7: =R7*H7 -> 5275.8 | X7: ='Юнит 01-04.01'!X7+'Юнит 05-11.01'!X7+'Юнит 12-18.01'!X7+'Юнит 19-25.01'!X7+'Юнит 26-31.01'!X7 -> 32884.25 | Y7: =IF(U7=0,0,X7/U7) -> 0.43 | Z7: ='Юнит 01-04.01'!Z7+'Юнит 05-11.01'!Z7+'Юнит 12-18.01'!Z7+'Юнит 19-25.01'!Z7+'Юнит 26-31.01'!Z7 -> 7888.72 | AA7: ='Юнит 01-04.01'!AA7+'Юнит 05-11.01'!AA7+'Юнит 12-18.01'!AA7+'Юнит 19-25.01'!AA7+'Юнит 26-31.01'!AA7 -> 20344.45 | AD7: =U7*1% -> 764.75 | AE7: =U7-W7-X7-Z7-AA7-AB7-AC7-AD7 -> 9317.0299 | AG7: =IF(R7=0,0,U7/R7) -> 1699.4444 | AH7: =H7 -> 117.24 | AI7: =IF(R7=0,0,X7/R7) -> 730.76111 | AJ7: =IF(P7=0,Z7/1,Z7/P7) -> 171.49391 | AK7: =IF(P7=0,0,AA7/P7) -> 442.27065 | AL7: {=_xlfn.IFS(R7=0,AE7,R7<0,AE7/-R7,R7>0,AE7/R7)} -> 207.04511 | AM7: =IF(AG7=0,0,AL7/AG7) -> 0.12183105 | AN7: =IF(AH7=0,0,AL7/AH7) -> 1.7659938 | AP7: =AL7*C7 -> 0
A8: 2676783005 | B8: MR8854 C2 | C8: ='Юнит 26-31.01'!C8 -> 0 | H8: 169.89 | I8: =C8*H8 -> 0 | K8: ='Юнит 01-04.01'!K8+'Юнит 05-11.01'!K8+'Юнит 12-18.01'!K8+'Юнит 19-25.01'!K8+'Юнит 26-31.01'!K8 -> 50 | N8: =K8/31 -> 1.6129032 | O8: =R8/31 -> 1 | P8: ='Юнит 01-04.01'!P8+'Юнит 05-11.01'!P8+'Юнит 12-18.01'!P8+'Юнит 19-25.01'!P8+'Юнит 26-31.01'!P8 -> 32 | Q8: ='Юнит 01-04.01'!Q8+'Юнит 05-11.01'!Q8+'Юнит 12-18.01'!Q8+'Юнит 19-25.01'!Q8+'Юнит 26-31.01'!Q8 -> 1 | R8: =P8-Q8 -> 31 | S8: ='Юнит 01-04.01'!S8+'Юнит 05-11.01'!S8+'Юнит 12-18.01'!S8+'Юнит 19-25.01'!S8+'Юнит 26-31.01'!S8 -> 47780 | T8: ='Юнит 01-04.01'!T8+'Юнит 05-11.01'!T8+'Юнит 12-18.01'!T8+'Юнит 19-25.01'!T8+'Юнит 26-31.01'!T8 -> -1202 | U8: =S8+T8 -> 46578 | V8: =U8/$U$24 -> 0.051129553 | W8: =R8*H8 -> 5266.59 | X8: ='Юнит 01-04.01'!X8+'Юнит 05-11.01'!X8+'Юнит 12-18.01'!X8+'Юнит 19-25.01'!X8+'Юнит 26-31.01'!X8 -> 20028.54 | Y8: =IF(U8=0,0,X8/U8) -> 0.43 | Z8: ='Юнит 01-04.01'!Z8+'Юнит 05-11.01'!Z8+'Юнит 12-18.01'!Z8+'Юнит 19-25.01'!Z8+'Юнит 26-31.01'!Z8 -> 4902.7 | AA8: ='Юнит 01-04.01'!AA8+'Юнит 05-11.01'!AA8+'Юнит 12-18.01'!AA8+'Юнит 19-25.01'!AA8+'Юнит 26-31.01'!AA8 -> 11861.792 | AD8: =U8*1% -> 465.78 | AE8: =U8-W8-X8-Z8-AA8-AB8-AC8-AD8 -> 4052.5984 | AG8: =IF(R8=0,0,U8/R8) -> 1502.5161 | AH8: =H8 -> 169.89 | AI8: =IF(R8=0,0,X8/R8) -> 646.08194 | AJ8: =IF(P8=0,Z8/1,Z8/P8) -> 153.20937 | AK8: =IF(P8=0,0,AA8/P8) -> 370.68099 | AL8: {=_xlfn.IFS(R8=0,AE8,R8<0,AE8/-R8,R8>0,AE8/R8)} -> 130.72898 | AM8: =IF(AG8=0,0,AL8/AG8) -> 0.087006707 | AN8: =IF(AH8=0,0,AL8/AH8) -> 0.76949191 | AP8: =AL8*C8 -> 0
A9: 3405092860 | B9: th черн | C9: ='Юнит 26-31.01'!C9 -> 0 | H9: 123 | I9: =C9*H9 -> 0 | K9: ='Юнит 01-04.01'!K9+'Юнит 05-11.01'!K9+'Юнит 12-18.01'!K9+'Юнит 19-25.01'!K9+'Юнит 26-31.01'!K9 -> 4 | N9: =K9/31 -> 0.12903226 | O9: =R9/31 -> 0.032258065 | P9: ='Юнит 01-04.01'!P9+'Юнит 05-11.01'!P9+'Юнит 12-18.01'!P9+'Юнит 19-25.01'!P9+'Юнит 26-31.01'!P9 -> 1 | Q9: ='Юнит 01-04.01'!Q9+'Юнит 05-11.01'!Q9+'Юнит 12-18.01'!Q9+'Юнит 19-25.01'!Q9+'Юнит 26-31.01'!Q9 -> 0 | R9: =P9-Q9 -> 1 | S9: ='Юнит 01-04.01'!S9+'Юнит 05-11.01'!S9+'Юнит 12-18.01'!S9+'Юнит 19-25.01'!S9+'Юнит 26-31.01'!S9 -> 2000 | T9: ='Юнит 01-04.01'!T9+'Юнит 05-11.01'!T9+'Юнит 12-18.01'!T9+'Юнит 19-25.01'!T9+'Юнит 26-31.01'!T9 -> 0 | U9: =S9+T9 -> 2000 | V9: =U9/$U$24 -> 0.0021954379 | W9: =R9*H9 -> 123 | X9: ='Юнит 01-04.01'!X9+'Юнит 05-11.01'!X9+'Юнит 12-18.01'!X9+'Юнит 19-25.01'!X9+'Юнит 26-31.01'!X9 -> 860 | Y9: =IF(U9=0,0,X9/U9) -> 0.43 | Z9: ='Юнит 01-04.01'!Z9+'Юнит 05-11.01'!Z9+'Юнит 12-18.01'!Z9+'Юнит 19-25.01'!Z9+'Юнит 26-31.01'!Z9 -> 155.81 | AA9: ='Юнит 01-04.01'!AA9+'Юнит 05-11.01'!AA9+'Юнит 12-18.01'!AA9+'Юнит 19-25.01'!AA9+'Юнит 26-31.01'!AA9 -> 556.81946 | AD9: =U9*1% -> 20 | AE9: =U9-W9-X9-Z9-AA9-AB9-AC9-AD9 -> 284.37054 | AG9: =IF(R9=0,0,U9/R9) -> 2000 | AH9: =H9 -> 123 | AI9: =IF(R9=0,0,X9/R9) -> 860 | AJ9: =IF(P9=0,Z9/1,Z9/P9) -> 155.81 | AK9: =IF(P9=0,0,AA9/P9) -> 556.81946 | AL9: {=_xlfn.IFS(R9=0,AE9,R9<0,AE9/-R9,R9>0,AE9/R9)} -> 284.37054 | AM9: =IF(AG9=0,0,AL9/AG9) -> 0.14218527 | AN9: =IF(AH9=0,0,AL9/AH9) -> 2.3119556 | AP9: =AL9*C9 -> 0
A10: 3405092836 | B10: th син | C10: ='Юнит 26-31.01'!C10 -> 0 | H10: 123 | I10: =C10*H10 -> 0 | K10: ='Юнит 01-04.01'!K10+'Юнит 05-11.01'!K10+'Юнит 12-18.01'!K10+'Юнит 19-25.01'!K10+'Юнит 26-31.01'!K10 -> 6 | N10: =K10/31 -> 0.19354839 | O10: =R10/31 -> 0 | P10: ='Юнит 01-04.01'!P10+'Юнит 05-11.01'!P10+'Юнит 12-18.01'!P10+'Юнит 19-25.01'!P10+'Юнит 26-31.01'!P10 -> 0 | Q10: ='Юнит 01-04.01'!Q10+'Юнит 05-11.01'!Q10+'Юнит 12-18.01'!Q10+'Юнит 19-25.01'!Q10+'Юнит 26-31.01'!Q10 -> 0 | R10: =P10-Q10 -> 0 | S10: ='Юнит 01-04.01'!S10+'Юнит 05-11.01'!S10+'Юнит 12-18.01'!S10+'Юнит 19-25.01'!S10+'Юнит 26-31.01'!S10 -> 0 | T10: ='Юнит 01-04.01'!T10+'Юнит 05-11.01'!T10+'Юнит 12-18.01'!T10+'Юнит 19-25.01'!T10+'Юнит 26-31.01'!T10 -> 0 | U10: =S10+T10 -> 0 | V10: =U10/$U$24 -> 0 | W10: =R10*H10 -> 0 | X10: ='Юнит 01-04.01'!X10+'Юнит 05-11.01'!X10+'Юнит 12-18.01'!X10+'Юнит 19-25.01'!X10+'Юнит 26-31.01'!X10 -> 0 | Y10: =IF(U10=0,0,X10/U10) -> 0 | Z10: ='Юнит 01-04.01'!Z10+'Юнит 05-11.01'!Z10+'Юнит 12-18.01'!Z10+'Юнит 19-25.01'!Z10+'Юнит 26-31.01'!Z10 -> 0 | AA10: ='Юнит 01-04.01'!AA10+'Юнит 05-11.01'!AA10+'Юнит 12-18.01'!AA10+'Юнит 19-25.01'!AA10+'Юнит 26-31.01'!AA10 -> 1517.4339 | AD10: =U10*1% -> 0 | AE10: =U10-W10-X10-Z10-AA10-AB10-AC10-AD10 -> -1517.4339 | AG10: =IF(R10=0,0,U10/R10) -> 0 | AH10: =H10 -> 123 | AI10: =IF(R10=0,0,X10/R10) -> 0 | AJ10: =IF(P10=0,Z10/1,Z10/P10) -> 0 | AK10: =IF(P10=0,0,AA10/P10) -> 0 | AL10: {=_xlfn.IFS(R10=0,AE10,R10<0,AE10/-R10,R10>0,AE10/R10)} -> -1517.4339 | AM10: =IF(AG10=0,0,AL10/AG10) -> 0 | AN10: =IF(AH10=0,0,AL10/AH10) -> -12.336861 | AP10: =AL10*C10 -> 0
A11: 3064346962 | B11: th желт | C11: ='Юнит 26-31.01'!C11 -> 0 | H11: 123 | I11: =C11*H11 -> 0 | K11: ='Юнит 01-04.01'!K11+'Юнит 05-11.01'!K11+'Юнит 12-18.01'!K11+'Юнит 19-25.01'!K11+'Юнит 26-31.01'!K11 -> 241 | N11: =K11/31 -> 7.7741935 | O11: =R11/31 -> 5.3225806 | P11: ='Юнит 01-04.01'!P11+'Юнит 05-11.01'!P11+'Юнит 12-18.01'!P11+'Юнит 19-25.01'!P11+'Юнит 26-31.01'!P11 -> 169 | Q11: ='Юнит 01-04.01'!Q11+'Юнит 05-11.01'!Q11+'Юнит 12-18.01'!Q11+'Юнит 19-25.01'!Q11+'Юнит 26-31.01'!Q11 -> 4 | R11: =P11-Q11 -> 165 | S11: ='Юнит 01-04.01'!S11+'Юнит 05-11.01'!S11+'Юнит 12-18.01'!S11+'Юнит 19-25.01'!S11+'Юнит 26-31.01'!S11 -> 288115 | T11: ='Юнит 01-04.01'!T11+'Юнит 05-11.01'!T11+'Юнит 12-18.01'!T11+'Юнит 19-25.01'!T11+'Юнит 26-31.01'!T11 -> -6890 | U11: =S11+T11 -> 281225 | V11: =U11/$U$24 -> 0.30870601 | W11: =R11*H11 -> 20295 | X11: ='Юнит 01-04.01'!X11+'Юнит 05-11.01'!X11+'Юнит 12-18.01'!X11+'Юнит 19-25.01'!X11+'Юнит 26-31.01'!X11 -> 120926.75 | Y11: =IF(U11=0,0,X11/U11) -> 0.43 | Z11: ='Юнит 01-04.01'!Z11+'Юнит 05-11.01'!Z11+'Юнит 12-18.01'!Z11+'Юнит 19-25.01'!Z11+'Юнит 26-31.01'!Z11 -> 30216.55 | AA11: ='Юнит 01-04.01'!AA11+'Юнит 05-11.01'!AA11+'Юнит 12-18.01'!AA11+'Юнит 19-25.01'!AA11+'Юнит 26-31.01'!AA11 -> 79164.206 | AD11: =U11*1% -> 2812.25 | AE11: =U11-W11-X11-Z11-AA11-AB11-AC11-AD11 -> 27810.244 | AG11: =IF(R11=0,0,U11/R11) -> 1704.3939 | AH11: =H11 -> 123 | AI11: =IF(R11=0,0,X11/R11) -> 732.88939 | AJ11: =IF(P11=0,Z11/1,Z11/P11) -> 178.79615 | AK11: =IF(P11=0,0,AA11/P11) -> 468.42725 | AL11: {=_xlfn.IFS(R11=0,AE11,R11<0,AE11/-R11,R11>0,AE11/R11)} -> 168.54693 | AM11: =IF(AG11=0,0,AL11/AG11) -> 0.098889658 | AN11: =IF(AH11=0,0,AL11/AH11) -> 1.3703003 | AP11: =AL11*C11 -> 0
A12: 3405092873 | B12: th коричн | C12: ='Юнит 26-31.01'!C12 -> 0 | H12: 117 | I12: =C12*H12 -> 0 | K12: ='Юнит 01-04.01'!K12+'Юнит 05-11.01'!K12+'Юнит 12-18.01'!K12+'Юнит 19-25.01'!K12+'Юнит 26-31.01'!K12 -> 5 | N12: =K12/31 -> 0.16129032 | O12: =R12/31 -> 0 | P12: ='Юнит 01-04.01'!P12+'Юнит 05-11.01'!P12+'Юнит 12-18.01'!P12+'Юнит 19-25.01'!P12+'Юнит 26-31.01'!P12 -> 0 | Q12: ='Юнит 01-04.01'!Q12+'Юнит 05-11.01'!Q12+'Юнит 12-18.01'!Q12+'Юнит 19-25.01'!Q12+'Юнит 26-31.01'!Q12 -> 0 | R12: =P12-Q12 -> 0 | S12: ='Юнит 01-04.01'!S12+'Юнит 05-11.01'!S12+'Юнит 12-18.01'!S12+'Юнит 19-25.01'!S12+'Юнит 26-31.01'!S12 -> 0 | T12: ='Юнит 01-04.01'!T12+'Юнит 05-11.01'!T12+'Юнит 12-18.01'!T12+'Юнит 19-25.01'!T12+'Юнит 26-31.01'!T12 -> 0 | U12: =S12+T12 -> 0 | V12: =U12/$U$24 -> 0 | W12: =R12*H12 -> 0 | X12: ='Юнит 01-04.01'!X12+'Юнит 05-11.01'!X12+'Юнит 12-18.01'!X12+'Юнит 19-25.01'!X12+'Юнит 26-31.01'!X12 -> 0 | Y12: =IF(U12=0,0,X12/U12) -> 0 | Z12: ='Юнит 01-04.01'!Z12+'Юнит 05-11.01'!Z12+'Юнит 12-18.01'!Z12+'Юнит 19-25.01'!Z12+'Юнит 26-31.01'!Z12 -> 0 | AA12: ='Юнит 01-04.01'!AA12+'Юнит 05-11.01'!AA12+'Юнит 12-18.01'!AA12+'Юнит 19-25.01'!AA12+'Юнит 26-31.01'!AA12 -> 555.84386 | AD12: =U12*1% -> 0 | AE12: =U12-W12-X12-Z12-AA12-AB12-AC12-AD12 -> -555.84386 | AG12: =IF(R12=0,0,U12/R12) -> 0 | AH12: =H12 -> 117 | AI12: =IF(R12=0,0,X12/R12) -> 0 | AJ12: =IF(P12=0,Z12/1,Z12/P12) -> 0 | AK12: =IF(P12=0,0,AA12/P12) -> 0 | AL12: {=_xlfn.IFS(R12=0,AE12,R12<0,AE12/-R12,R12>0,AE12/R12)} -> -555.84386 | AM12: =IF(AG12=0,0,AL12/AG12) -> 0 | AN12: =IF(AH12=0,0,AL12/AH12) -> -4.7508022 | AP12: =AL12*C12 -> 0
A13: 3405092993 | B13: flip черный | C13: ='Юнит 26-31.01'!C13 -> 0 | H13: 123 | I13: =C13*H13 -> 0 | K13: ='Юнит 01-04.01'!K13+'Юнит 05-11.01'!K13+'Юнит 12-18.01'!K13+'Юнит 19-25.01'!K13+'Юнит 26-31.01'!K13 -> 2 | N13: =K13/31 -> 0.064516129 | O13: =R13/31 -> 0.032258065 | P13: ='Юнит 01-04.01'!P13+'Юнит 05-11.01'!P13+'Юнит 12-18.01'!P13+'Юнит 19-25.01'!P13+'Юнит 26-31.01'!P13 -> 1 | Q13: ='Юнит 01-04.01'!Q13+'Юнит 05-11.01'!Q13+'Юнит 12-18.01'!Q13+'Юнит 19-25.01'!Q13+'Юнит 26-31.01'!Q13 -> 0 | R13: =P13-Q13 -> 1 | S13: ='Юнит 01-04.01'!S13+'Юнит 05-11.01'!S13+'Юнит 12-18.01'!S13+'Юнит 19-25.01'!S13+'Юнит 26-31.01'!S13 -> 2000 | T13: ='Юнит 01-04.01'!T13+'Юнит 05-11.01'!T13+'Юнит 12-18.01'!T13+'Юнит 19-25.01'!T13+'Юнит 26-31.01'!T13 -> 0 | U13: =S13+T13 -> 2000 | V13: =U13/$U$24 -> 0.0021954379 | W13: =R13*H13 -> 123 | X13: ='Юнит 01-04.01'!X13+'Юнит 05-11.01'!X13+'Юнит 12-18.01'!X13+'Юнит 19-25.01'!X13+'Юнит 26-31.01'!X13 -> 860 | Y13: =IF(U13=0,0,X13/U13) -> 0.43 | Z13: ='Юнит 01-04.01'!Z13+'Юнит 05-11.01'!Z13+'Юнит 12-18.01'!Z13+'Юнит 19-25.01'!Z13+'Юнит 26-31.01'!Z13 -> 155.81 | AA13: ='Юнит 01-04.01'!AA13+'Юнит 05-11.01'!AA13+'Юнит 12-18.01'!AA13+'Юнит 19-25.01'!AA13+'Юнит 26-31.01'!AA13 -> 633.38405 | AD13: =U13*1% -> 20 | AE13: =U13-W13-X13-Z13-AA13-AB13-AC13-AD13 -> 207.80595 | AG13: =IF(R13=0,0,U13/R13) -> 2000 | AH13: =H13 -> 123 | AI13: =IF(R13=0,0,X13/R13) -> 860 | AJ13: =IF(P13=0,Z13/1,Z13/P13) -> 155.81 | AK13: =IF(P13=0,0,AA13/P13) -> 633.38405 | AL13: {=_xlfn.IFS(R13=0,AE13,R13<0,AE13/-R13,R13>0,AE13/R13)} -> 207.80595 | AM13: =IF(AG13=0,0,AL13/AG13) -> 0.10390297 | AN13: =IF(AH13=0,0,AL13/AH13) -> 1.6894793 | AP13: =AL13*C13 -> 0
A14: 3405092868 | B14: flip синий | C14: ='Юнит 26-31.01'!C14 -> 0 | H14: 123 | I14: =C14*H14 -> 0 | K14: ='Юнит 01-04.01'!K14+'Юнит 05-11.01'!K14+'Юнит 12-18.01'!K14+'Юнит 19-25.01'!K14+'Юнит 26-31.01'!K14 -> 0 | N14: =K14/31 -> 0 | O14: =R14/31 -> 0 | P14: ='Юнит 01-04.01'!P14+'Юнит 05-11.01'!P14+'Юнит 12-18.01'!P14+'Юнит 19-25.01'!P14+'Юнит 26-31.01'!P14 -> 0 | Q14: ='Юнит 01-04.01'!Q14+'Юнит 05-11.01'!Q14+'Юнит 12-18.01'!Q14+'Юнит 19-25.01'!Q14+'Юнит 26-31.01'!Q14 -> 0 | R14: =P14-Q14 -> 0 | S14: ='Юнит 01-04.01'!S14+'Юнит 05-11.01'!S14+'Юнит 12-18.01'!S14+'Юнит 19-25.01'!S14+'Юнит 26-31.01'!S14 -> 0 | T14: ='Юнит 01-04.01'!T14+'Юнит 05-11.01'!T14+'Юнит 12-18.01'!T14+'Юнит 19-25.01'!T14+'Юнит 26-31.01'!T14 -> 0 | U14: =S14+T14 -> 0 | V14: =U14/$U$24 -> 0 | W14: =R14*H14 -> 0 | X14: ='Юнит 01-04.01'!X14+'Юнит 05-11.01'!X14+'Юнит 12-18.01'!X14+'Юнит 19-25.01'!X14+'Юнит 26-31.01'!X14 -> 0 | Y14: =IF(U14=0,0,X14/U14) -> 0 | Z14: ='Юнит 01-04.01'!Z14+'Юнит 05-11.01'!Z14+'Юнит 12-18.01'!Z14+'Юнит 19-25.01'!Z14+'Юнит 26-31.01'!Z14 -> 0 | AA14: ='Юнит 01-04.01'!AA14+'Юнит 05-11.01'!AA14+'Юнит 12-18.01'!AA14+'Юнит 19-25.01'!AA14+'Юнит 26-31.01'!AA14 -> 607.06546 | AD14: =U14*1% -> 0 | AE14: =U14-W14-X14-Z14-AA14-AB14-AC14-AD14 -> -607.06546 | AG14: =IF(R14=0,0,U14/R14) -> 0 | AH14: =H14 -> 123 | AI14: =IF(R14=0,0,X14/R14) -> 0 | AJ14: =IF(P14=0,Z14/1,Z14/P14) -> 0 | AK14: =IF(P14=0,0,AA14/P14) -> 0 | AL14: {=_xlfn.IFS(R14=0,AE14,R14<0,AE14/-R14,R14>0,AE14/R14)} -> -607.06546 | AM14: =IF(AG14=0,0,AL14/AG14) -> 0 | AN14: =IF(AH14=0,0,AL14/AH14) -> -4.9354915 | AP14: =AL14*C14 -> 0
A15: 3064346642 | B15: flip жел | C15: ='Юнит 26-31.01'!C15 -> 0 | H15: 123 | I15: =C15*H15 -> 0 | K15: ='Юнит 01-04.01'!K15+'Юнит 05-11.01'!K15+'Юнит 12-18.01'!K15+'Юнит 19-25.01'!K15+'Юнит 26-31.01'!K15 -> 239 | N15: =K15/31 -> 7.7096774 | O15: =R15/31 -> 5.1935484 | P15: ='Юнит 01-04.01'!P15+'Юнит 05-11.01'!P15+'Юнит 12-18.01'!P15+'Юнит 19-25.01'!P15+'Юнит 26-31.01'!P15 -> 166 | Q15: ='Юнит 01-04.01'!Q15+'Юнит 05-11.01'!Q15+'Юнит 12-18.01'!Q15+'Юнит 19-25.01'!Q15+'Юнит 26-31.01'!Q15 -> 5 | R15: =P15-Q15 -> 161 | S15: ='Юнит 01-04.01'!S15+'Юнит 05-11.01'!S15+'Юнит 12-18.01'!S15+'Юнит 19-25.01'!S15+'Юнит 26-31.01'!S15 -> 302635 | T15: ='Юнит 01-04.01'!T15+'Юнит 05-11.01'!T15+'Юнит 12-18.01'!T15+'Юнит 19-25.01'!T15+'Юнит 26-31.01'!T15 -> -9225 | U15: =S15+T15 -> 293410 | V15: =U15/$U$24 -> 0.32208171 | W15: =R15*H15 -> 19803 | X15: ='Юнит 01-04.01'!X15+'Юнит 05-11.01'!X15+'Юнит 12-18.01'!X15+'Юнит 19-25.01'!X15+'Юнит 26-31.01'!X15 -> 126166.3 | Y15: =IF(U15=0,0,X15/U15) -> 0.43 | Z15: ='Юнит 01-04.01'!Z15+'Юнит 05-11.01'!Z15+'Юнит 12-18.01'!Z15+'Юнит 19-25.01'!Z15+'Юнит 26-31.01'!Z15 -> 35029.13 | AA15: ='Юнит 01-04.01'!AA15+'Юнит 05-11.01'!AA15+'Юнит 12-18.01'!AA15+'Юнит 19-25.01'!AA15+'Юнит 26-31.01'!AA15 -> 79313.333 | AD15: =U15*1% -> 2934.1 | AE15: =U15-W15-X15-Z15-AA15-AB15-AC15-AD15 -> 30164.137 | AG15: =IF(R15=0,0,U15/R15) -> 1822.4224 | AH15: =H15 -> 123 | AI15: =IF(R15=0,0,X15/R15) -> 783.64161 | AJ15: =IF(P15=0,Z15/1,Z15/P15) -> 211.01886 | AK15: =IF(P15=0,0,AA15/P15) -> 477.79116 | AL15: {=_xlfn.IFS(R15=0,AE15,R15<0,AE15/-R15,R15>0,AE15/R15)} -> 187.35489 | AM15: =IF(AG15=0,0,AL15/AG15) -> 0.10280541 | AN15: =IF(AH15=0,0,AL15/AH15) -> 1.5232105 | AP15: =AL15*C15 -> 0
A16: 3405092287 | B16: flip коричневый | C16: ='Юнит 26-31.01'!C16 -> 0 | H16: 117 | I16: =C16*H16 -> 0 | K16: ='Юнит 01-04.01'!K16+'Юнит 05-11.01'!K16+'Юнит 12-18.01'!K16+'Юнит 19-25.01'!K16+'Юнит 26-31.01'!K16 -> 2 | N16: =K16/31 -> 0.064516129 | O16: =R16/31 -> 0 | P16: ='Юнит 01-04.01'!P16+'Юнит 05-11.01'!P16+'Юнит 12-18.01'!P16+'Юнит 19-25.01'!P16+'Юнит 26-31.01'!P16 -> 0 | Q16: ='Юнит 01-04.01'!Q16+'Юнит 05-11.01'!Q16+'Юнит 12-18.01'!Q16+'Юнит 19-25.01'!Q16+'Юнит 26-31.01'!Q16 -> 0 | R16: =P16-Q16 -> 0 | S16: ='Юнит 01-04.01'!S16+'Юнит 05-11.01'!S16+'Юнит 12-18.01'!S16+'Юнит 19-25.01'!S16+'Юнит 26-31.01'!S16 -> 0 | T16: ='Юнит 01-04.01'!T16+'Юнит 05-11.01'!T16+'Юнит 12-18.01'!T16+'Юнит 19-25.01'!T16+'Юнит 26-31.01'!T16 -> 0 | U16: =S16+T16 -> 0 | V16: =U16/$U$24 -> 0 | W16: =R16*H16 -> 0 | X16: ='Юнит 01-04.01'!X16+'Юнит 05-11.01'!X16+'Юнит 12-18.01'!X16+'Юнит 19-25.01'!X16+'Юнит 26-31.01'!X16 -> 0 | Y16: =IF(U16=0,0,X16/U16) -> 0 | Z16: ='Юнит 01-04.01'!Z16+'Юнит 05-11.01'!Z16+'Юнит 12-18.01'!Z16+'Юнит 19-25.01'!Z16+'Юнит 26-31.01'!Z16 -> 0 | AA16: ='Юнит 01-04.01'!AA16+'Юнит 05-11.01'!AA16+'Юнит 12-18.01'!AA16+'Юнит 19-25.01'!AA16+'Юнит 26-31.01'!AA16 -> 1324.8447 | AD16: =U16*1% -> 0 | AE16: =U16-W16-X16-Z16-AA16-AB16-AC16-AD16 -> -1324.8447 | AG16: =IF(R16=0,0,U16/R16) -> 0 | AH16: =H16 -> 117 | AI16: =IF(R16=0,0,X16/R16) -> 0 | AJ16: =IF(P16=0,Z16/1,Z16/P16) -> 0 | AK16: =IF(P16=0,0,AA16/P16) -> 0 | AL16: {=_xlfn.IFS(R16=0,AE16,R16<0,AE16/-R16,R16>0,AE16/R16)} -> -1324.8447 | AM16: =IF(AG16=0,0,AL16/AG16) -> 0 | AN16: =IF(AH16=0,0,AL16/AH16) -> -11.323459 | AP16: =AL16*C16 -> 0
AG17: =AVERAGEIF(AG3:AG15,"<>0",AG3:AG15) -> 1743.8825 | AH17: =AVERAGEIF(AH3:AH15,"<>0",AH3:AH15) -> 127.26 | AI17: =AVERAGEIF(AI3:AI15,"<>0",AI3:AI15) -> 749.86947 | AJ17: =AVERAGEIF(AJ3:AJ15,"<>0",AJ3:AJ15) -> 165.05275 | AK17: =AVERAGEIF(AK3:AK15,"<>0",AK3:AK15) -> 379.43397 | AL17: =AVERAGEIF(AL3:AL15,"<>0",AL3:AL15) -> 19.660482 | AM17: =AVERAGEIF(AM3:AM15,"<>0",AM3:AM15) -> 0.16975488 | AN17: =AVERAGEIF(AN3:AN15,"<>0",AN3:AN15) -> 0.087403381
A18: Итого очки | C18: =SUM(C3:C16) -> 0 | E18: 108496 | F18: 597 | G18: 295 | I18: =SUM(I3:I16) -> 0 | K18: =SUM(K3:K16) -> 803 | P18: =SUM(P3:P16) -> 544 | Q18: =SUM(Q3:Q16) -> 15 | R18: =SUM(R3:R16) -> 529 | S18: =SUM(S3:S16) -> 936447 | T18: =SUM(T3:T16) -> -25467 | U18: =SUM(U3:U16) -> 910980 | V18: =SUM(V3:V16) -> 1 | W18: =SUM(W3:W16) -> 66570.99 | X18: =SUM(X3:X16) -> 391721.4 | Y18: =IF(U18=0,0,X18/U18) -> 0.43 | Z18: =SUM(Z3:Z16) -> 98630.24 | AA18: =IFERROR(P18*AA24/P24,0) -> 239309.33 | AB18: =SUM(AB3:AB16) -> 0 | AC18: =SUM(AC3:AC16) -> 0 | AD18: =SUM(AD3:AD16) -> 9109.8 | AE18: =SUM(AE3:AE16) -> 110277.82 | AP18: =SUM(AP3:AP16) -> 0 | AZ18: 18592777
AA19: =SUM(AA3:AA16) -> 234669.75
AG21: =AVERAGEIF(AG20:AG20,"<>0",AG20:AG20) -> #DIV/0! | AH21: =AVERAGEIF(AH20:AH20,"<>0",AH20:AH20) -> #DIV/0! | AI21: =AVERAGEIF(AI20:AI20,"<>0",AI20:AI20) -> #DIV/0! | AJ21: =AVERAGEIF(AJ20:AJ20,"<>0",AJ20:AJ20) -> #DIV/0! | AK21: =AVERAGEIF(AK20:AK20,"<>0",AK20:AK20) -> #DIV/0! | AL21: =AVERAGEIF(AL20:AL20,"<>0",AL20:AL20) -> #DIV/0! | AM21: =AVERAGEIF(AM20:AM20,"<>0",AM20:AM20) -> #DIV/0! | AN21: =AVERAGEIF(AN20:AN20,"<>0",AN20:AN20) -> #DIV/0!
C22: =SUM(C20:C20) -> 0 | I22: =SUM(I20:I20) -> 0 | K22: =SUM(K20:K20) -> 0 | P22: =SUM(P20:P20) -> 0 | Q22: =SUM(Q20:Q20) -> 0 | R22: =SUM(R20:R20) -> 0 | S22: =SUM(S20:S20) -> 0 | T22: =SUM(T20:T20) -> 0 | U22: =SUM(U20:U20) -> 0 | V22: =SUM(V20:V20) -> 0 | W22: =SUM(W20:W20) -> 0 | X22: =SUM(X20:X20) -> 0 | Y22: =IF(U22=0,0,X22/U22) -> 0 | Z22: =SUM(Z20:Z20) -> 0 | AA22: =IFERROR(P22*AA24/P24,0) -> 0 | AB22: =SUM(AB20:AB20) -> 0 | AC22: =SUM(AC20:AC20) -> 0 | AD22: =SUM(AD20:AD20) -> 0 | AE22: =SUM(AE20:AE20) -> 0 | AP22: =SUM(AP20:AP20) -> 0
AA23: =SUM(AA20:AA20) -> 0
A24: ИТОГО | C24: =C18+C22 -> 0 | D24: =SUM(D3:D20) -> 0 | E24: =SUM(E3:E20) -> 108496 | F24: =SUM(F3:F20) -> 597 | G24: =SUM(G3:G20) -> 295 | I24: =I18+I22 -> 0 | J24: =J18+J22 -> 0 | K24: =K18+K22 -> 803 | P24: =P18+P22 -> 544 | Q24: =Q18+Q22 -> 15 | R24: =R18-R22 -> 529 | S24: =S18+S22 -> 936447 | T24: =T18+T22 -> -25467 | U24: =U18+U22 -> 910980 | V24: =V18+V22 -> 1 | W24: =W18+W22 -> 66570.99 | X24: =X18+X22 -> 391721.4 | Y24: =X24/U24 -> 0.43 | Z24: =Z18+Z22 -> 98630.24 | AA24: ='Юнит 01-04.01'!AA24+'Юнит 05-11.01'!AA24+'Юнит 12-18.01'!AA24+'Юнит 19-25.01'!AA24+'Юнит 26-31.01'!AA24 -> 239309.33 | AC24: =SUM(AC3:AC20) -> 0 | AD24: =AD18+AD22 -> 9109.8 | AE24: =AE18+AE22 -> 110277.82 | AK24: =AA25/P24 -> 439.90686 | AP24: =SUM(AP3:AP20) -> 0
AA25: =AA18+AA22 -> 239309.33 | AE25: =Сводная!Y17+Сводная!R17+Сводная!S17+Сводная!T17+Сводная!V17-Сводная!U17-Сводная!W17-(AA26-AA25) -> 110277.82
AA26: =AA19+AA23 -> 234669.75
I29: Себестоимость остатков | K29: Прибыль с остатков | L29: Рентабельность товарных остатков
H31: до 60 дн | I31: =SUMIF(J3:J20,"<60",I3:I20) -> 0 | J31: =I31/I24 -> #DIV/0! | K31: =SUMIF(J3:J20,"<60",AP3:AP20) -> 0 | L31: =K31/I31 -> #DIV/0!
H32: 60-120 дн | I32: =I24-I33-I31 -> 0 | J32: =I32/I24 -> #DIV/0! | K32: =AP24-K31-K33 -> 0 | L32: =K32/I32 -> #DIV/0!
H33: > 120 дн | I33: =SUMIF(J3:J20,">120",I3:I20) -> 0 | J33: =I33/I24 -> #DIV/0! | K33: =SUMIF(J3:J20,">120",AP3:AP20) -> 0 | L33: =K33/I33 -> #DIV/0!
H35: Если товар на сайте менее 30 дней - оборачиваемость 0

Sheet Юнит 26.01-01.02
B1: 26.01-01.02 | AG1: на 1 единицу проданного товара
B2: Артикул поставщика | C2: Остаток на | D2: В пути до клиента | E2: В пути от клиента | F2: Итого по складам ВБ | G2: Остаток на нашем складе на 02.09 | H2: Себетоимость на 1 ед на 29.09.25 | I2: Себестоимость остатков | J2: Оборачиваемость, дн | K2: Заказы, шт 7 дней | L2: Средняя цена, руб (столбец 32, AG) | M2: % выкупа за 7 дней (столбец 23, X) | N2: Скорость заказов | O2: Скорость продаж | P2: Кол-во ПРОДАЖИ | Q2: Кол-во ВОЗВРАТЫ | R2: Кол-во ПРОДАЖИ-ВОЗВРАТЫ | S2: Выручка ПРОДАЖИ | T2: Выручка ВОЗВРАТЫ | U2: Выручка с учетом согласованной скидки ПРОДАЖИ - ВОЗВРАТЫ | V2: Доля выручки, % от общего объема | W2: Себестоимость продаж | X2: Комиссия, руб | Y2: Комиссия, % | Z2: Логистика | AA2: Реклама | AB2: Хранение | AC2: Штрафы | AD2: Налог 1% | AE2: Прибыль | AG2: Выручка на 1 ед (средняя цена продажи со скидкой) | AH2: Себестоимость на 1 ед | AI2: Комиссия на 1 ед | AJ2: Логистика на 1 ед | AK2: Реклама на 1 ед | AL2: Прибыль на 1 ед | AM2: Маржинальность, % | AN2: Рентабельность, % | AP2: Прибыль с остатков
A3: 2676784153 | B3: черные с железкой классика | H3: 142.98 | I3: =C3*H3 -> 0 | K3: ='Юнит 26-31.01'!K3+'Юнит 01.02'!K3 -> 5 | N3: =K3/7 -> 0.71428571 | O3: =R3/7 -> 0.14285714 | P3: ='Юнит 26-31.01'!P3+'Юнит 01.02'!P3 -> 1 | Q3: ='Юнит 26-31.01'!Q3+'Юнит 01.02'!Q3 -> 0 | R3: =P3-Q3 -> 1 | S3: ='Юнит 26-31.01'!S3+'Юнит 01.02'!S3 -> 1750 | T3: ='Юнит 26-31.01'!T3+'Юнит 01.02'!T3 -> 0 | U3: =S3+T3 -> 1750 | V3: =U3/$U$24 -> 0.0076224492 | W3: =R3*H3 -> 142.98 | X3: ='Юнит 26-31.01'!X3+'Юнит 01.02'!X3 -> 752.5 | Y3: =IF(U3=0,0,X3/U3) -> 0.43 | Z3: ='Юнит 26-31.01'!Z3+'Юнит 01.02'!Z3 -> 224.91 | AA3: ='Юнит 26-31.01'!AA3+'Юнит 01.02'!AA3 -> 460 | AD3: =U3*1% -> 17.5 | AE3: =U3-W3-X3-Z3-AA3-AB3-AC3-AD3 -> 152.11 | AG3: =IF(R3=0,0,U3/R3) -> 1750 | AH3: =H3 -> 142.98 | AI3: =IF(R3=0,0,X3/R3) -> 752.5 | AJ3: =IF(P3=0,Z3/1,Z3/P3) -> 224.91 | AK3: =IF(P3=0,0,AA3/P3) -> 460 | AL3: =_xlfn.IFS(R3=0,AE3,R3<0,AE3/-R3,R3>0,AE3/R3) -> 152.11 | AM3: =IF(AG3=0,0,AL3/AG3) -> 0.08692 | AN3: =IF(AH3=0,0,AL3/AH3) -> 1.0638551 | AP3: =AL3*C3 -> 0
A4: 2676784638 | B4: qs черные | H4: 123.09 | I4: =C4*H4 -> 0 | K4: ='Юнит 26-31.01'!K4+'Юнит 01.02'!K4 -> 4 | N4: =K4/7 -> 0.57142857 | O4: =R4/7 -> 0.71428571 | P4: ='Юнит 26-31.01'!P4+'Юнит 01.02'!P4 -> 5 | Q4: ='Юнит 26-31.01'!Q4+'Юнит 01.02'!Q4 -> 0 | R4: =P4-Q4 -> 5 | S4: ='Юнит 26-31.01'!S4+'Юнит 01.02'!S4 -> 8750 | T4: ='Юнит 26-31.01'!T4+'Юнит 01.02'!T4 -> 0 | U4: =S4+T4 -> 8750 | V4: =U4/$U$24 -> 0.038112246 | W4: =R4*H4 -> 615.45 | X4: ='Юнит 26-31.01'!X4+'Юнит 01.02'!X4 -> 3762.5 | Y4: =IF(U4=0,0,X4/U4) -> 0.43 | Z4: ='Юнит 26-31.01'!Z4+'Юнит 01.02'!Z4 -> 787.5 | AA4: ='Юнит 26-31.01'!AA4+'Юнит 01.02'!AA4 -> 175 | AD4: =U4*1% -> 87.5 | AE4: =U4-W4-X4-Z4-AA4-AB4-AC4-AD4 -> 3322.05 | AG4: =IF(R4=0,0,U4/R4) -> 1750 | AH4: =H4 -> 123.09 | AI4: =IF(R4=0,0,X4/R4) -> 752.5 | AJ4: =IF(P4=0,Z4/1,Z4/P4) -> 157.5 | AK4: =IF(P4=0,0,AA4/P4) -> 35 | AL4: {=_xlfn.IFS(R4=0,AE4,R4<0,AE4/-R4,R4>0,AE4/R4)} -> 664.41 | AM4: =IF(AG4=0,0,AL4/AG4) -> 0.37966286 | AN4: =IF(AH4=0,0,AL4/AH4) -> 5.3977577 | AP4: =AL4*C4 -> 0
A5: 2676784504 | B5: qs синие | H5: 123.09 | I5: =C5*H5 -> 0 | K5: ='Юнит 26-31.01'!K5+'Юнит 01.02'!K5 -> 1 | N5: =K5/7 -> 0.14285714 | O5: =R5/7 -> 0 | P5: ='Юнит 26-31.01'!P5+'Юнит 01.02'!P5 -> 0 | Q5: ='Юнит 26-31.01'!Q5+'Юнит 01.02'!Q5 -> 0 | R5: =P5-Q5 -> 0 | S5: ='Юнит 26-31.01'!S5+'Юнит 01.02'!S5 -> 0 | T5: ='Юнит 26-31.01'!T5+'Юнит 01.02'!T5 -> 0 | U5: =S5+T5 -> 0 | V5: =U5/$U$24 -> 0 | W5: =R5*H5 -> 0 | X5: ='Юнит 26-31.01'!X5+'Юнит 01.02'!X5 -> 0 | Y5: =IF(U5=0,0,X5/U5) -> 0 | Z5: ='Юнит 26-31.01'!Z5+'Юнит 01.02'!Z5 -> 0 | AA5: ='Юнит 26-31.01'!AA5+'Юнит 01.02'!AA5 -> 0 | AD5: =U5*1% -> 0 | AE5: =U5-W5-X5-Z5-AA5-AB5-AC5-AD5 -> 0 | AG5: =IF(R5=0,0,U5/R5) -> 0 | AH5: =H5 -> 123.09 | AI5: =IF(R5=0,0,X5/R5) -> 0 | AJ5: =IF(P5=0,Z5/1,Z5/P5) -> 0 | AK5: =IF(P5=0,0,AA5/P5) -> 0 | AL5: {=_xlfn.IFS(R5=0,AE5,R5<0,AE5/-R5,R5>0,AE5/R5)} -> 0 | AM5: =IF(AG5=0,0,AL5/AG5) -> 0 | AN5: =IF(AH5=0,0,AL5/AH5) -> 0 | AP5: =AL5*C5 -> 0
A6: 2676784514 | B6: qs желтые | H6: 123.09 | I6: =C6*H6 -> 0 | K6: ='Юнит 26-31.01'!K6+'Юнит 01.02'!K6 -> 12 | N6: =K6/7 -> 1.7142857 | O6: =R6/7 -> 0.85714286 | P6: ='Юнит 26-31.01'!P6+'Юнит 01.02'!P6 -> 6 | Q6: ='Юнит 26-31.01'!Q6+'Юнит 01.02'!Q6 -> 0 | R6: =P6-Q6 -> 6 | S6: ='Юнит 26-31.01'!S6+'Юнит 01.02'!S6 -> 10500 | T6: ='Юнит 26-31.01'!T6+'Юнит 01.02'!T6 -> 0 | U6: =S6+T6 -> 10500 | V6: =U6/$U$24 -> 0.045734695 | W6: =R6*H6 -> 738.54 | X6: ='Юнит 26-31.01'!X6+'Юнит 01.02'!X6 -> 4515 | Y6: =IF(U6=0,0,X6/U6) -> 0.43 | Z6: ='Юнит 26-31.01'!Z6+'Юнит 01.02'!Z6 -> 1132.6 | AA6: ='Юнит 26-31.01'!AA6+'Юнит 01.02'!AA6 -> 2817.5 | AD6: =U6*1% -> 105 | AE6: =U6-W6-X6-Z6-AA6-AB6-AC6-AD6 -> 1191.36 | AG6: =IF(R6=0,0,U6/R6) -> 1750 | AH6: =H6 -> 123.09 | AI6: =IF(R6=0,0,X6/R6) -> 752.5 | AJ6: =IF(P6=0,Z6/1,Z6/P6) -> 188.76667 | AK6: =IF(P6=0,0,AA6/P6) -> 469.58333 | AL6: {=_xlfn.IFS(R6=0,AE6,R6<0,AE6/-R6,R6>0,AE6/R6)} -> 198.56 | AM6: =IF(AG6=0,0,AL6/AG6) -> 0.11346286 | AN6: =IF(AH6=0,0,AL6/AH6) -> 1.6131286 | AP6: =AL6*C6 -> 0
A7: 2676784181 | B7: qs коричневые | H7: 117.24 | I7: =C7*H7 -> 0 | K7: ='Юнит 26-31.01'!K7+'Юнит 01.02'!K7 -> 34 | N7: =K7/7 -> 4.8571429 | O7: =R7/7 -> 2.2857143 | P7: ='Юнит 26-31.01'!P7+'Юнит 01.02'!P7 -> 18 | Q7: ='Юнит 26-31.01'!Q7+'Юнит 01.02'!Q7 -> 2 | R7: =P7-Q7 -> 16 | S7: ='Юнит 26-31.01'!S7+'Юнит 01.02'!S7 -> 31325 | T7: ='Юнит 26-31.01'!T7+'Юнит 01.02'!T7 -> -3500 | U7: =S7+T7 -> 27825 | V7: =U7/$U$24 -> 0.12119694 | W7: =R7*H7 -> 1875.84 | X7: ='Юнит 26-31.01'!X7+'Юнит 01.02'!X7 -> 11964.75 | Y7: =IF(U7=0,0,X7/U7) -> 0.43 | Z7: ='Юнит 26-31.01'!Z7+'Юнит 01.02'!Z7 -> 3430.62 | AA7: ='Юнит 26-31.01'!AA7+'Юнит 01.02'!AA7 -> 10748.34 | AD7: =U7*1% -> 278.25 | AE7: =U7-W7-X7-Z7-AA7-AB7-AC7-AD7 -> -472.79957 | AG7: =IF(R7=0,0,U7/R7) -> 1739.0625 | AH7: =H7 -> 117.24 | AI7: =IF(R7=0,0,X7/R7) -> 747.79688 | AJ7: =IF(P7=0,Z7/1,Z7/P7) -> 190.59 | AK7: =IF(P7=0,0,AA7/P7) -> 597.12998 | AL7: {=_xlfn.IFS(R7=0,AE7,R7<0,AE7/-R7,R7>0,AE7/R7)} -> -29.549973 | AM7: =IF(AG7=0,0,AL7/AG7) -> -0.016991898 | AN7: =IF(AH7=0,0,AL7/AH7) -> -0.25204686 | AP7: =AL7*C7 -> 0
A8: 2676783005 | B8: MR8854 C2 | H8: 169.89 | I8: =C8*H8 -> 0 | K8: ='Юнит 26-31.01'!K8+'Юнит 01.02'!K8 -> 25 | N8: =K8/7 -> 3.5714286 | O8: =R8/7 -> 1.4285714 | P8: ='Юнит 26-31.01'!P8+'Юнит 01.02'!P8 -> 10 | Q8: ='Юнит 26-31.01'!Q8+'Юнит 01.02'!Q8 -> 0 | R8: =P8-Q8 -> 10 | S8: ='Юнит 26-31.01'!S8+'Юнит 01.02'!S8 -> 17500 | T8: ='Юнит 26-31.01'!T8+'Юнит 01.02'!T8 -> 0 | U8: =S8+T8 -> 17500 | V8: =U8/$U$24 -> 0.076224492 | W8: =R8*H8 -> 1698.9 | X8: ='Юнит 26-31.01'!X8+'Юнит 01.02'!X8 -> 7525 | Y8: =IF(U8=0,0,X8/U8) -> 0.43 | Z8: ='Юнит 26-31.01'!Z8+'Юнит 01.02'!Z8 -> 1682.24 | AA8: ='Юнит 26-31.01'!AA8+'Юнит 01.02'!AA8 -> 4569.3328 | AD8: =U8*1% -> 175 | AE8: =U8-W8-X8-Z8-AA8-AB8-AC8-AD8 -> 1849.5272 | AG8: =IF(R8=0,0,U8/R8) -> 1750 | AH8: =H8 -> 169.89 | AI8: =IF(R8=0,0,X8/R8) -> 752.5 | AJ8: =IF(P8=0,Z8/1,Z8/P8) -> 168.224 | AK8: =IF(P8=0,0,AA8/P8) -> 456.93328 | AL8: {=_xlfn.IFS(R8=0,AE8,R8<0,AE8/-R8,R8>0,AE8/R8)} -> 184.95272 | AM8: =IF(AG8=0,0,AL8/AG8) -> 0.10568727 | AN8: =IF(AH8=0,0,AL8/AH8) -> 1.0886616 | AP8: =AL8*C8 -> 0
A9: 3405092860 | B9: th черн | H9: 123 | I9: =C9*H9 -> 0 | K9: ='Юнит 26-31.01'!K9+'Юнит 01.02'!K9 -> 6 | N9: =K9/7 -> 0.85714286 | O9: =R9/7 -> 0.14285714 | P9: ='Юнит 26-31.01'!P9+'Юнит 01.02'!P9 -> 1 | Q9: ='Юнит 26-31.01'!Q9+'Юнит 01.02'!Q9 -> 0 | R9: =P9-Q9 -> 1 | S9: ='Юнит 26-31.01'!S9+'Юнит 01.02'!S9 -> 2000 | T9: ='Юнит 26-31.01'!T9+'Юнит 01.02'!T9 -> 0 | U9: =S9+T9 -> 2000 | V9: =U9/$U$24 -> 0.0087113705 | W9: =R9*H9 -> 123 | X9: ='Юнит 26-31.01'!X9+'Юнит 01.02'!X9 -> 860 | Y9: =IF(U9=0,0,X9/U9) -> 0.43 | Z9: ='Юнит 26-31.01'!Z9+'Юнит 01.02'!Z9 -> 155.81 | AA9: ='Юнит 26-31.01'!AA9+'Юнит 01.02'!AA9 -> 556.81946 | AD9: =U9*1% -> 20 | AE9: =U9-W9-X9-Z9-AA9-AB9-AC9-AD9 -> 284.37054 | AG9: =IF(R9=0,0,U9/R9) -> 2000 | AH9: =H9 -> 123 | AI9: =IF(R9=0,0,X9/R9) -> 860 | AJ9: =IF(P9=0,Z9/1,Z9/P9) -> 155.81 | AK9: =IF(P9=0,0,AA9/P9) -> 556.81946 | AL9: {=_xlfn.IFS(R9=0,AE9,R9<0,AE9/-R9,R9>0,AE9/R9)} -> 284.37054 | AM9: =IF(AG9=0,0,AL9/AG9) -> 0.14218527 | AN9: =IF(AH9=0,0,AL9/AH9) -> 2.3119556 | AP9: =AL9*C9 -> 0
A10: 3405092836 | B10: th син | H10: 123 | I10: =C10*H10 -> 0 | K10: ='Юнит 26-31.01'!K10+'Юнит 01.02'!K10 -> 8 | N10: =K10/7 -> 1.1428571 | O10: =R10/7 -> 0.14285714 | P10: ='Юнит 26-31.01'!P10+'Юнит 01.02'!P10 -> 1 | Q10: ='Юнит 26-31.01'!Q10+'Юнит 01.02'!Q10 -> 0 | R10: =P10-Q10 -> 1 | S10: ='Юнит 26-31.01'!S10+'Юнит 01.02'!S10 -> 2000 | T10: ='Юнит 26-31.01'!T10+'Юнит 01.02'!T10 -> 0 | U10: =S10+T10 -> 2000 | V10: =U10/$U$24 -> 0.0087113705 | W10: =R10*H10 -> 123 | X10: ='Юнит 26-31.01'!X10+'Юнит 01.02'!X10 -> 860 | Y10: =IF(U10=0,0,X10/U10) -> 0.43 | Z10: ='Юнит 26-31.01'!Z10+'Юнит 01.02'!Z10 -> 155.81 | AA10: ='Юнит 26-31.01'!AA10+'Юнит 01.02'!AA10 -> 1804.8669 | AD10: =U10*1% -> 20 | AE10: =U10-W10-X10-Z10-AA10-AB10-AC10-AD10 -> -963.6769 | AG10: =IF(R10=0,0,U10/R10) -> 2000 | AH10: =H10 -> 123 | AI10: =IF(R10=0,0,X10/R10) -> 860 | AJ10: =IF(P10=0,Z10/1,Z10/P10) -> 155.81 | AK10: =IF(P10=0,0,AA10/P10) -> 1804.8669 | AL10: {=_xlfn.IFS(R10=0,AE10,R10<0,AE10/-R10,R10>0,AE10/R10)} -> -963.6769 | AM10: =IF(AG10=0,0,AL10/AG10) -> -0.48183845 | AN10: =IF(AH10=0,0,AL10/AH10) -> -7.8347715 | AP10: =AL10*C10 -> 0
A11: 3064346962 | B11: th желт | H11: 123 | I11: =C11*H11 -> 0 | K11: ='Юнит 26-31.01'!K11+'Юнит 01.02'!K11 -> 67 | N11: =K11/7 -> 9.5714286 | O11: =R11/7 -> 6.8571429 | P11: ='Юнит 26-31.01'!P11+'Юнит 01.02'!P11 -> 48 | Q11: ='Юнит 26-31.01'!Q11+'Юнит 01.02'!Q11 -> 0 | R11: =P11-Q11 -> 48 | S11: ='Юнит 26-31.01'!S11+'Юнит 01.02'!S11 -> 86387 | T11: ='Юнит 26-31.01'!T11+'Юнит 01.02'!T11 -> 0 | U11: =S11+T11 -> 86387 | V11: =U11/$U$24 -> 0.37627458 | W11: =R11*H11 -> 5904 | X11: ='Юнит 26-31.01'!X11+'Юнит 01.02'!X11 -> 37146.41 | Y11: =IF(U11=0,0,X11/U11) -> 0.43 | Z11: ='Юнит 26-31.01'!Z11+'Юнит 01.02'!Z11 -> 8161.72 | AA11: ='Юнит 26-31.01'!AA11+'Юнит 01.02'!AA11 -> 18199.939 | AD11: =U11*1% -> 863.87 | AE11: =U11-W11-X11-Z11-AA11-AB11-AC11-AD11 -> 16111.061 | AG11: =IF(R11=0,0,U11/R11) -> 1799.7292 | AH11: =H11 -> 123 | AI11: =IF(R11=0,0,X11/R11) -> 773.88354 | AJ11: =IF(P11=0,Z11/1,Z11/P11) -> 170.03583 | AK11: =IF(P11=0,0,AA11/P11) -> 379.1654 | AL11: {=_xlfn.IFS(R11=0,AE11,R11<0,AE11/-R11,R11>0,AE11/R11)} -> 335.6471 | AM11: =IF(AG11=0,0,AL11/AG11) -> 0.18649867 | AN11: =IF(AH11=0,0,AL11/AH11) -> 2.7288382 | AP11: =AL11*C11 -> 0
A12: 3405092873 | B12: th коричн | H12: 117 | I12: =C12*H12 -> 0 | K12: ='Юнит 26-31.01'!K12+'Юнит 01.02'!K12 -> 5 | N12: =K12/7 -> 0.71428571 | O12: =R12/7 -> 0.14285714 | P12: ='Юнит 26-31.01'!P12+'Юнит 01.02'!P12 -> 1 | Q12: ='Юнит 26-31.01'!Q12+'Юнит 01.02'!Q12 -> 0 | R12: =P12-Q12 -> 1 | S12: ='Юнит 26-31.01'!S12+'Юнит 01.02'!S12 -> 2000 | T12: ='Юнит 26-31.01'!T12+'Юнит 01.02'!T12 -> 0 | U12: =S12+T12 -> 2000 | V12: =U12/$U$24 -> 0.0087113705 | W12: =R12*H12 -> 117 | X12: ='Юнит 26-31.01'!X12+'Юнит 01.02'!X12 -> 860 | Y12: =IF(U12=0,0,X12/U12) -> 0.43 | Z12: ='Юнит 26-31.01'!Z12+'Юнит 01.02'!Z12 -> 155.81 | AA12: ='Юнит 26-31.01'!AA12+'Юнит 01.02'!AA12 -> 555.84386 | AD12: =U12*1% -> 20 | AE12: =U12-W12-X12-Z12-AA12-AB12-AC12-AD12 -> 291.34614 | AG12: =IF(R12=0,0,U12/R12) -> 2000 | AH12: =H12 -> 117 | AI12: =IF(R12=0,0,X12/R12) -> 860 | AJ12: =IF(P12=0,Z12/1,Z12/P12) -> 155.81 | AK12: =IF(P12=0,0,AA12/P12) -> 555.84386 | AL12: {=_xlfn.IFS(R12=0,AE12,R12<0,AE12/-R12,R12>0,AE12/R12)} -> 291.34614 | AM12: =IF(AG12=0,0,AL12/AG12) -> 0.14567307 | AN12: =IF(AH12=0,0,AL12/AH12) -> 2.490138 | AP12: =AL12*C12 -> 0
A13: 3405092993 | B13: flip черный | H13: 123 | I13: =C13*H13 -> 0 | K13: ='Юнит 26-31.01'!K13+'Юнит 01.02'!K13 -> 4 | N13: =K13/7 -> 0.57142857 | O13: =R13/7 -> 0.14285714 | P13: ='Юнит 26-31.01'!P13+'Юнит 01.02'!P13 -> 1 | Q13: ='Юнит 26-31.01'!Q13+'Юнит 01.02'!Q13 -> 0 | R13: =P13-Q13 -> 1 | S13: ='Юнит 26-31.01'!S13+'Юнит 01.02'!S13 -> 2000 | T13: ='Юнит 26-31.01'!T13+'Юнит 01.02'!T13 -> 0 | U13: =S13+T13 -> 2000 | V13: =U13/$U$24 -> 0.0087113705 | W13: =R13*H13 -> 123 | X13: ='Юнит 26-31.01'!X13+'Юнит 01.02'!X13 -> 860 | Y13: =IF(U13=0,0,X13/U13) -> 0.43 | Z13: ='Юнит 26-31.01'!Z13+'Юнит 01.02'!Z13 -> 155.81 | AA13: ='Юнит 26-31.01'!AA13+'Юнит 01.02'!AA13 -> 633.38405 | AD13: =U13*1% -> 20 | AE13: =U13-W13-X13-Z13-AA13-AB13-AC13-AD13 -> 207.80595 | AG13: =IF(R13=0,0,U13/R13) -> 2000 | AH13: =H13 -> 123 | AI13: =IF(R13=0,0,X13/R13) -> 860 | AJ13: =IF(P13=0,Z13/1,Z13/P13) -> 155.81 | AK13: =IF(P13=0,0,AA13/P13) -> 633.38405 | AL13: {=_xlfn.IFS(R13=0,AE13,R13<0,AE13/-R13,R13>0,AE13/R13)} -> 207.80595 | AM13: =IF(AG13=0,0,AL13/AG13) -> 0.10390297 | AN13: =IF(AH13=0,0,AL13/AH13) -> 1.6894793 | AP13: =AL13*C13 -> 0
A14: 3405092868 | B14: flip синий | H14: 123 | I14: =C14*H14 -> 0 | K14: ='Юнит 26-31.01'!K14+'Юнит 01.02'!K14 -> 1 | N14: =K14/7 -> 0.14285714 | O14: =R14/7 -> 0 | P14: ='Юнит 26-31.01'!P14+'Юнит 01.02'!P14 -> 0 | Q14: ='Юнит 26-31.01'!Q14+'Юнит 01.02'!Q14 -> 0 | R14: =P14-Q14 -> 0 | S14: ='Юнит 26-31.01'!S14+'Юнит 01.02'!S14 -> 0 | T14: ='Юнит 26-31.01'!T14+'Юнит 01.02'!T14 -> 0 | U14: =S14+T14 -> 0 | V14: =U14/$U$24 -> 0 | W14: =R14*H14 -> 0 | X14: ='Юнит 26-31.01'!X14+'Юнит 01.02'!X14 -> 0 | Y14: =IF(U14=0,0,X14/U14) -> 0 | Z14: ='Юнит 26-31.01'!Z14+'Юнит 01.02'!Z14 -> 0 | AA14: ='Юнит 26-31.01'!AA14+'Юнит 01.02'!AA14 -> 807.06546 | AD14: =U14*1% -> 0 | AE14: =U14-W14-X14-Z14-AA14-AB14-AC14-AD14 -> -807.06546 | AG14: =IF(R14=0,0,U14/R14) -> 0 | AH14: =H14 -> 123 | AI14: =IF(R14=0,0,X14/R14) -> 0 | AJ14: =IF(P14=0,Z14/1,Z14/P14) -> 0 | AK14: =IF(P14=0,0,AA14/P14) -> 0 | AL14: {=_xlfn.IFS(R14=0,AE14,R14<0,AE14/-R14,R14>0,AE14/R14)} -> -807.06546 | AM14: =IF(AG14=0,0,AL14/AG14) -> 0 | AN14: =IF(AH14=0,0,AL14/AH14) -> -6.5615078 | AP14: =AL14*C14 -> 0
A15: 3064346642 | B15: flip жел | H15: 123 | I15: =C15*H15 -> 0 | K15: ='Юнит 26-31.01'!K15+'Юнит 01.02'!K15 -> 62 | N15: =K15/7 -> 8.8571429 | O15: =R15/7 -> 5.4285714 | P15: ='Юнит 26-31.01'!P15+'Юнит 01.02'!P15 -> 39 | Q15: ='Юнит 26-31.01'!Q15+'Юнит 01.02'!Q15 -> 1 | R15: =P15-Q15 -> 38 | S15: ='Юнит 26-31.01'!S15+'Юнит 01.02'!S15 -> 70718 | T15: ='Юнит 26-31.01'!T15+'Юнит 01.02'!T15 -> -1845 | U15: =S15+T15 -> 68873 | V15: =U15/$U$24 -> 0.29998911 | W15: =R15*H15 -> 4674 | X15: ='Юнит 26-31.01'!X15+'Юнит 01.02'!X15 -> 29615.39 | Y15: =IF(U15=0,0,X15/U15) -> 0.43 | Z15: ='Юнит 26-31.01'!Z15+'Юнит 01.02'!Z15 -> 7980.24 | AA15: ='Юнит 26-31.01'!AA15+'Юнит 01.02'!AA15 -> 14355.759 | AD15: =U15*1% -> 688.73 | AE15: =U15-W15-X15-Z15-AA15-AB15-AC15-AD15 -> 11558.881 | AG15: =IF(R15=0,0,U15/R15) -> 1812.4474 | AH15: =H15 -> 123 | AI15: =IF(R15=0,0,X15/R15) -> 779.35237 | AJ15: =IF(P15=0,Z15/1,Z15/P15) -> 204.62154 | AK15: =IF(P15=0,0,AA15/P15) -> 368.09638 | AL15: {=_xlfn.IFS(R15=0,AE15,R15<0,AE15/-R15,R15>0,AE15/R15)} -> 304.18108 | AM15: =IF(AG15=0,0,AL15/AG15) -> 0.16782892 | AN15: =IF(AH15=0,0,AL15/AH15) -> 2.4730169 | AP15: =AL15*C15 -> 0
A16: 3405092287 | B16: flip коричневый | H16: 117 | I16: =C16*H16 -> 0 | K16: ='Юнит 26-31.01'!K16+'Юнит 01.02'!K16 -> 2 | N16: =K16/7 -> 0.28571429 | O16: =R16/7 -> 0 | P16: ='Юнит 26-31.01'!P16+'Юнит 01.02'!P16 -> 0 | Q16: ='Юнит 26-31.01'!Q16+'Юнит 01.02'!Q16 -> 0 | R16: =P16-Q16 -> 0 | S16: ='Юнит 26-31.01'!S16+'Юнит 01.02'!S16 -> 0 | T16: ='Юнит 26-31.01'!T16+'Юнит 01.02'!T16 -> 0 | U16: =S16+T16 -> 0 | V16: =U16/$U$24 -> 0 | W16: =R16*H16 -> 0 | X16: ='Юнит 26-31.01'!X16+'Юнит 01.02'!X16 -> 0 | Y16: =IF(U16=0,0,X16/U16) -> 0 | Z16: ='Юнит 26-31.01'!Z16+'Юнит 01.02'!Z16 -> 0 | AA16: ='Юнит 26-31.01'!AA16+'Юнит 01.02'!AA16 -> 1604.7377 | AD16: =U16*1% -> 0 | AE16: =U16-W16-X16-Z16-AA16-AB16-AC16-AD16 -> -1604.7377 | AG16: =IF(R16=0,0,U16/R16) -> 0 | AH16: =H16 -> 117 | AI16: =IF(R16=0,0,X16/R16) -> 0 | AJ16: =IF(P16=0,Z16/1,Z16/P16) -> 0 | AK16: =IF(P16=0,0,AA16/P16) -> 0 | AL16: {=_xlfn.IFS(R16=0,AE16,R16<0,AE16/-R16,R16>0,AE16/R16)} -> -1604.7377 | AM16: =IF(AG16=0,0,AL16/AG16) -> 0 | AN16: =IF(AH16=0,0,AL16/AH16) -> -13.715707 | AP16: =AL16*C16 -> 0
AG17: =AVERAGEIF(AG3:AG15,"<>0",AG3:AG15) -> 1850.1126 | AH17: =AVERAGEIF(AH3:AH15,"<>0",AH3:AH15) -> 127.26 | AI17: =AVERAGEIF(AI3:AI15,"<>0",AI3:AI15) -> 795.54844 | AJ17: =AVERAGEIF(AJ3:AJ15,"<>0",AJ3:AJ15) -> 175.26255 | AK17: =AVERAGEIF(AK3:AK15,"<>0",AK3:AK15) -> 574.2566 | AL17: =AVERAGEIF(AL3:AL15,"<>0",AL3:AL15) -> 68.590935 | AM17: =AVERAGEIF(AM3:AM15,"<>0",AM3:AM15) -> 0.084817413 | AN17: =AVERAGEIF(AN3:AN15,"<>0",AN3:AN15) -> 0.51737541
A18: Итого очки | C18: =SUM(C3:C16) -> 0 | E18: 108496 | F18: 597 | G18: 295 | I18: =SUM(I3:I16) -> 0 | K18: =SUM(K3:K16) -> 236 | P18: =SUM(P3:P16) -> 131 | Q18: =SUM(Q3:Q16) -> 3 | R18: =SUM(R3:R16) -> 128 | S18: =SUM(S3:S16) -> 234930 | T18: =SUM(T3:T16) -> -5345 | U18: =SUM(U3:U16) -> 229585 | V18: =SUM(V3:V16) -> 1 | W18: =SUM(W3:W16) -> 16135.71 | X18: =SUM(X3:X16) -> 98721.55 | Y18: =IF(U18=0,0,X18/U18) -> 0.43 | Z18: =SUM(Z3:Z16) -> 24023.07 | AA18: ='Юнит 26-31.01'!AA18+'Юнит 01.02'!AA18 -> 58328.37 | AB18: =SUM(AB3:AB16) -> 0 | AC18: =SUM(AC3:AC16) -> 0 | AD18: =SUM(AD3:AD16) -> 2295.85 | AE18: =SUM(AE3:AE16) -> 31120.232 | AP18: =SUM(AP3:AP16) -> 0 | AZ18: 18592777
AA19: =SUM(AA3:AA16) -> 57288.588
AG21: =AVERAGEIF(AG20:AG20,"<>0",AG20:AG20) -> #DIV/0! | AH21: =AVERAGEIF(AH20:AH20,"<>0",AH20:AH20) -> #DIV/0! | AI21: =AVERAGEIF(AI20:AI20,"<>0",AI20:AI20) -> #DIV/0! | AJ21: =AVERAGEIF(AJ20:AJ20,"<>0",AJ20:AJ20) -> #DIV/0! | AK21: =AVERAGEIF(AK20:AK20,"<>0",AK20:AK20) -> #DIV/0! | AL21: =AVERAGEIF(AL20:AL20,"<>0",AL20:AL20) -> #DIV/0! | AM21: =AVERAGEIF(AM20:AM20,"<>0",AM20:AM20) -> #DIV/0! | AN21: =AVERAGEIF(AN20:AN20,"<>0",AN20:AN20) -> #DIV/0!
C22: =SUM(C20:C20) -> 0 | I22: =SUM(I20:I20) -> 0 | K22: =SUM(K20:K20) -> 0 | P22: =SUM(P20:P20) -> 0 | Q22: =SUM(Q20:Q20) -> 0 | R22: =SUM(R20:R20) -> 0 | S22: =SUM(S20:S20) -> 0 | T22: =SUM(T20:T20) -> 0 | U22: =SUM(U20:U20) -> 0 | V22: =SUM(V20:V20) -> 0 | W22: =SUM(W20:W20) -> 0 | X22: =SUM(X20:X20) -> 0 | Y22: =IF(U22=0,0,X22/U22) -> 0 | Z22: =SUM(Z20:Z20) -> 0 | AA22: =IFERROR(P22*AA24/P24,0) -> 0 | AB22: =SUM(AB20:AB20) -> 0 | AC22: =SUM(AC20:AC20) -> 0 | AD22: =SUM(AD20:AD20) -> 0 | AE22: =SUM(AE20:AE20) -> 0 | AP22: =SUM(AP20:AP20) -> 0
AA23: =SUM(AA20:AA20) -> 0
A24: ИТОГО | C24: =C18+C22 -> 0 | D24: =SUM(D3:D20) -> 0 | E24: =SUM(E3:E20) -> 108496 | F24: =SUM(F3:F20) -> 597 | G24: =SUM(G3:G20) -> 295 | I24: =I18+I22 -> 0 | J24: =J18+J22 -> 0 | K24: =K18+K22 -> 236 | P24: =P18+P22 -> 131 | Q24: =Q18+Q22 -> 3 | R24: =R18-R22 -> 128 | S24: =S18+S22 -> 234930 | T24: =T18+T22 -> -5345 | U24: =U18+U22 -> 229585 | V24: =V18+V22 -> 1 | W24: =W18+W22 -> 16135.71 | X24: =X18+X22 -> 98721.55 | Y24: =X24/U24 -> 0.43 | Z24: =Z18+Z22 -> 24023.07 | AA24: ='Юнит 26-31.01'!AA24+'Юнит 01.02'!AA24 -> 58328.37 | AC24: =SUM(AC3:AC20) -> 0 | AD24: =AD18+AD22 -> 2295.85 | AE24: =AE18+AE22 -> 31120.232 | AK24: =AA25/P24 -> 445.25473 | AP24: =SUM(AP3:AP20) -> 0
AA25: =AA18+AA22 -> 58328.37
AA26: =AA19+AA23 -> 57288.588
I29: Себестоимость остатков | K29: Прибыль с остатков | L29: Рентабельность товарных остатков
H31: до 60 дн | I31: =SUMIF(J3:J20,"<60",I3:I20) -> 0 | J31: =I31/I24 -> #DIV/0! | K31: =SUMIF(J3:J20,"<60",AP3:AP20) -> 0 | L31: =K31/I31 -> #DIV/0!
H32: 60-120 дн | I32: =I24-I33-I31 -> 0 | J32: =I32/I24 -> #DIV/0! | K32: =AP24-K31-K33 -> 0 | L32: =K32/I32 -> #DIV/0!
H33: > 120 дн | I33: =SUMIF(J3:J20,">120",I3:I20) -> 0 | J33: =I33/I24 -> #DIV/0! | K33: =SUMIF(J3:J20,">120",AP3:AP20) -> 0 | L33: =K33/I33 -> #DIV/0!
H35: Если товар на сайте менее 30 дней - оборачиваемость 0

Sheet Юнит 26-31.01
B1: 26-31.01 | AG1: на 1 единицу проданного товара
B2: Артикул поставщика | C2: Остаток на 01.02 | D2: В пути до клиента | E2: В пути от клиента | F2: Итого по складам ВБ | G2: Остаток на нашем складе на 02.09 | H2: Себетоимость на 1 ед на 29.09.25 | I2: Себестоимость остатков | J2: Оборачиваемость, дн | K2: Заказы, шт 6 дней | L2: Средняя цена, руб (столбец 32, AG) | M2: % выкупа за 7 дней (столбец 23, X) | N2: Скорость заказов | O2: Скорость продаж | P2: Кол-во ПРОДАЖИ | Q2: Кол-во ВОЗВРАТЫ | R2: Кол-во ПРОДАЖИ-ВОЗВРАТЫ | S2: Выручка ПРОДАЖИ | T2: Выручка ВОЗВРАТЫ | U2: Выручка с учетом согласованной скидки ПРОДАЖИ - ВОЗВРАТЫ | V2: Доля выручки, % от общего объема | W2: Себестоимость продаж | X2: Комиссия, руб | Y2: Комиссия, % | Z2: Логистика | AA2: Реклама | AB2: Хранение | AC2: Штрафы | AD2: Налог 1% | AE2: Прибыль | AG2: Выручка на 1 ед (средняя цена продажи со скидкой) | AH2: Себестоимость на 1 ед | AI2: Комиссия на 1 ед | AJ2: Логистика на 1 ед | AK2: Реклама на 1 ед | AL2: Прибыль на 1 ед | AM2: Маржинальность, % | AN2: Рентабельность, % | AP2: Прибыль с остатков
A3: 2676784153 | B3: черные с железкой классика | H3: 142.98 | I3: =C3*H3 -> 0 | K3: 4 | N3: =K3/6 -> 0.66666667 | O3: =R3/7 -> 0.14285714 | P3: =SUMIFS('Отчет 26-31.01'!H:H,'Отчет 26-31.01'!D:D,"Выручка",'Отчет 26-31.01'!E:E,B3) -> 1 | Q3: =SUMIFS('Отчет 26-31.01'!H:H,'Отчет 26-31.01'!D:D,"Возврат выручки",'Отчет 26-31.01'!E:E,B3) -> 0 | R3: =P3-Q3 -> 1 | S3: =SUMIFS('Отчет 26-31.01'!P:P,'Отчет 26-31.01'!C:C,"Продажи",'Отчет 26-31.01'!E:E,B3) -> 1750 | T3: =SUMIFS('Отчет 26-31.01'!P:P,'Отчет 26-31.01'!C:C,"Возвраты",'Отчет 26-31.01'!E:E,B3) -> 0 | U3: =S3+T3 -> 1750 | V3: =U3/$U$24 -> 0.0088849175 | W3: =R3*H3 -> 142.98 | X3: =-SUMIFS('Отчет 26-31.01'!P:P,'Отчет 26-31.01'!C:C,"Вознаграждение Ozon",'Отчет 26-31.01'!E:E,B3) -> 752.5 | Y3: =IF(U3=0,0,X3/U3) -> 0.43 | Z3: =-SUMIFS('Отчет 26-31.01'!P:P,'Отчет 26-31.01'!C:C,"Услуги доставки",'Отчет 26-31.01'!E:E,B3) -> 224.91 | AA3: 460 | AD3: =U3*1% -> 17.5 | AE3: =U3-W3-X3-Z3-AA3-AB3-AC3-AD3 -> 152.11 | AG3: =IF(R3=0,0,U3/R3) -> 1750 | AH3: =H3 -> 142.98 | AI3: =IF(R3=0,0,X3/R3) -> 752.5 | AJ3: =IF(P3=0,Z3/1,Z3/P3) -> 224.91 | AK3: =IF(P3=0,0,AA3/P3) -> 460 | AL3: =_xlfn.IFS(R3=0,AE3,R3<0,AE3/-R3,R3>0,AE3/R3) -> 152.11 | AM3: =IF(AG3=0,0,AL3/AG3) -> 0.08692 | AN3: =IF(AH3=0,0,AL3/AH3) -> 1.0638551 | AP3: =AL3*C3 -> 0
A4: 2676784638 | B4: qs черные | H4: 123.09 | I4: =C4*H4 -> 0 | K4: 4 | N4: =K4/7 -> 0.57142857 | O4: =R4/7 -> 0.57142857 | P4: =SUMIFS('Отчет 26-31.01'!H:H,'Отчет 26-31.01'!D:D,"Выручка",'Отчет 26-31.01'!E:E,B4) -> 4 | Q4: =SUMIFS('Отчет 26-31.01'!H:H,'Отчет 26-31.01'!D:D,"Возврат выручки",'Отчет 26-31.01'!E:E,B4) -> 0 | R4: =P4-Q4 -> 4 | S4: =SUMIFS('Отчет 26-31.01'!P:P,'Отчет 26-31.01'!C:C,"Продажи",'Отчет 26-31.01'!E:E,B4) -> 7000 | T4: =SUMIFS('Отчет 26-31.01'!P:P,'Отчет 26-31.01'!C:C,"Возвраты",'Отчет 26-31.01'!E:E,B4) -> 0 | U4: =S4+T4 -> 7000 | V4: =U4/$U$24 -> 0.03553967 | W4: =R4*H4 -> 492.36 | X4: =-SUMIFS('Отчет 26-31.01'!P:P,'Отчет 26-31.01'!C:C,"Вознаграждение Ozon",'Отчет 26-31.01'!E:E,B4) -> 3010 | Y4: =IF(U4=0,0,X4/U4) -> 0.43 | Z4: =-SUMIFS('Отчет 26-31.01'!P:P,'Отчет 26-31.01'!C:C,"Услуги доставки",'Отчет 26-31.01'!E:E,B4) -> 668.22 | AA4: 175 | AD4: =U4*1% -> 70 | AE4: =U4-W4-X4-Z4-AA4-AB4-AC4-AD4 -> 2584.42 | AG4: =IF(R4=0,0,U4/R4) -> 1750 | AH4: =H4 -> 123.09 | AI4: =IF(R4=0,0,X4/R4) -> 752.5 | AJ4: =IF(P4=0,Z4/1,Z4/P4) -> 167.055 | AK4: =IF(P4=0,0,AA4/P4) -> 43.75 | AL4: {=_xlfn.IFS(R4=0,AE4,R4<0,AE4/-R4,R4>0,AE4/R4)} -> 646.105 | AM4: =IF(AG4=0,0,AL4/AG4) -> 0.36920286 | AN4: =IF(AH4=0,0,AL4/AH4) -> 5.2490454 | AP4: =AL4*C4 -> 0
A5: 2676784504 | B5: qs синие | H5: 123.09 | I5: =C5*H5 -> 0 | K5: 1 | N5: =K5/7 -> 0.14285714 | O5: =R5/7 -> 0 | P5: =SUMIFS('Отчет 26-31.01'!H:H,'Отчет 26-31.01'!D:D,"Выручка",'Отчет 26-31.01'!E:E,B5) -> 0 | Q5: =SUMIFS('Отчет 26-31.01'!H:H,'Отчет 26-31.01'!D:D,"Возврат выручки",'Отчет 26-31.01'!E:E,B5) -> 0 | R5: =P5-Q5 -> 0 | S5: =SUMIFS('Отчет 26-31.01'!P:P,'Отчет 26-31.01'!C:C,"Продажи",'Отчет 26-31.01'!E:E,B5) -> 0 | T5: =SUMIFS('Отчет 26-31.01'!P:P,'Отчет 26-31.01'!C:C,"Возвраты",'Отчет 26-31.01'!E:E,B5) -> 0 | U5: =S5+T5 -> 0 | V5: =U5/$U$24 -> 0 | W5: =R5*H5 -> 0 | X5: =-SUMIFS('Отчет 26-31.01'!P:P,'Отчет 26-31.01'!C:C,"Вознаграждение Ozon",'Отчет 26-31.01'!E:E,B5) -> 0 | Y5: =IF(U5=0,0,X5/U5) -> 0 | Z5: =-SUMIFS('Отчет 26-31.01'!P:P,'Отчет 26-31.01'!C:C,"Услуги доставки",'Отчет 26-31.01'!E:E,B5) -> 0 | AA5: 0 | AD5: =U5*1% -> 0 | AE5: =U5-W5-X5-Z5-AA5-AB5-AC5-AD5 -> 0 | AG5: =IF(R5=0,0,U5/R5) -> 0 | AH5: =H5 -> 123.09 | AI5: =IF(R5=0,0,X5/R5) -> 0 | AJ5: =IF(P5=0,Z5/1,Z5/P5) -> 0 | AK5: =IF(P5=0,0,AA5/P5) -> 0 | AL5: {=_xlfn.IFS(R5=0,AE5,R5<0,AE5/-R5,R5>0,AE5/R5)} -> 0 | AM5: =IF(AG5=0,0,AL5/AG5) -> 0 | AN5: =IF(AH5=0,0,AL5/AH5) -> 0 | AP5: =AL5*C5 -> 0
A6: 2676784514 | B6: qs желтые | H6: 123.09 | I6: =C6*H6 -> 0 | K6: 11 | N6: =K6/7 -> 1.5714286 | O6: =R6/7 -> 0.85714286 | P6: =SUMIFS('Отчет 26-31.01'!H:H,'Отчет 26-31.01'!D:D,"Выручка",'Отчет 26-31.01'!E:E,B6) -> 6 | Q6: =SUMIFS('Отчет 26-31.01'!H:H,'Отчет 26-31.01'!D:D,"Возврат выручки",'Отчет 26-31.01'!E:E,B6) -> 0 | R6: =P6-Q6 -> 6 | S6: =SUMIFS('Отчет 26-31.01'!P:P,'Отчет 26-31.01'!C:C,"Продажи",'Отчет 26-31.01'!E:E,B6) -> 10500 | T6: =SUMIFS('Отчет 26-31.01'!P:P,'Отчет 26-31.01'!C:C,"Возвраты",'Отчет 26-31.01'!E:E,B6) -> 0 | U6: =S6+T6 -> 10500 | V6: =U6/$U$24 -> 0.053309505 | W6: =R6*H6 -> 738.54 | X6: =-SUMIFS('Отчет 26-31.01'!P:P,'Отчет 26-31.01'!C:C,"Вознаграждение Ozon",'Отчет 26-31.01'!E:E,B6) -> 4515 | Y6: =IF(U6=0,0,X6/U6) -> 0.43 | Z6: =-SUMIFS('Отчет 26-31.01'!P:P,'Отчет 26-31.01'!C:C,"Услуги доставки",'Отчет 26-31.01'!E:E,B6) -> 1132.6 | AA6: 2817.5 | AD6: =U6*1% -> 105 | AE6: =U6-W6-X6-Z6-AA6-AB6-AC6-AD6 -> 1191.36 | AG6: =IF(R6=0,0,U6/R6) -> 1750 | AH6: =H6 -> 123.09 | AI6: =IF(R6=0,0,X6/R6) -> 752.5 | AJ6: =IF(P6=0,Z6/1,Z6/P6) -> 188.76667 | AK6: =IF(P6=0,0,AA6/P6) -> 469.58333 | AL6: {=_xlfn.IFS(R6=0,AE6,R6<0,AE6/-R6,R6>0,AE6/R6)} -> 198.56 | AM6: =IF(AG6=0,0,AL6/AG6) -> 0.11346286 | AN6: =IF(AH6=0,0,AL6/AH6) -> 1.6131286 | AP6: =AL6*C6 -> 0
A7: 2676784181 | B7: qs коричневые | H7: 117.24 | I7: =C7*H7 -> 0 | K7: 30 | N7: =K7/7 -> 4.2857143 | O7: =R7/7 -> 2.1428571 | P7: =SUMIFS('Отчет 26-31.01'!H:H,'Отчет 26-31.01'!D:D,"Выручка",'Отчет 26-31.01'!E:E,B7) -> 16 | Q7: =SUMIFS('Отчет 26-31.01'!H:H,'Отчет 26-31.01'!D:D,"Возврат выручки",'Отчет 26-31.01'!E:E,B7) -> 1 | R7: =P7-Q7 -> 15 | S7: =SUMIFS('Отчет 26-31.01'!P:P,'Отчет 26-31.01'!C:C,"Продажи",'Отчет 26-31.01'!E:E,B7) -> 27825 | T7: =SUMIFS('Отчет 26-31.01'!P:P,'Отчет 26-31.01'!C:C,"Возвраты",'Отчет 26-31.01'!E:E,B7) -> -1750 | U7: =S7+T7 -> 26075 | V7: =U7/$U$24 -> 0.13238527 | W7: =R7*H7 -> 1758.6 | X7: =-SUMIFS('Отчет 26-31.01'!P:P,'Отчет 26-31.01'!C:C,"Вознаграждение Ozon",'Отчет 26-31.01'!E:E,B7) -> 11212.25 | Y7: =IF(U7=0,0,X7/U7) -> 0.43 | Z7: =-SUMIFS('Отчет 26-31.01'!P:P,'Отчет 26-31.01'!C:C,"Услуги доставки",'Отчет 26-31.01'!E:E,B7) -> 3167.88 | AA7: 9223.1513 | AD7: =U7*1% -> 260.75 | AE7: =U7-W7-X7-Z7-AA7-AB7-AC7-AD7 -> 452.36868 | AG7: =IF(R7=0,0,U7/R7) -> 1738.3333 | AH7: =H7 -> 117.24 | AI7: =IF(R7=0,0,X7/R7) -> 747.48333 | AJ7: =IF(P7=0,Z7/1,Z7/P7) -> 197.9925 | AK7: =IF(P7=0,0,AA7/P7) -> 576.44696 | AL7: {=_xlfn.IFS(R7=0,AE7,R7<0,AE7/-R7,R7>0,AE7/R7)} -> 30.157912 | AM7: =IF(AG7=0,0,AL7/AG7) -> 0.017348751 | AN7: =IF(AH7=0,0,AL7/AH7) -> 0.25723228 | AP7: =AL7*C7 -> 0
A8: 2676783005 | B8: MR8854 C2 | H8: 169.89 | I8: =C8*H8 -> 0 | K8: 17 | N8: =K8/7 -> 2.4285714 | O8: =R8/7 -> 1.2857143 | P8: =SUMIFS('Отчет 26-31.01'!H:H,'Отчет 26-31.01'!D:D,"Выручка",'Отчет 26-31.01'!E:E,B8) -> 9 | Q8: =SUMIFS('Отчет 26-31.01'!H:H,'Отчет 26-31.01'!D:D,"Возврат выручки",'Отчет 26-31.01'!E:E,B8) -> 0 | R8: =P8-Q8 -> 9 | S8: =SUMIFS('Отчет 26-31.01'!P:P,'Отчет 26-31.01'!C:C,"Продажи",'Отчет 26-31.01'!E:E,B8) -> 15750 | T8: =SUMIFS('Отчет 26-31.01'!P:P,'Отчет 26-31.01'!C:C,"Возвраты",'Отчет 26-31.01'!E:E,B8) -> 0 | U8: =S8+T8 -> 15750 | V8: =U8/$U$24 -> 0.079964257 | W8: =R8*H8 -> 1529.01 | X8: =-SUMIFS('Отчет 26-31.01'!P:P,'Отчет 26-31.01'!C:C,"Вознаграждение Ozon",'Отчет 26-31.01'!E:E,B8) -> 6772.5 | Y8: =IF(U8=0,0,X8/U8) -> 0.43 | Z8: =-SUMIFS('Отчет 26-31.01'!P:P,'Отчет 26-31.01'!C:C,"Услуги доставки",'Отчет 26-31.01'!E:E,B8) -> 1550.87 | AA8: 3607.2598 | AD8: =U8*1% -> 157.5 | AE8: =U8-W8-X8-Z8-AA8-AB8-AC8-AD8 -> 2132.8602 | AG8: =IF(R8=0,0,U8/R8) -> 1750 | AH8: =H8 -> 169.89 | AI8: =IF(R8=0,0,X8/R8) -> 752.5 | AJ8: =IF(P8=0,Z8/1,Z8/P8) -> 172.31889 | AK8: =IF(P8=0,0,AA8/P8) -> 400.80665 | AL8: {=_xlfn.IFS(R8=0,AE8,R8<0,AE8/-R8,R8>0,AE8/R8)} -> 236.98446 | AM8: =IF(AG8=0,0,AL8/AG8) -> 0.13541969 | AN8: =IF(AH8=0,0,AL8/AH8) -> 1.3949289 | AP8: =AL8*C8 -> 0
A9: 3405092860 | B9: th черн | H9: 123 | I9: =C9*H9 -> 0 | K9: 4 | N9: =K9/7 -> 0.57142857 | O9: =R9/7 -> 0.14285714 | P9: =SUMIFS('Отчет 26-31.01'!H:H,'Отчет 26-31.01'!D:D,"Выручка",'Отчет 26-31.01'!E:E,B9) -> 1 | Q9: =SUMIFS('Отчет 26-31.01'!H:H,'Отчет 26-31.01'!D:D,"Возврат выручки",'Отчет 26-31.01'!E:E,B9) -> 0 | R9: =P9-Q9 -> 1 | S9: =SUMIFS('Отчет 26-31.01'!P:P,'Отчет 26-31.01'!C:C,"Продажи",'Отчет 26-31.01'!E:E,B9) -> 2000 | T9: =SUMIFS('Отчет 26-31.01'!P:P,'Отчет 26-31.01'!C:C,"Возвраты",'Отчет 26-31.01'!E:E,B9) -> 0 | U9: =S9+T9 -> 2000 | V9: =U9/$U$24 -> 0.010154191 | W9: =R9*H9 -> 123 | X9: =-SUMIFS('Отчет 26-31.01'!P:P,'Отчет 26-31.01'!C:C,"Вознаграждение Ozon",'Отчет 26-31.01'!E:E,B9) -> 860 | Y9: =IF(U9=0,0,X9/U9) -> 0.43 | Z9: =-SUMIFS('Отчет 26-31.01'!P:P,'Отчет 26-31.01'!C:C,"Услуги доставки",'Отчет 26-31.01'!E:E,B9) -> 155.81 | AA9: 556.81946 | AD9: =U9*1% -> 20 | AE9: =U9-W9-X9-Z9-AA9-AB9-AC9-AD9 -> 284.37054 | AG9: =IF(R9=0,0,U9/R9) -> 2000 | AH9: =H9 -> 123 | AI9: =IF(R9=0,0,X9/R9) -> 860 | AJ9: =IF(P9=0,Z9/1,Z9/P9) -> 155.81 | AK9: =IF(P9=0,0,AA9/P9) -> 556.81946 | AL9: {=_xlfn.IFS(R9=0,AE9,R9<0,AE9/-R9,R9>0,AE9/R9)} -> 284.37054 | AM9: =IF(AG9=0,0,AL9/AG9) -> 0.14218527 | AN9: =IF(AH9=0,0,AL9/AH9) -> 2.3119556 | AP9: =AL9*C9 -> 0
A10: 3405092836 | B10: th син | H10: 123 | I10: =C10*H10 -> 0 | K10: 6 | N10: =K10/7 -> 0.85714286 | O10: =R10/7 -> 0 | P10: =SUMIFS('Отчет 26-31.01'!H:H,'Отчет 26-31.01'!D:D,"Выручка",'Отчет 26-31.01'!E:E,B10) -> 0 | Q10: =SUMIFS('Отчет 26-31.01'!H:H,'Отчет 26-31.01'!D:D,"Возврат выручки",'Отчет 26-31.01'!E:E,B10) -> 0 | R10: =P10-Q10 -> 0 | S10: =SUMIFS('Отчет 26-31.01'!P:P,'Отчет 26-31.01'!C:C,"Продажи",'Отчет 26-31.01'!E:E,B10) -> 0 | T10: =SUMIFS('Отчет 26-31.01'!P:P,'Отчет 26-31.01'!C:C,"Возвраты",'Отчет 26-31.01'!E:E,B10) -> 0 | U10: =S10+T10 -> 0 | V10: =U10/$U$24 -> 0 | W10: =R10*H10 -> 0 | X10: =-SUMIFS('Отчет 26-31.01'!P:P,'Отчет 26-31.01'!C:C,"Вознаграждение Ozon",'Отчет 26-31.01'!E:E,B10) -> 0 | Y10: =IF(U10=0,0,X10/U10) -> 0 | Z10: =-SUMIFS('Отчет 26-31.01'!P:P,'Отчет 26-31.01'!C:C,"Услуги доставки",'Отчет 26-31.01'!E:E,B10) -> 0 | AA10: 1517.4339 | AD10: =U10*1% -> 0 | AE10: =U10-W10-X10-Z10-AA10-AB10-AC10-AD10 -> -1517.4339 | AG10: =IF(R10=0,0,U10/R10) -> 0 | AH10: =H10 -> 123 | AI10: =IF(R10=0,0,X10/R10) -> 0 | AJ10: =IF(P10=0,Z10/1,Z10/P10) -> 0 | AK10: =IF(P10=0,0,AA10/P10) -> 0 | AL10: {=_xlfn.IFS(R10=0,AE10,R10<0,AE10/-R10,R10>0,AE10/R10)} -> -1517.4339 | AM10: =IF(AG10=0,0,AL10/AG10) -> 0 | AN10: =IF(AH10=0,0,AL10/AH10) -> -12.336861 | AP10: =AL10*C10 -> 0
A11: 3064346962 | B11: th желт | H11: 123 | I11: =C11*H11 -> 0 | K11: 59 | N11: =K11/7 -> 8.4285714 | O11: =R11/7 -> 5.7142857 | P11: =SUMIFS('Отчет 26-31.01'!H:H,'Отчет 26-31.01'!D:D,"Выручка",'Отчет 26-31.01'!E:E,B11) -> 40 | Q11: =SUMIFS('Отчет 26-31.01'!H:H,'Отчет 26-31.01'!D:D,"Возврат выручки",'Отчет 26-31.01'!E:E,B11) -> 0 | R11: =P11-Q11 -> 40 | S11: =SUMIFS('Отчет 26-31.01'!P:P,'Отчет 26-31.01'!C:C,"Продажи",'Отчет 26-31.01'!E:E,B11) -> 72075 | T11: =SUMIFS('Отчет 26-31.01'!P:P,'Отчет 26-31.01'!C:C,"Возвраты",'Отчет 26-31.01'!E:E,B11) -> 0 | U11: =S11+T11 -> 72075 | V11: =U11/$U$24 -> 0.36593167 | W11: =R11*H11 -> 4920 | X11: =-SUMIFS('Отчет 26-31.01'!P:P,'Отчет 26-31.01'!C:C,"Вознаграждение Ozon",'Отчет 26-31.01'!E:E,B11) -> 30992.25 | Y11: =IF(U11=0,0,X11/U11) -> 0.43 | Z11: =-SUMIFS('Отчет 26-31.01'!P:P,'Отчет 26-31.01'!C:C,"Услуги доставки",'Отчет 26-31.01'!E:E,B11) -> 6782.38 | AA11: 16128.437 | AD11: =U11*1% -> 720.75 | AE11: =U11-W11-X11-Z11-AA11-AB11-AC11-AD11 -> 12531.183 | AG11: =IF(R11=0,0,U11/R11) -> 1801.875 | AH11: =H11 -> 123 | AI11: =IF(R11=0,0,X11/R11) -> 774.80625 | AJ11: =IF(P11=0,Z11/1,Z11/P11) -> 169.5595 | AK11: =IF(P11=0,0,AA11/P11) -> 403.21094 | AL11: {=_xlfn.IFS(R11=0,AE11,R11<0,AE11/-R11,R11>0,AE11/R11)} -> 313.27956 | AM11: =IF(AG11=0,0,AL11/AG11) -> 0.1738631 | AN11: =IF(AH11=0,0,AL11/AH11) -> 2.5469883 | AP11: =AL11*C11 -> 0
A12: 3405092873 | B12: th коричн | H12: 117 | I12: =C12*H12 -> 0 | K12: 5 | N12: =K12/7 -> 0.71428571 | O12: =R12/7 -> 0 | P12: =SUMIFS('Отчет 26-31.01'!H:H,'Отчет 26-31.01'!D:D,"Выручка",'Отчет 26-31.01'!E:E,B12) -> 0 | Q12: =SUMIFS('Отчет 26-31.01'!H:H,'Отчет 26-31.01'!D:D,"Возврат выручки",'Отчет 26-31.01'!E:E,B12) -> 0 | R12: =P12-Q12 -> 0 | S12: =SUMIFS('Отчет 26-31.01'!P:P,'Отчет 26-31.01'!C:C,"Продажи",'Отчет 26-31.01'!E:E,B12) -> 0 | T12: =SUMIFS('Отчет 26-31.01'!P:P,'Отчет 26-31.01'!C:C,"Возвраты",'Отчет 26-31.01'!E:E,B12) -> 0 | U12: =S12+T12 -> 0 | V12: =U12/$U$24 -> 0 | W12: =R12*H12 -> 0 | X12: =-SUMIFS('Отчет 26-31.01'!P:P,'Отчет 26-31.01'!C:C,"Вознаграждение Ozon",'Отчет 26-31.01'!E:E,B12) -> 0 | Y12: =IF(U12=0,0,X12/U12) -> 0 | Z12: =-SUMIFS('Отчет 26-31.01'!P:P,'Отчет 26-31.01'!C:C,"Услуги доставки",'Отчет 26-31.01'!E:E,B12) -> 0 | AA12: 555.84386 | AD12: =U12*1% -> 0 | AE12: =U12-W12-X12-Z12-AA12-AB12-AC12-AD12 -> -555.84386 | AG12: =IF(R12=0,0,U12/R12) -> 0 | AH12: =H12 -> 117 | AI12: =IF(R12=0,0,X12/R12) -> 0 | AJ12: =IF(P12=0,Z12/1,Z12/P12) -> 0 | AK12: =IF(P12=0,0,AA12/P12) -> 0 | AL12: {=_xlfn.IFS(R12=0,AE12,R12<0,AE12/-R12,R12>0,AE12/R12)} -> -555.84386 | AM12: =IF(AG12=0,0,AL12/AG12) -> 0 | AN12: =IF(AH12=0,0,AL12/AH12) -> -4.7508022 | AP12: =AL12*C12 -> 0
A13: 3405092993 | B13: flip черный | H13: 123 | I13: =C13*H13 -> 0 | K13: 2 | N13: =K13/7 -> 0.28571429 | O13: =R13/7 -> 0.14285714 | P13: =SUMIFS('Отчет 26-31.01'!H:H,'Отчет 26-31.01'!D:D,"Выручка",'Отчет 26-31.01'!E:E,B13) -> 1 | Q13: =SUMIFS('Отчет 26-31.01'!H:H,'Отчет 26-31.01'!D:D,"Возврат выручки",'Отчет 26-31.01'!E:E,B13) -> 0 | R13: =P13-Q13 -> 1 | S13: =SUMIFS('Отчет 26-31.01'!P:P,'Отчет 26-31.01'!C:C,"Продажи",'Отчет 26-31.01'!E:E,B13) -> 2000 | T13: =SUMIFS('Отчет 26-31.01'!P:P,'Отчет 26-31.01'!C:C,"Возвраты",'Отчет 26-31.01'!E:E,B13) -> 0 | U13: =S13+T13 -> 2000 | V13: =U13/$U$24 -> 0.010154191 | W13: =R13*H13 -> 123 | X13: =-SUMIFS('Отчет 26-31.01'!P:P,'Отчет 26-31.01'!C:C,"Вознаграждение Ozon",'Отчет 26-31.01'!E:E,B13) -> 860 | Y13: =IF(U13=0,0,X13/U13) -> 0.43 | Z13: =-SUMIFS('Отчет 26-31.01'!P:P,'Отчет 26-31.01'!C:C,"Услуги доставки",'Отчет 26-31.01'!E:E,B13) -> 155.81 | AA13: 633.38405 | AD13: =U13*1% -> 20 | AE13: =U13-W13-X13-Z13-AA13-AB13-AC13-AD13 -> 207.80595 | AG13: =IF(R13=0,0,U13/R13) -> 2000 | AH13: =H13 -> 123 | AI13: =IF(R13=0,0,X13/R13) -> 860 | AJ13: =IF(P13=0,Z13/1,Z13/P13) -> 155.81 | AK13: =IF(P13=0,0,AA13/P13) -> 633.38405 | AL13: {=_xlfn.IFS(R13=0,AE13,R13<0,AE13/-R13,R13>0,AE13/R13)} -> 207.80595 | AM13: =IF(AG13=0,0,AL13/AG13) -> 0.10390297 | AN13: =IF(AH13=0,0,AL13/AH13) -> 1.6894793 | AP13: =AL13*C13 -> 0
A14: 3405092868 | B14: flip синий | H14: 123 | I14: =C14*H14 -> 0 | K14: 0 | N14: =K14/7 -> 0 | O14: =R14/7 -> 0 | P14: =SUMIFS('Отчет 26-31.01'!H:H,'Отчет 26-31.01'!D:D,"Выручка",'Отчет 26-31.01'!E:E,B14) -> 0 | Q14: =SUMIFS('Отчет 26-31.01'!H:H,'Отчет 26-31.01'!D:D,"Возврат выручки",'Отчет 26-31.01'!E:E,B14) -> 0 | R14: =P14-Q14 -> 0 | S14: =SUMIFS('Отчет 26-31.01'!P:P,'Отчет 26-31.01'!C:C,"Продажи",'Отчет 26-31.01'!E:E,B14) -> 0 | T14: =SUMIFS('Отчет 26-31.01'!P:P,'Отчет 26-31.01'!C:C,"Возвраты",'Отчет 26-31.01'!E:E,B14) -> 0 | U14: =S14+T14 -> 0 | V14: =U14/$U$24 -> 0 | W14: =R14*H14 -> 0 | X14: =-SUMIFS('Отчет 26-31.01'!P:P,'Отчет 26-31.01'!C:C,"Вознаграждение Ozon",'Отчет 26-31.01'!E:E,B14) -> 0 | Y14: =IF(U14=0,0,X14/U14) -> 0 | Z14: =-SUMIFS('Отчет 26-31.01'!P:P,'Отчет 26-31.01'!C:C,"Услуги доставки",'Отчет 26-31.01'!E:E,B14) -> 0 | AA14: 607.06546 | AD14: =U14*1% -> 0 | AE14: =U14-W14-X14-Z14-AA14-AB14-AC14-AD14 -> -607.06546 | AG14: =IF(R14=0,0,U14/R14) -> 0 | AH14: =H14 -> 123 | AI14: =IF(R14=0,0,X14/R14) -> 0 | AJ14: =IF(P14=0,Z14/1,Z14/P14) -> 0 | AK14: =IF(P14=0,0,AA14/P14) -> 0 | AL14: {=_xlfn.IFS(R14=0,AE14,R14<0,AE14/-R14,R14>0,AE14/R14)} -> -607.06546 | AM14: =IF(AG14=0,0,AL14/AG14) -> 0 | AN14: =IF(AH14=0,0,AL14/AH14) -> -4.9354915 | AP14: =AL14*C14 -> 0
A15: 3064346642 | B15: flip жел | H15: 123 | I15: =C15*H15 -> 0 | K15: 55 | N15: =K15/7 -> 7.8571429 | O15: =R15/7 -> 4.7142857 | P15: =SUMIFS('Отчет 26-31.01'!H:H,'Отчет 26-31.01'!D:D,"Выручка",'Отчет 26-31.01'!E:E,B15) -> 34 | Q15: =SUMIFS('Отчет 26-31.01'!H:H,'Отчет 26-31.01'!D:D,"Возврат выручки",'Отчет 26-31.01'!E:E,B15) -> 1 | R15: =P15-Q15 -> 33 | S15: =SUMIFS('Отчет 26-31.01'!P:P,'Отчет 26-31.01'!C:C,"Продажи",'Отчет 26-31.01'!E:E,B15) -> 61658 | T15: =SUMIFS('Отчет 26-31.01'!P:P,'Отчет 26-31.01'!C:C,"Возвраты",'Отчет 26-31.01'!E:E,B15) -> -1845 | U15: =S15+T15 -> 59813 | V15: =U15/$U$24 -> 0.30367632 | W15: =R15*H15 -> 4059 | X15: =-SUMIFS('Отчет 26-31.01'!P:P,'Отчет 26-31.01'!C:C,"Вознаграждение Ozon",'Отчет 26-31.01'!E:E,B15) -> 25719.59 | Y15: =IF(U15=0,0,X15/U15) -> 0.43 | Z15: =-SUMIFS('Отчет 26-31.01'!P:P,'Отчет 26-31.01'!C:C,"Услуги доставки",'Отчет 26-31.01'!E:E,B15) -> 7005.07 | AA15: 12274.135 | AD15: =U15*1% -> 598.13 | AE15: =U15-W15-X15-Z15-AA15-AB15-AC15-AD15 -> 10157.075 | AG15: =IF(R15=0,0,U15/R15) -> 1812.5152 | AH15: =H15 -> 123 | AI15: =IF(R15=0,0,X15/R15) -> 779.38152 | AJ15: =IF(P15=0,Z15/1,Z15/P15) -> 206.03147 | AK15: =IF(P15=0,0,AA15/P15) -> 361.00398 | AL15: {=_xlfn.IFS(R15=0,AE15,R15<0,AE15/-R15,R15>0,AE15/R15)} -> 307.79014 | AM15: =IF(AG15=0,0,AL15/AG15) -> 0.16981383 | AN15: =IF(AH15=0,0,AL15/AH15) -> 2.5023589 | AP15: =AL15*C15 -> 0
A16: 3405092287 | B16: flip коричневый | H16: 117 | I16: =C16*H16 -> 0 | K16: 2 | N16: =K16/7 -> 0.28571429 | O16: =R16/7 -> 0 | P16: =SUMIFS('Отчет 26-31.01'!H:H,'Отчет 26-31.01'!D:D,"Выручка",'Отчет 26-31.01'!E:E,B16) -> 0 | Q16: =SUMIFS('Отчет 26-31.01'!H:H,'Отчет 26-31.01'!D:D,"Возврат выручки",'Отчет 26-31.01'!E:E,B16) -> 0 | R16: =P16-Q16 -> 0 | S16: =SUMIFS('Отчет 26-31.01'!P:P,'Отчет 26-31.01'!C:C,"Продажи",'Отчет 26-31.01'!E:E,B16) -> 0 | T16: =SUMIFS('Отчет 26-31.01'!P:P,'Отчет 26-31.01'!C:C,"Возвраты",'Отчет 26-31.01'!E:E,B16) -> 0 | U16: =S16+T16 -> 0 | V16: =U16/$U$24 -> 0 | W16: =R16*H16 -> 0 | X16: =-SUMIFS('Отчет 26-31.01'!P:P,'Отчет 26-31.01'!C:C,"Вознаграждение Ozon",'Отчет 26-31.01'!E:E,B16) -> 0 | Y16: =IF(U16=0,0,X16/U16) -> 0 | Z16: =-SUMIFS('Отчет 26-31.01'!P:P,'Отчет 26-31.01'!C:C,"Услуги доставки",'Отчет 26-31.01'!E:E,B16) -> 0 | AA16: 1324.8447 | AD16: =U16*1% -> 0 | AE16: =U16-W16-X16-Z16-AA16-AB16-AC16-AD16 -> -1324.8447 | AG16: =IF(R16=0,0,U16/R16) -> 0 | AH16: =H16 -> 117 | AI16: =IF(R16=0,0,X16/R16) -> 0 | AJ16: =IF(P16=0,Z16/1,Z16/P16) -> 0 | AK16: =IF(P16=0,0,AA16/P16) -> 0 | AL16: {=_xlfn.IFS(R16=0,AE16,R16<0,AE16/-R16,R16>0,AE16/R16)} -> -1324.8447 | AM16: =IF(AG16=0,0,AL16/AG16) -> 0 | AN16: =IF(AH16=0,0,AL16/AH16) -> -11.323459 | AP16: =AL16*C16 -> 0
AG17: =AVERAGEIF(AG3:AG15,"<>0",AG3:AG15) -> 1816.9693 | AH17: =AVERAGEIF(AH3:AH15,"<>0",AH3:AH15) -> 127.26 | AI17: =AVERAGEIF(AI3:AI15,"<>0",AI3:AI15) -> 781.29679 | AJ17: =AVERAGEIF(AJ3:AJ15,"<>0",AJ3:AJ15) -> 182.02823 | AK17: =AVERAGEIF(AK3:AK15,"<>0",AK3:AK15) -> 433.88948 | AL17: =AVERAGEIF(AL3:AL15,"<>0",AL3:AL15) -> -25.264967 | AM17: =AVERAGEIF(AM3:AM15,"<>0",AM3:AM15) -> 0.14579104 | AN17: =AVERAGEIF(AN3:AN15,"<>0",AN3:AN15) -> -0.28284851
A18: Итого очки | C18: =SUM(C3:C16) -> 0 | E18: 108496 | F18: 597 | G18: 295 | I18: =SUM(I3:I16) -> 0 | K18: =SUM(K3:K16) -> 200 | P18: =SUM(P3:P16) -> 112 | Q18: =SUM(Q3:Q16) -> 2 | R18: =SUM(R3:R16) -> 110 | S18: =SUM(S3:S16) -> 200558 | T18: =SUM(T3:T16) -> -3595 | U18: =SUM(U3:U16) -> 196963 | V18: =SUM(V3:V16) -> 1 | W18: =SUM(W3:W16) -> 13886.49 | X18: =SUM(X3:X16) -> 84694.09 | Y18: =IF(U18=0,0,X18/U18) -> 0.43 | Z18: =SUM(Z3:Z16) -> 20843.55 | AA18: =IFERROR(P18*AA24/P24,0) -> 50770.67 | AB18: =SUM(AB3:AB16) -> 0 | AC18: =SUM(AC3:AC16) -> 0 | AD18: =SUM(AD3:AD16) -> 1969.63 | AE18: =SUM(AE3:AE16) -> 25688.365 | AP18: =SUM(AP3:AP16) -> 0 | AZ18: 18592777
AA19: =SUM(AA3:AA16) -> 49880.875
AG21: =AVERAGEIF(AG20:AG20,"<>0",AG20:AG20) -> #DIV/0! | AH21: =AVERAGEIF(AH20:AH20,"<>0",AH20:AH20) -> #DIV/0! | AI21: =AVERAGEIF(AI20:AI20,"<>0",AI20:AI20) -> #DIV/0! | AJ21: =AVERAGEIF(AJ20:AJ20,"<>0",AJ20:AJ20) -> #DIV/0! | AK21: =AVERAGEIF(AK20:AK20,"<>0",AK20:AK20) -> #DIV/0! | AL21: =AVERAGEIF(AL20:AL20,"<>0",AL20:AL20) -> #DIV/0! | AM21: =AVERAGEIF(AM20:AM20,"<>0",AM20:AM20) -> #DIV/0! | AN21: =AVERAGEIF(AN20:AN20,"<>0",AN20:AN20) -> #DIV/0!
C22: =SUM(C20:C20) -> 0 | I22: =SUM(I20:I20) -> 0 | K22: =SUM(K20:K20) -> 0 | P22: =SUM(P20:P20) -> 0 | Q22: =SUM(Q20:Q20) -> 0 | R22: =SUM(R20:R20) -> 0 | S22: =SUM(S20:S20) -> 0 | T22: =SUM(T20:T20) -> 0 | U22: =SUM(U20:U20) -> 0 | V22: =SUM(V20:V20) -> 0 | W22: =SUM(W20:W20) -> 0 | X22: =SUM(X20:X20) -> 0 | Y22: =IF(U22=0,0,X22/U22) -> 0 | Z22: =SUM(Z20:Z20) -> 0 | AA22: =IFERROR(P22*AA24/P24,0) -> 0 | AB22: =SUM(AB20:AB20) -> 0 | AC22: =SUM(AC20:AC20) -> 0 | AD22: =SUM(AD20:AD20) -> 0 | AE22: =SUM(AE20:AE20) -> 0 | AP22: =SUM(AP20:AP20) -> 0
AA23: =SUM(AA20:AA20) -> 0
A24: ИТОГО | C24: =C18+C22 -> 0 | D24: =SUM(D3:D20) -> 0 | E24: =SUM(E3:E20) -> 108496 | F24: =SUM(F3:F20) -> 597 | G24: =SUM(G3:G20) -> 295 | I24: =I18+I22 -> 0 | J24: =J18+J22 -> 0 | K24: =K18+K22 -> 200 | P24: =P18+P22 -> 112 | Q24: =Q18+Q22 -> 2 | R24: =R18-R22 -> 110 | S24: =S18+S22 -> 200558 | T24: =T18+T22 -> -3595 | U24: =U18+U22 -> 196963 | V24: =V18+V22 -> 1 | W24: =W18+W22 -> 13886.49 | X24: =X18+X22 -> 84694.09 | Y24: =X24/U24 -> 0.43 | Z24: =Z18+Z22 -> 20843.55 | AA24: 50770.67 | AC24: =SUM(AC3:AC20) -> 0 | AD24: =AD18+AD22 -> 1969.63 | AE24: =AE18+AE22 -> 25688.365 | AK24: =AA25/P24 -> 453.30955 | AP24: =SUM(AP3:AP20) -> 0
AA25: =AA18+AA22 -> 50770.67
AA26: =AA19+AA23 -> 49880.875
I29: Себестоимость остатков | K29: Прибыль с остатков | L29: Рентабельность товарных остатков
H31: до 60 дн | I31: =SUMIF(J3:J20,"<60",I3:I20) -> 0 | J31: =I31/I24 -> #DIV/0! | K31: =SUMIF(J3:J20,"<60",AP3:AP20) -> 0 | L31: =K31/I31 -> #DIV/0!
H32: 60-120 дн | I32: =I24-I33-I31 -> 0 | J32: =I32/I24 -> #DIV/0! | K32: =AP24-K31-K33 -> 0 | L32: =K32/I32 -> #DIV/0!
H33: > 120 дн | I33: =SUMIF(J3:J20,">120",I3:I20) -> 0 | J33: =I33/I24 -> #DIV/0! | K33: =SUMIF(J3:J20,">120",AP3:AP20) -> 0 | L33: =K33/I33 -> #DIV/0!
H35: Если товар на сайте менее 30 дней - оборачиваемость 0

Sheet Юнит 19-25.01
B1: 19-25.01 | AG1: на 1 единицу проданного товара
B2: Артикул поставщика | C2: Остаток на 26.01 | D2: В пути до клиента | E2: В пути от клиента | F2: Итого по складам ВБ | G2: Остаток на нашем складе на 02.09 | H2: Себетоимость на 1 ед на 29.09.25 | I2: Себестоимость остатков | J2: Оборачиваемость, дн | K2: Заказы, шт 7 дней | L2: Средняя цена, руб (столбец 32, AG) | M2: % выкупа за 7 дней (столбец 23, X) | N2: Скорость заказов | O2: Скорость продаж | P2: Кол-во ПРОДАЖИ | Q2: Кол-во ВОЗВРАТЫ | R2: Кол-во ПРОДАЖИ-ВОЗВРАТЫ | S2: Выручка ПРОДАЖИ | T2: Выручка ВОЗВРАТЫ | U2: Выручка с учетом согласованной скидки ПРОДАЖИ - ВОЗВРАТЫ | V2: Доля выручки, % от общего объема | W2: Себестоимость продаж | X2: Комиссия, руб | Y2: Комиссия, % | Z2: Логистика | AA2: Реклама | AB2: Хранение | AC2: Штрафы | AD2: Налог 1% | AE2: Прибыль | AG2: Выручка на 1 ед (средняя цена продажи со скидкой) | AH2: Себестоимость на 1 ед | AI2: Комиссия на 1 ед | AJ2: Логистика на 1 ед | AK2: Реклама на 1 ед | AL2: Прибыль на 1 ед | AM2: Маржинальность, % | AN2: Рентабельность, % | AP2: Прибыль с остатков
A3: 2676784153 | B3: черные с железкой классика | C3: 370 | H3: 142.98 | I3: =C3*H3 -> 52902.6 | K3: 3 | N3: =K3/7 -> 0.42857143 | O3: =R3/7 -> 0.71428571 | P3: =SUMIFS('Отчет 19-25.01'!H:H,'Отчет 19-25.01'!D:D,"Выручка",'Отчет 19-25.01'!E:E,B3) -> 5 | Q3: =SUMIFS('Отчет 19-25.01'!H:H,'Отчет 19-25.01'!D:D,"Возврат выручки",'Отчет 19-25.01'!E:E,B3) -> 0 | R3: =P3-Q3 -> 5 | S3: =SUMIFS('Отчет 19-25.01'!P:P,'Отчет 19-25.01'!C:C,"Продажи",'Отчет 19-25.01'!E:E,B3) -> 8046 | T3: =SUMIFS('Отчет 19-25.01'!P:P,'Отчет 19-25.01'!C:C,"Возвраты",'Отчет 19-25.01'!E:E,B3) -> 0 | U3: =S3+T3 -> 8046 | V3: =U3/$U$24 -> 0.05093082 | W3: =R3*H3 -> 714.9 | X3: =-SUMIFS('Отчет 19-25.01'!P:P,'Отчет 19-25.01'!C:C,"Вознаграждение Ozon",'Отчет 19-25.01'!E:E,B3) -> 3459.78 | Y3: =IF(U3=0,0,X3/U3) -> 0.43 | Z3: =-SUMIFS('Отчет 19-25.01'!P:P,'Отчет 19-25.01'!C:C,"Услуги доставки",'Отчет 19-25.01'!E:E,B3) -> 735.95 | AA3: 0 | AD3: =U3*1% -> 80.46 | AE3: =U3-W3-X3-Z3-AA3-AB3-AC3-AD3 -> 3054.91 | AG3: =IF(R3=0,0,U3/R3) -> 1609.2 | AH3: =H3 -> 142.98 | AI3: =IF(R3=0,0,X3/R3) -> 691.956 | AJ3: =IF(P3=0,Z3/1,Z3/P3) -> 147.19 | AK3: =IF(P3=0,0,AA3/P3) -> 0 | AL3: =_xlfn.IFS(R3=0,AE3,R3<0,AE3/-R3,R3>0,AE3/R3) -> 610.982 | AM3: =IF(AG3=0,0,AL3/AG3) -> 0.37968059 | AN3: =IF(AH3=0,0,AL3/AH3) -> 4.273199 | AP3: =AL3*C3 -> 226063.34
A4: 2676784638 | B4: qs черные | C4: 368 | H4: 123.09 | I4: =C4*H4 -> 45297.12 | K4: 10 | N4: =K4/7 -> 1.4285714 | O4: =R4/7 -> 1 | P4: =SUMIFS('Отчет 19-25.01'!H:H,'Отчет 19-25.01'!D:D,"Выручка",'Отчет 19-25.01'!E:E,B4) -> 7 | Q4: =SUMIFS('Отчет 19-25.01'!H:H,'Отчет 19-25.01'!D:D,"Возврат выручки",'Отчет 19-25.01'!E:E,B4) -> 0 | R4: =P4-Q4 -> 7 | S4: =SUMIFS('Отчет 19-25.01'!P:P,'Отчет 19-25.01'!C:C,"Продажи",'Отчет 19-25.01'!E:E,B4) -> 12250 | T4: =SUMIFS('Отчет 19-25.01'!P:P,'Отчет 19-25.01'!C:C,"Возвраты",'Отчет 19-25.01'!E:E,B4) -> 0 | U4: =S4+T4 -> 12250 | V4: =U4/$U$24 -> 0.077541952 | W4: =R4*H4 -> 861.63 | X4: =-SUMIFS('Отчет 19-25.01'!P:P,'Отчет 19-25.01'!C:C,"Вознаграждение Ozon",'Отчет 19-25.01'!E:E,B4) -> 5267.5 | Y4: =IF(U4=0,0,X4/U4) -> 0.43 | Z4: =-SUMIFS('Отчет 19-25.01'!P:P,'Отчет 19-25.01'!C:C,"Услуги доставки",'Отчет 19-25.01'!E:E,B4) -> 1015.78 | AA4: 103.13827 | AD4: =U4*1% -> 122.5 | AE4: =U4-W4-X4-Z4-AA4-AB4-AC4-AD4 -> 4879.4517 | AG4: =IF(R4=0,0,U4/R4) -> 1750 | AH4: =H4 -> 123.09 | AI4: =IF(R4=0,0,X4/R4) -> 752.5 | AJ4: =IF(P4=0,Z4/1,Z4/P4) -> 145.11143 | AK4: =IF(P4=0,0,AA4/P4) -> 14.734039 | AL4: {=_xlfn.IFS(R4=0,AE4,R4<0,AE4/-R4,R4>0,AE4/R4)} -> 697.06453 | AM4: =IF(AG4=0,0,AL4/AG4) -> 0.39832259 | AN4: =IF(AH4=0,0,AL4/AH4) -> 5.6630476 | AP4: =AL4*C4 -> 256519.75
A5: 2676784504 | B5: qs синие | C5: 379 | H5: 123.09 | I5: =C5*H5 -> 46651.11 | K5: 1 | N5: =K5/7 -> 0.14285714 | O5: =R5/7 -> 0.42857143 | P5: =SUMIFS('Отчет 19-25.01'!H:H,'Отчет 19-25.01'!D:D,"Выручка",'Отчет 19-25.01'!E:E,B5) -> 3 | Q5: =SUMIFS('Отчет 19-25.01'!H:H,'Отчет 19-25.01'!D:D,"Возврат выручки",'Отчет 19-25.01'!E:E,B5) -> 0 | R5: =P5-Q5 -> 3 | S5: =SUMIFS('Отчет 19-25.01'!P:P,'Отчет 19-25.01'!C:C,"Продажи",'Отчет 19-25.01'!E:E,B5) -> 5250 | T5: =SUMIFS('Отчет 19-25.01'!P:P,'Отчет 19-25.01'!C:C,"Возвраты",'Отчет 19-25.01'!E:E,B5) -> 0 | U5: =S5+T5 -> 5250 | V5: =U5/$U$24 -> 0.033232265 | W5: =R5*H5 -> 369.27 | X5: =-SUMIFS('Отчет 19-25.01'!P:P,'Отчет 19-25.01'!C:C,"Вознаграждение Ozon",'Отчет 19-25.01'!E:E,B5) -> 2257.5 | Y5: =IF(U5=0,0,X5/U5) -> 0.43 | Z5: =-SUMIFS('Отчет 19-25.01'!P:P,'Отчет 19-25.01'!C:C,"Услуги доставки",'Отчет 19-25.01'!E:E,B5) -> 483.61 | AA5: 0 | AD5: =U5*1% -> 52.5 | AE5: =U5-W5-X5-Z5-AA5-AB5-AC5-AD5 -> 2087.12 | AG5: =IF(R5=0,0,U5/R5) -> 1750 | AH5: =H5 -> 123.09 | AI5: =IF(R5=0,0,X5/R5) -> 752.5 | AJ5: =IF(P5=0,Z5/1,Z5/P5) -> 161.20333 | AK5: =IF(P5=0,0,AA5/P5) -> 0 | AL5: {=_xlfn.IFS(R5=0,AE5,R5<0,AE5/-R5,R5>0,AE5/R5)} -> 695.70667 | AM5: =IF(AG5=0,0,AL5/AG5) -> 0.39754667 | AN5: =IF(AH5=0,0,AL5/AH5) -> 5.6520161 | AP5: =AL5*C5 -> 263672.83
A6: 2676784514 | B6: qs желтые | C6: 687 | H6: 123.09 | I6: =C6*H6 -> 84562.83 | K6: 17 | N6: =K6/7 -> 2.4285714 | O6: =R6/7 -> 2.5714286 | P6: =SUMIFS('Отчет 19-25.01'!H:H,'Отчет 19-25.01'!D:D,"Выручка",'Отчет 19-25.01'!E:E,B6) -> 18 | Q6: =SUMIFS('Отчет 19-25.01'!H:H,'Отчет 19-25.01'!D:D,"Возврат выручки",'Отчет 19-25.01'!E:E,B6) -> 0 | R6: =P6-Q6 -> 18 | S6: =SUMIFS('Отчет 19-25.01'!P:P,'Отчет 19-25.01'!C:C,"Продажи",'Отчет 19-25.01'!E:E,B6) -> 31350 | T6: =SUMIFS('Отчет 19-25.01'!P:P,'Отчет 19-25.01'!C:C,"Возвраты",'Отчет 19-25.01'!E:E,B6) -> 0 | U6: =S6+T6 -> 31350 | V6: =U6/$U$24 -> 0.1984441 | W6: =R6*H6 -> 2215.62 | X6: =-SUMIFS('Отчет 19-25.01'!P:P,'Отчет 19-25.01'!C:C,"Вознаграждение Ozon",'Отчет 19-25.01'!E:E,B6) -> 13480.5 | Y6: =IF(U6=0,0,X6/U6) -> 0.43 | Z6: =-SUMIFS('Отчет 19-25.01'!P:P,'Отчет 19-25.01'!C:C,"Услуги доставки",'Отчет 19-25.01'!E:E,B6) -> 2736.46 | AA6: 2445 | AD6: =U6*1% -> 313.5 | AE6: =U6-W6-X6-Z6-AA6-AB6-AC6-AD6 -> 10158.92 | AG6: =IF(R6=0,0,U6/R6) -> 1741.6667 | AH6: =H6 -> 123.09 | AI6: =IF(R6=0,0,X6/R6) -> 748.91667 | AJ6: =IF(P6=0,Z6/1,Z6/P6) -> 152.02556 | AK6: =IF(P6=0,0,AA6/P6) -> 135.83333 | AL6: {=_xlfn.IFS(R6=0,AE6,R6<0,AE6/-R6,R6>0,AE6/R6)} -> 564.38444 | AM6: =IF(AG6=0,0,AL6/AG6) -> 0.32404848 | AN6: =IF(AH6=0,0,AL6/AH6) -> 4.5851364 | AP6: =AL6*C6 -> 387732.11
A7: 2676784181 | B7: qs коричневые | C7: 700 | H7: 117.24 | I7: =C7*H7 -> 82068 | K7: 28 | N7: =K7/7 -> 4 | O7: =R7/7 -> 1.4285714 | P7: =SUMIFS('Отчет 19-25.01'!H:H,'Отчет 19-25.01'!D:D,"Выручка",'Отчет 19-25.01'!E:E,B7) -> 10 | Q7: =SUMIFS('Отчет 19-25.01'!H:H,'Отчет 19-25.01'!D:D,"Возврат выручки",'Отчет 19-25.01'!E:E,B7) -> 0 | R7: =P7-Q7 -> 10 | S7: =SUMIFS('Отчет 19-25.01'!P:P,'Отчет 19-25.01'!C:C,"Продажи",'Отчет 19-25.01'!E:E,B7) -> 17500 | T7: =SUMIFS('Отчет 19-25.01'!P:P,'Отчет 19-25.01'!C:C,"Возвраты",'Отчет 19-25.01'!E:E,B7) -> 0 | U7: =S7+T7 -> 17500 | V7: =U7/$U$24 -> 0.11077422 | W7: =R7*H7 -> 1172.4 | X7: =-SUMIFS('Отчет 19-25.01'!P:P,'Отчет 19-25.01'!C:C,"Вознаграждение Ozon",'Отчет 19-25.01'!E:E,B7) -> 7525 | Y7: =IF(U7=0,0,X7/U7) -> 0.43 | Z7: =-SUMIFS('Отчет 19-25.01'!P:P,'Отчет 19-25.01'!C:C,"Услуги доставки",'Отчет 19-25.01'!E:E,B7) -> 1468.48 | AA7: 5523.1118 | AD7: =U7*1% -> 175 | AE7: =U7-W7-X7-Z7-AA7-AB7-AC7-AD7 -> 1636.0082 | AG7: =IF(R7=0,0,U7/R7) -> 1750 | AH7: =H7 -> 117.24 | AI7: =IF(R7=0,0,X7/R7) -> 752.5 | AJ7: =IF(P7=0,Z7/1,Z7/P7) -> 146.848 | AK7: =IF(P7=0,0,AA7/P7) -> 552.31118 | AL7: {=_xlfn.IFS(R7=0,AE7,R7<0,AE7/-R7,R7>0,AE7/R7)} -> 163.60082 | AM7: =IF(AG7=0,0,AL7/AG7) -> 0.093486183 | AN7: =IF(AH7=0,0,AL7/AH7) -> 1.3954352 | AP7: =AL7*C7 -> 114520.57
A8: 2676783005 | B8: MR8854 C2 | C8: 356 | H8: 169.89 | I8: =C8*H8 -> 60480.84 | K8: 8 | N8: =K8/7 -> 1.1428571 | O8: =R8/7 -> 0.42857143 | P8: =SUMIFS('Отчет 19-25.01'!H:H,'Отчет 19-25.01'!D:D,"Выручка",'Отчет 19-25.01'!E:E,B8) -> 4 | Q8: =SUMIFS('Отчет 19-25.01'!H:H,'Отчет 19-25.01'!D:D,"Возврат выручки",'Отчет 19-25.01'!E:E,B8) -> 1 | R8: =P8-Q8 -> 3 | S8: =SUMIFS('Отчет 19-25.01'!P:P,'Отчет 19-25.01'!C:C,"Продажи",'Отчет 19-25.01'!E:E,B8) -> 7000 | T8: =SUMIFS('Отчет 19-25.01'!P:P,'Отчет 19-25.01'!C:C,"Возвраты",'Отчет 19-25.01'!E:E,B8) -> -1202 | U8: =S8+T8 -> 5798 | V8: =U8/$U$24 -> 0.036701081 | W8: =R8*H8 -> 509.67 | X8: =-SUMIFS('Отчет 19-25.01'!P:P,'Отчет 19-25.01'!C:C,"Вознаграждение Ozon",'Отчет 19-25.01'!E:E,B8) -> 2493.14 | Y8: =IF(U8=0,0,X8/U8) -> 0.43 | Z8: =-SUMIFS('Отчет 19-25.01'!P:P,'Отчет 19-25.01'!C:C,"Услуги доставки",'Отчет 19-25.01'!E:E,B8) -> 598.84 | AA8: 2927.955 | AD8: =U8*1% -> 57.98 | AE8: =U8-W8-X8-Z8-AA8-AB8-AC8-AD8 -> -789.58498 | AG8: =IF(R8=0,0,U8/R8) -> 1932.6667 | AH8: =H8 -> 169.89 | AI8: =IF(R8=0,0,X8/R8) -> 831.04667 | AJ8: =IF(P8=0,Z8/1,Z8/P8) -> 149.71 | AK8: =IF(P8=0,0,AA8/P8) -> 731.98874 | AL8: {=_xlfn.IFS(R8=0,AE8,R8<0,AE8/-R8,R8>0,AE8/R8)} -> -263.19499 | AM8: =IF(AG8=0,0,AL8/AG8) -> -0.1361823 | AN8: =IF(AH8=0,0,AL8/AH8) -> -1.5492083 | AP8: =AL8*C8 -> -93697.417
A9: 3405092860 | B9: th черн | C9: 0 | H9: 123 | I9: =C9*H9 -> 0 | K9: 0 | N9: =K9/7 -> 0 | O9: =R9/7 -> 0 | P9: =SUMIFS('Отчет 19-25.01'!H:H,'Отчет 19-25.01'!D:D,"Выручка",'Отчет 19-25.01'!E:E,B9) -> 0 | Q9: =SUMIFS('Отчет 19-25.01'!H:H,'Отчет 19-25.01'!D:D,"Возврат выручки",'Отчет 19-25.01'!E:E,B9) -> 0 | R9: =P9-Q9 -> 0 | S9: =SUMIFS('Отчет 19-25.01'!P:P,'Отчет 19-25.01'!C:C,"Продажи",'Отчет 19-25.01'!E:E,B9) -> 0 | T9: =SUMIFS('Отчет 19-25.01'!P:P,'Отчет 19-25.01'!C:C,"Возвраты",'Отчет 19-25.01'!E:E,B9) -> 0 | U9: =S9+T9 -> 0 | V9: =U9/$U$24 -> 0 | W9: =R9*H9 -> 0 | X9: =-SUMIFS('Отчет 19-25.01'!P:P,'Отчет 19-25.01'!C:C,"Вознаграждение Ozon",'Отчет 19-25.01'!E:E,B9) -> 0 | Y9: =IF(U9=0,0,X9/U9) -> 0 | Z9: =-SUMIFS('Отчет 19-25.01'!P:P,'Отчет 19-25.01'!C:C,"Услуги доставки",'Отчет 19-25.01'!E:E,B9) -> 0 | AA9: 0 | AD9: =U9*1% -> 0 | AE9: =U9-W9-X9-Z9-AA9-AB9-AC9-AD9 -> 0 | AG9: =IF(R9=0,0,U9/R9) -> 0 | AH9: =H9 -> 123 | AI9: =IF(R9=0,0,X9/R9) -> 0 | AJ9: =IF(P9=0,Z9/1,Z9/P9) -> 0 | AK9: =IF(P9=0,0,AA9/P9) -> 0 | AL9: {=_xlfn.IFS(R9=0,AE9,R9<0,AE9/-R9,R9>0,AE9/R9)} -> 0 | AM9: =IF(AG9=0,0,AL9/AG9) -> 0 | AN9: =IF(AH9=0,0,AL9/AH9) -> 0 | AP9: =AL9*C9 -> 0
