Workbook

Sheet Реклама
B2: БАЛАНС | E2: СЧЕТ | H2: ПРОМОБОНУСЫ | K2: Неделя
B3: Номер документа | C3: Сумма | D3: Даты | E3: Номер документа | F3: Сумма | G3: Даты | H3: Номер документа | I3: Сумма | J3: Даты
B4: 277433850 | C4: 1376 | D4: 28-31.12 | E4: 277433847 | F4: 25829 | G4: 28-31.12 | H4: 0 | I4: 109 | J4: 29-31.12 | K4: 1
B5: 277539131 | C5: 1150 | D5: 36951 | E5: 277609313 | F5: 21489 | G5: 36982 | H5: 0 | I5: 363 | J5: 36982
B6: 279208603 | C6: 3455 | D6: 37168 | E6: 279208599 | F6: 51313 | G6: 37199 | H6: 0 | I6: 569 | J6: 37200 | K6: 2
B7: 280269091 | C7: 10268 | D7: 11-18.01 | E7: 280221209 | F7: 99763 | G7: 11-18.01 | H7: 0 | I7: 557 | J7: 12-18.01 | K7: 3
B8: 281267335 | C8: 70408 | D8: 19-25.01 | E8: 281348313 | F8: 67741 | G8: 18-25.01 | H8: 0 | I8: 195 | J8: 19-25.01 | K8: 4
B9: 282258474 | C9: 25521 | D9: 25-31.01 | E9: 282345086 | F9: 133680 | G9: 25-31.01 | H9: 0 | I9: 80 | J9: 26-31.01 | K9: 5
B10: 282365257 | C10: 1268 | D10: 46054 | E10: 282392960 | F10: 4672 | G10: 46054 | K10: 6
B11: 283332206 | C11: 111419 | D11: 37469 | E11: 283415801 | F11: 126688 | G11: 37469 | H11: 0 | I11: 3554 | J11: 37440
B12: 284423647 | C12: 145581 | D12: 08-15.02 | E12: 284416459 | F12: 138670 | G12: 08-15.02 | H12: 0 | I12: 44 | J12: 46063 | K12: 7
B13: 285348588 | C13: 50989 | D13: 15-22.02 | E13: 285348587 | F13: 265182 | G13: 15-22.02 | K13: 8
H39: .

Sheet Сводная
B2: Период | E2: Дата поступления дс | F2: Итого к перечислению на счет, руб | G2: шт. | J2: ВБ реализовал товар (выручка с СПП) | M2: Выручка до вычета комиссии ВБ | P2: Себестоимость продаж | Q2: Логистика WB | R2: Комиссия WB | S2: Хранение WB | T2: Платная приемка WB | U2: Штрафы WB | V2: Прочие удержания WB | W2: Реклама БАЛАНС | X2: Реклама СЧЕТ | Y2: Блогеры | Z2: Налог | AA2: Прочие поступления WB | AB2: Прибыль до вычета налогов | AC2: Прибыль после вычета налогов | AD2: Итог месяц | AE2: % Cебестоимости | AF2: Маржинальность, % | AG2: Рентабельность, % | AH2: Доля рекламы, %
B3: Месяц | C3: Даты | D3: Нед | G3: Заказы | H3: Продажи | I3: Возвраты | J3: Продажи | K3: Возвраты | L3: Общая | M3: Продажи | N3: Возвраты | O3: Общая
B4: Декабрь очки | C4: 29-31.12 | D4: 1 | F4: =IFERROR(O4-SUM(Q4:W4)+AA4,0) -> 62313.298 | G4: =ДЕКАБРЬ!N100 -> 129 | H4: =ДЕКАБРЬ!S100 -> 127 | I4: =ДЕКАБРЬ!T100 -> -5 | J4: =ДЕКАБРЬ!V100 -> 118047.57 | K4: =ДЕКАБРЬ!W100 -> -6409 | L4: =IFERROR(J4+K4,0) -> 111638.57 | M4: =ДЕКАБРЬ!Y100 -> 138964.57 | N4: =ДЕКАБРЬ!Z100 -> -7526 | O4: =IFERROR(M4+N4,0) -> 131438.57 | P4: =ДЕКАБРЬ!AD100 -> 15240.45 | Q4: =ДЕКАБРЬ!AG100 -> 17381.1 | R4: =ДЕКАБРЬ!AE100 -> 48126.54 | S4: =ДЕКАБРЬ!AL100 -> 3615.9322 | T4: 1.7 | U4: =ДЕКАБРЬ!AM100 -> 0 | W4: =ДЕКАБРЬ!AH100 -> 0 | X4: =ДЕКАБРЬ!AI100 -> 0 | Y4: =ДЕКАБРЬ!AK100 -> 0 | Z4: =ДЕКАБРЬ!AN100 -> 6374.5623 | AB4: =O4-SUM(P4:Y4)+AA4 -> 47072.848 | AC4: =O4-SUM(P4:Z4)+AA4 -> 40698.285 | AD4: =SUM(AC4:AC5) -> 40697.998 | AE4: =P4/O4 -> 0.11595112 | AF4: =AC4/P4 -> 2.6704123 | AG4: =AC4/O4 -> 0.30963731 | AH4: =(W4+X4+Y4)/O4 -> 0
B5: Декабрь туники | C5: 29-31.12 | D5: 1 | F5: =IFERROR(O5-SUM(Q5:W5)+AA5,0) -> -0.28775523 | G5: =ДЕКАБРЬ!N108 -> 0 | H5: =ДЕКАБРЬ!S108 -> 0 | I5: =ДЕКАБРЬ!T108 -> 0 | J5: =ДЕКАБРЬ!V108 -> 0 | K5: =ДЕКАБРЬ!W108 -> 0 | L5: =IFERROR(J5+K5,0) -> 0 | M5: =ДЕКАБРЬ!Y108 -> 0 | N5: =ДЕКАБРЬ!Z108 -> 0 | O5: =IFERROR(M5+N5,0) -> 0 | P5: =ДЕКАБРЬ!AD108 -> 0 | Q5: =ДЕКАБРЬ!AG108 -> 0 | R5: =ДЕКАБРЬ!AE108 -> 0 | S5: =ДЕКАБРЬ!AL108 -> 0.28775523 | U5: =ДЕКАБРЬ!AM108 -> 0 | W5: =ДЕКАБРЬ!AH108 -> 0 | X5: =ДЕКАБРЬ!AI108 -> 0 | Y5: =ДЕКАБРЬ!AK108 -> 0 | Z5: =ДЕКАБРЬ!AN108 -> 0 | AB5: =O5-SUM(P5:Y5)+AA5 -> -0.28775523 | AC5: =O5-SUM(P5:Z5)+AA5 -> -0.28775523 | AE5: =P5/O5 -> #DIV/0! | AF5: =AC5/P5 -> #DIV/0! | AG5: =AC5/O5 -> #DIV/0! | AH5: =(W5+X5+Y5)/O5 -> #DIV/0!
B6: Январь очки | C6: 01.01-01.02 | D6: 1-5 | F6: =IFERROR(O6-SUM(Q6:W6)+AA6,0) -> 955718.86 | G6: =ЯНВАРЬ!N100 -> 4961 | H6: =ЯНВАРЬ!S100 -> 2362 | I6: =ЯНВАРЬ!T100 -> -53 | J6: =ЯНВАРЬ!V100 -> 1728382.8 | K6: =ЯНВАРЬ!W100 -> -44657.88 | L6: =IFERROR(J6+K6,0) -> 1683724.9 | M6: =ЯНВАРЬ!Y100 -> 2303342.1 | N6: =ЯНВАРЬ!Z100 -> -58267.04 | O6: =IFERROR(M6+N6,0) -> 2245075 | P6: =ЯНВАРЬ!AD100 -> 292876.64 | Q6: =ЯНВАРЬ!AG100 -> 276475.65 | R6: =ЯНВАРЬ!AE100 -> 833669.77 | S6: =ЯНВАРЬ!AL100 -> 40333.14 | U6: =ЯНВАРЬ!AM100 -> 0 | V6: 25431.6 | W6: =ЯНВАРЬ!AH100 -> 113446 | X6: =ЯНВАРЬ!AI100 -> 404487 | Y6: =ЯНВАРЬ!AK100 -> 0 | Z6: =ЯНВАРЬ!AN100 -> 96140.692 | AB6: =O6-SUM(P6:Y6)+AA6 -> 258355.22 | AC6: =O6-SUM(P6:Z6)+AA6 -> 162214.53 | AD6: =SUM(AC6:AC8) -> 161855.14 | AE6: =P6/O6 -> 0.13045294 | AF6: =AC6/P6 -> 0.55386639 | AG6: =AC6/O6 -> 0.0722535 | AH6: =(W6+X6+Y6)/O6 -> 0.23069741
B7: Январь туники | C7: 01.01-01.02 | D7: 1-5 | F7: =IFERROR(O7-SUM(Q7:W7)+AA7,0) -> -186.4297 | G7: =ЯНВАРЬ!N108 -> 1 | H7: =ЯНВАРЬ!S108 -> 0 | I7: =ЯНВАРЬ!T108 -> 0 | J7: =ЯНВАРЬ!V108 -> 0 | K7: =ЯНВАРЬ!W108 -> 0 | L7: =IFERROR(J7+K7,0) -> 0 | M7: =ЯНВАРЬ!Y108 -> 0 | N7: =ЯНВАРЬ!Z108 -> 0 | O7: =IFERROR(M7+N7,0) -> 0 | P7: =ЯНВАРЬ!AD108 -> 0 | Q7: =ЯНВАРЬ!AG108 -> 183.22 | R7: =ЯНВАРЬ!AE108 -> 0 | S7: =ЯНВАРЬ!AL108 -> 3.209704 | U7: =ЯНВАРЬ!AM108 -> 0 | W7: =ЯНВАРЬ!AH108 -> 0 | X7: =ЯНВАРЬ!AI108 -> 0 | Y7: =ЯНВАРЬ!AK108 -> 0 | Z7: =ЯНВАРЬ!AN108 -> 0 | AB7: =O7-SUM(P7:Y7)+AA7 -> -186.4297 | AC7: =O7-SUM(P7:Z7)+AA7 -> -186.4297 | AE7: =P7/O7 -> #DIV/0! | AF7: =AC7/P7 -> #DIV/0! | AG7: =AC7/O7 -> #DIV/0! | AH7: =(W7+X7+Y7)/O7 -> #DIV/0!
B8: Январь шапки | C8: 01.01-01.02 | D8: 1-5 | F8: =IFERROR(O8-SUM(Q8:W8)+AA8,0) -> -172.96 | G8: =ЯНВАРЬ!N119 -> 0 | H8: =ЯНВАРЬ!S119 -> 0 | I8: =ЯНВАРЬ!T119 -> 0 | J8: =ЯНВАРЬ!V119 -> 0 | K8: =ЯНВАРЬ!W119 -> 0 | L8: =IFERROR(J8+K8,0) -> 0 | M8: =ЯНВАРЬ!Y119 -> 0 | N8: =ЯНВАРЬ!Z119 -> 0 | O8: =IFERROR(M8+N8,0) -> 0 | P8: =ЯНВАРЬ!AD119 -> 0 | Q8: =ЯНВАРЬ!AG119 -> 172.96 | R8: =ЯНВАРЬ!AE119 -> 0 | S8: =ЯНВАРЬ!AL119 -> 0 | U8: =ЯНВАРЬ!AM119 -> 0 | W8: =ЯНВАРЬ!AH119 -> 0 | X8: =ЯНВАРЬ!AI119 -> 0 | Y8: =ЯНВАРЬ!AK119 -> 0 | Z8: =ЯНВАРЬ!AN119 -> 0 | AB8: =O8-SUM(P8:Y8)+AA8 -> -172.96 | AC8: =O8-SUM(P8:Z8)+AA8 -> -172.96 | AE8: =P8/O8 -> #DIV/0! | AF8: =AC8/P8 -> #DIV/0! | AG8: =AC8/O8 -> #DIV/0! | AH8: =(W8+X8+Y8)/O8 -> #DIV/0!
B9: Февраль 1 | C9: 02-08.02 | D9: 6 | AD9: =SUM(AC9:AC13) -> 569969.91 | AE9: =P9/O9 -> #DIV/0! | AF9: =AC9/P9 -> #DIV/0! | AG9: =AC9/O9 -> #DIV/0! | AH9: =(W9+X9+Y9)/O9 -> #DIV/0!
B10: Февраль 2 | C10: 09-15.02 | D10: 7 | AE10: =P10/O10 -> #DIV/0! | AF10: =AC10/P10 -> #DIV/0! | AG10: =AC10/O10 -> #DIV/0! | AH10: =(W10+X10+Y10)/O10 -> #DIV/0!
B11: Февраль 3 очки | C11: 16-22.02 | D11: 8 | F11: =IFERROR(O11-SUM(Q11:W11)+AA11,0) -> 1204943.2 | G11: ='Юнит 8'!N105 -> 4413 | H11: ='Юнит 8'!S105 -> 2295 | I11: ='Юнит 8'!T105 -> -43 | J11: ='Юнит 8'!V105 -> 1593380.1 | K11: ='Юнит 8'!W105 -> -29254.63 | L11: =IFERROR(J11+K11,0) -> 1564125.5 | M11: ='Юнит 8'!Y105 -> 2501418.9 | N11: ='Юнит 8'!Z105 -> -47007.29 | O11: =IFERROR(M11+N11,0) -> 2454411.6 | P11: ='Юнит 8'!AD105 -> 280478.83 | Q11: ='Юнит 8'!AG105 -> 267875.33 | R11: ='Юнит 8'!AE105 -> 918234.84 | S11: ='Юнит 8'!AL105 -> 8623.9028 | U11: ='Юнит 8'!AM105 -> 466 | V11: 3279.36 | W11: ='Юнит 8'!AH105 -> 50989 | X11: ='Юнит 8'!AI105 -> 265182 | Y11: ='Юнит 8'!AK105 -> 0 | Z11: ='Юнит 8'!AN105 -> 89311.563 | AB11: =O11-SUM(P11:Y11)+AA11 -> 659282.34 | AC11: =O11-SUM(P11:Z11)+AA11 -> 569970.77 | AE11: =P11/O11 -> 0.11427538 | AF11: =AC11/P11 -> 2.0321347 | AG11: =AC11/O11 -> 0.23222298 | AH11: =(W11+X11+Y11)/O11 -> 0.12881743
B12: Февраль 3 туники | C12: 16-22.02 | D12: 8 | F12: =IFERROR(O12-SUM(Q12:W12)+AA12,0) -> -0.86724686 | G12: ='Юнит 8'!N113 -> 0 | H12: ='Юнит 8'!S113 -> 0 | I12: ='Юнит 8'!T113 -> 0 | J12: ='Юнит 8'!V113 -> 0 | K12: ='Юнит 8'!W113 -> 0 | L12: =IFERROR(J12+K12,0) -> 0 | M12: ='Юнит 8'!Y113 -> 0 | N12: ='Юнит 8'!Z113 -> 0 | O12: =IFERROR(M12+N12,0) -> 0 | P12: ='Юнит 8'!AD113 -> 0 | Q12: ='Юнит 8'!AG113 -> 0 | R12: ='Юнит 8'!AE113 -> 0 | S12: ='Юнит 8'!AL113 -> 0.86724686 | U12: ='Юнит 8'!AM113 -> 0 | W12: ='Юнит 8'!AH113 -> 0 | X12: ='Юнит 8'!AI113 -> 0 | Y12: ='Юнит 8'!AK113 -> 0 | Z12: ='Юнит 8'!AN113 -> 0 | AB12: =O12-SUM(P12:Y12)+AA12 -> -0.86724686 | AC12: =O12-SUM(P12:Z12)+AA12 -> -0.86724686 | AE12: =P12/O12 -> #DIV/0! | AF12: =AC12/P12 -> #DIV/0! | AG12: =AC12/O12 -> #DIV/0! | AH12: =(W12+X12+Y12)/O12 -> #DIV/0!
B13: Февраль 4 | C13: 23.02-01.03 | D13: 9 | AB13: =O13-SUM(P13:Y13)+AA13 -> 0 | AC13: =O13-SUM(P13:Z13)+AA13 -> 0 | AE13: =P13/O13 -> #DIV/0! | AF13: =AC13/P13 -> #DIV/0! | AG13: =AC13/O13 -> #DIV/0! | AH13: =(W13+X13+Y13)/O13 -> #DIV/0!
AB14: =O14-SUM(P14:Y14)+AA14 -> 0 | AC14: =O14-SUM(P14:Z14)+AA14 -> 0 | AE14: =P14/O14 -> #DIV/0! | AF14: =AC14/P14 -> #DIV/0! | AG14: =AC14/O14 -> #DIV/0! | AH14: =(W14+X14+Y14)/O14 -> #DIV/0!
B15: Итого | F15: =SUM(F8:F14) -> 1204769.3 | G15: =SUM(G8:G14) -> 4413 | H15: =SUM(H8:H14) -> 2295 | I15: =SUM(I8:I14) -> -43 | J15: =SUM(J8:J14) -> 1593380.1 | K15: =SUM(K8:K14) -> -29254.63 | L15: =SUM(L8:L14) -> 1564125.5 | M15: =SUM(M8:M14) -> 2501418.9 | ... AD15: =SUM(AD8:AD14) -> 569969.91 | AE15: =P15/O15 -> 0.11427538 | AF15: =AC15/P15 -> 2.031515 | AG15: =AC15/O15 -> 0.23215216 | AH15: =(W15+X15+Y15)/O15 -> 0.12881743
M16: % от выручки за весь период
N17: =-N15/M15 -> 0.01879225 | P17: =P15/$O$15 -> 0.11427538 | Q17: =Q15/$O$15 -> 0.10921081 | R17: =R15/$O$15 -> 0.37411608 | S17: =S15/$O$15 -> 0.0035139868 | T17: =T15/$O$15 -> 0 | U17: =U15/$O$15 -> 0.00018986221 | V17: =V15/$O$15 -> 0.0013361084 | W17: =W15/$O$15 -> 0.020774429 | ... Z17: =Z15/$O$15 -> 0.036388177 | AC17: =AC15/P15 -> 2.031515 | AD17: Маржинальность, %
W18: =(W15+X15)/O15 -> 0.12881743 | AC18: =AC15/O15 -> 0.23215216 | AD18: Рентабельность, %
B19: ЯНВАРЬ очки | G19: =G6 -> 4961 | H19: =H6 -> 2362 | I19: =I6 -> -53 | J19: =J6 -> 1728382.8 | K19: =K6 -> -44657.88 | L19: =L6 -> 1683724.9 | M19: =M6 -> 2303342.1 | N19: =N6 -> -58267.04 | ... AC19: =AC6 -> 162214.53
N20: =-N19/M19 -> 0.025296738 | P20: =P19/$O$19 -> 0.13045294 | Q20: =Q19/$O$19 -> 0.12314762 | R20: =R19/$O$19 -> 0.3713327 | S20: =S19/$O$19 -> 0.017965164 | T20: =T19/$O$19 -> 0 | U20: =U19/$O$19 -> 0 | V20: =V19/$O$19 -> 0.011327728 | W20: =W19/$O$19 -> 0.050531051 | ... AA20: =AA19/$O$19 -> 0 | AC20: =AC19/O19 -> 0.0722535

Sheet АВС 8
B2: ОЧКИ
C3: Прибыль | D3: % прибыль | E3: Доля | F3: ABC прибыль | G3: ABC кол-во | J3: Кол-во | K3: % кол-во | L3: Доля | M3: ABC кол-во
B4: QS черные PZ | C4: ='Юнит 8'!AO4 -> 187586.52 | D4: =C4/C$105 -> 0.32723328 | E4: =D4 -> 0.32723328 | F4: =IF(AND(E4<=0),"C",IF(E4<=0.8,"A",IF(E4<=0.95,"B","C"))) -> A | G4: =VLOOKUP(B$4:B$104,I$4:M$104,5,0) -> A | I4: QS черные PZ | J4: ='Юнит 8'!U4 -> 553 | K4: =J4/J$105 -> 0.2455595 | L4: =K4 -> 0.2455595 | M4: =_xlfn.IFS(L4<80%,"A",L4<=95%,"B",L4>95%,"C") -> A | P4: A | Q4: 0.8
B5: QS коричневые PZ | C5: ='Юнит 8'!AO7 -> 67172.51 | D5: =C5/C$105 -> 0.11717836 | E5: =E4+D5 -> 0.44441164 | F5: =IF(AND(E5<=0),"C",IF(E5<=0.8,"A",IF(E5<=0.95,"B","C"))) -> A | G5: =VLOOKUP(B$4:B$104,I$4:M$104,5,0) -> A | I5: QS коричневые PZ | J5: ='Юнит 8'!U7 -> 206 | K5: =J5/J$105 -> 0.091474245 | L5: =L4+K5 -> 0.33703375 | M5: =_xlfn.IFS(L5<80%,"A",L5<=95%,"B",L5>95%,"C") -> A | P5: B | Q5: 0.15
B6: th черн | C6: ='Юнит 8'!AO9 -> 42084.801 | D6: =C6/C$105 -> 0.073414376 | E6: =E5+D6 -> 0.51782601 | F6: =IF(AND(E6<=0),"C",IF(E6<=0.8,"A",IF(E6<=0.95,"B","C"))) -> A | G6: =VLOOKUP(B$4:B$104,I$4:M$104,5,0) -> A | I6: th син | J6: ='Юнит 8'!U10 -> 165 | K6: =J6/J$105 -> 0.073268206 | L6: =L5+K6 -> 0.41030195 | M6: =_xlfn.IFS(L6<80%,"A",L6<=95%,"B",L6>95%,"C") -> A | P6: C | Q6: 0.05
B7: QS синие PZ | C7: ='Юнит 8'!AO5 -> 41232.197 | D7: =C7/C$105 -> 0.071927061 | E7: =E6+D7 -> 0.58975308 | F7: =IF(AND(E7<=0),"C",IF(E7<=0.8,"A",IF(E7<=0.95,"B","C"))) -> A | G7: =VLOOKUP(B$4:B$104,I$4:M$104,5,0) -> A | I7: QS синие PZ | J7: ='Юнит 8'!U5 -> 151 | K7: =J7/J$105 -> 0.06705151 | L7: =L6+K7 -> 0.47735346 | M7: =_xlfn.IFS(L7<80%,"A",L7<=95%,"B",L7>95%,"C") -> A
B8: th син | C8: ='Юнит 8'!AO10 -> 35943.92 | D8: =C8/C$105 -> 0.062701983 | E8: =E7+D8 -> 0.65245506 | F8: =IF(AND(E8<=0),"C",IF(E8<=0.8,"A",IF(E8<=0.95,"B","C"))) -> A | G8: =VLOOKUP(B$4:B$104,I$4:M$104,5,0) -> A | I8: th черн | J8: ='Юнит 8'!U9 -> 135 | K8: =J8/J$105 -> 0.059946714 | L8: =L7+K8 -> 0.53730018 | M8: =_xlfn.IFS(L8<80%,"A",L8<=95%,"B",L8>95%,"C") -> A
B9: QS желтые PZ | C9: ='Юнит 8'!AO6 -> 35702.024 | D9: =C9/C$105 -> 0.06228001 | E9: =E8+D9 -> 0.71473507 | F9: =IF(AND(E9<=0),"C",IF(E9<=0.8,"A",IF(E9<=0.95,"B","C"))) -> A | G9: =VLOOKUP(B$4:B$104,I$4:M$104,5,0) -> A | I9: QS желтые PZ | J9: ='Юнит 8'!U6 -> 126 | K9: =J9/J$105 -> 0.055950266 | L9: =L8+K9 -> 0.59325044 | M9: =_xlfn.IFS(L9<80%,"A",L9<=95%,"B",L9>95%,"C") -> A
B10: flip коричневые | C10: ='Юнит 8'!AO16 -> 24641.241 | D10: =C10/C$105 -> 0.042985147 | E10: =E9+D10 -> 0.75772022 | F10: =IF(AND(E10<=0),"C",IF(E10<=0.8,"A",IF(E10<=0.95,"B","C"))) -> A | G10: =VLOOKUP(B$4:B$104,I$4:M$104,5,0) -> A | I10: sh3 | J10: ='Юнит 8'!U28 -> 96 | K10: =J10/J$105 -> 0.042628774 | L10: =L9+K10 -> 0.63587922 | M10: =_xlfn.IFS(L10<80%,"A",L10<=95%,"B",L10>95%,"C") -> A
B11: flip черные | C11: ='Юнит 8'!AO13 -> 22233.993 | D11: =C11/C$105 -> 0.03878585 | E11: =E10+D11 -> 0.79650607 | F11: =IF(AND(E11<=0),"C",IF(E11<=0.8,"A",IF(E11<=0.95,"B","C"))) -> A | G11: =VLOOKUP(B$4:B$104,I$4:M$104,5,0) -> A | I11: flip черные | J11: ='Юнит 8'!U13 -> 92 | K11: =J11/J$105 -> 0.040852575 | L11: =L10+K11 -> 0.67673179 | M11: =_xlfn.IFS(L11<80%,"A",L11<=95%,"B",L11>95%,"C") -> A
B12: sh3 | C12: ='Юнит 8'!AO28 -> 21229.534 | D12: =C12/C$105 -> 0.03703363 | E12: =E11+D12 -> 0.8335397 | F12: =IF(AND(E12<=0),"C",IF(E12<=0.8,"A",IF(E12<=0.95,"B","C"))) -> B | G12: =VLOOKUP(B$4:B$104,I$4:M$104,5,0) -> A | I12: flip коричневые | J12: ='Юнит 8'!U16 -> 85 | K12: =J12/J$105 -> 0.037744227 | L12: =L11+K12 -> 0.71447602 | M12: =_xlfn.IFS(L12<80%,"A",L12<=95%,"B",L12>95%,"C") -> A
B13: th коричн | C13: ='Юнит 8'!AO12 -> 16922.863 | D13: =C13/C$105 -> 0.029520905 | E13: =E12+D13 -> 0.8630606 | F13: =IF(AND(E13<=0),"C",IF(E13<=0.8,"A",IF(E13<=0.95,"B","C"))) -> B | G13: =VLOOKUP(B$4:B$104,I$4:M$104,5,0) -> B | I13: черные с железкой классика | J13: ='Юнит 8'!U3 -> 74 | K13: =J13/J$105 -> 0.03285968 | L13: =L12+K13 -> 0.7473357 | M13: =_xlfn.IFS(L13<80%,"A",L13<=95%,"B",L13>95%,"C") -> A
B14: MR8854 C2 Жен | C14: ='Юнит 8'!AO8 -> 15508.025 | D14: =C14/C$105 -> 0.027052807 | E14: =E13+D14 -> 0.89011341 | F14: =IF(AND(E14<=0),"C",IF(E14<=0.8,"A",IF(E14<=0.95,"B","C"))) -> B | G14: =VLOOKUP(B$4:B$104,I$4:M$104,5,0) -> A | I14: MR8854 C2 Жен | J14: ='Юнит 8'!U8 -> 68 | K14: =J14/J$105 -> 0.030195382 | L14: =L13+K14 -> 0.77753108 | M14: =_xlfn.IFS(L14<80%,"A",L14<=95%,"B",L14>95%,"C") -> A
B15: th желт | C15: ='Юнит 8'!AO11 -> 12076.316 | D15: =C15/C$105 -> 0.021066399 | E15: =E14+D15 -> 0.91117981 | F15: =IF(AND(E15<=0),"C",IF(E15<=0.8,"A",IF(E15<=0.95,"B","C"))) -> B | G15: =VLOOKUP(B$4:B$104,I$4:M$104,5,0) -> B | I15: th коричн | J15: ='Юнит 8'!U12 -> 68 | K15: =J15/J$105 -> 0.030195382 | L15: =L14+K15 -> 0.80772647 | M15: =_xlfn.IFS(L15<80%,"A",L15<=95%,"B",L15>95%,"C") -> B
B16: wwl8032 коричневые золото | C16: ='Юнит 8'!AO17 -> 9301.5132 | D16: =C16/C$105 -> 0.016225924 | E16: =E15+D16 -> 0.92740573 | F16: =IF(AND(E16<=0),"C",IF(E16<=0.8,"A",IF(E16<=0.95,"B","C"))) -> B | G16: =VLOOKUP(B$4:B$104,I$4:M$104,5,0) -> B | I16: ww 1022 черные | J16: ='Юнит 8'!U45 -> 67 | K16: =J16/J$105 -> 0.029751332 | L16: =L15+K16 -> 0.8374778 | M16: =_xlfn.IFS(L16<80%,"A",L16<=95%,"B",L16>95%,"C") -> B
B17: flip синие | C17: ='Юнит 8'!AO14 -> 9186.5031 | D17: =C17/C$105 -> 0.016025296 | E17: =E16+D17 -> 0.94343103 | F17: =IF(AND(E17<=0),"C",IF(E17<=0.8,"A",IF(E17<=0.95,"B","C"))) -> B | G17: =VLOOKUP(B$4:B$104,I$4:M$104,5,0) -> B | I17: th желт | J17: ='Юнит 8'!U11 -> 42 | K17: =J17/J$105 -> 0.018650089 | L17: =L16+K17 -> 0.85612789 | M17: =_xlfn.IFS(L17<80%,"A",L17<=95%,"B",L17>95%,"C") -> B
B18: ww 1022 коричневые | C18: ='Юнит 8'!AO48 -> 9125.125 | D18: =C18/C$105 -> 0.015918226 | E18: =E17+D18 -> 0.95934925 | F18: =IF(AND(E18<=0),"C",IF(E18<=0.8,"A",IF(E18<=0.95,"B","C"))) -> C | G18: =VLOOKUP(B$4:B$104,I$4:M$104,5,0) -> B | I18: wwl8032 хром металл | J18: ='Юнит 8'!U18 -> 41 | K18: =J18/J$105 -> 0.018206039 | L18: =L17+K18 -> 0.87433393 | M18: =_xlfn.IFS(L18<80%,"A",L18<=95%,"B",L18>95%,"C") -> B
B19: ww 1022 черные | C19: ='Юнит 8'!AO45 -> 8595.4514 | D19: =C19/C$105 -> 0.014994242 | E19: =E18+D19 -> 0.97434349 | F19: =IF(AND(E19<=0),"C",IF(E19<=0.8,"A",IF(E19<=0.95,"B","C"))) -> C | G19: =VLOOKUP(B$4:B$104,I$4:M$104,5,0) -> B | I19: flip синие | J19: ='Юнит 8'!U14 -> 34 | K19: =J19/J$105 -> 0.015097691 | L19: =L18+K19 -> 0.88943162 | M19: =_xlfn.IFS(L19<80%,"A",L19<=95%,"B",L19>95%,"C") -> B
B20: wwl8032 хром металл | C20: ='Юнит 8'!AO18 -> 7347.995 | D20: =C20/C$105 -> 0.012818131 | E20: =E19+D20 -> 0.98716162 | F20: =IF(AND(E20<=0),"C",IF(E20<=0.8,"A",IF(E20<=0.95,"B","C"))) -> C | G20: =VLOOKUP(B$4:B$104,I$4:M$104,5,0) -> B | I20: flip желтые | J20: ='Юнит 8'!U15 -> 32 | K20: =J20/J$105 -> 0.014209591 | L20: =L19+K20 -> 0.90364121 | M20: =_xlfn.IFS(L20<80%,"A",L20<=95%,"B",L20>95%,"C") -> B
B21: flip желтые | C21: ='Юнит 8'!AO15 -> 6832.1996 | D21: =C21/C$105 -> 0.011918357 | E21: =E20+D21 -> 0.99907998 | F21: =IF(AND(E21<=0),"C",IF(E21<=0.8,"A",IF(E21<=0.95,"B","C"))) -> C | G21: =VLOOKUP(B$4:B$104,I$4:M$104,5,0) -> B | I21: ww 1022 коричневые | J21: ='Юнит 8'!U48 -> 31 | K21: =J21/J$105 -> 0.013765542 | L21: =L20+K21 -> 0.91740675 | M21: =_xlfn.IFS(L21<80%,"A",L21<=95%,"B",L21>95%,"C") -> B
B22: ww 2018 черные | C22: ='Юнит 8'!AO49 -> 6086.6702 | D22: =C22/C$105 -> 0.010617826 | E22: =E21+D22 -> 1.0096978 | F22: =IF(AND(E22<=0),"C",IF(E22<=0.8,"A",IF(E22<=0.95,"B","C"))) -> C | G22: =VLOOKUP(B$4:B$104,I$4:M$104,5,0) -> B | I22: wwl8032 коричневые золото | J22: ='Юнит 8'!U17 -> 30 | K22: =J22/J$105 -> 0.013321492 | L22: =L21+K22 -> 0.93072824 | M22: =_xlfn.IFS(L22<80%,"A",L22<=95%,"B",L22>95%,"C") -> B
B23: ww 1022 желтые | C23: ='Юнит 8'!AO47 -> 4570.1747 | D23: =C23/C$105 -> 0.0079723919 | E23: =E22+D23 -> 1.0176702 | F23: =IF(AND(E23<=0),"C",IF(E23<=0.8,"A",IF(E23<=0.95,"B","C"))) -> C | G23: =VLOOKUP(B$4:B$104,I$4:M$104,5,0) -> C | I23: ww 2018 черные | J23: ='Юнит 8'!U49 -> 29 | K23: =J23/J$105 -> 0.012877442 | L23: =L22+K23 -> 0.94360568 | M23: =_xlfn.IFS(L23<80%,"A",L23<=95%,"B",L23>95%,"C") -> B
B24: MR Р1894 черные | C24: ='Юнит 8'!AO89 -> 2625.4827 | D24: =C24/C$105 -> 0.004579995 | E24: =E23+D24 -> 1.0222502 | F24: =IF(AND(E24<=0),"C",IF(E24<=0.8,"A",IF(E24<=0.95,"B","C"))) -> C | G24: =VLOOKUP(B$4:B$104,I$4:M$104,5,0) -> C | I24: sh1 | J24: ='Юнит 8'!U26 -> 26 | K24: =J24/J$105 -> 0.011545293 | L24: =L23+K24 -> 0.95515098 | M24: =_xlfn.IFS(L24<80%,"A",L24<=95%,"B",L24>95%,"C") -> C
B25: Chenlong черные | C25: ='Юнит 8'!AO76 -> 945.21524 | D25: =C25/C$105 -> 0.0016488705 | E25: =E24+D25 -> 1.0238991 | F25: =IF(AND(E25<=0),"C",IF(E25<=0.8,"A",IF(E25<=0.95,"B","C"))) -> C | G25: =VLOOKUP(B$4:B$104,I$4:M$104,5,0) -> C | I25: ww 1022 желтые | J25: ='Юнит 8'!U47 -> 13 | K25: =J25/J$105 -> 0.0057726465 | L25: =L24+K25 -> 0.96092362 | M25: =_xlfn.IFS(L25<80%,"A",L25<=95%,"B",L25>95%,"C") -> C
B26: sportlife красные | C26: ='Юнит 8'!AO25 -> 749.7631 | D26: =C26/C$105 -> 0.0013079161 | E26: =E25+D26 -> 1.025207 | F26: =IF(AND(E26<=0),"C",IF(E26<=0.8,"A",IF(E26<=0.95,"B","C"))) -> C | G26: =VLOOKUP(B$4:B$104,I$4:M$104,5,0) -> C | I26: ww 203 черные | J26: ='Юнит 8'!U44 -> 9 | K26: =J26/J$105 -> 0.0039964476 | L26: =L25+K26 -> 0.96492007 | M26: =_xlfn.IFS(L26<80%,"A",L26<=95%,"B",L26>95%,"C") -> C
B27: MANNA2114 | C27: ='Юнит 8'!AO67 -> 701.1945 | D27: =C27/C$105 -> 0.0012231912 | E27: =E26+D27 -> 1.0264302 | F27: =IF(AND(E27<=0),"C",IF(E27<=0.8,"A",IF(E27<=0.95,"B","C"))) -> C | G27: =VLOOKUP(B$4:B$104,I$4:M$104,5,0) -> C | I27: sh09 | J27: ='Юнит 8'!U33 -> 8 | K27: =J27/J$105 -> 0.0035523979 | L27: =L26+K27 -> 0.96847247 | M27: =_xlfn.IFS(L27<80%,"A",L27<=95%,"B",L27>95%,"C") -> C
B28: Linhai Baiyi розовая линза | C28: ='Юнит 8'!AO88 -> 653.61643 | D28: =C28/C$105 -> 0.0011401941 | E28: =E27+D28 -> 1.0275704 | F28: =IF(AND(E28<=0),"C",IF(E28<=0.8,"A",IF(E28<=0.95,"B","C"))) -> C | G28: =VLOOKUP(B$4:B$104,I$4:M$104,5,0) -> C | I28: ww 2018 желтые | J28: ='Юнит 8'!U50 -> 7 | K28: =J28/J$105 -> 0.0031083481 | L28: =L27+K28 -> 0.97158082 | M28: =_xlfn.IFS(L28<80%,"A",L28<=95%,"B",L28>95%,"C") -> C
B29: кс_черные_тест | C29: ='Юнит 8'!AO101 -> 617.01293 | D29: =C29/C$105 -> 0.0010763415 | E29: =E28+D29 -> 1.0286467 | F29: =IF(AND(E29<=0),"C",IF(E29<=0.8,"A",IF(E29<=0.95,"B","C"))) -> C | G29: =VLOOKUP(B$4:B$104,I$4:M$104,5,0) -> C | I29: sh2 | J29: ='Юнит 8'!U27 -> 6 | K29: =J29/J$105 -> 0.0026642984 | L29: =L28+K29 -> 0.97424512 | M29: =_xlfn.IFS(L29<80%,"A",L29<=95%,"B",L29>95%,"C") -> C
B30: MANNA2107 | C30: ='Юнит 8'!AO60 -> 587.15632 | D30: =C30/C$105 -> 0.0010242585 | E30: =E29+D30 -> 1.029671 | F30: =IF(AND(E30<=0),"C",IF(E30<=0.8,"A",IF(E30<=0.95,"B","C"))) -> C | G30: =VLOOKUP(B$4:B$104,I$4:M$104,5,0) -> C | I30: Hengda Optical черные | J30: ='Юнит 8'!U81 -> 6 | K30: =J30/J$105 -> 0.0026642984 | L30: =L29+K30 -> 0.97690941 | M30: =_xlfn.IFS(L30<80%,"A",L30<=95%,"B",L30>95%,"C") -> C
B31: ww 8010 черные | C31: ='Юнит 8'!AO51 -> 506.35831 | D31: =C31/C$105 -> 0.00088331127 | E31: =E30+D31 -> 1.0305543 | F31: =IF(AND(E31<=0),"C",IF(E31<=0.8,"A",IF(E31<=0.95,"B","C"))) -> C | G31: =VLOOKUP(B$4:B$104,I$4:M$104,5,0) -> C | I31: sh10 | J31: ='Юнит 8'!U34 -> 5 | K31: =J31/J$105 -> 0.0022202487 | L31: =L30+K31 -> 0.97912966 | M31: =_xlfn.IFS(L31<80%,"A",L31<=95%,"B",L31>95%,"C") -> C
B32: sh15 | C32: ='Юнит 8'!AO39 -> 506.18738 | D32: =C32/C$105 -> 0.00088301311 | E32: =E31+D32 -> 1.0314373 | F32: =IF(AND(E32<=0),"C",IF(E32<=0.8,"A",IF(E32<=0.95,"B","C"))) -> C | G32: =VLOOKUP(B$4:B$104,I$4:M$104,5,0) -> C | I32: MR Р1894 черные | J32: ='Юнит 8'!U89 -> 4 | K32: =J32/J$105 -> 0.0017761989 | L32: =L31+K32 -> 0.98090586 | M32: =_xlfn.IFS(L32<80%,"A",L32<=95%,"B",L32>95%,"C") -> C
B33: MANNA2119 | C33: ='Юнит 8'!AO72 -> 459.0738 | D33: =C33/C$105 -> 0.00080082633 | E33: =E32+D33 -> 1.0322381 | F33: =IF(AND(E33<=0),"C",IF(E33<=0.8,"A",IF(E33<=0.95,"B","C"))) -> C | G33: =VLOOKUP(B$4:B$104,I$4:M$104,5,0) -> C | I33: MANNA2119 | J33: ='Юнит 8'!U72 -> 3 | K33: =J33/J$105 -> 0.0013321492 | L33: =L32+K33 -> 0.98223801 | M33: =_xlfn.IFS(L33<80%,"A",L33<=95%,"B",L33>95%,"C") -> C
B34: sh09 | C34: ='Юнит 8'!AO33 -> 436.78676 | D34: =C34/C$105 -> 0.00076194794 | E34: =E33+D34 -> 1.0330001 | F34: =IF(AND(E34<=0),"C",IF(E34<=0.8,"A",IF(E34<=0.95,"B","C"))) -> C | G34: =VLOOKUP(B$4:B$104,I$4:M$104,5,0) -> C | I34: MANNA2120 | J34: ='Юнит 8'!U73 -> 3 | K34: =J34/J$105 -> 0.0013321492 | L34: =L33+K34 -> 0.98357016 | M34: =_xlfn.IFS(L34<80%,"A",L34<=95%,"B",L34>95%,"C") -> C
B35: Linhai Baiyi серая линза | C35: ='Юнит 8'!AO87 -> 430.51833 | D35: =C35/C$105 -> 0.00075101305 | E35: =E34+D35 -> 1.0337511 | F35: =IF(AND(E35<=0),"C",IF(E35<=0.8,"A",IF(E35<=0.95,"B","C"))) -> C | G35: =VLOOKUP(B$4:B$104,I$4:M$104,5,0) -> C | I35: Chenlong черные | J35: ='Юнит 8'!U76 -> 3 | K35: =J35/J$105 -> 0.0013321492 | L35: =L34+K35 -> 0.98490231 | M35: =_xlfn.IFS(L35<80%,"A",L35<=95%,"B",L35>95%,"C") -> C
B36: sh19 | C36: ='Юнит 8'!AO43 -> 376.87501 | D36: =C36/C$105 -> 0.00065743554 | E36: =E35+D36 -> 1.0344085 | F36: =IF(AND(E36<=0),"C",IF(E36<=0.8,"A",IF(E36<=0.95,"B","C"))) -> C | G36: =VLOOKUP(B$4:B$104,I$4:M$104,5,0) -> C | I36: Linhai Baiyi розовая линза | J36: ='Юнит 8'!U88 -> 3 | K36: =J36/J$105 -> 0.0013321492 | L36: =L35+K36 -> 0.98623446 | M36: =_xlfn.IFS(L36<80%,"A",L36<=95%,"B",L36>95%,"C") -> C
B37: sh10 | C37: ='Юнит 8'!AO34 -> 370.3062 | D37: =C37/C$105 -> 0.00064597664 | E37: =E36+D37 -> 1.0350545 | F37: =IF(AND(E37<=0),"C",IF(E37<=0.8,"A",IF(E37<=0.95,"B","C"))) -> C | G37: =VLOOKUP(B$4:B$104,I$4:M$104,5,0) -> C | I37: sportlife красные | J37: ='Юнит 8'!U25 -> 2 | K37: =J37/J$105 -> 0.00088809947 | L37: =L36+K37 -> 0.98712256 | M37: =_xlfn.IFS(L37<80%,"A",L37<=95%,"B",L37>95%,"C") -> C
B38: Иу Диту серый | C38: ='Юнит 8'!AO91 -> 324.66858 | D38: =C38/C$105 -> 0.0005663646 | E38: =E37+D38 -> 1.0356209 | F38: =IF(AND(E38<=0),"C",IF(E38<=0.8,"A",IF(E38<=0.95,"B","C"))) -> C | G38: =VLOOKUP(B$4:B$104,I$4:M$104,5,0) -> C | I38: sh07 | J38: ='Юнит 8'!U31 -> 2 | K38: =J38/J$105 -> 0.00088809947 | L38: =L37+K38 -> 0.98801066 | M38: =_xlfn.IFS(L38<80%,"A",L38<=95%,"B",L38>95%,"C") -> C
B39: sports красные | C39: ='Юнит 8'!AO22 -> 319.18295 | D39: =C39/C$105 -> 0.00055679525 | E39: =E35+D39 -> 1.0343079 | F39: =IF(AND(E39<=0),"C",IF(E39<=0.8,"A",IF(E39<=0.95,"B","C"))) -> C | G39: =VLOOKUP(B$4:B$104,I$4:M$104,5,0) -> C | I39: sh15 | J39: ='Юнит 8'!U39 -> 2 | K39: =J39/J$105 -> 0.00088809947 | L39: =L35+K39 -> 0.98579041 | M39: =_xlfn.IFS(L39<80%,"A",L39<=95%,"B",L39>95%,"C") -> C
B40: MANNA2120 | C40: ='Юнит 8'!AO73 -> 293.2309 | D40: =C40/C$105 -> 0.00051152347 | E40: =E39+D40 -> 1.0348194 | F40: =IF(AND(E40<=0),"C",IF(E40<=0.8,"A",IF(E40<=0.95,"B","C"))) -> C | G40: =VLOOKUP(B$4:B$104,I$4:M$104,5,0) -> C | I40: sh19 | J40: ='Юнит 8'!U43 -> 2 | K40: =J40/J$105 -> 0.00088809947 | L40: =L39+K40 -> 0.98667851 | M40: =_xlfn.IFS(L40<80%,"A",L40<=95%,"B",L40>95%,"C") -> C
B41: ww 203 черные | C41: ='Юнит 8'!AO44 -> 285.19976 | D41: =C41/C$105 -> 0.00049751364 | E41: =E40+D41 -> 1.0353169 | F41: =IF(AND(E41<=0),"C",IF(E41<=0.8,"A",IF(E41<=0.95,"B","C"))) -> C | G41: =VLOOKUP(B$4:B$104,I$4:M$104,5,0) -> C | I41: ww 8010 черные | J41: ='Юнит 8'!U51 -> 2 | K41: =J41/J$105 -> 0.00088809947 | L41: =L40+K41 -> 0.98756661 | M41: =_xlfn.IFS(L41<80%,"A",L41<=95%,"B",L41>95%,"C") -> C
B42: MANNA2121 | C42: ='Юнит 8'!AO74 -> 275.4758 | D42: =C42/C$105 -> 0.00048055078 | E42: =E41+D42 -> 1.0357975 | F42: =IF(AND(E42<=0),"C",IF(E42<=0.8,"A",IF(E42<=0.95,"B","C"))) -> C | G42: =VLOOKUP(B$4:B$104,I$4:M$104,5,0) -> C | I42: MANNA2105 | J42: ='Юнит 8'!U58 -> 2 | K42: =J42/J$105 -> 0.00088809947 | L42: =L41+K42 -> 0.98845471 | M42: =_xlfn.IFS(L42<80%,"A",L42<=95%,"B",L42>95%,"C") -> C
B43: sh07 | C43: ='Юнит 8'!AO31 -> 263.4797 | D43: =C43/C$105 -> 0.00045962431 | E43: =E42+D43 -> 1.0362571 | F43: =IF(AND(E43<=0),"C",IF(E43<=0.8,"A",IF(E43<=0.95,"B","C"))) -> C | G43: =VLOOKUP(B$4:B$104,I$4:M$104,5,0) -> C | I43: MANNA2107 | J43: ='Юнит 8'!U60 -> 2 | K43: =J43/J$105 -> 0.00088809947 | L43: =L42+K43 -> 0.98934281 | M43: =_xlfn.IFS(L43<80%,"A",L43<=95%,"B",L43>95%,"C") -> C
B44: WW 3055 коричневый | C44: ='Юнит 8'!AO53 -> 251.9858 | D44: =C44/C$105 -> 0.0004395739 | E44: =E43+D44 -> 1.0366967 | F44: =IF(AND(E44<=0),"C",IF(E44<=0.8,"A",IF(E44<=0.95,"B","C"))) -> C | G44: =VLOOKUP(B$4:B$104,I$4:M$104,5,0) -> C | I44: MANNA2114 | J44: ='Юнит 8'!U67 -> 2 | K44: =J44/J$105 -> 0.00088809947 | L44: =L43+K44 -> 0.99023091 | M44: =_xlfn.IFS(L44<80%,"A",L44<=95%,"B",L44>95%,"C") -> C
B45: Guangdu серебро серая линза | C45: ='Юнит 8'!AO80 -> 236.69479 | D45: =C45/C$105 -> 0.00041289966 | E45: =E44+D45 -> 1.0371096 | F45: =IF(AND(E45<=0),"C",IF(E45<=0.8,"A",IF(E45<=0.95,"B","C"))) -> C | G45: =VLOOKUP(B$4:B$104,I$4:M$104,5,0) -> C | I45: Иу Диту серый | J45: ='Юнит 8'!U91 -> 2 | K45: =J45/J$105 -> 0.00088809947 | L45: =L44+K45 -> 0.99111901 | M45: =_xlfn.IFS(L45<80%,"A",L45<=95%,"B",L45>95%,"C") -> C
B46: YIMEI 2391 C1 | C46: ='Юнит 8'!AO98 -> 225.47693 | D46: =C46/C$105 -> 0.0003933308 | E46: =E45+D46 -> 1.0375029 | F46: =IF(AND(E46<=0),"C",IF(E46<=0.8,"A",IF(E46<=0.95,"B","C"))) -> C | G46: =VLOOKUP(B$4:B$104,I$4:M$104,5,0) -> C | I46: YIMEI 2391 C1 | J46: ='Юнит 8'!U98 -> 2 | K46: =J46/J$105 -> 0.00088809947 | L46: =L45+K46 -> 0.9920071 | M46: =_xlfn.IFS(L46<80%,"A",L46<=95%,"B",L46>95%,"C") -> C
B47: MANNA2103 | C47: ='Юнит 8'!AO56 -> 124.3773 | D47: =C47/C$105 -> 0.00021696864 | E47: =E46+D47 -> 1.0377199 | F47: =IF(AND(E47<=0),"C",IF(E47<=0.8,"A",IF(E47<=0.95,"B","C"))) -> C | G47: =VLOOKUP(B$4:B$104,I$4:M$104,5,0) -> C | I47: кс_черные_тест | J47: ='Юнит 8'!U101 -> 2 | K47: =J47/J$105 -> 0.00088809947 | L47: =L46+K47 -> 0.9928952 | M47: =_xlfn.IFS(L47<80%,"A",L47<=95%,"B",L47>95%,"C") -> C
B48: sh4 | C48: ='Юнит 8'!AO29 -> 122.9223 | D48: =C48/C$105 -> 0.00021443048 | E48: =E47+D48 -> 1.0379343 | F48: =IF(AND(E48<=0),"C",IF(E48<=0.8,"A",IF(E48<=0.95,"B","C"))) -> C | G48: =VLOOKUP(B$4:B$104,I$4:M$104,5,0) -> C | I48: sports красные | J48: ='Юнит 8'!U22 -> 1 | K48: =J48/J$105 -> 0.00044404973 | L48: =L47+K48 -> 0.99333925 | M48: =_xlfn.IFS(L48<80%,"A",L48<=95%,"B",L48>95%,"C") -> C
B49: sh13 | C49: ='Юнит 8'!AO37 -> 87.553266 | D49: =C49/C$105 -> 0.00015273135 | E49: =E48+D49 -> 1.038087 | F49: =IF(AND(E49<=0),"C",IF(E49<=0.8,"A",IF(E49<=0.95,"B","C"))) -> C | G49: =VLOOKUP(B$4:B$104,I$4:M$104,5,0) -> C | I49: sh4 | J49: ='Юнит 8'!U29 -> 1 | K49: =J49/J$105 -> 0.00044404973 | L49: =L48+K49 -> 0.9937833 | M49: =_xlfn.IFS(L49<80%,"A",L49<=95%,"B",L49>95%,"C") -> C
B50: sh06 | C50: ='Юнит 8'!AO30 -> 72.8636 | D50: =C50/C$105 -> 0.00012710612 | E50: =E49+D50 -> 1.0382141 | F50: =IF(AND(E50<=0),"C",IF(E50<=0.8,"A",IF(E50<=0.95,"B","C"))) -> C | G50: =VLOOKUP(B$4:B$104,I$4:M$104,5,0) -> C | I50: sh06 | J50: ='Юнит 8'!U30 -> 1 | K50: =J50/J$105 -> 0.00044404973 | L50: =L49+K50 -> 0.99422735 | M50: =_xlfn.IFS(L50<80%,"A",L50<=95%,"B",L50>95%,"C") -> C
B51: wwl8032 черные серебро | C51: ='Юнит 8'!AO19 -> 0 | D51: =C51/C$105 -> 0 | E51: =E50+D51 -> 1.0382141 | F51: =IF(AND(E51<=0),"C",IF(E51<=0.8,"A",IF(E51<=0.95,"B","C"))) -> C | G51: =VLOOKUP(B$4:B$104,I$4:M$104,5,0) -> C | I51: sh13 | J51: ='Юнит 8'!U37 -> 1 | K51: =J51/J$105 -> 0.00044404973 | L51: =L50+K51 -> 0.9946714 | M51: =_xlfn.IFS(L51<80%,"A",L51<=95%,"B",L51>95%,"C") -> C
B52: sports синие | C52: ='Юнит 8'!AO20 -> 0 | D52: =C52/C$105 -> 0 | E52: =E51+D52 -> 1.0382141 | F52: =IF(AND(E52<=0),"C",IF(E52<=0.8,"A",IF(E52<=0.95,"B","C"))) -> C | G52: =VLOOKUP(B$4:B$104,I$4:M$104,5,0) -> C | I52: WW 3055 коричневый | J52: ='Юнит 8'!U53 -> 1 | K52: =J52/J$105 -> 0.00044404973 | L52: =L51+K52 -> 0.99511545 | M52: =_xlfn.IFS(L52<80%,"A",L52<=95%,"B",L52>95%,"C") -> C
B53: sportlife черные | C53: ='Юнит 8'!AO23 -> 0 | D53: =C53/C$105 -> 0 | E53: =E52+D53 -> 1.0382141 | F53: =IF(AND(E53<=0),"C",IF(E53<=0.8,"A",IF(E53<=0.95,"B","C"))) -> C | G53: =VLOOKUP(B$4:B$104,I$4:M$104,5,0) -> C | I53: MANNA2101 | J53: ='Юнит 8'!U54 -> 1 | K53: =J53/J$105 -> 0.00044404973 | L53: =L52+K53 -> 0.9955595 | M53: =_xlfn.IFS(L53<80%,"A",L53<=95%,"B",L53>95%,"C") -> C
B54: sportlife синие | C54: ='Юнит 8'!AO24 -> 0 | D54: =C54/C$105 -> 0 | E54: =E53+D54 -> 1.0382141 | F54: =IF(AND(E54<=0),"C",IF(E54<=0.8,"A",IF(E54<=0.95,"B","C"))) -> C | G54: =VLOOKUP(B$4:B$104,I$4:M$104,5,0) -> C | I54: MANNA2103 | J54: ='Юнит 8'!U56 -> 1 | K54: =J54/J$105 -> 0.00044404973 | L54: =L53+K54 -> 0.99600355 | M54: =_xlfn.IFS(L54<80%,"A",L54<=95%,"B",L54>95%,"C") -> C
B55: sh08 | C55: ='Юнит 8'!AO32 -> 0 | D55: =C55/C$105 -> 0 | E55: =E54+D55 -> 1.0382141 | F55: =IF(AND(E55<=0),"C",IF(E55<=0.8,"A",IF(E55<=0.95,"B","C"))) -> C | G55: =VLOOKUP(B$4:B$104,I$4:M$104,5,0) -> C | I55: MANNA2118 | J55: ='Юнит 8'!U71 -> 1 | K55: =J55/J$105 -> 0.00044404973 | L55: =L54+K55 -> 0.9964476 | M55: =_xlfn.IFS(L55<80%,"A",L55<=95%,"B",L55>95%,"C") -> C
B56: sh11 | C56: ='Юнит 8'!AO35 -> 0 | D56: =C56/C$105 -> 0 | E56: =E55+D56 -> 1.0382141 | F56: =IF(AND(E56<=0),"C",IF(E56<=0.8,"A",IF(E56<=0.95,"B","C"))) -> C | G56: =VLOOKUP(B$4:B$104,I$4:M$104,5,0) -> C | I56: MANNA2121 | J56: ='Юнит 8'!U74 -> 1 | K56: =J56/J$105 -> 0.00044404973 | L56: =L55+K56 -> 0.99689165 | M56: =_xlfn.IFS(L56<80%,"A",L56<=95%,"B",L56>95%,"C") -> C
B57: sh12 | C57: ='Юнит 8'!AO36 -> 0 | D57: =C57/C$105 -> 0 | E57: =E56+D57 -> 1.0382141 | F57: =IF(AND(E57<=0),"C",IF(E57<=0.8,"A",IF(E57<=0.95,"B","C"))) -> C | G57: =VLOOKUP(B$4:B$104,I$4:M$104,5,0) -> C | I57: Guangdu серебро серая линза | J57: ='Юнит 8'!U80 -> 1 | K57: =J57/J$105 -> 0.00044404973 | L57: =L56+K57 -> 0.9973357 | M57: =_xlfn.IFS(L57<80%,"A",L57<=95%,"B",L57>95%,"C") -> C
B58: ww 1022 черн-серебро | C58: ='Юнит 8'!AO46 -> 0 | D58: =C58/C$105 -> 0 | E58: =E57+D58 -> 1.0382141 | F58: =IF(AND(E58<=0),"C",IF(E58<=0.8,"A",IF(E58<=0.95,"B","C"))) -> C | G58: =VLOOKUP(B$4:B$104,I$4:M$104,5,0) -> C | I58: Linhai Baiyi серая линза | J58: ='Юнит 8'!U87 -> 1 | K58: =J58/J$105 -> 0.00044404973 | L58: =L57+K58 -> 0.99777975 | M58: =_xlfn.IFS(L58<80%,"A",L58<=95%,"B",L58>95%,"C") -> C
B59: MANNA2104 | C59: ='Юнит 8'!AO57 -> 0 | D59: =C59/C$105 -> 0 | E59: =E58+D59 -> 1.0382141 | F59: =IF(AND(E59<=0),"C",IF(E59<=0.8,"A",IF(E59<=0.95,"B","C"))) -> C | G59: =VLOOKUP(B$4:B$104,I$4:M$104,5,0) -> C | I59: wwl8032 черные серебро | J59: ='Юнит 8'!U19 -> 0 | K59: =J59/J$105 -> 0 | L59: =L58+K59 -> 0.99777975 | M59: =_xlfn.IFS(L59<80%,"A",L59<=95%,"B",L59>95%,"C") -> C
B60: MANNA2106 | C60: ='Юнит 8'!AO59 -> 0 | D60: =C60/C$105 -> 0 | E60: =E59+D60 -> 1.0382141 | F60: =IF(AND(E60<=0),"C",IF(E60<=0.8,"A",IF(E60<=0.95,"B","C"))) -> C | G60: =VLOOKUP(B$4:B$104,I$4:M$104,5,0) -> C | I60: sports синие | J60: ='Юнит 8'!U20 -> 0 | K60: =J60/J$105 -> 0 | L60: =L59+K60 -> 0.99777975 | M60: =_xlfn.IFS(L60<80%,"A",L60<=95%,"B",L60>95%,"C") -> C
B61: MANNA2109 | C61: ='Юнит 8'!AO62 -> 0 | D61: =C61/C$105 -> 0 | E61: =E60+D61 -> 1.0382141 | F61: =IF(AND(E61<=0),"C",IF(E61<=0.8,"A",IF(E61<=0.95,"B","C"))) -> C | G61: =VLOOKUP(B$4:B$104,I$4:M$104,5,0) -> C | I61: sports зеленые | J61: ='Юнит 8'!U21 -> 0 | K61: =J61/J$105 -> 0 | L61: =L60+K61 -> 0.99777975 | M61: =_xlfn.IFS(L61<80%,"A",L61<=95%,"B",L61>95%,"C") -> C
B62: MANNA2110 | C62: ='Юнит 8'!AO63 -> 0 | D62: =C62/C$105 -> 0 | E62: =E61+D62 -> 1.0382141 | F62: =IF(AND(E62<=0),"C",IF(E62<=0.8,"A",IF(E62<=0.95,"B","C"))) -> C | G62: =VLOOKUP(B$4:B$104,I$4:M$104,5,0) -> C | I62: sportlife черные | J62: ='Юнит 8'!U23 -> 0 | K62: =J62/J$105 -> 0 | L62: =L61+K62 -> 0.99777975 | M62: =_xlfn.IFS(L62<80%,"A",L62<=95%,"B",L62>95%,"C") -> C
B63: MANNA2111 | C63: ='Юнит 8'!AO64 -> 0 | D63: =C63/C$105 -> 0 | E63: =E62+D63 -> 1.0382141 | F63: =IF(AND(E63<=0),"C",IF(E63<=0.8,"A",IF(E63<=0.95,"B","C"))) -> C | G63: =VLOOKUP(B$4:B$104,I$4:M$104,5,0) -> C | I63: sportlife синие | J63: ='Юнит 8'!U24 -> 0 | K63: =J63/J$105 -> 0 | L63: =L62+K63 -> 0.99777975 | M63: =_xlfn.IFS(L63<80%,"A",L63<=95%,"B",L63>95%,"C") -> C
B64: MANNA2115 | C64: ='Юнит 8'!AO68 -> 0 | D64: =C64/C$105 -> 0 | E64: =E63+D64 -> 1.0382141 | F64: =IF(AND(E64<=0),"C",IF(E64<=0.8,"A",IF(E64<=0.95,"B","C"))) -> C | G64: =VLOOKUP(B$4:B$104,I$4:M$104,5,0) -> C | I64: sh08 | J64: ='Юнит 8'!U32 -> 0 | K64: =J64/J$105 -> 0 | L64: =L63+K64 -> 0.99777975 | M64: =_xlfn.IFS(L64<80%,"A",L64<=95%,"B",L64>95%,"C") -> C
B65: MAIERSHA 03898 C9-08 | C65: ='Юнит 8'!AO94 -> 0 | D65: =C65/C$105 -> 0 | E65: =E64+D65 -> 1.0382141 | F65: =IF(AND(E65<=0),"C",IF(E65<=0.8,"A",IF(E65<=0.95,"B","C"))) -> C | G65: =VLOOKUP(B$4:B$104,I$4:M$104,5,0) -> C | I65: sh11 | J65: ='Юнит 8'!U35 -> 0 | K65: =J65/J$105 -> 0 | L65: =L64+K65 -> 0.99777975 | M65: =_xlfn.IFS(L65<80%,"A",L65<=95%,"B",L65>95%,"C") -> C
B66: MAIERSHA 03914 C9-124 | C66: ='Юнит 8'!AO95 -> 0 | D66: =C66/C$105 -> 0 | E66: =E65+D66 -> 1.0382141 | F66: =IF(AND(E66<=0),"C",IF(E66<=0.8,"A",IF(E66<=0.95,"B","C"))) -> C | G66: =VLOOKUP(B$4:B$104,I$4:M$104,5,0) -> C | I66: sh12 | J66: ='Юнит 8'!U36 -> 0 | K66: =J66/J$105 -> 0 | L66: =L65+K66 -> 0.99777975 | M66: =_xlfn.IFS(L66<80%,"A",L66<=95%,"B",L66>95%,"C") -> C
B67: MARSTON 7171 C1 | C67: ='Юнит 8'!AO96 -> 0 | D67: =C67/C$105 -> 0 | E67: =E66+D67 -> 1.0382141 | F67: =IF(AND(E67<=0),"C",IF(E67<=0.8,"A",IF(E67<=0.95,"B","C"))) -> C | G67: =VLOOKUP(B$4:B$104,I$4:M$104,5,0) -> C | I67: sh14 | J67: ='Юнит 8'!U38 -> 0 | K67: =J67/J$105 -> 0 | L67: =L66+K67 -> 0.99777975 | M67: =_xlfn.IFS(L67<80%,"A",L67<=95%,"B",L67>95%,"C") -> C
B68: ЧСЖ_тест | C68: ='Юнит 8'!AO99 -> 0 | D68: =C68/C$105 -> 0 | E68: =E67+D68 -> 1.0382141 | F68: =IF(AND(E68<=0),"C",IF(E68<=0.8,"A",IF(E68<=0.95,"B","C"))) -> C | G68: =VLOOKUP(B$4:B$104,I$4:M$104,5,0) -> C | I68: sh16 | J68: ='Юнит 8'!U40 -> 0 | K68: =J68/J$105 -> 0 | L68: =L67+K68 -> 0.99777975 | M68: =_xlfn.IFS(L68<80%,"A",L68<=95%,"B",L68>95%,"C") -> C
B69: ЧСЖ_женские | C69: ='Юнит 8'!AO100 -> 0 | D69: =C69/C$105 -> 0 | E69: =E68+D69 -> 1.0382141 | F69: =IF(AND(E69<=0),"C",IF(E69<=0.8,"A",IF(E69<=0.95,"B","C"))) -> C | G69: =VLOOKUP(B$4:B$104,I$4:M$104,5,0) -> C | I69: sh17 | J69: ='Юнит 8'!U41 -> 0 | K69: =J69/J$105 -> 0 | L69: =L68+K69 -> 0.99777975 | M69: =_xlfn.IFS(L69<80%,"A",L69<=95%,"B",L69>95%,"C") -> C
B70: кс_черные_женские | C70: ='Юнит 8'!AO102 -> 0 | D70: =C70/C$105 -> 0 | E70: =E69+D70 -> 1.0382141 | F70: =IF(AND(E70<=0),"C",IF(E70<=0.8,"A",IF(E70<=0.95,"B","C"))) -> C | G70: =VLOOKUP(B$4:B$104,I$4:M$104,5,0) -> C | I70: sh18 | J70: ='Юнит 8'!U42 -> 0 | K70: =J70/J$105 -> 0 | L70: =L69+K70 -> 0.99777975 | M70: =_xlfn.IFS(L70<80%,"A",L70<=95%,"B",L70>95%,"C") -> C
B71: sports зеленые | C71: ='Юнит 8'!AO21 -> -0.86724686 | D71: =C71/C$105 -> -1.5128594e-06 | E71: =E70+D71 -> 1.0382126 | F71: =IF(AND(E71<=0),"C",IF(E71<=0.8,"A",IF(E71<=0.95,"B","C"))) -> C | G71: =VLOOKUP(B$4:B$104,I$4:M$104,5,0) -> C | I71: ww 1022 черн-серебро | J71: ='Юнит 8'!U46 -> 0 | K71: =J71/J$105 -> 0 | L71: =L70+K71 -> 0.99777975 | M71: =_xlfn.IFS(L71<80%,"A",L71<=95%,"B",L71>95%,"C") -> C
B72: MANNA2102 | C72: ='Юнит 8'!AO55 -> -0.86724686 | D72: =C72/C$105 -> -1.5128594e-06 | E72: =E71+D72 -> 1.0382111 | F72: =IF(AND(E72<=0),"C",IF(E72<=0.8,"A",IF(E72<=0.95,"B","C"))) -> C | G72: =VLOOKUP(B$4:B$104,I$4:M$104,5,0) -> C | I72: WW 3055 черный | J72: ='Юнит 8'!U52 -> 0 | K72: =J72/J$105 -> 0 | L72: =L71+K72 -> 0.99777975 | M72: =_xlfn.IFS(L72<80%,"A",L72<=95%,"B",L72>95%,"C") -> C
B73: MANNA2113 | C73: ='Юнит 8'!AO66 -> -0.86724686 | D73: =C73/C$105 -> -1.5128594e-06 | E73: =E72+D73 -> 1.0382096 | F73: =IF(AND(E73<=0),"C",IF(E73<=0.8,"A",IF(E73<=0.95,"B","C"))) -> C | G73: =VLOOKUP(B$4:B$104,I$4:M$104,5,0) -> C | I73: MANNA2102 | J73: ='Юнит 8'!U55 -> 0 | K73: =J73/J$105 -> 0 | L73: =L72+K73 -> 0.99777975 | M73: =_xlfn.IFS(L73<80%,"A",L73<=95%,"B",L73>95%,"C") -> C
B74: POMILED 08247 C4-08 | C74: ='Юнит 8'!AO97 -> -2.6017406 | D74: =C74/C$105 -> -4.5385782e-06 | E74: =E73+D74 -> 1.038205 | F74: =IF(AND(E74<=0),"C",IF(E74<=0.8,"A",IF(E74<=0.95,"B","C"))) -> C | G74: =VLOOKUP(B$4:B$104,I$4:M$104,5,0) -> C | I74: MANNA2104 | J74: ='Юнит 8'!U57 -> 0 | K74: =J74/J$105 -> 0 | L74: =L73+K74 -> 0.99777975 | M74: =_xlfn.IFS(L74<80%,"A",L74<=95%,"B",L74>95%,"C") -> C
B75: MANNA2116 | C75: ='Юнит 8'!AO69 -> -10.406962 | D75: =C75/C$105 -> -1.8154313e-05 | E75: =E74+D75 -> 1.0381869 | F75: =IF(AND(E75<=0),"C",IF(E75<=0.8,"A",IF(E75<=0.95,"B","C"))) -> C | G75: =VLOOKUP(B$4:B$104,I$4:M$104,5,0) -> C | I75: MANNA2106 | J75: ='Юнит 8'!U59 -> 0 | K75: =J75/J$105 -> 0 | L75: =L74+K75 -> 0.99777975 | M75: =_xlfn.IFS(L75<80%,"A",L75<=95%,"B",L75>95%,"C") -> C
B76: Chenlong коричневые | C76: ='Юнит 8'!AO77 -> -33.822627 | D76: =C76/C$105 -> -5.9001517e-05 | E76: =E49+D76 -> 1.038028 | F76: =IF(AND(E76<=0),"C",IF(E76<=0.8,"A",IF(E76<=0.95,"B","C"))) -> C | G76: =VLOOKUP(B$4:B$104,I$4:M$104,5,0) -> C | I76: MANNA2108 | J76: ='Юнит 8'!U61 -> 0 | K76: =J76/J$105 -> 0 | L76: =L49+K76 -> 0.9937833 | M76: =_xlfn.IFS(L76<80%,"A",L76<=95%,"B",L76>95%,"C") -> C
B77: sh17 | C77: ='Юнит 8'!AO41 -> -39.893355 | D77: =C77/C$105 -> -6.9591533e-05 | E77: =E76+D77 -> 1.0379584 | F77: =IF(AND(E77<=0),"C",IF(E77<=0.8,"A",IF(E77<=0.95,"B","C"))) -> C | G77: =VLOOKUP(B$4:B$104,I$4:M$104,5,0) -> C | I77: MANNA2109 | J77: ='Юнит 8'!U62 -> 0 | K77: =J77/J$105 -> 0 | L77: =L76+K77 -> 0.9937833 | M77: =_xlfn.IFS(L77<80%,"A",L77<=95%,"B",L77>95%,"C") -> C
B78: Linhai Baiyi коричневая линза | C78: ='Юнит 8'!AO86 -> -39.893355 | D78: =C78/C$105 -> -6.9591533e-05 | E78: =E77+D78 -> 1.0378888 | F78: =IF(AND(E78<=0),"C",IF(E78<=0.8,"A",IF(E78<=0.95,"B","C"))) -> C | G78: =VLOOKUP(B$4:B$104,I$4:M$104,5,0) -> C | I78: MANNA2110 | J78: ='Юнит 8'!U63 -> 0 | K78: =J78/J$105 -> 0 | L78: =L77+K78 -> 0.9937833 | M78: =_xlfn.IFS(L78<80%,"A",L78<=95%,"B",L78>95%,"C") -> C
B79: Hengda Optical леопард | C79: ='Юнит 8'!AO82 -> -41.627849 | D79: =C79/C$105 -> -7.2617252e-05 | E79: =E78+D79 -> 1.0378162 | F79: =IF(AND(E79<=0),"C",IF(E79<=0.8,"A",IF(E79<=0.95,"B","C"))) -> C | G79: =VLOOKUP(B$4:B$104,I$4:M$104,5,0) -> C | I79: MANNA2111 | J79: ='Юнит 8'!U64 -> 0 | K79: =J79/J$105 -> 0 | L79: =L78+K79 -> 0.9937833 | M79: =_xlfn.IFS(L79<80%,"A",L79<=95%,"B",L79>95%,"C") -> C
B80: Qianai коричневые | C80: ='Юнит 8'!AO84 -> -41.627849 | D80: =C80/C$105 -> -7.2617252e-05 | E80: =E79+D80 -> 1.0377436 | F80: =IF(AND(E80<=0),"C",IF(E80<=0.8,"A",IF(E80<=0.95,"B","C"))) -> C | G80: =VLOOKUP(B$4:B$104,I$4:M$104,5,0) -> C | I80: MANNA2112 | J80: ='Юнит 8'!U65 -> 0 | K80: =J80/J$105 -> 0 | L80: =L79+K80 -> 0.9937833 | M80: =_xlfn.IFS(L80<80%,"A",L80<=95%,"B",L80>95%,"C") -> C
B81: Taizhou Rayen sport розовый | C81: ='Юнит 8'!AO90 -> -43.362343 | D81: =C81/C$105 -> -7.564297e-05 | E81: =E80+D81 -> 1.037668 | F81: =IF(AND(E81<=0),"C",IF(E81<=0.8,"A",IF(E81<=0.95,"B","C"))) -> C | G81: =VLOOKUP(B$4:B$104,I$4:M$104,5,0) -> C | I81: MANNA2113 | J81: ='Юнит 8'!U66 -> 0 | K81: =J81/J$105 -> 0 | L81: =L80+K81 -> 0.9937833 | M81: =_xlfn.IFS(L81<80%,"A",L81<=95%,"B",L81>95%,"C") -> C
B82: MANNA2101 | C82: ='Юнит 8'!AO54 -> -51.169362 | D82: =C82/C$105 -> -8.926184e-05 | E82: =E81+D82 -> 1.0375787 | F82: =IF(AND(E82<=0),"C",IF(E82<=0.8,"A",IF(E82<=0.95,"B","C"))) -> C | G82: =VLOOKUP(B$4:B$104,I$4:M$104,5,0) -> C | I82: MANNA2115 | J82: ='Юнит 8'!U68 -> 0 | K82: =J82/J$105 -> 0 | L82: =L81+K82 -> 0.9937833 | M82: =_xlfn.IFS(L82<80%,"A",L82<=95%,"B",L82>95%,"C") -> C
B83: MANNA2112 | C83: ='Юнит 8'!AO65 -> -97.267247 | D83: =C83/C$105 -> -0.0001696768 | E83: =E82+D83 -> 1.037409 | F83: =IF(AND(E83<=0),"C",IF(E83<=0.8,"A",IF(E83<=0.95,"B","C"))) -> C | G83: =VLOOKUP(B$4:B$104,I$4:M$104,5,0) -> C | I83: MANNA2116 | J83: ='Юнит 8'!U69 -> 0 | K83: =J83/J$105 -> 0 | L83: =L82+K83 -> 0.9937833 | M83: =_xlfn.IFS(L83<80%,"A",L83<=95%,"B",L83>95%,"C") -> C
B84: MANNA2117 | C84: ='Юнит 8'!AO70 -> -101.19623 | D84: =C84/C$105 -> -0.00017653068 | E84: =E83+D84 -> 1.0372325 | F84: =IF(AND(E84<=0),"C",IF(E84<=0.8,"A",IF(E84<=0.95,"B","C"))) -> C | G84: =VLOOKUP(B$4:B$104,I$4:M$104,5,0) -> C | I84: MANNA2117 | J84: ='Юнит 8'!U70 -> 0 | K84: =J84/J$105 -> 0 | L84: =L83+K84 -> 0.9937833 | M84: =_xlfn.IFS(L84<80%,"A",L84<=95%,"B",L84>95%,"C") -> C
B85: sh18 | C85: ='Юнит 8'!AO42 -> -122.09161 | D85: =C85/C$105 -> -0.0002129814 | E85: =E84+D85 -> 1.0370195 | F85: =IF(AND(E85<=0),"C",IF(E85<=0.8,"A",IF(E85<=0.95,"B","C"))) -> C | G85: =VLOOKUP(B$4:B$104,I$4:M$104,5,0) -> C | I85: Chenlong коричневые | J85: ='Юнит 8'!U77 -> 0 | K85: =J85/J$105 -> 0 | L85: =L84+K85 -> 0.9937833 | M85: =_xlfn.IFS(L85<80%,"A",L85<=95%,"B",L85>95%,"C") -> C
B86: Chenlong белые | C86: ='Юнит 8'!AO78 -> -129.39392 | D86: =C86/C$105 -> -0.00022571983 | E86: =E85+D86 -> 1.0367938 | F86: =IF(AND(E86<=0),"C",IF(E86<=0.8,"A",IF(E86<=0.95,"B","C"))) -> C | G86: =VLOOKUP(B$4:B$104,I$4:M$104,5,0) -> C | I86: Chenlong белые | J86: ='Юнит 8'!U78 -> 0 | K86: =J86/J$105 -> 0 | L86: =L85+K86 -> 0.9937833 | M86: =_xlfn.IFS(L86<80%,"A",L86<=95%,"B",L86>95%,"C") -> C
B87: Ли Сян ретро серебро | C87: ='Юнит 8'!AO93 -> -132.1706 | D87: =C87/C$105 -> -0.00023056358 | E87: =E86+D87 -> 1.0365632 | F87: =IF(AND(E87<=0),"C",IF(E87<=0.8,"A",IF(E87<=0.95,"B","C"))) -> C | G87: =VLOOKUP(B$4:B$104,I$4:M$104,5,0) -> C | I87: Guangdu золото серая линза | J87: ='Юнит 8'!U79 -> 0 | K87: =J87/J$105 -> 0 | L87: =L86+K87 -> 0.9937833 | M87: =_xlfn.IFS(L87<80%,"A",L87<=95%,"B",L87>95%,"C") -> C
B88: Guangdu золото серая линза | C88: ='Юнит 8'!AO79 -> -136.75336 | D88: =C88/C$105 -> -0.00023855791 | E88: =E87+D88 -> 1.0363247 | F88: =IF(AND(E88<=0),"C",IF(E88<=0.8,"A",IF(E88<=0.95,"B","C"))) -> C | G88: =VLOOKUP(B$4:B$104,I$4:M$104,5,0) -> C | I88: Hengda Optical леопард | J88: ='Юнит 8'!U82 -> 0 | K88: =J88/J$105 -> 0 | L88: =L87+K88 -> 0.9937833 | M88: =_xlfn.IFS(L88<80%,"A",L88<=95%,"B",L88>95%,"C") -> C
B89: Qianai черные | C89: ='Юнит 8'!AO83 -> -147.60611 | D89: =C89/C$105 -> -0.00025748988 | E89: =E88+D89 -> 1.0360672 | F89: =IF(AND(E89<=0),"C",IF(E89<=0.8,"A",IF(E89<=0.95,"B","C"))) -> C | G89: =VLOOKUP(B$4:B$104,I$4:M$104,5,0) -> C | I89: Qianai черные | J89: ='Юнит 8'!U83 -> 0 | K89: =J89/J$105 -> 0 | L89: =L88+K89 -> 0.9937833 | M89: =_xlfn.IFS(L89<80%,"A",L89<=95%,"B",L89>95%,"C") -> C
B90: Ли Сян ретро золото | C90: ='Юнит 8'!AO92 -> -150.1751 | D90: =C90/C$105 -> -0.00026197132 | E90: =E89+D90 -> 1.0358052 | F90: =IF(AND(E90<=0),"C",IF(E90<=0.8,"A",IF(E90<=0.95,"B","C"))) -> C | G90: =VLOOKUP(B$4:B$104,I$4:M$104,5,0) -> C | I90: Qianai коричневые | J90: ='Юнит 8'!U84 -> 0 | K90: =J90/J$105 -> 0 | L90: =L89+K90 -> 0.9937833 | M90: =_xlfn.IFS(L90<80%,"A",L90<=95%,"B",L90>95%,"C") -> C
B91: Hengda Optical черные | C91: ='Юнит 8'!AO81 -> -179.12462 | D91: =C91/C$105 -> -0.000312472 | E91: =E90+D91 -> 1.0354927 | F91: =IF(AND(E91<=0),"C",IF(E91<=0.8,"A",IF(E91<=0.95,"B","C"))) -> C | G91: =VLOOKUP(B$4:B$104,I$4:M$104,5,0) -> C | I91: Linhai Baiyi коричневая линза | J91: ='Юнит 8'!U86 -> 0 | K91: =J91/J$105 -> 0 | L91: =L90+K91 -> 0.9937833 | M91: =_xlfn.IFS(L91<80%,"A",L91<=95%,"B",L91>95%,"C") -> C
B92: MANNA2108 | C92: ='Юнит 8'!AO61 -> -235.29124 | D92: =C92/C$105 -> -0.00041045126 | E92: =E91+D92 -> 1.0350823 | F92: =IF(AND(E92<=0),"C",IF(E92<=0.8,"A",IF(E92<=0.95,"B","C"))) -> C | G92: =VLOOKUP(B$4:B$104,I$4:M$104,5,0) -> C | I92: Taizhou Rayen sport розовый | J92: ='Юнит 8'!U90 -> 0 | K92: =J92/J$105 -> 0 | L92: =L91+K92 -> 0.9937833 | M92: =_xlfn.IFS(L92<80%,"A",L92<=95%,"B",L92>95%,"C") -> C
B93: ww 2018 желтые | C93: ='Юнит 8'!AO50 -> -240.01393 | D93: =C93/C$105 -> -0.00041868971 | E93: =E92+D93 -> 1.0346636 | F93: =IF(AND(E93<=0),"C",IF(E93<=0.8,"A",IF(E93<=0.95,"B","C"))) -> C | G93: =VLOOKUP(B$4:B$104,I$4:M$104,5,0) -> C | I93: Ли Сян ретро золото | J93: ='Юнит 8'!U92 -> 0 | K93: =J93/J$105 -> 0 | L93: =L92+K93 -> 0.9937833 | M93: =_xlfn.IFS(L93<80%,"A",L93<=95%,"B",L93>95%,"C") -> C
B94: 1022_коричневые_тест | C94: ='Юнит 8'!AO103 -> -336 | D94: =C94/C$105 -> -0.00058613157 | E94: =E93+D94 -> 1.0340775 | F94: =IF(AND(E94<=0),"C",IF(E94<=0.8,"A",IF(E94<=0.95,"B","C"))) -> C | G94: =VLOOKUP(B$4:B$104,I$4:M$104,5,0) -> C | I94: Ли Сян ретро серебро | J94: ='Юнит 8'!U93 -> 0 | K94: =J94/J$105 -> 0 | L94: =L93+K94 -> 0.9937833 | M94: =_xlfn.IFS(L94<80%,"A",L94<=95%,"B",L94>95%,"C") -> C
B95: MANNA2122 | C95: ='Юнит 8'!AO75 -> -352.323 | D95: =C95/C$105 -> -0.00061460605 | E95: =E94+D95 -> 1.0334629 | F95: =IF(AND(E95<=0),"C",IF(E95<=0.8,"A",IF(E95<=0.95,"B","C"))) -> C | G95: =VLOOKUP(B$4:B$104,I$4:M$104,5,0) -> C | I95: MAIERSHA 03898 C9-08 | J95: ='Юнит 8'!U94 -> 0 | K95: =J95/J$105 -> 0 | L95: =L94+K95 -> 0.9937833 | M95: =_xlfn.IFS(L95<80%,"A",L95<=95%,"B",L95>95%,"C") -> C
B96: sh14 | C96: ='Юнит 8'!AO38 -> -360.52336 | D96: =C96/C$105 -> -0.00062891107 | E96: =E95+D96 -> 1.0328339 | F96: =IF(AND(E96<=0),"C",IF(E96<=0.8,"A",IF(E96<=0.95,"B","C"))) -> C | G96: =VLOOKUP(B$4:B$104,I$4:M$104,5,0) -> C | I96: MAIERSHA 03914 C9-124 | J96: ='Юнит 8'!U95 -> 0 | K96: =J96/J$105 -> 0 | L96: =L95+K96 -> 0.9937833 | M96: =_xlfn.IFS(L96<80%,"A",L96<=95%,"B",L96>95%,"C") -> C
B97: MANNA2118 | C97: ='Юнит 8'!AO71 -> -452.54192 | D97: =C97/C$105 -> -0.00078943185 | E97: =E96+D97 -> 1.0320445 | F97: =IF(AND(E97<=0),"C",IF(E97<=0.8,"A",IF(E97<=0.95,"B","C"))) -> C | G97: =VLOOKUP(B$4:B$104,I$4:M$104,5,0) -> C | I97: MARSTON 7171 C1 | J97: ='Юнит 8'!U96 -> 0 | K97: =J97/J$105 -> 0 | L97: =L96+K97 -> 0.9937833 | M97: =_xlfn.IFS(L97<80%,"A",L97<=95%,"B",L97>95%,"C") -> C
B98: WW 3055 черный | C98: ='Юнит 8'!AO52 -> -459.71336 | D98: =C98/C$105 -> -0.00080194199 | E98: =E97+D98 -> 1.0312426 | F98: =IF(AND(E98<=0),"C",IF(E98<=0.8,"A",IF(E98<=0.95,"B","C"))) -> C | G98: =VLOOKUP(B$4:B$104,I$4:M$104,5,0) -> C | I98: POMILED 08247 C4-08 | J98: ='Юнит 8'!U97 -> 0 | K98: =J98/J$105 -> 0 | L98: =L97+K98 -> 0.9937833 | M98: =_xlfn.IFS(L98<80%,"A",L98<=95%,"B",L98>95%,"C") -> C
B99: sh16 | C99: ='Юнит 8'!AO40 -> -467.82712 | D99: =C99/C$105 -> -0.00081609596 | E99: =E93+D99 -> 1.0338475 | F99: =IF(AND(E99<=0),"C",IF(E99<=0.8,"A",IF(E99<=0.95,"B","C"))) -> C | G99: =VLOOKUP(B$4:B$104,I$4:M$104,5,0) -> C | I99: ЧСЖ_тест | J99: ='Юнит 8'!U99 -> 0 | K99: =J99/J$105 -> 0 | L99: =L93+K99 -> 0.9937833 | M99: =_xlfn.IFS(L99<80%,"A",L99<=95%,"B",L99>95%,"C") -> C
B100: sh2 | C100: ='Юнит 8'!AO27 -> -479.23771 | D100: =C100/C$105 -> -0.00083600104 | E100: =E94+D100 -> 1.0332415 | F100: =IF(AND(E100<=0),"C",IF(E100<=0.8,"A",IF(E100<=0.95,"B","C"))) -> C | G100: =VLOOKUP(B$4:B$104,I$4:M$104,5,0) -> C | I100: ЧСЖ_женские | J100: ='Юнит 8'!U100 -> 0 | K100: =J100/J$105 -> 0 | L100: =L94+K100 -> 0.9937833 | M100: =_xlfn.IFS(L100<80%,"A",L100<=95%,"B",L100>95%,"C") -> C
B101: Keming Aishi коричневые | C101: ='Юнит 8'!AO85 -> -894.03443 | D101: =C101/C$105 -> -0.0015595887 | E101: =E95+D101 -> 1.0319033 | F101: =IF(AND(E101<=0),"C",IF(E101<=0.8,"A",IF(E101<=0.95,"B","C"))) -> C | G101: =VLOOKUP(B$4:B$104,I$4:M$104,5,0) -> C | I101: кс_черные_женские | J101: ='Юнит 8'!U102 -> 0 | K101: =J101/J$105 -> 0 | L101: =L95+K101 -> 0.9937833 | M101: =_xlfn.IFS(L101<80%,"A",L101<=95%,"B",L101>95%,"C") -> C
...

Sheet АВС ЯНВАРЬ
B2: ОЧКИ
C3: Прибыль | D3: % прибыль | E3: Доля | F3: ABC прибыль | G3: ABC кол-во | J3: Кол-во | K3: % кол-во | L3: Доля | M3: ABC кол-во
B4: QS черные PZ | C4: =ЯНВАРЬ!AO4 -> 95522.058 | D4: =C4/C$100 -> 0.50905425 | E4: =D4 -> 0.50905425 | F4: =IF(AND(E4<=0),"C",IF(E4<=0.8,"A",IF(E4<=0.95,"B","C"))) -> A | G4: =VLOOKUP(B$4:B$99,I$4:M$99,5,0) -> A | I4: QS черные PZ | J4: =ЯНВАРЬ!U4 -> 602 | K4: =J4/J$100 -> 0.26071893 | L4: =K4 -> 0.26071893 | M4: =_xlfn.IFS(L4<80%,"A",L4<=95%,"B",L4>95%,"C") -> A | P4: A | Q4: 0.8
B5: QS синие PZ | C5: =ЯНВАРЬ!AO5 -> 47515.951 | D5: =C5/C$100 -> 0.25322106 | E5: =E4+D5 -> 0.76227531 | F5: =IF(AND(E5<=0),"C",IF(E5<=0.8,"A",IF(E5<=0.95,"B","C"))) -> A | G5: =VLOOKUP(B$4:B$99,I$4:M$99,5,0) -> A | I5: QS синие PZ | J5: =ЯНВАРЬ!U5 -> 201 | K5: =J5/J$100 -> 0.087050671 | L5: =L4+K5 -> 0.3477696 | M5: =_xlfn.IFS(L5<80%,"A",L5<=95%,"B",L5>95%,"C") -> A | P5: B | Q5: 0.15
B6: QS коричневые PZ | C6: =ЯНВАРЬ!AO7 -> 29383.213 | D6: =C6/C$100 -> 0.15658843 | E6: =E5+D6 -> 0.91886374 | F6: =IF(AND(E6<=0),"C",IF(E6<=0.8,"A",IF(E6<=0.95,"B","C"))) -> B | G6: =VLOOKUP(B$4:B$99,I$4:M$99,5,0) -> A | I6: QS желтые PZ | J6: =ЯНВАРЬ!U6 -> 177 | K6: =J6/J$100 -> 0.076656561 | L6: =L5+K6 -> 0.42442616 | M6: =_xlfn.IFS(L6<80%,"A",L6<=95%,"B",L6>95%,"C") -> A | P6: C | Q6: 0.05
B7: QS желтые PZ | C7: =ЯНВАРЬ!AO6 -> 29252.999 | D7: =C7/C$100 -> 0.1558945 | E7: =E6+D7 -> 1.0747582 | F7: =IF(AND(E7<=0),"C",IF(E7<=0.8,"A",IF(E7<=0.95,"B","C"))) -> C | G7: =VLOOKUP(B$4:B$99,I$4:M$99,5,0) -> A | I7: QS коричневые PZ | J7: =ЯНВАРЬ!U7 -> 159 | K7: =J7/J$100 -> 0.068860979 | L7: =L6+K7 -> 0.49328714 | M7: =_xlfn.IFS(L7<80%,"A",L7<=95%,"B",L7>95%,"C") -> A
B8: черные с железкой классика | C8: =ЯНВАРЬ!AO3 -> 22546.743 | D8: =C8/C$100 -> 0.12015565 | E8: =E7+D8 -> 1.1949139 | F8: =IF(AND(E8<=0),"C",IF(E8<=0.8,"A",IF(E8<=0.95,"B","C"))) -> C | G8: =VLOOKUP(B$4:B$99,I$4:M$99,5,0) -> A | I8: черные с железкой классика | J8: =ЯНВАРЬ!U3 -> 158 | K8: =J8/J$100 -> 0.068427891 | L8: =L7+K8 -> 0.56171503 | M8: =_xlfn.IFS(L8<80%,"A",L8<=95%,"B",L8>95%,"C") -> A
B9: th желт | C9: =ЯНВАРЬ!AO11 -> 15165.975 | D9: =C9/C$100 -> 0.080822214 | E9: =E8+D9 -> 1.2757361 | F9: =IF(AND(E9<=0),"C",IF(E9<=0.8,"A",IF(E9<=0.95,"B","C"))) -> C | G9: =VLOOKUP(B$4:B$99,I$4:M$99,5,0) -> A | I9: th черн | J9: =ЯНВАРЬ!U9 -> 122 | K9: =J9/J$100 -> 0.052836726 | L9: =L8+K9 -> 0.61455175 | M9: =_xlfn.IFS(L9<80%,"A",L9<=95%,"B",L9>95%,"C") -> A
B10: wwl8032 хром металл | C10: =ЯНВАРЬ!AO18 -> 6208.6752 | D10: =C10/C$100 -> 0.033087148 | E10: =E9+D10 -> 1.3088233 | F10: =IF(AND(E10<=0),"C",IF(E10<=0.8,"A",IF(E10<=0.95,"B","C"))) -> C | G10: =VLOOKUP(B$4:B$99,I$4:M$99,5,0) -> B | I10: MR8854 C2 Жен | J10: =ЯНВАРЬ!U8 -> 119 | K10: =J10/J$100 -> 0.051537462 | L10: =L9+K10 -> 0.66608922 | M10: =_xlfn.IFS(L10<80%,"A",L10<=95%,"B",L10>95%,"C") -> A
B11: flip черные | C11: =ЯНВАРЬ!AO13 -> 5861.1284 | D11: =C11/C$100 -> 0.031235009 | E11: =E10+D11 -> 1.3400583 | F11: =IF(AND(E11<=0),"C",IF(E11<=0.8,"A",IF(E11<=0.95,"B","C"))) -> C | G11: =VLOOKUP(B$4:B$99,I$4:M$99,5,0) -> A | I11: th син | J11: =ЯНВАРЬ!U10 -> 88 | K11: =J11/J$100 -> 0.038111737 | L11: =L10+K11 -> 0.70420095 | M11: =_xlfn.IFS(L11<80%,"A",L11<=95%,"B",L11>95%,"C") -> A
B12: th черн | C12: =ЯНВАРЬ!AO9 -> 5654.8891 | D12: =C12/C$100 -> 0.030135922 | E12: =E11+D12 -> 1.3701942 | F12: =IF(AND(E12<=0),"C",IF(E12<=0.8,"A",IF(E12<=0.95,"B","C"))) -> C | G12: =VLOOKUP(B$4:B$99,I$4:M$99,5,0) -> A | I12: th желт | J12: =ЯНВАРЬ!U11 -> 80 | K12: =J12/J$100 -> 0.034647033 | L12: =L11+K12 -> 0.73884799 | M12: =_xlfn.IFS(L12<80%,"A",L12<=95%,"B",L12>95%,"C") -> A
B13: ww 1022 черные | C13: =ЯНВАРЬ!AO45 -> 3561.3363 | D13: =C13/C$100 -> 0.018979002 | E13: =E12+D13 -> 1.3891732 | F13: =IF(AND(E13<=0),"C",IF(E13<=0.8,"A",IF(E13<=0.95,"B","C"))) -> C | G13: =VLOOKUP(B$4:B$99,I$4:M$99,5,0) -> C | I13: flip черные | J13: =ЯНВАРЬ!U13 -> 71 | K13: =J13/J$100 -> 0.030749242 | L13: =L12+K13 -> 0.76959723 | M13: =_xlfn.IFS(L13<80%,"A",L13<=95%,"B",L13>95%,"C") -> A
B14: sportlife красные | C14: =ЯНВАРЬ!AO25 -> 1753.7595 | D14: =C14/C$100 -> 0.0093461001 | E14: =E13+D14 -> 1.3985193 | F14: =IF(AND(E14<=0),"C",IF(E14<=0.8,"A",IF(E14<=0.95,"B","C"))) -> C | G14: =VLOOKUP(B$4:B$99,I$4:M$99,5,0) -> C | I14: sh3 | J14: =ЯНВАРЬ!U28 -> 62 | K14: =J14/J$100 -> 0.026851451 | L14: =L13+K14 -> 0.79644868 | M14: =_xlfn.IFS(L14<80%,"A",L14<=95%,"B",L14>95%,"C") -> A
B15: MANNA2121 | C15: =ЯНВАРЬ!AO74 -> 1363.8837 | D15: =C15/C$100 -> 0.0072683817 | E15: =E14+D15 -> 1.4057877 | F15: =IF(AND(E15<=0),"C",IF(E15<=0.8,"A",IF(E15<=0.95,"B","C"))) -> C | G15: =VLOOKUP(B$4:B$99,I$4:M$99,5,0) -> C | I15: flip коричневые | J15: =ЯНВАРЬ!U16 -> 58 | K15: =J15/J$100 -> 0.025119099 | L15: =L14+K15 -> 0.82156778 | M15: =_xlfn.IFS(L15<80%,"A",L15<=95%,"B",L15>95%,"C") -> B
B16: sportlife синие | C16: =ЯНВАРЬ!AO24 -> 1344.7674 | D16: =C16/C$100 -> 0.0071665076 | E16: =E15+D16 -> 1.4129542 | F16: =IF(AND(E16<=0),"C",IF(E16<=0.8,"A",IF(E16<=0.95,"B","C"))) -> C | G16: =VLOOKUP(B$4:B$99,I$4:M$99,5,0) -> C | I16: th коричн | J16: =ЯНВАРЬ!U12 -> 47 | K16: =J16/J$100 -> 0.020355132 | L16: =L15+K16 -> 0.84192291 | M16: =_xlfn.IFS(L16<80%,"A",L16<=95%,"B",L16>95%,"C") -> B
B17: ww 1022 желтые | C17: =ЯНВАРЬ!AO47 -> 1290.9451 | D17: =C17/C$100 -> 0.0068796789 | E17: =E16+D17 -> 1.4198339 | F17: =IF(AND(E17<=0),"C",IF(E17<=0.8,"A",IF(E17<=0.95,"B","C"))) -> C | G17: =VLOOKUP(B$4:B$99,I$4:M$99,5,0) -> C | I17: wwl8032 хром металл | J17: =ЯНВАРЬ!U18 -> 32 | K17: =J17/J$100 -> 0.013858813 | L17: =L16+K17 -> 0.85578172 | M17: =_xlfn.IFS(L17<80%,"A",L17<=95%,"B",L17>95%,"C") -> B
B18: flip коричневые | C18: =ЯНВАРЬ!AO16 -> 1251.1714 | D18: =C18/C$100 -> 0.0066677174 | E18: =E17+D18 -> 1.4265016 | F18: =IF(AND(E18<=0),"C",IF(E18<=0.8,"A",IF(E18<=0.95,"B","C"))) -> C | G18: =VLOOKUP(B$4:B$99,I$4:M$99,5,0) -> B | I18: ww 2018 черные | J18: =ЯНВАРЬ!U49 -> 32 | K18: =J18/J$100 -> 0.013858813 | L18: =L17+K18 -> 0.86964054 | M18: =_xlfn.IFS(L18<80%,"A",L18<=95%,"B",L18>95%,"C") -> B
B19: Linhai Baiyi коричневая линза | C19: =ЯНВАРЬ!AO86 -> 1123.957 | D19: =C19/C$100 -> 0.0059897692 | E19: =E18+D19 -> 1.4324913 | F19: =IF(AND(E19<=0),"C",IF(E19<=0.8,"A",IF(E19<=0.95,"B","C"))) -> C | G19: =VLOOKUP(B$4:B$99,I$4:M$99,5,0) -> C | I19: flip желтые | J19: =ЯНВАРЬ!U15 -> 29 | K19: =J19/J$100 -> 0.01255955 | L19: =L18+K19 -> 0.88220009 | M19: =_xlfn.IFS(L19<80%,"A",L19<=95%,"B",L19>95%,"C") -> B
B20: MANNA2122 | C20: =ЯНВАРЬ!AO75 -> 1087.5869 | D20: =C20/C$100 -> 0.0057959464 | E20: =E19+D20 -> 1.4382873 | F20: =IF(AND(E20<=0),"C",IF(E20<=0.8,"A",IF(E20<=0.95,"B","C"))) -> C | G20: =VLOOKUP(B$4:B$99,I$4:M$99,5,0) -> B | I20: wwl8032 коричневые золото | J20: =ЯНВАРЬ!U17 -> 29 | K20: =J20/J$100 -> 0.01255955 | L20: =L19+K20 -> 0.89475964 | M20: =_xlfn.IFS(L20<80%,"A",L20<=95%,"B",L20>95%,"C") -> B
B21: Linhai Baiyi серая линза | C21: =ЯНВАРЬ!AO87 -> 994.37752 | D21: =C21/C$100 -> 0.0052992168 | E21: =E20+D21 -> 1.4435865 | F21: =IF(AND(E21<=0),"C",IF(E21<=0.8,"A",IF(E21<=0.95,"B","C"))) -> C | G21: =VLOOKUP(B$4:B$99,I$4:M$99,5,0) -> C | I21: ww 2018 желтые | J21: =ЯНВАРЬ!U50 -> 26 | K21: =J21/J$100 -> 0.011260286 | L21: =L20+K21 -> 0.90601992 | M21: =_xlfn.IFS(L21<80%,"A",L21<=95%,"B",L21>95%,"C") -> B
B22: MANNA2114 | C22: =ЯНВАРЬ!AO67 -> 915.87686 | D22: =C22/C$100 -> 0.0048808727 | E22: =E21+D22 -> 1.4484674 | F22: =IF(AND(E22<=0),"C",IF(E22<=0.8,"A",IF(E22<=0.95,"B","C"))) -> C | G22: =VLOOKUP(B$4:B$99,I$4:M$99,5,0) -> C | I22: flip синие | J22: =ЯНВАРЬ!U14 -> 25 | K22: =J22/J$100 -> 0.010827198 | L22: =L21+K22 -> 0.91684712 | M22: =_xlfn.IFS(L22<80%,"A",L22<=95%,"B",L22>95%,"C") -> B
B23: MANNA2117 | C23: =ЯНВАРЬ!AO70 -> 904.89566 | D23: =C23/C$100 -> 0.0048223519 | E23: =E22+D23 -> 1.4532897 | F23: =IF(AND(E23<=0),"C",IF(E23<=0.8,"A",IF(E23<=0.95,"B","C"))) -> C | G23: =VLOOKUP(B$4:B$99,I$4:M$99,5,0) -> C | I23: MANNA2122 | J23: =ЯНВАРЬ!U75 -> 23 | K23: =J23/J$100 -> 0.0099610221 | L23: =L22+K23 -> 0.92680814 | M23: =_xlfn.IFS(L23<80%,"A",L23<=95%,"B",L23>95%,"C") -> B
B24: sh17 | C24: =ЯНВАРЬ!AO41 -> 765.23691 | D24: =C24/C$100 -> 0.0040780853 | E24: =E23+D24 -> 1.4573678 | F24: =IF(AND(E24<=0),"C",IF(E24<=0.8,"A",IF(E24<=0.95,"B","C"))) -> C | G24: =VLOOKUP(B$4:B$99,I$4:M$99,5,0) -> C | I24: sh1 | J24: =ЯНВАРЬ!U26 -> 22 | K24: =J24/J$100 -> 0.0095279342 | L24: =L23+K24 -> 0.93633608 | M24: =_xlfn.IFS(L24<80%,"A",L24<=95%,"B",L24>95%,"C") -> B
B25: ww 1022 коричневые | C25: =ЯНВАРЬ!AO48 -> 639.44127 | D25: =C25/C$100 -> 0.0034076977 | E25: =E24+D25 -> 1.4607755 | F25: =IF(AND(E25<=0),"C",IF(E25<=0.8,"A",IF(E25<=0.95,"B","C"))) -> C | G25: =VLOOKUP(B$4:B$99,I$4:M$99,5,0) -> C | I25: sh06 | J25: =ЯНВАРЬ!U30 -> 17 | K25: =J25/J$100 -> 0.0073624946 | L25: =L24+K25 -> 0.94369857 | M25: =_xlfn.IFS(L25<80%,"A",L25<=95%,"B",L25>95%,"C") -> B
B26: Chenlong белые | C26: =ЯНВАРЬ!AO78 -> 302.23318 | D26: =C26/C$100 -> 0.001610655 | E26: =E25+D26 -> 1.4623862 | F26: =IF(AND(E26<=0),"C",IF(E26<=0.8,"A",IF(E26<=0.95,"B","C"))) -> C | G26: =VLOOKUP(B$4:B$99,I$4:M$99,5,0) -> C | I26: sh07 | J26: =ЯНВАРЬ!U31 -> 17 | K26: =J26/J$100 -> 0.0073624946 | L26: =L25+K26 -> 0.95106107 | M26: =_xlfn.IFS(L26<80%,"A",L26<=95%,"B",L26>95%,"C") -> C
B27: MANNA2105 | C27: =ЯНВАРЬ!AO58 -> 252.9664 | D27: =C27/C$100 -> 0.0013481035 | E27: =E26+D27 -> 1.4637343 | F27: =IF(AND(E27<=0),"C",IF(E27<=0.8,"A",IF(E27<=0.95,"B","C"))) -> C | G27: =VLOOKUP(B$4:B$99,I$4:M$99,5,0) -> C | I27: Linhai Baiyi розовая линза | J27: =ЯНВАРЬ!U88 -> 17 | K27: =J27/J$100 -> 0.0073624946 | L27: =L26+K27 -> 0.95842356 | M27: =_xlfn.IFS(L27<80%,"A",L27<=95%,"B",L27>95%,"C") -> C
B28: sh13 | C28: =ЯНВАРЬ!AO37 -> 215.41374 | D28: =C28/C$100 -> 0.0011479786 | E28: =E27+D28 -> 1.4648822 | F28: =IF(AND(E28<=0),"C",IF(E28<=0.8,"A",IF(E28<=0.95,"B","C"))) -> C | G28: =VLOOKUP(B$4:B$99,I$4:M$99,5,0) -> C | I28: ww 1022 коричневые | J28: =ЯНВАРЬ!U48 -> 13 | K28: =J28/J$100 -> 0.0056301429 | L28: =L27+K28 -> 0.9640537 | M28: =_xlfn.IFS(L28<80%,"A",L28<=95%,"B",L28>95%,"C") -> C
B29: sh08 | C29: =ЯНВАРЬ!AO32 -> 156.7243 | D29: =C29/C$100 -> 0.00083521203 | E29: =E28+D29 -> 1.4657175 | F29: =IF(AND(E29<=0),"C",IF(E29<=0.8,"A",IF(E29<=0.95,"B","C"))) -> C | G29: =VLOOKUP(B$4:B$99,I$4:M$99,5,0) -> C | I29: ww 1022 черные | J29: =ЯНВАРЬ!U45 -> 12 | K29: =J29/J$100 -> 0.005197055 | L29: =L28+K29 -> 0.96925076 | M29: =_xlfn.IFS(L29<80%,"A",L29<=95%,"B",L29>95%,"C") -> C
B30: wwl8032 коричневые золото | C30: =ЯНВАРЬ!AO17 -> 147.05787 | D30: =C30/C$100 -> 0.00078369786 | E30: =E29+D30 -> 1.4665012 | F30: =IF(AND(E30<=0),"C",IF(E30<=0.8,"A",IF(E30<=0.95,"B","C"))) -> C | G30: =VLOOKUP(B$4:B$99,I$4:M$99,5,0) -> B | I30: ww 8010 черные | J30: =ЯНВАРЬ!U51 -> 12 | K30: =J30/J$100 -> 0.005197055 | L30: =L29+K30 -> 0.97444781 | M30: =_xlfn.IFS(L30<80%,"A",L30<=95%,"B",L30>95%,"C") -> C
B31: MANNA2120 | C31: =ЯНВАРЬ!AO73 -> 141.36734 | D31: =C31/C$100 -> 0.00075337199 | E31: =E30+D31 -> 1.4672545 | F31: =IF(AND(E31<=0),"C",IF(E31<=0.8,"A",IF(E31<=0.95,"B","C"))) -> C | G31: =VLOOKUP(B$4:B$99,I$4:M$99,5,0) -> C | I31: ww 1022 желтые | J31: =ЯНВАРЬ!U47 -> 6 | K31: =J31/J$100 -> 0.0025985275 | L31: =L30+K31 -> 0.97704634 | M31: =_xlfn.IFS(L31<80%,"A",L31<=95%,"B",L31>95%,"C") -> C
B32: sh16 | C32: =ЯНВАРЬ!AO40 -> 121.42311 | D32: =C32/C$100 -> 0.00064708563 | E32: =E31+D32 -> 1.4679016 | F32: =IF(AND(E32<=0),"C",IF(E32<=0.8,"A",IF(E32<=0.95,"B","C"))) -> C | G32: =VLOOKUP(B$4:B$99,I$4:M$99,5,0) -> C | I32: MANNA2121 | J32: =ЯНВАРЬ!U74 -> 6 | K32: =J32/J$100 -> 0.0025985275 | L32: =L31+K32 -> 0.97964487 | M32: =_xlfn.IFS(L32<80%,"A",L32<=95%,"B",L32>95%,"C") -> C
B33: MARSTON 7171 C1 | C33: =ЯНВАРЬ!AO96 -> 113.1339 | D33: =C33/C$100 -> 0.0006029109 | E33: =E32+D33 -> 1.4685045 | F33: =IF(AND(E33<=0),"C",IF(E33<=0.8,"A",IF(E33<=0.95,"B","C"))) -> C | G33: =VLOOKUP(B$4:B$99,I$4:M$99,5,0) -> C | I33: Keming Aishi коричневые | J33: =ЯНВАРЬ!U85 -> 6 | K33: =J33/J$100 -> 0.0025985275 | L33: =L32+K33 -> 0.9822434 | M33: =_xlfn.IFS(L33<80%,"A",L33<=95%,"B",L33>95%,"C") -> C
B34: MANNA2101 | C34: =ЯНВАРЬ!AO54 -> 104.92238 | D34: =C34/C$100 -> 0.00055915026 | E34: =E33+D34 -> 1.4690637 | F34: =IF(AND(E34<=0),"C",IF(E34<=0.8,"A",IF(E34<=0.95,"B","C"))) -> C | G34: =VLOOKUP(B$4:B$99,I$4:M$99,5,0) -> C | I34: sportlife красные | J34: =ЯНВАРЬ!U25 -> 5 | K34: =J34/J$100 -> 0.0021654396 | L34: =L33+K34 -> 0.98440883 | M34: =_xlfn.IFS(L34<80%,"A",L34<=95%,"B",L34>95%,"C") -> C
B35: MANNA2119 | C35: =ЯНВАРЬ!AO72 -> 103.18015 | D35: =C35/C$100 -> 0.00054986559 | E35: =E34+D35 -> 1.4696135 | F35: =IF(AND(E35<=0),"C",IF(E35<=0.8,"A",IF(E35<=0.95,"B","C"))) -> C | G35: =VLOOKUP(B$4:B$99,I$4:M$99,5,0) -> C | I35: sportlife синие | J35: =ЯНВАРЬ!U24 -> 4 | K35: =J35/J$100 -> 0.0017323517 | L35: =L34+K35 -> 0.98614119 | M35: =_xlfn.IFS(L35<80%,"A",L35<=95%,"B",L35>95%,"C") -> C
B36: WW 3055 коричневый | C36: =ЯНВАРЬ!AO53 -> 71.165605 | D36: =C36/C$100 -> 0.00037925432 | E36: =E35+D36 -> 1.4699928 | F36: =IF(AND(E36<=0),"C",IF(E36<=0.8,"A",IF(E36<=0.95,"B","C"))) -> C | G36: =VLOOKUP(B$4:B$99,I$4:M$99,5,0) -> C | I36: sh08 | J36: =ЯНВАРЬ!U32 -> 4 | K36: =J36/J$100 -> 0.0017323517 | L36: =L35+K36 -> 0.98787354 | M36: =_xlfn.IFS(L36<80%,"A",L36<=95%,"B",L36>95%,"C") -> C
B37: wwl8032 черные серебро | C37: =ЯНВАРЬ!AO19 -> 0 | D37: =C37/C$100 -> 0 | E37: =E36+D37 -> 1.4699928 | F37: =IF(AND(E37<=0),"C",IF(E37<=0.8,"A",IF(E37<=0.95,"B","C"))) -> C | G37: =VLOOKUP(B$4:B$99,I$4:M$99,5,0) -> C | I37: MANNA2114 | J37: =ЯНВАРЬ!U67 -> 3 | K37: =J37/J$100 -> 0.0012992638 | L37: =L36+K37 -> 0.9891728 | M37: =_xlfn.IFS(L37<80%,"A",L37<=95%,"B",L37>95%,"C") -> C
B38: sports синие | C38: =ЯНВАРЬ!AO20 -> 0 | D38: =C38/C$100 -> 0 | E38: =E37+D38 -> 1.4699928 | F38: =IF(AND(E38<=0),"C",IF(E38<=0.8,"A",IF(E38<=0.95,"B","C"))) -> C | G38: =VLOOKUP(B$4:B$99,I$4:M$99,5,0) -> C | I38: sh09 | J38: =ЯНВАРЬ!U33 -> 2 | K38: =J38/J$100 -> 0.00086617583 | L38: =L37+K38 -> 0.99003898 | M38: =_xlfn.IFS(L38<80%,"A",L38<=95%,"B",L38>95%,"C") -> C
B39: sportlife черные | C39: =ЯНВАРЬ!AO23 -> 0 | D39: =C39/C$100 -> 0 | E39: =E35+D39 -> 1.4696135 | F39: =IF(AND(E39<=0),"C",IF(E39<=0.8,"A",IF(E39<=0.95,"B","C"))) -> C | G39: =VLOOKUP(B$4:B$99,I$4:M$99,5,0) -> C | I39: sh17 | J39: =ЯНВАРЬ!U41 -> 2 | K39: =J39/J$100 -> 0.00086617583 | L39: =L35+K39 -> 0.98700736 | M39: =_xlfn.IFS(L39<80%,"A",L39<=95%,"B",L39>95%,"C") -> C
B40: sh11 | C40: =ЯНВАРЬ!AO35 -> 0 | D40: =C40/C$100 -> 0 | E40: =E39+D40 -> 1.4696135 | F40: =IF(AND(E40<=0),"C",IF(E40<=0.8,"A",IF(E40<=0.95,"B","C"))) -> C | G40: =VLOOKUP(B$4:B$99,I$4:M$99,5,0) -> C | I40: MANNA2117 | J40: =ЯНВАРЬ!U70 -> 2 | K40: =J40/J$100 -> 0.00086617583 | L40: =L39+K40 -> 0.98787354 | M40: =_xlfn.IFS(L40<80%,"A",L40<=95%,"B",L40>95%,"C") -> C
B41: sh12 | C41: =ЯНВАРЬ!AO36 -> 0 | D41: =C41/C$100 -> 0 | E41: =E40+D41 -> 1.4696135 | F41: =IF(AND(E41<=0),"C",IF(E41<=0.8,"A",IF(E41<=0.95,"B","C"))) -> C | G41: =VLOOKUP(B$4:B$99,I$4:M$99,5,0) -> C | I41: MANNA2119 | J41: =ЯНВАРЬ!U72 -> 2 | K41: =J41/J$100 -> 0.00086617583 | L41: =L40+K41 -> 0.98873971 | M41: =_xlfn.IFS(L41<80%,"A",L41<=95%,"B",L41>95%,"C") -> C
B42: ww 1022 черн-серебро | C42: =ЯНВАРЬ!AO46 -> 0 | D42: =C42/C$100 -> 0 | E42: =E41+D42 -> 1.4696135 | F42: =IF(AND(E42<=0),"C",IF(E42<=0.8,"A",IF(E42<=0.95,"B","C"))) -> C | G42: =VLOOKUP(B$4:B$99,I$4:M$99,5,0) -> C | I42: Linhai Baiyi коричневая линза | J42: =ЯНВАРЬ!U86 -> 2 | K42: =J42/J$100 -> 0.00086617583 | L42: =L41+K42 -> 0.98960589 | M42: =_xlfn.IFS(L42<80%,"A",L42<=95%,"B",L42>95%,"C") -> C
B43: MANNA2104 | C43: =ЯНВАРЬ!AO57 -> 0 | D43: =C43/C$100 -> 0 | E43: =E42+D43 -> 1.4696135 | F43: =IF(AND(E43<=0),"C",IF(E43<=0.8,"A",IF(E43<=0.95,"B","C"))) -> C | G43: =VLOOKUP(B$4:B$99,I$4:M$99,5,0) -> C | I43: Linhai Baiyi серая линза | J43: =ЯНВАРЬ!U87 -> 2 | K43: =J43/J$100 -> 0.00086617583 | L43: =L42+K43 -> 0.99047207 | M43: =_xlfn.IFS(L43<80%,"A",L43<=95%,"B",L43>95%,"C") -> C
B44: MANNA2106 | C44: =ЯНВАРЬ!AO59 -> 0 | D44: =C44/C$100 -> 0 | E44: =E43+D44 -> 1.4696135 | F44: =IF(AND(E44<=0),"C",IF(E44<=0.8,"A",IF(E44<=0.95,"B","C"))) -> C | G44: =VLOOKUP(B$4:B$99,I$4:M$99,5,0) -> C | I44: sh2 | J44: =ЯНВАРЬ!U27 -> 1 | K44: =J44/J$100 -> 0.00043308792 | L44: =L43+K44 -> 0.99090515 | M44: =_xlfn.IFS(L44<80%,"A",L44<=95%,"B",L44>95%,"C") -> C
B45: MANNA2109 | C45: =ЯНВАРЬ!AO62 -> 0 | D45: =C45/C$100 -> 0 | E45: =E44+D45 -> 1.4696135 | F45: =IF(AND(E45<=0),"C",IF(E45<=0.8,"A",IF(E45<=0.95,"B","C"))) -> C | G45: =VLOOKUP(B$4:B$99,I$4:M$99,5,0) -> C | I45: sh4 | J45: =ЯНВАРЬ!U29 -> 1 | K45: =J45/J$100 -> 0.00043308792 | L45: =L44+K45 -> 0.99133824 | M45: =_xlfn.IFS(L45<80%,"A",L45<=95%,"B",L45>95%,"C") -> C
B46: MANNA2110 | C46: =ЯНВАРЬ!AO63 -> 0 | D46: =C46/C$100 -> 0 | E46: =E45+D46 -> 1.4696135 | F46: =IF(AND(E46<=0),"C",IF(E46<=0.8,"A",IF(E46<=0.95,"B","C"))) -> C | G46: =VLOOKUP(B$4:B$99,I$4:M$99,5,0) -> C | I46: sh10 | J46: =ЯНВАРЬ!U34 -> 1 | K46: =J46/J$100 -> 0.00043308792 | L46: =L45+K46 -> 0.99177133 | M46: =_xlfn.IFS(L46<80%,"A",L46<=95%,"B",L46>95%,"C") -> C
B47: MANNA2111 | C47: =ЯНВАРЬ!AO64 -> 0 | D47: =C47/C$100 -> 0 | E47: =E46+D47 -> 1.4696135 | F47: =IF(AND(E47<=0),"C",IF(E47<=0.8,"A",IF(E47<=0.95,"B","C"))) -> C | G47: =VLOOKUP(B$4:B$99,I$4:M$99,5,0) -> C | I47: sh13 | J47: =ЯНВАРЬ!U37 -> 1 | K47: =J47/J$100 -> 0.00043308792 | L47: =L46+K47 -> 0.99220442 | M47: =_xlfn.IFS(L47<80%,"A",L47<=95%,"B",L47>95%,"C") -> C
B48: MANNA2115 | C48: =ЯНВАРЬ!AO68 -> 0 | D48: =C48/C$100 -> 0 | E48: =E47+D48 -> 1.4696135 | F48: =IF(AND(E48<=0),"C",IF(E48<=0.8,"A",IF(E48<=0.95,"B","C"))) -> C | G48: =VLOOKUP(B$4:B$99,I$4:M$99,5,0) -> C | I48: sh16 | J48: =ЯНВАРЬ!U40 -> 1 | K48: =J48/J$100 -> 0.00043308792 | L48: =L47+K48 -> 0.99263751 | M48: =_xlfn.IFS(L48<80%,"A",L48<=95%,"B",L48>95%,"C") -> C
B49: sports зеленые | C49: =ЯНВАРЬ!AO21 -> -3.209704 | D49: =C49/C$100 -> -1.710509e-05 | E49: =E48+D49 -> 1.4695964 | F49: =IF(AND(E49<=0),"C",IF(E49<=0.8,"A",IF(E49<=0.95,"B","C"))) -> C | G49: =VLOOKUP(B$4:B$99,I$4:M$99,5,0) -> C | I49: ww 203 черные | J49: =ЯНВАРЬ!U44 -> 1 | K49: =J49/J$100 -> 0.00043308792 | L49: =L48+K49 -> 0.99307059 | M49: =_xlfn.IFS(L49<80%,"A",L49<=95%,"B",L49>95%,"C") -> C
B50: MAIERSHA 03914 C9-124 | C50: =ЯНВАРЬ!AO95 -> -3.209704 | D50: =C50/C$100 -> -1.710509e-05 | E50: =E49+D50 -> 1.4695793 | F50: =IF(AND(E50<=0),"C",IF(E50<=0.8,"A",IF(E50<=0.95,"B","C"))) -> C | G50: =VLOOKUP(B$4:B$99,I$4:M$99,5,0) -> C | I50: WW 3055 коричневый | J50: =ЯНВАРЬ!U53 -> 1 | K50: =J50/J$100 -> 0.00043308792 | L50: =L49+K50 -> 0.99350368 | M50: =_xlfn.IFS(L50<80%,"A",L50<=95%,"B",L50>95%,"C") -> C
B51: MAIERSHA 03898 C9-08 | C51: =ЯНВАРЬ!AO94 -> -6.419408 | D51: =C51/C$100 -> -3.4210181e-05 | E51: =E50+D51 -> 1.4695451 | F51: =IF(AND(E51<=0),"C",IF(E51<=0.8,"A",IF(E51<=0.95,"B","C"))) -> C | G51: =VLOOKUP(B$4:B$99,I$4:M$99,5,0) -> C | I51: MANNA2101 | J51: =ЯНВАРЬ!U54 -> 1 | K51: =J51/J$100 -> 0.00043308792 | L51: =L50+K51 -> 0.99393677 | M51: =_xlfn.IFS(L51<80%,"A",L51<=95%,"B",L51>95%,"C") -> C
B52: POMILED 08247 C4-08 | C52: =ЯНВАРЬ!AO97 -> -12.838816 | D52: =C52/C$100 -> -6.8420362e-05 | E52: =E51+D52 -> 1.4694767 | F52: =IF(AND(E52<=0),"C",IF(E52<=0.8,"A",IF(E52<=0.95,"B","C"))) -> C | G52: =VLOOKUP(B$4:B$99,I$4:M$99,5,0) -> C | I52: MANNA2105 | J52: =ЯНВАРЬ!U58 -> 1 | K52: =J52/J$100 -> 0.00043308792 | L52: =L51+K52 -> 0.99436986 | M52: =_xlfn.IFS(L52<80%,"A",L52<=95%,"B",L52>95%,"C") -> C
B53: MANNA2116 | C53: =ЯНВАРЬ!AO69 -> -38.516448 | D53: =C53/C$100 -> -0.00020526109 | E53: =E52+D53 -> 1.4692714 | F53: =IF(AND(E53<=0),"C",IF(E53<=0.8,"A",IF(E53<=0.95,"B","C"))) -> C | G53: =VLOOKUP(B$4:B$99,I$4:M$99,5,0) -> C | I53: MANNA2118 | J53: =ЯНВАРЬ!U71 -> 1 | K53: =J53/J$100 -> 0.00043308792 | L53: =L52+K53 -> 0.99480294 | M53: =_xlfn.IFS(L53<80%,"A",L53<=95%,"B",L53>95%,"C") -> C
B54: YIMEI 2391 C1 | C54: =ЯНВАРЬ!AO98 -> -51.355264 | D54: =C54/C$100 -> -0.00027368145 | E54: =E53+D54 -> 1.4689978 | F54: =IF(AND(E54<=0),"C",IF(E54<=0.8,"A",IF(E54<=0.95,"B","C"))) -> C | G54: =VLOOKUP(B$4:B$99,I$4:M$99,5,0) -> C | I54: MANNA2120 | J54: =ЯНВАРЬ!U73 -> 1 | K54: =J54/J$100 -> 0.00043308792 | L54: =L53+K54 -> 0.99523603 | M54: =_xlfn.IFS(L54<80%,"A",L54<=95%,"B",L54>95%,"C") -> C
B55: MANNA2112 | C55: =ЯНВАРЬ!AO65 -> -96.86 | D55: =C55/C$100 -> -0.00051618438 | E55: =E54+D55 -> 1.4684816 | F55: =IF(AND(E55<=0),"C",IF(E55<=0.8,"A",IF(E55<=0.95,"B","C"))) -> C | G55: =VLOOKUP(B$4:B$99,I$4:M$99,5,0) -> C | I55: Chenlong белые | J55: =ЯНВАРЬ!U78 -> 1 | K55: =J55/J$100 -> 0.00043308792 | L55: =L54+K55 -> 0.99566912 | M55: =_xlfn.IFS(L55<80%,"A",L55<=95%,"B",L55>95%,"C") -> C
B56: MANNA2102 | C56: =ЯНВАРЬ!AO55 -> -97.139704 | D56: =C56/C$100 -> -0.00051767497 | E56: =E55+D56 -> 1.4679639 | F56: =IF(AND(E56<=0),"C",IF(E56<=0.8,"A",IF(E56<=0.95,"B","C"))) -> C | G56: =VLOOKUP(B$4:B$99,I$4:M$99,5,0) -> C | I56: MARSTON 7171 C1 | J56: =ЯНВАРЬ!U96 -> 1 | K56: =J56/J$100 -> 0.00043308792 | L56: =L55+K56 -> 0.99610221 | M56: =_xlfn.IFS(L56<80%,"A",L56<=95%,"B",L56>95%,"C") -> C
B57: sports красные | C57: =ЯНВАРЬ!AO22 -> -106.02911 | D57: =C57/C$100 -> -0.00056504823 | E57: =E56+D57 -> 1.4673989 | F57: =IF(AND(E57<=0),"C",IF(E57<=0.8,"A",IF(E57<=0.95,"B","C"))) -> C | G57: =VLOOKUP(B$4:B$99,I$4:M$99,5,0) -> C | I57: wwl8032 черные серебро | J57: =ЯНВАРЬ!U19 -> 0 | K57: =J57/J$100 -> 0 | L57: =L56+K57 -> 0.99610221 | M57: =_xlfn.IFS(L57<80%,"A",L57<=95%,"B",L57>95%,"C") -> C
B58: Иу Диту серый | C58: =ЯНВАРЬ!AO91 -> -118.75905 | D58: =C58/C$100 -> -0.00063288835 | E58: =E57+D58 -> 1.466766 | F58: =IF(AND(E58<=0),"C",IF(E58<=0.8,"A",IF(E58<=0.95,"B","C"))) -> C | G58: =VLOOKUP(B$4:B$99,I$4:M$99,5,0) -> C | I58: sports синие | J58: =ЯНВАРЬ!U20 -> 0 | K58: =J58/J$100 -> 0 | L58: =L57+K58 -> 0.99610221 | M58: =_xlfn.IFS(L58<80%,"A",L58<=95%,"B",L58>95%,"C") -> C
B59: Chenlong коричневые | C59: =ЯНВАРЬ!AO77 -> -125.17846 | D59: =C59/C$100 -> -0.00066709853 | E59: =E58+D59 -> 1.4660989 | F59: =IF(AND(E59<=0),"C",IF(E59<=0.8,"A",IF(E59<=0.95,"B","C"))) -> C | G59: =VLOOKUP(B$4:B$99,I$4:M$99,5,0) -> C | I59: sports зеленые | J59: =ЯНВАРЬ!U21 -> 0 | K59: =J59/J$100 -> 0 | L59: =L58+K59 -> 0.99610221 | M59: =_xlfn.IFS(L59<80%,"A",L59<=95%,"B",L59>95%,"C") -> C
B60: sh14 | C60: =ЯНВАРЬ!AO38 -> -150.85609 | D60: =C60/C$100 -> -0.00080393925 | E60: =E59+D60 -> 1.4652949 | F60: =IF(AND(E60<=0),"C",IF(E60<=0.8,"A",IF(E60<=0.95,"B","C"))) -> C | G60: =VLOOKUP(B$4:B$99,I$4:M$99,5,0) -> C | I60: sports красные | J60: =ЯНВАРЬ!U22 -> 0 | K60: =J60/J$100 -> 0 | L60: =L59+K60 -> 0.99610221 | M60: =_xlfn.IFS(L60<80%,"A",L60<=95%,"B",L60>95%,"C") -> C
B61: sh15 | C61: =ЯНВАРЬ!AO39 -> -157.2755 | D61: =C61/C$100 -> -0.00083814943 | E61: =E60+D61 -> 1.4644568 | F61: =IF(AND(E61<=0),"C",IF(E61<=0.8,"A",IF(E61<=0.95,"B","C"))) -> C | G61: =VLOOKUP(B$4:B$99,I$4:M$99,5,0) -> C | I61: sportlife черные | J61: =ЯНВАРЬ!U23 -> 0 | K61: =J61/J$100 -> 0 | L61: =L60+K61 -> 0.99610221 | M61: =_xlfn.IFS(L61<80%,"A",L61<=95%,"B",L61>95%,"C") -> C
B62: Guangdu серебро серая линза | C62: =ЯНВАРЬ!AO80 -> -157.2755 | D62: =C62/C$100 -> -0.00083814943 | E62: =E61+D62 -> 1.4636186 | F62: =IF(AND(E62<=0),"C",IF(E62<=0.8,"A",IF(E62<=0.95,"B","C"))) -> C | G62: =VLOOKUP(B$4:B$99,I$4:M$99,5,0) -> C | I62: sh11 | J62: =ЯНВАРЬ!U35 -> 0 | K62: =J62/J$100 -> 0 | L62: =L61+K62 -> 0.99610221 | M62: =_xlfn.IFS(L62<80%,"A",L62<=95%,"B",L62>95%,"C") -> C
B63: Hengda Optical леопард | C63: =ЯНВАРЬ!AO82 -> -157.2755 | D63: =C63/C$100 -> -0.00083814943 | E63: =E62+D63 -> 1.4627805 | F63: =IF(AND(E63<=0),"C",IF(E63<=0.8,"A",IF(E63<=0.95,"B","C"))) -> C | G63: =VLOOKUP(B$4:B$99,I$4:M$99,5,0) -> C | I63: sh12 | J63: =ЯНВАРЬ!U36 -> 0 | K63: =J63/J$100 -> 0 | L63: =L62+K63 -> 0.99610221 | M63: =_xlfn.IFS(L63<80%,"A",L63<=95%,"B",L63>95%,"C") -> C
B64: Chenlong черные | C64: =ЯНВАРЬ!AO76 -> -160.4852 | D64: =C64/C$100 -> -0.00085525452 | E64: =E63+D64 -> 1.4619252 | F64: =IF(AND(E64<=0),"C",IF(E64<=0.8,"A",IF(E64<=0.95,"B","C"))) -> C | G64: =VLOOKUP(B$4:B$99,I$4:M$99,5,0) -> C | I64: sh14 | J64: =ЯНВАРЬ!U38 -> 0 | K64: =J64/J$100 -> 0 | L64: =L63+K64 -> 0.99610221 | M64: =_xlfn.IFS(L64<80%,"A",L64<=95%,"B",L64>95%,"C") -> C
B65: Taizhou Rayen sport розовый | C65: =ЯНВАРЬ!AO90 -> -160.4852 | D65: =C65/C$100 -> -0.00085525452 | E65: =E64+D65 -> 1.46107 | F65: =IF(AND(E65<=0),"C",IF(E65<=0.8,"A",IF(E65<=0.95,"B","C"))) -> C | G65: =VLOOKUP(B$4:B$99,I$4:M$99,5,0) -> C | I65: sh15 | J65: =ЯНВАРЬ!U39 -> 0 | K65: =J65/J$100 -> 0 | L65: =L64+K65 -> 0.99610221 | M65: =_xlfn.IFS(L65<80%,"A",L65<=95%,"B",L65>95%,"C") -> C
B66: sh10 | C66: =ЯНВАРЬ!AO34 -> -160.74999 | D66: =C66/C$100 -> -0.00085666565 | E66: =E65+D66 -> 1.4602133 | F66: =IF(AND(E66<=0),"C",IF(E66<=0.8,"A",IF(E66<=0.95,"B","C"))) -> C | G66: =VLOOKUP(B$4:B$99,I$4:M$99,5,0) -> C | I66: sh18 | J66: =ЯНВАРЬ!U42 -> 0 | K66: =J66/J$100 -> 0 | L66: =L65+K66 -> 0.99610221 | M66: =_xlfn.IFS(L66<80%,"A",L66<=95%,"B",L66>95%,"C") -> C
B67: sh4 | C67: =ЯНВАРЬ!AO29 -> -177.05621 | D67: =C67/C$100 -> -0.00094356441 | E67: =E66+D67 -> 1.4592697 | F67: =IF(AND(E67<=0),"C",IF(E67<=0.8,"A",IF(E67<=0.95,"B","C"))) -> C | G67: =VLOOKUP(B$4:B$99,I$4:M$99,5,0) -> C | I67: sh19 | J67: =ЯНВАРЬ!U43 -> 0 | K67: =J67/J$100 -> 0 | L67: =L66+K67 -> 0.99610221 | M67: =_xlfn.IFS(L67<80%,"A",L67<=95%,"B",L67>95%,"C") -> C
B68: MANNA2113 | C68: =ЯНВАРЬ!AO66 -> -202.16941 | D68: =C68/C$100 -> -0.0010773972 | E68: =E67+D68 -> 1.4581923 | F68: =IF(AND(E68<=0),"C",IF(E68<=0.8,"A",IF(E68<=0.95,"B","C"))) -> C | G68: =VLOOKUP(B$4:B$99,I$4:M$99,5,0) -> C | I68: ww 1022 черн-серебро | J68: =ЯНВАРЬ!U46 -> 0 | K68: =J68/J$100 -> 0 | L68: =L67+K68 -> 0.99610221 | M68: =_xlfn.IFS(L68<80%,"A",L68<=95%,"B",L68>95%,"C") -> C
B69: sh18 | C69: =ЯНВАРЬ!AO42 -> -238.86579 | D69: =C69/C$100 -> -0.0012729588 | E69: =E68+D69 -> 1.4569194 | F69: =IF(AND(E69<=0),"C",IF(E69<=0.8,"A",IF(E69<=0.95,"B","C"))) -> C | G69: =VLOOKUP(B$4:B$99,I$4:M$99,5,0) -> C | I69: WW 3055 черный | J69: =ЯНВАРЬ!U52 -> 0 | K69: =J69/J$100 -> 0 | L69: =L68+K69 -> 0.99610221 | M69: =_xlfn.IFS(L69<80%,"A",L69<=95%,"B",L69>95%,"C") -> C
B70: Qianai черные | C70: =ЯНВАРЬ!AO83 -> -239.20579 | D70: =C70/C$100 -> -0.0012747707 | E70: =E69+D70 -> 1.4556446 | F70: =IF(AND(E70<=0),"C",IF(E70<=0.8,"A",IF(E70<=0.95,"B","C"))) -> C | G70: =VLOOKUP(B$4:B$99,I$4:M$99,5,0) -> C | I70: MANNA2102 | J70: =ЯНВАРЬ!U55 -> 0 | K70: =J70/J$100 -> 0 | L70: =L69+K70 -> 0.99610221 | M70: =_xlfn.IFS(L70<80%,"A",L70<=95%,"B",L70>95%,"C") -> C
B71: Guangdu золото серая линза | C71: =ЯНВАРЬ!AO79 -> -242.4155 | D71: =C71/C$100 -> -0.0012918758 | E71: =E70+D71 -> 1.4543527 | F71: =IF(AND(E71<=0),"C",IF(E71<=0.8,"A",IF(E71<=0.95,"B","C"))) -> C | G71: =VLOOKUP(B$4:B$99,I$4:M$99,5,0) -> C | I71: MANNA2103 | J71: =ЯНВАРЬ!U56 -> 0 | K71: =J71/J$100 -> 0 | L71: =L70+K71 -> 0.99610221 | M71: =_xlfn.IFS(L71<80%,"A",L71<=95%,"B",L71>95%,"C") -> C
B72: MANNA2118 | C72: =ЯНВАРЬ!AO71 -> -246.19788 | D72: =C72/C$100 -> -0.0013120328 | E72: =E71+D72 -> 1.4530407 | F72: =IF(AND(E72<=0),"C",IF(E72<=0.8,"A",IF(E72<=0.95,"B","C"))) -> C | G72: =VLOOKUP(B$4:B$99,I$4:M$99,5,0) -> C | I72: MANNA2104 | J72: =ЯНВАРЬ!U57 -> 0 | K72: =J72/J$100 -> 0 | L72: =L71+K72 -> 0.99610221 | M72: =_xlfn.IFS(L72<80%,"A",L72<=95%,"B",L72>95%,"C") -> C
B73: Ли Сян ретро золото | C73: =ЯНВАРЬ!AO92 -> -253.6755 | D73: =C73/C$100 -> -0.0013518824 | E73: =E72+D73 -> 1.4516888 | F73: =IF(AND(E73<=0),"C",IF(E73<=0.8,"A",IF(E73<=0.95,"B","C"))) -> C | G73: =VLOOKUP(B$4:B$99,I$4:M$99,5,0) -> C | I73: MANNA2106 | J73: =ЯНВАРЬ!U59 -> 0 | K73: =J73/J$100 -> 0 | L73: =L72+K73 -> 0.99610221 | M73: =_xlfn.IFS(L73<80%,"A",L73<=95%,"B",L73>95%,"C") -> C
B74: MR Р1894 черные | C74: =ЯНВАРЬ!AO89 -> -255.64638 | D74: =C74/C$100 -> -0.0013623856 | E74: =E73+D74 -> 1.4503264 | F74: =IF(AND(E74<=0),"C",IF(E74<=0.8,"A",IF(E74<=0.95,"B","C"))) -> C | G74: =VLOOKUP(B$4:B$99,I$4:M$99,5,0) -> C | I74: MANNA2107 | J74: =ЯНВАРЬ!U60 -> 0 | K74: =J74/J$100 -> 0 | L74: =L73+K74 -> 0.99610221 | M74: =_xlfn.IFS(L74<80%,"A",L74<=95%,"B",L74>95%,"C") -> C
B75: Ли Сян ретро серебро | C75: =ЯНВАРЬ!AO93 -> -257.96609 | D75: =C75/C$100 -> -0.0013747477 | E75: =E74+D75 -> 1.4489517 | F75: =IF(AND(E75<=0),"C",IF(E75<=0.8,"A",IF(E75<=0.95,"B","C"))) -> C | G75: =VLOOKUP(B$4:B$99,I$4:M$99,5,0) -> C | I75: MANNA2108 | J75: =ЯНВАРЬ!U61 -> 0 | K75: =J75/J$100 -> 0 | L75: =L74+K75 -> 0.99610221 | M75: =_xlfn.IFS(L75<80%,"A",L75<=95%,"B",L75>95%,"C") -> C
B76: sh19 | C76: =ЯНВАРЬ!AO43 -> -261.17579 | D76: =C76/C$100 -> -0.0013918528 | E76: =E49+D76 -> 1.4682046 | F76: =IF(AND(E76<=0),"C",IF(E76<=0.8,"A",IF(E76<=0.95,"B","C"))) -> C | G76: =VLOOKUP(B$4:B$99,I$4:M$99,5,0) -> C | I76: MANNA2109 | J76: =ЯНВАРЬ!U62 -> 0 | K76: =J76/J$100 -> 0 | L76: =L49+K76 -> 0.99307059 | M76: =_xlfn.IFS(L76<80%,"A",L76<=95%,"B",L76>95%,"C") -> C
B77: Hengda Optical черные | C77: =ЯНВАРЬ!AO81 -> -265.2755 | D77: =C77/C$100 -> -0.0014137009 | E77: =E76+D77 -> 1.4667909 | F77: =IF(AND(E77<=0),"C",IF(E77<=0.8,"A",IF(E77<=0.95,"B","C"))) -> C | G77: =VLOOKUP(B$4:B$99,I$4:M$99,5,0) -> C | I77: MANNA2110 | J77: =ЯНВАРЬ!U63 -> 0 | K77: =J77/J$100 -> 0 | L77: =L76+K77 -> 0.99307059 | M77: =_xlfn.IFS(L77<80%,"A",L77<=95%,"B",L77>95%,"C") -> C
B78: WW 3055 черный | C78: =ЯНВАРЬ!AO52 -> -265.8555 | D78: =C78/C$100 -> -0.0014167918 | E78: =E77+D78 -> 1.4653741 | F78: =IF(AND(E78<=0),"C",IF(E78<=0.8,"A",IF(E78<=0.95,"B","C"))) -> C | G78: =VLOOKUP(B$4:B$99,I$4:M$99,5,0) -> C | I78: MANNA2111 | J78: =ЯНВАРЬ!U64 -> 0 | K78: =J78/J$100 -> 0 | L78: =L77+K78 -> 0.99307059 | M78: =_xlfn.IFS(L78<80%,"A",L78<=95%,"B",L78>95%,"C") -> C
B79: MANNA2107 | C79: =ЯНВАРЬ!AO60 -> -277.27171 | D79: =C79/C$100 -> -0.0014776309 | E79: =E78+D79 -> 1.4638965 | F79: =IF(AND(E79<=0),"C",IF(E79<=0.8,"A",IF(E79<=0.95,"B","C"))) -> C | G79: =VLOOKUP(B$4:B$99,I$4:M$99,5,0) -> C | I79: MANNA2112 | J79: =ЯНВАРЬ!U65 -> 0 | K79: =J79/J$100 -> 0 | L79: =L78+K79 -> 0.99307059 | M79: =_xlfn.IFS(L79<80%,"A",L79<=95%,"B",L79>95%,"C") -> C
B80: MANNA2103 | C80: =ЯНВАРЬ!AO56 -> -408.85941 | D80: =C80/C$100 -> -0.0021788854 | E80: =E79+D80 -> 1.4617176 | F80: =IF(AND(E80<=0),"C",IF(E80<=0.8,"A",IF(E80<=0.95,"B","C"))) -> C | G80: =VLOOKUP(B$4:B$99,I$4:M$99,5,0) -> C | I80: MANNA2113 | J80: =ЯНВАРЬ!U66 -> 0 | K80: =J80/J$100 -> 0 | L80: =L79+K80 -> 0.99307059 | M80: =_xlfn.IFS(L80<80%,"A",L80<=95%,"B",L80>95%,"C") -> C
B81: Qianai коричневые | C81: =ЯНВАРЬ!AO84 -> -458.30638 | D81: =C81/C$100 -> -0.0024423972 | E81: =E80+D81 -> 1.4592752 | F81: =IF(AND(E81<=0),"C",IF(E81<=0.8,"A",IF(E81<=0.95,"B","C"))) -> C | G81: =VLOOKUP(B$4:B$99,I$4:M$99,5,0) -> C | I81: MANNA2115 | J81: =ЯНВАРЬ!U68 -> 0 | K81: =J81/J$100 -> 0 | L81: =L80+K81 -> 0.99307059 | M81: =_xlfn.IFS(L81<80%,"A",L81<=95%,"B",L81>95%,"C") -> C
B82: MANNA2108 | C82: =ЯНВАРЬ!AO61 -> -523.18175 | D82: =C82/C$100 -> -0.0027881297 | E82: =E81+D82 -> 1.456487 | F82: =IF(AND(E82<=0),"C",IF(E82<=0.8,"A",IF(E82<=0.95,"B","C"))) -> C | G82: =VLOOKUP(B$4:B$99,I$4:M$99,5,0) -> C | I82: MANNA2116 | J82: =ЯНВАРЬ!U69 -> 0 | K82: =J82/J$100 -> 0 | L82: =L81+K82 -> 0.99307059 | M82: =_xlfn.IFS(L82<80%,"A",L82<=95%,"B",L82>95%,"C") -> C
B83: sh09 | C83: =ЯНВАРЬ!AO33 -> -565.53751 | D83: =C83/C$100 -> -0.0030138512 | E83: =E82+D83 -> 1.4534732 | F83: =IF(AND(E83<=0),"C",IF(E83<=0.8,"A",IF(E83<=0.95,"B","C"))) -> C | G83: =VLOOKUP(B$4:B$99,I$4:M$99,5,0) -> C | I83: Chenlong черные | J83: =ЯНВАРЬ!U76 -> 0 | K83: =J83/J$100 -> 0 | L83: =L82+K83 -> 0.99307059 | M83: =_xlfn.IFS(L83<80%,"A",L83<=95%,"B",L83>95%,"C") -> C
B84: sh2 | C84: =ЯНВАРЬ!AO27 -> -569.4154 | D84: =C84/C$100 -> -0.0030345172 | E84: =E83+D84 -> 1.4504387 | F84: =IF(AND(E84<=0),"C",IF(E84<=0.8,"A",IF(E84<=0.95,"B","C"))) -> C | G84: =VLOOKUP(B$4:B$99,I$4:M$99,5,0) -> C | I84: Chenlong коричневые | J84: =ЯНВАРЬ!U77 -> 0 | K84: =J84/J$100 -> 0 | L84: =L83+K84 -> 0.99307059 | M84: =_xlfn.IFS(L84<80%,"A",L84<=95%,"B",L84>95%,"C") -> C
B85: sh06 | C85: =ЯНВАРЬ!AO30 -> -690.90554 | D85: =C85/C$100 -> -0.00368196 | E85: =E84+D85 -> 1.4467567 | F85: =IF(AND(E85<=0),"C",IF(E85<=0.8,"A",IF(E85<=0.95,"B","C"))) -> C | G85: =VLOOKUP(B$4:B$99,I$4:M$99,5,0) -> B | I85: Guangdu золото серая линза | J85: =ЯНВАРЬ!U79 -> 0 | K85: =J85/J$100 -> 0 | L85: =L84+K85 -> 0.99307059 | M85: =_xlfn.IFS(L85<80%,"A",L85<=95%,"B",L85>95%,"C") -> C
B86: ww 203 черные | C86: =ЯНВАРЬ!AO44 -> -827.14437 | D86: =C86/C$100 -> -0.0044080013 | E86: =E85+D86 -> 1.4423487 | F86: =IF(AND(E86<=0),"C",IF(E86<=0.8,"A",IF(E86<=0.95,"B","C"))) -> C | G86: =VLOOKUP(B$4:B$99,I$4:M$99,5,0) -> C | I86: Guangdu серебро серая линза | J86: =ЯНВАРЬ!U80 -> 0 | K86: =J86/J$100 -> 0 | L86: =L85+K86 -> 0.99307059 | M86: =_xlfn.IFS(L86<80%,"A",L86<=95%,"B",L86>95%,"C") -> C
B87: th син | C87: =ЯНВАРЬ!AO10 -> -1358.1577 | D87: =C87/C$100 -> -0.007237867 | E87: =E86+D87 -> 1.4351109 | F87: =IF(AND(E87<=0),"C",IF(E87<=0.8,"A",IF(E87<=0.95,"B","C"))) -> C | G87: =VLOOKUP(B$4:B$99,I$4:M$99,5,0) -> A | I87: Hengda Optical черные | J87: =ЯНВАРЬ!U81 -> 0 | K87: =J87/J$100 -> 0 | L87: =L86+K87 -> 0.99307059 | M87: =_xlfn.IFS(L87<80%,"A",L87<=95%,"B",L87>95%,"C") -> C
B88: ww 2018 черные | C88: =ЯНВАРЬ!AO49 -> -1364.659 | D88: =C88/C$100 -> -0.0072725136 | E88: =E87+D88 -> 1.4278383 | F88: =IF(AND(E88<=0),"C",IF(E88<=0.8,"A",IF(E88<=0.95,"B","C"))) -> C | G88: =VLOOKUP(B$4:B$99,I$4:M$99,5,0) -> B | I88: Hengda Optical леопард | J88: =ЯНВАРЬ!U82 -> 0 | K88: =J88/J$100 -> 0 | L88: =L87+K88 -> 0.99307059 | M88: =_xlfn.IFS(L88<80%,"A",L88<=95%,"B",L88>95%,"C") -> C
B89: sh07 | C89: =ЯНВАРЬ!AO31 -> -1717.1185 | D89: =C89/C$100 -> -0.0091508337 | E89: =E88+D89 -> 1.4186875 | F89: =IF(AND(E89<=0),"C",IF(E89<=0.8,"A",IF(E89<=0.95,"B","C"))) -> C | G89: =VLOOKUP(B$4:B$99,I$4:M$99,5,0) -> C | I89: Qianai черные | J89: =ЯНВАРЬ!U83 -> 0 | K89: =J89/J$100 -> 0 | L89: =L88+K89 -> 0.99307059 | M89: =_xlfn.IFS(L89<80%,"A",L89<=95%,"B",L89>95%,"C") -> C
B90: ww 2018 желтые | C90: =ЯНВАРЬ!AO50 -> -2847.0138 | D90: =C90/C$100 -> -0.015172249 | E90: =E89+D90 -> 1.4035153 | F90: =IF(AND(E90<=0),"C",IF(E90<=0.8,"A",IF(E90<=0.95,"B","C"))) -> C | G90: =VLOOKUP(B$4:B$99,I$4:M$99,5,0) -> B | I90: Qianai коричневые | J90: =ЯНВАРЬ!U84 -> 0 | K90: =J90/J$100 -> 0 | L90: =L89+K90 -> 0.99307059 | M90: =_xlfn.IFS(L90<80%,"A",L90<=95%,"B",L90>95%,"C") -> C
B91: Linhai Baiyi розовая линза | C91: =ЯНВАРЬ!AO88 -> -3351.1969 | D91: =C91/C$100 -> -0.017859132 | E91: =E90+D91 -> 1.3856561 | F91: =IF(AND(E91<=0),"C",IF(E91<=0.8,"A",IF(E91<=0.95,"B","C"))) -> C | G91: =VLOOKUP(B$4:B$99,I$4:M$99,5,0) -> C | I91: MR Р1894 черные | J91: =ЯНВАРЬ!U89 -> 0 | K91: =J91/J$100 -> 0 | L91: =L90+K91 -> 0.99307059 | M91: =_xlfn.IFS(L91<80%,"A",L91<=95%,"B",L91>95%,"C") -> C
B92: th коричн | C92: =ЯНВАРЬ!AO12 -> -5323.4968 | D92: =C92/C$100 -> -0.028369873 | E92: =E91+D92 -> 1.3572863 | F92: =IF(AND(E92<=0),"C",IF(E92<=0.8,"A",IF(E92<=0.95,"B","C"))) -> C | G92: =VLOOKUP(B$4:B$99,I$4:M$99,5,0) -> B | I92: Taizhou Rayen sport розовый | J92: =ЯНВАРЬ!U90 -> 0 | K92: =J92/J$100 -> 0 | L92: =L91+K92 -> 0.99307059 | M92: =_xlfn.IFS(L92<80%,"A",L92<=95%,"B",L92>95%,"C") -> C
B93: MR8854 C2 Жен | C93: =ЯНВАРЬ!AO8 -> -5671.1964 | D93: =C93/C$100 -> -0.030222826 | E93: =E92+D93 -> 1.3270634 | F93: =IF(AND(E93<=0),"C",IF(E93<=0.8,"A",IF(E93<=0.95,"B","C"))) -> C | G93: =VLOOKUP(B$4:B$99,I$4:M$99,5,0) -> A | I93: Иу Диту серый | J93: =ЯНВАРЬ!U91 -> 0 | K93: =J93/J$100 -> 0 | L93: =L92+K93 -> 0.99307059 | M93: =_xlfn.IFS(L93<80%,"A",L93<=95%,"B",L93>95%,"C") -> C
B94: flip желтые | C94: =ЯНВАРЬ!AO15 -> -5873.5181 | D94: =C94/C$100 -> -0.031301035 | E94: =E93+D94 -> 1.2957624 | F94: =IF(AND(E94<=0),"C",IF(E94<=0.8,"A",IF(E94<=0.95,"B","C"))) -> C | G94: =VLOOKUP(B$4:B$99,I$4:M$99,5,0) -> B | I94: Ли Сян ретро золото | J94: =ЯНВАРЬ!U92 -> 0 | K94: =J94/J$100 -> 0 | L94: =L93+K94 -> 0.99307059 | M94: =_xlfn.IFS(L94<80%,"A",L94<=95%,"B",L94>95%,"C") -> C
B95: Keming Aishi коричневые | C95: =ЯНВАРЬ!AO85 -> -7973.9206 | D95: =C95/C$100 -> -0.042494458 | E95: =E94+D95 -> 1.2532679 | F95: =IF(AND(E95<=0),"C",IF(E95<=0.8,"A",IF(E95<=0.95,"B","C"))) -> C | G95: =VLOOKUP(B$4:B$99,I$4:M$99,5,0) -> C | I95: Ли Сян ретро серебро | J95: =ЯНВАРЬ!U93 -> 0 | K95: =J95/J$100 -> 0 | L95: =L94+K95 -> 0.99307059 | M95: =_xlfn.IFS(L95<80%,"A",L95<=95%,"B",L95>95%,"C") -> C
B96: flip синие | C96: =ЯНВАРЬ!AO14 -> -8866.9886 | D96: =C96/C$100 -> -0.047253779 | E96: =E95+D96 -> 1.2060142 | F96: =IF(AND(E96<=0),"C",IF(E96<=0.8,"A",IF(E96<=0.95,"B","C"))) -> C | G96: =VLOOKUP(B$4:B$99,I$4:M$99,5,0) -> B | I96: MAIERSHA 03898 C9-08 | J96: =ЯНВАРЬ!U94 -> 0 | K96: =J96/J$100 -> 0 | L96: =L95+K96 -> 0.99307059 | M96: =_xlfn.IFS(L96<80%,"A",L96<=95%,"B",L96>95%,"C") -> C
B97: sh3 | C97: =ЯНВАРЬ!AO28 -> -10071.881 | D97: =C97/C$100 -> -0.053674867 | E97: =E96+D97 -> 1.1523393 | F97: =IF(AND(E97<=0),"C",IF(E97<=0.8,"A",IF(E97<=0.95,"B","C"))) -> C | G97: =VLOOKUP(B$4:B$99,I$4:M$99,5,0) -> A | I97: MAIERSHA 03914 C9-124 | J97: =ЯНВАРЬ!U95 -> 0 | K97: =J97/J$100 -> 0 | L97: =L96+K97 -> 0.99307059 | M97: =_xlfn.IFS(L97<80%,"A",L97<=95%,"B",L97>95%,"C") -> C
B98: ww 8010 черные | C98: =ЯНВАРЬ!AO51 -> -12157.174 | D98: =C98/C$100 -> -0.064787769 | E98: =E97+D98 -> 1.0875515 | F98: =IF(AND(E98<=0),"C",IF(E98<=0.8,"A",IF(E98<=0.95,"B","C"))) -> C | G98: =VLOOKUP(B$4:B$99,I$4:M$99,5,0) -> C | I98: POMILED 08247 C4-08 | J98: =ЯНВАРЬ!U97 -> 0 | K98: =J98/J$100 -> 0 | L98: =L97+K98 -> 0.99307059 | M98: =_xlfn.IFS(L98<80%,"A",L98<=95%,"B",L98>95%,"C") -> C
B99: sh1 | C99: =ЯНВАРЬ!AO26 -> -12625.961 | D99: =C99/C$100 -> -0.067286021 | E99: =E98+D99 -> 1.0202655 | F99: =IF(AND(E99<=0),"C",IF(E99<=0.8,"A",IF(E99<=0.95,"B","C"))) -> C | G99: =VLOOKUP(B$4:B$99,I$4:M$99,5,0) -> B | I99: YIMEI 2391 C1 | J99: =ЯНВАРЬ!U98 -> 0 | K99: =J99/J$100 -> 0 | L99: =L98+K99 -> 0.99307059 | M99: =_xlfn.IFS(L99<80%,"A",L99<=95%,"B",L99>95%,"C") -> C
C100: =SUM(C4:C99) -> 187646.13 | D100: =SUM(D4:D99) -> 1 | J100: =SUM(J4:J99) -> 2309 | K100: =SUM(K4:K99) -> 1
B102: ТУНИКИ
...

Sheet Юнит 9
A1: 16-22.02_8 нед | F1: Отчет по остаткам 3,4,5 | I1: Мой склад | M1: Цены и скидки 6 | N1: Воронка продаж 20,54,36 | AJ1: Без учета в прибыли | AL1: Вставить в Итого | AQ1: на 1 единицу проданного товара
A2: Бренд | B2: SKU | C2: Артикул поставщика | D2: Предмет | E2: Остаток на | F2: В пути до клиента | G2: В пути от клиента | H2: Итого по складам ВБ | I2: Остаток на осн. складе | J2: Остаток на фф | K2: Себетоимость на 1 ед на 29.09.25 | L2: Себестоимость остатков | M2: Оборачива-емость, дн | N2: Заказы, шт 32 дня | O2: Средняя цена, руб | P2: % выкупа за 7 дней | Q2: Скорость заказов | R2: Скорость продаж | S2: Кол-во ПРОДАЖИ | T2: Кол-во ВОЗВРАТЫ | U2: Кол-во ПРОДАЖИ-ВОЗВРАТЫ | V2: Выручка ВБ ПРОДАЖИ | W2: Выручка ВБ ВОЗВРАТЫ | X2: Выручка с учетом СПП ПРОДАЖИ - ВОЗВРАТЫ | Y2: Выручка ПРОДАЖИ | Z2: Выручка ВОЗВРАТЫ | AA2: Выручка с учетом согласованной скидки ПРОДАЖИ - ВОЗВРАТЫ | AB2: Выручка потенциальная | AC2: Доля выручки, % от общего объема | AD2: Себестоимость продаж | AE2: Комиссия, руб | AF2: Комиссия, % | AG2: Логистика | AH2: Реклама БАЛАНС | AI2: Реклама СЧЕТ | AJ2: Реклама Промо бонусы | AK2: Блогеры | AL2: Хранение | AM2: Штрафы | AN2: Налог 1%+ НДС 5% | AO2: Прибыль | AQ2: Выручка на 1 ед (средняя цена продажи со скидкой) | AR2: Себестоимость на 1 ед | AS2: Комиссия на 1 ед | AT2: Логистика на 1 ед | AU2: Реклама на 1 ед | AV2: Прибыль на 1 ед | AW2: Маржиналь-ность, % | AX2: Рентабель-ность, % | AZ2: Прибыль с остатков
A3: Ridges | B3: 170499929 | C3: черные с железкой классика | D3: Солнцезащитные очки | E3: =SUM(F3:J3) -> 0 | K3: 142.98 | L3: =E3*K3 -> 0 | Q3: =N3/32 -> 0 | R3: =U3/32 -> 0 | U3: =S3+T3 -> 0 | X3: =V3+W3 -> 0 | AA3: =Y3+Z3 -> 0 | AB3: =N3*O3*P3/100 -> 0 | AC3: =AA3/$AA$121 -> #DIV/0! | AD3: =U3*K3 -> 0 | AF3: =IF(AA3=0,0,AE3/AA3) -> 0 | AL3: =IFERROR($AL$121*H3/$H$121,0) -> 0 | AN3: =X3*5.71% -> 0 | AO3: =AA3-AD3-AE3-AG3-AH3-AI3-AK3-AL3-AN3-AM3 -> 0 | AQ3: =IF(U3=0,0,AA3/U3) -> 0 | AR3: =K3 -> 142.98 | AS3: =IF(U3=0,0,AE3/U3) -> 0 | AT3: =IF(S3=0,AG3/1,AG3/S3) -> 0 | AU3: =IF(S3=0,0,(AH3+AI3+AJ3)/S3) -> 0 | AV3: =_xlfn.IFS(U3=0,AO3,U3<0,AO3/-U3,U3>0,AO3/U3) -> 0 | AW3: =IF(AQ3=0,0,AV3/AQ3) -> 0 | AX3: =IF(AR3=0,0,AV3/AR3) -> 0 | AZ3: =AV3*E3 -> 0
A4: Ridges | B4: 170500631 | C4: QS черные PZ | D4: Солнцезащитные очки | E4: =SUM(F4:J4) -> 0 | K4: 123.09 | L4: =E4*K4 -> 0 | Q4: =N4/32 -> 0 | R4: =U4/32 -> 0 | U4: =S4+T4 -> 0 | X4: =V4+W4 -> 0 | AA4: =Y4+Z4 -> 0 | AB4: =N4*O4*P4/100 -> 0 | AC4: =AA4/$AA$121 -> #DIV/0! | AD4: =U4*K4 -> 0 | AF4: =IF(AA4=0,0,AE4/AA4) -> 0 | AL4: =IFERROR($AL$121*H4/$H$121,0) -> 0 | AN4: =X4*5.71% -> 0 | AO4: =AA4-AD4-AE4-AG4-AH4-AI4-AK4-AL4-AN4-AM4 -> 0 | AQ4: =IF(U4=0,0,AA4/U4) -> 0 | AR4: =K4 -> 123.09 | AS4: =IF(U4=0,0,AE4/U4) -> 0 | AT4: =IF(S4=0,AG4/1,AG4/S4) -> 0 | AU4: =IF(S4=0,0,(AH4+AI4+AJ4)/S4) -> 0 | AV4: {=_xlfn.IFS(U4=0,AO4,U4<0,AO4/-U4,U4>0,AO4/U4)} -> 0 | AW4: =IF(AQ4=0,0,AV4/AQ4) -> 0 | AX4: =IF(AR4=0,0,AV4/AR4) -> 0 | AZ4: =AV4*E4 -> 0
A5: Ridges | B5: 170500399 | C5: QS синие PZ | D5: Солнцезащитные очки | E5: =SUM(F5:J5) -> 0 | K5: 123.09 | L5: =E5*K5 -> 0 | Q5: =N5/32 -> 0 | R5: =U5/32 -> 0 | U5: =S5+T5 -> 0 | X5: =V5+W5 -> 0 | AA5: =Y5+Z5 -> 0 | AB5: =N5*O5*P5/100 -> 0 | AC5: =AA5/$AA$121 -> #DIV/0! | AD5: =U5*K5 -> 0 | AF5: =IF(AA5=0,0,AE5/AA5) -> 0 | AL5: =IFERROR($AL$121*H5/$H$121,0) -> 0 | AN5: =X5*5.71% -> 0 | AO5: =AA5-AD5-AE5-AG5-AH5-AI5-AK5-AL5-AN5-AM5 -> 0 | AQ5: =IF(U5=0,0,AA5/U5) -> 0 | AR5: =K5 -> 123.09 | AS5: =IF(U5=0,0,AE5/U5) -> 0 | AT5: =IF(S5=0,AG5/1,AG5/S5) -> 0 | AU5: =IF(S5=0,0,(AH5+AI5+AJ5)/S5) -> 0 | AV5: {=_xlfn.IFS(U5=0,AO5,U5<0,AO5/-U5,U5>0,AO5/U5)} -> 0 | AW5: =IF(AQ5=0,0,AV5/AQ5) -> 0 | AX5: =IF(AR5=0,0,AV5/AR5) -> 0 | AZ5: =AV5*E5 -> 0
A6: Ridges | B6: 170500725 | C6: QS желтые PZ | D6: Солнцезащитные очки | E6: =SUM(F6:J6) -> 0 | K6: 123.09 | L6: =E6*K6 -> 0 | Q6: =N6/32 -> 0 | R6: =U6/32 -> 0 | U6: =S6+T6 -> 0 | X6: =V6+W6 -> 0 | AA6: =Y6+Z6 -> 0 | AB6: =N6*O6*P6/100 -> 0 | AC6: =AA6/$AA$121 -> #DIV/0! | AD6: =U6*K6 -> 0 | AF6: =IF(AA6=0,0,AE6/AA6) -> 0 | AL6: =IFERROR($AL$121*H6/$H$121,0) -> 0 | AN6: =X6*5.71% -> 0 | AO6: =AA6-AD6-AE6-AG6-AH6-AI6-AK6-AL6-AN6-AM6 -> 0 | AQ6: =IF(U6=0,0,AA6/U6) -> 0 | AR6: =K6 -> 123.09 | AS6: =IF(U6=0,0,AE6/U6) -> 0 | AT6: =IF(S6=0,AG6/1,AG6/S6) -> 0 | AU6: =IF(S6=0,0,(AH6+AI6+AJ6)/S6) -> 0 | AV6: {=_xlfn.IFS(U6=0,AO6,U6<0,AO6/-U6,U6>0,AO6/U6)} -> 0 | AW6: =IF(AQ6=0,0,AV6/AQ6) -> 0 | AX6: =IF(AR6=0,0,AV6/AR6) -> 0 | AZ6: =AV6*E6 -> 0
A7: Ridges | B7: 246275459 | C7: QS коричневые PZ | D7: Солнцезащитные очки | E7: =SUM(F7:J7) -> 0 | K7: 117.24 | L7: =E7*K7 -> 0 | Q7: =N7/32 -> 0 | R7: =U7/32 -> 0 | U7: =S7+T7 -> 0 | X7: =V7+W7 -> 0 | AA7: =Y7+Z7 -> 0 | AB7: =N7*O7*P7/100 -> 0 | AC7: =AA7/$AA$121 -> #DIV/0! | AD7: =U7*K7 -> 0 | AF7: =IF(AA7=0,0,AE7/AA7) -> 0 | AL7: =IFERROR($AL$121*H7/$H$121,0) -> 0 | AN7: =X7*5.71% -> 0 | AO7: =AA7-AD7-AE7-AG7-AH7-AI7-AK7-AL7-AN7-AM7 -> 0 | AQ7: =IF(U7=0,0,AA7/U7) -> 0 | AR7: =K7 -> 117.24 | AS7: =IF(U7=0,0,AE7/U7) -> 0 | AT7: =IF(S7=0,AG7/1,AG7/S7) -> 0 | AU7: =IF(S7=0,0,(AH7+AI7+AJ7)/S7) -> 0 | AV7: {=_xlfn.IFS(U7=0,AO7,U7<0,AO7/-U7,U7>0,AO7/U7)} -> 0 | AW7: =IF(AQ7=0,0,AV7/AQ7) -> 0 | AX7: =IF(AR7=0,0,AV7/AR7) -> 0 | AZ7: =AV7*E7 -> 0
A8: Ridges | B8: 159900625 | C8: MR8854 C2 Жен | D8: Солнцезащитные очки | E8: =SUM(F8:J8) -> 0 | K8: 169.89 | L8: =E8*K8 -> 0 | Q8: =N8/32 -> 0 | R8: =U8/32 -> 0 | U8: =S8+T8 -> 0 | X8: =V8+W8 -> 0 | AA8: =Y8+Z8 -> 0 | AB8: =N8*O8*P8/100 -> 0 | AC8: =AA8/$AA$121 -> #DIV/0! | AD8: =U8*K8 -> 0 | AF8: =IF(AA8=0,0,AE8/AA8) -> 0 | AL8: =IFERROR($AL$121*H8/$H$121,0) -> 0 | AN8: =X8*5.71% -> 0 | AO8: =AA8-AD8-AE8-AG8-AH8-AI8-AK8-AL8-AN8-AM8 -> 0 | AQ8: =IF(U8=0,0,AA8/U8) -> 0 | AR8: =K8 -> 169.89 | AS8: =IF(U8=0,0,AE8/U8) -> 0 | AT8: =IF(S8=0,AG8/1,AG8/S8) -> 0 | AU8: =IF(S8=0,0,(AH8+AI8+AJ8)/S8) -> 0 | AV8: {=_xlfn.IFS(U8=0,AO8,U8<0,AO8/-U8,U8>0,AO8/U8)} -> 0 | AW8: =IF(AQ8=0,0,AV8/AQ8) -> 0 | AX8: =IF(AR8=0,0,AV8/AR8) -> 0 | AZ8: =AV8*E8 -> 0
A9: Ridges | B9: 251467353 | C9: th черн | D9: Солнцезащитные очки | E9: =SUM(F9:J9) -> 0 | K9: 123.09 | L9: =E9*K9 -> 0 | Q9: =N9/32 -> 0 | R9: =U9/32 -> 0 | U9: =S9+T9 -> 0 | X9: =V9+W9 -> 0 | AA9: =Y9+Z9 -> 0 | AB9: =N9*O9*P9/100 -> 0 | AC9: =AA9/$AA$121 -> #DIV/0! | AD9: =U9*K9 -> 0 | AF9: =IF(AA9=0,0,AE9/AA9) -> 0 | AL9: =IFERROR($AL$121*H9/$H$121,0) -> 0 | AN9: =X9*5.71% -> 0 | AO9: =AA9-AD9-AE9-AG9-AH9-AI9-AK9-AL9-AN9-AM9 -> 0 | AQ9: =IF(U9=0,0,AA9/U9) -> 0 | AR9: =K9 -> 123.09 | AS9: =IF(U9=0,0,AE9/U9) -> 0 | AT9: =IF(S9=0,AG9/1,AG9/S9) -> 0 | AU9: =IF(S9=0,0,(AH9+AI9+AJ9)/S9) -> 0 | AV9: {=_xlfn.IFS(U9=0,AO9,U9<0,AO9/-U9,U9>0,AO9/U9)} -> 0 | AW9: =IF(AQ9=0,0,AV9/AQ9) -> 0 | AX9: =IF(AR9=0,0,AV9/AR9) -> 0 | AZ9: =AV9*E9 -> 0
A10: Ridges | B10: 251467354 | C10: th син | D10: Солнцезащитные очки | E10: =SUM(F10:J10) -> 0 | K10: 123.09 | L10: =E10*K10 -> 0 | Q10: =N10/32 -> 0 | R10: =U10/32 -> 0 | U10: =S10+T10 -> 0 | X10: =V10+W10 -> 0 | AA10: =Y10+Z10 -> 0 | AB10: =N10*O10*P10/100 -> 0 | AC10: =AA10/$AA$121 -> #DIV/0! | AD10: =U10*K10 -> 0 | AF10: =IF(AA10=0,0,AE10/AA10) -> 0 | AL10: =IFERROR($AL$121*H10/$H$121,0) -> 0 | AN10: =X10*5.71% -> 0 | AO10: =AA10-AD10-AE10-AG10-AH10-AI10-AK10-AL10-AN10-AM10 -> 0 | AQ10: =IF(U10=0,0,AA10/U10) -> 0 | AR10: =K10 -> 123.09 | AS10: =IF(U10=0,0,AE10/U10) -> 0 | AT10: =IF(S10=0,AG10/1,AG10/S10) -> 0 | AU10: =IF(S10=0,0,(AH10+AI10+AJ10)/S10) -> 0 | AV10: {=_xlfn.IFS(U10=0,AO10,U10<0,AO10/-U10,U10>0,AO10/U10)} -> 0 | AW10: =IF(AQ10=0,0,AV10/AQ10) -> 0 | AX10: =IF(AR10=0,0,AV10/AR10) -> 0 | AZ10: =AV10*E10 -> 0
A11: Ridges | B11: 251467355 | C11: th желт | D11: Солнцезащитные очки | E11: =SUM(F11:J11) -> 0 | K11: 123.09 | L11: =E11*K11 -> 0 | Q11: =N11/32 -> 0 | R11: =U11/32 -> 0 | U11: =S11+T11 -> 0 | X11: =V11+W11 -> 0 | AA11: =Y11+Z11 -> 0 | AB11: =N11*O11*P11/100 -> 0 | AC11: =AA11/$AA$121 -> #DIV/0! | AD11: =U11*K11 -> 0 | AF11: =IF(AA11=0,0,AE11/AA11) -> 0 | AL11: =IFERROR($AL$121*H11/$H$121,0) -> 0 | AN11: =X11*5.71% -> 0 | AO11: =AA11-AD11-AE11-AG11-AH11-AI11-AK11-AL11-AN11-AM11 -> 0 | AQ11: =IF(U11=0,0,AA11/U11) -> 0 | AR11: =K11 -> 123.09 | AS11: =IF(U11=0,0,AE11/U11) -> 0 | AT11: =IF(S11=0,AG11/1,AG11/S11) -> 0 | AU11: =IF(S11=0,0,(AH11+AI11+AJ11)/S11) -> 0 | AV11: {=_xlfn.IFS(U11=0,AO11,U11<0,AO11/-U11,U11>0,AO11/U11)} -> 0 | AW11: =IF(AQ11=0,0,AV11/AQ11) -> 0 | AX11: =IF(AR11=0,0,AV11/AR11) -> 0 | AZ11: =AV11*E11 -> 0
A12: Ridges | B12: 303941289 | C12: th коричн | D12: Солнцезащитные очки | E12: =SUM(F12:J12) -> 0 | K12: 117.24 | L12: =E12*K12 -> 0 | Q12: =N12/32 -> 0 | R12: =U12/32 -> 0 | U12: =S12+T12 -> 0 | X12: =V12+W12 -> 0 | AA12: =Y12+Z12 -> 0 | AB12: =N12*O12*P12/100 -> 0 | AC12: =AA12/$AA$121 -> #DIV/0! | AD12: =U12*K12 -> 0 | AF12: =IF(AA12=0,0,AE12/AA12) -> 0 | AL12: =IFERROR($AL$121*H12/$H$121,0) -> 0 | AN12: =X12*5.71% -> 0 | AO12: =AA12-AD12-AE12-AG12-AH12-AI12-AK12-AL12-AN12-AM12 -> 0 | AQ12: =IF(U12=0,0,AA12/U12) -> 0 | AR12: =K12 -> 117.24 | AS12: =IF(U12=0,0,AE12/U12) -> 0 | AT12: =IF(S12=0,AG12/1,AG12/S12) -> 0 | AU12: =IF(S12=0,0,(AH12+AI12+AJ12)/S12) -> 0 | AV12: {=_xlfn.IFS(U12=0,AO12,U12<0,AO12/-U12,U12>0,AO12/U12)} -> 0 | AW12: =IF(AQ12=0,0,AV12/AQ12) -> 0 | AX12: =IF(AR12=0,0,AV12/AR12) -> 0 | AZ12: =AV12*E12 -> 0
A13: Ridges | B13: 274218038 | C13: flip черные | D13: Солнцезащитные очки | E13: =SUM(F13:J13) -> 0 | K13: 123.09 | L13: =E13*K13 -> 0 | Q13: =N13/32 -> 0 | R13: =U13/32 -> 0 | U13: =S13+T13 -> 0 | X13: =V13+W13 -> 0 | AA13: =Y13+Z13 -> 0 | AB13: =N13*O13*P13/100 -> 0 | AC13: =AA13/$AA$121 -> #DIV/0! | AD13: =U13*K13 -> 0 | AF13: =IF(AA13=0,0,AE13/AA13) -> 0 | AL13: =IFERROR($AL$121*H13/$H$121,0) -> 0 | AN13: =X13*5.71% -> 0 | AO13: =AA13-AD13-AE13-AG13-AH13-AI13-AK13-AL13-AN13-AM13 -> 0 | AQ13: =IF(U13=0,0,AA13/U13) -> 0 | AR13: =K13 -> 123.09 | AS13: =IF(U13=0,0,AE13/U13) -> 0 | AT13: =IF(S13=0,AG13/1,AG13/S13) -> 0 | AU13: =IF(S13=0,0,(AH13+AI13+AJ13)/S13) -> 0 | AV13: {=_xlfn.IFS(U13=0,AO13,U13<0,AO13/-U13,U13>0,AO13/U13)} -> 0 | AW13: =IF(AQ13=0,0,AV13/AQ13) -> 0 | AX13: =IF(AR13=0,0,AV13/AR13) -> 0 | AZ13: =AV13*E13 -> 0
A14: Ridges | B14: 274219203 | C14: flip синие | D14: Солнцезащитные очки | E14: =SUM(F14:J14) -> 0 | K14: 123.09 | L14: =E14*K14 -> 0 | Q14: =N14/32 -> 0 | R14: =U14/32 -> 0 | U14: =S14+T14 -> 0 | X14: =V14+W14 -> 0 | AA14: =Y14+Z14 -> 0 | AB14: =N14*O14*P14/100 -> 0 | AC14: =AA14/$AA$121 -> #DIV/0! | AD14: =U14*K14 -> 0 | AF14: =IF(AA14=0,0,AE14/AA14) -> 0 | AL14: =IFERROR($AL$121*H14/$H$121,0) -> 0 | AN14: =X14*5.71% -> 0 | AO14: =AA14-AD14-AE14-AG14-AH14-AI14-AK14-AL14-AN14-AM14 -> 0 | AQ14: =IF(U14=0,0,AA14/U14) -> 0 | AR14: =K14 -> 123.09 | AS14: =IF(U14=0,0,AE14/U14) -> 0 | AT14: =IF(S14=0,AG14/1,AG14/S14) -> 0 | AU14: =IF(S14=0,0,(AH14+AI14+AJ14)/S14) -> 0 | AV14: {=_xlfn.IFS(U14=0,AO14,U14<0,AO14/-U14,U14>0,AO14/U14)} -> 0 | AW14: =IF(AQ14=0,0,AV14/AQ14) -> 0 | AX14: =IF(AR14=0,0,AV14/AR14) -> 0 | AZ14: =AV14*E14 -> 0
A15: Ridges | B15: 274190322 | C15: flip желтые | D15: Солнцезащитные очки | E15: =SUM(F15:J15) -> 0 | K15: 123.09 | L15: =E15*K15 -> 0 | Q15: =N15/32 -> 0 | R15: =U15/32 -> 0 | U15: =S15+T15 -> 0 | X15: =V15+W15 -> 0 | AA15: =Y15+Z15 -> 0 | AB15: =N15*O15*P15/100 -> 0 | AC15: =AA15/$AA$121 -> #DIV/0! | AD15: =U15*K15 -> 0 | AF15: =IF(AA15=0,0,AE15/AA15) -> 0 | AL15: =IFERROR($AL$121*H15/$H$121,0) -> 0 | AN15: =X15*5.71% -> 0 | AO15: =AA15-AD15-AE15-AG15-AH15-AI15-AK15-AL15-AN15-AM15 -> 0 | AQ15: =IF(U15=0,0,AA15/U15) -> 0 | AR15: =K15 -> 123.09 | AS15: =IF(U15=0,0,AE15/U15) -> 0 | AT15: =IF(S15=0,AG15/1,AG15/S15) -> 0 | AU15: =IF(S15=0,0,(AH15+AI15+AJ15)/S15) -> 0 | AV15: {=_xlfn.IFS(U15=0,AO15,U15<0,AO15/-U15,U15>0,AO15/U15)} -> 0 | AW15: =IF(AQ15=0,0,AV15/AQ15) -> 0 | AX15: =IF(AR15=0,0,AV15/AR15) -> 0 | AZ15: =AV15*E15 -> 0
... A27: Ridges | B27: 207984027 | C27: sh2 | D27: Солнцезащитные очки | E27: =SUM(F27:J27) -> 0 | K27: 181.59 | L27: =E27*K27 -> 0 | Q27: =N27/32 -> 0 | R27: =U27/32 -> 0 | U27: =S27+T27 -> 0 | X27: =V27+W27 -> 0 | AA27: =Y27+Z27 -> 0 | AB27: =N27*O27*P27/100 -> 0 | AC27: =AA27/$AA$121 -> #DIV/0! | AD27: =U27*K27 -> 0 | AF27: =IF(AA27=0,0,AE27/AA27) -> 0 | AL27: =IFERROR($AL$121*H27/$H$121,0) -> 0 | AN27: =X27*5.71% -> 0 | AO27: =AA27-AD27-AE27-AG27-AH27-AI27-AK27-AL27-AN27-AM27 -> 0 | AQ27: =IF(U27=0,0,AA27/U27) -> 0 | AR27: =K27 -> 181.59 | AS27: =IF(U27=0,0,AE27/U27) -> 0 | AT27: =IF(S27=0,AG27/1,AG27/S27) -> 0 | AU27: =IF(S27=0,0,(AH27+AI27+AJ27)/S27) -> 0 | AV27: {=_xlfn.IFS(U27=0,AO27,U27<0,AO27/-U27,U27>0,AO27/U27)} -> 0 | AW27: =IF(AQ27=0,0,AV27/AQ27) -> 0 | AX27: =IF(AR27=0,0,AV27/AR27) -> 0 | AZ27: =AV27*E27 -> 0
A28: Ridges | B28: 207984028 | C28: sh3 | D28: Солнцезащитные очки | E28: =SUM(F28:J28) -> 0 | K28: 133.62 | L28: =E28*K28 -> 0 | Q28: =N28/32 -> 0 | R28: =U28/32 -> 0 | U28: =S28+T28 -> 0 | X28: =V28+W28 -> 0 | AA28: =Y28+Z28 -> 0 | AB28: =N28*O28*P28/100 -> 0 | AC28: =AA28/$AA$121 -> #DIV/0! | AD28: =U28*K28 -> 0 | AF28: =IF(AA28=0,0,AE28/AA28) -> 0 | AL28: =IFERROR($AL$121*H28/$H$121,0) -> 0 | AN28: =X28*5.71% -> 0 | AO28: =AA28-AD28-AE28-AG28-AH28-AI28-AK28-AL28-AN28-AM28 -> 0 | AQ28: =IF(U28=0,0,AA28/U28) -> 0 | AR28: =K28 -> 133.62 | AS28: =IF(U28=0,0,AE28/U28) -> 0 | AT28: =IF(S28=0,AG28/1,AG28/S28) -> 0 | AU28: =IF(S28=0,0,(AH28+AI28+AJ28)/S28) -> 0 | AV28: =_xlfn.IFS(U28=0,AO28,U28<0,AO28/-U28,U28>0,AO28/U28) -> 0 | AW28: =IF(AQ28=0,0,AV28/AQ28) -> 0 | AX28: =IF(AR28=0,0,AV28/AR28) -> 0 | AZ28: =AV28*E28 -> 0
A29: Ridges | B29: 207984029 | C29: sh4 | D29: Солнцезащитные очки | E29: =SUM(F29:J29) -> 0 | K29: 111.39 | L29: =E29*K29 -> 0 | Q29: =N29/32 -> 0 | R29: =U29/32 -> 0 | U29: =S29+T29 -> 0 | X29: =V29+W29 -> 0 | AA29: =Y29+Z29 -> 0 | AB29: =N29*O29*P29/100 -> 0 | AC29: =AA29/$AA$121 -> #DIV/0! | AD29: =U29*K29 -> 0 | AF29: =IF(AA29=0,0,AE29/AA29) -> 0 | AL29: =IFERROR($AL$121*H29/$H$121,0) -> 0 | AN29: =X29*5.71% -> 0 | AO29: =AA29-AD29-AE29-AG29-AH29-AI29-AK29-AL29-AN29-AM29 -> 0 | AQ29: =IF(U29=0,0,AA29/U29) -> 0 | AR29: =K29 -> 111.39 | AS29: =IF(U29=0,0,AE29/U29) -> 0 | AT29: =IF(S29=0,AG29/1,AG29/S29) -> 0 | AU29: =IF(S29=0,0,(AH29+AI29+AJ29)/S29) -> 0 | AV29: {=_xlfn.IFS(U29=0,AO29,U29<0,AO29/-U29,U29>0,AO29/U29)} -> 0 | AW29: =IF(AQ29=0,0,AV29/AQ29) -> 0 | AX29: =IF(AR29=0,0,AV29/AR29) -> 0 | AZ29: =AV29*E29 -> 0
A30: Ridges | B30: 233496972 | C30: sh06 | D30: Солнцезащитные очки | E30: =SUM(F30:J30) -> 0 | K30: 111.39 | L30: =E30*K30 -> 0 | Q30: =N30/32 -> 0 | R30: =U30/32 -> 0 | U30: =S30+T30 -> 0 | X30: =V30+W30 -> 0 | AA30: =Y30+Z30 -> 0 | AB30: =N30*O30*P30/100 -> 0 | AC30: =AA30/$AA$121 -> #DIV/0! | AD30: =U30*K30 -> 0 | AF30: =IF(AA30=0,0,AE30/AA30) -> 0 | AL30: =IFERROR($AL$121*H30/$H$121,0) -> 0 | AN30: =X30*5.71% -> 0 | AO30: =AA30-AD30-AE30-AG30-AH30-AI30-AK30-AL30-AN30-AM30 -> 0 | AQ30: =IF(U30=0,0,AA30/U30) -> 0 | AR30: =K30 -> 111.39 | AS30: =IF(U30=0,0,AE30/U30) -> 0 | AT30: =IF(S30=0,AG30/1,AG30/S30) -> 0 | AU30: =IF(S30=0,0,(AH30+AI30+AJ30)/S30) -> 0 | AV30: {=_xlfn.IFS(U30=0,AO30,U30<0,AO30/-U30,U30>0,AO30/U30)} -> 0 | AW30: =IF(AQ30=0,0,AV30/AQ30) -> 0 | AX30: =IF(AR30=0,0,AV30/AR30) -> 0 | AZ30: =AV30*E30 -> 0
A31: Ridges | B31: 233497520 | C31: sh07 | D31: Солнцезащитные очки | E31: =SUM(F31:J31) -> 0 | K31: 105.54 | L31: =E31*K31 -> 0 | Q31: =N31/32 -> 0 | R31: =U31/32 -> 0 | U31: =S31+T31 -> 0 | X31: =V31+W31 -> 0 | AA31: =Y31+Z31 -> 0 | AB31: =N31*O31*P31/100 -> 0 | AC31: =AA31/$AA$121 -> #DIV/0! | AD31: =U31*K31 -> 0 | AF31: =IF(AA31=0,0,AE31/AA31) -> 0 | AL31: =IFERROR($AL$121*H31/$H$121,0) -> 0 | AN31: =X31*5.71% -> 0 | AO31: =AA31-AD31-AE31-AG31-AH31-AI31-AK31-AL31-AN31-AM31 -> 0 | AQ31: =IF(U31=0,0,AA31/U31) -> 0 | AR31: =K31 -> 105.54 | AS31: =IF(U31=0,0,AE31/U31) -> 0 | AT31: =IF(S31=0,AG31/1,AG31/S31) -> 0 | AU31: =IF(S31=0,0,(AH31+AI31+AJ31)/S31) -> 0 | AV31: {=_xlfn.IFS(U31=0,AO31,U31<0,AO31/-U31,U31>0,AO31/U31)} -> 0 | AW31: =IF(AQ31=0,0,AV31/AQ31) -> 0 | AX31: =IF(AR31=0,0,AV31/AR31) -> 0 | AZ31: =AV31*E31 -> 0
A32: Ridges | B32: 233498313 | C32: sh08 | D32: Солнцезащитные очки | E32: =SUM(F32:J32) -> 0 | K32: 140.64 | L32: =E32*K32 -> 0 | Q32: =N32/32 -> 0 | R32: =U32/32 -> 0 | U32: =S32+T32 -> 0 | X32: =V32+W32 -> 0 | AA32: =Y32+Z32 -> 0 | AB32: =N32*O32*P32/100 -> 0 | AC32: =AA32/$AA$121 -> #DIV/0! | AD32: =U32*K32 -> 0 | AF32: =IF(AA32=0,0,AE32/AA32) -> 0 | AL32: =IFERROR($AL$121*H32/$H$121,0) -> 0 | AN32: =X32*5.71% -> 0 | AO32: =AA32-AD32-AE32-AG32-AH32-AI32-AK32-AL32-AN32-AM32 -> 0 | AQ32: =IF(U32=0,0,AA32/U32) -> 0 | AR32: =K32 -> 140.64 | AS32: =IF(U32=0,0,AE32/U32) -> 0 | AT32: =IF(S32=0,AG32/1,AG32/S32) -> 0 | AU32: =IF(S32=0,0,(AH32+AI32+AJ32)/S32) -> 0 | AV32: {=_xlfn.IFS(U32=0,AO32,U32<0,AO32/-U32,U32>0,AO32/U32)} -> 0 | AW32: =IF(AQ32=0,0,AV32/AQ32) -> 0 | AX32: =IF(AR32=0,0,AV32/AR32) -> 0 | AZ32: =AV32*E32 -> 0
A33: Ridges | B33: 233499847 | C33: sh09 | D33: Солнцезащитные очки | E33: =SUM(F33:J33) -> 0 | K33: 123.09 | L33: =E33*K33 -> 0 | Q33: =N33/32 -> 0 | R33: =U33/32 -> 0 | U33: =S33+T33 -> 0 | X33: =V33+W33 -> 0 | AA33: =Y33+Z33 -> 0 | AB33: =N33*O33*P33/100 -> 0 | AC33: =AA33/$AA$121 -> #DIV/0! | AD33: =U33*K33 -> 0 | AF33: =IF(AA33=0,0,AE33/AA33) -> 0 | AL33: =IFERROR($AL$121*H33/$H$121,0) -> 0 | AN33: =X33*5.71% -> 0 | AO33: =AA33-AD33-AE33-AG33-AH33-AI33-AK33-AL33-AN33-AM33 -> 0 | AQ33: =IF(U33=0,0,AA33/U33) -> 0 | AR33: =K33 -> 123.09 | AS33: =IF(U33=0,0,AE33/U33) -> 0 | AT33: =IF(S33=0,AG33/1,AG33/S33) -> 0 | AU33: =IF(S33=0,0,(AH33+AI33+AJ33)/S33) -> 0 | AV33: {=_xlfn.IFS(U33=0,AO33,U33<0,AO33/-U33,U33>0,AO33/U33)} -> 0 | AW33: =IF(AQ33=0,0,AV33/AQ33) -> 0 | AX33: =IF(AR33=0,0,AV33/AR33) -> 0 | AZ33: =AV33*E33 -> 0
A34: Ridges | B34: 233500274 | C34: sh10 | D34: Солнцезащитные очки | E34: =SUM(F34:J34) -> 0 | K34: 117.24 | L34: =E34*K34 -> 0 | Q34: =N34/32 -> 0 | R34: =U34/32 -> 0 | U34: =S34+T34 -> 0 | X34: =V34+W34 -> 0 | AA34: =Y34+Z34 -> 0 | AB34: =N34*O34*P34/100 -> 0 | AC34: =AA34/$AA$121 -> #DIV/0! | AD34: =U34*K34 -> 0 | AF34: =IF(AA34=0,0,AE34/AA34) -> 0 | AL34: =IFERROR($AL$121*H34/$H$121,0) -> 0 | AN34: =X34*5.71% -> 0 | AO34: =AA34-AD34-AE34-AG34-AH34-AI34-AK34-AL34-AN34-AM34 -> 0 | AQ34: =IF(U34=0,0,AA34/U34) -> 0 | AR34: =K34 -> 117.24 | AS34: =IF(U34=0,0,AE34/U34) -> 0 | AT34: =IF(S34=0,AG34/1,AG34/S34) -> 0 | AU34: =IF(S34=0,0,(AH34+AI34+AJ34)/S34) -> 0 | AV34: {=_xlfn.IFS(U34=0,AO34,U34<0,AO34/-U34,U34>0,AO34/U34)} -> 0 | AW34: =IF(AQ34=0,0,AV34/AQ34) -> 0 | AX34: =IF(AR34=0,0,AV34/AR34) -> 0 | AZ34: =AV34*E34 -> 0
A35: Ridges | B35: 471878869 | C35: sh11 | D35: Солнцезащитные очки | E35: =SUM(F35:J35) -> 0 | K35: 128.94 | L35: =E35*K35 -> 0 | Q35: =N35/32 -> 0 | R35: =U35/32 -> 0 | U35: =S35+T35 -> 0 | X35: =V35+W35 -> 0 | AA35: =Y35+Z35 -> 0 | AB35: =N35*O35*P35/100 -> 0 | AC35: =AA35/$AA$121 -> #DIV/0! | AD35: =U35*K35 -> 0 | AF35: =IF(AA35=0,0,AE35/AA35) -> 0 | AL35: =IFERROR($AL$121*H35/$H$121,0) -> 0 | AN35: =X35*5.71% -> 0 | AO35: =AA35-AD35-AE35-AG35-AH35-AI35-AK35-AL35-AN35-AM35 -> 0 | AQ35: =IF(U35=0,0,AA35/U35) -> 0 | AR35: =K35 -> 128.94 | AS35: =IF(U35=0,0,AE35/U35) -> 0 | AT35: =IF(S35=0,AG35/1,AG35/S35) -> 0 | AU35: =IF(S35=0,0,(AH35+AI35+AJ35)/S35) -> 0 | AV35: {=_xlfn.IFS(U35=0,AO35,U35<0,AO35/-U35,U35>0,AO35/U35)} -> 0 | AW35: =IF(AQ35=0,0,AV35/AQ35) -> 0 | AX35: =IF(AR35=0,0,AV35/AR35) -> 0 | AZ35: =AV35*E35 -> 0
A36: Ridges | B36: 471878989 | C36: sh12 | D36: Солнцезащитные очки | E36: =SUM(F36:J36) -> 0 | K36: 169.89 | L36: =E36*K36 -> 0 | Q36: =N36/32 -> 0 | R36: =U36/32 -> 0 | U36: =S36+T36 -> 0 | X36: =V36+W36 -> 0 | AA36: =Y36+Z36 -> 0 | AB36: =N36*O36*P36/100 -> 0 | AC36: =AA36/$AA$121 -> #DIV/0! | AD36: =U36*K36 -> 0 | AF36: =IF(AA36=0,0,AE36/AA36) -> 0 | AL36: =IFERROR($AL$121*H36/$H$121,0) -> 0 | AN36: =X36*5.71% -> 0 | AO36: =AA36-AD36-AE36-AG36-AH36-AI36-AK36-AL36-AN36-AM36 -> 0 | AQ36: =IF(U36=0,0,AA36/U36) -> 0 | AR36: =K36 -> 169.89 | AS36: =IF(U36=0,0,AE36/U36) -> 0 | AT36: =IF(S36=0,AG36/1,AG36/S36) -> 0 | AU36: =IF(S36=0,0,(AH36+AI36+AJ36)/S36) -> 0 | AV36: {=_xlfn.IFS(U36=0,AO36,U36<0,AO36/-U36,U36>0,AO36/U36)} -> 0 | AW36: =IF(AQ36=0,0,AV36/AQ36) -> 0 | AX36: =IF(AR36=0,0,AV36/AR36) -> 0 | AZ36: =AV36*E36 -> 0
A37: Ridges | B37: 471879283 | C37: sh13 | D37: Солнцезащитные очки | E37: =SUM(F37:J37) -> 0 | K37: 169.89 | L37: =E37*K37 -> 0 | Q37: =N37/32 -> 0 | R37: =U37/32 -> 0 | U37: =S37+T37 -> 0 | X37: =V37+W37 -> 0 | AA37: =Y37+Z37 -> 0 | AB37: =N37*O37*P37/100 -> 0 | AC37: =AA37/$AA$121 -> #DIV/0! | AD37: =U37*K37 -> 0 | AF37: =IF(AA37=0,0,AE37/AA37) -> 0 | AL37: =IFERROR($AL$121*H37/$H$121,0) -> 0 | AN37: =X37*5.71% -> 0 | AO37: =AA37-AD37-AE37-AG37-AH37-AI37-AK37-AL37-AN37-AM37 -> 0 | AQ37: =IF(U37=0,0,AA37/U37) -> 0 | AR37: =K37 -> 169.89 | AS37: =IF(U37=0,0,AE37/U37) -> 0 | AT37: =IF(S37=0,AG37/1,AG37/S37) -> 0 | AU37: =IF(S37=0,0,(AH37+AI37+AJ37)/S37) -> 0 | AV37: {=_xlfn.IFS(U37=0,AO37,U37<0,AO37/-U37,U37>0,AO37/U37)} -> 0 | AW37: =IF(AQ37=0,0,AV37/AQ37) -> 0 | AX37: =IF(AR37=0,0,AV37/AR37) -> 0 | AZ37: =AV37*E37 -> 0
A38: Ridges | B38: 507117329 | C38: sh14 | D38: Солнцезащитные очки | E38: =SUM(F38:J38) -> 0 | K38: 105.54 | L38: =E38*K38 -> 0 | Q38: =N38/32 -> 0 | R38: =U38/32 -> 0 | U38: =S38+T38 -> 0 | X38: =V38+W38 -> 0 | AA38: =Y38+Z38 -> 0 | AB38: =N38*O38*P38/100 -> 0 | AC38: =AA38/$AA$121 -> #DIV/0! | AD38: =U38*K38 -> 0 | AF38: =IF(AA38=0,0,AE38/AA38) -> 0 | AL38: =IFERROR($AL$121*H38/$H$121,0) -> 0 | AN38: =X38*5.71% -> 0 | AO38: =AA38-AD38-AE38-AG38-AH38-AI38-AK38-AL38-AN38-AM38 -> 0 | AQ38: =IF(U38=0,0,AA38/U38) -> 0 | AR38: =K38 -> 105.54 | AS38: =IF(U38=0,0,AE38/U38) -> 0 | AT38: =IF(S38=0,AG38/1,AG38/S38) -> 0 | AU38: =IF(S38=0,0,(AH38+AI38+AJ38)/S38) -> 0 | AV38: {=_xlfn.IFS(U38=0,AO38,U38<0,AO38/-U38,U38>0,AO38/U38)} -> 0 | AW38: =IF(AQ38=0,0,AV38/AQ38) -> 0 | AX38: =IF(AR38=0,0,AV38/AR38) -> 0 | AZ38: =AV38*E38 -> 0
A39: Ridges | B39: 507117646 | C39: sh15 | D39: Солнцезащитные очки | E39: =SUM(F39:J39) -> 0 | K39: 105.54 | L39: =E39*K39 -> 0 | Q39: =N39/32 -> 0 | R39: =U39/32 -> 0 | U39: =S39+T39 -> 0 | X39: =V39+W39 -> 0 | AA39: =Y39+Z39 -> 0 | AB39: =N39*O39*P39/100 -> 0 | AC39: =AA39/$AA$121 -> #DIV/0! | AD39: =U39*K39 -> 0 | AF39: =IF(AA39=0,0,AE39/AA39) -> 0 | AL39: =IFERROR($AL$121*H39/$H$121,0) -> 0 | AN39: =X39*5.71% -> 0 | AO39: =AA39-AD39-AE39-AG39-AH39-AI39-AK39-AL39-AN39-AM39 -> 0 | AQ39: =IF(U39=0,0,AA39/U39) -> 0 | AR39: =K39 -> 105.54 | AS39: =IF(U39=0,0,AE39/U39) -> 0 | AT39: =IF(S39=0,AG39/1,AG39/S39) -> 0 | AU39: =IF(S39=0,0,(AH39+AI39+AJ39)/S39) -> 0 | AV39: {=_xlfn.IFS(U39=0,AO39,U39<0,AO39/-U39,U39>0,AO39/U39)} -> 0 | AW39: =IF(AQ39=0,0,AV39/AQ39) -> 0 | AX39: =IF(AR39=0,0,AV39/AR39) -> 0 | AZ39: =AV39*E39 -> 0
A40: Ridges | B40: 507118076 | C40: sh16 | D40: Солнцезащитные очки | E40: =SUM(F40:J40) -> 0 | K40: 105.54 | L40: =E40*K40 -> 0 | Q40: =N40/32 -> 0 | R40: =U40/32 -> 0 | U40: =S40+T40 -> 0 | X40: =V40+W40 -> 0 | AA40: =Y40+Z40 -> 0 | AB40: =N40*O40*P40/100 -> 0 | AC40: =AA40/$AA$121 -> #DIV/0! | AD40: =U40*K40 -> 0 | AF40: =IF(AA40=0,0,AE40/AA40) -> 0 | AL40: =IFERROR($AL$121*H40/$H$121,0) -> 0 | AN40: =X40*5.71% -> 0 | AO40: =AA40-AD40-AE40-AG40-AH40-AI40-AK40-AL40-AN40-AM40 -> 0 | AQ40: =IF(U40=0,0,AA40/U40) -> 0 | AR40: =K40 -> 105.54 | AS40: =IF(U40=0,0,AE40/U40) -> 0 | AT40: =IF(S40=0,AG40/1,AG40/S40) -> 0 | AU40: =IF(S40=0,0,(AH40+AI40+AJ40)/S40) -> 0 | AV40: {=_xlfn.IFS(U40=0,AO40,U40<0,AO40/-U40,U40>0,AO40/U40)} -> 0 | AW40: =IF(AQ40=0,0,AV40/AQ40) -> 0 | AX40: =IF(AR40=0,0,AV40/AR40) -> 0 | AZ40: =AV40*E40 -> 0
... A98: Ridges | B98: 342820134 | C98: YIMEI 2391 C1 | D98: Солнцезащитные очки | E98: =SUM(F98:J98) -> 0 | K98: 300.08 | L98: =E98*K98 -> 0 | Q98: =N98/32 -> 0 | R98: =U98/32 -> 0 | U98: =S98+T98 -> 0 | X98: =V98+W98 -> 0 | AA98: =Y98+Z98 -> 0 | AB98: =N98*O98*P98/100 -> 0 | AC98: =AA98/$AA$121 -> #DIV/0! | AD98: =U98*K98 -> 0 | AF98: =IF(AA98=0,0,AE98/AA98) -> 0 | AL98: =IFERROR($AL$121*H98/$H$121,0) -> 0 | AN98: =X98*5.71% -> 0 | AO98: =AA98-AD98-AE98-AG98-AH98-AI98-AK98-AL98-AN98-AM98 -> 0 | AQ98: =IF(U98=0,0,AA98/U98) -> 0 | AR98: =K98 -> 300.08 | AS98: =IF(U98=0,0,AE98/U98) -> 0 | AT98: =IF(S98=0,AG98/1,AG98/S98) -> 0 | AU98: =IF(S98=0,0,(AH98+AI98+AJ98)/S98) -> 0 | AV98: {=_xlfn.IFS(U98=0,AO98,U98<0,AO98/-U98,U98>0,AO98/U98)} -> 0 | AW98: =IF(AQ98=0,0,AV98/AQ98) -> 0 | AX98: =IF(AR98=0,0,AV98/AR98) -> 0 | AZ98: =AV98*E98 -> 0
C99: Доп. артикулы | AQ99: =AVERAGE(AQ7:AQ98) -> 0 | AR99: =AVERAGE(AR7:AR98) -> 141.22217 | AS99: =AVERAGE(AS7:AS98) -> 0 | AT99: =AVERAGE(AT7:AT98) -> 0 | AU99: =AVERAGE(AU7:AU98) -> 0 | AV99: =AVERAGE(AV7:AV98) -> 0 | AW99: =AVERAGE(AW7:AW98) -> 0 | AX99: =AVERAGE(AX7:AX98) -> 0
A100: Итого очки | E100: =SUM(E3:E98) -> 0 | F100: =SUM(F3:F98) -> 0 | G100: =SUM(G3:G98) -> 0 | H100: =SUM(H3:H98) -> 0 | I100: =SUM(I3:I98) -> 0 | J100: =SUM(J3:J98) -> 0 | L100: =SUM(L3:L98) -> 0 | N100: =SUM(N3:N98) -> 0 | S100: =SUM(S3:S98) -> 0 | T100: =SUM(T3:T98) -> 0 | U100: =SUM(U3:U98) -> 0 | V100: =SUM(V3:V98) -> 0 | W100: =SUM(W3:W98) -> 0 | X100: =SUM(X3:X98) -> 0 | Y100: =SUM(Y3:Y98) -> 0 | Z100: =SUM(Z3:Z98) -> 0 | ... AE100: =SUM(AE3:AE98) -> 0 | AF100: =AE100/AA100 -> #DIV/0! | AG100: =SUM(AG3:AG98) -> 0 | AH100: =SUM(AH3:AH98) -> 0 | AI100: =SUM(AI3:AI98) -> 0 | AJ100: =SUM(AJ3:AJ98) -> 0 | AK100: =SUM(AK3:AK98) -> 0 | AL100: =SUM(AL3:AL98) -> 0 | AM100: =SUM(AM3:AM98) -> 0 | AN100: =SUM(AN3:AN98) -> 0 | AO100: =SUM(AO3:AO98) -> 0 | AU100: =(AH100+AI100+AJ100)/S100 -> #DIV/0! | AZ100: =SUM(AZ3:AZ98) -> 0
A102: Ridges Clothes | B102: 437023601 | C102: tunika01 (белая вышивка) | D102: Пляжная туника | E102: =SUM(F102:J102) -> 1 | H102: 0 | I102: 0 | J102: 1 | K102: 579.18 | L102: =E102*K102 -> 579.18 | Q102: =N102/32 -> 0 | R102: =U102/32 -> 0 | U102: =S102+T102 -> 0 | X102: =V102+W102 -> 0 | AA102: =Y102+Z102 -> 0 | AB102: =N102*O102*P102/100 -> 0 | AC102: =AA102/$AA$121 -> #DIV/0! | AD102: =U102*K102 -> 0 | AF102: =IF(AA102=0,0,AE102/AA102) -> 0 | AL102: =IFERROR($AL$121*H102/$H$121,0) -> 0 | AN102: =X102*5.71% -> 0 | AO102: =AA102-AD102-AE102-AG102-AH102-AI102-AK102-AL102-AN102-AM102 -> 0 | AQ102: =IF(U102=0,0,AA102/U102) -> 0 | AR102: =K102 -> 579.18 | AS102: =IF(U102=0,0,AE102/U102) -> 0 | AT102: =IF(S102=0,AG102/1,AG102/S102) -> 0 | AU102: =IF(S102=0,0,(AH102+AI102+AJ102)/S102) -> 0 | AV102: {=_xlfn.IFS(U102=0,AO102,U102<0,AO102/-U102,U102>0,AO102/U102)} -> 0 | AW102: =IF(AQ102=0,0,AV102/AQ102) -> 0 | AX102: =IF(AR102=0,0,AV102/AR102) -> 0 | AZ102: =AV102*E102 -> 0
A103: Ridges Clothes | B103: 437027509 | C103: tunika02 (зеленая вышивка) | D103: Пляжная туника | E103: =SUM(F103:J103) -> 2 | H103: 1 | I103: 0 | J103: 1 | K103: 579.18 | L103: =E103*K103 -> 1158.36 | Q103: =N103/32 -> 0 | R103: =U103/32 -> 0 | U103: =S103+T103 -> 0 | X103: =V103+W103 -> 0 | AA103: =Y103+Z103 -> 0 | AB103: =N103*O103*P103/100 -> 0 | AC103: =AA103/$AA$121 -> #DIV/0! | AD103: =U103*K103 -> 0 | AF103: =IF(AA103=0,0,AE103/AA103) -> 0 | AL103: =IFERROR($AL$121*H103/$H$121,0) -> 0 | AN103: =X103*5.71% -> 0 | AO103: =AA103-AD103-AE103-AG103-AH103-AI103-AK103-AL103-AN103-AM103 -> 0 | AQ103: =IF(U103=0,0,AA103/U103) -> 0 | AR103: =K103 -> 579.18 | AS103: =IF(U103=0,0,AE103/U103) -> 0 | AT103: =IF(S103=0,AG103/1,AG103/S103) -> 0 | AU103: =IF(S103=0,0,(AH103+AI103+AJ103)/S103) -> 0 | AV103: {=_xlfn.IFS(U103=0,AO103,U103<0,AO103/-U103,U103>0,AO103/U103)} -> 0 | AW103: =IF(AQ103=0,0,AV103/AQ103) -> 0 | AX103: =IF(AR103=0,0,AV103/AR103) -> 0 | AZ103: =AV103*E103 -> 0
A104: Ridges Clothes | B104: 437097997 | C104: tunika03 (черная распашная) | D104: Пляжная туника | E104: =SUM(F104:J104) -> 2 | H104: 0 | I104: 0 | J104: 2 | K104: 541.68 | L104: =E104*K104 -> 1083.36 | Q104: =N104/32 -> 0 | R104: =U104/32 -> 0 | U104: =S104+T104 -> 0 | X104: =V104+W104 -> 0 | AA104: =Y104+Z104 -> 0 | AB104: =N104*O104*P104/100 -> 0 | AC104: =AA104/$AA$121 -> #DIV/0! | AD104: =U104*K104 -> 0 | AF104: =IF(AA104=0,0,AE104/AA104) -> 0 | AL104: =IFERROR($AL$121*H104/$H$121,0) -> 0 | AN104: =X104*5.71% -> 0 | AO104: =AA104-AD104-AE104-AG104-AH104-AI104-AK104-AL104-AN104-AM104 -> 0 | AQ104: =IF(U104=0,0,AA104/U104) -> 0 | AR104: =K104 -> 541.68 | AS104: =IF(U104=0,0,AE104/U104) -> 0 | AT104: =IF(S104=0,AG104/1,AG104/S104) -> 0 | AU104: =IF(S104=0,0,(AH104+AI104+AJ104)/S104) -> 0 | AV104: {=_xlfn.IFS(U104=0,AO104,U104<0,AO104/-U104,U104>0,AO104/U104)} -> 0 | AW104: =IF(AQ104=0,0,AV104/AQ104) -> 0 | AX104: =IF(AR104=0,0,AV104/AR104) -> 0 | AZ104: =AV104*E104 -> 0
A105: Ridges Clothes | B105: 437061068 | C105: tunika04 (черная вышивка) | D105: Пляжная туника | E105: =SUM(F105:J105) -> 1 | H105: 0 | I105: 0 | J105: 1 | K105: 541.68 | L105: =E105*K105 -> 541.68 | Q105: =N105/32 -> 0 | R105: =U105/32 -> 0 | U105: =S105+T105 -> 0 | X105: =V105+W105 -> 0 | AA105: =Y105+Z105 -> 0 | AB105: =N105*O105*P105/100 -> 0 | AC105: =AA105/$AA$121 -> #DIV/0! | AD105: =U105*K105 -> 0 | AF105: =IF(AA105=0,0,AE105/AA105) -> 0 | AL105: =IFERROR($AL$121*H105/$H$121,0) -> 0 | AN105: =X105*5.71% -> 0 | AO105: =AA105-AD105-AE105-AG105-AH105-AI105-AK105-AL105-AN105-AM105 -> 0 | AQ105: =IF(U105=0,0,AA105/U105) -> 0 | AR105: =K105 -> 541.68 | AS105: =IF(U105=0,0,AE105/U105) -> 0 | AT105: =IF(S105=0,AG105/1,AG105/S105) -> 0 | AU105: =IF(S105=0,0,(AH105+AI105+AJ105)/S105) -> 0 | AV105: {=_xlfn.IFS(U105=0,AO105,U105<0,AO105/-U105,U105>0,AO105/U105)} -> 0 | AW105: =IF(AQ105=0,0,AV105/AQ105) -> 0 | AX105: =IF(AR105=0,0,AV105/AR105) -> 0 | AZ105: =AV105*E105 -> 0
A106: Ridges Clothes | B106: 437095304 | C106: tunika05 (белая распашная) | D106: Пляжная туника | E106: =SUM(F106:J106) -> 1 | H106: 0 | I106: 0 | J106: 1 | K106: 541.68 | L106: =E106*K106 -> 541.68 | Q106: =N106/32 -> 0 | R106: =U106/32 -> 0 | U106: =S106+T106 -> 0 | X106: =V106+W106 -> 0 | AA106: =Y106+Z106 -> 0 | AB106: =N106*O106*P106/100 -> 0 | AC106: =AA106/$AA$121 -> #DIV/0! | AD106: =U106*K106 -> 0 | AF106: =IF(AA106=0,0,AE106/AA106) -> 0 | AL106: =IFERROR($AL$121*H106/$H$121,0) -> 0 | AN106: =X106*5.71% -> 0 | AO106: =AA106-AD106-AE106-AG106-AH106-AI106-AK106-AL106-AN106-AM106 -> 0 | AQ106: =IF(U106=0,0,AA106/U106) -> 0 | AR106: =K106 -> 541.68 | AS106: =IF(U106=0,0,AE106/U106) -> 0 | AT106: =IF(S106=0,AG106/1,AG106/S106) -> 0 | AU106: =IF(S106=0,0,(AH106+AI106+AJ106)/S106) -> 0 | AV106: {=_xlfn.IFS(U106=0,AO106,U106<0,AO106/-U106,U106>0,AO106/U106)} -> 0 | AW106: =IF(AQ106=0,0,AV106/AQ106) -> 0 | AX106: =IF(AR106=0,0,AV106/AR106) -> 0 | AZ106: =AV106*E106 -> 0
AQ107: =AVERAGE(AQ102:AQ106) -> 0 | AR107: =AVERAGE(AR102:AR106) -> 556.68 | AS107: =AVERAGE(AS102:AS106) -> 0 | AT107: =AVERAGE(AT102:AT106) -> 0 | AU107: =AVERAGE(AU102:AU106) -> 0 | AV107: =AVERAGE(AV102:AV106) -> 0 | AW107: =AVERAGE(AW102:AW106) -> 0 | AX107: =AVERAGE(AX102:AX106) -> 0
A108: Итого туники | E108: =SUM(E102:E106) -> 7 | F108: =SUM(F102:F106) -> 0 | G108: =SUM(G102:G106) -> 0 | H108: =SUM(H102:H106) -> 1 | I108: =SUM(I102:I106) -> 0 | J108: =SUM(J102:J106) -> 6 | L108: =SUM(L102:L106) -> 3904.26 | N108: =SUM(N102:N106) -> 0 | S108: =SUM(S102:S106) -> 0 | T108: =SUM(T102:T106) -> 0 | U108: =SUM(U102:U106) -> 0 | V108: =SUM(V102:V106) -> 0 | W108: =SUM(W102:W106) -> 0 | X108: =SUM(X102:X106) -> 0 | Y108: =SUM(Y102:Y106) -> 0 | Z108: =SUM(Z102:Z106) -> 0 | ... AE108: =SUM(AE102:AE106) -> 0 | AF108: =AE108/AA108 -> #DIV/0! | AG108: =SUM(AG102:AG106) -> 0 | AH108: =SUM(AH102:AH106) -> 0 | AI108: =SUM(AI102:AI106) -> 0 | AJ108: =SUM(AJ102:AJ106) -> 0 | AK108: =SUM(AK102:AK106) -> 0 | AL108: =SUM(AL102:AL106) -> 0 | AM108: =SUM(AM102:AM106) -> 0 | AN108: =SUM(AN102:AN106) -> 0 | AO108: =SUM(AO102:AO106) -> 0 | AU108: =(AH108+AI108+AJ108)/S108 -> #DIV/0! | AZ108: =SUM(AZ102:AZ106) -> 0
A110: Ridges Clothes | B110: 260411674 | C110: fhd01 серый | E110: =SUM(F110:J110) -> 2 | H110: 0 | I110: 1 | J110: 1 | K110: 140 | L110: =E110*K110 -> 280 | Q110: =N110/32 -> 0 | R110: =U110/32 -> 0 | U110: =S110+T110 -> 0 | X110: =V110+W110 -> 0 | AA110: =Y110+Z110 -> 0 | AB110: =N110*O110*P110/100 -> 0 | AC110: =AA110/$AA$121 -> #DIV/0! | AD110: =U110*K110 -> 0 | AF110: =IF(AA110=0,0,AE110/AA110) -> 0 | AL110: =IFERROR($AL$121*H110/$H$121,0) -> 0 | AN110: =X110*5.71% -> 0 | AO110: =AA110-AD110-AE110-AG110-AH110-AI110-AK110-AL110-AN110-AM110 -> 0 | AQ110: =IF(U110=0,0,AA110/U110) -> 0 | AR110: =K110 -> 140 | AS110: =IF(U110=0,0,AE110/U110) -> 0 | AT110: =IF(S110=0,AG110/1,AG110/S110) -> 0 | AU110: =IF(S110=0,0,(AH110+AI110+AJ110)/S110) -> 0 | AV110: {=_xlfn.IFS(U110=0,AO110,U110<0,AO110/-U110,U110>0,AO110/U110)} -> 0 | AW110: =IF(AQ110=0,0,AV110/AQ110) -> 0 | AX110: =IF(AR110=0,0,AV110/AR110) -> 0 | AZ110: =AV110*E110 -> 0
A111: Ridges Clothes | B111: 260945325 | C111: fhd06 серый | E111: =SUM(F111:J111) -> 1 | H111: 0 | I111: 1 | K111: 154 | L111: =E111*K111 -> 154 | Q111: =N111/32 -> 0 | R111: =U111/32 -> 0 | U111: =S111+T111 -> 0 | X111: =V111+W111 -> 0 | AA111: =Y111+Z111 -> 0 | AB111: =N111*O111*P111/100 -> 0 | AC111: =AA111/$AA$121 -> #DIV/0! | AD111: =U111*K111 -> 0 | AF111: =IF(AA111=0,0,AE111/AA111) -> 0 | AL111: =IFERROR($AL$121*H111/$H$121,0) -> 0 | AN111: =X111*5.71% -> 0 | AO111: =AA111-AD111-AE111-AG111-AH111-AI111-AK111-AL111-AN111-AM111 -> 0 | AQ111: =IF(U111=0,0,AA111/U111) -> 0 | AR111: =K111 -> 154 | AS111: =IF(U111=0,0,AE111/U111) -> 0 | AT111: =IF(S111=0,AG111/1,AG111/S111) -> 0 | AU111: =IF(S111=0,0,(AH111+AI111+AJ111)/S111) -> 0 | AV111: {=_xlfn.IFS(U111=0,AO111,U111<0,AO111/-U111,U111>0,AO111/U111)} -> 0 | AW111: =IF(AQ111=0,0,AV111/AQ111) -> 0 | AX111: =IF(AR111=0,0,AV111/AR111) -> 0 | AZ111: =AV111*E111 -> 0
A112: Ridges Clothes | B112: 261545954 | C112: fhd08 черный | E112: =SUM(F112:J112) -> 1 | H112: 0 | I112: 1 | K112: 220 | L112: =E112*K112 -> 220 | Q112: =N112/32 -> 0 | R112: =U112/32 -> 0 | U112: =S112+T112 -> 0 | X112: =V112+W112 -> 0 | AA112: =Y112+Z112 -> 0 | AB112: =N112*O112*P112/100 -> 0 | AC112: =AA112/$AA$121 -> #DIV/0! | AD112: =U112*K112 -> 0 | AF112: =IF(AA112=0,0,AE112/AA112) -> 0 | AL112: =IFERROR($AL$121*H112/$H$121,0) -> 0 | AN112: =X112*5.71% -> 0 | AO112: =AA112-AD112-AE112-AG112-AH112-AI112-AK112-AL112-AN112-AM112 -> 0 | AQ112: =IF(U112=0,0,AA112/U112) -> 0 | AR112: =K112 -> 220 | AS112: =IF(U112=0,0,AE112/U112) -> 0 | AT112: =IF(S112=0,AG112/1,AG112/S112) -> 0 | AU112: =IF(S112=0,0,(AH112+AI112+AJ112)/S112) -> 0 | AV112: {=_xlfn.IFS(U112=0,AO112,U112<0,AO112/-U112,U112>0,AO112/U112)} -> 0 | AW112: =IF(AQ112=0,0,AV112/AQ112) -> 0 | AX112: =IF(AR112=0,0,AV112/AR112) -> 0 | AZ112: =AV112*E112 -> 0
A113: Ridges Clothes | B113: 261546082 | C113: fhd08 бордовый | E113: =SUM(F113:J113) -> 1 | H113: 0 | I113: 1 | K113: 220 | L113: =E113*K113 -> 220 | Q113: =N113/32 -> 0 | R113: =U113/32 -> 0 | U113: =S113+T113 -> 0 | X113: =V113+W113 -> 0 | AA113: =Y113+Z113 -> 0 | AB113: =N113*O113*P113/100 -> 0 | AC113: =AA113/$AA$121 -> #DIV/0! | AD113: =U113*K113 -> 0 | AF113: =IF(AA113=0,0,AE113/AA113) -> 0 | AL113: =IFERROR($AL$121*H113/$H$121,0) -> 0 | AN113: =X113*5.71% -> 0 | AO113: =AA113-AD113-AE113-AG113-AH113-AI113-AK113-AL113-AN113-AM113 -> 0 | AQ113: =IF(U113=0,0,AA113/U113) -> 0 | AR113: =K113 -> 220 | AS113: =IF(U113=0,0,AE113/U113) -> 0 | AT113: =IF(S113=0,AG113/1,AG113/S113) -> 0 | AU113: =IF(S113=0,0,(AH113+AI113+AJ113)/S113) -> 0 | AV113: {=_xlfn.IFS(U113=0,AO113,U113<0,AO113/-U113,U113>0,AO113/U113)} -> 0 | AW113: =IF(AQ113=0,0,AV113/AQ113) -> 0 | AX113: =IF(AR113=0,0,AV113/AR113) -> 0 | AZ113: =AV113*E113 -> 0
A114: Ridges Clothes | B114: 261546175 | C114: fhd08 темно-серый | E114: =SUM(F114:J114) -> 6 | H114: 0 | I114: 1 | J114: 5 | K114: 220 | L114: =E114*K114 -> 1320 | Q114: =N114/32 -> 0 | R114: =U114/32 -> 0 | U114: =S114+T114 -> 0 | X114: =V114+W114 -> 0 | AA114: =Y114+Z114 -> 0 | AB114: =N114*O114*P114/100 -> 0 | AC114: =AA114/$AA$121 -> #DIV/0! | AD114: =U114*K114 -> 0 | AF114: =IF(AA114=0,0,AE114/AA114) -> 0 | AL114: =IFERROR($AL$121*H114/$H$121,0) -> 0 | AN114: =X114*5.71% -> 0 | AO114: =AA114-AD114-AE114-AG114-AH114-AI114-AK114-AL114-AN114-AM114 -> 0 | AQ114: =IF(U114=0,0,AA114/U114) -> 0 | AR114: =K114 -> 220 | AS114: =IF(U114=0,0,AE114/U114) -> 0 | AT114: =IF(S114=0,AG114/1,AG114/S114) -> 0 | AU114: =IF(S114=0,0,(AH114+AI114+AJ114)/S114) -> 0 | AV114: {=_xlfn.IFS(U114=0,AO114,U114<0,AO114/-U114,U114>0,AO114/U114)} -> 0 | AW114: =IF(AQ114=0,0,AV114/AQ114) -> 0 | AX114: =IF(AR114=0,0,AV114/AR114) -> 0 | AZ114: =AV114*E114 -> 0
A115: Ridges Clothes | B115: 261548725 | C115: fhd10 черный | E115: =SUM(F115:J115) -> 1 | H115: 0 | I115: 1 | K115: 205 | L115: =E115*K115 -> 205 | Q115: =N115/32 -> 0 | R115: =U115/32 -> 0 | U115: =S115+T115 -> 0 | X115: =V115+W115 -> 0 | AA115: =Y115+Z115 -> 0 | AB115: =N115*O115*P115/100 -> 0 | AC115: =AA115/$AA$121 -> #DIV/0! | AD115: =U115*K115 -> 0 | AF115: =IF(AA115=0,0,AE115/AA115) -> 0 | AL115: =IFERROR($AL$121*H115/$H$121,0) -> 0 | AN115: =X115*5.71% -> 0 | AO115: =AA115-AD115-AE115-AG115-AH115-AI115-AK115-AL115-AN115-AM115 -> 0 | AQ115: =IF(U115=0,0,AA115/U115) -> 0 | AR115: =K115 -> 205 | AS115: =IF(U115=0,0,AE115/U115) -> 0 | AT115: =IF(S115=0,AG115/1,AG115/S115) -> 0 | AU115: =IF(S115=0,0,(AH115+AI115+AJ115)/S115) -> 0 | AV115: {=_xlfn.IFS(U115=0,AO115,U115<0,AO115/-U115,U115>0,AO115/U115)} -> 0 | AW115: =IF(AQ115=0,0,AV115/AQ115) -> 0 | AX115: =IF(AR115=0,0,AV115/AR115) -> 0 | AZ115: =AV115*E115 -> 0
A116: Ridges Clothes | B116: 261549082 | C116: fhd10 хаки | E116: =SUM(F116:J116) -> 1 | H116: 0 | I116: 1 | K116: 205 | L116: =E116*K116 -> 205 | Q116: =N116/32 -> 0 | R116: =U116/32 -> 0 | U116: =S116+T116 -> 0 | X116: =V116+W116 -> 0 | AA116: =Y116+Z116 -> 0 | AB116: =N116*O116*P116/100 -> 0 | AC116: =AA116/$AA$121 -> #DIV/0! | AD116: =U116*K116 -> 0 | AF116: =IF(AA116=0,0,AE116/AA116) -> 0 | AL116: =IFERROR($AL$121*H116/$H$121,0) -> 0 | AN116: =X116*5.71% -> 0 | AO116: =AA116-AD116-AE116-AG116-AH116-AI116-AK116-AL116-AN116-AM116 -> 0 | AQ116: =IF(U116=0,0,AA116/U116) -> 0 | AR116: =K116 -> 205 | AS116: =IF(U116=0,0,AE116/U116) -> 0 | AT116: =IF(S116=0,AG116/1,AG116/S116) -> 0 | AU116: =IF(S116=0,0,(AH116+AI116+AJ116)/S116) -> 0 | AV116: {=_xlfn.IFS(U116=0,AO116,U116<0,AO116/-U116,U116>0,AO116/U116)} -> 0 | AW116: =IF(AQ116=0,0,AV116/AQ116) -> 0 | AX116: =IF(AR116=0,0,AV116/AR116) -> 0 | AZ116: =AV116*E116 -> 0
A117: Ridges Clothes | B117: 261561322 | C117: fhd12 светло-серый | E117: =SUM(F117:J117) -> 1 | H117: 0 | I117: 1 | K117: 453 | L117: =E117*K117 -> 453 | Q117: =N117/32 -> 0 | R117: =U117/32 -> 0 | U117: =S117+T117 -> 0 | X117: =V117+W117 -> 0 | AA117: =Y117+Z117 -> 0 | AB117: =N117*O117*P117/100 -> 0 | AC117: =AA117/$AA$121 -> #DIV/0! | AD117: =U117*K117 -> 0 | AF117: =IF(AA117=0,0,AE117/AA117) -> 0 | AL117: =IFERROR($AL$121*H117/$H$121,0) -> 0 | AN117: =X117*5.71% -> 0 | AO117: =AA117-AD117-AE117-AG117-AH117-AI117-AK117-AL117-AN117-AM117 -> 0 | AQ117: =IF(U117=0,0,AA117/U117) -> 0 | AR117: =K117 -> 453 | AS117: =IF(U117=0,0,AE117/U117) -> 0 | AT117: =IF(S117=0,AG117/1,AG117/S117) -> 0 | AU117: =IF(S117=0,0,(AH117+AI117+AJ117)/S117) -> 0 | AV117: {=_xlfn.IFS(U117=0,AO117,U117<0,AO117/-U117,U117>0,AO117/U117)} -> 0 | AW117: =IF(AQ117=0,0,AV117/AQ117) -> 0 | AX117: =IF(AR117=0,0,AV117/AR117) -> 0 | AZ117: =AV117*E117 -> 0
AQ118: =AVERAGE(AQ110:AQ117) -> 0 | AR118: =AVERAGE(AR110:AR117) -> 227.125 | AS118: =AVERAGE(AS110:AS117) -> 0 | AT118: =AVERAGE(AT110:AT117) -> 0 | AU118: =AVERAGE(AU110:AU117) -> 0 | AV118: =AVERAGE(AV110:AV117) -> 0 | AW118: =AVERAGE(AW110:AW117) -> 0 | AX118: =AVERAGE(AX110:AX117) -> 0
A119: Итого шапки | E119: =SUM(E110:E117) -> 14 | F119: =SUM(F110:F117) -> 0 | G119: =SUM(G110:G117) -> 0 | H119: =SUM(H110:H117) -> 0 | I119: =SUM(I110:I117) -> 8 | J119: =SUM(J110:J117) -> 6 | L119: =SUM(L110:L117) -> 3057 | N119: =SUM(N110:N117) -> 0 | S119: =SUM(S110:S117) -> 0 | T119: =SUM(T110:T117) -> 0 | U119: =SUM(U110:U117) -> 0 | V119: =SUM(V110:V117) -> 0 | W119: =SUM(W110:W117) -> 0 | X119: =SUM(X110:X117) -> 0 | Y119: =SUM(Y110:Y117) -> 0 | Z119: =SUM(Z110:Z117) -> 0 | ... AE119: =SUM(AE110:AE117) -> 0 | AF119: =AE119/AA119 -> #DIV/0! | AG119: =SUM(AG110:AG117) -> 0 | AH119: =SUM(AH110:AH117) -> 0 | AI119: =SUM(AI110:AI117) -> 0 | AJ119: =SUM(AJ110:AJ117) -> 0 | AK119: =SUM(AK110:AK117) -> 0 | AL119: =SUM(AL110:AL117) -> 0 | AM119: =SUM(AM110:AM117) -> 0 | AN119: =SUM(AN110:AN117) -> 0 | AO119: =SUM(AO110:AO117) -> 0 | AU119: =(AH119+AI119+AJ119)/S119 -> #DIV/0! | AZ119: =SUM(AZ110:AZ117) -> 0
A121: ИТОГО | E121: =E100+E108+E119 -> 21 | F121: =F100+F108+F119 -> 0 | G121: =G100+G108+G119 -> 0 | H121: =H100+H108+H119 -> 1 | I121: =I100+I108+I119 -> 8 | J121: =J100+J108+J119 -> 12 | K121: =K100+K108+K119 -> 0 | L121: =L100+L108+L119 -> 6961.26 | ... AE121: =AE100+AE108+AE119 -> 0 | AF121: =AE121/AA121 -> #DIV/0! | AG121: =AG100+AG108+AG119 -> 0 | AH121: =AH100+AH108+AH119 -> 0 | AI121: =AI100+AI108+AI119 -> 0 | AJ121: =AJ100+AJ108+AJ119 -> 0 | AK121: =AK100+AK108+AK119 -> 0 | AM121: =AM100+AM108+AM119 -> 0 | AN121: =AN100+AN108+AN119 -> 0 | AO121: =AO100+AO108+AO119 -> 0 | AU121: =(AH121+AI121)/S121 -> #DIV/0! | AZ121: =AZ100+AZ119 -> 0
AH122: =AH101+AH109+AH120 -> 0

Sheet Юнит 8
A1: 16-22.02_8 нед | F1: Отчет по остаткам 3,4,5 | I1: Мой склад | M1: Цены и скидки 6 | N1: Воронка продаж 20,54,36 | AJ1: Без учета в прибыли | AL1: Вставить в Итого | AQ1: на 1 единицу проданного товара
A2: Бренд | B2: SKU | C2: Артикул поставщика | D2: Предмет | E2: Остаток на | F2: В пути до клиента | G2: В пути от клиента | H2: Итого по складам ВБ | I2: Остаток на осн. складе | J2: Остаток на фф | K2: Себетоимость на 1 ед на 29.09.25 | L2: Себестоимость остатков | M2: Оборачива-емость, дн | N2: Заказы, шт 7 дней | O2: Средняя цена, руб | P2: % выкупа за 7 дней | Q2: Скорость заказов | R2: Скорость продаж | S2: Кол-во ПРОДАЖИ | T2: Кол-во ВОЗВРАТЫ | U2: Кол-во ПРОДАЖИ-ВОЗВРАТЫ | V2: Выручка ВБ ПРОДАЖИ | W2: Выручка ВБ ВОЗВРАТЫ | X2: Выручка с учетом СПП ПРОДАЖИ - ВОЗВРАТЫ | Y2: Выручка ПРОДАЖИ | Z2: Выручка ВОЗВРАТЫ | AA2: Выручка с учетом согласованной скидки ПРОДАЖИ - ВОЗВРАТЫ | AB2: Выручка потенциальная | AC2: Доля выручки, % от общего объема | AD2: Себестоимость продаж | AE2: Комиссия, руб | AF2: Комиссия, % | AG2: Логистика | AH2: Реклама БАЛАНС | AI2: Реклама СЧЕТ | AJ2: Реклама Промо бонусы | AK2: Блогеры | AL2: Хранение | AM2: Штрафы | AN2: Налог 1%+ НДС 5% | AO2: Прибыль | AQ2: Выручка на 1 ед (средняя цена продажи со скидкой) | AR2: Себестоимость на 1 ед | AS2: Комиссия на 1 ед | AT2: Логистика на 1 ед | AU2: Реклама на 1 ед | AV2: Прибыль на 1 ед | AW2: Маржиналь-ность, % | AX2: Рентабель-ность, % | AZ2: Прибыль с остатков
A3: Ridges | B3: 170499929 | C3: черные с железкой классика | D3: Солнцезащитные очки | E3: =SUM(F3:J3) -> 4341 | F3: 118 | G3: 35 | H3: 827 | I3: 1 | J3: 3360 | K3: 142.98 | L3: =E3*K3 -> 620676.18 | M3: 76 | N3: 162 | O3: 1410 | P3: 61 | Q3: =N3/7 -> 23.142857 | R3: =U3/7 -> 10.571429 | S3: 76 | T3: -2 | U3: =S3+T3 -> 74 | V3: 65330.49 | W3: -1522 | X3: =V3+W3 -> 63808.49 | Y3: 102856.38 | Z3: -2593 | AA3: =Y3+Z3 -> 100263.38 | AB3: =N3*O3*P3/100 -> 139336.2 | AC3: =AA3/$AA$126 -> 0.040850271 | AD3: =U3*K3 -> 10580.52 | AE3: 37573.13 | AF3: =IF(AA3=0,0,AE3/AA3) -> 0.3747443 | AG3: 9341.34 | AH3: 8002 | AI3: 37195 | AL3: =IFERROR($AL$126*H3/$H$126,0) -> 717.21315 | AM3: 0 | AN3: =X3*5.71% -> 3643.4648 | AO3: =AA3-AD3-AE3-AG3-AH3-AI3-AK3-AL3-AN3-AM3 -> -6789.2879 | AQ3: =IF(U3=0,0,AA3/U3) -> 1354.9105 | AR3: =K3 -> 142.98 | AS3: =IF(U3=0,0,AE3/U3) -> 507.745 | AT3: =IF(S3=0,AG3/1,AG3/S3) -> 122.91237 | AU3: =IF(S3=0,0,(AH3+AI3+AJ3)/S3) -> 594.69737 | AV3: =_xlfn.IFS(U3=0,AO3,U3<0,AO3/-U3,U3>0,AO3/U3) -> -91.747134 | AW3: =IF(AQ3=0,0,AV3/AQ3) -> -0.067714533 | AX3: =IF(AR3=0,0,AV3/AR3) -> -0.6416781 | AZ3: =AV3*E3 -> -398274.31
A4: Ridges | B4: 170500631 | C4: QS черные PZ | D4: Солнцезащитные очки | E4: =SUM(F4:J4) -> 7753 | F4: 549 | G4: 90 | H4: 733 | I4: 0 | J4: 6381 | K4: 123.09 | L4: =E4*K4 -> 954316.77 | M4: 7 | N4: 916 | O4: 1030 | P4: 74 | Q4: =N4/7 -> 130.85714 | R4: =U4/7 -> 79 | S4: 559 | T4: -6 | U4: =S4+T4 -> 553 | V4: 349412.49 | W4: -3386.63 | X4: =V4+W4 -> 346025.86 | Y4: 533455.73 | Z4: -5176.98 | AA4: =Y4+Z4 -> 528278.75 | AB4: =N4*O4*P4/100 -> 698175.2 | AC4: =AA4/$AA$126 -> 0.21523641 | AD4: =U4*K4 -> 68068.77 | AE4: 197906.79 | AF4: =IF(AA4=0,0,AE4/AA4) -> 0.37462569 | AG4: 50961.9 | AH4: 2628 | AI4: 713 | AL4: =IFERROR($AL$126*H4/$H$126,0) -> 635.69195 | AM4: 20 | AN4: =X4*5.71% -> 19758.077 | AO4: =AA4-AD4-AE4-AG4-AH4-AI4-AK4-AL4-AN4-AM4 -> 187586.52 | AQ4: =IF(U4=0,0,AA4/U4) -> 955.29611 | AR4: =K4 -> 123.09 | AS4: =IF(U4=0,0,AE4/U4) -> 357.87846 | AT4: =IF(S4=0,AG4/1,AG4/S4) -> 91.16619 | AU4: =IF(S4=0,0,(AH4+AI4+AJ4)/S4) -> 5.9767442 | AV4: {=_xlfn.IFS(U4=0,AO4,U4<0,AO4/-U4,U4>0,AO4/U4)} -> 339.21613 | AW4: =IF(AQ4=0,0,AV4/AQ4) -> 0.35509004 | AX4: =IF(AR4=0,0,AV4/AR4) -> 2.7558383 | AZ4: =AV4*E4 -> 2629942.7
A5: Ridges | B5: 170500399 | C5: QS синие PZ | D5: Солнцезащитные очки | E5: =SUM(F5:J5) -> 5573 | F5: 145 | G5: 29 | H5: 505 | I5: 0 | J5: 4894 | K5: 123.09 | L5: =E5*K5 -> 685980.57 | M5: 38 | N5: 215 | O5: 1133 | P5: 70 | Q5: =N5/7 -> 30.714286 | R5: =U5/7 -> 21.571429 | S5: 151 | T5: 0 | U5: =S5+T5 -> 151 | V5: 102977.46 | W5: 0 | X5: =V5+W5 -> 102977.46 | Y5: 163663.61 | Z5: 0 | AA5: =Y5+Z5 -> 163663.61 | AB5: =N5*O5*P5/100 -> 170516.5 | AC5: =AA5/$AA$126 -> 0.066681403 | AD5: =U5*K5 -> 18586.59 | AE5: 61148.34 | AF5: =IF(AA5=0,0,AE5/AA5) -> 0.37362209 | AG5: 13912.51 | AH5: 1962 | AI5: 20504 | AL5: =IFERROR($AL$126*H5/$H$126,0) -> 437.95966 | AM5: 0 | AN5: =X5*5.71% -> 5880.013 | AO5: =AA5-AD5-AE5-AG5-AH5-AI5-AK5-AL5-AN5-AM5 -> 41232.197 | AQ5: =IF(U5=0,0,AA5/U5) -> 1083.865 | AR5: =K5 -> 123.09 | AS5: =IF(U5=0,0,AE5/U5) -> 404.95589 | AT5: =IF(S5=0,AG5/1,AG5/S5) -> 92.135828 | AU5: =IF(S5=0,0,(AH5+AI5+AJ5)/S5) -> 148.78146 | AV5: {=_xlfn.IFS(U5=0,AO5,U5<0,AO5/-U5,U5>0,AO5/U5)} -> 273.06091 | AW5: =IF(AQ5=0,0,AV5/AQ5) -> 0.25193259 | AX5: =IF(AR5=0,0,AV5/AR5) -> 2.2183842 | AZ5: =AV5*E5 -> 1521768.4
A6: Ridges | B6: 170500725 | C6: QS желтые PZ | D6: Солнцезащитные очки | E6: =SUM(F6:J6) -> 589 | F6: 119 | G6: 25 | H6: 304 | I6: 0 | J6: 141 | K6: 123.09 | L6: =E6*K6 -> 72500.01 | M6: 28 | N6: 173 | O6: 1041 | P6: 79 | Q6: =N6/7 -> 24.714286 | R6: =U6/7 -> 18 | S6: 129 | T6: -3 | U6: =S6+T6 -> 126 | V6: 83166.16 | W6: -1926 | X6: =V6+W6 -> 81240.16 | Y6: 128564.21 | Z6: -2998 | AA6: =Y6+Z6 -> 125566.21 | AB6: =N6*O6*P6/100 -> 142273.47 | AC6: =AA6/$AA$126 -> 0.051159394 | AD6: =U6*K6 -> 15509.34 | AE6: 46929.66 | AF6: =IF(AA6=0,0,AE6/AA6) -> 0.37374434 | AG6: 11100.73 | AH6: 1985 | AI6: 9437 | AL6: =IFERROR($AL$126*H6/$H$126,0) -> 263.64304 | AM6: 0 | AN6: =X6*5.71% -> 4638.8131 | AO6: =AA6-AD6-AE6-AG6-AH6-AI6-AK6-AL6-AN6-AM6 -> 35702.024 | AQ6: =IF(U6=0,0,AA6/U6) -> 996.55722 | AR6: =K6 -> 123.09 | AS6: =IF(U6=0,0,AE6/U6) -> 372.45762 | AT6: =IF(S6=0,AG6/1,AG6/S6) -> 86.052171 | AU6: =IF(S6=0,0,(AH6+AI6+AJ6)/S6) -> 88.542636 | AV6: {=_xlfn.IFS(U6=0,AO6,U6<0,AO6/-U6,U6>0,AO6/U6)} -> 283.3494 | AW6: =IF(AQ6=0,0,AV6/AQ6) -> 0.28432827 | AX6: =IF(AR6=0,0,AV6/AR6) -> 2.3019693 | AZ6: =AV6*E6 -> 166892.79
A7: Ridges | B7: 246275459 | C7: QS коричневые PZ | D7: Солнцезащитные очки | E7: =SUM(F7:J7) -> 5130 | F7: 201 | G7: 41 | H7: 268 | I7: 3 | J7: 4617 | K7: 117.24 | L7: =E7*K7 -> 601441.2 | M7: 13 | N7: 337 | O7: 1206 | P7: 74 | Q7: =N7/7 -> 48.142857 | R7: =U7/7 -> 29.428571 | S7: 208 | T7: -2 | U7: =S7+T7 -> 206 | V7: 145513.38 | W7: -1222 | X7: =V7+W7 -> 144291.38 | Y7: 231388.08 | Z7: -2032.59 | AA7: =Y7+Z7 -> 229355.49 | AB7: =N7*O7*P7/100 -> 300752.28 | AC7: =AA7/$AA$126 -> 0.093446221 | AD7: =U7*K7 -> 24151.44 | AE7: 84938.3 | AF7: =IF(AA7=0,0,AE7/AA7) -> 0.37033471 | AG7: 18514.78 | AH7: 1931 | AI7: 24176 | AL7: =IFERROR($AL$126*H7/$H$126,0) -> 232.42216 | AM7: 0 | AN7: =X7*5.71% -> 8239.0378 | AO7: =AA7-AD7-AE7-AG7-AH7-AI7-AK7-AL7-AN7-AM7 -> 67172.51 | AQ7: =IF(U7=0,0,AA7/U7) -> 1113.3762 | AR7: =K7 -> 117.24 | AS7: =IF(U7=0,0,AE7/U7) -> 412.32184 | AT7: =IF(S7=0,AG7/1,AG7/S7) -> 89.013365 | AU7: =IF(S7=0,0,(AH7+AI7+AJ7)/S7) -> 125.51442 | AV7: {=_xlfn.IFS(U7=0,AO7,U7<0,AO7/-U7,U7>0,AO7/U7)} -> 326.08015 | AW7: =IF(AQ7=0,0,AV7/AQ7) -> 0.29287509 | AX7: =IF(AR7=0,0,AV7/AR7) -> 2.7813046 | AZ7: =AV7*E7 -> 1672791.1
A8: Ridges | B8: 159900625 | C8: MR8854 C2 Жен | D8: Солнцезащитные очки | E8: =SUM(F8:J8) -> 470 | F8: 109 | G8: 32 | H8: 329 | I8: 0 | J8: 0 | K8: 169.89 | L8: =E8*K8 -> 79848.3 | M8: 38 | N8: 140 | O8: 1371 | P8: 52 | Q8: =N8/7 -> 20 | R8: =U8/7 -> 9.7142857 | S8: 69 | T8: -1 | U8: =S8+T8 -> 68 | V8: 57136.18 | W8: -812 | X8: =V8+W8 -> 56324.18 | Y8: 90536.1 | Z8: -1325 | AA8: =Y8+Z8 -> 89211.1 | AB8: =N8*O8*P8/100 -> 99808.8 | AC8: =AA8/$AA$126 -> 0.036347245 | AD8: =U8*K8 -> 11552.52 | AE8: 33354.78 | AF8: =IF(AA8=0,0,AE8/AA8) -> 0.37388599 | AG8: 9999.34 | AH8: 3721 | AI8: 11574 | AL8: =IFERROR($AL$126*H8/$H$126,0) -> 285.32422 | AM8: 0 | AN8: =X8*5.71% -> 3216.1107 | AO8: =AA8-AD8-AE8-AG8-AH8-AI8-AK8-AL8-AN8-AM8 -> 15508.025 | AQ8: =IF(U8=0,0,AA8/U8) -> 1311.9279 | AR8: =K8 -> 169.89 | AS8: =IF(U8=0,0,AE8/U8) -> 490.51147 | AT8: =IF(S8=0,AG8/1,AG8/S8) -> 144.91797 | AU8: =IF(S8=0,0,(AH8+AI8+AJ8)/S8) -> 221.66667 | AV8: {=_xlfn.IFS(U8=0,AO8,U8<0,AO8/-U8,U8>0,AO8/U8)} -> 228.05919 | AW8: =IF(AQ8=0,0,AV8/AQ8) -> 0.17383515 | AX8: =IF(AR8=0,0,AV8/AR8) -> 1.3423933 | AZ8: =AV8*E8 -> 107187.82
A9: Ridges | B9: 251467353 | C9: th черн | D9: Солнцезащитные очки | E9: =SUM(F9:J9) -> 11403 | F9: 207 | G9: 60 | H9: 459 | I9: 0 | J9: 10677 | K9: 123.09 | L9: =E9*K9 -> 1403595.3 | M9: 23 | N9: 321 | O9: 1429 | P9: 56 | Q9: =N9/7 -> 45.857143 | R9: =U9/7 -> 19.285714 | S9: 137 | T9: -2 | U9: =S9+T9 -> 135 | V9: 116367.83 | W9: -1693 | X9: =V9+W9 -> 114674.83 | Y9: 186033.16 | Z9: -2723 | AA9: =Y9+Z9 -> 183310.16 | AB9: =N9*O9*P9/100 -> 256877.04 | AC9: =AA9/$AA$126 -> 0.07468599 | AD9: =U9*K9 -> 16617.15 | AE9: 68729 | AF9: =IF(AA9=0,0,AE9/AA9) -> 0.37493285 | AG9: 19710.21 | AH9: 5213 | AI9: 24000 | AL9: =IFERROR($AL$126*H9/$H$126,0) -> 398.06631 | AM9: 10 | AN9: =X9*5.71% -> 6547.9328 | AO9: =AA9-AD9-AE9-AG9-AH9-AI9-AK9-AL9-AN9-AM9 -> 42084.801 | AQ9: =IF(U9=0,0,AA9/U9) -> 1357.853 | AR9: =K9 -> 123.09 | AS9: =IF(U9=0,0,AE9/U9) -> 509.1037 | AT9: =IF(S9=0,AG9/1,AG9/S9) -> 143.87015 | AU9: =IF(S9=0,0,(AH9+AI9+AJ9)/S9) -> 213.23358 | AV9: {=_xlfn.IFS(U9=0,AO9,U9<0,AO9/-U9,U9>0,AO9/U9)} -> 311.73927 | AW9: =IF(AQ9=0,0,AV9/AQ9) -> 0.22958248 | AX9: =IF(AR9=0,0,AV9/AR9) -> 2.5326124 | AZ9: =AV9*E9 -> 3554762.8
A10: Ridges | B10: 251467354 | C10: th син | D10: Солнцезащитные очки | E10: =SUM(F10:J10) -> 10110 | F10: 155 | G10: 32 | H10: 426 | I10: 0 | J10: 9497 | K10: 123.09 | L10: =E10*K10 -> 1244439.9 | M10: 18 | N10: 266 | O10: 1073 | P10: 77 | Q10: =N10/7 -> 38 | R10: =U10/7 -> 23.571429 | S10: 167 | T10: -2 | U10: =S10+T10 -> 165 | V10: 106430.21 | W10: -1175 | X10: =V10+W10 -> 105255.21 | Y10: 166081.43 | Z10: -1930.3 | AA10: =Y10+Z10 -> 164151.13 | AB10: =N10*O10*P10/100 -> 219771.86 | AC10: =AA10/$AA$126 -> 0.066880033 | AD10: =U10*K10 -> 20309.85 | AE10: 61590.9 | AF10: =IF(AA10=0,0,AE10/AA10) -> 0.3752085 | AG10: 16452.94 | AH10: 3974 | AI10: 19500 | AL10: =IFERROR($AL$126*H10/$H$126,0) -> 369.44716 | AM10: 0 | AN10: =X10*5.71% -> 6010.0725 | AO10: =AA10-AD10-AE10-AG10-AH10-AI10-AK10-AL10-AN10-AM10 -> 35943.92 | AQ10: =IF(U10=0,0,AA10/U10) -> 994.85533 | AR10: =K10 -> 123.09 | AS10: =IF(U10=0,0,AE10/U10) -> 373.27818 | AT10: =IF(S10=0,AG10/1,AG10/S10) -> 98.520599 | AU10: =IF(S10=0,0,(AH10+AI10+AJ10)/S10) -> 140.56287 | AV10: {=_xlfn.IFS(U10=0,AO10,U10<0,AO10/-U10,U10>0,AO10/U10)} -> 217.84194 | AW10: =IF(AQ10=0,0,AV10/AQ10) -> 0.21896846 | AX10: =IF(AR10=0,0,AV10/AR10) -> 1.7697777 | AZ10: =AV10*E10 -> 2202382
A11: Ridges | B11: 251467355 | C11: th желт | D11: Солнцезащитные очки | E11: =SUM(F11:J11) -> 2909 | F11: 64 | G11: 15 | H11: 468 | I11: 0 | J11: 2362 | K11: 123.09 | L11: =E11*K11 -> 358068.81 | M11: 77 | N11: 99 | O11: 1217 | P11: 53 | Q11: =N11/7 -> 14.142857 | R11: =U11/7 -> 6 | S11: 44 | T11: -2 | U11: =S11+T11 -> 42 | V11: 33417.96 | W11: -1461 | X11: =V11+W11 -> 31956.96 | Y11: 53524.98 | Z11: -2410 | AA11: =Y11+Z11 -> 51114.98 | AB11: =N11*O11*P11/100 -> 63855.99 | AC11: =AA11/$AA$126 -> 0.020825757 | AD11: =U11*K11 -> 5169.78 | AE11: 19142.39 | AF11: =IF(AA11=0,0,AE11/AA11) -> 0.37449667 | AG11: 5596.88 | AH11: 2306 | AI11: 4593 | AL11: =IFERROR($AL$126*H11/$H$126,0) -> 405.87153 | AM11: 0 | AN11: =X11*5.71% -> 1824.7424 | AO11: =AA11-AD11-AE11-AG11-AH11-AI11-AK11-AL11-AN11-AM11 -> 12076.316 | AQ11: =IF(U11=0,0,AA11/U11) -> 1217.0233 | AR11: =K11 -> 123.09 | AS11: =IF(U11=0,0,AE11/U11) -> 455.77119 | AT11: =IF(S11=0,AG11/1,AG11/S11) -> 127.20182 | AU11: =IF(S11=0,0,(AH11+AI11+AJ11)/S11) -> 156.79545 | AV11: {=_xlfn.IFS(U11=0,AO11,U11<0,AO11/-U11,U11>0,AO11/U11)} -> 287.53133 | AW11: =IF(AQ11=0,0,AV11/AQ11) -> 0.23625787 | AX11: =IF(AR11=0,0,AV11/AR11) -> 2.3359439 | AZ11: =AV11*E11 -> 836428.65
A12: Ridges | B12: 303941289 | C12: th коричн | D12: Солнцезащитные очки | E12: =SUM(F12:J12) -> 3312 | F12: 117 | G12: 36 | H12: 472 | I12: 1 | J12: 2686 | K12: 117.24 | L12: =E12*K12 -> 388298.88 | M12: 55 | N12: 173 | O12: 1246 | P12: 53 | Q12: =N12/7 -> 24.714286 | R12: =U12/7 -> 9.7142857 | S12: 68 | T12: 0 | U12: =S12+T12 -> 68 | V12: 51141.8 | W12: 0 | X12: =V12+W12 -> 51141.8 | Y12: 81407.71 | Z12: 0 | AA12: =Y12+Z12 -> 81407.71 | AB12: =N12*O12*P12/100 -> 114245.74 | AC12: =AA12/$AA$126 -> 0.033167913 | AD12: =U12*K12 -> 7972.32 | AE12: 30453.93 | AF12: =IF(AA12=0,0,AE12/AA12) -> 0.37409147 | AG12: 9992.06 | AH12: 874 | AI12: 11863 | AL12: =IFERROR($AL$126*H12/$H$126,0) -> 409.34052 | AM12: 0 | AN12: =X12*5.71% -> 2920.1968 | AO12: =AA12-AD12-AE12-AG12-AH12-AI12-AK12-AL12-AN12-AM12 -> 16922.863 | AQ12: =IF(U12=0,0,AA12/U12) -> 1197.1722 | AR12: =K12 -> 117.24 | AS12: =IF(U12=0,0,AE12/U12) -> 447.85191 | AT12: =IF(S12=0,AG12/1,AG12/S12) -> 146.94206 | AU12: =IF(S12=0,0,(AH12+AI12+AJ12)/S12) -> 187.30882 | AV12: {=_xlfn.IFS(U12=0,AO12,U12<0,AO12/-U12,U12>0,AO12/U12)} -> 248.86563 | AW12: =IF(AQ12=0,0,AV12/AQ12) -> 0.20787789 | AX12: =IF(AR12=0,0,AV12/AR12) -> 2.1227024 | AZ12: =AV12*E12 -> 824242.96
A13: Ridges | B13: 274218038 | C13: flip черные | D13: Солнцезащитные очки | E13: =SUM(F13:J13) -> 4261 | F13: 158 | G13: 34 | H13: 433 | I13: 1 | J13: 3635 | K13: 123.09 | L13: =E13*K13 -> 524486.49 | M13: 53 | N13: 242 | O13: 1408 | P13: 55 | Q13: =N13/7 -> 34.571429 | R13: =U13/7 -> 13.142857 | S13: 94 | T13: -2 | U13: =S13+T13 -> 92 | V13: 79996.49 | W13: -1679 | X13: =V13+W13 -> 78317.49 | Y13: 127841.48 | Z13: -2714.31 | AA13: =Y13+Z13 -> 125127.17 | AB13: =N13*O13*P13/100 -> 187404.8 | AC13: =AA13/$AA$126 -> 0.050980516 | AD13: =U13*K13 -> 11324.28 | AE13: 47004.43 | AF13: =IF(AA13=0,0,AE13/AA13) -> 0.37565327 | AG13: 12428.02 | AH13: 5000 | AI13: 22289 | AL13: =IFERROR($AL$126*H13/$H$126,0) -> 375.51789 | AM13: 0 | AN13: =X13*5.71% -> 4471.9287 | AO13: =AA13-AD13-AE13-AG13-AH13-AI13-AK13-AL13-AN13-AM13 -> 22233.993 | AQ13: =IF(U13=0,0,AA13/U13) -> 1360.0779 | AR13: =K13 -> 123.09 | AS13: =IF(U13=0,0,AE13/U13) -> 510.91772 | AT13: =IF(S13=0,AG13/1,AG13/S13) -> 132.21298 | AU13: =IF(S13=0,0,(AH13+AI13+AJ13)/S13) -> 290.30851 | AV13: {=_xlfn.IFS(U13=0,AO13,U13<0,AO13/-U13,U13>0,AO13/U13)} -> 241.67384 | AW13: =IF(AQ13=0,0,AV13/AQ13) -> 0.17769117 | AX13: =IF(AR13=0,0,AV13/AR13) -> 1.9633914 | AZ13: =AV13*E13 -> 1029772.2
A14: Ridges | B14: 274219203 | C14: flip синие | D14: Солнцезащитные очки | E14: =SUM(F14:J14) -> 3029 | F14: 40 | G14: 12 | H14: 471 | I14: 2 | J14: 2504 | K14: 123.09 | L14: =E14*K14 -> 372839.61 | M14: 106 | N14: 69 | O14: 1075 | P14: 79 | Q14: =N14/7 -> 9.8571429 | R14: =U14/7 -> 4.8571429 | S14: 34 | T14: 0 | U14: =S14+T14 -> 34 | V14: 22521.78 | W14: 0 | X14: =V14+W14 -> 22521.78 | Y14: 35599.36 | Z14: 0 | AA14: =Y14+Z14 -> 35599.36 | AB14: =N14*O14*P14/100 -> 58598.25 | AC14: =AA14/$AA$126 -> 0.014504234 | AD14: =U14*K14 -> 4185.06 | AE14: 13399.24 | AF14: =IF(AA14=0,0,AE14/AA14) -> 0.37638991 | AG14: 3310.09 | AH14: 1236 | AI14: 2588 | AL14: =IFERROR($AL$126*H14/$H$126,0) -> 408.47327 | AM14: 0 | AN14: =X14*5.71% -> 1285.9936 | AO14: =AA14-AD14-AE14-AG14-AH14-AI14-AK14-AL14-AN14-AM14 -> 9186.5031 | AQ14: =IF(U14=0,0,AA14/U14) -> 1047.04 | AR14: =K14 -> 123.09 | AS14: =IF(U14=0,0,AE14/U14) -> 394.09529 | AT14: =IF(S14=0,AG14/1,AG14/S14) -> 97.355588 | AU14: =IF(S14=0,0,(AH14+AI14+AJ14)/S14) -> 112.47059 | AV14: {=_xlfn.IFS(U14=0,AO14,U14<0,AO14/-U14,U14>0,AO14/U14)} -> 270.19127 | AW14: =IF(AQ14=0,0,AV14/AQ14) -> 0.25805248 | AX14: =IF(AR14=0,0,AV14/AR14) -> 2.1950708 | AZ14: =AV14*E14 -> 818409.35
A15: Ridges | B15: 274190322 | C15: flip желтые | D15: Солнцезащитные очки | E15: =SUM(F15:J15) -> 1020 | F15: 20 | G15: 10 | H15: 571 | I15: 0 | J15: 419 | K15: 123.09 | L15: =E15*K15 -> 125551.8 | M15: 153 | N15: 44 | O15: 1041 | P15: 77 | Q15: =N15/7 -> 6.2857143 | R15: =U15/7 -> 4.5714286 | S15: 32 | T15: 0 | U15: =S15+T15 -> 32 | V15: 20722.46 | W15: 0 | X15: =V15+W15 -> 20722.46 | Y15: 32094.22 | Z15: 0 | AA15: =Y15+Z15 -> 32094.22 | AB15: =N15*O15*P15/100 -> 35269.08 | AC15: =AA15/$AA$126 -> 0.013076136 | AD15: =U15*K15 -> 3938.88 | AE15: 12018.51 | AF15: =IF(AA15=0,0,AE15/AA15) -> 0.37447584 | AG15: 3792.18 | AH15: 933 | AI15: 2901 | AL15: =IFERROR($AL$126*H15/$H$126,0) -> 495.19796 | AM15: 0 | AN15: =X15*5.71% -> 1183.2525 | AO15: =AA15-AD15-AE15-AG15-AH15-AI15-AK15-AL15-AN15-AM15 -> 6832.1996 | AQ15: =IF(U15=0,0,AA15/U15) -> 1002.9444 | AR15: =K15 -> 123.09 | AS15: =IF(U15=0,0,AE15/U15) -> 375.57844 | AT15: =IF(S15=0,AG15/1,AG15/S15) -> 118.50563 | AU15: =IF(S15=0,0,(AH15+AI15+AJ15)/S15) -> 119.8125 | AV15: {=_xlfn.IFS(U15=0,AO15,U15<0,AO15/-U15,U15>0,AO15/U15)} -> 213.50624 | AW15: =IF(AQ15=0,0,AV15/AQ15) -> 0.21287944 | AX15: =IF(AR15=0,0,AV15/AR15) -> 1.7345539 | AZ15: =AV15*E15 -> 217776.36
... A18: Ridges | B18: 276815909 | C18: wwl8032 хром металл | D18: Солнцезащитные очки | E18: =SUM(F18:J18) -> 2151 | F18: 77 | G18: 22 | H18: 201 | I18: 2 | J18: 1849 | K18: 123.09 | L18: =E18*K18 -> 264766.59 | M18: 49 | N18: 126 | O18: 1336 | P18: 47 | Q18: =N18/7 -> 18 | R18: =U18/7 -> 5.8571429 | S18: 45 | T18: -4 | U18: =S18+T18 -> 41 | V18: 35555.57 | W18: -3157 | X18: =V18+W18 -> 32398.57 | Y18: 57216.55 | Z18: -5162 | AA18: =Y18+Z18 -> 52054.55 | AB18: =N18*O18*P18/100 -> 79117.92 | AC18: =AA18/$AA$126 -> 0.021208566 | AD18: =U18*K18 -> 5046.69 | AE18: 19524.51 | AF18: =IF(AA18=0,0,AE18/AA18) -> 0.37507788 | AG18: 6757.08 | AH18: 1382 | AI18: 9972 | AL18: =IFERROR($AL$126*H18/$H$126,0) -> 174.31662 | AM18: 0 | AN18: =X18*5.71% -> 1849.9583 | AO18: =AA18-AD18-AE18-AG18-AH18-AI18-AK18-AL18-AN18-AM18 -> 7347.995 | AQ18: =IF(U18=0,0,AA18/U18) -> 1269.6232 | AR18: =K18 -> 123.09 | AS18: =IF(U18=0,0,AE18/U18) -> 476.20756 | AT18: =IF(S18=0,AG18/1,AG18/S18) -> 150.15733 | AU18: =IF(S18=0,0,(AH18+AI18+AJ18)/S18) -> 252.31111 | AV18: {=_xlfn.IFS(U18=0,AO18,U18<0,AO18/-U18,U18>0,AO18/U18)} -> 179.21939 | AW18: =IF(AQ18=0,0,AV18/AQ18) -> 0.14115952 | AX18: =IF(AR18=0,0,AV18/AR18) -> 1.4560029 | AZ18: =AV18*E18 -> 385500.91
A19: Ridges | B19: 276817565 | C19: wwl8032 черные серебро | D19: Солнцезащитные очки | E19: =SUM(F19:J19) -> 1 | F19: 0 | G19: 0 | H19: 0 | I19: 1 | J19: 0 | K19: 123.09 | L19: =E19*K19 -> 123.09 | M19: 0 | N19: 0 | O19: 0 | P19: 0 | Q19: =N19/7 -> 0 | R19: =U19/7 -> 0 | S19: 0 | T19: 0 | U19: =S19+T19 -> 0 | V19: 0 | W19: 0 | X19: =V19+W19 -> 0 | Y19: 0 | Z19: 0 | AA19: =Y19+Z19 -> 0 | AB19: =N19*O19*P19/100 -> 0 | AC19: =AA19/$AA$126 -> 0 | AD19: =U19*K19 -> 0 | AE19: 0 | AF19: =IF(AA19=0,0,AE19/AA19) -> 0 | AG19: 0 | AL19: =IFERROR($AL$126*H19/$H$126,0) -> 0 | AM19: 0 | AN19: =X19*5.71% -> 0 | AO19: =AA19-AD19-AE19-AG19-AH19-AI19-AK19-AL19-AN19-AM19 -> 0 | AQ19: =IF(U19=0,0,AA19/U19) -> 0 | AR19: =K19 -> 123.09 | AS19: =IF(U19=0,0,AE19/U19) -> 0 | AT19: =IF(S19=0,AG19/1,AG19/S19) -> 0 | AU19: =IF(S19=0,0,(AH19+AI19+AJ19)/S19) -> 0 | AV19: {=_xlfn.IFS(U19=0,AO19,U19<0,AO19/-U19,U19>0,AO19/U19)} -> 0 | AW19: =IF(AQ19=0,0,AV19/AQ19) -> 0 | AX19: =IF(AR19=0,0,AV19/AR19) -> 0 | AZ19: =AV19*E19 -> 0
A20: Ridges | B20: 335387679 | C20: sports синие | D20: Солнцезащитные очки | E20: =SUM(F20:J20) -> 321 | F20: 0 | G20: 0 | H20: 0 | I20: 1 | J20: 320 | K20: 117.24 | L20: =E20*K20 -> 37634.04 | M20: 1 | N20: 0 | O20: 0 | P20: 0 | Q20: =N20/7 -> 0 | R20: =U20/7 -> 0 | S20: 0 | T20: 0 | U20: =S20+T20 -> 0 | V20: 0 | W20: 0 | X20: =V20+W20 -> 0 | Y20: 0 | Z20: 0 | AA20: =Y20+Z20 -> 0 | AB20: =N20*O20*P20/100 -> 0 | AC20: =AA20/$AA$126 -> 0 | AD20: =U20*K20 -> 0 | AE20: 0 | AF20: =IF(AA20=0,0,AE20/AA20) -> 0 | AG20: 0 | AL20: =IFERROR($AL$126*H20/$H$126,0) -> 0 | AM20: 0 | AN20: =X20*5.71% -> 0 | AO20: =AA20-AD20-AE20-AG20-AH20-AI20-AK20-AL20-AN20-AM20 -> 0 | AQ20: =IF(U20=0,0,AA20/U20) -> 0 | AR20: =K20 -> 117.24 | AS20: =IF(U20=0,0,AE20/U20) -> 0 | AT20: =IF(S20=0,AG20/1,AG20/S20) -> 0 | AU20: =IF(S20=0,0,(AH20+AI20+AJ20)/S20) -> 0 | AV20: {=_xlfn.IFS(U20=0,AO20,U20<0,AO20/-U20,U20>0,AO20/U20)} -> 0 | AW20: =IF(AQ20=0,0,AV20/AQ20) -> 0 | AX20: =IF(AR20=0,0,AV20/AR20) -> 0 | AZ20: =AV20*E20 -> 0
A21: Ridges | B21: 335388183 | C21: sports зеленые | D21: Солнцезащитные очки | E21: =SUM(F21:J21) -> 322 | H21: 1 | I21: 1 | J21: 320 | K21: 117.24 | L21: =E21*K21 -> 37751.28 | M21: 999 | N21: 0 | O21: 0 | P21: 0 | Q21: =N21/7 -> 0 | R21: =U21/7 -> 0 | S21: 0 | T21: 0 | U21: =S21+T21 -> 0 | V21: 0 | W21: 0 | X21: =V21+W21 -> 0 | Y21: 0 | Z21: 0 | AA21: =Y21+Z21 -> 0 | AB21: =N21*O21*P21/100 -> 0 | AC21: =AA21/$AA$126 -> 0 | AD21: =U21*K21 -> 0 | AE21: 0 | AF21: =IF(AA21=0,0,AE21/AA21) -> 0 | AG21: 0 | AL21: =IFERROR($AL$126*H21/$H$126,0) -> 0.86724686 | AM21: 0 | AN21: =X21*5.71% -> 0 | AO21: =AA21-AD21-AE21-AG21-AH21-AI21-AK21-AL21-AN21-AM21 -> -0.86724686 | AQ21: =IF(U21=0,0,AA21/U21) -> 0 | AR21: =K21 -> 117.24 | AS21: =IF(U21=0,0,AE21/U21) -> 0 | AT21: =IF(S21=0,AG21/1,AG21/S21) -> 0 | AU21: =IF(S21=0,0,(AH21+AI21+AJ21)/S21) -> 0 | AV21: {=_xlfn.IFS(U21=0,AO21,U21<0,AO21/-U21,U21>0,AO21/U21)} -> -0.86724686 | AW21: =IF(AQ21=0,0,AV21/AQ21) -> 0 | AX21: =IF(AR21=0,0,AV21/AR21) -> -0.0073971926 | AZ21: =AV21*E21 -> -279.25349
A22: Ridges | B22: 335388404 | C22: sports красные | D22: Солнцезащитные очки | E22: =SUM(F22:J22) -> 322 | H22: 1 | I22: 1 | J22: 320 | K22: 117.24 | L22: =E22*K22 -> 37751.28 | M22: 19 | N22: 0 | O22: 0 | P22: 0 | Q22: =N22/7 -> 0 | R22: =U22/7 -> 0.14285714 | S22: 1 | T22: 0 | U22: =S22+T22 -> 1 | V22: 538 | W22: 0 | X22: =V22+W22 -> 538 | Y22: 838 | Z22: 0 | AA22: =Y22+Z22 -> 838 | AB22: =N22*O22*P22/100 -> 0 | AC22: =AA22/$AA$126 -> 0.00034142603 | AD22: =U22*K22 -> 117.24 | AE22: 312.88 | AF22: =IF(AA22=0,0,AE22/AA22) -> 0.37336516 | AG22: 57.11 | AL22: =IFERROR($AL$126*H22/$H$126,0) -> 0.86724686 | AM22: 0 | AN22: =X22*5.71% -> 30.7198 | AO22: =AA22-AD22-AE22-AG22-AH22-AI22-AK22-AL22-AN22-AM22 -> 319.18295 | AQ22: =IF(U22=0,0,AA22/U22) -> 838 | AR22: =K22 -> 117.24 | AS22: =IF(U22=0,0,AE22/U22) -> 312.88 | AT22: =IF(S22=0,AG22/1,AG22/S22) -> 57.11 | AU22: =IF(S22=0,0,(AH22+AI22+AJ22)/S22) -> 0 | AV22: {=_xlfn.IFS(U22=0,AO22,U22<0,AO22/-U22,U22>0,AO22/U22)} -> 319.18295 | AW22: =IF(AQ22=0,0,AV22/AQ22) -> 0.38088658 | AX22: =IF(AR22=0,0,AV22/AR22) -> 2.7224749 | AZ22: =AV22*E22 -> 102776.91
A23: Ridges | B23: 335389672 | C23: sportlife черные | D23: Солнцезащитные очки | E23: =SUM(F23:J23) -> 1 | F23: 0 | G23: 0 | H23: 0 | I23: 1 | J23: 0 | K23: 117.24 | L23: =E23*K23 -> 117.24 | M23: 999 | N23: 0 | O23: 0 | P23: 0 | Q23: =N23/7 -> 0 | R23: =U23/7 -> 0 | S23: 0 | T23: 0 | U23: =S23+T23 -> 0 | V23: 0 | W23: 0 | X23: =V23+W23 -> 0 | Y23: 0 | Z23: 0 | AA23: =Y23+Z23 -> 0 | AB23: =N23*O23*P23/100 -> 0 | AC23: =AA23/$AA$126 -> 0 | AD23: =U23*K23 -> 0 | AE23: 0 | AF23: =IF(AA23=0,0,AE23/AA23) -> 0 | AG23: 0 | AL23: =IFERROR($AL$126*H23/$H$126,0) -> 0 | AM23: 0 | AN23: =X23*5.71% -> 0 | AO23: =AA23-AD23-AE23-AG23-AH23-AI23-AK23-AL23-AN23-AM23 -> 0 | AQ23: =IF(U23=0,0,AA23/U23) -> 0 | AR23: =K23 -> 117.24 | AS23: =IF(U23=0,0,AE23/U23) -> 0 | AT23: =IF(S23=0,AG23/1,AG23/S23) -> 0 | AU23: =IF(S23=0,0,(AH23+AI23+AJ23)/S23) -> 0 | AV23: {=_xlfn.IFS(U23=0,AO23,U23<0,AO23/-U23,U23>0,AO23/U23)} -> 0 | AW23: =IF(AQ23=0,0,AV23/AQ23) -> 0 | AX23: =IF(AR23=0,0,AV23/AR23) -> 0 | AZ23: =AV23*E23 -> 0
A24: Ridges | B24: 335389846 | C24: sportlife синие | D24: Солнцезащитные очки | E24: =SUM(F24:J24) -> 2 | G24: 1 | I24: 1 | J24: 0 | K24: 117.24 | L24: =E24*K24 -> 234.48 | M24: 1 | N24: 0 | O24: 0 | P24: 0 | Q24: =N24/7 -> 0 | R24: =U24/7 -> 0 | S24: 0 | T24: 0 | U24: =S24+T24 -> 0 | V24: 0 | W24: 0 | X24: =V24+W24 -> 0 | Y24: 0 | Z24: 0 | AA24: =Y24+Z24 -> 0 | AB24: =N24*O24*P24/100 -> 0 | AC24: =AA24/$AA$126 -> 0 | AD24: =U24*K24 -> 0 | AE24: 0 | AF24: =IF(AA24=0,0,AE24/AA24) -> 0 | AG24: 0 | AL24: =IFERROR($AL$126*H24/$H$126,0) -> 0 | AM24: 0 | AN24: =X24*5.71% -> 0 | AO24: =AA24-AD24-AE24-AG24-AH24-AI24-AK24-AL24-AN24-AM24 -> 0 | AQ24: =IF(U24=0,0,AA24/U24) -> 0 | AR24: =K24 -> 117.24 | AS24: =IF(U24=0,0,AE24/U24) -> 0 | AT24: =IF(S24=0,AG24/1,AG24/S24) -> 0 | AU24: =IF(S24=0,0,(AH24+AI24+AJ24)/S24) -> 0 | AV24: {=_xlfn.IFS(U24=0,AO24,U24<0,AO24/-U24,U24>0,AO24/U24)} -> 0 | AW24: =IF(AQ24=0,0,AV24/AQ24) -> 0 | AX24: =IF(AR24=0,0,AV24/AR24) -> 0 | AZ24: =AV24*E24 -> 0
A25: Ridges | B25: 335390038 | C25: sportlife красные | D25: Солнцезащитные очки | E25: =SUM(F25:J25) -> 1 | F25: 0 | G25: 0 | H25: 0 | I25: 1 | J25: 0 | K25: 117.24 | L25: =E25*K25 -> 117.24 | M25: 9 | N25: 2 | O25: 918 | P25: 100 | Q25: =N25/7 -> 0.28571429 | R25: =U25/7 -> 0.28571429 | S25: 2 | T25: 0 | U25: =S25+T25 -> 2 | V25: 1239 | W25: 0 | X25: =V25+W25 -> 1239 | Y25: 1836 | Z25: 0 | AA25: =Y25+Z25 -> 1836 | AB25: =N25*O25*P25/100 -> 1836 | AC25: =AA25/$AA$126 -> 0.00074804079 | AD25: =U25*K25 -> 234.48 | AE25: 671.57 | AF25: =IF(AA25=0,0,AE25/AA25) -> 0.36577887 | AG25: 109.44 | AL25: =IFERROR($AL$126*H25/$H$126,0) -> 0 | AM25: 0 | AN25: =X25*5.71% -> 70.7469 | AO25: =AA25-AD25-AE25-AG25-AH25-AI25-AK25-AL25-AN25-AM25 -> 749.7631 | AQ25: =IF(U25=0,0,AA25/U25) -> 918 | AR25: =K25 -> 117.24 | AS25: =IF(U25=0,0,AE25/U25) -> 335.785 | AT25: =IF(S25=0,AG25/1,AG25/S25) -> 54.72 | AU25: =IF(S25=0,0,(AH25+AI25+AJ25)/S25) -> 0 | AV25: {=_xlfn.IFS(U25=0,AO25,U25<0,AO25/-U25,U25>0,AO25/U25)} -> 374.88155 | AW25: =IF(AQ25=0,0,AV25/AQ25) -> 0.4083677 | AX25: =IF(AR25=0,0,AV25/AR25) -> 3.1975567 | AZ25: =AV25*E25 -> 374.88155
A26: Ridges | B26: 207984026 | C26: sh1 | D26: Солнцезащитные очки | E26: =SUM(F26:J26) -> 851 | F26: 86 | G26: 30 | H26: 209 | I26: 526 | J26: 0 | K26: 123.09 | L26: =E26*K26 -> 104749.59 | M26: 51 | N26: 102 | O26: 699 | P26: 26 | Q26: =N26/7 -> 14.571429 | R26: =U26/7 -> 3.7142857 | S26: 27 | T26: -1 | U26: =S26+T26 -> 26 | V26: 12240.48 | W26: -476 | X26: =V26+W26 -> 11764.48 | Y26: 18873.14 | Z26: -699 | AA26: =Y26+Z26 -> 18174.14 | AB26: =N26*O26*P26/100 -> 18537.48 | AC26: =AA26/$AA$126 -> 0.0074046831 | AD26: =U26*K26 -> 3200.34 | AE26: 6802.4 | AF26: =IF(AA26=0,0,AE26/AA26) -> 0.37429006 | AG26: 8619.17 | AH26: 1175 | AI26: 5873 | AL26: =IFERROR($AL$126*H26/$H$126,0) -> 181.25459 | AM26: 10 | AN26: =X26*5.71% -> 671.75181 | AO26: =AA26-AD26-AE26-AG26-AH26-AI26-AK26-AL26-AN26-AM26 -> -8358.7764 | AQ26: =IF(U26=0,0,AA26/U26) -> 699.00538 | AR26: =K26 -> 123.09 | AS26: =IF(U26=0,0,AE26/U26) -> 261.63077 | AT26: =IF(S26=0,AG26/1,AG26/S26) -> 319.22852 | AU26: =IF(S26=0,0,(AH26+AI26+AJ26)/S26) -> 261.03704 | AV26: {=_xlfn.IFS(U26=0,AO26,U26<0,AO26/-U26,U26>0,AO26/U26)} -> -321.4914 | AW26: =IF(AQ26=0,0,AV26/AQ26) -> -0.45992693 | AX26: =IF(AR26=0,0,AV26/AR26) -> -2.6118401 | AZ26: =AV26*E26 -> -273589.18
A27: Ridges | B27: 207984027 | C27: sh2 | D27: Солнцезащитные очки | E27: =SUM(F27:J27) -> 378 | F27: 6 | G27: 4 | H27: 48 | I27: 320 | J27: 0 | K27: 181.59 | L27: =E27*K27 -> 68641.02 | M27: 68 | N27: 11 | O27: 478 | P27: 67 | Q27: =N27/7 -> 1.5714286 | R27: =U27/7 -> 0.85714286 | S27: 6 | T27: 0 | U27: =S27+T27 -> 6 | V27: 1749.91 | W27: 0 | X27: =V27+W27 -> 1749.91 | Y27: 2868.52 | Z27: 0 | AA27: =Y27+Z27 -> 2868.52 | AB27: =N27*O27*P27/100 -> 3522.86 | AC27: =AA27/$AA$126 -> 0.00116872 | AD27: =U27*K27 -> 1089.54 | AE27: 1067.62 | AF27: =IF(AA27=0,0,AE27/AA27) -> 0.37218496 | AG27: 1049.05 | AL27: =IFERROR($AL$126*H27/$H$126,0) -> 41.627849 | AM27: 0 | AN27: =X27*5.71% -> 99.919861 | AO27: =AA27-AD27-AE27-AG27-AH27-AI27-AK27-AL27-AN27-AM27 -> -479.23771 | AQ27: =IF(U27=0,0,AA27/U27) -> 478.08667 | AR27: =K27 -> 181.59 | AS27: =IF(U27=0,0,AE27/U27) -> 177.93667 | AT27: =IF(S27=0,AG27/1,AG27/S27) -> 174.84167 | AU27: =IF(S27=0,0,(AH27+AI27+AJ27)/S27) -> 0 | AV27: {=_xlfn.IFS(U27=0,AO27,U27<0,AO27/-U27,U27>0,AO27/U27)} -> -79.872952 | AW27: =IF(AQ27=0,0,AV27/AQ27) -> -0.16706793 | AX27: =IF(AR27=0,0,AV27/AR27) -> -0.43985325 | AZ27: =AV27*E27 -> -30191.976
A28: Ridges | B28: 207984028 | C28: sh3 | D28: Солнцезащитные очки | E28: =SUM(F28:J28) -> 1384 | F28: 173 | G28: 64 | H28: 492 | I28: 0 | J28: 655 | K28: 133.62 | L28: =E28*K28 -> 184930.08 | M28: 45 | N28: 236 | O28: 1196 | P28: 44 | Q28: =N28/7 -> 33.714286 | R28: =U28/7 -> 13.714286 | S28: 101 | T28: -5 | U28: =S28+T28 -> 96 | V28: 71392.75 | W28: -3481 | X28: =V28+W28 -> 67911.75 | Y28: 114776.56 | Z28: -5681 | AA28: =Y28+Z28 -> 109095.56 | AB28: =N28*O28*P28/100 -> 124192.64 | AC28: =AA28/$AA$126 -> 0.044448763 | AD28: =U28*K28 -> 12827.52 | AE28: 40744.49 | AF28: =IF(AA28=0,0,AE28/AA28) -> 0.37347524 | AG28: 16137.57 | AH28: 1802 | AI28: 12000 | AL28: =IFERROR($AL$126*H28/$H$126,0) -> 426.68545 | AM28: 50 | AN28: =X28*5.71% -> 3877.7609 | AO28: =AA28-AD28-AE28-AG28-AH28-AI28-AK28-AL28-AN28-AM28 -> 21229.534 | AQ28: =IF(U28=0,0,AA28/U28) -> 1136.4121 | AR28: =K28 -> 133.62 | AS28: =IF(U28=0,0,AE28/U28) -> 424.42177 | AT28: =IF(S28=0,AG28/1,AG28/S28) -> 159.77792 | AU28: =IF(S28=0,0,(AH28+AI28+AJ28)/S28) -> 136.65347 | AV28: =_xlfn.IFS(U28=0,AO28,U28<0,AO28/-U28,U28>0,AO28/U28) -> 221.14098 | AW28: =IF(AQ28=0,0,AV28/AQ28) -> 0.19459576 | AX28: =IF(AR28=0,0,AV28/AR28) -> 1.6549991 | AZ28: =AV28*E28 -> 306059.11
A29: Ridges | B29: 207984029 | C29: sh4 | D29: Солнцезащитные очки | E29: =SUM(F29:J29) -> 640 | F29: 0 | G29: 0 | H29: 0 | I29: 640 | J29: 0 | K29: 111.39 | L29: =E29*K29 -> 71289.6 | M29: 3 | N29: 1 | O29: 478 | P29: 100 | Q29: =N29/7 -> 0.14285714 | R29: =U29/7 -> 0.14285714 | S29: 1 | T29: 0 | U29: =S29+T29 -> 1 | V29: 287 | W29: 0 | X29: =V29+W29 -> 287 | Y29: 478 | Z29: 0 | AA29: =Y29+Z29 -> 478 | AB29: =N29*O29*P29/100 -> 478 | AC29: =AA29/$AA$126 -> 0.00019475136 | AD29: =U29*K29 -> 111.39 | AE29: 179.98 | AF29: =IF(AA29=0,0,AE29/AA29) -> 0.3765272 | AG29: 47.32 | AL29: =IFERROR($AL$126*H29/$H$126,0) -> 0 | AM29: 0 | AN29: =X29*5.71% -> 16.3877 | AO29: =AA29-AD29-AE29-AG29-AH29-AI29-AK29-AL29-AN29-AM29 -> 122.9223 | AQ29: =IF(U29=0,0,AA29/U29) -> 478 | AR29: =K29 -> 111.39 | AS29: =IF(U29=0,0,AE29/U29) -> 179.98 | AT29: =IF(S29=0,AG29/1,AG29/S29) -> 47.32 | AU29: =IF(S29=0,0,(AH29+AI29+AJ29)/S29) -> 0 | AV29: {=_xlfn.IFS(U29=0,AO29,U29<0,AO29/-U29,U29>0,AO29/U29)} -> 122.9223 | AW29: =IF(AQ29=0,0,AV29/AQ29) -> 0.25715962 | AX29: =IF(AR29=0,0,AV29/AR29) -> 1.1035308 | AZ29: =AV29*E29 -> 78670.272
A30: Ridges | B30: 233496972 | C30: sh06 | D30: Солнцезащитные очки | E30: =SUM(F30:J30) -> 1 | G30: 1 | I30: 0 | J30: 0 | K30: 111.39 | L30: =E30*K30 -> 111.39 | M30: 999 | N30: 1 | O30: 558 | P30: 0 | Q30: =N30/7 -> 0.14285714 | R30: =U30/7 -> 0.14285714 | S30: 1 | T30: 0 | U30: =S30+T30 -> 1 | V30: 384 | W30: 0 | X30: =V30+W30 -> 384 | Y30: 558 | Z30: 0 | AA30: =Y30+Z30 -> 558 | AB30: =N30*O30*P30/100 -> 0 | AC30: =AA30/$AA$126 -> 0.00022734573 | AD30: =U30*K30 -> 111.39 | AE30: 211.93 | AF30: =IF(AA30=0,0,AE30/AA30) -> 0.37980287 | AG30: 139.89 | AL30: =IFERROR($AL$126*H30/$H$126,0) -> 0 | AM30: 0 | AN30: =X30*5.71% -> 21.9264 | AO30: =AA30-AD30-AE30-AG30-AH30-AI30-AK30-AL30-AN30-AM30 -> 72.8636 | AQ30: =IF(U30=0,0,AA30/U30) -> 558 | AR30: =K30 -> 111.39 | AS30: =IF(U30=0,0,AE30/U30) -> 211.93 | AT30: =IF(S30=0,AG30/1,AG30/S30) -> 139.89 | AU30: =IF(S30=0,0,(AH30+AI30+AJ30)/S30) -> 0 | AV30: {=_xlfn.IFS(U30=0,AO30,U30<0,AO30/-U30,U30>0,AO30/U30)} -> 72.8636 | AW30: =IF(AQ30=0,0,AV30/AQ30) -> 0.13057993 | AX30: =IF(AR30=0,0,AV30/AR30) -> 0.65413053 | AZ30: =AV30*E30 -> 72.8636
A31: Ridges | B31: 233497520 | C31: sh07 | D31: Солнцезащитные очки | E31: =SUM(F31:J31) -> 0 | F31: 0 | G31: 0 | H31: 0 | I31: 0 | J31: 0 | K31: 105.54 | L31: =E31*K31 -> 0 | M31: 999 | N31: 1 | O31: 499 | P31: 100 | Q31: =N31/7 -> 0.14285714 | R31: =U31/7 -> 0.28571429 | S31: 2 | T31: 0 | U31: =S31+T31 -> 2 | V31: 593 | W31: 0 | X31: =V31+W31 -> 593 | Y31: 998 | Z31: 0 | AA31: =Y31+Z31 -> 998 | AB31: =N31*O31*P31/100 -> 499 | AC31: =AA31/$AA$126 -> 0.00040661477 | AD31: =U31*K31 -> 211.08 | AE31: 375.4 | AF31: =IF(AA31=0,0,AE31/AA31) -> 0.3761523 | AG31: 94.18 | AI31: 20 | AL31: =IFERROR($AL$126*H31/$H$126,0) -> 0 | AM31: 0 | AN31: =X31*5.71% -> 33.8603 | AO31: =AA31-AD31-AE31-AG31-AH31-AI31-AK31-AL31-AN31-AM31 -> 263.4797 | AQ31: =IF(U31=0,0,AA31/U31) -> 499 | AR31: =K31 -> 105.54 | AS31: =IF(U31=0,0,AE31/U31) -> 187.7 | AT31: =IF(S31=0,AG31/1,AG31/S31) -> 47.09 | AU31: =IF(S31=0,0,(AH31+AI31+AJ31)/S31) -> 10 | AV31: {=_xlfn.IFS(U31=0,AO31,U31<0,AO31/-U31,U31>0,AO31/U31)} -> 131.73985 | AW31: =IF(AQ31=0,0,AV31/AQ31) -> 0.26400772 | AX31: =IF(AR31=0,0,AV31/AR31) -> 1.2482457 | AZ31: =AV31*E31 -> 0
A32: Ridges | B32: 233498313 | C32: sh08 | D32: Солнцезащитные очки | E32: =SUM(F32:J32) -> 84 | F32: 0 | G32: 0 | H32: 0 | I32: 84 | J32: 0 | K32: 140.64 | L32: =E32*K32 -> 11813.76 | M32: 999 | N32: 0 | O32: 0 | P32: 0 | Q32: =N32/7 -> 0 | R32: =U32/7 -> 0 | S32: 0 | T32: 0 | U32: =S32+T32 -> 0 | V32: 0 | W32: 0 | X32: =V32+W32 -> 0 | Y32: 0 | Z32: 0 | AA32: =Y32+Z32 -> 0 | AB32: =N32*O32*P32/100 -> 0 | AC32: =AA32/$AA$126 -> 0 | AD32: =U32*K32 -> 0 | AE32: 0 | AF32: =IF(AA32=0,0,AE32/AA32) -> 0 | AG32: 0 | AL32: =IFERROR($AL$126*H32/$H$126,0) -> 0 | AM32: 0 | AN32: =X32*5.71% -> 0 | AO32: =AA32-AD32-AE32-AG32-AH32-AI32-AK32-AL32-AN32-AM32 -> 0 | AQ32: =IF(U32=0,0,AA32/U32) -> 0 | AR32: =K32 -> 140.64 | AS32: =IF(U32=0,0,AE32/U32) -> 0 | AT32: =IF(S32=0,AG32/1,AG32/S32) -> 0 | AU32: =IF(S32=0,0,(AH32+AI32+AJ32)/S32) -> 0 | AV32: {=_xlfn.IFS(U32=0,AO32,U32<0,AO32/-U32,U32>0,AO32/U32)} -> 0 | AW32: =IF(AQ32=0,0,AV32/AQ32) -> 0 | AX32: =IF(AR32=0,0,AV32/AR32) -> 0 | AZ32: =AV32*E32 -> 0
A33: Ridges | B33: 233499847 | C33: sh09 | D33: Солнцезащитные очки | E33: =SUM(F33:J33) -> 162 | F33: 3 | G33: 1 | H33: 138 | I33: 20 | J33: 0 | K33: 123.09 | L33: =E33*K33 -> 19940.58 | M33: 235 | N33: 6 | O33: 1388 | P33: 100 | Q33: =N33/7 -> 0.85714286 | R33: =U33/7 -> 1.1428571 | S33: 8 | T33: 0 | U33: =S33+T33 -> 8 | V33: 2032.63 | W33: 0 | X33: =V33+W33 -> 2032.63 | Y33: 3335.83 | Z33: 0 | AA33: =Y33+Z33 -> 3335.83 | AB33: =N33*O33*P33/100 -> 8328 | AC33: =AA33/$AA$126 -> 0.001359116 | AD33: =U33*K33 -> 984.72 | AE33: 1244.16 | AF33: =IF(AA33=0,0,AE33/AA33) -> 0.37296865 | AG33: 434.42 | AL33: =IFERROR($AL$126*H33/$H$126,0) -> 119.68007 | AM33: 0 | AN33: =X33*5.71% -> 116.06317 | AO33: =AA33-AD33-AE33-AG33-AH33-AI33-AK33-AL33-AN33-AM33 -> 436.78676 | AQ33: =IF(U33=0,0,AA33/U33) -> 416.97875 | AR33: =K33 -> 123.09 | AS33: =IF(U33=0,0,AE33/U33) -> 155.52 | AT33: =IF(S33=0,AG33/1,AG33/S33) -> 54.3025 | AU33: =IF(S33=0,0,(AH33+AI33+AJ33)/S33) -> 0 | AV33: {=_xlfn.IFS(U33=0,AO33,U33<0,AO33/-U33,U33>0,AO33/U33)} -> 54.598345 | AW33: =IF(AQ33=0,0,AV33/AQ33) -> 0.13093796 | AX33: =IF(AR33=0,0,AV33/AR33) -> 0.44356443 | AZ33: =AV33*E33 -> 8844.9319
A34: Ridges | B34: 233500274 | C34: sh10 | D34: Солнцезащитные очки | E34: =SUM(F34:J34) -> 5 | F34: 4 | I34: 1 | J34: 0 | K34: 117.24 | L34: =E34*K34 -> 586.2 | M34: 16 | N34: 3 | O34: 439 | P34: 0 | Q34: =N34/7 -> 0.42857143 | R34: =U34/7 -> 0.71428571 | S34: 5 | T34: 0 | U34: =S34+T34 -> 5 | V34: 1344.55 | W34: 0 | X34: =V34+W34 -> 1344.55 | Y34: 2194.52 | Z34: 0 | AA34: =Y34+Z34 -> 2194.52 | AB34: =N34*O34*P34/100 -> 0 | AC34: =AA34/$AA$126 -> 0.00089411246 | AD34: =U34*K34 -> 586.2 | AE34: 815.86 | AF34: =IF(AA34=0,0,AE34/AA34) -> 0.3717715 | AG34: 345.38 | AL34: =IFERROR($AL$126*H34/$H$126,0) -> 0 | AM34: 0 | AN34: =X34*5.71% -> 76.773805 | AO34: =AA34-AD34-AE34-AG34-AH34-AI34-AK34-AL34-AN34-AM34 -> 370.3062 | AQ34: =IF(U34=0,0,AA34/U34) -> 438.904 | AR34: =K34 -> 117.24 | AS34: =IF(U34=0,0,AE34/U34) -> 163.172 | AT34: =IF(S34=0,AG34/1,AG34/S34) -> 69.076 | AU34: =IF(S34=0,0,(AH34+AI34+AJ34)/S34) -> 0 | AV34: {=_xlfn.IFS(U34=0,AO34,U34<0,AO34/-U34,U34>0,AO34/U34)} -> 74.061239 | AW34: =IF(AQ34=0,0,AV34/AQ34) -> 0.16874132 | AX34: =IF(AR34=0,0,AV34/AR34) -> 0.63170624 | AZ34: =AV34*E34 -> 370.3062
A35: Ridges | B35: 471878869 | C35: sh11 | D35: Солнцезащитные очки | E35: =SUM(F35:J35) -> 1 | F35: 0 | G35: 0 | H35: 0 | I35: 0 | J35: 1 | K35: 128.94 | L35: =E35*K35 -> 128.94 | M35: 0 | N35: 0 | O35: 0 | P35: 0 | Q35: =N35/7 -> 0 | R35: =U35/7 -> 0 | S35: 0 | T35: 0 | U35: =S35+T35 -> 0 | V35: 0 | W35: 0 | X35: =V35+W35 -> 0 | Y35: 0 | Z35: 0 | AA35: =Y35+Z35 -> 0 | AB35: =N35*O35*P35/100 -> 0 | AC35: =AA35/$AA$126 -> 0 | AD35: =U35*K35 -> 0 | AE35: 0 | AF35: =IF(AA35=0,0,AE35/AA35) -> 0 | AG35: 0 | AL35: =IFERROR($AL$126*H35/$H$126,0) -> 0 | AM35: 0 | AN35: =X35*5.71% -> 0 | AO35: =AA35-AD35-AE35-AG35-AH35-AI35-AK35-AL35-AN35-AM35 -> 0 | AQ35: =IF(U35=0,0,AA35/U35) -> 0 | AR35: =K35 -> 128.94 | AS35: =IF(U35=0,0,AE35/U35) -> 0 | AT35: =IF(S35=0,AG35/1,AG35/S35) -> 0 | AU35: =IF(S35=0,0,(AH35+AI35+AJ35)/S35) -> 0 | AV35: {=_xlfn.IFS(U35=0,AO35,U35<0,AO35/-U35,U35>0,AO35/U35)} -> 0 | AW35: =IF(AQ35=0,0,AV35/AQ35) -> 0 | AX35: =IF(AR35=0,0,AV35/AR35) -> 0 | AZ35: =AV35*E35 -> 0
A36: Ridges | B36: 471878989 | C36: sh12 | D36: Солнцезащитные очки | E36: =SUM(F36:J36) -> 1 | F36: 0 | G36: 0 | H36: 0 | I36: 0 | J36: 1 | K36: 169.89 | L36: =E36*K36 -> 169.89 | M36: 0 | N36: 0 | O36: 0 | P36: 0 | Q36: =N36/7 -> 0 | R36: =U36/7 -> 0 | S36: 0 | T36: 0 | U36: =S36+T36 -> 0 | V36: 0 | W36: 0 | X36: =V36+W36 -> 0 | Y36: 0 | Z36: 0 | AA36: =Y36+Z36 -> 0 | AB36: =N36*O36*P36/100 -> 0 | AC36: =AA36/$AA$126 -> 0 | AD36: =U36*K36 -> 0 | AE36: 0 | AF36: =IF(AA36=0,0,AE36/AA36) -> 0 | AG36: 0 | AL36: =IFERROR($AL$126*H36/$H$126,0) -> 0 | AM36: 0 | AN36: =X36*5.71% -> 0 | AO36: =AA36-AD36-AE36-AG36-AH36-AI36-AK36-AL36-AN36-AM36 -> 0 | AQ36: =IF(U36=0,0,AA36/U36) -> 0 | AR36: =K36 -> 169.89 | AS36: =IF(U36=0,0,AE36/U36) -> 0 | AT36: =IF(S36=0,AG36/1,AG36/S36) -> 0 | AU36: =IF(S36=0,0,(AH36+AI36+AJ36)/S36) -> 0 | AV36: {=_xlfn.IFS(U36=0,AO36,U36<0,AO36/-U36,U36>0,AO36/U36)} -> 0 | AW36: =IF(AQ36=0,0,AV36/AQ36) -> 0 | AX36: =IF(AR36=0,0,AV36/AR36) -> 0 | AZ36: =AV36*E36 -> 0
A37: Ridges | B37: 471879283 | C37: sh13 | D37: Солнцезащитные очки | E37: =SUM(F37:J37) -> 12 | F37: 4 | G37: 2 | H37: 5 | I37: 0 | J37: 1 | K37: 169.89 | L37: =E37*K37 -> 2038.68 | M37: 28 | N37: 5 | O37: 998 | P37: 0 | Q37: =N37/7 -> 0.71428571 | R37: =U37/7 -> 0.14285714 | S37: 1 | T37: 0 | U37: =S37+T37 -> 1 | V37: 655 | W37: 0 | X37: =V37+W37 -> 655 | Y37: 998 | Z37: 0 | AA37: =Y37+Z37 -> 998 | AB37: =N37*O37*P37/100 -> 0 | AC37: =AA37/$AA$126 -> 0.00040661477 | AD37: =U37*K37 -> 169.89 | AE37: 373.09 | AF37: =IF(AA37=0,0,AE37/AA37) -> 0.37383768 | AG37: 325.73 | AL37: =IFERROR($AL$126*H37/$H$126,0) -> 4.3362343 | AM37: 0 | AN37: =X37*5.71% -> 37.4005 | AO37: =AA37-AD37-AE37-AG37-AH37-AI37-AK37-AL37-AN37-AM37 -> 87.553266 | AQ37: =IF(U37=0,0,AA37/U37) -> 998 | AR37: =K37 -> 169.89 | AS37: =IF(U37=0,0,AE37/U37) -> 373.09 | AT37: =IF(S37=0,AG37/1,AG37/S37) -> 325.73 | AU37: =IF(S37=0,0,(AH37+AI37+AJ37)/S37) -> 0 | AV37: {=_xlfn.IFS(U37=0,AO37,U37<0,AO37/-U37,U37>0,AO37/U37)} -> 87.553266 | AW37: =IF(AQ37=0,0,AV37/AQ37) -> 0.087728723 | AX37: =IF(AR37=0,0,AV37/AR37) -> 0.51535267 | AZ37: =AV37*E37 -> 1050.6392
A38: Ridges | B38: 507117329 | C38: sh14 | D38: Солнцезащитные очки | E38: =SUM(F38:J38) -> 48 | G38: 1 | H38: 46 | I38: 0 | J38: 1 | K38: 105.54 | L38: =E38*K38 -> 5065.92 | M38: 459 | N38: 2 | O38: 1197 | P38: 0 | Q38: =N38/7 -> 0.28571429 | R38: =U38/7 -> 0 | S38: 0 | T38: 0 | U38: =S38+T38 -> 0 | V38: 0 | W38: 0 | X38: =V38+W38 -> 0 | Y38: 0 | Z38: 0 | AA38: =Y38+Z38 -> 0 | AB38: =N38*O38*P38/100 -> 0 | AC38: =AA38/$AA$126 -> 0 | AD38: =U38*K38 -> 0 | AE38: 0 | AF38: =IF(AA38=0,0,AE38/AA38) -> 0 | AG38: 320.63 | AL38: =IFERROR($AL$126*H38/$H$126,0) -> 39.893355 | AM38: 0 | AN38: =X38*5.71% -> 0 | AO38: =AA38-AD38-AE38-AG38-AH38-AI38-AK38-AL38-AN38-AM38 -> -360.52336 | AQ38: =IF(U38=0,0,AA38/U38) -> 0 | AR38: =K38 -> 105.54 | AS38: =IF(U38=0,0,AE38/U38) -> 0 | AT38: =IF(S38=0,AG38/1,AG38/S38) -> 320.63 | AU38: =IF(S38=0,0,(AH38+AI38+AJ38)/S38) -> 0 | AV38: {=_xlfn.IFS(U38=0,AO38,U38<0,AO38/-U38,U38>0,AO38/U38)} -> -360.52336 | AW38: =IF(AQ38=0,0,AV38/AQ38) -> 0 | AX38: =IF(AR38=0,0,AV38/AR38) -> -3.4159878 | AZ38: =AV38*E38 -> -17305.121
A39: Ridges | B39: 507117646 | C39: sh15 | D39: Солнцезащитные очки | E39: =SUM(F39:J39) -> 40 | F39: 7 | G39: 1 | H39: 31 | I39: 0 | J39: 1 | K39: 105.54 | L39: =E39*K39 -> 4221.6 | M39: 69 | N39: 6 | O39: 1077 | P39: 0 | Q39: =N39/7 -> 0.85714286 | R39: =U39/7 -> 0.28571429 | S39: 2 | T39: 0 | U39: =S39+T39 -> 2 | V39: 1500.84 | W39: 0 | X39: =V39+W39 -> 1500.84 | Y39: 2154.24 | Z39: 0 | AA39: =Y39+Z39 -> 2154.24 | AB39: =N39*O39*P39/100 -> 0 | AC39: =AA39/$AA$126 -> 0.0008777012 | AD39: =U39*K39 -> 211.08 | AE39: 800.02 | AF39: =IF(AA39=0,0,AE39/AA39) -> 0.37136995 | AG39: 523.37 | AH39: 1 | AL39: =IFERROR($AL$126*H39/$H$126,0) -> 26.884653 | AM39: 0 | AN39: =X39*5.71% -> 85.697964 | AO39: =AA39-AD39-AE39-AG39-AH39-AI39-AK39-AL39-AN39-AM39 -> 506.18738 | AQ39: =IF(U39=0,0,AA39/U39) -> 1077.12 | AR39: =K39 -> 105.54 | AS39: =IF(U39=0,0,AE39/U39) -> 400.01 | AT39: =IF(S39=0,AG39/1,AG39/S39) -> 261.685 | AU39: =IF(S39=0,0,(AH39+AI39+AJ39)/S39) -> 0.5 | AV39: {=_xlfn.IFS(U39=0,AO39,U39<0,AO39/-U39,U39>0,AO39/U39)} -> 253.09369 | AW39: =IF(AQ39=0,0,AV39/AQ39) -> 0.2349726 | AX39: =IF(AR39=0,0,AV39/AR39) -> 2.3980831 | AZ39: =AV39*E39 -> 10123.748
A40: Ridges | B40: 507118076 | C40: sh16 | D40: Солнцезащитные очки | E40: =SUM(F40:J40) -> 47 | F40: 2 | G40: 3 | H40: 41 | I40: 0 | J40: 1 | K40: 105.54 | L40: =E40*K40 -> 4960.38 | M40: 259 | N40: 2 | O40: 1197 | P40: 0 | Q40: =N40/7 -> 0.28571429 | R40: =U40/7 -> 0 | S40: 0 | T40: 0 | U40: =S40+T40 -> 0 | V40: 0 | W40: 0 | X40: =V40+W40 -> 0 | Y40: 0 | Z40: 0 | AA40: =Y40+Z40 -> 0 | AB40: =N40*O40*P40/100 -> 0 | AC40: =AA40/$AA$126 -> 0 | AD40: =U40*K40 -> 0 | AE40: 0 | AF40: =IF(AA40=0,0,AE40/AA40) -> 0 | AG40: 432.27 | AL40: =IFERROR($AL$126*H40/$H$126,0) -> 35.557121 | AM40: 0 | AN40: =X40*5.71% -> 0 | AO40: =AA40-AD40-AE40-AG40-AH40-AI40-AK40-AL40-AN40-AM40 -> -467.82712 | AQ40: =IF(U40=0,0,AA40/U40) -> 0 | AR40: =K40 -> 105.54 | AS40: =IF(U40=0,0,AE40/U40) -> 0 | AT40: =IF(S40=0,AG40/1,AG40/S40) -> 432.27 | AU40: =IF(S40=0,0,(AH40+AI40+AJ40)/S40) -> 0 | AV40: {=_xlfn.IFS(U40=0,AO40,U40<0,AO40/-U40,U40>0,AO40/U40)} -> -467.82712 | AW40: =IF(AQ40=0,0,AV40/AQ40) -> 0 | AX40: =IF(AR40=0,0,AV40/AR40) -> -4.4326997 | AZ40: =AV40*E40 -> -21987.875
A41: Ridges | B41: 507118377 | C41: sh17 | D41: Солнцезащитные очки | E41: =SUM(F41:J41) -> 47 | H41: 46 | I41: 0 | J41: 1 | K41: 123.09 | L41: =E41*K41 -> 5785.23 | M41: 999 | N41: 0 | O41: 0 | P41: 0 | Q41: =N41/7 -> 0 | R41: =U41/7 -> 0 | S41: 0 | T41: 0 | U41: =S41+T41 -> 0 | V41: 0 | W41: 0 | X41: =V41+W41 -> 0 | Y41: 0 | Z41: 0 | AA41: =Y41+Z41 -> 0 | AB41: =N41*O41*P41/100 -> 0 | AC41: =AA41/$AA$126 -> 0 | AD41: =U41*K41 -> 0 | AE41: 0 | AF41: =IF(AA41=0,0,AE41/AA41) -> 0 | AG41: 0 | AL41: =IFERROR($AL$126*H41/$H$126,0) -> 39.893355 | AM41: 0 | AN41: =X41*5.71% -> 0 | AO41: =AA41-AD41-AE41-AG41-AH41-AI41-AK41-AL41-AN41-AM41 -> -39.893355 | AQ41: =IF(U41=0,0,AA41/U41) -> 0 | AR41: =K41 -> 123.09 | AS41: =IF(U41=0,0,AE41/U41) -> 0 | AT41: =IF(S41=0,AG41/1,AG41/S41) -> 0 | AU41: =IF(S41=0,0,(AH41+AI41+AJ41)/S41) -> 0 | AV41: {=_xlfn.IFS(U41=0,AO41,U41<0,AO41/-U41,U41>0,AO41/U41)} -> -39.893355 | AW41: =IF(AQ41=0,0,AV41/AQ41) -> 0 | AX41: =IF(AR41=0,0,AV41/AR41) -> -0.32409908 | AZ41: =AV41*E41 -> -1874.9877
A42: Ridges | B42: 507119317 | C42: sh18 | D42: Солнцезащитные очки | E42: =SUM(F42:J42) -> 47 | F42: 3 | H42: 43 | I42: 0 | J42: 1 | K42: 123.09 | L42: =E42*K42 -> 5785.23 | M42: 344 | N42: 3 | O42: 1176 | P42: 0 | Q42: =N42/7 -> 0.42857143 | R42: =U42/7 -> 0 | S42: 0 | T42: 0 | U42: =S42+T42 -> 0 | V42: 0 | W42: 0 | X42: =V42+W42 -> 0 | Y42: 0 | Z42: 0 | AA42: =Y42+Z42 -> 0 | AB42: =N42*O42*P42/100 -> 0 | AC42: =AA42/$AA$126 -> 0 | AD42: =U42*K42 -> 0 | AE42: 0 | AF42: =IF(AA42=0,0,AE42/AA42) -> 0 | AG42: 84.8 | AL42: =IFERROR($AL$126*H42/$H$126,0) -> 37.291615 | AM42: 0 | AN42: =X42*5.71% -> 0 | AO42: =AA42-AD42-AE42-AG42-AH42-AI42-AK42-AL42-AN42-AM42 -> -122.09161 | AQ42: =IF(U42=0,0,AA42/U42) -> 0 | AR42: =K42 -> 123.09 | AS42: =IF(U42=0,0,AE42/U42) -> 0 | AT42: =IF(S42=0,AG42/1,AG42/S42) -> 84.8 | AU42: =IF(S42=0,0,(AH42+AI42+AJ42)/S42) -> 0 | AV42: {=_xlfn.IFS(U42=0,AO42,U42<0,AO42/-U42,U42>0,AO42/U42)} -> -122.09161 | AW42: =IF(AQ42=0,0,AV42/AQ42) -> 0 | AX42: =IF(AR42=0,0,AV42/AR42) -> -0.99188898 | AZ42: =AV42*E42 -> -5738.3059
A43: Ridges | B43: 507119522 | C43: sh19 | D43: Солнцезащитные очки | E43: =SUM(F43:J43) -> 45 | F43: 5 | G43: 3 | H43: 36 | I43: 0 | J43: 1 | K43: 123.09 | L43: =E43*K43 -> 5539.05 | M43: 102 | N43: 8 | O43: 1102 | P43: 0 | Q43: =N43/7 -> 1.1428571 | R43: =U43/7 -> 0.28571429 | S43: 2 | T43: 0 | U43: =S43+T43 -> 2 | V43: 1371 | W43: 0 | X43: =V43+W43 -> 1371 | Y43: 2204 | Z43: 0 | AA43: =Y43+Z43 -> 2204 | AB43: =N43*O43*P43/100 -> 0 | AC43: =AA43/$AA$126 -> 0.0008979749 | AD43: =U43*K43 -> 246.18 | AE43: 821.48 | AF43: =IF(AA43=0,0,AE43/AA43) -> 0.37272232 | AG43: 649.96 | AL43: =IFERROR($AL$126*H43/$H$126,0) -> 31.220887 | AM43: 0 | AN43: =X43*5.71% -> 78.2841 | AO43: =AA43-AD43-AE43-AG43-AH43-AI43-AK43-AL43-AN43-AM43 -> 376.87501 | AQ43: =IF(U43=0,0,AA43/U43) -> 1102 | AR43: =K43 -> 123.09 | AS43: =IF(U43=0,0,AE43/U43) -> 410.74 | AT43: =IF(S43=0,AG43/1,AG43/S43) -> 324.98 | AU43: =IF(S43=0,0,(AH43+AI43+AJ43)/S43) -> 0 | AV43: {=_xlfn.IFS(U43=0,AO43,U43<0,AO43/-U43,U43>0,AO43/U43)} -> 188.43751 | AW43: =IF(AQ43=0,0,AV43/AQ43) -> 0.17099592 | AX43: =IF(AR43=0,0,AV43/AR43) -> 1.5308921 | AZ43: =AV43*E43 -> 8479.6878
A44: Ridges | B44: 386597215 | C44: ww 203 черные | D44: Солнцезащитные очки | E44: =SUM(F44:J44) -> 1759 | F44: 18 | G44: 2 | H44: 178 | I44: 0 | J44: 1561 | K44: 111.39 | L44: =E44*K44 -> 195935.01 | M44: 148 | N44: 26 | O44: 995 | P44: 50 | Q44: =N44/7 -> 3.7142857 | R44: =U44/7 -> 1.2857143 | S44: 9 | T44: 0 | U44: =S44+T44 -> 9 | V44: 5693 | W44: 0 | X44: =V44+W44 -> 5693 | Y44: 9009.15 | Z44: 0 | AA44: =Y44+Z44 -> 9009.15 | AB44: =N44*O44*P44/100 -> 12935 | AC44: =AA44/$AA$126 -> 0.0036705946 | AD44: =U44*K44 -> 1002.51 | AE44: 3389.91 | AF44: =IF(AA44=0,0,AE44/AA44) -> 0.37627412 | AG44: 1403.09 | AH44: 482 | AI44: 1967 | AL44: =IFERROR($AL$126*H44/$H$126,0) -> 154.36994 | AM44: 0 | AN44: =X44*5.71% -> 325.0703 | AO44: =AA44-AD44-AE44-AG44-AH44-AI44-AK44-AL44-AN44-AM44 -> 285.19976 | AQ44: =IF(U44=0,0,AA44/U44) -> 1001.0167 | AR44: =K44 -> 111.39 | AS44: =IF(U44=0,0,AE44/U44) -> 376.65667 | AT44: =IF(S44=0,AG44/1,AG44/S44) -> 155.89889 | AU44: =IF(S44=0,0,(AH44+AI44+AJ44)/S44) -> 272.11111 | AV44: {=_xlfn.IFS(U44=0,AO44,U44<0,AO44/-U44,U44>0,AO44/U44)} -> 31.688862 | AW44: =IF(AQ44=0,0,AV44/AQ44) -> 0.031656678 | AX44: =IF(AR44=0,0,AV44/AR44) -> 0.2844857 | AZ44: =AV44*E44 -> 55740.709
A45: Ridges | B45: 386777272 | C45: ww 1022 черные | D45: Солнцезащитные очки | E45: =SUM(F45:J45) -> 330 | F45: 117 | G45: 32 | H45: 66 | I45: 0 | J45: 115 | K45: 107.88 | L45: =E45*K45 -> 35600.4 | M45: 27 | N45: 182 | O45: 1232 | P45: 47 | Q45: =N45/7 -> 26 | R45: =U45/7 -> 9.5714286 | S45: 71 | T45: -4 | U45: =S45+T45 -> 67 | V45: 50655.84 | W45: -2842 | X45: =V45+W45 -> 47813.84 | Y45: 80302.01 | Z45: -4464 | AA45: =Y45+Z45 -> 75838.01 | AB45: =N45*O45*P45/100 -> 105385.28 | AC45: =AA45/$AA$126 -> 0.030898652 | AD45: =U45*K45 -> 7227.96 | AE45: 28397.79 | AF45: =IF(AA45=0,0,AE45/AA45) -> 0.37445326 | AG45: 9687.4 | AH45: 2142 | AI45: 17000 | AL45: =IFERROR($AL$126*H45/$H$126,0) -> 57.238293 | AM45: 0 | AN45: =X45*5.71% -> 2730.1703 | AO45: =AA45-AD45-AE45-AG45-AH45-AI45-AK45-AL45-AN45-AM45 -> 8595.4514 | AQ45: =IF(U45=0,0,AA45/U45) -> 1131.9106 | AR45: =K45 -> 107.88 | AS45: =IF(U45=0,0,AE45/U45) -> 423.84761 | AT45: =IF(S45=0,AG45/1,AG45/S45) -> 136.44225 | AU45: =IF(S45=0,0,(AH45+AI45+AJ45)/S45) -> 269.60563 | AV45: {=_xlfn.IFS(U45=0,AO45,U45<0,AO45/-U45,U45>0,AO45/U45)} -> 128.29032 | AW45: =IF(AQ45=0,0,AV45/AQ45) -> 0.11333962 | AX45: =IF(AR45=0,0,AV45/AR45) -> 1.1891947 | AZ45: =AV45*E45 -> 42335.806
A46: Ridges | B46: 386777270 | C46: ww 1022 черн-серебро | D46: Солнцезащитные очки | E46: =SUM(F46:J46) -> 1 | F46: 0 | G46: 0 | H46: 0 | I46: 0 | J46: 1 | K46: 107.88 | L46: =E46*K46 -> 107.88 | M46: 0 | N46: 0 | O46: 0 | P46: 0 | Q46: =N46/7 -> 0 | R46: =U46/7 -> 0 | S46: 0 | T46: 0 | U46: =S46+T46 -> 0 | V46: 0 | W46: 0 | X46: =V46+W46 -> 0 | Y46: 0 | Z46: 0 | AA46: =Y46+Z46 -> 0 | AB46: =N46*O46*P46/100 -> 0 | AC46: =AA46/$AA$126 -> 0 | AD46: =U46*K46 -> 0 | AE46: 0 | AF46: =IF(AA46=0,0,AE46/AA46) -> 0 | AG46: 0 | AL46: =IFERROR($AL$126*H46/$H$126,0) -> 0 | AM46: 0 | AN46: =X46*5.71% -> 0 | AO46: =AA46-AD46-AE46-AG46-AH46-AI46-AK46-AL46-AN46-AM46 -> 0 | AQ46: =IF(U46=0,0,AA46/U46) -> 0 | AR46: =K46 -> 107.88 | AS46: =IF(U46=0,0,AE46/U46) -> 0 | AT46: =IF(S46=0,AG46/1,AG46/S46) -> 0 | AU46: =IF(S46=0,0,(AH46+AI46+AJ46)/S46) -> 0 | AV46: {=_xlfn.IFS(U46=0,AO46,U46<0,AO46/-U46,U46>0,AO46/U46)} -> 0 | AW46: =IF(AQ46=0,0,AV46/AQ46) -> 0 | AX46: =IF(AR46=0,0,AV46/AR46) -> 0 | AZ46: =AV46*E46 -> 0
A47: Ridges | B47: 386777273 | C47: ww 1022 желтые | D47: Солнцезащитные очки | E47: =SUM(F47:J47) -> 321 | F47: 15 | G47: 16 | H47: 110 | I47: 0 | J47: 180 | K47: 123.09 | L47: =E47*K47 -> 39511.89 | M47: 109 | N47: 20 | O47: 1044 | P47: 71 | Q47: =N47/7 -> 2.8571429 | R47: =U47/7 -> 1.8571429 | S47: 13 | T47: 0 | U47: =S47+T47 -> 13 | V47: 8111 | W47: 0 | X47: =V47+W47 -> 8111 | Y47: 13347.38 | Z47: 0 | AA47: =Y47+Z47 -> 13347.38 | AB47: =N47*O47*P47/100 -> 14824.8 | AC47: =AA47/$AA$126 -> 0.005438118 | AD47: =U47*K47 -> 1600.17 | AE47: 4995.3 | AF47: =IF(AA47=0,0,AE47/AA47) -> 0.37425322 | AG47: 1198.2 | AH47: 425 | AL47: =IFERROR($AL$126*H47/$H$126,0) -> 95.397154 | AM47: 0 | AN47: =X47*5.71% -> 463.1381 | AO47: =AA47-AD47-AE47-AG47-AH47-AI47-AK47-AL47-AN47-AM47 -> 4570.1747 | AQ47: =IF(U47=0,0,AA47/U47) -> 1026.7215 | AR47: =K47 -> 123.09 | AS47: =IF(U47=0,0,AE47/U47) -> 384.25385 | AT47: =IF(S47=0,AG47/1,AG47/S47) -> 92.169231 | AU47: =IF(S47=0,0,(AH47+AI47+AJ47)/S47) -> 32.692308 | AV47: {=_xlfn.IFS(U47=0,AO47,U47<0,AO47/-U47,U47>0,AO47/U47)} -> 351.5519 | AW47: =IF(AQ47=0,0,AV47/AQ47) -> 0.34240239 | AX47: =IF(AR47=0,0,AV47/AR47) -> 2.8560558 | AZ47: =AV47*E47 -> 112848.16
A48: Ridges | B48: 386777271 | C48: ww 1022 коричневые | D48: Солнцезащитные очки | E48: =SUM(F48:J48) -> 349 | F48: 58 | G48: 9 | H48: 271 | I48: 0 | J48: 11 | K48: 107.88 | L48: =E48*K48 -> 37650.12 | M48: 82 | N48: 75 | O48: 1261 | P48: 68 | Q48: =N48/7 -> 10.714286 | R48: =U48/7 -> 4.4285714 | S48: 31 | T48: 0 | U48: =S48+T48 -> 31 | V48: 23548.18 | W48: 0 | X48: =V48+W48 -> 23548.18 | Y48: 37348.71 | Z48: 0 | AA48: =Y48+Z48 -> 37348.71 | AB48: =N48*O48*P48/100 -> 64311 | AC48: =AA48/$AA$126 -> 0.015216971 | AD48: =U48*K48 -> 3344.28 | AE48: 13925.39 | AF48: =IF(AA48=0,0,AE48/AA48) -> 0.37284795 | AG48: 3312.29 | AH48: 562 | AI48: 5500 | AL48: =IFERROR($AL$126*H48/$H$126,0) -> 235.0239 | AM48: 0 | AN48: =X48*5.71% -> 1344.6011 | AO48: =AA48-AD48-AE48-AG48-AH48-AI48-AK48-AL48-AN48-AM48 -> 9125.125 | AQ48: =IF(U48=0,0,AA48/U48) -> 1204.7971 | AR48: =K48 -> 107.88 | AS48: =IF(U48=0,0,AE48/U48) -> 449.20613 | AT48: =IF(S48=0,AG48/1,AG48/S48) -> 106.84806 | AU48: =IF(S48=0,0,(AH48+AI48+AJ48)/S48) -> 195.54839 | AV48: {=_xlfn.IFS(U48=0,AO48,U48<0,AO48/-U48,U48>0,AO48/U48)} -> 294.35887 | AW48: =IF(AQ48=0,0,AV48/AQ48) -> 0.24432236 | AX48: =IF(AR48=0,0,AV48/AR48) -> 2.7285769 | AZ48: =AV48*E48 -> 102731.25
A49: Ridges | B49: 386753444 | C49: ww 2018 черные | D49: Солнцезащитные очки | E49: =SUM(F49:J49) -> 130 | F49: 65 | G49: 25 | H49: 38 | I49: 0 | J49: 2 | K49: 123.09 | L49: =E49*K49 -> 16001.7 | M49: 28 | N49: 95 | O49: 1354 | P49: 40 | Q49: =N49/7 -> 13.571429 | R49: =U49/7 -> 4.1428571 | S49: 29 | T49: 0 | U49: =S49+T49 -> 29 | V49: 24497.1 | W49: 0 | X49: =V49+W49 -> 24497.1 | Y49: 38717.15 | Z49: 0 | AA49: =Y49+Z49 -> 38717.15 | AB49: =N49*O49*P49/100 -> 51452 | AC49: =AA49/$AA$126 -> 0.015774514 | AD49: =U49*K49 -> 3569.61 | AE49: 14517.98 | AF49: =IF(AA49=0,0,AE49/AA49) -> 0.37497543 | AG49: 5081.15 | AH49: 115 | AI49: 7915 | AL49: =IFERROR($AL$126*H49/$H$126,0) -> 32.955381 | AM49: 0 | AN49: =X49*5.71% -> 1398.7844 | AO49: =AA49-AD49-AE49-AG49-AH49-AI49-AK49-AL49-AN49-AM49 -> 6086.6702 | AQ49: =IF(U49=0,0,AA49/U49) -> 1335.0741 | AR49: =K49 -> 123.09 | AS49: =IF(U49=0,0,AE49/U49) -> 500.62 | AT49: =IF(S49=0,AG49/1,AG49/S49) -> 175.21207 | AU49: =IF(S49=0,0,(AH49+AI49+AJ49)/S49) -> 276.89655 | AV49: {=_xlfn.IFS(U49=0,AO49,U49<0,AO49/-U49,U49>0,AO49/U49)} -> 209.88518 | AW49: =IF(AQ49=0,0,AV49/AQ49) -> 0.15720863 | AX49: =IF(AR49=0,0,AV49/AR49) -> 1.7051359 | AZ49: =AV49*E49 -> 27285.073
A50: Ridges | B50: 386733628 | C50: ww 2018 желтые | D50: Солнцезащитные очки | E50: =SUM(F50:J50) -> 207 | F50: 18 | G50: 8 | H50: 180 | I50: 0 | J50: 1 | K50: 134.79 | L50: =E50*K50 -> 27901.53 | M50: 121 | N50: 26 | O50: 1218 | P50: 30 | Q50: =N50/7 -> 3.7142857 | R50: =U50/7 -> 1 | S50: 8 | T50: -1 | U50: =S50+T50 -> 7 | V50: 6098 | W50: -753 | X50: =V50+W50 -> 5345 | Y50: 9744 | Z50: -1218 | AA50: =Y50+Z50 -> 8526 | AB50: =N50*O50*P50/100 -> 9500.4 | AC50: =AA50/$AA$126 -> 0.003473745 | AD50: =U50*K50 -> 943.53 | AE50: 3203.17 | AF50: =IF(AA50=0,0,AE50/AA50) -> 0.37569435 | AG50: 1839.01 | AH50: 394 | AI50: 1905 | AL50: =IFERROR($AL$126*H50/$H$126,0) -> 156.10443 | AM50: 20 | AN50: =X50*5.71% -> 305.1995 | AO50: =AA50-AD50-AE50-AG50-AH50-AI50-AK50-AL50-AN50-AM50 -> -240.01393 | AQ50: =IF(U50=0,0,AA50/U50) -> 1218 | AR50: =K50 -> 134.79 | AS50: =IF(U50=0,0,AE50/U50) -> 457.59571 | AT50: =IF(S50=0,AG50/1,AG50/S50) -> 229.87625 | AU50: =IF(S50=0,0,(AH50+AI50+AJ50)/S50) -> 287.375 | AV50: {=_xlfn.IFS(U50=0,AO50,U50<0,AO50/-U50,U50>0,AO50/U50)} -> -34.287705 | AW50: =IF(AQ50=0,0,AV50/AQ50) -> -0.028150825 | AX50: =IF(AR50=0,0,AV50/AR50) -> -0.2543787 | AZ50: =AV50*E50 -> -7097.5549
A51: Ridges | B51: 386787535 | C51: ww 8010 черные | D51: Солнцезащитные очки | E51: =SUM(F51:J51) -> 8 | F51: 3 | G51: 2 | H51: 2 | I51: 0 | J51: 1 | K51: 144.15 | L51: =E51*K51 -> 1153.2 | M51: 5 | N51: 3 | O51: 1119 | P51: 50 | Q51: =N51/7 -> 0.42857143 | R51: =U51/7 -> 0.28571429 | S51: 2 | T51: 0 | U51: =S51+T51 -> 2 | V51: 1432 | W51: 0 | X51: =V51+W51 -> 1432 | Y51: 2238 | Z51: 0 | AA51: =Y51+Z51 -> 2238 | AB51: =N51*O51*P51/100 -> 1678.5 | AC51: =AA51/$AA$126 -> 0.0009118275 | AD51: =U51*K51 -> 288.3 | AE51: 847.42 | AF51: =IF(AA51=0,0,AE51/AA51) -> 0.37865058 | AG51: 512.42 | AL51: =IFERROR($AL$126*H51/$H$126,0) -> 1.7344937 | AM51: 0 | AN51: =X51*5.71% -> 81.7672 | AO51: =AA51-AD51-AE51-AG51-AH51-AI51-AK51-AL51-AN51-AM51 -> 506.35831 | AQ51: =IF(U51=0,0,AA51/U51) -> 1119 | AR51: =K51 -> 144.15 | AS51: =IF(U51=0,0,AE51/U51) -> 423.71 | AT51: =IF(S51=0,AG51/1,AG51/S51) -> 256.21 | AU51: =IF(S51=0,0,(AH51+AI51+AJ51)/S51) -> 0 | AV51: {=_xlfn.IFS(U51=0,AO51,U51<0,AO51/-U51,U51>0,AO51/U51)} -> 253.17915 | AW51: =IF(AQ51=0,0,AV51/AQ51) -> 0.22625483 | AX51: =IF(AR51=0,0,AV51/AR51) -> 1.756359 | AZ51: =AV51*E51 -> 2025.4332
A52: Ridges | B52: 507114655 | C52: WW 3055 черный | D52: Солнцезащитные очки | E52: =SUM(F52:J52) -> 51 | F52: 2 | G52: 2 | H52: 46 | I52: 0 | J52: 1 | K52: 96.18 | L52: =E52*K52 -> 4905.18 | M52: 485 | N52: 2 | O52: 1106 | P52: 0 | Q52: =N52/7 -> 0.28571429 | R52: =U52/7 -> 0 | S52: 0 | T52: 0 | U52: =S52+T52 -> 0 | V52: 0 | W52: 0 | X52: =V52+W52 -> 0 | Y52: 0 | Z52: 0 | AA52: =Y52+Z52 -> 0 | AB52: =N52*O52*P52/100 -> 0 | AC52: =AA52/$AA$126 -> 0 | AD52: =U52*K52 -> 0 | AE52: 0 | AF52: =IF(AA52=0,0,AE52/AA52) -> 0 | AG52: 419.82 | AL52: =IFERROR($AL$126*H52/$H$126,0) -> 39.893355 | AM52: 0 | AN52: =X52*5.71% -> 0 | AO52: =AA52-AD52-AE52-AG52-AH52-AI52-AK52-AL52-AN52-AM52 -> -459.71336 | AQ52: =IF(U52=0,0,AA52/U52) -> 0 | AR52: =K52 -> 96.18 | AS52: =IF(U52=0,0,AE52/U52) -> 0 | AT52: =IF(S52=0,AG52/1,AG52/S52) -> 419.82 | AU52: =IF(S52=0,0,(AH52+AI52+AJ52)/S52) -> 0 | AV52: {=_xlfn.IFS(U52=0,AO52,U52<0,AO52/-U52,U52>0,AO52/U52)} -> -459.71336 | AW52: =IF(AQ52=0,0,AV52/AQ52) -> 0 | AX52: =IF(AR52=0,0,AV52/AR52) -> -4.7797188 | AZ52: =AV52*E52 -> -23445.381
A53: Ridges | B53: 507115073 | C53: WW 3055 коричневый | D53: Солнцезащитные очки | E53: =SUM(F53:J53) -> 48 | H53: 47 | I53: 0 | J53: 1 | K53: 96.18 | L53: =E53*K53 -> 4616.64 | M53: 999 | N53: 2 | O53: 1106 | P53: 50 | Q53: =N53/7 -> 0.28571429 | R53: =U53/7 -> 0.14285714 | S53: 1 | T53: 0 | U53: =S53+T53 -> 1 | V53: 616 | W53: 0 | X53: =V53+W53 -> 616 | Y53: 1072.82 | Z53: 0 | AA53: =Y53+Z53 -> 1072.82 | AB53: =N53*O53*P53/100 -> 1106 | AC53: =AA53/$AA$126 -> 0.00043709865 | AD53: =U53*K53 -> 96.18 | AE53: 398.19 | AF53: =IF(AA53=0,0,AE53/AA53) -> 0.37116198 | AG53: 250.53 | AL53: =IFERROR($AL$126*H53/$H$126,0) -> 40.760602 | AM53: 0 | AN53: =X53*5.71% -> 35.1736 | AO53: =AA53-AD53-AE53-AG53-AH53-AI53-AK53-AL53-AN53-AM53 -> 251.9858 | AQ53: =IF(U53=0,0,AA53/U53) -> 1072.82 | AR53: =K53 -> 96.18 | AS53: =IF(U53=0,0,AE53/U53) -> 398.19 | AT53: =IF(S53=0,AG53/1,AG53/S53) -> 250.53 | AU53: =IF(S53=0,0,(AH53+AI53+AJ53)/S53) -> 0 | AV53: {=_xlfn.IFS(U53=0,AO53,U53<0,AO53/-U53,U53>0,AO53/U53)} -> 251.9858 | AW53: =IF(AQ53=0,0,AV53/AQ53) -> 0.23488171 | AX53: =IF(AR53=0,0,AV53/AR53) -> 2.6199397 | AZ53: =AV53*E53 -> 12095.318
A54: Ridges | B54: 431398576 | C54: MANNA2101 | D54: Солнцезащитные очки | E54: =SUM(F54:J54) -> 51 | F54: 4 | G54: 2 | H54: 44 | I54: 0 | J54: 1 | K54: 123.09 | L54: =E54*K54 -> 6277.59 | M54: 171 | N54: 7 | O54: 998 | P54: 33 | Q54: =N54/7 -> 1 | R54: =U54/7 -> 0.14285714 | S54: 1 | T54: 0 | U54: =S54+T54 -> 1 | V54: 655 | W54: 0 | X54: =V54+W54 -> 655 | Y54: 998 | Z54: 0 | AA54: =Y54+Z54 -> 998 | AB54: =N54*O54*P54/100 -> 2305.38 | AC54: =AA54/$AA$126 -> 0.00040661477 | AD54: =U54*K54 -> 123.09 | AE54: 378 | AF54: =IF(AA54=0,0,AE54/AA54) -> 0.37875752 | AG54: 472.52 | AL54: =IFERROR($AL$126*H54/$H$126,0) -> 38.158862 | AM54: 0 | AN54: =X54*5.71% -> 37.4005 | AO54: =AA54-AD54-AE54-AG54-AH54-AI54-AK54-AL54-AN54-AM54 -> -51.169362 | AQ54: =IF(U54=0,0,AA54/U54) -> 998 | AR54: =K54 -> 123.09 | AS54: =IF(U54=0,0,AE54/U54) -> 378 | AT54: =IF(S54=0,AG54/1,AG54/S54) -> 472.52 | AU54: =IF(S54=0,0,(AH54+AI54+AJ54)/S54) -> 0 | AV54: {=_xlfn.IFS(U54=0,AO54,U54<0,AO54/-U54,U54>0,AO54/U54)} -> -51.169362 | AW54: =IF(AQ54=0,0,AV54/AQ54) -> -0.051271906 | AX54: =IF(AR54=0,0,AV54/AR54) -> -0.4157069 | AZ54: =AV54*E54 -> -2609.6374
A55: Ridges | B55: 431391163 | C55: MANNA2102 | D55: Солнцезащитные очки | E55: =SUM(F55:J55) -> 2 | H55: 1 | I55: 0 | J55: 1 | K55: 158.19 | L55: =E55*K55 -> 316.38 | M55: 999 | N55: 0 | O55: 0 | P55: 0 | Q55: =N55/7 -> 0 | R55: =U55/7 -> 0 | S55: 0 | T55: 0 | U55: =S55+T55 -> 0 | V55: 0 | W55: 0 | X55: =V55+W55 -> 0 | Y55: 0 | Z55: 0 | AA55: =Y55+Z55 -> 0 | AB55: =N55*O55*P55/100 -> 0 | AC55: =AA55/$AA$126 -> 0 | AD55: =U55*K55 -> 0 | AE55: 0 | AF55: =IF(AA55=0,0,AE55/AA55) -> 0 | AG55: 0 | AL55: =IFERROR($AL$126*H55/$H$126,0) -> 0.86724686 | AM55: 0 | AN55: =X55*5.71% -> 0 | AO55: =AA55-AD55-AE55-AG55-AH55-AI55-AK55-AL55-AN55-AM55 -> -0.86724686 | AQ55: =IF(U55=0,0,AA55/U55) -> 0 | AR55: =K55 -> 158.19 | AS55: =IF(U55=0,0,AE55/U55) -> 0 | AT55: =IF(S55=0,AG55/1,AG55/S55) -> 0 | AU55: =IF(S55=0,0,(AH55+AI55+AJ55)/S55) -> 0 | AV55: {=_xlfn.IFS(U55=0,AO55,U55<0,AO55/-U55,U55>0,AO55/U55)} -> -0.86724686 | AW55: =IF(AQ55=0,0,AV55/AQ55) -> 0 | AX55: =IF(AR55=0,0,AV55/AR55) -> -0.0054823115 | AZ55: =AV55*E55 -> -1.7344937
A56: Ridges | B56: 431392656 | C56: MANNA2103 | D56: Солнцезащитные очки | E56: =SUM(F56:J56) -> 2 | G56: 1 | I56: 0 | J56: 1 | K56: 152.34 | L56: =E56*K56 -> 304.68 | M56: 8 | N56: 0 | O56: 0 | P56: 0 | Q56: =N56/7 -> 0 | R56: =U56/7 -> 0.14285714 | S56: 1 | T56: 0 | U56: =S56+T56 -> 1 | V56: 637 | W56: 0 | X56: =V56+W56 -> 637 | Y56: 1049 | Z56: 0 | AA56: =Y56+Z56 -> 1049 | AB56: =N56*O56*P56/100 -> 0 | AC56: =AA56/$AA$126 -> 0.00042739368 | AD56: =U56*K56 -> 152.34 | AE56: 390.47 | AF56: =IF(AA56=0,0,AE56/AA56) -> 0.3722307 | AG56: 325.44 | AL56: =IFERROR($AL$126*H56/$H$126,0) -> 0 | AM56: 20 | AN56: =X56*5.71% -> 36.3727 | AO56: =AA56-AD56-AE56-AG56-AH56-AI56-AK56-AL56-AN56-AM56 -> 124.3773 | AQ56: =IF(U56=0,0,AA56/U56) -> 1049 | AR56: =K56 -> 152.34 | AS56: =IF(U56=0,0,AE56/U56) -> 390.47 | AT56: =IF(S56=0,AG56/1,AG56/S56) -> 325.44 | AU56: =IF(S56=0,0,(AH56+AI56+AJ56)/S56) -> 0 | AV56: {=_xlfn.IFS(U56=0,AO56,U56<0,AO56/-U56,U56>0,AO56/U56)} -> 124.3773 | AW56: =IF(AQ56=0,0,AV56/AQ56) -> 0.11856749 | AX56: =IF(AR56=0,0,AV56/AR56) -> 0.81644545 | AZ56: =AV56*E56 -> 248.7546
A57: Ridges | B57: 431394484 | C57: MANNA2104 | D57: Солнцезащитные очки | E57: =SUM(F57:J57) -> 41 | F57: 0 | G57: 0 | H57: 0 | I57: 0 | J57: 41 | K57: 93.84 | L57: =E57*K57 -> 3847.44 | M57: 0 | N57: 0 | O57: 0 | P57: 0 | Q57: =N57/7 -> 0 | R57: =U57/7 -> 0 | S57: 0 | T57: 0 | U57: =S57+T57 -> 0 | V57: 0 | W57: 0 | X57: =V57+W57 -> 0 | Y57: 0 | Z57: 0 | AA57: =Y57+Z57 -> 0 | AB57: =N57*O57*P57/100 -> 0 | AC57: =AA57/$AA$126 -> 0 | AD57: =U57*K57 -> 0 | AE57: 0 | AF57: =IF(AA57=0,0,AE57/AA57) -> 0 | AG57: 0 | AL57: =IFERROR($AL$126*H57/$H$126,0) -> 0 | AM57: 0 | AN57: =X57*5.71% -> 0 | AO57: =AA57-AD57-AE57-AG57-AH57-AI57-AK57-AL57-AN57-AM57 -> 0 | AQ57: =IF(U57=0,0,AA57/U57) -> 0 | AR57: =K57 -> 93.84 | AS57: =IF(U57=0,0,AE57/U57) -> 0 | AT57: =IF(S57=0,AG57/1,AG57/S57) -> 0 | AU57: =IF(S57=0,0,(AH57+AI57+AJ57)/S57) -> 0 | AV57: {=_xlfn.IFS(U57=0,AO57,U57<0,AO57/-U57,U57>0,AO57/U57)} -> 0 | AW57: =IF(AQ57=0,0,AV57/AQ57) -> 0 | AX57: =IF(AR57=0,0,AV57/AR57) -> 0 | AZ57: =AV57*E57 -> 0
A58: Ridges | B58: 431397787 | C58: MANNA2105 | D58: Солнцезащитные очки | E58: =SUM(F58:J58) -> 41 | F58: 7 | G58: 4 | H58: 29 | I58: 0 | J58: 1 | K58: 169.89 | L58: =E58*K58 -> 6965.49 | M58: 60 | N58: 8 | O58: 1039 | P58: 25 | Q58: =N58/7 -> 1.1428571 | R58: =U58/7 -> 0.28571429 | S58: 3 | T58: -1 | U58: =S58+T58 -> 2 | V58: 1931 | W58: -616 | X58: =V58+W58 -> 1315 | Y58: 3117 | Z58: -1039 | AA58: =Y58+Z58 -> 2078 | AB58: =N58*O58*P58/100 -> 2078 | AC58: =AA58/$AA$126 -> 0.00084663876 | AD58: =U58*K58 -> 339.78 | AE58: 775.21 | AF58: =IF(AA58=0,0,AE58/AA58) -> 0.37305582 | AG58: 1005.52 | AH58: 460 | AI58: 1447 | AL58: =IFERROR($AL$126*H58/$H$126,0) -> 25.150159 | AM58: 0 | AN58: =X58*5.71% -> 75.0865 | AO58: =AA58-AD58-AE58-AG58-AH58-AI58-AK58-AL58-AN58-AM58 -> -2049.7467 | AQ58: =IF(U58=0,0,AA58/U58) -> 1039 | AR58: =K58 -> 169.89 | AS58: =IF(U58=0,0,AE58/U58) -> 387.605 | AT58: =IF(S58=0,AG58/1,AG58/S58) -> 335.17333 | AU58: =IF(S58=0,0,(AH58+AI58+AJ58)/S58) -> 635.66667 | AV58: {=_xlfn.IFS(U58=0,AO58,U58<0,AO58/-U58,U58>0,AO58/U58)} -> -1024.8733 | AW58: =IF(AQ58=0,0,AV58/AQ58) -> -0.98640359 | AX58: =IF(AR58=0,0,AV58/AR58) -> -6.0325701 | AZ58: =AV58*E58 -> -42019.807
A59: Ridges | B59: 431399167 | C59: MANNA2106 | D59: Солнцезащитные очки | E59: =SUM(F59:J59) -> 1 | F59: 0 | G59: 0 | H59: 0 | I59: 0 | J59: 1 | K59: 158.19 | L59: =E59*K59 -> 158.19 | M59: 0 | N59: 0 | O59: 0 | P59: 0 | Q59: =N59/7 -> 0 | R59: =U59/7 -> 0 | S59: 0 | T59: 0 | U59: =S59+T59 -> 0 | V59: 0 | W59: 0 | X59: =V59+W59 -> 0 | Y59: 0 | Z59: 0 | AA59: =Y59+Z59 -> 0 | AB59: =N59*O59*P59/100 -> 0 | AC59: =AA59/$AA$126 -> 0 | AD59: =U59*K59 -> 0 | AE59: 0 | AF59: =IF(AA59=0,0,AE59/AA59) -> 0 | AG59: 0 | AL59: =IFERROR($AL$126*H59/$H$126,0) -> 0 | AM59: 0 | AN59: =X59*5.71% -> 0 | AO59: =AA59-AD59-AE59-AG59-AH59-AI59-AK59-AL59-AN59-AM59 -> 0 | AQ59: =IF(U59=0,0,AA59/U59) -> 0 | AR59: =K59 -> 158.19 | AS59: =IF(U59=0,0,AE59/U59) -> 0 | AT59: =IF(S59=0,AG59/1,AG59/S59) -> 0 | AU59: =IF(S59=0,0,(AH59+AI59+AJ59)/S59) -> 0 | AV59: {=_xlfn.IFS(U59=0,AO59,U59<0,AO59/-U59,U59>0,AO59/U59)} -> 0 | AW59: =IF(AQ59=0,0,AV59/AQ59) -> 0 | AX59: =IF(AR59=0,0,AV59/AR59) -> 0 | AZ59: =AV59*E59 -> 0
A60: Ridges | B60: 431399543 | C60: MANNA2107 | D60: Солнцезащитные очки | E60: =SUM(F60:J60) -> 69 | G60: 5 | H60: 23 | I60: 0 | J60: 41 | K60: 158.19 | L60: =E60*K60 -> 10915.11 | M60: 156 | N60: 3 | O60: 1049 | P60: 67 | Q60: =N60/7 -> 0.42857143 | R60: =U60/7 -> 0.28571429 | S60: 2 | T60: 0 | U60: =S60+T60 -> 2 | V60: 1270 | W60: 0 | X60: =V60+W60 -> 1270 | Y60: 2066.53 | Z60: 0 | AA60: =Y60+Z60 -> 2066.53 | AB60: =N60*O60*P60/100 -> 2108.49 | AC60: =AA60/$AA$126 -> 0.00084196554 | AD60: =U60*K60 -> 316.38 | AE60: 756.67 | AF60: =IF(AA60=0,0,AE60/AA60) -> 0.36615486 | AG60: 313.86 | AL60: =IFERROR($AL$126*H60/$H$126,0) -> 19.946678 | AM60: 0 | AN60: =X60*5.71% -> 72.517 | AO60: =AA60-AD60-AE60-AG60-AH60-AI60-AK60-AL60-AN60-AM60 -> 587.15632 | AQ60: =IF(U60=0,0,AA60/U60) -> 1033.265 | AR60: =K60 -> 158.19 | AS60: =IF(U60=0,0,AE60/U60) -> 378.335 | AT60: =IF(S60=0,AG60/1,AG60/S60) -> 156.93 | AU60: =IF(S60=0,0,(AH60+AI60+AJ60)/S60) -> 0 | AV60: {=_xlfn.IFS(U60=0,AO60,U60<0,AO60/-U60,U60>0,AO60/U60)} -> 293.57816 | AW60: =IF(AQ60=0,0,AV60/AQ60) -> 0.28412669 | AX60: =IF(AR60=0,0,AV60/AR60) -> 1.8558579 | AZ60: =AV60*E60 -> 20256.893
A61: Ridges | B61: 431399941 | C61: MANNA2108 | D61: Солнцезащитные очки | E61: =SUM(F61:J61) -> 484 | H61: 163 | I61: 0 | J61: 321 | K61: 128.94 | L61: =E61*K61 -> 62406.96 | M61: 999 | N61: 0 | O61: 0 | P61: 0 | Q61: =N61/7 -> 0 | R61: =U61/7 -> 0 | S61: 0 | T61: 0 | U61: =S61+T61 -> 0 | V61: 0 | W61: 0 | X61: =V61+W61 -> 0 | Y61: 0 | Z61: 0 | AA61: =Y61+Z61 -> 0 | AB61: =N61*O61*P61/100 -> 0 | AC61: =AA61/$AA$126 -> 0 | AD61: =U61*K61 -> 0 | AE61: 0 | AF61: =IF(AA61=0,0,AE61/AA61) -> 0 | AG61: 93.93 | AL61: =IFERROR($AL$126*H61/$H$126,0) -> 141.36124 | AM61: 0 | AN61: =X61*5.71% -> 0 | AO61: =AA61-AD61-AE61-AG61-AH61-AI61-AK61-AL61-AN61-AM61 -> -235.29124 | AQ61: =IF(U61=0,0,AA61/U61) -> 0 | AR61: =K61 -> 128.94 | AS61: =IF(U61=0,0,AE61/U61) -> 0 | AT61: =IF(S61=0,AG61/1,AG61/S61) -> 93.93 | AU61: =IF(S61=0,0,(AH61+AI61+AJ61)/S61) -> 0 | AV61: {=_xlfn.IFS(U61=0,AO61,U61<0,AO61/-U61,U61>0,AO61/U61)} -> -235.29124 | AW61: =IF(AQ61=0,0,AV61/AQ61) -> 0 | AX61: =IF(AR61=0,0,AV61/AR61) -> -1.8248118 | AZ61: =AV61*E61 -> -113880.96
A62: Ridges | B62: 431401135 | C62: MANNA2109 | D62: Солнцезащитные очки | E62: =SUM(F62:J62) -> 1 | F62: 0 | G62: 0 | H62: 0 | I62: 0 | J62: 1 | K62: 175.74 | L62: =E62*K62 -> 175.74 | M62: 0 | N62: 0 | O62: 0 | P62: 0 | Q62: =N62/7 -> 0 | R62: =U62/7 -> 0 | S62: 0 | T62: 0 | U62: =S62+T62 -> 0 | V62: 0 | W62: 0 | X62: =V62+W62 -> 0 | Y62: 0 | Z62: 0 | AA62: =Y62+Z62 -> 0 | AB62: =N62*O62*P62/100 -> 0 | AC62: =AA62/$AA$126 -> 0 | AD62: =U62*K62 -> 0 | AE62: 0 | AF62: =IF(AA62=0,0,AE62/AA62) -> 0 | AG62: 0 | AL62: =IFERROR($AL$126*H62/$H$126,0) -> 0 | AM62: 0 | AN62: =X62*5.71% -> 0 | AO62: =AA62-AD62-AE62-AG62-AH62-AI62-AK62-AL62-AN62-AM62 -> 0 | AQ62: =IF(U62=0,0,AA62/U62) -> 0 | AR62: =K62 -> 175.74 | AS62: =IF(U62=0,0,AE62/U62) -> 0 | AT62: =IF(S62=0,AG62/1,AG62/S62) -> 0 | AU62: =IF(S62=0,0,(AH62+AI62+AJ62)/S62) -> 0 | AV62: {=_xlfn.IFS(U62=0,AO62,U62<0,AO62/-U62,U62>0,AO62/U62)} -> 0 | AW62: =IF(AQ62=0,0,AV62/AQ62) -> 0 | AX62: =IF(AR62=0,0,AV62/AR62) -> 0 | AZ62: =AV62*E62 -> 0
A63: Ridges | B63: 431401715 | C63: MANNA2110 | D63: Солнцезащитные очки | E63: =SUM(F63:J63) -> 3 | F63: 0 | G63: 0 | H63: 0 | I63: 0 | J63: 3 | K63: 140.64 | L63: =E63*K63 -> 421.92 | M63: 0 | N63: 0 | O63: 0 | P63: 0 | Q63: =N63/7 -> 0 | R63: =U63/7 -> 0 | S63: 0 | T63: 0 | U63: =S63+T63 -> 0 | V63: 0 | W63: 0 | X63: =V63+W63 -> 0 | Y63: 0 | Z63: 0 | AA63: =Y63+Z63 -> 0 | AB63: =N63*O63*P63/100 -> 0 | AC63: =AA63/$AA$126 -> 0 | AD63: =U63*K63 -> 0 | AE63: 0 | AF63: =IF(AA63=0,0,AE63/AA63) -> 0 | AG63: 0 | AL63: =IFERROR($AL$126*H63/$H$126,0) -> 0 | AM63: 0 | AN63: =X63*5.71% -> 0 | AO63: =AA63-AD63-AE63-AG63-AH63-AI63-AK63-AL63-AN63-AM63 -> 0 | AQ63: =IF(U63=0,0,AA63/U63) -> 0 | AR63: =K63 -> 140.64 | AS63: =IF(U63=0,0,AE63/U63) -> 0 | AT63: =IF(S63=0,AG63/1,AG63/S63) -> 0 | AU63: =IF(S63=0,0,(AH63+AI63+AJ63)/S63) -> 0 | AV63: {=_xlfn.IFS(U63=0,AO63,U63<0,AO63/-U63,U63>0,AO63/U63)} -> 0 | AW63: =IF(AQ63=0,0,AV63/AQ63) -> 0 | AX63: =IF(AR63=0,0,AV63/AR63) -> 0 | AZ63: =AV63*E63 -> 0
A64: Ridges | B64: 431402918 | C64: MANNA2111 | D64: Солнцезащитные очки | E64: =SUM(F64:J64) -> 1 | F64: 0 | G64: 0 | H64: 0 | I64: 0 | J64: 1 | K64: 99.69 | L64: =E64*K64 -> 99.69 | M64: 0 | N64: 0 | O64: 0 | P64: 0 | Q64: =N64/7 -> 0 | R64: =U64/7 -> 0 | S64: 0 | T64: 0 | U64: =S64+T64 -> 0 | V64: 0 | W64: 0 | X64: =V64+W64 -> 0 | Y64: 0 | Z64: 0 | AA64: =Y64+Z64 -> 0 | AB64: =N64*O64*P64/100 -> 0 | AC64: =AA64/$AA$126 -> 0 | AD64: =U64*K64 -> 0 | AE64: 0 | AF64: =IF(AA64=0,0,AE64/AA64) -> 0 | AG64: 0 | AL64: =IFERROR($AL$126*H64/$H$126,0) -> 0 | AM64: 0 | AN64: =X64*5.71% -> 0 | AO64: =AA64-AD64-AE64-AG64-AH64-AI64-AK64-AL64-AN64-AM64 -> 0 | AQ64: =IF(U64=0,0,AA64/U64) -> 0 | AR64: =K64 -> 99.69 | AS64: =IF(U64=0,0,AE64/U64) -> 0 | AT64: =IF(S64=0,AG64/1,AG64/S64) -> 0 | AU64: =IF(S64=0,0,(AH64+AI64+AJ64)/S64) -> 0 | AV64: {=_xlfn.IFS(U64=0,AO64,U64<0,AO64/-U64,U64>0,AO64/U64)} -> 0 | AW64: =IF(AQ64=0,0,AV64/AQ64) -> 0 | AX64: =IF(AR64=0,0,AV64/AR64) -> 0 | AZ64: =AV64*E64 -> 0
A65: Ridges | B65: 431405619 | C65: MANNA2112 | D65: Солнцезащитные очки | E65: =SUM(F65:J65) -> 2 | H65: 1 | I65: 0 | J65: 1 | K65: 99.69 | L65: =E65*K65 -> 199.38 | M65: 999 | N65: 0 | O65: 0 | P65: 0 | Q65: =N65/7 -> 0 | R65: =U65/7 -> 0 | S65: 0 | T65: 0 | U65: =S65+T65 -> 0 | V65: 0 | W65: 0 | X65: =V65+W65 -> 0 | Y65: 0 | Z65: 0 | AA65: =Y65+Z65 -> 0 | AB65: =N65*O65*P65/100 -> 0 | AC65: =AA65/$AA$126 -> 0 | AD65: =U65*K65 -> 0 | AE65: 0 | AF65: =IF(AA65=0,0,AE65/AA65) -> 0 | AG65: 96.4 | AL65: =IFERROR($AL$126*H65/$H$126,0) -> 0.86724686 | AM65: 0 | AN65: =X65*5.71% -> 0 | AO65: =AA65-AD65-AE65-AG65-AH65-AI65-AK65-AL65-AN65-AM65 -> -97.267247 | AQ65: =IF(U65=0,0,AA65/U65) -> 0 | AR65: =K65 -> 99.69 | AS65: =IF(U65=0,0,AE65/U65) -> 0 | AT65: =IF(S65=0,AG65/1,AG65/S65) -> 96.4 | AU65: =IF(S65=0,0,(AH65+AI65+AJ65)/S65) -> 0 | AV65: {=_xlfn.IFS(U65=0,AO65,U65<0,AO65/-U65,U65>0,AO65/U65)} -> -97.267247 | AW65: =IF(AQ65=0,0,AV65/AQ65) -> 0 | AX65: =IF(AR65=0,0,AV65/AR65) -> -0.97569713 | AZ65: =AV65*E65 -> -194.53449
A66: Ridges | B66: 431408292 | C66: MANNA2113 | D66: Солнцезащитные очки | E66: =SUM(F66:J66) -> 2 | H66: 1 | I66: 0 | J66: 1 | K66: 97.35 | L66: =E66*K66 -> 194.7 | M66: 47 | N66: 0 | O66: 0 | P66: 0 | Q66: =N66/7 -> 0 | R66: =U66/7 -> 0 | S66: 0 | T66: 0 | U66: =S66+T66 -> 0 | V66: 0 | W66: 0 | X66: =V66+W66 -> 0 | Y66: 0 | Z66: 0 | AA66: =Y66+Z66 -> 0 | AB66: =N66*O66*P66/100 -> 0 | AC66: =AA66/$AA$126 -> 0 | AD66: =U66*K66 -> 0 | AE66: 0 | AF66: =IF(AA66=0,0,AE66/AA66) -> 0 | AG66: 0 | AL66: =IFERROR($AL$126*H66/$H$126,0) -> 0.86724686 | AM66: 0 | AN66: =X66*5.71% -> 0 | AO66: =AA66-AD66-AE66-AG66-AH66-AI66-AK66-AL66-AN66-AM66 -> -0.86724686 | AQ66: =IF(U66=0,0,AA66/U66) -> 0 | AR66: =K66 -> 97.35 | AS66: =IF(U66=0,0,AE66/U66) -> 0 | AT66: =IF(S66=0,AG66/1,AG66/S66) -> 0 | AU66: =IF(S66=0,0,(AH66+AI66+AJ66)/S66) -> 0 | AV66: {=_xlfn.IFS(U66=0,AO66,U66<0,AO66/-U66,U66>0,AO66/U66)} -> -0.86724686 | AW66: =IF(AQ66=0,0,AV66/AQ66) -> 0 | AX66: =IF(AR66=0,0,AV66/AR66) -> -0.008908545 | AZ66: =AV66*E66 -> -1.7344937
A67: Ridges | B67: 431411210 | C67: MANNA2114 | D67: Солнцезащитные очки | E67: =SUM(F67:J67) -> 3 | F67: 2 | I67: 0 | J67: 1 | K67: 161.7 | L67: =E67*K67 -> 485.1 | M67: 12 | N67: 1 | O67: 1049 | P67: 0 | Q67: =N67/7 -> 0.14285714 | R67: =U67/7 -> 0.28571429 | S67: 2 | T67: 0 | U67: =S67+T67 -> 2 | V67: 1305 | W67: 0 | X67: =V67+W67 -> 1305 | Y67: 2098 | Z67: 0 | AA67: =Y67+Z67 -> 2098 | AB67: =N67*O67*P67/100 -> 0 | AC67: =AA67/$AA$126 -> 0.00085478736 | AD67: =U67*K67 -> 323.4 | AE67: 781.95 | AF67: =IF(AA67=0,0,AE67/AA67) -> 0.37271211 | AG67: 216.94 | AL67: =IFERROR($AL$126*H67/$H$126,0) -> 0 | AM67: 0 | AN67: =X67*5.71% -> 74.5155 | AO67: =AA67-AD67-AE67-AG67-AH67-AI67-AK67-AL67-AN67-AM67 -> 701.1945 | AQ67: =IF(U67=0,0,AA67/U67) -> 1049 | AR67: =K67 -> 161.7 | AS67: =IF(U67=0,0,AE67/U67) -> 390.975 | AT67: =IF(S67=0,AG67/1,AG67/S67) -> 108.47 | AU67: =IF(S67=0,0,(AH67+AI67+AJ67)/S67) -> 0 | AV67: {=_xlfn.IFS(U67=0,AO67,U67<0,AO67/-U67,U67>0,AO67/U67)} -> 350.59725 | AW67: =IF(AQ67=0,0,AV67/AQ67) -> 0.33422045 | AX67: =IF(AR67=0,0,AV67/AR67) -> 2.1681957 | AZ67: =AV67*E67 -> 1051.7918
