Workbook

Sheet Реклама
B2: БАЛАНС | E2: СЧЕТ | H2: ПРОМОБОНУСЫ | K2: Неделя
B3: Номер документа | C3: Сумма | D3: Даты | E3: Номер документа | F3: Сумма | G3: Даты | H3: Номер документа | I3: Сумма | J3: Даты
B4: 277433850 | C4: 1376 | D4: 28-31.12 | E4: 277433847 | F4: 25829 | G4: 28-31.12 | H4: 0 | I4: 109 | J4: 29-31.12 | K4: 1
B5: 277539131 | C5: 1150 | D5: 36951 | E5: 277609313 | F5: 21489 | G5: 36982 | H5: 0 | I5: 363 | J5: 36982
B6: 279208603 | C6: 3455 | D6: 37168 | E6: 279208599 | F6: 51313 | G6: 37199 | H6: 0 | I6: 569 | J6: 37200 | K6: 2
B7: 280269091 | C7: 10268 | D7: 11-18.01 | E7: 280221209 | F7: 99763 | G7: 11-18.01 | H7: 0 | I7: 557 | J7: 12-18.01 | K7: 3
B8: 281267335 | C8: 70408 | D8: 19-25.01 | E8: 281348313 | F8: 67741 | G8: 18-25.01 | H8: 0 | I8: 195 | J8: 19-25.01 | K8: 4
B9: 282258474 | C9: 25521 | D9: 25-31.01 | E9: 282345086 | F9: 133680 | G9: 25-31.01 | H9: 0 | I9: 80 | J9: 26-31.01 | K9: 5
B10: 282365257 | C10: 1268 | D10: 46054 | E10: 282392960 | F10: 4672 | G10: 46054
B11: 283332206 | C11: 111419 | D11: 37469 | E11: 283415801 | F11: 126688 | G11: 37469 | H11: 0 | I11: 3554 | J11: 37440 | K11: 6
B12: 284423647 | C12: 145581 | D12: 08-15.02 | E12: 284416459 | F12: 138670 | G12: 08-15.02 | H12: 0 | I12: 44 | J12: 46063 | K12: 7
B13: 285348588 | C13: 50989 | D13: 15-22.02 | E13: 285348587 | F13: 265182 | G13: 15-22.02 | K13: 8
B14: 286343097 | C14: 232417 | D14: 22-28.02 | E14: 286343091 | F14: 72806 | G14: 22-28.02 | H14: 0 | I14: 26 | J14: 46081 | K14: 9
B15: 286459024 | C15: 1243 | D15: 46082 | E15: 286489905 | F15: 5815 | G15: 46082
B16: 287708507 | C16: 74484 | D16: 01.03-08.03 | E16: 287655729 | F16: 252853 | G16: 01.03-08.03 | K16: 10
B17: 288763309 | C17: 304803 | D17: 08-15.03 | E17: 288777227 | F17: 178004 | G17: 08-15.03 | H17: 0 | I17: 46 | J17: 46091 | K17: 11
B18: 289700671 | C18: 48225 | D18: 15-22.03 | E18: 289749174 | F18: 468432 | G18: 15-22.03 | K18: 12
B19: 290703200 | C19: 88346 | D19: 22-29.03 | E19: 290753220 | F19: 464760 | G19: 22-29.03 | K19: 13
B20: 291680098 | C20: 7470 | D20: 29-31.03 | E20: 291680097 | F20: 197884 | G20: 29-31.03 | K20: 14
B21: 291826234 | C21: 2212 | D21: 1.04-05.04 | E21: 291909845 | F21: 303004 | G21: 01.04-05.04
B22: 292843081 | C22: 2405 | D22: 05.04-10.04 | E22: 292896526 | F22: 301236 | G22: 05.10-12.04 | K22: 15
B23: 293929962 | C23: 43580 | D23: 12-19.04 | E23: 293877308 | F23: 287584 | G23: 12-19.04 | K23: 16
B24: 294860190 | C24: 6217 | D24: 19-26.04 | E24: 294949927 | F24: 172288 | G24: 19-26.04 | H24: 0 | I24: 215420 | J24: 22-26.04 | K24: 17
B25: 295827714 | C25: 820 | D25: 27-30.04 | E25: 295827712 | F25: 21338 | G25: 26-30.04 | H25: 0 | I25: 100588 | J25: 27-30.04 | K25: 18
B26: 296028599 | C26: 157 | D26: 46143 | E26: 296042023 | F26: 5286 | G26: 01.05-03.05 | H26: 0 | I26: 93678 | J26: 01.05-03.05
B27: 296942084 | C27: 320 | D27: 03.05-09.05 | E27: 296986662 | F27: 17442 | G27: 03.05-10.05 | H27: 0 | I27: 329393 | J27: 04.05-10.05 | K27: 19
H39: .

Sheet Сводная_план
B2: Период | E2: Дата поступления дс | F2: Итого к перечислению на счет, руб | G2: шт. | J2: ВБ реализовал товар (выручка с СПП) | M2: Выручка до вычета комиссии ВБ | P2: Себестоимость продаж | Q2: Логистика WB | R2: Комиссия WB | S2: Хранение WB | T2: Платная приемка WB | U2: Штрафы WB | V2: Прочие удержания WB | W2: Реклама БАЛАНС | X2: Реклама СЧЕТ | Y2: Реклама ПРОМОБОНУСЫ | Z2: Блогеры | AA2: Стоимость участия в программе лояльности | AB2: Сумма удержанная за начисленные баллы программы лояльности | AC2: Налог | AD2: Прочие поступления WB | AE2: Прибыль до вычета налогов | AF2: Прибыль после вычета налогов | AG2: Итог месяц | AH2: % Cебестоимости | AI2: Маржинальность, % | AJ2: Рентабельность, % | AK2: Доля рекламы, %
B3: Месяц | C3: Даты | D3: Нед | G3: Заказы | H3: Продажи | I3: Возвраты | J3: Продажи | K3: Возвраты | L3: Общая | M3: Продажи | N3: Возвраты | O3: Общая
B4: Декабрь очки | C4: 29-31.12 | D4: 1 | F4: =IFERROR(O4-SUM(Q4:W4)+AD4,0) -> 0 | AG4: =SUM(AF4:AF5) -> 0 | AH4: =P4/O4 -> #DIV/0! | AI4: =AF4/P4 -> #DIV/0! | AJ4: =AF4/O4 -> #DIV/0! | AK4: =(W4+X4+Z4)/O4 -> #DIV/0!
B5: Декабрь туники | C5: 29-31.12 | D5: 1 | F5: =IFERROR(O5-SUM(Q5:W5)+AD5,0) -> 0 | AH5: =P5/O5 -> #DIV/0! | AI5: =AF5/P5 -> #DIV/0! | AJ5: =AF5/O5 -> #DIV/0! | AK5: =(W5+X5+Z5)/O5 -> #DIV/0!
B6: Январь очки | C6: 01.01-01.02 | D6: 1-5 | F6: =IFERROR(O6-SUM(Q6:W6)+AD6,0) -> 0 | AG6: =SUM(AF6:AF8) -> 0 | AH6: =P6/O6 -> #DIV/0! | AI6: =AF6/P6 -> #DIV/0! | AJ6: =AF6/O6 -> #DIV/0! | AK6: =(W6+X6+Z6)/O6 -> #DIV/0!
B7: Январь туники | C7: 01.01-01.02 | D7: 1-5 | F7: =IFERROR(O7-SUM(Q7:W7)+AD7,0) -> 0 | AH7: =P7/O7 -> #DIV/0! | AI7: =AF7/P7 -> #DIV/0! | AJ7: =AF7/O7 -> #DIV/0! | AK7: =(W7+X7+Z7)/O7 -> #DIV/0!
B8: Январь шапки | C8: 01.01-01.02 | D8: 1-5 | F8: =IFERROR(O8-SUM(Q8:W8)+AD8,0) -> 0 | AH8: =P8/O8 -> #DIV/0! | AI8: =AF8/P8 -> #DIV/0! | AJ8: =AF8/O8 -> #DIV/0! | AK8: =(W8+X8+Z8)/O8 -> #DIV/0!
B9: Февраль 1 очки | C9: 02-08.02 | D9: 6 | F9: =IFERROR(O9-SUM(Q9:W9)+AD9,0) -> 0 | AG9: =SUM(AF9:AF16) -> 0 | AH9: =P9/O9 -> #DIV/0! | AI9: =AF9/P9 -> #DIV/0! | AJ9: =AF9/O9 -> #DIV/0! | AK9: =(W9+X9+Z9)/O9 -> #DIV/0!
B10: Февраль 1 туники | C10: 02-08.02 | D10: 6 | F10: =IFERROR(O10-SUM(Q10:W10)+AD10,0) -> 0 | AH10: =P10/O10 -> #DIV/0! | AI10: =AF10/P10 -> #DIV/0! | AJ10: =AF10/O10 -> #DIV/0! | AK10: =(W10+X10+Z10)/O10 -> #DIV/0!
B11: Февраль 2 очки | C11: 09-15.02 | D11: 7 | F11: =IFERROR(O11-SUM(Q11:W11)+AD11,0) -> 0 | AH11: =P11/O11 -> #DIV/0! | AI11: =AF11/P11 -> #DIV/0! | AJ11: =AF11/O11 -> #DIV/0! | AK11: =(W11+X11+Z11)/O11 -> #DIV/0!
B12: Февраль 2 туники | C12: 09-15.02 | D12: 7 | F12: =IFERROR(O12-SUM(Q12:W12)+AD12,0) -> 0 | AH12: =P12/O12 -> #DIV/0! | AI12: =AF12/P12 -> #DIV/0! | AJ12: =AF12/O12 -> #DIV/0! | AK12: =(W12+X12+Z12)/O12 -> #DIV/0!
B13: Февраль 3 очки | C13: 16-22.02 | D13: 8 | F13: =IFERROR(O13-SUM(Q13:W13)+AD13,0) -> 0 | AH13: =P13/O13 -> #DIV/0! | AI13: =AF13/P13 -> #DIV/0! | AJ13: =AF13/O13 -> #DIV/0! | AK13: =(W13+X13+Z13)/O13 -> #DIV/0!
B14: Февраль 3 туники | C14: 16-22.02 | D14: 8 | F14: =IFERROR(O14-SUM(Q14:W14)+AD14,0) -> 0 | AH14: =P14/O14 -> #DIV/0! | AI14: =AF14/P14 -> #DIV/0! | AJ14: =AF14/O14 -> #DIV/0! | AK14: =(W14+X14+Z14)/O14 -> #DIV/0!
B15: Февраль 4 очки | C15: 23.02-01.03 | D15: 9 | F15: =IFERROR(O15-SUM(Q15:W15)+AD15,0) -> 0 | AH15: =P15/O15 -> #DIV/0! | AI15: =AF15/P15 -> #DIV/0! | AJ15: =AF15/O15 -> #DIV/0! | AK15: =(W15+X15+Z15)/O15 -> #DIV/0!
B16: Февраль 4 прочее | C16: 23.02-01.03 | D16: 9 | F16: =IFERROR(O16-SUM(Q16:W16)+AD16,0) -> 0 | AH16: =P16/O16 -> #DIV/0! | AI16: =AF16/P16 -> #DIV/0! | AJ16: =AF16/O16 -> #DIV/0! | AK16: =(W16+X16+Z16)/O16 -> #DIV/0!
B17: Март 1 очки | C17: 02-08.03 | D17: 10 | F17: =IFERROR(O17-SUM(Q17:W17)+AD17,0) -> 0 | AG17: =SUM(AF17:AF20) -> 0 | AH17: =P17/O17 -> #DIV/0! | AI17: =AF17/P17 -> #DIV/0! | AJ17: =AF17/O17 -> #DIV/0! | AK17: =(W17+X17+Z17)/O17 -> #DIV/0!
B18: Март 2 очки | C18: 09-15.03 | D18: 11 | F18: =IFERROR(O18-SUM(Q18:W18)+AD18,0) -> 0 | AH18: =P18/O18 -> #DIV/0! | AI18: =AF18/P18 -> #DIV/0! | AJ18: =AF18/O18 -> #DIV/0! | AK18: =(W18+X18+Z18)/O18 -> #DIV/0!
B19: Март 3 очки | C19: 16-22.03 | D19: 12 | F19: =IFERROR(O19-SUM(Q19:W19)+AD19,0) -> 0 | AH19: =P19/O19 -> #DIV/0! | AI19: =AF19/P19 -> #DIV/0! | AJ19: =AF19/O19 -> #DIV/0! | AK19: =(W19+X19+Z19)/O19 -> #DIV/0!
B20: Март 4 очки | C20: 23-29.03 | D20: 13 | F20: =IFERROR(O20-SUM(Q20:W20)+AD20,0) -> 0 | AH20: =P20/O20 -> #DIV/0! | AI20: =AF20/P20 -> #DIV/0! | AJ20: =AF20/O20 -> #DIV/0! | AK20: =(W20+X20+Z20)/O20 -> #DIV/0!
B21: Апрель 1 очки | C21: 30.03-05.04 | D21: 14 | F21: =IFERROR(O21-SUM(Q21:W21)-AA21-AB21+AD21,0) -> 2248396 | G21: ='Юнит 14'!N$125 -> 4971 | H21: ='Юнит 14'!S$125 -> 2810 | I21: ='Юнит 14'!T$125 -> -71 | J21: ='Юнит 14'!V$125 -> 2849625.8 | K21: ='Юнит 14'!W$125 -> -71864.03 | L21: =IFERROR(J21+K21,0) -> 2777761.8 | M21: ='Юнит 14'!Y$125 -> 4320373.6 | N21: ='Юнит 14'!Z$125 -> -108465.8 | O21: =IFERROR(M21+N21,0) -> 4211907.8 | P21: ='Юнит 14'!AD$125 -> 339512.76 | Q21: ='Юнит 14'!AG$125 -> 363484.23 | R21: ='Юнит 14'!AE$125 -> 1585688.2 | S21: ='Юнит 14'!AL$125 -> 6774.7746 | U21: ='Юнит 14'!AM$125 -> 950 | V21: 702.72 | W21: ='Юнит 14'!AH$125 -> 4494 | X21: ='Юнит 14'!AI$125 -> 455354 | Z21: ='Юнит 14'!AK$125 -> 0 | AA21: 128.9 | AB21: 1289 | AC21: ='Юнит 14'!AN$125 -> 158610.2 | AE21: =O21-SUM(P21:AB21)+AD21 -> 1453529.2 | AF21: =O21-SUM(P21:AC21)+AD21 -> 1294919 | AH21: =P21/O21 -> 0.080607833 | AI21: =AF21/P21 -> 3.8140511 | AJ21: =AF21/O21 -> 0.30744239 | AK21: =(W21+X21+Z21)/O21 -> 0.10917808
B22: Апрель 2 очки | C22: 06-12.04 | D22: 15 | F22: =IFERROR(O22-SUM(Q22:W22)-AA22-AB22+AD22,0) -> 1600934.5 | G22: ='Юнит 15'!N$125 -> 3297 | H22: ='Юнит 15'!S$125 -> 2059 | I22: ='Юнит 15'!T$125 -> -47 | J22: ='Юнит 15'!V$125 -> 2106763.1 | K22: ='Юнит 15'!W$125 -> -48891.37 | L22: =IFERROR(J22+K22,0) -> 2057871.7 | M22: ='Юнит 15'!Y$125 -> 3166314.9 | N22: ='Юнит 15'!Z$125 -> -74091.17 | O22: =IFERROR(M22+N22,0) -> 3092223.7 | P22: ='Юнит 15'!AD$125 -> 248851.65 | Q22: ='Юнит 15'!AG$125 -> 274874.64 | R22: ='Юнит 15'!AE$125 -> 1169082.7 | S22: ='Юнит 15'!AL$125 -> 7404.9464 | U22: ='Юнит 15'!AM$125 -> 4873.98 | V22: 22990 | W22: ='Юнит 15'!AH$125 -> 2405 | X22: ='Юнит 15'!AI$125 -> 289210 | Z22: ='Юнит 15'!AK$125 -> 0 | AA22: 878 | AB22: 8780 | AC22: ='Юнит 15'!AN$125 -> 117504.47 | AE22: =O22-SUM(P22:AB22)+AD22 -> 1062872.9 | AF22: =O22-SUM(P22:AC22)+AD22 -> 945368.38 | AH22: =P22/O22 -> 0.080476599 | AI22: =AF22/P22 -> 3.7989235 | AJ22: =AF22/O22 -> 0.30572444 | AK22: =(W22+X22+Z22)/O22 -> 0.094305918
B23: Апрель 3 очки | C23: 13-19.04 | D23: 16 | F23: =IFERROR(O23-SUM(Q23:W23)-AA23-AB23+AD23,0) -> 1437469 | G23: ='Юнит 16'!N$126 -> 3224 | H23: ='Юнит 16'!S$126 -> 1892 | I23: ='Юнит 16'!T$126 -> -41 | J23: ='Юнит 16'!V$126 -> 1903067.3 | K23: ='Юнит 16'!W$126 -> -40767.59 | L23: =IFERROR(J23+K23,0) -> 1862299.7 | M23: ='Юнит 16'!Y$126 -> 2844861.5 | N23: ='Юнит 16'!Z$126 -> -60944.33 | O23: =IFERROR(M23+N23,0) -> 2783917.2 | P23: ='Юнит 16'!AD$126 -> 228955.77 | Q23: ='Юнит 16'!AG$126 -> 234083.09 | R23: ='Юнит 16'!AE$126 -> 1050005.8 | S23: ='Юнит 16'!AL$126 -> 9009.0466 | U23: ='Юнит 16'!AM$126 -> 2269 | W23: ='Юнит 16'!AH$126 -> 41816 | X23: ='Юнит 16'!AI$126 -> 275395 | Z23: ='Юнит 16'!AK$126 -> 0 | AA23: 842.3 | AB23: 8423 | AC23: ='Юнит 16'!AN$126 -> 106337.31 | AE23: =O23-SUM(P23:AB23)+AD23 -> 933118.2 | AF23: =O23-SUM(P23:AC23)+AD23 -> 826780.89 | AH23: =P23/O23 -> 0.082242306 | AI23: =AF23/P23 -> 3.6110944 | AJ23: =AF23/O23 -> 0.29698473 | AK23: =(W23+X23+Z23)/O23 -> 0.11394412
B24: Апрель 4 очки | C24: 20-26.04 | D24: 17 | F24: =IFERROR(O24-SUM(Q24:W24)-AA24-AB24+AD24,0) -> 1205095.8 | G24: ='Юнит 17'!N$126 -> 2848 | H24: ='Юнит 17'!S$126 -> 1645 | I24: ='Юнит 17'!T$126 -> -32 | J24: ='Юнит 17'!V$126 -> 1612009.3 | K24: ='Юнит 17'!W$126 -> -33188 | L24: =IFERROR(J24+K24,0) -> 1578821.3 | M24: ='Юнит 17'!Y$126 -> 2353906.9 | N24: ='Юнит 17'!Z$126 -> -49562.13 | O24: =IFERROR(M24+N24,0) -> 2304344.8 | P24: ='Юнит 17'!AD$126 -> 199750.44 | Q24: ='Юнит 17'!AG$126 -> 210197.66 | R24: ='Юнит 17'!AE$126 -> 872396.09 | S24: ='Юнит 17'!AL$126 -> 8583.5482 | U24: ='Юнит 17'!AM$126 -> 1310 | W24: ='Юнит 17'!AH$126 -> 5159 | X24: ='Юнит 17'!AI$126 -> 163766 | Y24: ='Юнит 17'!AJ126 -> 212040 | Z24: ='Юнит 17'!AK$126 -> 0 | AA24: 145.7 | AB24: 1457 | AC24: ='Юнит 17'!AN$126 -> 90150.697 | AE24: =O24-SUM(P24:AB24)+AD24 -> 629539.36 | AF24: =O24-SUM(P24:AC24)+AD24 -> 539388.66 | AH24: =P24/O24 -> 0.086684267 | AI24: =AF24/P24 -> 2.7003128 | AJ24: =AF24/O24 -> 0.23407463 | AK24: =(W24+X24+Z24)/O24 -> 0.073307172
B25: Апрель 5 очки | C25: 27.04-03.05 | D25: 18 | F25: =IFERROR(O25-SUM(Q25:W25)-AA25-AB25+AD25,0) -> 1085604.2 | G25: ='Юнит 18'!N$126 -> 2619 | H25: ='Юнит 18'!S$126 -> 1536 | I25: ='Юнит 18'!T$126 -> -19 | J25: ='Юнит 18'!V$126 -> 1484556 | K25: ='Юнит 18'!W$126 -> -19493.18 | L25: =IFERROR(J25+K25,0) -> 1465062.8 | M25: ='Юнит 18'!Y$126 -> 2086963.8 | N25: ='Юнит 18'!Z$126 -> -27710.54 | O25: =IFERROR(M25+N25,0) -> 2059253.3 | P25: ='Юнит 18'!AD$126 -> 187888.17 | Q25: ='Юнит 18'!AG$126 -> 184328.48 | R25: ='Юнит 18'!AE$126 -> 779957.46 | S25: ='Юнит 18'!AL$126 -> 7221.3259 | U25: ='Юнит 18'!AM$126 -> 1495 | W25: ='Юнит 18'!AH$126 -> 440 | X25: ='Юнит 18'!AI$126 -> 22859 | Y25: ='Юнит 18'!AJ$126 -> 179991 | Z25: ='Юнит 18'!AK$126 -> 0 | AA25: 18.8 | AB25: 188 | AC25: ='Юнит 18'!AN$126 -> 83655.085 | AE25: =O25-SUM(P25:AB25)+AD25 -> 694866.04 | AF25: =O25-SUM(P25:AC25)+AD25 -> 611210.96 | AH25: =P25/O25 -> 0.091240923 | AI25: =AF25/P25 -> 3.2530572 | AJ25: =AF25/O25 -> 0.29681194 | AK25: =(W25+X25+Z25)/O25 -> 0.011314295
B29: Итого | F29: =SUM(F4:F28) -> 7577499.5 | G29: =SUM(G4:G28) -> 16959 | H29: =SUM(H4:H28) -> 9942 | I29: =SUM(I4:I28) -> -210 | J29: =SUM(J4:J28) -> 9956021.4 | K29: =SUM(K4:K28) -> -214204.17 | L29: =SUM(L4:L28) -> 9741817.2 | M29: =SUM(M4:M28) -> 14772421 | ... X29: =SUM(X4:X28) -> 1206584 | Z29: =SUM(Z4:Z28) -> 0 | AC29: =SUM(AC4:AC28) -> 556257.76 | AD29: =SUM(AD4:AD28) -> 0 | AE29: =SUM(AE4:AE28) -> 4773925.7 | AF29: =SUM(AF4:AF28) -> 4217667.9 | AG29: =SUM(AG4:AG28) -> 0 | AH29: =P29/O29 -> 0.083378649 | AI29: =AF29/P29 -> 3.5002591 | AJ29: =AF29/O29 -> 0.29184687 | AK29: =(W29+X29+Z29)/O29 -> 0.087249434
M30: % от выручки за весь период
N31: =-N29/M29 -> 0.021714381 | P31: =P29/$O$29 -> 0.083378649 | Q31: =Q29/$O$29 -> 0.087669462 | R31: =R29/$O$29 -> 0.37761303 | S31: =S29/$O$29 -> 0.0026982144 | T31: =T29/$O$29 -> 0 | U31: =U29/$O$29 -> 0.00075409953 | V31: =V29/$O$29 -> 0.0016394478 | W31: =W29/$O$29 -> 0.003758326 | X31: =X29/$O$29 -> 0.083491108 | Z31: =Z29/$O$29 -> 0 | AC31: =AC29/$O$29 -> 0.03849096 | AG31: =AF29/P29 -> 3.5002591 | AH31: Маржинальность, %
W32: =(W29+X29)/O29 -> 0.087249434 | AG32: =AF29/O29 -> 0.29184687 | AH32: Рентабельность, %
B35: 14 нед | W35: =W21/O21 -> 0.0010669749 | X35: =X21/O21 -> 0.1081111
B36: 15 нед | W36: =W22/O22 -> 0.00077775743 | X36: =X22/O22 -> 0.093528161
B37: 16 нед | W37: =W23/O23 -> 0.015020562 | X37: =X23/O23 -> 0.09892356
B38: 17 нед | W38: =W24/O24 -> 0.0022388143 | X38: =X24/O24 -> 0.071068357 | Y38: =Y24/O24 -> 0.092017479
B39: 18 нед | W39: =W25/O25 -> 0.00021366969 | X39: =X25/O25 -> 0.011100626 | Y39: =Y25/O25 -> 0.087405955
B40: апрель | W40: =SUM(W21:W25)/SUM(O21:O25) -> 0.003758326 | X40: =SUM(X21:X25)/SUM(O21:O25) -> 0.083491108 | Y40: =SUM(Y21:Y25)/SUM(O21:O25) -> 0.027127081

Sheet Сводная
B2: Период | E2: Дата поступления дс | F2: Итого к перечислению на счет, руб | G2: шт. | J2: ВБ реализовал товар (выручка с СПП) | M2: Выручка до вычета комиссии ВБ | P2: Себестоимость продаж | Q2: Логистика WB | R2: Комиссия WB | S2: Хранение WB | T2: Платная приемка WB | U2: Штрафы WB | V2: Прочие удержания WB | W2: Реклама БАЛАНС | X2: Реклама СЧЕТ | Y2: Реклама ПРОМОБОНУСЫ | Z2: Блогеры | AA2: Стоимость участия в программе лояльности | AB2: Сумма удержанная за начисленные баллы программы лояльности | AC2: Налог | AD2: Прочие поступления WB | AE2: Прибыль до вычета налогов | AF2: Прибыль после вычета налогов | AG2: Итог месяц | AH2: % Cебестоимости | AI2: Маржинальность, % | AJ2: Рентабельность, % | AK2: Доля рекламы, %
B3: Месяц | C3: Даты | D3: Нед | G3: Заказы | H3: Продажи | I3: Возвраты | J3: Продажи | K3: Возвраты | L3: Общая | M3: Продажи | N3: Возвраты | O3: Общая
B4: Декабрь очки | C4: 29-31.12 | D4: 1 | F4: =IFERROR(O4-SUM(Q4:W4)+AD4,0) -> 62313.298 | G4: =ДЕКАБРЬ!N100 -> 129 | H4: =ДЕКАБРЬ!S100 -> 127 | I4: =ДЕКАБРЬ!T100 -> -5 | J4: =ДЕКАБРЬ!V100 -> 118047.57 | K4: =ДЕКАБРЬ!W100 -> -6409 | L4: =IFERROR(J4+K4,0) -> 111638.57 | M4: =ДЕКАБРЬ!Y100 -> 138964.57 | N4: =ДЕКАБРЬ!Z100 -> -7526 | O4: =IFERROR(M4+N4,0) -> 131438.57 | P4: =ДЕКАБРЬ!AD100 -> 15240.45 | Q4: =ДЕКАБРЬ!AG100 -> 17381.1 | R4: =ДЕКАБРЬ!AE100 -> 48126.54 | S4: =ДЕКАБРЬ!AL100 -> 3615.9322 | T4: 1.7 | U4: =ДЕКАБРЬ!AM100 -> 0 | W4: =ДЕКАБРЬ!AH100 -> 0 | X4: =ДЕКАБРЬ!AI100 -> 0 | Z4: =ДЕКАБРЬ!AK100 -> 0 | AC4: =ДЕКАБРЬ!AN100 -> 6067.24 | AE4: =O4-SUM(P4:Z4)+AD4 -> 47072.848 | AF4: =O4-SUM(P4:AC4)+AD4 -> 41005.608 | AG4: =SUM(AF4:AF5) -> 41005.32 | AH4: =P4/O4 -> 0.11595112 | AI4: =AF4/P4 -> 2.6905772 | AJ4: =AF4/O4 -> 0.31197546 | AK4: =(W4+X4+Z4)/O4 -> 0
B5: Декабрь туники | C5: 29-31.12 | D5: 1 | F5: =IFERROR(O5-SUM(Q5:W5)+AD5,0) -> -0.28775523 | G5: =ДЕКАБРЬ!N108 -> 0 | H5: =ДЕКАБРЬ!S108 -> 0 | I5: =ДЕКАБРЬ!T108 -> 0 | J5: =ДЕКАБРЬ!V108 -> 0 | K5: =ДЕКАБРЬ!W108 -> 0 | L5: =IFERROR(J5+K5,0) -> 0 | M5: =ДЕКАБРЬ!Y108 -> 0 | N5: =ДЕКАБРЬ!Z108 -> 0 | O5: =IFERROR(M5+N5,0) -> 0 | P5: =ДЕКАБРЬ!AD108 -> 0 | Q5: =ДЕКАБРЬ!AG108 -> 0 | R5: =ДЕКАБРЬ!AE108 -> 0 | S5: =ДЕКАБРЬ!AL108 -> 0.28775523 | U5: =ДЕКАБРЬ!AM108 -> 0 | W5: =ДЕКАБРЬ!AH108 -> 0 | X5: =ДЕКАБРЬ!AI108 -> 0 | Z5: =ДЕКАБРЬ!AK108 -> 0 | AC5: =ДЕКАБРЬ!AN108 -> 0 | AE5: =O5-SUM(P5:Z5)+AD5 -> -0.28775523 | AF5: =O5-SUM(P5:AC5)+AD5 -> -0.28775523 | AH5: =P5/O5 -> #DIV/0! | AI5: =AF5/P5 -> #DIV/0! | AJ5: =AF5/O5 -> #DIV/0! | AK5: =(W5+X5+Z5)/O5 -> #DIV/0!
B6: Январь очки | C6: 01.01-01.02 | D6: 1-5 | F6: =IFERROR(O6-SUM(Q6:W6)+AD6,0) -> 955718.86 | G6: =ЯНВАРЬ!N100 -> 4961 | H6: =ЯНВАРЬ!S100 -> 2362 | I6: =ЯНВАРЬ!T100 -> -53 | J6: =ЯНВАРЬ!V100 -> 1728382.8 | K6: =ЯНВАРЬ!W100 -> -44657.88 | L6: =IFERROR(J6+K6,0) -> 1683724.9 | M6: =ЯНВАРЬ!Y100 -> 2303342.1 | N6: =ЯНВАРЬ!Z100 -> -58267.04 | O6: =IFERROR(M6+N6,0) -> 2245075 | P6: =ЯНВАРЬ!AD100 -> 292876.64 | Q6: =ЯНВАРЬ!AG100 -> 276475.65 | R6: =ЯНВАРЬ!AE100 -> 833669.77 | S6: =ЯНВАРЬ!AL100 -> 40333.14 | U6: =ЯНВАРЬ!AM100 -> 0 | V6: 25431.6 | W6: =ЯНВАРЬ!AH100 -> 113446 | X6: =ЯНВАРЬ!AI100 -> 404487 | Z6: =ЯНВАРЬ!AK100 -> 0 | AC6: =ЯНВАРЬ!AN100 -> 95827.42 | AE6: =O6-SUM(P6:Z6)+AD6 -> 258355.22 | AF6: =O6-SUM(P6:AC6)+AD6 -> 162527.8 | AG6: =SUM(AF6:AF8) -> 162168.41 | AH6: =P6/O6 -> 0.13045294 | AI6: =AF6/P6 -> 0.55493603 | AJ6: =AF6/O6 -> 0.072393037 | AK6: =(W6+X6+Z6)/O6 -> 0.23069741
B7: Январь туники | C7: 01.01-01.02 | D7: 1-5 | F7: =IFERROR(O7-SUM(Q7:W7)+AD7,0) -> -186.4297 | G7: =ЯНВАРЬ!N108 -> 1 | H7: =ЯНВАРЬ!S108 -> 0 | I7: =ЯНВАРЬ!T108 -> 0 | J7: =ЯНВАРЬ!V108 -> 0 | K7: =ЯНВАРЬ!W108 -> 0 | L7: =IFERROR(J7+K7,0) -> 0 | M7: =ЯНВАРЬ!Y108 -> 0 | N7: =ЯНВАРЬ!Z108 -> 0 | O7: =IFERROR(M7+N7,0) -> 0 | P7: =ЯНВАРЬ!AD108 -> 0 | Q7: =ЯНВАРЬ!AG108 -> 183.22 | R7: =ЯНВАРЬ!AE108 -> 0 | S7: =ЯНВАРЬ!AL108 -> 3.209704 | U7: =ЯНВАРЬ!AM108 -> 0 | W7: =ЯНВАРЬ!AH108 -> 0 | X7: =ЯНВАРЬ!AI108 -> 0 | Z7: =ЯНВАРЬ!AK108 -> 0 | AC7: =ЯНВАРЬ!AN108 -> 0 | AE7: =O7-SUM(P7:Z7)+AD7 -> -186.4297 | AF7: =O7-SUM(P7:AC7)+AD7 -> -186.4297 | AH7: =P7/O7 -> #DIV/0! | AI7: =AF7/P7 -> #DIV/0! | AJ7: =AF7/O7 -> #DIV/0! | AK7: =(W7+X7+Z7)/O7 -> #DIV/0!
B8: Январь шапки | C8: 01.01-01.02 | D8: 1-5 | F8: =IFERROR(O8-SUM(Q8:W8)+AD8,0) -> -172.96 | G8: =ЯНВАРЬ!N119 -> 0 | H8: =ЯНВАРЬ!S119 -> 0 | I8: =ЯНВАРЬ!T119 -> 0 | J8: =ЯНВАРЬ!V119 -> 0 | K8: =ЯНВАРЬ!W119 -> 0 | L8: =IFERROR(J8+K8,0) -> 0 | M8: =ЯНВАРЬ!Y119 -> 0 | N8: =ЯНВАРЬ!Z119 -> 0 | O8: =IFERROR(M8+N8,0) -> 0 | P8: =ЯНВАРЬ!AD119 -> 0 | Q8: =ЯНВАРЬ!AG119 -> 172.96 | R8: =ЯНВАРЬ!AE119 -> 0 | S8: =ЯНВАРЬ!AL119 -> 0 | U8: =ЯНВАРЬ!AM119 -> 0 | W8: =ЯНВАРЬ!AH119 -> 0 | X8: =ЯНВАРЬ!AI119 -> 0 | Z8: =ЯНВАРЬ!AK119 -> 0 | AC8: =ЯНВАРЬ!AN119 -> 0 | AE8: =O8-SUM(P8:Z8)+AD8 -> -172.96 | AF8: =O8-SUM(P8:AC8)+AD8 -> -172.96 | AH8: =P8/O8 -> #DIV/0! | AI8: =AF8/P8 -> #DIV/0! | AJ8: =AF8/O8 -> #DIV/0! | AK8: =(W8+X8+Z8)/O8 -> #DIV/0!
B9: Февраль 1 очки | C9: 02-08.02 | D9: 6 | F9: =IFERROR(O9-SUM(Q9:W9)+AD9,0) -> 539419.19 | G9: ='Юнит 6'!N105 -> 2829 | H9: ='Юнит 6'!S105 -> 1418 | I9: ='Юнит 6'!T105 -> -25 | J9: ='Юнит 6'!V105 -> 894889.93 | K9: ='Юнит 6'!W105 -> -16453.5 | L9: =IFERROR(J9+K9,0) -> 878436.43 | M9: ='Юнит 6'!Y105 -> 1357375 | N9: ='Юнит 6'!Z105 -> -24887.06 | O9: =IFERROR(M9+N9,0) -> 1332487.9 | P9: ='Юнит 6'!AD105 -> 175437.39 | Q9: ='Юнит 6'!AG105 -> 153486.12 | R9: ='Юнит 6'!AE105 -> 495216.11 | S9: ='Юнит 6'!AL105 -> 8160.06 | U9: ='Юнит 6'!AM105 -> 0 | V9: =5797.44+18990 -> 24787.44 | W9: ='Юнит 6'!AH105 -> 111419 | X9: ='Юнит 6'!AI105 -> 126688 | Z9: ='Юнит 6'!AK105 -> 0 | AC9: =304652.46*O9/SUM(O$9:O$16) -> 47907.536 | AE9: =O9-SUM(P9:Z9)+AD9 -> 237293.8 | AF9: =O9-SUM(P9:AC9)+AD9 -> 189386.26 | AG9: =SUM(AF9:AF16) -> 1876556.2 | AH9: =P9/O9 -> 0.13166152 | AI9: =AF9/P9 -> 1.0795091 | AJ9: =AF9/O9 -> 0.14212982 | AK9: =(W9+X9+Z9)/O9 -> 0.17869355
B10: Февраль 1 туники | C10: 02-08.02 | D10: 6 | F10: =IFERROR(O10-SUM(Q10:W10)+AD10,0) -> 0 | G10: ='Юнит 6'!N113 -> 1 | H10: ='Юнит 6'!S113 -> 0 | I10: ='Юнит 6'!T113 -> 0 | J10: ='Юнит 6'!V113 -> 0 | K10: ='Юнит 6'!W113 -> 0 | L10: =IFERROR(J10+K10,0) -> 0 | M10: ='Юнит 6'!Y113 -> 0 | N10: ='Юнит 6'!Z113 -> 0 | O10: =IFERROR(M10+N10,0) -> 0 | P10: ='Юнит 6'!AD113 -> 0 | Q10: ='Юнит 6'!AG113 -> 0 | R10: ='Юнит 6'!AE113 -> 0 | S10: ='Юнит 6'!AL113 -> 0 | U10: ='Юнит 6'!AM113 -> 0 | W10: ='Юнит 6'!AH113 -> 0 | X10: ='Юнит 6'!AI113 -> 0 | Z10: ='Юнит 6'!AK113 -> 0 | AC10: =304652.46*O10/SUM(O$9:O$16) -> 0 | AE10: =O10-SUM(P10:Z10)+AD10 -> 0 | AF10: =O10-SUM(P10:AC10)+AD10 -> 0 | AH10: =P10/O10 -> #DIV/0! | AI10: =AF10/P10 -> #DIV/0! | AJ10: =AF10/O10 -> #DIV/0! | AK10: =(W10+X10+Z10)/O10 -> #DIV/0!
B11: Февраль 2 очки | C11: 09-15.02 | D11: 7 | F11: =IFERROR(O11-SUM(Q11:W11)+AD11,0) -> 811496.75 | G11: ='Юнит 7'!N105 -> 3325 | H11: ='Юнит 7'!S105 -> 1882 | I11: ='Юнит 7'!T105 -> -40 | J11: ='Юнит 7'!V105 -> 1236743.8 | K11: ='Юнит 7'!W105 -> -26582.27 | L11: =IFERROR(J11+K11,0) -> 1210161.6 | M11: ='Юнит 7'!Y105 -> 1920260.7 | N11: ='Юнит 7'!Z105 -> -41194.47 | O11: =IFERROR(M11+N11,0) -> 1879066.2 | P11: ='Юнит 7'!AD105 -> 230374.86 | Q11: ='Юнит 7'!AG105 -> 212380.68 | R11: ='Юнит 7'!AE105 -> 695831.51 | S11: ='Юнит 7'!AL105 -> 8132.98 | T11: 30 | U11: ='Юнит 7'!AM105 -> 826 | V11: 4787.28 | W11: ='Юнит 7'!AH105 -> 145581 | X11: ='Юнит 7'!AI105 -> 138670 | Z11: ='Юнит 7'!AK105 -> 0 | AC11: =304652.46*O11/SUM(O$9:O$16) -> 67558.911 | AE11: =O11-SUM(P11:Z11)+AD11 -> 442451.89 | AF11: =O11-SUM(P11:AC11)+AD11 -> 374892.98 | AH11: =P11/O11 -> 0.12260072 | AI11: =AF11/P11 -> 1.6273172 | AJ11: =AF11/O11 -> 0.19951026 | AK11: =(W11+X11+Z11)/O11 -> 0.15127248
B12: Февраль 2 туники | C12: 09-15.02 | D12: 7 | F12: =IFERROR(O12-SUM(Q12:W12)+AD12,0) -> 1191.57 | G12: ='Юнит 7'!N113 -> 0 | H12: ='Юнит 7'!S113 -> 1 | I12: ='Юнит 7'!T113 -> 0 | J12: ='Юнит 7'!V113 -> 1407 | K12: ='Юнит 7'!W113 -> 0 | L12: =IFERROR(J12+K12,0) -> 1407 | M12: ='Юнит 7'!Y113 -> 2079 | N12: ='Юнит 7'!Z113 -> 0 | O12: =IFERROR(M12+N12,0) -> 2079 | P12: ='Юнит 7'!AD113 -> 579.18 | Q12: ='Юнит 7'!AG113 -> 124.34 | R12: ='Юнит 7'!AE113 -> 763.09 | S12: ='Юнит 7'!AL113 -> 0 | U12: ='Юнит 7'!AM113 -> 0 | W12: ='Юнит 7'!AH113 -> 0 | X12: ='Юнит 7'!AI113 -> 0 | Z12: ='Юнит 7'!AK113 -> 0 | AC12: =304652.46*O12/SUM(O$9:O$16) -> 74.74722 | AE12: =O12-SUM(P12:Z12)+AD12 -> 612.39 | AF12: =O12-SUM(P12:AC12)+AD12 -> 537.64278 | AH12: =P12/O12 -> 0.27858586 | AI12: =AF12/P12 -> 0.92828271 | AJ12: =AF12/O12 -> 0.25860644 | AK12: =(W12+X12+Z12)/O12 -> 0
B13: Февраль 3 очки | C13: 16-22.02 | D13: 8 | F13: =IFERROR(O13-SUM(Q13:W13)+AD13,0) -> 1204943.2 | G13: ='Юнит 8'!N$105 -> 4413 | H13: ='Юнит 8'!S$105 -> 2295 | I13: ='Юнит 8'!T$105 -> -43 | J13: ='Юнит 8'!V$105 -> 1593380.1 | K13: ='Юнит 8'!W$105 -> -29254.63 | L13: =IFERROR(J13+K13,0) -> 1564125.5 | M13: ='Юнит 8'!Y$105 -> 2501418.9 | N13: ='Юнит 8'!Z$105 -> -47007.29 | O13: =IFERROR(M13+N13,0) -> 2454411.6 | P13: ='Юнит 8'!AD$105 -> 280478.83 | Q13: ='Юнит 8'!AG$105 -> 267875.33 | R13: ='Юнит 8'!AE$105 -> 918234.84 | S13: ='Юнит 8'!AL$105 -> 8623.9028 | U13: ='Юнит 8'!AM$105 -> 466 | V13: 3279.36 | W13: ='Юнит 8'!AH$105 -> 50989 | X13: ='Юнит 8'!AI$105 -> 265182 | Z13: ='Юнит 8'!AK$105 -> 0 | AC13: =304652.46*O13/SUM(O$9:O$16) -> 88244.562 | AE13: =O13-SUM(P13:Z13)+AD13 -> 659282.34 | AF13: =O13-SUM(P13:AC13)+AD13 -> 571037.78 | AH13: =P13/O13 -> 0.11427538 | AI13: =AF13/P13 -> 2.035939 | AJ13: =AF13/O13 -> 0.23265771 | AK13: =(W13+X13+Z13)/O13 -> 0.12881743
B14: Февраль 3 туники | C14: 16-22.02 | D14: 8 | F14: =IFERROR(O14-SUM(Q14:W14)+AD14,0) -> -0.86724686 | G14: ='Юнит 8'!N113 -> 0 | H14: ='Юнит 8'!S113 -> 0 | I14: ='Юнит 8'!T113 -> 0 | J14: ='Юнит 8'!V113 -> 0 | K14: ='Юнит 8'!W113 -> 0 | L14: =IFERROR(J14+K14,0) -> 0 | M14: ='Юнит 8'!Y113 -> 0 | N14: ='Юнит 8'!Z113 -> 0 | O14: =IFERROR(M14+N14,0) -> 0 | P14: ='Юнит 8'!AD113 -> 0 | Q14: ='Юнит 8'!AG113 -> 0 | R14: ='Юнит 8'!AE113 -> 0 | S14: ='Юнит 8'!AL113 -> 0.86724686 | U14: ='Юнит 8'!AM113 -> 0 | W14: ='Юнит 8'!AH113 -> 0 | X14: ='Юнит 8'!AI113 -> 0 | Z14: ='Юнит 8'!AK113 -> 0 | AC14: =304652.46*O14/SUM(O$9:O$16) -> 0 | AE14: =O14-SUM(P14:Z14)+AD14 -> -0.86724686 | AF14: =O14-SUM(P14:AC14)+AD14 -> -0.86724686 | AH14: =P14/O14 -> #DIV/0! | AI14: =AF14/P14 -> #DIV/0! | AJ14: =AF14/O14 -> #DIV/0! | AK14: =(W14+X14+Z14)/O14 -> #DIV/0!
B15: Февраль 4 очки | C15: 23.02-01.03 | D15: 9 | F15: =IFERROR(O15-SUM(Q15:W15)+AD15,0) -> 1208387.9 | G15: ='Юнит 9'!N$105 -> 3950 | H15: ='Юнит 9'!S$105 -> 2372 | I15: ='Юнит 9'!T$105 -> -63 | J15: ='Юнит 9'!V$105 -> 1818463.8 | K15: ='Юнит 9'!W$105 -> -46702.77 | L15: =IFERROR(J15+K15,0) -> 1771761 | M15: ='Юнит 9'!Y$105 -> 2879025.2 | N15: ='Юнит 9'!Z$105 -> -73544.64 | O15: =IFERROR(M15+N15,0) -> 2805480.6 | P15: ='Юнит 9'!AD$105 -> 288027.84 | Q15: ='Юнит 9'!AG$105 -> 299415.53 | R15: ='Юнит 9'!AE$105 -> 1051752.7 | S15: ='Юнит 9'!AL$105 -> 8471.4 | U15: ='Юнит 9'!AM$105 -> 1392.11 | V15: 2400.96 | W15: ='Юнит 9'!AH$105 -> 233660 | X15: ='Юнит 9'!AI$105 -> 78621 | Z15: ='Юнит 9'!AK$105 -> 0 | AC15: =304652.46*O15/SUM(O$9:O$16) -> 100866.7 | AE15: =O15-SUM(P15:Z15)+AD15 -> 841739.09 | AF15: =O15-SUM(P15:AC15)+AD15 -> 740872.39 | AH15: =P15/O15 -> 0.10266613 | AI15: =AF15/P15 -> 2.5722249 | AJ15: =AF15/O15 -> 0.26408038 | AK15: =(W15+X15+Z15)/O15 -> 0.11131105
B16: Февраль 4 прочее | C16: 23.02-01.03 | D16: 9 | F16: =IFERROR(O16-SUM(Q16:W16)+AD16,0) -> -170 | Q16: ='Юнит 9'!AG125 -> 170 | AC16: =304652.46*O16/SUM(O$9:O$16) -> 0 | AE16: =O16-SUM(P16:Z16)+AD16 -> -170 | AF16: =O16-SUM(P16:AC16)+AD16 -> -170 | AH16: =P16/O16 -> #DIV/0! | AI16: =AF16/P16 -> #DIV/0! | AJ16: =AF16/O16 -> #DIV/0! | AK16: =(W16+X16+Z16)/O16 -> #DIV/0!
B17: Март 1 очки | C17: 02-08.03 | D17: 10 | F17: =IFERROR(O17-SUM(Q17:W17)+AD17,0) -> 1238601.7 | G17: ='Юнит 10'!N$105 -> 3795 | H17: ='Юнит 10'!S$105 -> 2096 | I17: ='Юнит 10'!T$105 -> -53 | J17: ='Юнит 10'!V$105 -> 1702514.8 | K17: ='Юнит 10'!W$105 -> -41251 | L17: =IFERROR(J17+K17,0) -> 1661263.8 | M17: ='Юнит 10'!Y$105 -> 2657773.4 | N17: ='Юнит 10'!Z$105 -> -65375.4 | O17: =IFERROR(M17+N17,0) -> 2592398 | P17: ='Юнит 10'!AD$105 -> 254974.68 | Q17: ='Юнит 10'!AG$105 -> 270558.84 | R17: ='Юнит 10'!AE$105 -> 972977.25 | S17: ='Юнит 10'!AL$105 -> 11702.83 | U17: ='Юнит 10'!AM$105 -> 0 | V17: =1083.36+22990 -> 24073.36 | W17: ='Юнит 10'!AH$105 -> 74484 | X17: ='Юнит 10'!AI$105 -> 252853 | Z17: ='Юнит 10'!AK$105 -> 0 | AC17: =666212.62*O17/SUM(O$17:O$20) -> 94861.253 | AE17: =O17-SUM(P17:Z17)+AD17 -> 730774.06 | AF17: =O17-SUM(P17:AC17)+AD17 -> 635912.81 | AG17: =SUM(AF17:AF20) -> 5396896.8 | AH17: =P17/O17 -> 0.098354758 | AI17: =AF17/P17 -> 2.4940234 | AJ17: =AF17/O17 -> 0.24529906 | AK17: =(W17+X17+Z17)/O17 -> 0.12626803
B18: Март 2 очки | C18: 09-15.03 | D18: 11 | F18: =IFERROR(O18-SUM(Q18:W18)+AD18,0) -> 2101556.8 | G18: ='Юнит 11'!N$105 -> 8243 | H18: ='Юнит 11'!S$105 -> 3480 | I18: ='Юнит 11'!T$105 -> -60 | J18: ='Юнит 11'!V$105 -> 3014405.3 | K18: ='Юнит 11'!W$105 -> -49269.89 | L18: =IFERROR(J18+K18,0) -> 2965135.4 | M18: ='Юнит 11'!Y$105 -> 4668001.6 | N18: ='Юнит 11'!Z$105 -> -76772.74 | O18: =IFERROR(M18+N18,0) -> 4591228.8 | P18: ='Юнит 11'!AD$105 -> 424325.4 | Q18: ='Юнит 11'!AG$105 -> 445765.14 | R18: ='Юнит 11'!AE$105 -> 1726243.8 | S18: ='Юнит 11'!AL$105 -> 9729.77 | U18: ='Юнит 11'!AM$105 -> 1842 | V18: 1288.32 | W18: ='Юнит 11'!AH$105 -> 304803 | X18: ='Юнит 11'!AI$105 -> 178004 | Z18: ='Юнит 11'!AK$105 -> 0 | AC18: =666212.62*O18/SUM(O$17:O$20) -> 168002.64 | AE18: =O18-SUM(P18:Z18)+AD18 -> 1499227.4 | AF18: =O18-SUM(P18:AC18)+AD18 -> 1331224.8 | AH18: =P18/O18 -> 0.092420878 | AI18: =AF18/P18 -> 3.1372734 | AJ18: =AF18/O18 -> 0.28994956 | AK18: =(W18+X18+Z18)/O18 -> 0.10515856
B19: Март 3 очки | C19: 16-22.03 | D19: 12 | F19: =IFERROR(O19-SUM(Q19:W19)+AD19,0) -> 2992995 | G19: ='Юнит 12'!N$105 -> 6902 | H19: ='Юнит 12'!S$105 -> 4072 | I19: ='Юнит 12'!T$105 -> -94 | J19: ='Юнит 12'!V$105 -> 3910621.8 | K19: ='Юнит 12'!W$105 -> -85755 | L19: =IFERROR(J19+K19,0) -> 3824866.8 | M19: ='Юнит 12'!Y$105 -> 5914054.7 | N19: ='Юнит 12'!Z$105 -> -132706.71 | O19: =IFERROR(M19+N19,0) -> 5781348 | P19: ='Юнит 12'!AD$105 -> 494039.24 | Q19: ='Юнит 12'!AG$105 -> 557216.52 | R19: ='Юнит 12'!AE$105 -> 2176223 | S19: ='Юнит 12'!AL$105 -> 6558.48 | U19: ='Юнит 12'!AM$105 -> 130 | W19: ='Юнит 12'!AH$105 -> 48225 | X19: ='Юнит 12'!AI$105 -> 468432 | Z19: ='Юнит 12'!AK$105 -> 0 | AC19: =666212.62*O19/SUM(O$17:O$20) -> 211551.59 | AE19: =O19-SUM(P19:Z19)+AD19 -> 2030523.7 | AF19: =O19-SUM(P19:AC19)+AD19 -> 1818972.1 | AH19: =P19/O19 -> 0.085453988 | AI19: =AF19/P19 -> 3.6818374 | AJ19: =AF19/O19 -> 0.31462768 | AK19: =(W19+X19+Z19)/O19 -> 0.089366182
B20: Март 4 очки | C20: 23-29.03 | D20: 13 | F20: =IFERROR(O20-SUM(Q20:W20)+AD20,0) -> 2696708.9 | G20: ='Юнит 13'!N$105 -> 6707 | H20: ='Юнит 13'!S$105 -> 3565 | I20: ='Юнит 13'!T$105 -> -97 | J20: ='Юнит 13'!V$105 -> 3582763.6 | K20: ='Юнит 13'!W$105 -> -97407.33 | L20: =IFERROR(J20+K20,0) -> 3485356.2 | M20: ='Юнит 13'!Y$105 -> 5387638.1 | N20: ='Юнит 13'!Z$105 -> -146145.86 | O20: =IFERROR(M20+N20,0) -> 5241492.2 | P20: ='Юнит 13'!AD$105 -> 429364.71 | Q20: ='Юнит 13'!AG$105 -> 472771.32 | R20: ='Юнит 13'!AE$105 -> 1975944.8 | S20: ='Юнит 13'!AL$105 -> 8091.54 | U20: ='Юнит 13'!AM$105 -> -1073 | V20: 702.72 | W20: ='Юнит 13'!AH$105 -> 88346 | X20: ='Юнит 13'!AI$105 -> 464760 | Z20: ='Юнит 13'!AK$105 -> 0 | AC20: =666212.62*O20/SUM(O$17:O$20) -> 191797.14 | AE20: =O20-SUM(P20:Z20)+AD20 -> 1802584.2 | AF20: =O20-SUM(P20:AC20)+AD20 -> 1610787.1 | AH20: =P20/O20 -> 0.081916502 | AI20: =AF20/P20 -> 3.751559 | AJ20: =AF20/O20 -> 0.30731459 | AK20: =(W20+X20+Z20)/O20 -> 0.10552453
B21: Апрель 1 очки | C21: 30.03-05.04 | D21: 14 | F21: =IFERROR(O21-SUM(Q21:W21)-AA21-AB21+AD21,0) -> 2335595.7 | G21: ='Юнит 14'!N$105 -> 5475 | H21: ='Юнит 14'!S$105 -> 3012 | I21: ='Юнит 14'!T$105 -> -85 | J21: ='Юнит 14'!V$105 -> 3007932.1 | K21: ='Юнит 14'!W$105 -> -82412.17 | L21: =IFERROR(J21+K21,0) -> 2925519.9 | M21: ='Юнит 14'!Y$105 -> 4561244.2 | N21: ='Юнит 14'!Z$105 -> -124396.78 | O21: =IFERROR(M21+N21,0) -> 4436847.4 | P21: ='Юнит 14'!AD$105 -> 363233.15 | Q21: ='Юнит 14'!AG$105 -> 409675.01 | R21: ='Юнит 14'!AE$105 -> 1670278 | S21: ='Юнит 14'!AL$105 -> 8536.1 | U21: ='Юнит 14'!AM$105 -> 960 | V21: 702.72 | W21: ='Юнит 14'!AH$105 -> 9682 | X21: ='Юнит 14'!AI$105 -> 500888 | Z21: ='Юнит 14'!AK$105 -> 0 | AA21: 128.9 | AB21: 1289 | AC21: ='Юнит 14'!AN$105 -> 167047.19 | AE21: =O21-SUM(P21:AB21)+AD21 -> 1471474.5 | AF21: =O21-SUM(P21:AC21)+AD21 -> 1304427.3 | AG21: =SUM(AF21:AF25) -> 4293476.1 | AH21: =P21/O21 -> 0.081867397 | AI21: =AF21/P21 -> 3.5911572 | AJ21: =AF21/O21 -> 0.29399869 | AK21: =(W21+X21+Z21)/O21 -> 0.11507495
B22: Апрель 2 очки | C22: 06-12.04 | D22: 15 | F22: =IFERROR(O22-SUM(Q22:W22)-AA22-AB22+AD22,0) -> 1648542.8 | G22: ='Юнит 15'!N$105 -> 3532 | H22: ='Юнит 15'!S$105 -> 2176 | I22: ='Юнит 15'!T$105 -> -59 | J22: ='Юнит 15'!V$105 -> 2198880.5 | K22: ='Юнит 15'!W$105 -> -57961.37 | L22: =IFERROR(J22+K22,0) -> 2140919.2 | M22: ='Юнит 15'!Y$105 -> 3303471.3 | N22: ='Юнит 15'!Z$105 -> -87984.17 | O22: =IFERROR(M22+N22,0) -> 3215487.2 | P22: ='Юнит 15'!AD$105 -> 261816.2 | Q22: ='Юнит 15'!AG$105 -> 302367.43 | R22: ='Юнит 15'!AE$105 -> 1215469.6 | S22: ='Юнит 15'!AL$105 -> 9130.33 | U22: ='Юнит 15'!AM$105 -> 4923.98 | V22: 22990 | W22: ='Юнит 15'!AH$105 -> 2405 | X22: ='Юнит 15'!AI$105 -> 301236 | Z22: ='Юнит 15'!AK$105 -> 0 | AA22: 878 | AB22: 8780 | AC22: ='Юнит 15'!AN$105 -> 122246.48 | AE22: =O22-SUM(P22:AB22)+AD22 -> 1085490.6 | AF22: =O22-SUM(P22:AC22)+AD22 -> 963244.12 | AH22: =P22/O22 -> 0.081423494 | AI22: =AF22/P22 -> 3.6790852 | AJ22: =AF22/O22 -> 0.29956397 | AK22: =(W22+X22+Z22)/O22 -> 0.094430792
B23: Апрель 3 очки | C23: 13-19.04 | D23: 16 | F23: =IFERROR(O23-SUM(Q23:W23)-AA23-AB23+AD23,0) -> 1468778.3 | G23: ='Юнит 16'!N$106 -> 3479 | H23: ='Юнит 16'!S$106 -> 1972 | I23: ='Юнит 16'!T$106 -> -47 | J23: ='Юнит 16'!V$106 -> 1966605.2 | K23: ='Юнит 16'!W$106 -> -45569.59 | L23: =IFERROR(J23+K23,0) -> 1921035.6 | M23: ='Юнит 16'!Y$106 -> 2939167.4 | N23: ='Юнит 16'!Z$106 -> -68089.33 | O23: =IFERROR(M23+N23,0) -> 2871078.1 | P23: ='Юнит 16'!AD$106 -> 238729.31 | Q23: ='Юнит 16'!AG$106 -> 252691.82 | R23: ='Юнит 16'!AE$106 -> 1082608.5 | S23: ='Юнит 16'!AL$106 -> 11044.13 | U23: ='Юнит 16'!AM$106 -> 3110 | W23: ='Юнит 16'!AH$106 -> 43580 | X23: ='Юнит 16'!AI$106 -> 287584 | Z23: ='Юнит 16'!AK$106 -> 0 | AA23: 842.3 | AB23: 8423 | AC23: ='Юнит 16'!AN$106 -> 109691.13 | AE23: =O23-SUM(P23:AB23)+AD23 -> 942465 | AF23: =O23-SUM(P23:AC23)+AD23 -> 832773.87 | AH23: =P23/O23 -> 0.08314971 | AI23: =AF23/P23 -> 3.4883604 | AJ23: =AF23/O23 -> 0.29005616 | AK23: =(W23+X23+Z23)/O23 -> 0.11534483
B24: Апрель 4 очки | C24: 20-26.04 | D24: 17 | F24: =IFERROR(O24-SUM(Q24:W24)-AA24-AB24+AD24,0) -> 1257598.6 | G24: ='Юнит 17'!N$106 -> 3101 | H24: ='Юнит 17'!S$106 -> 1730 | I24: ='Юнит 17'!T$106 -> -35 | J24: ='Юнит 17'!V$106 -> 1694803.1 | K24: ='Юнит 17'!W$106 -> -35587.44 | L24: =IFERROR(J24+K24,0) -> 1659215.6 | M24: ='Юнит 17'!Y$106 -> 2465283.2 | N24: ='Юнит 17'!Z$106 -> -52946.24 | O24: =IFERROR(M24+N24,0) -> 2412337 | P24: ='Юнит 17'!AD$106 -> 210794.5 | Q24: ='Юнит 17'!AG$106 -> 226778.55 | R24: ='Юнит 17'!AE$106 -> 908073.2 | S24: ='Юнит 17'!AL$106 -> 10756.94 | U24: ='Юнит 17'!AM$106 -> 1310 | W24: ='Юнит 17'!AH$106 -> 6217 | X24: ='Юнит 17'!AI$106 -> 172288 | Y24: ='Юнит 17'!AJ106 -> 215420 | Z24: ='Юнит 17'!AK$106 -> 0 | AA24: 145.7 | AB24: 1457 | AC24: ='Юнит 17'!AN$106 -> 94741.212 | AE24: =O24-SUM(P24:AB24)+AD24 -> 659096.12 | AF24: =O24-SUM(P24:AC24)+AD24 -> 564354.91 | AH24: =P24/O24 -> 0.087381862 | AI24: =AF24/P24 -> 2.6772753 | AJ24: =AF24/O24 -> 0.2339453 | AK24: =(W24+X24+Z24)/O24 -> 0.073996709
B25: Апрель 5 очки | C25: 27.04-03.05 | D25: 18 | F25: =IFERROR(O25-SUM(Q25:W25)-AA25-AB25+AD25,0) -> 1135755.1 | G25: ='Юнит 18'!N$106 -> 2848 | H25: ='Юнит 18'!S$106 -> 1619 | I25: ='Юнит 18'!T$106 -> -25 | J25: ='Юнит 18'!V$106 -> 1568485.2 | K25: ='Юнит 18'!W$106 -> -24497.18 | L25: =IFERROR(J25+K25,0) -> 1543988 | M25: ='Юнит 18'!Y$106 -> 2195247.5 | N25: ='Юнит 18'!Z$106 -> -35177.54 | O25: =IFERROR(M25+N25,0) -> 2160069.9 | P25: ='Юнит 18'!AD$106 -> 198027.47 | Q25: ='Юнит 18'!AG$106 -> 200716.59 | R25: ='Юнит 18'!AE$106 -> 811495.47 | S25: ='Юнит 18'!AL$106 -> 9333.97 | U25: ='Юнит 18'!AM$106 -> 1585 | W25: ='Юнит 18'!AH$106 -> 977 | X25: ='Юнит 18'!AI$106 -> 26624 | Y25: ='Юнит 18'!AJ$106 -> 194266 | Z25: ='Юнит 18'!AK$106 -> 0 | AA25: 18.8 | AB25: 188 | AC25: ='Юнит 18'!AN$106 -> 88161.717 | AE25: =O25-SUM(P25:AB25)+AD25 -> 716837.63 | AF25: =O25-SUM(P25:AC25)+AD25 -> 628675.91 | AH25: =P25/O25 -> 0.091676416 | AI25: =AF25/P25 -> 3.1746904 | AJ25: =AF25/O25 -> 0.29104424 | AK25: =(W25+X25+Z25)/O25 -> 0.012777827
B26: Май 1 очки | C26: 04-10.05 | D26: 19 | F26: =IFERROR(O26-SUM(Q26:W26)-AA26-AB26+AD26,0) -> 1268914.2 | G26: ='Юнит 19'!N$110 -> 3857 | H26: ='Юнит 19'!S$110 -> 1781 | I26: ='Юнит 19'!T$110 -> -43 | J26: ='Юнит 19'!V$110 -> 1836894.4 | K26: ='Юнит 19'!W$110 -> -42304 | L26: =IFERROR(J26+K26,0) -> 1794590.4 | M26: ='Юнит 19'!Y$110 -> 2527540.2 | N26: ='Юнит 19'!Z$110 -> -59373 | O26: =IFERROR(M26+N26,0) -> 2468167.2 | P26: ='Юнит 19'!AD$110 -> 216179.16 | Q26: ='Юнит 19'!AG$110 -> 230746.09 | R26: ='Юнит 19'!AE$110 -> 937659.92 | S26: ='Юнит 19'!AL$110 -> 7487.02 | T26: 30 | U26: ='Юнит 19'!AM$110 -> 20 | V26: 22990 | W26: ='Юнит 19'!AH$110 -> 320 | X26: ='Юнит 19'!AI$110 -> 17442 | Y26: ='Юнит 19'!AJ$110 -> 329393 | Z26: ='Юнит 19'!AK$110 -> 0 | AC26: ='Юнит 19'!AN$110 -> 102471.11 | AE26: =O26-SUM(P26:AB26)+AD26 -> 705900.04 | AF26: =O26-SUM(P26:AC26)+AD26 -> 603428.93
B28: Итого | F28: =SUM(F4:F27) -> 22927987 | G28: =SUM(G4:G27) -> 67548 | H28: =SUM(H4:H27) -> 35960 | I28: =SUM(I4:I27) -> -827 | J28: =SUM(J4:J27) -> 31875221 | K28: =SUM(K4:K27) -> -732075.02 | L28: =SUM(L4:L27) -> 31143146 | M28: =SUM(M4:M27) -> 47721887 | ... AG28: =SUM(AG4:AG27) -> 11770103 | AH28: =P28/O28 -> 0.093832106 | AI28: =AF28/P28 -> 2.8285597 | AJ28: =AF28/O28 -> 0.26540972 | AK28: =(W28+X28+Z28)/O28 -> 0.1054878
M29: % от выручки за весь период
N30: =-N28/M28 -> 0.023079437 | P30: =P28/$O$28 -> 0.093832106 | Q30: =Q28/$O$28 -> 0.098603682 | R30: =R28/$O$28 -> 0.37581259 | S30: =S28/$O$28 -> 0.0036403066 | T30: =T28/$O$28 -> 1.3234523e-06 | U30: =U28/$O$28 -> 0.00033230215 | V30: =V28/$O$28 -> 0.0028621268 | W30: =W28/$O$28 -> 0.026471921 | X30: =X28/$O$28 -> 0.079015874 | Z30: =Z28/$O$28 -> 0 | AC30: =AC28/$O$28 -> 0.037689833 | AG30: =AF28/P28 -> 2.8285597 | AH30: Маржинальность, %
W31: =(W28+X28)/O28 -> 0.1054878 | AG31: =AF28/O28 -> 0.26540972 | AH31: Рентабельность, %
B33: ЯНВАРЬ очки | G33: =G6 -> 4961 | H33: =H6 -> 2362 | I33: =I6 -> -53 | J33: =J6 -> 1728382.8 | K33: =K6 -> -44657.88 | L33: =L6 -> 1683724.9 | M33: =M6 -> 2303342.1 | N33: =N6 -> -58267.04 | ... X33: =X6 -> 404487 | Z33: =Z6 -> 0 | AC33: =AC6 -> 95827.42 | AD33: =AD6 -> 0 | AE33: =AE6 -> 258355.22 | AF33: =AF6 -> 162527.8 | AG33: =AF33/P33 -> 0.55493603
N34: =-N33/M33 -> 0.025296738 | P34: =P33/$O$33 -> 0.13045294 | Q34: =Q33/$O$33 -> 0.12314762 | R34: =R33/$O$33 -> 0.3713327 | S34: =S33/$O$33 -> 0.017965164 | T34: =T33/$O$33 -> 0 | U34: =U33/$O$33 -> 0 | V34: =V33/$O$33 -> 0.011327728 | W34: =W33/$O$33 -> 0.050531051 | X34: =X33/$O$33 -> 0.18016636 | Z34: =Z33/$O$33 -> 0 | AC34: =AC33/$O$33 -> 0.042683393 | AD34: =AD33/$O$33 -> 0 | AF34: =AF33/O33 -> 0.072393037 | AG34: =AF33/O33 -> 0.072393037
B36: 7 нед очки | P36: =P11/$O$11 -> 0.12260072 | Q36: =Q11/$O$11 -> 0.11302459 | R36: =R11/$O$11 -> 0.37030708 | S36: =S11/$O$11 -> 0.004328203 | T36: =T11/$O$11 -> 1.5965377e-05 | U36: =U11/$O$11 -> 0.00043958004 | V36: =V11/$O$11 -> 0.002547691 | W36: =W11/$O$11 -> 0.077475184 | X36: =X11/$O$11 -> 0.073797294 | Z36: =Z11/$O$11 -> 0 | AC36: =AC11/$O$11 -> 0.035953449 | AD36: =AD11/$O$11 -> 0 | AG36: =AF11/P11 -> 1.6273172 | AH36: Маржинальность, %
AG37: =AF11/O11 -> 0.19951026 | AH37: Рентабельность, %
C38: ё
B39: ФЕВРАЛЬ очки | G39: =G9+G11+G13+G15 -> 14517 | H39: =H9+H11+H13+H15 -> 7967 | I39: =I9+I11+I13+I15 -> -171 | J39: =J9+J11+J13+J15 -> 5543477.6 | K39: =K9+K11+K13+K15 -> -118993.17 | L39: =L9+L11+L13+L15 -> 5424484.4 | M39: =M9+M11+M13+M15 -> 8658079.8 | N39: =N9+N11+N13+N15 -> -186633.46 | ... X39: =X9+X11+X13+X15 -> 609161 | Z39: =Z9+Z11+Z13+Z15 -> 0 | AC39: =AC9+AC11+AC13+AC15 -> 304577.71 | AD39: =AD9+AD11+AD13+AD15 -> 0 | AE39: =AE9+AE11+AE13+AE15 -> 2180767.1 | AF39: =AF9+AF11+AF13+AF15 -> 1876189.4 | AG39: =AF39/P39 -> 1.925642
N40: =-N39/M39 -> 0.021555988 | P40: =P39/$O$39 -> 0.11501211 | Q40: =Q39/$O$39 -> 0.11015329 | R40: =R39/$O$39 -> 0.37313996 | S40: =S39/$O$39 -> 0.0039412801 | T40: =T39/$O$39 -> 3.5413079e-06 | U40: =U39/$O$39 -> 0.000316842 | V40: =V39/$O$39 -> 0.0041616317 | W40: =W39/$O$39 -> 0.063938196 | X40: =X39/$O$39 -> 0.071907556 | Z40: =Z39/$O$39 -> 0 | AC40: =AC39/$O$39 -> 0.035953449 | AD40: =AD39/$O$39 -> 0 | AF40: =AF39/O39 -> 0.22147215 | AG40: =AF39/O39 -> 0.22147215
B42: 9 нед очки | P42: =P15/$O$15 -> 0.10266613 | Q42: =Q15/$O$15 -> 0.10672522 | R42: =R15/$O$15 -> 0.37489216 | S42: =S15/$O$15 -> 0.0030195896 | T42: =T15/$O$15 -> 0 | U42: =U15/$O$15 -> 0.00049621088 | V42: =V15/$O$15 -> 0.00085581058 | W42: =W15/$O$15 -> 0.083286977 | X42: =X15/$O$15 -> 0.028024075 | Z42: =Z15/$O$15 -> 0 | AC42: =AC15/$O$15 -> 0.035953449 | AD42: =AD15/$O$15 -> 0 | AG42: =AF15/P15 -> 2.5722249 | AH42: Маржинальность, %
AG43: =AF15/O15 -> 0.26408038 | AH43: Рентабельность, %
B45: МАРТ очки | G45: =SUM(G17:G20) -> 25647 | H45: =SUM(H17:H20) -> 13213 | I45: =SUM(I17:I20) -> -304 | J45: =SUM(J17:J20) -> 12210305 | K45: =SUM(K17:K20) -> -273683.22 | L45: =SUM(L17:L20) -> 11936622 | M45: =SUM(M17:M20) -> 18627468 | N45: =SUM(N17:N20) -> -421000.71 | ... X45: =SUM(X17:X20) -> 1364049 | Z45: =SUM(Z17:Z20) -> 0 | AC45: =SUM(AC17:AC20) -> 666212.62 | AD45: =SUM(AD17:AD20) -> 0 | AE45: =SUM(AE17:AE20) -> 6063109.4 | AF45: =SUM(AF17:AF20) -> 5396896.8 | AG45: =AF45/P45 -> 3.3673696 | AH45: Маржинальность, %
P46: =P45/$O$45 -> 0.088029381 | Q46: =Q45/$O$45 -> 0.095917116 | R46: =R45/$O$45 -> 0.37631622 | S46: =S45/$O$45 -> 0.0019818573 | T46: =T45/$O$45 -> 0 | U46: =U45/$O$45 -> 4.9378059e-05 | V46: =V45/$O$45 -> 0.0014316012 | W46: =W45/$O$45 -> 0.028333778 | X46: =X45/$O$45 -> 0.074921125 | Z46: =Z45/$O$45 -> 0 | AC46: =AC45/$O$45 -> 0.036592087 | AD46: =AD45/$O$45 -> 0 | AF46: =AF45/O45 -> 0.29642746 | AG46: =AF45/O45 -> 0.29642746 | AH46: Рентабельность, %
B48: АПРЕЛЬ очки | G48: =SUM(G21:G25) -> 18435 | H48: =SUM(H21:H25) -> 10509 | I48: =SUM(I21:I25) -> -251 | J48: =SUM(J21:J25) -> 10436706 | K48: =SUM(K21:K25) -> -246027.75 | L48: =SUM(L21:L25) -> 10190678 | M48: =SUM(M21:M25) -> 15464414 | N48: =SUM(N21:N25) -> -368594.06 | ... AF48: =SUM(AF21:AF25) -> 4293476.1 | AG48: =AF48/P48 -> 3.3737812 | AH48: Маржинальность, %
P49: =P48/$O$48 -> 0.084301526 | Q49: =Q48/$O$48 -> 0.092226155 | R49: =R48/$O$48 -> 0.37678808 | S49: =S48/$O$48 -> 0.0032327804 | T49: =T48/$O$48 -> 0 | U49: =U48/$O$48 -> 0.00078756771 | V49: =V48/$O$48 -> 0.0015694888 | W49: =W48/$O$48 -> 0.004164133 | ... AD49: =AD48/$O$48 -> 0 | AF49: =AF48/O48 -> 0.28441491 | AG49: =AF48/O48 -> 0.28441491 | AH49: Рентабельность, %

Sheet АВС 20
B2: ОЧКИ
C3: Прибыль | D3: % прибыль | E3: Доля | F3: ABC прибыль | G3: ABC кол-во | J3: Кол-во | K3: % кол-во | L3: Доля | M3: ABC кол-во
B4: черные с железкой классика | D4: =C4/C$110 -> #DIV/0! | E4: =D4 -> #DIV/0! | F4: =IF(AND(E4<=0),"C",IF(E4<=0.8,"A",IF(E4<=0.95,"B","C"))) -> #DIV/0! | G4: =VLOOKUP(B$4:B$104,I$4:M$104,5,0) -> #DIV/0! | I4: черные с железкой классика | K4: =J4/J$110 -> #DIV/0! | L4: =K4 -> #DIV/0! | M4: =_xlfn.IFS(L4<80%,"A",L4<=95%,"B",L4>95%,"C") -> #DIV/0! | P4: A | Q4: 0.8
B5: QS черные PZ | D5: =C5/C$110 -> #DIV/0! | E5: =E4+D5 -> #DIV/0! | F5: =IF(AND(E5<=0),"C",IF(E5<=0.8,"A",IF(E5<=0.95,"B","C"))) -> #DIV/0! | G5: =VLOOKUP(B$4:B$104,I$4:M$104,5,0) -> #DIV/0! | I5: QS черные PZ | K5: =J5/J$110 -> #DIV/0! | L5: =L4+K5 -> #DIV/0! | M5: =_xlfn.IFS(L5<80%,"A",L5<=95%,"B",L5>95%,"C") -> #DIV/0! | P5: B | Q5: 0.15
B6: QS синие PZ | D6: =C6/C$110 -> #DIV/0! | E6: =E5+D6 -> #DIV/0! | F6: =IF(AND(E6<=0),"C",IF(E6<=0.8,"A",IF(E6<=0.95,"B","C"))) -> #DIV/0! | G6: =VLOOKUP(B$4:B$104,I$4:M$104,5,0) -> #DIV/0! | I6: QS синие PZ | K6: =J6/J$110 -> #DIV/0! | L6: =L5+K6 -> #DIV/0! | M6: =_xlfn.IFS(L6<80%,"A",L6<=95%,"B",L6>95%,"C") -> #DIV/0! | P6: C | Q6: 0.05
B7: QS желтые PZ | D7: =C7/C$110 -> #DIV/0! | E7: =E6+D7 -> #DIV/0! | F7: =IF(AND(E7<=0),"C",IF(E7<=0.8,"A",IF(E7<=0.95,"B","C"))) -> #DIV/0! | G7: =VLOOKUP(B$4:B$104,I$4:M$104,5,0) -> #DIV/0! | I7: QS желтые PZ | K7: =J7/J$110 -> #DIV/0! | L7: =L6+K7 -> #DIV/0! | M7: =_xlfn.IFS(L7<80%,"A",L7<=95%,"B",L7>95%,"C") -> #DIV/0!
B8: QS коричневые PZ | D8: =C8/C$110 -> #DIV/0! | E8: =E7+D8 -> #DIV/0! | F8: =IF(AND(E8<=0),"C",IF(E8<=0.8,"A",IF(E8<=0.95,"B","C"))) -> #DIV/0! | G8: =VLOOKUP(B$4:B$104,I$4:M$104,5,0) -> #DIV/0! | I8: QS коричневые PZ | K8: =J8/J$110 -> #DIV/0! | L8: =L7+K8 -> #DIV/0! | M8: =_xlfn.IFS(L8<80%,"A",L8<=95%,"B",L8>95%,"C") -> #DIV/0!
B9: MR8854 C2 Жен | D9: =C9/C$110 -> #DIV/0! | E9: =E8+D9 -> #DIV/0! | F9: =IF(AND(E9<=0),"C",IF(E9<=0.8,"A",IF(E9<=0.95,"B","C"))) -> #DIV/0! | G9: =VLOOKUP(B$4:B$104,I$4:M$104,5,0) -> #DIV/0! | I9: MR8854 C2 Жен | K9: =J9/J$110 -> #DIV/0! | L9: =L8+K9 -> #DIV/0! | M9: =_xlfn.IFS(L9<80%,"A",L9<=95%,"B",L9>95%,"C") -> #DIV/0!
B10: th черн | D10: =C10/C$110 -> #DIV/0! | E10: =E9+D10 -> #DIV/0! | F10: =IF(AND(E10<=0),"C",IF(E10<=0.8,"A",IF(E10<=0.95,"B","C"))) -> #DIV/0! | G10: =VLOOKUP(B$4:B$104,I$4:M$104,5,0) -> #DIV/0! | I10: th черн | K10: =J10/J$110 -> #DIV/0! | L10: =L9+K10 -> #DIV/0! | M10: =_xlfn.IFS(L10<80%,"A",L10<=95%,"B",L10>95%,"C") -> #DIV/0!
B11: th син | D11: =C11/C$110 -> #DIV/0! | E11: =E10+D11 -> #DIV/0! | F11: =IF(AND(E11<=0),"C",IF(E11<=0.8,"A",IF(E11<=0.95,"B","C"))) -> #DIV/0! | G11: =VLOOKUP(B$4:B$104,I$4:M$104,5,0) -> #DIV/0! | I11: th син | K11: =J11/J$110 -> #DIV/0! | L11: =L10+K11 -> #DIV/0! | M11: =_xlfn.IFS(L11<80%,"A",L11<=95%,"B",L11>95%,"C") -> #DIV/0!
B12: th желт | D12: =C12/C$110 -> #DIV/0! | E12: =E11+D12 -> #DIV/0! | F12: =IF(AND(E12<=0),"C",IF(E12<=0.8,"A",IF(E12<=0.95,"B","C"))) -> #DIV/0! | G12: =VLOOKUP(B$4:B$104,I$4:M$104,5,0) -> #DIV/0! | I12: th желт | K12: =J12/J$110 -> #DIV/0! | L12: =L11+K12 -> #DIV/0! | M12: =_xlfn.IFS(L12<80%,"A",L12<=95%,"B",L12>95%,"C") -> #DIV/0!
B13: th коричн | D13: =C13/C$110 -> #DIV/0! | E13: =E12+D13 -> #DIV/0! | F13: =IF(AND(E13<=0),"C",IF(E13<=0.8,"A",IF(E13<=0.95,"B","C"))) -> #DIV/0! | G13: =VLOOKUP(B$4:B$104,I$4:M$104,5,0) -> #DIV/0! | I13: th коричн | K13: =J13/J$110 -> #DIV/0! | L13: =L12+K13 -> #DIV/0! | M13: =_xlfn.IFS(L13<80%,"A",L13<=95%,"B",L13>95%,"C") -> #DIV/0!
B14: flip черные | D14: =C14/C$110 -> #DIV/0! | E14: =E13+D14 -> #DIV/0! | F14: =IF(AND(E14<=0),"C",IF(E14<=0.8,"A",IF(E14<=0.95,"B","C"))) -> #DIV/0! | G14: =VLOOKUP(B$4:B$104,I$4:M$104,5,0) -> #DIV/0! | I14: flip черные | K14: =J14/J$110 -> #DIV/0! | L14: =L13+K14 -> #DIV/0! | M14: =_xlfn.IFS(L14<80%,"A",L14<=95%,"B",L14>95%,"C") -> #DIV/0!
B15: flip синие | D15: =C15/C$110 -> #DIV/0! | E15: =E14+D15 -> #DIV/0! | F15: =IF(AND(E15<=0),"C",IF(E15<=0.8,"A",IF(E15<=0.95,"B","C"))) -> #DIV/0! | G15: =VLOOKUP(B$4:B$104,I$4:M$104,5,0) -> #DIV/0! | I15: flip синие | K15: =J15/J$110 -> #DIV/0! | L15: =L14+K15 -> #DIV/0! | M15: =_xlfn.IFS(L15<80%,"A",L15<=95%,"B",L15>95%,"C") -> #DIV/0!
B16: flip желтые | D16: =C16/C$110 -> #DIV/0! | E16: =E15+D16 -> #DIV/0! | F16: =IF(AND(E16<=0),"C",IF(E16<=0.8,"A",IF(E16<=0.95,"B","C"))) -> #DIV/0! | G16: =VLOOKUP(B$4:B$104,I$4:M$104,5,0) -> #DIV/0! | I16: flip желтые | K16: =J16/J$110 -> #DIV/0! | L16: =L15+K16 -> #DIV/0! | M16: =_xlfn.IFS(L16<80%,"A",L16<=95%,"B",L16>95%,"C") -> #DIV/0!
B17: flip коричневые | D17: =C17/C$110 -> #DIV/0! | E17: =E16+D17 -> #DIV/0! | F17: =IF(AND(E17<=0),"C",IF(E17<=0.8,"A",IF(E17<=0.95,"B","C"))) -> #DIV/0! | G17: =VLOOKUP(B$4:B$104,I$4:M$104,5,0) -> #DIV/0! | I17: flip коричневые | K17: =J17/J$110 -> #DIV/0! | L17: =L16+K17 -> #DIV/0! | M17: =_xlfn.IFS(L17<80%,"A",L17<=95%,"B",L17>95%,"C") -> #DIV/0!
B18: wwl8032 коричневые золото | D18: =C18/C$110 -> #DIV/0! | E18: =E17+D18 -> #DIV/0! | F18: =IF(AND(E18<=0),"C",IF(E18<=0.8,"A",IF(E18<=0.95,"B","C"))) -> #DIV/0! | G18: =VLOOKUP(B$4:B$104,I$4:M$104,5,0) -> #DIV/0! | I18: wwl8032 коричневые золото | K18: =J18/J$110 -> #DIV/0! | L18: =L17+K18 -> #DIV/0! | M18: =_xlfn.IFS(L18<80%,"A",L18<=95%,"B",L18>95%,"C") -> #DIV/0!
... B38: sh13 | D38: =C38/C$110 -> #DIV/0! | E38: =E37+D38 -> #DIV/0! | F38: =IF(AND(E38<=0),"C",IF(E38<=0.8,"A",IF(E38<=0.95,"B","C"))) -> #DIV/0! | G38: =VLOOKUP(B$4:B$104,I$4:M$104,5,0) -> #DIV/0! | I38: sh13 | K38: =J38/J$110 -> #DIV/0! | L38: =L37+K38 -> #DIV/0! | M38: =_xlfn.IFS(L38<80%,"A",L38<=95%,"B",L38>95%,"C") -> #DIV/0!
B39: sh14 | D39: =C39/C$110 -> #DIV/0! | E39: =E35+D39 -> #DIV/0! | F39: =IF(AND(E39<=0),"C",IF(E39<=0.8,"A",IF(E39<=0.95,"B","C"))) -> #DIV/0! | G39: =VLOOKUP(B$4:B$104,I$4:M$104,5,0) -> #DIV/0! | I39: sh14 | K39: =J39/J$110 -> #DIV/0! | L39: =L35+K39 -> #DIV/0! | M39: =_xlfn.IFS(L39<80%,"A",L39<=95%,"B",L39>95%,"C") -> #DIV/0!
B40: sh15 | D40: =C40/C$110 -> #DIV/0! | E40: =E39+D40 -> #DIV/0! | F40: =IF(AND(E40<=0),"C",IF(E40<=0.8,"A",IF(E40<=0.95,"B","C"))) -> #DIV/0! | G40: =VLOOKUP(B$4:B$104,I$4:M$104,5,0) -> #DIV/0! | I40: sh15 | K40: =J40/J$110 -> #DIV/0! | L40: =L39+K40 -> #DIV/0! | M40: =_xlfn.IFS(L40<80%,"A",L40<=95%,"B",L40>95%,"C") -> #DIV/0!
B41: sh16 | D41: =C41/C$110 -> #DIV/0! | E41: =E40+D41 -> #DIV/0! | F41: =IF(AND(E41<=0),"C",IF(E41<=0.8,"A",IF(E41<=0.95,"B","C"))) -> #DIV/0! | G41: =VLOOKUP(B$4:B$104,I$4:M$104,5,0) -> #DIV/0! | I41: sh16 | K41: =J41/J$110 -> #DIV/0! | L41: =L40+K41 -> #DIV/0! | M41: =_xlfn.IFS(L41<80%,"A",L41<=95%,"B",L41>95%,"C") -> #DIV/0!
B42: sh17 | D42: =C42/C$110 -> #DIV/0! | E42: =E41+D42 -> #DIV/0! | F42: =IF(AND(E42<=0),"C",IF(E42<=0.8,"A",IF(E42<=0.95,"B","C"))) -> #DIV/0! | G42: =VLOOKUP(B$4:B$104,I$4:M$104,5,0) -> #DIV/0! | I42: sh17 | K42: =J42/J$110 -> #DIV/0! | L42: =L41+K42 -> #DIV/0! | M42: =_xlfn.IFS(L42<80%,"A",L42<=95%,"B",L42>95%,"C") -> #DIV/0!
B43: sh18 | D43: =C43/C$110 -> #DIV/0! | E43: =E42+D43 -> #DIV/0! | F43: =IF(AND(E43<=0),"C",IF(E43<=0.8,"A",IF(E43<=0.95,"B","C"))) -> #DIV/0! | G43: =VLOOKUP(B$4:B$104,I$4:M$104,5,0) -> #DIV/0! | I43: sh18 | K43: =J43/J$110 -> #DIV/0! | L43: =L42+K43 -> #DIV/0! | M43: =_xlfn.IFS(L43<80%,"A",L43<=95%,"B",L43>95%,"C") -> #DIV/0!
B44: sh19 | D44: =C44/C$110 -> #DIV/0! | E44: =E43+D44 -> #DIV/0! | F44: =IF(AND(E44<=0),"C",IF(E44<=0.8,"A",IF(E44<=0.95,"B","C"))) -> #DIV/0! | G44: =VLOOKUP(B$4:B$104,I$4:M$104,5,0) -> #DIV/0! | I44: sh19 | K44: =J44/J$110 -> #DIV/0! | L44: =L43+K44 -> #DIV/0! | M44: =_xlfn.IFS(L44<80%,"A",L44<=95%,"B",L44>95%,"C") -> #DIV/0!
B45: ww 203 черные | D45: =C45/C$110 -> #DIV/0! | E45: =E44+D45 -> #DIV/0! | F45: =IF(AND(E45<=0),"C",IF(E45<=0.8,"A",IF(E45<=0.95,"B","C"))) -> #DIV/0! | G45: =VLOOKUP(B$4:B$104,I$4:M$104,5,0) -> #DIV/0! | I45: ww 203 черные | K45: =J45/J$110 -> #DIV/0! | L45: =L44+K45 -> #DIV/0! | M45: =_xlfn.IFS(L45<80%,"A",L45<=95%,"B",L45>95%,"C") -> #DIV/0!
B46: ww 1022 черные | D46: =C46/C$110 -> #DIV/0! | E46: =E45+D46 -> #DIV/0! | F46: =IF(AND(E46<=0),"C",IF(E46<=0.8,"A",IF(E46<=0.95,"B","C"))) -> #DIV/0! | G46: =VLOOKUP(B$4:B$104,I$4:M$104,5,0) -> #DIV/0! | I46: ww 1022 черные | K46: =J46/J$110 -> #DIV/0! | L46: =L45+K46 -> #DIV/0! | M46: =_xlfn.IFS(L46<80%,"A",L46<=95%,"B",L46>95%,"C") -> #DIV/0!
B47: ww 1022 черн-серебро | D47: =C47/C$110 -> #DIV/0! | E47: =E46+D47 -> #DIV/0! | F47: =IF(AND(E47<=0),"C",IF(E47<=0.8,"A",IF(E47<=0.95,"B","C"))) -> #DIV/0! | G47: =VLOOKUP(B$4:B$104,I$4:M$104,5,0) -> #DIV/0! | I47: ww 1022 черн-серебро | K47: =J47/J$110 -> #DIV/0! | L47: =L46+K47 -> #DIV/0! | M47: =_xlfn.IFS(L47<80%,"A",L47<=95%,"B",L47>95%,"C") -> #DIV/0!
B48: ww 1022 желтые | D48: =C48/C$110 -> #DIV/0! | E48: =E47+D48 -> #DIV/0! | F48: =IF(AND(E48<=0),"C",IF(E48<=0.8,"A",IF(E48<=0.95,"B","C"))) -> #DIV/0! | G48: =VLOOKUP(B$4:B$104,I$4:M$104,5,0) -> #DIV/0! | I48: ww 1022 желтые | K48: =J48/J$110 -> #DIV/0! | L48: =L47+K48 -> #DIV/0! | M48: =_xlfn.IFS(L48<80%,"A",L48<=95%,"B",L48>95%,"C") -> #DIV/0!
B49: ww 1022 коричневые | D49: =C49/C$110 -> #DIV/0! | E49: =E48+D49 -> #DIV/0! | F49: =IF(AND(E49<=0),"C",IF(E49<=0.8,"A",IF(E49<=0.95,"B","C"))) -> #DIV/0! | G49: =VLOOKUP(B$4:B$104,I$4:M$104,5,0) -> #DIV/0! | I49: ww 1022 коричневые | K49: =J49/J$110 -> #DIV/0! | L49: =L48+K49 -> #DIV/0! | M49: =_xlfn.IFS(L49<80%,"A",L49<=95%,"B",L49>95%,"C") -> #DIV/0!
B50: ww 2018 черные | D50: =C50/C$110 -> #DIV/0! | E50: =E49+D50 -> #DIV/0! | F50: =IF(AND(E50<=0),"C",IF(E50<=0.8,"A",IF(E50<=0.95,"B","C"))) -> #DIV/0! | G50: =VLOOKUP(B$4:B$104,I$4:M$104,5,0) -> #DIV/0! | I50: ww 2018 черные | K50: =J50/J$110 -> #DIV/0! | L50: =L49+K50 -> #DIV/0! | M50: =_xlfn.IFS(L50<80%,"A",L50<=95%,"B",L50>95%,"C") -> #DIV/0!
B51: ww 2018 желтые | D51: =C51/C$110 -> #DIV/0! | E51: =E50+D51 -> #DIV/0! | F51: =IF(AND(E51<=0),"C",IF(E51<=0.8,"A",IF(E51<=0.95,"B","C"))) -> #DIV/0! | G51: =VLOOKUP(B$4:B$104,I$4:M$104,5,0) -> #DIV/0! | I51: ww 2018 желтые | K51: =J51/J$110 -> #DIV/0! | L51: =L50+K51 -> #DIV/0! | M51: =_xlfn.IFS(L51<80%,"A",L51<=95%,"B",L51>95%,"C") -> #DIV/0!
... B75: MANNA2121 | D75: =C75/C$110 -> #DIV/0! | E75: =E74+D75 -> #DIV/0! | F75: =IF(AND(E75<=0),"C",IF(E75<=0.8,"A",IF(E75<=0.95,"B","C"))) -> #DIV/0! | G75: =VLOOKUP(B$4:B$104,I$4:M$104,5,0) -> #DIV/0! | I75: MANNA2121 | K75: =J75/J$110 -> #DIV/0! | L75: =L74+K75 -> #DIV/0! | M75: =_xlfn.IFS(L75<80%,"A",L75<=95%,"B",L75>95%,"C") -> #DIV/0!
B76: MANNA2122 | D76: =C76/C$110 -> #DIV/0! | E76: =E49+D76 -> #DIV/0! | F76: =IF(AND(E76<=0),"C",IF(E76<=0.8,"A",IF(E76<=0.95,"B","C"))) -> #DIV/0! | G76: =VLOOKUP(B$4:B$104,I$4:M$104,5,0) -> #DIV/0! | I76: MANNA2122 | K76: =J76/J$110 -> #DIV/0! | L76: =L49+K76 -> #DIV/0! | M76: =_xlfn.IFS(L76<80%,"A",L76<=95%,"B",L76>95%,"C") -> #DIV/0!
B77: Chenlong черные | D77: =C77/C$110 -> #DIV/0! | E77: =E76+D77 -> #DIV/0! | F77: =IF(AND(E77<=0),"C",IF(E77<=0.8,"A",IF(E77<=0.95,"B","C"))) -> #DIV/0! | G77: =VLOOKUP(B$4:B$104,I$4:M$104,5,0) -> #DIV/0! | I77: Chenlong черные | K77: =J77/J$110 -> #DIV/0! | L77: =L76+K77 -> #DIV/0! | M77: =_xlfn.IFS(L77<80%,"A",L77<=95%,"B",L77>95%,"C") -> #DIV/0!
B78: Chenlong коричневые | D78: =C78/C$110 -> #DIV/0! | E78: =E77+D78 -> #DIV/0! | F78: =IF(AND(E78<=0),"C",IF(E78<=0.8,"A",IF(E78<=0.95,"B","C"))) -> #DIV/0! | G78: =VLOOKUP(B$4:B$104,I$4:M$104,5,0) -> #DIV/0! | I78: Chenlong коричневые | K78: =J78/J$110 -> #DIV/0! | L78: =L77+K78 -> #DIV/0! | M78: =_xlfn.IFS(L78<80%,"A",L78<=95%,"B",L78>95%,"C") -> #DIV/0!
B79: Chenlong белые | D79: =C79/C$110 -> #DIV/0! | E79: =E78+D79 -> #DIV/0! | F79: =IF(AND(E79<=0),"C",IF(E79<=0.8,"A",IF(E79<=0.95,"B","C"))) -> #DIV/0! | G79: =VLOOKUP(B$4:B$104,I$4:M$104,5,0) -> #DIV/0! | I79: Chenlong белые | K79: =J79/J$110 -> #DIV/0! | L79: =L78+K79 -> #DIV/0! | M79: =_xlfn.IFS(L79<80%,"A",L79<=95%,"B",L79>95%,"C") -> #DIV/0!
B80: Guangdu золото серая линза | D80: =C80/C$110 -> #DIV/0! | E80: =E79+D80 -> #DIV/0! | F80: =IF(AND(E80<=0),"C",IF(E80<=0.8,"A",IF(E80<=0.95,"B","C"))) -> #DIV/0! | G80: =VLOOKUP(B$4:B$104,I$4:M$104,5,0) -> #DIV/0! | I80: Guangdu золото серая линза | K80: =J80/J$110 -> #DIV/0! | L80: =L79+K80 -> #DIV/0! | M80: =_xlfn.IFS(L80<80%,"A",L80<=95%,"B",L80>95%,"C") -> #DIV/0!
B81: Guangdu серебро серая линза | D81: =C81/C$110 -> #DIV/0! | E81: =E80+D81 -> #DIV/0! | F81: =IF(AND(E81<=0),"C",IF(E81<=0.8,"A",IF(E81<=0.95,"B","C"))) -> #DIV/0! | G81: =VLOOKUP(B$4:B$104,I$4:M$104,5,0) -> #DIV/0! | I81: Guangdu серебро серая линза | K81: =J81/J$110 -> #DIV/0! | L81: =L80+K81 -> #DIV/0! | M81: =_xlfn.IFS(L81<80%,"A",L81<=95%,"B",L81>95%,"C") -> #DIV/0!
B82: Hengda Optical черные | D82: =C82/C$110 -> #DIV/0! | E82: =E81+D82 -> #DIV/0! | F82: =IF(AND(E82<=0),"C",IF(E82<=0.8,"A",IF(E82<=0.95,"B","C"))) -> #DIV/0! | G82: =VLOOKUP(B$4:B$104,I$4:M$104,5,0) -> #DIV/0! | I82: Hengda Optical черные | K82: =J82/J$110 -> #DIV/0! | L82: =L81+K82 -> #DIV/0! | M82: =_xlfn.IFS(L82<80%,"A",L82<=95%,"B",L82>95%,"C") -> #DIV/0!
B83: Hengda Optical леопард | D83: =C83/C$110 -> #DIV/0! | E83: =E82+D83 -> #DIV/0! | F83: =IF(AND(E83<=0),"C",IF(E83<=0.8,"A",IF(E83<=0.95,"B","C"))) -> #DIV/0! | G83: =VLOOKUP(B$4:B$104,I$4:M$104,5,0) -> #DIV/0! | I83: Hengda Optical леопард | K83: =J83/J$110 -> #DIV/0! | L83: =L82+K83 -> #DIV/0! | M83: =_xlfn.IFS(L83<80%,"A",L83<=95%,"B",L83>95%,"C") -> #DIV/0!
B84: Qianai черные | D84: =C84/C$110 -> #DIV/0! | E84: =E83+D84 -> #DIV/0! | F84: =IF(AND(E84<=0),"C",IF(E84<=0.8,"A",IF(E84<=0.95,"B","C"))) -> #DIV/0! | G84: =VLOOKUP(B$4:B$104,I$4:M$104,5,0) -> #DIV/0! | I84: Qianai черные | K84: =J84/J$110 -> #DIV/0! | L84: =L83+K84 -> #DIV/0! | M84: =_xlfn.IFS(L84<80%,"A",L84<=95%,"B",L84>95%,"C") -> #DIV/0!
B85: Qianai коричневые | D85: =C85/C$110 -> #DIV/0! | E85: =E84+D85 -> #DIV/0! | F85: =IF(AND(E85<=0),"C",IF(E85<=0.8,"A",IF(E85<=0.95,"B","C"))) -> #DIV/0! | G85: =VLOOKUP(B$4:B$104,I$4:M$104,5,0) -> #DIV/0! | I85: Qianai коричневые | K85: =J85/J$110 -> #DIV/0! | L85: =L84+K85 -> #DIV/0! | M85: =_xlfn.IFS(L85<80%,"A",L85<=95%,"B",L85>95%,"C") -> #DIV/0!
B86: Keming Aishi коричневые | D86: =C86/C$110 -> #DIV/0! | E86: =E85+D86 -> #DIV/0! | F86: =IF(AND(E86<=0),"C",IF(E86<=0.8,"A",IF(E86<=0.95,"B","C"))) -> #DIV/0! | G86: =VLOOKUP(B$4:B$104,I$4:M$104,5,0) -> #DIV/0! | I86: Keming Aishi коричневые | K86: =J86/J$110 -> #DIV/0! | L86: =L85+K86 -> #DIV/0! | M86: =_xlfn.IFS(L86<80%,"A",L86<=95%,"B",L86>95%,"C") -> #DIV/0!
B87: Linhai Baiyi коричневая линза | D87: =C87/C$110 -> #DIV/0! | E87: =E86+D87 -> #DIV/0! | F87: =IF(AND(E87<=0),"C",IF(E87<=0.8,"A",IF(E87<=0.95,"B","C"))) -> #DIV/0! | G87: =VLOOKUP(B$4:B$104,I$4:M$104,5,0) -> #DIV/0! | I87: Linhai Baiyi коричневая линза | K87: =J87/J$110 -> #DIV/0! | L87: =L86+K87 -> #DIV/0! | M87: =_xlfn.IFS(L87<80%,"A",L87<=95%,"B",L87>95%,"C") -> #DIV/0!
B88: Linhai Baiyi серая линза | D88: =C88/C$110 -> #DIV/0! | E88: =E87+D88 -> #DIV/0! | F88: =IF(AND(E88<=0),"C",IF(E88<=0.8,"A",IF(E88<=0.95,"B","C"))) -> #DIV/0! | G88: =VLOOKUP(B$4:B$104,I$4:M$104,5,0) -> #DIV/0! | I88: Linhai Baiyi серая линза | K88: =J88/J$110 -> #DIV/0! | L88: =L87+K88 -> #DIV/0! | M88: =_xlfn.IFS(L88<80%,"A",L88<=95%,"B",L88>95%,"C") -> #DIV/0!
... B98: POMILED 08247 C4-08 | D98: =C98/C$110 -> #DIV/0! | E98: =E97+D98 -> #DIV/0! | F98: =IF(AND(E98<=0),"C",IF(E98<=0.8,"A",IF(E98<=0.95,"B","C"))) -> #DIV/0! | G98: =VLOOKUP(B$4:B$104,I$4:M$104,5,0) -> #DIV/0! | I98: POMILED 08247 C4-08 | K98: =J98/J$110 -> #DIV/0! | L98: =L97+K98 -> #DIV/0! | M98: =_xlfn.IFS(L98<80%,"A",L98<=95%,"B",L98>95%,"C") -> #DIV/0!
B99: YIMEI 2391 C1 | D99: =C99/C$110 -> #DIV/0! | E99: =E93+D99 -> #DIV/0! | F99: =IF(AND(E99<=0),"C",IF(E99<=0.8,"A",IF(E99<=0.95,"B","C"))) -> #DIV/0! | G99: =VLOOKUP(B$4:B$104,I$4:M$104,5,0) -> #DIV/0! | I99: YIMEI 2391 C1 | K99: =J99/J$110 -> #DIV/0! | L99: =L93+K99 -> #DIV/0! | M99: =_xlfn.IFS(L99<80%,"A",L99<=95%,"B",L99>95%,"C") -> #DIV/0!
B100: ЧСЖ_тест | D100: =C100/C$110 -> #DIV/0! | E100: =E94+D100 -> #DIV/0! | F100: =IF(AND(E100<=0),"C",IF(E100<=0.8,"A",IF(E100<=0.95,"B","C"))) -> #DIV/0! | G100: =VLOOKUP(B$4:B$104,I$4:M$104,5,0) -> #DIV/0! | I100: ЧСЖ_тест | K100: =J100/J$110 -> #DIV/0! | L100: =L94+K100 -> #DIV/0! | M100: =_xlfn.IFS(L100<80%,"A",L100<=95%,"B",L100>95%,"C") -> #DIV/0!
B101: ЧСЖ_женские | D101: =C101/C$110 -> #DIV/0! | E101: =E95+D101 -> #DIV/0! | F101: =IF(AND(E101<=0),"C",IF(E101<=0.8,"A",IF(E101<=0.95,"B","C"))) -> #DIV/0! | G101: =VLOOKUP(B$4:B$104,I$4:M$104,5,0) -> #DIV/0! | I101: ЧСЖ_женские | K101: =J101/J$110 -> #DIV/0! | L101: =L95+K101 -> #DIV/0! | M101: =_xlfn.IFS(L101<80%,"A",L101<=95%,"B",L101>95%,"C") -> #DIV/0!
B102: кс_черные_тест | D102: =C102/C$110 -> #DIV/0! | E102: =E96+D102 -> #DIV/0! | F102: =IF(AND(E102<=0),"C",IF(E102<=0.8,"A",IF(E102<=0.95,"B","C"))) -> #DIV/0! | G102: =VLOOKUP(B$4:B$104,I$4:M$104,5,0) -> #DIV/0! | I102: кс_черные_тест | K102: =J102/J$110 -> #DIV/0! | L102: =L96+K102 -> #DIV/0! | M102: =_xlfn.IFS(L102<80%,"A",L102<=95%,"B",L102>95%,"C") -> #DIV/0!
B103: кс_черные_женские | D103: =C103/C$110 -> #DIV/0! | E103: =E97+D103 -> #DIV/0! | F103: =IF(AND(E103<=0),"C",IF(E103<=0.8,"A",IF(E103<=0.95,"B","C"))) -> #DIV/0! | G103: =VLOOKUP(B$4:B$104,I$4:M$104,5,0) -> #DIV/0! | I103: кс_черные_женские | K103: =J103/J$110 -> #DIV/0! | L103: =L97+K103 -> #DIV/0! | M103: =_xlfn.IFS(L103<80%,"A",L103<=95%,"B",L103>95%,"C") -> #DIV/0!
B104: 1022_коричневые_тест | D104: =C104/C$110 -> #DIV/0! | E104: =E98+D104 -> #DIV/0! | F104: =IF(AND(E104<=0),"C",IF(E104<=0.8,"A",IF(E104<=0.95,"B","C"))) -> #DIV/0! | G104: =VLOOKUP(B$4:B$104,I$4:M$104,5,0) -> #DIV/0! | I104: 1022_коричневые_тест | K104: =J104/J$110 -> #DIV/0! | L104: =L98+K104 -> #DIV/0! | M104: =_xlfn.IFS(L104<80%,"A",L104<=95%,"B",L104>95%,"C") -> #DIV/0!
B105: ridges brand 01 | D105: =C105/C$110 -> #DIV/0! | E105: =E99+D105 -> #DIV/0! | F105: =IF(AND(E105<=0),"C",IF(E105<=0.8,"A",IF(E105<=0.95,"B","C"))) -> #DIV/0! | G105: =VLOOKUP(B$4:B$104,I$4:M$104,5,0) -> #VALUE! | I105: ridges brand 01 | K105: =J105/J$110 -> #DIV/0! | L105: =L99+K105 -> #DIV/0! | M105: =_xlfn.IFS(L105<80%,"A",L105<=95%,"B",L105>95%,"C") -> #DIV/0!
B106: А1248 С3 | D106: =C106/C$110 -> #DIV/0! | E106: =E100+D106 -> #DIV/0! | F106: =IF(AND(E106<=0),"C",IF(E106<=0.8,"A",IF(E106<=0.95,"B","C"))) -> #DIV/0! | G106: =VLOOKUP(B$4:B$104,I$4:M$104,5,0) -> #VALUE! | I106: А1248 С3 | K106: =J106/J$110 -> #DIV/0! | L106: =L100+K106 -> #DIV/0! | M106: =_xlfn.IFS(L106<80%,"A",L106<=95%,"B",L106>95%,"C") -> #DIV/0!
B107: 2422 С1 | D107: =C107/C$110 -> #DIV/0! | E107: =E101+D107 -> #DIV/0! | F107: =IF(AND(E107<=0),"C",IF(E107<=0.8,"A",IF(E107<=0.95,"B","C"))) -> #DIV/0! | G107: =VLOOKUP(B$4:B$104,I$4:M$104,5,0) -> #VALUE! | I107: 2422 С1 | K107: =J107/J$110 -> #DIV/0! | L107: =L101+K107 -> #DIV/0! | M107: =_xlfn.IFS(L107<80%,"A",L107<=95%,"B",L107>95%,"C") -> #DIV/0!
B108: 88118 C8-22 (2303 C3) | D108: =C108/C$110 -> #DIV/0! | E108: =E102+D108 -> #DIV/0! | F108: =IF(AND(E108<=0),"C",IF(E108<=0.8,"A",IF(E108<=0.95,"B","C"))) -> #DIV/0! | G108: =VLOOKUP(B$4:B$104,I$4:M$104,5,0) -> #VALUE! | I108: 88118 C8-22 (2303 C3) | K108: =J108/J$110 -> #DIV/0! | L108: =L102+K108 -> #DIV/0! | M108: =_xlfn.IFS(L108<80%,"A",L108<=95%,"B",L108>95%,"C") -> #DIV/0!
B109: 88118 C9-124 (2303 C1) | D109: =C109/C$110 -> #DIV/0! | E109: =E103+D109 -> #DIV/0! | F109: =IF(AND(E109<=0),"C",IF(E109<=0.8,"A",IF(E109<=0.95,"B","C"))) -> #DIV/0! | G109: =VLOOKUP(B$4:B$104,I$4:M$104,5,0) -> #VALUE! | I109: 88118 C9-124 (2303 C1) | K109: =J109/J$110 -> #DIV/0! | L109: =L103+K109 -> #DIV/0! | M109: =_xlfn.IFS(L109<80%,"A",L109<=95%,"B",L109>95%,"C") -> #DIV/0!
C110: =SUM(C4:C109) -> 0 | D110: =SUM(D4:D109) -> #DIV/0! | J110: =SUM(J4:J109) -> 0 | K110: =SUM(K4:K109) -> #DIV/0!

Sheet АВС 19
B2: ОЧКИ
C3: Прибыль | D3: % прибыль | E3: Доля | F3: ABC прибыль | G3: ABC кол-во | J3: Кол-во | K3: % кол-во | L3: Доля | M3: ABC кол-во
B4: QS черные PZ | C4: ='Юнит 19'!AO4 -> 111612.32 | D4: =C4/C$110 -> 0.17816667 | E4: =D4 -> 0.17816667 | F4: =IF(AND(E4<=0),"C",IF(E4<=0.8,"A",IF(E4<=0.95,"B","C"))) -> A | G4: =VLOOKUP(B$4:B$104,I$4:M$104,5,0) -> A | I4: QS черные PZ | J4: ='Юнит 19'!U4 -> 214 | K4: =J4/J$110 -> 0.12313003 | L4: =K4 -> 0.12313003 | M4: =_xlfn.IFS(L4<80%,"A",L4<=95%,"B",L4>95%,"C") -> A | P4: A | Q4: 0.8
B5: черные с железкой классика | C5: ='Юнит 19'!AO3 -> 57107.728 | D5: =C5/C$110 -> 0.091161028 | E5: =E4+D5 -> 0.26932769 | F5: =IF(AND(E5<=0),"C",IF(E5<=0.8,"A",IF(E5<=0.95,"B","C"))) -> A | G5: =VLOOKUP(B$4:B$104,I$4:M$104,5,0) -> A | I5: flip черные | J5: ='Юнит 19'!U13 -> 211 | K5: =J5/J$110 -> 0.12140391 | L5: =L4+K5 -> 0.24453395 | M5: =_xlfn.IFS(L5<80%,"A",L5<=95%,"B",L5>95%,"C") -> A | P5: B | Q5: 0.15
B6: flip черные | C6: ='Юнит 19'!AO13 -> 54215.878 | D6: =C6/C$110 -> 0.086544769 | E6: =E5+D6 -> 0.35587246 | F6: =IF(AND(E6<=0),"C",IF(E6<=0.8,"A",IF(E6<=0.95,"B","C"))) -> A | G6: =VLOOKUP(B$4:B$104,I$4:M$104,5,0) -> A | I6: th черн | J6: ='Юнит 19'!U9 -> 187 | K6: =J6/J$110 -> 0.10759494 | L6: =L5+K6 -> 0.35212888 | M6: =_xlfn.IFS(L6<80%,"A",L6<=95%,"B",L6>95%,"C") -> A | P6: C | Q6: 0.05
B7: th черн | C7: ='Юнит 19'!AO9 -> 52188.35 | D7: =C7/C$110 -> 0.083308227 | E7: =E6+D7 -> 0.43918069 | F7: =IF(AND(E7<=0),"C",IF(E7<=0.8,"A",IF(E7<=0.95,"B","C"))) -> A | G7: =VLOOKUP(B$4:B$104,I$4:M$104,5,0) -> A | I7: QS синие PZ | J7: ='Юнит 19'!U5 -> 131 | K7: =J7/J$110 -> 0.075373993 | L7: =L6+K7 -> 0.42750288 | M7: =_xlfn.IFS(L7<80%,"A",L7<=95%,"B",L7>95%,"C") -> A
B8: QS синие PZ | C8: ='Юнит 19'!AO5 -> 52027.459 | D8: =C8/C$110 -> 0.083051397 | E8: =E7+D8 -> 0.52223209 | F8: =IF(AND(E8<=0),"C",IF(E8<=0.8,"A",IF(E8<=0.95,"B","C"))) -> A | G8: =VLOOKUP(B$4:B$104,I$4:M$104,5,0) -> A | I8: черные с железкой классика | J8: ='Юнит 19'!U3 -> 121 | K8: =J8/J$110 -> 0.069620253 | L8: =L7+K8 -> 0.49712313 | M8: =_xlfn.IFS(L8<80%,"A",L8<=95%,"B",L8>95%,"C") -> A
B9: flip коричневые | C9: ='Юнит 19'!AO16 -> 45750.218 | D9: =C9/C$110 -> 0.073031041 | E9: =E8+D9 -> 0.59526313 | F9: =IF(AND(E9<=0),"C",IF(E9<=0.8,"A",IF(E9<=0.95,"B","C"))) -> A | G9: =VLOOKUP(B$4:B$104,I$4:M$104,5,0) -> A | I9: flip коричневые | J9: ='Юнит 19'!U16 -> 116 | K9: =J9/J$110 -> 0.066743383 | L9: =L8+K9 -> 0.56386651 | M9: =_xlfn.IFS(L9<80%,"A",L9<=95%,"B",L9>95%,"C") -> A
B10: QS коричневые PZ | C10: ='Юнит 19'!AO7 -> 41835.802 | D10: =C10/C$110 -> 0.066782462 | E10: =E9+D10 -> 0.66204559 | F10: =IF(AND(E10<=0),"C",IF(E10<=0.8,"A",IF(E10<=0.95,"B","C"))) -> A | G10: =VLOOKUP(B$4:B$104,I$4:M$104,5,0) -> A | I10: QS коричневые PZ | J10: ='Юнит 19'!U7 -> 97 | K10: =J10/J$110 -> 0.055811277 | L10: =L9+K10 -> 0.61967779 | M10: =_xlfn.IFS(L10<80%,"A",L10<=95%,"B",L10>95%,"C") -> A
B11: th син | C11: ='Юнит 19'!AO10 -> 25640.956 | D11: =C11/C$110 -> 0.04093064 | E11: =E10+D11 -> 0.70297623 | F11: =IF(AND(E11<=0),"C",IF(E11<=0.8,"A",IF(E11<=0.95,"B","C"))) -> A | G11: =VLOOKUP(B$4:B$104,I$4:M$104,5,0) -> A | I11: th син | J11: ='Юнит 19'!U10 -> 76 | K11: =J11/J$110 -> 0.043728423 | L11: =L10+K11 -> 0.66340621 | M11: =_xlfn.IFS(L11<80%,"A",L11<=95%,"B",L11>95%,"C") -> A
B12: QS желтые PZ | C12: ='Юнит 19'!AO6 -> 22642.573 | D12: =C12/C$110 -> 0.036144323 | E12: =E11+D12 -> 0.73912056 | F12: =IF(AND(E12<=0),"C",IF(E12<=0.8,"A",IF(E12<=0.95,"B","C"))) -> A | G12: =VLOOKUP(B$4:B$104,I$4:M$104,5,0) -> A | I12: th коричн | J12: ='Юнит 19'!U12 -> 57 | K12: =J12/J$110 -> 0.032796318 | L12: =L11+K12 -> 0.69620253 | M12: =_xlfn.IFS(L12<80%,"A",L12<=95%,"B",L12>95%,"C") -> A
B13: th коричн | C13: ='Юнит 19'!AO12 -> 22447.755 | D13: =C13/C$110 -> 0.035833336 | E13: =E12+D13 -> 0.77495389 | F13: =IF(AND(E13<=0),"C",IF(E13<=0.8,"A",IF(E13<=0.95,"B","C"))) -> A | G13: =VLOOKUP(B$4:B$104,I$4:M$104,5,0) -> A | I13: th желт | J13: ='Юнит 19'!U11 -> 53 | K13: =J13/J$110 -> 0.030494822 | L13: =L12+K13 -> 0.72669735 | M13: =_xlfn.IFS(L13<80%,"A",L13<=95%,"B",L13>95%,"C") -> A
B14: th желт | C14: ='Юнит 19'!AO11 -> 20415.579 | D14: =C14/C$110 -> 0.032589375 | E14: =E13+D14 -> 0.80754327 | F14: =IF(AND(E14<=0),"C",IF(E14<=0.8,"A",IF(E14<=0.95,"B","C"))) -> B | G14: =VLOOKUP(B$4:B$104,I$4:M$104,5,0) -> A | I14: QS желтые PZ | J14: ='Юнит 19'!U6 -> 47 | K14: =J14/J$110 -> 0.027042578 | L14: =L13+K14 -> 0.75373993 | M14: =_xlfn.IFS(L14<80%,"A",L14<=95%,"B",L14>95%,"C") -> A
B15: flip синие | C15: ='Юнит 19'!AO14 -> 20255.351 | D15: =C15/C$110 -> 0.032333603 | E15: =E14+D15 -> 0.83987687 | F15: =IF(AND(E15<=0),"C",IF(E15<=0.8,"A",IF(E15<=0.95,"B","C"))) -> B | G15: =VLOOKUP(B$4:B$104,I$4:M$104,5,0) -> A | I15: flip синие | J15: ='Юнит 19'!U14 -> 46 | K15: =J15/J$110 -> 0.026467204 | L15: =L14+K15 -> 0.78020713 | M15: =_xlfn.IFS(L15<80%,"A",L15<=95%,"B",L15>95%,"C") -> A
B16: MR8854 C2 Жен | C16: ='Юнит 19'!AO8 -> 14194.86 | D16: =C16/C$110 -> 0.022659245 | E16: =E15+D16 -> 0.86253611 | F16: =IF(AND(E16<=0),"C",IF(E16<=0.8,"A",IF(E16<=0.95,"B","C"))) -> B | G16: =VLOOKUP(B$4:B$104,I$4:M$104,5,0) -> B | I16: ww 1022 коричневые | J16: ='Юнит 19'!U48 -> 41 | K16: =J16/J$110 -> 0.023590334 | L16: =L15+K16 -> 0.80379747 | M16: =_xlfn.IFS(L16<80%,"A",L16<=95%,"B",L16>95%,"C") -> B
B17: ww 1022 коричневые | C17: ='Юнит 19'!AO48 -> 13730.754 | D17: =C17/C$110 -> 0.021918393 | E17: =E16+D17 -> 0.88445451 | F17: =IF(AND(E17<=0),"C",IF(E17<=0.8,"A",IF(E17<=0.95,"B","C"))) -> B | G17: =VLOOKUP(B$4:B$104,I$4:M$104,5,0) -> B | I17: ww 2018 черные | J17: ='Юнит 19'!U49 -> 34 | K17: =J17/J$110 -> 0.019562716 | L17: =L16+K17 -> 0.82336018 | M17: =_xlfn.IFS(L17<80%,"A",L17<=95%,"B",L17>95%,"C") -> B
B18: flip желтые | C18: ='Юнит 19'!AO15 -> 12765.051 | D18: =C18/C$110 -> 0.020376842 | E18: =E17+D18 -> 0.90483135 | F18: =IF(AND(E18<=0),"C",IF(E18<=0.8,"A",IF(E18<=0.95,"B","C"))) -> B | G18: =VLOOKUP(B$4:B$104,I$4:M$104,5,0) -> B | I18: ww 1022 черные | J18: ='Юнит 19'!U45 -> 32 | K18: =J18/J$110 -> 0.018411968 | L18: =L17+K18 -> 0.84177215 | M18: =_xlfn.IFS(L18<80%,"A",L18<=95%,"B",L18>95%,"C") -> B
B19: ww 1022 черные | C19: ='Юнит 19'!AO45 -> 11330.69 | D19: =C19/C$110 -> 0.018087173 | E19: =E18+D19 -> 0.92291852 | F19: =IF(AND(E19<=0),"C",IF(E19<=0.8,"A",IF(E19<=0.95,"B","C"))) -> B | G19: =VLOOKUP(B$4:B$104,I$4:M$104,5,0) -> B | I19: flip желтые | J19: ='Юнит 19'!U15 -> 30 | K19: =J19/J$110 -> 0.01726122 | L19: =L18+K19 -> 0.85903337 | M19: =_xlfn.IFS(L19<80%,"A",L19<=95%,"B",L19>95%,"C") -> B
B20: ww 2018 желтые | C20: ='Юнит 19'!AO50 -> 10430.702 | D20: =C20/C$110 -> 0.016650522 | E20: =E19+D20 -> 0.93956904 | F20: =IF(AND(E20<=0),"C",IF(E20<=0.8,"A",IF(E20<=0.95,"B","C"))) -> B | G20: =VLOOKUP(B$4:B$104,I$4:M$104,5,0) -> B | I20: MR8854 C2 Жен | J20: ='Юнит 19'!U8 -> 29 | K20: =J20/J$110 -> 0.016685846 | L20: =L19+K20 -> 0.87571922 | M20: =_xlfn.IFS(L20<80%,"A",L20<=95%,"B",L20>95%,"C") -> B
B21: ww 2018 черные | C21: ='Юнит 19'!AO49 -> 10287.709 | D21: =C21/C$110 -> 0.016422262 | E21: =E20+D21 -> 0.95599131 | F21: =IF(AND(E21<=0),"C",IF(E21<=0.8,"A",IF(E21<=0.95,"B","C"))) -> C | G21: =VLOOKUP(B$4:B$104,I$4:M$104,5,0) -> B | I21: ridges brand 01 | J21: ='Юнит 19'!U104 -> 26 | K21: =J21/J$110 -> 0.014959724 | L21: =L20+K21 -> 0.89067894 | M21: =_xlfn.IFS(L21<80%,"A",L21<=95%,"B",L21>95%,"C") -> B
B22: wwl8032 хром металл | C22: ='Юнит 19'!AO18 -> 7750.9703 | D22: =C22/C$110 -> 0.012372869 | E22: =E21+D22 -> 0.96836417 | F22: =IF(AND(E22<=0),"C",IF(E22<=0.8,"A",IF(E22<=0.95,"B","C"))) -> C | G22: =VLOOKUP(B$4:B$104,I$4:M$104,5,0) -> B | I22: ww 2018 желтые | J22: ='Юнит 19'!U50 -> 24 | K22: =J22/J$110 -> 0.013808976 | L22: =L21+K22 -> 0.90448792 | M22: =_xlfn.IFS(L22<80%,"A",L22<=95%,"B",L22>95%,"C") -> B
B23: ww 203 черные | C23: ='Юнит 19'!AO44 -> 7388.8949 | D23: =C23/C$110 -> 0.011794888 | E23: =E22+D23 -> 0.98015906 | F23: =IF(AND(E23<=0),"C",IF(E23<=0.8,"A",IF(E23<=0.95,"B","C"))) -> C | G23: =VLOOKUP(B$4:B$104,I$4:M$104,5,0) -> B | I23: wwl8032 хром металл | J23: ='Юнит 19'!U18 -> 21 | K23: =J23/J$110 -> 0.012082854 | L23: =L22+K23 -> 0.91657077 | M23: =_xlfn.IFS(L23<80%,"A",L23<=95%,"B",L23>95%,"C") -> B
B24: wwl8032 коричневые золото | C24: ='Юнит 19'!AO17 -> 5129.8781 | D24: =C24/C$110 -> 0.0081888209 | E24: =E23+D24 -> 0.98834788 | F24: =IF(AND(E24<=0),"C",IF(E24<=0.8,"A",IF(E24<=0.95,"B","C"))) -> C | G24: =VLOOKUP(B$4:B$104,I$4:M$104,5,0) -> B | I24: sh3 | J24: ='Юнит 19'!U28 -> 20 | K24: =J24/J$110 -> 0.01150748 | L24: =L23+K24 -> 0.92807825 | M24: =_xlfn.IFS(L24<80%,"A",L24<=95%,"B",L24>95%,"C") -> B
B25: ww 1022 желтые | C25: ='Юнит 19'!AO47 -> 4410.2847 | D25: =C25/C$110 -> 0.0070401345 | E25: =E24+D25 -> 0.99538802 | F25: =IF(AND(E25<=0),"C",IF(E25<=0.8,"A",IF(E25<=0.95,"B","C"))) -> C | G25: =VLOOKUP(B$4:B$104,I$4:M$104,5,0) -> C | I25: ww 203 черные | J25: ='Юнит 19'!U44 -> 17 | K25: =J25/J$110 -> 0.0097813579 | L25: =L24+K25 -> 0.93785961 | M25: =_xlfn.IFS(L25<80%,"A",L25<=95%,"B",L25>95%,"C") -> B
B26: MR Р1894 черные | C26: ='Юнит 19'!AO89 -> 2591.8024 | D26: =C26/C$110 -> 0.0041372924 | E26: =E25+D26 -> 0.99952531 | F26: =IF(AND(E26<=0),"C",IF(E26<=0.8,"A",IF(E26<=0.95,"B","C"))) -> C | G26: =VLOOKUP(B$4:B$104,I$4:M$104,5,0) -> C | I26: wwl8032 коричневые золото | J26: ='Юнит 19'!U17 -> 16 | K26: =J26/J$110 -> 0.0092059839 | L26: =L25+K26 -> 0.94706559 | M26: =_xlfn.IFS(L26<80%,"A",L26<=95%,"B",L26>95%,"C") -> B
B27: sh3 | C27: ='Юнит 19'!AO28 -> 2464.8841 | D27: =C27/C$110 -> 0.0039346928 | E27: =E26+D27 -> 1.00346 | F27: =IF(AND(E27<=0),"C",IF(E27<=0.8,"A",IF(E27<=0.95,"B","C"))) -> C | G27: =VLOOKUP(B$4:B$104,I$4:M$104,5,0) -> B | I27: sports красные | J27: ='Юнит 19'!U22 -> 12 | K27: =J27/J$110 -> 0.0069044879 | L27: =L26+K27 -> 0.95397008 | M27: =_xlfn.IFS(L27<80%,"A",L27<=95%,"B",L27>95%,"C") -> C
B28: sh1 | C28: ='Юнит 19'!AO26 -> 2078.8322 | D28: =C28/C$110 -> 0.0033184385 | E28: =E27+D28 -> 1.0067784 | F28: =IF(AND(E28<=0),"C",IF(E28<=0.8,"A",IF(E28<=0.95,"B","C"))) -> C | G28: =VLOOKUP(B$4:B$104,I$4:M$104,5,0) -> C | I28: ww 1022 желтые | J28: ='Юнит 19'!U47 -> 10 | K28: =J28/J$110 -> 0.0057537399 | L28: =L27+K28 -> 0.95972382 | M28: =_xlfn.IFS(L28<80%,"A",L28<=95%,"B",L28>95%,"C") -> C
B29: Guangdu золото серая линза | C29: ='Юнит 19'!AO79 -> 1587.6387 | D29: =C29/C$110 -> 0.0025343466 | E29: =E28+D29 -> 1.0093128 | F29: =IF(AND(E29<=0),"C",IF(E29<=0.8,"A",IF(E29<=0.95,"B","C"))) -> C | G29: =VLOOKUP(B$4:B$104,I$4:M$104,5,0) -> C | I29: sports синие | J29: ='Юнит 19'!U20 -> 9 | K29: =J29/J$110 -> 0.0051783659 | L29: =L28+K29 -> 0.96490219 | M29: =_xlfn.IFS(L29<80%,"A",L29<=95%,"B",L29>95%,"C") -> C
B30: ridges brand 01 | C30: ='Юнит 19'!AO104 -> 916.89114 | D30: =C30/C$110 -> 0.0014636327 | E30: =E29+D30 -> 1.0107764 | F30: =IF(AND(E30<=0),"C",IF(E30<=0.8,"A",IF(E30<=0.95,"B","C"))) -> C | G30: =VLOOKUP(B$4:B$104,I$4:M$104,5,0) -> B | I30: sports зеленые | J30: ='Юнит 19'!U21 -> 7 | K30: =J30/J$110 -> 0.004027618 | L30: =L29+K30 -> 0.9689298 | M30: =_xlfn.IFS(L30<80%,"A",L30<=95%,"B",L30>95%,"C") -> C
B31: sh09 | C31: ='Юнит 19'!AO33 -> 897.0323 | D31: =C31/C$110 -> 0.0014319321 | E31: =E30+D31 -> 1.0122084 | F31: =IF(AND(E31<=0),"C",IF(E31<=0.8,"A",IF(E31<=0.95,"B","C"))) -> C | G31: =VLOOKUP(B$4:B$104,I$4:M$104,5,0) -> C | I31: Guangdu золото серая линза | J31: ='Юнит 19'!U79 -> 7 | K31: =J31/J$110 -> 0.004027618 | L31: =L30+K31 -> 0.97295742 | M31: =_xlfn.IFS(L31<80%,"A",L31<=95%,"B",L31>95%,"C") -> C
B32: sh19 | C32: ='Юнит 19'!AO43 -> 843.7996 | D32: =C32/C$110 -> 0.0013469567 | E32: =E31+D32 -> 1.0135553 | F32: =IF(AND(E32<=0),"C",IF(E32<=0.8,"A",IF(E32<=0.95,"B","C"))) -> C | G32: =VLOOKUP(B$4:B$104,I$4:M$104,5,0) -> C | I32: sh09 | J32: ='Юнит 19'!U33 -> 6 | K32: =J32/J$110 -> 0.003452244 | L32: =L31+K32 -> 0.97640967 | M32: =_xlfn.IFS(L32<80%,"A",L32<=95%,"B",L32>95%,"C") -> C
B33: sportlife синие | C33: ='Юнит 19'!AO24 -> 684.51776 | D33: =C33/C$110 -> 0.0010926952 | E33: =E32+D33 -> 1.014648 | F33: =IF(AND(E33<=0),"C",IF(E33<=0.8,"A",IF(E33<=0.95,"B","C"))) -> C | G33: =VLOOKUP(B$4:B$104,I$4:M$104,5,0) -> C | I33: sh1 | J33: ='Юнит 19'!U26 -> 5 | K33: =J33/J$110 -> 0.00287687 | L33: =L32+K33 -> 0.97928654 | M33: =_xlfn.IFS(L33<80%,"A",L33<=95%,"B",L33>95%,"C") -> C
B34: MANNA2101 | C34: ='Юнит 19'!AO54 -> 551.10211 | D34: =C34/C$110 -> 0.00087972392 | E34: =E33+D34 -> 1.0155277 | F34: =IF(AND(E34<=0),"C",IF(E34<=0.8,"A",IF(E34<=0.95,"B","C"))) -> C | G34: =VLOOKUP(B$4:B$104,I$4:M$104,5,0) -> C | I34: MR Р1894 черные | J34: ='Юнит 19'!U89 -> 4 | K34: =J34/J$110 -> 0.002301496 | L34: =L33+K34 -> 0.98158803 | M34: =_xlfn.IFS(L34<80%,"A",L34<=95%,"B",L34>95%,"C") -> C
B35: sh16 | C35: ='Юнит 19'!AO40 -> 486.31296 | D35: =C35/C$110 -> 0.00077630106 | E35: =E34+D35 -> 1.016304 | F35: =IF(AND(E35<=0),"C",IF(E35<=0.8,"A",IF(E35<=0.95,"B","C"))) -> C | G35: =VLOOKUP(B$4:B$104,I$4:M$104,5,0) -> C | I35: WW 3055 черный | J35: ='Юнит 19'!U52 -> 3 | K35: =J35/J$110 -> 0.001726122 | L35: =L34+K35 -> 0.98331415 | M35: =_xlfn.IFS(L35<80%,"A",L35<=95%,"B",L35>95%,"C") -> C
B36: Guangdu серебро серая линза | C36: ='Юнит 19'!AO80 -> 450.87083 | D36: =C36/C$110 -> 0.00071972481 | E36: =E35+D36 -> 1.0170238 | F36: =IF(AND(E36<=0),"C",IF(E36<=0.8,"A",IF(E36<=0.95,"B","C"))) -> C | G36: =VLOOKUP(B$4:B$104,I$4:M$104,5,0) -> C | I36: Chenlong черные | J36: ='Юнит 19'!U76 -> 3 | K36: =J36/J$110 -> 0.001726122 | L36: =L35+K36 -> 0.98504028 | M36: =_xlfn.IFS(L36<80%,"A",L36<=95%,"B",L36>95%,"C") -> C
B37: Qianai коричневые | C37: ='Юнит 19'!AO84 -> 445.44658 | D37: =C37/C$110 -> 0.00071106607 | E37: =E36+D37 -> 1.0177348 | F37: =IF(AND(E37<=0),"C",IF(E37<=0.8,"A",IF(E37<=0.95,"B","C"))) -> C | G37: =VLOOKUP(B$4:B$104,I$4:M$104,5,0) -> C | I37: Linhai Baiyi коричневая линза | J37: ='Юнит 19'!U86 -> 3 | K37: =J37/J$110 -> 0.001726122 | L37: =L36+K37 -> 0.9867664 | M37: =_xlfn.IFS(L37<80%,"A",L37<=95%,"B",L37>95%,"C") -> C
B38: MANNA2122 | C38: ='Юнит 19'!AO75 -> 435.08966 | D38: =C38/C$110 -> 0.00069453333 | E38: =E37+D38 -> 1.0184294 | F38: =IF(AND(E38<=0),"C",IF(E38<=0.8,"A",IF(E38<=0.95,"B","C"))) -> C | G38: =VLOOKUP(B$4:B$104,I$4:M$104,5,0) -> C | I38: sportlife синие | J38: ='Юнит 19'!U24 -> 2 | K38: =J38/J$110 -> 0.001150748 | L38: =L37+K38 -> 0.98791715 | M38: =_xlfn.IFS(L38<80%,"A",L38<=95%,"B",L38>95%,"C") -> C
B39: MANNA2112 | C39: ='Юнит 19'!AO65 -> 423.3255 | D39: =C39/C$110 -> 0.00067575421 | E39: =E35+D39 -> 1.0169798 | F39: =IF(AND(E39<=0),"C",IF(E39<=0.8,"A",IF(E39<=0.95,"B","C"))) -> C | G39: =VLOOKUP(B$4:B$104,I$4:M$104,5,0) -> C | I39: sh19 | J39: ='Юнит 19'!U43 -> 2 | K39: =J39/J$110 -> 0.001150748 | L39: =L35+K39 -> 0.9844649 | M39: =_xlfn.IFS(L39<80%,"A",L39<=95%,"B",L39>95%,"C") -> C
B40: sh15 | C40: ='Юнит 19'!AO39 -> 377.03592 | D40: =C40/C$110 -> 0.00060186218 | E40: =E39+D40 -> 1.0175816 | F40: =IF(AND(E40<=0),"C",IF(E40<=0.8,"A",IF(E40<=0.95,"B","C"))) -> C | G40: =VLOOKUP(B$4:B$104,I$4:M$104,5,0) -> C | I40: MANNA2101 | J40: ='Юнит 19'!U54 -> 2 | K40: =J40/J$110 -> 0.001150748 | L40: =L39+K40 -> 0.98561565 | M40: =_xlfn.IFS(L40<80%,"A",L40<=95%,"B",L40>95%,"C") -> C
B41: Linhai Baiyi серая линза | C41: ='Юнит 19'!AO87 -> 253.4616 | D41: =C41/C$110 -> 0.00040460058 | E41: =E40+D41 -> 1.0179862 | F41: =IF(AND(E41<=0),"C",IF(E41<=0.8,"A",IF(E41<=0.95,"B","C"))) -> C | G41: =VLOOKUP(B$4:B$104,I$4:M$104,5,0) -> C | I41: MANNA2122 | J41: ='Юнит 19'!U75 -> 2 | K41: =J41/J$110 -> 0.001150748 | L41: =L40+K41 -> 0.9867664 | M41: =_xlfn.IFS(L41<80%,"A",L41<=95%,"B",L41>95%,"C") -> C
B42: Ли Сян ретро золото | C42: ='Юнит 19'!AO92 -> 231.10277 | D42: =C42/C$110 -> 0.0003689092 | E42: =E41+D42 -> 1.0183552 | F42: =IF(AND(E42<=0),"C",IF(E42<=0.8,"A",IF(E42<=0.95,"B","C"))) -> C | G42: =VLOOKUP(B$4:B$104,I$4:M$104,5,0) -> C | I42: Chenlong коричневые | J42: ='Юнит 19'!U77 -> 2 | K42: =J42/J$110 -> 0.001150748 | L42: =L41+K42 -> 0.98791715 | M42: =_xlfn.IFS(L42<80%,"A",L42<=95%,"B",L42>95%,"C") -> C
B43: MANNA2118 | C43: ='Юнит 19'!AO71 -> 66.461663 | D43: =C43/C$110 -> 0.00010609271 | E43: =E42+D43 -> 1.0184612 | F43: =IF(AND(E43<=0),"C",IF(E43<=0.8,"A",IF(E43<=0.95,"B","C"))) -> C | G43: =VLOOKUP(B$4:B$104,I$4:M$104,5,0) -> C | I43: Guangdu серебро серая линза | J43: ='Юнит 19'!U80 -> 2 | K43: =J43/J$110 -> 0.001150748 | L43: =L42+K43 -> 0.98906789 | M43: =_xlfn.IFS(L43<80%,"A",L43<=95%,"B",L43>95%,"C") -> C
B44: wwl8032 черные серебро | C44: ='Юнит 19'!AO19 -> 0 | D44: =C44/C$110 -> 0 | E44: =E43+D44 -> 1.0184612 | F44: =IF(AND(E44<=0),"C",IF(E44<=0.8,"A",IF(E44<=0.95,"B","C"))) -> C | G44: =VLOOKUP(B$4:B$104,I$4:M$104,5,0) -> C | I44: sh15 | J44: ='Юнит 19'!U39 -> 1 | K44: =J44/J$110 -> 0.00057537399 | L44: =L43+K44 -> 0.98964327 | M44: =_xlfn.IFS(L44<80%,"A",L44<=95%,"B",L44>95%,"C") -> C
B45: sportlife черные | C45: ='Юнит 19'!AO23 -> 0 | D45: =C45/C$110 -> 0 | E45: =E44+D45 -> 1.0184612 | F45: =IF(AND(E45<=0),"C",IF(E45<=0.8,"A",IF(E45<=0.95,"B","C"))) -> C | G45: =VLOOKUP(B$4:B$104,I$4:M$104,5,0) -> C | I45: sh16 | J45: ='Юнит 19'!U40 -> 1 | K45: =J45/J$110 -> 0.00057537399 | L45: =L44+K45 -> 0.99021864 | M45: =_xlfn.IFS(L45<80%,"A",L45<=95%,"B",L45>95%,"C") -> C
B46: sportlife красные | C46: ='Юнит 19'!AO25 -> 0 | D46: =C46/C$110 -> 0 | E46: =E45+D46 -> 1.0184612 | F46: =IF(AND(E46<=0),"C",IF(E46<=0.8,"A",IF(E46<=0.95,"B","C"))) -> C | G46: =VLOOKUP(B$4:B$104,I$4:M$104,5,0) -> C | I46: WW 3055 коричневый | J46: ='Юнит 19'!U53 -> 1 | K46: =J46/J$110 -> 0.00057537399 | L46: =L45+K46 -> 0.99079402 | M46: =_xlfn.IFS(L46<80%,"A",L46<=95%,"B",L46>95%,"C") -> C
B47: sh4 | C47: ='Юнит 19'!AO29 -> 0 | D47: =C47/C$110 -> 0 | E47: =E46+D47 -> 1.0184612 | F47: =IF(AND(E47<=0),"C",IF(E47<=0.8,"A",IF(E47<=0.95,"B","C"))) -> C | G47: =VLOOKUP(B$4:B$104,I$4:M$104,5,0) -> C | I47: MANNA2112 | J47: ='Юнит 19'!U65 -> 1 | K47: =J47/J$110 -> 0.00057537399 | L47: =L46+K47 -> 0.99136939 | M47: =_xlfn.IFS(L47<80%,"A",L47<=95%,"B",L47>95%,"C") -> C
B48: sh06 | C48: ='Юнит 19'!AO30 -> 0 | D48: =C48/C$110 -> 0 | E48: =E47+D48 -> 1.0184612 | F48: =IF(AND(E48<=0),"C",IF(E48<=0.8,"A",IF(E48<=0.95,"B","C"))) -> C | G48: =VLOOKUP(B$4:B$104,I$4:M$104,5,0) -> C | I48: MANNA2118 | J48: ='Юнит 19'!U71 -> 1 | K48: =J48/J$110 -> 0.00057537399 | L48: =L47+K48 -> 0.99194476 | M48: =_xlfn.IFS(L48<80%,"A",L48<=95%,"B",L48>95%,"C") -> C
B49: sh07 | C49: ='Юнит 19'!AO31 -> 0 | D49: =C49/C$110 -> 0 | E49: =E48+D49 -> 1.0184612 | F49: =IF(AND(E49<=0),"C",IF(E49<=0.8,"A",IF(E49<=0.95,"B","C"))) -> C | G49: =VLOOKUP(B$4:B$104,I$4:M$104,5,0) -> C | I49: Chenlong белые | J49: ='Юнит 19'!U78 -> 1 | K49: =J49/J$110 -> 0.00057537399 | L49: =L48+K49 -> 0.99252014 | M49: =_xlfn.IFS(L49<80%,"A",L49<=95%,"B",L49>95%,"C") -> C
B50: sh08 | C50: ='Юнит 19'!AO32 -> 0 | D50: =C50/C$110 -> 0 | E50: =E49+D50 -> 1.0184612 | F50: =IF(AND(E50<=0),"C",IF(E50<=0.8,"A",IF(E50<=0.95,"B","C"))) -> C | G50: =VLOOKUP(B$4:B$104,I$4:M$104,5,0) -> C | I50: Qianai коричневые | J50: ='Юнит 19'!U84 -> 1 | K50: =J50/J$110 -> 0.00057537399 | L50: =L49+K50 -> 0.99309551 | M50: =_xlfn.IFS(L50<80%,"A",L50<=95%,"B",L50>95%,"C") -> C
B51: sh10 | C51: ='Юнит 19'!AO34 -> 0 | D51: =C51/C$110 -> 0 | E51: =E50+D51 -> 1.0184612 | F51: =IF(AND(E51<=0),"C",IF(E51<=0.8,"A",IF(E51<=0.95,"B","C"))) -> C | G51: =VLOOKUP(B$4:B$104,I$4:M$104,5,0) -> C | I51: Keming Aishi коричневые | J51: ='Юнит 19'!U85 -> 1 | K51: =J51/J$110 -> 0.00057537399 | L51: =L50+K51 -> 0.99367089 | M51: =_xlfn.IFS(L51<80%,"A",L51<=95%,"B",L51>95%,"C") -> C
B52: sh11 | C52: ='Юнит 19'!AO35 -> 0 | D52: =C52/C$110 -> 0 | E52: =E51+D52 -> 1.0184612 | F52: =IF(AND(E52<=0),"C",IF(E52<=0.8,"A",IF(E52<=0.95,"B","C"))) -> C | G52: =VLOOKUP(B$4:B$104,I$4:M$104,5,0) -> C | I52: Linhai Baiyi серая линза | J52: ='Юнит 19'!U87 -> 1 | K52: =J52/J$110 -> 0.00057537399 | L52: =L51+K52 -> 0.99424626 | M52: =_xlfn.IFS(L52<80%,"A",L52<=95%,"B",L52>95%,"C") -> C
B53: sh12 | C53: ='Юнит 19'!AO36 -> 0 | D53: =C53/C$110 -> 0 | E53: =E52+D53 -> 1.0184612 | F53: =IF(AND(E53<=0),"C",IF(E53<=0.8,"A",IF(E53<=0.95,"B","C"))) -> C | G53: =VLOOKUP(B$4:B$104,I$4:M$104,5,0) -> C | I53: Ли Сян ретро золото | J53: ='Юнит 19'!U92 -> 1 | K53: =J53/J$110 -> 0.00057537399 | L53: =L52+K53 -> 0.99482163 | M53: =_xlfn.IFS(L53<80%,"A",L53<=95%,"B",L53>95%,"C") -> C
B54: ww 1022 черн-серебро | C54: ='Юнит 19'!AO46 -> 0 | D54: =C54/C$110 -> 0 | E54: =E53+D54 -> 1.0184612 | F54: =IF(AND(E54<=0),"C",IF(E54<=0.8,"A",IF(E54<=0.95,"B","C"))) -> C | G54: =VLOOKUP(B$4:B$104,I$4:M$104,5,0) -> C | I54: кс_черные_женские | J54: ='Юнит 19'!U102 -> 1 | K54: =J54/J$110 -> 0.00057537399 | L54: =L53+K54 -> 0.99539701 | M54: =_xlfn.IFS(L54<80%,"A",L54<=95%,"B",L54>95%,"C") -> C
B55: MANNA2102 | C55: ='Юнит 19'!AO55 -> 0 | D55: =C55/C$110 -> 0 | E55: =E54+D55 -> 1.0184612 | F55: =IF(AND(E55<=0),"C",IF(E55<=0.8,"A",IF(E55<=0.95,"B","C"))) -> C | G55: =VLOOKUP(B$4:B$104,I$4:M$104,5,0) -> C | I55: wwl8032 черные серебро | J55: ='Юнит 19'!U19 -> 0 | K55: =J55/J$110 -> 0 | L55: =L54+K55 -> 0.99539701 | M55: =_xlfn.IFS(L55<80%,"A",L55<=95%,"B",L55>95%,"C") -> C
B56: MANNA2103 | C56: ='Юнит 19'!AO56 -> 0 | D56: =C56/C$110 -> 0 | E56: =E55+D56 -> 1.0184612 | F56: =IF(AND(E56<=0),"C",IF(E56<=0.8,"A",IF(E56<=0.95,"B","C"))) -> C | G56: =VLOOKUP(B$4:B$104,I$4:M$104,5,0) -> C | I56: sportlife черные | J56: ='Юнит 19'!U23 -> 0 | K56: =J56/J$110 -> 0 | L56: =L55+K56 -> 0.99539701 | M56: =_xlfn.IFS(L56<80%,"A",L56<=95%,"B",L56>95%,"C") -> C
B57: MANNA2104 | C57: ='Юнит 19'!AO57 -> 0 | D57: =C57/C$110 -> 0 | E57: =E56+D57 -> 1.0184612 | F57: =IF(AND(E57<=0),"C",IF(E57<=0.8,"A",IF(E57<=0.95,"B","C"))) -> C | G57: =VLOOKUP(B$4:B$104,I$4:M$104,5,0) -> C | I57: sportlife красные | J57: ='Юнит 19'!U25 -> 0 | K57: =J57/J$110 -> 0 | L57: =L56+K57 -> 0.99539701 | M57: =_xlfn.IFS(L57<80%,"A",L57<=95%,"B",L57>95%,"C") -> C
B58: MANNA2106 | C58: ='Юнит 19'!AO59 -> 0 | D58: =C58/C$110 -> 0 | E58: =E57+D58 -> 1.0184612 | F58: =IF(AND(E58<=0),"C",IF(E58<=0.8,"A",IF(E58<=0.95,"B","C"))) -> C | G58: =VLOOKUP(B$4:B$104,I$4:M$104,5,0) -> C | I58: sh2 | J58: ='Юнит 19'!U27 -> 0 | K58: =J58/J$110 -> 0 | L58: =L57+K58 -> 0.99539701 | M58: =_xlfn.IFS(L58<80%,"A",L58<=95%,"B",L58>95%,"C") -> C
B59: MANNA2109 | C59: ='Юнит 19'!AO62 -> 0 | D59: =C59/C$110 -> 0 | E59: =E58+D59 -> 1.0184612 | F59: =IF(AND(E59<=0),"C",IF(E59<=0.8,"A",IF(E59<=0.95,"B","C"))) -> C | G59: =VLOOKUP(B$4:B$104,I$4:M$104,5,0) -> C | I59: sh4 | J59: ='Юнит 19'!U29 -> 0 | K59: =J59/J$110 -> 0 | L59: =L58+K59 -> 0.99539701 | M59: =_xlfn.IFS(L59<80%,"A",L59<=95%,"B",L59>95%,"C") -> C
B60: MANNA2110 | C60: ='Юнит 19'!AO63 -> 0 | D60: =C60/C$110 -> 0 | E60: =E59+D60 -> 1.0184612 | F60: =IF(AND(E60<=0),"C",IF(E60<=0.8,"A",IF(E60<=0.95,"B","C"))) -> C | G60: =VLOOKUP(B$4:B$104,I$4:M$104,5,0) -> C | I60: sh06 | J60: ='Юнит 19'!U30 -> 0 | K60: =J60/J$110 -> 0 | L60: =L59+K60 -> 0.99539701 | M60: =_xlfn.IFS(L60<80%,"A",L60<=95%,"B",L60>95%,"C") -> C
B61: MANNA2111 | C61: ='Юнит 19'!AO64 -> 0 | D61: =C61/C$110 -> 0 | E61: =E60+D61 -> 1.0184612 | F61: =IF(AND(E61<=0),"C",IF(E61<=0.8,"A",IF(E61<=0.95,"B","C"))) -> C | G61: =VLOOKUP(B$4:B$104,I$4:M$104,5,0) -> C | I61: sh07 | J61: ='Юнит 19'!U31 -> 0 | K61: =J61/J$110 -> 0 | L61: =L60+K61 -> 0.99539701 | M61: =_xlfn.IFS(L61<80%,"A",L61<=95%,"B",L61>95%,"C") -> C
B62: MANNA2114 | C62: ='Юнит 19'!AO67 -> 0 | D62: =C62/C$110 -> 0 | E62: =E61+D62 -> 1.0184612 | F62: =IF(AND(E62<=0),"C",IF(E62<=0.8,"A",IF(E62<=0.95,"B","C"))) -> C | G62: =VLOOKUP(B$4:B$104,I$4:M$104,5,0) -> C | I62: sh08 | J62: ='Юнит 19'!U32 -> 0 | K62: =J62/J$110 -> 0 | L62: =L61+K62 -> 0.99539701 | M62: =_xlfn.IFS(L62<80%,"A",L62<=95%,"B",L62>95%,"C") -> C
B63: MANNA2115 | C63: ='Юнит 19'!AO68 -> 0 | D63: =C63/C$110 -> 0 | E63: =E62+D63 -> 1.0184612 | F63: =IF(AND(E63<=0),"C",IF(E63<=0.8,"A",IF(E63<=0.95,"B","C"))) -> C | G63: =VLOOKUP(B$4:B$104,I$4:M$104,5,0) -> C | I63: sh10 | J63: ='Юнит 19'!U34 -> 0 | K63: =J63/J$110 -> 0 | L63: =L62+K63 -> 0.99539701 | M63: =_xlfn.IFS(L63<80%,"A",L63<=95%,"B",L63>95%,"C") -> C
B64: MANNA2117 | C64: ='Юнит 19'!AO70 -> 0 | D64: =C64/C$110 -> 0 | E64: =E63+D64 -> 1.0184612 | F64: =IF(AND(E64<=0),"C",IF(E64<=0.8,"A",IF(E64<=0.95,"B","C"))) -> C | G64: =VLOOKUP(B$4:B$104,I$4:M$104,5,0) -> C | I64: sh11 | J64: ='Юнит 19'!U35 -> 0 | K64: =J64/J$110 -> 0 | L64: =L63+K64 -> 0.99539701 | M64: =_xlfn.IFS(L64<80%,"A",L64<=95%,"B",L64>95%,"C") -> C
B65: MANNA2119 | C65: ='Юнит 19'!AO72 -> 0 | D65: =C65/C$110 -> 0 | E65: =E64+D65 -> 1.0184612 | F65: =IF(AND(E65<=0),"C",IF(E65<=0.8,"A",IF(E65<=0.95,"B","C"))) -> C | G65: =VLOOKUP(B$4:B$104,I$4:M$104,5,0) -> C | I65: sh12 | J65: ='Юнит 19'!U36 -> 0 | K65: =J65/J$110 -> 0 | L65: =L64+K65 -> 0.99539701 | M65: =_xlfn.IFS(L65<80%,"A",L65<=95%,"B",L65>95%,"C") -> C
B66: MANNA2121 | C66: ='Юнит 19'!AO74 -> 0 | D66: =C66/C$110 -> 0 | E66: =E65+D66 -> 1.0184612 | F66: =IF(AND(E66<=0),"C",IF(E66<=0.8,"A",IF(E66<=0.95,"B","C"))) -> C | G66: =VLOOKUP(B$4:B$104,I$4:M$104,5,0) -> C | I66: sh13 | J66: ='Юнит 19'!U37 -> 0 | K66: =J66/J$110 -> 0 | L66: =L65+K66 -> 0.99539701 | M66: =_xlfn.IFS(L66<80%,"A",L66<=95%,"B",L66>95%,"C") -> C
B67: MAIERSHA 03898 C9-08 | C67: ='Юнит 19'!AO94 -> 0 | D67: =C67/C$110 -> 0 | E67: =E66+D67 -> 1.0184612 | F67: =IF(AND(E67<=0),"C",IF(E67<=0.8,"A",IF(E67<=0.95,"B","C"))) -> C | G67: =VLOOKUP(B$4:B$104,I$4:M$104,5,0) -> C | I67: sh14 | J67: ='Юнит 19'!U38 -> 0 | K67: =J67/J$110 -> 0 | L67: =L66+K67 -> 0.99539701 | M67: =_xlfn.IFS(L67<80%,"A",L67<=95%,"B",L67>95%,"C") -> C
B68: MAIERSHA 03914 C9-124 | C68: ='Юнит 19'!AO95 -> 0 | D68: =C68/C$110 -> 0 | E68: =E67+D68 -> 1.0184612 | F68: =IF(AND(E68<=0),"C",IF(E68<=0.8,"A",IF(E68<=0.95,"B","C"))) -> C | G68: =VLOOKUP(B$4:B$104,I$4:M$104,5,0) -> C | I68: sh17 | J68: ='Юнит 19'!U41 -> 0 | K68: =J68/J$110 -> 0 | L68: =L67+K68 -> 0.99539701 | M68: =_xlfn.IFS(L68<80%,"A",L68<=95%,"B",L68>95%,"C") -> C
B69: MARSTON 7171 C1 | C69: ='Юнит 19'!AO96 -> 0 | D69: =C69/C$110 -> 0 | E69: =E68+D69 -> 1.0184612 | F69: =IF(AND(E69<=0),"C",IF(E69<=0.8,"A",IF(E69<=0.95,"B","C"))) -> C | G69: =VLOOKUP(B$4:B$104,I$4:M$104,5,0) -> C | I69: sh18 | J69: ='Юнит 19'!U42 -> 0 | K69: =J69/J$110 -> 0 | L69: =L68+K69 -> 0.99539701 | M69: =_xlfn.IFS(L69<80%,"A",L69<=95%,"B",L69>95%,"C") -> C
B70: ЧСЖ_тест | C70: ='Юнит 19'!AO99 -> 0 | D70: =C70/C$110 -> 0 | E70: =E69+D70 -> 1.0184612 | F70: =IF(AND(E70<=0),"C",IF(E70<=0.8,"A",IF(E70<=0.95,"B","C"))) -> C | G70: =VLOOKUP(B$4:B$104,I$4:M$104,5,0) -> C | I70: ww 1022 черн-серебро | J70: ='Юнит 19'!U46 -> 0 | K70: =J70/J$110 -> 0 | L70: =L69+K70 -> 0.99539701 | M70: =_xlfn.IFS(L70<80%,"A",L70<=95%,"B",L70>95%,"C") -> C
B71: кс_черные_тест | C71: ='Юнит 19'!AO101 -> 0 | D71: =C71/C$110 -> 0 | E71: =E70+D71 -> 1.0184612 | F71: =IF(AND(E71<=0),"C",IF(E71<=0.8,"A",IF(E71<=0.95,"B","C"))) -> C | G71: =VLOOKUP(B$4:B$104,I$4:M$104,5,0) -> C | I71: ww 8010 черные | J71: ='Юнит 19'!U51 -> 0 | K71: =J71/J$110 -> 0 | L71: =L70+K71 -> 0.99539701 | M71: =_xlfn.IFS(L71<80%,"A",L71<=95%,"B",L71>95%,"C") -> C
B72: 1022_коричневые_тест | C72: ='Юнит 19'!AO103 -> 0 | D72: =C72/C$110 -> 0 | E72: =E71+D72 -> 1.0184612 | F72: =IF(AND(E72<=0),"C",IF(E72<=0.8,"A",IF(E72<=0.95,"B","C"))) -> C | G72: =VLOOKUP(B$4:B$104,I$4:M$104,5,0) -> #N/A | I72: MANNA2102 | J72: ='Юнит 19'!U55 -> 0 | K72: =J72/J$110 -> 0 | L72: =L71+K72 -> 0.99539701 | M72: =_xlfn.IFS(L72<80%,"A",L72<=95%,"B",L72>95%,"C") -> C
B73: А1248 С3 | C73: ='Юнит 19'!AO105 -> 0 | D73: =C73/C$110 -> 0 | E73: =E72+D73 -> 1.0184612 | F73: =IF(AND(E73<=0),"C",IF(E73<=0.8,"A",IF(E73<=0.95,"B","C"))) -> C | G73: =VLOOKUP(B$4:B$104,I$4:M$104,5,0) -> #N/A | I73: MANNA2103 | J73: ='Юнит 19'!U56 -> 0 | K73: =J73/J$110 -> 0 | L73: =L72+K73 -> 0.99539701 | M73: =_xlfn.IFS(L73<80%,"A",L73<=95%,"B",L73>95%,"C") -> C
B74: 2422 С1 | C74: ='Юнит 19'!AO106 -> 0 | D74: =C74/C$110 -> 0 | E74: =E73+D74 -> 1.0184612 | F74: =IF(AND(E74<=0),"C",IF(E74<=0.8,"A",IF(E74<=0.95,"B","C"))) -> C | G74: =VLOOKUP(B$4:B$104,I$4:M$104,5,0) -> #N/A | I74: MANNA2104 | J74: ='Юнит 19'!U57 -> 0 | K74: =J74/J$110 -> 0 | L74: =L73+K74 -> 0.99539701 | M74: =_xlfn.IFS(L74<80%,"A",L74<=95%,"B",L74>95%,"C") -> C
B75: 88118 C8-22 (2303 C3) | C75: ='Юнит 19'!AO107 -> 0 | D75: =C75/C$110 -> 0 | E75: =E74+D75 -> 1.0184612 | F75: =IF(AND(E75<=0),"C",IF(E75<=0.8,"A",IF(E75<=0.95,"B","C"))) -> C | G75: =VLOOKUP(B$4:B$104,I$4:M$104,5,0) -> #N/A | I75: MANNA2105 | J75: ='Юнит 19'!U58 -> 0 | K75: =J75/J$110 -> 0 | L75: =L74+K75 -> 0.99539701 | M75: =_xlfn.IFS(L75<80%,"A",L75<=95%,"B",L75>95%,"C") -> C
B76: 88118 C9-124 (2303 C1) | C76: ='Юнит 19'!AO108 -> 0 | D76: =C76/C$110 -> 0 | E76: =E49+D76 -> 1.0184612 | F76: =IF(AND(E76<=0),"C",IF(E76<=0.8,"A",IF(E76<=0.95,"B","C"))) -> C | G76: =VLOOKUP(B$4:B$104,I$4:M$104,5,0) -> #N/A | I76: MANNA2106 | J76: ='Юнит 19'!U59 -> 0 | K76: =J76/J$110 -> 0 | L76: =L49+K76 -> 0.99252014 | M76: =_xlfn.IFS(L76<80%,"A",L76<=95%,"B",L76>95%,"C") -> C
B77: ww 8010 черные | C77: ='Юнит 19'!AO51 -> -1.057937 | D77: =C77/C$110 -> -1.6887841e-06 | E77: =E76+D77 -> 1.0184596 | F77: =IF(AND(E77<=0),"C",IF(E77<=0.8,"A",IF(E77<=0.95,"B","C"))) -> C | G77: =VLOOKUP(B$4:B$104,I$4:M$104,5,0) -> C | I77: MANNA2107 | J77: ='Юнит 19'!U60 -> 0 | K77: =J77/J$110 -> 0 | L77: =L76+K77 -> 0.99252014 | M77: =_xlfn.IFS(L77<80%,"A",L77<=95%,"B",L77>95%,"C") -> C
B78: MANNA2120 | C78: ='Юнит 19'!AO73 -> -1.057937 | D78: =C78/C$110 -> -1.6887841e-06 | E78: =E77+D78 -> 1.0184579 | F78: =IF(AND(E78<=0),"C",IF(E78<=0.8,"A",IF(E78<=0.95,"B","C"))) -> C | G78: =VLOOKUP(B$4:B$104,I$4:M$104,5,0) -> C | I78: MANNA2108 | J78: ='Юнит 19'!U61 -> 0 | K78: =J78/J$110 -> 0 | L78: =L77+K78 -> 0.99252014 | M78: =_xlfn.IFS(L78<80%,"A",L78<=95%,"B",L78>95%,"C") -> C
B79: MANNA2113 | C79: ='Юнит 19'!AO66 -> -2.115874 | D79: =C79/C$110 -> -3.3775682e-06 | E79: =E78+D79 -> 1.0184545 | F79: =IF(AND(E79<=0),"C",IF(E79<=0.8,"A",IF(E79<=0.95,"B","C"))) -> C | G79: =VLOOKUP(B$4:B$104,I$4:M$104,5,0) -> C | I79: MANNA2109 | J79: ='Юнит 19'!U62 -> 0 | K79: =J79/J$110 -> 0 | L79: =L78+K79 -> 0.99252014 | M79: =_xlfn.IFS(L79<80%,"A",L79<=95%,"B",L79>95%,"C") -> C
B80: YIMEI 2391 C1 | C80: ='Юнит 19'!AO98 -> -5.2896849 | D80: =C80/C$110 -> -8.4439204e-06 | E80: =E79+D80 -> 1.018446 | F80: =IF(AND(E80<=0),"C",IF(E80<=0.8,"A",IF(E80<=0.95,"B","C"))) -> C | G80: =VLOOKUP(B$4:B$104,I$4:M$104,5,0) -> C | I80: MANNA2110 | J80: ='Юнит 19'!U63 -> 0 | K80: =J80/J$110 -> 0 | L80: =L79+K80 -> 0.99252014 | M80: =_xlfn.IFS(L80<80%,"A",L80<=95%,"B",L80>95%,"C") -> C
B81: Chenlong черные | C81: ='Юнит 19'!AO76 -> -11.836796 | D81: =C81/C$110 -> -1.889507e-05 | E81: =E80+D81 -> 1.0184272 | F81: =IF(AND(E81<=0),"C",IF(E81<=0.8,"A",IF(E81<=0.95,"B","C"))) -> C | G81: =VLOOKUP(B$4:B$104,I$4:M$104,5,0) -> C | I81: MANNA2111 | J81: ='Юнит 19'!U64 -> 0 | K81: =J81/J$110 -> 0 | L81: =L80+K81 -> 0.99252014 | M81: =_xlfn.IFS(L81<80%,"A",L81<=95%,"B",L81>95%,"C") -> C
B82: Hengda Optical черные | C82: ='Юнит 19'!AO81 -> -13.753181 | D82: =C82/C$110 -> -2.1954193e-05 | E82: =E81+D82 -> 1.0184052 | F82: =IF(AND(E82<=0),"C",IF(E82<=0.8,"A",IF(E82<=0.95,"B","C"))) -> C | G82: =VLOOKUP(B$4:B$104,I$4:M$104,5,0) -> C | I82: MANNA2113 | J82: ='Юнит 19'!U66 -> 0 | K82: =J82/J$110 -> 0 | L82: =L81+K82 -> 0.99252014 | M82: =_xlfn.IFS(L82<80%,"A",L82<=95%,"B",L82>95%,"C") -> C
B83: Chenlong белые | C83: ='Юнит 19'!AO78 -> -19.941824 | D83: =C83/C$110 -> -3.183312e-05 | E83: =E82+D83 -> 1.0183734 | F83: =IF(AND(E83<=0),"C",IF(E83<=0.8,"A",IF(E83<=0.95,"B","C"))) -> C | G83: =VLOOKUP(B$4:B$104,I$4:M$104,5,0) -> C | I83: MANNA2114 | J83: ='Юнит 19'!U67 -> 0 | K83: =J83/J$110 -> 0 | L83: =L82+K83 -> 0.99252014 | M83: =_xlfn.IFS(L83<80%,"A",L83<=95%,"B",L83>95%,"C") -> C
B84: sh17 | C84: ='Юнит 19'!AO41 -> -42.317479 | D84: =C84/C$110 -> -6.7551363e-05 | E84: =E83+D84 -> 1.0183058 | F84: =IF(AND(E84<=0),"C",IF(E84<=0.8,"A",IF(E84<=0.95,"B","C"))) -> C | G84: =VLOOKUP(B$4:B$104,I$4:M$104,5,0) -> C | I84: MANNA2115 | J84: ='Юнит 19'!U68 -> 0 | K84: =J84/J$110 -> 0 | L84: =L83+K84 -> 0.99252014 | M84: =_xlfn.IFS(L84<80%,"A",L84<=95%,"B",L84>95%,"C") -> C
B85: Qianai черные | C85: ='Юнит 19'!AO83 -> -44.433353 | D85: =C85/C$110 -> -7.0928931e-05 | E85: =E84+D85 -> 1.0182349 | F85: =IF(AND(E85<=0),"C",IF(E85<=0.8,"A",IF(E85<=0.95,"B","C"))) -> C | G85: =VLOOKUP(B$4:B$104,I$4:M$104,5,0) -> C | I85: MANNA2116 | J85: ='Юнит 19'!U69 -> 0 | K85: =J85/J$110 -> 0 | L85: =L84+K85 -> 0.99252014 | M85: =_xlfn.IFS(L85<80%,"A",L85<=95%,"B",L85>95%,"C") -> C
B86: sh14 | C86: ='Юнит 19'!AO38 -> -45.49129 | D86: =C86/C$110 -> -7.2617716e-05 | E86: =E85+D86 -> 1.0181623 | F86: =IF(AND(E86<=0),"C",IF(E86<=0.8,"A",IF(E86<=0.95,"B","C"))) -> C | G86: =VLOOKUP(B$4:B$104,I$4:M$104,5,0) -> C | I86: MANNA2117 | J86: ='Юнит 19'!U70 -> 0 | K86: =J86/J$110 -> 0 | L86: =L85+K86 -> 0.99252014 | M86: =_xlfn.IFS(L86<80%,"A",L86<=95%,"B",L86>95%,"C") -> C
B87: Taizhou Rayen sport розовый | C87: ='Юнит 19'!AO90 -> -50.780975 | D87: =C87/C$110 -> -8.1061636e-05 | E87: =E86+D87 -> 1.0180812 | F87: =IF(AND(E87<=0),"C",IF(E87<=0.8,"A",IF(E87<=0.95,"B","C"))) -> C | G87: =VLOOKUP(B$4:B$104,I$4:M$104,5,0) -> C | I87: MANNA2119 | J87: ='Юнит 19'!U72 -> 0 | K87: =J87/J$110 -> 0 | L87: =L86+K87 -> 0.99252014 | M87: =_xlfn.IFS(L87<80%,"A",L87<=95%,"B",L87>95%,"C") -> C
B88: Linhai Baiyi коричневая линза | C88: ='Юнит 19'!AO86 -> -65.1113 | D88: =C88/C$110 -> -0.00010393712 | E88: =E87+D88 -> 1.0179773 | F88: =IF(AND(E88<=0),"C",IF(E88<=0.8,"A",IF(E88<=0.95,"B","C"))) -> C | G88: =VLOOKUP(B$4:B$104,I$4:M$104,5,0) -> C | I88: MANNA2120 | J88: ='Юнит 19'!U73 -> 0 | K88: =J88/J$110 -> 0 | L88: =L87+K88 -> 0.99252014 | M88: =_xlfn.IFS(L88<80%,"A",L88<=95%,"B",L88>95%,"C") -> C
B89: POMILED 08247 C4-08 | C89: ='Юнит 19'!AO97 -> -71.56 | D89: =C89/C$110 -> -0.00011423118 | E89: =E88+D89 -> 1.017863 | F89: =IF(AND(E89<=0),"C",IF(E89<=0.8,"A",IF(E89<=0.95,"B","C"))) -> C | G89: =VLOOKUP(B$4:B$104,I$4:M$104,5,0) -> C | I89: MANNA2121 | J89: ='Юнит 19'!U74 -> 0 | K89: =J89/J$110 -> 0 | L89: =L88+K89 -> 0.99252014 | M89: =_xlfn.IFS(L89<80%,"A",L89<=95%,"B",L89>95%,"C") -> C
B90: sh18 | C90: ='Юнит 19'!AO42 -> -87.026361 | D90: =C90/C$110 -> -0.00013892012 | E90: =E89+D90 -> 1.0177241 | F90: =IF(AND(E90<=0),"C",IF(E90<=0.8,"A",IF(E90<=0.95,"B","C"))) -> C | G90: =VLOOKUP(B$4:B$104,I$4:M$104,5,0) -> C | I90: Hengda Optical черные | J90: ='Юнит 19'!U81 -> 0 | K90: =J90/J$110 -> 0 | L90: =L89+K90 -> 0.99252014 | M90: =_xlfn.IFS(L90<80%,"A",L90<=95%,"B",L90>95%,"C") -> C
B91: sh13 | C91: ='Юнит 19'!AO37 -> -87.897937 | D91: =C91/C$110 -> -0.00014031142 | E91: =E90+D91 -> 1.0175838 | F91: =IF(AND(E91<=0),"C",IF(E91<=0.8,"A",IF(E91<=0.95,"B","C"))) -> C | G91: =VLOOKUP(B$4:B$104,I$4:M$104,5,0) -> C | I91: Hengda Optical леопард | J91: ='Юнит 19'!U82 -> 0 | K91: =J91/J$110 -> 0 | L91: =L90+K91 -> 0.99252014 | M91: =_xlfn.IFS(L91<80%,"A",L91<=95%,"B",L91>95%,"C") -> C
B92: MANNA2116 | C92: ='Юнит 19'!AO69 -> -87.897937 | D92: =C92/C$110 -> -0.00014031142 | E92: =E91+D92 -> 1.0174435 | F92: =IF(AND(E92<=0),"C",IF(E92<=0.8,"A",IF(E92<=0.95,"B","C"))) -> C | G92: =VLOOKUP(B$4:B$104,I$4:M$104,5,0) -> C | I92: Qianai черные | J92: ='Юнит 19'!U83 -> 0 | K92: =J92/J$110 -> 0 | L92: =L91+K92 -> 0.99252014 | M92: =_xlfn.IFS(L92<80%,"A",L92<=95%,"B",L92>95%,"C") -> C
B93: Keming Aishi коричневые | C93: ='Юнит 19'!AO85 -> -94.124583 | D93: =C93/C$110 -> -0.00015025101 | E93: =E92+D93 -> 1.0172932 | F93: =IF(AND(E93<=0),"C",IF(E93<=0.8,"A",IF(E93<=0.95,"B","C"))) -> C | G93: =VLOOKUP(B$4:B$104,I$4:M$104,5,0) -> C | I93: Linhai Baiyi розовая линза | J93: ='Юнит 19'!U88 -> 0 | K93: =J93/J$110 -> 0 | L93: =L92+K93 -> 0.99252014 | M93: =_xlfn.IFS(L93<80%,"A",L93<=95%,"B",L93>95%,"C") -> C
B94: кс_черные_женские | C94: ='Юнит 19'!AO102 -> -95.287868 | D94: =C94/C$110 -> -0.00015210796 | E94: =E93+D94 -> 1.0171411 | F94: =IF(AND(E94<=0),"C",IF(E94<=0.8,"A",IF(E94<=0.95,"B","C"))) -> C | G94: =VLOOKUP(B$4:B$104,I$4:M$104,5,0) -> C | I94: Taizhou Rayen sport розовый | J94: ='Юнит 19'!U90 -> 0 | K94: =J94/J$110 -> 0 | L94: =L93+K94 -> 0.99252014 | M94: =_xlfn.IFS(L94<80%,"A",L94<=95%,"B",L94>95%,"C") -> C
B95: MANNA2107 | C95: ='Юнит 19'!AO60 -> -97.320803 | D95: =C95/C$110 -> -0.00015535313 | E95: =E94+D95 -> 1.0169858 | F95: =IF(AND(E95<=0),"C",IF(E95<=0.8,"A",IF(E95<=0.95,"B","C"))) -> C | G95: =VLOOKUP(B$4:B$104,I$4:M$104,5,0) -> C | I95: Иу Диту серый | J95: ='Юнит 19'!U91 -> 0 | K95: =J95/J$110 -> 0 | L95: =L94+K95 -> 0.99252014 | M95: =_xlfn.IFS(L95<80%,"A",L95<=95%,"B",L95>95%,"C") -> C
B96: sh2 | C96: ='Юнит 19'!AO27 -> -150.23794 | D96: =C96/C$110 -> -0.00023982472 | E96: =E95+D96 -> 1.016746 | F96: =IF(AND(E96<=0),"C",IF(E96<=0.8,"A",IF(E96<=0.95,"B","C"))) -> C | G96: =VLOOKUP(B$4:B$104,I$4:M$104,5,0) -> C | I96: Ли Сян ретро серебро | J96: ='Юнит 19'!U93 -> 0 | K96: =J96/J$110 -> 0 | L96: =L95+K96 -> 0.99252014 | M96: =_xlfn.IFS(L96<80%,"A",L96<=95%,"B",L96>95%,"C") -> C
B97: Linhai Baiyi розовая линза | C97: ='Юнит 19'!AO88 -> -154.02 | D97: =C97/C$110 -> -0.00024586202 | E97: =E96+D97 -> 1.0165001 | F97: =IF(AND(E97<=0),"C",IF(E97<=0.8,"A",IF(E97<=0.95,"B","C"))) -> C | G97: =VLOOKUP(B$4:B$104,I$4:M$104,5,0) -> C | I97: MAIERSHA 03898 C9-08 | J97: ='Юнит 19'!U94 -> 0 | K97: =J97/J$110 -> 0 | L97: =L96+K97 -> 0.99252014 | M97: =_xlfn.IFS(L97<80%,"A",L97<=95%,"B",L97>95%,"C") -> C
B98: MANNA2108 | C98: ='Юнит 19'!AO61 -> -165.03817 | D98: =C98/C$110 -> -0.00026345032 | E98: =E97+D98 -> 1.0162366 | F98: =IF(AND(E98<=0),"C",IF(E98<=0.8,"A",IF(E98<=0.95,"B","C"))) -> C | G98: =VLOOKUP(B$4:B$104,I$4:M$104,5,0) -> C | I98: MAIERSHA 03914 C9-124 | J98: ='Юнит 19'!U95 -> 0 | K98: =J98/J$110 -> 0 | L98: =L97+K98 -> 0.99252014 | M98: =_xlfn.IFS(L98<80%,"A",L98<=95%,"B",L98>95%,"C") -> C
B99: Ли Сян ретро серебро | C99: ='Юнит 19'!AO93 -> -233.76954 | D99: =C99/C$110 -> -0.00037316616 | E99: =E93+D99 -> 1.0169201 | F99: =IF(AND(E99<=0),"C",IF(E99<=0.8,"A",IF(E99<=0.95,"B","C"))) -> C | G99: =VLOOKUP(B$4:B$104,I$4:M$104,5,0) -> C | I99: MARSTON 7171 C1 | J99: ='Юнит 19'!U96 -> 0 | K99: =J99/J$110 -> 0 | L99: =L93+K99 -> 0.99252014 | M99: =_xlfn.IFS(L99<80%,"A",L99<=95%,"B",L99>95%,"C") -> C
B100: ЧСЖ_женские | C100: ='Юнит 19'!AO100 -> -280.79605 | D100: =C100/C$110 -> -0.00044823454 | E100: =E94+D100 -> 1.0166929 | F100: =IF(AND(E100<=0),"C",IF(E100<=0.8,"A",IF(E100<=0.95,"B","C"))) -> C | G100: =VLOOKUP(B$4:B$104,I$4:M$104,5,0) -> C | I100: POMILED 08247 C4-08 | J100: ='Юнит 19'!U97 -> 0 | K100: =J100/J$110 -> 0 | L100: =L94+K100 -> 0.99252014 | M100: =_xlfn.IFS(L100<80%,"A",L100<=95%,"B",L100>95%,"C") -> C
B101: Иу Диту серый | C101: ='Юнит 19'!AO91 -> -324.05461 | D101: =C101/C$110 -> -0.00051728816 | E101: =E95+D101 -> 1.0164685 | F101: =IF(AND(E101<=0),"C",IF(E101<=0.8,"A",IF(E101<=0.95,"B","C"))) -> C | G101: =VLOOKUP(B$4:B$104,I$4:M$104,5,0) -> C | I101: YIMEI 2391 C1 | J101: ='Юнит 19'!U98 -> 0 | K101: =J101/J$110 -> 0 | L101: =L95+K101 -> 0.99252014 | M101: =_xlfn.IFS(L101<80%,"A",L101<=95%,"B",L101>95%,"C") -> C
...

Sheet АВС АПРЕЛЬ
B2: ОЧКИ
C3: Прибыль | D3: % прибыль | E3: Доля | F3: ABC прибыль | G3: ABC кол-во | J3: Кол-во | K3: % кол-во | L3: Доля | M3: ABC кол-во
B4: QS черные PZ | C4: =АПРЕЛЬ!AO4 -> 881964.35 | D4: =C4/C$106 -> 0.20324946 | E4: =D4 -> 0.20324946 | F4: =IF(AND(E4<=0),"C",IF(E4<=0.8,"A",IF(E4<=0.95,"B","C"))) -> A | G4: =VLOOKUP(B$4:B$104,I$4:M$104,5,0) -> A | I4: QS черные PZ | J4: =АПРЕЛЬ!U4 -> 1719 | K4: =J4/J$106 -> 0.16757653 | L4: =K4 -> 0.16757653 | M4: =_xlfn.IFS(L4<80%,"A",L4<=95%,"B",L4>95%,"C") -> A | P4: A | Q4: 0.8
B5: flip черные | C5: =АПРЕЛЬ!AO13 -> 422668.33 | D5: =C5/C$106 -> 0.097404287 | E5: =E4+D5 -> 0.30065375 | F5: =IF(AND(E5<=0),"C",IF(E5<=0.8,"A",IF(E5<=0.95,"B","C"))) -> A | G5: =VLOOKUP(B$4:B$104,I$4:M$104,5,0) -> A | I5: flip черные | J5: =АПРЕЛЬ!U13 -> 989 | K5: =J5/J$106 -> 0.096412556 | L5: =L4+K5 -> 0.26398908 | M5: =_xlfn.IFS(L5<80%,"A",L5<=95%,"B",L5>95%,"C") -> A | P5: B | Q5: 0.15
B6: flip коричневые | C6: =АПРЕЛЬ!AO16 -> 402050.95 | D6: =C6/C$106 -> 0.092652994 | E6: =E5+D6 -> 0.39330674 | F6: =IF(AND(E6<=0),"C",IF(E6<=0.8,"A",IF(E6<=0.95,"B","C"))) -> A | G6: =VLOOKUP(B$4:B$104,I$4:M$104,5,0) -> A | I6: th черн | J6: =АПРЕЛЬ!U9 -> 899 | K6: =J6/J$106 -> 0.087638916 | L6: =L5+K6 -> 0.351628 | M6: =_xlfn.IFS(L6<80%,"A",L6<=95%,"B",L6>95%,"C") -> A | P6: C | Q6: 0.05
B7: th черн | C7: =АПРЕЛЬ!AO9 -> 368738.71 | D7: =C7/C$106 -> 0.08497616 | E7: =E6+D7 -> 0.4782829 | F7: =IF(AND(E7<=0),"C",IF(E7<=0.8,"A",IF(E7<=0.95,"B","C"))) -> A | G7: =VLOOKUP(B$4:B$104,I$4:M$104,5,0) -> A | I7: flip коричневые | J7: =АПРЕЛЬ!U16 -> 777 | K7: =J7/J$106 -> 0.075745759 | L7: =L6+K7 -> 0.42737376 | M7: =_xlfn.IFS(L7<80%,"A",L7<=95%,"B",L7>95%,"C") -> A
B8: QS коричневые PZ | C8: =АПРЕЛЬ!AO7 -> 267745.78 | D8: =C8/C$106 -> 0.061702249 | E8: =E7+D8 -> 0.53998515 | F8: =IF(AND(E8<=0),"C",IF(E8<=0.8,"A",IF(E8<=0.95,"B","C"))) -> A | G8: =VLOOKUP(B$4:B$104,I$4:M$104,5,0) -> A | I8: th син | J8: =АПРЕЛЬ!U10 -> 686 | K8: =J8/J$106 -> 0.066874634 | L8: =L7+K8 -> 0.49424839 | M8: =_xlfn.IFS(L8<80%,"A",L8<=95%,"B",L8>95%,"C") -> A
B9: QS синие PZ | C9: =АПРЕЛЬ!AO5 -> 266086.63 | D9: =C9/C$106 -> 0.061319897 | E9: =E8+D9 -> 0.60130505 | F9: =IF(AND(E9<=0),"C",IF(E9<=0.8,"A",IF(E9<=0.95,"B","C"))) -> A | G9: =VLOOKUP(B$4:B$104,I$4:M$104,5,0) -> A | I9: QS коричневые PZ | J9: =АПРЕЛЬ!U7 -> 607 | K9: =J9/J$106 -> 0.059173328 | L9: =L8+K9 -> 0.55342172 | M9: =_xlfn.IFS(L9<80%,"A",L9<=95%,"B",L9>95%,"C") -> A
B10: черные с железкой классика | C10: =АПРЕЛЬ!AO3 -> 258843.84 | D10: =C10/C$106 -> 0.059650791 | E10: =E9+D10 -> 0.66095584 | F10: =IF(AND(E10<=0),"C",IF(E10<=0.8,"A",IF(E10<=0.95,"B","C"))) -> A | G10: =VLOOKUP(B$4:B$104,I$4:M$104,5,0) -> A | I10: черные с железкой классика | J10: =АПРЕЛЬ!U3 -> 597 | K10: =J10/J$106 -> 0.058198479 | L10: =L9+K10 -> 0.6116202 | M10: =_xlfn.IFS(L10<80%,"A",L10<=95%,"B",L10>95%,"C") -> A
B11: th син | C11: =АПРЕЛЬ!AO10 -> 223194.85 | D11: =C11/C$106 -> 0.051435449 | E11: =E10+D11 -> 0.71239129 | F11: =IF(AND(E11<=0),"C",IF(E11<=0.8,"A",IF(E11<=0.95,"B","C"))) -> A | G11: =VLOOKUP(B$4:B$104,I$4:M$104,5,0) -> A | I11: QS синие PZ | J11: =АПРЕЛЬ!U5 -> 586 | K11: =J11/J$106 -> 0.057126145 | L11: =L10+K11 -> 0.66874634 | M11: =_xlfn.IFS(L11<80%,"A",L11<=95%,"B",L11>95%,"C") -> A
B12: th коричн | C12: =АПРЕЛЬ!AO12 -> 175321.55 | D12: =C12/C$106 -> 0.040403005 | E12: =E11+D12 -> 0.75279429 | F12: =IF(AND(E12<=0),"C",IF(E12<=0.8,"A",IF(E12<=0.95,"B","C"))) -> A | G12: =VLOOKUP(B$4:B$104,I$4:M$104,5,0) -> A | I12: th коричн | J12: =АПРЕЛЬ!U12 -> 476 | K12: =J12/J$106 -> 0.046402808 | L12: =L11+K12 -> 0.71514915 | M12: =_xlfn.IFS(L12<80%,"A",L12<=95%,"B",L12>95%,"C") -> A
B13: th желт | C13: =АПРЕЛЬ!AO11 -> 154503.17 | D13: =C13/C$106 -> 0.035605391 | E13: =E12+D13 -> 0.78839968 | F13: =IF(AND(E13<=0),"C",IF(E13<=0.8,"A",IF(E13<=0.95,"B","C"))) -> A | G13: =VLOOKUP(B$4:B$104,I$4:M$104,5,0) -> A | I13: th желт | J13: =АПРЕЛЬ!U11 -> 382 | K13: =J13/J$106 -> 0.037239228 | L13: =L12+K13 -> 0.75238838 | M13: =_xlfn.IFS(L13<80%,"A",L13<=95%,"B",L13>95%,"C") -> A
B14: QS желтые PZ | C14: =АПРЕЛЬ!AO6 -> 145425.82 | D14: =C14/C$106 -> 0.033513509 | E14: =E13+D14 -> 0.82191319 | F14: =IF(AND(E14<=0),"C",IF(E14<=0.8,"A",IF(E14<=0.95,"B","C"))) -> B | G14: =VLOOKUP(B$4:B$104,I$4:M$104,5,0) -> A | I14: QS желтые PZ | J14: =АПРЕЛЬ!U6 -> 313 | K14: =J14/J$106 -> 0.030512771 | L14: =L13+K14 -> 0.78290115 | M14: =_xlfn.IFS(L14<80%,"A",L14<=95%,"B",L14>95%,"C") -> A
B15: flip желтые | C15: =АПРЕЛЬ!AO15 -> 109930.18 | D15: =C15/C$106 -> 0.025333507 | E15: =E14+D15 -> 0.8472467 | F15: =IF(AND(E15<=0),"C",IF(E15<=0.8,"A",IF(E15<=0.95,"B","C"))) -> B | G15: =VLOOKUP(B$4:B$104,I$4:M$104,5,0) -> B | I15: flip желтые | J15: =АПРЕЛЬ!U15 -> 244 | K15: =J15/J$106 -> 0.023786313 | L15: =L14+K15 -> 0.80668746 | M15: =_xlfn.IFS(L15<80%,"A",L15<=95%,"B",L15>95%,"C") -> B
B16: ww 2018 желтые | C16: =АПРЕЛЬ!AO50 -> 88151.131 | D16: =C16/C$106 -> 0.020314506 | E16: =E15+D16 -> 0.8675612 | F16: =IF(AND(E16<=0),"C",IF(E16<=0.8,"A",IF(E16<=0.95,"B","C"))) -> B | G16: =VLOOKUP(B$4:B$104,I$4:M$104,5,0) -> B | I16: sh3 | J16: =АПРЕЛЬ!U28 -> 213 | K16: =J16/J$106 -> 0.020764282 | L16: =L15+K16 -> 0.82745174 | M16: =_xlfn.IFS(L16<80%,"A",L16<=95%,"B",L16>95%,"C") -> B
B17: ww 1022 коричневые | C17: =АПРЕЛЬ!AO48 -> 82151.036 | D17: =C17/C$106 -> 0.018931778 | E17: =E16+D17 -> 0.88649298 | F17: =IF(AND(E17<=0),"C",IF(E17<=0.8,"A",IF(E17<=0.95,"B","C"))) -> B | G17: =VLOOKUP(B$4:B$104,I$4:M$104,5,0) -> B | I17: ww 1022 коричневые | J17: =АПРЕЛЬ!U48 -> 207 | K17: =J17/J$106 -> 0.020179372 | L17: =L16+K17 -> 0.84763112 | M17: =_xlfn.IFS(L17<80%,"A",L17<=95%,"B",L17>95%,"C") -> B
B18: flip синие | C18: =АПРЕЛЬ!AO14 -> 74371.195 | D18: =C18/C$106 -> 0.017138907 | E18: =E17+D18 -> 0.90363189 | F18: =IF(AND(E18<=0),"C",IF(E18<=0.8,"A",IF(E18<=0.95,"B","C"))) -> B | G18: =VLOOKUP(B$4:B$104,I$4:M$104,5,0) -> B | I18: flip синие | J18: =АПРЕЛЬ!U14 -> 183 | K18: =J18/J$106 -> 0.017839735 | L18: =L17+K18 -> 0.86547085 | M18: =_xlfn.IFS(L18<80%,"A",L18<=95%,"B",L18>95%,"C") -> B
B19: sh3 | C19: =АПРЕЛЬ!AO28 -> 64977.063 | D19: =C19/C$106 -> 0.014974021 | E19: =E18+D19 -> 0.91860591 | F19: =IF(AND(E19<=0),"C",IF(E19<=0.8,"A",IF(E19<=0.95,"B","C"))) -> B | G19: =VLOOKUP(B$4:B$104,I$4:M$104,5,0) -> B | I19: ww 2018 желтые | J19: =АПРЕЛЬ!U50 -> 177 | K19: =J19/J$106 -> 0.017254826 | L19: =L18+K19 -> 0.88272568 | M19: =_xlfn.IFS(L19<80%,"A",L19<=95%,"B",L19>95%,"C") -> B
B20: ww 2018 черные | C20: =АПРЕЛЬ!AO49 -> 62024.495 | D20: =C20/C$106 -> 0.014293599 | E20: =E19+D20 -> 0.93289951 | F20: =IF(AND(E20<=0),"C",IF(E20<=0.8,"A",IF(E20<=0.95,"B","C"))) -> B | G20: =VLOOKUP(B$4:B$104,I$4:M$104,5,0) -> B | I20: ww 2018 черные | J20: =АПРЕЛЬ!U49 -> 160 | K20: =J20/J$106 -> 0.015597582 | L20: =L19+K20 -> 0.89832326 | M20: =_xlfn.IFS(L20<80%,"A",L20<=95%,"B",L20>95%,"C") -> B
B21: MR8854 C2 Жен | C21: =АПРЕЛЬ!AO8 -> 60560.952 | D21: =C21/C$106 -> 0.013956325 | E21: =E20+D21 -> 0.94685583 | F21: =IF(AND(E21<=0),"C",IF(E21<=0.8,"A",IF(E21<=0.95,"B","C"))) -> B | G21: =VLOOKUP(B$4:B$104,I$4:M$104,5,0) -> B | I21: MR8854 C2 Жен | J21: =АПРЕЛЬ!U8 -> 135 | K21: =J21/J$106 -> 0.01316046 | L21: =L20+K21 -> 0.91148372 | M21: =_xlfn.IFS(L21<80%,"A",L21<=95%,"B",L21>95%,"C") -> B
B22: wwl8032 коричневые золото | C22: =АПРЕЛЬ!AO17 -> 58207.399 | D22: =C22/C$106 -> 0.013413946 | E22: =E21+D22 -> 0.96026978 | F22: =IF(AND(E22<=0),"C",IF(E22<=0.8,"A",IF(E22<=0.95,"B","C"))) -> C | G22: =VLOOKUP(B$4:B$104,I$4:M$104,5,0) -> B | I22: wwl8032 хром металл | J22: =АПРЕЛЬ!U18 -> 134 | K22: =J22/J$106 -> 0.013062975 | L22: =L21+K22 -> 0.9245467 | M22: =_xlfn.IFS(L22<80%,"A",L22<=95%,"B",L22>95%,"C") -> B
B23: wwl8032 хром металл | C23: =АПРЕЛЬ!AO18 -> 50040.417 | D23: =C23/C$106 -> 0.011531858 | E23: =E22+D23 -> 0.97180164 | F23: =IF(AND(E23<=0),"C",IF(E23<=0.8,"A",IF(E23<=0.95,"B","C"))) -> C | G23: =VLOOKUP(B$4:B$104,I$4:M$104,5,0) -> B | I23: wwl8032 коричневые золото | J23: =АПРЕЛЬ!U17 -> 131 | K23: =J23/J$106 -> 0.012770521 | L23: =L22+K23 -> 0.93731722 | M23: =_xlfn.IFS(L23<80%,"A",L23<=95%,"B",L23>95%,"C") -> B
B24: ww 203 черные | C24: =АПРЕЛЬ!AO44 -> 39046.118 | D24: =C24/C$106 -> 0.0089982121 | E24: =E23+D24 -> 0.98079985 | F24: =IF(AND(E24<=0),"C",IF(E24<=0.8,"A",IF(E24<=0.95,"B","C"))) -> C | G24: =VLOOKUP(B$4:B$104,I$4:M$104,5,0) -> B | I24: ww 203 черные | J24: =АПРЕЛЬ!U44 -> 117 | K24: =J24/J$106 -> 0.011405732 | L24: =L23+K24 -> 0.94872295 | M24: =_xlfn.IFS(L24<80%,"A",L24<=95%,"B",L24>95%,"C") -> B
B25: ww 1022 черные | C25: =АПРЕЛЬ!AO45 -> 35787.051 | D25: =C25/C$106 -> 0.0082471572 | E25: =E24+D25 -> 0.98904701 | F25: =IF(AND(E25<=0),"C",IF(E25<=0.8,"A",IF(E25<=0.95,"B","C"))) -> C | G25: =VLOOKUP(B$4:B$104,I$4:M$104,5,0) -> C | I25: ww 1022 черные | J25: =АПРЕЛЬ!U45 -> 94 | K25: =J25/J$106 -> 0.0091635796 | L25: =L24+K25 -> 0.95788653 | M25: =_xlfn.IFS(L25<80%,"A",L25<=95%,"B",L25>95%,"C") -> C
B26: ridges brand 01 | C26: =АПРЕЛЬ!AO104 -> 32598.174 | D26: =C26/C$106 -> 0.0075122778 | E26: =E25+D26 -> 0.99655928 | F26: =IF(AND(E26<=0),"C",IF(E26<=0.8,"A",IF(E26<=0.95,"B","C"))) -> C | G26: =VLOOKUP(B$4:B$104,I$4:M$104,5,0) -> C | I26: sh1 | J26: =АПРЕЛЬ!U26 -> 33 | K26: =J26/J$106 -> 0.0032170014 | L26: =L25+K26 -> 0.96110353 | M26: =_xlfn.IFS(L26<80%,"A",L26<=95%,"B",L26>95%,"C") -> C
B27: ww 1022 желтые | C27: =АПРЕЛЬ!AO47 -> 10766.436 | D27: =C27/C$106 -> 0.0024811345 | E27: =E26+D27 -> 0.99904042 | F27: =IF(AND(E27<=0),"C",IF(E27<=0.8,"A",IF(E27<=0.95,"B","C"))) -> C | G27: =VLOOKUP(B$4:B$104,I$4:M$104,5,0) -> C | I27: кс_черные_женские | J27: =АПРЕЛЬ!U102 -> 33 | K27: =J27/J$106 -> 0.0032170014 | L27: =L26+K27 -> 0.96432053 | M27: =_xlfn.IFS(L27<80%,"A",L27<=95%,"B",L27>95%,"C") -> C
B28: sports красные | C28: =АПРЕЛЬ!AO22 -> 8499.363 | D28: =C28/C$106 -> 0.0019586857 | E28: =E27+D28 -> 1.0009991 | F28: =IF(AND(E28<=0),"C",IF(E28<=0.8,"A",IF(E28<=0.95,"B","C"))) -> C | G28: =VLOOKUP(B$4:B$104,I$4:M$104,5,0) -> C | I28: sports красные | J28: =АПРЕЛЬ!U22 -> 32 | K28: =J28/J$106 -> 0.0031195165 | L28: =L27+K28 -> 0.96744005 | M28: =_xlfn.IFS(L28<80%,"A",L28<=95%,"B",L28>95%,"C") -> C
B29: MR Р1894 черные | C29: =АПРЕЛЬ!AO89 -> 7751.1643 | D29: =C29/C$106 -> 0.0017862626 | E29: =E28+D29 -> 1.0027854 | F29: =IF(AND(E29<=0),"C",IF(E29<=0.8,"A",IF(E29<=0.95,"B","C"))) -> C | G29: =VLOOKUP(B$4:B$104,I$4:M$104,5,0) -> C | I29: ridges brand 01 | J29: =АПРЕЛЬ!U104 -> 30 | K29: =J29/J$106 -> 0.0029245467 | L29: =L28+K29 -> 0.97036459 | M29: =_xlfn.IFS(L29<80%,"A",L29<=95%,"B",L29>95%,"C") -> C
B30: sh1 | C30: =АПРЕЛЬ!AO26 -> 5601.1034 | D30: =C30/C$106 -> 0.0012907792 | E30: =E29+D30 -> 1.0040761 | F30: =IF(AND(E30<=0),"C",IF(E30<=0.8,"A",IF(E30<=0.95,"B","C"))) -> C | G30: =VLOOKUP(B$4:B$104,I$4:M$104,5,0) -> C | I30: sports синие | J30: =АПРЕЛЬ!U20 -> 25 | K30: =J30/J$106 -> 0.0024371222 | L30: =L29+K30 -> 0.97280172 | M30: =_xlfn.IFS(L30<80%,"A",L30<=95%,"B",L30>95%,"C") -> C
B31: sports синие | C31: =АПРЕЛЬ!AO20 -> 5342.268 | D31: =C31/C$106 -> 0.0012311303 | E31: =E30+D31 -> 1.0053073 | F31: =IF(AND(E31<=0),"C",IF(E31<=0.8,"A",IF(E31<=0.95,"B","C"))) -> C | G31: =VLOOKUP(B$4:B$104,I$4:M$104,5,0) -> C | I31: ww 1022 желтые | J31: =АПРЕЛЬ!U47 -> 23 | K31: =J31/J$106 -> 0.0022421525 | L31: =L30+K31 -> 0.97504387 | M31: =_xlfn.IFS(L31<80%,"A",L31<=95%,"B",L31>95%,"C") -> C
B32: ЧСЖ_женские | C32: =АПРЕЛЬ!AO100 -> 3898.5128 | D32: =C32/C$106 -> 0.0008984157 | E32: =E31+D32 -> 1.0062057 | F32: =IF(AND(E32<=0),"C",IF(E32<=0.8,"A",IF(E32<=0.95,"B","C"))) -> C | G32: =VLOOKUP(B$4:B$104,I$4:M$104,5,0) -> C | I32: sports зеленые | J32: =АПРЕЛЬ!U21 -> 22 | K32: =J32/J$106 -> 0.0021446676 | L32: =L31+K32 -> 0.97718854 | M32: =_xlfn.IFS(L32<80%,"A",L32<=95%,"B",L32>95%,"C") -> C
B33: MANNA2101 | C33: =АПРЕЛЬ!AO54 -> 2596.5336 | D33: =C33/C$106 -> 0.00059837345 | E33: =E32+D33 -> 1.0068041 | F33: =IF(AND(E33<=0),"C",IF(E33<=0.8,"A",IF(E33<=0.95,"B","C"))) -> C | G33: =VLOOKUP(B$4:B$104,I$4:M$104,5,0) -> C | I33: Guangdu золото серая линза | J33: =АПРЕЛЬ!U79 -> 15 | K33: =J33/J$106 -> 0.0014622733 | L33: =L32+K33 -> 0.97865081 | M33: =_xlfn.IFS(L33<80%,"A",L33<=95%,"B",L33>95%,"C") -> C
B34: sh09 | C34: =АПРЕЛЬ!AO33 -> 2256.3425 | D34: =C34/C$106 -> 0.0005199761 | E34: =E33+D34 -> 1.007324 | F34: =IF(AND(E34<=0),"C",IF(E34<=0.8,"A",IF(E34<=0.95,"B","C"))) -> C | G34: =VLOOKUP(B$4:B$104,I$4:M$104,5,0) -> C | I34: MR Р1894 черные | J34: =АПРЕЛЬ!U89 -> 15 | K34: =J34/J$106 -> 0.0014622733 | L34: =L33+K34 -> 0.98011308 | M34: =_xlfn.IFS(L34<80%,"A",L34<=95%,"B",L34>95%,"C") -> C
B35: Linhai Baiyi серая линза | C35: =АПРЕЛЬ!AO87 -> 1995.919 | D35: =C35/C$106 -> 0.00045996129 | E35: =E34+D35 -> 1.007784 | F35: =IF(AND(E35<=0),"C",IF(E35<=0.8,"A",IF(E35<=0.95,"B","C"))) -> C | G35: =VLOOKUP(B$4:B$104,I$4:M$104,5,0) -> C | I35: MANNA2122 | J35: =АПРЕЛЬ!U75 -> 14 | K35: =J35/J$106 -> 0.0013647885 | L35: =L34+K35 -> 0.98147787 | M35: =_xlfn.IFS(L35<80%,"A",L35<=95%,"B",L35>95%,"C") -> C
B36: кс_черные_женские | C36: =АПРЕЛЬ!AO102 -> 1714.2004 | D36: =C36/C$106 -> 0.00039503899 | E36: =E35+D36 -> 1.008179 | F36: =IF(AND(E36<=0),"C",IF(E36<=0.8,"A",IF(E36<=0.95,"B","C"))) -> C | G36: =VLOOKUP(B$4:B$104,I$4:M$104,5,0) -> C | I36: sh09 | J36: =АПРЕЛЬ!U33 -> 13 | K36: =J36/J$106 -> 0.0012673036 | L36: =L35+K36 -> 0.98274517 | M36: =_xlfn.IFS(L36<80%,"A",L36<=95%,"B",L36>95%,"C") -> C
B37: MANNA2116 | C37: =АПРЕЛЬ!AO69 -> 1340.3832 | D37: =C37/C$106 -> 0.00030889248 | E37: =E36+D37 -> 1.0084879 | F37: =IF(AND(E37<=0),"C",IF(E37<=0.8,"A",IF(E37<=0.95,"B","C"))) -> C | G37: =VLOOKUP(B$4:B$104,I$4:M$104,5,0) -> C | I37: MANNA2101 | J37: =АПРЕЛЬ!U54 -> 11 | K37: =J37/J$106 -> 0.0010723338 | L37: =L36+K37 -> 0.98381751 | M37: =_xlfn.IFS(L37<80%,"A",L37<=95%,"B",L37>95%,"C") -> C
B38: MANNA2122 | C38: =АПРЕЛЬ!AO75 -> 1324.4373 | D38: =C38/C$106 -> 0.00030521773 | E38: =E37+D38 -> 1.0087932 | F38: =IF(AND(E38<=0),"C",IF(E38<=0.8,"A",IF(E38<=0.95,"B","C"))) -> C | G38: =VLOOKUP(B$4:B$104,I$4:M$104,5,0) -> C | I38: Chenlong коричневые | J38: =АПРЕЛЬ!U77 -> 11 | K38: =J38/J$106 -> 0.0010723338 | L38: =L37+K38 -> 0.98488984 | M38: =_xlfn.IFS(L38<80%,"A",L38<=95%,"B",L38>95%,"C") -> C
B39: sh16 | C39: =АПРЕЛЬ!AO40 -> 1229.2892 | D39: =C39/C$106 -> 0.00028329077 | E39: =E35+D39 -> 1.0080673 | F39: =IF(AND(E39<=0),"C",IF(E39<=0.8,"A",IF(E39<=0.95,"B","C"))) -> C | G39: =VLOOKUP(B$4:B$104,I$4:M$104,5,0) -> C | I39: Linhai Baiyi серая линза | J39: =АПРЕЛЬ!U87 -> 11 | K39: =J39/J$106 -> 0.0010723338 | L39: =L35+K39 -> 0.9825502 | M39: =_xlfn.IFS(L39<80%,"A",L39<=95%,"B",L39>95%,"C") -> C
B40: Ли Сян ретро серебро | C40: =АПРЕЛЬ!AO93 -> 1135.4263 | D40: =C40/C$106 -> 0.00026166 | E40: =E39+D40 -> 1.008329 | F40: =IF(AND(E40<=0),"C",IF(E40<=0.8,"A",IF(E40<=0.95,"B","C"))) -> C | G40: =VLOOKUP(B$4:B$104,I$4:M$104,5,0) -> C | I40: WW 3055 черный | J40: =АПРЕЛЬ!U52 -> 10 | K40: =J40/J$106 -> 0.0009748489 | L40: =L39+K40 -> 0.98352505 | M40: =_xlfn.IFS(L40<80%,"A",L40<=95%,"B",L40>95%,"C") -> C
B41: sh19 | C41: =АПРЕЛЬ!AO43 -> 1052.1745 | D41: =C41/C$106 -> 0.00024247454 | E41: =E40+D41 -> 1.0085714 | F41: =IF(AND(E41<=0),"C",IF(E41<=0.8,"A",IF(E41<=0.95,"B","C"))) -> C | G41: =VLOOKUP(B$4:B$104,I$4:M$104,5,0) -> C | I41: Guangdu серебро серая линза | J41: =АПРЕЛЬ!U80 -> 10 | K41: =J41/J$106 -> 0.0009748489 | L41: =L40+K41 -> 0.9844999 | M41: =_xlfn.IFS(L41<80%,"A",L41<=95%,"B",L41>95%,"C") -> C
B42: MANNA2117 | C42: =АПРЕЛЬ!AO70 -> 880.5291 | D42: =C42/C$106 -> 0.0002029187 | E42: =E41+D42 -> 1.0087743 | F42: =IF(AND(E42<=0),"C",IF(E42<=0.8,"A",IF(E42<=0.95,"B","C"))) -> C | G42: =VLOOKUP(B$4:B$104,I$4:M$104,5,0) -> C | I42: ЧСЖ_женские | J42: =АПРЕЛЬ!U100 -> 9 | K42: =J42/J$106 -> 0.00087736401 | L42: =L41+K42 -> 0.98537727 | M42: =_xlfn.IFS(L42<80%,"A",L42<=95%,"B",L42>95%,"C") -> C
B43: sports зеленые | C43: =АПРЕЛЬ!AO21 -> 814.75289 | D43: =C43/C$106 -> 0.00018776052 | E43: =E42+D43 -> 1.0089621 | F43: =IF(AND(E43<=0),"C",IF(E43<=0.8,"A",IF(E43<=0.95,"B","C"))) -> C | G43: =VLOOKUP(B$4:B$104,I$4:M$104,5,0) -> C | I43: sh2 | J43: =АПРЕЛЬ!U27 -> 8 | K43: =J43/J$106 -> 0.00077987912 | L43: =L42+K43 -> 0.98615715 | M43: =_xlfn.IFS(L43<80%,"A",L43<=95%,"B",L43>95%,"C") -> C
B44: MANNA2120 | C44: =АПРЕЛЬ!AO73 -> 760.77716 | D44: =C44/C$106 -> 0.00017532176 | E44: =E43+D44 -> 1.0091374 | F44: =IF(AND(E44<=0),"C",IF(E44<=0.8,"A",IF(E44<=0.95,"B","C"))) -> C | G44: =VLOOKUP(B$4:B$104,I$4:M$104,5,0) -> C | I44: Linhai Baiyi коричневая линза | J44: =АПРЕЛЬ!U86 -> 8 | K44: =J44/J$106 -> 0.00077987912 | L44: =L43+K44 -> 0.98693702 | M44: =_xlfn.IFS(L44<80%,"A",L44<=95%,"B",L44>95%,"C") -> C
B45: sh18 | C45: =АПРЕЛЬ!AO42 -> 752.13927 | D45: =C45/C$106 -> 0.00017333115 | E45: =E44+D45 -> 1.0093108 | F45: =IF(AND(E45<=0),"C",IF(E45<=0.8,"A",IF(E45<=0.95,"B","C"))) -> C | G45: =VLOOKUP(B$4:B$104,I$4:M$104,5,0) -> C | I45: Qianai коричневые | J45: =АПРЕЛЬ!U84 -> 7 | K45: =J45/J$106 -> 0.00068239423 | L45: =L44+K45 -> 0.98761942 | M45: =_xlfn.IFS(L45<80%,"A",L45<=95%,"B",L45>95%,"C") -> C
B46: Taizhou Rayen sport розовый | C46: =АПРЕЛЬ!AO90 -> 692.8941 | D46: =C46/C$106 -> 0.00015967805 | E46: =E45+D46 -> 1.0094704 | F46: =IF(AND(E46<=0),"C",IF(E46<=0.8,"A",IF(E46<=0.95,"B","C"))) -> C | G46: =VLOOKUP(B$4:B$104,I$4:M$104,5,0) -> C | I46: MANNA2116 | J46: =АПРЕЛЬ!U69 -> 6 | K46: =J46/J$106 -> 0.00058490934 | L46: =L45+K46 -> 0.98820433 | M46: =_xlfn.IFS(L46<80%,"A",L46<=95%,"B",L46>95%,"C") -> C
B47: YIMEI 2391 C1 | C47: =АПРЕЛЬ!AO98 -> 684.00247 | D47: =C47/C$106 -> 0.00015762897 | E47: =E46+D47 -> 1.0096281 | F47: =IF(AND(E47<=0),"C",IF(E47<=0.8,"A",IF(E47<=0.95,"B","C"))) -> C | G47: =VLOOKUP(B$4:B$104,I$4:M$104,5,0) -> C | I47: Chenlong белые | J47: =АПРЕЛЬ!U78 -> 6 | K47: =J47/J$106 -> 0.00058490934 | L47: =L46+K47 -> 0.98878924 | M47: =_xlfn.IFS(L47<80%,"A",L47<=95%,"B",L47>95%,"C") -> C
B48: sportlife синие | C48: =АПРЕЛЬ!AO24 -> 562.65427 | D48: =C48/C$106 -> 0.00012966417 | E48: =E47+D48 -> 1.0097577 | F48: =IF(AND(E48<=0),"C",IF(E48<=0.8,"A",IF(E48<=0.95,"B","C"))) -> C | G48: =VLOOKUP(B$4:B$104,I$4:M$104,5,0) -> C | I48: YIMEI 2391 C1 | J48: =АПРЕЛЬ!U98 -> 6 | K48: =J48/J$106 -> 0.00058490934 | L48: =L47+K48 -> 0.98937415 | M48: =_xlfn.IFS(L48<80%,"A",L48<=95%,"B",L48>95%,"C") -> C
B49: sh17 | C49: =АПРЕЛЬ!AO41 -> 495.69543 | D49: =C49/C$106 -> 0.00011423345 | E49: =E48+D49 -> 1.009872 | F49: =IF(AND(E49<=0),"C",IF(E49<=0.8,"A",IF(E49<=0.95,"B","C"))) -> C | G49: =VLOOKUP(B$4:B$104,I$4:M$104,5,0) -> C | I49: sh18 | J49: =АПРЕЛЬ!U42 -> 5 | K49: =J49/J$106 -> 0.00048742445 | L49: =L48+K49 -> 0.98986157 | M49: =_xlfn.IFS(L49<80%,"A",L49<=95%,"B",L49>95%,"C") -> C
B50: Hengda Optical черные | C50: =АПРЕЛЬ!AO81 -> 379.20416 | D50: =C50/C$106 -> 8.7387932e-05 | E50: =E49+D50 -> 1.0099594 | F50: =IF(AND(E50<=0),"C",IF(E50<=0.8,"A",IF(E50<=0.95,"B","C"))) -> C | G50: =VLOOKUP(B$4:B$104,I$4:M$104,5,0) -> C | I50: sh19 | J50: =АПРЕЛЬ!U43 -> 5 | K50: =J50/J$106 -> 0.00048742445 | L50: =L49+K50 -> 0.990349 | M50: =_xlfn.IFS(L50<80%,"A",L50<=95%,"B",L50>95%,"C") -> C
B51: sh10 | C51: =АПРЕЛЬ!AO34 -> 314.6804 | D51: =C51/C$106 -> 7.2518374e-05 | E51: =E50+D51 -> 1.0100319 | F51: =IF(AND(E51<=0),"C",IF(E51<=0.8,"A",IF(E51<=0.95,"B","C"))) -> C | G51: =VLOOKUP(B$4:B$104,I$4:M$104,5,0) -> C | I51: WW 3055 коричневый | J51: =АПРЕЛЬ!U53 -> 5 | K51: =J51/J$106 -> 0.00048742445 | L51: =L50+K51 -> 0.99083642 | M51: =_xlfn.IFS(L51<80%,"A",L51<=95%,"B",L51>95%,"C") -> C
B52: sh07 | C52: =АПРЕЛЬ!AO31 -> 313.14 | D52: =C52/C$106 -> 7.2163388e-05 | E52: =E51+D52 -> 1.010104 | F52: =IF(AND(E52<=0),"C",IF(E52<=0.8,"A",IF(E52<=0.95,"B","C"))) -> C | G52: =VLOOKUP(B$4:B$104,I$4:M$104,5,0) -> C | I52: Chenlong черные | J52: =АПРЕЛЬ!U76 -> 5 | K52: =J52/J$106 -> 0.00048742445 | L52: =L51+K52 -> 0.99132384 | M52: =_xlfn.IFS(L52<80%,"A",L52<=95%,"B",L52>95%,"C") -> C
B53: MANNA2119 | C53: =АПРЕЛЬ!AO72 -> 303.5717 | D53: =C53/C$106 -> 6.9958365e-05 | E53: =E52+D53 -> 1.010174 | F53: =IF(AND(E53<=0),"C",IF(E53<=0.8,"A",IF(E53<=0.95,"B","C"))) -> C | G53: =VLOOKUP(B$4:B$104,I$4:M$104,5,0) -> C | I53: sh16 | J53: =АПРЕЛЬ!U40 -> 4 | K53: =J53/J$106 -> 0.00038993956 | L53: =L52+K53 -> 0.99171378 | M53: =_xlfn.IFS(L53<80%,"A",L53<=95%,"B",L53>95%,"C") -> C
B54: MANNA2107 | C54: =АПРЕЛЬ!AO60 -> 291.87675 | D54: =C54/C$106 -> 6.7263253e-05 | E54: =E53+D54 -> 1.0102413 | F54: =IF(AND(E54<=0),"C",IF(E54<=0.8,"A",IF(E54<=0.95,"B","C"))) -> C | G54: =VLOOKUP(B$4:B$104,I$4:M$104,5,0) -> C | I54: MANNA2105 | J54: =АПРЕЛЬ!U58 -> 4 | K54: =J54/J$106 -> 0.00038993956 | L54: =L53+K54 -> 0.99210372 | M54: =_xlfn.IFS(L54<80%,"A",L54<=95%,"B",L54>95%,"C") -> C
B55: Qianai черные | C55: =АПРЕЛЬ!AO83 -> 137.58136 | D55: =C55/C$106 -> 3.1705745e-05 | E55: =E54+D55 -> 1.010273 | F55: =IF(AND(E55<=0),"C",IF(E55<=0.8,"A",IF(E55<=0.95,"B","C"))) -> C | G55: =VLOOKUP(B$4:B$104,I$4:M$104,5,0) -> C | I55: MANNA2108 | J55: =АПРЕЛЬ!U61 -> 4 | K55: =J55/J$106 -> 0.00038993956 | L55: =L54+K55 -> 0.99249366 | M55: =_xlfn.IFS(L55<80%,"A",L55<=95%,"B",L55>95%,"C") -> C
B56: Linhai Baiyi розовая линза | C56: =АПРЕЛЬ!AO88 -> 96.973711 | D56: =C56/C$106 -> 2.2347677e-05 | E56: =E55+D56 -> 1.0102953 | F56: =IF(AND(E56<=0),"C",IF(E56<=0.8,"A",IF(E56<=0.95,"B","C"))) -> C | G56: =VLOOKUP(B$4:B$104,I$4:M$104,5,0) -> C | I56: MANNA2120 | J56: =АПРЕЛЬ!U73 -> 4 | K56: =J56/J$106 -> 0.00038993956 | L56: =L55+K56 -> 0.9928836 | M56: =_xlfn.IFS(L56<80%,"A",L56<=95%,"B",L56>95%,"C") -> C
B57: sh15 | C57: =АПРЕЛЬ!AO39 -> 75.812474 | D57: =C57/C$106 -> 1.7471051e-05 | E57: =E56+D57 -> 1.0103128 | F57: =IF(AND(E57<=0),"C",IF(E57<=0.8,"A",IF(E57<=0.95,"B","C"))) -> C | G57: =VLOOKUP(B$4:B$104,I$4:M$104,5,0) -> C | I57: Hengda Optical леопард | J57: =АПРЕЛЬ!U82 -> 4 | K57: =J57/J$106 -> 0.00038993956 | L57: =L56+K57 -> 0.99327354 | M57: =_xlfn.IFS(L57<80%,"A",L57<=95%,"B",L57>95%,"C") -> C
B58: wwl8032 черные серебро | C58: =АПРЕЛЬ!AO19 -> 0 | D58: =C58/C$106 -> 0 | E58: =E57+D58 -> 1.0103128 | F58: =IF(AND(E58<=0),"C",IF(E58<=0.8,"A",IF(E58<=0.95,"B","C"))) -> C | G58: =VLOOKUP(B$4:B$104,I$4:M$104,5,0) -> C | I58: Ли Сян ретро золото | J58: =АПРЕЛЬ!U92 -> 4 | K58: =J58/J$106 -> 0.00038993956 | L58: =L57+K58 -> 0.99366348 | M58: =_xlfn.IFS(L58<80%,"A",L58<=95%,"B",L58>95%,"C") -> C
B59: sportlife черные | C59: =АПРЕЛЬ!AO23 -> 0 | D59: =C59/C$106 -> 0 | E59: =E58+D59 -> 1.0103128 | F59: =IF(AND(E59<=0),"C",IF(E59<=0.8,"A",IF(E59<=0.95,"B","C"))) -> C | G59: =VLOOKUP(B$4:B$104,I$4:M$104,5,0) -> C | I59: sh15 | J59: =АПРЕЛЬ!U39 -> 3 | K59: =J59/J$106 -> 0.00029245467 | L59: =L58+K59 -> 0.99395594 | M59: =_xlfn.IFS(L59<80%,"A",L59<=95%,"B",L59>95%,"C") -> C
B60: sportlife красные | C60: =АПРЕЛЬ!AO25 -> 0 | D60: =C60/C$106 -> 0 | E60: =E59+D60 -> 1.0103128 | F60: =IF(AND(E60<=0),"C",IF(E60<=0.8,"A",IF(E60<=0.95,"B","C"))) -> C | G60: =VLOOKUP(B$4:B$104,I$4:M$104,5,0) -> C | I60: Ли Сян ретро серебро | J60: =АПРЕЛЬ!U93 -> 3 | K60: =J60/J$106 -> 0.00029245467 | L60: =L59+K60 -> 0.99424839 | M60: =_xlfn.IFS(L60<80%,"A",L60<=95%,"B",L60>95%,"C") -> C
B61: sh4 | C61: =АПРЕЛЬ!AO29 -> 0 | D61: =C61/C$106 -> 0 | E61: =E60+D61 -> 1.0103128 | F61: =IF(AND(E61<=0),"C",IF(E61<=0.8,"A",IF(E61<=0.95,"B","C"))) -> C | G61: =VLOOKUP(B$4:B$104,I$4:M$104,5,0) -> C | I61: sportlife синие | J61: =АПРЕЛЬ!U24 -> 2 | K61: =J61/J$106 -> 0.00019496978 | L61: =L60+K61 -> 0.99444336 | M61: =_xlfn.IFS(L61<80%,"A",L61<=95%,"B",L61>95%,"C") -> C
B62: sh06 | C62: =АПРЕЛЬ!AO30 -> 0 | D62: =C62/C$106 -> 0 | E62: =E61+D62 -> 1.0103128 | F62: =IF(AND(E62<=0),"C",IF(E62<=0.8,"A",IF(E62<=0.95,"B","C"))) -> C | G62: =VLOOKUP(B$4:B$104,I$4:M$104,5,0) -> C | I62: sh10 | J62: =АПРЕЛЬ!U34 -> 2 | K62: =J62/J$106 -> 0.00019496978 | L62: =L61+K62 -> 0.99463833 | M62: =_xlfn.IFS(L62<80%,"A",L62<=95%,"B",L62>95%,"C") -> C
B63: sh08 | C63: =АПРЕЛЬ!AO32 -> 0 | D63: =C63/C$106 -> 0 | E63: =E62+D63 -> 1.0103128 | F63: =IF(AND(E63<=0),"C",IF(E63<=0.8,"A",IF(E63<=0.95,"B","C"))) -> C | G63: =VLOOKUP(B$4:B$104,I$4:M$104,5,0) -> C | I63: sh17 | J63: =АПРЕЛЬ!U41 -> 2 | K63: =J63/J$106 -> 0.00019496978 | L63: =L62+K63 -> 0.9948333 | M63: =_xlfn.IFS(L63<80%,"A",L63<=95%,"B",L63>95%,"C") -> C
B64: sh11 | C64: =АПРЕЛЬ!AO35 -> 0 | D64: =C64/C$106 -> 0 | E64: =E63+D64 -> 1.0103128 | F64: =IF(AND(E64<=0),"C",IF(E64<=0.8,"A",IF(E64<=0.95,"B","C"))) -> C | G64: =VLOOKUP(B$4:B$104,I$4:M$104,5,0) -> C | I64: MANNA2107 | J64: =АПРЕЛЬ!U60 -> 2 | K64: =J64/J$106 -> 0.00019496978 | L64: =L63+K64 -> 0.99502827 | M64: =_xlfn.IFS(L64<80%,"A",L64<=95%,"B",L64>95%,"C") -> C
B65: sh12 | C65: =АПРЕЛЬ!AO36 -> 0 | D65: =C65/C$106 -> 0 | E65: =E64+D65 -> 1.0103128 | F65: =IF(AND(E65<=0),"C",IF(E65<=0.8,"A",IF(E65<=0.95,"B","C"))) -> C | G65: =VLOOKUP(B$4:B$104,I$4:M$104,5,0) -> C | I65: MANNA2117 | J65: =АПРЕЛЬ!U70 -> 2 | K65: =J65/J$106 -> 0.00019496978 | L65: =L64+K65 -> 0.99522324 | M65: =_xlfn.IFS(L65<80%,"A",L65<=95%,"B",L65>95%,"C") -> C
B66: ww 1022 черн-серебро | C66: =АПРЕЛЬ!AO46 -> 0 | D66: =C66/C$106 -> 0 | E66: =E65+D66 -> 1.0103128 | F66: =IF(AND(E66<=0),"C",IF(E66<=0.8,"A",IF(E66<=0.95,"B","C"))) -> C | G66: =VLOOKUP(B$4:B$104,I$4:M$104,5,0) -> C | I66: Hengda Optical черные | J66: =АПРЕЛЬ!U81 -> 2 | K66: =J66/J$106 -> 0.00019496978 | L66: =L65+K66 -> 0.99541821 | M66: =_xlfn.IFS(L66<80%,"A",L66<=95%,"B",L66>95%,"C") -> C
B67: MANNA2103 | C67: =АПРЕЛЬ!AO56 -> 0 | D67: =C67/C$106 -> 0 | E67: =E66+D67 -> 1.0103128 | F67: =IF(AND(E67<=0),"C",IF(E67<=0.8,"A",IF(E67<=0.95,"B","C"))) -> C | G67: =VLOOKUP(B$4:B$104,I$4:M$104,5,0) -> C | I67: Qianai черные | J67: =АПРЕЛЬ!U83 -> 2 | K67: =J67/J$106 -> 0.00019496978 | L67: =L66+K67 -> 0.99561318 | M67: =_xlfn.IFS(L67<80%,"A",L67<=95%,"B",L67>95%,"C") -> C
B68: MANNA2104 | C68: =АПРЕЛЬ!AO57 -> 0 | D68: =C68/C$106 -> 0 | E68: =E67+D68 -> 1.0103128 | F68: =IF(AND(E68<=0),"C",IF(E68<=0.8,"A",IF(E68<=0.95,"B","C"))) -> C | G68: =VLOOKUP(B$4:B$104,I$4:M$104,5,0) -> C | I68: Taizhou Rayen sport розовый | J68: =АПРЕЛЬ!U90 -> 2 | K68: =J68/J$106 -> 0.00019496978 | L68: =L67+K68 -> 0.99580815 | M68: =_xlfn.IFS(L68<80%,"A",L68<=95%,"B",L68>95%,"C") -> C
B69: MANNA2106 | C69: =АПРЕЛЬ!AO59 -> 0 | D69: =C69/C$106 -> 0 | E69: =E68+D69 -> 1.0103128 | F69: =IF(AND(E69<=0),"C",IF(E69<=0.8,"A",IF(E69<=0.95,"B","C"))) -> C | G69: =VLOOKUP(B$4:B$104,I$4:M$104,5,0) -> C | I69: Иу Диту серый | J69: =АПРЕЛЬ!U91 -> 2 | K69: =J69/J$106 -> 0.00019496978 | L69: =L68+K69 -> 0.99600312 | M69: =_xlfn.IFS(L69<80%,"A",L69<=95%,"B",L69>95%,"C") -> C
B70: MANNA2109 | C70: =АПРЕЛЬ!AO62 -> 0 | D70: =C70/C$106 -> 0 | E70: =E69+D70 -> 1.0103128 | F70: =IF(AND(E70<=0),"C",IF(E70<=0.8,"A",IF(E70<=0.95,"B","C"))) -> C | G70: =VLOOKUP(B$4:B$104,I$4:M$104,5,0) -> C | I70: sh07 | J70: =АПРЕЛЬ!U31 -> 1 | K70: =J70/J$106 -> 9.748489e-05 | L70: =L69+K70 -> 0.9961006 | M70: =_xlfn.IFS(L70<80%,"A",L70<=95%,"B",L70>95%,"C") -> C
B71: MANNA2110 | C71: =АПРЕЛЬ!AO63 -> 0 | D71: =C71/C$106 -> 0 | E71: =E70+D71 -> 1.0103128 | F71: =IF(AND(E71<=0),"C",IF(E71<=0.8,"A",IF(E71<=0.95,"B","C"))) -> C | G71: =VLOOKUP(B$4:B$104,I$4:M$104,5,0) -> C | I71: sh14 | J71: =АПРЕЛЬ!U38 -> 1 | K71: =J71/J$106 -> 9.748489e-05 | L71: =L70+K71 -> 0.99619809 | M71: =_xlfn.IFS(L71<80%,"A",L71<=95%,"B",L71>95%,"C") -> C
B72: MANNA2111 | C72: =АПРЕЛЬ!AO64 -> 0 | D72: =C72/C$106 -> 0 | E72: =E71+D72 -> 1.0103128 | F72: =IF(AND(E72<=0),"C",IF(E72<=0.8,"A",IF(E72<=0.95,"B","C"))) -> C | G72: =VLOOKUP(B$4:B$104,I$4:M$104,5,0) -> C | I72: MANNA2118 | J72: =АПРЕЛЬ!U71 -> 1 | K72: =J72/J$106 -> 9.748489e-05 | L72: =L71+K72 -> 0.99629557 | M72: =_xlfn.IFS(L72<80%,"A",L72<=95%,"B",L72>95%,"C") -> C
B73: MANNA2114 | C73: =АПРЕЛЬ!AO67 -> 0 | D73: =C73/C$106 -> 0 | E73: =E72+D73 -> 1.0103128 | F73: =IF(AND(E73<=0),"C",IF(E73<=0.8,"A",IF(E73<=0.95,"B","C"))) -> C | G73: =VLOOKUP(B$4:B$104,I$4:M$104,5,0) -> C | I73: MANNA2119 | J73: =АПРЕЛЬ!U72 -> 1 | K73: =J73/J$106 -> 9.748489e-05 | L73: =L72+K73 -> 0.99639306 | M73: =_xlfn.IFS(L73<80%,"A",L73<=95%,"B",L73>95%,"C") -> C
B74: MANNA2115 | C74: =АПРЕЛЬ!AO68 -> 0 | D74: =C74/C$106 -> 0 | E74: =E73+D74 -> 1.0103128 | F74: =IF(AND(E74<=0),"C",IF(E74<=0.8,"A",IF(E74<=0.95,"B","C"))) -> C | G74: =VLOOKUP(B$4:B$104,I$4:M$104,5,0) -> C | I74: Keming Aishi коричневые | J74: =АПРЕЛЬ!U85 -> 1 | K74: =J74/J$106 -> 9.748489e-05 | L74: =L73+K74 -> 0.99649054 | M74: =_xlfn.IFS(L74<80%,"A",L74<=95%,"B",L74>95%,"C") -> C
B75: MAIERSHA 03898 C9-08 | C75: =АПРЕЛЬ!AO94 -> 0 | D75: =C75/C$106 -> 0 | E75: =E74+D75 -> 1.0103128 | F75: =IF(AND(E75<=0),"C",IF(E75<=0.8,"A",IF(E75<=0.95,"B","C"))) -> C | G75: =VLOOKUP(B$4:B$104,I$4:M$104,5,0) -> C | I75: Linhai Baiyi розовая линза | J75: =АПРЕЛЬ!U88 -> 1 | K75: =J75/J$106 -> 9.748489e-05 | L75: =L74+K75 -> 0.99658803 | M75: =_xlfn.IFS(L75<80%,"A",L75<=95%,"B",L75>95%,"C") -> C
B76: MAIERSHA 03914 C9-124 | C76: =АПРЕЛЬ!AO95 -> 0 | D76: =C76/C$106 -> 0 | E76: =E49+D76 -> 1.009872 | F76: =IF(AND(E76<=0),"C",IF(E76<=0.8,"A",IF(E76<=0.95,"B","C"))) -> C | G76: =VLOOKUP(B$4:B$104,I$4:M$104,5,0) -> C | I76: wwl8032 черные серебро | J76: =АПРЕЛЬ!U19 -> 0 | K76: =J76/J$106 -> 0 | L76: =L49+K76 -> 0.98986157 | M76: =_xlfn.IFS(L76<80%,"A",L76<=95%,"B",L76>95%,"C") -> C
B77: MARSTON 7171 C1 | C77: =АПРЕЛЬ!AO96 -> 0 | D77: =C77/C$106 -> 0 | E77: =E76+D77 -> 1.009872 | F77: =IF(AND(E77<=0),"C",IF(E77<=0.8,"A",IF(E77<=0.95,"B","C"))) -> C | G77: =VLOOKUP(B$4:B$104,I$4:M$104,5,0) -> C | I77: sportlife черные | J77: =АПРЕЛЬ!U23 -> 0 | K77: =J77/J$106 -> 0 | L77: =L76+K77 -> 0.98986157 | M77: =_xlfn.IFS(L77<80%,"A",L77<=95%,"B",L77>95%,"C") -> C
B78: ЧСЖ_тест | C78: =АПРЕЛЬ!AO99 -> 0 | D78: =C78/C$106 -> 0 | E78: =E77+D78 -> 1.009872 | F78: =IF(AND(E78<=0),"C",IF(E78<=0.8,"A",IF(E78<=0.95,"B","C"))) -> C | G78: =VLOOKUP(B$4:B$104,I$4:M$104,5,0) -> C | I78: sportlife красные | J78: =АПРЕЛЬ!U25 -> 0 | K78: =J78/J$106 -> 0 | L78: =L77+K78 -> 0.98986157 | M78: =_xlfn.IFS(L78<80%,"A",L78<=95%,"B",L78>95%,"C") -> C
B79: кс_черные_тест | C79: =АПРЕЛЬ!AO101 -> 0 | D79: =C79/C$106 -> 0 | E79: =E78+D79 -> 1.009872 | F79: =IF(AND(E79<=0),"C",IF(E79<=0.8,"A",IF(E79<=0.95,"B","C"))) -> C | G79: =VLOOKUP(B$4:B$104,I$4:M$104,5,0) -> C | I79: sh4 | J79: =АПРЕЛЬ!U29 -> 0 | K79: =J79/J$106 -> 0 | L79: =L78+K79 -> 0.98986157 | M79: =_xlfn.IFS(L79<80%,"A",L79<=95%,"B",L79>95%,"C") -> C
B80: 1022_коричневые_тест | C80: =АПРЕЛЬ!AO103 -> 0 | D80: =C80/C$106 -> 0 | E80: =E79+D80 -> 1.009872 | F80: =IF(AND(E80<=0),"C",IF(E80<=0.8,"A",IF(E80<=0.95,"B","C"))) -> C | G80: =VLOOKUP(B$4:B$104,I$4:M$104,5,0) -> #N/A | I80: sh06 | J80: =АПРЕЛЬ!U30 -> 0 | K80: =J80/J$106 -> 0 | L80: =L79+K80 -> 0.98986157 | M80: =_xlfn.IFS(L80<80%,"A",L80<=95%,"B",L80>95%,"C") -> C
B81: MANNA2112 | C81: =АПРЕЛЬ!AO65 -> -5.0275997 | D81: =C81/C$106 -> -1.1586148e-06 | E81: =E80+D81 -> 1.0098708 | F81: =IF(AND(E81<=0),"C",IF(E81<=0.8,"A",IF(E81<=0.95,"B","C"))) -> C | G81: =VLOOKUP(B$4:B$104,I$4:M$104,5,0) -> C | I81: sh08 | J81: =АПРЕЛЬ!U32 -> 0 | K81: =J81/J$106 -> 0 | L81: =L80+K81 -> 0.98986157 | M81: =_xlfn.IFS(L81<80%,"A",L81<=95%,"B",L81>95%,"C") -> C
B82: MANNA2113 | C82: =АПРЕЛЬ!AO66 -> -9.6386749 | D82: =C82/C$106 -> -2.2212411e-06 | E82: =E81+D82 -> 1.0098686 | F82: =IF(AND(E82<=0),"C",IF(E82<=0.8,"A",IF(E82<=0.95,"B","C"))) -> C | G82: =VLOOKUP(B$4:B$104,I$4:M$104,5,0) -> C | I82: sh11 | J82: =АПРЕЛЬ!U35 -> 0 | K82: =J82/J$106 -> 0 | L82: =L81+K82 -> 0.98986157 | M82: =_xlfn.IFS(L82<80%,"A",L82<=95%,"B",L82>95%,"C") -> C
B83: MANNA2121 | C83: =АПРЕЛЬ!AO74 -> -59.3 | D83: =C83/C$106 -> -1.3665737e-05 | E83: =E82+D83 -> 1.0098549 | F83: =IF(AND(E83<=0),"C",IF(E83<=0.8,"A",IF(E83<=0.95,"B","C"))) -> C | G83: =VLOOKUP(B$4:B$104,I$4:M$104,5,0) -> C | I83: sh12 | J83: =АПРЕЛЬ!U36 -> 0 | K83: =J83/J$106 -> 0 | L83: =L82+K83 -> 0.98986157 | M83: =_xlfn.IFS(L83<80%,"A",L83<=95%,"B",L83>95%,"C") -> C
B84: MANNA2118 | C84: =АПРЕЛЬ!AO71 -> -65.135369 | D84: =C84/C$106 -> -1.5010503e-05 | E84: =E83+D84 -> 1.0098399 | F84: =IF(AND(E84<=0),"C",IF(E84<=0.8,"A",IF(E84<=0.95,"B","C"))) -> C | G84: =VLOOKUP(B$4:B$104,I$4:M$104,5,0) -> C | I84: sh13 | J84: =АПРЕЛЬ!U37 -> 0 | K84: =J84/J$106 -> 0 | L84: =L83+K84 -> 0.98986157 | M84: =_xlfn.IFS(L84<80%,"A",L84<=95%,"B",L84>95%,"C") -> C
B85: MANNA2102 | C85: =АПРЕЛЬ!AO55 -> -97.181431 | D85: =C85/C$106 -> -2.2395546e-05 | E85: =E84+D85 -> 1.0098175 | F85: =IF(AND(E85<=0),"C",IF(E85<=0.8,"A",IF(E85<=0.95,"B","C"))) -> C | G85: =VLOOKUP(B$4:B$104,I$4:M$104,5,0) -> C | I85: ww 1022 черн-серебро | J85: =АПРЕЛЬ!U46 -> 0 | K85: =J85/J$106 -> 0 | L85: =L84+K85 -> 0.98986157 | M85: =_xlfn.IFS(L85<80%,"A",L85<=95%,"B",L85>95%,"C") -> C
B86: Guangdu серебро серая линза | C86: =АПРЕЛЬ!AO80 -> -100.34234 | D86: =C86/C$106 -> -2.3123981e-05 | E86: =E85+D86 -> 1.0097944 | F86: =IF(AND(E86<=0),"C",IF(E86<=0.8,"A",IF(E86<=0.95,"B","C"))) -> C | G86: =VLOOKUP(B$4:B$104,I$4:M$104,5,0) -> C | I86: ww 8010 черные | J86: =АПРЕЛЬ!U51 -> 0 | K86: =J86/J$106 -> 0 | L86: =L85+K86 -> 0.98986157 | M86: =_xlfn.IFS(L86<80%,"A",L86<=95%,"B",L86>95%,"C") -> C
B87: MANNA2108 | C87: =АПРЕЛЬ!AO61 -> -118.67302 | D87: =C87/C$106 -> -2.7348301e-05 | E87: =E86+D87 -> 1.009767 | F87: =IF(AND(E87<=0),"C",IF(E87<=0.8,"A",IF(E87<=0.95,"B","C"))) -> C | G87: =VLOOKUP(B$4:B$104,I$4:M$104,5,0) -> C | I87: MANNA2102 | J87: =АПРЕЛЬ!U55 -> 0 | K87: =J87/J$106 -> 0 | L87: =L86+K87 -> 0.98986157 | M87: =_xlfn.IFS(L87<80%,"A",L87<=95%,"B",L87>95%,"C") -> C
B88: ww 8010 черные | C88: =АПРЕЛЬ!AO51 -> -152.01275 | D88: =C88/C$106 -> -3.5031471e-05 | E88: =E87+D88 -> 1.009732 | F88: =IF(AND(E88<=0),"C",IF(E88<=0.8,"A",IF(E88<=0.95,"B","C"))) -> C | G88: =VLOOKUP(B$4:B$104,I$4:M$104,5,0) -> C | I88: MANNA2103 | J88: =АПРЕЛЬ!U56 -> 0 | K88: =J88/J$106 -> 0 | L88: =L87+K88 -> 0.98986157 | M88: =_xlfn.IFS(L88<80%,"A",L88<=95%,"B",L88>95%,"C") -> C
B89: sh14 | C89: =АПРЕЛЬ!AO38 -> -258.56554 | D89: =C89/C$106 -> -5.9586656e-05 | E89: =E88+D89 -> 1.0096724 | F89: =IF(AND(E89<=0),"C",IF(E89<=0.8,"A",IF(E89<=0.95,"B","C"))) -> C | G89: =VLOOKUP(B$4:B$104,I$4:M$104,5,0) -> C | I89: MANNA2104 | J89: =АПРЕЛЬ!U57 -> 0 | K89: =J89/J$106 -> 0 | L89: =L88+K89 -> 0.98986157 | M89: =_xlfn.IFS(L89<80%,"A",L89<=95%,"B",L89>95%,"C") -> C
B90: sh13 | C90: =АПРЕЛЬ!AO37 -> -279.90408 | D90: =C90/C$106 -> -6.4504141e-05 | E90: =E89+D90 -> 1.0096079 | F90: =IF(AND(E90<=0),"C",IF(E90<=0.8,"A",IF(E90<=0.95,"B","C"))) -> C | G90: =VLOOKUP(B$4:B$104,I$4:M$104,5,0) -> C | I90: MANNA2106 | J90: =АПРЕЛЬ!U59 -> 0 | K90: =J90/J$106 -> 0 | L90: =L89+K90 -> 0.98986157 | M90: =_xlfn.IFS(L90<80%,"A",L90<=95%,"B",L90>95%,"C") -> C
B91: sh2 | C91: =АПРЕЛЬ!AO27 -> -282.52693 | D91: =C91/C$106 -> -6.5108578e-05 | E91: =E90+D91 -> 1.0095428 | F91: =IF(AND(E91<=0),"C",IF(E91<=0.8,"A",IF(E91<=0.95,"B","C"))) -> C | G91: =VLOOKUP(B$4:B$104,I$4:M$104,5,0) -> C | I91: MANNA2109 | J91: =АПРЕЛЬ!U62 -> 0 | K91: =J91/J$106 -> 0 | L91: =L90+K91 -> 0.98986157 | M91: =_xlfn.IFS(L91<80%,"A",L91<=95%,"B",L91>95%,"C") -> C
B92: POMILED 08247 C4-08 | C92: =АПРЕЛЬ!AO97 -> -473.14551 | D92: =C92/C$106 -> -0.0001090368 | E92: =E91+D92 -> 1.0094338 | F92: =IF(AND(E92<=0),"C",IF(E92<=0.8,"A",IF(E92<=0.95,"B","C"))) -> C | G92: =VLOOKUP(B$4:B$104,I$4:M$104,5,0) -> C | I92: MANNA2110 | J92: =АПРЕЛЬ!U63 -> 0 | K92: =J92/J$106 -> 0 | L92: =L91+K92 -> 0.98986157 | M92: =_xlfn.IFS(L92<80%,"A",L92<=95%,"B",L92>95%,"C") -> C
B93: Guangdu золото серая линза | C93: =АПРЕЛЬ!AO79 -> -1496.9953 | D93: =C93/C$106 -> -0.00034498387 | E93: =E92+D93 -> 1.0090888 | F93: =IF(AND(E93<=0),"C",IF(E93<=0.8,"A",IF(E93<=0.95,"B","C"))) -> C | G93: =VLOOKUP(B$4:B$104,I$4:M$104,5,0) -> C | I93: MANNA2111 | J93: =АПРЕЛЬ!U64 -> 0 | K93: =J93/J$106 -> 0 | L93: =L92+K93 -> 0.98986157 | M93: =_xlfn.IFS(L93<80%,"A",L93<=95%,"B",L93>95%,"C") -> C
B94: Linhai Baiyi коричневая линза | C94: =АПРЕЛЬ!AO86 -> -1901.3716 | D94: =C94/C$106 -> -0.00043817276 | E94: =E93+D94 -> 1.0086506 | F94: =IF(AND(E94<=0),"C",IF(E94<=0.8,"A",IF(E94<=0.95,"B","C"))) -> C | G94: =VLOOKUP(B$4:B$104,I$4:M$104,5,0) -> C | I94: MANNA2112 | J94: =АПРЕЛЬ!U65 -> 0 | K94: =J94/J$106 -> 0 | L94: =L93+K94 -> 0.98986157 | M94: =_xlfn.IFS(L94<80%,"A",L94<=95%,"B",L94>95%,"C") -> C
B95: Hengda Optical леопард | C95: =АПРЕЛЬ!AO82 -> -2280.2504 | D95: =C95/C$106 -> -0.0005254857 | E95: =E94+D95 -> 1.0081251 | F95: =IF(AND(E95<=0),"C",IF(E95<=0.8,"A",IF(E95<=0.95,"B","C"))) -> C | G95: =VLOOKUP(B$4:B$104,I$4:M$104,5,0) -> C | I95: MANNA2113 | J95: =АПРЕЛЬ!U66 -> 0 | K95: =J95/J$106 -> 0 | L95: =L94+K95 -> 0.98986157 | M95: =_xlfn.IFS(L95<80%,"A",L95<=95%,"B",L95>95%,"C") -> C
B96: WW 3055 черный | C96: =АПРЕЛЬ!AO52 -> -2829.0551 | D96: =C96/C$106 -> -0.00065195823 | E96: =E95+D96 -> 1.0074732 | F96: =IF(AND(E96<=0),"C",IF(E96<=0.8,"A",IF(E96<=0.95,"B","C"))) -> C | G96: =VLOOKUP(B$4:B$104,I$4:M$104,5,0) -> C | I96: MANNA2114 | J96: =АПРЕЛЬ!U67 -> 0 | K96: =J96/J$106 -> 0 | L96: =L95+K96 -> 0.98986157 | M96: =_xlfn.IFS(L96<80%,"A",L96<=95%,"B",L96>95%,"C") -> C
B97: Chenlong коричневые | C97: =АПРЕЛЬ!AO77 -> -3061.9327 | D97: =C97/C$106 -> -0.00070562507 | E97: =E96+D97 -> 1.0067675 | F97: =IF(AND(E97<=0),"C",IF(E97<=0.8,"A",IF(E97<=0.95,"B","C"))) -> C | G97: =VLOOKUP(B$4:B$104,I$4:M$104,5,0) -> C | I97: MANNA2115 | J97: =АПРЕЛЬ!U68 -> 0 | K97: =J97/J$106 -> 0 | L97: =L96+K97 -> 0.98986157 | M97: =_xlfn.IFS(L97<80%,"A",L97<=95%,"B",L97>95%,"C") -> C
B98: MANNA2105 | C98: =АПРЕЛЬ!AO58 -> -3150.0656 | D98: =C98/C$106 -> -0.00072593538 | E98: =E97+D98 -> 1.0060416 | F98: =IF(AND(E98<=0),"C",IF(E98<=0.8,"A",IF(E98<=0.95,"B","C"))) -> C | G98: =VLOOKUP(B$4:B$104,I$4:M$104,5,0) -> C | I98: MANNA2121 | J98: =АПРЕЛЬ!U74 -> 0 | K98: =J98/J$106 -> 0 | L98: =L97+K98 -> 0.98986157 | M98: =_xlfn.IFS(L98<80%,"A",L98<=95%,"B",L98>95%,"C") -> C
B99: Qianai коричневые | C99: =АПРЕЛЬ!AO84 -> -3186.2876 | D99: =C99/C$106 -> -0.00073428277 | E99: =E93+D99 -> 1.0083545 | F99: =IF(AND(E99<=0),"C",IF(E99<=0.8,"A",IF(E99<=0.95,"B","C"))) -> C | G99: =VLOOKUP(B$4:B$104,I$4:M$104,5,0) -> C | I99: MAIERSHA 03898 C9-08 | J99: =АПРЕЛЬ!U94 -> 0 | K99: =J99/J$106 -> 0 | L99: =L93+K99 -> 0.98986157 | M99: =_xlfn.IFS(L99<80%,"A",L99<=95%,"B",L99>95%,"C") -> C
B100: Chenlong белые | C100: =АПРЕЛЬ!AO78 -> -3351.0835 | D100: =C100/C$106 -> -0.00077226014 | E100: =E94+D100 -> 1.0078784 | F100: =IF(AND(E100<=0),"C",IF(E100<=0.8,"A",IF(E100<=0.95,"B","C"))) -> C | G100: =VLOOKUP(B$4:B$104,I$4:M$104,5,0) -> C | I100: MAIERSHA 03914 C9-124 | J100: =АПРЕЛЬ!U95 -> 0 | K100: =J100/J$106 -> 0 | L100: =L94+K100 -> 0.98986157 | M100: =_xlfn.IFS(L100<80%,"A",L100<=95%,"B",L100>95%,"C") -> C
B101: Иу Диту серый | C101: =АПРЕЛЬ!AO91 -> -3769.8197 | D101: =C101/C$106 -> -0.00086875827 | E101: =E95+D101 -> 1.0072564 | F101: =IF(AND(E101<=0),"C",IF(E101<=0.8,"A",IF(E101<=0.95,"B","C"))) -> C | G101: =VLOOKUP(B$4:B$104,I$4:M$104,5,0) -> C | I101: MARSTON 7171 C1 | J101: =АПРЕЛЬ!U96 -> 0 | K101: =J101/J$106 -> 0 | L101: =L95+K101 -> 0.98986157 | M101: =_xlfn.IFS(L101<80%,"A",L101<=95%,"B",L101>95%,"C") -> C
...

Sheet АВС 18
B2: ОЧКИ
C3: Прибыль | D3: % прибыль | E3: Доля | F3: ABC прибыль | G3: ABC кол-во | J3: Кол-во | K3: % кол-во | L3: Доля | M3: ABC кол-во
B4: QS черные PZ | C4: ='Юнит 18'!AO4 -> 152899.34 | D4: =C4/C$106 -> 0.24312855 | E4: =D4 -> 0.24312855 | F4: =IF(AND(E4<=0),"C",IF(E4<=0.8,"A",IF(E4<=0.95,"B","C"))) -> A | G4: =VLOOKUP(B$4:B$104,I$4:M$104,5,0) -> A | I4: QS черные PZ | J4: ='Юнит 18'!U4 -> 325 | K4: =J4/J$106 -> 0.20388959 | L4: =K4 -> 0.20388959 | M4: =_xlfn.IFS(L4<80%,"A",L4<=95%,"B",L4>95%,"C") -> A | P4: A | Q4: 0.8
B5: flip коричневые | C5: ='Юнит 18'!AO16 -> 54125.259 | D5: =C5/C$106 -> 0.086065744 | E5: =E4+D5 -> 0.3291943 | F5: =IF(AND(E5<=0),"C",IF(E5<=0.8,"A",IF(E5<=0.95,"B","C"))) -> A | G5: =VLOOKUP(B$4:B$104,I$4:M$104,5,0) -> A | I5: flip черные | J5: ='Юнит 18'!U13 -> 159 | K5: =J5/J$106 -> 0.099749059 | L5: =L4+K5 -> 0.30363864 | M5: =_xlfn.IFS(L5<80%,"A",L5<=95%,"B",L5>95%,"C") -> A | P5: B | Q5: 0.15
B6: th черн | C6: ='Юнит 18'!AO9 -> 49251.158 | D6: =C6/C$106 -> 0.078315332 | E6: =E5+D6 -> 0.40750963 | F6: =IF(AND(E6<=0),"C",IF(E6<=0.8,"A",IF(E6<=0.95,"B","C"))) -> A | G6: =VLOOKUP(B$4:B$104,I$4:M$104,5,0) -> A | I6: th черн | J6: ='Юнит 18'!U9 -> 144 | K6: =J6/J$106 -> 0.09033877 | L6: =L5+K6 -> 0.39397742 | M6: =_xlfn.IFS(L6<80%,"A",L6<=95%,"B",L6>95%,"C") -> A | P6: C | Q6: 0.05
B7: flip черные | C7: ='Юнит 18'!AO13 -> 48332.649 | D7: =C7/C$106 -> 0.07685479 | E7: =E6+D7 -> 0.48436442 | F7: =IF(AND(E7<=0),"C",IF(E7<=0.8,"A",IF(E7<=0.95,"B","C"))) -> A | G7: =VLOOKUP(B$4:B$104,I$4:M$104,5,0) -> A | I7: flip коричневые | J7: ='Юнит 18'!U16 -> 118 | K7: =J7/J$106 -> 0.074027604 | L7: =L6+K7 -> 0.46800502 | M7: =_xlfn.IFS(L7<80%,"A",L7<=95%,"B",L7>95%,"C") -> A
B8: th син | C8: ='Юнит 18'!AO10 -> 39757.841 | D8: =C8/C$106 -> 0.063219802 | E8: =E7+D8 -> 0.54758422 | F8: =IF(AND(E8<=0),"C",IF(E8<=0.8,"A",IF(E8<=0.95,"B","C"))) -> A | G8: =VLOOKUP(B$4:B$104,I$4:M$104,5,0) -> A | I8: QS синие PZ | J8: ='Юнит 18'!U5 -> 96 | K8: =J8/J$106 -> 0.060225847 | L8: =L7+K8 -> 0.52823087 | M8: =_xlfn.IFS(L8<80%,"A",L8<=95%,"B",L8>95%,"C") -> A
B9: черные с железкой классика | C9: ='Юнит 18'!AO3 -> 38522.371 | D9: =C9/C$106 -> 0.061255255 | E9: =E8+D9 -> 0.60883947 | F9: =IF(AND(E9<=0),"C",IF(E9<=0.8,"A",IF(E9<=0.95,"B","C"))) -> A | G9: =VLOOKUP(B$4:B$104,I$4:M$104,5,0) -> A | I9: th син | J9: ='Юнит 18'!U10 -> 96 | K9: =J9/J$106 -> 0.060225847 | L9: =L8+K9 -> 0.58845671 | M9: =_xlfn.IFS(L9<80%,"A",L9<=95%,"B",L9>95%,"C") -> A
B10: QS синие PZ | C10: ='Юнит 18'!AO5 -> 35720.93 | D10: =C10/C$106 -> 0.056800623 | E10: =E9+D10 -> 0.6656401 | F10: =IF(AND(E10<=0),"C",IF(E10<=0.8,"A",IF(E10<=0.95,"B","C"))) -> A | G10: =VLOOKUP(B$4:B$104,I$4:M$104,5,0) -> A | I10: черные с железкой классика | J10: ='Юнит 18'!U3 -> 95 | K10: =J10/J$106 -> 0.059598494 | L10: =L9+K10 -> 0.64805521 | M10: =_xlfn.IFS(L10<80%,"A",L10<=95%,"B",L10>95%,"C") -> A
B11: QS коричневые PZ | C11: ='Юнит 18'!AO7 -> 28936.842 | D11: =C11/C$106 -> 0.046013098 | E11: =E10+D11 -> 0.7116532 | F11: =IF(AND(E11<=0),"C",IF(E11<=0.8,"A",IF(E11<=0.95,"B","C"))) -> A | G11: =VLOOKUP(B$4:B$104,I$4:M$104,5,0) -> A | I11: QS коричневые PZ | J11: ='Юнит 18'!U7 -> 69 | K11: =J11/J$106 -> 0.043287327 | L11: =L10+K11 -> 0.69134253 | M11: =_xlfn.IFS(L11<80%,"A",L11<=95%,"B",L11>95%,"C") -> A
B12: QS желтые PZ | C12: ='Юнит 18'!AO6 -> 25904.542 | D12: =C12/C$106 -> 0.041191372 | E12: =E11+D12 -> 0.75284457 | F12: =IF(AND(E12<=0),"C",IF(E12<=0.8,"A",IF(E12<=0.95,"B","C"))) -> A | G12: =VLOOKUP(B$4:B$104,I$4:M$104,5,0) -> A | I12: th коричн | J12: ='Юнит 18'!U12 -> 57 | K12: =J12/J$106 -> 0.035759097 | L12: =L11+K12 -> 0.72710163 | M12: =_xlfn.IFS(L12<80%,"A",L12<=95%,"B",L12>95%,"C") -> A
B13: th коричн | C13: ='Юнит 18'!AO12 -> 19891.381 | D13: =C13/C$106 -> 0.031629715 | E13: =E12+D13 -> 0.78447428 | F13: =IF(AND(E13<=0),"C",IF(E13<=0.8,"A",IF(E13<=0.95,"B","C"))) -> A | G13: =VLOOKUP(B$4:B$104,I$4:M$104,5,0) -> A | I13: QS желтые PZ | J13: ='Юнит 18'!U6 -> 55 | K13: =J13/J$106 -> 0.034504391 | L13: =L12+K13 -> 0.76160602 | M13: =_xlfn.IFS(L13<80%,"A",L13<=95%,"B",L13>95%,"C") -> A
B14: th желт | C14: ='Юнит 18'!AO11 -> 17835.083 | D14: =C14/C$106 -> 0.028359951 | E14: =E13+D14 -> 0.81283423 | F14: =IF(AND(E14<=0),"C",IF(E14<=0.8,"A",IF(E14<=0.95,"B","C"))) -> B | G14: =VLOOKUP(B$4:B$104,I$4:M$104,5,0) -> A | I14: th желт | J14: ='Юнит 18'!U11 -> 47 | K14: =J14/J$106 -> 0.029485571 | L14: =L13+K14 -> 0.79109159 | M14: =_xlfn.IFS(L14<80%,"A",L14<=95%,"B",L14>95%,"C") -> A
B15: flip желтые | C15: ='Юнит 18'!AO15 -> 17425.896 | D15: =C15/C$106 -> 0.027709294 | E15: =E14+D15 -> 0.84054353 | F15: =IF(AND(E15<=0),"C",IF(E15<=0.8,"A",IF(E15<=0.95,"B","C"))) -> B | G15: =VLOOKUP(B$4:B$104,I$4:M$104,5,0) -> B | I15: flip желтые | J15: ='Юнит 18'!U15 -> 40 | K15: =J15/J$106 -> 0.025094103 | L15: =L14+K15 -> 0.8161857 | M15: =_xlfn.IFS(L15<80%,"A",L15<=95%,"B",L15>95%,"C") -> B
B16: flip синие | C16: ='Юнит 18'!AO14 -> 14351.423 | D16: =C16/C$106 -> 0.022820507 | E16: =E15+D16 -> 0.86336404 | F16: =IF(AND(E16<=0),"C",IF(E16<=0.8,"A",IF(E16<=0.95,"B","C"))) -> B | G16: =VLOOKUP(B$4:B$104,I$4:M$104,5,0) -> B | I16: sh3 | J16: ='Юнит 18'!U28 -> 32 | K16: =J16/J$106 -> 0.020075282 | L16: =L15+K16 -> 0.83626098 | M16: =_xlfn.IFS(L16<80%,"A",L16<=95%,"B",L16>95%,"C") -> B
B17: sh3 | C17: ='Юнит 18'!AO28 -> 13580.878 | D17: =C17/C$106 -> 0.021595247 | E17: =E16+D17 -> 0.88495928 | F17: =IF(AND(E17<=0),"C",IF(E17<=0.8,"A",IF(E17<=0.95,"B","C"))) -> B | G17: =VLOOKUP(B$4:B$104,I$4:M$104,5,0) -> B | I17: flip синие | J17: ='Юнит 18'!U14 -> 30 | K17: =J17/J$106 -> 0.018820577 | L17: =L16+K17 -> 0.85508156 | M17: =_xlfn.IFS(L17<80%,"A",L17<=95%,"B",L17>95%,"C") -> B
B18: ridges brand 01 | C18: ='Юнит 18'!AO104 -> 13222.112 | D18: =C18/C$106 -> 0.021024767 | E18: =E17+D18 -> 0.90598405 | F18: =IF(AND(E18<=0),"C",IF(E18<=0.8,"A",IF(E18<=0.95,"B","C"))) -> B | G18: =VLOOKUP(B$4:B$104,I$4:M$104,5,0) -> C | I18: ww 1022 коричневые | J18: ='Юнит 18'!U48 -> 24 | K18: =J18/J$106 -> 0.015056462 | L18: =L17+K18 -> 0.87013802 | M18: =_xlfn.IFS(L18<80%,"A",L18<=95%,"B",L18>95%,"C") -> B
B19: ww 2018 желтые | C19: ='Юнит 18'!AO50 -> 10238.42 | D19: =C19/C$106 -> 0.016280332 | E19: =E18+D19 -> 0.92226438 | F19: =IF(AND(E19<=0),"C",IF(E19<=0.8,"A",IF(E19<=0.95,"B","C"))) -> B | G19: =VLOOKUP(B$4:B$104,I$4:M$104,5,0) -> B | I19: ww 2018 желтые | J19: ='Юнит 18'!U50 -> 24 | K19: =J19/J$106 -> 0.015056462 | L19: =L18+K19 -> 0.88519448 | M19: =_xlfn.IFS(L19<80%,"A",L19<=95%,"B",L19>95%,"C") -> B
B20: ww 1022 коричневые | C20: ='Юнит 18'!AO48 -> 8940.0592 | D20: =C20/C$106 -> 0.014215781 | E20: =E19+D20 -> 0.93648016 | F20: =IF(AND(E20<=0),"C",IF(E20<=0.8,"A",IF(E20<=0.95,"B","C"))) -> B | G20: =VLOOKUP(B$4:B$104,I$4:M$104,5,0) -> B | I20: ww 1022 черные | J20: ='Юнит 18'!U45 -> 23 | K20: =J20/J$106 -> 0.014429109 | L20: =L19+K20 -> 0.89962359 | M20: =_xlfn.IFS(L20<80%,"A",L20<=95%,"B",L20>95%,"C") -> B
B21: wwl8032 коричневые золото | C21: ='Юнит 18'!AO17 -> 7982.9514 | D21: =C21/C$106 -> 0.012693864 | E21: =E20+D21 -> 0.94917403 | F21: =IF(AND(E21<=0),"C",IF(E21<=0.8,"A",IF(E21<=0.95,"B","C"))) -> B | G21: =VLOOKUP(B$4:B$104,I$4:M$104,5,0) -> B | I21: ww 2018 черные | J21: ='Юнит 18'!U49 -> 23 | K21: =J21/J$106 -> 0.014429109 | L21: =L20+K21 -> 0.9140527 | M21: =_xlfn.IFS(L21<80%,"A",L21<=95%,"B",L21>95%,"C") -> B
B22: ww 1022 черные | C22: ='Юнит 18'!AO45 -> 7037.3747 | D22: =C22/C$106 -> 0.011190282 | E22: =E21+D22 -> 0.96036431 | F22: =IF(AND(E22<=0),"C",IF(E22<=0.8,"A",IF(E22<=0.95,"B","C"))) -> C | G22: =VLOOKUP(B$4:B$104,I$4:M$104,5,0) -> B | I22: wwl8032 коричневые золото | J22: ='Юнит 18'!U17 -> 20 | K22: =J22/J$106 -> 0.012547051 | L22: =L21+K22 -> 0.92659975 | M22: =_xlfn.IFS(L22<80%,"A",L22<=95%,"B",L22>95%,"C") -> B
B23: wwl8032 хром металл | C23: ='Юнит 18'!AO18 -> 7034.7279 | D23: =C23/C$106 -> 0.011186073 | E23: =E22+D23 -> 0.97155038 | F23: =IF(AND(E23<=0),"C",IF(E23<=0.8,"A",IF(E23<=0.95,"B","C"))) -> C | G23: =VLOOKUP(B$4:B$104,I$4:M$104,5,0) -> B | I23: MR8854 C2 Жен | J23: ='Юнит 18'!U8 -> 17 | K23: =J23/J$106 -> 0.010664994 | L23: =L22+K23 -> 0.93726474 | M23: =_xlfn.IFS(L23<80%,"A",L23<=95%,"B",L23>95%,"C") -> B
B24: MR8854 C2 Жен | C24: ='Юнит 18'!AO8 -> 6600.7762 | D24: =C24/C$106 -> 0.010496037 | E24: =E23+D24 -> 0.98204642 | F24: =IF(AND(E24<=0),"C",IF(E24<=0.8,"A",IF(E24<=0.95,"B","C"))) -> C | G24: =VLOOKUP(B$4:B$104,I$4:M$104,5,0) -> B | I24: wwl8032 хром металл | J24: ='Юнит 18'!U18 -> 17 | K24: =J24/J$106 -> 0.010664994 | L24: =L23+K24 -> 0.94792974 | M24: =_xlfn.IFS(L24<80%,"A",L24<=95%,"B",L24>95%,"C") -> B
B25: ww 203 черные | C25: ='Юнит 18'!AO44 -> 5771.7294 | D25: =C25/C$106 -> 0.0091777517 | E25: =E24+D25 -> 0.99122417 | F25: =IF(AND(E25<=0),"C",IF(E25<=0.8,"A",IF(E25<=0.95,"B","C"))) -> C | G25: =VLOOKUP(B$4:B$104,I$4:M$104,5,0) -> C | I25: ridges brand 01 | J25: ='Юнит 18'!U104 -> 15 | K25: =J25/J$106 -> 0.0094102886 | L25: =L24+K25 -> 0.95734003 | M25: =_xlfn.IFS(L25<80%,"A",L25<=95%,"B",L25>95%,"C") -> C
B26: ww 2018 черные | C26: ='Юнит 18'!AO49 -> 4321.8178 | D26: =C26/C$106 -> 0.006872216 | E26: =E25+D26 -> 0.99809639 | F26: =IF(AND(E26<=0),"C",IF(E26<=0.8,"A",IF(E26<=0.95,"B","C"))) -> C | G26: =VLOOKUP(B$4:B$104,I$4:M$104,5,0) -> B | I26: ww 203 черные | J26: ='Юнит 18'!U44 -> 14 | K26: =J26/J$106 -> 0.008782936 | L26: =L25+K26 -> 0.96612296 | M26: =_xlfn.IFS(L26<80%,"A",L26<=95%,"B",L26>95%,"C") -> C
B27: ww 1022 желтые | C27: ='Юнит 18'!AO47 -> 2726.0369 | D27: =C27/C$106 -> 0.0043347302 | E27: =E26+D27 -> 1.0024311 | F27: =IF(AND(E27<=0),"C",IF(E27<=0.8,"A",IF(E27<=0.95,"B","C"))) -> C | G27: =VLOOKUP(B$4:B$104,I$4:M$104,5,0) -> C | I27: ww 1022 желтые | J27: ='Юнит 18'!U47 -> 6 | K27: =J27/J$106 -> 0.0037641154 | L27: =L26+K27 -> 0.96988708 | M27: =_xlfn.IFS(L27<80%,"A",L27<=95%,"B",L27>95%,"C") -> C
B28: sports красные | C28: ='Юнит 18'!AO22 -> 2221.6382 | D28: =C28/C$106 -> 0.0035326749 | E28: =E27+D28 -> 1.0059638 | F28: =IF(AND(E28<=0),"C",IF(E28<=0.8,"A",IF(E28<=0.95,"B","C"))) -> C | G28: =VLOOKUP(B$4:B$104,I$4:M$104,5,0) -> C | I28: sports красные | J28: ='Юнит 18'!U22 -> 5 | K28: =J28/J$106 -> 0.0031367629 | L28: =L27+K28 -> 0.97302384 | M28: =_xlfn.IFS(L28<80%,"A",L28<=95%,"B",L28>95%,"C") -> C
B29: sh1 | C29: ='Юнит 18'!AO26 -> 1735.3614 | D29: =C29/C$106 -> 0.0027594357 | E29: =E28+D29 -> 1.0087232 | F29: =IF(AND(E29<=0),"C",IF(E29<=0.8,"A",IF(E29<=0.95,"B","C"))) -> C | G29: =VLOOKUP(B$4:B$104,I$4:M$104,5,0) -> C | I29: sh1 | J29: ='Юнит 18'!U26 -> 5 | K29: =J29/J$106 -> 0.0031367629 | L29: =L28+K29 -> 0.9761606 | M29: =_xlfn.IFS(L29<80%,"A",L29<=95%,"B",L29>95%,"C") -> C
B30: sports синие | C30: ='Юнит 18'!AO20 -> 1667.852 | D30: =C30/C$106 -> 0.0026520876 | E30: =E29+D30 -> 1.0113753 | F30: =IF(AND(E30<=0),"C",IF(E30<=0.8,"A",IF(E30<=0.95,"B","C"))) -> C | G30: =VLOOKUP(B$4:B$104,I$4:M$104,5,0) -> C | I30: Linhai Baiyi коричневая линза | J30: ='Юнит 18'!U86 -> 5 | K30: =J30/J$106 -> 0.0031367629 | L30: =L29+K30 -> 0.97929737 | M30: =_xlfn.IFS(L30<80%,"A",L30<=95%,"B",L30>95%,"C") -> C
B31: sports зеленые | C31: ='Юнит 18'!AO21 -> 1064.5807 | D31: =C31/C$106 -> 0.0016928128 | E31: =E30+D31 -> 1.0130681 | F31: =IF(AND(E31<=0),"C",IF(E31<=0.8,"A",IF(E31<=0.95,"B","C"))) -> C | G31: =VLOOKUP(B$4:B$104,I$4:M$104,5,0) -> C | I31: sports синие | J31: ='Юнит 18'!U20 -> 4 | K31: =J31/J$106 -> 0.0025094103 | L31: =L30+K31 -> 0.98180678 | M31: =_xlfn.IFS(L31<80%,"A",L31<=95%,"B",L31>95%,"C") -> C
B32: MANNA2101 | C32: ='Юнит 18'!AO54 -> 773.72425 | D32: =C32/C$106 -> 0.0012303157 | E32: =E31+D32 -> 1.0142984 | F32: =IF(AND(E32<=0),"C",IF(E32<=0.8,"A",IF(E32<=0.95,"B","C"))) -> C | G32: =VLOOKUP(B$4:B$104,I$4:M$104,5,0) -> C | I32: sports зеленые | J32: ='Юнит 18'!U21 -> 3 | K32: =J32/J$106 -> 0.0018820577 | L32: =L31+K32 -> 0.98368883 | M32: =_xlfn.IFS(L32<80%,"A",L32<=95%,"B",L32>95%,"C") -> C
B33: Linhai Baiyi серая линза | C33: ='Юнит 18'!AO87 -> 584.34196 | D33: =C33/C$106 -> 0.00092917479 | E33: =E32+D33 -> 1.0152276 | F33: =IF(AND(E33<=0),"C",IF(E33<=0.8,"A",IF(E33<=0.95,"B","C"))) -> C | G33: =VLOOKUP(B$4:B$104,I$4:M$104,5,0) -> C | I33: Guangdu золото серая линза | J33: ='Юнит 18'!U79 -> 3 | K33: =J33/J$106 -> 0.0018820577 | L33: =L32+K33 -> 0.98557089 | M33: =_xlfn.IFS(L33<80%,"A",L33<=95%,"B",L33>95%,"C") -> C
B34: кс_черные_женские | C34: ='Юнит 18'!AO102 -> 581.71422 | D34: =C34/C$106 -> 0.00092499637 | E34: =E33+D34 -> 1.0161526 | F34: =IF(AND(E34<=0),"C",IF(E34<=0.8,"A",IF(E34<=0.95,"B","C"))) -> C | G34: =VLOOKUP(B$4:B$104,I$4:M$104,5,0) -> C | I34: WW 3055 черный | J34: ='Юнит 18'!U52 -> 2 | K34: =J34/J$106 -> 0.0012547051 | L34: =L33+K34 -> 0.9868256 | M34: =_xlfn.IFS(L34<80%,"A",L34<=95%,"B",L34>95%,"C") -> C
B35: sh18 | C35: ='Юнит 18'!AO42 -> 396.50822 | D35: =C35/C$106 -> 0.00063049629 | E35: =E34+D35 -> 1.0167831 | F35: =IF(AND(E35<=0),"C",IF(E35<=0.8,"A",IF(E35<=0.95,"B","C"))) -> C | G35: =VLOOKUP(B$4:B$104,I$4:M$104,5,0) -> C | I35: MANNA2101 | J35: ='Юнит 18'!U54 -> 2 | K35: =J35/J$106 -> 0.0012547051 | L35: =L34+K35 -> 0.9880803 | M35: =_xlfn.IFS(L35<80%,"A",L35<=95%,"B",L35>95%,"C") -> C
B36: sh07 | C36: ='Юнит 18'!AO31 -> 313.14 | D36: =C36/C$106 -> 0.00049793068 | E36: =E35+D36 -> 1.017281 | F36: =IF(AND(E36<=0),"C",IF(E36<=0.8,"A",IF(E36<=0.95,"B","C"))) -> C | G36: =VLOOKUP(B$4:B$104,I$4:M$104,5,0) -> C | I36: MANNA2105 | J36: ='Юнит 18'!U58 -> 2 | K36: =J36/J$106 -> 0.0012547051 | L36: =L35+K36 -> 0.98933501 | M36: =_xlfn.IFS(L36<80%,"A",L36<=95%,"B",L36>95%,"C") -> C
B37: Guangdu серебро серая линза | C37: ='Юнит 18'!AO80 -> 257.65956 | D37: =C37/C$106 -> 0.00040971004 | E37: =E36+D37 -> 1.0176908 | F37: =IF(AND(E37<=0),"C",IF(E37<=0.8,"A",IF(E37<=0.95,"B","C"))) -> C | G37: =VLOOKUP(B$4:B$104,I$4:M$104,5,0) -> C | I37: Guangdu серебро серая линза | J37: ='Юнит 18'!U80 -> 2 | K37: =J37/J$106 -> 0.0012547051 | L37: =L36+K37 -> 0.99058971 | M37: =_xlfn.IFS(L37<80%,"A",L37<=95%,"B",L37>95%,"C") -> C
B38: ЧСЖ_женские | C38: ='Юнит 18'!AO100 -> 250.31641 | D38: =C38/C$106 -> 0.00039803353 | E38: =E37+D38 -> 1.0180888 | F38: =IF(AND(E38<=0),"C",IF(E38<=0.8,"A",IF(E38<=0.95,"B","C"))) -> C | G38: =VLOOKUP(B$4:B$104,I$4:M$104,5,0) -> C | I38: Linhai Baiyi серая линза | J38: ='Юнит 18'!U87 -> 2 | K38: =J38/J$106 -> 0.0012547051 | L38: =L37+K38 -> 0.99184442 | M38: =_xlfn.IFS(L38<80%,"A",L38<=95%,"B",L38>95%,"C") -> C
B39: YIMEI 2391 C1 | C39: ='Юнит 18'!AO98 -> 78.685574 | D39: =C39/C$106 -> 0.00012511963 | E39: =E35+D39 -> 1.0169082 | F39: =IF(AND(E39<=0),"C",IF(E39<=0.8,"A",IF(E39<=0.95,"B","C"))) -> C | G39: =VLOOKUP(B$4:B$104,I$4:M$104,5,0) -> C | I39: кс_черные_женские | J39: ='Юнит 18'!U102 -> 2 | K39: =J39/J$106 -> 0.0012547051 | L39: =L35+K39 -> 0.98933501 | M39: =_xlfn.IFS(L39<80%,"A",L39<=95%,"B",L39>95%,"C") -> C
B40: Keming Aishi коричневые | C40: ='Юнит 18'!AO85 -> 72.553031 | D40: =C40/C$106 -> 0.00011536814 | E40: =E39+D40 -> 1.0170236 | F40: =IF(AND(E40<=0),"C",IF(E40<=0.8,"A",IF(E40<=0.95,"B","C"))) -> C | G40: =VLOOKUP(B$4:B$104,I$4:M$104,5,0) -> C | I40: sh07 | J40: ='Юнит 18'!U31 -> 1 | K40: =J40/J$106 -> 0.00062735257 | L40: =L39+K40 -> 0.98996236 | M40: =_xlfn.IFS(L40<80%,"A",L40<=95%,"B",L40>95%,"C") -> C
B41: wwl8032 черные серебро | C41: ='Юнит 18'!AO19 -> 0 | D41: =C41/C$106 -> 0 | E41: =E40+D41 -> 1.0170236 | F41: =IF(AND(E41<=0),"C",IF(E41<=0.8,"A",IF(E41<=0.95,"B","C"))) -> C | G41: =VLOOKUP(B$4:B$104,I$4:M$104,5,0) -> C | I41: sh09 | J41: ='Юнит 18'!U33 -> 1 | K41: =J41/J$106 -> 0.00062735257 | L41: =L40+K41 -> 0.99058971 | M41: =_xlfn.IFS(L41<80%,"A",L41<=95%,"B",L41>95%,"C") -> C
B42: sportlife черные | C42: ='Юнит 18'!AO23 -> 0 | D42: =C42/C$106 -> 0 | E42: =E41+D42 -> 1.0170236 | F42: =IF(AND(E42<=0),"C",IF(E42<=0.8,"A",IF(E42<=0.95,"B","C"))) -> C | G42: =VLOOKUP(B$4:B$104,I$4:M$104,5,0) -> C | I42: sh18 | J42: ='Юнит 18'!U42 -> 1 | K42: =J42/J$106 -> 0.00062735257 | L42: =L41+K42 -> 0.99121706 | M42: =_xlfn.IFS(L42<80%,"A",L42<=95%,"B",L42>95%,"C") -> C
B43: sportlife красные | C43: ='Юнит 18'!AO25 -> 0 | D43: =C43/C$106 -> 0 | E43: =E42+D43 -> 1.0170236 | F43: =IF(AND(E43<=0),"C",IF(E43<=0.8,"A",IF(E43<=0.95,"B","C"))) -> C | G43: =VLOOKUP(B$4:B$104,I$4:M$104,5,0) -> C | I43: MANNA2122 | J43: ='Юнит 18'!U75 -> 1 | K43: =J43/J$106 -> 0.00062735257 | L43: =L42+K43 -> 0.99184442 | M43: =_xlfn.IFS(L43<80%,"A",L43<=95%,"B",L43>95%,"C") -> C
B44: sh4 | C44: ='Юнит 18'!AO29 -> 0 | D44: =C44/C$106 -> 0 | E44: =E43+D44 -> 1.0170236 | F44: =IF(AND(E44<=0),"C",IF(E44<=0.8,"A",IF(E44<=0.95,"B","C"))) -> C | G44: =VLOOKUP(B$4:B$104,I$4:M$104,5,0) -> C | I44: Chenlong черные | J44: ='Юнит 18'!U76 -> 1 | K44: =J44/J$106 -> 0.00062735257 | L44: =L43+K44 -> 0.99247177 | M44: =_xlfn.IFS(L44<80%,"A",L44<=95%,"B",L44>95%,"C") -> C
B45: sh06 | C45: ='Юнит 18'!AO30 -> 0 | D45: =C45/C$106 -> 0 | E45: =E44+D45 -> 1.0170236 | F45: =IF(AND(E45<=0),"C",IF(E45<=0.8,"A",IF(E45<=0.95,"B","C"))) -> C | G45: =VLOOKUP(B$4:B$104,I$4:M$104,5,0) -> C | I45: Hengda Optical леопард | J45: ='Юнит 18'!U82 -> 1 | K45: =J45/J$106 -> 0.00062735257 | L45: =L44+K45 -> 0.99309912 | M45: =_xlfn.IFS(L45<80%,"A",L45<=95%,"B",L45>95%,"C") -> C
B46: sh08 | C46: ='Юнит 18'!AO32 -> 0 | D46: =C46/C$106 -> 0 | E46: =E45+D46 -> 1.0170236 | F46: =IF(AND(E46<=0),"C",IF(E46<=0.8,"A",IF(E46<=0.95,"B","C"))) -> C | G46: =VLOOKUP(B$4:B$104,I$4:M$104,5,0) -> C | I46: Keming Aishi коричневые | J46: ='Юнит 18'!U85 -> 1 | K46: =J46/J$106 -> 0.00062735257 | L46: =L45+K46 -> 0.99372647 | M46: =_xlfn.IFS(L46<80%,"A",L46<=95%,"B",L46>95%,"C") -> C
B47: sh10 | C47: ='Юнит 18'!AO34 -> 0 | D47: =C47/C$106 -> 0 | E47: =E46+D47 -> 1.0170236 | F47: =IF(AND(E47<=0),"C",IF(E47<=0.8,"A",IF(E47<=0.95,"B","C"))) -> C | G47: =VLOOKUP(B$4:B$104,I$4:M$104,5,0) -> C | I47: Иу Диту серый | J47: ='Юнит 18'!U91 -> 1 | K47: =J47/J$106 -> 0.00062735257 | L47: =L46+K47 -> 0.99435383 | M47: =_xlfn.IFS(L47<80%,"A",L47<=95%,"B",L47>95%,"C") -> C
B48: sh11 | C48: ='Юнит 18'!AO35 -> 0 | D48: =C48/C$106 -> 0 | E48: =E47+D48 -> 1.0170236 | F48: =IF(AND(E48<=0),"C",IF(E48<=0.8,"A",IF(E48<=0.95,"B","C"))) -> C | G48: =VLOOKUP(B$4:B$104,I$4:M$104,5,0) -> C | I48: Ли Сян ретро золото | J48: ='Юнит 18'!U92 -> 1 | K48: =J48/J$106 -> 0.00062735257 | L48: =L47+K48 -> 0.99498118 | M48: =_xlfn.IFS(L48<80%,"A",L48<=95%,"B",L48>95%,"C") -> C
B49: sh12 | C49: ='Юнит 18'!AO36 -> 0 | D49: =C49/C$106 -> 0 | E49: =E48+D49 -> 1.0170236 | F49: =IF(AND(E49<=0),"C",IF(E49<=0.8,"A",IF(E49<=0.95,"B","C"))) -> C | G49: =VLOOKUP(B$4:B$104,I$4:M$104,5,0) -> C | I49: YIMEI 2391 C1 | J49: ='Юнит 18'!U98 -> 1 | K49: =J49/J$106 -> 0.00062735257 | L49: =L48+K49 -> 0.99560853 | M49: =_xlfn.IFS(L49<80%,"A",L49<=95%,"B",L49>95%,"C") -> C
B50: sh13 | C50: ='Юнит 18'!AO37 -> 0 | D50: =C50/C$106 -> 0 | E50: =E49+D50 -> 1.0170236 | F50: =IF(AND(E50<=0),"C",IF(E50<=0.8,"A",IF(E50<=0.95,"B","C"))) -> C | G50: =VLOOKUP(B$4:B$104,I$4:M$104,5,0) -> C | I50: ЧСЖ_женские | J50: ='Юнит 18'!U100 -> 1 | K50: =J50/J$106 -> 0.00062735257 | L50: =L49+K50 -> 0.99623588 | M50: =_xlfn.IFS(L50<80%,"A",L50<=95%,"B",L50>95%,"C") -> C
B51: ww 1022 черн-серебро | C51: ='Юнит 18'!AO46 -> 0 | D51: =C51/C$106 -> 0 | E51: =E50+D51 -> 1.0170236 | F51: =IF(AND(E51<=0),"C",IF(E51<=0.8,"A",IF(E51<=0.95,"B","C"))) -> C | G51: =VLOOKUP(B$4:B$104,I$4:M$104,5,0) -> C | I51: wwl8032 черные серебро | J51: ='Юнит 18'!U19 -> 0 | K51: =J51/J$106 -> 0 | L51: =L50+K51 -> 0.99623588 | M51: =_xlfn.IFS(L51<80%,"A",L51<=95%,"B",L51>95%,"C") -> C
B52: MANNA2102 | C52: ='Юнит 18'!AO55 -> 0 | D52: =C52/C$106 -> 0 | E52: =E51+D52 -> 1.0170236 | F52: =IF(AND(E52<=0),"C",IF(E52<=0.8,"A",IF(E52<=0.95,"B","C"))) -> C | G52: =VLOOKUP(B$4:B$104,I$4:M$104,5,0) -> C | I52: sportlife черные | J52: ='Юнит 18'!U23 -> 0 | K52: =J52/J$106 -> 0 | L52: =L51+K52 -> 0.99623588 | M52: =_xlfn.IFS(L52<80%,"A",L52<=95%,"B",L52>95%,"C") -> C
B53: MANNA2103 | C53: ='Юнит 18'!AO56 -> 0 | D53: =C53/C$106 -> 0 | E53: =E52+D53 -> 1.0170236 | F53: =IF(AND(E53<=0),"C",IF(E53<=0.8,"A",IF(E53<=0.95,"B","C"))) -> C | G53: =VLOOKUP(B$4:B$104,I$4:M$104,5,0) -> C | I53: sportlife синие | J53: ='Юнит 18'!U24 -> 0 | K53: =J53/J$106 -> 0 | L53: =L52+K53 -> 0.99623588 | M53: =_xlfn.IFS(L53<80%,"A",L53<=95%,"B",L53>95%,"C") -> C
B54: MANNA2104 | C54: ='Юнит 18'!AO57 -> 0 | D54: =C54/C$106 -> 0 | E54: =E53+D54 -> 1.0170236 | F54: =IF(AND(E54<=0),"C",IF(E54<=0.8,"A",IF(E54<=0.95,"B","C"))) -> C | G54: =VLOOKUP(B$4:B$104,I$4:M$104,5,0) -> C | I54: sportlife красные | J54: ='Юнит 18'!U25 -> 0 | K54: =J54/J$106 -> 0 | L54: =L53+K54 -> 0.99623588 | M54: =_xlfn.IFS(L54<80%,"A",L54<=95%,"B",L54>95%,"C") -> C
B55: MANNA2106 | C55: ='Юнит 18'!AO59 -> 0 | D55: =C55/C$106 -> 0 | E55: =E54+D55 -> 1.0170236 | F55: =IF(AND(E55<=0),"C",IF(E55<=0.8,"A",IF(E55<=0.95,"B","C"))) -> C | G55: =VLOOKUP(B$4:B$104,I$4:M$104,5,0) -> C | I55: sh2 | J55: ='Юнит 18'!U27 -> 0 | K55: =J55/J$106 -> 0 | L55: =L54+K55 -> 0.99623588 | M55: =_xlfn.IFS(L55<80%,"A",L55<=95%,"B",L55>95%,"C") -> C
B56: MANNA2109 | C56: ='Юнит 18'!AO62 -> 0 | D56: =C56/C$106 -> 0 | E56: =E55+D56 -> 1.0170236 | F56: =IF(AND(E56<=0),"C",IF(E56<=0.8,"A",IF(E56<=0.95,"B","C"))) -> C | G56: =VLOOKUP(B$4:B$104,I$4:M$104,5,0) -> C | I56: sh4 | J56: ='Юнит 18'!U29 -> 0 | K56: =J56/J$106 -> 0 | L56: =L55+K56 -> 0.99623588 | M56: =_xlfn.IFS(L56<80%,"A",L56<=95%,"B",L56>95%,"C") -> C
B57: MANNA2110 | C57: ='Юнит 18'!AO63 -> 0 | D57: =C57/C$106 -> 0 | E57: =E56+D57 -> 1.0170236 | F57: =IF(AND(E57<=0),"C",IF(E57<=0.8,"A",IF(E57<=0.95,"B","C"))) -> C | G57: =VLOOKUP(B$4:B$104,I$4:M$104,5,0) -> C | I57: sh06 | J57: ='Юнит 18'!U30 -> 0 | K57: =J57/J$106 -> 0 | L57: =L56+K57 -> 0.99623588 | M57: =_xlfn.IFS(L57<80%,"A",L57<=95%,"B",L57>95%,"C") -> C
B58: MANNA2111 | C58: ='Юнит 18'!AO64 -> 0 | D58: =C58/C$106 -> 0 | E58: =E57+D58 -> 1.0170236 | F58: =IF(AND(E58<=0),"C",IF(E58<=0.8,"A",IF(E58<=0.95,"B","C"))) -> C | G58: =VLOOKUP(B$4:B$104,I$4:M$104,5,0) -> C | I58: sh08 | J58: ='Юнит 18'!U32 -> 0 | K58: =J58/J$106 -> 0 | L58: =L57+K58 -> 0.99623588 | M58: =_xlfn.IFS(L58<80%,"A",L58<=95%,"B",L58>95%,"C") -> C
B59: MANNA2112 | C59: ='Юнит 18'!AO65 -> 0 | D59: =C59/C$106 -> 0 | E59: =E58+D59 -> 1.0170236 | F59: =IF(AND(E59<=0),"C",IF(E59<=0.8,"A",IF(E59<=0.95,"B","C"))) -> C | G59: =VLOOKUP(B$4:B$104,I$4:M$104,5,0) -> C | I59: sh10 | J59: ='Юнит 18'!U34 -> 0 | K59: =J59/J$106 -> 0 | L59: =L58+K59 -> 0.99623588 | M59: =_xlfn.IFS(L59<80%,"A",L59<=95%,"B",L59>95%,"C") -> C
B60: MANNA2114 | C60: ='Юнит 18'!AO67 -> 0 | D60: =C60/C$106 -> 0 | E60: =E59+D60 -> 1.0170236 | F60: =IF(AND(E60<=0),"C",IF(E60<=0.8,"A",IF(E60<=0.95,"B","C"))) -> C | G60: =VLOOKUP(B$4:B$104,I$4:M$104,5,0) -> C | I60: sh11 | J60: ='Юнит 18'!U35 -> 0 | K60: =J60/J$106 -> 0 | L60: =L59+K60 -> 0.99623588 | M60: =_xlfn.IFS(L60<80%,"A",L60<=95%,"B",L60>95%,"C") -> C
B61: MANNA2115 | C61: ='Юнит 18'!AO68 -> 0 | D61: =C61/C$106 -> 0 | E61: =E60+D61 -> 1.0170236 | F61: =IF(AND(E61<=0),"C",IF(E61<=0.8,"A",IF(E61<=0.95,"B","C"))) -> C | G61: =VLOOKUP(B$4:B$104,I$4:M$104,5,0) -> C | I61: sh12 | J61: ='Юнит 18'!U36 -> 0 | K61: =J61/J$106 -> 0 | L61: =L60+K61 -> 0.99623588 | M61: =_xlfn.IFS(L61<80%,"A",L61<=95%,"B",L61>95%,"C") -> C
B62: MANNA2117 | C62: ='Юнит 18'!AO70 -> 0 | D62: =C62/C$106 -> 0 | E62: =E61+D62 -> 1.0170236 | F62: =IF(AND(E62<=0),"C",IF(E62<=0.8,"A",IF(E62<=0.95,"B","C"))) -> C | G62: =VLOOKUP(B$4:B$104,I$4:M$104,5,0) -> C | I62: sh13 | J62: ='Юнит 18'!U37 -> 0 | K62: =J62/J$106 -> 0 | L62: =L61+K62 -> 0.99623588 | M62: =_xlfn.IFS(L62<80%,"A",L62<=95%,"B",L62>95%,"C") -> C
B63: MANNA2118 | C63: ='Юнит 18'!AO71 -> 0 | D63: =C63/C$106 -> 0 | E63: =E62+D63 -> 1.0170236 | F63: =IF(AND(E63<=0),"C",IF(E63<=0.8,"A",IF(E63<=0.95,"B","C"))) -> C | G63: =VLOOKUP(B$4:B$104,I$4:M$104,5,0) -> C | I63: sh14 | J63: ='Юнит 18'!U38 -> 0 | K63: =J63/J$106 -> 0 | L63: =L62+K63 -> 0.99623588 | M63: =_xlfn.IFS(L63<80%,"A",L63<=95%,"B",L63>95%,"C") -> C
B64: MANNA2119 | C64: ='Юнит 18'!AO72 -> 0 | D64: =C64/C$106 -> 0 | E64: =E63+D64 -> 1.0170236 | F64: =IF(AND(E64<=0),"C",IF(E64<=0.8,"A",IF(E64<=0.95,"B","C"))) -> C | G64: =VLOOKUP(B$4:B$104,I$4:M$104,5,0) -> C | I64: sh15 | J64: ='Юнит 18'!U39 -> 0 | K64: =J64/J$106 -> 0 | L64: =L63+K64 -> 0.99623588 | M64: =_xlfn.IFS(L64<80%,"A",L64<=95%,"B",L64>95%,"C") -> C
B65: MAIERSHA 03898 C9-08 | C65: ='Юнит 18'!AO94 -> 0 | D65: =C65/C$106 -> 0 | E65: =E64+D65 -> 1.0170236 | F65: =IF(AND(E65<=0),"C",IF(E65<=0.8,"A",IF(E65<=0.95,"B","C"))) -> C | G65: =VLOOKUP(B$4:B$104,I$4:M$104,5,0) -> C | I65: sh16 | J65: ='Юнит 18'!U40 -> 0 | K65: =J65/J$106 -> 0 | L65: =L64+K65 -> 0.99623588 | M65: =_xlfn.IFS(L65<80%,"A",L65<=95%,"B",L65>95%,"C") -> C
B66: MAIERSHA 03914 C9-124 | C66: ='Юнит 18'!AO95 -> 0 | D66: =C66/C$106 -> 0 | E66: =E65+D66 -> 1.0170236 | F66: =IF(AND(E66<=0),"C",IF(E66<=0.8,"A",IF(E66<=0.95,"B","C"))) -> C | G66: =VLOOKUP(B$4:B$104,I$4:M$104,5,0) -> C | I66: sh17 | J66: ='Юнит 18'!U41 -> 0 | K66: =J66/J$106 -> 0 | L66: =L65+K66 -> 0.99623588 | M66: =_xlfn.IFS(L66<80%,"A",L66<=95%,"B",L66>95%,"C") -> C
B67: MARSTON 7171 C1 | C67: ='Юнит 18'!AO96 -> 0 | D67: =C67/C$106 -> 0 | E67: =E66+D67 -> 1.0170236 | F67: =IF(AND(E67<=0),"C",IF(E67<=0.8,"A",IF(E67<=0.95,"B","C"))) -> C | G67: =VLOOKUP(B$4:B$104,I$4:M$104,5,0) -> C | I67: sh19 | J67: ='Юнит 18'!U43 -> 0 | K67: =J67/J$106 -> 0 | L67: =L66+K67 -> 0.99623588 | M67: =_xlfn.IFS(L67<80%,"A",L67<=95%,"B",L67>95%,"C") -> C
B68: ЧСЖ_тест | C68: ='Юнит 18'!AO99 -> 0 | D68: =C68/C$106 -> 0 | E68: =E67+D68 -> 1.0170236 | F68: =IF(AND(E68<=0),"C",IF(E68<=0.8,"A",IF(E68<=0.95,"B","C"))) -> C | G68: =VLOOKUP(B$4:B$104,I$4:M$104,5,0) -> C | I68: ww 1022 черн-серебро | J68: ='Юнит 18'!U46 -> 0 | K68: =J68/J$106 -> 0 | L68: =L67+K68 -> 0.99623588 | M68: =_xlfn.IFS(L68<80%,"A",L68<=95%,"B",L68>95%,"C") -> C
B69: кс_черные_тест | C69: ='Юнит 18'!AO101 -> 0 | D69: =C69/C$106 -> 0 | E69: =E68+D69 -> 1.0170236 | F69: =IF(AND(E69<=0),"C",IF(E69<=0.8,"A",IF(E69<=0.95,"B","C"))) -> C | G69: =VLOOKUP(B$4:B$104,I$4:M$104,5,0) -> C | I69: ww 8010 черные | J69: ='Юнит 18'!U51 -> 0 | K69: =J69/J$106 -> 0 | L69: =L68+K69 -> 0.99623588 | M69: =_xlfn.IFS(L69<80%,"A",L69<=95%,"B",L69>95%,"C") -> C
B70: 1022_коричневые_тест | C70: ='Юнит 18'!AO103 -> 0 | D70: =C70/C$106 -> 0 | E70: =E69+D70 -> 1.0170236 | F70: =IF(AND(E70<=0),"C",IF(E70<=0.8,"A",IF(E70<=0.95,"B","C"))) -> C | G70: =VLOOKUP(B$4:B$104,I$4:M$104,5,0) -> #N/A | I70: WW 3055 коричневый | J70: ='Юнит 18'!U53 -> 0 | K70: =J70/J$106 -> 0 | L70: =L69+K70 -> 0.99623588 | M70: =_xlfn.IFS(L70<80%,"A",L70<=95%,"B",L70>95%,"C") -> C
B71: MANNA2121 | C71: ='Юнит 18'!AO74 -> -1.01 | D71: =C71/C$106 -> -1.6060228e-06 | E71: =E70+D71 -> 1.017022 | F71: =IF(AND(E71<=0),"C",IF(E71<=0.8,"A",IF(E71<=0.95,"B","C"))) -> C | G71: =VLOOKUP(B$4:B$104,I$4:M$104,5,0) -> C | I71: MANNA2102 | J71: ='Юнит 18'!U55 -> 0 | K71: =J71/J$106 -> 0 | L71: =L70+K71 -> 0.99623588 | M71: =_xlfn.IFS(L71<80%,"A",L71<=95%,"B",L71>95%,"C") -> C
B72: ww 8010 черные | C72: ='Юнит 18'!AO51 -> -1.0417377 | D72: =C72/C$106 -> -1.6564897e-06 | E72: =E71+D72 -> 1.0170203 | F72: =IF(AND(E72<=0),"C",IF(E72<=0.8,"A",IF(E72<=0.95,"B","C"))) -> C | G72: =VLOOKUP(B$4:B$104,I$4:M$104,5,0) -> C | I72: MANNA2103 | J72: ='Юнит 18'!U56 -> 0 | K72: =J72/J$106 -> 0 | L72: =L71+K72 -> 0.99623588 | M72: =_xlfn.IFS(L72<80%,"A",L72<=95%,"B",L72>95%,"C") -> C
B73: MANNA2120 | C73: ='Юнит 18'!AO73 -> -1.0417377 | D73: =C73/C$106 -> -1.6564897e-06 | E73: =E72+D73 -> 1.0170187 | F73: =IF(AND(E73<=0),"C",IF(E73<=0.8,"A",IF(E73<=0.95,"B","C"))) -> C | G73: =VLOOKUP(B$4:B$104,I$4:M$104,5,0) -> C | I73: MANNA2104 | J73: ='Юнит 18'!U57 -> 0 | K73: =J73/J$106 -> 0 | L73: =L72+K73 -> 0.99623588 | M73: =_xlfn.IFS(L73<80%,"A",L73<=95%,"B",L73>95%,"C") -> C
B74: Иу Диту серый | C74: ='Юнит 18'!AO91 -> -1.5246299 | D74: =C74/C$106 -> -2.424347e-06 | E74: =E73+D74 -> 1.0170163 | F74: =IF(AND(E74<=0),"C",IF(E74<=0.8,"A",IF(E74<=0.95,"B","C"))) -> C | G74: =VLOOKUP(B$4:B$104,I$4:M$104,5,0) -> C | I74: MANNA2106 | J74: ='Юнит 18'!U59 -> 0 | K74: =J74/J$106 -> 0 | L74: =L73+K74 -> 0.99623588 | M74: =_xlfn.IFS(L74<80%,"A",L74<=95%,"B",L74>95%,"C") -> C
B75: Linhai Baiyi розовая линза | C75: ='Юнит 18'!AO88 -> -1.75 | D75: =C75/C$106 -> -2.7827128e-06 | E75: =E74+D75 -> 1.0170135 | F75: =IF(AND(E75<=0),"C",IF(E75<=0.8,"A",IF(E75<=0.95,"B","C"))) -> C | G75: =VLOOKUP(B$4:B$104,I$4:M$104,5,0) -> C | I75: MANNA2107 | J75: ='Юнит 18'!U60 -> 0 | K75: =J75/J$106 -> 0 | L75: =L74+K75 -> 0.99623588 | M75: =_xlfn.IFS(L75<80%,"A",L75<=95%,"B",L75>95%,"C") -> C
B76: MANNA2113 | C76: ='Юнит 18'!AO66 -> -2.0834754 | D76: =C76/C$106 -> -3.3129794e-06 | E76: =E49+D76 -> 1.0170203 | F76: =IF(AND(E76<=0),"C",IF(E76<=0.8,"A",IF(E76<=0.95,"B","C"))) -> C | G76: =VLOOKUP(B$4:B$104,I$4:M$104,5,0) -> C | I76: MANNA2108 | J76: ='Юнит 18'!U61 -> 0 | K76: =J76/J$106 -> 0 | L76: =L49+K76 -> 0.99560853 | M76: =_xlfn.IFS(L76<80%,"A",L76<=95%,"B",L76>95%,"C") -> C
B77: Hengda Optical черные | C77: ='Юнит 18'!AO81 -> -13.54259 | D77: =C77/C$106 -> -2.1534366e-05 | E77: =E76+D77 -> 1.0169988 | F77: =IF(AND(E77<=0),"C",IF(E77<=0.8,"A",IF(E77<=0.95,"B","C"))) -> C | G77: =VLOOKUP(B$4:B$104,I$4:M$104,5,0) -> C | I77: MANNA2109 | J77: ='Юнит 18'!U62 -> 0 | K77: =J77/J$106 -> 0 | L77: =L76+K77 -> 0.99560853 | M77: =_xlfn.IFS(L77<80%,"A",L77<=95%,"B",L77>95%,"C") -> C
B78: sportlife синие | C78: ='Юнит 18'!AO24 -> -26.043443 | D78: =C78/C$106 -> -4.1412242e-05 | E78: =E77+D78 -> 1.0169573 | F78: =IF(AND(E78<=0),"C",IF(E78<=0.8,"A",IF(E78<=0.95,"B","C"))) -> C | G78: =VLOOKUP(B$4:B$104,I$4:M$104,5,0) -> C | I78: MANNA2110 | J78: ='Юнит 18'!U63 -> 0 | K78: =J78/J$106 -> 0 | L78: =L77+K78 -> 0.99560853 | M78: =_xlfn.IFS(L78<80%,"A",L78<=95%,"B",L78>95%,"C") -> C
B79: sh16 | C79: ='Юнит 18'!AO40 -> -30.838656 | D79: =C79/C$106 -> -4.9037214e-05 | E79: =E78+D79 -> 1.0169083 | F79: =IF(AND(E79<=0),"C",IF(E79<=0.8,"A",IF(E79<=0.95,"B","C"))) -> C | G79: =VLOOKUP(B$4:B$104,I$4:M$104,5,0) -> C | I79: MANNA2111 | J79: ='Юнит 18'!U64 -> 0 | K79: =J79/J$106 -> 0 | L79: =L78+K79 -> 0.99560853 | M79: =_xlfn.IFS(L79<80%,"A",L79<=95%,"B",L79>95%,"C") -> C
B80: Ли Сян ретро серебро | C80: ='Юнит 18'!AO93 -> -41.396033 | D80: =C80/C$106 -> -6.5824728e-05 | E80: =E79+D80 -> 1.0168425 | F80: =IF(AND(E80<=0),"C",IF(E80<=0.8,"A",IF(E80<=0.95,"B","C"))) -> C | G80: =VLOOKUP(B$4:B$104,I$4:M$104,5,0) -> C | I80: MANNA2112 | J80: ='Юнит 18'!U65 -> 0 | K80: =J80/J$106 -> 0 | L80: =L79+K80 -> 0.99560853 | M80: =_xlfn.IFS(L80<80%,"A",L80<=95%,"B",L80>95%,"C") -> C
B81: sh17 | C81: ='Юнит 18'!AO41 -> -41.669509 | D81: =C81/C$106 -> -6.6259587e-05 | E81: =E80+D81 -> 1.0167762 | F81: =IF(AND(E81<=0),"C",IF(E81<=0.8,"A",IF(E81<=0.95,"B","C"))) -> C | G81: =VLOOKUP(B$4:B$104,I$4:M$104,5,0) -> C | I81: MANNA2113 | J81: ='Юнит 18'!U66 -> 0 | K81: =J81/J$106 -> 0 | L81: =L80+K81 -> 0.99560853 | M81: =_xlfn.IFS(L81<80%,"A",L81<=95%,"B",L81>95%,"C") -> C
B82: Taizhou Rayen sport розовый | C82: ='Юнит 18'!AO90 -> -50.003411 | D82: =C82/C$106 -> -7.9511505e-05 | E82: =E81+D82 -> 1.0166967 | F82: =IF(AND(E82<=0),"C",IF(E82<=0.8,"A",IF(E82<=0.95,"B","C"))) -> C | G82: =VLOOKUP(B$4:B$104,I$4:M$104,5,0) -> C | I82: MANNA2114 | J82: ='Юнит 18'!U67 -> 0 | K82: =J82/J$106 -> 0 | L82: =L81+K82 -> 0.99560853 | M82: =_xlfn.IFS(L82<80%,"A",L82<=95%,"B",L82>95%,"C") -> C
B83: MANNA2122 | C83: ='Юнит 18'!AO75 -> -50.558913 | D83: =C83/C$106 -> -8.0394821e-05 | E83: =E82+D83 -> 1.0166163 | F83: =IF(AND(E83<=0),"C",IF(E83<=0.8,"A",IF(E83<=0.95,"B","C"))) -> C | G83: =VLOOKUP(B$4:B$104,I$4:M$104,5,0) -> C | I83: MANNA2115 | J83: ='Юнит 18'!U68 -> 0 | K83: =J83/J$106 -> 0 | L83: =L82+K83 -> 0.99560853 | M83: =_xlfn.IFS(L83<80%,"A",L83<=95%,"B",L83>95%,"C") -> C
B84: POMILED 08247 C4-08 | C84: ='Юнит 18'!AO97 -> -79.47 | D84: =C84/C$106 -> -0.00012636697 | E84: =E83+D84 -> 1.0164899 | F84: =IF(AND(E84<=0),"C",IF(E84<=0.8,"A",IF(E84<=0.95,"B","C"))) -> C | G84: =VLOOKUP(B$4:B$104,I$4:M$104,5,0) -> C | I84: MANNA2116 | J84: ='Юнит 18'!U69 -> 0 | K84: =J84/J$106 -> 0 | L84: =L83+K84 -> 0.99560853 | M84: =_xlfn.IFS(L84<80%,"A",L84<=95%,"B",L84>95%,"C") -> C
B85: sh19 | C85: ='Юнит 18'!AO43 -> -81.56 | D85: =C85/C$106 -> -0.00012969032 | E85: =E84+D85 -> 1.0163603 | F85: =IF(AND(E85<=0),"C",IF(E85<=0.8,"A",IF(E85<=0.95,"B","C"))) -> C | G85: =VLOOKUP(B$4:B$104,I$4:M$104,5,0) -> C | I85: MANNA2117 | J85: ='Юнит 18'!U70 -> 0 | K85: =J85/J$106 -> 0 | L85: =L84+K85 -> 0.99560853 | M85: =_xlfn.IFS(L85<80%,"A",L85<=95%,"B",L85>95%,"C") -> C
B86: sh2 | C86: ='Юнит 18'!AO27 -> -88.98 | D86: =C86/C$106 -> -0.00014148902 | E86: =E85+D86 -> 1.0162188 | F86: =IF(AND(E86<=0),"C",IF(E86<=0.8,"A",IF(E86<=0.95,"B","C"))) -> C | G86: =VLOOKUP(B$4:B$104,I$4:M$104,5,0) -> C | I86: MANNA2118 | J86: ='Юнит 18'!U71 -> 0 | K86: =J86/J$106 -> 0 | L86: =L85+K86 -> 0.99560853 | M86: =_xlfn.IFS(L86<80%,"A",L86<=95%,"B",L86>95%,"C") -> C
B87: sh14 | C87: ='Юнит 18'!AO38 -> -121.23298 | D87: =C87/C$106 -> -0.00019277519 | E87: =E86+D87 -> 1.016026 | F87: =IF(AND(E87<=0),"C",IF(E87<=0.8,"A",IF(E87<=0.95,"B","C"))) -> C | G87: =VLOOKUP(B$4:B$104,I$4:M$104,5,0) -> C | I87: MANNA2119 | J87: ='Юнит 18'!U72 -> 0 | K87: =J87/J$106 -> 0 | L87: =L86+K87 -> 0.99560853 | M87: =_xlfn.IFS(L87<80%,"A",L87<=95%,"B",L87>95%,"C") -> C
B88: MANNA2107 | C88: ='Юнит 18'!AO60 -> -122.40062 | D88: =C88/C$106 -> -0.00019463187 | E88: =E87+D88 -> 1.0158314 | F88: =IF(AND(E88<=0),"C",IF(E88<=0.8,"A",IF(E88<=0.95,"B","C"))) -> C | G88: =VLOOKUP(B$4:B$104,I$4:M$104,5,0) -> C | I88: MANNA2120 | J88: ='Юнит 18'!U73 -> 0 | K88: =J88/J$106 -> 0 | L88: =L87+K88 -> 0.99560853 | M88: =_xlfn.IFS(L88<80%,"A",L88<=95%,"B",L88>95%,"C") -> C
B89: Qianai черные | C89: ='Юнит 18'!AO83 -> -143.19125 | D89: =C89/C$106 -> -0.0002276915 | E89: =E88+D89 -> 1.0156037 | F89: =IF(AND(E89<=0),"C",IF(E89<=0.8,"A",IF(E89<=0.95,"B","C"))) -> C | G89: =VLOOKUP(B$4:B$104,I$4:M$104,5,0) -> C | I89: MANNA2121 | J89: ='Юнит 18'!U74 -> 0 | K89: =J89/J$106 -> 0 | L89: =L88+K89 -> 0.99560853 | M89: =_xlfn.IFS(L89<80%,"A",L89<=95%,"B",L89>95%,"C") -> C
B90: MR Р1894 черные | C90: ='Юнит 18'!AO89 -> -160.37348 | D90: =C90/C$106 -> -0.00025501333 | E90: =E89+D90 -> 1.0153487 | F90: =IF(AND(E90<=0),"C",IF(E90<=0.8,"A",IF(E90<=0.95,"B","C"))) -> C | G90: =VLOOKUP(B$4:B$104,I$4:M$104,5,0) -> C | I90: Chenlong коричневые | J90: ='Юнит 18'!U77 -> 0 | K90: =J90/J$106 -> 0 | L90: =L89+K90 -> 0.99560853 | M90: =_xlfn.IFS(L90<80%,"A",L90<=95%,"B",L90>95%,"C") -> C
B91: MANNA2108 | C91: ='Юнит 18'!AO61 -> -166.19282 | D91: =C91/C$106 -> -0.0002642668 | E91: =E90+D91 -> 1.0150844 | F91: =IF(AND(E91<=0),"C",IF(E91<=0.8,"A",IF(E91<=0.95,"B","C"))) -> C | G91: =VLOOKUP(B$4:B$104,I$4:M$104,5,0) -> C | I91: Chenlong белые | J91: ='Юнит 18'!U78 -> 0 | K91: =J91/J$106 -> 0 | L91: =L90+K91 -> 0.99560853 | M91: =_xlfn.IFS(L91<80%,"A",L91<=95%,"B",L91>95%,"C") -> C
B92: sh15 | C92: ='Юнит 18'!AO39 -> -170.17043 | D92: =C92/C$106 -> -0.00027059167 | E92: =E91+D92 -> 1.0148138 | F92: =IF(AND(E92<=0),"C",IF(E92<=0.8,"A",IF(E92<=0.95,"B","C"))) -> C | G92: =VLOOKUP(B$4:B$104,I$4:M$104,5,0) -> C | I92: Hengda Optical черные | J92: ='Юнит 18'!U81 -> 0 | K92: =J92/J$106 -> 0 | L92: =L91+K92 -> 0.99560853 | M92: =_xlfn.IFS(L92<80%,"A",L92<=95%,"B",L92>95%,"C") -> C
B93: MANNA2116 | C93: ='Юнит 18'!AO69 -> -235.60174 | D93: =C93/C$106 -> -0.00037463542 | E93: =E92+D93 -> 1.0144392 | F93: =IF(AND(E93<=0),"C",IF(E93<=0.8,"A",IF(E93<=0.95,"B","C"))) -> C | G93: =VLOOKUP(B$4:B$104,I$4:M$104,5,0) -> C | I93: Qianai черные | J93: ='Юнит 18'!U83 -> 0 | K93: =J93/J$106 -> 0 | L93: =L92+K93 -> 0.99560853 | M93: =_xlfn.IFS(L93<80%,"A",L93<=95%,"B",L93>95%,"C") -> C
B94: Chenlong белые | C94: ='Юнит 18'!AO78 -> -240.84564 | D94: =C94/C$106 -> -0.00038297386 | E94: =E93+D94 -> 1.0140562 | F94: =IF(AND(E94<=0),"C",IF(E94<=0.8,"A",IF(E94<=0.95,"B","C"))) -> C | G94: =VLOOKUP(B$4:B$104,I$4:M$104,5,0) -> C | I94: Qianai коричневые | J94: ='Юнит 18'!U84 -> 0 | K94: =J94/J$106 -> 0 | L94: =L93+K94 -> 0.99560853 | M94: =_xlfn.IFS(L94<80%,"A",L94<=95%,"B",L94>95%,"C") -> C
B95: sh09 | C95: ='Юнит 18'!AO33 -> -429.03515 | D95: =C95/C$106 -> -0.00068221807 | E95: =E94+D95 -> 1.013374 | F95: =IF(AND(E95<=0),"C",IF(E95<=0.8,"A",IF(E95<=0.95,"B","C"))) -> C | G95: =VLOOKUP(B$4:B$104,I$4:M$104,5,0) -> C | I95: Linhai Baiyi розовая линза | J95: ='Юнит 18'!U88 -> 0 | K95: =J95/J$106 -> 0 | L95: =L94+K95 -> 0.99560853 | M95: =_xlfn.IFS(L95<80%,"A",L95<=95%,"B",L95>95%,"C") -> C
B96: Ли Сян ретро золото | C96: ='Юнит 18'!AO92 -> -475.99818 | D96: =C96/C$106 -> -0.000756895 | E96: =E95+D96 -> 1.0126171 | F96: =IF(AND(E96<=0),"C",IF(E96<=0.8,"A",IF(E96<=0.95,"B","C"))) -> C | G96: =VLOOKUP(B$4:B$104,I$4:M$104,5,0) -> C | I96: MR Р1894 черные | J96: ='Юнит 18'!U89 -> 0 | K96: =J96/J$106 -> 0 | L96: =L95+K96 -> 0.99560853 | M96: =_xlfn.IFS(L96<80%,"A",L96<=95%,"B",L96>95%,"C") -> C
B97: Guangdu золото серая линза | C97: ='Юнит 18'!AO79 -> -539.34832 | D97: =C97/C$106 -> -0.00085762943 | E97: =E96+D97 -> 1.0117594 | F97: =IF(AND(E97<=0),"C",IF(E97<=0.8,"A",IF(E97<=0.95,"B","C"))) -> C | G97: =VLOOKUP(B$4:B$104,I$4:M$104,5,0) -> C | I97: Taizhou Rayen sport розовый | J97: ='Юнит 18'!U90 -> 0 | K97: =J97/J$106 -> 0 | L97: =L96+K97 -> 0.99560853 | M97: =_xlfn.IFS(L97<80%,"A",L97<=95%,"B",L97>95%,"C") -> C
B98: Linhai Baiyi коричневая линза | C98: ='Юнит 18'!AO86 -> -616.49828 | D98: =C98/C$106 -> -0.00098030725 | E98: =E97+D98 -> 1.0107791 | F98: =IF(AND(E98<=0),"C",IF(E98<=0.8,"A",IF(E98<=0.95,"B","C"))) -> C | G98: =VLOOKUP(B$4:B$104,I$4:M$104,5,0) -> C | I98: Ли Сян ретро серебро | J98: ='Юнит 18'!U93 -> 0 | K98: =J98/J$106 -> 0 | L98: =L97+K98 -> 0.99560853 | M98: =_xlfn.IFS(L98<80%,"A",L98<=95%,"B",L98>95%,"C") -> C
B99: WW 3055 коричневый | C99: ='Юнит 18'!AO53 -> -685.89734 | D99: =C99/C$106 -> -0.0010906602 | E99: =E93+D99 -> 1.0133485 | F99: =IF(AND(E99<=0),"C",IF(E99<=0.8,"A",IF(E99<=0.95,"B","C"))) -> C | G99: =VLOOKUP(B$4:B$104,I$4:M$104,5,0) -> C | I99: MAIERSHA 03898 C9-08 | J99: ='Юнит 18'!U94 -> 0 | K99: =J99/J$106 -> 0 | L99: =L93+K99 -> 0.99560853 | M99: =_xlfn.IFS(L99<80%,"A",L99<=95%,"B",L99>95%,"C") -> C
B100: Qianai коричневые | C100: ='Юнит 18'!AO84 -> -696.51603 | D100: =C100/C$106 -> -0.0011075452 | E100: =E94+D100 -> 1.0129486 | F100: =IF(AND(E100<=0),"C",IF(E100<=0.8,"A",IF(E100<=0.95,"B","C"))) -> C | G100: =VLOOKUP(B$4:B$104,I$4:M$104,5,0) -> C | I100: MAIERSHA 03914 C9-124 | J100: ='Юнит 18'!U95 -> 0 | K100: =J100/J$106 -> 0 | L100: =L94+K100 -> 0.99560853 | M100: =_xlfn.IFS(L100<80%,"A",L100<=95%,"B",L100>95%,"C") -> C
B101: MANNA2105 | C101: ='Юнит 18'!AO58 -> -714.32969 | D101: =C101/C$106 -> -0.0011358711 | E101: =E95+D101 -> 1.0122381 | F101: =IF(AND(E101<=0),"C",IF(E101<=0.8,"A",IF(E101<=0.95,"B","C"))) -> C | G101: =VLOOKUP(B$4:B$104,I$4:M$104,5,0) -> C | I101: MARSTON 7171 C1 | J101: ='Юнит 18'!U96 -> 0 | K101: =J101/J$106 -> 0 | L101: =L95+K101 -> 0.99560853 | M101: =_xlfn.IFS(L101<80%,"A",L101<=95%,"B",L101>95%,"C") -> C
...

Sheet АВС 17
B2: ОЧКИ
C3: Прибыль | D3: % прибыль | E3: Доля | F3: ABC прибыль | G3: ABC кол-во | J3: Кол-во | K3: % кол-во | L3: Доля | M3: ABC кол-во
B4: QS черные PZ | C4: ='Юнит 17'!AO4 -> 123838.64 | D4: =C4/C$106 -> 0.21881256 | E4: =D4 -> 0.21881256 | F4: =IF(AND(E4<=0),"C",IF(E4<=0.8,"A",IF(E4<=0.95,"B","C"))) -> A | G4: =VLOOKUP(B$4:B$104,I$4:M$104,5,0) -> A | I4: QS черные PZ | J4: ='Юнит 17'!U4 -> 327 | K4: =J4/J$106 -> 0.19292035 | L4: =K4 -> 0.19292035 | M4: =_xlfn.IFS(L4<80%,"A",L4<=95%,"B",L4>95%,"C") -> A | P4: A | Q4: 0.8
B5: flip коричневые | C5: ='Юнит 17'!AO16 -> 61360.969 | D5: =C5/C$106 -> 0.10841973 | E5: =E4+D5 -> 0.32723229 | F5: =IF(AND(E5<=0),"C",IF(E5<=0.8,"A",IF(E5<=0.95,"B","C"))) -> A | G5: =VLOOKUP(B$4:B$104,I$4:M$104,5,0) -> A | I5: flip черные | J5: ='Юнит 17'!U13 -> 184 | K5: =J5/J$106 -> 0.10855457 | L5: =L4+K5 -> 0.30147493 | M5: =_xlfn.IFS(L5<80%,"A",L5<=95%,"B",L5>95%,"C") -> A | P5: B | Q5: 0.15
B6: flip черные | C6: ='Юнит 17'!AO13 -> 43494.59 | D6: =C6/C$106 -> 0.076851321 | E6: =E5+D6 -> 0.40408361 | F6: =IF(AND(E6<=0),"C",IF(E6<=0.8,"A",IF(E6<=0.95,"B","C"))) -> A | G6: =VLOOKUP(B$4:B$104,I$4:M$104,5,0) -> A | I6: th черн | J6: ='Юнит 17'!U9 -> 156 | K6: =J6/J$106 -> 0.092035398 | L6: =L5+K6 -> 0.39351032 | M6: =_xlfn.IFS(L6<80%,"A",L6<=95%,"B",L6>95%,"C") -> A | P6: C | Q6: 0.05
B7: th черн | C7: ='Юнит 17'!AO9 -> 39870.964 | D7: =C7/C$106 -> 0.070448675 | E7: =E6+D7 -> 0.47453229 | F7: =IF(AND(E7<=0),"C",IF(E7<=0.8,"A",IF(E7<=0.95,"B","C"))) -> A | G7: =VLOOKUP(B$4:B$104,I$4:M$104,5,0) -> A | I7: flip коричневые | J7: ='Юнит 17'!U16 -> 135 | K7: =J7/J$106 -> 0.079646018 | L7: =L6+K7 -> 0.47315634 | M7: =_xlfn.IFS(L7<80%,"A",L7<=95%,"B",L7>95%,"C") -> A
B8: QS синие PZ | C8: ='Юнит 17'!AO5 -> 33241.337 | D8: =C8/C$106 -> 0.058734677 | E8: =E7+D8 -> 0.53326696 | F8: =IF(AND(E8<=0),"C",IF(E8<=0.8,"A",IF(E8<=0.95,"B","C"))) -> A | G8: =VLOOKUP(B$4:B$104,I$4:M$104,5,0) -> A | I8: th син | J8: ='Юнит 17'!U10 -> 110 | K8: =J8/J$106 -> 0.064896755 | L8: =L7+K8 -> 0.5380531 | M8: =_xlfn.IFS(L8<80%,"A",L8<=95%,"B",L8>95%,"C") -> A
B9: QS коричневые PZ | C9: ='Юнит 17'!AO7 -> 32082.786 | D9: =C9/C$106 -> 0.056687613 | E9: =E8+D9 -> 0.58995458 | F9: =IF(AND(E9<=0),"C",IF(E9<=0.8,"A",IF(E9<=0.95,"B","C"))) -> A | G9: =VLOOKUP(B$4:B$104,I$4:M$104,5,0) -> A | I9: черные с железкой классика | J9: ='Юнит 17'!U3 -> 101 | K9: =J9/J$106 -> 0.059587021 | L9: =L8+K9 -> 0.59764012 | M9: =_xlfn.IFS(L9<80%,"A",L9<=95%,"B",L9>95%,"C") -> A
B10: th коричн | C10: ='Юнит 17'!AO12 -> 31242.105 | D10: =C10/C$106 -> 0.0552022 | E10: =E9+D10 -> 0.64515678 | F10: =IF(AND(E10<=0),"C",IF(E10<=0.8,"A",IF(E10<=0.95,"B","C"))) -> A | G10: =VLOOKUP(B$4:B$104,I$4:M$104,5,0) -> A | I10: QS синие PZ | J10: ='Юнит 17'!U5 -> 89 | K10: =J10/J$106 -> 0.052507375 | L10: =L9+K10 -> 0.65014749 | M10: =_xlfn.IFS(L10<80%,"A",L10<=95%,"B",L10>95%,"C") -> A
B11: черные с железкой классика | C11: ='Юнит 17'!AO3 -> 26574.335 | D11: =C11/C$106 -> 0.046954639 | E11: =E10+D11 -> 0.69211141 | F11: =IF(AND(E11<=0),"C",IF(E11<=0.8,"A",IF(E11<=0.95,"B","C"))) -> A | G11: =VLOOKUP(B$4:B$104,I$4:M$104,5,0) -> A | I11: th коричн | J11: ='Юнит 17'!U12 -> 77 | K11: =J11/J$106 -> 0.045427729 | L11: =L10+K11 -> 0.69557522 | M11: =_xlfn.IFS(L11<80%,"A",L11<=95%,"B",L11>95%,"C") -> A
B12: th син | C12: ='Юнит 17'!AO10 -> 23782.119 | D12: =C12/C$106 -> 0.042021026 | E12: =E11+D12 -> 0.73413244 | F12: =IF(AND(E12<=0),"C",IF(E12<=0.8,"A",IF(E12<=0.95,"B","C"))) -> A | G12: =VLOOKUP(B$4:B$104,I$4:M$104,5,0) -> A | I12: QS коричневые PZ | J12: ='Юнит 17'!U7 -> 74 | K12: =J12/J$106 -> 0.043657817 | L12: =L11+K12 -> 0.73923304 | M12: =_xlfn.IFS(L12<80%,"A",L12<=95%,"B",L12>95%,"C") -> A
B13: QS желтые PZ | C13: ='Юнит 17'!AO6 -> 22574.93 | D13: =C13/C$106 -> 0.039888023 | E13: =E12+D13 -> 0.77402046 | F13: =IF(AND(E13<=0),"C",IF(E13<=0.8,"A",IF(E13<=0.95,"B","C"))) -> A | G13: =VLOOKUP(B$4:B$104,I$4:M$104,5,0) -> B | I13: th желт | J13: ='Юнит 17'!U11 -> 60 | K13: =J13/J$106 -> 0.03539823 | L13: =L12+K13 -> 0.77463127 | M13: =_xlfn.IFS(L13<80%,"A",L13<=95%,"B",L13>95%,"C") -> A
B14: th желт | C14: ='Юнит 17'!AO11 -> 20625.479 | D14: =C14/C$106 -> 0.036443505 | E14: =E13+D14 -> 0.81046397 | F14: =IF(AND(E14<=0),"C",IF(E14<=0.8,"A",IF(E14<=0.95,"B","C"))) -> B | G14: =VLOOKUP(B$4:B$104,I$4:M$104,5,0) -> A | I14: QS желтые PZ | J14: ='Юнит 17'!U6 -> 50 | K14: =J14/J$106 -> 0.029498525 | L14: =L13+K14 -> 0.80412979 | M14: =_xlfn.IFS(L14<80%,"A",L14<=95%,"B",L14>95%,"C") -> B
B15: flip желтые | C15: ='Юнит 17'!AO15 -> 20118.65 | D15: =C15/C$106 -> 0.03554798 | E15: =E14+D15 -> 0.84601195 | F15: =IF(AND(E15<=0),"C",IF(E15<=0.8,"A",IF(E15<=0.95,"B","C"))) -> B | G15: =VLOOKUP(B$4:B$104,I$4:M$104,5,0) -> B | I15: flip желтые | J15: ='Юнит 17'!U15 -> 43 | K15: =J15/J$106 -> 0.025368732 | L15: =L14+K15 -> 0.82949853 | M15: =_xlfn.IFS(L15<80%,"A",L15<=95%,"B",L15>95%,"C") -> B
B16: ridges brand 01 | C16: ='Юнит 17'!AO104 -> 19543.819 | D16: =C16/C$106 -> 0.034532302 | E16: =E15+D16 -> 0.88054425 | F16: =IF(AND(E16<=0),"C",IF(E16<=0.8,"A",IF(E16<=0.95,"B","C"))) -> B | G16: =VLOOKUP(B$4:B$104,I$4:M$104,5,0) -> C | I16: ww 1022 коричневые | J16: ='Юнит 17'!U48 -> 30 | K16: =J16/J$106 -> 0.017699115 | L16: =L15+K16 -> 0.84719764 | M16: =_xlfn.IFS(L16<80%,"A",L16<=95%,"B",L16>95%,"C") -> B
B17: wwl8032 коричневые золото | C17: ='Юнит 17'!AO17 -> 13512.606 | D17: =C17/C$106 -> 0.023875651 | E17: =E16+D17 -> 0.9044199 | F17: =IF(AND(E17<=0),"C",IF(E17<=0.8,"A",IF(E17<=0.95,"B","C"))) -> B | G17: =VLOOKUP(B$4:B$104,I$4:M$104,5,0) -> B | I17: wwl8032 коричневые золото | J17: ='Юнит 17'!U17 -> 27 | K17: =J17/J$106 -> 0.015929204 | L17: =L16+K17 -> 0.86312684 | M17: =_xlfn.IFS(L17<80%,"A",L17<=95%,"B",L17>95%,"C") -> B
B18: ww 2018 желтые | C18: ='Юнит 17'!AO50 -> 13346.652 | D18: =C18/C$106 -> 0.023582423 | E18: =E17+D18 -> 0.92800232 | F18: =IF(AND(E18<=0),"C",IF(E18<=0.8,"A",IF(E18<=0.95,"B","C"))) -> B | G18: =VLOOKUP(B$4:B$104,I$4:M$104,5,0) -> B | I18: ww 2018 желтые | J18: ='Юнит 17'!U50 -> 26 | K18: =J18/J$106 -> 0.015339233 | L18: =L17+K18 -> 0.87846608 | M18: =_xlfn.IFS(L18<80%,"A",L18<=95%,"B",L18>95%,"C") -> B
B19: ww 1022 коричневые | C19: ='Юнит 17'!AO48 -> 13296.046 | D19: =C19/C$106 -> 0.023493007 | E19: =E18+D19 -> 0.95149533 | F19: =IF(AND(E19<=0),"C",IF(E19<=0.8,"A",IF(E19<=0.95,"B","C"))) -> C | G19: =VLOOKUP(B$4:B$104,I$4:M$104,5,0) -> B | I19: ww 2018 черные | J19: ='Юнит 17'!U49 -> 23 | K19: =J19/J$106 -> 0.013569322 | L19: =L18+K19 -> 0.8920354 | M19: =_xlfn.IFS(L19<80%,"A",L19<=95%,"B",L19>95%,"C") -> B
B20: ww 2018 черные | C20: ='Юнит 17'!AO49 -> 10258.196 | D20: =C20/C$106 -> 0.018125379 | E20: =E19+D20 -> 0.96962071 | F20: =IF(AND(E20<=0),"C",IF(E20<=0.8,"A",IF(E20<=0.95,"B","C"))) -> C | G20: =VLOOKUP(B$4:B$104,I$4:M$104,5,0) -> B | I20: MR8854 C2 Жен | J20: ='Юнит 17'!U8 -> 22 | K20: =J20/J$106 -> 0.012979351 | L20: =L19+K20 -> 0.90501475 | M20: =_xlfn.IFS(L20<80%,"A",L20<=95%,"B",L20>95%,"C") -> B
B21: MR8854 C2 Жен | C21: ='Юнит 17'!AO8 -> 9350.0704 | D21: =C21/C$106 -> 0.016520796 | E21: =E20+D21 -> 0.98614151 | F21: =IF(AND(E21<=0),"C",IF(E21<=0.8,"A",IF(E21<=0.95,"B","C"))) -> C | G21: =VLOOKUP(B$4:B$104,I$4:M$104,5,0) -> B | I21: flip синие | J21: ='Юнит 17'!U14 -> 22 | K21: =J21/J$106 -> 0.012979351 | L21: =L20+K21 -> 0.9179941 | M21: =_xlfn.IFS(L21<80%,"A",L21<=95%,"B",L21>95%,"C") -> B
B22: flip синие | C22: ='Юнит 17'!AO14 -> 7721.7316 | D22: =C22/C$106 -> 0.013643657 | E22: =E21+D22 -> 0.99978516 | F22: =IF(AND(E22<=0),"C",IF(E22<=0.8,"A",IF(E22<=0.95,"B","C"))) -> C | G22: =VLOOKUP(B$4:B$104,I$4:M$104,5,0) -> B | I22: sh3 | J22: ='Юнит 17'!U28 -> 21 | K22: =J22/J$106 -> 0.012389381 | L22: =L21+K22 -> 0.93038348 | M22: =_xlfn.IFS(L22<80%,"A",L22<=95%,"B",L22>95%,"C") -> B
B23: ww 203 черные | C23: ='Юнит 17'!AO44 -> 5766.4422 | D23: =C23/C$106 -> 0.010188824 | E23: =E22+D23 -> 1.009974 | F23: =IF(AND(E23<=0),"C",IF(E23<=0.8,"A",IF(E23<=0.95,"B","C"))) -> C | G23: =VLOOKUP(B$4:B$104,I$4:M$104,5,0) -> B | I23: wwl8032 хром металл | J23: ='Юнит 17'!U18 -> 18 | K23: =J23/J$106 -> 0.010619469 | L23: =L22+K23 -> 0.94100295 | M23: =_xlfn.IFS(L23<80%,"A",L23<=95%,"B",L23>95%,"C") -> B
B24: sports зеленые | C24: ='Юнит 17'!AO21 -> 2379.5724 | D24: =C24/C$106 -> 0.0042045065 | E24: =E23+D24 -> 1.0141785 | F24: =IF(AND(E24<=0),"C",IF(E24<=0.8,"A",IF(E24<=0.95,"B","C"))) -> C | G24: =VLOOKUP(B$4:B$104,I$4:M$104,5,0) -> C | I24: ww 203 черные | J24: ='Юнит 17'!U44 -> 15 | K24: =J24/J$106 -> 0.0088495575 | L24: =L23+K24 -> 0.94985251 | M24: =_xlfn.IFS(L24<80%,"A",L24<=95%,"B",L24>95%,"C") -> B
B25: sports красные | C25: ='Юнит 17'!AO22 -> 1871.2509 | D25: =C25/C$106 -> 0.0033063447 | E25: =E24+D25 -> 1.0174848 | F25: =IF(AND(E25<=0),"C",IF(E25<=0.8,"A",IF(E25<=0.95,"B","C"))) -> C | G25: =VLOOKUP(B$4:B$104,I$4:M$104,5,0) -> C | I25: ww 1022 черные | J25: ='Юнит 17'!U45 -> 15 | K25: =J25/J$106 -> 0.0088495575 | L25: =L24+K25 -> 0.95870206 | M25: =_xlfn.IFS(L25<80%,"A",L25<=95%,"B",L25>95%,"C") -> C
B26: Linhai Baiyi серая линза | C26: ='Юнит 17'!AO87 -> 1390.4106 | D26: =C26/C$106 -> 0.0024567398 | E26: =E25+D26 -> 1.0199416 | F26: =IF(AND(E26<=0),"C",IF(E26<=0.8,"A",IF(E26<=0.95,"B","C"))) -> C | G26: =VLOOKUP(B$4:B$104,I$4:M$104,5,0) -> C | I26: ridges brand 01 | J26: ='Юнит 17'!U104 -> 15 | K26: =J26/J$106 -> 0.0088495575 | L26: =L25+K26 -> 0.96755162 | M26: =_xlfn.IFS(L26<80%,"A",L26<=95%,"B",L26>95%,"C") -> C
B27: ww 1022 желтые | C27: ='Юнит 17'!AO47 -> 1268.684 | D27: =C27/C$106 -> 0.0022416591 | E27: =E26+D27 -> 1.0221832 | F27: =IF(AND(E27<=0),"C",IF(E27<=0.8,"A",IF(E27<=0.95,"B","C"))) -> C | G27: =VLOOKUP(B$4:B$104,I$4:M$104,5,0) -> C | I27: sports зеленые | J27: ='Юнит 17'!U21 -> 5 | K27: =J27/J$106 -> 0.0029498525 | L27: =L26+K27 -> 0.97050147 | M27: =_xlfn.IFS(L27<80%,"A",L27<=95%,"B",L27>95%,"C") -> C
B28: sh1 | C28: ='Юнит 17'!AO26 -> 1184.0505 | D28: =C28/C$106 -> 0.0020921187 | E28: =E27+D28 -> 1.0242754 | F28: =IF(AND(E28<=0),"C",IF(E28<=0.8,"A",IF(E28<=0.95,"B","C"))) -> C | G28: =VLOOKUP(B$4:B$104,I$4:M$104,5,0) -> C | I28: Guangdu золото серая линза | J28: ='Юнит 17'!U79 -> 5 | K28: =J28/J$106 -> 0.0029498525 | L28: =L27+K28 -> 0.97345133 | M28: =_xlfn.IFS(L28<80%,"A",L28<=95%,"B",L28>95%,"C") -> C
B29: Guangdu золото серая линза | C29: ='Юнит 17'!AO79 -> 1060.8412 | D29: =C29/C$106 -> 0.0018744182 | E29: =E28+D29 -> 1.0261498 | F29: =IF(AND(E29<=0),"C",IF(E29<=0.8,"A",IF(E29<=0.95,"B","C"))) -> C | G29: =VLOOKUP(B$4:B$104,I$4:M$104,5,0) -> C | I29: sports красные | J29: ='Юнит 17'!U22 -> 4 | K29: =J29/J$106 -> 0.002359882 | L29: =L28+K29 -> 0.97581121 | M29: =_xlfn.IFS(L29<80%,"A",L29<=95%,"B",L29>95%,"C") -> C
B30: wwl8032 хром металл | C30: ='Юнит 17'!AO18 -> 950.01894 | D30: =C30/C$106 -> 0.0016786044 | E30: =E29+D30 -> 1.0278284 | F30: =IF(AND(E30<=0),"C",IF(E30<=0.8,"A",IF(E30<=0.95,"B","C"))) -> C | G30: =VLOOKUP(B$4:B$104,I$4:M$104,5,0) -> B | I30: sh1 | J30: ='Юнит 17'!U26 -> 4 | K30: =J30/J$106 -> 0.002359882 | L30: =L29+K30 -> 0.97817109 | M30: =_xlfn.IFS(L30<80%,"A",L30<=95%,"B",L30>95%,"C") -> C
B31: sports синие | C31: ='Юнит 17'!AO20 -> 868.60638 | D31: =C31/C$106 -> 0.0015347552 | E31: =E30+D31 -> 1.0293631 | F31: =IF(AND(E31<=0),"C",IF(E31<=0.8,"A",IF(E31<=0.95,"B","C"))) -> C | G31: =VLOOKUP(B$4:B$104,I$4:M$104,5,0) -> C | I31: Linhai Baiyi серая линза | J31: ='Юнит 17'!U87 -> 4 | K31: =J31/J$106 -> 0.002359882 | L31: =L30+K31 -> 0.98053097 | M31: =_xlfn.IFS(L31<80%,"A",L31<=95%,"B",L31>95%,"C") -> C
B32: sh19 | C32: ='Юнит 17'!AO43 -> 837.1619 | D32: =C32/C$106 -> 0.0014791954 | E32: =E31+D32 -> 1.0308423 | F32: =IF(AND(E32<=0),"C",IF(E32<=0.8,"A",IF(E32<=0.95,"B","C"))) -> C | G32: =VLOOKUP(B$4:B$104,I$4:M$104,5,0) -> C | I32: ww 1022 желтые | J32: ='Юнит 17'!U47 -> 3 | K32: =J32/J$106 -> 0.0017699115 | L32: =L31+K32 -> 0.98230088 | M32: =_xlfn.IFS(L32<80%,"A",L32<=95%,"B",L32>95%,"C") -> C
B33: Linhai Baiyi коричневая линза | C33: ='Юнит 17'!AO86 -> 724.22792 | D33: =C33/C$106 -> 0.0012796505 | E33: =E32+D33 -> 1.032122 | F33: =IF(AND(E33<=0),"C",IF(E33<=0.8,"A",IF(E33<=0.95,"B","C"))) -> C | G33: =VLOOKUP(B$4:B$104,I$4:M$104,5,0) -> C | I33: кс_черные_женские | J33: ='Юнит 17'!U102 -> 3 | K33: =J33/J$106 -> 0.0017699115 | L33: =L32+K33 -> 0.9840708 | M33: =_xlfn.IFS(L33<80%,"A",L33<=95%,"B",L33>95%,"C") -> C
B34: кс_черные_женские | C34: ='Юнит 17'!AO102 -> 703.48998 | D34: =C34/C$106 -> 0.0012430083 | E34: =E33+D34 -> 1.033365 | F34: =IF(AND(E34<=0),"C",IF(E34<=0.8,"A",IF(E34<=0.95,"B","C"))) -> C | G34: =VLOOKUP(B$4:B$104,I$4:M$104,5,0) -> C | I34: sports синие | J34: ='Юнит 17'!U20 -> 2 | K34: =J34/J$106 -> 0.001179941 | L34: =L33+K34 -> 0.98525074 | M34: =_xlfn.IFS(L34<80%,"A",L34<=95%,"B",L34>95%,"C") -> C
B35: MR Р1894 черные | C35: ='Юнит 17'!AO89 -> 575.79849 | D35: =C35/C$106 -> 0.001017388 | E35: =E34+D35 -> 1.0343824 | F35: =IF(AND(E35<=0),"C",IF(E35<=0.8,"A",IF(E35<=0.95,"B","C"))) -> C | G35: =VLOOKUP(B$4:B$104,I$4:M$104,5,0) -> C | I35: sh09 | J35: ='Юнит 17'!U33 -> 2 | K35: =J35/J$106 -> 0.001179941 | L35: =L34+K35 -> 0.98643068 | M35: =_xlfn.IFS(L35<80%,"A",L35<=95%,"B",L35>95%,"C") -> C
B36: sh09 | C36: ='Юнит 17'!AO33 -> 521.2412 | D36: =C36/C$106 -> 0.00092098984 | E36: =E35+D36 -> 1.0353034 | F36: =IF(AND(E36<=0),"C",IF(E36<=0.8,"A",IF(E36<=0.95,"B","C"))) -> C | G36: =VLOOKUP(B$4:B$104,I$4:M$104,5,0) -> C | I36: sh19 | J36: ='Юнит 17'!U43 -> 2 | K36: =J36/J$106 -> 0.001179941 | L36: =L35+K36 -> 0.98761062 | M36: =_xlfn.IFS(L36<80%,"A",L36<=95%,"B",L36>95%,"C") -> C
B37: ЧСЖ_женские | C37: ='Юнит 17'!AO100 -> 380.49118 | D37: =C37/C$106 -> 0.00067229626 | E37: =E36+D37 -> 1.0359757 | F37: =IF(AND(E37<=0),"C",IF(E37<=0.8,"A",IF(E37<=0.95,"B","C"))) -> C | G37: =VLOOKUP(B$4:B$104,I$4:M$104,5,0) -> C | I37: Linhai Baiyi коричневая линза | J37: ='Юнит 17'!U86 -> 2 | K37: =J37/J$106 -> 0.001179941 | L37: =L36+K37 -> 0.98879056 | M37: =_xlfn.IFS(L37<80%,"A",L37<=95%,"B",L37>95%,"C") -> C
B38: sportlife синие | C38: ='Юнит 17'!AO24 -> 341.25256 | D38: =C38/C$106 -> 0.00060296488 | E38: =E37+D38 -> 1.0365786 | F38: =IF(AND(E38<=0),"C",IF(E38<=0.8,"A",IF(E38<=0.95,"B","C"))) -> C | G38: =VLOOKUP(B$4:B$104,I$4:M$104,5,0) -> C | I38: Ли Сян ретро золото | J38: ='Юнит 17'!U92 -> 2 | K38: =J38/J$106 -> 0.001179941 | L38: =L37+K38 -> 0.9899705 | M38: =_xlfn.IFS(L38<80%,"A",L38<=95%,"B",L38>95%,"C") -> C
B39: sh17 | C39: ='Юнит 17'!AO41 -> 301.87036 | D39: =C39/C$106 -> 0.0005333798 | E39: =E35+D39 -> 1.0349158 | F39: =IF(AND(E39<=0),"C",IF(E39<=0.8,"A",IF(E39<=0.95,"B","C"))) -> C | G39: =VLOOKUP(B$4:B$104,I$4:M$104,5,0) -> C | I39: YIMEI 2391 C1 | J39: ='Юнит 17'!U98 -> 2 | K39: =J39/J$106 -> 0.001179941 | L39: =L35+K39 -> 0.98761062 | M39: =_xlfn.IFS(L39<80%,"A",L39<=95%,"B",L39>95%,"C") -> C
B40: MANNA2107 | C40: ='Юнит 17'!AO60 -> 301.47674 | D40: =C40/C$106 -> 0.00053268431 | E40: =E39+D40 -> 1.0354484 | F40: =IF(AND(E40<=0),"C",IF(E40<=0.8,"A",IF(E40<=0.95,"B","C"))) -> C | G40: =VLOOKUP(B$4:B$104,I$4:M$104,5,0) -> C | I40: sportlife синие | J40: ='Юнит 17'!U24 -> 1 | K40: =J40/J$106 -> 0.0005899705 | L40: =L39+K40 -> 0.98820059 | M40: =_xlfn.IFS(L40<80%,"A",L40<=95%,"B",L40>95%,"C") -> C
B41: YIMEI 2391 C1 | C41: ='Юнит 17'!AO98 -> 225.18053 | D41: =C41/C$106 -> 0.00039787526 | E41: =E40+D41 -> 1.0358463 | F41: =IF(AND(E41<=0),"C",IF(E41<=0.8,"A",IF(E41<=0.95,"B","C"))) -> C | G41: =VLOOKUP(B$4:B$104,I$4:M$104,5,0) -> C | I41: sh2 | J41: ='Юнит 17'!U27 -> 1 | K41: =J41/J$106 -> 0.0005899705 | L41: =L40+K41 -> 0.98879056 | M41: =_xlfn.IFS(L41<80%,"A",L41<=95%,"B",L41>95%,"C") -> C
B42: MANNA2116 | C42: ='Юнит 17'!AO69 -> 206.1901 | D42: =C42/C$106 -> 0.00036432075 | E42: =E41+D42 -> 1.0362106 | F42: =IF(AND(E42<=0),"C",IF(E42<=0.8,"A",IF(E42<=0.95,"B","C"))) -> C | G42: =VLOOKUP(B$4:B$104,I$4:M$104,5,0) -> C | I42: sh10 | J42: ='Юнит 17'!U34 -> 1 | K42: =J42/J$106 -> 0.0005899705 | L42: =L41+K42 -> 0.98938053 | M42: =_xlfn.IFS(L42<80%,"A",L42<=95%,"B",L42>95%,"C") -> C
B43: MANNA2120 | C43: ='Юнит 17'!AO73 -> 205.75399 | D43: =C43/C$106 -> 0.00036355017 | E43: =E42+D43 -> 1.0365742 | F43: =IF(AND(E43<=0),"C",IF(E43<=0.8,"A",IF(E43<=0.95,"B","C"))) -> C | G43: =VLOOKUP(B$4:B$104,I$4:M$104,5,0) -> C | I43: sh15 | J43: ='Юнит 17'!U39 -> 1 | K43: =J43/J$106 -> 0.0005899705 | L43: =L42+K43 -> 0.9899705 | M43: =_xlfn.IFS(L43<80%,"A",L43<=95%,"B",L43>95%,"C") -> C
B44: sh15 | C44: ='Юнит 17'!AO39 -> 199.92984 | D44: =C44/C$106 -> 0.0003532594 | E44: =E43+D44 -> 1.0369274 | F44: =IF(AND(E44<=0),"C",IF(E44<=0.8,"A",IF(E44<=0.95,"B","C"))) -> C | G44: =VLOOKUP(B$4:B$104,I$4:M$104,5,0) -> C | I44: sh17 | J44: ='Юнит 17'!U41 -> 1 | K44: =J44/J$106 -> 0.0005899705 | L44: =L43+K44 -> 0.99056047 | M44: =_xlfn.IFS(L44<80%,"A",L44<=95%,"B",L44>95%,"C") -> C
B45: MANNA2101 | C45: ='Юнит 17'!AO54 -> 156.10391 | D45: =C45/C$106 -> 0.00027582261 | E45: =E44+D45 -> 1.0372033 | F45: =IF(AND(E45<=0),"C",IF(E45<=0.8,"A",IF(E45<=0.95,"B","C"))) -> C | G45: =VLOOKUP(B$4:B$104,I$4:M$104,5,0) -> C | I45: WW 3055 черный | J45: ='Юнит 17'!U52 -> 1 | K45: =J45/J$106 -> 0.0005899705 | L45: =L44+K45 -> 0.99115044 | M45: =_xlfn.IFS(L45<80%,"A",L45<=95%,"B",L45>95%,"C") -> C
B46: Chenlong белые | C46: ='Юнит 17'!AO78 -> 139.1265 | D46: =C46/C$106 -> 0.00024582495 | E46: =E45+D46 -> 1.0374491 | F46: =IF(AND(E46<=0),"C",IF(E46<=0.8,"A",IF(E46<=0.95,"B","C"))) -> C | G46: =VLOOKUP(B$4:B$104,I$4:M$104,5,0) -> C | I46: MANNA2101 | J46: ='Юнит 17'!U54 -> 1 | K46: =J46/J$106 -> 0.0005899705 | L46: =L45+K46 -> 0.99174041 | M46: =_xlfn.IFS(L46<80%,"A",L46<=95%,"B",L46>95%,"C") -> C
B47: Qianai коричневые | C47: ='Юнит 17'!AO84 -> 84.524557 | D47: =C47/C$106 -> 0.00014934786 | E47: =E46+D47 -> 1.0375984 | F47: =IF(AND(E47<=0),"C",IF(E47<=0.8,"A",IF(E47<=0.95,"B","C"))) -> C | G47: =VLOOKUP(B$4:B$104,I$4:M$104,5,0) -> C | I47: MANNA2107 | J47: ='Юнит 17'!U60 -> 1 | K47: =J47/J$106 -> 0.0005899705 | L47: =L46+K47 -> 0.99233038 | M47: =_xlfn.IFS(L47<80%,"A",L47<=95%,"B",L47>95%,"C") -> C
B48: sh10 | C48: ='Юнит 17'!AO34 -> 75.8104 | D48: =C48/C$106 -> 0.00013395067 | E48: =E47+D48 -> 1.0377324 | F48: =IF(AND(E48<=0),"C",IF(E48<=0.8,"A",IF(E48<=0.95,"B","C"))) -> C | G48: =VLOOKUP(B$4:B$104,I$4:M$104,5,0) -> C | I48: MANNA2116 | J48: ='Юнит 17'!U69 -> 1 | K48: =J48/J$106 -> 0.0005899705 | L48: =L47+K48 -> 0.99292035 | M48: =_xlfn.IFS(L48<80%,"A",L48<=95%,"B",L48>95%,"C") -> C
B49: wwl8032 черные серебро | C49: ='Юнит 17'!AO19 -> 0 | D49: =C49/C$106 -> 0 | E49: =E48+D49 -> 1.0377324 | F49: =IF(AND(E49<=0),"C",IF(E49<=0.8,"A",IF(E49<=0.95,"B","C"))) -> C | G49: =VLOOKUP(B$4:B$104,I$4:M$104,5,0) -> C | I49: MANNA2120 | J49: ='Юнит 17'!U73 -> 1 | K49: =J49/J$106 -> 0.0005899705 | L49: =L48+K49 -> 0.99351032 | M49: =_xlfn.IFS(L49<80%,"A",L49<=95%,"B",L49>95%,"C") -> C
B50: sportlife черные | C50: ='Юнит 17'!AO23 -> 0 | D50: =C50/C$106 -> 0 | E50: =E49+D50 -> 1.0377324 | F50: =IF(AND(E50<=0),"C",IF(E50<=0.8,"A",IF(E50<=0.95,"B","C"))) -> C | G50: =VLOOKUP(B$4:B$104,I$4:M$104,5,0) -> C | I50: MANNA2122 | J50: ='Юнит 17'!U75 -> 1 | K50: =J50/J$106 -> 0.0005899705 | L50: =L49+K50 -> 0.99410029 | M50: =_xlfn.IFS(L50<80%,"A",L50<=95%,"B",L50>95%,"C") -> C
B51: sportlife красные | C51: ='Юнит 17'!AO25 -> 0 | D51: =C51/C$106 -> 0 | E51: =E50+D51 -> 1.0377324 | F51: =IF(AND(E51<=0),"C",IF(E51<=0.8,"A",IF(E51<=0.95,"B","C"))) -> C | G51: =VLOOKUP(B$4:B$104,I$4:M$104,5,0) -> C | I51: Chenlong коричневые | J51: ='Юнит 17'!U77 -> 1 | K51: =J51/J$106 -> 0.0005899705 | L51: =L50+K51 -> 0.99469027 | M51: =_xlfn.IFS(L51<80%,"A",L51<=95%,"B",L51>95%,"C") -> C
B52: sh4 | C52: ='Юнит 17'!AO29 -> 0 | D52: =C52/C$106 -> 0 | E52: =E51+D52 -> 1.0377324 | F52: =IF(AND(E52<=0),"C",IF(E52<=0.8,"A",IF(E52<=0.95,"B","C"))) -> C | G52: =VLOOKUP(B$4:B$104,I$4:M$104,5,0) -> C | I52: Chenlong белые | J52: ='Юнит 17'!U78 -> 1 | K52: =J52/J$106 -> 0.0005899705 | L52: =L51+K52 -> 0.99528024 | M52: =_xlfn.IFS(L52<80%,"A",L52<=95%,"B",L52>95%,"C") -> C
B53: sh06 | C53: ='Юнит 17'!AO30 -> 0 | D53: =C53/C$106 -> 0 | E53: =E52+D53 -> 1.0377324 | F53: =IF(AND(E53<=0),"C",IF(E53<=0.8,"A",IF(E53<=0.95,"B","C"))) -> C | G53: =VLOOKUP(B$4:B$104,I$4:M$104,5,0) -> C | I53: Qianai коричневые | J53: ='Юнит 17'!U84 -> 1 | K53: =J53/J$106 -> 0.0005899705 | L53: =L52+K53 -> 0.99587021 | M53: =_xlfn.IFS(L53<80%,"A",L53<=95%,"B",L53>95%,"C") -> C
B54: sh07 | C54: ='Юнит 17'!AO31 -> 0 | D54: =C54/C$106 -> 0 | E54: =E53+D54 -> 1.0377324 | F54: =IF(AND(E54<=0),"C",IF(E54<=0.8,"A",IF(E54<=0.95,"B","C"))) -> C | G54: =VLOOKUP(B$4:B$104,I$4:M$104,5,0) -> C | I54: MR Р1894 черные | J54: ='Юнит 17'!U89 -> 1 | K54: =J54/J$106 -> 0.0005899705 | L54: =L53+K54 -> 0.99646018 | M54: =_xlfn.IFS(L54<80%,"A",L54<=95%,"B",L54>95%,"C") -> C
B55: sh08 | C55: ='Юнит 17'!AO32 -> 0 | D55: =C55/C$106 -> 0 | E55: =E54+D55 -> 1.0377324 | F55: =IF(AND(E55<=0),"C",IF(E55<=0.8,"A",IF(E55<=0.95,"B","C"))) -> C | G55: =VLOOKUP(B$4:B$104,I$4:M$104,5,0) -> C | I55: Иу Диту серый | J55: ='Юнит 17'!U91 -> 1 | K55: =J55/J$106 -> 0.0005899705 | L55: =L54+K55 -> 0.99705015 | M55: =_xlfn.IFS(L55<80%,"A",L55<=95%,"B",L55>95%,"C") -> C
B56: sh11 | C56: ='Юнит 17'!AO35 -> 0 | D56: =C56/C$106 -> 0 | E56: =E55+D56 -> 1.0377324 | F56: =IF(AND(E56<=0),"C",IF(E56<=0.8,"A",IF(E56<=0.95,"B","C"))) -> C | G56: =VLOOKUP(B$4:B$104,I$4:M$104,5,0) -> C | I56: ЧСЖ_женские | J56: ='Юнит 17'!U100 -> 1 | K56: =J56/J$106 -> 0.0005899705 | L56: =L55+K56 -> 0.99764012 | M56: =_xlfn.IFS(L56<80%,"A",L56<=95%,"B",L56>95%,"C") -> C
