Workbook

Sheet Реклама
B2: БАЛАНС | E2: СЧЕТ | H2: ПРОМОБОНУСЫ | K2: Неделя
B3: Номер документа | C3: Сумма | D3: Даты | E3: Номер документа | F3: Сумма | G3: Даты | H3: Номер документа | I3: Сумма | J3: Даты
B4: 277433850 | C4: 1376 | D4: 28-31.12 | E4: 277433847 | F4: 25829 | G4: 28-31.12 | H4: 0 | I4: 109 | J4: 29-31.12 | K4: 1
B5: 277539131 | C5: 1150 | D5: 36951 | E5: 277609313 | F5: 21489 | G5: 36982 | H5: 0 | I5: 363 | J5: 36982
B6: 279208603 | C6: 3455 | D6: 37168 | E6: 279208599 | F6: 51313 | G6: 37199 | H6: 0 | I6: 569 | J6: 37200 | K6: 2
B7: 280269091 | C7: 10268 | D7: 11-18.01 | E7: 280221209 | F7: 99763 | G7: 11-18.01 | H7: 0 | I7: 557 | J7: 12-18.01 | K7: 3
B8: 281267335 | C8: 70408 | D8: 19-25.01 | E8: 281348313 | F8: 67741 | G8: 18-25.01 | H8: 0 | I8: 195 | J8: 19-25.01 | K8: 4
B9: 282258474 | C9: 25521 | D9: 25-31.01 | E9: 282345086 | F9: 133680 | G9: 25-31.01 | H9: 0 | I9: 80 | J9: 26-31.01 | K9: 5
B10: 282365257 | C10: 1268 | D10: 46054 | E10: 282392960 | F10: 4672 | G10: 46054
B11: 283332206 | C11: 111419 | D11: 37469 | E11: 283415801 | F11: 126688 | G11: 37469 | H11: 0 | I11: 3554 | J11: 37440 | K11: 6
B12: 284423647 | C12: 145581 | D12: 08-15.02 | E12: 284416459 | F12: 138670 | G12: 08-15.02 | H12: 0 | I12: 44 | J12: 46063 | K12: 7
B13: 285348588 | C13: 50989 | D13: 15-22.02 | E13: 285348587 | F13: 265182 | G13: 15-22.02 | K13: 8
B14: 286343097 | C14: 232417 | D14: 22-28.02 | E14: 286343091 | F14: 72806 | G14: 22-28.02 | H14: 0 | I14: 26 | J14: 46081 | K14: 9
B15: 286459024 | C15: 1243 | D15: 46082 | E15: 286489905 | F15: 5815 | G15: 46082
B16: 287708507 | C16: 74484 | D16: 01.03-08.03 | E16: 287655729 | F16: 252853 | G16: 01.03-08.03 | K16: 10
B17: 288763309 | C17: 304803 | D17: 08-15.03 | E17: 288777227 | F17: 178004 | G17: 08-15.03 | H17: 0 | I17: 46 | J17: 46091 | K17: 11
B18: 289700671 | C18: 48225 | D18: 15-22.03 | E18: 289749174 | F18: 468432 | G18: 15-22.03 | K18: 12
B19: 290703200 | C19: 88346 | D19: 22-29.03 | E19: 290753220 | F19: 464760 | G19: 22-29.03 | K19: 13
K20: 14
H39: .

Sheet Сводная
B2: Период | E2: Дата поступления дс | F2: Итого к перечислению на счет, руб | G2: шт. | J2: ВБ реализовал товар (выручка с СПП) | M2: Выручка до вычета комиссии ВБ | P2: Себестоимость продаж | Q2: Логистика WB | R2: Комиссия WB | S2: Хранение WB | T2: Платная приемка WB | U2: Штрафы WB | V2: Прочие удержания WB | W2: Реклама БАЛАНС | X2: Реклама СЧЕТ | Y2: Блогеры | Z2: Налог | AA2: Прочие поступления WB | AB2: Прибыль до вычета налогов | AC2: Прибыль после вычета налогов | AD2: Итог месяц | AE2: % Cебестоимости | AF2: Маржинальность, % | AG2: Рентабельность, % | AH2: Доля рекламы, %
B3: Месяц | C3: Даты | D3: Нед | G3: Заказы | H3: Продажи | I3: Возвраты | J3: Продажи | K3: Возвраты | L3: Общая | M3: Продажи | N3: Возвраты | O3: Общая
B4: Декабрь очки | C4: 29-31.12 | D4: 1 | F4: =IFERROR(O4-SUM(Q4:W4)+AA4,0) -> 62313.298 | G4: =ДЕКАБРЬ!N100 -> 129 | H4: =ДЕКАБРЬ!S100 -> 127 | I4: =ДЕКАБРЬ!T100 -> -5 | J4: =ДЕКАБРЬ!V100 -> 118047.57 | K4: =ДЕКАБРЬ!W100 -> -6409 | L4: =IFERROR(J4+K4,0) -> 111638.57 | M4: =ДЕКАБРЬ!Y100 -> 138964.57 | N4: =ДЕКАБРЬ!Z100 -> -7526 | O4: =IFERROR(M4+N4,0) -> 131438.57 | P4: =ДЕКАБРЬ!AD100 -> 15240.45 | Q4: =ДЕКАБРЬ!AG100 -> 17381.1 | R4: =ДЕКАБРЬ!AE100 -> 48126.54 | S4: =ДЕКАБРЬ!AL100 -> 3615.9322 | T4: 1.7 | U4: =ДЕКАБРЬ!AM100 -> 0 | W4: =ДЕКАБРЬ!AH100 -> 0 | X4: =ДЕКАБРЬ!AI100 -> 0 | Y4: =ДЕКАБРЬ!AK100 -> 0 | Z4: =ДЕКАБРЬ!AN100 -> 6117.8 | AB4: =O4-SUM(P4:Y4)+AA4 -> 47072.848 | AC4: =O4-SUM(P4:Z4)+AA4 -> 40955.048 | AD4: =SUM(AC4:AC5) -> 40954.76 | AE4: =P4/O4 -> 0.11595112 | AF4: =AC4/P4 -> 2.6872597 | AG4: =AC4/O4 -> 0.31159079 | AH4: =(W4+X4+Y4)/O4 -> 0
B5: Декабрь туники | C5: 29-31.12 | D5: 1 | F5: =IFERROR(O5-SUM(Q5:W5)+AA5,0) -> -0.28775523 | G5: =ДЕКАБРЬ!N108 -> 0 | H5: =ДЕКАБРЬ!S108 -> 0 | I5: =ДЕКАБРЬ!T108 -> 0 | J5: =ДЕКАБРЬ!V108 -> 0 | K5: =ДЕКАБРЬ!W108 -> 0 | L5: =IFERROR(J5+K5,0) -> 0 | M5: =ДЕКАБРЬ!Y108 -> 0 | N5: =ДЕКАБРЬ!Z108 -> 0 | O5: =IFERROR(M5+N5,0) -> 0 | P5: =ДЕКАБРЬ!AD108 -> 0 | Q5: =ДЕКАБРЬ!AG108 -> 0 | R5: =ДЕКАБРЬ!AE108 -> 0 | S5: =ДЕКАБРЬ!AL108 -> 0.28775523 | U5: =ДЕКАБРЬ!AM108 -> 0 | W5: =ДЕКАБРЬ!AH108 -> 0 | X5: =ДЕКАБРЬ!AI108 -> 0 | Y5: =ДЕКАБРЬ!AK108 -> 0 | Z5: =ДЕКАБРЬ!AN108 -> 0 | AB5: =O5-SUM(P5:Y5)+AA5 -> -0.28775523 | AC5: =O5-SUM(P5:Z5)+AA5 -> -0.28775523 | AE5: =P5/O5 -> #DIV/0! | AF5: =AC5/P5 -> #DIV/0! | AG5: =AC5/O5 -> #DIV/0! | AH5: =(W5+X5+Y5)/O5 -> #DIV/0!
B6: Январь очки | C6: 01.01-01.02 | D6: 1-5 | F6: =IFERROR(O6-SUM(Q6:W6)+AA6,0) -> 955718.86 | G6: =ЯНВАРЬ!N100 -> 4961 | H6: =ЯНВАРЬ!S100 -> 2362 | I6: =ЯНВАРЬ!T100 -> -53 | J6: =ЯНВАРЬ!V100 -> 1728382.8 | K6: =ЯНВАРЬ!W100 -> -44657.88 | L6: =IFERROR(J6+K6,0) -> 1683724.9 | M6: =ЯНВАРЬ!Y100 -> 2303342.1 | N6: =ЯНВАРЬ!Z100 -> -58267.04 | O6: =IFERROR(M6+N6,0) -> 2245075 | P6: =ЯНВАРЬ!AD100 -> 292876.64 | Q6: =ЯНВАРЬ!AG100 -> 276475.65 | R6: =ЯНВАРЬ!AE100 -> 833669.77 | S6: =ЯНВАРЬ!AL100 -> 40333.14 | U6: =ЯНВАРЬ!AM100 -> 0 | V6: 25431.6 | W6: =ЯНВАРЬ!AH100 -> 113446 | X6: =ЯНВАРЬ!AI100 -> 404487 | Y6: =ЯНВАРЬ!AK100 -> 0 | Z6: =ЯНВАРЬ!AN100 -> 96625.98 | AB6: =O6-SUM(P6:Y6)+AA6 -> 258355.22 | AC6: =O6-SUM(P6:Z6)+AA6 -> 161729.24 | AD6: =SUM(AC6:AC8) -> 161369.85 | AE6: =P6/O6 -> 0.13045294 | AF6: =AC6/P6 -> 0.55220942 | AG6: =AC6/O6 -> 0.072037343 | AH6: =(W6+X6+Y6)/O6 -> 0.23069741
B7: Январь туники | C7: 01.01-01.02 | D7: 1-5 | F7: =IFERROR(O7-SUM(Q7:W7)+AA7,0) -> -186.4297 | G7: =ЯНВАРЬ!N108 -> 1 | H7: =ЯНВАРЬ!S108 -> 0 | I7: =ЯНВАРЬ!T108 -> 0 | J7: =ЯНВАРЬ!V108 -> 0 | K7: =ЯНВАРЬ!W108 -> 0 | L7: =IFERROR(J7+K7,0) -> 0 | M7: =ЯНВАРЬ!Y108 -> 0 | N7: =ЯНВАРЬ!Z108 -> 0 | O7: =IFERROR(M7+N7,0) -> 0 | P7: =ЯНВАРЬ!AD108 -> 0 | Q7: =ЯНВАРЬ!AG108 -> 183.22 | R7: =ЯНВАРЬ!AE108 -> 0 | S7: =ЯНВАРЬ!AL108 -> 3.209704 | U7: =ЯНВАРЬ!AM108 -> 0 | W7: =ЯНВАРЬ!AH108 -> 0 | X7: =ЯНВАРЬ!AI108 -> 0 | Y7: =ЯНВАРЬ!AK108 -> 0 | Z7: =ЯНВАРЬ!AN108 -> 0 | AB7: =O7-SUM(P7:Y7)+AA7 -> -186.4297 | AC7: =O7-SUM(P7:Z7)+AA7 -> -186.4297 | AE7: =P7/O7 -> #DIV/0! | AF7: =AC7/P7 -> #DIV/0! | AG7: =AC7/O7 -> #DIV/0! | AH7: =(W7+X7+Y7)/O7 -> #DIV/0!
B8: Январь шапки | C8: 01.01-01.02 | D8: 1-5 | F8: =IFERROR(O8-SUM(Q8:W8)+AA8,0) -> -172.96 | G8: =ЯНВАРЬ!N119 -> 0 | H8: =ЯНВАРЬ!S119 -> 0 | I8: =ЯНВАРЬ!T119 -> 0 | J8: =ЯНВАРЬ!V119 -> 0 | K8: =ЯНВАРЬ!W119 -> 0 | L8: =IFERROR(J8+K8,0) -> 0 | M8: =ЯНВАРЬ!Y119 -> 0 | N8: =ЯНВАРЬ!Z119 -> 0 | O8: =IFERROR(M8+N8,0) -> 0 | P8: =ЯНВАРЬ!AD119 -> 0 | Q8: =ЯНВАРЬ!AG119 -> 172.96 | R8: =ЯНВАРЬ!AE119 -> 0 | S8: =ЯНВАРЬ!AL119 -> 0 | U8: =ЯНВАРЬ!AM119 -> 0 | W8: =ЯНВАРЬ!AH119 -> 0 | X8: =ЯНВАРЬ!AI119 -> 0 | Y8: =ЯНВАРЬ!AK119 -> 0 | Z8: =ЯНВАРЬ!AN119 -> 0 | AB8: =O8-SUM(P8:Y8)+AA8 -> -172.96 | AC8: =O8-SUM(P8:Z8)+AA8 -> -172.96 | AE8: =P8/O8 -> #DIV/0! | AF8: =AC8/P8 -> #DIV/0! | AG8: =AC8/O8 -> #DIV/0! | AH8: =(W8+X8+Y8)/O8 -> #DIV/0!
B9: Февраль 1 очки | C9: 02-08.02 | D9: 6 | F9: =IFERROR(O9-SUM(Q9:W9)+AA9,0) -> 539419.19 | G9: ='Юнит 6'!N105 -> 2829 | H9: ='Юнит 6'!S105 -> 1418 | I9: ='Юнит 6'!T105 -> -25 | J9: ='Юнит 6'!V105 -> 894889.93 | K9: ='Юнит 6'!W105 -> -16453.5 | L9: =IFERROR(J9+K9,0) -> 878436.43 | M9: ='Юнит 6'!Y105 -> 1357375 | N9: ='Юнит 6'!Z105 -> -24887.06 | O9: =IFERROR(M9+N9,0) -> 1332487.9 | P9: ='Юнит 6'!AD105 -> 175437.39 | Q9: ='Юнит 6'!AG105 -> 153486.12 | R9: ='Юнит 6'!AE105 -> 495216.11 | S9: ='Юнит 6'!AL105 -> 8160.06 | U9: ='Юнит 6'!AM105 -> 0 | V9: =5797.44+18990 -> 24787.44 | W9: ='Юнит 6'!AH105 -> 111419 | X9: ='Юнит 6'!AI105 -> 126688 | Y9: ='Юнит 6'!AK105 -> 0 | Z9: =307190.66*O9/SUM(O$9:O$16) -> 48306.676 | AB9: =O9-SUM(P9:Y9)+AA9 -> 237293.8 | AC9: =O9-SUM(P9:Z9)+AA9 -> 188987.12 | AD9: =SUM(AC9:AC16) -> 1874018 | AE9: =P9/O9 -> 0.13166152 | AF9: =AC9/P9 -> 1.077234 | AG9: =AC9/O9 -> 0.14183027 | AH9: =(W9+X9+Y9)/O9 -> 0.17869355
B10: Февраль 1 туники | C10: 02-08.02 | D10: 6 | F10: =IFERROR(O10-SUM(Q10:W10)+AA10,0) -> 0 | G10: ='Юнит 6'!N113 -> 1 | H10: ='Юнит 6'!S113 -> 0 | I10: ='Юнит 6'!T113 -> 0 | J10: ='Юнит 6'!V113 -> 0 | K10: ='Юнит 6'!W113 -> 0 | L10: =IFERROR(J10+K10,0) -> 0 | M10: ='Юнит 6'!Y113 -> 0 | N10: ='Юнит 6'!Z113 -> 0 | O10: =IFERROR(M10+N10,0) -> 0 | P10: ='Юнит 6'!AD113 -> 0 | Q10: ='Юнит 6'!AG113 -> 0 | R10: ='Юнит 6'!AE113 -> 0 | S10: ='Юнит 6'!AL113 -> 0 | U10: ='Юнит 6'!AM113 -> 0 | W10: ='Юнит 6'!AH113 -> 0 | X10: ='Юнит 6'!AI113 -> 0 | Y10: ='Юнит 6'!AK113 -> 0 | Z10: =307190.66*O10/SUM(O$9:O$16) -> 0 | AB10: =O10-SUM(P10:Y10)+AA10 -> 0 | AC10: =O10-SUM(P10:Z10)+AA10 -> 0 | AE10: =P10/O10 -> #DIV/0! | AF10: =AC10/P10 -> #DIV/0! | AG10: =AC10/O10 -> #DIV/0! | AH10: =(W10+X10+Y10)/O10 -> #DIV/0!
B11: Февраль 2 очки | C11: 09-15.02 | D11: 7 | F11: =IFERROR(O11-SUM(Q11:W11)+AA11,0) -> 811496.75 | G11: ='Юнит 7'!N105 -> 3325 | H11: ='Юнит 7'!S105 -> 1882 | I11: ='Юнит 7'!T105 -> -40 | J11: ='Юнит 7'!V105 -> 1236743.8 | K11: ='Юнит 7'!W105 -> -26582.27 | L11: =IFERROR(J11+K11,0) -> 1210161.6 | M11: ='Юнит 7'!Y105 -> 1920260.7 | N11: ='Юнит 7'!Z105 -> -41194.47 | O11: =IFERROR(M11+N11,0) -> 1879066.2 | P11: ='Юнит 7'!AD105 -> 230374.86 | Q11: ='Юнит 7'!AG105 -> 212380.68 | R11: ='Юнит 7'!AE105 -> 695831.51 | S11: ='Юнит 7'!AL105 -> 8132.98 | T11: 30 | U11: ='Юнит 7'!AM105 -> 826 | V11: 4787.28 | W11: ='Юнит 7'!AH105 -> 145581 | X11: ='Юнит 7'!AI105 -> 138670 | Y11: ='Юнит 7'!AK105 -> 0 | Z11: =307190.66*O11/SUM(O$9:O$16) -> 68121.775 | AB11: =O11-SUM(P11:Y11)+AA11 -> 442451.89 | AC11: =O11-SUM(P11:Z11)+AA11 -> 374330.11 | AE11: =P11/O11 -> 0.12260072 | AF11: =AC11/P11 -> 1.624874 | AG11: =AC11/O11 -> 0.19921071 | AH11: =(W11+X11+Y11)/O11 -> 0.15127248
B12: Февраль 2 туники | C12: 09-15.02 | D12: 7 | F12: =IFERROR(O12-SUM(Q12:W12)+AA12,0) -> 1191.57 | G12: ='Юнит 7'!N113 -> 0 | H12: ='Юнит 7'!S113 -> 1 | I12: ='Юнит 7'!T113 -> 0 | J12: ='Юнит 7'!V113 -> 1407 | K12: ='Юнит 7'!W113 -> 0 | L12: =IFERROR(J12+K12,0) -> 1407 | M12: ='Юнит 7'!Y113 -> 2079 | N12: ='Юнит 7'!Z113 -> 0 | O12: =IFERROR(M12+N12,0) -> 2079 | P12: ='Юнит 7'!AD113 -> 579.18 | Q12: ='Юнит 7'!AG113 -> 124.34 | R12: ='Юнит 7'!AE113 -> 763.09 | S12: ='Юнит 7'!AL113 -> 0 | U12: ='Юнит 7'!AM113 -> 0 | W12: ='Юнит 7'!AH113 -> 0 | X12: ='Юнит 7'!AI113 -> 0 | Y12: ='Юнит 7'!AK113 -> 0 | Z12: =307190.66*O12/SUM(O$9:O$16) -> 75.369974 | AB12: =O12-SUM(P12:Y12)+AA12 -> 612.39 | AC12: =O12-SUM(P12:Z12)+AA12 -> 537.02003 | AE12: =P12/O12 -> 0.27858586 | AF12: =AC12/P12 -> 0.92720748 | AG12: =AC12/O12 -> 0.25830689 | AH12: =(W12+X12+Y12)/O12 -> 0
B13: Февраль 3 очки | C13: 16-22.02 | D13: 8 | F13: =IFERROR(O13-SUM(Q13:W13)+AA13,0) -> 1204943.2 | G13: ='Юнит 8'!N$105 -> 4413 | H13: ='Юнит 8'!S$105 -> 2295 | I13: ='Юнит 8'!T$105 -> -43 | J13: ='Юнит 8'!V$105 -> 1593380.1 | K13: ='Юнит 8'!W$105 -> -29254.63 | L13: =IFERROR(J13+K13,0) -> 1564125.5 | M13: ='Юнит 8'!Y$105 -> 2501418.9 | N13: ='Юнит 8'!Z$105 -> -47007.29 | O13: =IFERROR(M13+N13,0) -> 2454411.6 | P13: ='Юнит 8'!AD$105 -> 280478.83 | Q13: ='Юнит 8'!AG$105 -> 267875.33 | R13: ='Юнит 8'!AE$105 -> 918234.84 | S13: ='Юнит 8'!AL$105 -> 8623.9028 | U13: ='Юнит 8'!AM$105 -> 466 | V13: 3279.36 | W13: ='Юнит 8'!AH$105 -> 50989 | X13: ='Юнит 8'!AI$105 -> 265182 | Y13: ='Юнит 8'!AK$105 -> 0 | Z13: =307190.66*O13/SUM(O$9:O$16) -> 88979.768 | AB13: =O13-SUM(P13:Y13)+AA13 -> 659282.34 | AC13: =O13-SUM(P13:Z13)+AA13 -> 570302.57 | AE13: =P13/O13 -> 0.11427538 | AF13: =AC13/P13 -> 2.0333177 | AG13: =AC13/O13 -> 0.23235816 | AH13: =(W13+X13+Y13)/O13 -> 0.12881743
B14: Февраль 3 туники | C14: 16-22.02 | D14: 8 | F14: =IFERROR(O14-SUM(Q14:W14)+AA14,0) -> -0.86724686 | G14: ='Юнит 8'!N113 -> 0 | H14: ='Юнит 8'!S113 -> 0 | I14: ='Юнит 8'!T113 -> 0 | J14: ='Юнит 8'!V113 -> 0 | K14: ='Юнит 8'!W113 -> 0 | L14: =IFERROR(J14+K14,0) -> 0 | M14: ='Юнит 8'!Y113 -> 0 | N14: ='Юнит 8'!Z113 -> 0 | O14: =IFERROR(M14+N14,0) -> 0 | P14: ='Юнит 8'!AD113 -> 0 | Q14: ='Юнит 8'!AG113 -> 0 | R14: ='Юнит 8'!AE113 -> 0 | S14: ='Юнит 8'!AL113 -> 0.86724686 | U14: ='Юнит 8'!AM113 -> 0 | W14: ='Юнит 8'!AH113 -> 0 | X14: ='Юнит 8'!AI113 -> 0 | Y14: ='Юнит 8'!AK113 -> 0 | Z14: =307190.66*O14/SUM(O$9:O$16) -> 0 | AB14: =O14-SUM(P14:Y14)+AA14 -> -0.86724686 | AC14: =O14-SUM(P14:Z14)+AA14 -> -0.86724686 | AE14: =P14/O14 -> #DIV/0! | AF14: =AC14/P14 -> #DIV/0! | AG14: =AC14/O14 -> #DIV/0! | AH14: =(W14+X14+Y14)/O14 -> #DIV/0!
B15: Февраль 4 очки | C15: 23.02-01.03 | D15: 9 | F15: =IFERROR(O15-SUM(Q15:W15)+AA15,0) -> 1208387.9 | G15: ='Юнит 9'!N$105 -> 3950 | H15: ='Юнит 9'!S$105 -> 2372 | I15: ='Юнит 9'!T$105 -> -63 | J15: ='Юнит 9'!V$105 -> 1818463.8 | K15: ='Юнит 9'!W$105 -> -46702.77 | L15: =IFERROR(J15+K15,0) -> 1771761 | M15: ='Юнит 9'!Y$105 -> 2879025.2 | N15: ='Юнит 9'!Z$105 -> -73544.64 | O15: =IFERROR(M15+N15,0) -> 2805480.6 | P15: ='Юнит 9'!AD$105 -> 288027.84 | Q15: ='Юнит 9'!AG$105 -> 299415.53 | R15: ='Юнит 9'!AE$105 -> 1051752.7 | S15: ='Юнит 9'!AL$105 -> 8471.4 | U15: ='Юнит 9'!AM$105 -> 1392.11 | V15: 2400.96 | W15: ='Юнит 9'!AH$105 -> 233660 | X15: ='Юнит 9'!AI$105 -> 78621 | Y15: ='Юнит 9'!AK$105 -> 0 | Z15: =307190.66*O15/SUM(O$9:O$16) -> 101707.07 | AB15: =O15-SUM(P15:Y15)+AA15 -> 841739.09 | AC15: =O15-SUM(P15:Z15)+AA15 -> 740032.02 | AE15: =P15/O15 -> 0.10266613 | AF15: =AC15/P15 -> 2.5693073 | AG15: =AC15/O15 -> 0.26378084 | AH15: =(W15+X15+Y15)/O15 -> 0.11131105
B16: Февраль 4 прочее | C16: 23.02-01.03 | D16: 9 | F16: =IFERROR(O16-SUM(Q16:W16)+AA16,0) -> -170 | Q16: ='Юнит 9'!AG125 -> 170 | Z16: =307190.66*O16/SUM(O$9:O$16) -> 0 | AB16: =O16-SUM(P16:Y16)+AA16 -> -170 | AC16: =O16-SUM(P16:Z16)+AA16 -> -170 | AE16: =P16/O16 -> #DIV/0! | AF16: =AC16/P16 -> #DIV/0! | AG16: =AC16/O16 -> #DIV/0! | AH16: =(W16+X16+Y16)/O16 -> #DIV/0!
B17: Март 1 очки | C17: 02-08.02 | D17: 10 | F17: =IFERROR(O17-SUM(Q17:W17)+AA17,0) -> 1238601.7 | G17: ='Юнит 10'!N$105 -> 3795 | H17: ='Юнит 10'!S$105 -> 2096 | I17: ='Юнит 10'!T$105 -> -53 | J17: ='Юнит 10'!V$105 -> 1702514.8 | K17: ='Юнит 10'!W$105 -> -41251 | L17: =IFERROR(J17+K17,0) -> 1661263.8 | M17: ='Юнит 10'!Y$105 -> 2657773.4 | N17: ='Юнит 10'!Z$105 -> -65375.4 | O17: =IFERROR(M17+N17,0) -> 2592398 | P17: ='Юнит 10'!AD$105 -> 254974.68 | Q17: ='Юнит 10'!AG$105 -> 270558.84 | R17: ='Юнит 10'!AE$105 -> 972977.25 | S17: ='Юнит 10'!AL$105 -> 11702.83 | U17: ='Юнит 10'!AM$105 -> 0 | V17: =1083.36+22990 -> 24073.36 | W17: ='Юнит 10'!AH$105 -> 74484 | X17: ='Юнит 10'!AI$105 -> 252853 | Y17: ='Юнит 10'!AK$105 -> 0 | Z17: ='Юнит 10'!AN$105 -> 94858.164 | AB17: =O17-SUM(P17:Y17)+AA17 -> 730774.06 | AC17: =O17-SUM(P17:Z17)+AA17 -> 635915.9 | AD17: =SUM(AC17:AC20) -> 5381528.3 | AE17: =P17/O17 -> 0.098354758 | AF17: =AC17/P17 -> 2.4940355 | AG17: =AC17/O17 -> 0.24530026 | AH17: =(W17+X17+Y17)/O17 -> 0.12626803
B18: Март 2 очки | C18: 09-15.02 | D18: 11 | F18: =IFERROR(O18-SUM(Q18:W18)+AA18,0) -> 2101556.8 | G18: ='Юнит 11'!N$105 -> 8243 | H18: ='Юнит 11'!S$105 -> 3480 | I18: ='Юнит 11'!T$105 -> -60 | J18: ='Юнит 11'!V$105 -> 3014405.3 | K18: ='Юнит 11'!W$105 -> -49269.89 | L18: =IFERROR(J18+K18,0) -> 2965135.4 | M18: ='Юнит 11'!Y$105 -> 4668001.6 | N18: ='Юнит 11'!Z$105 -> -76772.74 | O18: =IFERROR(M18+N18,0) -> 4591228.8 | P18: ='Юнит 11'!AD$105 -> 424325.4 | Q18: ='Юнит 11'!AG$105 -> 445765.14 | R18: ='Юнит 11'!AE$105 -> 1726243.8 | S18: ='Юнит 11'!AL$105 -> 9729.77 | U18: ='Юнит 11'!AM$105 -> 1842 | V18: 1288.32 | W18: ='Юнит 11'!AH$105 -> 304803 | X18: ='Юнит 11'!AI$105 -> 178004 | Y18: ='Юнит 11'!AK$105 -> 0 | Z18: ='Юнит 11'!AN$105 -> 169309.23 | AB18: =O18-SUM(P18:Y18)+AA18 -> 1499227.4 | AC18: =O18-SUM(P18:Z18)+AA18 -> 1329918.2 | AE18: =P18/O18 -> 0.092420878 | AF18: =AC18/P18 -> 3.1341942 | AG18: =AC18/O18 -> 0.28966498 | AH18: =(W18+X18+Y18)/O18 -> 0.10515856
B19: Март 3 очки | C19: 16-22.02 | D19: 12 | F19: =IFERROR(O19-SUM(Q19:W19)+AA19,0) -> 2992995 | G19: ='Юнит 12'!N$105 -> 6902 | H19: ='Юнит 12'!S$105 -> 4072 | I19: ='Юнит 12'!T$105 -> -94 | J19: ='Юнит 12'!V$105 -> 3910621.8 | K19: ='Юнит 12'!W$105 -> -85755 | L19: =IFERROR(J19+K19,0) -> 3824866.8 | M19: ='Юнит 12'!Y$105 -> 5914054.7 | N19: ='Юнит 12'!Z$105 -> -132706.71 | O19: =IFERROR(M19+N19,0) -> 5781348 | P19: ='Юнит 12'!AD$105 -> 494039.24 | Q19: ='Юнит 12'!AG$105 -> 557216.52 | R19: ='Юнит 12'!AE$105 -> 2176223 | S19: ='Юнит 12'!AL$105 -> 6558.48 | U19: ='Юнит 12'!AM$105 -> 130 | W19: ='Юнит 12'!AH$105 -> 48225 | X19: ='Юнит 12'!AI$105 -> 468432 | Y19: ='Юнит 12'!AK$105 -> 0 | Z19: ='Юнит 12'!AN$105 -> 218399.89 | AB19: =O19-SUM(P19:Y19)+AA19 -> 2030523.7 | AC19: =O19-SUM(P19:Z19)+AA19 -> 1812123.8 | AE19: =P19/O19 -> 0.085453988 | AF19: =AC19/P19 -> 3.6679755 | AG19: =AC19/O19 -> 0.31344313 | AH19: =(W19+X19+Y19)/O19 -> 0.089366182
B20: Март 4 очки | C20: 23-29.02 | D20: 13 | F20: =IFERROR(O20-SUM(Q20:W20)+AA20,0) -> 2696708.9 | G20: ='Юнит 13'!N$105 -> 6707 | H20: ='Юнит 13'!S$105 -> 3565 | I20: ='Юнит 13'!T$105 -> -97 | J20: ='Юнит 13'!V$105 -> 3582763.6 | K20: ='Юнит 13'!W$105 -> -97407.33 | L20: =IFERROR(J20+K20,0) -> 3485356.2 | M20: ='Юнит 13'!Y$105 -> 5387638.1 | N20: ='Юнит 13'!Z$105 -> -146145.86 | O20: =IFERROR(M20+N20,0) -> 5241492.2 | P20: ='Юнит 13'!AD$105 -> 429364.71 | Q20: ='Юнит 13'!AG$105 -> 472771.32 | R20: ='Юнит 13'!AE$105 -> 1975944.8 | S20: ='Юнит 13'!AL$105 -> 8091.54 | U20: ='Юнит 13'!AM$105 -> -1073 | V20: 702.72 | W20: ='Юнит 13'!AH$105 -> 88346 | X20: ='Юнит 13'!AI$105 -> 464760 | Y20: ='Юнит 13'!AK$105 -> 0 | Z20: ='Юнит 13'!AN$105 -> 199013.84 | AB20: =O20-SUM(P20:Y20)+AA20 -> 1802584.2 | AC20: =O20-SUM(P20:Z20)+AA20 -> 1603570.3 | AE20: =P20/O20 -> 0.081916502 | AF20: =AC20/P20 -> 3.7347512 | AG20: =AC20/O20 -> 0.30593775 | AH20: =(W20+X20+Y20)/O20 -> 0.10552453
B25: Итого | F25: =SUM(F4:F20) -> 13812803 | G25: =SUM(G4:G20) -> 45256 | H25: =SUM(H4:H20) -> 23670 | I25: =SUM(I4:I20) -> -533 | J25: =SUM(J4:J20) -> 19601620 | K25: =SUM(K4:K20) -> -443743.27 | L25: =SUM(L4:L20) -> 19157877 | M25: =SUM(M4:M20) -> 29729933 | ... AD25: =SUM(AD4:AD20) -> 7457870.9 | AE25: =P25/O25 -> 0.099314048 | AF25: =AC25/P25 -> 2.5844063 | AG25: =AC25/O25 -> 0.25666785 | AH25: =(W25+X25+Y25)/O25 -> 0.12212927
M26: % от выручки за весь период
N27: =-N25/M25 -> 0.022651487 | P27: =P25/$O$25 -> 0.099314048 | Q27: =Q25/$O$25 -> 0.10235149 | R27: =R25/$O$25 -> 0.37495848 | S27: =S25/$O$25 -> 0.0039035801 | T27: =T25/$O$25 -> 1.0909777e-06 | U27: =U25/$O$25 -> 0.00012331524 | V27: =V25/$O$25 -> 0.0029855978 | W27: =W25/$O$25 -> 0.040299167 | ... Z27: =Z25/$O$25 -> 0.037565273 | AD27: =AC25/P25 -> 2.5844063 | AE27: Маржинальность, %
W28: =(W25+X25)/O25 -> 0.12212927 | AD28: =AC25/O25 -> 0.25666785 | AE28: Рентабельность, %
B30: ЯНВАРЬ очки | G30: =G6 -> 4961 | H30: =H6 -> 2362 | I30: =I6 -> -53 | J30: =J6 -> 1728382.8 | K30: =K6 -> -44657.88 | L30: =L6 -> 1683724.9 | M30: =M6 -> 2303342.1 | N30: =N6 -> -58267.04 | ... AC30: =AC6 -> 161729.24 | AD30: =AC30/P30 -> 0.55220942
N31: =-N30/M30 -> 0.025296738 | P31: =P30/$O$30 -> 0.13045294 | Q31: =Q30/$O$30 -> 0.12314762 | R31: =R30/$O$30 -> 0.3713327 | S31: =S30/$O$30 -> 0.017965164 | T31: =T30/$O$30 -> 0 | U31: =U30/$O$30 -> 0 | V31: =V30/$O$30 -> 0.011327728 | W31: =W30/$O$30 -> 0.050531051 | ... AA31: =AA30/$O$30 -> 0 | AC31: =AC30/O30 -> 0.072037343 | AD31: =AC30/O30 -> 0.072037343
B33: 7 нед очки | P33: =P11/$O$11 -> 0.12260072 | Q33: =Q11/$O$11 -> 0.11302459 | R33: =R11/$O$11 -> 0.37030708 | S33: =S11/$O$11 -> 0.004328203 | T33: =T11/$O$11 -> 1.5965377e-05 | U33: =U11/$O$11 -> 0.00043958004 | V33: =V11/$O$11 -> 0.002547691 | W33: =W11/$O$11 -> 0.077475184 | ... AA33: =AA11/$O$11 -> 0 | AD33: =AC11/P11 -> 1.624874 | AE33: Маржинальность, %
AD34: =AC11/O11 -> 0.19921071 | AE34: Рентабельность, %
B36: ФЕВРАЛЬ очки | G36: =G9+G11+G13+G15 -> 14517 | H36: =H9+H11+H13+H15 -> 7967 | I36: =I9+I11+I13+I15 -> -171 | J36: =J9+J11+J13+J15 -> 5543477.6 | K36: =K9+K11+K13+K15 -> -118993.17 | L36: =L9+L11+L13+L15 -> 5424484.4 | M36: =M9+M11+M13+M15 -> 8658079.8 | N36: =N9+N11+N13+N15 -> -186633.46 | ... AC36: =AC9+AC11+AC13+AC15 -> 1873651.8 | AD36: =AC36/P36 -> 1.9230375
N37: =-N36/M36 -> 0.021555988 | P37: =P36/$O$36 -> 0.11501211 | Q37: =Q36/$O$36 -> 0.11015329 | R37: =R36/$O$36 -> 0.37313996 | S37: =S36/$O$36 -> 0.0039412801 | T37: =T36/$O$36 -> 3.5413079e-06 | U37: =U36/$O$36 -> 0.000316842 | V37: =V36/$O$36 -> 0.0041616317 | W37: =W36/$O$36 -> 0.063938196 | ... AA37: =AA36/$O$36 -> 0 | AC37: =AC36/O36 -> 0.2211726 | AD37: =AC36/O36 -> 0.2211726
B39: 9 нед очки | P39: =P15/$O$15 -> 0.10266613 | Q39: =Q15/$O$15 -> 0.10672522 | R39: =R15/$O$15 -> 0.37489216 | S39: =S15/$O$15 -> 0.0030195896 | T39: =T15/$O$15 -> 0 | U39: =U15/$O$15 -> 0.00049621088 | V39: =V15/$O$15 -> 0.00085581058 | W39: =W15/$O$15 -> 0.083286977 | ... AA39: =AA15/$O$15 -> 0 | AD39: =AC15/P15 -> 2.5693073 | AE39: Маржинальность, %
AD40: =AC15/O15 -> 0.26378084 | AE40: Рентабельность, %
B42: МАРТ очки | G42: =SUM(G17:G20) -> 25647 | H42: =SUM(H17:H20) -> 13213 | I42: =SUM(I17:I20) -> -304 | J42: =SUM(J17:J20) -> 12210305 | K42: =SUM(K17:K20) -> -273683.22 | L42: =SUM(L17:L20) -> 11936622 | M42: =SUM(M17:M20) -> 18627468 | N42: =SUM(N17:N20) -> -421000.71 | ... AC42: =SUM(AC17:AC20) -> 5381528.3 | AD42: =AC42/P42 -> 3.3577805 | AE42: Маржинальность, %
P43: =P42/$O$42 -> 0.088029381 | Q43: =Q42/$O$42 -> 0.095917116 | R43: =R42/$O$42 -> 0.37631622 | S43: =S42/$O$42 -> 0.0019818573 | T43: =T42/$O$42 -> 0 | U43: =U42/$O$42 -> 4.9378059e-05 | V43: =V42/$O$42 -> 0.0014316012 | W43: =W42/$O$42 -> 0.028333778 | ... AA43: =AA42/$O$42 -> 0 | AC43: =AC42/O42 -> 0.29558334 | AD43: =AC42/O42 -> 0.29558334 | AE43: Рентабельность, %

Sheet АВС 14
B2: ОЧКИ
C3: Прибыль | D3: % прибыль | E3: Доля | F3: ABC прибыль | G3: ABC кол-во | J3: Кол-во | K3: % кол-во | L3: Доля | M3: ABC кол-во
B4: черные с железкой классика | D4: =C4/C$105 -> #DIV/0! | E4: =D4 -> #DIV/0! | F4: =IF(AND(E4<=0),"C",IF(E4<=0.8,"A",IF(E4<=0.95,"B","C"))) -> #DIV/0! | G4: =VLOOKUP(B$4:B$104,I$4:M$104,5,0) -> #DIV/0! | I4: черные с железкой классика | K4: =J4/J$105 -> #DIV/0! | L4: =K4 -> #DIV/0! | M4: =_xlfn.IFS(L4<80%,"A",L4<=95%,"B",L4>95%,"C") -> #DIV/0! | P4: A | Q4: 0.8
B5: QS черные PZ | D5: =C5/C$105 -> #DIV/0! | E5: =E4+D5 -> #DIV/0! | F5: =IF(AND(E5<=0),"C",IF(E5<=0.8,"A",IF(E5<=0.95,"B","C"))) -> #DIV/0! | G5: =VLOOKUP(B$4:B$104,I$4:M$104,5,0) -> #DIV/0! | I5: QS черные PZ | K5: =J5/J$105 -> #DIV/0! | L5: =L4+K5 -> #DIV/0! | M5: =_xlfn.IFS(L5<80%,"A",L5<=95%,"B",L5>95%,"C") -> #DIV/0! | P5: B | Q5: 0.15
B6: QS синие PZ | D6: =C6/C$105 -> #DIV/0! | E6: =E5+D6 -> #DIV/0! | F6: =IF(AND(E6<=0),"C",IF(E6<=0.8,"A",IF(E6<=0.95,"B","C"))) -> #DIV/0! | G6: =VLOOKUP(B$4:B$104,I$4:M$104,5,0) -> #DIV/0! | I6: QS синие PZ | K6: =J6/J$105 -> #DIV/0! | L6: =L5+K6 -> #DIV/0! | M6: =_xlfn.IFS(L6<80%,"A",L6<=95%,"B",L6>95%,"C") -> #DIV/0! | P6: C | Q6: 0.05
B7: QS желтые PZ | D7: =C7/C$105 -> #DIV/0! | E7: =E6+D7 -> #DIV/0! | F7: =IF(AND(E7<=0),"C",IF(E7<=0.8,"A",IF(E7<=0.95,"B","C"))) -> #DIV/0! | G7: =VLOOKUP(B$4:B$104,I$4:M$104,5,0) -> #DIV/0! | I7: QS желтые PZ | K7: =J7/J$105 -> #DIV/0! | L7: =L6+K7 -> #DIV/0! | M7: =_xlfn.IFS(L7<80%,"A",L7<=95%,"B",L7>95%,"C") -> #DIV/0!
B8: QS коричневые PZ | D8: =C8/C$105 -> #DIV/0! | E8: =E7+D8 -> #DIV/0! | F8: =IF(AND(E8<=0),"C",IF(E8<=0.8,"A",IF(E8<=0.95,"B","C"))) -> #DIV/0! | G8: =VLOOKUP(B$4:B$104,I$4:M$104,5,0) -> #DIV/0! | I8: QS коричневые PZ | K8: =J8/J$105 -> #DIV/0! | L8: =L7+K8 -> #DIV/0! | M8: =_xlfn.IFS(L8<80%,"A",L8<=95%,"B",L8>95%,"C") -> #DIV/0!
B9: MR8854 C2 Жен | D9: =C9/C$105 -> #DIV/0! | E9: =E8+D9 -> #DIV/0! | F9: =IF(AND(E9<=0),"C",IF(E9<=0.8,"A",IF(E9<=0.95,"B","C"))) -> #DIV/0! | G9: =VLOOKUP(B$4:B$104,I$4:M$104,5,0) -> #DIV/0! | I9: MR8854 C2 Жен | K9: =J9/J$105 -> #DIV/0! | L9: =L8+K9 -> #DIV/0! | M9: =_xlfn.IFS(L9<80%,"A",L9<=95%,"B",L9>95%,"C") -> #DIV/0!
B10: th черн | D10: =C10/C$105 -> #DIV/0! | E10: =E9+D10 -> #DIV/0! | F10: =IF(AND(E10<=0),"C",IF(E10<=0.8,"A",IF(E10<=0.95,"B","C"))) -> #DIV/0! | G10: =VLOOKUP(B$4:B$104,I$4:M$104,5,0) -> #DIV/0! | I10: th черн | K10: =J10/J$105 -> #DIV/0! | L10: =L9+K10 -> #DIV/0! | M10: =_xlfn.IFS(L10<80%,"A",L10<=95%,"B",L10>95%,"C") -> #DIV/0!
B11: th син | D11: =C11/C$105 -> #DIV/0! | E11: =E10+D11 -> #DIV/0! | F11: =IF(AND(E11<=0),"C",IF(E11<=0.8,"A",IF(E11<=0.95,"B","C"))) -> #DIV/0! | G11: =VLOOKUP(B$4:B$104,I$4:M$104,5,0) -> #DIV/0! | I11: th син | K11: =J11/J$105 -> #DIV/0! | L11: =L10+K11 -> #DIV/0! | M11: =_xlfn.IFS(L11<80%,"A",L11<=95%,"B",L11>95%,"C") -> #DIV/0!
B12: th желт | D12: =C12/C$105 -> #DIV/0! | E12: =E11+D12 -> #DIV/0! | F12: =IF(AND(E12<=0),"C",IF(E12<=0.8,"A",IF(E12<=0.95,"B","C"))) -> #DIV/0! | G12: =VLOOKUP(B$4:B$104,I$4:M$104,5,0) -> #DIV/0! | I12: th желт | K12: =J12/J$105 -> #DIV/0! | L12: =L11+K12 -> #DIV/0! | M12: =_xlfn.IFS(L12<80%,"A",L12<=95%,"B",L12>95%,"C") -> #DIV/0!
B13: th коричн | D13: =C13/C$105 -> #DIV/0! | E13: =E12+D13 -> #DIV/0! | F13: =IF(AND(E13<=0),"C",IF(E13<=0.8,"A",IF(E13<=0.95,"B","C"))) -> #DIV/0! | G13: =VLOOKUP(B$4:B$104,I$4:M$104,5,0) -> #DIV/0! | I13: th коричн | K13: =J13/J$105 -> #DIV/0! | L13: =L12+K13 -> #DIV/0! | M13: =_xlfn.IFS(L13<80%,"A",L13<=95%,"B",L13>95%,"C") -> #DIV/0!
B14: flip черные | D14: =C14/C$105 -> #DIV/0! | E14: =E13+D14 -> #DIV/0! | F14: =IF(AND(E14<=0),"C",IF(E14<=0.8,"A",IF(E14<=0.95,"B","C"))) -> #DIV/0! | G14: =VLOOKUP(B$4:B$104,I$4:M$104,5,0) -> #DIV/0! | I14: flip черные | K14: =J14/J$105 -> #DIV/0! | L14: =L13+K14 -> #DIV/0! | M14: =_xlfn.IFS(L14<80%,"A",L14<=95%,"B",L14>95%,"C") -> #DIV/0!
B15: flip синие | D15: =C15/C$105 -> #DIV/0! | E15: =E14+D15 -> #DIV/0! | F15: =IF(AND(E15<=0),"C",IF(E15<=0.8,"A",IF(E15<=0.95,"B","C"))) -> #DIV/0! | G15: =VLOOKUP(B$4:B$104,I$4:M$104,5,0) -> #DIV/0! | I15: flip синие | K15: =J15/J$105 -> #DIV/0! | L15: =L14+K15 -> #DIV/0! | M15: =_xlfn.IFS(L15<80%,"A",L15<=95%,"B",L15>95%,"C") -> #DIV/0!
B16: flip желтые | D16: =C16/C$105 -> #DIV/0! | E16: =E15+D16 -> #DIV/0! | F16: =IF(AND(E16<=0),"C",IF(E16<=0.8,"A",IF(E16<=0.95,"B","C"))) -> #DIV/0! | G16: =VLOOKUP(B$4:B$104,I$4:M$104,5,0) -> #DIV/0! | I16: flip желтые | K16: =J16/J$105 -> #DIV/0! | L16: =L15+K16 -> #DIV/0! | M16: =_xlfn.IFS(L16<80%,"A",L16<=95%,"B",L16>95%,"C") -> #DIV/0!
B17: flip коричневые | D17: =C17/C$105 -> #DIV/0! | E17: =E16+D17 -> #DIV/0! | F17: =IF(AND(E17<=0),"C",IF(E17<=0.8,"A",IF(E17<=0.95,"B","C"))) -> #DIV/0! | G17: =VLOOKUP(B$4:B$104,I$4:M$104,5,0) -> #DIV/0! | I17: flip коричневые | K17: =J17/J$105 -> #DIV/0! | L17: =L16+K17 -> #DIV/0! | M17: =_xlfn.IFS(L17<80%,"A",L17<=95%,"B",L17>95%,"C") -> #DIV/0!
B18: wwl8032 коричневые золото | D18: =C18/C$105 -> #DIV/0! | E18: =E17+D18 -> #DIV/0! | F18: =IF(AND(E18<=0),"C",IF(E18<=0.8,"A",IF(E18<=0.95,"B","C"))) -> #DIV/0! | G18: =VLOOKUP(B$4:B$104,I$4:M$104,5,0) -> #DIV/0! | I18: wwl8032 коричневые золото | K18: =J18/J$105 -> #DIV/0! | L18: =L17+K18 -> #DIV/0! | M18: =_xlfn.IFS(L18<80%,"A",L18<=95%,"B",L18>95%,"C") -> #DIV/0!
... B38: sh13 | D38: =C38/C$105 -> #DIV/0! | E38: =E37+D38 -> #DIV/0! | F38: =IF(AND(E38<=0),"C",IF(E38<=0.8,"A",IF(E38<=0.95,"B","C"))) -> #DIV/0! | G38: =VLOOKUP(B$4:B$104,I$4:M$104,5,0) -> #DIV/0! | I38: sh13 | K38: =J38/J$105 -> #DIV/0! | L38: =L37+K38 -> #DIV/0! | M38: =_xlfn.IFS(L38<80%,"A",L38<=95%,"B",L38>95%,"C") -> #DIV/0!
B39: sh14 | D39: =C39/C$105 -> #DIV/0! | E39: =E35+D39 -> #DIV/0! | F39: =IF(AND(E39<=0),"C",IF(E39<=0.8,"A",IF(E39<=0.95,"B","C"))) -> #DIV/0! | G39: =VLOOKUP(B$4:B$104,I$4:M$104,5,0) -> #DIV/0! | I39: sh14 | K39: =J39/J$105 -> #DIV/0! | L39: =L35+K39 -> #DIV/0! | M39: =_xlfn.IFS(L39<80%,"A",L39<=95%,"B",L39>95%,"C") -> #DIV/0!
B40: sh15 | D40: =C40/C$105 -> #DIV/0! | E40: =E39+D40 -> #DIV/0! | F40: =IF(AND(E40<=0),"C",IF(E40<=0.8,"A",IF(E40<=0.95,"B","C"))) -> #DIV/0! | G40: =VLOOKUP(B$4:B$104,I$4:M$104,5,0) -> #DIV/0! | I40: sh15 | K40: =J40/J$105 -> #DIV/0! | L40: =L39+K40 -> #DIV/0! | M40: =_xlfn.IFS(L40<80%,"A",L40<=95%,"B",L40>95%,"C") -> #DIV/0!
B41: sh16 | D41: =C41/C$105 -> #DIV/0! | E41: =E40+D41 -> #DIV/0! | F41: =IF(AND(E41<=0),"C",IF(E41<=0.8,"A",IF(E41<=0.95,"B","C"))) -> #DIV/0! | G41: =VLOOKUP(B$4:B$104,I$4:M$104,5,0) -> #DIV/0! | I41: sh16 | K41: =J41/J$105 -> #DIV/0! | L41: =L40+K41 -> #DIV/0! | M41: =_xlfn.IFS(L41<80%,"A",L41<=95%,"B",L41>95%,"C") -> #DIV/0!
B42: sh17 | D42: =C42/C$105 -> #DIV/0! | E42: =E41+D42 -> #DIV/0! | F42: =IF(AND(E42<=0),"C",IF(E42<=0.8,"A",IF(E42<=0.95,"B","C"))) -> #DIV/0! | G42: =VLOOKUP(B$4:B$104,I$4:M$104,5,0) -> #DIV/0! | I42: sh17 | K42: =J42/J$105 -> #DIV/0! | L42: =L41+K42 -> #DIV/0! | M42: =_xlfn.IFS(L42<80%,"A",L42<=95%,"B",L42>95%,"C") -> #DIV/0!
B43: sh18 | D43: =C43/C$105 -> #DIV/0! | E43: =E42+D43 -> #DIV/0! | F43: =IF(AND(E43<=0),"C",IF(E43<=0.8,"A",IF(E43<=0.95,"B","C"))) -> #DIV/0! | G43: =VLOOKUP(B$4:B$104,I$4:M$104,5,0) -> #DIV/0! | I43: sh18 | K43: =J43/J$105 -> #DIV/0! | L43: =L42+K43 -> #DIV/0! | M43: =_xlfn.IFS(L43<80%,"A",L43<=95%,"B",L43>95%,"C") -> #DIV/0!
B44: sh19 | D44: =C44/C$105 -> #DIV/0! | E44: =E43+D44 -> #DIV/0! | F44: =IF(AND(E44<=0),"C",IF(E44<=0.8,"A",IF(E44<=0.95,"B","C"))) -> #DIV/0! | G44: =VLOOKUP(B$4:B$104,I$4:M$104,5,0) -> #DIV/0! | I44: sh19 | K44: =J44/J$105 -> #DIV/0! | L44: =L43+K44 -> #DIV/0! | M44: =_xlfn.IFS(L44<80%,"A",L44<=95%,"B",L44>95%,"C") -> #DIV/0!
B45: ww 203 черные | D45: =C45/C$105 -> #DIV/0! | E45: =E44+D45 -> #DIV/0! | F45: =IF(AND(E45<=0),"C",IF(E45<=0.8,"A",IF(E45<=0.95,"B","C"))) -> #DIV/0! | G45: =VLOOKUP(B$4:B$104,I$4:M$104,5,0) -> #DIV/0! | I45: ww 203 черные | K45: =J45/J$105 -> #DIV/0! | L45: =L44+K45 -> #DIV/0! | M45: =_xlfn.IFS(L45<80%,"A",L45<=95%,"B",L45>95%,"C") -> #DIV/0!
B46: ww 1022 черные | D46: =C46/C$105 -> #DIV/0! | E46: =E45+D46 -> #DIV/0! | F46: =IF(AND(E46<=0),"C",IF(E46<=0.8,"A",IF(E46<=0.95,"B","C"))) -> #DIV/0! | G46: =VLOOKUP(B$4:B$104,I$4:M$104,5,0) -> #DIV/0! | I46: ww 1022 черные | K46: =J46/J$105 -> #DIV/0! | L46: =L45+K46 -> #DIV/0! | M46: =_xlfn.IFS(L46<80%,"A",L46<=95%,"B",L46>95%,"C") -> #DIV/0!
B47: ww 1022 черн-серебро | D47: =C47/C$105 -> #DIV/0! | E47: =E46+D47 -> #DIV/0! | F47: =IF(AND(E47<=0),"C",IF(E47<=0.8,"A",IF(E47<=0.95,"B","C"))) -> #DIV/0! | G47: =VLOOKUP(B$4:B$104,I$4:M$104,5,0) -> #DIV/0! | I47: ww 1022 черн-серебро | K47: =J47/J$105 -> #DIV/0! | L47: =L46+K47 -> #DIV/0! | M47: =_xlfn.IFS(L47<80%,"A",L47<=95%,"B",L47>95%,"C") -> #DIV/0!
B48: ww 1022 желтые | D48: =C48/C$105 -> #DIV/0! | E48: =E47+D48 -> #DIV/0! | F48: =IF(AND(E48<=0),"C",IF(E48<=0.8,"A",IF(E48<=0.95,"B","C"))) -> #DIV/0! | G48: =VLOOKUP(B$4:B$104,I$4:M$104,5,0) -> #DIV/0! | I48: ww 1022 желтые | K48: =J48/J$105 -> #DIV/0! | L48: =L47+K48 -> #DIV/0! | M48: =_xlfn.IFS(L48<80%,"A",L48<=95%,"B",L48>95%,"C") -> #DIV/0!
B49: ww 1022 коричневые | D49: =C49/C$105 -> #DIV/0! | E49: =E48+D49 -> #DIV/0! | F49: =IF(AND(E49<=0),"C",IF(E49<=0.8,"A",IF(E49<=0.95,"B","C"))) -> #DIV/0! | G49: =VLOOKUP(B$4:B$104,I$4:M$104,5,0) -> #DIV/0! | I49: ww 1022 коричневые | K49: =J49/J$105 -> #DIV/0! | L49: =L48+K49 -> #DIV/0! | M49: =_xlfn.IFS(L49<80%,"A",L49<=95%,"B",L49>95%,"C") -> #DIV/0!
B50: ww 2018 черные | D50: =C50/C$105 -> #DIV/0! | E50: =E49+D50 -> #DIV/0! | F50: =IF(AND(E50<=0),"C",IF(E50<=0.8,"A",IF(E50<=0.95,"B","C"))) -> #DIV/0! | G50: =VLOOKUP(B$4:B$104,I$4:M$104,5,0) -> #DIV/0! | I50: ww 2018 черные | K50: =J50/J$105 -> #DIV/0! | L50: =L49+K50 -> #DIV/0! | M50: =_xlfn.IFS(L50<80%,"A",L50<=95%,"B",L50>95%,"C") -> #DIV/0!
B51: ww 2018 желтые | D51: =C51/C$105 -> #DIV/0! | E51: =E50+D51 -> #DIV/0! | F51: =IF(AND(E51<=0),"C",IF(E51<=0.8,"A",IF(E51<=0.95,"B","C"))) -> #DIV/0! | G51: =VLOOKUP(B$4:B$104,I$4:M$104,5,0) -> #DIV/0! | I51: ww 2018 желтые | K51: =J51/J$105 -> #DIV/0! | L51: =L50+K51 -> #DIV/0! | M51: =_xlfn.IFS(L51<80%,"A",L51<=95%,"B",L51>95%,"C") -> #DIV/0!
... B75: MANNA2121 | D75: =C75/C$105 -> #DIV/0! | E75: =E74+D75 -> #DIV/0! | F75: =IF(AND(E75<=0),"C",IF(E75<=0.8,"A",IF(E75<=0.95,"B","C"))) -> #DIV/0! | G75: =VLOOKUP(B$4:B$104,I$4:M$104,5,0) -> #DIV/0! | I75: MANNA2121 | K75: =J75/J$105 -> #DIV/0! | L75: =L74+K75 -> #DIV/0! | M75: =_xlfn.IFS(L75<80%,"A",L75<=95%,"B",L75>95%,"C") -> #DIV/0!
B76: MANNA2122 | D76: =C76/C$105 -> #DIV/0! | E76: =E49+D76 -> #DIV/0! | F76: =IF(AND(E76<=0),"C",IF(E76<=0.8,"A",IF(E76<=0.95,"B","C"))) -> #DIV/0! | G76: =VLOOKUP(B$4:B$104,I$4:M$104,5,0) -> #DIV/0! | I76: MANNA2122 | K76: =J76/J$105 -> #DIV/0! | L76: =L49+K76 -> #DIV/0! | M76: =_xlfn.IFS(L76<80%,"A",L76<=95%,"B",L76>95%,"C") -> #DIV/0!
B77: Chenlong черные | D77: =C77/C$105 -> #DIV/0! | E77: =E76+D77 -> #DIV/0! | F77: =IF(AND(E77<=0),"C",IF(E77<=0.8,"A",IF(E77<=0.95,"B","C"))) -> #DIV/0! | G77: =VLOOKUP(B$4:B$104,I$4:M$104,5,0) -> #DIV/0! | I77: Chenlong черные | K77: =J77/J$105 -> #DIV/0! | L77: =L76+K77 -> #DIV/0! | M77: =_xlfn.IFS(L77<80%,"A",L77<=95%,"B",L77>95%,"C") -> #DIV/0!
B78: Chenlong коричневые | D78: =C78/C$105 -> #DIV/0! | E78: =E77+D78 -> #DIV/0! | F78: =IF(AND(E78<=0),"C",IF(E78<=0.8,"A",IF(E78<=0.95,"B","C"))) -> #DIV/0! | G78: =VLOOKUP(B$4:B$104,I$4:M$104,5,0) -> #DIV/0! | I78: Chenlong коричневые | K78: =J78/J$105 -> #DIV/0! | L78: =L77+K78 -> #DIV/0! | M78: =_xlfn.IFS(L78<80%,"A",L78<=95%,"B",L78>95%,"C") -> #DIV/0!
B79: Chenlong белые | D79: =C79/C$105 -> #DIV/0! | E79: =E78+D79 -> #DIV/0! | F79: =IF(AND(E79<=0),"C",IF(E79<=0.8,"A",IF(E79<=0.95,"B","C"))) -> #DIV/0! | G79: =VLOOKUP(B$4:B$104,I$4:M$104,5,0) -> #DIV/0! | I79: Chenlong белые | K79: =J79/J$105 -> #DIV/0! | L79: =L78+K79 -> #DIV/0! | M79: =_xlfn.IFS(L79<80%,"A",L79<=95%,"B",L79>95%,"C") -> #DIV/0!
B80: Guangdu золото серая линза | D80: =C80/C$105 -> #DIV/0! | E80: =E79+D80 -> #DIV/0! | F80: =IF(AND(E80<=0),"C",IF(E80<=0.8,"A",IF(E80<=0.95,"B","C"))) -> #DIV/0! | G80: =VLOOKUP(B$4:B$104,I$4:M$104,5,0) -> #DIV/0! | I80: Guangdu золото серая линза | K80: =J80/J$105 -> #DIV/0! | L80: =L79+K80 -> #DIV/0! | M80: =_xlfn.IFS(L80<80%,"A",L80<=95%,"B",L80>95%,"C") -> #DIV/0!
B81: Guangdu серебро серая линза | D81: =C81/C$105 -> #DIV/0! | E81: =E80+D81 -> #DIV/0! | F81: =IF(AND(E81<=0),"C",IF(E81<=0.8,"A",IF(E81<=0.95,"B","C"))) -> #DIV/0! | G81: =VLOOKUP(B$4:B$104,I$4:M$104,5,0) -> #DIV/0! | I81: Guangdu серебро серая линза | K81: =J81/J$105 -> #DIV/0! | L81: =L80+K81 -> #DIV/0! | M81: =_xlfn.IFS(L81<80%,"A",L81<=95%,"B",L81>95%,"C") -> #DIV/0!
B82: Hengda Optical черные | D82: =C82/C$105 -> #DIV/0! | E82: =E81+D82 -> #DIV/0! | F82: =IF(AND(E82<=0),"C",IF(E82<=0.8,"A",IF(E82<=0.95,"B","C"))) -> #DIV/0! | G82: =VLOOKUP(B$4:B$104,I$4:M$104,5,0) -> #DIV/0! | I82: Hengda Optical черные | K82: =J82/J$105 -> #DIV/0! | L82: =L81+K82 -> #DIV/0! | M82: =_xlfn.IFS(L82<80%,"A",L82<=95%,"B",L82>95%,"C") -> #DIV/0!
B83: Hengda Optical леопард | D83: =C83/C$105 -> #DIV/0! | E83: =E82+D83 -> #DIV/0! | F83: =IF(AND(E83<=0),"C",IF(E83<=0.8,"A",IF(E83<=0.95,"B","C"))) -> #DIV/0! | G83: =VLOOKUP(B$4:B$104,I$4:M$104,5,0) -> #DIV/0! | I83: Hengda Optical леопард | K83: =J83/J$105 -> #DIV/0! | L83: =L82+K83 -> #DIV/0! | M83: =_xlfn.IFS(L83<80%,"A",L83<=95%,"B",L83>95%,"C") -> #DIV/0!
B84: Qianai черные | D84: =C84/C$105 -> #DIV/0! | E84: =E83+D84 -> #DIV/0! | F84: =IF(AND(E84<=0),"C",IF(E84<=0.8,"A",IF(E84<=0.95,"B","C"))) -> #DIV/0! | G84: =VLOOKUP(B$4:B$104,I$4:M$104,5,0) -> #DIV/0! | I84: Qianai черные | K84: =J84/J$105 -> #DIV/0! | L84: =L83+K84 -> #DIV/0! | M84: =_xlfn.IFS(L84<80%,"A",L84<=95%,"B",L84>95%,"C") -> #DIV/0!
B85: Qianai коричневые | D85: =C85/C$105 -> #DIV/0! | E85: =E84+D85 -> #DIV/0! | F85: =IF(AND(E85<=0),"C",IF(E85<=0.8,"A",IF(E85<=0.95,"B","C"))) -> #DIV/0! | G85: =VLOOKUP(B$4:B$104,I$4:M$104,5,0) -> #DIV/0! | I85: Qianai коричневые | K85: =J85/J$105 -> #DIV/0! | L85: =L84+K85 -> #DIV/0! | M85: =_xlfn.IFS(L85<80%,"A",L85<=95%,"B",L85>95%,"C") -> #DIV/0!
B86: Keming Aishi коричневые | D86: =C86/C$105 -> #DIV/0! | E86: =E85+D86 -> #DIV/0! | F86: =IF(AND(E86<=0),"C",IF(E86<=0.8,"A",IF(E86<=0.95,"B","C"))) -> #DIV/0! | G86: =VLOOKUP(B$4:B$104,I$4:M$104,5,0) -> #DIV/0! | I86: Keming Aishi коричневые | K86: =J86/J$105 -> #DIV/0! | L86: =L85+K86 -> #DIV/0! | M86: =_xlfn.IFS(L86<80%,"A",L86<=95%,"B",L86>95%,"C") -> #DIV/0!
B87: Linhai Baiyi коричневая линза | D87: =C87/C$105 -> #DIV/0! | E87: =E86+D87 -> #DIV/0! | F87: =IF(AND(E87<=0),"C",IF(E87<=0.8,"A",IF(E87<=0.95,"B","C"))) -> #DIV/0! | G87: =VLOOKUP(B$4:B$104,I$4:M$104,5,0) -> #DIV/0! | I87: Linhai Baiyi коричневая линза | K87: =J87/J$105 -> #DIV/0! | L87: =L86+K87 -> #DIV/0! | M87: =_xlfn.IFS(L87<80%,"A",L87<=95%,"B",L87>95%,"C") -> #DIV/0!
B88: Linhai Baiyi серая линза | D88: =C88/C$105 -> #DIV/0! | E88: =E87+D88 -> #DIV/0! | F88: =IF(AND(E88<=0),"C",IF(E88<=0.8,"A",IF(E88<=0.95,"B","C"))) -> #DIV/0! | G88: =VLOOKUP(B$4:B$104,I$4:M$104,5,0) -> #DIV/0! | I88: Linhai Baiyi серая линза | K88: =J88/J$105 -> #DIV/0! | L88: =L87+K88 -> #DIV/0! | M88: =_xlfn.IFS(L88<80%,"A",L88<=95%,"B",L88>95%,"C") -> #DIV/0!
... B98: POMILED 08247 C4-08 | D98: =C98/C$105 -> #DIV/0! | E98: =E97+D98 -> #DIV/0! | F98: =IF(AND(E98<=0),"C",IF(E98<=0.8,"A",IF(E98<=0.95,"B","C"))) -> #DIV/0! | G98: =VLOOKUP(B$4:B$104,I$4:M$104,5,0) -> #DIV/0! | I98: POMILED 08247 C4-08 | K98: =J98/J$105 -> #DIV/0! | L98: =L97+K98 -> #DIV/0! | M98: =_xlfn.IFS(L98<80%,"A",L98<=95%,"B",L98>95%,"C") -> #DIV/0!
B99: YIMEI 2391 C1 | D99: =C99/C$105 -> #DIV/0! | E99: =E93+D99 -> #DIV/0! | F99: =IF(AND(E99<=0),"C",IF(E99<=0.8,"A",IF(E99<=0.95,"B","C"))) -> #DIV/0! | G99: =VLOOKUP(B$4:B$104,I$4:M$104,5,0) -> #DIV/0! | I99: YIMEI 2391 C1 | K99: =J99/J$105 -> #DIV/0! | L99: =L93+K99 -> #DIV/0! | M99: =_xlfn.IFS(L99<80%,"A",L99<=95%,"B",L99>95%,"C") -> #DIV/0!
B100: ЧСЖ_тест | D100: =C100/C$105 -> #DIV/0! | E100: =E94+D100 -> #DIV/0! | F100: =IF(AND(E100<=0),"C",IF(E100<=0.8,"A",IF(E100<=0.95,"B","C"))) -> #DIV/0! | G100: =VLOOKUP(B$4:B$104,I$4:M$104,5,0) -> #DIV/0! | I100: ЧСЖ_тест | K100: =J100/J$105 -> #DIV/0! | L100: =L94+K100 -> #DIV/0! | M100: =_xlfn.IFS(L100<80%,"A",L100<=95%,"B",L100>95%,"C") -> #DIV/0!
B101: ЧСЖ_женские | D101: =C101/C$105 -> #DIV/0! | E101: =E95+D101 -> #DIV/0! | F101: =IF(AND(E101<=0),"C",IF(E101<=0.8,"A",IF(E101<=0.95,"B","C"))) -> #DIV/0! | G101: =VLOOKUP(B$4:B$104,I$4:M$104,5,0) -> #DIV/0! | I101: ЧСЖ_женские | K101: =J101/J$105 -> #DIV/0! | L101: =L95+K101 -> #DIV/0! | M101: =_xlfn.IFS(L101<80%,"A",L101<=95%,"B",L101>95%,"C") -> #DIV/0!
B102: кс_черные_тест | D102: =C102/C$105 -> #DIV/0! | E102: =E96+D102 -> #DIV/0! | F102: =IF(AND(E102<=0),"C",IF(E102<=0.8,"A",IF(E102<=0.95,"B","C"))) -> #DIV/0! | G102: =VLOOKUP(B$4:B$104,I$4:M$104,5,0) -> #DIV/0! | I102: кс_черные_тест | K102: =J102/J$105 -> #DIV/0! | L102: =L96+K102 -> #DIV/0! | M102: =_xlfn.IFS(L102<80%,"A",L102<=95%,"B",L102>95%,"C") -> #DIV/0!
B103: кс_черные_женские | D103: =C103/C$105 -> #DIV/0! | E103: =E97+D103 -> #DIV/0! | F103: =IF(AND(E103<=0),"C",IF(E103<=0.8,"A",IF(E103<=0.95,"B","C"))) -> #DIV/0! | G103: =VLOOKUP(B$4:B$104,I$4:M$104,5,0) -> #DIV/0! | I103: кс_черные_женские | K103: =J103/J$105 -> #DIV/0! | L103: =L97+K103 -> #DIV/0! | M103: =_xlfn.IFS(L103<80%,"A",L103<=95%,"B",L103>95%,"C") -> #DIV/0!
B104: 1022_коричневые_тест | D104: =C104/C$105 -> #DIV/0! | E104: =E98+D104 -> #DIV/0! | F104: =IF(AND(E104<=0),"C",IF(E104<=0.8,"A",IF(E104<=0.95,"B","C"))) -> #DIV/0! | G104: =VLOOKUP(B$4:B$104,I$4:M$104,5,0) -> #DIV/0! | I104: 1022_коричневые_тест | K104: =J104/J$105 -> #DIV/0! | L104: =L98+K104 -> #DIV/0! | M104: =_xlfn.IFS(L104<80%,"A",L104<=95%,"B",L104>95%,"C") -> #DIV/0!
C105: =SUM(C4:C104) -> 0 | D105: =SUM(D4:D104) -> #DIV/0! | J105: =SUM(J4:J104) -> 0 | K105: =SUM(K4:K104) -> #DIV/0!

Sheet АВС МАРТ
B2: ОЧКИ
C3: Прибыль | D3: % прибыль | E3: Доля | F3: ABC прибыль | G3: ABC кол-во | J3: Кол-во | K3: % кол-во | L3: Доля | M3: ABC кол-во
B4: QS черные PZ | C4: =МАРТ!AO4 -> 1353993.7 | D4: =C4/C$105 -> 0.25038752 | E4: =D4 -> 0.25038752 | F4: =IF(AND(E4<=0),"C",IF(E4<=0.8,"A",IF(E4<=0.95,"B","C"))) -> A | G4: =VLOOKUP(B$4:B$104,I$4:M$104,5,0) -> A | I4: QS черные PZ | J4: =МАРТ!U4 -> 2570 | K4: =J4/J$105 -> 0.19908591 | L4: =K4 -> 0.19908591 | M4: =_xlfn.IFS(L4<80%,"A",L4<=95%,"B",L4>95%,"C") -> A | P4: A | Q4: 0.8
B5: th черн | C5: =МАРТ!AO9 -> 430121.77 | D5: =C5/C$105 -> 0.079540341 | E5: =E4+D5 -> 0.32992786 | F5: =IF(AND(E5<=0),"C",IF(E5<=0.8,"A",IF(E5<=0.95,"B","C"))) -> A | G5: =VLOOKUP(B$4:B$104,I$4:M$104,5,0) -> A | I5: th черн | J5: =МАРТ!U9 -> 943 | K5: =J5/J$105 -> 0.07304981 | L5: =L4+K5 -> 0.27213572 | M5: =_xlfn.IFS(L5<80%,"A",L5<=95%,"B",L5>95%,"C") -> A | P5: B | Q5: 0.15
B6: flip черные | C6: =МАРТ!AO13 -> 417301.88 | D6: =C6/C$105 -> 0.077169621 | E6: =E5+D6 -> 0.40709749 | F6: =IF(AND(E6<=0),"C",IF(E6<=0.8,"A",IF(E6<=0.95,"B","C"))) -> A | G6: =VLOOKUP(B$4:B$104,I$4:M$104,5,0) -> A | I6: flip черные | J6: =МАРТ!U13 -> 929 | K6: =J6/J$105 -> 0.071965296 | L6: =L5+K6 -> 0.34410101 | M6: =_xlfn.IFS(L6<80%,"A",L6<=95%,"B",L6>95%,"C") -> A | P6: C | Q6: 0.05
B7: QS коричневые PZ | C7: =МАРТ!AO7 -> 396725.45 | D7: =C7/C$105 -> 0.073364521 | E7: =E6+D7 -> 0.48046201 | F7: =IF(AND(E7<=0),"C",IF(E7<=0.8,"A",IF(E7<=0.95,"B","C"))) -> A | G7: =VLOOKUP(B$4:B$104,I$4:M$104,5,0) -> A | I7: QS коричневые PZ | J7: =МАРТ!U7 -> 887 | K7: =J7/J$105 -> 0.068711751 | L7: =L6+K7 -> 0.41281277 | M7: =_xlfn.IFS(L7<80%,"A",L7<=95%,"B",L7>95%,"C") -> A
B8: flip коричневые | C8: =МАРТ!AO16 -> 357837.63 | D8: =C8/C$105 -> 0.066173185 | E8: =E7+D8 -> 0.54663519 | F8: =IF(AND(E8<=0),"C",IF(E8<=0.8,"A",IF(E8<=0.95,"B","C"))) -> A | G8: =VLOOKUP(B$4:B$104,I$4:M$104,5,0) -> A | I8: flip коричневые | J8: =МАРТ!U16 -> 821 | K8: =J8/J$105 -> 0.063599039 | L8: =L7+K8 -> 0.47641181 | M8: =_xlfn.IFS(L8<80%,"A",L8<=95%,"B",L8>95%,"C") -> A
B9: QS синие PZ | C9: =МАРТ!AO5 -> 349444.45 | D9: =C9/C$105 -> 0.064621075 | E9: =E8+D9 -> 0.61125627 | F9: =IF(AND(E9<=0),"C",IF(E9<=0.8,"A",IF(E9<=0.95,"B","C"))) -> A | G9: =VLOOKUP(B$4:B$104,I$4:M$104,5,0) -> A | I9: th син | J9: =МАРТ!U10 -> 783 | K9: =J9/J$105 -> 0.060655357 | L9: =L8+K9 -> 0.53706716 | M9: =_xlfn.IFS(L9<80%,"A",L9<=95%,"B",L9>95%,"C") -> A
B10: черные с железкой классика | C10: =МАРТ!AO3 -> 330694.75 | D10: =C10/C$105 -> 0.061153783 | E10: =E9+D10 -> 0.67241005 | F10: =IF(AND(E10<=0),"C",IF(E10<=0.8,"A",IF(E10<=0.95,"B","C"))) -> A | G10: =VLOOKUP(B$4:B$104,I$4:M$104,5,0) -> A | I10: QS синие PZ | J10: =МАРТ!U5 -> 747 | K10: =J10/J$105 -> 0.057866605 | L10: =L9+K10 -> 0.59493377 | M10: =_xlfn.IFS(L10<80%,"A",L10<=95%,"B",L10>95%,"C") -> A
B11: th син | C11: =МАРТ!AO10 -> 275911.97 | D11: =C11/C$105 -> 0.051023068 | E11: =E10+D11 -> 0.72343312 | F11: =IF(AND(E11<=0),"C",IF(E11<=0.8,"A",IF(E11<=0.95,"B","C"))) -> A | G11: =VLOOKUP(B$4:B$104,I$4:M$104,5,0) -> A | I11: черные с железкой классика | J11: =МАРТ!U3 -> 676 | K11: =J11/J$105 -> 0.052366566 | L11: =L10+K11 -> 0.64730033 | M11: =_xlfn.IFS(L11<80%,"A",L11<=95%,"B",L11>95%,"C") -> A
B12: th коричн | C12: =МАРТ!AO12 -> 244429.68 | D12: =C12/C$105 -> 0.0452012 | E12: =E11+D12 -> 0.76863432 | F12: =IF(AND(E12<=0),"C",IF(E12<=0.8,"A",IF(E12<=0.95,"B","C"))) -> A | G12: =VLOOKUP(B$4:B$104,I$4:M$104,5,0) -> A | I12: th коричн | J12: =МАРТ!U12 -> 587 | K12: =J12/J$105 -> 0.045472151 | L12: =L11+K12 -> 0.69277248 | M12: =_xlfn.IFS(L12<80%,"A",L12<=95%,"B",L12>95%,"C") -> A
B13: sh3 | C13: =МАРТ!AO28 -> 188980.39 | D13: =C13/C$105 -> 0.034947231 | E13: =E12+D13 -> 0.80358155 | F13: =IF(AND(E13<=0),"C",IF(E13<=0.8,"A",IF(E13<=0.95,"B","C"))) -> B | G13: =VLOOKUP(B$4:B$104,I$4:M$104,5,0) -> A | I13: sh3 | J13: =МАРТ!U28 -> 553 | K13: =J13/J$105 -> 0.04283833 | L13: =L12+K13 -> 0.73561081 | M13: =_xlfn.IFS(L13<80%,"A",L13<=95%,"B",L13>95%,"C") -> A
B14: QS желтые PZ | C14: =МАРТ!AO6 -> 161508.36 | D14: =C14/C$105 -> 0.02986696 | E14: =E13+D14 -> 0.83344851 | F14: =IF(AND(E14<=0),"C",IF(E14<=0.8,"A",IF(E14<=0.95,"B","C"))) -> B | G14: =VLOOKUP(B$4:B$104,I$4:M$104,5,0) -> A | I14: QS желтые PZ | J14: =МАРТ!U6 -> 407 | K14: =J14/J$105 -> 0.031528391 | L14: =L13+K14 -> 0.76713921 | M14: =_xlfn.IFS(L14<80%,"A",L14<=95%,"B",L14>95%,"C") -> A
B15: th желт | C15: =МАРТ!AO11 -> 144920.91 | D15: =C15/C$105 -> 0.026799523 | E15: =E14+D15 -> 0.86024803 | F15: =IF(AND(E15<=0),"C",IF(E15<=0.8,"A",IF(E15<=0.95,"B","C"))) -> B | G15: =VLOOKUP(B$4:B$104,I$4:M$104,5,0) -> A | I15: th желт | J15: =МАРТ!U11 -> 381 | K15: =J15/J$105 -> 0.029514292 | L15: =L14+K15 -> 0.7966535 | M15: =_xlfn.IFS(L15<80%,"A",L15<=95%,"B",L15>95%,"C") -> A
B16: wwl8032 хром металл | C16: =МАРТ!AO18 -> 113131.65 | D16: =C16/C$105 -> 0.02092089 | E16: =E15+D16 -> 0.88116892 | F16: =IF(AND(E16<=0),"C",IF(E16<=0.8,"A",IF(E16<=0.95,"B","C"))) -> B | G16: =VLOOKUP(B$4:B$104,I$4:M$104,5,0) -> B | I16: wwl8032 хром металл | J16: =МАРТ!U18 -> 290 | K16: =J16/J$105 -> 0.022464947 | L16: =L15+K16 -> 0.81911844 | M16: =_xlfn.IFS(L16<80%,"A",L16<=95%,"B",L16>95%,"C") -> B
B17: flip синие | C17: =МАРТ!AO14 -> 112101.37 | D17: =C17/C$105 -> 0.020730365 | E17: =E16+D17 -> 0.90189929 | F17: =IF(AND(E17<=0),"C",IF(E17<=0.8,"A",IF(E17<=0.95,"B","C"))) -> B | G17: =VLOOKUP(B$4:B$104,I$4:M$104,5,0) -> B | I17: flip синие | J17: =МАРТ!U14 -> 274 | K17: =J17/J$105 -> 0.021225502 | L17: =L16+K17 -> 0.84034395 | M17: =_xlfn.IFS(L17<80%,"A",L17<=95%,"B",L17>95%,"C") -> B
B18: flip желтые | C18: =МАРТ!AO15 -> 98410.12 | D18: =C18/C$105 -> 0.018198508 | E18: =E17+D18 -> 0.92009779 | F18: =IF(AND(E18<=0),"C",IF(E18<=0.8,"A",IF(E18<=0.95,"B","C"))) -> B | G18: =VLOOKUP(B$4:B$104,I$4:M$104,5,0) -> B | I18: flip желтые | J18: =МАРТ!U15 -> 222 | K18: =J18/J$105 -> 0.017197304 | L18: =L17+K18 -> 0.85754125 | M18: =_xlfn.IFS(L18<80%,"A",L18<=95%,"B",L18>95%,"C") -> B
B19: ww 1022 коричневые | C19: =МАРТ!AO48 -> 73374.246 | D19: =C19/C$105 -> 0.013568745 | E19: =E18+D19 -> 0.93366654 | F19: =IF(AND(E19<=0),"C",IF(E19<=0.8,"A",IF(E19<=0.95,"B","C"))) -> B | G19: =VLOOKUP(B$4:B$104,I$4:M$104,5,0) -> B | I19: ww 1022 коричневые | J19: =МАРТ!U48 -> 209 | K19: =J19/J$105 -> 0.016190255 | L19: =L18+K19 -> 0.87373151 | M19: =_xlfn.IFS(L19<80%,"A",L19<=95%,"B",L19>95%,"C") -> B
B20: ww 1022 черные | C20: =МАРТ!AO45 -> 69776.12 | D20: =C20/C$105 -> 0.012903361 | E20: =E19+D20 -> 0.9465699 | F20: =IF(AND(E20<=0),"C",IF(E20<=0.8,"A",IF(E20<=0.95,"B","C"))) -> B | G20: =VLOOKUP(B$4:B$104,I$4:M$104,5,0) -> B | I20: ww 2018 черные | J20: =МАРТ!U49 -> 205 | K20: =J20/J$105 -> 0.015880394 | L20: =L19+K20 -> 0.8896119 | M20: =_xlfn.IFS(L20<80%,"A",L20<=95%,"B",L20>95%,"C") -> B
B21: ww 2018 черные | C21: =МАРТ!AO49 -> 69396.753 | D21: =C21/C$105 -> 0.012833206 | E21: =E20+D21 -> 0.95940311 | F21: =IF(AND(E21<=0),"C",IF(E21<=0.8,"A",IF(E21<=0.95,"B","C"))) -> C | G21: =VLOOKUP(B$4:B$104,I$4:M$104,5,0) -> B | I21: ww 1022 черные | J21: =МАРТ!U45 -> 176 | K21: =J21/J$105 -> 0.013633899 | L21: =L20+K21 -> 0.9032458 | M21: =_xlfn.IFS(L21<80%,"A",L21<=95%,"B",L21>95%,"C") -> B
B22: MR8854 C2 Жен | C22: =МАРТ!AO8 -> 64135.703 | D22: =C22/C$105 -> 0.011860306 | E22: =E21+D22 -> 0.97126341 | F22: =IF(AND(E22<=0),"C",IF(E22<=0.8,"A",IF(E22<=0.95,"B","C"))) -> C | G22: =VLOOKUP(B$4:B$104,I$4:M$104,5,0) -> B | I22: MR8854 C2 Жен | J22: =МАРТ!U8 -> 169 | K22: =J22/J$105 -> 0.013091641 | L22: =L21+K22 -> 0.91633744 | M22: =_xlfn.IFS(L22<80%,"A",L22<=95%,"B",L22>95%,"C") -> B
B23: ww 2018 желтые | C23: =МАРТ!AO50 -> 55726.672 | D23: =C23/C$105 -> 0.010305264 | E23: =E22+D23 -> 0.98156868 | F23: =IF(AND(E23<=0),"C",IF(E23<=0.8,"A",IF(E23<=0.95,"B","C"))) -> C | G23: =VLOOKUP(B$4:B$104,I$4:M$104,5,0) -> B | I23: ww 203 черные | J23: =МАРТ!U44 -> 155 | K23: =J23/J$105 -> 0.012007127 | L23: =L22+K23 -> 0.92834457 | M23: =_xlfn.IFS(L23<80%,"A",L23<=95%,"B",L23>95%,"C") -> B
B24: ww 203 черные | C24: =МАРТ!AO44 -> 45849.038 | D24: =C24/C$105 -> 0.0084786411 | E24: =E23+D24 -> 0.99004732 | F24: =IF(AND(E24<=0),"C",IF(E24<=0.8,"A",IF(E24<=0.95,"B","C"))) -> C | G24: =VLOOKUP(B$4:B$104,I$4:M$104,5,0) -> B | I24: ww 2018 желтые | J24: =МАРТ!U50 -> 150 | K24: =J24/J$105 -> 0.0116198 | L24: =L23+K24 -> 0.93996437 | M24: =_xlfn.IFS(L24<80%,"A",L24<=95%,"B",L24>95%,"C") -> B
B25: wwl8032 коричневые золото | C25: =МАРТ!AO17 -> 43815.275 | D25: =C25/C$105 -> 0.0081025473 | E25: =E24+D25 -> 0.99814987 | F25: =IF(AND(E25<=0),"C",IF(E25<=0.8,"A",IF(E25<=0.95,"B","C"))) -> C | G25: =VLOOKUP(B$4:B$104,I$4:M$104,5,0) -> C | I25: sh1 | J25: =МАРТ!U26 -> 142 | K25: =J25/J$105 -> 0.011000077 | L25: =L24+K25 -> 0.95096444 | M25: =_xlfn.IFS(L25<80%,"A",L25<=95%,"B",L25>95%,"C") -> C
B26: ww 1022 желтые | C26: =МАРТ!AO47 -> 24769.07 | D26: =C26/C$105 -> 0.0045804246 | E26: =E25+D26 -> 1.0027303 | F26: =IF(AND(E26<=0),"C",IF(E26<=0.8,"A",IF(E26<=0.95,"B","C"))) -> C | G26: =VLOOKUP(B$4:B$104,I$4:M$104,5,0) -> C | I26: wwl8032 коричневые золото | J26: =МАРТ!U17 -> 115 | K26: =J26/J$105 -> 0.0089085134 | L26: =L25+K26 -> 0.95987296 | M26: =_xlfn.IFS(L26<80%,"A",L26<=95%,"B",L26>95%,"C") -> C
B27: sh19 | C27: =МАРТ!AO43 -> 8961.6119 | D27: =C27/C$105 -> 0.0016572276 | E27: =E26+D27 -> 1.0043875 | F27: =IF(AND(E27<=0),"C",IF(E27<=0.8,"A",IF(E27<=0.95,"B","C"))) -> C | G27: =VLOOKUP(B$4:B$104,I$4:M$104,5,0) -> C | I27: ww 1022 желтые | J27: =МАРТ!U47 -> 74 | K27: =J27/J$105 -> 0.0057324347 | L27: =L26+K27 -> 0.96560539 | M27: =_xlfn.IFS(L27<80%,"A",L27<=95%,"B",L27>95%,"C") -> C
B28: MR Р1894 черные | C28: =МАРТ!AO89 -> 8797.7487 | D28: =C28/C$105 -> 0.0016269252 | E28: =E27+D28 -> 1.0060144 | F28: =IF(AND(E28<=0),"C",IF(E28<=0.8,"A",IF(E28<=0.95,"B","C"))) -> C | G28: =VLOOKUP(B$4:B$104,I$4:M$104,5,0) -> C | I28: кс_черные_женские | J28: =МАРТ!U102 -> 44 | K28: =J28/J$105 -> 0.0034084747 | L28: =L27+K28 -> 0.96901387 | M28: =_xlfn.IFS(L28<80%,"A",L28<=95%,"B",L28>95%,"C") -> C
B29: sh18 | C29: =МАРТ!AO42 -> 5006.0251 | D29: =C29/C$105 -> 0.00092574005 | E29: =E28+D29 -> 1.0069402 | F29: =IF(AND(E29<=0),"C",IF(E29<=0.8,"A",IF(E29<=0.95,"B","C"))) -> C | G29: =VLOOKUP(B$4:B$104,I$4:M$104,5,0) -> C | I29: sh2 | J29: =МАРТ!U27 -> 39 | K29: =J29/J$105 -> 0.003021148 | L29: =L28+K29 -> 0.97203501 | M29: =_xlfn.IFS(L29<80%,"A",L29<=95%,"B",L29>95%,"C") -> C
B30: sh16 | C30: =МАРТ!AO40 -> 4480.789 | D30: =C30/C$105 -> 0.00082861068 | E30: =E29+D30 -> 1.0077688 | F30: =IF(AND(E30<=0),"C",IF(E30<=0.8,"A",IF(E30<=0.95,"B","C"))) -> C | G30: =VLOOKUP(B$4:B$104,I$4:M$104,5,0) -> C | I30: sh19 | J30: =МАРТ!U43 -> 34 | K30: =J30/J$105 -> 0.0026338214 | L30: =L29+K30 -> 0.97466884 | M30: =_xlfn.IFS(L30<80%,"A",L30<=95%,"B",L30>95%,"C") -> C
B31: MANNA2101 | C31: =МАРТ!AO54 -> 4208.7825 | D31: =C31/C$105 -> 0.00077830981 | E31: =E30+D31 -> 1.0085471 | F31: =IF(AND(E31<=0),"C",IF(E31<=0.8,"A",IF(E31<=0.95,"B","C"))) -> C | G31: =VLOOKUP(B$4:B$104,I$4:M$104,5,0) -> C | I31: Linhai Baiyi серая линза | J31: =МАРТ!U87 -> 28 | K31: =J31/J$105 -> 0.0021690294 | L31: =L30+K31 -> 0.97683787 | M31: =_xlfn.IFS(L31<80%,"A",L31<=95%,"B",L31>95%,"C") -> C
B32: sh15 | C32: =МАРТ!AO39 -> 2990.5657 | D32: =C32/C$105 -> 0.00055303088 | E32: =E31+D32 -> 1.0091001 | F32: =IF(AND(E32<=0),"C",IF(E32<=0.8,"A",IF(E32<=0.95,"B","C"))) -> C | G32: =VLOOKUP(B$4:B$104,I$4:M$104,5,0) -> C | I32: sh15 | J32: =МАРТ!U39 -> 25 | K32: =J32/J$105 -> 0.0019366334 | L32: =L31+K32 -> 0.9787745 | M32: =_xlfn.IFS(L32<80%,"A",L32<=95%,"B",L32>95%,"C") -> C
B33: Linhai Baiyi розовая линза | C33: =МАРТ!AO88 -> 2767.2936 | D33: =C33/C$105 -> 0.00051174223 | E33: =E32+D33 -> 1.0096119 | F33: =IF(AND(E33<=0),"C",IF(E33<=0.8,"A",IF(E33<=0.95,"B","C"))) -> C | G33: =VLOOKUP(B$4:B$104,I$4:M$104,5,0) -> C | I33: Hengda Optical черные | J33: =МАРТ!U81 -> 18 | K33: =J33/J$105 -> 0.001394376 | L33: =L32+K33 -> 0.98016887 | M33: =_xlfn.IFS(L33<80%,"A",L33<=95%,"B",L33>95%,"C") -> C
B34: кс_черные_женские | C34: =МАРТ!AO102 -> 2431.7275 | D34: =C34/C$105 -> 0.00044968762 | E34: =E33+D34 -> 1.0100616 | F34: =IF(AND(E34<=0),"C",IF(E34<=0.8,"A",IF(E34<=0.95,"B","C"))) -> C | G34: =VLOOKUP(B$4:B$104,I$4:M$104,5,0) -> C | I34: WW 3055 черный | J34: =МАРТ!U52 -> 17 | K34: =J34/J$105 -> 0.0013169107 | L34: =L33+K34 -> 0.98148579 | M34: =_xlfn.IFS(L34<80%,"A",L34<=95%,"B",L34>95%,"C") -> C
B35: Ли Сян ретро серебро | C35: =МАРТ!AO93 -> 2166.395 | D35: =C35/C$105 -> 0.00040062096 | E35: =E34+D35 -> 1.0104622 | F35: =IF(AND(E35<=0),"C",IF(E35<=0.8,"A",IF(E35<=0.95,"B","C"))) -> C | G35: =VLOOKUP(B$4:B$104,I$4:M$104,5,0) -> C | I35: MR Р1894 черные | J35: =МАРТ!U89 -> 17 | K35: =J35/J$105 -> 0.0013169107 | L35: =L34+K35 -> 0.9828027 | M35: =_xlfn.IFS(L35<80%,"A",L35<=95%,"B",L35>95%,"C") -> C
B36: sh13 | C36: =МАРТ!AO37 -> 1554.2602 | D36: =C36/C$105 -> 0.00028742183 | E36: =E35+D36 -> 1.0107496 | F36: =IF(AND(E36<=0),"C",IF(E36<=0.8,"A",IF(E36<=0.95,"B","C"))) -> C | G36: =VLOOKUP(B$4:B$104,I$4:M$104,5,0) -> C | I36: MANNA2101 | J36: =МАРТ!U54 -> 16 | K36: =J36/J$105 -> 0.0012394453 | L36: =L35+K36 -> 0.98404214 | M36: =_xlfn.IFS(L36<80%,"A",L36<=95%,"B",L36>95%,"C") -> C
B37: MANNA2119 | C37: =МАРТ!AO72 -> 1397.0905 | D37: =C37/C$105 -> 0.0002583572 | E37: =E36+D37 -> 1.011008 | F37: =IF(AND(E37<=0),"C",IF(E37<=0.8,"A",IF(E37<=0.95,"B","C"))) -> C | G37: =VLOOKUP(B$4:B$104,I$4:M$104,5,0) -> C | I37: MANNA2105 | J37: =МАРТ!U58 -> 15 | K37: =J37/J$105 -> 0.00116198 | L37: =L36+K37 -> 0.98520412 | M37: =_xlfn.IFS(L37<80%,"A",L37<=95%,"B",L37>95%,"C") -> C
B38: sh17 | C38: =МАРТ!AO41 -> 1056.9455 | D38: =C38/C$105 -> 0.00019545583 | E38: =E37+D38 -> 1.0112034 | F38: =IF(AND(E38<=0),"C",IF(E38<=0.8,"A",IF(E38<=0.95,"B","C"))) -> C | G38: =VLOOKUP(B$4:B$104,I$4:M$104,5,0) -> C | I38: sh18 | J38: =МАРТ!U42 -> 14 | K38: =J38/J$105 -> 0.0010845147 | L38: =L37+K38 -> 0.98628864 | M38: =_xlfn.IFS(L38<80%,"A",L38<=95%,"B",L38>95%,"C") -> C
B39: MANNA2117 | C39: =МАРТ!AO70 -> 1009.3484 | D39: =C39/C$105 -> 0.00018665392 | E39: =E35+D39 -> 1.0106488 | F39: =IF(AND(E39<=0),"C",IF(E39<=0.8,"A",IF(E39<=0.95,"B","C"))) -> C | G39: =VLOOKUP(B$4:B$104,I$4:M$104,5,0) -> C | I39: sh16 | J39: =МАРТ!U40 -> 13 | K39: =J39/J$105 -> 0.0010070493 | L39: =L35+K39 -> 0.98380975 | M39: =_xlfn.IFS(L39<80%,"A",L39<=95%,"B",L39>95%,"C") -> C
B40: Hengda Optical леопард | C40: =МАРТ!AO82 -> 864.07299 | D40: =C40/C$105 -> 0.00015978885 | E40: =E39+D40 -> 1.0108086 | F40: =IF(AND(E40<=0),"C",IF(E40<=0.8,"A",IF(E40<=0.95,"B","C"))) -> C | G40: =VLOOKUP(B$4:B$104,I$4:M$104,5,0) -> C | I40: MANNA2118 | J40: =МАРТ!U71 -> 11 | K40: =J40/J$105 -> 0.00085211868 | L40: =L39+K40 -> 0.98466186 | M40: =_xlfn.IFS(L40<80%,"A",L40<=95%,"B",L40>95%,"C") -> C
B41: ww 8010 черные | C41: =МАРТ!AO51 -> 842.93067 | D41: =C41/C$105 -> 0.0001558791 | E41: =E40+D41 -> 1.0109645 | F41: =IF(AND(E41<=0),"C",IF(E41<=0.8,"A",IF(E41<=0.95,"B","C"))) -> C | G41: =VLOOKUP(B$4:B$104,I$4:M$104,5,0) -> C | I41: MANNA2122 | J41: =МАРТ!U75 -> 11 | K41: =J41/J$105 -> 0.00085211868 | L41: =L40+K41 -> 0.98551398 | M41: =_xlfn.IFS(L41<80%,"A",L41<=95%,"B",L41>95%,"C") -> C
B42: MANNA2116 | C42: =МАРТ!AO69 -> 766.70148 | D42: =C42/C$105 -> 0.0001417824 | E42: =E41+D42 -> 1.0111063 | F42: =IF(AND(E42<=0),"C",IF(E42<=0.8,"A",IF(E42<=0.95,"B","C"))) -> C | G42: =VLOOKUP(B$4:B$104,I$4:M$104,5,0) -> C | I42: Guangdu серебро серая линза | J42: =МАРТ!U80 -> 11 | K42: =J42/J$105 -> 0.00085211868 | L42: =L41+K42 -> 0.9863661 | M42: =_xlfn.IFS(L42<80%,"A",L42<=95%,"B",L42>95%,"C") -> C
B43: MANNA2114 | C43: =МАРТ!AO67 -> 689.478 | D43: =C43/C$105 -> 0.00012750184 | E43: =E42+D43 -> 1.0112338 | F43: =IF(AND(E43<=0),"C",IF(E43<=0.8,"A",IF(E43<=0.95,"B","C"))) -> C | G43: =VLOOKUP(B$4:B$104,I$4:M$104,5,0) -> C | I43: sh09 | J43: =МАРТ!U33 -> 9 | K43: =J43/J$105 -> 0.00069718801 | L43: =L42+K43 -> 0.98706329 | M43: =_xlfn.IFS(L43<80%,"A",L43<=95%,"B",L43>95%,"C") -> C
B44: POMILED 08247 C4-08 | C44: =МАРТ!AO97 -> 537.5111 | D44: =C44/C$105 -> 9.9399331e-05 | E44: =E43+D44 -> 1.0113332 | F44: =IF(AND(E44<=0),"C",IF(E44<=0.8,"A",IF(E44<=0.95,"B","C"))) -> C | G44: =VLOOKUP(B$4:B$104,I$4:M$104,5,0) -> C | I44: Linhai Baiyi розовая линза | J44: =МАРТ!U88 -> 9 | K44: =J44/J$105 -> 0.00069718801 | L44: =L43+K44 -> 0.98776048 | M44: =_xlfn.IFS(L44<80%,"A",L44<=95%,"B",L44>95%,"C") -> C
B45: MANNA2107 | C45: =МАРТ!AO60 -> 514.47819 | D45: =C45/C$105 -> 9.5139967e-05 | E45: =E44+D45 -> 1.0114283 | F45: =IF(AND(E45<=0),"C",IF(E45<=0.8,"A",IF(E45<=0.95,"B","C"))) -> C | G45: =VLOOKUP(B$4:B$104,I$4:M$104,5,0) -> C | I45: ЧСЖ_женские | J45: =МАРТ!U100 -> 9 | K45: =J45/J$105 -> 0.00069718801 | L45: =L44+K45 -> 0.98845767 | M45: =_xlfn.IFS(L45<80%,"A",L45<=95%,"B",L45>95%,"C") -> C
B46: ЧСЖ_женские | C46: =МАРТ!AO100 -> 473.12476 | D46: =C46/C$105 -> 8.7492677e-05 | E46: =E45+D46 -> 1.0115158 | F46: =IF(AND(E46<=0),"C",IF(E46<=0.8,"A",IF(E46<=0.95,"B","C"))) -> C | G46: =VLOOKUP(B$4:B$104,I$4:M$104,5,0) -> C | I46: Keming Aishi коричневые | J46: =МАРТ!U85 -> 8 | K46: =J46/J$105 -> 0.00061972267 | L46: =L45+K46 -> 0.98907739 | M46: =_xlfn.IFS(L46<80%,"A",L46<=95%,"B",L46>95%,"C") -> C
B47: sportlife синие | C47: =МАРТ!AO24 -> 346.0091 | D47: =C47/C$105 -> 6.3985792e-05 | E47: =E46+D47 -> 1.0115798 | F47: =IF(AND(E47<=0),"C",IF(E47<=0.8,"A",IF(E47<=0.95,"B","C"))) -> C | G47: =VLOOKUP(B$4:B$104,I$4:M$104,5,0) -> C | I47: WW 3055 коричневый | J47: =МАРТ!U53 -> 7 | K47: =J47/J$105 -> 0.00054225734 | L47: =L46+K47 -> 0.98961965 | M47: =_xlfn.IFS(L47<80%,"A",L47<=95%,"B",L47>95%,"C") -> C
B48: MAIERSHA 03898 C9-08 | C48: =МАРТ!AO94 -> 311.817 | D48: =C48/C$105 -> 5.7662812e-05 | E48: =E47+D48 -> 1.0116375 | F48: =IF(AND(E48<=0),"C",IF(E48<=0.8,"A",IF(E48<=0.95,"B","C"))) -> C | G48: =VLOOKUP(B$4:B$104,I$4:M$104,5,0) -> C | I48: Chenlong черные | J48: =МАРТ!U76 -> 7 | K48: =J48/J$105 -> 0.00054225734 | L48: =L47+K48 -> 0.9901619 | M48: =_xlfn.IFS(L48<80%,"A",L48<=95%,"B",L48>95%,"C") -> C
B49: Qianai черные | C49: =МАРТ!AO83 -> 178.52926 | D49: =C49/C$105 -> 3.3014554e-05 | E49: =E48+D49 -> 1.0116705 | F49: =IF(AND(E49<=0),"C",IF(E49<=0.8,"A",IF(E49<=0.95,"B","C"))) -> C | G49: =VLOOKUP(B$4:B$104,I$4:M$104,5,0) -> C | I49: sh13 | J49: =МАРТ!U37 -> 6 | K49: =J49/J$105 -> 0.00046479201 | L49: =L48+K49 -> 0.99062669 | M49: =_xlfn.IFS(L49<80%,"A",L49<=95%,"B",L49>95%,"C") -> C
B50: sh07 | C50: =МАРТ!AO31 -> 164.6256 | D50: =C50/C$105 -> 3.0443417e-05 | E50: =E49+D50 -> 1.0117009 | F50: =IF(AND(E50<=0),"C",IF(E50<=0.8,"A",IF(E50<=0.95,"B","C"))) -> C | G50: =VLOOKUP(B$4:B$104,I$4:M$104,5,0) -> C | I50: MANNA2119 | J50: =МАРТ!U72 -> 6 | K50: =J50/J$105 -> 0.00046479201 | L50: =L49+K50 -> 0.99109149 | M50: =_xlfn.IFS(L50<80%,"A",L50<=95%,"B",L50>95%,"C") -> C
B51: MANNA2118 | C51: =МАРТ!AO71 -> 90.1421 | D51: =C51/C$105 -> 1.6669543e-05 | E51: =E50+D51 -> 1.0117176 | F51: =IF(AND(E51<=0),"C",IF(E51<=0.8,"A",IF(E51<=0.95,"B","C"))) -> C | G51: =VLOOKUP(B$4:B$104,I$4:M$104,5,0) -> C | I51: Ли Сян ретро серебро | J51: =МАРТ!U93 -> 6 | K51: =J51/J$105 -> 0.00046479201 | L51: =L50+K51 -> 0.99155628 | M51: =_xlfn.IFS(L51<80%,"A",L51<=95%,"B",L51>95%,"C") -> C
B52: sh06 | C52: =МАРТ!AO30 -> 53.413485 | D52: =C52/C$105 -> 9.8774978e-06 | E52: =E51+D52 -> 1.0117275 | F52: =IF(AND(E52<=0),"C",IF(E52<=0.8,"A",IF(E52<=0.95,"B","C"))) -> C | G52: =VLOOKUP(B$4:B$104,I$4:M$104,5,0) -> C | I52: MANNA2107 | J52: =МАРТ!U60 -> 5 | K52: =J52/J$105 -> 0.00038732667 | L52: =L51+K52 -> 0.99194361 | M52: =_xlfn.IFS(L52<80%,"A",L52<=95%,"B",L52>95%,"C") -> C
B53: Hengda Optical черные | C53: =МАРТ!AO81 -> 42.004177 | D53: =C53/C$105 -> 7.7676296e-06 | E53: =E52+D53 -> 1.0117352 | F53: =IF(AND(E53<=0),"C",IF(E53<=0.8,"A",IF(E53<=0.95,"B","C"))) -> C | G53: =VLOOKUP(B$4:B$104,I$4:M$104,5,0) -> C | I53: Иу Диту серый | J53: =МАРТ!U91 -> 5 | K53: =J53/J$105 -> 0.00038732667 | L53: =L52+K53 -> 0.99233093 | M53: =_xlfn.IFS(L53<80%,"A",L53<=95%,"B",L53>95%,"C") -> C
B54: sh10 | C54: =МАРТ!AO34 -> 4.6482 | D54: =C54/C$105 -> 8.5956918e-07 | E54: =E53+D54 -> 1.0117361 | F54: =IF(AND(E54<=0),"C",IF(E54<=0.8,"A",IF(E54<=0.95,"B","C"))) -> C | G54: =VLOOKUP(B$4:B$104,I$4:M$104,5,0) -> C | I54: MANNA2117 | J54: =МАРТ!U70 -> 4 | K54: =J54/J$105 -> 0.00030986134 | L54: =L53+K54 -> 0.99264079 | M54: =_xlfn.IFS(L54<80%,"A",L54<=95%,"B",L54>95%,"C") -> C
B55: wwl8032 черные серебро | C55: =МАРТ!AO19 -> 0 | D55: =C55/C$105 -> 0 | E55: =E54+D55 -> 1.0117361 | F55: =IF(AND(E55<=0),"C",IF(E55<=0.8,"A",IF(E55<=0.95,"B","C"))) -> C | G55: =VLOOKUP(B$4:B$104,I$4:M$104,5,0) -> C | I55: Chenlong белые | J55: =МАРТ!U78 -> 4 | K55: =J55/J$105 -> 0.00030986134 | L55: =L54+K55 -> 0.99295065 | M55: =_xlfn.IFS(L55<80%,"A",L55<=95%,"B",L55>95%,"C") -> C
B56: sportlife черные | C56: =МАРТ!AO23 -> 0 | D56: =C56/C$105 -> 0 | E56: =E55+D56 -> 1.0117361 | F56: =IF(AND(E56<=0),"C",IF(E56<=0.8,"A",IF(E56<=0.95,"B","C"))) -> C | G56: =VLOOKUP(B$4:B$104,I$4:M$104,5,0) -> C | I56: sh14 | J56: =МАРТ!U38 -> 3 | K56: =J56/J$105 -> 0.000232396 | L56: =L55+K56 -> 0.99318305 | M56: =_xlfn.IFS(L56<80%,"A",L56<=95%,"B",L56>95%,"C") -> C
B57: sportlife красные | C57: =МАРТ!AO25 -> 0 | D57: =C57/C$105 -> 0 | E57: =E56+D57 -> 1.0117361 | F57: =IF(AND(E57<=0),"C",IF(E57<=0.8,"A",IF(E57<=0.95,"B","C"))) -> C | G57: =VLOOKUP(B$4:B$104,I$4:M$104,5,0) -> C | I57: sh17 | J57: =МАРТ!U41 -> 3 | K57: =J57/J$105 -> 0.000232396 | L57: =L56+K57 -> 0.99341545 | M57: =_xlfn.IFS(L57<80%,"A",L57<=95%,"B",L57>95%,"C") -> C
B58: sh4 | C58: =МАРТ!AO29 -> 0 | D58: =C58/C$105 -> 0 | E58: =E57+D58 -> 1.0117361 | F58: =IF(AND(E58<=0),"C",IF(E58<=0.8,"A",IF(E58<=0.95,"B","C"))) -> C | G58: =VLOOKUP(B$4:B$104,I$4:M$104,5,0) -> C | I58: ww 8010 черные | J58: =МАРТ!U51 -> 3 | K58: =J58/J$105 -> 0.000232396 | L58: =L57+K58 -> 0.99364784 | M58: =_xlfn.IFS(L58<80%,"A",L58<=95%,"B",L58>95%,"C") -> C
B59: sh08 | C59: =МАРТ!AO32 -> 0 | D59: =C59/C$105 -> 0 | E59: =E58+D59 -> 1.0117361 | F59: =IF(AND(E59<=0),"C",IF(E59<=0.8,"A",IF(E59<=0.95,"B","C"))) -> C | G59: =VLOOKUP(B$4:B$104,I$4:M$104,5,0) -> C | I59: MANNA2116 | J59: =МАРТ!U69 -> 3 | K59: =J59/J$105 -> 0.000232396 | L59: =L58+K59 -> 0.99388024 | M59: =_xlfn.IFS(L59<80%,"A",L59<=95%,"B",L59>95%,"C") -> C
B60: sh11 | C60: =МАРТ!AO35 -> 0 | D60: =C60/C$105 -> 0 | E60: =E59+D60 -> 1.0117361 | F60: =IF(AND(E60<=0),"C",IF(E60<=0.8,"A",IF(E60<=0.95,"B","C"))) -> C | G60: =VLOOKUP(B$4:B$104,I$4:M$104,5,0) -> C | I60: MANNA2120 | J60: =МАРТ!U73 -> 3 | K60: =J60/J$105 -> 0.000232396 | L60: =L59+K60 -> 0.99411263 | M60: =_xlfn.IFS(L60<80%,"A",L60<=95%,"B",L60>95%,"C") -> C
B61: sh12 | C61: =МАРТ!AO36 -> 0 | D61: =C61/C$105 -> 0 | E61: =E60+D61 -> 1.0117361 | F61: =IF(AND(E61<=0),"C",IF(E61<=0.8,"A",IF(E61<=0.95,"B","C"))) -> C | G61: =VLOOKUP(B$4:B$104,I$4:M$104,5,0) -> C | I61: Chenlong коричневые | J61: =МАРТ!U77 -> 3 | K61: =J61/J$105 -> 0.000232396 | L61: =L60+K61 -> 0.99434503 | M61: =_xlfn.IFS(L61<80%,"A",L61<=95%,"B",L61>95%,"C") -> C
B62: ww 1022 черн-серебро | C62: =МАРТ!AO46 -> 0 | D62: =C62/C$105 -> 0 | E62: =E61+D62 -> 1.0117361 | F62: =IF(AND(E62<=0),"C",IF(E62<=0.8,"A",IF(E62<=0.95,"B","C"))) -> C | G62: =VLOOKUP(B$4:B$104,I$4:M$104,5,0) -> C | I62: Guangdu золото серая линза | J62: =МАРТ!U79 -> 3 | K62: =J62/J$105 -> 0.000232396 | L62: =L61+K62 -> 0.99457743 | M62: =_xlfn.IFS(L62<80%,"A",L62<=95%,"B",L62>95%,"C") -> C
B63: MANNA2102 | C63: =МАРТ!AO55 -> 0 | D63: =C63/C$105 -> 0 | E63: =E62+D63 -> 1.0117361 | F63: =IF(AND(E63<=0),"C",IF(E63<=0.8,"A",IF(E63<=0.95,"B","C"))) -> C | G63: =VLOOKUP(B$4:B$104,I$4:M$104,5,0) -> C | I63: Hengda Optical леопард | J63: =МАРТ!U82 -> 3 | K63: =J63/J$105 -> 0.000232396 | L63: =L62+K63 -> 0.99480982 | M63: =_xlfn.IFS(L63<80%,"A",L63<=95%,"B",L63>95%,"C") -> C
B64: MANNA2103 | C64: =МАРТ!AO56 -> 0 | D64: =C64/C$105 -> 0 | E64: =E63+D64 -> 1.0117361 | F64: =IF(AND(E64<=0),"C",IF(E64<=0.8,"A",IF(E64<=0.95,"B","C"))) -> C | G64: =VLOOKUP(B$4:B$104,I$4:M$104,5,0) -> C | I64: Qianai черные | J64: =МАРТ!U83 -> 3 | K64: =J64/J$105 -> 0.000232396 | L64: =L63+K64 -> 0.99504222 | M64: =_xlfn.IFS(L64<80%,"A",L64<=95%,"B",L64>95%,"C") -> C
B65: MANNA2104 | C65: =МАРТ!AO57 -> 0 | D65: =C65/C$105 -> 0 | E65: =E64+D65 -> 1.0117361 | F65: =IF(AND(E65<=0),"C",IF(E65<=0.8,"A",IF(E65<=0.95,"B","C"))) -> C | G65: =VLOOKUP(B$4:B$104,I$4:M$104,5,0) -> C | I65: Linhai Baiyi коричневая линза | J65: =МАРТ!U86 -> 3 | K65: =J65/J$105 -> 0.000232396 | L65: =L64+K65 -> 0.99527461 | M65: =_xlfn.IFS(L65<80%,"A",L65<=95%,"B",L65>95%,"C") -> C
B66: MANNA2106 | C66: =МАРТ!AO59 -> 0 | D66: =C66/C$105 -> 0 | E66: =E65+D66 -> 1.0117361 | F66: =IF(AND(E66<=0),"C",IF(E66<=0.8,"A",IF(E66<=0.95,"B","C"))) -> C | G66: =VLOOKUP(B$4:B$104,I$4:M$104,5,0) -> C | I66: sports синие | J66: =МАРТ!U20 -> 2 | K66: =J66/J$105 -> 0.00015493067 | L66: =L65+K66 -> 0.99542955 | M66: =_xlfn.IFS(L66<80%,"A",L66<=95%,"B",L66>95%,"C") -> C
B67: MANNA2109 | C67: =МАРТ!AO62 -> 0 | D67: =C67/C$105 -> 0 | E67: =E66+D67 -> 1.0117361 | F67: =IF(AND(E67<=0),"C",IF(E67<=0.8,"A",IF(E67<=0.95,"B","C"))) -> C | G67: =VLOOKUP(B$4:B$104,I$4:M$104,5,0) -> C | I67: sports красные | J67: =МАРТ!U22 -> 2 | K67: =J67/J$105 -> 0.00015493067 | L67: =L66+K67 -> 0.99558448 | M67: =_xlfn.IFS(L67<80%,"A",L67<=95%,"B",L67>95%,"C") -> C
B68: MANNA2110 | C68: =МАРТ!AO63 -> 0 | D68: =C68/C$105 -> 0 | E68: =E67+D68 -> 1.0117361 | F68: =IF(AND(E68<=0),"C",IF(E68<=0.8,"A",IF(E68<=0.95,"B","C"))) -> C | G68: =VLOOKUP(B$4:B$104,I$4:M$104,5,0) -> C | I68: MANNA2108 | J68: =МАРТ!U61 -> 2 | K68: =J68/J$105 -> 0.00015493067 | L68: =L67+K68 -> 0.99573941 | M68: =_xlfn.IFS(L68<80%,"A",L68<=95%,"B",L68>95%,"C") -> C
B69: MANNA2111 | C69: =МАРТ!AO64 -> 0 | D69: =C69/C$105 -> 0 | E69: =E68+D69 -> 1.0117361 | F69: =IF(AND(E69<=0),"C",IF(E69<=0.8,"A",IF(E69<=0.95,"B","C"))) -> C | G69: =VLOOKUP(B$4:B$104,I$4:M$104,5,0) -> C | I69: MANNA2114 | J69: =МАРТ!U67 -> 2 | K69: =J69/J$105 -> 0.00015493067 | L69: =L68+K69 -> 0.99589434 | M69: =_xlfn.IFS(L69<80%,"A",L69<=95%,"B",L69>95%,"C") -> C
B70: MANNA2115 | C70: =МАРТ!AO68 -> 0 | D70: =C70/C$105 -> 0 | E70: =E69+D70 -> 1.0117361 | F70: =IF(AND(E70<=0),"C",IF(E70<=0.8,"A",IF(E70<=0.95,"B","C"))) -> C | G70: =VLOOKUP(B$4:B$104,I$4:M$104,5,0) -> C | I70: POMILED 08247 C4-08 | J70: =МАРТ!U97 -> 2 | K70: =J70/J$105 -> 0.00015493067 | L70: =L69+K70 -> 0.99604927 | M70: =_xlfn.IFS(L70<80%,"A",L70<=95%,"B",L70>95%,"C") -> C
B71: MAIERSHA 03914 C9-124 | C71: =МАРТ!AO95 -> 0 | D71: =C71/C$105 -> 0 | E71: =E70+D71 -> 1.0117361 | F71: =IF(AND(E71<=0),"C",IF(E71<=0.8,"A",IF(E71<=0.95,"B","C"))) -> C | G71: =VLOOKUP(B$4:B$104,I$4:M$104,5,0) -> C | I71: sportlife синие | J71: =МАРТ!U24 -> 1 | K71: =J71/J$105 -> 7.7465334e-05 | L71: =L70+K71 -> 0.99612673 | M71: =_xlfn.IFS(L71<80%,"A",L71<=95%,"B",L71>95%,"C") -> C
B72: MARSTON 7171 C1 | C72: =МАРТ!AO96 -> 0 | D72: =C72/C$105 -> 0 | E72: =E71+D72 -> 1.0117361 | F72: =IF(AND(E72<=0),"C",IF(E72<=0.8,"A",IF(E72<=0.95,"B","C"))) -> C | G72: =VLOOKUP(B$4:B$104,I$4:M$104,5,0) -> C | I72: sh06 | J72: =МАРТ!U30 -> 1 | K72: =J72/J$105 -> 7.7465334e-05 | L72: =L71+K72 -> 0.9962042 | M72: =_xlfn.IFS(L72<80%,"A",L72<=95%,"B",L72>95%,"C") -> C
B73: ЧСЖ_тест | C73: =МАРТ!AO99 -> 0 | D73: =C73/C$105 -> 0 | E73: =E72+D73 -> 1.0117361 | F73: =IF(AND(E73<=0),"C",IF(E73<=0.8,"A",IF(E73<=0.95,"B","C"))) -> C | G73: =VLOOKUP(B$4:B$104,I$4:M$104,5,0) -> C | I73: sh07 | J73: =МАРТ!U31 -> 1 | K73: =J73/J$105 -> 7.7465334e-05 | L73: =L72+K73 -> 0.99628166 | M73: =_xlfn.IFS(L73<80%,"A",L73<=95%,"B",L73>95%,"C") -> C
B74: кс_черные_тест | C74: =МАРТ!AO101 -> 0 | D74: =C74/C$105 -> 0 | E74: =E73+D74 -> 1.0117361 | F74: =IF(AND(E74<=0),"C",IF(E74<=0.8,"A",IF(E74<=0.95,"B","C"))) -> C | G74: =VLOOKUP(B$4:B$104,I$4:M$104,5,0) -> C | I74: Qianai коричневые | J74: =МАРТ!U84 -> 1 | K74: =J74/J$105 -> 7.7465334e-05 | L74: =L73+K74 -> 0.99635913 | M74: =_xlfn.IFS(L74<80%,"A",L74<=95%,"B",L74>95%,"C") -> C
B75: 1022_коричневые_тест | C75: =МАРТ!AO103 -> 0 | D75: =C75/C$105 -> 0 | E75: =E74+D75 -> 1.0117361 | F75: =IF(AND(E75<=0),"C",IF(E75<=0.8,"A",IF(E75<=0.95,"B","C"))) -> C | G75: =VLOOKUP(B$4:B$104,I$4:M$104,5,0) -> C | I75: MAIERSHA 03898 C9-08 | J75: =МАРТ!U94 -> 1 | K75: =J75/J$105 -> 7.7465334e-05 | L75: =L74+K75 -> 0.99643659 | M75: =_xlfn.IFS(L75<80%,"A",L75<=95%,"B",L75>95%,"C") -> C
B76: MANNA2113 | C76: =МАРТ!AO66 -> -6.9109072 | D76: =C76/C$105 -> -1.2780007e-06 | E76: =E49+D76 -> 1.0116692 | F76: =IF(AND(E76<=0),"C",IF(E76<=0.8,"A",IF(E76<=0.95,"B","C"))) -> C | G76: =VLOOKUP(B$4:B$104,I$4:M$104,5,0) -> C | I76: YIMEI 2391 C1 | J76: =МАРТ!U98 -> 1 | K76: =J76/J$105 -> 7.7465334e-05 | L76: =L49+K76 -> 0.99070416 | M76: =_xlfn.IFS(L76<80%,"A",L76<=95%,"B",L76>95%,"C") -> C
B77: MANNA2112 | C77: =МАРТ!AO65 -> -177.25716 | D77: =C77/C$105 -> -3.2779311e-05 | E77: =E76+D77 -> 1.0116364 | F77: =IF(AND(E77<=0),"C",IF(E77<=0.8,"A",IF(E77<=0.95,"B","C"))) -> C | G77: =VLOOKUP(B$4:B$104,I$4:M$104,5,0) -> C | I77: wwl8032 черные серебро | J77: =МАРТ!U19 -> 0 | K77: =J77/J$105 -> 0 | L77: =L76+K77 -> 0.99070416 | M77: =_xlfn.IFS(L77<80%,"A",L77<=95%,"B",L77>95%,"C") -> C
B78: sports синие | C78: =МАРТ!AO20 -> -182.53011 | D78: =C78/C$105 -> -3.3754412e-05 | E78: =E77+D78 -> 1.0116027 | F78: =IF(AND(E78<=0),"C",IF(E78<=0.8,"A",IF(E78<=0.95,"B","C"))) -> C | G78: =VLOOKUP(B$4:B$104,I$4:M$104,5,0) -> C | I78: sports зеленые | J78: =МАРТ!U21 -> 0 | K78: =J78/J$105 -> 0 | L78: =L77+K78 -> 0.99070416 | M78: =_xlfn.IFS(L78<80%,"A",L78<=95%,"B",L78>95%,"C") -> C
B79: Taizhou Rayen sport розовый | C79: =МАРТ!AO90 -> -197.01139 | D79: =C79/C$105 -> -3.6432366e-05 | E79: =E78+D79 -> 1.0115662 | F79: =IF(AND(E79<=0),"C",IF(E79<=0.8,"A",IF(E79<=0.95,"B","C"))) -> C | G79: =VLOOKUP(B$4:B$104,I$4:M$104,5,0) -> C | I79: sportlife черные | J79: =МАРТ!U23 -> 0 | K79: =J79/J$105 -> 0 | L79: =L78+K79 -> 0.99070416 | M79: =_xlfn.IFS(L79<80%,"A",L79<=95%,"B",L79>95%,"C") -> C
B80: WW 3055 черный | C80: =МАРТ!AO52 -> -199.88087 | D80: =C80/C$105 -> -3.6963004e-05 | E80: =E79+D80 -> 1.0115293 | F80: =IF(AND(E80<=0),"C",IF(E80<=0.8,"A",IF(E80<=0.95,"B","C"))) -> C | G80: =VLOOKUP(B$4:B$104,I$4:M$104,5,0) -> C | I80: sportlife красные | J80: =МАРТ!U25 -> 0 | K80: =J80/J$105 -> 0 | L80: =L79+K80 -> 0.99070416 | M80: =_xlfn.IFS(L80<80%,"A",L80<=95%,"B",L80>95%,"C") -> C
B81: MANNA2121 | C81: =МАРТ!AO74 -> -204.83 | D81: =C81/C$105 -> -3.7878223e-05 | E81: =E80+D81 -> 1.0114914 | F81: =IF(AND(E81<=0),"C",IF(E81<=0.8,"A",IF(E81<=0.95,"B","C"))) -> C | G81: =VLOOKUP(B$4:B$104,I$4:M$104,5,0) -> C | I81: sh4 | J81: =МАРТ!U29 -> 0 | K81: =J81/J$105 -> 0 | L81: =L80+K81 -> 0.99070416 | M81: =_xlfn.IFS(L81<80%,"A",L81<=95%,"B",L81>95%,"C") -> C
B82: YIMEI 2391 C1 | C82: =МАРТ!AO98 -> -261.70687 | D82: =C82/C$105 -> -4.8396188e-05 | E82: =E81+D82 -> 1.011443 | F82: =IF(AND(E82<=0),"C",IF(E82<=0.8,"A",IF(E82<=0.95,"B","C"))) -> C | G82: =VLOOKUP(B$4:B$104,I$4:M$104,5,0) -> C | I82: sh08 | J82: =МАРТ!U32 -> 0 | K82: =J82/J$105 -> 0 | L82: =L81+K82 -> 0.99070416 | M82: =_xlfn.IFS(L82<80%,"A",L82<=95%,"B",L82>95%,"C") -> C
B83: MANNA2108 | C83: =МАРТ!AO61 -> -533.21323 | D83: =C83/C$105 -> -9.8604548e-05 | E83: =E82+D83 -> 1.0113444 | F83: =IF(AND(E83<=0),"C",IF(E83<=0.8,"A",IF(E83<=0.95,"B","C"))) -> C | G83: =VLOOKUP(B$4:B$104,I$4:M$104,5,0) -> C | I83: sh10 | J83: =МАРТ!U34 -> 0 | K83: =J83/J$105 -> 0 | L83: =L82+K83 -> 0.99070416 | M83: =_xlfn.IFS(L83<80%,"A",L83<=95%,"B",L83>95%,"C") -> C
B84: sh14 | C84: =МАРТ!AO38 -> -633.56533 | D84: =C84/C$105 -> -0.00011716218 | E84: =E83+D84 -> 1.0112272 | F84: =IF(AND(E84<=0),"C",IF(E84<=0.8,"A",IF(E84<=0.95,"B","C"))) -> C | G84: =VLOOKUP(B$4:B$104,I$4:M$104,5,0) -> C | I84: sh11 | J84: =МАРТ!U35 -> 0 | K84: =J84/J$105 -> 0 | L84: =L83+K84 -> 0.99070416 | M84: =_xlfn.IFS(L84<80%,"A",L84<=95%,"B",L84>95%,"C") -> C
B85: Ли Сян ретро золото | C85: =МАРТ!AO92 -> -729.07806 | D85: =C85/C$105 -> -0.00013482488 | E85: =E84+D85 -> 1.0110924 | F85: =IF(AND(E85<=0),"C",IF(E85<=0.8,"A",IF(E85<=0.95,"B","C"))) -> C | G85: =VLOOKUP(B$4:B$104,I$4:M$104,5,0) -> C | I85: sh12 | J85: =МАРТ!U36 -> 0 | K85: =J85/J$105 -> 0 | L85: =L84+K85 -> 0.99070416 | M85: =_xlfn.IFS(L85<80%,"A",L85<=95%,"B",L85>95%,"C") -> C
B86: sh2 | C86: =МАРТ!AO27 -> -833.71369 | D86: =C86/C$105 -> -0.00015417465 | E86: =E85+D86 -> 1.0109382 | F86: =IF(AND(E86<=0),"C",IF(E86<=0.8,"A",IF(E86<=0.95,"B","C"))) -> C | G86: =VLOOKUP(B$4:B$104,I$4:M$104,5,0) -> C | I86: ww 1022 черн-серебро | J86: =МАРТ!U46 -> 0 | K86: =J86/J$105 -> 0 | L86: =L85+K86 -> 0.99070416 | M86: =_xlfn.IFS(L86<80%,"A",L86<=95%,"B",L86>95%,"C") -> C
B87: Guangdu серебро серая линза | C87: =МАРТ!AO80 -> -882.67116 | D87: =C87/C$105 -> -0.00016322811 | E87: =E86+D87 -> 1.010775 | F87: =IF(AND(E87<=0),"C",IF(E87<=0.8,"A",IF(E87<=0.95,"B","C"))) -> C | G87: =VLOOKUP(B$4:B$104,I$4:M$104,5,0) -> C | I87: MANNA2102 | J87: =МАРТ!U55 -> 0 | K87: =J87/J$105 -> 0 | L87: =L86+K87 -> 0.99070416 | M87: =_xlfn.IFS(L87<80%,"A",L87<=95%,"B",L87>95%,"C") -> C
B88: MANNA2120 | C88: =МАРТ!AO73 -> -914.97817 | D88: =C88/C$105 -> -0.00016920249 | E88: =E87+D88 -> 1.0106058 | F88: =IF(AND(E88<=0),"C",IF(E88<=0.8,"A",IF(E88<=0.95,"B","C"))) -> C | G88: =VLOOKUP(B$4:B$104,I$4:M$104,5,0) -> C | I88: MANNA2103 | J88: =МАРТ!U56 -> 0 | K88: =J88/J$105 -> 0 | L88: =L87+K88 -> 0.99070416 | M88: =_xlfn.IFS(L88<80%,"A",L88<=95%,"B",L88>95%,"C") -> C
B89: sports красные | C89: =МАРТ!AO22 -> -1171.3044 | D89: =C89/C$105 -> -0.00021660367 | E89: =E88+D89 -> 1.0103892 | F89: =IF(AND(E89<=0),"C",IF(E89<=0.8,"A",IF(E89<=0.95,"B","C"))) -> C | G89: =VLOOKUP(B$4:B$104,I$4:M$104,5,0) -> C | I89: MANNA2104 | J89: =МАРТ!U57 -> 0 | K89: =J89/J$105 -> 0 | L89: =L88+K89 -> 0.99070416 | M89: =_xlfn.IFS(L89<80%,"A",L89<=95%,"B",L89>95%,"C") -> C
B90: MANNA2122 | C90: =МАРТ!AO75 -> -1378.3265 | D90: =C90/C$105 -> -0.00025488727 | E90: =E89+D90 -> 1.0101343 | F90: =IF(AND(E90<=0),"C",IF(E90<=0.8,"A",IF(E90<=0.95,"B","C"))) -> C | G90: =VLOOKUP(B$4:B$104,I$4:M$104,5,0) -> C | I90: MANNA2106 | J90: =МАРТ!U59 -> 0 | K90: =J90/J$105 -> 0 | L90: =L89+K90 -> 0.99070416 | M90: =_xlfn.IFS(L90<80%,"A",L90<=95%,"B",L90>95%,"C") -> C
B91: Chenlong коричневые | C91: =МАРТ!AO77 -> -1491.9307 | D91: =C91/C$105 -> -0.00027589554 | E91: =E90+D91 -> 1.0098584 | F91: =IF(AND(E91<=0),"C",IF(E91<=0.8,"A",IF(E91<=0.95,"B","C"))) -> C | G91: =VLOOKUP(B$4:B$104,I$4:M$104,5,0) -> C | I91: MANNA2109 | J91: =МАРТ!U62 -> 0 | K91: =J91/J$105 -> 0 | L91: =L90+K91 -> 0.99070416 | M91: =_xlfn.IFS(L91<80%,"A",L91<=95%,"B",L91>95%,"C") -> C
B92: Иу Диту серый | C92: =МАРТ!AO91 -> -1708.4474 | D92: =C92/C$105 -> -0.00031593494 | E92: =E91+D92 -> 1.0095425 | F92: =IF(AND(E92<=0),"C",IF(E92<=0.8,"A",IF(E92<=0.95,"B","C"))) -> C | G92: =VLOOKUP(B$4:B$104,I$4:M$104,5,0) -> C | I92: MANNA2110 | J92: =МАРТ!U63 -> 0 | K92: =J92/J$105 -> 0 | L92: =L91+K92 -> 0.99070416 | M92: =_xlfn.IFS(L92<80%,"A",L92<=95%,"B",L92>95%,"C") -> C
B93: Guangdu золото серая линза | C93: =МАРТ!AO79 -> -1905.5562 | D93: =C93/C$105 -> -0.00035238531 | E93: =E92+D93 -> 1.0091901 | F93: =IF(AND(E93<=0),"C",IF(E93<=0.8,"A",IF(E93<=0.95,"B","C"))) -> C | G93: =VLOOKUP(B$4:B$104,I$4:M$104,5,0) -> C | I93: MANNA2111 | J93: =МАРТ!U64 -> 0 | K93: =J93/J$105 -> 0 | L93: =L92+K93 -> 0.99070416 | M93: =_xlfn.IFS(L93<80%,"A",L93<=95%,"B",L93>95%,"C") -> C
B94: Linhai Baiyi коричневая линза | C94: =МАРТ!AO86 -> -1946.832 | D94: =C94/C$105 -> -0.00036001824 | E94: =E93+D94 -> 1.0088301 | F94: =IF(AND(E94<=0),"C",IF(E94<=0.8,"A",IF(E94<=0.95,"B","C"))) -> C | G94: =VLOOKUP(B$4:B$104,I$4:M$104,5,0) -> C | I94: MANNA2112 | J94: =МАРТ!U65 -> 0 | K94: =J94/J$105 -> 0 | L94: =L93+K94 -> 0.99070416 | M94: =_xlfn.IFS(L94<80%,"A",L94<=95%,"B",L94>95%,"C") -> C
B95: sports зеленые | C95: =МАРТ!AO21 -> -2040.6397 | D95: =C95/C$105 -> -0.00037736565 | E95: =E94+D95 -> 1.0084527 | F95: =IF(AND(E95<=0),"C",IF(E95<=0.8,"A",IF(E95<=0.95,"B","C"))) -> C | G95: =VLOOKUP(B$4:B$104,I$4:M$104,5,0) -> C | I95: MANNA2113 | J95: =МАРТ!U66 -> 0 | K95: =J95/J$105 -> 0 | L95: =L94+K95 -> 0.99070416 | M95: =_xlfn.IFS(L95<80%,"A",L95<=95%,"B",L95>95%,"C") -> C
B96: WW 3055 коричневый | C96: =МАРТ!AO53 -> -2117.7827 | D96: =C96/C$105 -> -0.00039163132 | E96: =E95+D96 -> 1.0080611 | F96: =IF(AND(E96<=0),"C",IF(E96<=0.8,"A",IF(E96<=0.95,"B","C"))) -> C | G96: =VLOOKUP(B$4:B$104,I$4:M$104,5,0) -> C | I96: MANNA2115 | J96: =МАРТ!U68 -> 0 | K96: =J96/J$105 -> 0 | L96: =L95+K96 -> 0.99070416 | M96: =_xlfn.IFS(L96<80%,"A",L96<=95%,"B",L96>95%,"C") -> C
B97: MANNA2105 | C97: =МАРТ!AO58 -> -2667.9502 | D97: =C97/C$105 -> -0.00049337115 | E97: =E96+D97 -> 1.0075677 | F97: =IF(AND(E97<=0),"C",IF(E97<=0.8,"A",IF(E97<=0.95,"B","C"))) -> C | G97: =VLOOKUP(B$4:B$104,I$4:M$104,5,0) -> C | I97: MANNA2121 | J97: =МАРТ!U74 -> 0 | K97: =J97/J$105 -> 0 | L97: =L96+K97 -> 0.99070416 | M97: =_xlfn.IFS(L97<80%,"A",L97<=95%,"B",L97>95%,"C") -> C
B98: Keming Aishi коричневые | C98: =МАРТ!AO85 -> -2697.9025 | D98: =C98/C$105 -> -0.00049891008 | E98: =E97+D98 -> 1.0070688 | F98: =IF(AND(E98<=0),"C",IF(E98<=0.8,"A",IF(E98<=0.95,"B","C"))) -> C | G98: =VLOOKUP(B$4:B$104,I$4:M$104,5,0) -> C | I98: Taizhou Rayen sport розовый | J98: =МАРТ!U90 -> 0 | K98: =J98/J$105 -> 0 | L98: =L97+K98 -> 0.99070416 | M98: =_xlfn.IFS(L98<80%,"A",L98<=95%,"B",L98>95%,"C") -> C
B99: Chenlong белые | C99: =МАРТ!AO78 -> -3030.7804 | D99: =C99/C$105 -> -0.00056046758 | E99: =E93+D99 -> 1.0086296 | F99: =IF(AND(E99<=0),"C",IF(E99<=0.8,"A",IF(E99<=0.95,"B","C"))) -> C | G99: =VLOOKUP(B$4:B$104,I$4:M$104,5,0) -> C | I99: Ли Сян ретро золото | J99: =МАРТ!U92 -> 0 | K99: =J99/J$105 -> 0 | L99: =L93+K99 -> 0.99070416 | M99: =_xlfn.IFS(L99<80%,"A",L99<=95%,"B",L99>95%,"C") -> C
B100: Linhai Baiyi серая линза | C100: =МАРТ!AO87 -> -3671.7878 | D100: =C100/C$105 -> -0.00067900599 | E100: =E94+D100 -> 1.0081511 | F100: =IF(AND(E100<=0),"C",IF(E100<=0.8,"A",IF(E100<=0.95,"B","C"))) -> C | G100: =VLOOKUP(B$4:B$104,I$4:M$104,5,0) -> C | I100: MAIERSHA 03914 C9-124 | J100: =МАРТ!U95 -> 0 | K100: =J100/J$105 -> 0 | L100: =L94+K100 -> 0.99070416 | M100: =_xlfn.IFS(L100<80%,"A",L100<=95%,"B",L100>95%,"C") -> C
B101: Chenlong черные | C101: =МАРТ!AO76 -> -4009.1724 | D101: =C101/C$105 -> -0.00074139689 | E101: =E95+D101 -> 1.0077113 | F101: =IF(AND(E101<=0),"C",IF(E101<=0.8,"A",IF(E101<=0.95,"B","C"))) -> C | G101: =VLOOKUP(B$4:B$104,I$4:M$104,5,0) -> C | I101: MARSTON 7171 C1 | J101: =МАРТ!U96 -> 0 | K101: =J101/J$105 -> 0 | L101: =L95+K101 -> 0.99070416 | M101: =_xlfn.IFS(L101<80%,"A",L101<=95%,"B",L101>95%,"C") -> C
...

Sheet АВС 13
B2: ОЧКИ
C3: Прибыль | D3: % прибыль | E3: Доля | F3: ABC прибыль | G3: ABC кол-во | J3: Кол-во | K3: % кол-во | L3: Доля | M3: ABC кол-во
B4: QS черные PZ | C4: ='Юнит 13'!AO4 -> 348338.27 | D4: =C4/C$105 -> 0.21713153 | E4: =D4 -> 0.21713153 | F4: =IF(AND(E4<=0),"C",IF(E4<=0.8,"A",IF(E4<=0.95,"B","C"))) -> A | G4: =VLOOKUP(B$4:B$104,I$4:M$104,5,0) -> A | I4: QS черные PZ | J4: ='Юнит 13'!U4 -> 589 | K4: =J4/J$105 -> 0.16983852 | L4: =K4 -> 0.16983852 | M4: =_xlfn.IFS(L4<80%,"A",L4<=95%,"B",L4>95%,"C") -> A | P4: A | Q4: 0.8
B5: flip черные | C5: ='Юнит 13'!AO13 -> 160493.45 | D5: =C5/C$105 -> 0.10004123 | E5: =E4+D5 -> 0.31717276 | F5: =IF(AND(E5<=0),"C",IF(E5<=0.8,"A",IF(E5<=0.95,"B","C"))) -> A | G5: =VLOOKUP(B$4:B$104,I$4:M$104,5,0) -> A | I5: flip черные | J5: ='Юнит 13'!U13 -> 304 | K5: =J5/J$105 -> 0.087658593 | L5: =L4+K5 -> 0.25749712 | M5: =_xlfn.IFS(L5<80%,"A",L5<=95%,"B",L5>95%,"C") -> A | P5: B | Q5: 0.15
B6: th черн | C6: ='Юнит 13'!AO9 -> 152158.85 | D6: =C6/C$105 -> 0.094845977 | E6: =E5+D6 -> 0.41201873 | F6: =IF(AND(E6<=0),"C",IF(E6<=0.8,"A",IF(E6<=0.95,"B","C"))) -> A | G6: =VLOOKUP(B$4:B$104,I$4:M$104,5,0) -> A | I6: th черн | J6: ='Юнит 13'!U9 -> 301 | K6: =J6/J$105 -> 0.086793541 | L6: =L5+K6 -> 0.34429066 | M6: =_xlfn.IFS(L6<80%,"A",L6<=95%,"B",L6>95%,"C") -> A | P6: C | Q6: 0.05
B7: flip коричневые | C7: ='Юнит 13'!AO16 -> 125466.65 | D7: =C7/C$105 -> 0.078207789 | E7: =E6+D7 -> 0.49022652 | F7: =IF(AND(E7<=0),"C",IF(E7<=0.8,"A",IF(E7<=0.95,"B","C"))) -> A | G7: =VLOOKUP(B$4:B$104,I$4:M$104,5,0) -> A | I7: flip коричневые | J7: ='Юнит 13'!U16 -> 264 | K7: =J7/J$105 -> 0.076124567 | L7: =L6+K7 -> 0.42041522 | M7: =_xlfn.IFS(L7<80%,"A",L7<=95%,"B",L7>95%,"C") -> A
B8: QS коричневые PZ | C8: ='Юнит 13'!AO7 -> 106958 | D8: =C8/C$105 -> 0.066670694 | E8: =E7+D8 -> 0.55689722 | F8: =IF(AND(E8<=0),"C",IF(E8<=0.8,"A",IF(E8<=0.95,"B","C"))) -> A | G8: =VLOOKUP(B$4:B$104,I$4:M$104,5,0) -> A | I8: QS коричневые PZ | J8: ='Юнит 13'!U7 -> 245 | K8: =J8/J$105 -> 0.070645905 | L8: =L7+K8 -> 0.49106113 | M8: =_xlfn.IFS(L8<80%,"A",L8<=95%,"B",L8>95%,"C") -> A
B9: QS синие PZ | C9: ='Юнит 13'!AO5 -> 105310 | D9: =C9/C$105 -> 0.065643436 | E9: =E8+D9 -> 0.62254065 | F9: =IF(AND(E9<=0),"C",IF(E9<=0.8,"A",IF(E9<=0.95,"B","C"))) -> A | G9: =VLOOKUP(B$4:B$104,I$4:M$104,5,0) -> A | I9: th син | J9: ='Юнит 13'!U10 -> 211 | K9: =J9/J$105 -> 0.060841984 | L9: =L8+K9 -> 0.55190311 | M9: =_xlfn.IFS(L9<80%,"A",L9<=95%,"B",L9>95%,"C") -> A
B10: th коричн | C10: ='Юнит 13'!AO12 -> 93641.879 | D10: =C10/C$105 -> 0.058370287 | E10: =E9+D10 -> 0.68091094 | F10: =IF(AND(E10<=0),"C",IF(E10<=0.8,"A",IF(E10<=0.95,"B","C"))) -> A | G10: =VLOOKUP(B$4:B$104,I$4:M$104,5,0) -> A | I10: th коричн | J10: ='Юнит 13'!U12 -> 201 | K10: =J10/J$105 -> 0.057958478 | L10: =L9+K10 -> 0.60986159 | M10: =_xlfn.IFS(L10<80%,"A",L10<=95%,"B",L10>95%,"C") -> A
B11: черные с железкой классика | C11: ='Юнит 13'!AO3 -> 88818.696 | D11: =C11/C$105 -> 0.055363827 | E11: =E10+D11 -> 0.73627477 | F11: =IF(AND(E11<=0),"C",IF(E11<=0.8,"A",IF(E11<=0.95,"B","C"))) -> A | G11: =VLOOKUP(B$4:B$104,I$4:M$104,5,0) -> A | I11: QS синие PZ | J11: ='Юнит 13'!U5 -> 190 | K11: =J11/J$105 -> 0.054786621 | L11: =L10+K11 -> 0.66464821 | M11: =_xlfn.IFS(L11<80%,"A",L11<=95%,"B",L11>95%,"C") -> A
B12: th син | C12: ='Юнит 13'!AO10 -> 77988.707 | D12: =C12/C$105 -> 0.048613113 | E12: =E11+D12 -> 0.78488788 | F12: =IF(AND(E12<=0),"C",IF(E12<=0.8,"A",IF(E12<=0.95,"B","C"))) -> A | G12: =VLOOKUP(B$4:B$104,I$4:M$104,5,0) -> A | I12: черные с железкой классика | J12: ='Юнит 13'!U3 -> 173 | K12: =J12/J$105 -> 0.04988466 | L12: =L11+K12 -> 0.71453287 | M12: =_xlfn.IFS(L12<80%,"A",L12<=95%,"B",L12>95%,"C") -> A
B13: th желт | C13: ='Юнит 13'!AO11 -> 42145.967 | D13: =C13/C$105 -> 0.026271068 | E13: =E12+D13 -> 0.81115895 | F13: =IF(AND(E13<=0),"C",IF(E13<=0.8,"A",IF(E13<=0.95,"B","C"))) -> B | G13: =VLOOKUP(B$4:B$104,I$4:M$104,5,0) -> A | I13: th желт | J13: ='Юнит 13'!U11 -> 109 | K13: =J13/J$105 -> 0.031430219 | L13: =L12+K13 -> 0.74596309 | M13: =_xlfn.IFS(L13<80%,"A",L13<=95%,"B",L13>95%,"C") -> A
B14: flip синие | C14: ='Юнит 13'!AO14 -> 41306.469 | D14: =C14/C$105 -> 0.025747779 | E14: =E13+D14 -> 0.83690673 | F14: =IF(AND(E14<=0),"C",IF(E14<=0.8,"A",IF(E14<=0.95,"B","C"))) -> B | G14: =VLOOKUP(B$4:B$104,I$4:M$104,5,0) -> A | I14: sh3 | J14: ='Юнит 13'!U28 -> 92 | K14: =J14/J$105 -> 0.026528258 | L14: =L13+K14 -> 0.77249135 | M14: =_xlfn.IFS(L14<80%,"A",L14<=95%,"B",L14>95%,"C") -> A
B15: QS желтые PZ | C15: ='Юнит 13'!AO6 -> 38847.498 | D15: =C15/C$105 -> 0.024215016 | E15: =E14+D15 -> 0.86112174 | F15: =IF(AND(E15<=0),"C",IF(E15<=0.8,"A",IF(E15<=0.95,"B","C"))) -> B | G15: =VLOOKUP(B$4:B$104,I$4:M$104,5,0) -> B | I15: flip синие | J15: ='Юнит 13'!U14 -> 89 | K15: =J15/J$105 -> 0.025663206 | L15: =L14+K15 -> 0.79815456 | M15: =_xlfn.IFS(L15<80%,"A",L15<=95%,"B",L15>95%,"C") -> A
B16: sh3 | C16: ='Юнит 13'!AO28 -> 36184.931 | D16: =C16/C$105 -> 0.022555344 | E16: =E15+D16 -> 0.88367709 | F16: =IF(AND(E16<=0),"C",IF(E16<=0.8,"A",IF(E16<=0.95,"B","C"))) -> B | G16: =VLOOKUP(B$4:B$104,I$4:M$104,5,0) -> A | I16: QS желтые PZ | J16: ='Юнит 13'!U6 -> 83 | K16: =J16/J$105 -> 0.023933103 | L16: =L15+K16 -> 0.82208766 | M16: =_xlfn.IFS(L16<80%,"A",L16<=95%,"B",L16>95%,"C") -> B
B17: flip желтые | C17: ='Юнит 13'!AO15 -> 36032.316 | D17: =C17/C$105 -> 0.022460214 | E17: =E16+D17 -> 0.9061373 | F17: =IF(AND(E17<=0),"C",IF(E17<=0.8,"A",IF(E17<=0.95,"B","C"))) -> B | G17: =VLOOKUP(B$4:B$104,I$4:M$104,5,0) -> B | I17: flip желтые | J17: ='Юнит 13'!U15 -> 72 | K17: =J17/J$105 -> 0.020761246 | L17: =L16+K17 -> 0.8428489 | M17: =_xlfn.IFS(L17<80%,"A",L17<=95%,"B",L17>95%,"C") -> B
B18: wwl8032 хром металл | C18: ='Юнит 13'!AO18 -> 30112.708 | D18: =C18/C$105 -> 0.018770313 | E18: =E17+D18 -> 0.92490761 | F18: =IF(AND(E18<=0),"C",IF(E18<=0.8,"A",IF(E18<=0.95,"B","C"))) -> B | G18: =VLOOKUP(B$4:B$104,I$4:M$104,5,0) -> B | I18: ww 2018 черные | J18: ='Юнит 13'!U49 -> 70 | K18: =J18/J$105 -> 0.020184544 | L18: =L17+K18 -> 0.86303345 | M18: =_xlfn.IFS(L18<80%,"A",L18<=95%,"B",L18>95%,"C") -> B
B19: ww 2018 черные | C19: ='Юнит 13'!AO49 -> 29434.325 | D19: =C19/C$105 -> 0.018347453 | E19: =E18+D19 -> 0.94325507 | F19: =IF(AND(E19<=0),"C",IF(E19<=0.8,"A",IF(E19<=0.95,"B","C"))) -> B | G19: =VLOOKUP(B$4:B$104,I$4:M$104,5,0) -> B | I19: wwl8032 хром металл | J19: ='Юнит 13'!U18 -> 66 | K19: =J19/J$105 -> 0.019031142 | L19: =L18+K19 -> 0.88206459 | M19: =_xlfn.IFS(L19<80%,"A",L19<=95%,"B",L19>95%,"C") -> B
B20: MR8854 C2 Жен | C20: ='Юнит 13'!AO8 -> 21235.197 | D20: =C20/C$105 -> 0.013236647 | E20: =E19+D20 -> 0.95649171 | F20: =IF(AND(E20<=0),"C",IF(E20<=0.8,"A",IF(E20<=0.95,"B","C"))) -> C | G20: =VLOOKUP(B$4:B$104,I$4:M$104,5,0) -> B | I20: MR8854 C2 Жен | J20: ='Юнит 13'!U8 -> 57 | K20: =J20/J$105 -> 0.016435986 | L20: =L19+K20 -> 0.89850058 | M20: =_xlfn.IFS(L20<80%,"A",L20<=95%,"B",L20>95%,"C") -> B
B21: ww 2018 желтые | C21: ='Юнит 13'!AO50 -> 20080.235 | D21: =C21/C$105 -> 0.012516719 | E21: =E20+D21 -> 0.96900843 | F21: =IF(AND(E21<=0),"C",IF(E21<=0.8,"A",IF(E21<=0.95,"B","C"))) -> C | G21: =VLOOKUP(B$4:B$104,I$4:M$104,5,0) -> B | I21: ww 1022 коричневые | J21: ='Юнит 13'!U48 -> 57 | K21: =J21/J$105 -> 0.016435986 | L21: =L20+K21 -> 0.91493656 | M21: =_xlfn.IFS(L21<80%,"A",L21<=95%,"B",L21>95%,"C") -> B
B22: ww 203 черные | C22: ='Юнит 13'!AO44 -> 15977.062 | D22: =C22/C$105 -> 0.0099590664 | E22: =E21+D22 -> 0.9789675 | F22: =IF(AND(E22<=0),"C",IF(E22<=0.8,"A",IF(E22<=0.95,"B","C"))) -> C | G22: =VLOOKUP(B$4:B$104,I$4:M$104,5,0) -> B | I22: ww 203 черные | J22: ='Юнит 13'!U44 -> 52 | K22: =J22/J$105 -> 0.014994233 | L22: =L21+K22 -> 0.9299308 | M22: =_xlfn.IFS(L22<80%,"A",L22<=95%,"B",L22>95%,"C") -> B
B23: ww 1022 коричневые | C23: ='Юнит 13'!AO48 -> 15402.792 | D23: =C23/C$105 -> 0.0096011036 | E23: =E22+D23 -> 0.9885686 | F23: =IF(AND(E23<=0),"C",IF(E23<=0.8,"A",IF(E23<=0.95,"B","C"))) -> C | G23: =VLOOKUP(B$4:B$104,I$4:M$104,5,0) -> B | I23: ww 2018 желтые | J23: ='Юнит 13'!U50 -> 44 | K23: =J23/J$105 -> 0.012687428 | L23: =L22+K23 -> 0.94261822 | M23: =_xlfn.IFS(L23<80%,"A",L23<=95%,"B",L23>95%,"C") -> B
B24: wwl8032 коричневые золото | C24: ='Юнит 13'!AO17 -> 13744.004 | D24: =C24/C$105 -> 0.0085671225 | E24: =E23+D24 -> 0.99713573 | F24: =IF(AND(E24<=0),"C",IF(E24<=0.8,"A",IF(E24<=0.95,"B","C"))) -> C | G24: =VLOOKUP(B$4:B$104,I$4:M$104,5,0) -> C | I24: wwl8032 коричневые золото | J24: ='Юнит 13'!U17 -> 35 | K24: =J24/J$105 -> 0.010092272 | L24: =L23+K24 -> 0.9527105 | M24: =_xlfn.IFS(L24<80%,"A",L24<=95%,"B",L24>95%,"C") -> C
B25: ww 1022 черные | C25: ='Юнит 13'!AO45 -> 12318.776 | D25: =C25/C$105 -> 0.0076787277 | E25: =E24+D25 -> 1.0048145 | F25: =IF(AND(E25<=0),"C",IF(E25<=0.8,"A",IF(E25<=0.95,"B","C"))) -> C | G25: =VLOOKUP(B$4:B$104,I$4:M$104,5,0) -> C | I25: ww 1022 черные | J25: ='Юнит 13'!U45 -> 20 | K25: =J25/J$105 -> 0.0057670127 | L25: =L24+K25 -> 0.95847751 | M25: =_xlfn.IFS(L25<80%,"A",L25<=95%,"B",L25>95%,"C") -> C
B26: MR Р1894 черные | C26: ='Юнит 13'!AO89 -> 5131.1743 | D26: =C26/C$105 -> 0.003198442 | E26: =E25+D26 -> 1.0080129 | F26: =IF(AND(E26<=0),"C",IF(E26<=0.8,"A",IF(E26<=0.95,"B","C"))) -> C | G26: =VLOOKUP(B$4:B$104,I$4:M$104,5,0) -> C | I26: sh1 | J26: ='Юнит 13'!U26 -> 15 | K26: =J26/J$105 -> 0.0043252595 | L26: =L25+K26 -> 0.96280277 | M26: =_xlfn.IFS(L26<80%,"A",L26<=95%,"B",L26>95%,"C") -> C
B27: ww 1022 желтые | C27: ='Юнит 13'!AO47 -> 4167.7848 | D27: =C27/C$105 -> 0.0025979273 | E27: =E26+D27 -> 1.0106108 | F27: =IF(AND(E27<=0),"C",IF(E27<=0.8,"A",IF(E27<=0.95,"B","C"))) -> C | G27: =VLOOKUP(B$4:B$104,I$4:M$104,5,0) -> C | I27: кс_черные_женские | J27: ='Юнит 13'!U102 -> 12 | K27: =J27/J$105 -> 0.0034602076 | L27: =L26+K27 -> 0.96626298 | M27: =_xlfn.IFS(L27<80%,"A",L27<=95%,"B",L27>95%,"C") -> C
B28: sh16 | C28: ='Юнит 13'!AO40 -> 2833.6174 | D28: =C28/C$105 -> 0.0017662937 | E28: =E27+D28 -> 1.0123771 | F28: =IF(AND(E28<=0),"C",IF(E28<=0.8,"A",IF(E28<=0.95,"B","C"))) -> C | G28: =VLOOKUP(B$4:B$104,I$4:M$104,5,0) -> C | I28: MR Р1894 черные | J28: ='Юнит 13'!U89 -> 10 | K28: =J28/J$105 -> 0.0028835063 | L28: =L27+K28 -> 0.96914648 | M28: =_xlfn.IFS(L28<80%,"A",L28<=95%,"B",L28>95%,"C") -> C
B29: ЧСЖ_женские | C29: ='Юнит 13'!AO100 -> 2676.0157 | D29: =C29/C$105 -> 0.001668055 | E29: =E28+D29 -> 1.0140452 | F29: =IF(AND(E29<=0),"C",IF(E29<=0.8,"A",IF(E29<=0.95,"B","C"))) -> C | G29: =VLOOKUP(B$4:B$104,I$4:M$104,5,0) -> C | I29: ww 1022 желтые | J29: ='Юнит 13'!U47 -> 8 | K29: =J29/J$105 -> 0.0023068051 | L29: =L28+K29 -> 0.97145329 | M29: =_xlfn.IFS(L29<80%,"A",L29<=95%,"B",L29>95%,"C") -> C
B30: sh18 | C30: ='Юнит 13'!AO42 -> 2493.1364 | D30: =C30/C$105 -> 0.0015540599 | E30: =E29+D30 -> 1.0155992 | F30: =IF(AND(E30<=0),"C",IF(E30<=0.8,"A",IF(E30<=0.95,"B","C"))) -> C | G30: =VLOOKUP(B$4:B$104,I$4:M$104,5,0) -> C | I30: sh16 | J30: ='Юнит 13'!U40 -> 7 | K30: =J30/J$105 -> 0.0020184544 | L30: =L29+K30 -> 0.97347174 | M30: =_xlfn.IFS(L30<80%,"A",L30<=95%,"B",L30>95%,"C") -> C
B31: sh19 | C31: ='Юнит 13'!AO43 -> 2083.2306 | D31: =C31/C$105 -> 0.0012985511 | E31: =E30+D31 -> 1.0168978 | F31: =IF(AND(E31<=0),"C",IF(E31<=0.8,"A",IF(E31<=0.95,"B","C"))) -> C | G31: =VLOOKUP(B$4:B$104,I$4:M$104,5,0) -> C | I31: sh18 | J31: ='Юнит 13'!U42 -> 7 | K31: =J31/J$105 -> 0.0020184544 | L31: =L30+K31 -> 0.9754902 | M31: =_xlfn.IFS(L31<80%,"A",L31<=95%,"B",L31>95%,"C") -> C
B32: Linhai Baiyi серая линза | C32: ='Юнит 13'!AO87 -> 1585.7614 | D32: =C32/C$105 -> 0.00098846105 | E32: =E31+D32 -> 1.0178862 | F32: =IF(AND(E32<=0),"C",IF(E32<=0.8,"A",IF(E32<=0.95,"B","C"))) -> C | G32: =VLOOKUP(B$4:B$104,I$4:M$104,5,0) -> C | I32: Linhai Baiyi серая линза | J32: ='Юнит 13'!U87 -> 7 | K32: =J32/J$105 -> 0.0020184544 | L32: =L31+K32 -> 0.97750865 | M32: =_xlfn.IFS(L32<80%,"A",L32<=95%,"B",L32>95%,"C") -> C
B33: sh15 | C33: ='Юнит 13'!AO39 -> 1012.7332 | D33: =C33/C$105 -> 0.0006312723 | E33: =E32+D33 -> 1.0185175 | F33: =IF(AND(E33<=0),"C",IF(E33<=0.8,"A",IF(E33<=0.95,"B","C"))) -> C | G33: =VLOOKUP(B$4:B$104,I$4:M$104,5,0) -> C | I33: WW 3055 черный | J33: ='Юнит 13'!U52 -> 6 | K33: =J33/J$105 -> 0.0017301038 | L33: =L32+K33 -> 0.97923875 | M33: =_xlfn.IFS(L33<80%,"A",L33<=95%,"B",L33>95%,"C") -> C
B34: Qianai черные | C34: ='Юнит 13'!AO83 -> 833.08078 | D34: =C34/C$105 -> 0.00051928864 | E34: =E33+D34 -> 1.0190368 | F34: =IF(AND(E34<=0),"C",IF(E34<=0.8,"A",IF(E34<=0.95,"B","C"))) -> C | G34: =VLOOKUP(B$4:B$104,I$4:M$104,5,0) -> C | I34: sh19 | J34: ='Юнит 13'!U43 -> 5 | K34: =J34/J$105 -> 0.0014417532 | L34: =L33+K34 -> 0.98068051 | M34: =_xlfn.IFS(L34<80%,"A",L34<=95%,"B",L34>95%,"C") -> C
B35: MANNA2118 | C35: ='Юнит 13'!AO71 -> 805.10781 | D35: =C35/C$105 -> 0.0005018521 | E35: =E34+D35 -> 1.0195387 | F35: =IF(AND(E35<=0),"C",IF(E35<=0.8,"A",IF(E35<=0.95,"B","C"))) -> C | G35: =VLOOKUP(B$4:B$104,I$4:M$104,5,0) -> C | I35: WW 3055 коричневый | J35: ='Юнит 13'!U53 -> 5 | K35: =J35/J$105 -> 0.0014417532 | L35: =L34+K35 -> 0.98212226 | M35: =_xlfn.IFS(L35<80%,"A",L35<=95%,"B",L35>95%,"C") -> C
B36: MANNA2117 | C36: ='Юнит 13'!AO70 -> 795.5848 | D36: =C36/C$105 -> 0.00049591607 | E36: =E35+D36 -> 1.0200346 | F36: =IF(AND(E36<=0),"C",IF(E36<=0.8,"A",IF(E36<=0.95,"B","C"))) -> C | G36: =VLOOKUP(B$4:B$104,I$4:M$104,5,0) -> C | I36: MANNA2118 | J36: ='Юнит 13'!U71 -> 5 | K36: =J36/J$105 -> 0.0014417532 | L36: =L35+K36 -> 0.98356401 | M36: =_xlfn.IFS(L36<80%,"A",L36<=95%,"B",L36>95%,"C") -> C
B37: MANNA2101 | C37: ='Юнит 13'!AO54 -> 767.04556 | D37: =C37/C$105 -> 0.00047812656 | E37: =E36+D37 -> 1.0205127 | F37: =IF(AND(E37<=0),"C",IF(E37<=0.8,"A",IF(E37<=0.95,"B","C"))) -> C | G37: =VLOOKUP(B$4:B$104,I$4:M$104,5,0) -> C | I37: ЧСЖ_женские | J37: ='Юнит 13'!U100 -> 5 | K37: =J37/J$105 -> 0.0014417532 | L37: =L36+K37 -> 0.98500577 | M37: =_xlfn.IFS(L37<80%,"A",L37<=95%,"B",L37>95%,"C") -> C
B38: Hengda Optical леопард | C38: ='Юнит 13'!AO82 -> 701.6129 | D38: =C38/C$105 -> 0.00043734007 | E38: =E37+D38 -> 1.02095 | F38: =IF(AND(E38<=0),"C",IF(E38<=0.8,"A",IF(E38<=0.95,"B","C"))) -> C | G38: =VLOOKUP(B$4:B$104,I$4:M$104,5,0) -> C | I38: sh2 | J38: ='Юнит 13'!U27 -> 4 | K38: =J38/J$105 -> 0.0011534025 | L38: =L37+K38 -> 0.98615917 | M38: =_xlfn.IFS(L38<80%,"A",L38<=95%,"B",L38>95%,"C") -> C
B39: WW 3055 черный | C39: ='Юнит 13'!AO52 -> 647.65236 | D39: =C39/C$105 -> 0.00040370456 | E39: =E35+D39 -> 1.0199424 | F39: =IF(AND(E39<=0),"C",IF(E39<=0.8,"A",IF(E39<=0.95,"B","C"))) -> C | G39: =VLOOKUP(B$4:B$104,I$4:M$104,5,0) -> C | I39: sh15 | J39: ='Юнит 13'!U39 -> 4 | K39: =J39/J$105 -> 0.0011534025 | L39: =L35+K39 -> 0.98327566 | M39: =_xlfn.IFS(L39<80%,"A",L39<=95%,"B",L39>95%,"C") -> C
B40: Hengda Optical черные | C40: ='Юнит 13'!AO81 -> 635.16916 | D40: =C40/C$105 -> 0.00039592334 | E40: =E39+D40 -> 1.0203383 | F40: =IF(AND(E40<=0),"C",IF(E40<=0.8,"A",IF(E40<=0.95,"B","C"))) -> C | G40: =VLOOKUP(B$4:B$104,I$4:M$104,5,0) -> C | I40: MANNA2101 | J40: ='Юнит 13'!U54 -> 4 | K40: =J40/J$105 -> 0.0011534025 | L40: =L39+K40 -> 0.98442907 | M40: =_xlfn.IFS(L40<80%,"A",L40<=95%,"B",L40>95%,"C") -> C
B41: MANNA2114 | C41: ='Юнит 13'!AO67 -> 377.1784 | D41: =C41/C$105 -> 0.0002351086 | E41: =E40+D41 -> 1.0205734 | F41: =IF(AND(E41<=0),"C",IF(E41<=0.8,"A",IF(E41<=0.95,"B","C"))) -> C | G41: =VLOOKUP(B$4:B$104,I$4:M$104,5,0) -> C | I41: Chenlong черные | J41: ='Юнит 13'!U76 -> 4 | K41: =J41/J$105 -> 0.0011534025 | L41: =L40+K41 -> 0.98558247 | M41: =_xlfn.IFS(L41<80%,"A",L41<=95%,"B",L41>95%,"C") -> C
B42: sh14 | C42: ='Юнит 13'!AO38 -> 365.11096 | D42: =C42/C$105 -> 0.00022758654 | E42: =E41+D42 -> 1.020801 | F42: =IF(AND(E42<=0),"C",IF(E42<=0.8,"A",IF(E42<=0.95,"B","C"))) -> C | G42: =VLOOKUP(B$4:B$104,I$4:M$104,5,0) -> C | I42: sh09 | J42: ='Юнит 13'!U33 -> 3 | K42: =J42/J$105 -> 0.0008650519 | L42: =L41+K42 -> 0.98644752 | M42: =_xlfn.IFS(L42<80%,"A",L42<=95%,"B",L42>95%,"C") -> C
B43: sportlife синие | C43: ='Юнит 13'!AO24 -> 346.0091 | D43: =C43/C$105 -> 0.00021567968 | E43: =E42+D43 -> 1.0210167 | F43: =IF(AND(E43<=0),"C",IF(E43<=0.8,"A",IF(E43<=0.95,"B","C"))) -> C | G43: =VLOOKUP(B$4:B$104,I$4:M$104,5,0) -> C | I43: MANNA2105 | J43: ='Юнит 13'!U58 -> 3 | K43: =J43/J$105 -> 0.0008650519 | L43: =L42+K43 -> 0.98731257 | M43: =_xlfn.IFS(L43<80%,"A",L43<=95%,"B",L43>95%,"C") -> C
B44: sh10 | C44: ='Юнит 13'!AO34 -> 328.99 | D44: =C44/C$105 -> 0.00020507107 | E44: =E43+D44 -> 1.0212217 | F44: =IF(AND(E44<=0),"C",IF(E44<=0.8,"A",IF(E44<=0.95,"B","C"))) -> C | G44: =VLOOKUP(B$4:B$104,I$4:M$104,5,0) -> C | I44: Hengda Optical черные | J44: ='Юнит 13'!U81 -> 3 | K44: =J44/J$105 -> 0.0008650519 | L44: =L43+K44 -> 0.98817762 | M44: =_xlfn.IFS(L44<80%,"A",L44<=95%,"B",L44>95%,"C") -> C
B45: ww 8010 черные | C45: ='Юнит 13'!AO51 -> 290.249 | D45: =C45/C$105 -> 0.00018092244 | E45: =E44+D45 -> 1.0214027 | F45: =IF(AND(E45<=0),"C",IF(E45<=0.8,"A",IF(E45<=0.95,"B","C"))) -> C | G45: =VLOOKUP(B$4:B$104,I$4:M$104,5,0) -> C | I45: sports синие | J45: ='Юнит 13'!U20 -> 2 | K45: =J45/J$105 -> 0.00057670127 | L45: =L44+K45 -> 0.98875433 | M45: =_xlfn.IFS(L45<80%,"A",L45<=95%,"B",L45>95%,"C") -> C
B46: MANNA2105 | C46: ='Юнит 13'!AO58 -> 260.32428 | D46: =C46/C$105 -> 0.00016226931 | E46: =E45+D46 -> 1.0215649 | F46: =IF(AND(E46<=0),"C",IF(E46<=0.8,"A",IF(E46<=0.95,"B","C"))) -> C | G46: =VLOOKUP(B$4:B$104,I$4:M$104,5,0) -> C | I46: sh14 | J46: ='Юнит 13'!U38 -> 2 | K46: =J46/J$105 -> 0.00057670127 | L46: =L45+K46 -> 0.98933103 | M46: =_xlfn.IFS(L46<80%,"A",L46<=95%,"B",L46>95%,"C") -> C
B47: Linhai Baiyi розовая линза | C47: ='Юнит 13'!AO88 -> 140.04124 | D47: =C47/C$105 -> 8.7292645e-05 | E47: =E46+D47 -> 1.0216522 | F47: =IF(AND(E47<=0),"C",IF(E47<=0.8,"A",IF(E47<=0.95,"B","C"))) -> C | G47: =VLOOKUP(B$4:B$104,I$4:M$104,5,0) -> C | I47: MANNA2117 | J47: ='Юнит 13'!U70 -> 2 | K47: =J47/J$105 -> 0.00057670127 | L47: =L46+K47 -> 0.98990773 | M47: =_xlfn.IFS(L47<80%,"A",L47<=95%,"B",L47>95%,"C") -> C
B48: MANNA2107 | C48: ='Юнит 13'!AO60 -> 134.91042 | D48: =C48/C$105 -> 8.4094422e-05 | E48: =E47+D48 -> 1.0217363 | F48: =IF(AND(E48<=0),"C",IF(E48<=0.8,"A",IF(E48<=0.95,"B","C"))) -> C | G48: =VLOOKUP(B$4:B$104,I$4:M$104,5,0) -> C | I48: Guangdu золото серая линза | J48: ='Юнит 13'!U79 -> 2 | K48: =J48/J$105 -> 0.00057670127 | L48: =L47+K48 -> 0.99048443 | M48: =_xlfn.IFS(L48<80%,"A",L48<=95%,"B",L48>95%,"C") -> C
B49: MANNA2120 | C49: ='Юнит 13'!AO73 -> 115.4508 | D49: =C49/C$105 -> 7.1964557e-05 | E49: =E48+D49 -> 1.0218083 | F49: =IF(AND(E49<=0),"C",IF(E49<=0.8,"A",IF(E49<=0.95,"B","C"))) -> C | G49: =VLOOKUP(B$4:B$104,I$4:M$104,5,0) -> C | I49: Guangdu серебро серая линза | J49: ='Юнит 13'!U80 -> 2 | K49: =J49/J$105 -> 0.00057670127 | L49: =L48+K49 -> 0.99106113 | M49: =_xlfn.IFS(L49<80%,"A",L49<=95%,"B",L49>95%,"C") -> C
B50: wwl8032 черные серебро | C50: ='Юнит 13'!AO19 -> 0 | D50: =C50/C$105 -> 0 | E50: =E49+D50 -> 1.0218083 | F50: =IF(AND(E50<=0),"C",IF(E50<=0.8,"A",IF(E50<=0.95,"B","C"))) -> C | G50: =VLOOKUP(B$4:B$104,I$4:M$104,5,0) -> C | I50: Hengda Optical леопард | J50: ='Юнит 13'!U82 -> 2 | K50: =J50/J$105 -> 0.00057670127 | L50: =L49+K50 -> 0.99163783 | M50: =_xlfn.IFS(L50<80%,"A",L50<=95%,"B",L50>95%,"C") -> C
B51: sportlife черные | C51: ='Юнит 13'!AO23 -> 0 | D51: =C51/C$105 -> 0 | E51: =E50+D51 -> 1.0218083 | F51: =IF(AND(E51<=0),"C",IF(E51<=0.8,"A",IF(E51<=0.95,"B","C"))) -> C | G51: =VLOOKUP(B$4:B$104,I$4:M$104,5,0) -> C | I51: Qianai черные | J51: ='Юнит 13'!U83 -> 2 | K51: =J51/J$105 -> 0.00057670127 | L51: =L50+K51 -> 0.99221453 | M51: =_xlfn.IFS(L51<80%,"A",L51<=95%,"B",L51>95%,"C") -> C
B52: sportlife красные | C52: ='Юнит 13'!AO25 -> 0 | D52: =C52/C$105 -> 0 | E52: =E51+D52 -> 1.0218083 | F52: =IF(AND(E52<=0),"C",IF(E52<=0.8,"A",IF(E52<=0.95,"B","C"))) -> C | G52: =VLOOKUP(B$4:B$104,I$4:M$104,5,0) -> C | I52: Keming Aishi коричневые | J52: ='Юнит 13'!U85 -> 2 | K52: =J52/J$105 -> 0.00057670127 | L52: =L51+K52 -> 0.99279123 | M52: =_xlfn.IFS(L52<80%,"A",L52<=95%,"B",L52>95%,"C") -> C
B53: sh4 | C53: ='Юнит 13'!AO29 -> 0 | D53: =C53/C$105 -> 0 | E53: =E52+D53 -> 1.0218083 | F53: =IF(AND(E53<=0),"C",IF(E53<=0.8,"A",IF(E53<=0.95,"B","C"))) -> C | G53: =VLOOKUP(B$4:B$104,I$4:M$104,5,0) -> C | I53: sports красные | J53: ='Юнит 13'!U22 -> 1 | K53: =J53/J$105 -> 0.00028835063 | L53: =L52+K53 -> 0.99307958 | M53: =_xlfn.IFS(L53<80%,"A",L53<=95%,"B",L53>95%,"C") -> C
B54: sh06 | C54: ='Юнит 13'!AO30 -> 0 | D54: =C54/C$105 -> 0 | E54: =E53+D54 -> 1.0218083 | F54: =IF(AND(E54<=0),"C",IF(E54<=0.8,"A",IF(E54<=0.95,"B","C"))) -> C | G54: =VLOOKUP(B$4:B$104,I$4:M$104,5,0) -> C | I54: sportlife синие | J54: ='Юнит 13'!U24 -> 1 | K54: =J54/J$105 -> 0.00028835063 | L54: =L53+K54 -> 0.99336794 | M54: =_xlfn.IFS(L54<80%,"A",L54<=95%,"B",L54>95%,"C") -> C
B55: sh07 | C55: ='Юнит 13'!AO31 -> 0 | D55: =C55/C$105 -> 0 | E55: =E54+D55 -> 1.0218083 | F55: =IF(AND(E55<=0),"C",IF(E55<=0.8,"A",IF(E55<=0.95,"B","C"))) -> C | G55: =VLOOKUP(B$4:B$104,I$4:M$104,5,0) -> C | I55: sh10 | J55: ='Юнит 13'!U34 -> 1 | K55: =J55/J$105 -> 0.00028835063 | L55: =L54+K55 -> 0.99365629 | M55: =_xlfn.IFS(L55<80%,"A",L55<=95%,"B",L55>95%,"C") -> C
B56: sh08 | C56: ='Юнит 13'!AO32 -> 0 | D56: =C56/C$105 -> 0 | E56: =E55+D56 -> 1.0218083 | F56: =IF(AND(E56<=0),"C",IF(E56<=0.8,"A",IF(E56<=0.95,"B","C"))) -> C | G56: =VLOOKUP(B$4:B$104,I$4:M$104,5,0) -> C | I56: ww 8010 черные | J56: ='Юнит 13'!U51 -> 1 | K56: =J56/J$105 -> 0.00028835063 | L56: =L55+K56 -> 0.99394464 | M56: =_xlfn.IFS(L56<80%,"A",L56<=95%,"B",L56>95%,"C") -> C
B57: sh11 | C57: ='Юнит 13'!AO35 -> 0 | D57: =C57/C$105 -> 0 | E57: =E56+D57 -> 1.0218083 | F57: =IF(AND(E57<=0),"C",IF(E57<=0.8,"A",IF(E57<=0.95,"B","C"))) -> C | G57: =VLOOKUP(B$4:B$104,I$4:M$104,5,0) -> C | I57: MANNA2107 | J57: ='Юнит 13'!U60 -> 1 | K57: =J57/J$105 -> 0.00028835063 | L57: =L56+K57 -> 0.99423299 | M57: =_xlfn.IFS(L57<80%,"A",L57<=95%,"B",L57>95%,"C") -> C
B58: sh12 | C58: ='Юнит 13'!AO36 -> 0 | D58: =C58/C$105 -> 0 | E58: =E57+D58 -> 1.0218083 | F58: =IF(AND(E58<=0),"C",IF(E58<=0.8,"A",IF(E58<=0.95,"B","C"))) -> C | G58: =VLOOKUP(B$4:B$104,I$4:M$104,5,0) -> C | I58: MANNA2114 | J58: ='Юнит 13'!U67 -> 1 | K58: =J58/J$105 -> 0.00028835063 | L58: =L57+K58 -> 0.99452134 | M58: =_xlfn.IFS(L58<80%,"A",L58<=95%,"B",L58>95%,"C") -> C
B59: ww 1022 черн-серебро | C59: ='Юнит 13'!AO46 -> 0 | D59: =C59/C$105 -> 0 | E59: =E58+D59 -> 1.0218083 | F59: =IF(AND(E59<=0),"C",IF(E59<=0.8,"A",IF(E59<=0.95,"B","C"))) -> C | G59: =VLOOKUP(B$4:B$104,I$4:M$104,5,0) -> C | I59: MANNA2120 | J59: ='Юнит 13'!U73 -> 1 | K59: =J59/J$105 -> 0.00028835063 | L59: =L58+K59 -> 0.99480969 | M59: =_xlfn.IFS(L59<80%,"A",L59<=95%,"B",L59>95%,"C") -> C
B60: MANNA2102 | C60: ='Юнит 13'!AO55 -> 0 | D60: =C60/C$105 -> 0 | E60: =E59+D60 -> 1.0218083 | F60: =IF(AND(E60<=0),"C",IF(E60<=0.8,"A",IF(E60<=0.95,"B","C"))) -> C | G60: =VLOOKUP(B$4:B$104,I$4:M$104,5,0) -> C | I60: MANNA2122 | J60: ='Юнит 13'!U75 -> 1 | K60: =J60/J$105 -> 0.00028835063 | L60: =L59+K60 -> 0.99509804 | M60: =_xlfn.IFS(L60<80%,"A",L60<=95%,"B",L60>95%,"C") -> C
B61: MANNA2103 | C61: ='Юнит 13'!AO56 -> 0 | D61: =C61/C$105 -> 0 | E61: =E60+D61 -> 1.0218083 | F61: =IF(AND(E61<=0),"C",IF(E61<=0.8,"A",IF(E61<=0.95,"B","C"))) -> C | G61: =VLOOKUP(B$4:B$104,I$4:M$104,5,0) -> C | I61: Chenlong коричневые | J61: ='Юнит 13'!U77 -> 1 | K61: =J61/J$105 -> 0.00028835063 | L61: =L60+K61 -> 0.99538639 | M61: =_xlfn.IFS(L61<80%,"A",L61<=95%,"B",L61>95%,"C") -> C
B62: MANNA2104 | C62: ='Юнит 13'!AO57 -> 0 | D62: =C62/C$105 -> 0 | E62: =E61+D62 -> 1.0218083 | F62: =IF(AND(E62<=0),"C",IF(E62<=0.8,"A",IF(E62<=0.95,"B","C"))) -> C | G62: =VLOOKUP(B$4:B$104,I$4:M$104,5,0) -> C | I62: Qianai коричневые | J62: ='Юнит 13'!U84 -> 1 | K62: =J62/J$105 -> 0.00028835063 | L62: =L61+K62 -> 0.99567474 | M62: =_xlfn.IFS(L62<80%,"A",L62<=95%,"B",L62>95%,"C") -> C
B63: MANNA2106 | C63: ='Юнит 13'!AO59 -> 0 | D63: =C63/C$105 -> 0 | E63: =E62+D63 -> 1.0218083 | F63: =IF(AND(E63<=0),"C",IF(E63<=0.8,"A",IF(E63<=0.95,"B","C"))) -> C | G63: =VLOOKUP(B$4:B$104,I$4:M$104,5,0) -> C | I63: Linhai Baiyi розовая линза | J63: ='Юнит 13'!U88 -> 1 | K63: =J63/J$105 -> 0.00028835063 | L63: =L62+K63 -> 0.99596309 | M63: =_xlfn.IFS(L63<80%,"A",L63<=95%,"B",L63>95%,"C") -> C
B64: MANNA2109 | C64: ='Юнит 13'!AO62 -> 0 | D64: =C64/C$105 -> 0 | E64: =E63+D64 -> 1.0218083 | F64: =IF(AND(E64<=0),"C",IF(E64<=0.8,"A",IF(E64<=0.95,"B","C"))) -> C | G64: =VLOOKUP(B$4:B$104,I$4:M$104,5,0) -> C | I64: Иу Диту серый | J64: ='Юнит 13'!U91 -> 1 | K64: =J64/J$105 -> 0.00028835063 | L64: =L63+K64 -> 0.99625144 | M64: =_xlfn.IFS(L64<80%,"A",L64<=95%,"B",L64>95%,"C") -> C
B65: MANNA2110 | C65: ='Юнит 13'!AO63 -> 0 | D65: =C65/C$105 -> 0 | E65: =E64+D65 -> 1.0218083 | F65: =IF(AND(E65<=0),"C",IF(E65<=0.8,"A",IF(E65<=0.95,"B","C"))) -> C | G65: =VLOOKUP(B$4:B$104,I$4:M$104,5,0) -> C | I65: wwl8032 черные серебро | J65: ='Юнит 13'!U19 -> 0 | K65: =J65/J$105 -> 0 | L65: =L64+K65 -> 0.99625144 | M65: =_xlfn.IFS(L65<80%,"A",L65<=95%,"B",L65>95%,"C") -> C
B66: MANNA2111 | C66: ='Юнит 13'!AO64 -> 0 | D66: =C66/C$105 -> 0 | E66: =E65+D66 -> 1.0218083 | F66: =IF(AND(E66<=0),"C",IF(E66<=0.8,"A",IF(E66<=0.95,"B","C"))) -> C | G66: =VLOOKUP(B$4:B$104,I$4:M$104,5,0) -> C | I66: sports зеленые | J66: ='Юнит 13'!U21 -> 0 | K66: =J66/J$105 -> 0 | L66: =L65+K66 -> 0.99625144 | M66: =_xlfn.IFS(L66<80%,"A",L66<=95%,"B",L66>95%,"C") -> C
B67: MANNA2115 | C67: ='Юнит 13'!AO68 -> 0 | D67: =C67/C$105 -> 0 | E67: =E66+D67 -> 1.0218083 | F67: =IF(AND(E67<=0),"C",IF(E67<=0.8,"A",IF(E67<=0.95,"B","C"))) -> C | G67: =VLOOKUP(B$4:B$104,I$4:M$104,5,0) -> C | I67: sportlife черные | J67: ='Юнит 13'!U23 -> 0 | K67: =J67/J$105 -> 0 | L67: =L66+K67 -> 0.99625144 | M67: =_xlfn.IFS(L67<80%,"A",L67<=95%,"B",L67>95%,"C") -> C
B68: MANNA2121 | C68: ='Юнит 13'!AO74 -> 0 | D68: =C68/C$105 -> 0 | E68: =E67+D68 -> 1.0218083 | F68: =IF(AND(E68<=0),"C",IF(E68<=0.8,"A",IF(E68<=0.95,"B","C"))) -> C | G68: =VLOOKUP(B$4:B$104,I$4:M$104,5,0) -> C | I68: sportlife красные | J68: ='Юнит 13'!U25 -> 0 | K68: =J68/J$105 -> 0 | L68: =L67+K68 -> 0.99625144 | M68: =_xlfn.IFS(L68<80%,"A",L68<=95%,"B",L68>95%,"C") -> C
B69: MAIERSHA 03898 C9-08 | C69: ='Юнит 13'!AO94 -> 0 | D69: =C69/C$105 -> 0 | E69: =E68+D69 -> 1.0218083 | F69: =IF(AND(E69<=0),"C",IF(E69<=0.8,"A",IF(E69<=0.95,"B","C"))) -> C | G69: =VLOOKUP(B$4:B$104,I$4:M$104,5,0) -> C | I69: sh4 | J69: ='Юнит 13'!U29 -> 0 | K69: =J69/J$105 -> 0 | L69: =L68+K69 -> 0.99625144 | M69: =_xlfn.IFS(L69<80%,"A",L69<=95%,"B",L69>95%,"C") -> C
B70: MAIERSHA 03914 C9-124 | C70: ='Юнит 13'!AO95 -> 0 | D70: =C70/C$105 -> 0 | E70: =E69+D70 -> 1.0218083 | F70: =IF(AND(E70<=0),"C",IF(E70<=0.8,"A",IF(E70<=0.95,"B","C"))) -> C | G70: =VLOOKUP(B$4:B$104,I$4:M$104,5,0) -> C | I70: sh06 | J70: ='Юнит 13'!U30 -> 0 | K70: =J70/J$105 -> 0 | L70: =L69+K70 -> 0.99625144 | M70: =_xlfn.IFS(L70<80%,"A",L70<=95%,"B",L70>95%,"C") -> C
B71: MARSTON 7171 C1 | C71: ='Юнит 13'!AO96 -> 0 | D71: =C71/C$105 -> 0 | E71: =E70+D71 -> 1.0218083 | F71: =IF(AND(E71<=0),"C",IF(E71<=0.8,"A",IF(E71<=0.95,"B","C"))) -> C | G71: =VLOOKUP(B$4:B$104,I$4:M$104,5,0) -> C | I71: sh07 | J71: ='Юнит 13'!U31 -> 0 | K71: =J71/J$105 -> 0 | L71: =L70+K71 -> 0.99625144 | M71: =_xlfn.IFS(L71<80%,"A",L71<=95%,"B",L71>95%,"C") -> C
B72: ЧСЖ_тест | C72: ='Юнит 13'!AO99 -> 0 | D72: =C72/C$105 -> 0 | E72: =E71+D72 -> 1.0218083 | F72: =IF(AND(E72<=0),"C",IF(E72<=0.8,"A",IF(E72<=0.95,"B","C"))) -> C | G72: =VLOOKUP(B$4:B$104,I$4:M$104,5,0) -> C | I72: sh08 | J72: ='Юнит 13'!U32 -> 0 | K72: =J72/J$105 -> 0 | L72: =L71+K72 -> 0.99625144 | M72: =_xlfn.IFS(L72<80%,"A",L72<=95%,"B",L72>95%,"C") -> C
B73: кс_черные_тест | C73: ='Юнит 13'!AO101 -> 0 | D73: =C73/C$105 -> 0 | E73: =E72+D73 -> 1.0218083 | F73: =IF(AND(E73<=0),"C",IF(E73<=0.8,"A",IF(E73<=0.95,"B","C"))) -> C | G73: =VLOOKUP(B$4:B$104,I$4:M$104,5,0) -> C | I73: sh11 | J73: ='Юнит 13'!U35 -> 0 | K73: =J73/J$105 -> 0 | L73: =L72+K73 -> 0.99625144 | M73: =_xlfn.IFS(L73<80%,"A",L73<=95%,"B",L73>95%,"C") -> C
B74: 1022_коричневые_тест | C74: ='Юнит 13'!AO103 -> 0 | D74: =C74/C$105 -> 0 | E74: =E73+D74 -> 1.0218083 | F74: =IF(AND(E74<=0),"C",IF(E74<=0.8,"A",IF(E74<=0.95,"B","C"))) -> C | G74: =VLOOKUP(B$4:B$104,I$4:M$104,5,0) -> C | I74: sh12 | J74: ='Юнит 13'!U36 -> 0 | K74: =J74/J$105 -> 0 | L74: =L73+K74 -> 0.99625144 | M74: =_xlfn.IFS(L74<80%,"A",L74<=95%,"B",L74>95%,"C") -> C
B75: MANNA2113 | C75: ='Юнит 13'!AO66 -> -1.6933222 | D75: =C75/C$105 -> -1.0555074e-06 | E75: =E74+D75 -> 1.0218072 | F75: =IF(AND(E75<=0),"C",IF(E75<=0.8,"A",IF(E75<=0.95,"B","C"))) -> C | G75: =VLOOKUP(B$4:B$104,I$4:M$104,5,0) -> C | I75: sh13 | J75: ='Юнит 13'!U37 -> 0 | K75: =J75/J$105 -> 0 | L75: =L74+K75 -> 0.99625144 | M75: =_xlfn.IFS(L75<80%,"A",L75<=95%,"B",L75>95%,"C") -> C
B76: Taizhou Rayen sport розовый | C76: ='Юнит 13'!AO90 -> -41.486393 | D76: =C76/C$105 -> -2.5859932e-05 | E76: =E49+D76 -> 1.0217824 | F76: =IF(AND(E76<=0),"C",IF(E76<=0.8,"A",IF(E76<=0.95,"B","C"))) -> C | G76: =VLOOKUP(B$4:B$104,I$4:M$104,5,0) -> C | I76: sh17 | J76: ='Юнит 13'!U41 -> 0 | K76: =J76/J$105 -> 0 | L76: =L49+K76 -> 0.99106113 | M76: =_xlfn.IFS(L76<80%,"A",L76<=95%,"B",L76>95%,"C") -> C
B77: MANNA2112 | C77: ='Юнит 13'!AO65 -> -64.986661 | D77: =C77/C$105 -> -4.0508478e-05 | E77: =E76+D77 -> 1.0217419 | F77: =IF(AND(E77<=0),"C",IF(E77<=0.8,"A",IF(E77<=0.95,"B","C"))) -> C | G77: =VLOOKUP(B$4:B$104,I$4:M$104,5,0) -> C | I77: ww 1022 черн-серебро | J77: ='Юнит 13'!U46 -> 0 | K77: =J77/J$105 -> 0 | L77: =L76+K77 -> 0.99106113 | M77: =_xlfn.IFS(L77<80%,"A",L77<=95%,"B",L77>95%,"C") -> C
B78: MANNA2116 | C78: ='Юнит 13'!AO69 -> -80.093305 | D78: =C78/C$105 -> -4.9924983e-05 | E78: =E77+D78 -> 1.021692 | F78: =IF(AND(E78<=0),"C",IF(E78<=0.8,"A",IF(E78<=0.95,"B","C"))) -> C | G78: =VLOOKUP(B$4:B$104,I$4:M$104,5,0) -> C | I78: MANNA2102 | J78: ='Юнит 13'!U55 -> 0 | K78: =J78/J$105 -> 0 | L78: =L77+K78 -> 0.99106113 | M78: =_xlfn.IFS(L78<80%,"A",L78<=95%,"B",L78>95%,"C") -> C
B79: YIMEI 2391 C1 | C79: ='Юнит 13'!AO98 -> -85.173272 | D79: =C79/C$105 -> -5.3091505e-05 | E79: =E78+D79 -> 1.0216389 | F79: =IF(AND(E79<=0),"C",IF(E79<=0.8,"A",IF(E79<=0.95,"B","C"))) -> C | G79: =VLOOKUP(B$4:B$104,I$4:M$104,5,0) -> C | I79: MANNA2103 | J79: ='Юнит 13'!U56 -> 0 | K79: =J79/J$105 -> 0 | L79: =L78+K79 -> 0.99106113 | M79: =_xlfn.IFS(L79<80%,"A",L79<=95%,"B",L79>95%,"C") -> C
B80: MANNA2119 | C80: ='Юнит 13'!AO72 -> -86.11 | D80: =C80/C$105 -> -5.3675401e-05 | E80: =E79+D80 -> 1.0215852 | F80: =IF(AND(E80<=0),"C",IF(E80<=0.8,"A",IF(E80<=0.95,"B","C"))) -> C | G80: =VLOOKUP(B$4:B$104,I$4:M$104,5,0) -> C | I80: MANNA2104 | J80: ='Юнит 13'!U57 -> 0 | K80: =J80/J$105 -> 0 | L80: =L79+K80 -> 0.99106113 | M80: =_xlfn.IFS(L80<80%,"A",L80<=95%,"B",L80>95%,"C") -> C
B81: sh13 | C81: ='Юнит 13'!AO37 -> -94.9 | D81: =C81/C$105 -> -5.9154518e-05 | E81: =E80+D81 -> 1.0215261 | F81: =IF(AND(E81<=0),"C",IF(E81<=0.8,"A",IF(E81<=0.95,"B","C"))) -> C | G81: =VLOOKUP(B$4:B$104,I$4:M$104,5,0) -> C | I81: MANNA2106 | J81: ='Юнит 13'!U59 -> 0 | K81: =J81/J$105 -> 0 | L81: =L80+K81 -> 0.99106113 | M81: =_xlfn.IFS(L81<80%,"A",L81<=95%,"B",L81>95%,"C") -> C
B82: POMILED 08247 C4-08 | C82: ='Юнит 13'!AO97 -> -149.29 | D82: =C82/C$105 -> -9.3057724e-05 | E82: =E81+D82 -> 1.021433 | F82: =IF(AND(E82<=0),"C",IF(E82<=0.8,"A",IF(E82<=0.95,"B","C"))) -> C | G82: =VLOOKUP(B$4:B$104,I$4:M$104,5,0) -> C | I82: MANNA2108 | J82: ='Юнит 13'!U61 -> 0 | K82: =J82/J$105 -> 0 | L82: =L81+K82 -> 0.99106113 | M82: =_xlfn.IFS(L82<80%,"A",L82<=95%,"B",L82>95%,"C") -> C
B83: sports синие | C83: ='Юнит 13'!AO20 -> -182.53011 | D83: =C83/C$105 -> -0.00011377746 | E83: =E82+D83 -> 1.0213192 | F83: =IF(AND(E83<=0),"C",IF(E83<=0.8,"A",IF(E83<=0.95,"B","C"))) -> C | G83: =VLOOKUP(B$4:B$104,I$4:M$104,5,0) -> C | I83: MANNA2109 | J83: ='Юнит 13'!U62 -> 0 | K83: =J83/J$105 -> 0 | L83: =L82+K83 -> 0.99106113 | M83: =_xlfn.IFS(L83<80%,"A",L83<=95%,"B",L83>95%,"C") -> C
B84: sh2 | C84: ='Юнит 13'!AO27 -> -214.17612 | D84: =C84/C$105 -> -0.00013350353 | E84: =E83+D84 -> 1.0211857 | F84: =IF(AND(E84<=0),"C",IF(E84<=0.8,"A",IF(E84<=0.95,"B","C"))) -> C | G84: =VLOOKUP(B$4:B$104,I$4:M$104,5,0) -> C | I84: MANNA2110 | J84: ='Юнит 13'!U63 -> 0 | K84: =J84/J$105 -> 0 | L84: =L83+K84 -> 0.99106113 | M84: =_xlfn.IFS(L84<80%,"A",L84<=95%,"B",L84>95%,"C") -> C
B85: sh17 | C85: ='Юнит 13'!AO41 -> -301.78644 | D85: =C85/C$105 -> -0.00018811414 | E85: =E84+D85 -> 1.0209976 | F85: =IF(AND(E85<=0),"C",IF(E85<=0.8,"A",IF(E85<=0.95,"B","C"))) -> C | G85: =VLOOKUP(B$4:B$104,I$4:M$104,5,0) -> C | I85: MANNA2111 | J85: ='Юнит 13'!U64 -> 0 | K85: =J85/J$105 -> 0 | L85: =L84+K85 -> 0.99106113 | M85: =_xlfn.IFS(L85<80%,"A",L85<=95%,"B",L85>95%,"C") -> C
B86: Guangdu серебро серая линза | C86: ='Юнит 13'!AO80 -> -328.9987 | D86: =C86/C$105 -> -0.0002050765 | E86: =E85+D86 -> 1.0207925 | F86: =IF(AND(E86<=0),"C",IF(E86<=0.8,"A",IF(E86<=0.95,"B","C"))) -> C | G86: =VLOOKUP(B$4:B$104,I$4:M$104,5,0) -> C | I86: MANNA2112 | J86: ='Юнит 13'!U65 -> 0 | K86: =J86/J$105 -> 0 | L86: =L85+K86 -> 0.99106113 | M86: =_xlfn.IFS(L86<80%,"A",L86<=95%,"B",L86>95%,"C") -> C
B87: Иу Диту серый | C87: ='Юнит 13'!AO91 -> -354.38209 | D87: =C87/C$105 -> -0.00022089886 | E87: =E86+D87 -> 1.0205716 | F87: =IF(AND(E87<=0),"C",IF(E87<=0.8,"A",IF(E87<=0.95,"B","C"))) -> C | G87: =VLOOKUP(B$4:B$104,I$4:M$104,5,0) -> C | I87: MANNA2113 | J87: ='Юнит 13'!U66 -> 0 | K87: =J87/J$105 -> 0 | L87: =L86+K87 -> 0.99106113 | M87: =_xlfn.IFS(L87<80%,"A",L87<=95%,"B",L87>95%,"C") -> C
B88: Ли Сян ретро золото | C88: ='Юнит 13'!AO92 -> -365.82641 | D88: =C88/C$105 -> -0.00022803251 | E88: =E87+D88 -> 1.0203436 | F88: =IF(AND(E88<=0),"C",IF(E88<=0.8,"A",IF(E88<=0.95,"B","C"))) -> C | G88: =VLOOKUP(B$4:B$104,I$4:M$104,5,0) -> C | I88: MANNA2115 | J88: ='Юнит 13'!U68 -> 0 | K88: =J88/J$105 -> 0 | L88: =L87+K88 -> 0.99106113 | M88: =_xlfn.IFS(L88<80%,"A",L88<=95%,"B",L88>95%,"C") -> C
B89: Chenlong белые | C89: ='Юнит 13'!AO78 -> -500.10992 | D89: =C89/C$105 -> -0.00031173615 | E89: =E88+D89 -> 1.0200319 | F89: =IF(AND(E89<=0),"C",IF(E89<=0.8,"A",IF(E89<=0.95,"B","C"))) -> C | G89: =VLOOKUP(B$4:B$104,I$4:M$104,5,0) -> C | I89: MANNA2116 | J89: ='Юнит 13'!U69 -> 0 | K89: =J89/J$105 -> 0 | L89: =L88+K89 -> 0.99106113 | M89: =_xlfn.IFS(L89<80%,"A",L89<=95%,"B",L89>95%,"C") -> C
B90: MANNA2108 | C90: ='Юнит 13'!AO61 -> -509.68581 | D90: =C90/C$105 -> -0.00031770514 | E90: =E89+D90 -> 1.0197142 | F90: =IF(AND(E90<=0),"C",IF(E90<=0.8,"A",IF(E90<=0.95,"B","C"))) -> C | G90: =VLOOKUP(B$4:B$104,I$4:M$104,5,0) -> C | I90: MANNA2119 | J90: ='Юнит 13'!U72 -> 0 | K90: =J90/J$105 -> 0 | L90: =L89+K90 -> 0.99106113 | M90: =_xlfn.IFS(L90<80%,"A",L90<=95%,"B",L90>95%,"C") -> C
B91: Linhai Baiyi коричневая линза | C91: ='Юнит 13'!AO86 -> -819.52648 | D91: =C91/C$105 -> -0.00051083976 | E91: =E90+D91 -> 1.0192033 | F91: =IF(AND(E91<=0),"C",IF(E91<=0.8,"A",IF(E91<=0.95,"B","C"))) -> C | G91: =VLOOKUP(B$4:B$104,I$4:M$104,5,0) -> C | I91: MANNA2121 | J91: ='Юнит 13'!U74 -> 0 | K91: =J91/J$105 -> 0 | L91: =L90+K91 -> 0.99106113 | M91: =_xlfn.IFS(L91<80%,"A",L91<=95%,"B",L91>95%,"C") -> C
B92: MANNA2122 | C92: ='Юнит 13'!AO75 -> -835.88231 | D92: =C92/C$105 -> -0.00052103493 | E92: =E91+D92 -> 1.0186823 | F92: =IF(AND(E92<=0),"C",IF(E92<=0.8,"A",IF(E92<=0.95,"B","C"))) -> C | G92: =VLOOKUP(B$4:B$104,I$4:M$104,5,0) -> C | I92: Chenlong белые | J92: ='Юнит 13'!U78 -> 0 | K92: =J92/J$105 -> 0 | L92: =L91+K92 -> 0.99106113 | M92: =_xlfn.IFS(L92<80%,"A",L92<=95%,"B",L92>95%,"C") -> C
B93: Ли Сян ретро серебро | C93: ='Юнит 13'!AO93 -> -1039.4461 | D93: =C93/C$105 -> -0.00064792342 | E93: =E92+D93 -> 1.0180344 | F93: =IF(AND(E93<=0),"C",IF(E93<=0.8,"A",IF(E93<=0.95,"B","C"))) -> C | G93: =VLOOKUP(B$4:B$104,I$4:M$104,5,0) -> C | I93: Linhai Baiyi коричневая линза | J93: ='Юнит 13'!U86 -> 0 | K93: =J93/J$105 -> 0 | L93: =L92+K93 -> 0.99106113 | M93: =_xlfn.IFS(L93<80%,"A",L93<=95%,"B",L93>95%,"C") -> C
B94: sports красные | C94: ='Юнит 13'!AO22 -> -1478.5543 | D94: =C94/C$105 -> -0.00092163508 | E94: =E93+D94 -> 1.0171127 | F94: =IF(AND(E94<=0),"C",IF(E94<=0.8,"A",IF(E94<=0.95,"B","C"))) -> C | G94: =VLOOKUP(B$4:B$104,I$4:M$104,5,0) -> C | I94: Taizhou Rayen sport розовый | J94: ='Юнит 13'!U90 -> 0 | K94: =J94/J$105 -> 0 | L94: =L93+K94 -> 0.99106113 | M94: =_xlfn.IFS(L94<80%,"A",L94<=95%,"B",L94>95%,"C") -> C
B95: Guangdu золото серая линза | C95: ='Юнит 13'!AO79 -> -1503.3933 | D95: =C95/C$105 -> -0.00093711809 | E95: =E94+D95 -> 1.0161756 | F95: =IF(AND(E95<=0),"C",IF(E95<=0.8,"A",IF(E95<=0.95,"B","C"))) -> C | G95: =VLOOKUP(B$4:B$104,I$4:M$104,5,0) -> C | I95: Ли Сян ретро золото | J95: ='Юнит 13'!U92 -> 0 | K95: =J95/J$105 -> 0 | L95: =L94+K95 -> 0.99106113 | M95: =_xlfn.IFS(L95<80%,"A",L95<=95%,"B",L95>95%,"C") -> C
B96: Chenlong коричневые | C96: ='Юнит 13'!AO77 -> -1856.3619 | D96: =C96/C$105 -> -0.0011571359 | E96: =E95+D96 -> 1.0150185 | F96: =IF(AND(E96<=0),"C",IF(E96<=0.8,"A",IF(E96<=0.95,"B","C"))) -> C | G96: =VLOOKUP(B$4:B$104,I$4:M$104,5,0) -> C | I96: MAIERSHA 03898 C9-08 | J96: ='Юнит 13'!U94 -> 0 | K96: =J96/J$105 -> 0 | L96: =L95+K96 -> 0.99106113 | M96: =_xlfn.IFS(L96<80%,"A",L96<=95%,"B",L96>95%,"C") -> C
B97: sports зеленые | C97: ='Юнит 13'!AO21 -> -2040.6397 | D97: =C97/C$105 -> -0.0012720027 | E97: =E96+D97 -> 1.0137465 | F97: =IF(AND(E97<=0),"C",IF(E97<=0.8,"A",IF(E97<=0.95,"B","C"))) -> C | G97: =VLOOKUP(B$4:B$104,I$4:M$104,5,0) -> C | I97: MAIERSHA 03914 C9-124 | J97: ='Юнит 13'!U95 -> 0 | K97: =J97/J$105 -> 0 | L97: =L96+K97 -> 0.99106113 | M97: =_xlfn.IFS(L97<80%,"A",L97<=95%,"B",L97>95%,"C") -> C
B98: WW 3055 коричневый | C98: ='Юнит 13'!AO53 -> -2484.1292 | D98: =C98/C$105 -> -0.0015484454 | E98: =E97+D98 -> 1.012198 | F98: =IF(AND(E98<=0),"C",IF(E98<=0.8,"A",IF(E98<=0.95,"B","C"))) -> C | G98: =VLOOKUP(B$4:B$104,I$4:M$104,5,0) -> C | I98: MARSTON 7171 C1 | J98: ='Юнит 13'!U96 -> 0 | K98: =J98/J$105 -> 0 | L98: =L97+K98 -> 0.99106113 | M98: =_xlfn.IFS(L98<80%,"A",L98<=95%,"B",L98>95%,"C") -> C
B99: Keming Aishi коричневые | C99: ='Юнит 13'!AO85 -> -2777.1506 | D99: =C99/C$105 -> -0.0017310959 | E99: =E93+D99 -> 1.0163033 | F99: =IF(AND(E99<=0),"C",IF(E99<=0.8,"A",IF(E99<=0.95,"B","C"))) -> C | G99: =VLOOKUP(B$4:B$104,I$4:M$104,5,0) -> C | I99: POMILED 08247 C4-08 | J99: ='Юнит 13'!U97 -> 0 | K99: =J99/J$105 -> 0 | L99: =L93+K99 -> 0.99106113 | M99: =_xlfn.IFS(L99<80%,"A",L99<=95%,"B",L99>95%,"C") -> C
B100: sh1 | C100: ='Юнит 13'!AO26 -> -2790.7907 | D100: =C100/C$105 -> -0.0017395983 | E100: =E94+D100 -> 1.0153731 | F100: =IF(AND(E100<=0),"C",IF(E100<=0.8,"A",IF(E100<=0.95,"B","C"))) -> C | G100: =VLOOKUP(B$4:B$104,I$4:M$104,5,0) -> C | I100: YIMEI 2391 C1 | J100: ='Юнит 13'!U98 -> 0 | K100: =J100/J$105 -> 0 | L100: =L94+K100 -> 0.99106113 | M100: =_xlfn.IFS(L100<80%,"A",L100<=95%,"B",L100>95%,"C") -> C
B101: Chenlong черные | C101: ='Юнит 13'!AO76 -> -3835.8007 | D101: =C101/C$105 -> -0.0023909899 | E101: =E95+D101 -> 1.0137846 | F101: =IF(AND(E101<=0),"C",IF(E101<=0.8,"A",IF(E101<=0.95,"B","C"))) -> C | G101: =VLOOKUP(B$4:B$104,I$4:M$104,5,0) -> C | I101: ЧСЖ_тест | J101: ='Юнит 13'!U99 -> 0 | K101: =J101/J$105 -> 0 | L101: =L95+K101 -> 0.99106113 | M101: =_xlfn.IFS(L101<80%,"A",L101<=95%,"B",L101>95%,"C") -> C
...

Sheet АВС 12
B2: ОЧКИ
C3: Прибыль | D3: % прибыль | E3: Доля | F3: ABC прибыль | G3: ABC кол-во | J3: Кол-во | K3: % кол-во | L3: Доля | M3: ABC кол-во
B4: QS черные PZ | C4: ='Юнит 12'!AO4 -> 452246.82 | D4: =C4/C$105 -> 0.24956728 | E4: =D4 -> 0.24956728 | F4: =IF(AND(E4<=0),"C",IF(E4<=0.8,"A",IF(E4<=0.95,"B","C"))) -> A | G4: =VLOOKUP(B$4:B$104,I$4:M$104,5,0) -> A | I4: QS черные PZ | J4: ='Юнит 12'!U4 -> 796 | K4: =J4/J$105 -> 0.20010055 | L4: =K4 -> 0.20010055 | M4: =_xlfn.IFS(L4<80%,"A",L4<=95%,"B",L4>95%,"C") -> A | P4: A | Q4: 0.8
B5: QS коричневые PZ | C5: ='Юнит 12'!AO7 -> 142766.57 | D5: =C5/C$105 -> 0.078784113 | E5: =E4+D5 -> 0.3283514 | F5: =IF(AND(E5<=0),"C",IF(E5<=0.8,"A",IF(E5<=0.95,"B","C"))) -> A | G5: =VLOOKUP(B$4:B$104,I$4:M$104,5,0) -> A | I5: th черн | J5: ='Юнит 12'!U9 -> 298 | K5: =J5/J$105 -> 0.074912016 | L5: =L4+K5 -> 0.27501257 | M5: =_xlfn.IFS(L5<80%,"A",L5<=95%,"B",L5>95%,"C") -> A | P5: B | Q5: 0.15
B6: th черн | C6: ='Юнит 12'!AO9 -> 138362.1 | D6: =C6/C$105 -> 0.076353558 | E6: =E5+D6 -> 0.40470495 | F6: =IF(AND(E6<=0),"C",IF(E6<=0.8,"A",IF(E6<=0.95,"B","C"))) -> A | G6: =VLOOKUP(B$4:B$104,I$4:M$104,5,0) -> A | I6: QS коричневые PZ | J6: ='Юнит 12'!U7 -> 291 | K6: =J6/J$105 -> 0.073152338 | L6: =L5+K6 -> 0.34816491 | M6: =_xlfn.IFS(L6<80%,"A",L6<=95%,"B",L6>95%,"C") -> A | P6: C | Q6: 0.05
B7: черные с железкой классика | C7: ='Юнит 12'!AO3 -> 123093.16 | D7: =C7/C$105 -> 0.067927564 | E7: =E6+D7 -> 0.47263252 | F7: =IF(AND(E7<=0),"C",IF(E7<=0.8,"A",IF(E7<=0.95,"B","C"))) -> A | G7: =VLOOKUP(B$4:B$104,I$4:M$104,5,0) -> A | I7: th син | J7: ='Юнит 12'!U10 -> 262 | K7: =J7/J$105 -> 0.065862242 | L7: =L6+K7 -> 0.41402715 | M7: =_xlfn.IFS(L7<80%,"A",L7<=95%,"B",L7>95%,"C") -> A
B8: th син | C8: ='Юнит 12'!AO10 -> 110343.3 | D8: =C8/C$105 -> 0.0608917 | E8: =E7+D8 -> 0.53352422 | F8: =IF(AND(E8<=0),"C",IF(E8<=0.8,"A",IF(E8<=0.95,"B","C"))) -> A | G8: =VLOOKUP(B$4:B$104,I$4:M$104,5,0) -> A | I8: flip черные | J8: ='Юнит 12'!U13 -> 249 | K8: =J8/J$105 -> 0.062594268 | L8: =L7+K8 -> 0.47662142 | M8: =_xlfn.IFS(L8<80%,"A",L8<=95%,"B",L8>95%,"C") -> A
B9: flip коричневые | C9: ='Юнит 12'!AO16 -> 109820.29 | D9: =C9/C$105 -> 0.060603082 | E9: =E8+D9 -> 0.5941273 | F9: =IF(AND(E9<=0),"C",IF(E9<=0.8,"A",IF(E9<=0.95,"B","C"))) -> A | G9: =VLOOKUP(B$4:B$104,I$4:M$104,5,0) -> A | I9: flip коричневые | J9: ='Юнит 12'!U16 -> 233 | K9: =J9/J$105 -> 0.058572147 | L9: =L8+K9 -> 0.53519356 | M9: =_xlfn.IFS(L9<80%,"A",L9<=95%,"B",L9>95%,"C") -> A
B10: flip черные | C10: ='Юнит 12'!AO13 -> 109416.1 | D10: =C10/C$105 -> 0.060380036 | E10: =E9+D10 -> 0.65450733 | F10: =IF(AND(E10<=0),"C",IF(E10<=0.8,"A",IF(E10<=0.95,"B","C"))) -> A | G10: =VLOOKUP(B$4:B$104,I$4:M$104,5,0) -> A | I10: черные с железкой классика | J10: ='Юнит 12'!U3 -> 228 | K10: =J10/J$105 -> 0.057315234 | L10: =L9+K10 -> 0.5925088 | M10: =_xlfn.IFS(L10<80%,"A",L10<=95%,"B",L10>95%,"C") -> A
B11: QS синие PZ | C11: ='Юнит 12'!AO5 -> 108243.43 | D11: =C11/C$105 -> 0.059732912 | E11: =E10+D11 -> 0.71424025 | F11: =IF(AND(E11<=0),"C",IF(E11<=0.8,"A",IF(E11<=0.95,"B","C"))) -> A | G11: =VLOOKUP(B$4:B$104,I$4:M$104,5,0) -> A | I11: QS синие PZ | J11: ='Юнит 12'!U5 -> 225 | K11: =J11/J$105 -> 0.056561086 | L11: =L10+K11 -> 0.64906988 | M11: =_xlfn.IFS(L11<80%,"A",L11<=95%,"B",L11>95%,"C") -> A
B12: th коричн | C12: ='Юнит 12'!AO12 -> 83722.534 | D12: =C12/C$105 -> 0.046201332 | E12: =E11+D12 -> 0.76044158 | F12: =IF(AND(E12<=0),"C",IF(E12<=0.8,"A",IF(E12<=0.95,"B","C"))) -> A | G12: =VLOOKUP(B$4:B$104,I$4:M$104,5,0) -> A | I12: th коричн | J12: ='Юнит 12'!U12 -> 194 | K12: =J12/J$105 -> 0.048768225 | L12: =L11+K12 -> 0.69783811 | M12: =_xlfn.IFS(L12<80%,"A",L12<=95%,"B",L12>95%,"C") -> A
B13: sh3 | C13: ='Юнит 12'!AO28 -> 74826.116 | D13: =C13/C$105 -> 0.041291944 | E13: =E12+D13 -> 0.80173352 | F13: =IF(AND(E13<=0),"C",IF(E13<=0.8,"A",IF(E13<=0.95,"B","C"))) -> B | G13: =VLOOKUP(B$4:B$104,I$4:M$104,5,0) -> A | I13: sh3 | J13: ='Юнит 12'!U28 -> 188 | K13: =J13/J$105 -> 0.04725993 | L13: =L12+K13 -> 0.74509804 | M13: =_xlfn.IFS(L13<80%,"A",L13<=95%,"B",L13>95%,"C") -> A
B14: QS желтые PZ | C14: ='Юнит 12'!AO6 -> 45560.404 | D14: =C14/C$105 -> 0.025141992 | E14: =E13+D14 -> 0.82687551 | F14: =IF(AND(E14<=0),"C",IF(E14<=0.8,"A",IF(E14<=0.95,"B","C"))) -> B | G14: =VLOOKUP(B$4:B$104,I$4:M$104,5,0) -> A | I14: th желт | J14: ='Юнит 12'!U11 -> 107 | K14: =J14/J$105 -> 0.026897939 | L14: =L13+K14 -> 0.77199598 | M14: =_xlfn.IFS(L14<80%,"A",L14<=95%,"B",L14>95%,"C") -> A
B15: wwl8032 хром металл | C15: ='Юнит 12'!AO18 -> 45147.554 | D15: =C15/C$105 -> 0.024914166 | E15: =E14+D15 -> 0.85178968 | F15: =IF(AND(E15<=0),"C",IF(E15<=0.8,"A",IF(E15<=0.95,"B","C"))) -> B | G15: =VLOOKUP(B$4:B$104,I$4:M$104,5,0) -> B | I15: QS желтые PZ | J15: ='Юнит 12'!U6 -> 103 | K15: =J15/J$105 -> 0.025892408 | L15: =L14+K15 -> 0.79788839 | M15: =_xlfn.IFS(L15<80%,"A",L15<=95%,"B",L15>95%,"C") -> A
B16: th желт | C16: ='Юнит 12'!AO11 -> 43126.257 | D16: =C16/C$105 -> 0.023798736 | E16: =E15+D16 -> 0.87558842 | F16: =IF(AND(E16<=0),"C",IF(E16<=0.8,"A",IF(E16<=0.95,"B","C"))) -> B | G16: =VLOOKUP(B$4:B$104,I$4:M$104,5,0) -> A | I16: wwl8032 хром металл | J16: ='Юнит 12'!U18 -> 103 | K16: =J16/J$105 -> 0.025892408 | L16: =L15+K16 -> 0.82378079 | M16: =_xlfn.IFS(L16<80%,"A",L16<=95%,"B",L16>95%,"C") -> B
B17: flip синие | C17: ='Юнит 12'!AO14 -> 37695.446 | D17: =C17/C$105 -> 0.020801805 | E17: =E16+D17 -> 0.89639022 | F17: =IF(AND(E17<=0),"C",IF(E17<=0.8,"A",IF(E17<=0.95,"B","C"))) -> B | G17: =VLOOKUP(B$4:B$104,I$4:M$104,5,0) -> B | I17: flip синие | J17: ='Юнит 12'!U14 -> 91 | K17: =J17/J$105 -> 0.022875817 | L17: =L16+K17 -> 0.84665661 | M17: =_xlfn.IFS(L17<80%,"A",L17<=95%,"B",L17>95%,"C") -> B
B18: flip желтые | C18: ='Юнит 12'!AO15 -> 36552.862 | D18: =C18/C$105 -> 0.020171283 | E18: =E17+D18 -> 0.9165615 | F18: =IF(AND(E18<=0),"C",IF(E18<=0.8,"A",IF(E18<=0.95,"B","C"))) -> B | G18: =VLOOKUP(B$4:B$104,I$4:M$104,5,0) -> B | I18: flip желтые | J18: ='Юнит 12'!U15 -> 80 | K18: =J18/J$105 -> 0.020110608 | L18: =L17+K18 -> 0.86676722 | M18: =_xlfn.IFS(L18<80%,"A",L18<=95%,"B",L18>95%,"C") -> B
B19: ww 1022 черные | C19: ='Юнит 12'!AO45 -> 27351.153 | D19: =C19/C$105 -> 0.015093424 | E19: =E18+D19 -> 0.93165493 | F19: =IF(AND(E19<=0),"C",IF(E19<=0.8,"A",IF(E19<=0.95,"B","C"))) -> B | G19: =VLOOKUP(B$4:B$104,I$4:M$104,5,0) -> B | I19: ww 2018 черные | J19: ='Юнит 12'!U49 -> 69 | K19: =J19/J$105 -> 0.0173454 | L19: =L18+K19 -> 0.88411262 | M19: =_xlfn.IFS(L19<80%,"A",L19<=95%,"B",L19>95%,"C") -> B
B20: ww 2018 черные | C20: ='Юнит 12'!AO49 -> 23758.322 | D20: =C20/C$105 -> 0.013110761 | E20: =E19+D20 -> 0.94476569 | F20: =IF(AND(E20<=0),"C",IF(E20<=0.8,"A",IF(E20<=0.95,"B","C"))) -> B | G20: =VLOOKUP(B$4:B$104,I$4:M$104,5,0) -> B | I20: ww 203 черные | J20: ='Юнит 12'!U44 -> 58 | K20: =J20/J$105 -> 0.014580191 | L20: =L19+K20 -> 0.89869281 | M20: =_xlfn.IFS(L20<80%,"A",L20<=95%,"B",L20>95%,"C") -> B
B21: ww 203 черные | C21: ='Юнит 12'!AO44 -> 19848.405 | D21: =C21/C$105 -> 0.010953117 | E21: =E20+D21 -> 0.95571881 | F21: =IF(AND(E21<=0),"C",IF(E21<=0.8,"A",IF(E21<=0.95,"B","C"))) -> C | G21: =VLOOKUP(B$4:B$104,I$4:M$104,5,0) -> B | I21: ww 1022 черные | J21: ='Юнит 12'!U45 -> 52 | K21: =J21/J$105 -> 0.013071895 | L21: =L20+K21 -> 0.91176471 | M21: =_xlfn.IFS(L21<80%,"A",L21<=95%,"B",L21>95%,"C") -> B
B22: wwl8032 коричневые золото | C22: ='Юнит 12'!AO17 -> 18831.738 | D22: =C22/C$105 -> 0.010392081 | E22: =E21+D22 -> 0.96611089 | F22: =IF(AND(E22<=0),"C",IF(E22<=0.8,"A",IF(E22<=0.95,"B","C"))) -> C | G22: =VLOOKUP(B$4:B$104,I$4:M$104,5,0) -> B | I22: ww 2018 желтые | J22: ='Юнит 12'!U50 -> 50 | K22: =J22/J$105 -> 0.01256913 | L22: =L21+K22 -> 0.92433384 | M22: =_xlfn.IFS(L22<80%,"A",L22<=95%,"B",L22>95%,"C") -> B
B23: ww 1022 коричневые | C23: ='Юнит 12'!AO48 -> 18685.246 | D23: =C23/C$105 -> 0.010311241 | E23: =E22+D23 -> 0.97642213 | F23: =IF(AND(E23<=0),"C",IF(E23<=0.8,"A",IF(E23<=0.95,"B","C"))) -> C | G23: =VLOOKUP(B$4:B$104,I$4:M$104,5,0) -> B | I23: ww 1022 коричневые | J23: ='Юнит 12'!U48 -> 46 | K23: =J23/J$105 -> 0.0115636 | L23: =L22+K23 -> 0.93589744 | M23: =_xlfn.IFS(L23<80%,"A",L23<=95%,"B",L23>95%,"C") -> B
B24: ww 2018 желтые | C24: ='Юнит 12'!AO50 -> 18102.454 | D24: =C24/C$105 -> 0.0099896341 | E24: =E23+D24 -> 0.98641176 | F24: =IF(AND(E24<=0),"C",IF(E24<=0.8,"A",IF(E24<=0.95,"B","C"))) -> C | G24: =VLOOKUP(B$4:B$104,I$4:M$104,5,0) -> B | I24: wwl8032 коричневые золото | J24: ='Юнит 12'!U17 -> 42 | K24: =J24/J$105 -> 0.010558069 | L24: =L23+K24 -> 0.94645551 | M24: =_xlfn.IFS(L24<80%,"A",L24<=95%,"B",L24>95%,"C") -> B
B25: MR8854 C2 Жен | C25: ='Юнит 12'!AO8 -> 10089.229 | D25: =C25/C$105 -> 0.0055676266 | E25: =E24+D25 -> 0.99197939 | F25: =IF(AND(E25<=0),"C",IF(E25<=0.8,"A",IF(E25<=0.95,"B","C"))) -> C | G25: =VLOOKUP(B$4:B$104,I$4:M$104,5,0) -> C | I25: MR8854 C2 Жен | J25: ='Юнит 12'!U8 -> 29 | K25: =J25/J$105 -> 0.0072900955 | L25: =L24+K25 -> 0.9537456 | M25: =_xlfn.IFS(L25<80%,"A",L25<=95%,"B",L25>95%,"C") -> C
B26: ww 1022 желтые | C26: ='Юнит 12'!AO47 -> 8275.1165 | D26: =C26/C$105 -> 0.0045665292 | E26: =E25+D26 -> 0.99654592 | F26: =IF(AND(E26<=0),"C",IF(E26<=0.8,"A",IF(E26<=0.95,"B","C"))) -> C | G26: =VLOOKUP(B$4:B$104,I$4:M$104,5,0) -> C | I26: ww 1022 желтые | J26: ='Юнит 12'!U47 -> 28 | K26: =J26/J$105 -> 0.0070387129 | L26: =L25+K26 -> 0.96078431 | M26: =_xlfn.IFS(L26<80%,"A",L26<=95%,"B",L26>95%,"C") -> C
B27: кс_черные_женские | C27: ='Юнит 12'!AO102 -> 4625.6078 | D27: =C27/C$105 -> 0.0025525893 | E27: =E26+D27 -> 0.99909851 | F27: =IF(AND(E27<=0),"C",IF(E27<=0.8,"A",IF(E27<=0.95,"B","C"))) -> C | G27: =VLOOKUP(B$4:B$104,I$4:M$104,5,0) -> C | I27: sh1 | J27: ='Юнит 12'!U26 -> 27 | K27: =J27/J$105 -> 0.0067873303 | L27: =L26+K27 -> 0.96757164 | M27: =_xlfn.IFS(L27<80%,"A",L27<=95%,"B",L27>95%,"C") -> C
B28: MANNA2101 | C28: ='Юнит 12'!AO54 -> 3265.0385 | D28: =C28/C$105 -> 0.0018017745 | E28: =E27+D28 -> 1.0009003 | F28: =IF(AND(E28<=0),"C",IF(E28<=0.8,"A",IF(E28<=0.95,"B","C"))) -> C | G28: =VLOOKUP(B$4:B$104,I$4:M$104,5,0) -> C | I28: sh2 | J28: ='Юнит 12'!U27 -> 13 | K28: =J28/J$105 -> 0.0032679739 | L28: =L27+K28 -> 0.97083962 | M28: =_xlfn.IFS(L28<80%,"A",L28<=95%,"B",L28>95%,"C") -> C
B29: MR Р1894 черные | C29: ='Юнит 12'!AO89 -> 2571.3554 | D29: =C29/C$105 -> 0.0014189733 | E29: =E28+D29 -> 1.0023193 | F29: =IF(AND(E29<=0),"C",IF(E29<=0.8,"A",IF(E29<=0.95,"B","C"))) -> C | G29: =VLOOKUP(B$4:B$104,I$4:M$104,5,0) -> C | I29: кс_черные_женские | J29: ='Юнит 12'!U102 -> 11 | K29: =J29/J$105 -> 0.0027652086 | L29: =L28+K29 -> 0.97360483 | M29: =_xlfn.IFS(L29<80%,"A",L29<=95%,"B",L29>95%,"C") -> C
B30: Ли Сян ретро серебро | C30: ='Юнит 12'!AO93 -> 2524.8495 | D30: =C30/C$105 -> 0.0013933096 | E30: =E29+D30 -> 1.0037126 | F30: =IF(AND(E30<=0),"C",IF(E30<=0.8,"A",IF(E30<=0.95,"B","C"))) -> C | G30: =VLOOKUP(B$4:B$104,I$4:M$104,5,0) -> C | I30: Hengda Optical черные | J30: ='Юнит 12'!U81 -> 10 | K30: =J30/J$105 -> 0.002513826 | L30: =L29+K30 -> 0.97611865 | M30: =_xlfn.IFS(L30<80%,"A",L30<=95%,"B",L30>95%,"C") -> C
B31: sh17 | C31: ='Юнит 12'!AO41 -> 1020.2121 | D31: =C31/C$105 -> 0.00056299251 | E31: =E30+D31 -> 1.0042756 | F31: =IF(AND(E31<=0),"C",IF(E31<=0.8,"A",IF(E31<=0.95,"B","C"))) -> C | G31: =VLOOKUP(B$4:B$104,I$4:M$104,5,0) -> C | I31: WW 3055 черный | J31: ='Юнит 12'!U52 -> 9 | K31: =J31/J$105 -> 0.0022624434 | L31: =L30+K31 -> 0.9783811 | M31: =_xlfn.IFS(L31<80%,"A",L31<=95%,"B",L31>95%,"C") -> C
B32: Linhai Baiyi серая линза | C32: ='Юнит 12'!AO87 -> 969.10302 | D32: =C32/C$105 -> 0.00053478852 | E32: =E31+D32 -> 1.0048103 | F32: =IF(AND(E32<=0),"C",IF(E32<=0.8,"A",IF(E32<=0.95,"B","C"))) -> C | G32: =VLOOKUP(B$4:B$104,I$4:M$104,5,0) -> C | I32: MANNA2101 | J32: ='Юнит 12'!U54 -> 9 | K32: =J32/J$105 -> 0.0022624434 | L32: =L31+K32 -> 0.98064354 | M32: =_xlfn.IFS(L32<80%,"A",L32<=95%,"B",L32>95%,"C") -> C
B33: sh15 | C33: ='Юнит 12'!AO39 -> 953.28394 | D33: =C33/C$105 -> 0.00052605894 | E33: =E32+D33 -> 1.0053364 | F33: =IF(AND(E33<=0),"C",IF(E33<=0.8,"A",IF(E33<=0.95,"B","C"))) -> C | G33: =VLOOKUP(B$4:B$104,I$4:M$104,5,0) -> C | I33: Linhai Baiyi серая линза | J33: ='Юнит 12'!U87 -> 8 | K33: =J33/J$105 -> 0.0020110608 | L33: =L32+K33 -> 0.9826546 | M33: =_xlfn.IFS(L33<80%,"A",L33<=95%,"B",L33>95%,"C") -> C
B34: POMILED 08247 C4-08 | C34: ='Юнит 12'!AO97 -> 882.832 | D34: =C34/C$105 -> 0.00048718084 | E34: =E33+D34 -> 1.0058236 | F34: =IF(AND(E34<=0),"C",IF(E34<=0.8,"A",IF(E34<=0.95,"B","C"))) -> C | G34: =VLOOKUP(B$4:B$104,I$4:M$104,5,0) -> C | I34: Guangdu серебро серая линза | J34: ='Юнит 12'!U80 -> 6 | K34: =J34/J$105 -> 0.0015082956 | L34: =L33+K34 -> 0.9841629 | M34: =_xlfn.IFS(L34<80%,"A",L34<=95%,"B",L34>95%,"C") -> C
B35: sh16 | C35: ='Юнит 12'!AO40 -> 810.80939 | D35: =C35/C$105 -> 0.00044743598 | E35: =E34+D35 -> 1.006271 | F35: =IF(AND(E35<=0),"C",IF(E35<=0.8,"A",IF(E35<=0.95,"B","C"))) -> C | G35: =VLOOKUP(B$4:B$104,I$4:M$104,5,0) -> C | I35: MANNA2105 | J35: ='Юнит 12'!U58 -> 5 | K35: =J35/J$105 -> 0.001256913 | L35: =L34+K35 -> 0.98541981 | M35: =_xlfn.IFS(L35<80%,"A",L35<=95%,"B",L35>95%,"C") -> C
B36: MANNA2117 | C36: ='Юнит 12'!AO70 -> 804.84515 | D36: =C36/C$105 -> 0.00044414467 | E36: =E35+D36 -> 1.0067152 | F36: =IF(AND(E36<=0),"C",IF(E36<=0.8,"A",IF(E36<=0.95,"B","C"))) -> C | G36: =VLOOKUP(B$4:B$104,I$4:M$104,5,0) -> C | I36: MR Р1894 черные | J36: ='Юнит 12'!U89 -> 5 | K36: =J36/J$105 -> 0.001256913 | L36: =L35+K36 -> 0.98667672 | M36: =_xlfn.IFS(L36<80%,"A",L36<=95%,"B",L36>95%,"C") -> C
B37: MANNA2116 | C37: ='Юнит 12'!AO69 -> 759.88273 | D37: =C37/C$105 -> 0.00041933267 | E37: =E36+D37 -> 1.0071345 | F37: =IF(AND(E37<=0),"C",IF(E37<=0.8,"A",IF(E37<=0.95,"B","C"))) -> C | G37: =VLOOKUP(B$4:B$104,I$4:M$104,5,0) -> C | I37: Ли Сян ретро серебро | J37: ='Юнит 12'!U93 -> 5 | K37: =J37/J$105 -> 0.001256913 | L37: =L36+K37 -> 0.98793363 | M37: =_xlfn.IFS(L37<80%,"A",L37<=95%,"B",L37>95%,"C") -> C
B38: Guangdu серебро серая линза | C38: ='Юнит 12'!AO80 -> 726.006 | D38: =C38/C$105 -> 0.00040063818 | E38: =E37+D38 -> 1.0075351 | F38: =IF(AND(E38<=0),"C",IF(E38<=0.8,"A",IF(E38<=0.95,"B","C"))) -> C | G38: =VLOOKUP(B$4:B$104,I$4:M$104,5,0) -> C | I38: sh09 | J38: ='Юнит 12'!U33 -> 4 | K38: =J38/J$105 -> 0.0010055304 | L38: =L37+K38 -> 0.98893917 | M38: =_xlfn.IFS(L38<80%,"A",L38<=95%,"B",L38>95%,"C") -> C
B39: sh13 | C39: ='Юнит 12'!AO37 -> 700.5775 | D39: =C39/C$105 -> 0.00038660575 | E39: =E35+D39 -> 1.0066576 | F39: =IF(AND(E39<=0),"C",IF(E39<=0.8,"A",IF(E39<=0.95,"B","C"))) -> C | G39: =VLOOKUP(B$4:B$104,I$4:M$104,5,0) -> C | I39: sh15 | J39: ='Юнит 12'!U39 -> 4 | K39: =J39/J$105 -> 0.0010055304 | L39: =L35+K39 -> 0.98642534 | M39: =_xlfn.IFS(L39<80%,"A",L39<=95%,"B",L39>95%,"C") -> C
B40: MANNA2105 | C40: ='Юнит 12'!AO58 -> 698.80556 | D40: =C40/C$105 -> 0.00038562793 | E40: =E39+D40 -> 1.0070433 | F40: =IF(AND(E40<=0),"C",IF(E40<=0.8,"A",IF(E40<=0.95,"B","C"))) -> C | G40: =VLOOKUP(B$4:B$104,I$4:M$104,5,0) -> C | I40: MANNA2122 | J40: ='Юнит 12'!U75 -> 4 | K40: =J40/J$105 -> 0.0010055304 | L40: =L39+K40 -> 0.98743087 | M40: =_xlfn.IFS(L40<80%,"A",L40<=95%,"B",L40>95%,"C") -> C
B41: WW 3055 коричневый | C41: ='Юнит 12'!AO53 -> 670.91787 | D41: =C41/C$105 -> 0.00037023842 | E41: =E40+D41 -> 1.0074135 | F41: =IF(AND(E41<=0),"C",IF(E41<=0.8,"A",IF(E41<=0.95,"B","C"))) -> C | G41: =VLOOKUP(B$4:B$104,I$4:M$104,5,0) -> C | I41: Иу Диту серый | J41: ='Юнит 12'!U91 -> 4 | K41: =J41/J$105 -> 0.0010055304 | L41: =L40+K41 -> 0.9884364 | M41: =_xlfn.IFS(L41<80%,"A",L41<=95%,"B",L41>95%,"C") -> C
B42: Иу Диту серый | C42: ='Юнит 12'!AO91 -> 646.61894 | D42: =C42/C$105 -> 0.00035682934 | E42: =E41+D42 -> 1.0077703 | F42: =IF(AND(E42<=0),"C",IF(E42<=0.8,"A",IF(E42<=0.95,"B","C"))) -> C | G42: =VLOOKUP(B$4:B$104,I$4:M$104,5,0) -> C | I42: sh16 | J42: ='Юнит 12'!U40 -> 3 | K42: =J42/J$105 -> 0.00075414781 | L42: =L41+K42 -> 0.98919055 | M42: =_xlfn.IFS(L42<80%,"A",L42<=95%,"B",L42>95%,"C") -> C
B43: MANNA2108 | C43: ='Юнит 12'!AO61 -> 446.62831 | D43: =C43/C$105 -> 0.00024646677 | E43: =E42+D43 -> 1.0080168 | F43: =IF(AND(E43<=0),"C",IF(E43<=0.8,"A",IF(E43<=0.95,"B","C"))) -> C | G43: =VLOOKUP(B$4:B$104,I$4:M$104,5,0) -> C | I43: MANNA2118 | J43: ='Юнит 12'!U71 -> 3 | K43: =J43/J$105 -> 0.00075414781 | L43: =L42+K43 -> 0.9899447 | M43: =_xlfn.IFS(L43<80%,"A",L43<=95%,"B",L43>95%,"C") -> C
B44: ЧСЖ_женские | C44: ='Юнит 12'!AO100 -> 363.52771 | D44: =C44/C$105 -> 0.00020060865 | E44: =E43+D44 -> 1.0082174 | F44: =IF(AND(E44<=0),"C",IF(E44<=0.8,"A",IF(E44<=0.95,"B","C"))) -> C | G44: =VLOOKUP(B$4:B$104,I$4:M$104,5,0) -> C | I44: sh13 | J44: ='Юнит 12'!U37 -> 2 | K44: =J44/J$105 -> 0.00050276521 | L44: =L43+K44 -> 0.99044746 | M44: =_xlfn.IFS(L44<80%,"A",L44<=95%,"B",L44>95%,"C") -> C
B45: MANNA2107 | C45: ='Юнит 12'!AO60 -> 317.35028 | D45: =C45/C$105 -> 0.00017512616 | E45: =E44+D45 -> 1.0083925 | F45: =IF(AND(E45<=0),"C",IF(E45<=0.8,"A",IF(E45<=0.95,"B","C"))) -> C | G45: =VLOOKUP(B$4:B$104,I$4:M$104,5,0) -> C | I45: sh17 | J45: ='Юнит 12'!U41 -> 2 | K45: =J45/J$105 -> 0.00050276521 | L45: =L44+K45 -> 0.99095023 | M45: =_xlfn.IFS(L45<80%,"A",L45<=95%,"B",L45>95%,"C") -> C
B46: WW 3055 черный | C46: ='Юнит 12'!AO52 -> 282.02744 | D46: =C46/C$105 -> 0.00015563365 | E46: =E45+D46 -> 1.0085482 | F46: =IF(AND(E46<=0),"C",IF(E46<=0.8,"A",IF(E46<=0.95,"B","C"))) -> C | G46: =VLOOKUP(B$4:B$104,I$4:M$104,5,0) -> C | I46: WW 3055 коричневый | J46: ='Юнит 12'!U53 -> 2 | K46: =J46/J$105 -> 0.00050276521 | L46: =L45+K46 -> 0.99145299 | M46: =_xlfn.IFS(L46<80%,"A",L46<=95%,"B",L46>95%,"C") -> C
B47: Guangdu золото серая линза | C47: ='Юнит 12'!AO79 -> 229.65853 | D47: =C47/C$105 -> 0.00012673446 | E47: =E46+D47 -> 1.0086749 | F47: =IF(AND(E47<=0),"C",IF(E47<=0.8,"A",IF(E47<=0.95,"B","C"))) -> C | G47: =VLOOKUP(B$4:B$104,I$4:M$104,5,0) -> C | I47: MANNA2107 | J47: ='Юнит 12'!U60 -> 2 | K47: =J47/J$105 -> 0.00050276521 | L47: =L46+K47 -> 0.99195576 | M47: =_xlfn.IFS(L47<80%,"A",L47<=95%,"B",L47>95%,"C") -> C
B48: Chenlong коричневые | C48: ='Юнит 12'!AO77 -> 160.1494 | D48: =C48/C$105 -> 8.8376634e-05 | E48: =E47+D48 -> 1.0087633 | F48: =IF(AND(E48<=0),"C",IF(E48<=0.8,"A",IF(E48<=0.95,"B","C"))) -> C | G48: =VLOOKUP(B$4:B$104,I$4:M$104,5,0) -> C | I48: MANNA2108 | J48: ='Юнит 12'!U61 -> 2 | K48: =J48/J$105 -> 0.00050276521 | L48: =L47+K48 -> 0.99245852 | M48: =_xlfn.IFS(L48<80%,"A",L48<=95%,"B",L48>95%,"C") -> C
B49: MANNA2118 | C49: ='Юнит 12'!AO71 -> 136.40142 | D49: =C49/C$105 -> 7.5271577e-05 | E49: =E48+D49 -> 1.0088385 | F49: =IF(AND(E49<=0),"C",IF(E49<=0.8,"A",IF(E49<=0.95,"B","C"))) -> C | G49: =VLOOKUP(B$4:B$104,I$4:M$104,5,0) -> C | I49: MANNA2116 | J49: ='Юнит 12'!U69 -> 2 | K49: =J49/J$105 -> 0.00050276521 | L49: =L48+K49 -> 0.99296129 | M49: =_xlfn.IFS(L49<80%,"A",L49<=95%,"B",L49>95%,"C") -> C
B50: MANNA2119 | C50: ='Юнит 12'!AO72 -> 121.6011 | D50: =C50/C$105 -> 6.7104189e-05 | E50: =E49+D50 -> 1.0089056 | F50: =IF(AND(E50<=0),"C",IF(E50<=0.8,"A",IF(E50<=0.95,"B","C"))) -> C | G50: =VLOOKUP(B$4:B$104,I$4:M$104,5,0) -> C | I50: MANNA2117 | J50: ='Юнит 12'!U70 -> 2 | K50: =J50/J$105 -> 0.00050276521 | L50: =L49+K50 -> 0.99346405 | M50: =_xlfn.IFS(L50<80%,"A",L50<=95%,"B",L50>95%,"C") -> C
B51: Hengda Optical черные | C51: ='Юнит 12'!AO81 -> 115.05072 | D51: =C51/C$105 -> 6.3489437e-05 | E51: =E50+D51 -> 1.0089691 | F51: =IF(AND(E51<=0),"C",IF(E51<=0.8,"A",IF(E51<=0.95,"B","C"))) -> C | G51: =VLOOKUP(B$4:B$104,I$4:M$104,5,0) -> C | I51: Chenlong белые | J51: ='Юнит 12'!U78 -> 2 | K51: =J51/J$105 -> 0.00050276521 | L51: =L50+K51 -> 0.99396682 | M51: =_xlfn.IFS(L51<80%,"A",L51<=95%,"B",L51>95%,"C") -> C
B52: YIMEI 2391 C1 | C52: ='Юнит 12'!AO98 -> 63.865274 | D52: =C52/C$105 -> 3.5243328e-05 | E52: =E51+D52 -> 1.0090044 | F52: =IF(AND(E52<=0),"C",IF(E52<=0.8,"A",IF(E52<=0.95,"B","C"))) -> C | G52: =VLOOKUP(B$4:B$104,I$4:M$104,5,0) -> C | I52: POMILED 08247 C4-08 | J52: ='Юнит 12'!U97 -> 2 | K52: =J52/J$105 -> 0.00050276521 | L52: =L51+K52 -> 0.99446958 | M52: =_xlfn.IFS(L52<80%,"A",L52<=95%,"B",L52>95%,"C") -> C
B53: Qianai черные | C53: ='Юнит 12'!AO83 -> 49.203206 | D53: =C53/C$105 -> 2.7152232e-05 | E53: =E52+D53 -> 1.0090315 | F53: =IF(AND(E53<=0),"C",IF(E53<=0.8,"A",IF(E53<=0.95,"B","C"))) -> C | G53: =VLOOKUP(B$4:B$104,I$4:M$104,5,0) -> C | I53: sh14 | J53: ='Юнит 12'!U38 -> 1 | K53: =J53/J$105 -> 0.0002513826 | L53: =L52+K53 -> 0.99472097 | M53: =_xlfn.IFS(L53<80%,"A",L53<=95%,"B",L53>95%,"C") -> C
B54: Linhai Baiyi розовая линза | C54: ='Юнит 12'!AO88 -> 21.698073 | D54: =C54/C$105 -> 1.1973836e-05 | E54: =E53+D54 -> 1.0090435 | F54: =IF(AND(E54<=0),"C",IF(E54<=0.8,"A",IF(E54<=0.95,"B","C"))) -> C | G54: =VLOOKUP(B$4:B$104,I$4:M$104,5,0) -> C | I54: MANNA2119 | J54: ='Юнит 12'!U72 -> 1 | K54: =J54/J$105 -> 0.0002513826 | L54: =L53+K54 -> 0.99497235 | M54: =_xlfn.IFS(L54<80%,"A",L54<=95%,"B",L54>95%,"C") -> C
B55: wwl8032 черные серебро | C55: ='Юнит 12'!AO19 -> 0 | D55: =C55/C$105 -> 0 | E55: =E54+D55 -> 1.0090435 | F55: =IF(AND(E55<=0),"C",IF(E55<=0.8,"A",IF(E55<=0.95,"B","C"))) -> C | G55: =VLOOKUP(B$4:B$104,I$4:M$104,5,0) -> C | I55: Chenlong коричневые | J55: ='Юнит 12'!U77 -> 1 | K55: =J55/J$105 -> 0.0002513826 | L55: =L54+K55 -> 0.99522373 | M55: =_xlfn.IFS(L55<80%,"A",L55<=95%,"B",L55>95%,"C") -> C
B56: sports синие | C56: ='Юнит 12'!AO20 -> 0 | D56: =C56/C$105 -> 0 | E56: =E55+D56 -> 1.0090435 | F56: =IF(AND(E56<=0),"C",IF(E56<=0.8,"A",IF(E56<=0.95,"B","C"))) -> C | G56: =VLOOKUP(B$4:B$104,I$4:M$104,5,0) -> C | I56: Guangdu золото серая линза | J56: ='Юнит 12'!U79 -> 1 | K56: =J56/J$105 -> 0.0002513826 | L56: =L55+K56 -> 0.99547511 | M56: =_xlfn.IFS(L56<80%,"A",L56<=95%,"B",L56>95%,"C") -> C
B57: sports зеленые | C57: ='Юнит 12'!AO21 -> 0 | D57: =C57/C$105 -> 0 | E57: =E56+D57 -> 1.0090435 | F57: =IF(AND(E57<=0),"C",IF(E57<=0.8,"A",IF(E57<=0.95,"B","C"))) -> C | G57: =VLOOKUP(B$4:B$104,I$4:M$104,5,0) -> C | I57: Qianai черные | J57: ='Юнит 12'!U83 -> 1 | K57: =J57/J$105 -> 0.0002513826 | L57: =L56+K57 -> 0.9957265 | M57: =_xlfn.IFS(L57<80%,"A",L57<=95%,"B",L57>95%,"C") -> C
B58: sports красные | C58: ='Юнит 12'!AO22 -> 0 | D58: =C58/C$105 -> 0 | E58: =E57+D58 -> 1.0090435 | F58: =IF(AND(E58<=0),"C",IF(E58<=0.8,"A",IF(E58<=0.95,"B","C"))) -> C | G58: =VLOOKUP(B$4:B$104,I$4:M$104,5,0) -> C | I58: Keming Aishi коричневые | J58: ='Юнит 12'!U85 -> 1 | K58: =J58/J$105 -> 0.0002513826 | L58: =L57+K58 -> 0.99597788 | M58: =_xlfn.IFS(L58<80%,"A",L58<=95%,"B",L58>95%,"C") -> C
B59: sportlife черные | C59: ='Юнит 12'!AO23 -> 0 | D59: =C59/C$105 -> 0 | E59: =E58+D59 -> 1.0090435 | F59: =IF(AND(E59<=0),"C",IF(E59<=0.8,"A",IF(E59<=0.95,"B","C"))) -> C | G59: =VLOOKUP(B$4:B$104,I$4:M$104,5,0) -> C | I59: Linhai Baiyi розовая линза | J59: ='Юнит 12'!U88 -> 1 | K59: =J59/J$105 -> 0.0002513826 | L59: =L58+K59 -> 0.99622926 | M59: =_xlfn.IFS(L59<80%,"A",L59<=95%,"B",L59>95%,"C") -> C
B60: sportlife синие | C60: ='Юнит 12'!AO24 -> 0 | D60: =C60/C$105 -> 0 | E60: =E59+D60 -> 1.0090435 | F60: =IF(AND(E60<=0),"C",IF(E60<=0.8,"A",IF(E60<=0.95,"B","C"))) -> C | G60: =VLOOKUP(B$4:B$104,I$4:M$104,5,0) -> C | I60: YIMEI 2391 C1 | J60: ='Юнит 12'!U98 -> 1 | K60: =J60/J$105 -> 0.0002513826 | L60: =L59+K60 -> 0.99648064 | M60: =_xlfn.IFS(L60<80%,"A",L60<=95%,"B",L60>95%,"C") -> C
B61: sportlife красные | C61: ='Юнит 12'!AO25 -> 0 | D61: =C61/C$105 -> 0 | E61: =E60+D61 -> 1.0090435 | F61: =IF(AND(E61<=0),"C",IF(E61<=0.8,"A",IF(E61<=0.95,"B","C"))) -> C | G61: =VLOOKUP(B$4:B$104,I$4:M$104,5,0) -> C | I61: ЧСЖ_женские | J61: ='Юнит 12'!U100 -> 1 | K61: =J61/J$105 -> 0.0002513826 | L61: =L60+K61 -> 0.99673203 | M61: =_xlfn.IFS(L61<80%,"A",L61<=95%,"B",L61>95%,"C") -> C
B62: sh4 | C62: ='Юнит 12'!AO29 -> 0 | D62: =C62/C$105 -> 0 | E62: =E61+D62 -> 1.0090435 | F62: =IF(AND(E62<=0),"C",IF(E62<=0.8,"A",IF(E62<=0.95,"B","C"))) -> C | G62: =VLOOKUP(B$4:B$104,I$4:M$104,5,0) -> C | I62: wwl8032 черные серебро | J62: ='Юнит 12'!U19 -> 0 | K62: =J62/J$105 -> 0 | L62: =L61+K62 -> 0.99673203 | M62: =_xlfn.IFS(L62<80%,"A",L62<=95%,"B",L62>95%,"C") -> C
B63: sh06 | C63: ='Юнит 12'!AO30 -> 0 | D63: =C63/C$105 -> 0 | E63: =E62+D63 -> 1.0090435 | F63: =IF(AND(E63<=0),"C",IF(E63<=0.8,"A",IF(E63<=0.95,"B","C"))) -> C | G63: =VLOOKUP(B$4:B$104,I$4:M$104,5,0) -> C | I63: sports синие | J63: ='Юнит 12'!U20 -> 0 | K63: =J63/J$105 -> 0 | L63: =L62+K63 -> 0.99673203 | M63: =_xlfn.IFS(L63<80%,"A",L63<=95%,"B",L63>95%,"C") -> C
B64: sh07 | C64: ='Юнит 12'!AO31 -> 0 | D64: =C64/C$105 -> 0 | E64: =E63+D64 -> 1.0090435 | F64: =IF(AND(E64<=0),"C",IF(E64<=0.8,"A",IF(E64<=0.95,"B","C"))) -> C | G64: =VLOOKUP(B$4:B$104,I$4:M$104,5,0) -> C | I64: sports зеленые | J64: ='Юнит 12'!U21 -> 0 | K64: =J64/J$105 -> 0 | L64: =L63+K64 -> 0.99673203 | M64: =_xlfn.IFS(L64<80%,"A",L64<=95%,"B",L64>95%,"C") -> C
B65: sh08 | C65: ='Юнит 12'!AO32 -> 0 | D65: =C65/C$105 -> 0 | E65: =E64+D65 -> 1.0090435 | F65: =IF(AND(E65<=0),"C",IF(E65<=0.8,"A",IF(E65<=0.95,"B","C"))) -> C | G65: =VLOOKUP(B$4:B$104,I$4:M$104,5,0) -> C | I65: sports красные | J65: ='Юнит 12'!U22 -> 0 | K65: =J65/J$105 -> 0 | L65: =L64+K65 -> 0.99673203 | M65: =_xlfn.IFS(L65<80%,"A",L65<=95%,"B",L65>95%,"C") -> C
B66: sh10 | C66: ='Юнит 12'!AO34 -> 0 | D66: =C66/C$105 -> 0 | E66: =E65+D66 -> 1.0090435 | F66: =IF(AND(E66<=0),"C",IF(E66<=0.8,"A",IF(E66<=0.95,"B","C"))) -> C | G66: =VLOOKUP(B$4:B$104,I$4:M$104,5,0) -> C | I66: sportlife черные | J66: ='Юнит 12'!U23 -> 0 | K66: =J66/J$105 -> 0 | L66: =L65+K66 -> 0.99673203 | M66: =_xlfn.IFS(L66<80%,"A",L66<=95%,"B",L66>95%,"C") -> C
B67: sh11 | C67: ='Юнит 12'!AO35 -> 0 | D67: =C67/C$105 -> 0 | E67: =E66+D67 -> 1.0090435 | F67: =IF(AND(E67<=0),"C",IF(E67<=0.8,"A",IF(E67<=0.95,"B","C"))) -> C | G67: =VLOOKUP(B$4:B$104,I$4:M$104,5,0) -> C | I67: sportlife синие | J67: ='Юнит 12'!U24 -> 0 | K67: =J67/J$105 -> 0 | L67: =L66+K67 -> 0.99673203 | M67: =_xlfn.IFS(L67<80%,"A",L67<=95%,"B",L67>95%,"C") -> C
B68: sh12 | C68: ='Юнит 12'!AO36 -> 0 | D68: =C68/C$105 -> 0 | E68: =E67+D68 -> 1.0090435 | F68: =IF(AND(E68<=0),"C",IF(E68<=0.8,"A",IF(E68<=0.95,"B","C"))) -> C | G68: =VLOOKUP(B$4:B$104,I$4:M$104,5,0) -> C | I68: sportlife красные | J68: ='Юнит 12'!U25 -> 0 | K68: =J68/J$105 -> 0 | L68: =L67+K68 -> 0.99673203 | M68: =_xlfn.IFS(L68<80%,"A",L68<=95%,"B",L68>95%,"C") -> C
B69: ww 1022 черн-серебро | C69: ='Юнит 12'!AO46 -> 0 | D69: =C69/C$105 -> 0 | E69: =E68+D69 -> 1.0090435 | F69: =IF(AND(E69<=0),"C",IF(E69<=0.8,"A",IF(E69<=0.95,"B","C"))) -> C | G69: =VLOOKUP(B$4:B$104,I$4:M$104,5,0) -> C | I69: sh4 | J69: ='Юнит 12'!U29 -> 0 | K69: =J69/J$105 -> 0 | L69: =L68+K69 -> 0.99673203 | M69: =_xlfn.IFS(L69<80%,"A",L69<=95%,"B",L69>95%,"C") -> C
B70: MANNA2102 | C70: ='Юнит 12'!AO55 -> 0 | D70: =C70/C$105 -> 0 | E70: =E69+D70 -> 1.0090435 | F70: =IF(AND(E70<=0),"C",IF(E70<=0.8,"A",IF(E70<=0.95,"B","C"))) -> C | G70: =VLOOKUP(B$4:B$104,I$4:M$104,5,0) -> C | I70: sh06 | J70: ='Юнит 12'!U30 -> 0 | K70: =J70/J$105 -> 0 | L70: =L69+K70 -> 0.99673203 | M70: =_xlfn.IFS(L70<80%,"A",L70<=95%,"B",L70>95%,"C") -> C
B71: MANNA2103 | C71: ='Юнит 12'!AO56 -> 0 | D71: =C71/C$105 -> 0 | E71: =E70+D71 -> 1.0090435 | F71: =IF(AND(E71<=0),"C",IF(E71<=0.8,"A",IF(E71<=0.95,"B","C"))) -> C | G71: =VLOOKUP(B$4:B$104,I$4:M$104,5,0) -> C | I71: sh07 | J71: ='Юнит 12'!U31 -> 0 | K71: =J71/J$105 -> 0 | L71: =L70+K71 -> 0.99673203 | M71: =_xlfn.IFS(L71<80%,"A",L71<=95%,"B",L71>95%,"C") -> C
B72: MANNA2104 | C72: ='Юнит 12'!AO57 -> 0 | D72: =C72/C$105 -> 0 | E72: =E71+D72 -> 1.0090435 | F72: =IF(AND(E72<=0),"C",IF(E72<=0.8,"A",IF(E72<=0.95,"B","C"))) -> C | G72: =VLOOKUP(B$4:B$104,I$4:M$104,5,0) -> C | I72: sh08 | J72: ='Юнит 12'!U32 -> 0 | K72: =J72/J$105 -> 0 | L72: =L71+K72 -> 0.99673203 | M72: =_xlfn.IFS(L72<80%,"A",L72<=95%,"B",L72>95%,"C") -> C
B73: MANNA2106 | C73: ='Юнит 12'!AO59 -> 0 | D73: =C73/C$105 -> 0 | E73: =E72+D73 -> 1.0090435 | F73: =IF(AND(E73<=0),"C",IF(E73<=0.8,"A",IF(E73<=0.95,"B","C"))) -> C | G73: =VLOOKUP(B$4:B$104,I$4:M$104,5,0) -> C | I73: sh10 | J73: ='Юнит 12'!U34 -> 0 | K73: =J73/J$105 -> 0 | L73: =L72+K73 -> 0.99673203 | M73: =_xlfn.IFS(L73<80%,"A",L73<=95%,"B",L73>95%,"C") -> C
B74: MANNA2109 | C74: ='Юнит 12'!AO62 -> 0 | D74: =C74/C$105 -> 0 | E74: =E73+D74 -> 1.0090435 | F74: =IF(AND(E74<=0),"C",IF(E74<=0.8,"A",IF(E74<=0.95,"B","C"))) -> C | G74: =VLOOKUP(B$4:B$104,I$4:M$104,5,0) -> C | I74: sh11 | J74: ='Юнит 12'!U35 -> 0 | K74: =J74/J$105 -> 0 | L74: =L73+K74 -> 0.99673203 | M74: =_xlfn.IFS(L74<80%,"A",L74<=95%,"B",L74>95%,"C") -> C
B75: MANNA2110 | C75: ='Юнит 12'!AO63 -> 0 | D75: =C75/C$105 -> 0 | E75: =E74+D75 -> 1.0090435 | F75: =IF(AND(E75<=0),"C",IF(E75<=0.8,"A",IF(E75<=0.95,"B","C"))) -> C | G75: =VLOOKUP(B$4:B$104,I$4:M$104,5,0) -> C | I75: sh12 | J75: ='Юнит 12'!U36 -> 0 | K75: =J75/J$105 -> 0 | L75: =L74+K75 -> 0.99673203 | M75: =_xlfn.IFS(L75<80%,"A",L75<=95%,"B",L75>95%,"C") -> C
B76: MANNA2111 | C76: ='Юнит 12'!AO64 -> 0 | D76: =C76/C$105 -> 0 | E76: =E49+D76 -> 1.0088385 | F76: =IF(AND(E76<=0),"C",IF(E76<=0.8,"A",IF(E76<=0.95,"B","C"))) -> C | G76: =VLOOKUP(B$4:B$104,I$4:M$104,5,0) -> C | I76: sh18 | J76: ='Юнит 12'!U42 -> 0 | K76: =J76/J$105 -> 0 | L76: =L49+K76 -> 0.99296129 | M76: =_xlfn.IFS(L76<80%,"A",L76<=95%,"B",L76>95%,"C") -> C
B77: MANNA2114 | C77: ='Юнит 12'!AO67 -> 0 | D77: =C77/C$105 -> 0 | E77: =E76+D77 -> 1.0088385 | F77: =IF(AND(E77<=0),"C",IF(E77<=0.8,"A",IF(E77<=0.95,"B","C"))) -> C | G77: =VLOOKUP(B$4:B$104,I$4:M$104,5,0) -> C | I77: sh19 | J77: ='Юнит 12'!U43 -> 0 | K77: =J77/J$105 -> 0 | L77: =L76+K77 -> 0.99296129 | M77: =_xlfn.IFS(L77<80%,"A",L77<=95%,"B",L77>95%,"C") -> C
B78: MANNA2115 | C78: ='Юнит 12'!AO68 -> 0 | D78: =C78/C$105 -> 0 | E78: =E77+D78 -> 1.0088385 | F78: =IF(AND(E78<=0),"C",IF(E78<=0.8,"A",IF(E78<=0.95,"B","C"))) -> C | G78: =VLOOKUP(B$4:B$104,I$4:M$104,5,0) -> C | I78: ww 1022 черн-серебро | J78: ='Юнит 12'!U46 -> 0 | K78: =J78/J$105 -> 0 | L78: =L77+K78 -> 0.99296129 | M78: =_xlfn.IFS(L78<80%,"A",L78<=95%,"B",L78>95%,"C") -> C
B79: MAIERSHA 03898 C9-08 | C79: ='Юнит 12'!AO94 -> 0 | D79: =C79/C$105 -> 0 | E79: =E78+D79 -> 1.0088385 | F79: =IF(AND(E79<=0),"C",IF(E79<=0.8,"A",IF(E79<=0.95,"B","C"))) -> C | G79: =VLOOKUP(B$4:B$104,I$4:M$104,5,0) -> C | I79: MANNA2102 | J79: ='Юнит 12'!U55 -> 0 | K79: =J79/J$105 -> 0 | L79: =L78+K79 -> 0.99296129 | M79: =_xlfn.IFS(L79<80%,"A",L79<=95%,"B",L79>95%,"C") -> C
B80: MAIERSHA 03914 C9-124 | C80: ='Юнит 12'!AO95 -> 0 | D80: =C80/C$105 -> 0 | E80: =E79+D80 -> 1.0088385 | F80: =IF(AND(E80<=0),"C",IF(E80<=0.8,"A",IF(E80<=0.95,"B","C"))) -> C | G80: =VLOOKUP(B$4:B$104,I$4:M$104,5,0) -> C | I80: MANNA2103 | J80: ='Юнит 12'!U56 -> 0 | K80: =J80/J$105 -> 0 | L80: =L79+K80 -> 0.99296129 | M80: =_xlfn.IFS(L80<80%,"A",L80<=95%,"B",L80>95%,"C") -> C
B81: MARSTON 7171 C1 | C81: ='Юнит 12'!AO96 -> 0 | D81: =C81/C$105 -> 0 | E81: =E80+D81 -> 1.0088385 | F81: =IF(AND(E81<=0),"C",IF(E81<=0.8,"A",IF(E81<=0.95,"B","C"))) -> C | G81: =VLOOKUP(B$4:B$104,I$4:M$104,5,0) -> C | I81: MANNA2104 | J81: ='Юнит 12'!U57 -> 0 | K81: =J81/J$105 -> 0 | L81: =L80+K81 -> 0.99296129 | M81: =_xlfn.IFS(L81<80%,"A",L81<=95%,"B",L81>95%,"C") -> C
B82: ЧСЖ_тест | C82: ='Юнит 12'!AO99 -> 0 | D82: =C82/C$105 -> 0 | E82: =E81+D82 -> 1.0088385 | F82: =IF(AND(E82<=0),"C",IF(E82<=0.8,"A",IF(E82<=0.95,"B","C"))) -> C | G82: =VLOOKUP(B$4:B$104,I$4:M$104,5,0) -> C | I82: MANNA2106 | J82: ='Юнит 12'!U59 -> 0 | K82: =J82/J$105 -> 0 | L82: =L81+K82 -> 0.99296129 | M82: =_xlfn.IFS(L82<80%,"A",L82<=95%,"B",L82>95%,"C") -> C
B83: кс_черные_тест | C83: ='Юнит 12'!AO101 -> 0 | D83: =C83/C$105 -> 0 | E83: =E82+D83 -> 1.0088385 | F83: =IF(AND(E83<=0),"C",IF(E83<=0.8,"A",IF(E83<=0.95,"B","C"))) -> C | G83: =VLOOKUP(B$4:B$104,I$4:M$104,5,0) -> C | I83: MANNA2109 | J83: ='Юнит 12'!U62 -> 0 | K83: =J83/J$105 -> 0 | L83: =L82+K83 -> 0.99296129 | M83: =_xlfn.IFS(L83<80%,"A",L83<=95%,"B",L83>95%,"C") -> C
B84: 1022_коричневые_тест | C84: ='Юнит 12'!AO103 -> 0 | D84: =C84/C$105 -> 0 | E84: =E83+D84 -> 1.0088385 | F84: =IF(AND(E84<=0),"C",IF(E84<=0.8,"A",IF(E84<=0.95,"B","C"))) -> C | G84: =VLOOKUP(B$4:B$104,I$4:M$104,5,0) -> C | I84: MANNA2110 | J84: ='Юнит 12'!U63 -> 0 | K84: =J84/J$105 -> 0 | L84: =L83+K84 -> 0.99296129 | M84: =_xlfn.IFS(L84<80%,"A",L84<=95%,"B",L84>95%,"C") -> C
B85: MANNA2112 | C85: ='Юнит 12'!AO65 -> -0.77642713 | D85: =C85/C$105 -> -4.2846252e-07 | E85: =E84+D85 -> 1.0088381 | F85: =IF(AND(E85<=0),"C",IF(E85<=0.8,"A",IF(E85<=0.95,"B","C"))) -> C | G85: =VLOOKUP(B$4:B$104,I$4:M$104,5,0) -> C | I85: MANNA2111 | J85: ='Юнит 12'!U64 -> 0 | K85: =J85/J$105 -> 0 | L85: =L84+K85 -> 0.99296129 | M85: =_xlfn.IFS(L85<80%,"A",L85<=95%,"B",L85>95%,"C") -> C
B86: MANNA2113 | C86: ='Юнит 12'!AO66 -> -1.5528543 | D86: =C86/C$105 -> -8.5692503e-07 | E86: =E85+D86 -> 1.0088373 | F86: =IF(AND(E86<=0),"C",IF(E86<=0.8,"A",IF(E86<=0.95,"B","C"))) -> C | G86: =VLOOKUP(B$4:B$104,I$4:M$104,5,0) -> C | I86: MANNA2112 | J86: ='Юнит 12'!U65 -> 0 | K86: =J86/J$105 -> 0 | L86: =L85+K86 -> 0.99296129 | M86: =_xlfn.IFS(L86<80%,"A",L86<=95%,"B",L86>95%,"C") -> C
B87: Ли Сян ретро золото | C87: ='Юнит 12'!AO92 -> -36.492075 | D87: =C87/C$105 -> -2.0137738e-05 | E87: =E86+D87 -> 1.0088171 | F87: =IF(AND(E87<=0),"C",IF(E87<=0.8,"A",IF(E87<=0.95,"B","C"))) -> C | G87: =VLOOKUP(B$4:B$104,I$4:M$104,5,0) -> C | I87: MANNA2113 | J87: ='Юнит 12'!U66 -> 0 | K87: =J87/J$105 -> 0 | L87: =L86+K87 -> 0.99296129 | M87: =_xlfn.IFS(L87<80%,"A",L87<=95%,"B",L87>95%,"C") -> C
B88: Taizhou Rayen sport розовый | C88: ='Юнит 12'!AO90 -> -38.821357 | D88: =C88/C$105 -> -2.1423126e-05 | E88: =E87+D88 -> 1.0087957 | F88: =IF(AND(E88<=0),"C",IF(E88<=0.8,"A",IF(E88<=0.95,"B","C"))) -> C | G88: =VLOOKUP(B$4:B$104,I$4:M$104,5,0) -> C | I88: MANNA2114 | J88: ='Юнит 12'!U67 -> 0 | K88: =J88/J$105 -> 0 | L88: =L87+K88 -> 0.99296129 | M88: =_xlfn.IFS(L88<80%,"A",L88<=95%,"B",L88>95%,"C") -> C
B89: MANNA2121 | C89: ='Юнит 12'!AO74 -> -93.93 | D89: =C89/C$105 -> -5.1834206e-05 | E89: =E88+D89 -> 1.0087439 | F89: =IF(AND(E89<=0),"C",IF(E89<=0.8,"A",IF(E89<=0.95,"B","C"))) -> C | G89: =VLOOKUP(B$4:B$104,I$4:M$104,5,0) -> C | I89: MANNA2115 | J89: ='Юнит 12'!U68 -> 0 | K89: =J89/J$105 -> 0 | L89: =L88+K89 -> 0.99296129 | M89: =_xlfn.IFS(L89<80%,"A",L89<=95%,"B",L89>95%,"C") -> C
B90: Hengda Optical леопард | C90: ='Юнит 12'!AO82 -> -144.87565 | D90: =C90/C$105 -> -7.9947985e-05 | E90: =E89+D90 -> 1.0086639 | F90: =IF(AND(E90<=0),"C",IF(E90<=0.8,"A",IF(E90<=0.95,"B","C"))) -> C | G90: =VLOOKUP(B$4:B$104,I$4:M$104,5,0) -> C | I90: MANNA2120 | J90: ='Юнит 12'!U73 -> 0 | K90: =J90/J$105 -> 0 | L90: =L89+K90 -> 0.99296129 | M90: =_xlfn.IFS(L90<80%,"A",L90<=95%,"B",L90>95%,"C") -> C
B91: Chenlong белые | C91: ='Юнит 12'!AO78 -> -169.70968 | D91: =C91/C$105 -> -9.3652364e-05 | E91: =E90+D91 -> 1.0085703 | F91: =IF(AND(E91<=0),"C",IF(E91<=0.8,"A",IF(E91<=0.95,"B","C"))) -> C | G91: =VLOOKUP(B$4:B$104,I$4:M$104,5,0) -> C | I91: MANNA2121 | J91: ='Юнит 12'!U74 -> 0 | K91: =J91/J$105 -> 0 | L91: =L90+K91 -> 0.99296129 | M91: =_xlfn.IFS(L91<80%,"A",L91<=95%,"B",L91>95%,"C") -> C
B92: sh14 | C92: ='Юнит 12'!AO38 -> -181.98576 | D92: =C92/C$105 -> -0.00010042678 | E92: =E91+D92 -> 1.0084698 | F92: =IF(AND(E92<=0),"C",IF(E92<=0.8,"A",IF(E92<=0.95,"B","C"))) -> C | G92: =VLOOKUP(B$4:B$104,I$4:M$104,5,0) -> C | I92: Chenlong черные | J92: ='Юнит 12'!U76 -> 0 | K92: =J92/J$105 -> 0 | L92: =L91+K92 -> 0.99296129 | M92: =_xlfn.IFS(L92<80%,"A",L92<=95%,"B",L92>95%,"C") -> C
B93: sh2 | C93: ='Юнит 12'!AO27 -> -195.37945 | D93: =C93/C$105 -> -0.00010781794 | E93: =E92+D93 -> 1.008362 | F93: =IF(AND(E93<=0),"C",IF(E93<=0.8,"A",IF(E93<=0.95,"B","C"))) -> C | G93: =VLOOKUP(B$4:B$104,I$4:M$104,5,0) -> C | I93: Hengda Optical леопард | J93: ='Юнит 12'!U82 -> 0 | K93: =J93/J$105 -> 0 | L93: =L92+K93 -> 0.99296129 | M93: =_xlfn.IFS(L93<80%,"A",L93<=95%,"B",L93>95%,"C") -> C
B94: MANNA2120 | C94: ='Юнит 12'!AO73 -> -483.29 | D94: =C94/C$105 -> -0.00026669811 | E94: =E93+D94 -> 1.0080953 | F94: =IF(AND(E94<=0),"C",IF(E94<=0.8,"A",IF(E94<=0.95,"B","C"))) -> C | G94: =VLOOKUP(B$4:B$104,I$4:M$104,5,0) -> C | I94: Qianai коричневые | J94: ='Юнит 12'!U84 -> 0 | K94: =J94/J$105 -> 0 | L94: =L93+K94 -> 0.99296129 | M94: =_xlfn.IFS(L94<80%,"A",L94<=95%,"B",L94>95%,"C") -> C
B95: sh18 | C95: ='Юнит 12'!AO42 -> -561.02782 | D95: =C95/C$105 -> -0.00030959685 | E95: =E94+D95 -> 1.0077857 | F95: =IF(AND(E95<=0),"C",IF(E95<=0.8,"A",IF(E95<=0.95,"B","C"))) -> C | G95: =VLOOKUP(B$4:B$104,I$4:M$104,5,0) -> C | I95: Linhai Baiyi коричневая линза | J95: ='Юнит 12'!U86 -> 0 | K95: =J95/J$105 -> 0 | L95: =L94+K95 -> 0.99296129 | M95: =_xlfn.IFS(L95<80%,"A",L95<=95%,"B",L95>95%,"C") -> C
B96: MANNA2122 | C96: ='Юнит 12'!AO75 -> -599.92596 | D96: =C96/C$105 -> -0.00033106234 | E96: =E95+D96 -> 1.0074547 | F96: =IF(AND(E96<=0),"C",IF(E96<=0.8,"A",IF(E96<=0.95,"B","C"))) -> C | G96: =VLOOKUP(B$4:B$104,I$4:M$104,5,0) -> C | I96: Taizhou Rayen sport розовый | J96: ='Юнит 12'!U90 -> 0 | K96: =J96/J$105 -> 0 | L96: =L95+K96 -> 0.99296129 | M96: =_xlfn.IFS(L96<80%,"A",L96<=95%,"B",L96>95%,"C") -> C
B97: ww 8010 черные | C97: ='Юнит 12'!AO51 -> -752.1645 | D97: =C97/C$105 -> -0.00041507346 | E97: =E96+D97 -> 1.0070396 | F97: =IF(AND(E97<=0),"C",IF(E97<=0.8,"A",IF(E97<=0.95,"B","C"))) -> C | G97: =VLOOKUP(B$4:B$104,I$4:M$104,5,0) -> C | I97: Ли Сян ретро золото | J97: ='Юнит 12'!U92 -> 0 | K97: =J97/J$105 -> 0 | L97: =L96+K97 -> 0.99296129 | M97: =_xlfn.IFS(L97<80%,"A",L97<=95%,"B",L97>95%,"C") -> C
B98: sh19 | C98: ='Юнит 12'!AO43 -> -902.4 | D98: =C98/C$105 -> -0.00049797921 | E98: =E97+D98 -> 1.0065416 | F98: =IF(AND(E98<=0),"C",IF(E98<=0.8,"A",IF(E98<=0.95,"B","C"))) -> C | G98: =VLOOKUP(B$4:B$104,I$4:M$104,5,0) -> C | I98: MAIERSHA 03898 C9-08 | J98: ='Юнит 12'!U94 -> 0 | K98: =J98/J$105 -> 0 | L98: =L97+K98 -> 0.99296129 | M98: =_xlfn.IFS(L98<80%,"A",L98<=95%,"B",L98>95%,"C") -> C
B99: Keming Aishi коричневые | C99: ='Юнит 12'!AO85 -> -1161.3418 | D99: =C99/C$105 -> -0.00064087333 | E99: =E93+D99 -> 1.0077211 | F99: =IF(AND(E99<=0),"C",IF(E99<=0.8,"A",IF(E99<=0.95,"B","C"))) -> C | G99: =VLOOKUP(B$4:B$104,I$4:M$104,5,0) -> C | I99: MAIERSHA 03914 C9-124 | J99: ='Юнит 12'!U95 -> 0 | K99: =J99/J$105 -> 0 | L99: =L93+K99 -> 0.99296129 | M99: =_xlfn.IFS(L99<80%,"A",L99<=95%,"B",L99>95%,"C") -> C
B100: Qianai коричневые | C100: ='Юнит 12'!AO84 -> -1287.8628 | D100: =C100/C$105 -> -0.00071069249 | E100: =E94+D100 -> 1.0073846 | F100: =IF(AND(E100<=0),"C",IF(E100<=0.8,"A",IF(E100<=0.95,"B","C"))) -> C | G100: =VLOOKUP(B$4:B$104,I$4:M$104,5,0) -> C | I100: MARSTON 7171 C1 | J100: ='Юнит 12'!U96 -> 0 | K100: =J100/J$105 -> 0 | L100: =L94+K100 -> 0.99296129 | M100: =_xlfn.IFS(L100<80%,"A",L100<=95%,"B",L100>95%,"C") -> C
B101: Chenlong черные | C101: ='Юнит 12'!AO76 -> -1329.4328 | D101: =C101/C$105 -> -0.00073363242 | E101: =E95+D101 -> 1.0070521 | F101: =IF(AND(E101<=0),"C",IF(E101<=0.8,"A",IF(E101<=0.95,"B","C"))) -> C | G101: =VLOOKUP(B$4:B$104,I$4:M$104,5,0) -> C | I101: ЧСЖ_тест | J101: ='Юнит 12'!U99 -> 0 | K101: =J101/J$105 -> 0 | L101: =L95+K101 -> 0.99296129 | M101: =_xlfn.IFS(L101<80%,"A",L101<=95%,"B",L101>95%,"C") -> C
...

Sheet АВС 11
B2: ОЧКИ
C3: Прибыль | D3: % прибыль | E3: Доля | F3: ABC прибыль | G3: ABC кол-во | J3: Кол-во | K3: % кол-во | L3: Доля | M3: ABC кол-во
B4: QS черные PZ | C4: ='Юнит 11'!AO4 -> 372695.38 | D4: =C4/C$105 -> 0.27996811 | E4: =D4 -> 0.27996811 | F4: =IF(AND(E4<=0),"C",IF(E4<=0.8,"A",IF(E4<=0.95,"B","C"))) -> A | G4: =VLOOKUP(B$4:B$104,I$4:M$104,5,0) -> A | I4: QS черные PZ | J4: ='Юнит 11'!U4 -> 758 | K4: =J4/J$105 -> 0.22163743 | L4: =K4 -> 0.22163743 | M4: =_xlfn.IFS(L4<80%,"A",L4<=95%,"B",L4>95%,"C") -> A | P4: A | Q4: 0.8
B5: th черн | C5: ='Юнит 11'!AO9 -> 101443.23 | D5: =C5/C$105 -> 0.076203977 | E5: =E4+D5 -> 0.35617209 | F5: =IF(AND(E5<=0),"C",IF(E5<=0.8,"A",IF(E5<=0.95,"B","C"))) -> A | G5: =VLOOKUP(B$4:B$104,I$4:M$104,5,0) -> A | I5: flip черные | J5: ='Юнит 11'!U13 -> 244 | K5: =J5/J$105 -> 0.071345029 | L5: =L4+K5 -> 0.29298246 | M5: =_xlfn.IFS(L5<80%,"A",L5<=95%,"B",L5>95%,"C") -> A | P5: B | Q5: 0.15
B6: flip черные | C6: ='Юнит 11'!AO13 -> 98640.755 | D6: =C6/C$105 -> 0.074098761 | E6: =E5+D6 -> 0.43027085 | F6: =IF(AND(E6<=0),"C",IF(E6<=0.8,"A",IF(E6<=0.95,"B","C"))) -> A | G6: =VLOOKUP(B$4:B$104,I$4:M$104,5,0) -> A | I6: th черн | J6: ='Юнит 11'!U9 -> 237 | K6: =J6/J$105 -> 0.069298246 | L6: =L5+K6 -> 0.3622807 | M6: =_xlfn.IFS(L6<80%,"A",L6<=95%,"B",L6>95%,"C") -> A | P6: C | Q6: 0.05
B7: QS коричневые PZ | C7: ='Юнит 11'!AO7 -> 90179.079 | D7: =C7/C$105 -> 0.067742366 | E7: =E6+D7 -> 0.49801322 | F7: =IF(AND(E7<=0),"C",IF(E7<=0.8,"A",IF(E7<=0.95,"B","C"))) -> A | G7: =VLOOKUP(B$4:B$104,I$4:M$104,5,0) -> A | I7: flip коричневые | J7: ='Юнит 11'!U16 -> 213 | K7: =J7/J$105 -> 0.062280702 | L7: =L6+K7 -> 0.4245614 | M7: =_xlfn.IFS(L7<80%,"A",L7<=95%,"B",L7>95%,"C") -> A
B8: flip коричневые | C8: ='Юнит 11'!AO16 -> 85947.698 | D8: =C8/C$105 -> 0.064563759 | E8: =E7+D8 -> 0.56257698 | F8: =IF(AND(E8<=0),"C",IF(E8<=0.8,"A",IF(E8<=0.95,"B","C"))) -> A | G8: =VLOOKUP(B$4:B$104,I$4:M$104,5,0) -> A | I8: QS коричневые PZ | J8: ='Юнит 11'!U7 -> 212 | K8: =J8/J$105 -> 0.061988304 | L8: =L7+K8 -> 0.48654971 | M8: =_xlfn.IFS(L8<80%,"A",L8<=95%,"B",L8>95%,"C") -> A
B9: черные с железкой классика | C9: ='Юнит 11'!AO3 -> 83816.677 | D9: =C9/C$105 -> 0.06296294 | E9: =E8+D9 -> 0.62553992 | F9: =IF(AND(E9<=0),"C",IF(E9<=0.8,"A",IF(E9<=0.95,"B","C"))) -> A | G9: =VLOOKUP(B$4:B$104,I$4:M$104,5,0) -> A | I9: th син | J9: ='Юнит 11'!U10 -> 199 | K9: =J9/J$105 -> 0.058187135 | L9: =L8+K9 -> 0.54473684 | M9: =_xlfn.IFS(L9<80%,"A",L9<=95%,"B",L9>95%,"C") -> A
B10: QS синие PZ | C10: ='Юнит 11'!AO5 -> 76669.887 | D10: =C10/C$105 -> 0.057594284 | E10: =E9+D10 -> 0.6831342 | F10: =IF(AND(E10<=0),"C",IF(E10<=0.8,"A",IF(E10<=0.95,"B","C"))) -> A | G10: =VLOOKUP(B$4:B$104,I$4:M$104,5,0) -> A | I10: QS синие PZ | J10: ='Юнит 11'!U5 -> 189 | K10: =J10/J$105 -> 0.055263158 | L10: =L9+K10 -> 0.6 | M10: =_xlfn.IFS(L10<80%,"A",L10<=95%,"B",L10>95%,"C") -> A
B11: th син | C11: ='Юнит 11'!AO10 -> 65001.22 | D11: =C11/C$105 -> 0.048828802 | E11: =E10+D11 -> 0.731963 | F11: =IF(AND(E11<=0),"C",IF(E11<=0.8,"A",IF(E11<=0.95,"B","C"))) -> A | G11: =VLOOKUP(B$4:B$104,I$4:M$104,5,0) -> A | I11: черные с железкой классика | J11: ='Юнит 11'!U3 -> 174 | K11: =J11/J$105 -> 0.050877193 | L11: =L10+K11 -> 0.65087719 | M11: =_xlfn.IFS(L11<80%,"A",L11<=95%,"B",L11>95%,"C") -> A
B12: th коричн | C12: ='Юнит 11'!AO12 -> 47119.494 | D12: =C12/C$105 -> 0.035396081 | E12: =E11+D12 -> 0.76735908 | F12: =IF(AND(E12<=0),"C",IF(E12<=0.8,"A",IF(E12<=0.95,"B","C"))) -> A | G12: =VLOOKUP(B$4:B$104,I$4:M$104,5,0) -> A | I12: sh3 | J12: ='Юнит 11'!U28 -> 161 | K12: =J12/J$105 -> 0.047076023 | L12: =L11+K12 -> 0.69795322 | M12: =_xlfn.IFS(L12<80%,"A",L12<=95%,"B",L12>95%,"C") -> A
B13: sh3 | C13: ='Юнит 11'!AO28 -> 46993.254 | D13: =C13/C$105 -> 0.035301249 | E13: =E12+D13 -> 0.80266033 | F13: =IF(AND(E13<=0),"C",IF(E13<=0.8,"A",IF(E13<=0.95,"B","C"))) -> B | G13: =VLOOKUP(B$4:B$104,I$4:M$104,5,0) -> A | I13: th коричн | J13: ='Юнит 11'!U12 -> 131 | K13: =J13/J$105 -> 0.038304094 | L13: =L12+K13 -> 0.73625731 | M13: =_xlfn.IFS(L13<80%,"A",L13<=95%,"B",L13>95%,"C") -> A
B14: QS желтые PZ | C14: ='Юнит 11'!AO6 -> 41935.561 | D14: =C14/C$105 -> 0.03150192 | E14: =E13+D14 -> 0.83416225 | F14: =IF(AND(E14<=0),"C",IF(E14<=0.8,"A",IF(E14<=0.95,"B","C"))) -> B | G14: =VLOOKUP(B$4:B$104,I$4:M$104,5,0) -> A | I14: QS желтые PZ | J14: ='Юнит 11'!U6 -> 116 | K14: =J14/J$105 -> 0.033918129 | L14: =L13+K14 -> 0.77017544 | M14: =_xlfn.IFS(L14<80%,"A",L14<=95%,"B",L14>95%,"C") -> A
B15: th желт | C15: ='Юнит 11'!AO11 -> 36095.771 | D15: =C15/C$105 -> 0.02711508 | E15: =E14+D15 -> 0.86127733 | F15: =IF(AND(E15<=0),"C",IF(E15<=0.8,"A",IF(E15<=0.95,"B","C"))) -> B | G15: =VLOOKUP(B$4:B$104,I$4:M$104,5,0) -> B | I15: th желт | J15: ='Юнит 11'!U11 -> 103 | K15: =J15/J$105 -> 0.030116959 | L15: =L14+K15 -> 0.8002924 | M15: =_xlfn.IFS(L15<80%,"A",L15<=95%,"B",L15>95%,"C") -> B
B16: ww 1022 коричневые | C16: ='Юнит 11'!AO48 -> 30869.087 | D16: =C16/C$105 -> 0.023188804 | E16: =E15+D16 -> 0.88446614 | F16: =IF(AND(E16<=0),"C",IF(E16<=0.8,"A",IF(E16<=0.95,"B","C"))) -> B | G16: =VLOOKUP(B$4:B$104,I$4:M$104,5,0) -> B | I16: wwl8032 хром металл | J16: ='Юнит 11'!U18 -> 80 | K16: =J16/J$105 -> 0.023391813 | L16: =L15+K16 -> 0.82368421 | M16: =_xlfn.IFS(L16<80%,"A",L16<=95%,"B",L16>95%,"C") -> B
B17: wwl8032 хром металл | C17: ='Юнит 11'!AO18 -> 29336.565 | D17: =C17/C$105 -> 0.022037576 | E17: =E16+D17 -> 0.90650371 | F17: =IF(AND(E17<=0),"C",IF(E17<=0.8,"A",IF(E17<=0.95,"B","C"))) -> B | G17: =VLOOKUP(B$4:B$104,I$4:M$104,5,0) -> B | I17: ww 1022 коричневые | J17: ='Юнит 11'!U48 -> 78 | K17: =J17/J$105 -> 0.022807018 | L17: =L16+K17 -> 0.84649123 | M17: =_xlfn.IFS(L17<80%,"A",L17<=95%,"B",L17>95%,"C") -> B
B18: flip синие | C18: ='Юнит 11'!AO14 -> 22061.684 | D18: =C18/C$105 -> 0.016572698 | E18: =E17+D18 -> 0.92307641 | F18: =IF(AND(E18<=0),"C",IF(E18<=0.8,"A",IF(E18<=0.95,"B","C"))) -> B | G18: =VLOOKUP(B$4:B$104,I$4:M$104,5,0) -> B | I18: ww 1022 черные | J18: ='Юнит 11'!U45 -> 65 | K18: =J18/J$105 -> 0.019005848 | L18: =L17+K18 -> 0.86549708 | M18: =_xlfn.IFS(L18<80%,"A",L18<=95%,"B",L18>95%,"C") -> B
B19: MR8854 C2 Жен | C19: ='Юнит 11'!AO8 -> 18609.356 | D19: =C19/C$105 -> 0.013979316 | E19: =E18+D19 -> 0.93705573 | F19: =IF(AND(E19<=0),"C",IF(E19<=0.8,"A",IF(E19<=0.95,"B","C"))) -> B | G19: =VLOOKUP(B$4:B$104,I$4:M$104,5,0) -> B | I19: flip синие | J19: ='Юнит 11'!U14 -> 59 | K19: =J19/J$105 -> 0.017251462 | L19: =L18+K19 -> 0.88274854 | M19: =_xlfn.IFS(L19<80%,"A",L19<=95%,"B",L19>95%,"C") -> B
B20: flip желтые | C20: ='Юнит 11'!AO15 -> 17310.689 | D20: =C20/C$105 -> 0.013003759 | E20: =E19+D20 -> 0.95005949 | F20: =IF(AND(E20<=0),"C",IF(E20<=0.8,"A",IF(E20<=0.95,"B","C"))) -> C | G20: =VLOOKUP(B$4:B$104,I$4:M$104,5,0) -> B | I20: sh1 | J20: ='Юнит 11'!U26 -> 47 | K20: =J20/J$105 -> 0.01374269 | L20: =L19+K20 -> 0.89649123 | M20: =_xlfn.IFS(L20<80%,"A",L20<=95%,"B",L20>95%,"C") -> B
B21: ww 1022 черные | C21: ='Юнит 11'!AO45 -> 16241.369 | D21: =C21/C$105 -> 0.012200488 | E21: =E20+D21 -> 0.96225997 | F21: =IF(AND(E21<=0),"C",IF(E21<=0.8,"A",IF(E21<=0.95,"B","C"))) -> C | G21: =VLOOKUP(B$4:B$104,I$4:M$104,5,0) -> B | I21: flip желтые | J21: ='Юнит 11'!U15 -> 45 | K21: =J21/J$105 -> 0.013157895 | L21: =L20+K21 -> 0.90964912 | M21: =_xlfn.IFS(L21<80%,"A",L21<=95%,"B",L21>95%,"C") -> B
B22: ww 2018 желтые | C22: ='Юнит 11'!AO50 -> 12918.717 | D22: =C22/C$105 -> 0.0097045174 | E22: =E21+D22 -> 0.97196449 | F22: =IF(AND(E22<=0),"C",IF(E22<=0.8,"A",IF(E22<=0.95,"B","C"))) -> C | G22: =VLOOKUP(B$4:B$104,I$4:M$104,5,0) -> B | I22: ww 2018 черные | J22: ='Юнит 11'!U49 -> 41 | K22: =J22/J$105 -> 0.011988304 | L22: =L21+K22 -> 0.92163743 | M22: =_xlfn.IFS(L22<80%,"A",L22<=95%,"B",L22>95%,"C") -> B
B23: ww 2018 черные | C23: ='Юнит 11'!AO49 -> 9394.169 | D23: =C23/C$105 -> 0.0070568832 | E23: =E22+D23 -> 0.97902137 | F23: =IF(AND(E23<=0),"C",IF(E23<=0.8,"A",IF(E23<=0.95,"B","C"))) -> C | G23: =VLOOKUP(B$4:B$104,I$4:M$104,5,0) -> B | I23: MR8854 C2 Жен | J23: ='Юнит 11'!U8 -> 40 | K23: =J23/J$105 -> 0.011695906 | L23: =L22+K23 -> 0.93333333 | M23: =_xlfn.IFS(L23<80%,"A",L23<=95%,"B",L23>95%,"C") -> B
B24: ww 1022 желтые | C24: ='Юнит 11'!AO47 -> 7539.9411 | D24: =C24/C$105 -> 0.0056639905 | E24: =E23+D24 -> 0.98468537 | F24: =IF(AND(E24<=0),"C",IF(E24<=0.8,"A",IF(E24<=0.95,"B","C"))) -> C | G24: =VLOOKUP(B$4:B$104,I$4:M$104,5,0) -> C | I24: ww 2018 желтые | J24: ='Юнит 11'!U50 -> 40 | K24: =J24/J$105 -> 0.011695906 | L24: =L23+K24 -> 0.94502924 | M24: =_xlfn.IFS(L24<80%,"A",L24<=95%,"B",L24>95%,"C") -> B
B25: ww 203 черные | C25: ='Юнит 11'!AO44 -> 7503.8357 | D25: =C25/C$105 -> 0.0056368682 | E25: =E24+D25 -> 0.99032223 | F25: =IF(AND(E25<=0),"C",IF(E25<=0.8,"A",IF(E25<=0.95,"B","C"))) -> C | G25: =VLOOKUP(B$4:B$104,I$4:M$104,5,0) -> C | I25: ww 203 черные | J25: ='Юнит 11'!U44 -> 31 | K25: =J25/J$105 -> 0.0090643275 | L25: =L24+K25 -> 0.95409357 | M25: =_xlfn.IFS(L25<80%,"A",L25<=95%,"B",L25>95%,"C") -> C
B26: кс_черные_женские | C26: ='Юнит 11'!AO102 -> 6221.3993 | D26: =C26/C$105 -> 0.0046735042 | E26: =E25+D26 -> 0.99499574 | F26: =IF(AND(E26<=0),"C",IF(E26<=0.8,"A",IF(E26<=0.95,"B","C"))) -> C | G26: =VLOOKUP(B$4:B$104,I$4:M$104,5,0) -> C | I26: ww 1022 желтые | J26: ='Юнит 11'!U47 -> 24 | K26: =J26/J$105 -> 0.0070175439 | L26: =L25+K26 -> 0.96111111 | M26: =_xlfn.IFS(L26<80%,"A",L26<=95%,"B",L26>95%,"C") -> C
B27: wwl8032 коричневые золото | C27: ='Юнит 11'!AO17 -> 4815.3401 | D27: =C27/C$105 -> 0.003617275 | E27: =E26+D27 -> 0.99861301 | F27: =IF(AND(E27<=0),"C",IF(E27<=0.8,"A",IF(E27<=0.95,"B","C"))) -> C | G27: =VLOOKUP(B$4:B$104,I$4:M$104,5,0) -> C | I27: wwl8032 коричневые золото | J27: ='Юнит 11'!U17 -> 19 | K27: =J27/J$105 -> 0.0055555556 | L27: =L26+K27 -> 0.96666667 | M27: =_xlfn.IFS(L27<80%,"A",L27<=95%,"B",L27>95%,"C") -> C
B28: sh19 | C28: ='Юнит 11'!AO43 -> 4196.4358 | D28: =C28/C$105 -> 0.0031523552 | E28: =E27+D28 -> 1.0017654 | F28: =IF(AND(E28<=0),"C",IF(E28<=0.8,"A",IF(E28<=0.95,"B","C"))) -> C | G28: =VLOOKUP(B$4:B$104,I$4:M$104,5,0) -> C | I28: кс_черные_женские | J28: ='Юнит 11'!U102 -> 17 | K28: =J28/J$105 -> 0.0049707602 | L28: =L27+K28 -> 0.97163743 | M28: =_xlfn.IFS(L28<80%,"A",L28<=95%,"B",L28>95%,"C") -> C
B29: sh15 | C29: ='Юнит 11'!AO39 -> 2682.254 | D29: =C29/C$105 -> 0.0020149045 | E29: =E28+D29 -> 1.0037803 | F29: =IF(AND(E29<=0),"C",IF(E29<=0.8,"A",IF(E29<=0.95,"B","C"))) -> C | G29: =VLOOKUP(B$4:B$104,I$4:M$104,5,0) -> C | I29: sh2 | J29: ='Юнит 11'!U27 -> 12 | K29: =J29/J$105 -> 0.0035087719 | L29: =L28+K29 -> 0.9751462 | M29: =_xlfn.IFS(L29<80%,"A",L29<=95%,"B",L29>95%,"C") -> C
B30: Linhai Baiyi розовая линза | C30: ='Юнит 11'!AO88 -> 2197.8883 | D30: =C30/C$105 -> 0.0016510499 | E30: =E29+D30 -> 1.0054313 | F30: =IF(AND(E30<=0),"C",IF(E30<=0.8,"A",IF(E30<=0.95,"B","C"))) -> C | G30: =VLOOKUP(B$4:B$104,I$4:M$104,5,0) -> C | I30: sh19 | J30: ='Юнит 11'!U43 -> 12 | K30: =J30/J$105 -> 0.0035087719 | L30: =L29+K30 -> 0.97865497 | M30: =_xlfn.IFS(L30<80%,"A",L30<=95%,"B",L30>95%,"C") -> C
B31: sh18 | C31: ='Юнит 11'!AO42 -> 2188.725 | D31: =C31/C$105 -> 0.0016441664 | E31: =E30+D31 -> 1.0070755 | F31: =IF(AND(E31<=0),"C",IF(E31<=0.8,"A",IF(E31<=0.95,"B","C"))) -> C | G31: =VLOOKUP(B$4:B$104,I$4:M$104,5,0) -> C | I31: sh15 | J31: ='Юнит 11'!U39 -> 10 | K31: =J31/J$105 -> 0.0029239766 | L31: =L30+K31 -> 0.98157895 | M31: =_xlfn.IFS(L31<80%,"A",L31<=95%,"B",L31>95%,"C") -> C
B32: ww 8010 черные | C32: ='Юнит 11'!AO51 -> 1306.853 | D32: =C32/C$105 -> 0.00098170567 | E32: =E31+D32 -> 1.0080572 | F32: =IF(AND(E32<=0),"C",IF(E32<=0.8,"A",IF(E32<=0.95,"B","C"))) -> C | G32: =VLOOKUP(B$4:B$104,I$4:M$104,5,0) -> C | I32: sh18 | J32: ='Юнит 11'!U42 -> 5 | K32: =J32/J$105 -> 0.0014619883 | L32: =L31+K32 -> 0.98304094 | M32: =_xlfn.IFS(L32<80%,"A",L32<=95%,"B",L32>95%,"C") -> C
B33: sh16 | C33: ='Юнит 11'!AO40 -> 1276.7088 | D33: =C33/C$105 -> 0.00095906141 | E33: =E32+D33 -> 1.0090163 | F33: =IF(AND(E33<=0),"C",IF(E33<=0.8,"A",IF(E33<=0.95,"B","C"))) -> C | G33: =VLOOKUP(B$4:B$104,I$4:M$104,5,0) -> C | I33: MANNA2105 | J33: ='Юнит 11'!U58 -> 5 | K33: =J33/J$105 -> 0.0014619883 | L33: =L32+K33 -> 0.98450292 | M33: =_xlfn.IFS(L33<80%,"A",L33<=95%,"B",L33>95%,"C") -> C
B34: Linhai Baiyi коричневая линза | C34: ='Юнит 11'!AO86 -> 1271.0432 | D34: =C34/C$105 -> 0.00095480545 | E34: =E33+D34 -> 1.0099711 | F34: =IF(AND(E34<=0),"C",IF(E34<=0.8,"A",IF(E34<=0.95,"B","C"))) -> C | G34: =VLOOKUP(B$4:B$104,I$4:M$104,5,0) -> C | I34: MANNA2122 | J34: ='Юнит 11'!U75 -> 5 | K34: =J34/J$105 -> 0.0014619883 | L34: =L33+K34 -> 0.98596491 | M34: =_xlfn.IFS(L34<80%,"A",L34<=95%,"B",L34>95%,"C") -> C
B35: MR Р1894 черные | C35: ='Юнит 11'!AO89 -> 1130.3385 | D35: =C35/C$105 -> 0.00084910831 | E35: =E34+D35 -> 1.0108202 | F35: =IF(AND(E35<=0),"C",IF(E35<=0.8,"A",IF(E35<=0.95,"B","C"))) -> C | G35: =VLOOKUP(B$4:B$104,I$4:M$104,5,0) -> C | I35: Linhai Baiyi серая линза | J35: ='Юнит 11'!U87 -> 5 | K35: =J35/J$105 -> 0.0014619883 | L35: =L34+K35 -> 0.9874269 | M35: =_xlfn.IFS(L35<80%,"A",L35<=95%,"B",L35>95%,"C") -> C
B36: Keming Aishi коричневые | C36: ='Юнит 11'!AO85 -> 1055.4695 | D36: =C36/C$105 -> 0.00079286682 | E36: =E35+D36 -> 1.011613 | F36: =IF(AND(E36<=0),"C",IF(E36<=0.8,"A",IF(E36<=0.95,"B","C"))) -> C | G36: =VLOOKUP(B$4:B$104,I$4:M$104,5,0) -> C | I36: Linhai Baiyi розовая линза | J36: ='Юнит 11'!U88 -> 5 | K36: =J36/J$105 -> 0.0014619883 | L36: =L35+K36 -> 0.98888889 | M36: =_xlfn.IFS(L36<80%,"A",L36<=95%,"B",L36>95%,"C") -> C
B37: ЧСЖ_женские | C37: ='Юнит 11'!AO100 -> 800.73503 | D37: =C37/C$105 -> 0.00060151074 | E37: =E36+D37 -> 1.0122145 | F37: =IF(AND(E37<=0),"C",IF(E37<=0.8,"A",IF(E37<=0.95,"B","C"))) -> C | G37: =VLOOKUP(B$4:B$104,I$4:M$104,5,0) -> C | I37: Keming Aishi коричневые | J37: ='Юнит 11'!U85 -> 4 | K37: =J37/J$105 -> 0.0011695906 | L37: =L36+K37 -> 0.99005848 | M37: =_xlfn.IFS(L37<80%,"A",L37<=95%,"B",L37>95%,"C") -> C
B38: MANNA2119 | C38: ='Юнит 11'!AO72 -> 537.4095 | D38: =C38/C$105 -> 0.00040370107 | E38: =E37+D38 -> 1.0126182 | F38: =IF(AND(E38<=0),"C",IF(E38<=0.8,"A",IF(E38<=0.95,"B","C"))) -> C | G38: =VLOOKUP(B$4:B$104,I$4:M$104,5,0) -> C | I38: sh16 | J38: ='Юнит 11'!U40 -> 3 | K38: =J38/J$105 -> 0.00087719298 | L38: =L37+K38 -> 0.99093567 | M38: =_xlfn.IFS(L38<80%,"A",L38<=95%,"B",L38>95%,"C") -> C
B39: MAIERSHA 03898 C9-08 | C39: ='Юнит 11'!AO94 -> 311.817 | D39: =C39/C$105 -> 0.00023423638 | E39: =E35+D39 -> 1.0110544 | F39: =IF(AND(E39<=0),"C",IF(E39<=0.8,"A",IF(E39<=0.95,"B","C"))) -> C | G39: =VLOOKUP(B$4:B$104,I$4:M$104,5,0) -> C | I39: ww 8010 черные | J39: ='Юнит 11'!U51 -> 3 | K39: =J39/J$105 -> 0.00087719298 | L39: =L35+K39 -> 0.98830409 | M39: =_xlfn.IFS(L39<80%,"A",L39<=95%,"B",L39>95%,"C") -> C
B40: Chenlong черные | C40: ='Юнит 11'!AO76 -> 292.84346 | D40: =C40/C$105 -> 0.00021998349 | E40: =E39+D40 -> 1.0112744 | F40: =IF(AND(E40<=0),"C",IF(E40<=0.8,"A",IF(E40<=0.95,"B","C"))) -> C | G40: =VLOOKUP(B$4:B$104,I$4:M$104,5,0) -> C | I40: MANNA2118 | J40: ='Юнит 11'!U71 -> 3 | K40: =J40/J$105 -> 0.00087719298 | L40: =L39+K40 -> 0.98918129 | M40: =_xlfn.IFS(L40<80%,"A",L40<=95%,"B",L40>95%,"C") -> C
B41: MANNA2107 | C41: ='Юнит 11'!AO60 -> 273.02262 | D41: =C41/C$105 -> 0.00020509411 | E41: =E40+D41 -> 1.0114795 | F41: =IF(AND(E41<=0),"C",IF(E41<=0.8,"A",IF(E41<=0.95,"B","C"))) -> C | G41: =VLOOKUP(B$4:B$104,I$4:M$104,5,0) -> C | I41: Linhai Baiyi коричневая линза | J41: ='Юнит 11'!U86 -> 3 | K41: =J41/J$105 -> 0.00087719298 | L41: =L40+K41 -> 0.99005848 | M41: =_xlfn.IFS(L41<80%,"A",L41<=95%,"B",L41>95%,"C") -> C
B42: MANNA2116 | C42: ='Юнит 11'!AO69 -> 192.25938 | D42: =C42/C$105 -> 0.00014442491 | E42: =E41+D42 -> 1.0116239 | F42: =IF(AND(E42<=0),"C",IF(E42<=0.8,"A",IF(E42<=0.95,"B","C"))) -> C | G42: =VLOOKUP(B$4:B$104,I$4:M$104,5,0) -> C | I42: ЧСЖ_женские | J42: ='Юнит 11'!U100 -> 3 | K42: =J42/J$105 -> 0.00087719298 | L42: =L41+K42 -> 0.99093567 | M42: =_xlfn.IFS(L42<80%,"A",L42<=95%,"B",L42>95%,"C") -> C
B43: Ли Сян ретро серебро | C43: ='Юнит 11'!AO93 -> 172.40769 | D43: =C43/C$105 -> 0.00012951235 | E43: =E42+D43 -> 1.0117534 | F43: =IF(AND(E43<=0),"C",IF(E43<=0.8,"A",IF(E43<=0.95,"B","C"))) -> C | G43: =VLOOKUP(B$4:B$104,I$4:M$104,5,0) -> C | I43: MANNA2101 | J43: ='Юнит 11'!U54 -> 2 | K43: =J43/J$105 -> 0.00058479532 | L43: =L42+K43 -> 0.99152047 | M43: =_xlfn.IFS(L43<80%,"A",L43<=95%,"B",L43>95%,"C") -> C
B44: sh06 | C44: ='Юнит 11'!AO30 -> 169.4869 | D44: =C44/C$105 -> 0.00012731826 | E44: =E43+D44 -> 1.0118807 | F44: =IF(AND(E44<=0),"C",IF(E44<=0.8,"A",IF(E44<=0.95,"B","C"))) -> C | G44: =VLOOKUP(B$4:B$104,I$4:M$104,5,0) -> C | I44: MANNA2107 | J44: ='Юнит 11'!U60 -> 2 | K44: =J44/J$105 -> 0.00058479532 | L44: =L43+K44 -> 0.99210526 | M44: =_xlfn.IFS(L44<80%,"A",L44<=95%,"B",L44>95%,"C") -> C
B45: sh07 | C45: ='Юнит 11'!AO31 -> 164.6256 | D45: =C45/C$105 -> 0.00012366646 | E45: =E44+D45 -> 1.0120044 | F45: =IF(AND(E45<=0),"C",IF(E45<=0.8,"A",IF(E45<=0.95,"B","C"))) -> C | G45: =VLOOKUP(B$4:B$104,I$4:M$104,5,0) -> C | I45: MANNA2119 | J45: ='Юнит 11'!U72 -> 2 | K45: =J45/J$105 -> 0.00058479532 | L45: =L44+K45 -> 0.99269006 | M45: =_xlfn.IFS(L45<80%,"A",L45<=95%,"B",L45>95%,"C") -> C
B46: MANNA2122 | C46: ='Юнит 11'!AO75 -> 102.2359 | D46: =C46/C$105 -> 7.6799426e-05 | E46: =E45+D46 -> 1.0120812 | F46: =IF(AND(E46<=0),"C",IF(E46<=0.8,"A",IF(E46<=0.95,"B","C"))) -> C | G46: =VLOOKUP(B$4:B$104,I$4:M$104,5,0) -> C | I46: MR Р1894 черные | J46: ='Юнит 11'!U89 -> 2 | K46: =J46/J$105 -> 0.00058479532 | L46: =L45+K46 -> 0.99327485 | M46: =_xlfn.IFS(L46<80%,"A",L46<=95%,"B",L46>95%,"C") -> C
B47: wwl8032 черные серебро | C47: ='Юнит 11'!AO19 -> 0 | D47: =C47/C$105 -> 0 | E47: =E46+D47 -> 1.0120812 | F47: =IF(AND(E47<=0),"C",IF(E47<=0.8,"A",IF(E47<=0.95,"B","C"))) -> C | G47: =VLOOKUP(B$4:B$104,I$4:M$104,5,0) -> C | I47: sh06 | J47: ='Юнит 11'!U30 -> 1 | K47: =J47/J$105 -> 0.00029239766 | L47: =L46+K47 -> 0.99356725 | M47: =_xlfn.IFS(L47<80%,"A",L47<=95%,"B",L47>95%,"C") -> C
B48: sports синие | C48: ='Юнит 11'!AO20 -> 0 | D48: =C48/C$105 -> 0 | E48: =E47+D48 -> 1.0120812 | F48: =IF(AND(E48<=0),"C",IF(E48<=0.8,"A",IF(E48<=0.95,"B","C"))) -> C | G48: =VLOOKUP(B$4:B$104,I$4:M$104,5,0) -> C | I48: sh07 | J48: ='Юнит 11'!U31 -> 1 | K48: =J48/J$105 -> 0.00029239766 | L48: =L47+K48 -> 0.99385965 | M48: =_xlfn.IFS(L48<80%,"A",L48<=95%,"B",L48>95%,"C") -> C
B49: sports зеленые | C49: ='Юнит 11'!AO21 -> 0 | D49: =C49/C$105 -> 0 | E49: =E48+D49 -> 1.0120812 | F49: =IF(AND(E49<=0),"C",IF(E49<=0.8,"A",IF(E49<=0.95,"B","C"))) -> C | G49: =VLOOKUP(B$4:B$104,I$4:M$104,5,0) -> C | I49: sh09 | J49: ='Юнит 11'!U33 -> 1 | K49: =J49/J$105 -> 0.00029239766 | L49: =L48+K49 -> 0.99415205 | M49: =_xlfn.IFS(L49<80%,"A",L49<=95%,"B",L49>95%,"C") -> C
B50: sports красные | C50: ='Юнит 11'!AO22 -> 0 | D50: =C50/C$105 -> 0 | E50: =E49+D50 -> 1.0120812 | F50: =IF(AND(E50<=0),"C",IF(E50<=0.8,"A",IF(E50<=0.95,"B","C"))) -> C | G50: =VLOOKUP(B$4:B$104,I$4:M$104,5,0) -> C | I50: MANNA2116 | J50: ='Юнит 11'!U69 -> 1 | K50: =J50/J$105 -> 0.00029239766 | L50: =L49+K50 -> 0.99444444 | M50: =_xlfn.IFS(L50<80%,"A",L50<=95%,"B",L50>95%,"C") -> C
B51: sportlife черные | C51: ='Юнит 11'!AO23 -> 0 | D51: =C51/C$105 -> 0 | E51: =E50+D51 -> 1.0120812 | F51: =IF(AND(E51<=0),"C",IF(E51<=0.8,"A",IF(E51<=0.95,"B","C"))) -> C | G51: =VLOOKUP(B$4:B$104,I$4:M$104,5,0) -> C | I51: MANNA2120 | J51: ='Юнит 11'!U73 -> 1 | K51: =J51/J$105 -> 0.00029239766 | L51: =L50+K51 -> 0.99473684 | M51: =_xlfn.IFS(L51<80%,"A",L51<=95%,"B",L51>95%,"C") -> C
B52: sportlife синие | C52: ='Юнит 11'!AO24 -> 0 | D52: =C52/C$105 -> 0 | E52: =E51+D52 -> 1.0120812 | F52: =IF(AND(E52<=0),"C",IF(E52<=0.8,"A",IF(E52<=0.95,"B","C"))) -> C | G52: =VLOOKUP(B$4:B$104,I$4:M$104,5,0) -> C | I52: Chenlong черные | J52: ='Юнит 11'!U76 -> 1 | K52: =J52/J$105 -> 0.00029239766 | L52: =L51+K52 -> 0.99502924 | M52: =_xlfn.IFS(L52<80%,"A",L52<=95%,"B",L52>95%,"C") -> C
B53: sportlife красные | C53: ='Юнит 11'!AO25 -> 0 | D53: =C53/C$105 -> 0 | E53: =E52+D53 -> 1.0120812 | F53: =IF(AND(E53<=0),"C",IF(E53<=0.8,"A",IF(E53<=0.95,"B","C"))) -> C | G53: =VLOOKUP(B$4:B$104,I$4:M$104,5,0) -> C | I53: Chenlong белые | J53: ='Юнит 11'!U78 -> 1 | K53: =J53/J$105 -> 0.00029239766 | L53: =L52+K53 -> 0.99532164 | M53: =_xlfn.IFS(L53<80%,"A",L53<=95%,"B",L53>95%,"C") -> C
B54: sh4 | C54: ='Юнит 11'!AO29 -> 0 | D54: =C54/C$105 -> 0 | E54: =E53+D54 -> 1.0120812 | F54: =IF(AND(E54<=0),"C",IF(E54<=0.8,"A",IF(E54<=0.95,"B","C"))) -> C | G54: =VLOOKUP(B$4:B$104,I$4:M$104,5,0) -> C | I54: Guangdu серебро серая линза | J54: ='Юнит 11'!U80 -> 1 | K54: =J54/J$105 -> 0.00029239766 | L54: =L53+K54 -> 0.99561404 | M54: =_xlfn.IFS(L54<80%,"A",L54<=95%,"B",L54>95%,"C") -> C
B55: sh08 | C55: ='Юнит 11'!AO32 -> 0 | D55: =C55/C$105 -> 0 | E55: =E54+D55 -> 1.0120812 | F55: =IF(AND(E55<=0),"C",IF(E55<=0.8,"A",IF(E55<=0.95,"B","C"))) -> C | G55: =VLOOKUP(B$4:B$104,I$4:M$104,5,0) -> C | I55: Hengda Optical черные | J55: ='Юнит 11'!U81 -> 1 | K55: =J55/J$105 -> 0.00029239766 | L55: =L54+K55 -> 0.99590643 | M55: =_xlfn.IFS(L55<80%,"A",L55<=95%,"B",L55>95%,"C") -> C
B56: sh11 | C56: ='Юнит 11'!AO35 -> 0 | D56: =C56/C$105 -> 0 | E56: =E55+D56 -> 1.0120812 | F56: =IF(AND(E56<=0),"C",IF(E56<=0.8,"A",IF(E56<=0.95,"B","C"))) -> C | G56: =VLOOKUP(B$4:B$104,I$4:M$104,5,0) -> C | I56: Ли Сян ретро серебро | J56: ='Юнит 11'!U93 -> 1 | K56: =J56/J$105 -> 0.00029239766 | L56: =L55+K56 -> 0.99619883 | M56: =_xlfn.IFS(L56<80%,"A",L56<=95%,"B",L56>95%,"C") -> C
B57: sh12 | C57: ='Юнит 11'!AO36 -> 0 | D57: =C57/C$105 -> 0 | E57: =E56+D57 -> 1.0120812 | F57: =IF(AND(E57<=0),"C",IF(E57<=0.8,"A",IF(E57<=0.95,"B","C"))) -> C | G57: =VLOOKUP(B$4:B$104,I$4:M$104,5,0) -> C | I57: MAIERSHA 03898 C9-08 | J57: ='Юнит 11'!U94 -> 1 | K57: =J57/J$105 -> 0.00029239766 | L57: =L56+K57 -> 0.99649123 | M57: =_xlfn.IFS(L57<80%,"A",L57<=95%,"B",L57>95%,"C") -> C
B58: ww 1022 черн-серебро | C58: ='Юнит 11'!AO46 -> 0 | D58: =C58/C$105 -> 0 | E58: =E57+D58 -> 1.0120812 | F58: =IF(AND(E58<=0),"C",IF(E58<=0.8,"A",IF(E58<=0.95,"B","C"))) -> C | G58: =VLOOKUP(B$4:B$104,I$4:M$104,5,0) -> C | I58: wwl8032 черные серебро | J58: ='Юнит 11'!U19 -> 0 | K58: =J58/J$105 -> 0 | L58: =L57+K58 -> 0.99649123 | M58: =_xlfn.IFS(L58<80%,"A",L58<=95%,"B",L58>95%,"C") -> C
B59: MANNA2102 | C59: ='Юнит 11'!AO55 -> 0 | D59: =C59/C$105 -> 0 | E59: =E58+D59 -> 1.0120812 | F59: =IF(AND(E59<=0),"C",IF(E59<=0.8,"A",IF(E59<=0.95,"B","C"))) -> C | G59: =VLOOKUP(B$4:B$104,I$4:M$104,5,0) -> C | I59: sports синие | J59: ='Юнит 11'!U20 -> 0 | K59: =J59/J$105 -> 0 | L59: =L58+K59 -> 0.99649123 | M59: =_xlfn.IFS(L59<80%,"A",L59<=95%,"B",L59>95%,"C") -> C
B60: MANNA2103 | C60: ='Юнит 11'!AO56 -> 0 | D60: =C60/C$105 -> 0 | E60: =E59+D60 -> 1.0120812 | F60: =IF(AND(E60<=0),"C",IF(E60<=0.8,"A",IF(E60<=0.95,"B","C"))) -> C | G60: =VLOOKUP(B$4:B$104,I$4:M$104,5,0) -> C | I60: sports зеленые | J60: ='Юнит 11'!U21 -> 0 | K60: =J60/J$105 -> 0 | L60: =L59+K60 -> 0.99649123 | M60: =_xlfn.IFS(L60<80%,"A",L60<=95%,"B",L60>95%,"C") -> C
B61: MANNA2104 | C61: ='Юнит 11'!AO57 -> 0 | D61: =C61/C$105 -> 0 | E61: =E60+D61 -> 1.0120812 | F61: =IF(AND(E61<=0),"C",IF(E61<=0.8,"A",IF(E61<=0.95,"B","C"))) -> C | G61: =VLOOKUP(B$4:B$104,I$4:M$104,5,0) -> C | I61: sports красные | J61: ='Юнит 11'!U22 -> 0 | K61: =J61/J$105 -> 0 | L61: =L60+K61 -> 0.99649123 | M61: =_xlfn.IFS(L61<80%,"A",L61<=95%,"B",L61>95%,"C") -> C
B62: MANNA2106 | C62: ='Юнит 11'!AO59 -> 0 | D62: =C62/C$105 -> 0 | E62: =E61+D62 -> 1.0120812 | F62: =IF(AND(E62<=0),"C",IF(E62<=0.8,"A",IF(E62<=0.95,"B","C"))) -> C | G62: =VLOOKUP(B$4:B$104,I$4:M$104,5,0) -> C | I62: sportlife черные | J62: ='Юнит 11'!U23 -> 0 | K62: =J62/J$105 -> 0 | L62: =L61+K62 -> 0.99649123 | M62: =_xlfn.IFS(L62<80%,"A",L62<=95%,"B",L62>95%,"C") -> C
B63: MANNA2109 | C63: ='Юнит 11'!AO62 -> 0 | D63: =C63/C$105 -> 0 | E63: =E62+D63 -> 1.0120812 | F63: =IF(AND(E63<=0),"C",IF(E63<=0.8,"A",IF(E63<=0.95,"B","C"))) -> C | G63: =VLOOKUP(B$4:B$104,I$4:M$104,5,0) -> C | I63: sportlife синие | J63: ='Юнит 11'!U24 -> 0 | K63: =J63/J$105 -> 0 | L63: =L62+K63 -> 0.99649123 | M63: =_xlfn.IFS(L63<80%,"A",L63<=95%,"B",L63>95%,"C") -> C
B64: MANNA2110 | C64: ='Юнит 11'!AO63 -> 0 | D64: =C64/C$105 -> 0 | E64: =E63+D64 -> 1.0120812 | F64: =IF(AND(E64<=0),"C",IF(E64<=0.8,"A",IF(E64<=0.95,"B","C"))) -> C | G64: =VLOOKUP(B$4:B$104,I$4:M$104,5,0) -> C | I64: sportlife красные | J64: ='Юнит 11'!U25 -> 0 | K64: =J64/J$105 -> 0 | L64: =L63+K64 -> 0.99649123 | M64: =_xlfn.IFS(L64<80%,"A",L64<=95%,"B",L64>95%,"C") -> C
B65: MANNA2111 | C65: ='Юнит 11'!AO64 -> 0 | D65: =C65/C$105 -> 0 | E65: =E64+D65 -> 1.0120812 | F65: =IF(AND(E65<=0),"C",IF(E65<=0.8,"A",IF(E65<=0.95,"B","C"))) -> C | G65: =VLOOKUP(B$4:B$104,I$4:M$104,5,0) -> C | I65: sh4 | J65: ='Юнит 11'!U29 -> 0 | K65: =J65/J$105 -> 0 | L65: =L64+K65 -> 0.99649123 | M65: =_xlfn.IFS(L65<80%,"A",L65<=95%,"B",L65>95%,"C") -> C
B66: MANNA2114 | C66: ='Юнит 11'!AO67 -> 0 | D66: =C66/C$105 -> 0 | E66: =E65+D66 -> 1.0120812 | F66: =IF(AND(E66<=0),"C",IF(E66<=0.8,"A",IF(E66<=0.95,"B","C"))) -> C | G66: =VLOOKUP(B$4:B$104,I$4:M$104,5,0) -> C | I66: sh08 | J66: ='Юнит 11'!U32 -> 0 | K66: =J66/J$105 -> 0 | L66: =L65+K66 -> 0.99649123 | M66: =_xlfn.IFS(L66<80%,"A",L66<=95%,"B",L66>95%,"C") -> C
B67: MANNA2115 | C67: ='Юнит 11'!AO68 -> 0 | D67: =C67/C$105 -> 0 | E67: =E66+D67 -> 1.0120812 | F67: =IF(AND(E67<=0),"C",IF(E67<=0.8,"A",IF(E67<=0.95,"B","C"))) -> C | G67: =VLOOKUP(B$4:B$104,I$4:M$104,5,0) -> C | I67: sh10 | J67: ='Юнит 11'!U34 -> 0 | K67: =J67/J$105 -> 0 | L67: =L66+K67 -> 0.99649123 | M67: =_xlfn.IFS(L67<80%,"A",L67<=95%,"B",L67>95%,"C") -> C
B68: MANNA2121 | C68: ='Юнит 11'!AO74 -> 0 | D68: =C68/C$105 -> 0 | E68: =E67+D68 -> 1.0120812 | F68: =IF(AND(E68<=0),"C",IF(E68<=0.8,"A",IF(E68<=0.95,"B","C"))) -> C | G68: =VLOOKUP(B$4:B$104,I$4:M$104,5,0) -> C | I68: sh11 | J68: ='Юнит 11'!U35 -> 0 | K68: =J68/J$105 -> 0 | L68: =L67+K68 -> 0.99649123 | M68: =_xlfn.IFS(L68<80%,"A",L68<=95%,"B",L68>95%,"C") -> C
B69: MAIERSHA 03914 C9-124 | C69: ='Юнит 11'!AO95 -> 0 | D69: =C69/C$105 -> 0 | E69: =E68+D69 -> 1.0120812 | F69: =IF(AND(E69<=0),"C",IF(E69<=0.8,"A",IF(E69<=0.95,"B","C"))) -> C | G69: =VLOOKUP(B$4:B$104,I$4:M$104,5,0) -> C | I69: sh12 | J69: ='Юнит 11'!U36 -> 0 | K69: =J69/J$105 -> 0 | L69: =L68+K69 -> 0.99649123 | M69: =_xlfn.IFS(L69<80%,"A",L69<=95%,"B",L69>95%,"C") -> C
B70: MARSTON 7171 C1 | C70: ='Юнит 11'!AO96 -> 0 | D70: =C70/C$105 -> 0 | E70: =E69+D70 -> 1.0120812 | F70: =IF(AND(E70<=0),"C",IF(E70<=0.8,"A",IF(E70<=0.95,"B","C"))) -> C | G70: =VLOOKUP(B$4:B$104,I$4:M$104,5,0) -> C | I70: sh13 | J70: ='Юнит 11'!U37 -> 0 | K70: =J70/J$105 -> 0 | L70: =L69+K70 -> 0.99649123 | M70: =_xlfn.IFS(L70<80%,"A",L70<=95%,"B",L70>95%,"C") -> C
B71: ЧСЖ_тест | C71: ='Юнит 11'!AO99 -> 0 | D71: =C71/C$105 -> 0 | E71: =E70+D71 -> 1.0120812 | F71: =IF(AND(E71<=0),"C",IF(E71<=0.8,"A",IF(E71<=0.95,"B","C"))) -> C | G71: =VLOOKUP(B$4:B$104,I$4:M$104,5,0) -> C | I71: sh14 | J71: ='Юнит 11'!U38 -> 0 | K71: =J71/J$105 -> 0 | L71: =L70+K71 -> 0.99649123 | M71: =_xlfn.IFS(L71<80%,"A",L71<=95%,"B",L71>95%,"C") -> C
B72: кс_черные_тест | C72: ='Юнит 11'!AO101 -> 0 | D72: =C72/C$105 -> 0 | E72: =E71+D72 -> 1.0120812 | F72: =IF(AND(E72<=0),"C",IF(E72<=0.8,"A",IF(E72<=0.95,"B","C"))) -> C | G72: =VLOOKUP(B$4:B$104,I$4:M$104,5,0) -> C | I72: sh17 | J72: ='Юнит 11'!U41 -> 0 | K72: =J72/J$105 -> 0 | L72: =L71+K72 -> 0.99649123 | M72: =_xlfn.IFS(L72<80%,"A",L72<=95%,"B",L72>95%,"C") -> C
B73: 1022_коричневые_тест | C73: ='Юнит 11'!AO103 -> 0 | D73: =C73/C$105 -> 0 | E73: =E72+D73 -> 1.0120812 | F73: =IF(AND(E73<=0),"C",IF(E73<=0.8,"A",IF(E73<=0.95,"B","C"))) -> C | G73: =VLOOKUP(B$4:B$104,I$4:M$104,5,0) -> C | I73: ww 1022 черн-серебро | J73: ='Юнит 11'!U46 -> 0 | K73: =J73/J$105 -> 0 | L73: =L72+K73 -> 0.99649123 | M73: =_xlfn.IFS(L73<80%,"A",L73<=95%,"B",L73>95%,"C") -> C
B74: MANNA2112 | C74: ='Юнит 11'!AO65 -> -1.3306578 | D74: =C74/C$105 -> -9.9958781e-07 | E74: =E73+D74 -> 1.0120802 | F74: =IF(AND(E74<=0),"C",IF(E74<=0.8,"A",IF(E74<=0.95,"B","C"))) -> C | G74: =VLOOKUP(B$4:B$104,I$4:M$104,5,0) -> C | I74: WW 3055 черный | J74: ='Юнит 11'!U52 -> 0 | K74: =J74/J$105 -> 0 | L74: =L73+K74 -> 0.99649123 | M74: =_xlfn.IFS(L74<80%,"A",L74<=95%,"B",L74>95%,"C") -> C
B75: MANNA2113 | C75: ='Юнит 11'!AO66 -> -2.6613156 | D75: =C75/C$105 -> -1.9991756e-06 | E75: =E74+D75 -> 1.0120782 | F75: =IF(AND(E75<=0),"C",IF(E75<=0.8,"A",IF(E75<=0.95,"B","C"))) -> C | G75: =VLOOKUP(B$4:B$104,I$4:M$104,5,0) -> C | I75: WW 3055 коричневый | J75: ='Юнит 11'!U53 -> 0 | K75: =J75/J$105 -> 0 | L75: =L74+K75 -> 0.99649123 | M75: =_xlfn.IFS(L75<80%,"A",L75<=95%,"B",L75>95%,"C") -> C
B76: MANNA2101 | C76: ='Юнит 11'!AO54 -> -17.853993 | D76: =C76/C$105 -> -1.3411888e-05 | E76: =E49+D76 -> 1.0120678 | F76: =IF(AND(E76<=0),"C",IF(E76<=0.8,"A",IF(E76<=0.95,"B","C"))) -> C | G76: =VLOOKUP(B$4:B$104,I$4:M$104,5,0) -> C | I76: MANNA2102 | J76: ='Юнит 11'!U55 -> 0 | K76: =J76/J$105 -> 0 | L76: =L49+K76 -> 0.99415205 | M76: =_xlfn.IFS(L76<80%,"A",L76<=95%,"B",L76>95%,"C") -> C
B77: Qianai коричневые | C77: ='Юнит 11'!AO84 -> -62.540918 | D77: =C77/C$105 -> -4.6980627e-05 | E77: =E76+D77 -> 1.0120208 | F77: =IF(AND(E77<=0),"C",IF(E77<=0.8,"A",IF(E77<=0.95,"B","C"))) -> C | G77: =VLOOKUP(B$4:B$104,I$4:M$104,5,0) -> C | I77: MANNA2103 | J77: ='Юнит 11'!U56 -> 0 | K77: =J77/J$105 -> 0 | L77: =L76+K77 -> 0.99415205 | M77: =_xlfn.IFS(L77<80%,"A",L77<=95%,"B",L77>95%,"C") -> C
B78: Ли Сян ретро золото | C78: ='Юнит 11'!AO92 -> -65.202233 | D78: =C78/C$105 -> -4.8979803e-05 | E78: =E77+D78 -> 1.0119718 | F78: =IF(AND(E78<=0),"C",IF(E78<=0.8,"A",IF(E78<=0.95,"B","C"))) -> C | G78: =VLOOKUP(B$4:B$104,I$4:M$104,5,0) -> C | I78: MANNA2104 | J78: ='Юнит 11'!U57 -> 0 | K78: =J78/J$105 -> 0 | L78: =L77+K78 -> 0.99415205 | M78: =_xlfn.IFS(L78<80%,"A",L78<=95%,"B",L78>95%,"C") -> C
B79: Taizhou Rayen sport розовый | C79: ='Юнит 11'!AO90 -> -66.532891 | D79: =C79/C$105 -> -4.9979391e-05 | E79: =E78+D79 -> 1.0119219 | F79: =IF(AND(E79<=0),"C",IF(E79<=0.8,"A",IF(E79<=0.95,"B","C"))) -> C | G79: =VLOOKUP(B$4:B$104,I$4:M$104,5,0) -> C | I79: MANNA2106 | J79: ='Юнит 11'!U59 -> 0 | K79: =J79/J$105 -> 0 | L79: =L78+K79 -> 0.99415205 | M79: =_xlfn.IFS(L79<80%,"A",L79<=95%,"B",L79>95%,"C") -> C
B80: MANNA2120 | C80: ='Юнит 11'!AO73 -> -113.12863 | D80: =C80/C$105 -> -8.4982026e-05 | E80: =E79+D80 -> 1.0118369 | F80: =IF(AND(E80<=0),"C",IF(E80<=0.8,"A",IF(E80<=0.95,"B","C"))) -> C | G80: =VLOOKUP(B$4:B$104,I$4:M$104,5,0) -> C | I80: MANNA2108 | J80: ='Юнит 11'!U61 -> 0 | K80: =J80/J$105 -> 0 | L80: =L79+K80 -> 0.99415205 | M80: =_xlfn.IFS(L80<80%,"A",L80<=95%,"B",L80>95%,"C") -> C
B81: YIMEI 2391 C1 | C81: ='Юнит 11'!AO98 -> -113.28789 | D81: =C81/C$105 -> -8.5101666e-05 | E81: =E80+D81 -> 1.0117518 | F81: =IF(AND(E81<=0),"C",IF(E81<=0.8,"A",IF(E81<=0.95,"B","C"))) -> C | G81: =VLOOKUP(B$4:B$104,I$4:M$104,5,0) -> C | I81: MANNA2109 | J81: ='Юнит 11'!U62 -> 0 | K81: =J81/J$105 -> 0 | L81: =L80+K81 -> 0.99415205 | M81: =_xlfn.IFS(L81<80%,"A",L81<=95%,"B",L81>95%,"C") -> C
B82: MANNA2118 | C82: ='Юнит 11'!AO71 -> -126.6803 | D82: =C82/C$105 -> -9.5162018e-05 | E82: =E81+D82 -> 1.0116566 | F82: =IF(AND(E82<=0),"C",IF(E82<=0.8,"A",IF(E82<=0.95,"B","C"))) -> C | G82: =VLOOKUP(B$4:B$104,I$4:M$104,5,0) -> C | I82: MANNA2110 | J82: ='Юнит 11'!U63 -> 0 | K82: =J82/J$105 -> 0 | L82: =L81+K82 -> 0.99415205 | M82: =_xlfn.IFS(L82<80%,"A",L82<=95%,"B",L82>95%,"C") -> C
B83: sh10 | C83: ='Юнит 11'!AO34 -> -129 | D83: =C83/C$105 -> -9.6904573e-05 | E83: =E82+D83 -> 1.0115597 | F83: =IF(AND(E83<=0),"C",IF(E83<=0.8,"A",IF(E83<=0.95,"B","C"))) -> C | G83: =VLOOKUP(B$4:B$104,I$4:M$104,5,0) -> C | I83: MANNA2111 | J83: ='Юнит 11'!U64 -> 0 | K83: =J83/J$105 -> 0 | L83: =L82+K83 -> 0.99415205 | M83: =_xlfn.IFS(L83<80%,"A",L83<=95%,"B",L83>95%,"C") -> C
B84: sh17 | C84: ='Юнит 11'!AO41 -> -150.25763 | D84: =C84/C$105 -> -0.00011287327 | E84: =E83+D84 -> 1.0114468 | F84: =IF(AND(E84<=0),"C",IF(E84<=0.8,"A",IF(E84<=0.95,"B","C"))) -> C | G84: =VLOOKUP(B$4:B$104,I$4:M$104,5,0) -> C | I84: MANNA2112 | J84: ='Юнит 11'!U65 -> 0 | K84: =J84/J$105 -> 0 | L84: =L83+K84 -> 0.99415205 | M84: =_xlfn.IFS(L84<80%,"A",L84<=95%,"B",L84>95%,"C") -> C
B85: Hengda Optical леопард | C85: ='Юнит 11'!AO82 -> -158.53026 | D85: =C85/C$105 -> -0.00011908765 | E85: =E84+D85 -> 1.0113277 | F85: =IF(AND(E85<=0),"C",IF(E85<=0.8,"A",IF(E85<=0.95,"B","C"))) -> C | G85: =VLOOKUP(B$4:B$104,I$4:M$104,5,0) -> C | I85: MANNA2113 | J85: ='Юнит 11'!U66 -> 0 | K85: =J85/J$105 -> 0 | L85: =L84+K85 -> 0.99415205 | M85: =_xlfn.IFS(L85<80%,"A",L85<=95%,"B",L85>95%,"C") -> C
B86: Qianai черные | C86: ='Юнит 11'!AO83 -> -165.04763 | D86: =C86/C$105 -> -0.00012398349 | E86: =E85+D86 -> 1.0112038 | F86: =IF(AND(E86<=0),"C",IF(E86<=0.8,"A",IF(E86<=0.95,"B","C"))) -> C | G86: =VLOOKUP(B$4:B$104,I$4:M$104,5,0) -> C | I86: MANNA2114 | J86: ='Юнит 11'!U67 -> 0 | K86: =J86/J$105 -> 0 | L86: =L85+K86 -> 0.99415205 | M86: =_xlfn.IFS(L86<80%,"A",L86<=95%,"B",L86>95%,"C") -> C
B87: POMILED 08247 C4-08 | C87: ='Юнит 11'!AO97 -> -193.02066 | D87: =C87/C$105 -> -0.00014499678 | E87: =E86+D87 -> 1.0110588 | F87: =IF(AND(E87<=0),"C",IF(E87<=0.8,"A",IF(E87<=0.95,"B","C"))) -> C | G87: =VLOOKUP(B$4:B$104,I$4:M$104,5,0) -> C | I87: MANNA2115 | J87: ='Юнит 11'!U68 -> 0 | K87: =J87/J$105 -> 0 | L87: =L86+K87 -> 0.99415205 | M87: =_xlfn.IFS(L87<80%,"A",L87<=95%,"B",L87>95%,"C") -> C
B88: sh13 | C88: ='Юнит 11'!AO37 -> -209.43 | D88: =C88/C$105 -> -0.00015732345 | E88: =E87+D88 -> 1.0109014 | F88: =IF(AND(E88<=0),"C",IF(E88<=0.8,"A",IF(E88<=0.95,"B","C"))) -> C | G88: =VLOOKUP(B$4:B$104,I$4:M$104,5,0) -> C | I88: MANNA2117 | J88: ='Юнит 11'!U70 -> 0 | K88: =J88/J$105 -> 0 | L88: =L87+K88 -> 0.99415205 | M88: =_xlfn.IFS(L88<80%,"A",L88<=95%,"B",L88>95%,"C") -> C
B89: Hengda Optical черные | C89: ='Юнит 11'!AO81 -> -236.44141 | D89: =C89/C$105 -> -0.00017761437 | E89: =E88+D89 -> 1.0107238 | F89: =IF(AND(E89<=0),"C",IF(E89<=0.8,"A",IF(E89<=0.95,"B","C"))) -> C | G89: =VLOOKUP(B$4:B$104,I$4:M$104,5,0) -> C | I89: MANNA2121 | J89: ='Юнит 11'!U74 -> 0 | K89: =J89/J$105 -> 0 | L89: =L88+K89 -> 0.99415205 | M89: =_xlfn.IFS(L89<80%,"A",L89<=95%,"B",L89>95%,"C") -> C
B90: Chenlong коричневые | C90: ='Юнит 11'!AO77 -> -254.38368 | D90: =C90/C$105 -> -0.00019109257 | E90: =E89+D90 -> 1.0105327 | F90: =IF(AND(E90<=0),"C",IF(E90<=0.8,"A",IF(E90<=0.95,"B","C"))) -> C | G90: =VLOOKUP(B$4:B$104,I$4:M$104,5,0) -> C | I90: Chenlong коричневые | J90: ='Юнит 11'!U77 -> 0 | K90: =J90/J$105 -> 0 | L90: =L89+K90 -> 0.99415205 | M90: =_xlfn.IFS(L90<80%,"A",L90<=95%,"B",L90>95%,"C") -> C
B91: WW 3055 коричневый | C91: ='Юнит 11'!AO53 -> -259.41763 | D91: =C91/C$105 -> -0.00019487407 | E91: =E90+D91 -> 1.0103379 | F91: =IF(AND(E91<=0),"C",IF(E91<=0.8,"A",IF(E91<=0.95,"B","C"))) -> C | G91: =VLOOKUP(B$4:B$104,I$4:M$104,5,0) -> C | I91: Guangdu золото серая линза | J91: ='Юнит 11'!U79 -> 0 | K91: =J91/J$105 -> 0 | L91: =L90+K91 -> 0.99415205 | M91: =_xlfn.IFS(L91<80%,"A",L91<=95%,"B",L91>95%,"C") -> C
B92: Guangdu золото серая линза | C92: ='Юнит 11'!AO79 -> -269.02092 | D92: =C92/C$105 -> -0.00020208804 | E92: =E91+D92 -> 1.0101358 | F92: =IF(AND(E92<=0),"C",IF(E92<=0.8,"A",IF(E92<=0.95,"B","C"))) -> C | G92: =VLOOKUP(B$4:B$104,I$4:M$104,5,0) -> C | I92: Hengda Optical леопард | J92: ='Юнит 11'!U82 -> 0 | K92: =J92/J$105 -> 0 | L92: =L91+K92 -> 0.99415205 | M92: =_xlfn.IFS(L92<80%,"A",L92<=95%,"B",L92>95%,"C") -> C
B93: MANNA2108 | C93: ='Юнит 11'!AO61 -> -308.60591 | D93: =C93/C$105 -> -0.00023182422 | E93: =E92+D93 -> 1.0099039 | F93: =IF(AND(E93<=0),"C",IF(E93<=0.8,"A",IF(E93<=0.95,"B","C"))) -> C | G93: =VLOOKUP(B$4:B$104,I$4:M$104,5,0) -> C | I93: Qianai черные | J93: ='Юнит 11'!U83 -> 0 | K93: =J93/J$105 -> 0 | L93: =L92+K93 -> 0.99415205 | M93: =_xlfn.IFS(L93<80%,"A",L93<=95%,"B",L93>95%,"C") -> C
B94: sh2 | C94: ='Юнит 11'!AO27 -> -372.33783 | D94: =C94/C$105 -> -0.00027969952 | E94: =E93+D94 -> 1.0096242 | F94: =IF(AND(E94<=0),"C",IF(E94<=0.8,"A",IF(E94<=0.95,"B","C"))) -> C | G94: =VLOOKUP(B$4:B$104,I$4:M$104,5,0) -> C | I94: Qianai коричневые | J94: ='Юнит 11'!U84 -> 0 | K94: =J94/J$105 -> 0 | L94: =L93+K94 -> 0.99415205 | M94: =_xlfn.IFS(L94<80%,"A",L94<=95%,"B",L94>95%,"C") -> C
B95: sh14 | C95: ='Юнит 11'!AO38 -> -463.83368 | D95: =C95/C$105 -> -0.00034843104 | E95: =E94+D95 -> 1.0092758 | F95: =IF(AND(E95<=0),"C",IF(E95<=0.8,"A",IF(E95<=0.95,"B","C"))) -> C | G95: =VLOOKUP(B$4:B$104,I$4:M$104,5,0) -> C | I95: Taizhou Rayen sport розовый | J95: ='Юнит 11'!U90 -> 0 | K95: =J95/J$105 -> 0 | L95: =L94+K95 -> 0.99415205 | M95: =_xlfn.IFS(L95<80%,"A",L95<=95%,"B",L95>95%,"C") -> C
B96: MANNA2117 | C96: ='Юнит 11'!AO70 -> -490.75132 | D96: =C96/C$105 -> -0.00036865152 | E96: =E95+D96 -> 1.0089072 | F96: =IF(AND(E96<=0),"C",IF(E96<=0.8,"A",IF(E96<=0.95,"B","C"))) -> C | G96: =VLOOKUP(B$4:B$104,I$4:M$104,5,0) -> C | I96: Иу Диту серый | J96: ='Юнит 11'!U91 -> 0 | K96: =J96/J$105 -> 0 | L96: =L95+K96 -> 0.99415205 | M96: =_xlfn.IFS(L96<80%,"A",L96<=95%,"B",L96>95%,"C") -> C
B97: sh09 | C97: ='Юнит 11'!AO33 -> -569.01579 | D97: =C97/C$105 -> -0.00042744366 | E97: =E96+D97 -> 1.0084797 | F97: =IF(AND(E97<=0),"C",IF(E97<=0.8,"A",IF(E97<=0.95,"B","C"))) -> C | G97: =VLOOKUP(B$4:B$104,I$4:M$104,5,0) -> C | I97: Ли Сян ретро золото | J97: ='Юнит 11'!U92 -> 0 | K97: =J97/J$105 -> 0 | L97: =L96+K97 -> 0.99415205 | M97: =_xlfn.IFS(L97<80%,"A",L97<=95%,"B",L97>95%,"C") -> C
B98: Guangdu серебро серая линза | C98: ='Юнит 11'!AO80 -> -1210.0744 | D98: =C98/C$105 -> -0.00090900578 | E98: =E97+D98 -> 1.0075707 | F98: =IF(AND(E98<=0),"C",IF(E98<=0.8,"A",IF(E98<=0.95,"B","C"))) -> C | G98: =VLOOKUP(B$4:B$104,I$4:M$104,5,0) -> C | I98: MAIERSHA 03914 C9-124 | J98: ='Юнит 11'!U95 -> 0 | K98: =J98/J$105 -> 0 | L98: =L97+K98 -> 0.99415205 | M98: =_xlfn.IFS(L98<80%,"A",L98<=95%,"B",L98>95%,"C") -> C
B99: Иу Диту серый | C99: ='Юнит 11'!AO91 -> -1504.6518 | D99: =C99/C$105 -> -0.0011302918 | E99: =E93+D99 -> 1.0087737 | F99: =IF(AND(E99<=0),"C",IF(E99<=0.8,"A",IF(E99<=0.95,"B","C"))) -> C | G99: =VLOOKUP(B$4:B$104,I$4:M$104,5,0) -> C | I99: MARSTON 7171 C1 | J99: ='Юнит 11'!U96 -> 0 | K99: =J99/J$105 -> 0 | L99: =L93+K99 -> 0.99415205 | M99: =_xlfn.IFS(L99<80%,"A",L99<=95%,"B",L99>95%,"C") -> C
B100: Linhai Baiyi серая линза | C100: ='Юнит 11'!AO87 -> -1583.8159 | D100: =C100/C$105 -> -0.0011897597 | E100: =E94+D100 -> 1.0084345 | F100: =IF(AND(E100<=0),"C",IF(E100<=0.8,"A",IF(E100<=0.95,"B","C"))) -> C | G100: =VLOOKUP(B$4:B$104,I$4:M$104,5,0) -> C | I100: POMILED 08247 C4-08 | J100: ='Юнит 11'!U97 -> 0 | K100: =J100/J$105 -> 0 | L100: =L94+K100 -> 0.99415205 | M100: =_xlfn.IFS(L100<80%,"A",L100<=95%,"B",L100>95%,"C") -> C
B101: Chenlong белые | C101: ='Юнит 11'!AO78 -> -1634.8335 | D101: =C101/C$105 -> -0.0012280841 | E101: =E95+D101 -> 1.0080477 | F101: =IF(AND(E101<=0),"C",IF(E101<=0.8,"A",IF(E101<=0.95,"B","C"))) -> C | G101: =VLOOKUP(B$4:B$104,I$4:M$104,5,0) -> C | I101: YIMEI 2391 C1 | J101: ='Юнит 11'!U98 -> 0 | K101: =J101/J$105 -> 0 | L101: =L95+K101 -> 0.99415205 | M101: =_xlfn.IFS(L101<80%,"A",L101<=95%,"B",L101>95%,"C") -> C
...

Sheet АВС 10
B2: ОЧКИ
C3: Прибыль | D3: % прибыль | E3: Доля | F3: ABC прибыль | G3: ABC кол-во | J3: Кол-во | K3: % кол-во | L3: Доля | M3: ABC кол-во
B4: QS черные PZ | C4: ='Юнит 10'!AO4 -> 180713.27 | D4: =C4/C$105 -> 0.27381245 | E4: =D4 -> 0.27381245 | F4: =IF(AND(E4<=0),"C",IF(E4<=0.8,"A",IF(E4<=0.95,"B","C"))) -> A | G4: =VLOOKUP(B$4:B$104,I$4:M$104,5,0) -> A | I4: QS черные PZ | J4: ='Юнит 10'!U4 -> 427 | K4: =J4/J$105 -> 0.20900636 | L4: =K4 -> 0.20900636 | M4: =_xlfn.IFS(L4<80%,"A",L4<=95%,"B",L4>95%,"C") -> A | P4: A | Q4: 0.8
B5: QS синие PZ | C5: ='Юнит 10'!AO5 -> 59221.135 | D5: =C5/C$105 -> 0.089730454 | E5: =E4+D5 -> 0.3635429 | F5: =IF(AND(E5<=0),"C",IF(E5<=0.8,"A",IF(E5<=0.95,"B","C"))) -> A | G5: =VLOOKUP(B$4:B$104,I$4:M$104,5,0) -> A | I5: QS синие PZ | J5: ='Юнит 10'!U5 -> 143 | K5: =J5/J$105 -> 0.069995105 | L5: =L4+K5 -> 0.27900147 | M5: =_xlfn.IFS(L5<80%,"A",L5<=95%,"B",L5>95%,"C") -> A | P5: B | Q5: 0.15
B6: QS коричневые PZ | C6: ='Юнит 10'!AO7 -> 56821.8 | D6: =C6/C$105 -> 0.086095038 | E6: =E5+D6 -> 0.44963794 | F6: =IF(AND(E6<=0),"C",IF(E6<=0.8,"A",IF(E6<=0.95,"B","C"))) -> A | G6: =VLOOKUP(B$4:B$104,I$4:M$104,5,0) -> A | I6: QS коричневые PZ | J6: ='Юнит 10'!U7 -> 139 | K6: =J6/J$105 -> 0.0680372 | L6: =L5+K6 -> 0.34703867 | M6: =_xlfn.IFS(L6<80%,"A",L6<=95%,"B",L6>95%,"C") -> A | P6: C | Q6: 0.05
B7: flip черные | C7: ='Юнит 10'!AO13 -> 48751.577 | D7: =C7/C$105 -> 0.073867228 | E7: =E6+D7 -> 0.52350516 | F7: =IF(AND(E7<=0),"C",IF(E7<=0.8,"A",IF(E7<=0.95,"B","C"))) -> A | G7: =VLOOKUP(B$4:B$104,I$4:M$104,5,0) -> A | I7: flip черные | J7: ='Юнит 10'!U13 -> 132 | K7: =J7/J$105 -> 0.064610866 | L7: =L6+K7 -> 0.41164953 | M7: =_xlfn.IFS(L7<80%,"A",L7<=95%,"B",L7>95%,"C") -> A
B8: th черн | C8: ='Юнит 10'!AO9 -> 38157.585 | D8: =C8/C$105 -> 0.057815464 | E8: =E7+D8 -> 0.58132063 | F8: =IF(AND(E8<=0),"C",IF(E8<=0.8,"A",IF(E8<=0.95,"B","C"))) -> A | G8: =VLOOKUP(B$4:B$104,I$4:M$104,5,0) -> A | I8: sh3 | J8: ='Юнит 10'!U28 -> 112 | K8: =J8/J$105 -> 0.054821341 | L8: =L7+K8 -> 0.46647088 | M8: =_xlfn.IFS(L8<80%,"A",L8<=95%,"B",L8>95%,"C") -> A
B9: flip коричневые | C9: ='Юнит 10'!AO16 -> 36602.996 | D9: =C9/C$105 -> 0.055459987 | E9: =E8+D9 -> 0.63678062 | F9: =IF(AND(E9<=0),"C",IF(E9<=0.8,"A",IF(E9<=0.95,"B","C"))) -> A | G9: =VLOOKUP(B$4:B$104,I$4:M$104,5,0) -> A | I9: th син | J9: ='Юнит 10'!U10 -> 111 | K9: =J9/J$105 -> 0.054331865 | L9: =L8+K9 -> 0.52080274 | M9: =_xlfn.IFS(L9<80%,"A",L9<=95%,"B",L9>95%,"C") -> A
B10: QS желтые PZ | C10: ='Юнит 10'!AO6 -> 35164.892 | D10: =C10/C$105 -> 0.053281007 | E10: =E9+D10 -> 0.69006162 | F10: =IF(AND(E10<=0),"C",IF(E10<=0.8,"A",IF(E10<=0.95,"B","C"))) -> A | G10: =VLOOKUP(B$4:B$104,I$4:M$104,5,0) -> A | I10: flip коричневые | J10: ='Юнит 10'!U16 -> 111 | K10: =J10/J$105 -> 0.054331865 | L10: =L9+K10 -> 0.57513461 | M10: =_xlfn.IFS(L10<80%,"A",L10<=95%,"B",L10>95%,"C") -> A
B11: черные с железкой классика | C11: ='Юнит 10'!AO3 -> 34966.219 | D11: =C11/C$105 -> 0.052979982 | E11: =E10+D11 -> 0.74304161 | F11: =IF(AND(E11<=0),"C",IF(E11<=0.8,"A",IF(E11<=0.95,"B","C"))) -> A | G11: =VLOOKUP(B$4:B$104,I$4:M$104,5,0) -> A | I11: th черн | J11: ='Юнит 10'!U9 -> 107 | K11: =J11/J$105 -> 0.05237396 | L11: =L10+K11 -> 0.62750857 | M11: =_xlfn.IFS(L11<80%,"A",L11<=95%,"B",L11>95%,"C") -> A
B12: sh3 | C12: ='Юнит 10'!AO28 -> 30976.089 | D12: =C12/C$105 -> 0.046934232 | E12: =E11+D12 -> 0.78997584 | F12: =IF(AND(E12<=0),"C",IF(E12<=0.8,"A",IF(E12<=0.95,"B","C"))) -> A | G12: =VLOOKUP(B$4:B$104,I$4:M$104,5,0) -> A | I12: QS желтые PZ | J12: ='Юнит 10'!U6 -> 105 | K12: =J12/J$105 -> 0.051395007 | L12: =L11+K12 -> 0.67890357 | M12: =_xlfn.IFS(L12<80%,"A",L12<=95%,"B",L12>95%,"C") -> A
B13: th желт | C13: ='Юнит 10'!AO11 -> 23552.911 | D13: =C13/C$105 -> 0.03568681 | E13: =E12+D13 -> 0.82566265 | F13: =IF(AND(E13<=0),"C",IF(E13<=0.8,"A",IF(E13<=0.95,"B","C"))) -> B | G13: =VLOOKUP(B$4:B$104,I$4:M$104,5,0) -> A | I13: черные с железкой классика | J13: ='Юнит 10'!U3 -> 101 | K13: =J13/J$105 -> 0.049437102 | L13: =L12+K13 -> 0.72834068 | M13: =_xlfn.IFS(L13<80%,"A",L13<=95%,"B",L13>95%,"C") -> A
B14: th син | C14: ='Юнит 10'!AO10 -> 22578.741 | D14: =C14/C$105 -> 0.03421077 | E14: =E13+D14 -> 0.85987342 | F14: =IF(AND(E14<=0),"C",IF(E14<=0.8,"A",IF(E14<=0.95,"B","C"))) -> B | G14: =VLOOKUP(B$4:B$104,I$4:M$104,5,0) -> A | I14: th желт | J14: ='Юнит 10'!U11 -> 62 | K14: =J14/J$105 -> 0.030347528 | L14: =L13+K14 -> 0.7586882 | M14: =_xlfn.IFS(L14<80%,"A",L14<=95%,"B",L14>95%,"C") -> A
