Workbook

Sheet Реклама
B2: БАЛАНС | E2: СЧЕТ | H2: ПРОМОБОНУСЫ | K2: Неделя
B3: Номер документа | C3: Сумма | D3: Даты | E3: Номер документа | F3: Сумма | G3: Даты | H3: Номер документа | I3: Сумма | J3: Даты
B4: 277433850 | C4: 1376 | D4: 28-31.12 | E4: 277433847 | F4: 25829 | G4: 28-31.12 | H4: 0 | I4: 109 | J4: 29-31.12 | K4: 1
B5: 277539131 | C5: 1150 | D5: 36951 | E5: 277609313 | F5: 21489 | G5: 36982 | H5: 0 | I5: 363 | J5: 36982
B6: 279208603 | C6: 3455 | D6: 37168 | E6: 279208599 | F6: 51313 | G6: 37199 | H6: 0 | I6: 569 | J6: 37200 | K6: 2
B7: 280269091 | C7: 10268 | D7: 11-18.01 | E7: 280221209 | F7: 99763 | G7: 11-18.01 | H7: 0 | I7: 557 | J7: 12-18.01 | K7: 3
B8: 281267335 | C8: 70408 | D8: 19-25.01 | E8: 281348313 | F8: 67741 | G8: 18-25.01 | H8: 0 | I8: 195 | J8: 19-25.01 | K8: 4
B9: 282258474 | C9: 25521 | D9: 25-31.01 | E9: 282345086 | F9: 133680 | G9: 25-31.01 | H9: 0 | I9: 80 | J9: 26-31.01 | K9: 5
B10: 282365257 | C10: 1268 | D10: 46054 | E10: 282392960 | F10: 4672 | G10: 46054
B11: 283332206 | C11: 111419 | D11: 37469 | E11: 283415801 | F11: 126688 | G11: 37469 | H11: 0 | I11: 3554 | J11: 37440 | K11: 6
B12: 284423647 | C12: 145581 | D12: 08-15.02 | E12: 284416459 | F12: 138670 | G12: 08-15.02 | H12: 0 | I12: 44 | J12: 46063 | K12: 7
B13: 285348588 | C13: 50989 | D13: 15-22.02 | E13: 285348587 | F13: 265182 | G13: 15-22.02 | K13: 8
B14: 286343097 | C14: 232417 | D14: 22-28.02 | E14: 286343091 | F14: 72806 | G14: 22-28.02 | H14: 0 | I14: 26 | J14: 46081 | K14: 9
B15: 286459024 | C15: 1243 | D15: 46082 | E15: 286489905 | F15: 5815 | G15: 46082
B16: 287708507 | C16: 74484 | D16: 01.03-08.03 | E16: 287655729 | F16: 252853 | G16: 01.03-08.03 | K16: 10
B17: 288763309 | C17: 304803 | D17: 08-15.03 | E17: 288777227 | F17: 178004 | G17: 08-15.03 | H17: 0 | I17: 46 | J17: 46091 | K17: 11
B18: 289700671 | C18: 48225 | D18: 15-22.03 | E18: 289749174 | F18: 468432 | G18: 15-22.03 | K18: 12
B19: 290703200 | C19: 88346 | D19: 22-29.03 | E19: 290753220 | F19: 464760 | G19: 22-29.03 | K19: 13
B20: 291680098 | C20: 7470 | D20: 29-31.03 | E20: 291680097 | F20: 197884 | G20: 29-31.03 | K20: 14
B21: 291826234 | C21: 2212 | D21: 1.04-05.04 | E21: 291909845 | F21: 303004 | G21: 01.04-05.04
B22: 292843081 | C22: 2405 | D22: 05.04-10.04 | E22: 292896526 | F22: 301236 | G22: 05.10-12.04 | K22: 15
B23: 293929962 | C23: 43580 | D23: 12-19.04 | E23: 293877308 | F23: 287584 | G23: 12-19.04 | K23: 16
B24: 294860190 | C24: 6217 | D24: 19-26.04 | E24: 294949927 | F24: 172288 | G24: 19-26.04 | H24: 0 | I24: 215420 | J24: 22-26.04 | K24: 17
H39: .

Sheet Сводная_план
B2: Период | E2: Дата поступления дс | F2: Итого к перечислению на счет, руб | G2: шт. | J2: ВБ реализовал товар (выручка с СПП) | M2: Выручка до вычета комиссии ВБ | P2: Себестоимость продаж | Q2: Логистика WB | R2: Комиссия WB | S2: Хранение WB | T2: Платная приемка WB | U2: Штрафы WB | V2: Прочие удержания WB | W2: Реклама БАЛАНС | X2: Реклама СЧЕТ | Y2: Реклама ПРОМОБОНУСЫ | Z2: Блогеры | AA2: Стоимость участия в программе лояльности | AB2: Сумма удержанная за начисленные баллы программы лояльности | AC2: Налог | AD2: Прочие поступления WB | AE2: Прибыль до вычета налогов | AF2: Прибыль после вычета налогов | AG2: Итог месяц | AH2: % Cебестоимости | AI2: Маржинальность, % | AJ2: Рентабельность, % | AK2: Доля рекламы, %
B3: Месяц | C3: Даты | D3: Нед | G3: Заказы | H3: Продажи | I3: Возвраты | J3: Продажи | K3: Возвраты | L3: Общая | M3: Продажи | N3: Возвраты | O3: Общая
B4: Декабрь очки | C4: 29-31.12 | D4: 1 | F4: =IFERROR(O4-SUM(Q4:W4)+AD4,0) -> 0 | AG4: =SUM(AF4:AF5) -> 0 | AH4: =P4/O4 -> #DIV/0! | AI4: =AF4/P4 -> #DIV/0! | AJ4: =AF4/O4 -> #DIV/0! | AK4: =(W4+X4+Z4)/O4 -> #DIV/0!
B5: Декабрь туники | C5: 29-31.12 | D5: 1 | F5: =IFERROR(O5-SUM(Q5:W5)+AD5,0) -> 0 | AH5: =P5/O5 -> #DIV/0! | AI5: =AF5/P5 -> #DIV/0! | AJ5: =AF5/O5 -> #DIV/0! | AK5: =(W5+X5+Z5)/O5 -> #DIV/0!
B6: Январь очки | C6: 01.01-01.02 | D6: 1-5 | F6: =IFERROR(O6-SUM(Q6:W6)+AD6,0) -> 0 | AG6: =SUM(AF6:AF8) -> 0 | AH6: =P6/O6 -> #DIV/0! | AI6: =AF6/P6 -> #DIV/0! | AJ6: =AF6/O6 -> #DIV/0! | AK6: =(W6+X6+Z6)/O6 -> #DIV/0!
B7: Январь туники | C7: 01.01-01.02 | D7: 1-5 | F7: =IFERROR(O7-SUM(Q7:W7)+AD7,0) -> 0 | AH7: =P7/O7 -> #DIV/0! | AI7: =AF7/P7 -> #DIV/0! | AJ7: =AF7/O7 -> #DIV/0! | AK7: =(W7+X7+Z7)/O7 -> #DIV/0!
B8: Январь шапки | C8: 01.01-01.02 | D8: 1-5 | F8: =IFERROR(O8-SUM(Q8:W8)+AD8,0) -> 0 | AH8: =P8/O8 -> #DIV/0! | AI8: =AF8/P8 -> #DIV/0! | AJ8: =AF8/O8 -> #DIV/0! | AK8: =(W8+X8+Z8)/O8 -> #DIV/0!
B9: Февраль 1 очки | C9: 02-08.02 | D9: 6 | F9: =IFERROR(O9-SUM(Q9:W9)+AD9,0) -> 0 | AG9: =SUM(AF9:AF16) -> 0 | AH9: =P9/O9 -> #DIV/0! | AI9: =AF9/P9 -> #DIV/0! | AJ9: =AF9/O9 -> #DIV/0! | AK9: =(W9+X9+Z9)/O9 -> #DIV/0!
B10: Февраль 1 туники | C10: 02-08.02 | D10: 6 | F10: =IFERROR(O10-SUM(Q10:W10)+AD10,0) -> 0 | AH10: =P10/O10 -> #DIV/0! | AI10: =AF10/P10 -> #DIV/0! | AJ10: =AF10/O10 -> #DIV/0! | AK10: =(W10+X10+Z10)/O10 -> #DIV/0!
B11: Февраль 2 очки | C11: 09-15.02 | D11: 7 | F11: =IFERROR(O11-SUM(Q11:W11)+AD11,0) -> 0 | AH11: =P11/O11 -> #DIV/0! | AI11: =AF11/P11 -> #DIV/0! | AJ11: =AF11/O11 -> #DIV/0! | AK11: =(W11+X11+Z11)/O11 -> #DIV/0!
B12: Февраль 2 туники | C12: 09-15.02 | D12: 7 | F12: =IFERROR(O12-SUM(Q12:W12)+AD12,0) -> 0 | AH12: =P12/O12 -> #DIV/0! | AI12: =AF12/P12 -> #DIV/0! | AJ12: =AF12/O12 -> #DIV/0! | AK12: =(W12+X12+Z12)/O12 -> #DIV/0!
B13: Февраль 3 очки | C13: 16-22.02 | D13: 8 | F13: =IFERROR(O13-SUM(Q13:W13)+AD13,0) -> 0 | AH13: =P13/O13 -> #DIV/0! | AI13: =AF13/P13 -> #DIV/0! | AJ13: =AF13/O13 -> #DIV/0! | AK13: =(W13+X13+Z13)/O13 -> #DIV/0!
B14: Февраль 3 туники | C14: 16-22.02 | D14: 8 | F14: =IFERROR(O14-SUM(Q14:W14)+AD14,0) -> 0 | AH14: =P14/O14 -> #DIV/0! | AI14: =AF14/P14 -> #DIV/0! | AJ14: =AF14/O14 -> #DIV/0! | AK14: =(W14+X14+Z14)/O14 -> #DIV/0!
B15: Февраль 4 очки | C15: 23.02-01.03 | D15: 9 | F15: =IFERROR(O15-SUM(Q15:W15)+AD15,0) -> 0 | AH15: =P15/O15 -> #DIV/0! | AI15: =AF15/P15 -> #DIV/0! | AJ15: =AF15/O15 -> #DIV/0! | AK15: =(W15+X15+Z15)/O15 -> #DIV/0!
B16: Февраль 4 прочее | C16: 23.02-01.03 | D16: 9 | F16: =IFERROR(O16-SUM(Q16:W16)+AD16,0) -> 0 | AH16: =P16/O16 -> #DIV/0! | AI16: =AF16/P16 -> #DIV/0! | AJ16: =AF16/O16 -> #DIV/0! | AK16: =(W16+X16+Z16)/O16 -> #DIV/0!
B17: Март 1 очки | C17: 02-08.03 | D17: 10 | F17: =IFERROR(O17-SUM(Q17:W17)+AD17,0) -> 0 | AG17: =SUM(AF17:AF20) -> 0 | AH17: =P17/O17 -> #DIV/0! | AI17: =AF17/P17 -> #DIV/0! | AJ17: =AF17/O17 -> #DIV/0! | AK17: =(W17+X17+Z17)/O17 -> #DIV/0!
B18: Март 2 очки | C18: 09-15.03 | D18: 11 | F18: =IFERROR(O18-SUM(Q18:W18)+AD18,0) -> 0 | AH18: =P18/O18 -> #DIV/0! | AI18: =AF18/P18 -> #DIV/0! | AJ18: =AF18/O18 -> #DIV/0! | AK18: =(W18+X18+Z18)/O18 -> #DIV/0!
B19: Март 3 очки | C19: 16-22.03 | D19: 12 | F19: =IFERROR(O19-SUM(Q19:W19)+AD19,0) -> 0 | AH19: =P19/O19 -> #DIV/0! | AI19: =AF19/P19 -> #DIV/0! | AJ19: =AF19/O19 -> #DIV/0! | AK19: =(W19+X19+Z19)/O19 -> #DIV/0!
B20: Март 4 очки | C20: 23-29.03 | D20: 13 | F20: =IFERROR(O20-SUM(Q20:W20)+AD20,0) -> 0 | AH20: =P20/O20 -> #DIV/0! | AI20: =AF20/P20 -> #DIV/0! | AJ20: =AF20/O20 -> #DIV/0! | AK20: =(W20+X20+Z20)/O20 -> #DIV/0!
B21: Апрель 1 очки | C21: 30.03-05.04 | D21: 14 | F21: =IFERROR(O21-SUM(Q21:W21)-AA21-AB21+AD21,0) -> 2248396 | G21: ='Юнит 14'!N$125 -> 4971 | H21: ='Юнит 14'!S$125 -> 2810 | I21: ='Юнит 14'!T$125 -> -71 | J21: ='Юнит 14'!V$125 -> 2849625.8 | K21: ='Юнит 14'!W$125 -> -71864.03 | L21: =IFERROR(J21+K21,0) -> 2777761.8 | M21: ='Юнит 14'!Y$125 -> 4320373.6 | N21: ='Юнит 14'!Z$125 -> -108465.8 | O21: =IFERROR(M21+N21,0) -> 4211907.8 | P21: ='Юнит 14'!AD$125 -> 339512.76 | Q21: ='Юнит 14'!AG$125 -> 363484.23 | R21: ='Юнит 14'!AE$125 -> 1585688.2 | S21: ='Юнит 14'!AL$125 -> 6774.7746 | U21: ='Юнит 14'!AM$125 -> 950 | V21: 702.72 | W21: ='Юнит 14'!AH$125 -> 4494 | X21: ='Юнит 14'!AI$125 -> 455354 | Z21: ='Юнит 14'!AK$125 -> 0 | AA21: 128.9 | AB21: 1289 | AC21: ='Юнит 14'!AN$125 -> 158610.2 | AE21: =O21-SUM(P21:AB21)+AD21 -> 1453529.2 | AF21: =O21-SUM(P21:AC21)+AD21 -> 1294919 | AH21: =P21/O21 -> 0.080607833 | AI21: =AF21/P21 -> 3.8140511 | AJ21: =AF21/O21 -> 0.30744239 | AK21: =(W21+X21+Z21)/O21 -> 0.10917808
B22: Апрель 2 очки | C22: 06-12.04 | D22: 15 | F22: =IFERROR(O22-SUM(Q22:W22)-AA22-AB22+AD22,0) -> 1600934.5 | G22: ='Юнит 15'!N$125 -> 3297 | H22: ='Юнит 15'!S$125 -> 2059 | I22: ='Юнит 15'!T$125 -> -47 | J22: ='Юнит 15'!V$125 -> 2106763.1 | K22: ='Юнит 15'!W$125 -> -48891.37 | L22: =IFERROR(J22+K22,0) -> 2057871.7 | M22: ='Юнит 15'!Y$125 -> 3166314.9 | N22: ='Юнит 15'!Z$125 -> -74091.17 | O22: =IFERROR(M22+N22,0) -> 3092223.7 | P22: ='Юнит 15'!AD$125 -> 248851.65 | Q22: ='Юнит 15'!AG$125 -> 274874.64 | R22: ='Юнит 15'!AE$125 -> 1169082.7 | S22: ='Юнит 15'!AL$125 -> 7404.9464 | U22: ='Юнит 15'!AM$125 -> 4873.98 | V22: 22990 | W22: ='Юнит 15'!AH$125 -> 2405 | X22: ='Юнит 15'!AI$125 -> 289210 | Z22: ='Юнит 15'!AK$125 -> 0 | AA22: 878 | AB22: 8780 | AC22: ='Юнит 15'!AN$125 -> 117504.47 | AE22: =O22-SUM(P22:AB22)+AD22 -> 1062872.9 | AF22: =O22-SUM(P22:AC22)+AD22 -> 945368.38 | AH22: =P22/O22 -> 0.080476599 | AI22: =AF22/P22 -> 3.7989235 | AJ22: =AF22/O22 -> 0.30572444 | AK22: =(W22+X22+Z22)/O22 -> 0.094305918
B23: Апрель 3 очки | C23: 13-19.04 | D23: 16 | F23: =IFERROR(O23-SUM(Q23:W23)-AA23-AB23+AD23,0) -> 1437469 | G23: ='Юнит 16'!N$126 -> 3224 | H23: ='Юнит 16'!S$126 -> 1892 | I23: ='Юнит 16'!T$126 -> -41 | J23: ='Юнит 16'!V$126 -> 1903067.3 | K23: ='Юнит 16'!W$126 -> -40767.59 | L23: =IFERROR(J23+K23,0) -> 1862299.7 | M23: ='Юнит 16'!Y$126 -> 2844861.5 | N23: ='Юнит 16'!Z$126 -> -60944.33 | O23: =IFERROR(M23+N23,0) -> 2783917.2 | P23: ='Юнит 16'!AD$126 -> 228955.77 | Q23: ='Юнит 16'!AG$126 -> 234083.09 | R23: ='Юнит 16'!AE$126 -> 1050005.8 | S23: ='Юнит 16'!AL$126 -> 9009.0466 | U23: ='Юнит 16'!AM$126 -> 2269 | W23: ='Юнит 16'!AH$126 -> 41816 | X23: ='Юнит 16'!AI$126 -> 275395 | Z23: ='Юнит 16'!AK$126 -> 0 | AA23: 842.3 | AB23: 8423 | AC23: ='Юнит 16'!AN$126 -> 106337.31 | AE23: =O23-SUM(P23:AB23)+AD23 -> 933118.2 | AF23: =O23-SUM(P23:AC23)+AD23 -> 826780.89 | AH23: =P23/O23 -> 0.082242306 | AI23: =AF23/P23 -> 3.6110944 | AJ23: =AF23/O23 -> 0.29698473 | AK23: =(W23+X23+Z23)/O23 -> 0.11394412
B24: Апрель 4 очки | C24: 20-26.04 | D24: 17 | F24: =IFERROR(O24-SUM(Q24:W24)-AA24-AB24+AD24,0) -> 1205095.8 | G24: ='Юнит 17'!N$126 -> 2848 | H24: ='Юнит 17'!S$126 -> 1645 | I24: ='Юнит 17'!T$126 -> -32 | J24: ='Юнит 17'!V$126 -> 1612009.3 | K24: ='Юнит 17'!W$126 -> -33188 | L24: =IFERROR(J24+K24,0) -> 1578821.3 | M24: ='Юнит 17'!Y$126 -> 2353906.9 | N24: ='Юнит 17'!Z$126 -> -49562.13 | O24: =IFERROR(M24+N24,0) -> 2304344.8 | P24: ='Юнит 17'!AD$126 -> 199750.44 | Q24: ='Юнит 17'!AG$126 -> 210197.66 | R24: ='Юнит 17'!AE$126 -> 872396.09 | S24: ='Юнит 17'!AL$126 -> 8583.5482 | U24: ='Юнит 17'!AM$126 -> 1310 | W24: ='Юнит 17'!AH$126 -> 5159 | X24: ='Юнит 17'!AI$126 -> 163766 | Y24: ='Юнит 17'!AJ126 -> 212040 | Z24: ='Юнит 17'!AK$126 -> 0 | AA24: 145.7 | AB24: 1457 | AC24: ='Юнит 17'!AN$126 -> 90150.697 | AE24: =O24-SUM(P24:AB24)+AD24 -> 629539.36 | AF24: =O24-SUM(P24:AC24)+AD24 -> 539388.66 | AH24: =P24/O24 -> 0.086684267 | AI24: =AF24/P24 -> 2.7003128 | AJ24: =AF24/O24 -> 0.23407463 | AK24: =(W24+X24+Z24)/O24 -> 0.073307172
B29: Итого | F29: =SUM(F4:F28) -> 6491895.3 | G29: =SUM(G4:G28) -> 14340 | H29: =SUM(H4:H28) -> 8406 | I29: =SUM(I4:I28) -> -191 | J29: =SUM(J4:J28) -> 8471465.4 | K29: =SUM(K4:K28) -> -194710.99 | L29: =SUM(L4:L28) -> 8276754.5 | M29: =SUM(M4:M28) -> 12685457 | ... X29: =SUM(X4:X28) -> 1183725 | Z29: =SUM(Z4:Z28) -> 0 | AC29: =SUM(AC4:AC28) -> 472602.68 | AD29: =SUM(AD4:AD28) -> 0 | AE29: =SUM(AE4:AE28) -> 4079059.6 | AF29: =SUM(AF4:AF28) -> 3606457 | AG29: =SUM(AG4:AG28) -> 0 | AH29: =P29/O29 -> 0.082072169 | AI29: =AF29/P29 -> 3.5459258 | AJ29: =AF29/O29 -> 0.29102182 | AK29: =(W29+X29+Z29)/O29 -> 0.099867632
M30: % от выручки за весь период
N31: =-N29/M29 -> 0.023102316 | P31: =P29/$O$29 -> 0.082072169 | Q31: =Q29/$O$29 -> 0.087363238 | R31: =R29/$O$29 -> 0.37742287 | S31: =S29/$O$29 -> 0.0025638563 | T31: =T29/$O$29 -> 0 | U31: =U29/$O$29 -> 0.00075877029 | V31: =V29/$O$29 -> 0.001911876 | W31: =W29/$O$29 -> 0.0043473442 | X31: =X29/$O$29 -> 0.095520288 | Z31: =Z29/$O$29 -> 0 | AC31: =AC29/$O$29 -> 0.038136513 | AG31: =AF29/P29 -> 3.5459258 | AH31: Маржинальность, %
W32: =(W29+X29)/O29 -> 0.099867632 | AG32: =AF29/O29 -> 0.29102182 | AH32: Рентабельность, %
B35: 14 нед | W35: =W21/O21 -> 0.0010669749 | X35: =X21/O21 -> 0.1081111
B36: 15 нед | W36: =W22/O22 -> 0.00077775743 | X36: =X22/O22 -> 0.093528161
B37: 16 нед | W37: =W23/O23 -> 0.015020562 | X37: =X23/O23 -> 0.09892356
B38: 17 нед | W38: =W24/O24 -> 0.0022388143 | X38: =X24/O24 -> 0.071068357 | Y38: =Y24/O24 -> 0.092017479

Sheet Сводная
B2: Период | E2: Дата поступления дс | F2: Итого к перечислению на счет, руб | G2: шт. | J2: ВБ реализовал товар (выручка с СПП) | M2: Выручка до вычета комиссии ВБ | P2: Себестоимость продаж | Q2: Логистика WB | R2: Комиссия WB | S2: Хранение WB | T2: Платная приемка WB | U2: Штрафы WB | V2: Прочие удержания WB | W2: Реклама БАЛАНС | X2: Реклама СЧЕТ | Y2: Реклама ПРОМОБОНУСЫ | Z2: Блогеры | AA2: Стоимость участия в программе лояльности | AB2: Сумма удержанная за начисленные баллы программы лояльности | AC2: Налог | AD2: Прочие поступления WB | AE2: Прибыль до вычета налогов | AF2: Прибыль после вычета налогов | AG2: Итог месяц | AH2: % Cебестоимости | AI2: Маржинальность, % | AJ2: Рентабельность, % | AK2: Доля рекламы, %
B3: Месяц | C3: Даты | D3: Нед | G3: Заказы | H3: Продажи | I3: Возвраты | J3: Продажи | K3: Возвраты | L3: Общая | M3: Продажи | N3: Возвраты | O3: Общая
B4: Декабрь очки | C4: 29-31.12 | D4: 1 | F4: =IFERROR(O4-SUM(Q4:W4)+AD4,0) -> 62313.298 | G4: =ДЕКАБРЬ!N100 -> 129 | H4: =ДЕКАБРЬ!S100 -> 127 | I4: =ДЕКАБРЬ!T100 -> -5 | J4: =ДЕКАБРЬ!V100 -> 118047.57 | K4: =ДЕКАБРЬ!W100 -> -6409 | L4: =IFERROR(J4+K4,0) -> 111638.57 | M4: =ДЕКАБРЬ!Y100 -> 138964.57 | N4: =ДЕКАБРЬ!Z100 -> -7526 | O4: =IFERROR(M4+N4,0) -> 131438.57 | P4: =ДЕКАБРЬ!AD100 -> 15240.45 | Q4: =ДЕКАБРЬ!AG100 -> 17381.1 | R4: =ДЕКАБРЬ!AE100 -> 48126.54 | S4: =ДЕКАБРЬ!AL100 -> 3615.9322 | T4: 1.7 | U4: =ДЕКАБРЬ!AM100 -> 0 | W4: =ДЕКАБРЬ!AH100 -> 0 | X4: =ДЕКАБРЬ!AI100 -> 0 | Z4: =ДЕКАБРЬ!AK100 -> 0 | AC4: =ДЕКАБРЬ!AN100 -> 6067.24 | AE4: =O4-SUM(P4:Z4)+AD4 -> 47072.848 | AF4: =O4-SUM(P4:AC4)+AD4 -> 41005.608 | AG4: =SUM(AF4:AF5) -> 41005.32 | AH4: =P4/O4 -> 0.11595112 | AI4: =AF4/P4 -> 2.6905772 | AJ4: =AF4/O4 -> 0.31197546 | AK4: =(W4+X4+Z4)/O4 -> 0
B5: Декабрь туники | C5: 29-31.12 | D5: 1 | F5: =IFERROR(O5-SUM(Q5:W5)+AD5,0) -> -0.28775523 | G5: =ДЕКАБРЬ!N108 -> 0 | H5: =ДЕКАБРЬ!S108 -> 0 | I5: =ДЕКАБРЬ!T108 -> 0 | J5: =ДЕКАБРЬ!V108 -> 0 | K5: =ДЕКАБРЬ!W108 -> 0 | L5: =IFERROR(J5+K5,0) -> 0 | M5: =ДЕКАБРЬ!Y108 -> 0 | N5: =ДЕКАБРЬ!Z108 -> 0 | O5: =IFERROR(M5+N5,0) -> 0 | P5: =ДЕКАБРЬ!AD108 -> 0 | Q5: =ДЕКАБРЬ!AG108 -> 0 | R5: =ДЕКАБРЬ!AE108 -> 0 | S5: =ДЕКАБРЬ!AL108 -> 0.28775523 | U5: =ДЕКАБРЬ!AM108 -> 0 | W5: =ДЕКАБРЬ!AH108 -> 0 | X5: =ДЕКАБРЬ!AI108 -> 0 | Z5: =ДЕКАБРЬ!AK108 -> 0 | AC5: =ДЕКАБРЬ!AN108 -> 0 | AE5: =O5-SUM(P5:Z5)+AD5 -> -0.28775523 | AF5: =O5-SUM(P5:AC5)+AD5 -> -0.28775523 | AH5: =P5/O5 -> #DIV/0! | AI5: =AF5/P5 -> #DIV/0! | AJ5: =AF5/O5 -> #DIV/0! | AK5: =(W5+X5+Z5)/O5 -> #DIV/0!
B6: Январь очки | C6: 01.01-01.02 | D6: 1-5 | F6: =IFERROR(O6-SUM(Q6:W6)+AD6,0) -> 955718.86 | G6: =ЯНВАРЬ!N100 -> 4961 | H6: =ЯНВАРЬ!S100 -> 2362 | I6: =ЯНВАРЬ!T100 -> -53 | J6: =ЯНВАРЬ!V100 -> 1728382.8 | K6: =ЯНВАРЬ!W100 -> -44657.88 | L6: =IFERROR(J6+K6,0) -> 1683724.9 | M6: =ЯНВАРЬ!Y100 -> 2303342.1 | N6: =ЯНВАРЬ!Z100 -> -58267.04 | O6: =IFERROR(M6+N6,0) -> 2245075 | P6: =ЯНВАРЬ!AD100 -> 292876.64 | Q6: =ЯНВАРЬ!AG100 -> 276475.65 | R6: =ЯНВАРЬ!AE100 -> 833669.77 | S6: =ЯНВАРЬ!AL100 -> 40333.14 | U6: =ЯНВАРЬ!AM100 -> 0 | V6: 25431.6 | W6: =ЯНВАРЬ!AH100 -> 113446 | X6: =ЯНВАРЬ!AI100 -> 404487 | Z6: =ЯНВАРЬ!AK100 -> 0 | AC6: =ЯНВАРЬ!AN100 -> 95827.42 | AE6: =O6-SUM(P6:Z6)+AD6 -> 258355.22 | AF6: =O6-SUM(P6:AC6)+AD6 -> 162527.8 | AG6: =SUM(AF6:AF8) -> 162168.41 | AH6: =P6/O6 -> 0.13045294 | AI6: =AF6/P6 -> 0.55493603 | AJ6: =AF6/O6 -> 0.072393037 | AK6: =(W6+X6+Z6)/O6 -> 0.23069741
B7: Январь туники | C7: 01.01-01.02 | D7: 1-5 | F7: =IFERROR(O7-SUM(Q7:W7)+AD7,0) -> -186.4297 | G7: =ЯНВАРЬ!N108 -> 1 | H7: =ЯНВАРЬ!S108 -> 0 | I7: =ЯНВАРЬ!T108 -> 0 | J7: =ЯНВАРЬ!V108 -> 0 | K7: =ЯНВАРЬ!W108 -> 0 | L7: =IFERROR(J7+K7,0) -> 0 | M7: =ЯНВАРЬ!Y108 -> 0 | N7: =ЯНВАРЬ!Z108 -> 0 | O7: =IFERROR(M7+N7,0) -> 0 | P7: =ЯНВАРЬ!AD108 -> 0 | Q7: =ЯНВАРЬ!AG108 -> 183.22 | R7: =ЯНВАРЬ!AE108 -> 0 | S7: =ЯНВАРЬ!AL108 -> 3.209704 | U7: =ЯНВАРЬ!AM108 -> 0 | W7: =ЯНВАРЬ!AH108 -> 0 | X7: =ЯНВАРЬ!AI108 -> 0 | Z7: =ЯНВАРЬ!AK108 -> 0 | AC7: =ЯНВАРЬ!AN108 -> 0 | AE7: =O7-SUM(P7:Z7)+AD7 -> -186.4297 | AF7: =O7-SUM(P7:AC7)+AD7 -> -186.4297 | AH7: =P7/O7 -> #DIV/0! | AI7: =AF7/P7 -> #DIV/0! | AJ7: =AF7/O7 -> #DIV/0! | AK7: =(W7+X7+Z7)/O7 -> #DIV/0!
B8: Январь шапки | C8: 01.01-01.02 | D8: 1-5 | F8: =IFERROR(O8-SUM(Q8:W8)+AD8,0) -> -172.96 | G8: =ЯНВАРЬ!N119 -> 0 | H8: =ЯНВАРЬ!S119 -> 0 | I8: =ЯНВАРЬ!T119 -> 0 | J8: =ЯНВАРЬ!V119 -> 0 | K8: =ЯНВАРЬ!W119 -> 0 | L8: =IFERROR(J8+K8,0) -> 0 | M8: =ЯНВАРЬ!Y119 -> 0 | N8: =ЯНВАРЬ!Z119 -> 0 | O8: =IFERROR(M8+N8,0) -> 0 | P8: =ЯНВАРЬ!AD119 -> 0 | Q8: =ЯНВАРЬ!AG119 -> 172.96 | R8: =ЯНВАРЬ!AE119 -> 0 | S8: =ЯНВАРЬ!AL119 -> 0 | U8: =ЯНВАРЬ!AM119 -> 0 | W8: =ЯНВАРЬ!AH119 -> 0 | X8: =ЯНВАРЬ!AI119 -> 0 | Z8: =ЯНВАРЬ!AK119 -> 0 | AC8: =ЯНВАРЬ!AN119 -> 0 | AE8: =O8-SUM(P8:Z8)+AD8 -> -172.96 | AF8: =O8-SUM(P8:AC8)+AD8 -> -172.96 | AH8: =P8/O8 -> #DIV/0! | AI8: =AF8/P8 -> #DIV/0! | AJ8: =AF8/O8 -> #DIV/0! | AK8: =(W8+X8+Z8)/O8 -> #DIV/0!
B9: Февраль 1 очки | C9: 02-08.02 | D9: 6 | F9: =IFERROR(O9-SUM(Q9:W9)+AD9,0) -> 539419.19 | G9: ='Юнит 6'!N105 -> 2829 | H9: ='Юнит 6'!S105 -> 1418 | I9: ='Юнит 6'!T105 -> -25 | J9: ='Юнит 6'!V105 -> 894889.93 | K9: ='Юнит 6'!W105 -> -16453.5 | L9: =IFERROR(J9+K9,0) -> 878436.43 | M9: ='Юнит 6'!Y105 -> 1357375 | N9: ='Юнит 6'!Z105 -> -24887.06 | O9: =IFERROR(M9+N9,0) -> 1332487.9 | P9: ='Юнит 6'!AD105 -> 175437.39 | Q9: ='Юнит 6'!AG105 -> 153486.12 | R9: ='Юнит 6'!AE105 -> 495216.11 | S9: ='Юнит 6'!AL105 -> 8160.06 | U9: ='Юнит 6'!AM105 -> 0 | V9: =5797.44+18990 -> 24787.44 | W9: ='Юнит 6'!AH105 -> 111419 | X9: ='Юнит 6'!AI105 -> 126688 | Z9: ='Юнит 6'!AK105 -> 0 | AC9: =304652.46*O9/SUM(O$9:O$16) -> 47907.536 | AE9: =O9-SUM(P9:Z9)+AD9 -> 237293.8 | AF9: =O9-SUM(P9:AC9)+AD9 -> 189386.26 | AG9: =SUM(AF9:AF16) -> 1876556.2 | AH9: =P9/O9 -> 0.13166152 | AI9: =AF9/P9 -> 1.0795091 | AJ9: =AF9/O9 -> 0.14212982 | AK9: =(W9+X9+Z9)/O9 -> 0.17869355
B10: Февраль 1 туники | C10: 02-08.02 | D10: 6 | F10: =IFERROR(O10-SUM(Q10:W10)+AD10,0) -> 0 | G10: ='Юнит 6'!N113 -> 1 | H10: ='Юнит 6'!S113 -> 0 | I10: ='Юнит 6'!T113 -> 0 | J10: ='Юнит 6'!V113 -> 0 | K10: ='Юнит 6'!W113 -> 0 | L10: =IFERROR(J10+K10,0) -> 0 | M10: ='Юнит 6'!Y113 -> 0 | N10: ='Юнит 6'!Z113 -> 0 | O10: =IFERROR(M10+N10,0) -> 0 | P10: ='Юнит 6'!AD113 -> 0 | Q10: ='Юнит 6'!AG113 -> 0 | R10: ='Юнит 6'!AE113 -> 0 | S10: ='Юнит 6'!AL113 -> 0 | U10: ='Юнит 6'!AM113 -> 0 | W10: ='Юнит 6'!AH113 -> 0 | X10: ='Юнит 6'!AI113 -> 0 | Z10: ='Юнит 6'!AK113 -> 0 | AC10: =304652.46*O10/SUM(O$9:O$16) -> 0 | AE10: =O10-SUM(P10:Z10)+AD10 -> 0 | AF10: =O10-SUM(P10:AC10)+AD10 -> 0 | AH10: =P10/O10 -> #DIV/0! | AI10: =AF10/P10 -> #DIV/0! | AJ10: =AF10/O10 -> #DIV/0! | AK10: =(W10+X10+Z10)/O10 -> #DIV/0!
B11: Февраль 2 очки | C11: 09-15.02 | D11: 7 | F11: =IFERROR(O11-SUM(Q11:W11)+AD11,0) -> 811496.75 | G11: ='Юнит 7'!N105 -> 3325 | H11: ='Юнит 7'!S105 -> 1882 | I11: ='Юнит 7'!T105 -> -40 | J11: ='Юнит 7'!V105 -> 1236743.8 | K11: ='Юнит 7'!W105 -> -26582.27 | L11: =IFERROR(J11+K11,0) -> 1210161.6 | M11: ='Юнит 7'!Y105 -> 1920260.7 | N11: ='Юнит 7'!Z105 -> -41194.47 | O11: =IFERROR(M11+N11,0) -> 1879066.2 | P11: ='Юнит 7'!AD105 -> 230374.86 | Q11: ='Юнит 7'!AG105 -> 212380.68 | R11: ='Юнит 7'!AE105 -> 695831.51 | S11: ='Юнит 7'!AL105 -> 8132.98 | T11: 30 | U11: ='Юнит 7'!AM105 -> 826 | V11: 4787.28 | W11: ='Юнит 7'!AH105 -> 145581 | X11: ='Юнит 7'!AI105 -> 138670 | Z11: ='Юнит 7'!AK105 -> 0 | AC11: =304652.46*O11/SUM(O$9:O$16) -> 67558.911 | AE11: =O11-SUM(P11:Z11)+AD11 -> 442451.89 | AF11: =O11-SUM(P11:AC11)+AD11 -> 374892.98 | AH11: =P11/O11 -> 0.12260072 | AI11: =AF11/P11 -> 1.6273172 | AJ11: =AF11/O11 -> 0.19951026 | AK11: =(W11+X11+Z11)/O11 -> 0.15127248
B12: Февраль 2 туники | C12: 09-15.02 | D12: 7 | F12: =IFERROR(O12-SUM(Q12:W12)+AD12,0) -> 1191.57 | G12: ='Юнит 7'!N113 -> 0 | H12: ='Юнит 7'!S113 -> 1 | I12: ='Юнит 7'!T113 -> 0 | J12: ='Юнит 7'!V113 -> 1407 | K12: ='Юнит 7'!W113 -> 0 | L12: =IFERROR(J12+K12,0) -> 1407 | M12: ='Юнит 7'!Y113 -> 2079 | N12: ='Юнит 7'!Z113 -> 0 | O12: =IFERROR(M12+N12,0) -> 2079 | P12: ='Юнит 7'!AD113 -> 579.18 | Q12: ='Юнит 7'!AG113 -> 124.34 | R12: ='Юнит 7'!AE113 -> 763.09 | S12: ='Юнит 7'!AL113 -> 0 | U12: ='Юнит 7'!AM113 -> 0 | W12: ='Юнит 7'!AH113 -> 0 | X12: ='Юнит 7'!AI113 -> 0 | Z12: ='Юнит 7'!AK113 -> 0 | AC12: =304652.46*O12/SUM(O$9:O$16) -> 74.74722 | AE12: =O12-SUM(P12:Z12)+AD12 -> 612.39 | AF12: =O12-SUM(P12:AC12)+AD12 -> 537.64278 | AH12: =P12/O12 -> 0.27858586 | AI12: =AF12/P12 -> 0.92828271 | AJ12: =AF12/O12 -> 0.25860644 | AK12: =(W12+X12+Z12)/O12 -> 0
B13: Февраль 3 очки | C13: 16-22.02 | D13: 8 | F13: =IFERROR(O13-SUM(Q13:W13)+AD13,0) -> 1204943.2 | G13: ='Юнит 8'!N$105 -> 4413 | H13: ='Юнит 8'!S$105 -> 2295 | I13: ='Юнит 8'!T$105 -> -43 | J13: ='Юнит 8'!V$105 -> 1593380.1 | K13: ='Юнит 8'!W$105 -> -29254.63 | L13: =IFERROR(J13+K13,0) -> 1564125.5 | M13: ='Юнит 8'!Y$105 -> 2501418.9 | N13: ='Юнит 8'!Z$105 -> -47007.29 | O13: =IFERROR(M13+N13,0) -> 2454411.6 | P13: ='Юнит 8'!AD$105 -> 280478.83 | Q13: ='Юнит 8'!AG$105 -> 267875.33 | R13: ='Юнит 8'!AE$105 -> 918234.84 | S13: ='Юнит 8'!AL$105 -> 8623.9028 | U13: ='Юнит 8'!AM$105 -> 466 | V13: 3279.36 | W13: ='Юнит 8'!AH$105 -> 50989 | X13: ='Юнит 8'!AI$105 -> 265182 | Z13: ='Юнит 8'!AK$105 -> 0 | AC13: =304652.46*O13/SUM(O$9:O$16) -> 88244.562 | AE13: =O13-SUM(P13:Z13)+AD13 -> 659282.34 | AF13: =O13-SUM(P13:AC13)+AD13 -> 571037.78 | AH13: =P13/O13 -> 0.11427538 | AI13: =AF13/P13 -> 2.035939 | AJ13: =AF13/O13 -> 0.23265771 | AK13: =(W13+X13+Z13)/O13 -> 0.12881743
B14: Февраль 3 туники | C14: 16-22.02 | D14: 8 | F14: =IFERROR(O14-SUM(Q14:W14)+AD14,0) -> -0.86724686 | G14: ='Юнит 8'!N113 -> 0 | H14: ='Юнит 8'!S113 -> 0 | I14: ='Юнит 8'!T113 -> 0 | J14: ='Юнит 8'!V113 -> 0 | K14: ='Юнит 8'!W113 -> 0 | L14: =IFERROR(J14+K14,0) -> 0 | M14: ='Юнит 8'!Y113 -> 0 | N14: ='Юнит 8'!Z113 -> 0 | O14: =IFERROR(M14+N14,0) -> 0 | P14: ='Юнит 8'!AD113 -> 0 | Q14: ='Юнит 8'!AG113 -> 0 | R14: ='Юнит 8'!AE113 -> 0 | S14: ='Юнит 8'!AL113 -> 0.86724686 | U14: ='Юнит 8'!AM113 -> 0 | W14: ='Юнит 8'!AH113 -> 0 | X14: ='Юнит 8'!AI113 -> 0 | Z14: ='Юнит 8'!AK113 -> 0 | AC14: =304652.46*O14/SUM(O$9:O$16) -> 0 | AE14: =O14-SUM(P14:Z14)+AD14 -> -0.86724686 | AF14: =O14-SUM(P14:AC14)+AD14 -> -0.86724686 | AH14: =P14/O14 -> #DIV/0! | AI14: =AF14/P14 -> #DIV/0! | AJ14: =AF14/O14 -> #DIV/0! | AK14: =(W14+X14+Z14)/O14 -> #DIV/0!
B15: Февраль 4 очки | C15: 23.02-01.03 | D15: 9 | F15: =IFERROR(O15-SUM(Q15:W15)+AD15,0) -> 1208387.9 | G15: ='Юнит 9'!N$105 -> 3950 | H15: ='Юнит 9'!S$105 -> 2372 | I15: ='Юнит 9'!T$105 -> -63 | J15: ='Юнит 9'!V$105 -> 1818463.8 | K15: ='Юнит 9'!W$105 -> -46702.77 | L15: =IFERROR(J15+K15,0) -> 1771761 | M15: ='Юнит 9'!Y$105 -> 2879025.2 | N15: ='Юнит 9'!Z$105 -> -73544.64 | O15: =IFERROR(M15+N15,0) -> 2805480.6 | P15: ='Юнит 9'!AD$105 -> 288027.84 | Q15: ='Юнит 9'!AG$105 -> 299415.53 | R15: ='Юнит 9'!AE$105 -> 1051752.7 | S15: ='Юнит 9'!AL$105 -> 8471.4 | U15: ='Юнит 9'!AM$105 -> 1392.11 | V15: 2400.96 | W15: ='Юнит 9'!AH$105 -> 233660 | X15: ='Юнит 9'!AI$105 -> 78621 | Z15: ='Юнит 9'!AK$105 -> 0 | AC15: =304652.46*O15/SUM(O$9:O$16) -> 100866.7 | AE15: =O15-SUM(P15:Z15)+AD15 -> 841739.09 | AF15: =O15-SUM(P15:AC15)+AD15 -> 740872.39 | AH15: =P15/O15 -> 0.10266613 | AI15: =AF15/P15 -> 2.5722249 | AJ15: =AF15/O15 -> 0.26408038 | AK15: =(W15+X15+Z15)/O15 -> 0.11131105
B16: Февраль 4 прочее | C16: 23.02-01.03 | D16: 9 | F16: =IFERROR(O16-SUM(Q16:W16)+AD16,0) -> -170 | Q16: ='Юнит 9'!AG125 -> 170 | AC16: =304652.46*O16/SUM(O$9:O$16) -> 0 | AE16: =O16-SUM(P16:Z16)+AD16 -> -170 | AF16: =O16-SUM(P16:AC16)+AD16 -> -170 | AH16: =P16/O16 -> #DIV/0! | AI16: =AF16/P16 -> #DIV/0! | AJ16: =AF16/O16 -> #DIV/0! | AK16: =(W16+X16+Z16)/O16 -> #DIV/0!
B17: Март 1 очки | C17: 02-08.03 | D17: 10 | F17: =IFERROR(O17-SUM(Q17:W17)+AD17,0) -> 1238601.7 | G17: ='Юнит 10'!N$105 -> 3795 | H17: ='Юнит 10'!S$105 -> 2096 | I17: ='Юнит 10'!T$105 -> -53 | J17: ='Юнит 10'!V$105 -> 1702514.8 | K17: ='Юнит 10'!W$105 -> -41251 | L17: =IFERROR(J17+K17,0) -> 1661263.8 | M17: ='Юнит 10'!Y$105 -> 2657773.4 | N17: ='Юнит 10'!Z$105 -> -65375.4 | O17: =IFERROR(M17+N17,0) -> 2592398 | P17: ='Юнит 10'!AD$105 -> 254974.68 | Q17: ='Юнит 10'!AG$105 -> 270558.84 | R17: ='Юнит 10'!AE$105 -> 972977.25 | S17: ='Юнит 10'!AL$105 -> 11702.83 | U17: ='Юнит 10'!AM$105 -> 0 | V17: =1083.36+22990 -> 24073.36 | W17: ='Юнит 10'!AH$105 -> 74484 | X17: ='Юнит 10'!AI$105 -> 252853 | Z17: ='Юнит 10'!AK$105 -> 0 | AC17: =666212.62*O17/SUM(O$17:O$20) -> 94861.253 | AE17: =O17-SUM(P17:Z17)+AD17 -> 730774.06 | AF17: =O17-SUM(P17:AC17)+AD17 -> 635912.81 | AG17: =SUM(AF17:AF20) -> 5396896.8 | AH17: =P17/O17 -> 0.098354758 | AI17: =AF17/P17 -> 2.4940234 | AJ17: =AF17/O17 -> 0.24529906 | AK17: =(W17+X17+Z17)/O17 -> 0.12626803
B18: Март 2 очки | C18: 09-15.03 | D18: 11 | F18: =IFERROR(O18-SUM(Q18:W18)+AD18,0) -> 2101556.8 | G18: ='Юнит 11'!N$105 -> 8243 | H18: ='Юнит 11'!S$105 -> 3480 | I18: ='Юнит 11'!T$105 -> -60 | J18: ='Юнит 11'!V$105 -> 3014405.3 | K18: ='Юнит 11'!W$105 -> -49269.89 | L18: =IFERROR(J18+K18,0) -> 2965135.4 | M18: ='Юнит 11'!Y$105 -> 4668001.6 | N18: ='Юнит 11'!Z$105 -> -76772.74 | O18: =IFERROR(M18+N18,0) -> 4591228.8 | P18: ='Юнит 11'!AD$105 -> 424325.4 | Q18: ='Юнит 11'!AG$105 -> 445765.14 | R18: ='Юнит 11'!AE$105 -> 1726243.8 | S18: ='Юнит 11'!AL$105 -> 9729.77 | U18: ='Юнит 11'!AM$105 -> 1842 | V18: 1288.32 | W18: ='Юнит 11'!AH$105 -> 304803 | X18: ='Юнит 11'!AI$105 -> 178004 | Z18: ='Юнит 11'!AK$105 -> 0 | AC18: =666212.62*O18/SUM(O$17:O$20) -> 168002.64 | AE18: =O18-SUM(P18:Z18)+AD18 -> 1499227.4 | AF18: =O18-SUM(P18:AC18)+AD18 -> 1331224.8 | AH18: =P18/O18 -> 0.092420878 | AI18: =AF18/P18 -> 3.1372734 | AJ18: =AF18/O18 -> 0.28994956 | AK18: =(W18+X18+Z18)/O18 -> 0.10515856
B19: Март 3 очки | C19: 16-22.03 | D19: 12 | F19: =IFERROR(O19-SUM(Q19:W19)+AD19,0) -> 2992995 | G19: ='Юнит 12'!N$105 -> 6902 | H19: ='Юнит 12'!S$105 -> 4072 | I19: ='Юнит 12'!T$105 -> -94 | J19: ='Юнит 12'!V$105 -> 3910621.8 | K19: ='Юнит 12'!W$105 -> -85755 | L19: =IFERROR(J19+K19,0) -> 3824866.8 | M19: ='Юнит 12'!Y$105 -> 5914054.7 | N19: ='Юнит 12'!Z$105 -> -132706.71 | O19: =IFERROR(M19+N19,0) -> 5781348 | P19: ='Юнит 12'!AD$105 -> 494039.24 | Q19: ='Юнит 12'!AG$105 -> 557216.52 | R19: ='Юнит 12'!AE$105 -> 2176223 | S19: ='Юнит 12'!AL$105 -> 6558.48 | U19: ='Юнит 12'!AM$105 -> 130 | W19: ='Юнит 12'!AH$105 -> 48225 | X19: ='Юнит 12'!AI$105 -> 468432 | Z19: ='Юнит 12'!AK$105 -> 0 | AC19: =666212.62*O19/SUM(O$17:O$20) -> 211551.59 | AE19: =O19-SUM(P19:Z19)+AD19 -> 2030523.7 | AF19: =O19-SUM(P19:AC19)+AD19 -> 1818972.1 | AH19: =P19/O19 -> 0.085453988 | AI19: =AF19/P19 -> 3.6818374 | AJ19: =AF19/O19 -> 0.31462768 | AK19: =(W19+X19+Z19)/O19 -> 0.089366182
B20: Март 4 очки | C20: 23-29.03 | D20: 13 | F20: =IFERROR(O20-SUM(Q20:W20)+AD20,0) -> 2696708.9 | G20: ='Юнит 13'!N$105 -> 6707 | H20: ='Юнит 13'!S$105 -> 3565 | I20: ='Юнит 13'!T$105 -> -97 | J20: ='Юнит 13'!V$105 -> 3582763.6 | K20: ='Юнит 13'!W$105 -> -97407.33 | L20: =IFERROR(J20+K20,0) -> 3485356.2 | M20: ='Юнит 13'!Y$105 -> 5387638.1 | N20: ='Юнит 13'!Z$105 -> -146145.86 | O20: =IFERROR(M20+N20,0) -> 5241492.2 | P20: ='Юнит 13'!AD$105 -> 429364.71 | Q20: ='Юнит 13'!AG$105 -> 472771.32 | R20: ='Юнит 13'!AE$105 -> 1975944.8 | S20: ='Юнит 13'!AL$105 -> 8091.54 | U20: ='Юнит 13'!AM$105 -> -1073 | V20: 702.72 | W20: ='Юнит 13'!AH$105 -> 88346 | X20: ='Юнит 13'!AI$105 -> 464760 | Z20: ='Юнит 13'!AK$105 -> 0 | AC20: =666212.62*O20/SUM(O$17:O$20) -> 191797.14 | AE20: =O20-SUM(P20:Z20)+AD20 -> 1802584.2 | AF20: =O20-SUM(P20:AC20)+AD20 -> 1610787.1 | AH20: =P20/O20 -> 0.081916502 | AI20: =AF20/P20 -> 3.751559 | AJ20: =AF20/O20 -> 0.30731459 | AK20: =(W20+X20+Z20)/O20 -> 0.10552453
B21: Апрель 1 очки | C21: 30.03-05.04 | D21: 14 | F21: =IFERROR(O21-SUM(Q21:W21)-AA21-AB21+AD21,0) -> 2335595.7 | G21: ='Юнит 14'!N$105 -> 5475 | H21: ='Юнит 14'!S$105 -> 3012 | I21: ='Юнит 14'!T$105 -> -85 | J21: ='Юнит 14'!V$105 -> 3007932.1 | K21: ='Юнит 14'!W$105 -> -82412.17 | L21: =IFERROR(J21+K21,0) -> 2925519.9 | M21: ='Юнит 14'!Y$105 -> 4561244.2 | N21: ='Юнит 14'!Z$105 -> -124396.78 | O21: =IFERROR(M21+N21,0) -> 4436847.4 | P21: ='Юнит 14'!AD$105 -> 363233.15 | Q21: ='Юнит 14'!AG$105 -> 409675.01 | R21: ='Юнит 14'!AE$105 -> 1670278 | S21: ='Юнит 14'!AL$105 -> 8536.1 | U21: ='Юнит 14'!AM$105 -> 960 | V21: 702.72 | W21: ='Юнит 14'!AH$105 -> 9682 | X21: ='Юнит 14'!AI$105 -> 500888 | Z21: ='Юнит 14'!AK$105 -> 0 | AA21: 128.9 | AB21: 1289 | AC21: ='Юнит 14'!AN$105 -> 167047.19 | AE21: =O21-SUM(P21:AB21)+AD21 -> 1471474.5 | AF21: =O21-SUM(P21:AC21)+AD21 -> 1304427.3 | AG21: =SUM(AF21:AF25) -> 3664800.2 | AH21: =P21/O21 -> 0.081867397 | AI21: =AF21/P21 -> 3.5911572 | AJ21: =AF21/O21 -> 0.29399869 | AK21: =(W21+X21+Z21)/O21 -> 0.11507495
B22: Апрель 2 очки | C22: 06-12.04 | D22: 15 | F22: =IFERROR(O22-SUM(Q22:W22)-AA22-AB22+AD22,0) -> 1648542.8 | G22: ='Юнит 15'!N$105 -> 3532 | H22: ='Юнит 15'!S$105 -> 2176 | I22: ='Юнит 15'!T$105 -> -59 | J22: ='Юнит 15'!V$105 -> 2198880.5 | K22: ='Юнит 15'!W$105 -> -57961.37 | L22: =IFERROR(J22+K22,0) -> 2140919.2 | M22: ='Юнит 15'!Y$105 -> 3303471.3 | N22: ='Юнит 15'!Z$105 -> -87984.17 | O22: =IFERROR(M22+N22,0) -> 3215487.2 | P22: ='Юнит 15'!AD$105 -> 261816.2 | Q22: ='Юнит 15'!AG$105 -> 302367.43 | R22: ='Юнит 15'!AE$105 -> 1215469.6 | S22: ='Юнит 15'!AL$105 -> 9130.33 | U22: ='Юнит 15'!AM$105 -> 4923.98 | V22: 22990 | W22: ='Юнит 15'!AH$105 -> 2405 | X22: ='Юнит 15'!AI$105 -> 301236 | Z22: ='Юнит 15'!AK$105 -> 0 | AA22: 878 | AB22: 8780 | AC22: ='Юнит 15'!AN$105 -> 122246.48 | AE22: =O22-SUM(P22:AB22)+AD22 -> 1085490.6 | AF22: =O22-SUM(P22:AC22)+AD22 -> 963244.12 | AH22: =P22/O22 -> 0.081423494 | AI22: =AF22/P22 -> 3.6790852 | AJ22: =AF22/O22 -> 0.29956397 | AK22: =(W22+X22+Z22)/O22 -> 0.094430792
B23: Апрель 3 очки | C23: 13-19.04 | D23: 16 | F23: =IFERROR(O23-SUM(Q23:W23)-AA23-AB23+AD23,0) -> 1468778.3 | G23: ='Юнит 16'!N$106 -> 3479 | H23: ='Юнит 16'!S$106 -> 1972 | I23: ='Юнит 16'!T$106 -> -47 | J23: ='Юнит 16'!V$106 -> 1966605.2 | K23: ='Юнит 16'!W$106 -> -45569.59 | L23: =IFERROR(J23+K23,0) -> 1921035.6 | M23: ='Юнит 16'!Y$106 -> 2939167.4 | N23: ='Юнит 16'!Z$106 -> -68089.33 | O23: =IFERROR(M23+N23,0) -> 2871078.1 | P23: ='Юнит 16'!AD$106 -> 238729.31 | Q23: ='Юнит 16'!AG$106 -> 252691.82 | R23: ='Юнит 16'!AE$106 -> 1082608.5 | S23: ='Юнит 16'!AL$106 -> 11044.13 | U23: ='Юнит 16'!AM$106 -> 3110 | W23: ='Юнит 16'!AH$106 -> 43580 | X23: ='Юнит 16'!AI$106 -> 287584 | Z23: ='Юнит 16'!AK$106 -> 0 | AA23: 842.3 | AB23: 8423 | AC23: ='Юнит 16'!AN$106 -> 109691.13 | AE23: =O23-SUM(P23:AB23)+AD23 -> 942465 | AF23: =O23-SUM(P23:AC23)+AD23 -> 832773.87 | AH23: =P23/O23 -> 0.08314971 | AI23: =AF23/P23 -> 3.4883604 | AJ23: =AF23/O23 -> 0.29005616 | AK23: =(W23+X23+Z23)/O23 -> 0.11534483
B24: Апрель 4 очки | C24: 20-26.04 | D24: 17 | F24: =IFERROR(O24-SUM(Q24:W24)-AA24-AB24+AD24,0) -> 1257598.6 | G24: ='Юнит 17'!N$106 -> 3101 | H24: ='Юнит 17'!S$106 -> 1730 | I24: ='Юнит 17'!T$106 -> -35 | J24: ='Юнит 17'!V$106 -> 1694803.1 | K24: ='Юнит 17'!W$106 -> -35587.44 | L24: =IFERROR(J24+K24,0) -> 1659215.6 | M24: ='Юнит 17'!Y$106 -> 2465283.2 | N24: ='Юнит 17'!Z$106 -> -52946.24 | O24: =IFERROR(M24+N24,0) -> 2412337 | P24: ='Юнит 17'!AD$106 -> 210794.5 | Q24: ='Юнит 17'!AG$106 -> 226778.55 | R24: ='Юнит 17'!AE$106 -> 908073.2 | S24: ='Юнит 17'!AL$106 -> 10756.94 | U24: ='Юнит 17'!AM$106 -> 1310 | W24: ='Юнит 17'!AH$106 -> 6217 | X24: ='Юнит 17'!AI$106 -> 172288 | Y24: ='Юнит 17'!AJ106 -> 215420 | Z24: ='Юнит 17'!AK$106 -> 0 | AA24: 145.7 | AB24: 1457 | AC24: ='Юнит 17'!AN$106 -> 94741.212 | AE24: =O24-SUM(P24:AB24)+AD24 -> 659096.12 | AF24: =O24-SUM(P24:AC24)+AD24 -> 564354.91 | AH24: =P24/O24 -> 0.087381862 | AI24: =AF24/P24 -> 2.6772753 | AJ24: =AF24/O24 -> 0.2339453 | AK24: =(W24+X24+Z24)/O24 -> 0.073996709
B25: Апрель 5 очки | C25: 27.04-03.05 | D25: 18 | AH25: =P25/O25 -> #DIV/0! | AI25: =AF25/P25 -> #DIV/0! | AJ25: =AF25/O25 -> #DIV/0! | AK25: =(W25+X25+Z25)/O25 -> #DIV/0!
B28: Итого | F28: =SUM(F4:F27) -> 20523318 | G28: =SUM(G4:G27) -> 60843 | H28: =SUM(H4:H27) -> 32560 | I28: =SUM(I4:I27) -> -759 | J28: =SUM(J4:J27) -> 28469841 | K28: =SUM(K4:K27) -> -665273.84 | L28: =SUM(L4:L27) -> 27804567 | M28: =SUM(M4:M27) -> 42999099 | ... X28: =SUM(X4:X27) -> 3639693 | Z28: =SUM(Z4:Z27) -> 0 | AC28: =SUM(AC4:AC27) -> 1566485.8 | AD28: =SUM(AD4:AD27) -> 0 | AE28: =SUM(AE4:AE27) -> 12707913 | AF28: =SUM(AF4:AF27) -> 11141427 | AG28: =SUM(AG4:AG27) -> 11141427 | AH28: =P28/O28 -> 0.094310065 | AI28: =AF28/P28 -> 2.8132839 | AJ28: =AF28/O28 -> 0.26532099 | AK28: =(W28+X28+Z28)/O28 -> 0.11603401
M29: % от выручки за весь период
N30: =-N28/M28 -> 0.023415461 | P30: =P28/$O$28 -> 0.094310065 | Q30: =Q28/$O$28 -> 0.099196614 | R30: =R28/$O$28 -> 0.37557908 | S30: =S28/$O$28 -> 0.0036409547 | T30: =T28/$O$28 -> 7.549011e-07 | U30: =U28/$O$28 -> 0.00033070598 | V30: =V28/$O$28 -> 0.0026300983 | W30: =W28/$O$28 -> 0.029358675 | X30: =X28/$O$28 -> 0.086675339 | Z30: =Z28/$O$28 -> 0 | AC30: =AC28/$O$28 -> 0.037304158 | AG30: =AF28/P28 -> 2.8132839 | AH30: Маржинальность, %
W31: =(W28+X28)/O28 -> 0.11603401 | AG31: =AF28/O28 -> 0.26532099 | AH31: Рентабельность, %
B33: ЯНВАРЬ очки | G33: =G6 -> 4961 | H33: =H6 -> 2362 | I33: =I6 -> -53 | J33: =J6 -> 1728382.8 | K33: =K6 -> -44657.88 | L33: =L6 -> 1683724.9 | M33: =M6 -> 2303342.1 | N33: =N6 -> -58267.04 | ... X33: =X6 -> 404487 | Z33: =Z6 -> 0 | AC33: =AC6 -> 95827.42 | AD33: =AD6 -> 0 | AE33: =AE6 -> 258355.22 | AF33: =AF6 -> 162527.8 | AG33: =AF33/P33 -> 0.55493603
N34: =-N33/M33 -> 0.025296738 | P34: =P33/$O$33 -> 0.13045294 | Q34: =Q33/$O$33 -> 0.12314762 | R34: =R33/$O$33 -> 0.3713327 | S34: =S33/$O$33 -> 0.017965164 | T34: =T33/$O$33 -> 0 | U34: =U33/$O$33 -> 0 | V34: =V33/$O$33 -> 0.011327728 | W34: =W33/$O$33 -> 0.050531051 | X34: =X33/$O$33 -> 0.18016636 | Z34: =Z33/$O$33 -> 0 | AC34: =AC33/$O$33 -> 0.042683393 | AD34: =AD33/$O$33 -> 0 | AF34: =AF33/O33 -> 0.072393037 | AG34: =AF33/O33 -> 0.072393037
B36: 7 нед очки | P36: =P11/$O$11 -> 0.12260072 | Q36: =Q11/$O$11 -> 0.11302459 | R36: =R11/$O$11 -> 0.37030708 | S36: =S11/$O$11 -> 0.004328203 | T36: =T11/$O$11 -> 1.5965377e-05 | U36: =U11/$O$11 -> 0.00043958004 | V36: =V11/$O$11 -> 0.002547691 | W36: =W11/$O$11 -> 0.077475184 | X36: =X11/$O$11 -> 0.073797294 | Z36: =Z11/$O$11 -> 0 | AC36: =AC11/$O$11 -> 0.035953449 | AD36: =AD11/$O$11 -> 0 | AG36: =AF11/P11 -> 1.6273172 | AH36: Маржинальность, %
AG37: =AF11/O11 -> 0.19951026 | AH37: Рентабельность, %
B39: ФЕВРАЛЬ очки | G39: =G9+G11+G13+G15 -> 14517 | H39: =H9+H11+H13+H15 -> 7967 | I39: =I9+I11+I13+I15 -> -171 | J39: =J9+J11+J13+J15 -> 5543477.6 | K39: =K9+K11+K13+K15 -> -118993.17 | L39: =L9+L11+L13+L15 -> 5424484.4 | M39: =M9+M11+M13+M15 -> 8658079.8 | N39: =N9+N11+N13+N15 -> -186633.46 | ... X39: =X9+X11+X13+X15 -> 609161 | Z39: =Z9+Z11+Z13+Z15 -> 0 | AC39: =AC9+AC11+AC13+AC15 -> 304577.71 | AD39: =AD9+AD11+AD13+AD15 -> 0 | AE39: =AE9+AE11+AE13+AE15 -> 2180767.1 | AF39: =AF9+AF11+AF13+AF15 -> 1876189.4 | AG39: =AF39/P39 -> 1.925642
N40: =-N39/M39 -> 0.021555988 | P40: =P39/$O$39 -> 0.11501211 | Q40: =Q39/$O$39 -> 0.11015329 | R40: =R39/$O$39 -> 0.37313996 | S40: =S39/$O$39 -> 0.0039412801 | T40: =T39/$O$39 -> 3.5413079e-06 | U40: =U39/$O$39 -> 0.000316842 | V40: =V39/$O$39 -> 0.0041616317 | W40: =W39/$O$39 -> 0.063938196 | X40: =X39/$O$39 -> 0.071907556 | Z40: =Z39/$O$39 -> 0 | AC40: =AC39/$O$39 -> 0.035953449 | AD40: =AD39/$O$39 -> 0 | AF40: =AF39/O39 -> 0.22147215 | AG40: =AF39/O39 -> 0.22147215
B42: 9 нед очки | P42: =P15/$O$15 -> 0.10266613 | Q42: =Q15/$O$15 -> 0.10672522 | R42: =R15/$O$15 -> 0.37489216 | S42: =S15/$O$15 -> 0.0030195896 | T42: =T15/$O$15 -> 0 | U42: =U15/$O$15 -> 0.00049621088 | V42: =V15/$O$15 -> 0.00085581058 | W42: =W15/$O$15 -> 0.083286977 | X42: =X15/$O$15 -> 0.028024075 | Z42: =Z15/$O$15 -> 0 | AC42: =AC15/$O$15 -> 0.035953449 | AD42: =AD15/$O$15 -> 0 | AG42: =AF15/P15 -> 2.5722249 | AH42: Маржинальность, %
AG43: =AF15/O15 -> 0.26408038 | AH43: Рентабельность, %
B45: МАРТ очки | G45: =SUM(G17:G20) -> 25647 | H45: =SUM(H17:H20) -> 13213 | I45: =SUM(I17:I20) -> -304 | J45: =SUM(J17:J20) -> 12210305 | K45: =SUM(K17:K20) -> -273683.22 | L45: =SUM(L17:L20) -> 11936622 | M45: =SUM(M17:M20) -> 18627468 | N45: =SUM(N17:N20) -> -421000.71 | ... X45: =SUM(X17:X20) -> 1364049 | Z45: =SUM(Z17:Z20) -> 0 | AC45: =SUM(AC17:AC20) -> 666212.62 | AD45: =SUM(AD17:AD20) -> 0 | AE45: =SUM(AE17:AE20) -> 6063109.4 | AF45: =SUM(AF17:AF20) -> 5396896.8 | AG45: =AF45/P45 -> 3.3673696 | AH45: Маржинальность, %
P46: =P45/$O$45 -> 0.088029381 | Q46: =Q45/$O$45 -> 0.095917116 | R46: =R45/$O$45 -> 0.37631622 | S46: =S45/$O$45 -> 0.0019818573 | T46: =T45/$O$45 -> 0 | U46: =U45/$O$45 -> 4.9378059e-05 | V46: =V45/$O$45 -> 0.0014316012 | W46: =W45/$O$45 -> 0.028333778 | X46: =X45/$O$45 -> 0.074921125 | Z46: =Z45/$O$45 -> 0 | AC46: =AC45/$O$45 -> 0.036592087 | AD46: =AD45/$O$45 -> 0 | AF46: =AF45/O45 -> 0.29642746 | AG46: =AF45/O45 -> 0.29642746 | AH46: Рентабельность, %

Sheet АВС 18
B2: ОЧКИ
C3: Прибыль | D3: % прибыль | E3: Доля | F3: ABC прибыль | G3: ABC кол-во | J3: Кол-во | K3: % кол-во | L3: Доля | M3: ABC кол-во
B4: черные с железкой классика | D4: =C4/C$106 -> #DIV/0! | E4: =D4 -> #DIV/0! | F4: =IF(AND(E4<=0),"C",IF(E4<=0.8,"A",IF(E4<=0.95,"B","C"))) -> #DIV/0! | G4: =VLOOKUP(B$4:B$104,I$4:M$104,5,0) -> #DIV/0! | I4: черные с железкой классика | K4: =J4/J$106 -> #DIV/0! | L4: =K4 -> #DIV/0! | M4: =_xlfn.IFS(L4<80%,"A",L4<=95%,"B",L4>95%,"C") -> #DIV/0! | P4: A | Q4: 0.8
B5: QS черные PZ | D5: =C5/C$106 -> #DIV/0! | E5: =E4+D5 -> #DIV/0! | F5: =IF(AND(E5<=0),"C",IF(E5<=0.8,"A",IF(E5<=0.95,"B","C"))) -> #DIV/0! | G5: =VLOOKUP(B$4:B$104,I$4:M$104,5,0) -> #DIV/0! | I5: QS черные PZ | K5: =J5/J$106 -> #DIV/0! | L5: =L4+K5 -> #DIV/0! | M5: =_xlfn.IFS(L5<80%,"A",L5<=95%,"B",L5>95%,"C") -> #DIV/0! | P5: B | Q5: 0.15
B6: QS синие PZ | D6: =C6/C$106 -> #DIV/0! | E6: =E5+D6 -> #DIV/0! | F6: =IF(AND(E6<=0),"C",IF(E6<=0.8,"A",IF(E6<=0.95,"B","C"))) -> #DIV/0! | G6: =VLOOKUP(B$4:B$104,I$4:M$104,5,0) -> #DIV/0! | I6: QS синие PZ | K6: =J6/J$106 -> #DIV/0! | L6: =L5+K6 -> #DIV/0! | M6: =_xlfn.IFS(L6<80%,"A",L6<=95%,"B",L6>95%,"C") -> #DIV/0! | P6: C | Q6: 0.05
B7: QS желтые PZ | D7: =C7/C$106 -> #DIV/0! | E7: =E6+D7 -> #DIV/0! | F7: =IF(AND(E7<=0),"C",IF(E7<=0.8,"A",IF(E7<=0.95,"B","C"))) -> #DIV/0! | G7: =VLOOKUP(B$4:B$104,I$4:M$104,5,0) -> #DIV/0! | I7: QS желтые PZ | K7: =J7/J$106 -> #DIV/0! | L7: =L6+K7 -> #DIV/0! | M7: =_xlfn.IFS(L7<80%,"A",L7<=95%,"B",L7>95%,"C") -> #DIV/0!
B8: QS коричневые PZ | D8: =C8/C$106 -> #DIV/0! | E8: =E7+D8 -> #DIV/0! | F8: =IF(AND(E8<=0),"C",IF(E8<=0.8,"A",IF(E8<=0.95,"B","C"))) -> #DIV/0! | G8: =VLOOKUP(B$4:B$104,I$4:M$104,5,0) -> #DIV/0! | I8: QS коричневые PZ | K8: =J8/J$106 -> #DIV/0! | L8: =L7+K8 -> #DIV/0! | M8: =_xlfn.IFS(L8<80%,"A",L8<=95%,"B",L8>95%,"C") -> #DIV/0!
B9: MR8854 C2 Жен | D9: =C9/C$106 -> #DIV/0! | E9: =E8+D9 -> #DIV/0! | F9: =IF(AND(E9<=0),"C",IF(E9<=0.8,"A",IF(E9<=0.95,"B","C"))) -> #DIV/0! | G9: =VLOOKUP(B$4:B$104,I$4:M$104,5,0) -> #DIV/0! | I9: MR8854 C2 Жен | K9: =J9/J$106 -> #DIV/0! | L9: =L8+K9 -> #DIV/0! | M9: =_xlfn.IFS(L9<80%,"A",L9<=95%,"B",L9>95%,"C") -> #DIV/0!
B10: th черн | D10: =C10/C$106 -> #DIV/0! | E10: =E9+D10 -> #DIV/0! | F10: =IF(AND(E10<=0),"C",IF(E10<=0.8,"A",IF(E10<=0.95,"B","C"))) -> #DIV/0! | G10: =VLOOKUP(B$4:B$104,I$4:M$104,5,0) -> #DIV/0! | I10: th черн | K10: =J10/J$106 -> #DIV/0! | L10: =L9+K10 -> #DIV/0! | M10: =_xlfn.IFS(L10<80%,"A",L10<=95%,"B",L10>95%,"C") -> #DIV/0!
B11: th син | D11: =C11/C$106 -> #DIV/0! | E11: =E10+D11 -> #DIV/0! | F11: =IF(AND(E11<=0),"C",IF(E11<=0.8,"A",IF(E11<=0.95,"B","C"))) -> #DIV/0! | G11: =VLOOKUP(B$4:B$104,I$4:M$104,5,0) -> #DIV/0! | I11: th син | K11: =J11/J$106 -> #DIV/0! | L11: =L10+K11 -> #DIV/0! | M11: =_xlfn.IFS(L11<80%,"A",L11<=95%,"B",L11>95%,"C") -> #DIV/0!
B12: th желт | D12: =C12/C$106 -> #DIV/0! | E12: =E11+D12 -> #DIV/0! | F12: =IF(AND(E12<=0),"C",IF(E12<=0.8,"A",IF(E12<=0.95,"B","C"))) -> #DIV/0! | G12: =VLOOKUP(B$4:B$104,I$4:M$104,5,0) -> #DIV/0! | I12: th желт | K12: =J12/J$106 -> #DIV/0! | L12: =L11+K12 -> #DIV/0! | M12: =_xlfn.IFS(L12<80%,"A",L12<=95%,"B",L12>95%,"C") -> #DIV/0!
B13: th коричн | D13: =C13/C$106 -> #DIV/0! | E13: =E12+D13 -> #DIV/0! | F13: =IF(AND(E13<=0),"C",IF(E13<=0.8,"A",IF(E13<=0.95,"B","C"))) -> #DIV/0! | G13: =VLOOKUP(B$4:B$104,I$4:M$104,5,0) -> #DIV/0! | I13: th коричн | K13: =J13/J$106 -> #DIV/0! | L13: =L12+K13 -> #DIV/0! | M13: =_xlfn.IFS(L13<80%,"A",L13<=95%,"B",L13>95%,"C") -> #DIV/0!
B14: flip черные | D14: =C14/C$106 -> #DIV/0! | E14: =E13+D14 -> #DIV/0! | F14: =IF(AND(E14<=0),"C",IF(E14<=0.8,"A",IF(E14<=0.95,"B","C"))) -> #DIV/0! | G14: =VLOOKUP(B$4:B$104,I$4:M$104,5,0) -> #DIV/0! | I14: flip черные | K14: =J14/J$106 -> #DIV/0! | L14: =L13+K14 -> #DIV/0! | M14: =_xlfn.IFS(L14<80%,"A",L14<=95%,"B",L14>95%,"C") -> #DIV/0!
B15: flip синие | D15: =C15/C$106 -> #DIV/0! | E15: =E14+D15 -> #DIV/0! | F15: =IF(AND(E15<=0),"C",IF(E15<=0.8,"A",IF(E15<=0.95,"B","C"))) -> #DIV/0! | G15: =VLOOKUP(B$4:B$104,I$4:M$104,5,0) -> #DIV/0! | I15: flip синие | K15: =J15/J$106 -> #DIV/0! | L15: =L14+K15 -> #DIV/0! | M15: =_xlfn.IFS(L15<80%,"A",L15<=95%,"B",L15>95%,"C") -> #DIV/0!
B16: flip желтые | D16: =C16/C$106 -> #DIV/0! | E16: =E15+D16 -> #DIV/0! | F16: =IF(AND(E16<=0),"C",IF(E16<=0.8,"A",IF(E16<=0.95,"B","C"))) -> #DIV/0! | G16: =VLOOKUP(B$4:B$104,I$4:M$104,5,0) -> #DIV/0! | I16: flip желтые | K16: =J16/J$106 -> #DIV/0! | L16: =L15+K16 -> #DIV/0! | M16: =_xlfn.IFS(L16<80%,"A",L16<=95%,"B",L16>95%,"C") -> #DIV/0!
B17: flip коричневые | D17: =C17/C$106 -> #DIV/0! | E17: =E16+D17 -> #DIV/0! | F17: =IF(AND(E17<=0),"C",IF(E17<=0.8,"A",IF(E17<=0.95,"B","C"))) -> #DIV/0! | G17: =VLOOKUP(B$4:B$104,I$4:M$104,5,0) -> #DIV/0! | I17: flip коричневые | K17: =J17/J$106 -> #DIV/0! | L17: =L16+K17 -> #DIV/0! | M17: =_xlfn.IFS(L17<80%,"A",L17<=95%,"B",L17>95%,"C") -> #DIV/0!
B18: wwl8032 коричневые золото | D18: =C18/C$106 -> #DIV/0! | E18: =E17+D18 -> #DIV/0! | F18: =IF(AND(E18<=0),"C",IF(E18<=0.8,"A",IF(E18<=0.95,"B","C"))) -> #DIV/0! | G18: =VLOOKUP(B$4:B$104,I$4:M$104,5,0) -> #DIV/0! | I18: wwl8032 коричневые золото | K18: =J18/J$106 -> #DIV/0! | L18: =L17+K18 -> #DIV/0! | M18: =_xlfn.IFS(L18<80%,"A",L18<=95%,"B",L18>95%,"C") -> #DIV/0!
... B38: sh13 | D38: =C38/C$106 -> #DIV/0! | E38: =E37+D38 -> #DIV/0! | F38: =IF(AND(E38<=0),"C",IF(E38<=0.8,"A",IF(E38<=0.95,"B","C"))) -> #DIV/0! | G38: =VLOOKUP(B$4:B$104,I$4:M$104,5,0) -> #DIV/0! | I38: sh13 | K38: =J38/J$106 -> #DIV/0! | L38: =L37+K38 -> #DIV/0! | M38: =_xlfn.IFS(L38<80%,"A",L38<=95%,"B",L38>95%,"C") -> #DIV/0!
B39: sh14 | D39: =C39/C$106 -> #DIV/0! | E39: =E35+D39 -> #DIV/0! | F39: =IF(AND(E39<=0),"C",IF(E39<=0.8,"A",IF(E39<=0.95,"B","C"))) -> #DIV/0! | G39: =VLOOKUP(B$4:B$104,I$4:M$104,5,0) -> #DIV/0! | I39: sh14 | K39: =J39/J$106 -> #DIV/0! | L39: =L35+K39 -> #DIV/0! | M39: =_xlfn.IFS(L39<80%,"A",L39<=95%,"B",L39>95%,"C") -> #DIV/0!
B40: sh15 | D40: =C40/C$106 -> #DIV/0! | E40: =E39+D40 -> #DIV/0! | F40: =IF(AND(E40<=0),"C",IF(E40<=0.8,"A",IF(E40<=0.95,"B","C"))) -> #DIV/0! | G40: =VLOOKUP(B$4:B$104,I$4:M$104,5,0) -> #DIV/0! | I40: sh15 | K40: =J40/J$106 -> #DIV/0! | L40: =L39+K40 -> #DIV/0! | M40: =_xlfn.IFS(L40<80%,"A",L40<=95%,"B",L40>95%,"C") -> #DIV/0!
B41: sh16 | D41: =C41/C$106 -> #DIV/0! | E41: =E40+D41 -> #DIV/0! | F41: =IF(AND(E41<=0),"C",IF(E41<=0.8,"A",IF(E41<=0.95,"B","C"))) -> #DIV/0! | G41: =VLOOKUP(B$4:B$104,I$4:M$104,5,0) -> #DIV/0! | I41: sh16 | K41: =J41/J$106 -> #DIV/0! | L41: =L40+K41 -> #DIV/0! | M41: =_xlfn.IFS(L41<80%,"A",L41<=95%,"B",L41>95%,"C") -> #DIV/0!
B42: sh17 | D42: =C42/C$106 -> #DIV/0! | E42: =E41+D42 -> #DIV/0! | F42: =IF(AND(E42<=0),"C",IF(E42<=0.8,"A",IF(E42<=0.95,"B","C"))) -> #DIV/0! | G42: =VLOOKUP(B$4:B$104,I$4:M$104,5,0) -> #DIV/0! | I42: sh17 | K42: =J42/J$106 -> #DIV/0! | L42: =L41+K42 -> #DIV/0! | M42: =_xlfn.IFS(L42<80%,"A",L42<=95%,"B",L42>95%,"C") -> #DIV/0!
B43: sh18 | D43: =C43/C$106 -> #DIV/0! | E43: =E42+D43 -> #DIV/0! | F43: =IF(AND(E43<=0),"C",IF(E43<=0.8,"A",IF(E43<=0.95,"B","C"))) -> #DIV/0! | G43: =VLOOKUP(B$4:B$104,I$4:M$104,5,0) -> #DIV/0! | I43: sh18 | K43: =J43/J$106 -> #DIV/0! | L43: =L42+K43 -> #DIV/0! | M43: =_xlfn.IFS(L43<80%,"A",L43<=95%,"B",L43>95%,"C") -> #DIV/0!
B44: sh19 | D44: =C44/C$106 -> #DIV/0! | E44: =E43+D44 -> #DIV/0! | F44: =IF(AND(E44<=0),"C",IF(E44<=0.8,"A",IF(E44<=0.95,"B","C"))) -> #DIV/0! | G44: =VLOOKUP(B$4:B$104,I$4:M$104,5,0) -> #DIV/0! | I44: sh19 | K44: =J44/J$106 -> #DIV/0! | L44: =L43+K44 -> #DIV/0! | M44: =_xlfn.IFS(L44<80%,"A",L44<=95%,"B",L44>95%,"C") -> #DIV/0!
B45: ww 203 черные | D45: =C45/C$106 -> #DIV/0! | E45: =E44+D45 -> #DIV/0! | F45: =IF(AND(E45<=0),"C",IF(E45<=0.8,"A",IF(E45<=0.95,"B","C"))) -> #DIV/0! | G45: =VLOOKUP(B$4:B$104,I$4:M$104,5,0) -> #DIV/0! | I45: ww 203 черные | K45: =J45/J$106 -> #DIV/0! | L45: =L44+K45 -> #DIV/0! | M45: =_xlfn.IFS(L45<80%,"A",L45<=95%,"B",L45>95%,"C") -> #DIV/0!
B46: ww 1022 черные | D46: =C46/C$106 -> #DIV/0! | E46: =E45+D46 -> #DIV/0! | F46: =IF(AND(E46<=0),"C",IF(E46<=0.8,"A",IF(E46<=0.95,"B","C"))) -> #DIV/0! | G46: =VLOOKUP(B$4:B$104,I$4:M$104,5,0) -> #DIV/0! | I46: ww 1022 черные | K46: =J46/J$106 -> #DIV/0! | L46: =L45+K46 -> #DIV/0! | M46: =_xlfn.IFS(L46<80%,"A",L46<=95%,"B",L46>95%,"C") -> #DIV/0!
B47: ww 1022 черн-серебро | D47: =C47/C$106 -> #DIV/0! | E47: =E46+D47 -> #DIV/0! | F47: =IF(AND(E47<=0),"C",IF(E47<=0.8,"A",IF(E47<=0.95,"B","C"))) -> #DIV/0! | G47: =VLOOKUP(B$4:B$104,I$4:M$104,5,0) -> #DIV/0! | I47: ww 1022 черн-серебро | K47: =J47/J$106 -> #DIV/0! | L47: =L46+K47 -> #DIV/0! | M47: =_xlfn.IFS(L47<80%,"A",L47<=95%,"B",L47>95%,"C") -> #DIV/0!
B48: ww 1022 желтые | D48: =C48/C$106 -> #DIV/0! | E48: =E47+D48 -> #DIV/0! | F48: =IF(AND(E48<=0),"C",IF(E48<=0.8,"A",IF(E48<=0.95,"B","C"))) -> #DIV/0! | G48: =VLOOKUP(B$4:B$104,I$4:M$104,5,0) -> #DIV/0! | I48: ww 1022 желтые | K48: =J48/J$106 -> #DIV/0! | L48: =L47+K48 -> #DIV/0! | M48: =_xlfn.IFS(L48<80%,"A",L48<=95%,"B",L48>95%,"C") -> #DIV/0!
B49: ww 1022 коричневые | D49: =C49/C$106 -> #DIV/0! | E49: =E48+D49 -> #DIV/0! | F49: =IF(AND(E49<=0),"C",IF(E49<=0.8,"A",IF(E49<=0.95,"B","C"))) -> #DIV/0! | G49: =VLOOKUP(B$4:B$104,I$4:M$104,5,0) -> #DIV/0! | I49: ww 1022 коричневые | K49: =J49/J$106 -> #DIV/0! | L49: =L48+K49 -> #DIV/0! | M49: =_xlfn.IFS(L49<80%,"A",L49<=95%,"B",L49>95%,"C") -> #DIV/0!
B50: ww 2018 черные | D50: =C50/C$106 -> #DIV/0! | E50: =E49+D50 -> #DIV/0! | F50: =IF(AND(E50<=0),"C",IF(E50<=0.8,"A",IF(E50<=0.95,"B","C"))) -> #DIV/0! | G50: =VLOOKUP(B$4:B$104,I$4:M$104,5,0) -> #DIV/0! | I50: ww 2018 черные | K50: =J50/J$106 -> #DIV/0! | L50: =L49+K50 -> #DIV/0! | M50: =_xlfn.IFS(L50<80%,"A",L50<=95%,"B",L50>95%,"C") -> #DIV/0!
B51: ww 2018 желтые | D51: =C51/C$106 -> #DIV/0! | E51: =E50+D51 -> #DIV/0! | F51: =IF(AND(E51<=0),"C",IF(E51<=0.8,"A",IF(E51<=0.95,"B","C"))) -> #DIV/0! | G51: =VLOOKUP(B$4:B$104,I$4:M$104,5,0) -> #DIV/0! | I51: ww 2018 желтые | K51: =J51/J$106 -> #DIV/0! | L51: =L50+K51 -> #DIV/0! | M51: =_xlfn.IFS(L51<80%,"A",L51<=95%,"B",L51>95%,"C") -> #DIV/0!
... B75: MANNA2121 | D75: =C75/C$106 -> #DIV/0! | E75: =E74+D75 -> #DIV/0! | F75: =IF(AND(E75<=0),"C",IF(E75<=0.8,"A",IF(E75<=0.95,"B","C"))) -> #DIV/0! | G75: =VLOOKUP(B$4:B$104,I$4:M$104,5,0) -> #DIV/0! | I75: MANNA2121 | K75: =J75/J$106 -> #DIV/0! | L75: =L74+K75 -> #DIV/0! | M75: =_xlfn.IFS(L75<80%,"A",L75<=95%,"B",L75>95%,"C") -> #DIV/0!
B76: MANNA2122 | D76: =C76/C$106 -> #DIV/0! | E76: =E49+D76 -> #DIV/0! | F76: =IF(AND(E76<=0),"C",IF(E76<=0.8,"A",IF(E76<=0.95,"B","C"))) -> #DIV/0! | G76: =VLOOKUP(B$4:B$104,I$4:M$104,5,0) -> #DIV/0! | I76: MANNA2122 | K76: =J76/J$106 -> #DIV/0! | L76: =L49+K76 -> #DIV/0! | M76: =_xlfn.IFS(L76<80%,"A",L76<=95%,"B",L76>95%,"C") -> #DIV/0!
B77: Chenlong черные | D77: =C77/C$106 -> #DIV/0! | E77: =E76+D77 -> #DIV/0! | F77: =IF(AND(E77<=0),"C",IF(E77<=0.8,"A",IF(E77<=0.95,"B","C"))) -> #DIV/0! | G77: =VLOOKUP(B$4:B$104,I$4:M$104,5,0) -> #DIV/0! | I77: Chenlong черные | K77: =J77/J$106 -> #DIV/0! | L77: =L76+K77 -> #DIV/0! | M77: =_xlfn.IFS(L77<80%,"A",L77<=95%,"B",L77>95%,"C") -> #DIV/0!
B78: Chenlong коричневые | D78: =C78/C$106 -> #DIV/0! | E78: =E77+D78 -> #DIV/0! | F78: =IF(AND(E78<=0),"C",IF(E78<=0.8,"A",IF(E78<=0.95,"B","C"))) -> #DIV/0! | G78: =VLOOKUP(B$4:B$104,I$4:M$104,5,0) -> #DIV/0! | I78: Chenlong коричневые | K78: =J78/J$106 -> #DIV/0! | L78: =L77+K78 -> #DIV/0! | M78: =_xlfn.IFS(L78<80%,"A",L78<=95%,"B",L78>95%,"C") -> #DIV/0!
B79: Chenlong белые | D79: =C79/C$106 -> #DIV/0! | E79: =E78+D79 -> #DIV/0! | F79: =IF(AND(E79<=0),"C",IF(E79<=0.8,"A",IF(E79<=0.95,"B","C"))) -> #DIV/0! | G79: =VLOOKUP(B$4:B$104,I$4:M$104,5,0) -> #DIV/0! | I79: Chenlong белые | K79: =J79/J$106 -> #DIV/0! | L79: =L78+K79 -> #DIV/0! | M79: =_xlfn.IFS(L79<80%,"A",L79<=95%,"B",L79>95%,"C") -> #DIV/0!
B80: Guangdu золото серая линза | D80: =C80/C$106 -> #DIV/0! | E80: =E79+D80 -> #DIV/0! | F80: =IF(AND(E80<=0),"C",IF(E80<=0.8,"A",IF(E80<=0.95,"B","C"))) -> #DIV/0! | G80: =VLOOKUP(B$4:B$104,I$4:M$104,5,0) -> #DIV/0! | I80: Guangdu золото серая линза | K80: =J80/J$106 -> #DIV/0! | L80: =L79+K80 -> #DIV/0! | M80: =_xlfn.IFS(L80<80%,"A",L80<=95%,"B",L80>95%,"C") -> #DIV/0!
B81: Guangdu серебро серая линза | D81: =C81/C$106 -> #DIV/0! | E81: =E80+D81 -> #DIV/0! | F81: =IF(AND(E81<=0),"C",IF(E81<=0.8,"A",IF(E81<=0.95,"B","C"))) -> #DIV/0! | G81: =VLOOKUP(B$4:B$104,I$4:M$104,5,0) -> #DIV/0! | I81: Guangdu серебро серая линза | K81: =J81/J$106 -> #DIV/0! | L81: =L80+K81 -> #DIV/0! | M81: =_xlfn.IFS(L81<80%,"A",L81<=95%,"B",L81>95%,"C") -> #DIV/0!
B82: Hengda Optical черные | D82: =C82/C$106 -> #DIV/0! | E82: =E81+D82 -> #DIV/0! | F82: =IF(AND(E82<=0),"C",IF(E82<=0.8,"A",IF(E82<=0.95,"B","C"))) -> #DIV/0! | G82: =VLOOKUP(B$4:B$104,I$4:M$104,5,0) -> #DIV/0! | I82: Hengda Optical черные | K82: =J82/J$106 -> #DIV/0! | L82: =L81+K82 -> #DIV/0! | M82: =_xlfn.IFS(L82<80%,"A",L82<=95%,"B",L82>95%,"C") -> #DIV/0!
B83: Hengda Optical леопард | D83: =C83/C$106 -> #DIV/0! | E83: =E82+D83 -> #DIV/0! | F83: =IF(AND(E83<=0),"C",IF(E83<=0.8,"A",IF(E83<=0.95,"B","C"))) -> #DIV/0! | G83: =VLOOKUP(B$4:B$104,I$4:M$104,5,0) -> #DIV/0! | I83: Hengda Optical леопард | K83: =J83/J$106 -> #DIV/0! | L83: =L82+K83 -> #DIV/0! | M83: =_xlfn.IFS(L83<80%,"A",L83<=95%,"B",L83>95%,"C") -> #DIV/0!
B84: Qianai черные | D84: =C84/C$106 -> #DIV/0! | E84: =E83+D84 -> #DIV/0! | F84: =IF(AND(E84<=0),"C",IF(E84<=0.8,"A",IF(E84<=0.95,"B","C"))) -> #DIV/0! | G84: =VLOOKUP(B$4:B$104,I$4:M$104,5,0) -> #DIV/0! | I84: Qianai черные | K84: =J84/J$106 -> #DIV/0! | L84: =L83+K84 -> #DIV/0! | M84: =_xlfn.IFS(L84<80%,"A",L84<=95%,"B",L84>95%,"C") -> #DIV/0!
B85: Qianai коричневые | D85: =C85/C$106 -> #DIV/0! | E85: =E84+D85 -> #DIV/0! | F85: =IF(AND(E85<=0),"C",IF(E85<=0.8,"A",IF(E85<=0.95,"B","C"))) -> #DIV/0! | G85: =VLOOKUP(B$4:B$104,I$4:M$104,5,0) -> #DIV/0! | I85: Qianai коричневые | K85: =J85/J$106 -> #DIV/0! | L85: =L84+K85 -> #DIV/0! | M85: =_xlfn.IFS(L85<80%,"A",L85<=95%,"B",L85>95%,"C") -> #DIV/0!
B86: Keming Aishi коричневые | D86: =C86/C$106 -> #DIV/0! | E86: =E85+D86 -> #DIV/0! | F86: =IF(AND(E86<=0),"C",IF(E86<=0.8,"A",IF(E86<=0.95,"B","C"))) -> #DIV/0! | G86: =VLOOKUP(B$4:B$104,I$4:M$104,5,0) -> #DIV/0! | I86: Keming Aishi коричневые | K86: =J86/J$106 -> #DIV/0! | L86: =L85+K86 -> #DIV/0! | M86: =_xlfn.IFS(L86<80%,"A",L86<=95%,"B",L86>95%,"C") -> #DIV/0!
B87: Linhai Baiyi коричневая линза | D87: =C87/C$106 -> #DIV/0! | E87: =E86+D87 -> #DIV/0! | F87: =IF(AND(E87<=0),"C",IF(E87<=0.8,"A",IF(E87<=0.95,"B","C"))) -> #DIV/0! | G87: =VLOOKUP(B$4:B$104,I$4:M$104,5,0) -> #DIV/0! | I87: Linhai Baiyi коричневая линза | K87: =J87/J$106 -> #DIV/0! | L87: =L86+K87 -> #DIV/0! | M87: =_xlfn.IFS(L87<80%,"A",L87<=95%,"B",L87>95%,"C") -> #DIV/0!
B88: Linhai Baiyi серая линза | D88: =C88/C$106 -> #DIV/0! | E88: =E87+D88 -> #DIV/0! | F88: =IF(AND(E88<=0),"C",IF(E88<=0.8,"A",IF(E88<=0.95,"B","C"))) -> #DIV/0! | G88: =VLOOKUP(B$4:B$104,I$4:M$104,5,0) -> #DIV/0! | I88: Linhai Baiyi серая линза | K88: =J88/J$106 -> #DIV/0! | L88: =L87+K88 -> #DIV/0! | M88: =_xlfn.IFS(L88<80%,"A",L88<=95%,"B",L88>95%,"C") -> #DIV/0!
... B98: POMILED 08247 C4-08 | D98: =C98/C$106 -> #DIV/0! | E98: =E97+D98 -> #DIV/0! | F98: =IF(AND(E98<=0),"C",IF(E98<=0.8,"A",IF(E98<=0.95,"B","C"))) -> #DIV/0! | G98: =VLOOKUP(B$4:B$104,I$4:M$104,5,0) -> #DIV/0! | I98: POMILED 08247 C4-08 | K98: =J98/J$106 -> #DIV/0! | L98: =L97+K98 -> #DIV/0! | M98: =_xlfn.IFS(L98<80%,"A",L98<=95%,"B",L98>95%,"C") -> #DIV/0!
B99: YIMEI 2391 C1 | D99: =C99/C$106 -> #DIV/0! | E99: =E93+D99 -> #DIV/0! | F99: =IF(AND(E99<=0),"C",IF(E99<=0.8,"A",IF(E99<=0.95,"B","C"))) -> #DIV/0! | G99: =VLOOKUP(B$4:B$104,I$4:M$104,5,0) -> #DIV/0! | I99: YIMEI 2391 C1 | K99: =J99/J$106 -> #DIV/0! | L99: =L93+K99 -> #DIV/0! | M99: =_xlfn.IFS(L99<80%,"A",L99<=95%,"B",L99>95%,"C") -> #DIV/0!
B100: ЧСЖ_тест | D100: =C100/C$106 -> #DIV/0! | E100: =E94+D100 -> #DIV/0! | F100: =IF(AND(E100<=0),"C",IF(E100<=0.8,"A",IF(E100<=0.95,"B","C"))) -> #DIV/0! | G100: =VLOOKUP(B$4:B$104,I$4:M$104,5,0) -> #DIV/0! | I100: ЧСЖ_тест | K100: =J100/J$106 -> #DIV/0! | L100: =L94+K100 -> #DIV/0! | M100: =_xlfn.IFS(L100<80%,"A",L100<=95%,"B",L100>95%,"C") -> #DIV/0!
B101: ЧСЖ_женские | D101: =C101/C$106 -> #DIV/0! | E101: =E95+D101 -> #DIV/0! | F101: =IF(AND(E101<=0),"C",IF(E101<=0.8,"A",IF(E101<=0.95,"B","C"))) -> #DIV/0! | G101: =VLOOKUP(B$4:B$104,I$4:M$104,5,0) -> #DIV/0! | I101: ЧСЖ_женские | K101: =J101/J$106 -> #DIV/0! | L101: =L95+K101 -> #DIV/0! | M101: =_xlfn.IFS(L101<80%,"A",L101<=95%,"B",L101>95%,"C") -> #DIV/0!
B102: кс_черные_тест | D102: =C102/C$106 -> #DIV/0! | E102: =E96+D102 -> #DIV/0! | F102: =IF(AND(E102<=0),"C",IF(E102<=0.8,"A",IF(E102<=0.95,"B","C"))) -> #DIV/0! | G102: =VLOOKUP(B$4:B$104,I$4:M$104,5,0) -> #DIV/0! | I102: кс_черные_тест | K102: =J102/J$106 -> #DIV/0! | L102: =L96+K102 -> #DIV/0! | M102: =_xlfn.IFS(L102<80%,"A",L102<=95%,"B",L102>95%,"C") -> #DIV/0!
B103: кс_черные_женские | D103: =C103/C$106 -> #DIV/0! | E103: =E97+D103 -> #DIV/0! | F103: =IF(AND(E103<=0),"C",IF(E103<=0.8,"A",IF(E103<=0.95,"B","C"))) -> #DIV/0! | G103: =VLOOKUP(B$4:B$104,I$4:M$104,5,0) -> #DIV/0! | I103: кс_черные_женские | K103: =J103/J$106 -> #DIV/0! | L103: =L97+K103 -> #DIV/0! | M103: =_xlfn.IFS(L103<80%,"A",L103<=95%,"B",L103>95%,"C") -> #DIV/0!
B104: 1022_коричневые_тест | D104: =C104/C$106 -> #DIV/0! | E104: =E98+D104 -> #DIV/0! | F104: =IF(AND(E104<=0),"C",IF(E104<=0.8,"A",IF(E104<=0.95,"B","C"))) -> #DIV/0! | G104: =VLOOKUP(B$4:B$104,I$4:M$104,5,0) -> #DIV/0! | I104: 1022_коричневые_тест | K104: =J104/J$106 -> #DIV/0! | L104: =L98+K104 -> #DIV/0! | M104: =_xlfn.IFS(L104<80%,"A",L104<=95%,"B",L104>95%,"C") -> #DIV/0!
B105: ridges brand 01 | D105: =C105/C$106 -> #DIV/0! | E105: =E99+D105 -> #DIV/0! | F105: =IF(AND(E105<=0),"C",IF(E105<=0.8,"A",IF(E105<=0.95,"B","C"))) -> #DIV/0! | G105: =VLOOKUP(B$4:B$104,I$4:M$104,5,0) -> #VALUE! | I105: ridges brand 01 | K105: =J105/J$106 -> #DIV/0! | L105: =L99+K105 -> #DIV/0! | M105: =_xlfn.IFS(L105<80%,"A",L105<=95%,"B",L105>95%,"C") -> #DIV/0!
C106: =SUM(C4:C104) -> 0 | D106: =SUM(D4:D105) -> #DIV/0! | J106: =SUM(J4:J104) -> 0 | K106: =SUM(K4:K105) -> #DIV/0!

Sheet АВС 17
B2: ОЧКИ
C3: Прибыль | D3: % прибыль | E3: Доля | F3: ABC прибыль | G3: ABC кол-во | J3: Кол-во | K3: % кол-во | L3: Доля | M3: ABC кол-во
B4: QS черные PZ | C4: ='Юнит 17'!AO4 -> 123838.64 | D4: =C4/C$106 -> 0.21881256 | E4: =D4 -> 0.21881256 | F4: =IF(AND(E4<=0),"C",IF(E4<=0.8,"A",IF(E4<=0.95,"B","C"))) -> A | G4: =VLOOKUP(B$4:B$104,I$4:M$104,5,0) -> A | I4: QS черные PZ | J4: ='Юнит 17'!U4 -> 327 | K4: =J4/J$106 -> 0.19292035 | L4: =K4 -> 0.19292035 | M4: =_xlfn.IFS(L4<80%,"A",L4<=95%,"B",L4>95%,"C") -> A | P4: A | Q4: 0.8
B5: flip коричневые | C5: ='Юнит 17'!AO16 -> 61360.969 | D5: =C5/C$106 -> 0.10841973 | E5: =E4+D5 -> 0.32723229 | F5: =IF(AND(E5<=0),"C",IF(E5<=0.8,"A",IF(E5<=0.95,"B","C"))) -> A | G5: =VLOOKUP(B$4:B$104,I$4:M$104,5,0) -> A | I5: flip черные | J5: ='Юнит 17'!U13 -> 184 | K5: =J5/J$106 -> 0.10855457 | L5: =L4+K5 -> 0.30147493 | M5: =_xlfn.IFS(L5<80%,"A",L5<=95%,"B",L5>95%,"C") -> A | P5: B | Q5: 0.15
B6: flip черные | C6: ='Юнит 17'!AO13 -> 43494.59 | D6: =C6/C$106 -> 0.076851321 | E6: =E5+D6 -> 0.40408361 | F6: =IF(AND(E6<=0),"C",IF(E6<=0.8,"A",IF(E6<=0.95,"B","C"))) -> A | G6: =VLOOKUP(B$4:B$104,I$4:M$104,5,0) -> A | I6: th черн | J6: ='Юнит 17'!U9 -> 156 | K6: =J6/J$106 -> 0.092035398 | L6: =L5+K6 -> 0.39351032 | M6: =_xlfn.IFS(L6<80%,"A",L6<=95%,"B",L6>95%,"C") -> A | P6: C | Q6: 0.05
B7: th черн | C7: ='Юнит 17'!AO9 -> 39870.964 | D7: =C7/C$106 -> 0.070448675 | E7: =E6+D7 -> 0.47453229 | F7: =IF(AND(E7<=0),"C",IF(E7<=0.8,"A",IF(E7<=0.95,"B","C"))) -> A | G7: =VLOOKUP(B$4:B$104,I$4:M$104,5,0) -> A | I7: flip коричневые | J7: ='Юнит 17'!U16 -> 135 | K7: =J7/J$106 -> 0.079646018 | L7: =L6+K7 -> 0.47315634 | M7: =_xlfn.IFS(L7<80%,"A",L7<=95%,"B",L7>95%,"C") -> A
B8: QS синие PZ | C8: ='Юнит 17'!AO5 -> 33241.337 | D8: =C8/C$106 -> 0.058734677 | E8: =E7+D8 -> 0.53326696 | F8: =IF(AND(E8<=0),"C",IF(E8<=0.8,"A",IF(E8<=0.95,"B","C"))) -> A | G8: =VLOOKUP(B$4:B$104,I$4:M$104,5,0) -> A | I8: th син | J8: ='Юнит 17'!U10 -> 110 | K8: =J8/J$106 -> 0.064896755 | L8: =L7+K8 -> 0.5380531 | M8: =_xlfn.IFS(L8<80%,"A",L8<=95%,"B",L8>95%,"C") -> A
B9: QS коричневые PZ | C9: ='Юнит 17'!AO7 -> 32082.786 | D9: =C9/C$106 -> 0.056687613 | E9: =E8+D9 -> 0.58995458 | F9: =IF(AND(E9<=0),"C",IF(E9<=0.8,"A",IF(E9<=0.95,"B","C"))) -> A | G9: =VLOOKUP(B$4:B$104,I$4:M$104,5,0) -> A | I9: черные с железкой классика | J9: ='Юнит 17'!U3 -> 101 | K9: =J9/J$106 -> 0.059587021 | L9: =L8+K9 -> 0.59764012 | M9: =_xlfn.IFS(L9<80%,"A",L9<=95%,"B",L9>95%,"C") -> A
B10: th коричн | C10: ='Юнит 17'!AO12 -> 31242.105 | D10: =C10/C$106 -> 0.0552022 | E10: =E9+D10 -> 0.64515678 | F10: =IF(AND(E10<=0),"C",IF(E10<=0.8,"A",IF(E10<=0.95,"B","C"))) -> A | G10: =VLOOKUP(B$4:B$104,I$4:M$104,5,0) -> A | I10: QS синие PZ | J10: ='Юнит 17'!U5 -> 89 | K10: =J10/J$106 -> 0.052507375 | L10: =L9+K10 -> 0.65014749 | M10: =_xlfn.IFS(L10<80%,"A",L10<=95%,"B",L10>95%,"C") -> A
B11: черные с железкой классика | C11: ='Юнит 17'!AO3 -> 26574.335 | D11: =C11/C$106 -> 0.046954639 | E11: =E10+D11 -> 0.69211141 | F11: =IF(AND(E11<=0),"C",IF(E11<=0.8,"A",IF(E11<=0.95,"B","C"))) -> A | G11: =VLOOKUP(B$4:B$104,I$4:M$104,5,0) -> A | I11: th коричн | J11: ='Юнит 17'!U12 -> 77 | K11: =J11/J$106 -> 0.045427729 | L11: =L10+K11 -> 0.69557522 | M11: =_xlfn.IFS(L11<80%,"A",L11<=95%,"B",L11>95%,"C") -> A
B12: th син | C12: ='Юнит 17'!AO10 -> 23782.119 | D12: =C12/C$106 -> 0.042021026 | E12: =E11+D12 -> 0.73413244 | F12: =IF(AND(E12<=0),"C",IF(E12<=0.8,"A",IF(E12<=0.95,"B","C"))) -> A | G12: =VLOOKUP(B$4:B$104,I$4:M$104,5,0) -> A | I12: QS коричневые PZ | J12: ='Юнит 17'!U7 -> 74 | K12: =J12/J$106 -> 0.043657817 | L12: =L11+K12 -> 0.73923304 | M12: =_xlfn.IFS(L12<80%,"A",L12<=95%,"B",L12>95%,"C") -> A
B13: QS желтые PZ | C13: ='Юнит 17'!AO6 -> 22574.93 | D13: =C13/C$106 -> 0.039888023 | E13: =E12+D13 -> 0.77402046 | F13: =IF(AND(E13<=0),"C",IF(E13<=0.8,"A",IF(E13<=0.95,"B","C"))) -> A | G13: =VLOOKUP(B$4:B$104,I$4:M$104,5,0) -> B | I13: th желт | J13: ='Юнит 17'!U11 -> 60 | K13: =J13/J$106 -> 0.03539823 | L13: =L12+K13 -> 0.77463127 | M13: =_xlfn.IFS(L13<80%,"A",L13<=95%,"B",L13>95%,"C") -> A
B14: th желт | C14: ='Юнит 17'!AO11 -> 20625.479 | D14: =C14/C$106 -> 0.036443505 | E14: =E13+D14 -> 0.81046397 | F14: =IF(AND(E14<=0),"C",IF(E14<=0.8,"A",IF(E14<=0.95,"B","C"))) -> B | G14: =VLOOKUP(B$4:B$104,I$4:M$104,5,0) -> A | I14: QS желтые PZ | J14: ='Юнит 17'!U6 -> 50 | K14: =J14/J$106 -> 0.029498525 | L14: =L13+K14 -> 0.80412979 | M14: =_xlfn.IFS(L14<80%,"A",L14<=95%,"B",L14>95%,"C") -> B
B15: flip желтые | C15: ='Юнит 17'!AO15 -> 20118.65 | D15: =C15/C$106 -> 0.03554798 | E15: =E14+D15 -> 0.84601195 | F15: =IF(AND(E15<=0),"C",IF(E15<=0.8,"A",IF(E15<=0.95,"B","C"))) -> B | G15: =VLOOKUP(B$4:B$104,I$4:M$104,5,0) -> B | I15: flip желтые | J15: ='Юнит 17'!U15 -> 43 | K15: =J15/J$106 -> 0.025368732 | L15: =L14+K15 -> 0.82949853 | M15: =_xlfn.IFS(L15<80%,"A",L15<=95%,"B",L15>95%,"C") -> B
B16: ridges brand 01 | C16: ='Юнит 17'!AO104 -> 19543.819 | D16: =C16/C$106 -> 0.034532302 | E16: =E15+D16 -> 0.88054425 | F16: =IF(AND(E16<=0),"C",IF(E16<=0.8,"A",IF(E16<=0.95,"B","C"))) -> B | G16: =VLOOKUP(B$4:B$104,I$4:M$104,5,0) -> C | I16: ww 1022 коричневые | J16: ='Юнит 17'!U48 -> 30 | K16: =J16/J$106 -> 0.017699115 | L16: =L15+K16 -> 0.84719764 | M16: =_xlfn.IFS(L16<80%,"A",L16<=95%,"B",L16>95%,"C") -> B
B17: wwl8032 коричневые золото | C17: ='Юнит 17'!AO17 -> 13512.606 | D17: =C17/C$106 -> 0.023875651 | E17: =E16+D17 -> 0.9044199 | F17: =IF(AND(E17<=0),"C",IF(E17<=0.8,"A",IF(E17<=0.95,"B","C"))) -> B | G17: =VLOOKUP(B$4:B$104,I$4:M$104,5,0) -> B | I17: wwl8032 коричневые золото | J17: ='Юнит 17'!U17 -> 27 | K17: =J17/J$106 -> 0.015929204 | L17: =L16+K17 -> 0.86312684 | M17: =_xlfn.IFS(L17<80%,"A",L17<=95%,"B",L17>95%,"C") -> B
B18: ww 2018 желтые | C18: ='Юнит 17'!AO50 -> 13346.652 | D18: =C18/C$106 -> 0.023582423 | E18: =E17+D18 -> 0.92800232 | F18: =IF(AND(E18<=0),"C",IF(E18<=0.8,"A",IF(E18<=0.95,"B","C"))) -> B | G18: =VLOOKUP(B$4:B$104,I$4:M$104,5,0) -> B | I18: ww 2018 желтые | J18: ='Юнит 17'!U50 -> 26 | K18: =J18/J$106 -> 0.015339233 | L18: =L17+K18 -> 0.87846608 | M18: =_xlfn.IFS(L18<80%,"A",L18<=95%,"B",L18>95%,"C") -> B
B19: ww 1022 коричневые | C19: ='Юнит 17'!AO48 -> 13296.046 | D19: =C19/C$106 -> 0.023493007 | E19: =E18+D19 -> 0.95149533 | F19: =IF(AND(E19<=0),"C",IF(E19<=0.8,"A",IF(E19<=0.95,"B","C"))) -> C | G19: =VLOOKUP(B$4:B$104,I$4:M$104,5,0) -> B | I19: ww 2018 черные | J19: ='Юнит 17'!U49 -> 23 | K19: =J19/J$106 -> 0.013569322 | L19: =L18+K19 -> 0.8920354 | M19: =_xlfn.IFS(L19<80%,"A",L19<=95%,"B",L19>95%,"C") -> B
B20: ww 2018 черные | C20: ='Юнит 17'!AO49 -> 10258.196 | D20: =C20/C$106 -> 0.018125379 | E20: =E19+D20 -> 0.96962071 | F20: =IF(AND(E20<=0),"C",IF(E20<=0.8,"A",IF(E20<=0.95,"B","C"))) -> C | G20: =VLOOKUP(B$4:B$104,I$4:M$104,5,0) -> B | I20: MR8854 C2 Жен | J20: ='Юнит 17'!U8 -> 22 | K20: =J20/J$106 -> 0.012979351 | L20: =L19+K20 -> 0.90501475 | M20: =_xlfn.IFS(L20<80%,"A",L20<=95%,"B",L20>95%,"C") -> B
B21: MR8854 C2 Жен | C21: ='Юнит 17'!AO8 -> 9350.0704 | D21: =C21/C$106 -> 0.016520796 | E21: =E20+D21 -> 0.98614151 | F21: =IF(AND(E21<=0),"C",IF(E21<=0.8,"A",IF(E21<=0.95,"B","C"))) -> C | G21: =VLOOKUP(B$4:B$104,I$4:M$104,5,0) -> B | I21: flip синие | J21: ='Юнит 17'!U14 -> 22 | K21: =J21/J$106 -> 0.012979351 | L21: =L20+K21 -> 0.9179941 | M21: =_xlfn.IFS(L21<80%,"A",L21<=95%,"B",L21>95%,"C") -> B
B22: flip синие | C22: ='Юнит 17'!AO14 -> 7721.7316 | D22: =C22/C$106 -> 0.013643657 | E22: =E21+D22 -> 0.99978516 | F22: =IF(AND(E22<=0),"C",IF(E22<=0.8,"A",IF(E22<=0.95,"B","C"))) -> C | G22: =VLOOKUP(B$4:B$104,I$4:M$104,5,0) -> B | I22: sh3 | J22: ='Юнит 17'!U28 -> 21 | K22: =J22/J$106 -> 0.012389381 | L22: =L21+K22 -> 0.93038348 | M22: =_xlfn.IFS(L22<80%,"A",L22<=95%,"B",L22>95%,"C") -> B
B23: ww 203 черные | C23: ='Юнит 17'!AO44 -> 5766.4422 | D23: =C23/C$106 -> 0.010188824 | E23: =E22+D23 -> 1.009974 | F23: =IF(AND(E23<=0),"C",IF(E23<=0.8,"A",IF(E23<=0.95,"B","C"))) -> C | G23: =VLOOKUP(B$4:B$104,I$4:M$104,5,0) -> B | I23: wwl8032 хром металл | J23: ='Юнит 17'!U18 -> 18 | K23: =J23/J$106 -> 0.010619469 | L23: =L22+K23 -> 0.94100295 | M23: =_xlfn.IFS(L23<80%,"A",L23<=95%,"B",L23>95%,"C") -> B
B24: sports зеленые | C24: ='Юнит 17'!AO21 -> 2379.5724 | D24: =C24/C$106 -> 0.0042045065 | E24: =E23+D24 -> 1.0141785 | F24: =IF(AND(E24<=0),"C",IF(E24<=0.8,"A",IF(E24<=0.95,"B","C"))) -> C | G24: =VLOOKUP(B$4:B$104,I$4:M$104,5,0) -> C | I24: ww 203 черные | J24: ='Юнит 17'!U44 -> 15 | K24: =J24/J$106 -> 0.0088495575 | L24: =L23+K24 -> 0.94985251 | M24: =_xlfn.IFS(L24<80%,"A",L24<=95%,"B",L24>95%,"C") -> B
B25: sports красные | C25: ='Юнит 17'!AO22 -> 1871.2509 | D25: =C25/C$106 -> 0.0033063447 | E25: =E24+D25 -> 1.0174848 | F25: =IF(AND(E25<=0),"C",IF(E25<=0.8,"A",IF(E25<=0.95,"B","C"))) -> C | G25: =VLOOKUP(B$4:B$104,I$4:M$104,5,0) -> C | I25: ww 1022 черные | J25: ='Юнит 17'!U45 -> 15 | K25: =J25/J$106 -> 0.0088495575 | L25: =L24+K25 -> 0.95870206 | M25: =_xlfn.IFS(L25<80%,"A",L25<=95%,"B",L25>95%,"C") -> C
B26: Linhai Baiyi серая линза | C26: ='Юнит 17'!AO87 -> 1390.4106 | D26: =C26/C$106 -> 0.0024567398 | E26: =E25+D26 -> 1.0199416 | F26: =IF(AND(E26<=0),"C",IF(E26<=0.8,"A",IF(E26<=0.95,"B","C"))) -> C | G26: =VLOOKUP(B$4:B$104,I$4:M$104,5,0) -> C | I26: ridges brand 01 | J26: ='Юнит 17'!U104 -> 15 | K26: =J26/J$106 -> 0.0088495575 | L26: =L25+K26 -> 0.96755162 | M26: =_xlfn.IFS(L26<80%,"A",L26<=95%,"B",L26>95%,"C") -> C
B27: ww 1022 желтые | C27: ='Юнит 17'!AO47 -> 1268.684 | D27: =C27/C$106 -> 0.0022416591 | E27: =E26+D27 -> 1.0221832 | F27: =IF(AND(E27<=0),"C",IF(E27<=0.8,"A",IF(E27<=0.95,"B","C"))) -> C | G27: =VLOOKUP(B$4:B$104,I$4:M$104,5,0) -> C | I27: sports зеленые | J27: ='Юнит 17'!U21 -> 5 | K27: =J27/J$106 -> 0.0029498525 | L27: =L26+K27 -> 0.97050147 | M27: =_xlfn.IFS(L27<80%,"A",L27<=95%,"B",L27>95%,"C") -> C
B28: sh1 | C28: ='Юнит 17'!AO26 -> 1184.0505 | D28: =C28/C$106 -> 0.0020921187 | E28: =E27+D28 -> 1.0242754 | F28: =IF(AND(E28<=0),"C",IF(E28<=0.8,"A",IF(E28<=0.95,"B","C"))) -> C | G28: =VLOOKUP(B$4:B$104,I$4:M$104,5,0) -> C | I28: Guangdu золото серая линза | J28: ='Юнит 17'!U79 -> 5 | K28: =J28/J$106 -> 0.0029498525 | L28: =L27+K28 -> 0.97345133 | M28: =_xlfn.IFS(L28<80%,"A",L28<=95%,"B",L28>95%,"C") -> C
B29: Guangdu золото серая линза | C29: ='Юнит 17'!AO79 -> 1060.8412 | D29: =C29/C$106 -> 0.0018744182 | E29: =E28+D29 -> 1.0261498 | F29: =IF(AND(E29<=0),"C",IF(E29<=0.8,"A",IF(E29<=0.95,"B","C"))) -> C | G29: =VLOOKUP(B$4:B$104,I$4:M$104,5,0) -> C | I29: sports красные | J29: ='Юнит 17'!U22 -> 4 | K29: =J29/J$106 -> 0.002359882 | L29: =L28+K29 -> 0.97581121 | M29: =_xlfn.IFS(L29<80%,"A",L29<=95%,"B",L29>95%,"C") -> C
B30: wwl8032 хром металл | C30: ='Юнит 17'!AO18 -> 950.01894 | D30: =C30/C$106 -> 0.0016786044 | E30: =E29+D30 -> 1.0278284 | F30: =IF(AND(E30<=0),"C",IF(E30<=0.8,"A",IF(E30<=0.95,"B","C"))) -> C | G30: =VLOOKUP(B$4:B$104,I$4:M$104,5,0) -> B | I30: sh1 | J30: ='Юнит 17'!U26 -> 4 | K30: =J30/J$106 -> 0.002359882 | L30: =L29+K30 -> 0.97817109 | M30: =_xlfn.IFS(L30<80%,"A",L30<=95%,"B",L30>95%,"C") -> C
B31: sports синие | C31: ='Юнит 17'!AO20 -> 868.60638 | D31: =C31/C$106 -> 0.0015347552 | E31: =E30+D31 -> 1.0293631 | F31: =IF(AND(E31<=0),"C",IF(E31<=0.8,"A",IF(E31<=0.95,"B","C"))) -> C | G31: =VLOOKUP(B$4:B$104,I$4:M$104,5,0) -> C | I31: Linhai Baiyi серая линза | J31: ='Юнит 17'!U87 -> 4 | K31: =J31/J$106 -> 0.002359882 | L31: =L30+K31 -> 0.98053097 | M31: =_xlfn.IFS(L31<80%,"A",L31<=95%,"B",L31>95%,"C") -> C
B32: sh19 | C32: ='Юнит 17'!AO43 -> 837.1619 | D32: =C32/C$106 -> 0.0014791954 | E32: =E31+D32 -> 1.0308423 | F32: =IF(AND(E32<=0),"C",IF(E32<=0.8,"A",IF(E32<=0.95,"B","C"))) -> C | G32: =VLOOKUP(B$4:B$104,I$4:M$104,5,0) -> C | I32: ww 1022 желтые | J32: ='Юнит 17'!U47 -> 3 | K32: =J32/J$106 -> 0.0017699115 | L32: =L31+K32 -> 0.98230088 | M32: =_xlfn.IFS(L32<80%,"A",L32<=95%,"B",L32>95%,"C") -> C
B33: Linhai Baiyi коричневая линза | C33: ='Юнит 17'!AO86 -> 724.22792 | D33: =C33/C$106 -> 0.0012796505 | E33: =E32+D33 -> 1.032122 | F33: =IF(AND(E33<=0),"C",IF(E33<=0.8,"A",IF(E33<=0.95,"B","C"))) -> C | G33: =VLOOKUP(B$4:B$104,I$4:M$104,5,0) -> C | I33: кс_черные_женские | J33: ='Юнит 17'!U102 -> 3 | K33: =J33/J$106 -> 0.0017699115 | L33: =L32+K33 -> 0.9840708 | M33: =_xlfn.IFS(L33<80%,"A",L33<=95%,"B",L33>95%,"C") -> C
B34: кс_черные_женские | C34: ='Юнит 17'!AO102 -> 703.48998 | D34: =C34/C$106 -> 0.0012430083 | E34: =E33+D34 -> 1.033365 | F34: =IF(AND(E34<=0),"C",IF(E34<=0.8,"A",IF(E34<=0.95,"B","C"))) -> C | G34: =VLOOKUP(B$4:B$104,I$4:M$104,5,0) -> C | I34: sports синие | J34: ='Юнит 17'!U20 -> 2 | K34: =J34/J$106 -> 0.001179941 | L34: =L33+K34 -> 0.98525074 | M34: =_xlfn.IFS(L34<80%,"A",L34<=95%,"B",L34>95%,"C") -> C
B35: MR Р1894 черные | C35: ='Юнит 17'!AO89 -> 575.79849 | D35: =C35/C$106 -> 0.001017388 | E35: =E34+D35 -> 1.0343824 | F35: =IF(AND(E35<=0),"C",IF(E35<=0.8,"A",IF(E35<=0.95,"B","C"))) -> C | G35: =VLOOKUP(B$4:B$104,I$4:M$104,5,0) -> C | I35: sh09 | J35: ='Юнит 17'!U33 -> 2 | K35: =J35/J$106 -> 0.001179941 | L35: =L34+K35 -> 0.98643068 | M35: =_xlfn.IFS(L35<80%,"A",L35<=95%,"B",L35>95%,"C") -> C
B36: sh09 | C36: ='Юнит 17'!AO33 -> 521.2412 | D36: =C36/C$106 -> 0.00092098984 | E36: =E35+D36 -> 1.0353034 | F36: =IF(AND(E36<=0),"C",IF(E36<=0.8,"A",IF(E36<=0.95,"B","C"))) -> C | G36: =VLOOKUP(B$4:B$104,I$4:M$104,5,0) -> C | I36: sh19 | J36: ='Юнит 17'!U43 -> 2 | K36: =J36/J$106 -> 0.001179941 | L36: =L35+K36 -> 0.98761062 | M36: =_xlfn.IFS(L36<80%,"A",L36<=95%,"B",L36>95%,"C") -> C
B37: ЧСЖ_женские | C37: ='Юнит 17'!AO100 -> 380.49118 | D37: =C37/C$106 -> 0.00067229626 | E37: =E36+D37 -> 1.0359757 | F37: =IF(AND(E37<=0),"C",IF(E37<=0.8,"A",IF(E37<=0.95,"B","C"))) -> C | G37: =VLOOKUP(B$4:B$104,I$4:M$104,5,0) -> C | I37: Linhai Baiyi коричневая линза | J37: ='Юнит 17'!U86 -> 2 | K37: =J37/J$106 -> 0.001179941 | L37: =L36+K37 -> 0.98879056 | M37: =_xlfn.IFS(L37<80%,"A",L37<=95%,"B",L37>95%,"C") -> C
B38: sportlife синие | C38: ='Юнит 17'!AO24 -> 341.25256 | D38: =C38/C$106 -> 0.00060296488 | E38: =E37+D38 -> 1.0365786 | F38: =IF(AND(E38<=0),"C",IF(E38<=0.8,"A",IF(E38<=0.95,"B","C"))) -> C | G38: =VLOOKUP(B$4:B$104,I$4:M$104,5,0) -> C | I38: Ли Сян ретро золото | J38: ='Юнит 17'!U92 -> 2 | K38: =J38/J$106 -> 0.001179941 | L38: =L37+K38 -> 0.9899705 | M38: =_xlfn.IFS(L38<80%,"A",L38<=95%,"B",L38>95%,"C") -> C
B39: sh17 | C39: ='Юнит 17'!AO41 -> 301.87036 | D39: =C39/C$106 -> 0.0005333798 | E39: =E35+D39 -> 1.0349158 | F39: =IF(AND(E39<=0),"C",IF(E39<=0.8,"A",IF(E39<=0.95,"B","C"))) -> C | G39: =VLOOKUP(B$4:B$104,I$4:M$104,5,0) -> C | I39: YIMEI 2391 C1 | J39: ='Юнит 17'!U98 -> 2 | K39: =J39/J$106 -> 0.001179941 | L39: =L35+K39 -> 0.98761062 | M39: =_xlfn.IFS(L39<80%,"A",L39<=95%,"B",L39>95%,"C") -> C
B40: MANNA2107 | C40: ='Юнит 17'!AO60 -> 301.47674 | D40: =C40/C$106 -> 0.00053268431 | E40: =E39+D40 -> 1.0354484 | F40: =IF(AND(E40<=0),"C",IF(E40<=0.8,"A",IF(E40<=0.95,"B","C"))) -> C | G40: =VLOOKUP(B$4:B$104,I$4:M$104,5,0) -> C | I40: sportlife синие | J40: ='Юнит 17'!U24 -> 1 | K40: =J40/J$106 -> 0.0005899705 | L40: =L39+K40 -> 0.98820059 | M40: =_xlfn.IFS(L40<80%,"A",L40<=95%,"B",L40>95%,"C") -> C
B41: YIMEI 2391 C1 | C41: ='Юнит 17'!AO98 -> 225.18053 | D41: =C41/C$106 -> 0.00039787526 | E41: =E40+D41 -> 1.0358463 | F41: =IF(AND(E41<=0),"C",IF(E41<=0.8,"A",IF(E41<=0.95,"B","C"))) -> C | G41: =VLOOKUP(B$4:B$104,I$4:M$104,5,0) -> C | I41: sh2 | J41: ='Юнит 17'!U27 -> 1 | K41: =J41/J$106 -> 0.0005899705 | L41: =L40+K41 -> 0.98879056 | M41: =_xlfn.IFS(L41<80%,"A",L41<=95%,"B",L41>95%,"C") -> C
B42: MANNA2116 | C42: ='Юнит 17'!AO69 -> 206.1901 | D42: =C42/C$106 -> 0.00036432075 | E42: =E41+D42 -> 1.0362106 | F42: =IF(AND(E42<=0),"C",IF(E42<=0.8,"A",IF(E42<=0.95,"B","C"))) -> C | G42: =VLOOKUP(B$4:B$104,I$4:M$104,5,0) -> C | I42: sh10 | J42: ='Юнит 17'!U34 -> 1 | K42: =J42/J$106 -> 0.0005899705 | L42: =L41+K42 -> 0.98938053 | M42: =_xlfn.IFS(L42<80%,"A",L42<=95%,"B",L42>95%,"C") -> C
B43: MANNA2120 | C43: ='Юнит 17'!AO73 -> 205.75399 | D43: =C43/C$106 -> 0.00036355017 | E43: =E42+D43 -> 1.0365742 | F43: =IF(AND(E43<=0),"C",IF(E43<=0.8,"A",IF(E43<=0.95,"B","C"))) -> C | G43: =VLOOKUP(B$4:B$104,I$4:M$104,5,0) -> C | I43: sh15 | J43: ='Юнит 17'!U39 -> 1 | K43: =J43/J$106 -> 0.0005899705 | L43: =L42+K43 -> 0.9899705 | M43: =_xlfn.IFS(L43<80%,"A",L43<=95%,"B",L43>95%,"C") -> C
B44: sh15 | C44: ='Юнит 17'!AO39 -> 199.92984 | D44: =C44/C$106 -> 0.0003532594 | E44: =E43+D44 -> 1.0369274 | F44: =IF(AND(E44<=0),"C",IF(E44<=0.8,"A",IF(E44<=0.95,"B","C"))) -> C | G44: =VLOOKUP(B$4:B$104,I$4:M$104,5,0) -> C | I44: sh17 | J44: ='Юнит 17'!U41 -> 1 | K44: =J44/J$106 -> 0.0005899705 | L44: =L43+K44 -> 0.99056047 | M44: =_xlfn.IFS(L44<80%,"A",L44<=95%,"B",L44>95%,"C") -> C
B45: MANNA2101 | C45: ='Юнит 17'!AO54 -> 156.10391 | D45: =C45/C$106 -> 0.00027582261 | E45: =E44+D45 -> 1.0372033 | F45: =IF(AND(E45<=0),"C",IF(E45<=0.8,"A",IF(E45<=0.95,"B","C"))) -> C | G45: =VLOOKUP(B$4:B$104,I$4:M$104,5,0) -> C | I45: WW 3055 черный | J45: ='Юнит 17'!U52 -> 1 | K45: =J45/J$106 -> 0.0005899705 | L45: =L44+K45 -> 0.99115044 | M45: =_xlfn.IFS(L45<80%,"A",L45<=95%,"B",L45>95%,"C") -> C
B46: Chenlong белые | C46: ='Юнит 17'!AO78 -> 139.1265 | D46: =C46/C$106 -> 0.00024582495 | E46: =E45+D46 -> 1.0374491 | F46: =IF(AND(E46<=0),"C",IF(E46<=0.8,"A",IF(E46<=0.95,"B","C"))) -> C | G46: =VLOOKUP(B$4:B$104,I$4:M$104,5,0) -> C | I46: MANNA2101 | J46: ='Юнит 17'!U54 -> 1 | K46: =J46/J$106 -> 0.0005899705 | L46: =L45+K46 -> 0.99174041 | M46: =_xlfn.IFS(L46<80%,"A",L46<=95%,"B",L46>95%,"C") -> C
B47: Qianai коричневые | C47: ='Юнит 17'!AO84 -> 84.524557 | D47: =C47/C$106 -> 0.00014934786 | E47: =E46+D47 -> 1.0375984 | F47: =IF(AND(E47<=0),"C",IF(E47<=0.8,"A",IF(E47<=0.95,"B","C"))) -> C | G47: =VLOOKUP(B$4:B$104,I$4:M$104,5,0) -> C | I47: MANNA2107 | J47: ='Юнит 17'!U60 -> 1 | K47: =J47/J$106 -> 0.0005899705 | L47: =L46+K47 -> 0.99233038 | M47: =_xlfn.IFS(L47<80%,"A",L47<=95%,"B",L47>95%,"C") -> C
B48: sh10 | C48: ='Юнит 17'!AO34 -> 75.8104 | D48: =C48/C$106 -> 0.00013395067 | E48: =E47+D48 -> 1.0377324 | F48: =IF(AND(E48<=0),"C",IF(E48<=0.8,"A",IF(E48<=0.95,"B","C"))) -> C | G48: =VLOOKUP(B$4:B$104,I$4:M$104,5,0) -> C | I48: MANNA2116 | J48: ='Юнит 17'!U69 -> 1 | K48: =J48/J$106 -> 0.0005899705 | L48: =L47+K48 -> 0.99292035 | M48: =_xlfn.IFS(L48<80%,"A",L48<=95%,"B",L48>95%,"C") -> C
B49: wwl8032 черные серебро | C49: ='Юнит 17'!AO19 -> 0 | D49: =C49/C$106 -> 0 | E49: =E48+D49 -> 1.0377324 | F49: =IF(AND(E49<=0),"C",IF(E49<=0.8,"A",IF(E49<=0.95,"B","C"))) -> C | G49: =VLOOKUP(B$4:B$104,I$4:M$104,5,0) -> C | I49: MANNA2120 | J49: ='Юнит 17'!U73 -> 1 | K49: =J49/J$106 -> 0.0005899705 | L49: =L48+K49 -> 0.99351032 | M49: =_xlfn.IFS(L49<80%,"A",L49<=95%,"B",L49>95%,"C") -> C
B50: sportlife черные | C50: ='Юнит 17'!AO23 -> 0 | D50: =C50/C$106 -> 0 | E50: =E49+D50 -> 1.0377324 | F50: =IF(AND(E50<=0),"C",IF(E50<=0.8,"A",IF(E50<=0.95,"B","C"))) -> C | G50: =VLOOKUP(B$4:B$104,I$4:M$104,5,0) -> C | I50: MANNA2122 | J50: ='Юнит 17'!U75 -> 1 | K50: =J50/J$106 -> 0.0005899705 | L50: =L49+K50 -> 0.99410029 | M50: =_xlfn.IFS(L50<80%,"A",L50<=95%,"B",L50>95%,"C") -> C
B51: sportlife красные | C51: ='Юнит 17'!AO25 -> 0 | D51: =C51/C$106 -> 0 | E51: =E50+D51 -> 1.0377324 | F51: =IF(AND(E51<=0),"C",IF(E51<=0.8,"A",IF(E51<=0.95,"B","C"))) -> C | G51: =VLOOKUP(B$4:B$104,I$4:M$104,5,0) -> C | I51: Chenlong коричневые | J51: ='Юнит 17'!U77 -> 1 | K51: =J51/J$106 -> 0.0005899705 | L51: =L50+K51 -> 0.99469027 | M51: =_xlfn.IFS(L51<80%,"A",L51<=95%,"B",L51>95%,"C") -> C
B52: sh4 | C52: ='Юнит 17'!AO29 -> 0 | D52: =C52/C$106 -> 0 | E52: =E51+D52 -> 1.0377324 | F52: =IF(AND(E52<=0),"C",IF(E52<=0.8,"A",IF(E52<=0.95,"B","C"))) -> C | G52: =VLOOKUP(B$4:B$104,I$4:M$104,5,0) -> C | I52: Chenlong белые | J52: ='Юнит 17'!U78 -> 1 | K52: =J52/J$106 -> 0.0005899705 | L52: =L51+K52 -> 0.99528024 | M52: =_xlfn.IFS(L52<80%,"A",L52<=95%,"B",L52>95%,"C") -> C
B53: sh06 | C53: ='Юнит 17'!AO30 -> 0 | D53: =C53/C$106 -> 0 | E53: =E52+D53 -> 1.0377324 | F53: =IF(AND(E53<=0),"C",IF(E53<=0.8,"A",IF(E53<=0.95,"B","C"))) -> C | G53: =VLOOKUP(B$4:B$104,I$4:M$104,5,0) -> C | I53: Qianai коричневые | J53: ='Юнит 17'!U84 -> 1 | K53: =J53/J$106 -> 0.0005899705 | L53: =L52+K53 -> 0.99587021 | M53: =_xlfn.IFS(L53<80%,"A",L53<=95%,"B",L53>95%,"C") -> C
B54: sh07 | C54: ='Юнит 17'!AO31 -> 0 | D54: =C54/C$106 -> 0 | E54: =E53+D54 -> 1.0377324 | F54: =IF(AND(E54<=0),"C",IF(E54<=0.8,"A",IF(E54<=0.95,"B","C"))) -> C | G54: =VLOOKUP(B$4:B$104,I$4:M$104,5,0) -> C | I54: MR Р1894 черные | J54: ='Юнит 17'!U89 -> 1 | K54: =J54/J$106 -> 0.0005899705 | L54: =L53+K54 -> 0.99646018 | M54: =_xlfn.IFS(L54<80%,"A",L54<=95%,"B",L54>95%,"C") -> C
B55: sh08 | C55: ='Юнит 17'!AO32 -> 0 | D55: =C55/C$106 -> 0 | E55: =E54+D55 -> 1.0377324 | F55: =IF(AND(E55<=0),"C",IF(E55<=0.8,"A",IF(E55<=0.95,"B","C"))) -> C | G55: =VLOOKUP(B$4:B$104,I$4:M$104,5,0) -> C | I55: Иу Диту серый | J55: ='Юнит 17'!U91 -> 1 | K55: =J55/J$106 -> 0.0005899705 | L55: =L54+K55 -> 0.99705015 | M55: =_xlfn.IFS(L55<80%,"A",L55<=95%,"B",L55>95%,"C") -> C
B56: sh11 | C56: ='Юнит 17'!AO35 -> 0 | D56: =C56/C$106 -> 0 | E56: =E55+D56 -> 1.0377324 | F56: =IF(AND(E56<=0),"C",IF(E56<=0.8,"A",IF(E56<=0.95,"B","C"))) -> C | G56: =VLOOKUP(B$4:B$104,I$4:M$104,5,0) -> C | I56: ЧСЖ_женские | J56: ='Юнит 17'!U100 -> 1 | K56: =J56/J$106 -> 0.0005899705 | L56: =L55+K56 -> 0.99764012 | M56: =_xlfn.IFS(L56<80%,"A",L56<=95%,"B",L56>95%,"C") -> C
B57: sh12 | C57: ='Юнит 17'!AO36 -> 0 | D57: =C57/C$106 -> 0 | E57: =E56+D57 -> 1.0377324 | F57: =IF(AND(E57<=0),"C",IF(E57<=0.8,"A",IF(E57<=0.95,"B","C"))) -> C | G57: =VLOOKUP(B$4:B$104,I$4:M$104,5,0) -> C | I57: wwl8032 черные серебро | J57: ='Юнит 17'!U19 -> 0 | K57: =J57/J$106 -> 0 | L57: =L56+K57 -> 0.99764012 | M57: =_xlfn.IFS(L57<80%,"A",L57<=95%,"B",L57>95%,"C") -> C
B58: ww 1022 черн-серебро | C58: ='Юнит 17'!AO46 -> 0 | D58: =C58/C$106 -> 0 | E58: =E57+D58 -> 1.0377324 | F58: =IF(AND(E58<=0),"C",IF(E58<=0.8,"A",IF(E58<=0.95,"B","C"))) -> C | G58: =VLOOKUP(B$4:B$104,I$4:M$104,5,0) -> C | I58: sportlife черные | J58: ='Юнит 17'!U23 -> 0 | K58: =J58/J$106 -> 0 | L58: =L57+K58 -> 0.99764012 | M58: =_xlfn.IFS(L58<80%,"A",L58<=95%,"B",L58>95%,"C") -> C
B59: MANNA2103 | C59: ='Юнит 17'!AO56 -> 0 | D59: =C59/C$106 -> 0 | E59: =E58+D59 -> 1.0377324 | F59: =IF(AND(E59<=0),"C",IF(E59<=0.8,"A",IF(E59<=0.95,"B","C"))) -> C | G59: =VLOOKUP(B$4:B$104,I$4:M$104,5,0) -> C | I59: sportlife красные | J59: ='Юнит 17'!U25 -> 0 | K59: =J59/J$106 -> 0 | L59: =L58+K59 -> 0.99764012 | M59: =_xlfn.IFS(L59<80%,"A",L59<=95%,"B",L59>95%,"C") -> C
B60: MANNA2104 | C60: ='Юнит 17'!AO57 -> 0 | D60: =C60/C$106 -> 0 | E60: =E59+D60 -> 1.0377324 | F60: =IF(AND(E60<=0),"C",IF(E60<=0.8,"A",IF(E60<=0.95,"B","C"))) -> C | G60: =VLOOKUP(B$4:B$104,I$4:M$104,5,0) -> C | I60: sh4 | J60: ='Юнит 17'!U29 -> 0 | K60: =J60/J$106 -> 0 | L60: =L59+K60 -> 0.99764012 | M60: =_xlfn.IFS(L60<80%,"A",L60<=95%,"B",L60>95%,"C") -> C
B61: MANNA2106 | C61: ='Юнит 17'!AO59 -> 0 | D61: =C61/C$106 -> 0 | E61: =E60+D61 -> 1.0377324 | F61: =IF(AND(E61<=0),"C",IF(E61<=0.8,"A",IF(E61<=0.95,"B","C"))) -> C | G61: =VLOOKUP(B$4:B$104,I$4:M$104,5,0) -> C | I61: sh06 | J61: ='Юнит 17'!U30 -> 0 | K61: =J61/J$106 -> 0 | L61: =L60+K61 -> 0.99764012 | M61: =_xlfn.IFS(L61<80%,"A",L61<=95%,"B",L61>95%,"C") -> C
B62: MANNA2109 | C62: ='Юнит 17'!AO62 -> 0 | D62: =C62/C$106 -> 0 | E62: =E61+D62 -> 1.0377324 | F62: =IF(AND(E62<=0),"C",IF(E62<=0.8,"A",IF(E62<=0.95,"B","C"))) -> C | G62: =VLOOKUP(B$4:B$104,I$4:M$104,5,0) -> C | I62: sh07 | J62: ='Юнит 17'!U31 -> 0 | K62: =J62/J$106 -> 0 | L62: =L61+K62 -> 0.99764012 | M62: =_xlfn.IFS(L62<80%,"A",L62<=95%,"B",L62>95%,"C") -> C
B63: MANNA2110 | C63: ='Юнит 17'!AO63 -> 0 | D63: =C63/C$106 -> 0 | E63: =E62+D63 -> 1.0377324 | F63: =IF(AND(E63<=0),"C",IF(E63<=0.8,"A",IF(E63<=0.95,"B","C"))) -> C | G63: =VLOOKUP(B$4:B$104,I$4:M$104,5,0) -> C | I63: sh08 | J63: ='Юнит 17'!U32 -> 0 | K63: =J63/J$106 -> 0 | L63: =L62+K63 -> 0.99764012 | M63: =_xlfn.IFS(L63<80%,"A",L63<=95%,"B",L63>95%,"C") -> C
B64: MANNA2111 | C64: ='Юнит 17'!AO64 -> 0 | D64: =C64/C$106 -> 0 | E64: =E63+D64 -> 1.0377324 | F64: =IF(AND(E64<=0),"C",IF(E64<=0.8,"A",IF(E64<=0.95,"B","C"))) -> C | G64: =VLOOKUP(B$4:B$104,I$4:M$104,5,0) -> C | I64: sh11 | J64: ='Юнит 17'!U35 -> 0 | K64: =J64/J$106 -> 0 | L64: =L63+K64 -> 0.99764012 | M64: =_xlfn.IFS(L64<80%,"A",L64<=95%,"B",L64>95%,"C") -> C
B65: MANNA2114 | C65: ='Юнит 17'!AO67 -> 0 | D65: =C65/C$106 -> 0 | E65: =E64+D65 -> 1.0377324 | F65: =IF(AND(E65<=0),"C",IF(E65<=0.8,"A",IF(E65<=0.95,"B","C"))) -> C | G65: =VLOOKUP(B$4:B$104,I$4:M$104,5,0) -> C | I65: sh12 | J65: ='Юнит 17'!U36 -> 0 | K65: =J65/J$106 -> 0 | L65: =L64+K65 -> 0.99764012 | M65: =_xlfn.IFS(L65<80%,"A",L65<=95%,"B",L65>95%,"C") -> C
B66: MANNA2115 | C66: ='Юнит 17'!AO68 -> 0 | D66: =C66/C$106 -> 0 | E66: =E65+D66 -> 1.0377324 | F66: =IF(AND(E66<=0),"C",IF(E66<=0.8,"A",IF(E66<=0.95,"B","C"))) -> C | G66: =VLOOKUP(B$4:B$104,I$4:M$104,5,0) -> C | I66: sh13 | J66: ='Юнит 17'!U37 -> 0 | K66: =J66/J$106 -> 0 | L66: =L65+K66 -> 0.99764012 | M66: =_xlfn.IFS(L66<80%,"A",L66<=95%,"B",L66>95%,"C") -> C
B67: MANNA2117 | C67: ='Юнит 17'!AO70 -> 0 | D67: =C67/C$106 -> 0 | E67: =E66+D67 -> 1.0377324 | F67: =IF(AND(E67<=0),"C",IF(E67<=0.8,"A",IF(E67<=0.95,"B","C"))) -> C | G67: =VLOOKUP(B$4:B$104,I$4:M$104,5,0) -> C | I67: sh14 | J67: ='Юнит 17'!U38 -> 0 | K67: =J67/J$106 -> 0 | L67: =L66+K67 -> 0.99764012 | M67: =_xlfn.IFS(L67<80%,"A",L67<=95%,"B",L67>95%,"C") -> C
B68: MANNA2119 | C68: ='Юнит 17'!AO72 -> 0 | D68: =C68/C$106 -> 0 | E68: =E67+D68 -> 1.0377324 | F68: =IF(AND(E68<=0),"C",IF(E68<=0.8,"A",IF(E68<=0.95,"B","C"))) -> C | G68: =VLOOKUP(B$4:B$104,I$4:M$104,5,0) -> C | I68: sh18 | J68: ='Юнит 17'!U42 -> 0 | K68: =J68/J$106 -> 0 | L68: =L67+K68 -> 0.99764012 | M68: =_xlfn.IFS(L68<80%,"A",L68<=95%,"B",L68>95%,"C") -> C
B69: MANNA2121 | C69: ='Юнит 17'!AO74 -> 0 | D69: =C69/C$106 -> 0 | E69: =E68+D69 -> 1.0377324 | F69: =IF(AND(E69<=0),"C",IF(E69<=0.8,"A",IF(E69<=0.95,"B","C"))) -> C | G69: =VLOOKUP(B$4:B$104,I$4:M$104,5,0) -> C | I69: ww 1022 черн-серебро | J69: ='Юнит 17'!U46 -> 0 | K69: =J69/J$106 -> 0 | L69: =L68+K69 -> 0.99764012 | M69: =_xlfn.IFS(L69<80%,"A",L69<=95%,"B",L69>95%,"C") -> C
B70: MAIERSHA 03898 C9-08 | C70: ='Юнит 17'!AO94 -> 0 | D70: =C70/C$106 -> 0 | E70: =E69+D70 -> 1.0377324 | F70: =IF(AND(E70<=0),"C",IF(E70<=0.8,"A",IF(E70<=0.95,"B","C"))) -> C | G70: =VLOOKUP(B$4:B$104,I$4:M$104,5,0) -> C | I70: ww 8010 черные | J70: ='Юнит 17'!U51 -> 0 | K70: =J70/J$106 -> 0 | L70: =L69+K70 -> 0.99764012 | M70: =_xlfn.IFS(L70<80%,"A",L70<=95%,"B",L70>95%,"C") -> C
B71: MAIERSHA 03914 C9-124 | C71: ='Юнит 17'!AO95 -> 0 | D71: =C71/C$106 -> 0 | E71: =E70+D71 -> 1.0377324 | F71: =IF(AND(E71<=0),"C",IF(E71<=0.8,"A",IF(E71<=0.95,"B","C"))) -> C | G71: =VLOOKUP(B$4:B$104,I$4:M$104,5,0) -> C | I71: WW 3055 коричневый | J71: ='Юнит 17'!U53 -> 0 | K71: =J71/J$106 -> 0 | L71: =L70+K71 -> 0.99764012 | M71: =_xlfn.IFS(L71<80%,"A",L71<=95%,"B",L71>95%,"C") -> C
B72: MARSTON 7171 C1 | C72: ='Юнит 17'!AO96 -> 0 | D72: =C72/C$106 -> 0 | E72: =E71+D72 -> 1.0377324 | F72: =IF(AND(E72<=0),"C",IF(E72<=0.8,"A",IF(E72<=0.95,"B","C"))) -> C | G72: =VLOOKUP(B$4:B$104,I$4:M$104,5,0) -> C | I72: MANNA2102 | J72: ='Юнит 17'!U55 -> 0 | K72: =J72/J$106 -> 0 | L72: =L71+K72 -> 0.99764012 | M72: =_xlfn.IFS(L72<80%,"A",L72<=95%,"B",L72>95%,"C") -> C
B73: ЧСЖ_тест | C73: ='Юнит 17'!AO99 -> 0 | D73: =C73/C$106 -> 0 | E73: =E72+D73 -> 1.0377324 | F73: =IF(AND(E73<=0),"C",IF(E73<=0.8,"A",IF(E73<=0.95,"B","C"))) -> C | G73: =VLOOKUP(B$4:B$104,I$4:M$104,5,0) -> C | I73: MANNA2103 | J73: ='Юнит 17'!U56 -> 0 | K73: =J73/J$106 -> 0 | L73: =L72+K73 -> 0.99764012 | M73: =_xlfn.IFS(L73<80%,"A",L73<=95%,"B",L73>95%,"C") -> C
B74: кс_черные_тест | C74: ='Юнит 17'!AO101 -> 0 | D74: =C74/C$106 -> 0 | E74: =E73+D74 -> 1.0377324 | F74: =IF(AND(E74<=0),"C",IF(E74<=0.8,"A",IF(E74<=0.95,"B","C"))) -> C | G74: =VLOOKUP(B$4:B$104,I$4:M$104,5,0) -> C | I74: MANNA2104 | J74: ='Юнит 17'!U57 -> 0 | K74: =J74/J$106 -> 0 | L74: =L73+K74 -> 0.99764012 | M74: =_xlfn.IFS(L74<80%,"A",L74<=95%,"B",L74>95%,"C") -> C
B75: 1022_коричневые_тест | C75: ='Юнит 17'!AO103 -> 0 | D75: =C75/C$106 -> 0 | E75: =E74+D75 -> 1.0377324 | F75: =IF(AND(E75<=0),"C",IF(E75<=0.8,"A",IF(E75<=0.95,"B","C"))) -> C | G75: =VLOOKUP(B$4:B$104,I$4:M$104,5,0) -> C | I75: MANNA2105 | J75: ='Юнит 17'!U58 -> 0 | K75: =J75/J$106 -> 0 | L75: =L74+K75 -> 0.99764012 | M75: =_xlfn.IFS(L75<80%,"A",L75<=95%,"B",L75>95%,"C") -> C
B76: ww 8010 черные | C76: ='Юнит 17'!AO51 -> -1.0379139 | D76: =C76/C$106 -> -1.8339076e-06 | E76: =E49+D76 -> 1.0377306 | F76: =IF(AND(E76<=0),"C",IF(E76<=0.8,"A",IF(E76<=0.95,"B","C"))) -> C | G76: =VLOOKUP(B$4:B$104,I$4:M$104,5,0) -> C | I76: MANNA2106 | J76: ='Юнит 17'!U59 -> 0 | K76: =J76/J$106 -> 0 | L76: =L49+K76 -> 0.99351032 | M76: =_xlfn.IFS(L76<80%,"A",L76<=95%,"B",L76>95%,"C") -> C
B77: MANNA2102 | C77: ='Юнит 17'!AO55 -> -1.0379139 | D77: =C77/C$106 -> -1.8339076e-06 | E77: =E76+D77 -> 1.0377287 | F77: =IF(AND(E77<=0),"C",IF(E77<=0.8,"A",IF(E77<=0.95,"B","C"))) -> C | G77: =VLOOKUP(B$4:B$104,I$4:M$104,5,0) -> C | I77: MANNA2109 | J77: ='Юнит 17'!U62 -> 0 | K77: =J77/J$106 -> 0 | L77: =L76+K77 -> 0.99351032 | M77: =_xlfn.IFS(L77<80%,"A",L77<=95%,"B",L77>95%,"C") -> C
B78: MANNA2112 | C78: ='Юнит 17'!AO65 -> -1.0379139 | D78: =C78/C$106 -> -1.8339076e-06 | E78: =E77+D78 -> 1.0377269 | F78: =IF(AND(E78<=0),"C",IF(E78<=0.8,"A",IF(E78<=0.95,"B","C"))) -> C | G78: =VLOOKUP(B$4:B$104,I$4:M$104,5,0) -> C | I78: MANNA2110 | J78: ='Юнит 17'!U63 -> 0 | K78: =J78/J$106 -> 0 | L78: =L77+K78 -> 0.99351032 | M78: =_xlfn.IFS(L78<80%,"A",L78<=95%,"B",L78>95%,"C") -> C
B79: MANNA2113 | C79: ='Юнит 17'!AO66 -> -2.0758279 | D79: =C79/C$106 -> -3.6678151e-06 | E79: =E78+D79 -> 1.0377232 | F79: =IF(AND(E79<=0),"C",IF(E79<=0.8,"A",IF(E79<=0.95,"B","C"))) -> C | G79: =VLOOKUP(B$4:B$104,I$4:M$104,5,0) -> C | I79: MANNA2111 | J79: ='Юнит 17'!U64 -> 0 | K79: =J79/J$106 -> 0 | L79: =L78+K79 -> 0.99351032 | M79: =_xlfn.IFS(L79<80%,"A",L79<=95%,"B",L79>95%,"C") -> C
B80: POMILED 08247 C4-08 | C80: ='Юнит 17'!AO97 -> -5.9558279 | D80: =C80/C$106 -> -1.0523452e-05 | E80: =E79+D80 -> 1.0377127 | F80: =IF(AND(E80<=0),"C",IF(E80<=0.8,"A",IF(E80<=0.95,"B","C"))) -> C | G80: =VLOOKUP(B$4:B$104,I$4:M$104,5,0) -> C | I80: MANNA2112 | J80: ='Юнит 17'!U65 -> 0 | K80: =J80/J$106 -> 0 | L80: =L79+K80 -> 0.99351032 | M80: =_xlfn.IFS(L80<80%,"A",L80<=95%,"B",L80>95%,"C") -> C
B81: Hengda Optical черные | C81: ='Юнит 17'!AO81 -> -13.492881 | D81: =C81/C$106 -> -2.3840798e-05 | E81: =E80+D81 -> 1.0376889 | F81: =IF(AND(E81<=0),"C",IF(E81<=0.8,"A",IF(E81<=0.95,"B","C"))) -> C | G81: =VLOOKUP(B$4:B$104,I$4:M$104,5,0) -> C | I81: MANNA2113 | J81: ='Юнит 17'!U66 -> 0 | K81: =J81/J$106 -> 0 | L81: =L80+K81 -> 0.99351032 | M81: =_xlfn.IFS(L81<80%,"A",L81<=95%,"B",L81>95%,"C") -> C
B82: sh2 | C82: ='Юнит 17'!AO27 -> -40.8726 | D82: =C82/C$106 -> -7.2218483e-05 | E82: =E81+D82 -> 1.0376166 | F82: =IF(AND(E82<=0),"C",IF(E82<=0.8,"A",IF(E82<=0.95,"B","C"))) -> C | G82: =VLOOKUP(B$4:B$104,I$4:M$104,5,0) -> C | I82: MANNA2114 | J82: ='Юнит 17'!U67 -> 0 | K82: =J82/J$106 -> 0 | L82: =L81+K82 -> 0.99351032 | M82: =_xlfn.IFS(L82<80%,"A",L82<=95%,"B",L82>95%,"C") -> C
B83: MANNA2122 | C83: ='Юнит 17'!AO75 -> -47.845024 | D83: =C83/C$106 -> -8.4538176e-05 | E83: =E82+D83 -> 1.0375321 | F83: =IF(AND(E83<=0),"C",IF(E83<=0.8,"A",IF(E83<=0.95,"B","C"))) -> C | G83: =VLOOKUP(B$4:B$104,I$4:M$104,5,0) -> C | I83: MANNA2115 | J83: ='Юнит 17'!U68 -> 0 | K83: =J83/J$106 -> 0 | L83: =L82+K83 -> 0.99351032 | M83: =_xlfn.IFS(L83<80%,"A",L83<=95%,"B",L83>95%,"C") -> C
B84: Taizhou Rayen sport розовый | C84: ='Юнит 17'!AO90 -> -49.819869 | D84: =C84/C$106 -> -8.8027563e-05 | E84: =E83+D84 -> 1.0374441 | F84: =IF(AND(E84<=0),"C",IF(E84<=0.8,"A",IF(E84<=0.95,"B","C"))) -> C | G84: =VLOOKUP(B$4:B$104,I$4:M$104,5,0) -> C | I84: MANNA2117 | J84: ='Юнит 17'!U70 -> 0 | K84: =J84/J$106 -> 0 | L84: =L83+K84 -> 0.99351032 | M84: =_xlfn.IFS(L84<80%,"A",L84<=95%,"B",L84>95%,"C") -> C
B85: MANNA2118 | C85: ='Юнит 17'!AO71 -> -88.547914 | D85: =C85/C$106 -> -0.0001564568 | E85: =E84+D85 -> 1.0372876 | F85: =IF(AND(E85<=0),"C",IF(E85<=0.8,"A",IF(E85<=0.95,"B","C"))) -> C | G85: =VLOOKUP(B$4:B$104,I$4:M$104,5,0) -> C | I85: MANNA2118 | J85: ='Юнит 17'!U71 -> 0 | K85: =J85/J$106 -> 0 | L85: =L84+K85 -> 0.99351032 | M85: =_xlfn.IFS(L85<80%,"A",L85<=95%,"B",L85>95%,"C") -> C
B86: sh13 | C86: ='Юнит 17'!AO37 -> -93.617914 | D86: =C86/C$106 -> -0.00016541506 | E86: =E85+D86 -> 1.0371222 | F86: =IF(AND(E86<=0),"C",IF(E86<=0.8,"A",IF(E86<=0.95,"B","C"))) -> C | G86: =VLOOKUP(B$4:B$104,I$4:M$104,5,0) -> C | I86: MANNA2119 | J86: ='Юнит 17'!U72 -> 0 | K86: =J86/J$106 -> 0 | L86: =L85+K86 -> 0.99351032 | M86: =_xlfn.IFS(L86<80%,"A",L86<=95%,"B",L86>95%,"C") -> C
B87: sh14 | C87: ='Юнит 17'!AO38 -> -118.20447 | D87: =C87/C$106 -> -0.00020885746 | E87: =E86+D87 -> 1.0369133 | F87: =IF(AND(E87<=0),"C",IF(E87<=0.8,"A",IF(E87<=0.95,"B","C"))) -> C | G87: =VLOOKUP(B$4:B$104,I$4:M$104,5,0) -> C | I87: MANNA2121 | J87: ='Юнит 17'!U74 -> 0 | K87: =J87/J$106 -> 0 | L87: =L86+K87 -> 0.99351032 | M87: =_xlfn.IFS(L87<80%,"A",L87<=95%,"B",L87>95%,"C") -> C
B88: Qianai черные | C88: ='Юнит 17'!AO83 -> -133.39447 | D88: =C88/C$106 -> -0.00023569693 | E88: =E87+D88 -> 1.0366776 | F88: =IF(AND(E88<=0),"C",IF(E88<=0.8,"A",IF(E88<=0.95,"B","C"))) -> C | G88: =VLOOKUP(B$4:B$104,I$4:M$104,5,0) -> C | I88: Chenlong черные | J88: ='Юнит 17'!U76 -> 0 | K88: =J88/J$106 -> 0 | L88: =L87+K88 -> 0.99351032 | M88: =_xlfn.IFS(L88<80%,"A",L88<=95%,"B",L88>95%,"C") -> C
B89: Ли Сян ретро золото | C89: ='Юнит 17'!AO92 -> -173.3706 | D89: =C89/C$106 -> -0.00030633142 | E89: =E88+D89 -> 1.0363713 | F89: =IF(AND(E89<=0),"C",IF(E89<=0.8,"A",IF(E89<=0.95,"B","C"))) -> C | G89: =VLOOKUP(B$4:B$104,I$4:M$104,5,0) -> C | I89: Guangdu серебро серая линза | J89: ='Юнит 17'!U80 -> 0 | K89: =J89/J$106 -> 0 | L89: =L88+K89 -> 0.99351032 | M89: =_xlfn.IFS(L89<80%,"A",L89<=95%,"B",L89>95%,"C") -> C
B90: sh18 | C90: ='Юнит 17'!AO42 -> -209.39576 | D90: =C90/C$106 -> -0.00036998489 | E90: =E89+D90 -> 1.0360013 | F90: =IF(AND(E90<=0),"C",IF(E90<=0.8,"A",IF(E90<=0.95,"B","C"))) -> C | G90: =VLOOKUP(B$4:B$104,I$4:M$104,5,0) -> C | I90: Hengda Optical черные | J90: ='Юнит 17'!U81 -> 0 | K90: =J90/J$106 -> 0 | L90: =L89+K90 -> 0.99351032 | M90: =_xlfn.IFS(L90<80%,"A",L90<=95%,"B",L90>95%,"C") -> C
B91: Ли Сян ретро серебро | C91: ='Юнит 17'!AO93 -> -218.05864 | D91: =C91/C$106 -> -0.00038529148 | E91: =E90+D91 -> 1.035616 | F91: =IF(AND(E91<=0),"C",IF(E91<=0.8,"A",IF(E91<=0.95,"B","C"))) -> C | G91: =VLOOKUP(B$4:B$104,I$4:M$104,5,0) -> C | I91: Hengda Optical леопард | J91: ='Юнит 17'!U82 -> 0 | K91: =J91/J$106 -> 0 | L91: =L90+K91 -> 0.99351032 | M91: =_xlfn.IFS(L91<80%,"A",L91<=95%,"B",L91>95%,"C") -> C
B92: Linhai Baiyi розовая линза | C92: ='Юнит 17'!AO88 -> -259.75 | D92: =C92/C$106 -> -0.00045895664 | E92: =E91+D92 -> 1.0351571 | F92: =IF(AND(E92<=0),"C",IF(E92<=0.8,"A",IF(E92<=0.95,"B","C"))) -> C | G92: =VLOOKUP(B$4:B$104,I$4:M$104,5,0) -> C | I92: Qianai черные | J92: ='Юнит 17'!U83 -> 0 | K92: =J92/J$106 -> 0 | L92: =L91+K92 -> 0.99351032 | M92: =_xlfn.IFS(L92<80%,"A",L92<=95%,"B",L92>95%,"C") -> C
B93: MANNA2108 | C93: ='Юнит 17'!AO61 -> -607.18677 | D93: =C93/C$106 -> -0.0010728485 | E93: =E92+D93 -> 1.0340842 | F93: =IF(AND(E93<=0),"C",IF(E93<=0.8,"A",IF(E93<=0.95,"B","C"))) -> C | G93: =VLOOKUP(B$4:B$104,I$4:M$104,5,0) -> #N/A | I93: Keming Aishi коричневые | J93: ='Юнит 17'!U85 -> 0 | K93: =J93/J$106 -> 0 | L93: =L92+K93 -> 0.99351032 | M93: =_xlfn.IFS(L93<80%,"A",L93<=95%,"B",L93>95%,"C") -> C
B94: sh16 | C94: ='Юнит 17'!AO40 -> -742.2727 | D94: =C94/C$106 -> -0.0013115341 | E94: =E93+D94 -> 1.0327727 | F94: =IF(AND(E94<=0),"C",IF(E94<=0.8,"A",IF(E94<=0.95,"B","C"))) -> C | G94: =VLOOKUP(B$4:B$104,I$4:M$104,5,0) -> C | I94: Linhai Baiyi розовая линза | J94: ='Юнит 17'!U88 -> 0 | K94: =J94/J$106 -> 0 | L94: =L93+K94 -> 0.99351032 | M94: =_xlfn.IFS(L94<80%,"A",L94<=95%,"B",L94>95%,"C") -> C
B95: WW 3055 коричневый | C95: ='Юнит 17'!AO53 -> -845.62116 | D95: =C95/C$106 -> -0.0014941422 | E95: =E94+D95 -> 1.0312786 | F95: =IF(AND(E95<=0),"C",IF(E95<=0.8,"A",IF(E95<=0.95,"B","C"))) -> C | G95: =VLOOKUP(B$4:B$104,I$4:M$104,5,0) -> C | I95: Taizhou Rayen sport розовый | J95: ='Юнит 17'!U90 -> 0 | K95: =J95/J$106 -> 0 | L95: =L94+K95 -> 0.99351032 | M95: =_xlfn.IFS(L95<80%,"A",L95<=95%,"B",L95>95%,"C") -> C
B96: Chenlong коричневые | C96: ='Юнит 17'!AO77 -> -902.74559 | D96: =C96/C$106 -> -0.0015950763 | E96: =E95+D96 -> 1.0296835 | F96: =IF(AND(E96<=0),"C",IF(E96<=0.8,"A",IF(E96<=0.95,"B","C"))) -> C | G96: =VLOOKUP(B$4:B$104,I$4:M$104,5,0) -> C | I96: Ли Сян ретро серебро | J96: ='Юнит 17'!U93 -> 0 | K96: =J96/J$106 -> 0 | L96: =L95+K96 -> 0.99351032 | M96: =_xlfn.IFS(L96<80%,"A",L96<=95%,"B",L96>95%,"C") -> C
B97: MANNA2105 | C97: ='Юнит 17'!AO58 -> -927.95036 | D97: =C97/C$106 -> -0.0016396111 | E97: =E96+D97 -> 1.0280439 | F97: =IF(AND(E97<=0),"C",IF(E97<=0.8,"A",IF(E97<=0.95,"B","C"))) -> C | G97: =VLOOKUP(B$4:B$104,I$4:M$104,5,0) -> C | I97: MAIERSHA 03898 C9-08 | J97: ='Юнит 17'!U94 -> 0 | K97: =J97/J$106 -> 0 | L97: =L96+K97 -> 0.99351032 | M97: =_xlfn.IFS(L97<80%,"A",L97<=95%,"B",L97>95%,"C") -> C
B98: Keming Aishi коричневые | C98: ='Юнит 17'!AO85 -> -1100.8712 | D98: =C98/C$106 -> -0.0019451477 | E98: =E97+D98 -> 1.0260987 | F98: =IF(AND(E98<=0),"C",IF(E98<=0.8,"A",IF(E98<=0.95,"B","C"))) -> C | G98: =VLOOKUP(B$4:B$104,I$4:M$104,5,0) -> C | I98: MAIERSHA 03914 C9-124 | J98: ='Юнит 17'!U95 -> 0 | K98: =J98/J$106 -> 0 | L98: =L97+K98 -> 0.99351032 | M98: =_xlfn.IFS(L98<80%,"A",L98<=95%,"B",L98>95%,"C") -> C
B99: Guangdu серебро серая линза | C99: ='Юнит 17'!AO80 -> -1112.3045 | D99: =C99/C$106 -> -0.0019653496 | E99: =E93+D99 -> 1.0321189 | F99: =IF(AND(E99<=0),"C",IF(E99<=0.8,"A",IF(E99<=0.95,"B","C"))) -> C | G99: =VLOOKUP(B$4:B$104,I$4:M$104,5,0) -> C | I99: MARSTON 7171 C1 | J99: ='Юнит 17'!U96 -> 0 | K99: =J99/J$106 -> 0 | L99: =L93+K99 -> 0.99351032 | M99: =_xlfn.IFS(L99<80%,"A",L99<=95%,"B",L99>95%,"C") -> C
B100: Иу Диту серый | C100: ='Юнит 17'!AO91 -> -1191.1213 | D100: =C100/C$106 -> -0.0021046122 | E100: =E94+D100 -> 1.0306681 | F100: =IF(AND(E100<=0),"C",IF(E100<=0.8,"A",IF(E100<=0.95,"B","C"))) -> C | G100: =VLOOKUP(B$4:B$104,I$4:M$104,5,0) -> C | I100: POMILED 08247 C4-08 | J100: ='Юнит 17'!U97 -> 0 | K100: =J100/J$106 -> 0 | L100: =L94+K100 -> 0.99351032 | M100: =_xlfn.IFS(L100<80%,"A",L100<=95%,"B",L100>95%,"C") -> C
B101: Chenlong черные | C101: ='Юнит 17'!AO76 -> -1422.7753 | D101: =C101/C$106 -> -0.0025139256 | E101: =E95+D101 -> 1.0287646 | F101: =IF(AND(E101<=0),"C",IF(E101<=0.8,"A",IF(E101<=0.95,"B","C"))) -> C | G101: =VLOOKUP(B$4:B$104,I$4:M$104,5,0) -> C | I101: ЧСЖ_тест | J101: ='Юнит 17'!U99 -> 0 | K101: =J101/J$106 -> 0 | L101: =L95+K101 -> 0.99351032 | M101: =_xlfn.IFS(L101<80%,"A",L101<=95%,"B",L101>95%,"C") -> C
...

Sheet АВС 16
B2: ОЧКИ
C3: Прибыль | D3: % прибыль | E3: Доля | F3: ABC прибыль | G3: ABC кол-во | J3: Кол-во | K3: % кол-во | L3: Доля | M3: ABC кол-во
B4: QS черные PZ | C4: ='Юнит 16'!AO4 -> 158353.6 | D4: =C4/C$106 -> 0.18805966 | E4: =D4 -> 0.18805966 | F4: =IF(AND(E4<=0),"C",IF(E4<=0.8,"A",IF(E4<=0.95,"B","C"))) -> A | G4: =VLOOKUP(B$4:B$104,I$4:M$104,5,0) -> A | I4: QS черные PZ | J4: ='Юнит 16'!U4 -> 305 | K4: =J4/J$106 -> 0.15844156 | L4: =K4 -> 0.15844156 | M4: =_xlfn.IFS(L4<80%,"A",L4<=95%,"B",L4>95%,"C") -> A | P4: A | Q4: 0.8
B5: flip коричневые | C5: ='Юнит 16'!AO16 -> 99211.41 | D5: =C5/C$106 -> 0.1178228 | E5: =E4+D5 -> 0.30588246 | F5: =IF(AND(E5<=0),"C",IF(E5<=0.8,"A",IF(E5<=0.95,"B","C"))) -> A | G5: =VLOOKUP(B$4:B$104,I$4:M$104,5,0) -> A | I5: flip черные | J5: ='Юнит 16'!U13 -> 181 | K5: =J5/J$106 -> 0.094025974 | L5: =L4+K5 -> 0.25246753 | M5: =_xlfn.IFS(L5<80%,"A",L5<=95%,"B",L5>95%,"C") -> A | P5: B | Q5: 0.15
B6: flip черные | C6: ='Юнит 16'!AO13 -> 77693.478 | D6: =C6/C$106 -> 0.092268247 | E6: =E5+D6 -> 0.39815071 | F6: =IF(AND(E6<=0),"C",IF(E6<=0.8,"A",IF(E6<=0.95,"B","C"))) -> A | G6: =VLOOKUP(B$4:B$104,I$4:M$104,5,0) -> A | I6: flip коричневые | J6: ='Юнит 16'!U16 -> 168 | K6: =J6/J$106 -> 0.087272727 | L6: =L5+K6 -> 0.33974026 | M6: =_xlfn.IFS(L6<80%,"A",L6<=95%,"B",L6>95%,"C") -> A | P6: C | Q6: 0.05
B7: th черн | C7: ='Юнит 16'!AO9 -> 61411.887 | D7: =C7/C$106 -> 0.07293234 | E7: =E6+D7 -> 0.47108305 | F7: =IF(AND(E7<=0),"C",IF(E7<=0.8,"A",IF(E7<=0.95,"B","C"))) -> A | G7: =VLOOKUP(B$4:B$104,I$4:M$104,5,0) -> A | I7: th черн | J7: ='Юнит 16'!U9 -> 166 | K7: =J7/J$106 -> 0.086233766 | L7: =L6+K7 -> 0.42597403 | M7: =_xlfn.IFS(L7<80%,"A",L7<=95%,"B",L7>95%,"C") -> A
B8: QS синие PZ | C8: ='Юнит 16'!AO5 -> 58503.347 | D8: =C8/C$106 -> 0.069478178 | E8: =E7+D8 -> 0.54056123 | F8: =IF(AND(E8<=0),"C",IF(E8<=0.8,"A",IF(E8<=0.95,"B","C"))) -> A | G8: =VLOOKUP(B$4:B$104,I$4:M$104,5,0) -> A | I8: th син | J8: ='Юнит 16'!U10 -> 139 | K8: =J8/J$106 -> 0.072207792 | L8: =L7+K8 -> 0.49818182 | M8: =_xlfn.IFS(L8<80%,"A",L8<=95%,"B",L8>95%,"C") -> A
B9: QS коричневые PZ | C9: ='Юнит 16'!AO7 -> 57203.084 | D9: =C9/C$106 -> 0.067933994 | E9: =E8+D9 -> 0.60849522 | F9: =IF(AND(E9<=0),"C",IF(E9<=0.8,"A",IF(E9<=0.95,"B","C"))) -> A | G9: =VLOOKUP(B$4:B$104,I$4:M$104,5,0) -> A | I9: QS коричневые PZ | J9: ='Юнит 16'!U7 -> 118 | K9: =J9/J$106 -> 0.061298701 | L9: =L8+K9 -> 0.55948052 | M9: =_xlfn.IFS(L9<80%,"A",L9<=95%,"B",L9>95%,"C") -> A
B10: черные с железкой классика | C10: ='Юнит 16'!AO3 -> 51737.748 | D10: =C10/C$106 -> 0.061443399 | E10: =E9+D10 -> 0.66993862 | F10: =IF(AND(E10<=0),"C",IF(E10<=0.8,"A",IF(E10<=0.95,"B","C"))) -> A | G10: =VLOOKUP(B$4:B$104,I$4:M$104,5,0) -> A | I10: черные с железкой классика | J10: ='Юнит 16'!U3 -> 112 | K10: =J10/J$106 -> 0.058181818 | L10: =L9+K10 -> 0.61766234 | M10: =_xlfn.IFS(L10<80%,"A",L10<=95%,"B",L10>95%,"C") -> A
B11: th син | C11: ='Юнит 16'!AO10 -> 41043.761 | D11: =C11/C$106 -> 0.048743292 | E11: =E10+D11 -> 0.71868191 | F11: =IF(AND(E11<=0),"C",IF(E11<=0.8,"A",IF(E11<=0.95,"B","C"))) -> A | G11: =VLOOKUP(B$4:B$104,I$4:M$104,5,0) -> A | I11: QS синие PZ | J11: ='Юнит 16'!U5 -> 109 | K11: =J11/J$106 -> 0.056623377 | L11: =L10+K11 -> 0.67428571 | M11: =_xlfn.IFS(L11<80%,"A",L11<=95%,"B",L11>95%,"C") -> A
B12: th желт | C12: ='Юнит 16'!AO11 -> 33767.008 | D12: =C12/C$106 -> 0.04010147 | E12: =E11+D12 -> 0.75878338 | F12: =IF(AND(E12<=0),"C",IF(E12<=0.8,"A",IF(E12<=0.95,"B","C"))) -> A | G12: =VLOOKUP(B$4:B$104,I$4:M$104,5,0) -> A | I12: th коричн | J12: ='Юнит 16'!U12 -> 99 | K12: =J12/J$106 -> 0.051428571 | L12: =L11+K12 -> 0.72571429 | M12: =_xlfn.IFS(L12<80%,"A",L12<=95%,"B",L12>95%,"C") -> A
B13: QS желтые PZ | C13: ='Юнит 16'!AO6 -> 30951.522 | D13: =C13/C$106 -> 0.036757817 | E13: =E12+D13 -> 0.7955412 | F13: =IF(AND(E13<=0),"C",IF(E13<=0.8,"A",IF(E13<=0.95,"B","C"))) -> A | G13: =VLOOKUP(B$4:B$104,I$4:M$104,5,0) -> A | I13: th желт | J13: ='Юнит 16'!U11 -> 78 | K13: =J13/J$106 -> 0.040519481 | L13: =L12+K13 -> 0.76623377 | M13: =_xlfn.IFS(L13<80%,"A",L13<=95%,"B",L13>95%,"C") -> A
B14: th коричн | C14: ='Юнит 16'!AO12 -> 30790.726 | D14: =C14/C$106 -> 0.036566857 | E14: =E13+D14 -> 0.83210805 | F14: =IF(AND(E14<=0),"C",IF(E14<=0.8,"A",IF(E14<=0.95,"B","C"))) -> B | G14: =VLOOKUP(B$4:B$104,I$4:M$104,5,0) -> A | I14: QS желтые PZ | J14: ='Юнит 16'!U6 -> 63 | K14: =J14/J$106 -> 0.032727273 | L14: =L13+K14 -> 0.79896104 | M14: =_xlfn.IFS(L14<80%,"A",L14<=95%,"B",L14>95%,"C") -> A
B15: flip желтые | C15: ='Юнит 16'!AO15 -> 25537.369 | D15: =C15/C$106 -> 0.030328007 | E15: =E14+D15 -> 0.86243606 | F15: =IF(AND(E15<=0),"C",IF(E15<=0.8,"A",IF(E15<=0.95,"B","C"))) -> B | G15: =VLOOKUP(B$4:B$104,I$4:M$104,5,0) -> B | I15: flip желтые | J15: ='Юнит 16'!U15 -> 55 | K15: =J15/J$106 -> 0.028571429 | L15: =L14+K15 -> 0.82753247 | M15: =_xlfn.IFS(L15<80%,"A",L15<=95%,"B",L15>95%,"C") -> B
B16: ww 1022 коричневые | C16: ='Юнит 16'!AO48 -> 19712.981 | D16: =C16/C$106 -> 0.023411002 | E16: =E15+D16 -> 0.88584706 | F16: =IF(AND(E16<=0),"C",IF(E16<=0.8,"A",IF(E16<=0.95,"B","C"))) -> B | G16: =VLOOKUP(B$4:B$104,I$4:M$104,5,0) -> B | I16: ww 1022 коричневые | J16: ='Юнит 16'!U48 -> 41 | K16: =J16/J$106 -> 0.021298701 | L16: =L15+K16 -> 0.84883117 | M16: =_xlfn.IFS(L16<80%,"A",L16<=95%,"B",L16>95%,"C") -> B
B17: ww 2018 желтые | C17: ='Юнит 16'!AO50 -> 16703.179 | D17: =C17/C$106 -> 0.019836582 | E17: =E16+D17 -> 0.90568365 | F17: =IF(AND(E17<=0),"C",IF(E17<=0.8,"A",IF(E17<=0.95,"B","C"))) -> B | G17: =VLOOKUP(B$4:B$104,I$4:M$104,5,0) -> B | I17: sh3 | J17: ='Юнит 16'!U28 -> 32 | K17: =J17/J$106 -> 0.016623377 | L17: =L16+K17 -> 0.86545455 | M17: =_xlfn.IFS(L17<80%,"A",L17<=95%,"B",L17>95%,"C") -> B
B18: MR8854 C2 Жен | C18: ='Юнит 16'!AO8 -> 13986.896 | D18: =C18/C$106 -> 0.016610743 | E18: =E17+D18 -> 0.92229439 | F18: =IF(AND(E18<=0),"C",IF(E18<=0.8,"A",IF(E18<=0.95,"B","C"))) -> B | G18: =VLOOKUP(B$4:B$104,I$4:M$104,5,0) -> B | I18: ww 2018 желтые | J18: ='Юнит 16'!U50 -> 32 | K18: =J18/J$106 -> 0.016623377 | L18: =L17+K18 -> 0.88207792 | M18: =_xlfn.IFS(L18<80%,"A",L18<=95%,"B",L18>95%,"C") -> B
B19: sh3 | C19: ='Юнит 16'!AO28 -> 12084.527 | D19: =C19/C$106 -> 0.014351503 | E19: =E18+D19 -> 0.93664589 | F19: =IF(AND(E19<=0),"C",IF(E19<=0.8,"A",IF(E19<=0.95,"B","C"))) -> B | G19: =VLOOKUP(B$4:B$104,I$4:M$104,5,0) -> B | I19: MR8854 C2 Жен | J19: ='Юнит 16'!U8 -> 29 | K19: =J19/J$106 -> 0.015064935 | L19: =L18+K19 -> 0.89714286 | M19: =_xlfn.IFS(L19<80%,"A",L19<=95%,"B",L19>95%,"C") -> B
B20: ww 1022 черные | C20: ='Юнит 16'!AO45 -> 10449.954 | D20: =C20/C$106 -> 0.012410294 | E20: =E19+D20 -> 0.94905619 | F20: =IF(AND(E20<=0),"C",IF(E20<=0.8,"A",IF(E20<=0.95,"B","C"))) -> B | G20: =VLOOKUP(B$4:B$104,I$4:M$104,5,0) -> C | I20: wwl8032 хром металл | J20: ='Юнит 16'!U18 -> 29 | K20: =J20/J$106 -> 0.015064935 | L20: =L19+K20 -> 0.91220779 | M20: =_xlfn.IFS(L20<80%,"A",L20<=95%,"B",L20>95%,"C") -> B
B21: wwl8032 хром металл | C21: ='Юнит 16'!AO18 -> 9493.4544 | D21: =C21/C$106 -> 0.011274362 | E21: =E20+D21 -> 0.96033055 | F21: =IF(AND(E21<=0),"C",IF(E21<=0.8,"A",IF(E21<=0.95,"B","C"))) -> C | G21: =VLOOKUP(B$4:B$104,I$4:M$104,5,0) -> B | I21: ww 2018 черные | J21: ='Юнит 16'!U49 -> 25 | K21: =J21/J$106 -> 0.012987013 | L21: =L20+K21 -> 0.92519481 | M21: =_xlfn.IFS(L21<80%,"A",L21<=95%,"B",L21>95%,"C") -> B
B22: ww 2018 черные | C22: ='Юнит 16'!AO49 -> 8440.6416 | D22: =C22/C$106 -> 0.010024049 | E22: =E21+D22 -> 0.9703546 | F22: =IF(AND(E22<=0),"C",IF(E22<=0.8,"A",IF(E22<=0.95,"B","C"))) -> C | G22: =VLOOKUP(B$4:B$104,I$4:M$104,5,0) -> B | I22: flip синие | J22: ='Юнит 16'!U14 -> 24 | K22: =J22/J$106 -> 0.012467532 | L22: =L21+K22 -> 0.93766234 | M22: =_xlfn.IFS(L22<80%,"A",L22<=95%,"B",L22>95%,"C") -> B
B23: wwl8032 коричневые золото | C23: ='Юнит 16'!AO17 -> 8153.919 | D23: =C23/C$106 -> 0.0096835389 | E23: =E22+D23 -> 0.98003814 | F23: =IF(AND(E23<=0),"C",IF(E23<=0.8,"A",IF(E23<=0.95,"B","C"))) -> C | G23: =VLOOKUP(B$4:B$104,I$4:M$104,5,0) -> B | I23: wwl8032 коричневые золото | J23: ='Юнит 16'!U17 -> 20 | K23: =J23/J$106 -> 0.01038961 | L23: =L22+K23 -> 0.94805195 | M23: =_xlfn.IFS(L23<80%,"A",L23<=95%,"B",L23>95%,"C") -> B
B24: flip синие | C24: ='Юнит 16'!AO14 -> 7514.0944 | D24: =C24/C$106 -> 0.0089236875 | E24: =E23+D24 -> 0.98896182 | F24: =IF(AND(E24<=0),"C",IF(E24<=0.8,"A",IF(E24<=0.95,"B","C"))) -> C | G24: =VLOOKUP(B$4:B$104,I$4:M$104,5,0) -> B | I24: ww 1022 черные | J24: ='Юнит 16'!U45 -> 20 | K24: =J24/J$106 -> 0.01038961 | L24: =L23+K24 -> 0.95844156 | M24: =_xlfn.IFS(L24<80%,"A",L24<=95%,"B",L24>95%,"C") -> C
B25: ww 203 черные | C25: ='Юнит 16'!AO44 -> 4138.6463 | D25: =C25/C$106 -> 0.0049150283 | E25: =E24+D25 -> 0.99387685 | F25: =IF(AND(E25<=0),"C",IF(E25<=0.8,"A",IF(E25<=0.95,"B","C"))) -> C | G25: =VLOOKUP(B$4:B$104,I$4:M$104,5,0) -> C | I25: ww 203 черные | J25: ='Юнит 16'!U44 -> 18 | K25: =J25/J$106 -> 0.0093506494 | L25: =L24+K25 -> 0.96779221 | M25: =_xlfn.IFS(L25<80%,"A",L25<=95%,"B",L25>95%,"C") -> C
B26: MR Р1894 черные | C26: ='Юнит 16'!AO89 -> 3447.0665 | D26: =C26/C$106 -> 0.0040937128 | E26: =E25+D26 -> 0.99797056 | F26: =IF(AND(E26<=0),"C",IF(E26<=0.8,"A",IF(E26<=0.95,"B","C"))) -> C | G26: =VLOOKUP(B$4:B$104,I$4:M$104,5,0) -> C | I26: sports красные | J26: ='Юнит 16'!U22 -> 7 | K26: =J26/J$106 -> 0.0036363636 | L26: =L25+K26 -> 0.97142857 | M26: =_xlfn.IFS(L26<80%,"A",L26<=95%,"B",L26>95%,"C") -> C
B27: ww 1022 желтые | C27: ='Юнит 16'!AO47 -> 3301.6032 | D27: =C27/C$106 -> 0.0039209616 | E27: =E26+D27 -> 1.0018915 | F27: =IF(AND(E27<=0),"C",IF(E27<=0.8,"A",IF(E27<=0.95,"B","C"))) -> C | G27: =VLOOKUP(B$4:B$104,I$4:M$104,5,0) -> C | I27: ww 1022 желтые | J27: ='Юнит 16'!U47 -> 6 | K27: =J27/J$106 -> 0.0031168831 | L27: =L26+K27 -> 0.97454545 | M27: =_xlfn.IFS(L27<80%,"A",L27<=95%,"B",L27>95%,"C") -> C
B28: sports красные | C28: ='Юнит 16'!AO22 -> 2282.355 | D28: =C28/C$106 -> 0.0027105093 | E28: =E27+D28 -> 1.004602 | F28: =IF(AND(E28<=0),"C",IF(E28<=0.8,"A",IF(E28<=0.95,"B","C"))) -> C | G28: =VLOOKUP(B$4:B$104,I$4:M$104,5,0) -> C | I28: MR Р1894 черные | J28: ='Юнит 16'!U89 -> 6 | K28: =J28/J$106 -> 0.0031168831 | L28: =L27+K28 -> 0.97766234 | M28: =_xlfn.IFS(L28<80%,"A",L28<=95%,"B",L28>95%,"C") -> C
B29: кс_черные_женские | C29: ='Юнит 16'!AO102 -> 1901.7491 | D29: =C29/C$106 -> 0.0022585043 | E29: =E28+D29 -> 1.0068605 | F29: =IF(AND(E29<=0),"C",IF(E29<=0.8,"A",IF(E29<=0.95,"B","C"))) -> C | G29: =VLOOKUP(B$4:B$104,I$4:M$104,5,0) -> C | I29: sh1 | J29: ='Юнит 16'!U26 -> 5 | K29: =J29/J$106 -> 0.0025974026 | L29: =L28+K29 -> 0.98025974 | M29: =_xlfn.IFS(L29<80%,"A",L29<=95%,"B",L29>95%,"C") -> C
B30: ЧСЖ_женские | C30: ='Юнит 16'!AO100 -> 957.73961 | D30: =C30/C$106 -> 0.0011374051 | E30: =E29+D30 -> 1.0079979 | F30: =IF(AND(E30<=0),"C",IF(E30<=0.8,"A",IF(E30<=0.95,"B","C"))) -> C | G30: =VLOOKUP(B$4:B$104,I$4:M$104,5,0) -> C | I30: кс_черные_женские | J30: ='Юнит 16'!U102 -> 5 | K30: =J30/J$106 -> 0.0025974026 | L30: =L29+K30 -> 0.98285714 | M30: =_xlfn.IFS(L30<80%,"A",L30<=95%,"B",L30>95%,"C") -> C
B31: sports синие | C31: ='Юнит 16'!AO20 -> 894.56625 | D31: =C31/C$106 -> 0.0010623808 | E31: =E30+D31 -> 1.0090603 | F31: =IF(AND(E31<=0),"C",IF(E31<=0.8,"A",IF(E31<=0.95,"B","C"))) -> C | G31: =VLOOKUP(B$4:B$104,I$4:M$104,5,0) -> C | I31: sports синие | J31: ='Юнит 16'!U20 -> 4 | K31: =J31/J$106 -> 0.0020779221 | L31: =L30+K31 -> 0.98493506 | M31: =_xlfn.IFS(L31<80%,"A",L31<=95%,"B",L31>95%,"C") -> C
B32: WW 3055 черный | C32: ='Юнит 16'!AO52 -> 676.14857 | D32: =C32/C$106 -> 0.00080298946 | E32: =E31+D32 -> 1.0098633 | F32: =IF(AND(E32<=0),"C",IF(E32<=0.8,"A",IF(E32<=0.95,"B","C"))) -> C | G32: =VLOOKUP(B$4:B$104,I$4:M$104,5,0) -> C | I32: sports зеленые | J32: ='Юнит 16'!U21 -> 2 | K32: =J32/J$106 -> 0.001038961 | L32: =L31+K32 -> 0.98597403 | M32: =_xlfn.IFS(L32<80%,"A",L32<=95%,"B",L32>95%,"C") -> C
B33: sh1 | C33: ='Юнит 16'!AO26 -> 516.79116 | D33: =C33/C$106 -> 0.00061373768 | E33: =E32+D33 -> 1.0104771 | F33: =IF(AND(E33<=0),"C",IF(E33<=0.8,"A",IF(E33<=0.95,"B","C"))) -> C | G33: =VLOOKUP(B$4:B$104,I$4:M$104,5,0) -> C | I33: sh2 | J33: ='Юнит 16'!U27 -> 2 | K33: =J33/J$106 -> 0.001038961 | L33: =L32+K33 -> 0.98701299 | M33: =_xlfn.IFS(L33<80%,"A",L33<=95%,"B",L33>95%,"C") -> C
B34: MANNA2107 | C34: ='Юнит 16'!AO60 -> 379.49817 | D34: =C34/C$106 -> 0.00045068945 | E34: =E33+D34 -> 1.0109277 | F34: =IF(AND(E34<=0),"C",IF(E34<=0.8,"A",IF(E34<=0.95,"B","C"))) -> C | G34: =VLOOKUP(B$4:B$104,I$4:M$104,5,0) -> C | I34: WW 3055 черный | J34: ='Юнит 16'!U52 -> 2 | K34: =J34/J$106 -> 0.001038961 | L34: =L33+K34 -> 0.98805195 | M34: =_xlfn.IFS(L34<80%,"A",L34<=95%,"B",L34>95%,"C") -> C
B35: Hengda Optical черные | C35: ='Юнит 16'!AO81 -> 378.25495 | D35: =C35/C$106 -> 0.00044921301 | E35: =E34+D35 -> 1.011377 | F35: =IF(AND(E35<=0),"C",IF(E35<=0.8,"A",IF(E35<=0.95,"B","C"))) -> C | G35: =VLOOKUP(B$4:B$104,I$4:M$104,5,0) -> C | I35: MANNA2122 | J35: ='Юнит 16'!U75 -> 2 | K35: =J35/J$106 -> 0.001038961 | L35: =L34+K35 -> 0.98909091 | M35: =_xlfn.IFS(L35<80%,"A",L35<=95%,"B",L35>95%,"C") -> C
B36: Qianai черные | C36: ='Юнит 16'!AO83 -> 303.24024 | D36: =C36/C$106 -> 0.00036012605 | E36: =E35+D36 -> 1.0117371 | F36: =IF(AND(E36<=0),"C",IF(E36<=0.8,"A",IF(E36<=0.95,"B","C"))) -> C | G36: =VLOOKUP(B$4:B$104,I$4:M$104,5,0) -> C | I36: Chenlong белые | J36: ='Юнит 16'!U78 -> 2 | K36: =J36/J$106 -> 0.001038961 | L36: =L35+K36 -> 0.99012987 | M36: =_xlfn.IFS(L36<80%,"A",L36<=95%,"B",L36>95%,"C") -> C
B37: Linhai Baiyi серая линза | C37: ='Юнит 16'!AO87 -> 289.30565 | D37: =C37/C$106 -> 0.00034357742 | E37: =E36+D37 -> 1.0120807 | F37: =IF(AND(E37<=0),"C",IF(E37<=0.8,"A",IF(E37<=0.95,"B","C"))) -> C | G37: =VLOOKUP(B$4:B$104,I$4:M$104,5,0) -> C | I37: Guangdu золото серая линза | J37: ='Юнит 16'!U79 -> 2 | K37: =J37/J$106 -> 0.001038961 | L37: =L36+K37 -> 0.99116883 | M37: =_xlfn.IFS(L37<80%,"A",L37<=95%,"B",L37>95%,"C") -> C
B38: MANNA2116 | C38: ='Юнит 16'!AO69 -> 287.7056 | D38: =C38/C$106 -> 0.00034167722 | E38: =E37+D38 -> 1.0124223 | F38: =IF(AND(E38<=0),"C",IF(E38<=0.8,"A",IF(E38<=0.95,"B","C"))) -> C | G38: =VLOOKUP(B$4:B$104,I$4:M$104,5,0) -> C | I38: Guangdu серебро серая линза | J38: ='Юнит 16'!U80 -> 2 | K38: =J38/J$106 -> 0.001038961 | L38: =L37+K38 -> 0.99220779 | M38: =_xlfn.IFS(L38<80%,"A",L38<=95%,"B",L38>95%,"C") -> C
B39: sportlife синие | C39: ='Юнит 16'!AO24 -> 269.29609 | D39: =C39/C$106 -> 0.00031981421 | E39: =E35+D39 -> 1.0116968 | F39: =IF(AND(E39<=0),"C",IF(E39<=0.8,"A",IF(E39<=0.95,"B","C"))) -> C | G39: =VLOOKUP(B$4:B$104,I$4:M$104,5,0) -> C | I39: Linhai Baiyi серая линза | J39: ='Юнит 16'!U87 -> 2 | K39: =J39/J$106 -> 0.001038961 | L39: =L35+K39 -> 0.99012987 | M39: =_xlfn.IFS(L39<80%,"A",L39<=95%,"B",L39>95%,"C") -> C
B40: MANNA2108 | C40: ='Юнит 16'!AO61 -> 224.87777 | D40: =C40/C$106 -> 0.00026706331 | E40: =E39+D40 -> 1.0119638 | F40: =IF(AND(E40<=0),"C",IF(E40<=0.8,"A",IF(E40<=0.95,"B","C"))) -> C | G40: =VLOOKUP(B$4:B$104,I$4:M$104,5,0) -> C | I40: ЧСЖ_женские | J40: ='Юнит 16'!U100 -> 2 | K40: =J40/J$106 -> 0.001038961 | L40: =L39+K40 -> 0.99116883 | M40: =_xlfn.IFS(L40<80%,"A",L40<=95%,"B",L40>95%,"C") -> C
B41: sh18 | C41: ='Юнит 16'!AO42 -> 207.64039 | D41: =C41/C$106 -> 0.00024659232 | E41: =E40+D41 -> 1.0122104 | F41: =IF(AND(E41<=0),"C",IF(E41<=0.8,"A",IF(E41<=0.95,"B","C"))) -> C | G41: =VLOOKUP(B$4:B$104,I$4:M$104,5,0) -> C | I41: sportlife синие | J41: ='Юнит 16'!U24 -> 1 | K41: =J41/J$106 -> 0.00051948052 | L41: =L40+K41 -> 0.99168831 | M41: =_xlfn.IFS(L41<80%,"A",L41<=95%,"B",L41>95%,"C") -> C
B42: YIMEI 2391 C1 | C42: ='Юнит 16'!AO98 -> 163.70867 | D42: =C42/C$106 -> 0.00019441931 | E42: =E41+D42 -> 1.0124048 | F42: =IF(AND(E42<=0),"C",IF(E42<=0.8,"A",IF(E42<=0.95,"B","C"))) -> C | G42: =VLOOKUP(B$4:B$104,I$4:M$104,5,0) -> C | I42: sh09 | J42: ='Юнит 16'!U33 -> 1 | K42: =J42/J$106 -> 0.00051948052 | L42: =L41+K42 -> 0.99220779 | M42: =_xlfn.IFS(L42<80%,"A",L42<=95%,"B",L42>95%,"C") -> C
B43: Chenlong коричневые | C43: ='Юнит 16'!AO77 -> 147.75798 | D43: =C43/C$106 -> 0.00017547637 | E43: =E42+D43 -> 1.0125803 | F43: =IF(AND(E43<=0),"C",IF(E43<=0.8,"A",IF(E43<=0.95,"B","C"))) -> C | G43: =VLOOKUP(B$4:B$104,I$4:M$104,5,0) -> C | I43: sh18 | J43: ='Юнит 16'!U42 -> 1 | K43: =J43/J$106 -> 0.00051948052 | L43: =L42+K43 -> 0.99272727 | M43: =_xlfn.IFS(L43<80%,"A",L43<=95%,"B",L43>95%,"C") -> C
B44: MANNA2120 | C44: ='Юнит 16'!AO73 -> 144.18271 | D44: =C44/C$106 -> 0.0001712304 | E44: =E43+D44 -> 1.0127516 | F44: =IF(AND(E44<=0),"C",IF(E44<=0.8,"A",IF(E44<=0.95,"B","C"))) -> C | G44: =VLOOKUP(B$4:B$104,I$4:M$104,5,0) -> C | I44: sh19 | J44: ='Юнит 16'!U43 -> 1 | K44: =J44/J$106 -> 0.00051948052 | L44: =L43+K44 -> 0.99324675 | M44: =_xlfn.IFS(L44<80%,"A",L44<=95%,"B",L44>95%,"C") -> C
B45: MANNA2122 | C45: ='Юнит 16'!AO75 -> 126.5578 | D45: =C45/C$106 -> 0.00015029918 | E45: =E44+D45 -> 1.0129018 | F45: =IF(AND(E45<=0),"C",IF(E45<=0.8,"A",IF(E45<=0.95,"B","C"))) -> C | G45: =VLOOKUP(B$4:B$104,I$4:M$104,5,0) -> C | I45: MANNA2105 | J45: ='Юнит 16'!U58 -> 1 | K45: =J45/J$106 -> 0.00051948052 | L45: =L44+K45 -> 0.99376623 | M45: =_xlfn.IFS(L45<80%,"A",L45<=95%,"B",L45>95%,"C") -> C
B46: sh19 | C46: ='Юнит 16'!AO43 -> 108.44551 | D46: =C46/C$106 -> 0.00012878915 | E46: =E45+D46 -> 1.0130306 | F46: =IF(AND(E46<=0),"C",IF(E46<=0.8,"A",IF(E46<=0.95,"B","C"))) -> C | G46: =VLOOKUP(B$4:B$104,I$4:M$104,5,0) -> C | I46: MANNA2107 | J46: ='Юнит 16'!U60 -> 1 | K46: =J46/J$106 -> 0.00051948052 | L46: =L45+K46 -> 0.99428571 | M46: =_xlfn.IFS(L46<80%,"A",L46<=95%,"B",L46>95%,"C") -> C
B47: sh2 | C47: ='Юнит 16'!AO27 -> 31.522843 | D47: =C47/C$106 -> 3.7436314e-05 | E47: =E46+D47 -> 1.0130681 | F47: =IF(AND(E47<=0),"C",IF(E47<=0.8,"A",IF(E47<=0.95,"B","C"))) -> C | G47: =VLOOKUP(B$4:B$104,I$4:M$104,5,0) -> C | I47: MANNA2108 | J47: ='Юнит 16'!U61 -> 1 | K47: =J47/J$106 -> 0.00051948052 | L47: =L46+K47 -> 0.99480519 | M47: =_xlfn.IFS(L47<80%,"A",L47<=95%,"B",L47>95%,"C") -> C
B48: wwl8032 черные серебро | C48: ='Юнит 16'!AO19 -> 0 | D48: =C48/C$106 -> 0 | E48: =E47+D48 -> 1.0130681 | F48: =IF(AND(E48<=0),"C",IF(E48<=0.8,"A",IF(E48<=0.95,"B","C"))) -> C | G48: =VLOOKUP(B$4:B$104,I$4:M$104,5,0) -> C | I48: MANNA2116 | J48: ='Юнит 16'!U69 -> 1 | K48: =J48/J$106 -> 0.00051948052 | L48: =L47+K48 -> 0.99532468 | M48: =_xlfn.IFS(L48<80%,"A",L48<=95%,"B",L48>95%,"C") -> C
B49: sportlife черные | C49: ='Юнит 16'!AO23 -> 0 | D49: =C49/C$106 -> 0 | E49: =E48+D49 -> 1.0130681 | F49: =IF(AND(E49<=0),"C",IF(E49<=0.8,"A",IF(E49<=0.95,"B","C"))) -> C | G49: =VLOOKUP(B$4:B$104,I$4:M$104,5,0) -> C | I49: MANNA2120 | J49: ='Юнит 16'!U73 -> 1 | K49: =J49/J$106 -> 0.00051948052 | L49: =L48+K49 -> 0.99584416 | M49: =_xlfn.IFS(L49<80%,"A",L49<=95%,"B",L49>95%,"C") -> C
B50: sportlife красные | C50: ='Юнит 16'!AO25 -> 0 | D50: =C50/C$106 -> 0 | E50: =E49+D50 -> 1.0130681 | F50: =IF(AND(E50<=0),"C",IF(E50<=0.8,"A",IF(E50<=0.95,"B","C"))) -> C | G50: =VLOOKUP(B$4:B$104,I$4:M$104,5,0) -> C | I50: Chenlong коричневые | J50: ='Юнит 16'!U77 -> 1 | K50: =J50/J$106 -> 0.00051948052 | L50: =L49+K50 -> 0.99636364 | M50: =_xlfn.IFS(L50<80%,"A",L50<=95%,"B",L50>95%,"C") -> C
B51: sh4 | C51: ='Юнит 16'!AO29 -> 0 | D51: =C51/C$106 -> 0 | E51: =E50+D51 -> 1.0130681 | F51: =IF(AND(E51<=0),"C",IF(E51<=0.8,"A",IF(E51<=0.95,"B","C"))) -> C | G51: =VLOOKUP(B$4:B$104,I$4:M$104,5,0) -> C | I51: Hengda Optical черные | J51: ='Юнит 16'!U81 -> 1 | K51: =J51/J$106 -> 0.00051948052 | L51: =L50+K51 -> 0.99688312 | M51: =_xlfn.IFS(L51<80%,"A",L51<=95%,"B",L51>95%,"C") -> C
B52: sh06 | C52: ='Юнит 16'!AO30 -> 0 | D52: =C52/C$106 -> 0 | E52: =E51+D52 -> 1.0130681 | F52: =IF(AND(E52<=0),"C",IF(E52<=0.8,"A",IF(E52<=0.95,"B","C"))) -> C | G52: =VLOOKUP(B$4:B$104,I$4:M$104,5,0) -> C | I52: Qianai черные | J52: ='Юнит 16'!U83 -> 1 | K52: =J52/J$106 -> 0.00051948052 | L52: =L51+K52 -> 0.9974026 | M52: =_xlfn.IFS(L52<80%,"A",L52<=95%,"B",L52>95%,"C") -> C
B53: sh07 | C53: ='Юнит 16'!AO31 -> 0 | D53: =C53/C$106 -> 0 | E53: =E52+D53 -> 1.0130681 | F53: =IF(AND(E53<=0),"C",IF(E53<=0.8,"A",IF(E53<=0.95,"B","C"))) -> C | G53: =VLOOKUP(B$4:B$104,I$4:M$104,5,0) -> C | I53: YIMEI 2391 C1 | J53: ='Юнит 16'!U98 -> 1 | K53: =J53/J$106 -> 0.00051948052 | L53: =L52+K53 -> 0.99792208 | M53: =_xlfn.IFS(L53<80%,"A",L53<=95%,"B",L53>95%,"C") -> C
B54: sh08 | C54: ='Юнит 16'!AO32 -> 0 | D54: =C54/C$106 -> 0 | E54: =E53+D54 -> 1.0130681 | F54: =IF(AND(E54<=0),"C",IF(E54<=0.8,"A",IF(E54<=0.95,"B","C"))) -> C | G54: =VLOOKUP(B$4:B$104,I$4:M$104,5,0) -> C | I54: wwl8032 черные серебро | J54: ='Юнит 16'!U19 -> 0 | K54: =J54/J$106 -> 0 | L54: =L53+K54 -> 0.99792208 | M54: =_xlfn.IFS(L54<80%,"A",L54<=95%,"B",L54>95%,"C") -> C
B55: sh11 | C55: ='Юнит 16'!AO35 -> 0 | D55: =C55/C$106 -> 0 | E55: =E54+D55 -> 1.0130681 | F55: =IF(AND(E55<=0),"C",IF(E55<=0.8,"A",IF(E55<=0.95,"B","C"))) -> C | G55: =VLOOKUP(B$4:B$104,I$4:M$104,5,0) -> C | I55: sportlife черные | J55: ='Юнит 16'!U23 -> 0 | K55: =J55/J$106 -> 0 | L55: =L54+K55 -> 0.99792208 | M55: =_xlfn.IFS(L55<80%,"A",L55<=95%,"B",L55>95%,"C") -> C
B56: sh12 | C56: ='Юнит 16'!AO36 -> 0 | D56: =C56/C$106 -> 0 | E56: =E55+D56 -> 1.0130681 | F56: =IF(AND(E56<=0),"C",IF(E56<=0.8,"A",IF(E56<=0.95,"B","C"))) -> C | G56: =VLOOKUP(B$4:B$104,I$4:M$104,5,0) -> C | I56: sportlife красные | J56: ='Юнит 16'!U25 -> 0 | K56: =J56/J$106 -> 0 | L56: =L55+K56 -> 0.99792208 | M56: =_xlfn.IFS(L56<80%,"A",L56<=95%,"B",L56>95%,"C") -> C
B57: ww 1022 черн-серебро | C57: ='Юнит 16'!AO46 -> 0 | D57: =C57/C$106 -> 0 | E57: =E56+D57 -> 1.0130681 | F57: =IF(AND(E57<=0),"C",IF(E57<=0.8,"A",IF(E57<=0.95,"B","C"))) -> C | G57: =VLOOKUP(B$4:B$104,I$4:M$104,5,0) -> C | I57: sh4 | J57: ='Юнит 16'!U29 -> 0 | K57: =J57/J$106 -> 0 | L57: =L56+K57 -> 0.99792208 | M57: =_xlfn.IFS(L57<80%,"A",L57<=95%,"B",L57>95%,"C") -> C
B58: MANNA2103 | C58: ='Юнит 16'!AO56 -> 0 | D58: =C58/C$106 -> 0 | E58: =E57+D58 -> 1.0130681 | F58: =IF(AND(E58<=0),"C",IF(E58<=0.8,"A",IF(E58<=0.95,"B","C"))) -> C | G58: =VLOOKUP(B$4:B$104,I$4:M$104,5,0) -> C | I58: sh06 | J58: ='Юнит 16'!U30 -> 0 | K58: =J58/J$106 -> 0 | L58: =L57+K58 -> 0.99792208 | M58: =_xlfn.IFS(L58<80%,"A",L58<=95%,"B",L58>95%,"C") -> C
B59: MANNA2104 | C59: ='Юнит 16'!AO57 -> 0 | D59: =C59/C$106 -> 0 | E59: =E58+D59 -> 1.0130681 | F59: =IF(AND(E59<=0),"C",IF(E59<=0.8,"A",IF(E59<=0.95,"B","C"))) -> C | G59: =VLOOKUP(B$4:B$104,I$4:M$104,5,0) -> C | I59: sh07 | J59: ='Юнит 16'!U31 -> 0 | K59: =J59/J$106 -> 0 | L59: =L58+K59 -> 0.99792208 | M59: =_xlfn.IFS(L59<80%,"A",L59<=95%,"B",L59>95%,"C") -> C
B60: MANNA2106 | C60: ='Юнит 16'!AO59 -> 0 | D60: =C60/C$106 -> 0 | E60: =E59+D60 -> 1.0130681 | F60: =IF(AND(E60<=0),"C",IF(E60<=0.8,"A",IF(E60<=0.95,"B","C"))) -> C | G60: =VLOOKUP(B$4:B$104,I$4:M$104,5,0) -> C | I60: sh08 | J60: ='Юнит 16'!U32 -> 0 | K60: =J60/J$106 -> 0 | L60: =L59+K60 -> 0.99792208 | M60: =_xlfn.IFS(L60<80%,"A",L60<=95%,"B",L60>95%,"C") -> C
B61: MANNA2109 | C61: ='Юнит 16'!AO62 -> 0 | D61: =C61/C$106 -> 0 | E61: =E60+D61 -> 1.0130681 | F61: =IF(AND(E61<=0),"C",IF(E61<=0.8,"A",IF(E61<=0.95,"B","C"))) -> C | G61: =VLOOKUP(B$4:B$104,I$4:M$104,5,0) -> C | I61: sh10 | J61: ='Юнит 16'!U34 -> 0 | K61: =J61/J$106 -> 0 | L61: =L60+K61 -> 0.99792208 | M61: =_xlfn.IFS(L61<80%,"A",L61<=95%,"B",L61>95%,"C") -> C
B62: MANNA2110 | C62: ='Юнит 16'!AO63 -> 0 | D62: =C62/C$106 -> 0 | E62: =E61+D62 -> 1.0130681 | F62: =IF(AND(E62<=0),"C",IF(E62<=0.8,"A",IF(E62<=0.95,"B","C"))) -> C | G62: =VLOOKUP(B$4:B$104,I$4:M$104,5,0) -> C | I62: sh11 | J62: ='Юнит 16'!U35 -> 0 | K62: =J62/J$106 -> 0 | L62: =L61+K62 -> 0.99792208 | M62: =_xlfn.IFS(L62<80%,"A",L62<=95%,"B",L62>95%,"C") -> C
B63: MANNA2111 | C63: ='Юнит 16'!AO64 -> 0 | D63: =C63/C$106 -> 0 | E63: =E62+D63 -> 1.0130681 | F63: =IF(AND(E63<=0),"C",IF(E63<=0.8,"A",IF(E63<=0.95,"B","C"))) -> C | G63: =VLOOKUP(B$4:B$104,I$4:M$104,5,0) -> C | I63: sh12 | J63: ='Юнит 16'!U36 -> 0 | K63: =J63/J$106 -> 0 | L63: =L62+K63 -> 0.99792208 | M63: =_xlfn.IFS(L63<80%,"A",L63<=95%,"B",L63>95%,"C") -> C
B64: MANNA2114 | C64: ='Юнит 16'!AO67 -> 0 | D64: =C64/C$106 -> 0 | E64: =E63+D64 -> 1.0130681 | F64: =IF(AND(E64<=0),"C",IF(E64<=0.8,"A",IF(E64<=0.95,"B","C"))) -> C | G64: =VLOOKUP(B$4:B$104,I$4:M$104,5,0) -> C | I64: sh13 | J64: ='Юнит 16'!U37 -> 0 | K64: =J64/J$106 -> 0 | L64: =L63+K64 -> 0.99792208 | M64: =_xlfn.IFS(L64<80%,"A",L64<=95%,"B",L64>95%,"C") -> C
B65: MANNA2115 | C65: ='Юнит 16'!AO68 -> 0 | D65: =C65/C$106 -> 0 | E65: =E64+D65 -> 1.0130681 | F65: =IF(AND(E65<=0),"C",IF(E65<=0.8,"A",IF(E65<=0.95,"B","C"))) -> C | G65: =VLOOKUP(B$4:B$104,I$4:M$104,5,0) -> C | I65: sh14 | J65: ='Юнит 16'!U38 -> 0 | K65: =J65/J$106 -> 0 | L65: =L64+K65 -> 0.99792208 | M65: =_xlfn.IFS(L65<80%,"A",L65<=95%,"B",L65>95%,"C") -> C
B66: MANNA2117 | C66: ='Юнит 16'!AO70 -> 0 | D66: =C66/C$106 -> 0 | E66: =E65+D66 -> 1.0130681 | F66: =IF(AND(E66<=0),"C",IF(E66<=0.8,"A",IF(E66<=0.95,"B","C"))) -> C | G66: =VLOOKUP(B$4:B$104,I$4:M$104,5,0) -> C | I66: sh16 | J66: ='Юнит 16'!U40 -> 0 | K66: =J66/J$106 -> 0 | L66: =L65+K66 -> 0.99792208 | M66: =_xlfn.IFS(L66<80%,"A",L66<=95%,"B",L66>95%,"C") -> C
B67: MANNA2119 | C67: ='Юнит 16'!AO72 -> 0 | D67: =C67/C$106 -> 0 | E67: =E66+D67 -> 1.0130681 | F67: =IF(AND(E67<=0),"C",IF(E67<=0.8,"A",IF(E67<=0.95,"B","C"))) -> C | G67: =VLOOKUP(B$4:B$104,I$4:M$104,5,0) -> C | I67: sh17 | J67: ='Юнит 16'!U41 -> 0 | K67: =J67/J$106 -> 0 | L67: =L66+K67 -> 0.99792208 | M67: =_xlfn.IFS(L67<80%,"A",L67<=95%,"B",L67>95%,"C") -> C
B68: MANNA2121 | C68: ='Юнит 16'!AO74 -> 0 | D68: =C68/C$106 -> 0 | E68: =E67+D68 -> 1.0130681 | F68: =IF(AND(E68<=0),"C",IF(E68<=0.8,"A",IF(E68<=0.95,"B","C"))) -> C | G68: =VLOOKUP(B$4:B$104,I$4:M$104,5,0) -> C | I68: ww 1022 черн-серебро | J68: ='Юнит 16'!U46 -> 0 | K68: =J68/J$106 -> 0 | L68: =L67+K68 -> 0.99792208 | M68: =_xlfn.IFS(L68<80%,"A",L68<=95%,"B",L68>95%,"C") -> C
B69: MAIERSHA 03898 C9-08 | C69: ='Юнит 16'!AO94 -> 0 | D69: =C69/C$106 -> 0 | E69: =E68+D69 -> 1.0130681 | F69: =IF(AND(E69<=0),"C",IF(E69<=0.8,"A",IF(E69<=0.95,"B","C"))) -> C | G69: =VLOOKUP(B$4:B$104,I$4:M$104,5,0) -> C | I69: ww 8010 черные | J69: ='Юнит 16'!U51 -> 0 | K69: =J69/J$106 -> 0 | L69: =L68+K69 -> 0.99792208 | M69: =_xlfn.IFS(L69<80%,"A",L69<=95%,"B",L69>95%,"C") -> C
B70: MAIERSHA 03914 C9-124 | C70: ='Юнит 16'!AO95 -> 0 | D70: =C70/C$106 -> 0 | E70: =E69+D70 -> 1.0130681 | F70: =IF(AND(E70<=0),"C",IF(E70<=0.8,"A",IF(E70<=0.95,"B","C"))) -> C | G70: =VLOOKUP(B$4:B$104,I$4:M$104,5,0) -> C | I70: MANNA2101 | J70: ='Юнит 16'!U54 -> 0 | K70: =J70/J$106 -> 0 | L70: =L69+K70 -> 0.99792208 | M70: =_xlfn.IFS(L70<80%,"A",L70<=95%,"B",L70>95%,"C") -> C
B71: MARSTON 7171 C1 | C71: ='Юнит 16'!AO96 -> 0 | D71: =C71/C$106 -> 0 | E71: =E70+D71 -> 1.0130681 | F71: =IF(AND(E71<=0),"C",IF(E71<=0.8,"A",IF(E71<=0.95,"B","C"))) -> C | G71: =VLOOKUP(B$4:B$104,I$4:M$104,5,0) -> C | I71: MANNA2102 | J71: ='Юнит 16'!U55 -> 0 | K71: =J71/J$106 -> 0 | L71: =L70+K71 -> 0.99792208 | M71: =_xlfn.IFS(L71<80%,"A",L71<=95%,"B",L71>95%,"C") -> C
B72: ЧСЖ_тест | C72: ='Юнит 16'!AO99 -> 0 | D72: =C72/C$106 -> 0 | E72: =E71+D72 -> 1.0130681 | F72: =IF(AND(E72<=0),"C",IF(E72<=0.8,"A",IF(E72<=0.95,"B","C"))) -> C | G72: =VLOOKUP(B$4:B$104,I$4:M$104,5,0) -> C | I72: MANNA2103 | J72: ='Юнит 16'!U56 -> 0 | K72: =J72/J$106 -> 0 | L72: =L71+K72 -> 0.99792208 | M72: =_xlfn.IFS(L72<80%,"A",L72<=95%,"B",L72>95%,"C") -> C
B73: кс_черные_тест | C73: ='Юнит 16'!AO101 -> 0 | D73: =C73/C$106 -> 0 | E73: =E72+D73 -> 1.0130681 | F73: =IF(AND(E73<=0),"C",IF(E73<=0.8,"A",IF(E73<=0.95,"B","C"))) -> C | G73: =VLOOKUP(B$4:B$104,I$4:M$104,5,0) -> C | I73: MANNA2104 | J73: ='Юнит 16'!U57 -> 0 | K73: =J73/J$106 -> 0 | L73: =L72+K73 -> 0.99792208 | M73: =_xlfn.IFS(L73<80%,"A",L73<=95%,"B",L73>95%,"C") -> C
B74: 1022_коричневые_тест | C74: ='Юнит 16'!AO103 -> 0 | D74: =C74/C$106 -> 0 | E74: =E73+D74 -> 1.0130681 | F74: =IF(AND(E74<=0),"C",IF(E74<=0.8,"A",IF(E74<=0.95,"B","C"))) -> C | G74: =VLOOKUP(B$4:B$104,I$4:M$104,5,0) -> C | I74: MANNA2106 | J74: ='Юнит 16'!U59 -> 0 | K74: =J74/J$106 -> 0 | L74: =L73+K74 -> 0.99792208 | M74: =_xlfn.IFS(L74<80%,"A",L74<=95%,"B",L74>95%,"C") -> C
B75: ww 8010 черные | C75: ='Юнит 16'!AO51 -> -0.93309649 | D75: =C75/C$106 -> -1.1081391e-06 | E75: =E74+D75 -> 1.013067 | F75: =IF(AND(E75<=0),"C",IF(E75<=0.8,"A",IF(E75<=0.95,"B","C"))) -> C | G75: =VLOOKUP(B$4:B$104,I$4:M$104,5,0) -> C | I75: MANNA2109 | J75: ='Юнит 16'!U62 -> 0 | K75: =J75/J$106 -> 0 | L75: =L74+K75 -> 0.99792208 | M75: =_xlfn.IFS(L75<80%,"A",L75<=95%,"B",L75>95%,"C") -> C
B76: MANNA2102 | C76: ='Юнит 16'!AO55 -> -0.93309649 | D76: =C76/C$106 -> -1.1081391e-06 | E76: =E49+D76 -> 1.013067 | F76: =IF(AND(E76<=0),"C",IF(E76<=0.8,"A",IF(E76<=0.95,"B","C"))) -> C | G76: =VLOOKUP(B$4:B$104,I$4:M$104,5,0) -> C | I76: MANNA2110 | J76: ='Юнит 16'!U63 -> 0 | K76: =J76/J$106 -> 0 | L76: =L49+K76 -> 0.99584416 | M76: =_xlfn.IFS(L76<80%,"A",L76<=95%,"B",L76>95%,"C") -> C
B77: Linhai Baiyi розовая линза | C77: ='Юнит 16'!AO88 -> -1.63 | D77: =C77/C$106 -> -1.9357769e-06 | E77: =E76+D77 -> 1.013065 | F77: =IF(AND(E77<=0),"C",IF(E77<=0.8,"A",IF(E77<=0.95,"B","C"))) -> C | G77: =VLOOKUP(B$4:B$104,I$4:M$104,5,0) -> C | I77: MANNA2111 | J77: ='Юнит 16'!U64 -> 0 | K77: =J77/J$106 -> 0 | L77: =L76+K77 -> 0.99584416 | M77: =_xlfn.IFS(L77<80%,"A",L77<=95%,"B",L77>95%,"C") -> C
B78: MANNA2113 | C78: ='Юнит 16'!AO66 -> -1.866193 | D78: =C78/C$106 -> -2.2162781e-06 | E78: =E77+D78 -> 1.0130628 | F78: =IF(AND(E78<=0),"C",IF(E78<=0.8,"A",IF(E78<=0.95,"B","C"))) -> C | G78: =VLOOKUP(B$4:B$104,I$4:M$104,5,0) -> C | I78: MANNA2112 | J78: ='Юнит 16'!U65 -> 0 | K78: =J78/J$106 -> 0 | L78: =L77+K78 -> 0.99584416 | M78: =_xlfn.IFS(L78<80%,"A",L78<=95%,"B",L78>95%,"C") -> C
B79: MANNA2112 | C79: ='Юнит 16'!AO65 -> -2.1830965 | D79: =C79/C$106 -> -2.5926306e-06 | E79: =E78+D79 -> 1.0130602 | F79: =IF(AND(E79<=0),"C",IF(E79<=0.8,"A",IF(E79<=0.95,"B","C"))) -> C | G79: =VLOOKUP(B$4:B$104,I$4:M$104,5,0) -> C | I79: MANNA2113 | J79: ='Юнит 16'!U66 -> 0 | K79: =J79/J$106 -> 0 | L79: =L78+K79 -> 0.99584416 | M79: =_xlfn.IFS(L79<80%,"A",L79<=95%,"B",L79>95%,"C") -> C
B80: MANNA2118 | C80: ='Юнит 16'!AO71 -> -4.596193 | D80: =C80/C$106 -> -5.4584076e-06 | E80: =E79+D80 -> 1.0130548 | F80: =IF(AND(E80<=0),"C",IF(E80<=0.8,"A",IF(E80<=0.95,"B","C"))) -> C | G80: =VLOOKUP(B$4:B$104,I$4:M$104,5,0) -> C | I80: MANNA2114 | J80: ='Юнит 16'!U67 -> 0 | K80: =J80/J$106 -> 0 | L80: =L79+K80 -> 0.99584416 | M80: =_xlfn.IFS(L80<80%,"A",L80<=95%,"B",L80>95%,"C") -> C
B81: sh17 | C81: ='Юнит 16'!AO41 -> -37.323859 | D81: =C81/C$106 -> -4.4325562e-05 | E81: =E80+D81 -> 1.0130104 | F81: =IF(AND(E81<=0),"C",IF(E81<=0.8,"A",IF(E81<=0.95,"B","C"))) -> C | G81: =VLOOKUP(B$4:B$104,I$4:M$104,5,0) -> C | I81: MANNA2115 | J81: ='Юнит 16'!U68 -> 0 | K81: =J81/J$106 -> 0 | L81: =L80+K81 -> 0.99584416 | M81: =_xlfn.IFS(L81<80%,"A",L81<=95%,"B",L81>95%,"C") -> C
B82: Ли Сян ретро серебро | C82: ='Юнит 16'!AO93 -> -43.110763 | D82: =C82/C$106 -> -5.1198049e-05 | E82: =E81+D82 -> 1.0129592 | F82: =IF(AND(E82<=0),"C",IF(E82<=0.8,"A",IF(E82<=0.95,"B","C"))) -> C | G82: =VLOOKUP(B$4:B$104,I$4:M$104,5,0) -> C | I82: MANNA2117 | J82: ='Юнит 16'!U70 -> 0 | K82: =J82/J$106 -> 0 | L82: =L81+K82 -> 0.99584416 | M82: =_xlfn.IFS(L82<80%,"A",L82<=95%,"B",L82>95%,"C") -> C
B83: Taizhou Rayen sport розовый | C83: ='Юнит 16'!AO90 -> -44.788631 | D83: =C83/C$106 -> -5.3190675e-05 | E83: =E82+D83 -> 1.012906 | F83: =IF(AND(E83<=0),"C",IF(E83<=0.8,"A",IF(E83<=0.95,"B","C"))) -> C | G83: =VLOOKUP(B$4:B$104,I$4:M$104,5,0) -> C | I83: MANNA2118 | J83: ='Юнит 16'!U71 -> 0 | K83: =J83/J$106 -> 0 | L83: =L82+K83 -> 0.99584416 | M83: =_xlfn.IFS(L83<80%,"A",L83<=95%,"B",L83>95%,"C") -> C
B84: POMILED 08247 C4-08 | C84: ='Юнит 16'!AO97 -> -67.183096 | D84: =C84/C$106 -> -7.9786189e-05 | E84: =E83+D84 -> 1.0128263 | F84: =IF(AND(E84<=0),"C",IF(E84<=0.8,"A",IF(E84<=0.95,"B","C"))) -> C | G84: =VLOOKUP(B$4:B$104,I$4:M$104,5,0) -> C | I84: MANNA2119 | J84: ='Юнит 16'!U72 -> 0 | K84: =J84/J$106 -> 0 | L84: =L83+K84 -> 0.99584416 | M84: =_xlfn.IFS(L84<80%,"A",L84<=95%,"B",L84>95%,"C") -> C
B85: sh13 | C85: ='Юнит 16'!AO37 -> -91.89 | D85: =C85/C$106 -> -0.00010912794 | E85: =E84+D85 -> 1.0127171 | F85: =IF(AND(E85<=0),"C",IF(E85<=0.8,"A",IF(E85<=0.95,"B","C"))) -> C | G85: =VLOOKUP(B$4:B$104,I$4:M$104,5,0) -> C | I85: MANNA2121 | J85: ='Юнит 16'!U74 -> 0 | K85: =J85/J$106 -> 0 | L85: =L84+K85 -> 0.99584416 | M85: =_xlfn.IFS(L85<80%,"A",L85<=95%,"B",L85>95%,"C") -> C
B86: sh10 | C86: ='Юнит 16'!AO34 -> -94.37 | D86: =C86/C$106 -> -0.00011207317 | E86: =E85+D86 -> 1.0126051 | F86: =IF(AND(E86<=0),"C",IF(E86<=0.8,"A",IF(E86<=0.95,"B","C"))) -> C | G86: =VLOOKUP(B$4:B$104,I$4:M$104,5,0) -> C | I86: Chenlong черные | J86: ='Юнит 16'!U76 -> 0 | K86: =J86/J$106 -> 0 | L86: =L85+K86 -> 0.99584416 | M86: =_xlfn.IFS(L86<80%,"A",L86<=95%,"B",L86>95%,"C") -> C
B87: sh14 | C87: ='Юнит 16'!AO38 -> -117.98005 | D87: =C87/C$106 -> -0.00014011231 | E87: =E86+D87 -> 1.0124649 | F87: =IF(AND(E87<=0),"C",IF(E87<=0.8,"A",IF(E87<=0.95,"B","C"))) -> C | G87: =VLOOKUP(B$4:B$104,I$4:M$104,5,0) -> C | I87: Hengda Optical леопард | J87: ='Юнит 16'!U82 -> 0 | K87: =J87/J$106 -> 0 | L87: =L86+K87 -> 0.99584416 | M87: =_xlfn.IFS(L87<80%,"A",L87<=95%,"B",L87>95%,"C") -> C
B88: MANNA2101 | C88: ='Юнит 16'!AO54 -> -159.11193 | D88: =C88/C$106 -> -0.00018896025 | E88: =E87+D88 -> 1.012276 | F88: =IF(AND(E88<=0),"C",IF(E88<=0.8,"A",IF(E88<=0.95,"B","C"))) -> C | G88: =VLOOKUP(B$4:B$104,I$4:M$104,5,0) -> C | I88: Qianai коричневые | J88: ='Юнит 16'!U84 -> 0 | K88: =J88/J$106 -> 0 | L88: =L87+K88 -> 0.99584416 | M88: =_xlfn.IFS(L88<80%,"A",L88<=95%,"B",L88>95%,"C") -> C
B89: ridges brand 01 | C89: ='Юнит 16'!AO104 -> -167.75726 | D89: =C89/C$106 -> -0.00019922739 | E89: =E88+D89 -> 1.0120768 | F89: =IF(AND(E89<=0),"C",IF(E89<=0.8,"A",IF(E89<=0.95,"B","C"))) -> C | G89: =VLOOKUP(B$4:B$104,I$4:M$104,5,0) -> C | I89: Keming Aishi коричневые | J89: ='Юнит 16'!U85 -> 0 | K89: =J89/J$106 -> 0 | L89: =L88+K89 -> 0.99584416 | M89: =_xlfn.IFS(L89<80%,"A",L89<=95%,"B",L89>95%,"C") -> C
B90: sh16 | C90: ='Юнит 16'!AO40 -> -200.57361 | D90: =C90/C$106 -> -0.00023819985 | E90: =E89+D90 -> 1.0118386 | F90: =IF(AND(E90<=0),"C",IF(E90<=0.8,"A",IF(E90<=0.95,"B","C"))) -> C | G90: =VLOOKUP(B$4:B$104,I$4:M$104,5,0) -> C | I90: Linhai Baiyi коричневая линза | J90: ='Юнит 16'!U86 -> 0 | K90: =J90/J$106 -> 0 | L90: =L89+K90 -> 0.99584416 | M90: =_xlfn.IFS(L90<80%,"A",L90<=95%,"B",L90>95%,"C") -> C
B91: Qianai коричневые | C91: ='Юнит 16'!AO84 -> -274.64147 | D91: =C91/C$106 -> -0.00032616235 | E91: =E90+D91 -> 1.0115124 | F91: =IF(AND(E91<=0),"C",IF(E91<=0.8,"A",IF(E91<=0.95,"B","C"))) -> C | G91: =VLOOKUP(B$4:B$104,I$4:M$104,5,0) -> C | I91: Linhai Baiyi розовая линза | J91: ='Юнит 16'!U88 -> 0 | K91: =J91/J$106 -> 0 | L91: =L90+K91 -> 0.99584416 | M91: =_xlfn.IFS(L91<80%,"A",L91<=95%,"B",L91>95%,"C") -> C
B92: Ли Сян ретро золото | C92: ='Юнит 16'!AO92 -> -306.48315 | D92: =C92/C$106 -> -0.00036397731 | E92: =E91+D92 -> 1.0111484 | F92: =IF(AND(E92<=0),"C",IF(E92<=0.8,"A",IF(E92<=0.95,"B","C"))) -> C | G92: =VLOOKUP(B$4:B$104,I$4:M$104,5,0) -> C | I92: Taizhou Rayen sport розовый | J92: ='Юнит 16'!U90 -> 0 | K92: =J92/J$106 -> 0 | L92: =L91+K92 -> 0.99584416 | M92: =_xlfn.IFS(L92<80%,"A",L92<=95%,"B",L92>95%,"C") -> C
B93: Hengda Optical леопард | C93: ='Юнит 16'!AO82 -> -340.39005 | D93: =C93/C$106 -> -0.00040424492 | E93: =E92+D93 -> 1.0107442 | F93: =IF(AND(E93<=0),"C",IF(E93<=0.8,"A",IF(E93<=0.95,"B","C"))) -> C | G93: =VLOOKUP(B$4:B$104,I$4:M$104,5,0) -> C | I93: Иу Диту серый | J93: ='Юнит 16'!U91 -> 0 | K93: =J93/J$106 -> 0 | L93: =L92+K93 -> 0.99584416 | M93: =_xlfn.IFS(L93<80%,"A",L93<=95%,"B",L93>95%,"C") -> C
B94: MANNA2105 | C94: ='Юнит 16'!AO58 -> -433.75023 | D94: =C94/C$106 -> -0.00051511883 | E94: =E93+D94 -> 1.0102291 | F94: =IF(AND(E94<=0),"C",IF(E94<=0.8,"A",IF(E94<=0.95,"B","C"))) -> C | G94: =VLOOKUP(B$4:B$104,I$4:M$104,5,0) -> C | I94: Ли Сян ретро золото | J94: ='Юнит 16'!U92 -> 0 | K94: =J94/J$106 -> 0 | L94: =L93+K94 -> 0.99584416 | M94: =_xlfn.IFS(L94<80%,"A",L94<=95%,"B",L94>95%,"C") -> C
B95: Chenlong черные | C95: ='Юнит 16'!AO76 -> -524.93218 | D95: =C95/C$106 -> -0.0006234059 | E95: =E94+D95 -> 1.0096057 | F95: =IF(AND(E95<=0),"C",IF(E95<=0.8,"A",IF(E95<=0.95,"B","C"))) -> C | G95: =VLOOKUP(B$4:B$104,I$4:M$104,5,0) -> C | I95: Ли Сян ретро серебро | J95: ='Юнит 16'!U93 -> 0 | K95: =J95/J$106 -> 0 | L95: =L94+K95 -> 0.99584416 | M95: =_xlfn.IFS(L95<80%,"A",L95<=95%,"B",L95>95%,"C") -> C
B96: Guangdu серебро серая линза | C96: ='Юнит 16'!AO80 -> -642.22065 | D96: =C96/C$106 -> -0.00076269689 | E96: =E95+D96 -> 1.008843 | F96: =IF(AND(E96<=0),"C",IF(E96<=0.8,"A",IF(E96<=0.95,"B","C"))) -> C | G96: =VLOOKUP(B$4:B$104,I$4:M$104,5,0) -> C | I96: MAIERSHA 03898 C9-08 | J96: ='Юнит 16'!U94 -> 0 | K96: =J96/J$106 -> 0 | L96: =L95+K96 -> 0.99584416 | M96: =_xlfn.IFS(L96<80%,"A",L96<=95%,"B",L96>95%,"C") -> C
B97: sh15 | C97: ='Юнит 16'!AO39 -> -653.74717 | D97: =C97/C$106 -> -0.0007763857 | E97: =E96+D97 -> 1.0080666 | F97: =IF(AND(E97<=0),"C",IF(E97<=0.8,"A",IF(E97<=0.95,"B","C"))) -> C | G97: =VLOOKUP(B$4:B$104,I$4:M$104,5,0) -> C | I97: MAIERSHA 03914 C9-124 | J97: ='Юнит 16'!U95 -> 0 | K97: =J97/J$106 -> 0 | L97: =L96+K97 -> 0.99584416 | M97: =_xlfn.IFS(L97<80%,"A",L97<=95%,"B",L97>95%,"C") -> C
B98: Keming Aishi коричневые | C98: ='Юнит 16'!AO85 -> -658.31909 | D98: =C98/C$106 -> -0.00078181528 | E98: =E97+D98 -> 1.0072848 | F98: =IF(AND(E98<=0),"C",IF(E98<=0.8,"A",IF(E98<=0.95,"B","C"))) -> C | G98: =VLOOKUP(B$4:B$104,I$4:M$104,5,0) -> C | I98: MARSTON 7171 C1 | J98: ='Юнит 16'!U96 -> 0 | K98: =J98/J$106 -> 0 | L98: =L97+K98 -> 0.99584416 | M98: =_xlfn.IFS(L98<80%,"A",L98<=95%,"B",L98>95%,"C") -> C
B99: Guangdu золото серая линза | C99: ='Юнит 16'!AO79 -> -720.44591 | D99: =C99/C$106 -> -0.00085559667 | E99: =E93+D99 -> 1.0098886 | F99: =IF(AND(E99<=0),"C",IF(E99<=0.8,"A",IF(E99<=0.95,"B","C"))) -> C | G99: =VLOOKUP(B$4:B$104,I$4:M$104,5,0) -> C | I99: POMILED 08247 C4-08 | J99: ='Юнит 16'!U97 -> 0 | K99: =J99/J$106 -> 0 | L99: =L93+K99 -> 0.99584416 | M99: =_xlfn.IFS(L99<80%,"A",L99<=95%,"B",L99>95%,"C") -> C
B100: Chenlong белые | C100: ='Юнит 16'!AO78 -> -785.18557 | D100: =C100/C$106 -> -0.00093248106 | E100: =E94+D100 -> 1.0092966 | F100: =IF(AND(E100<=0),"C",IF(E100<=0.8,"A",IF(E100<=0.95,"B","C"))) -> C | G100: =VLOOKUP(B$4:B$104,I$4:M$104,5,0) -> C | I100: ЧСЖ_тест | J100: ='Юнит 16'!U99 -> 0 | K100: =J100/J$106 -> 0 | L100: =L94+K100 -> 0.99584416 | M100: =_xlfn.IFS(L100<80%,"A",L100<=95%,"B",L100>95%,"C") -> C
B101: Иу Диту серый | C101: ='Юнит 16'!AO91 -> -805.06883 | D101: =C101/C$106 -> -0.00095609428 | E101: =E95+D101 -> 1.0086496 | F101: =IF(AND(E101<=0),"C",IF(E101<=0.8,"A",IF(E101<=0.95,"B","C"))) -> C | G101: =VLOOKUP(B$4:B$104,I$4:M$104,5,0) -> C | I101: кс_черные_тест | J101: ='Юнит 16'!U101 -> 0 | K101: =J101/J$106 -> 0 | L101: =L95+K101 -> 0.99584416 | M101: =_xlfn.IFS(L101<80%,"A",L101<=95%,"B",L101>95%,"C") -> C
...

Sheet АВС 15
B2: ОЧКИ
C3: Прибыль | D3: % прибыль | E3: Доля | F3: ABC прибыль | G3: ABC кол-во | J3: Кол-во | K3: % кол-во | L3: Доля | M3: ABC кол-во
B4: QS черные PZ | C4: ='Юнит 15'!AO4 -> 182652.84 | D4: =C4/C$105 -> 0.18340625 | E4: =D4 -> 0.18340625 | F4: =IF(AND(E4<=0),"C",IF(E4<=0.8,"A",IF(E4<=0.95,"B","C"))) -> A | G4: =VLOOKUP(B$4:B$104,I$4:M$104,5,0) -> A | I4: QS черные PZ | J4: ='Юнит 15'!U4 -> 315 | K4: =J4/J$105 -> 0.14879547 | L4: =K4 -> 0.14879547 | M4: =_xlfn.IFS(L4<80%,"A",L4<=95%,"B",L4>95%,"C") -> A | P4: A | Q4: 0.8
B5: flip черные | C5: ='Юнит 15'!AO13 -> 101216.48 | D5: =C5/C$105 -> 0.10163398 | E5: =E4+D5 -> 0.28504023 | F5: =IF(AND(E5<=0),"C",IF(E5<=0.8,"A",IF(E5<=0.95,"B","C"))) -> A | G5: =VLOOKUP(B$4:B$104,I$4:M$104,5,0) -> A | I5: flip черные | J5: ='Юнит 15'!U13 -> 190 | K5: =J5/J$105 -> 0.089749646 | L5: =L4+K5 -> 0.23854511 | M5: =_xlfn.IFS(L5<80%,"A",L5<=95%,"B",L5>95%,"C") -> A | P5: B | Q5: 0.15
B6: th черн | C6: ='Юнит 15'!AO9 -> 93844.337 | D6: =C6/C$105 -> 0.094231428 | E6: =E5+D6 -> 0.37927166 | F6: =IF(AND(E6<=0),"C",IF(E6<=0.8,"A",IF(E6<=0.95,"B","C"))) -> A | G6: =VLOOKUP(B$4:B$104,I$4:M$104,5,0) -> A | I6: th черн | J6: ='Юнит 15'!U9 -> 180 | K6: =J6/J$105 -> 0.08502598 | L6: =L5+K6 -> 0.32357109 | M6: =_xlfn.IFS(L6<80%,"A",L6<=95%,"B",L6>95%,"C") -> A | P6: C | Q6: 0.05
B7: flip коричневые | C7: ='Юнит 15'!AO16 -> 81890.737 | D7: =C7/C$105 -> 0.082228522 | E7: =E6+D7 -> 0.46150018 | F7: =IF(AND(E7<=0),"C",IF(E7<=0.8,"A",IF(E7<=0.95,"B","C"))) -> A | G7: =VLOOKUP(B$4:B$104,I$4:M$104,5,0) -> A | I7: QS коричневые PZ | J7: ='Юнит 15'!U7 -> 155 | K7: =J7/J$105 -> 0.073216816 | L7: =L6+K7 -> 0.39678791 | M7: =_xlfn.IFS(L7<80%,"A",L7<=95%,"B",L7>95%,"C") -> A
B8: QS коричневые PZ | C8: ='Юнит 15'!AO7 -> 72275.075 | D8: =C8/C$105 -> 0.072573197 | E8: =E7+D8 -> 0.53407338 | F8: =IF(AND(E8<=0),"C",IF(E8<=0.8,"A",IF(E8<=0.95,"B","C"))) -> A | G8: =VLOOKUP(B$4:B$104,I$4:M$104,5,0) -> A | I8: th син | J8: ='Юнит 15'!U10 -> 153 | K8: =J8/J$105 -> 0.072272083 | L8: =L7+K8 -> 0.46905999 | M8: =_xlfn.IFS(L8<80%,"A",L8<=95%,"B",L8>95%,"C") -> A
B9: QS синие PZ | C9: ='Юнит 15'!AO5 -> 62875.189 | D9: =C9/C$105 -> 0.063134538 | E9: =E8+D9 -> 0.59720791 | F9: =IF(AND(E9<=0),"C",IF(E9<=0.8,"A",IF(E9<=0.95,"B","C"))) -> A | G9: =VLOOKUP(B$4:B$104,I$4:M$104,5,0) -> A | I9: flip коричневые | J9: ='Юнит 15'!U16 -> 147 | K9: =J9/J$105 -> 0.069437884 | L9: =L8+K9 -> 0.53849787 | M9: =_xlfn.IFS(L9<80%,"A",L9<=95%,"B",L9>95%,"C") -> A
B10: черные с железкой классика | C10: ='Юнит 15'!AO3 -> 59823.329 | D10: =C10/C$105 -> 0.06007009 | E10: =E9+D10 -> 0.657278 | F10: =IF(AND(E10<=0),"C",IF(E10<=0.8,"A",IF(E10<=0.95,"B","C"))) -> A | G10: =VLOOKUP(B$4:B$104,I$4:M$104,5,0) -> A | I10: QS синие PZ | J10: ='Юнит 15'!U5 -> 124 | K10: =J10/J$105 -> 0.058573453 | L10: =L9+K10 -> 0.59707133 | M10: =_xlfn.IFS(L10<80%,"A",L10<=95%,"B",L10>95%,"C") -> A
B11: th син | C11: ='Юнит 15'!AO10 -> 57630.333 | D11: =C11/C$105 -> 0.057868048 | E11: =E10+D11 -> 0.71514605 | F11: =IF(AND(E11<=0),"C",IF(E11<=0.8,"A",IF(E11<=0.95,"B","C"))) -> A | G11: =VLOOKUP(B$4:B$104,I$4:M$104,5,0) -> A | I11: черные с железкой классика | J11: ='Юнит 15'!U3 -> 116 | K11: =J11/J$105 -> 0.054794521 | L11: =L10+K11 -> 0.65186585 | M11: =_xlfn.IFS(L11<80%,"A",L11<=95%,"B",L11>95%,"C") -> A
B12: th коричн | C12: ='Юнит 15'!AO12 -> 43739.958 | D12: =C12/C$105 -> 0.043920377 | E12: =E11+D12 -> 0.75906643 | F12: =IF(AND(E12<=0),"C",IF(E12<=0.8,"A",IF(E12<=0.95,"B","C"))) -> A | G12: =VLOOKUP(B$4:B$104,I$4:M$104,5,0) -> A | I12: th коричн | J12: ='Юнит 15'!U12 -> 108 | K12: =J12/J$105 -> 0.051015588 | L12: =L11+K12 -> 0.70288144 | M12: =_xlfn.IFS(L12<80%,"A",L12<=95%,"B",L12>95%,"C") -> A
B13: th желт | C13: ='Юнит 15'!AO11 -> 31038.073 | D13: =C13/C$105 -> 0.031166099 | E13: =E12+D13 -> 0.79023253 | F13: =IF(AND(E13<=0),"C",IF(E13<=0.8,"A",IF(E13<=0.95,"B","C"))) -> A | G13: =VLOOKUP(B$4:B$104,I$4:M$104,5,0) -> A | I13: th желт | J13: ='Юнит 15'!U11 -> 85 | K13: =J13/J$105 -> 0.040151157 | L13: =L12+K13 -> 0.74303259 | M13: =_xlfn.IFS(L13<80%,"A",L13<=95%,"B",L13>95%,"C") -> A
B14: QS желтые PZ | C14: ='Юнит 15'!AO6 -> 30960.496 | D14: =C14/C$105 -> 0.031088203 | E14: =E13+D14 -> 0.82132073 | F14: =IF(AND(E14<=0),"C",IF(E14<=0.8,"A",IF(E14<=0.95,"B","C"))) -> B | G14: =VLOOKUP(B$4:B$104,I$4:M$104,5,0) -> A | I14: QS желтые PZ | J14: ='Юнит 15'!U6 -> 69 | K14: =J14/J$105 -> 0.032593292 | L14: =L13+K14 -> 0.77562589 | M14: =_xlfn.IFS(L14<80%,"A",L14<=95%,"B",L14>95%,"C") -> A
B15: flip синие | C15: ='Юнит 15'!AO14 -> 23642.762 | D15: =C15/C$105 -> 0.023740285 | E15: =E14+D15 -> 0.84506102 | F15: =IF(AND(E15<=0),"C",IF(E15<=0.8,"A",IF(E15<=0.95,"B","C"))) -> B | G15: =VLOOKUP(B$4:B$104,I$4:M$104,5,0) -> B | I15: flip синие | J15: ='Юнит 15'!U14 -> 52 | K15: =J15/J$105 -> 0.024563061 | L15: =L14+K15 -> 0.80018895 | M15: =_xlfn.IFS(L15<80%,"A",L15<=95%,"B",L15>95%,"C") -> B
B16: flip желтые | C16: ='Юнит 15'!AO15 -> 21256.768 | D16: =C16/C$105 -> 0.021344448 | E16: =E15+D16 -> 0.86640546 | F16: =IF(AND(E16<=0),"C",IF(E16<=0.8,"A",IF(E16<=0.95,"B","C"))) -> B | G16: =VLOOKUP(B$4:B$104,I$4:M$104,5,0) -> B | I16: flip желтые | J16: ='Юнит 15'!U15 -> 49 | K16: =J16/J$105 -> 0.023145961 | L16: =L15+K16 -> 0.82333491 | M16: =_xlfn.IFS(L16<80%,"A",L16<=95%,"B",L16>95%,"C") -> B
B17: ww 2018 черные | C17: ='Юнит 15'!AO49 -> 19409.455 | D17: =C17/C$105 -> 0.019489516 | E17: =E16+D17 -> 0.88589498 | F17: =IF(AND(E17<=0),"C",IF(E17<=0.8,"A",IF(E17<=0.95,"B","C"))) -> B | G17: =VLOOKUP(B$4:B$104,I$4:M$104,5,0) -> B | I17: sh3 | J17: ='Юнит 15'!U28 -> 49 | K17: =J17/J$105 -> 0.023145961 | L17: =L16+K17 -> 0.84648087 | M17: =_xlfn.IFS(L17<80%,"A",L17<=95%,"B",L17>95%,"C") -> B
B18: ww 1022 коричневые | C18: ='Юнит 15'!AO48 -> 18206.416 | D18: =C18/C$105 -> 0.018281515 | E18: =E17+D18 -> 0.9041765 | F18: =IF(AND(E18<=0),"C",IF(E18<=0.8,"A",IF(E18<=0.95,"B","C"))) -> B | G18: =VLOOKUP(B$4:B$104,I$4:M$104,5,0) -> B | I18: ww 1022 коричневые | J18: ='Юнит 15'!U48 -> 45 | K18: =J18/J$105 -> 0.021256495 | L18: =L17+K18 -> 0.86773736 | M18: =_xlfn.IFS(L18<80%,"A",L18<=95%,"B",L18>95%,"C") -> B
B19: ww 2018 желтые | C19: ='Юнит 15'!AO50 -> 15255.86 | D19: =C19/C$105 -> 0.015318787 | E19: =E18+D19 -> 0.91949528 | F19: =IF(AND(E19<=0),"C",IF(E19<=0.8,"A",IF(E19<=0.95,"B","C"))) -> B | G19: =VLOOKUP(B$4:B$104,I$4:M$104,5,0) -> B | I19: ww 2018 черные | J19: ='Юнит 15'!U49 -> 37 | K19: =J19/J$105 -> 0.017477563 | L19: =L18+K19 -> 0.88521493 | M19: =_xlfn.IFS(L19<80%,"A",L19<=95%,"B",L19>95%,"C") -> B
B20: sh3 | C20: ='Юнит 15'!AO28 -> 13706.162 | D20: =C20/C$105 -> 0.013762698 | E20: =E19+D20 -> 0.93325798 | F20: =IF(AND(E20<=0),"C",IF(E20<=0.8,"A",IF(E20<=0.95,"B","C"))) -> B | G20: =VLOOKUP(B$4:B$104,I$4:M$104,5,0) -> B | I20: ww 203 черные | J20: ='Юнит 15'!U44 -> 33 | K20: =J20/J$105 -> 0.015588096 | L20: =L19+K20 -> 0.90080302 | M20: =_xlfn.IFS(L20<80%,"A",L20<=95%,"B",L20>95%,"C") -> B
B21: MR8854 C2 Жен | C21: ='Юнит 15'!AO8 -> 13507.963 | D21: =C21/C$105 -> 0.013563681 | E21: =E20+D21 -> 0.94682166 | F21: =IF(AND(E21<=0),"C",IF(E21<=0.8,"A",IF(E21<=0.95,"B","C"))) -> B | G21: =VLOOKUP(B$4:B$104,I$4:M$104,5,0) -> B | I21: ww 2018 желтые | J21: ='Юнит 15'!U50 -> 33 | K21: =J21/J$105 -> 0.015588096 | L21: =L20+K21 -> 0.91639112 | M21: =_xlfn.IFS(L21<80%,"A",L21<=95%,"B",L21>95%,"C") -> B
B22: wwl8032 коричневые золото | C22: ='Юнит 15'!AO17 -> 12267.25 | D22: =C22/C$105 -> 0.01231785 | E22: =E21+D22 -> 0.95913951 | F22: =IF(AND(E22<=0),"C",IF(E22<=0.8,"A",IF(E22<=0.95,"B","C"))) -> C | G22: =VLOOKUP(B$4:B$104,I$4:M$104,5,0) -> B | I22: MR8854 C2 Жен | J22: ='Юнит 15'!U8 -> 29 | K22: =J22/J$105 -> 0.01369863 | L22: =L21+K22 -> 0.93008975 | M22: =_xlfn.IFS(L22<80%,"A",L22<=95%,"B",L22>95%,"C") -> B
B23: wwl8032 хром металл | C23: ='Юнит 15'!AO18 -> 12021.438 | D23: =C23/C$105 -> 0.012071024 | E23: =E22+D23 -> 0.97121054 | F23: =IF(AND(E23<=0),"C",IF(E23<=0.8,"A",IF(E23<=0.95,"B","C"))) -> C | G23: =VLOOKUP(B$4:B$104,I$4:M$104,5,0) -> C | I23: wwl8032 коричневые золото | J23: ='Юнит 15'!U17 -> 29 | K23: =J23/J$105 -> 0.01369863 | L23: =L22+K23 -> 0.94378838 | M23: =_xlfn.IFS(L23<80%,"A",L23<=95%,"B",L23>95%,"C") -> B
B24: ww 203 черные | C24: ='Юнит 15'!AO44 -> 11867.158 | D24: =C24/C$105 -> 0.011916108 | E24: =E23+D24 -> 0.98312664 | F24: =IF(AND(E24<=0),"C",IF(E24<=0.8,"A",IF(E24<=0.95,"B","C"))) -> C | G24: =VLOOKUP(B$4:B$104,I$4:M$104,5,0) -> B | I24: wwl8032 хром металл | J24: ='Юнит 15'!U18 -> 23 | K24: =J24/J$105 -> 0.010864431 | L24: =L23+K24 -> 0.95465281 | M24: =_xlfn.IFS(L24<80%,"A",L24<=95%,"B",L24>95%,"C") -> C
B25: ww 1022 черные | C25: ='Юнит 15'!AO45 -> 7964.8073 | D25: =C25/C$105 -> 0.0079976608 | E25: =E24+D25 -> 0.9911243 | F25: =IF(AND(E25<=0),"C",IF(E25<=0.8,"A",IF(E25<=0.95,"B","C"))) -> C | G25: =VLOOKUP(B$4:B$104,I$4:M$104,5,0) -> C | I25: ww 1022 черные | J25: ='Юнит 15'!U45 -> 19 | K25: =J25/J$105 -> 0.0089749646 | L25: =L24+K25 -> 0.96362778 | M25: =_xlfn.IFS(L25<80%,"A",L25<=95%,"B",L25>95%,"C") -> C
B26: sports синие | C26: ='Юнит 15'!AO20 -> 3974.1096 | D26: =C26/C$105 -> 0.0039905021 | E26: =E25+D26 -> 0.99511481 | F26: =IF(AND(E26<=0),"C",IF(E26<=0.8,"A",IF(E26<=0.95,"B","C"))) -> C | G26: =VLOOKUP(B$4:B$104,I$4:M$104,5,0) -> C | I26: sports синие | J26: ='Юнит 15'!U20 -> 10 | K26: =J26/J$105 -> 0.0047236656 | L26: =L25+K26 -> 0.96835144 | M26: =_xlfn.IFS(L26<80%,"A",L26<=95%,"B",L26>95%,"C") -> C
B27: ww 1022 желтые | C27: ='Юнит 15'!AO47 -> 2830.6558 | D27: =C27/C$105 -> 0.0028423318 | E27: =E26+D27 -> 0.99795714 | F27: =IF(AND(E27<=0),"C",IF(E27<=0.8,"A",IF(E27<=0.95,"B","C"))) -> C | G27: =VLOOKUP(B$4:B$104,I$4:M$104,5,0) -> C | I27: sports зеленые | J27: ='Юнит 15'!U21 -> 5 | K27: =J27/J$105 -> 0.0023618328 | L27: =L26+K27 -> 0.97071327 | M27: =_xlfn.IFS(L27<80%,"A",L27<=95%,"B",L27>95%,"C") -> C
B28: sh16 | C28: ='Юнит 15'!AO40 -> 1559.1891 | D28: =C28/C$105 -> 0.0015656205 | E28: =E27+D28 -> 0.99952276 | F28: =IF(AND(E28<=0),"C",IF(E28<=0.8,"A",IF(E28<=0.95,"B","C"))) -> C | G28: =VLOOKUP(B$4:B$104,I$4:M$104,5,0) -> C | I28: sports красные | J28: ='Юнит 15'!U22 -> 5 | K28: =J28/J$105 -> 0.0023618328 | L28: =L27+K28 -> 0.97307511 | M28: =_xlfn.IFS(L28<80%,"A",L28<=95%,"B",L28>95%,"C") -> C
B29: sports зеленые | C29: ='Юнит 15'!AO21 -> 1162.1394 | D29: =C29/C$105 -> 0.0011669331 | E29: =E28+D29 -> 1.0006897 | F29: =IF(AND(E29<=0),"C",IF(E29<=0.8,"A",IF(E29<=0.95,"B","C"))) -> C | G29: =VLOOKUP(B$4:B$104,I$4:M$104,5,0) -> C | I29: sh1 | J29: ='Юнит 15'!U26 -> 5 | K29: =J29/J$105 -> 0.0023618328 | L29: =L28+K29 -> 0.97543694 | M29: =_xlfn.IFS(L29<80%,"A",L29<=95%,"B",L29>95%,"C") -> C
B30: sports красные | C30: ='Юнит 15'!AO22 -> 1140.3671 | D30: =C30/C$105 -> 0.0011450709 | E30: =E29+D30 -> 1.0018348 | F30: =IF(AND(E30<=0),"C",IF(E30<=0.8,"A",IF(E30<=0.95,"B","C"))) -> C | G30: =VLOOKUP(B$4:B$104,I$4:M$104,5,0) -> C | I30: ww 1022 желтые | J30: ='Юнит 15'!U47 -> 5 | K30: =J30/J$105 -> 0.0023618328 | L30: =L29+K30 -> 0.97779877 | M30: =_xlfn.IFS(L30<80%,"A",L30<=95%,"B",L30>95%,"C") -> C
B31: WW 3055 коричневый | C31: ='Юнит 15'!AO53 -> 1069.6358 | D31: =C31/C$105 -> 0.0010740479 | E31: =E30+D31 -> 1.0029088 | F31: =IF(AND(E31<=0),"C",IF(E31<=0.8,"A",IF(E31<=0.95,"B","C"))) -> C | G31: =VLOOKUP(B$4:B$104,I$4:M$104,5,0) -> C | I31: WW 3055 коричневый | J31: ='Юнит 15'!U53 -> 5 | K31: =J31/J$105 -> 0.0023618328 | L31: =L30+K31 -> 0.9801606 | M31: =_xlfn.IFS(L31<80%,"A",L31<=95%,"B",L31>95%,"C") -> C
B32: sh09 | C32: ='Юнит 15'!AO33 -> 1059.4123 | D32: =C32/C$105 -> 0.0010637822 | E32: =E31+D32 -> 1.0039726 | F32: =IF(AND(E32<=0),"C",IF(E32<=0.8,"A",IF(E32<=0.95,"B","C"))) -> C | G32: =VLOOKUP(B$4:B$104,I$4:M$104,5,0) -> C | I32: MANNA2122 | J32: ='Юнит 15'!U75 -> 5 | K32: =J32/J$105 -> 0.0023618328 | L32: =L31+K32 -> 0.98252244 | M32: =_xlfn.IFS(L32<80%,"A",L32<=95%,"B",L32>95%,"C") -> C
B33: MR Р1894 черные | C33: ='Юнит 15'!AO89 -> 870.3196 | D33: =C33/C$105 -> 0.00087390952 | E33: =E32+D33 -> 1.0048465 | F33: =IF(AND(E33<=0),"C",IF(E33<=0.8,"A",IF(E33<=0.95,"B","C"))) -> C | G33: =VLOOKUP(B$4:B$104,I$4:M$104,5,0) -> C | I33: кс_черные_женские | J33: ='Юнит 15'!U102 -> 5 | K33: =J33/J$105 -> 0.0023618328 | L33: =L32+K33 -> 0.98488427 | M33: =_xlfn.IFS(L33<80%,"A",L33<=95%,"B",L33>95%,"C") -> C
B34: sh15 | C34: ='Юнит 15'!AO39 -> 855.70943 | D34: =C34/C$105 -> 0.00085923909 | E34: =E33+D34 -> 1.0057057 | F34: =IF(AND(E34<=0),"C",IF(E34<=0.8,"A",IF(E34<=0.95,"B","C"))) -> C | G34: =VLOOKUP(B$4:B$104,I$4:M$104,5,0) -> C | I34: sh16 | J34: ='Юнит 15'!U40 -> 3 | K34: =J34/J$105 -> 0.0014170997 | L34: =L33+K34 -> 0.98630137 | M34: =_xlfn.IFS(L34<80%,"A",L34<=95%,"B",L34>95%,"C") -> C
B35: MANNA2122 | C35: ='Юнит 15'!AO75 -> 811.61312 | D35: =C35/C$105 -> 0.00081496088 | E35: =E34+D35 -> 1.0065207 | F35: =IF(AND(E35<=0),"C",IF(E35<=0.8,"A",IF(E35<=0.95,"B","C"))) -> C | G35: =VLOOKUP(B$4:B$104,I$4:M$104,5,0) -> C | I35: MANNA2101 | J35: ='Юнит 15'!U54 -> 3 | K35: =J35/J$105 -> 0.0014170997 | L35: =L34+K35 -> 0.98771847 | M35: =_xlfn.IFS(L35<80%,"A",L35<=95%,"B",L35>95%,"C") -> C
B36: MANNA2101 | C36: ='Юнит 15'!AO54 -> 622.02367 | D36: =C36/C$105 -> 0.00062458941 | E36: =E35+D36 -> 1.0071453 | F36: =IF(AND(E36<=0),"C",IF(E36<=0.8,"A",IF(E36<=0.95,"B","C"))) -> C | G36: =VLOOKUP(B$4:B$104,I$4:M$104,5,0) -> C | I36: Chenlong коричневые | J36: ='Юнит 15'!U77 -> 3 | K36: =J36/J$105 -> 0.0014170997 | L36: =L35+K36 -> 0.98913557 | M36: =_xlfn.IFS(L36<80%,"A",L36<=95%,"B",L36>95%,"C") -> C
B37: MANNA2116 | C37: ='Юнит 15'!AO69 -> 539.59374 | D37: =C37/C$105 -> 0.00054181947 | E37: =E36+D37 -> 1.0076871 | F37: =IF(AND(E37<=0),"C",IF(E37<=0.8,"A",IF(E37<=0.95,"B","C"))) -> C | G37: =VLOOKUP(B$4:B$104,I$4:M$104,5,0) -> C | I37: sh2 | J37: ='Юнит 15'!U27 -> 2 | K37: =J37/J$105 -> 0.00094473311 | L37: =L36+K37 -> 0.9900803 | M37: =_xlfn.IFS(L37<80%,"A",L37<=95%,"B",L37>95%,"C") -> C
B38: Linhai Baiyi розовая линза | C38: ='Юнит 15'!AO88 -> 525.96988 | D38: =C38/C$105 -> 0.00052813941 | E38: =E37+D38 -> 1.0082153 | F38: =IF(AND(E38<=0),"C",IF(E38<=0.8,"A",IF(E38<=0.95,"B","C"))) -> C | G38: =VLOOKUP(B$4:B$104,I$4:M$104,5,0) -> C | I38: sh09 | J38: ='Юнит 15'!U33 -> 2 | K38: =J38/J$105 -> 0.00094473311 | L38: =L37+K38 -> 0.99102504 | M38: =_xlfn.IFS(L38<80%,"A",L38<=95%,"B",L38>95%,"C") -> C
B39: sh17 | C39: ='Юнит 15'!AO41 -> 497.45135 | D39: =C39/C$105 -> 0.00049950325 | E39: =E35+D39 -> 1.0070202 | F39: =IF(AND(E39<=0),"C",IF(E39<=0.8,"A",IF(E39<=0.95,"B","C"))) -> C | G39: =VLOOKUP(B$4:B$104,I$4:M$104,5,0) -> C | I39: sh15 | J39: ='Юнит 15'!U39 -> 2 | K39: =J39/J$105 -> 0.00094473311 | L39: =L35+K39 -> 0.9886632 | M39: =_xlfn.IFS(L39<80%,"A",L39<=95%,"B",L39>95%,"C") -> C
B40: Hengda Optical леопард | C40: ='Юнит 15'!AO82 -> 447.90643 | D40: =C40/C$105 -> 0.00044975397 | E40: =E39+D40 -> 1.00747 | F40: =IF(AND(E40<=0),"C",IF(E40<=0.8,"A",IF(E40<=0.95,"B","C"))) -> C | G40: =VLOOKUP(B$4:B$104,I$4:M$104,5,0) -> C | I40: MANNA2116 | J40: ='Юнит 15'!U69 -> 2 | K40: =J40/J$105 -> 0.00094473311 | L40: =L39+K40 -> 0.98960794 | M40: =_xlfn.IFS(L40<80%,"A",L40<=95%,"B",L40>95%,"C") -> C
B41: кс_черные_женские | C41: ='Юнит 15'!AO102 -> 374.33609 | D41: =C41/C$105 -> 0.00037588016 | E41: =E40+D41 -> 1.0078458 | F41: =IF(AND(E41<=0),"C",IF(E41<=0.8,"A",IF(E41<=0.95,"B","C"))) -> C | G41: =VLOOKUP(B$4:B$104,I$4:M$104,5,0) -> C | I41: Guangdu золото серая линза | J41: ='Юнит 15'!U79 -> 2 | K41: =J41/J$105 -> 0.00094473311 | L41: =L40+K41 -> 0.99055267 | M41: =_xlfn.IFS(L41<80%,"A",L41<=95%,"B",L41>95%,"C") -> C
B42: ЧСЖ_женские | C42: ='Юнит 15'!AO100 -> 307.84148 | D42: =C42/C$105 -> 0.00030911127 | E42: =E41+D42 -> 1.008155 | F42: =IF(AND(E42<=0),"C",IF(E42<=0.8,"A",IF(E42<=0.95,"B","C"))) -> C | G42: =VLOOKUP(B$4:B$104,I$4:M$104,5,0) -> C | I42: Qianai коричневые | J42: ='Юнит 15'!U84 -> 2 | K42: =J42/J$105 -> 0.00094473311 | L42: =L41+K42 -> 0.9914974 | M42: =_xlfn.IFS(L42<80%,"A",L42<=95%,"B",L42>95%,"C") -> C
B43: Linhai Baiyi серая линза | C43: ='Юнит 15'!AO87 -> 266.45068 | D43: =C43/C$105 -> 0.00026754974 | E43: =E42+D43 -> 1.0084225 | F43: =IF(AND(E43<=0),"C",IF(E43<=0.8,"A",IF(E43<=0.95,"B","C"))) -> C | G43: =VLOOKUP(B$4:B$104,I$4:M$104,5,0) -> C | I43: Linhai Baiyi серая линза | J43: ='Юнит 15'!U87 -> 2 | K43: =J43/J$105 -> 0.00094473311 | L43: =L42+K43 -> 0.99244214 | M43: =_xlfn.IFS(L43<80%,"A",L43<=95%,"B",L43>95%,"C") -> C
B44: YIMEI 2391 C1 | C44: ='Юнит 15'!AO98 -> 143.29521 | D44: =C44/C$105 -> 0.00014388628 | E44: =E43+D44 -> 1.0085664 | F44: =IF(AND(E44<=0),"C",IF(E44<=0.8,"A",IF(E44<=0.95,"B","C"))) -> C | G44: =VLOOKUP(B$4:B$104,I$4:M$104,5,0) -> C | I44: MR Р1894 черные | J44: ='Юнит 15'!U89 -> 2 | K44: =J44/J$105 -> 0.00094473311 | L44: =L43+K44 -> 0.99338687 | M44: =_xlfn.IFS(L44<80%,"A",L44<=95%,"B",L44>95%,"C") -> C
B45: wwl8032 черные серебро | C45: ='Юнит 15'!AO19 -> 0 | D45: =C45/C$105 -> 0 | E45: =E44+D45 -> 1.0085664 | F45: =IF(AND(E45<=0),"C",IF(E45<=0.8,"A",IF(E45<=0.95,"B","C"))) -> C | G45: =VLOOKUP(B$4:B$104,I$4:M$104,5,0) -> C | I45: sh17 | J45: ='Юнит 15'!U41 -> 1 | K45: =J45/J$105 -> 0.00047236656 | L45: =L44+K45 -> 0.99385923 | M45: =_xlfn.IFS(L45<80%,"A",L45<=95%,"B",L45>95%,"C") -> C
B46: sportlife черные | C46: ='Юнит 15'!AO23 -> 0 | D46: =C46/C$105 -> 0 | E46: =E45+D46 -> 1.0085664 | F46: =IF(AND(E46<=0),"C",IF(E46<=0.8,"A",IF(E46<=0.95,"B","C"))) -> C | G46: =VLOOKUP(B$4:B$104,I$4:M$104,5,0) -> C | I46: WW 3055 черный | J46: ='Юнит 15'!U52 -> 1 | K46: =J46/J$105 -> 0.00047236656 | L46: =L45+K46 -> 0.9943316 | M46: =_xlfn.IFS(L46<80%,"A",L46<=95%,"B",L46>95%,"C") -> C
B47: sportlife красные | C47: ='Юнит 15'!AO25 -> 0 | D47: =C47/C$105 -> 0 | E47: =E46+D47 -> 1.0085664 | F47: =IF(AND(E47<=0),"C",IF(E47<=0.8,"A",IF(E47<=0.95,"B","C"))) -> C | G47: =VLOOKUP(B$4:B$104,I$4:M$104,5,0) -> C | I47: MANNA2108 | J47: ='Юнит 15'!U61 -> 1 | K47: =J47/J$105 -> 0.00047236656 | L47: =L46+K47 -> 0.99480397 | M47: =_xlfn.IFS(L47<80%,"A",L47<=95%,"B",L47>95%,"C") -> C
B48: sh4 | C48: ='Юнит 15'!AO29 -> 0 | D48: =C48/C$105 -> 0 | E48: =E47+D48 -> 1.0085664 | F48: =IF(AND(E48<=0),"C",IF(E48<=0.8,"A",IF(E48<=0.95,"B","C"))) -> C | G48: =VLOOKUP(B$4:B$104,I$4:M$104,5,0) -> C | I48: Guangdu серебро серая линза | J48: ='Юнит 15'!U80 -> 1 | K48: =J48/J$105 -> 0.00047236656 | L48: =L47+K48 -> 0.99527633 | M48: =_xlfn.IFS(L48<80%,"A",L48<=95%,"B",L48>95%,"C") -> C
B49: sh06 | C49: ='Юнит 15'!AO30 -> 0 | D49: =C49/C$105 -> 0 | E49: =E48+D49 -> 1.0085664 | F49: =IF(AND(E49<=0),"C",IF(E49<=0.8,"A",IF(E49<=0.95,"B","C"))) -> C | G49: =VLOOKUP(B$4:B$104,I$4:M$104,5,0) -> C | I49: Hengda Optical леопард | J49: ='Юнит 15'!U82 -> 1 | K49: =J49/J$105 -> 0.00047236656 | L49: =L48+K49 -> 0.9957487 | M49: =_xlfn.IFS(L49<80%,"A",L49<=95%,"B",L49>95%,"C") -> C
B50: sh07 | C50: ='Юнит 15'!AO31 -> 0 | D50: =C50/C$105 -> 0 | E50: =E49+D50 -> 1.0085664 | F50: =IF(AND(E50<=0),"C",IF(E50<=0.8,"A",IF(E50<=0.95,"B","C"))) -> C | G50: =VLOOKUP(B$4:B$104,I$4:M$104,5,0) -> C | I50: Linhai Baiyi розовая линза | J50: ='Юнит 15'!U88 -> 1 | K50: =J50/J$105 -> 0.00047236656 | L50: =L49+K50 -> 0.99622107 | M50: =_xlfn.IFS(L50<80%,"A",L50<=95%,"B",L50>95%,"C") -> C
B51: sh08 | C51: ='Юнит 15'!AO32 -> 0 | D51: =C51/C$105 -> 0 | E51: =E50+D51 -> 1.0085664 | F51: =IF(AND(E51<=0),"C",IF(E51<=0.8,"A",IF(E51<=0.95,"B","C"))) -> C | G51: =VLOOKUP(B$4:B$104,I$4:M$104,5,0) -> C | I51: YIMEI 2391 C1 | J51: ='Юнит 15'!U98 -> 1 | K51: =J51/J$105 -> 0.00047236656 | L51: =L50+K51 -> 0.99669343 | M51: =_xlfn.IFS(L51<80%,"A",L51<=95%,"B",L51>95%,"C") -> C
B52: sh10 | C52: ='Юнит 15'!AO34 -> 0 | D52: =C52/C$105 -> 0 | E52: =E51+D52 -> 1.0085664 | F52: =IF(AND(E52<=0),"C",IF(E52<=0.8,"A",IF(E52<=0.95,"B","C"))) -> C | G52: =VLOOKUP(B$4:B$104,I$4:M$104,5,0) -> C | I52: ЧСЖ_женские | J52: ='Юнит 15'!U100 -> 1 | K52: =J52/J$105 -> 0.00047236656 | L52: =L51+K52 -> 0.9971658 | M52: =_xlfn.IFS(L52<80%,"A",L52<=95%,"B",L52>95%,"C") -> C
B53: sh11 | C53: ='Юнит 15'!AO35 -> 0 | D53: =C53/C$105 -> 0 | E53: =E52+D53 -> 1.0085664 | F53: =IF(AND(E53<=0),"C",IF(E53<=0.8,"A",IF(E53<=0.95,"B","C"))) -> C | G53: =VLOOKUP(B$4:B$104,I$4:M$104,5,0) -> C | I53: wwl8032 черные серебро | J53: ='Юнит 15'!U19 -> 0 | K53: =J53/J$105 -> 0 | L53: =L52+K53 -> 0.9971658 | M53: =_xlfn.IFS(L53<80%,"A",L53<=95%,"B",L53>95%,"C") -> C
B54: sh12 | C54: ='Юнит 15'!AO36 -> 0 | D54: =C54/C$105 -> 0 | E54: =E53+D54 -> 1.0085664 | F54: =IF(AND(E54<=0),"C",IF(E54<=0.8,"A",IF(E54<=0.95,"B","C"))) -> C | G54: =VLOOKUP(B$4:B$104,I$4:M$104,5,0) -> C | I54: sportlife черные | J54: ='Юнит 15'!U23 -> 0 | K54: =J54/J$105 -> 0 | L54: =L53+K54 -> 0.9971658 | M54: =_xlfn.IFS(L54<80%,"A",L54<=95%,"B",L54>95%,"C") -> C
B55: sh13 | C55: ='Юнит 15'!AO37 -> 0 | D55: =C55/C$105 -> 0 | E55: =E54+D55 -> 1.0085664 | F55: =IF(AND(E55<=0),"C",IF(E55<=0.8,"A",IF(E55<=0.95,"B","C"))) -> C | G55: =VLOOKUP(B$4:B$104,I$4:M$104,5,0) -> C | I55: sportlife синие | J55: ='Юнит 15'!U24 -> 0 | K55: =J55/J$105 -> 0 | L55: =L54+K55 -> 0.9971658 | M55: =_xlfn.IFS(L55<80%,"A",L55<=95%,"B",L55>95%,"C") -> C
B56: ww 1022 черн-серебро | C56: ='Юнит 15'!AO46 -> 0 | D56: =C56/C$105 -> 0 | E56: =E55+D56 -> 1.0085664 | F56: =IF(AND(E56<=0),"C",IF(E56<=0.8,"A",IF(E56<=0.95,"B","C"))) -> C | G56: =VLOOKUP(B$4:B$104,I$4:M$104,5,0) -> C | I56: sportlife красные | J56: ='Юнит 15'!U25 -> 0 | K56: =J56/J$105 -> 0 | L56: =L55+K56 -> 0.9971658 | M56: =_xlfn.IFS(L56<80%,"A",L56<=95%,"B",L56>95%,"C") -> C
B57: MANNA2103 | C57: ='Юнит 15'!AO56 -> 0 | D57: =C57/C$105 -> 0 | E57: =E56+D57 -> 1.0085664 | F57: =IF(AND(E57<=0),"C",IF(E57<=0.8,"A",IF(E57<=0.95,"B","C"))) -> C | G57: =VLOOKUP(B$4:B$104,I$4:M$104,5,0) -> C | I57: sh4 | J57: ='Юнит 15'!U29 -> 0 | K57: =J57/J$105 -> 0 | L57: =L56+K57 -> 0.9971658 | M57: =_xlfn.IFS(L57<80%,"A",L57<=95%,"B",L57>95%,"C") -> C
B58: MANNA2104 | C58: ='Юнит 15'!AO57 -> 0 | D58: =C58/C$105 -> 0 | E58: =E57+D58 -> 1.0085664 | F58: =IF(AND(E58<=0),"C",IF(E58<=0.8,"A",IF(E58<=0.95,"B","C"))) -> C | G58: =VLOOKUP(B$4:B$104,I$4:M$104,5,0) -> C | I58: sh06 | J58: ='Юнит 15'!U30 -> 0 | K58: =J58/J$105 -> 0 | L58: =L57+K58 -> 0.9971658 | M58: =_xlfn.IFS(L58<80%,"A",L58<=95%,"B",L58>95%,"C") -> C
B59: MANNA2106 | C59: ='Юнит 15'!AO59 -> 0 | D59: =C59/C$105 -> 0 | E59: =E58+D59 -> 1.0085664 | F59: =IF(AND(E59<=0),"C",IF(E59<=0.8,"A",IF(E59<=0.95,"B","C"))) -> C | G59: =VLOOKUP(B$4:B$104,I$4:M$104,5,0) -> C | I59: sh07 | J59: ='Юнит 15'!U31 -> 0 | K59: =J59/J$105 -> 0 | L59: =L58+K59 -> 0.9971658 | M59: =_xlfn.IFS(L59<80%,"A",L59<=95%,"B",L59>95%,"C") -> C
B60: MANNA2109 | C60: ='Юнит 15'!AO62 -> 0 | D60: =C60/C$105 -> 0 | E60: =E59+D60 -> 1.0085664 | F60: =IF(AND(E60<=0),"C",IF(E60<=0.8,"A",IF(E60<=0.95,"B","C"))) -> C | G60: =VLOOKUP(B$4:B$104,I$4:M$104,5,0) -> C | I60: sh08 | J60: ='Юнит 15'!U32 -> 0 | K60: =J60/J$105 -> 0 | L60: =L59+K60 -> 0.9971658 | M60: =_xlfn.IFS(L60<80%,"A",L60<=95%,"B",L60>95%,"C") -> C
B61: MANNA2110 | C61: ='Юнит 15'!AO63 -> 0 | D61: =C61/C$105 -> 0 | E61: =E60+D61 -> 1.0085664 | F61: =IF(AND(E61<=0),"C",IF(E61<=0.8,"A",IF(E61<=0.95,"B","C"))) -> C | G61: =VLOOKUP(B$4:B$104,I$4:M$104,5,0) -> C | I61: sh10 | J61: ='Юнит 15'!U34 -> 0 | K61: =J61/J$105 -> 0 | L61: =L60+K61 -> 0.9971658 | M61: =_xlfn.IFS(L61<80%,"A",L61<=95%,"B",L61>95%,"C") -> C
B62: MANNA2111 | C62: ='Юнит 15'!AO64 -> 0 | D62: =C62/C$105 -> 0 | E62: =E61+D62 -> 1.0085664 | F62: =IF(AND(E62<=0),"C",IF(E62<=0.8,"A",IF(E62<=0.95,"B","C"))) -> C | G62: =VLOOKUP(B$4:B$104,I$4:M$104,5,0) -> C | I62: sh11 | J62: ='Юнит 15'!U35 -> 0 | K62: =J62/J$105 -> 0 | L62: =L61+K62 -> 0.9971658 | M62: =_xlfn.IFS(L62<80%,"A",L62<=95%,"B",L62>95%,"C") -> C
B63: MANNA2114 | C63: ='Юнит 15'!AO67 -> 0 | D63: =C63/C$105 -> 0 | E63: =E62+D63 -> 1.0085664 | F63: =IF(AND(E63<=0),"C",IF(E63<=0.8,"A",IF(E63<=0.95,"B","C"))) -> C | G63: =VLOOKUP(B$4:B$104,I$4:M$104,5,0) -> C | I63: sh12 | J63: ='Юнит 15'!U36 -> 0 | K63: =J63/J$105 -> 0 | L63: =L62+K63 -> 0.9971658 | M63: =_xlfn.IFS(L63<80%,"A",L63<=95%,"B",L63>95%,"C") -> C
B64: MANNA2115 | C64: ='Юнит 15'!AO68 -> 0 | D64: =C64/C$105 -> 0 | E64: =E63+D64 -> 1.0085664 | F64: =IF(AND(E64<=0),"C",IF(E64<=0.8,"A",IF(E64<=0.95,"B","C"))) -> C | G64: =VLOOKUP(B$4:B$104,I$4:M$104,5,0) -> C | I64: sh13 | J64: ='Юнит 15'!U37 -> 0 | K64: =J64/J$105 -> 0 | L64: =L63+K64 -> 0.9971658 | M64: =_xlfn.IFS(L64<80%,"A",L64<=95%,"B",L64>95%,"C") -> C
B65: MANNA2117 | C65: ='Юнит 15'!AO70 -> 0 | D65: =C65/C$105 -> 0 | E65: =E64+D65 -> 1.0085664 | F65: =IF(AND(E65<=0),"C",IF(E65<=0.8,"A",IF(E65<=0.95,"B","C"))) -> C | G65: =VLOOKUP(B$4:B$104,I$4:M$104,5,0) -> C | I65: sh14 | J65: ='Юнит 15'!U38 -> 0 | K65: =J65/J$105 -> 0 | L65: =L64+K65 -> 0.9971658 | M65: =_xlfn.IFS(L65<80%,"A",L65<=95%,"B",L65>95%,"C") -> C
B66: MANNA2119 | C66: ='Юнит 15'!AO72 -> 0 | D66: =C66/C$105 -> 0 | E66: =E65+D66 -> 1.0085664 | F66: =IF(AND(E66<=0),"C",IF(E66<=0.8,"A",IF(E66<=0.95,"B","C"))) -> C | G66: =VLOOKUP(B$4:B$104,I$4:M$104,5,0) -> C | I66: sh18 | J66: ='Юнит 15'!U42 -> 0 | K66: =J66/J$105 -> 0 | L66: =L65+K66 -> 0.9971658 | M66: =_xlfn.IFS(L66<80%,"A",L66<=95%,"B",L66>95%,"C") -> C
B67: MAIERSHA 03898 C9-08 | C67: ='Юнит 15'!AO94 -> 0 | D67: =C67/C$105 -> 0 | E67: =E66+D67 -> 1.0085664 | F67: =IF(AND(E67<=0),"C",IF(E67<=0.8,"A",IF(E67<=0.95,"B","C"))) -> C | G67: =VLOOKUP(B$4:B$104,I$4:M$104,5,0) -> C | I67: sh19 | J67: ='Юнит 15'!U43 -> 0 | K67: =J67/J$105 -> 0 | L67: =L66+K67 -> 0.9971658 | M67: =_xlfn.IFS(L67<80%,"A",L67<=95%,"B",L67>95%,"C") -> C
B68: MAIERSHA 03914 C9-124 | C68: ='Юнит 15'!AO95 -> 0 | D68: =C68/C$105 -> 0 | E68: =E67+D68 -> 1.0085664 | F68: =IF(AND(E68<=0),"C",IF(E68<=0.8,"A",IF(E68<=0.95,"B","C"))) -> C | G68: =VLOOKUP(B$4:B$104,I$4:M$104,5,0) -> C | I68: ww 1022 черн-серебро | J68: ='Юнит 15'!U46 -> 0 | K68: =J68/J$105 -> 0 | L68: =L67+K68 -> 0.9971658 | M68: =_xlfn.IFS(L68<80%,"A",L68<=95%,"B",L68>95%,"C") -> C
B69: MARSTON 7171 C1 | C69: ='Юнит 15'!AO96 -> 0 | D69: =C69/C$105 -> 0 | E69: =E68+D69 -> 1.0085664 | F69: =IF(AND(E69<=0),"C",IF(E69<=0.8,"A",IF(E69<=0.95,"B","C"))) -> C | G69: =VLOOKUP(B$4:B$104,I$4:M$104,5,0) -> C | I69: ww 8010 черные | J69: ='Юнит 15'!U51 -> 0 | K69: =J69/J$105 -> 0 | L69: =L68+K69 -> 0.9971658 | M69: =_xlfn.IFS(L69<80%,"A",L69<=95%,"B",L69>95%,"C") -> C
B70: ЧСЖ_тест | C70: ='Юнит 15'!AO99 -> 0 | D70: =C70/C$105 -> 0 | E70: =E69+D70 -> 1.0085664 | F70: =IF(AND(E70<=0),"C",IF(E70<=0.8,"A",IF(E70<=0.95,"B","C"))) -> C | G70: =VLOOKUP(B$4:B$104,I$4:M$104,5,0) -> C | I70: MANNA2102 | J70: ='Юнит 15'!U55 -> 0 | K70: =J70/J$105 -> 0 | L70: =L69+K70 -> 0.9971658 | M70: =_xlfn.IFS(L70<80%,"A",L70<=95%,"B",L70>95%,"C") -> C
B71: кс_черные_тест | C71: ='Юнит 15'!AO101 -> 0 | D71: =C71/C$105 -> 0 | E71: =E70+D71 -> 1.0085664 | F71: =IF(AND(E71<=0),"C",IF(E71<=0.8,"A",IF(E71<=0.95,"B","C"))) -> C | G71: =VLOOKUP(B$4:B$104,I$4:M$104,5,0) -> C | I71: MANNA2103 | J71: ='Юнит 15'!U56 -> 0 | K71: =J71/J$105 -> 0 | L71: =L70+K71 -> 0.9971658 | M71: =_xlfn.IFS(L71<80%,"A",L71<=95%,"B",L71>95%,"C") -> C
B72: 1022_коричневые_тест | C72: ='Юнит 15'!AO103 -> 0 | D72: =C72/C$105 -> 0 | E72: =E71+D72 -> 1.0085664 | F72: =IF(AND(E72<=0),"C",IF(E72<=0.8,"A",IF(E72<=0.95,"B","C"))) -> C | G72: =VLOOKUP(B$4:B$104,I$4:M$104,5,0) -> C | I72: MANNA2104 | J72: ='Юнит 15'!U57 -> 0 | K72: =J72/J$105 -> 0 | L72: =L71+K72 -> 0.9971658 | M72: =_xlfn.IFS(L72<80%,"A",L72<=95%,"B",L72>95%,"C") -> C
B73: MANNA2102 | C73: ='Юнит 15'!AO55 -> -0.84042066 | D73: =C73/C$105 -> -8.4388725e-07 | E73: =E72+D73 -> 1.0085655 | F73: =IF(AND(E73<=0),"C",IF(E73<=0.8,"A",IF(E73<=0.95,"B","C"))) -> C | G73: =VLOOKUP(B$4:B$104,I$4:M$104,5,0) -> C | I73: MANNA2105 | J73: ='Юнит 15'!U58 -> 0 | K73: =J73/J$105 -> 0 | L73: =L72+K73 -> 0.9971658 | M73: =_xlfn.IFS(L73<80%,"A",L73<=95%,"B",L73>95%,"C") -> C
B74: MANNA2112 | C74: ='Юнит 15'!AO65 -> -0.84042066 | D74: =C74/C$105 -> -8.4388725e-07 | E74: =E73+D74 -> 1.0085647 | F74: =IF(AND(E74<=0),"C",IF(E74<=0.8,"A",IF(E74<=0.95,"B","C"))) -> C | G74: =VLOOKUP(B$4:B$104,I$4:M$104,5,0) -> C | I74: MANNA2106 | J74: ='Юнит 15'!U59 -> 0 | K74: =J74/J$105 -> 0 | L74: =L73+K74 -> 0.9971658 | M74: =_xlfn.IFS(L74<80%,"A",L74<=95%,"B",L74>95%,"C") -> C
B75: MANNA2120 | C75: ='Юнит 15'!AO73 -> -0.84042066 | D75: =C75/C$105 -> -8.4388725e-07 | E75: =E74+D75 -> 1.0085639 | F75: =IF(AND(E75<=0),"C",IF(E75<=0.8,"A",IF(E75<=0.95,"B","C"))) -> C | G75: =VLOOKUP(B$4:B$104,I$4:M$104,5,0) -> C | I75: MANNA2107 | J75: ='Юнит 15'!U60 -> 0 | K75: =J75/J$105 -> 0 | L75: =L74+K75 -> 0.9971658 | M75: =_xlfn.IFS(L75<80%,"A",L75<=95%,"B",L75>95%,"C") -> C
B76: MANNA2113 | C76: ='Юнит 15'!AO66 -> -1.6808413 | D76: =C76/C$105 -> -1.6877745e-06 | E76: =E49+D76 -> 1.0085647 | F76: =IF(AND(E76<=0),"C",IF(E76<=0.8,"A",IF(E76<=0.95,"B","C"))) -> C | G76: =VLOOKUP(B$4:B$104,I$4:M$104,5,0) -> C | I76: MANNA2109 | J76: ='Юнит 15'!U62 -> 0 | K76: =J76/J$105 -> 0 | L76: =L49+K76 -> 0.9957487 | M76: =_xlfn.IFS(L76<80%,"A",L76<=95%,"B",L76>95%,"C") -> C
B77: MANNA2118 | C77: ='Юнит 15'!AO71 -> -2.521262 | D77: =C77/C$105 -> -2.5316617e-06 | E77: =E76+D77 -> 1.0085622 | F77: =IF(AND(E77<=0),"C",IF(E77<=0.8,"A",IF(E77<=0.95,"B","C"))) -> C | G77: =VLOOKUP(B$4:B$104,I$4:M$104,5,0) -> C | I77: MANNA2110 | J77: ='Юнит 15'!U63 -> 0 | K77: =J77/J$105 -> 0 | L77: =L76+K77 -> 0.9957487 | M77: =_xlfn.IFS(L77<80%,"A",L77<=95%,"B",L77>95%,"C") -> C
B78: sportlife синие | C78: ='Юнит 15'!AO24 -> -21.850937 | D78: =C78/C$105 -> -2.1941068e-05 | E78: =E77+D78 -> 1.0085402 | F78: =IF(AND(E78<=0),"C",IF(E78<=0.8,"A",IF(E78<=0.95,"B","C"))) -> C | G78: =VLOOKUP(B$4:B$104,I$4:M$104,5,0) -> C | I78: MANNA2111 | J78: ='Юнит 15'!U64 -> 0 | K78: =J78/J$105 -> 0 | L78: =L77+K78 -> 0.9957487 | M78: =_xlfn.IFS(L78<80%,"A",L78<=95%,"B",L78>95%,"C") -> C
B79: Ли Сян ретро серебро | C79: ='Юнит 15'!AO93 -> -32.776406 | D79: =C79/C$105 -> -3.2911603e-05 | E79: =E78+D79 -> 1.0085073 | F79: =IF(AND(E79<=0),"C",IF(E79<=0.8,"A",IF(E79<=0.95,"B","C"))) -> C | G79: =VLOOKUP(B$4:B$104,I$4:M$104,5,0) -> C | I79: MANNA2112 | J79: ='Юнит 15'!U65 -> 0 | K79: =J79/J$105 -> 0 | L79: =L78+K79 -> 0.9957487 | M79: =_xlfn.IFS(L79<80%,"A",L79<=95%,"B",L79>95%,"C") -> C
B80: Guangdu серебро серая линза | C80: ='Юнит 15'!AO80 -> -38.168872 | D80: =C80/C$105 -> -3.8326312e-05 | E80: =E79+D80 -> 1.008469 | F80: =IF(AND(E80<=0),"C",IF(E80<=0.8,"A",IF(E80<=0.95,"B","C"))) -> C | G80: =VLOOKUP(B$4:B$104,I$4:M$104,5,0) -> C | I80: MANNA2113 | J80: ='Юнит 15'!U66 -> 0 | K80: =J80/J$105 -> 0 | L80: =L79+K80 -> 0.9957487 | M80: =_xlfn.IFS(L80<80%,"A",L80<=95%,"B",L80>95%,"C") -> C
B81: Taizhou Rayen sport розовый | C81: ='Юнит 15'!AO90 -> -40.340191 | D81: =C81/C$105 -> -4.0506588e-05 | E81: =E80+D81 -> 1.0084285 | F81: =IF(AND(E81<=0),"C",IF(E81<=0.8,"A",IF(E81<=0.95,"B","C"))) -> C | G81: =VLOOKUP(B$4:B$104,I$4:M$104,5,0) -> C | I81: MANNA2114 | J81: ='Юнит 15'!U67 -> 0 | K81: =J81/J$105 -> 0 | L81: =L80+K81 -> 0.9957487 | M81: =_xlfn.IFS(L81<80%,"A",L81<=95%,"B",L81>95%,"C") -> C
B82: MANNA2121 | C82: ='Юнит 15'!AO74 -> -58.29 | D82: =C82/C$105 -> -5.8530436e-05 | E82: =E81+D82 -> 1.00837 | F82: =IF(AND(E82<=0),"C",IF(E82<=0.8,"A",IF(E82<=0.95,"B","C"))) -> C | G82: =VLOOKUP(B$4:B$104,I$4:M$104,5,0) -> C | I82: MANNA2115 | J82: ='Юнит 15'!U68 -> 0 | K82: =J82/J$105 -> 0 | L82: =L81+K82 -> 0.9957487 | M82: =_xlfn.IFS(L82<80%,"A",L82<=95%,"B",L82>95%,"C") -> C
B83: sh1 | C83: ='Юнит 15'!AO26 -> -96.630333 | D83: =C83/C$105 -> -9.7028916e-05 | E83: =E82+D83 -> 1.0082729 | F83: =IF(AND(E83<=0),"C",IF(E83<=0.8,"A",IF(E83<=0.95,"B","C"))) -> C | G83: =VLOOKUP(B$4:B$104,I$4:M$104,5,0) -> C | I83: MANNA2117 | J83: ='Юнит 15'!U70 -> 0 | K83: =J83/J$105 -> 0 | L83: =L82+K83 -> 0.9957487 | M83: =_xlfn.IFS(L83<80%,"A",L83<=95%,"B",L83>95%,"C") -> C
B84: MANNA2108 | C84: ='Юнит 15'!AO61 -> -101.35258 | D84: =C84/C$105 -> -0.00010177064 | E84: =E83+D84 -> 1.0081712 | F84: =IF(AND(E84<=0),"C",IF(E84<=0.8,"A",IF(E84<=0.95,"B","C"))) -> C | G84: =VLOOKUP(B$4:B$104,I$4:M$104,5,0) -> C | I84: MANNA2118 | J84: ='Юнит 15'!U71 -> 0 | K84: =J84/J$105 -> 0 | L84: =L83+K84 -> 0.9957487 | M84: =_xlfn.IFS(L84<80%,"A",L84<=95%,"B",L84>95%,"C") -> C
B85: Hengda Optical черные | C85: ='Юнит 15'!AO81 -> -104.26463 | D85: =C85/C$105 -> -0.0001046947 | E85: =E84+D85 -> 1.0080665 | F85: =IF(AND(E85<=0),"C",IF(E85<=0.8,"A",IF(E85<=0.95,"B","C"))) -> C | G85: =VLOOKUP(B$4:B$104,I$4:M$104,5,0) -> C | I85: MANNA2119 | J85: ='Юнит 15'!U72 -> 0 | K85: =J85/J$105 -> 0 | L85: =L84+K85 -> 0.9957487 | M85: =_xlfn.IFS(L85<80%,"A",L85<=95%,"B",L85>95%,"C") -> C
B86: Chenlong коричневые | C86: ='Юнит 15'!AO77 -> -106.1111 | D86: =C86/C$105 -> -0.00010654879 | E86: =E85+D86 -> 1.0079599 | F86: =IF(AND(E86<=0),"C",IF(E86<=0.8,"A",IF(E86<=0.95,"B","C"))) -> C | G86: =VLOOKUP(B$4:B$104,I$4:M$104,5,0) -> C | I86: MANNA2120 | J86: ='Юнит 15'!U73 -> 0 | K86: =J86/J$105 -> 0 | L86: =L85+K86 -> 0.9957487 | M86: =_xlfn.IFS(L86<80%,"A",L86<=95%,"B",L86>95%,"C") -> C
B87: sh2 | C87: ='Юнит 15'!AO27 -> -132.6656 | D87: =C87/C$105 -> -0.00013321282 | E87: =E86+D87 -> 1.0078267 | F87: =IF(AND(E87<=0),"C",IF(E87<=0.8,"A",IF(E87<=0.95,"B","C"))) -> C | G87: =VLOOKUP(B$4:B$104,I$4:M$104,5,0) -> C | I87: MANNA2121 | J87: ='Юнит 15'!U74 -> 0 | K87: =J87/J$105 -> 0 | L87: =L86+K87 -> 0.9957487 | M87: =_xlfn.IFS(L87<80%,"A",L87<=95%,"B",L87>95%,"C") -> C
B88: WW 3055 черный | C88: ='Юнит 15'!AO52 -> -134.80592 | D88: =C88/C$105 -> -0.00013536197 | E88: =E87+D88 -> 1.0076913 | F88: =IF(AND(E88<=0),"C",IF(E88<=0.8,"A",IF(E88<=0.95,"B","C"))) -> C | G88: =VLOOKUP(B$4:B$104,I$4:M$104,5,0) -> C | I88: Chenlong черные | J88: ='Юнит 15'!U76 -> 0 | K88: =J88/J$105 -> 0 | L88: =L87+K88 -> 0.9957487 | M88: =_xlfn.IFS(L88<80%,"A",L88<=95%,"B",L88>95%,"C") -> C
B89: ww 8010 черные | C89: ='Юнит 15'!AO51 -> -149 | D89: =C89/C$105 -> -0.0001496146 | E89: =E88+D89 -> 1.0075417 | F89: =IF(AND(E89<=0),"C",IF(E89<=0.8,"A",IF(E89<=0.95,"B","C"))) -> C | G89: =VLOOKUP(B$4:B$104,I$4:M$104,5,0) -> C | I89: Chenlong белые | J89: ='Юнит 15'!U78 -> 0 | K89: =J89/J$105 -> 0 | L89: =L88+K89 -> 0.9957487 | M89: =_xlfn.IFS(L89<80%,"A",L89<=95%,"B",L89>95%,"C") -> C
B90: POMILED 08247 C4-08 | C90: ='Юнит 15'!AO97 -> -154.67042 | D90: =C90/C$105 -> -0.00015530841 | E90: =E89+D90 -> 1.0073864 | F90: =IF(AND(E90<=0),"C",IF(E90<=0.8,"A",IF(E90<=0.95,"B","C"))) -> C | G90: =VLOOKUP(B$4:B$104,I$4:M$104,5,0) -> C | I90: Hengda Optical черные | J90: ='Юнит 15'!U81 -> 0 | K90: =J90/J$105 -> 0 | L90: =L89+K90 -> 0.9957487 | M90: =_xlfn.IFS(L90<80%,"A",L90<=95%,"B",L90>95%,"C") -> C
B91: sh14 | C91: ='Юнит 15'!AO38 -> -203.96809 | D91: =C91/C$105 -> -0.00020480942 | E91: =E90+D91 -> 1.0071816 | F91: =IF(AND(E91<=0),"C",IF(E91<=0.8,"A",IF(E91<=0.95,"B","C"))) -> C | G91: =VLOOKUP(B$4:B$104,I$4:M$104,5,0) -> C | I91: Qianai черные | J91: ='Юнит 15'!U83 -> 0 | K91: =J91/J$105 -> 0 | L91: =L90+K91 -> 0.9957487 | M91: =_xlfn.IFS(L91<80%,"A",L91<=95%,"B",L91>95%,"C") -> C
B92: Qianai черные | C92: ='Юнит 15'!AO83 -> -209.61725 | D92: =C92/C$105 -> -0.00021048188 | E92: =E91+D92 -> 1.0069711 | F92: =IF(AND(E92<=0),"C",IF(E92<=0.8,"A",IF(E92<=0.95,"B","C"))) -> C | G92: =VLOOKUP(B$4:B$104,I$4:M$104,5,0) -> C | I92: Keming Aishi коричневые | J92: ='Юнит 15'!U85 -> 0 | K92: =J92/J$105 -> 0 | L92: =L91+K92 -> 0.9957487 | M92: =_xlfn.IFS(L92<80%,"A",L92<=95%,"B",L92>95%,"C") -> C
B93: Linhai Baiyi коричневая линза | C93: ='Юнит 15'!AO86 -> -214.62683 | D93: =C93/C$105 -> -0.00021551213 | E93: =E92+D93 -> 1.0067556 | F93: =IF(AND(E93<=0),"C",IF(E93<=0.8,"A",IF(E93<=0.95,"B","C"))) -> C | G93: =VLOOKUP(B$4:B$104,I$4:M$104,5,0) -> C | I93: Linhai Baiyi коричневая линза | J93: ='Юнит 15'!U86 -> 0 | K93: =J93/J$105 -> 0 | L93: =L92+K93 -> 0.9957487 | M93: =_xlfn.IFS(L93<80%,"A",L93<=95%,"B",L93>95%,"C") -> C
B94: MANNA2107 | C94: ='Юнит 15'!AO60 -> -246.40799 | D94: =C94/C$105 -> -0.00024742438 | E94: =E93+D94 -> 1.0065082 | F94: =IF(AND(E94<=0),"C",IF(E94<=0.8,"A",IF(E94<=0.95,"B","C"))) -> C | G94: =VLOOKUP(B$4:B$104,I$4:M$104,5,0) -> C | I94: Taizhou Rayen sport розовый | J94: ='Юнит 15'!U90 -> 0 | K94: =J94/J$105 -> 0 | L94: =L93+K94 -> 0.9957487 | M94: =_xlfn.IFS(L94<80%,"A",L94<=95%,"B",L94>95%,"C") -> C
B95: sh18 | C95: ='Юнит 15'!AO42 -> -248.86136 | D95: =C95/C$105 -> -0.00024988787 | E95: =E94+D95 -> 1.0062583 | F95: =IF(AND(E95<=0),"C",IF(E95<=0.8,"A",IF(E95<=0.95,"B","C"))) -> C | G95: =VLOOKUP(B$4:B$104,I$4:M$104,5,0) -> C | I95: Ли Сян ретро золото | J95: ='Юнит 15'!U92 -> 0 | K95: =J95/J$105 -> 0 | L95: =L94+K95 -> 0.9957487 | M95: =_xlfn.IFS(L95<80%,"A",L95<=95%,"B",L95>95%,"C") -> C
B96: Guangdu золото серая линза | C96: ='Юнит 15'!AO79 -> -286.34386 | D96: =C96/C$105 -> -0.00028752498 | E96: =E95+D96 -> 1.0059708 | F96: =IF(AND(E96<=0),"C",IF(E96<=0.8,"A",IF(E96<=0.95,"B","C"))) -> C | G96: =VLOOKUP(B$4:B$104,I$4:M$104,5,0) -> C | I96: Ли Сян ретро серебро | J96: ='Юнит 15'!U93 -> 0 | K96: =J96/J$105 -> 0 | L96: =L95+K96 -> 0.9957487 | M96: =_xlfn.IFS(L96<80%,"A",L96<=95%,"B",L96>95%,"C") -> C
B97: sh19 | C97: ='Юнит 15'!AO43 -> -324.31084 | D97: =C97/C$105 -> -0.00032564857 | E97: =E96+D97 -> 1.0056451 | F97: =IF(AND(E97<=0),"C",IF(E97<=0.8,"A",IF(E97<=0.95,"B","C"))) -> C | G97: =VLOOKUP(B$4:B$104,I$4:M$104,5,0) -> C | I97: MAIERSHA 03898 C9-08 | J97: ='Юнит 15'!U94 -> 0 | K97: =J97/J$105 -> 0 | L97: =L96+K97 -> 0.9957487 | M97: =_xlfn.IFS(L97<80%,"A",L97<=95%,"B",L97>95%,"C") -> C
B98: Qianai коричневые | C98: ='Юнит 15'!AO84 -> -664.32154 | D98: =C98/C$105 -> -0.00066706175 | E98: =E97+D98 -> 1.0049781 | F98: =IF(AND(E98<=0),"C",IF(E98<=0.8,"A",IF(E98<=0.95,"B","C"))) -> C | G98: =VLOOKUP(B$4:B$104,I$4:M$104,5,0) -> C | I98: MAIERSHA 03914 C9-124 | J98: ='Юнит 15'!U95 -> 0 | K98: =J98/J$105 -> 0 | L98: =L97+K98 -> 0.9957487 | M98: =_xlfn.IFS(L98<80%,"A",L98<=95%,"B",L98>95%,"C") -> C
B99: Keming Aishi коричневые | C99: ='Юнит 15'!AO85 -> -778.3543 | D99: =C99/C$105 -> -0.00078156488 | E99: =E93+D99 -> 1.005974 | F99: =IF(AND(E99<=0),"C",IF(E99<=0.8,"A",IF(E99<=0.95,"B","C"))) -> C | G99: =VLOOKUP(B$4:B$104,I$4:M$104,5,0) -> C | I99: MARSTON 7171 C1 | J99: ='Юнит 15'!U96 -> 0 | K99: =J99/J$105 -> 0 | L99: =L93+K99 -> 0.9957487 | M99: =_xlfn.IFS(L99<80%,"A",L99<=95%,"B",L99>95%,"C") -> C
B100: MANNA2105 | C100: ='Юнит 15'!AO58 -> -823.42841 | D100: =C100/C$105 -> -0.00082682491 | E100: =E94+D100 -> 1.0056814 | F100: =IF(AND(E100<=0),"C",IF(E100<=0.8,"A",IF(E100<=0.95,"B","C"))) -> C | G100: =VLOOKUP(B$4:B$104,I$4:M$104,5,0) -> C | I100: POMILED 08247 C4-08 | J100: ='Юнит 15'!U97 -> 0 | K100: =J100/J$105 -> 0 | L100: =L94+K100 -> 0.9957487 | M100: =_xlfn.IFS(L100<80%,"A",L100<=95%,"B",L100>95%,"C") -> C
B101: Chenlong белые | C101: ='Юнит 15'!AO78 -> -951.42631 | D101: =C101/C$105 -> -0.00095535078 | E101: =E95+D101 -> 1.0053029 | F101: =IF(AND(E101<=0),"C",IF(E101<=0.8,"A",IF(E101<=0.95,"B","C"))) -> C | G101: =VLOOKUP(B$4:B$104,I$4:M$104,5,0) -> C | I101: ЧСЖ_тест | J101: ='Юнит 15'!U99 -> 0 | K101: =J101/J$105 -> 0 | L101: =L95+K101 -> 0.9957487 | M101: =_xlfn.IFS(L101<80%,"A",L101<=95%,"B",L101>95%,"C") -> C
...

Sheet АВС 14
B2: ОЧКИ
C3: Прибыль | D3: % прибыль | E3: Доля | F3: ABC прибыль | G3: ABC кол-во | J3: Кол-во | K3: % кол-во | L3: Доля | M3: ABC кол-во
B4: QS черные PZ | C4: ='Юнит 14'!AO4 -> 264219.93 | D4: =C4/C$105 -> 0.20222751 | E4: =D4 -> 0.20222751 | F4: =IF(AND(E4<=0),"C",IF(E4<=0.8,"A",IF(E4<=0.95,"B","C"))) -> A | G4: =VLOOKUP(B$4:B$104,I$4:M$104,5,0) -> A | I4: QS черные PZ | J4: ='Юнит 14'!U4 -> 447 | K4: =J4/J$105 -> 0.15271609 | L4: =K4 -> 0.15271609 | M4: =_xlfn.IFS(L4<80%,"A",L4<=95%,"B",L4>95%,"C") -> A | P4: A | Q4: 0.8
B5: flip черные | C5: ='Юнит 14'!AO13 -> 151931.13 | D5: =C5/C$105 -> 0.11628439 | E5: =E4+D5 -> 0.3185119 | F5: =IF(AND(E5<=0),"C",IF(E5<=0.8,"A",IF(E5<=0.95,"B","C"))) -> A | G5: =VLOOKUP(B$4:B$104,I$4:M$104,5,0) -> A | I5: flip черные | J5: ='Юнит 14'!U13 -> 275 | K5: =J5/J$105 -> 0.093952853 | L5: =L4+K5 -> 0.24666894 | M5: =_xlfn.IFS(L5<80%,"A",L5<=95%,"B",L5>95%,"C") -> A | P5: B | Q5: 0.15
B6: th черн | C6: ='Юнит 14'!AO9 -> 124360.37 | D6: =C6/C$105 -> 0.095182398 | E6: =E5+D6 -> 0.41369429 | F6: =IF(AND(E6<=0),"C",IF(E6<=0.8,"A",IF(E6<=0.95,"B","C"))) -> A | G6: =VLOOKUP(B$4:B$104,I$4:M$104,5,0) -> A | I6: th черн | J6: ='Юнит 14'!U9 -> 253 | K6: =J6/J$105 -> 0.086436625 | L6: =L5+K6 -> 0.33310557 | M6: =_xlfn.IFS(L6<80%,"A",L6<=95%,"B",L6>95%,"C") -> A | P6: C | Q6: 0.05
B7: flip коричневые | C7: ='Юнит 14'!AO16 -> 105462.57 | D7: =C7/C$105 -> 0.080718487 | E7: =E6+D7 -> 0.49441278 | F7: =IF(AND(E7<=0),"C",IF(E7<=0.8,"A",IF(E7<=0.95,"B","C"))) -> A | G7: =VLOOKUP(B$4:B$104,I$4:M$104,5,0) -> A | I7: flip коричневые | J7: ='Юнит 14'!U16 -> 209 | K7: =J7/J$105 -> 0.071404168 | L7: =L6+K7 -> 0.40450974 | M7: =_xlfn.IFS(L7<80%,"A",L7<=95%,"B",L7>95%,"C") -> A
B8: черные с железкой классика | C8: ='Юнит 14'!AO3 -> 82186.06 | D8: =C8/C$105 -> 0.06290321 | E8: =E7+D8 -> 0.55731599 | F8: =IF(AND(E8<=0),"C",IF(E8<=0.8,"A",IF(E8<=0.95,"B","C"))) -> A | G8: =VLOOKUP(B$4:B$104,I$4:M$104,5,0) -> A | I8: QS коричневые PZ | J8: ='Юнит 14'!U7 -> 191 | K8: =J8/J$105 -> 0.065254527 | L8: =L7+K8 -> 0.46976426 | M8: =_xlfn.IFS(L8<80%,"A",L8<=95%,"B",L8>95%,"C") -> A
B9: QS коричневые PZ | C9: ='Юнит 14'!AO7 -> 77247.989 | D9: =C9/C$105 -> 0.059123731 | E9: =E8+D9 -> 0.61643972 | F9: =IF(AND(E9<=0),"C",IF(E9<=0.8,"A",IF(E9<=0.95,"B","C"))) -> A | G9: =VLOOKUP(B$4:B$104,I$4:M$104,5,0) -> A | I9: th син | J9: ='Юнит 14'!U10 -> 188 | K9: =J9/J$105 -> 0.064229587 | L9: =L8+K9 -> 0.53399385 | M9: =_xlfn.IFS(L9<80%,"A",L9<=95%,"B",L9>95%,"C") -> A
B10: QS синие PZ | C10: ='Юнит 14'!AO5 -> 75745.827 | D10: =C10/C$105 -> 0.057974012 | E10: =E9+D10 -> 0.67441373 | F10: =IF(AND(E10<=0),"C",IF(E10<=0.8,"A",IF(E10<=0.95,"B","C"))) -> A | G10: =VLOOKUP(B$4:B$104,I$4:M$104,5,0) -> A | I10: черные с железкой классика | J10: ='Юнит 14'!U3 -> 173 | K10: =J10/J$105 -> 0.059104886 | L10: =L9+K10 -> 0.59309874 | M10: =_xlfn.IFS(L10<80%,"A",L10<=95%,"B",L10>95%,"C") -> A
B11: th син | C11: ='Юнит 14'!AO10 -> 60980.795 | D11: =C11/C$105 -> 0.046673216 | E11: =E10+D11 -> 0.72108695 | F11: =IF(AND(E11<=0),"C",IF(E11<=0.8,"A",IF(E11<=0.95,"B","C"))) -> A | G11: =VLOOKUP(B$4:B$104,I$4:M$104,5,0) -> A | I11: QS синие PZ | J11: ='Юнит 14'!U5 -> 168 | K11: =J11/J$105 -> 0.057396652 | L11: =L10+K11 -> 0.65049539 | M11: =_xlfn.IFS(L11<80%,"A",L11<=95%,"B",L11>95%,"C") -> A
B12: th желт | C12: ='Юнит 14'!AO11 -> 51237.526 | D12: =C12/C$105 -> 0.039215955 | E12: =E11+D12 -> 0.7603029 | F12: =IF(AND(E12<=0),"C",IF(E12<=0.8,"A",IF(E12<=0.95,"B","C"))) -> A | G12: =VLOOKUP(B$4:B$104,I$4:M$104,5,0) -> A | I12: th коричн | J12: ='Юнит 14'!U12 -> 135 | K12: =J12/J$105 -> 0.04612231 | L12: =L11+K12 -> 0.6966177 | M12: =_xlfn.IFS(L12<80%,"A",L12<=95%,"B",L12>95%,"C") -> A
B13: th коричн | C13: ='Юнит 14'!AO12 -> 49657.381 | D13: =C13/C$105 -> 0.038006551 | E13: =E12+D13 -> 0.79830946 | F13: =IF(AND(E13<=0),"C",IF(E13<=0.8,"A",IF(E13<=0.95,"B","C"))) -> A | G13: =VLOOKUP(B$4:B$104,I$4:M$104,5,0) -> A | I13: th желт | J13: ='Юнит 14'!U11 -> 112 | K13: =J13/J$105 -> 0.038264435 | L13: =L12+K13 -> 0.73488213 | M13: =_xlfn.IFS(L13<80%,"A",L13<=95%,"B",L13>95%,"C") -> A
B14: QS желтые PZ | C14: ='Юнит 14'!AO6 -> 35034.333 | D14: =C14/C$105 -> 0.026814426 | E14: =E13+D14 -> 0.82512388 | F14: =IF(AND(E14<=0),"C",IF(E14<=0.8,"A",IF(E14<=0.95,"B","C"))) -> B | G14: =VLOOKUP(B$4:B$104,I$4:M$104,5,0) -> A | I14: sh3 | J14: ='Юнит 14'!U28 -> 79 | K14: =J14/J$105 -> 0.026990092 | L14: =L13+K14 -> 0.76187222 | M14: =_xlfn.IFS(L14<80%,"A",L14<=95%,"B",L14>95%,"C") -> A
B15: ww 2018 желтые | C15: ='Юнит 14'!AO50 -> 32607.021 | D15: =C15/C$105 -> 0.02495662 | E15: =E14+D15 -> 0.8500805 | F15: =IF(AND(E15<=0),"C",IF(E15<=0.8,"A",IF(E15<=0.95,"B","C"))) -> B | G15: =VLOOKUP(B$4:B$104,I$4:M$104,5,0) -> B | I15: QS желтые PZ | J15: ='Юнит 14'!U6 -> 76 | K15: =J15/J$105 -> 0.025965152 | L15: =L14+K15 -> 0.78783738 | M15: =_xlfn.IFS(L15<80%,"A",L15<=95%,"B",L15>95%,"C") -> A
B16: sh3 | C16: ='Юнит 14'!AO28 -> 29891.064 | D16: =C16/C$105 -> 0.022877893 | E16: =E15+D16 -> 0.87295839 | F16: =IF(AND(E16<=0),"C",IF(E16<=0.8,"A",IF(E16<=0.95,"B","C"))) -> B | G16: =VLOOKUP(B$4:B$104,I$4:M$104,5,0) -> A | I16: ww 1022 коричневые | J16: ='Юнит 14'!U48 -> 67 | K16: =J16/J$105 -> 0.022890331 | L16: =L15+K16 -> 0.81072771 | M16: =_xlfn.IFS(L16<80%,"A",L16<=95%,"B",L16>95%,"C") -> B
B17: flip желтые | C17: ='Юнит 14'!AO15 -> 25591.497 | D17: =C17/C$105 -> 0.019587109 | E17: =E16+D17 -> 0.8925455 | F17: =IF(AND(E17<=0),"C",IF(E17<=0.8,"A",IF(E17<=0.95,"B","C"))) -> B | G17: =VLOOKUP(B$4:B$104,I$4:M$104,5,0) -> B | I17: ww 2018 желтые | J17: ='Юнит 14'!U50 -> 62 | K17: =J17/J$105 -> 0.021182098 | L17: =L16+K17 -> 0.83190981 | M17: =_xlfn.IFS(L17<80%,"A",L17<=95%,"B",L17>95%,"C") -> B
B18: ww 1022 коричневые | C18: ='Юнит 14'!AO48 -> 21995.534 | D18: =C18/C$105 -> 0.016834846 | E18: =E17+D18 -> 0.90938035 | F18: =IF(AND(E18<=0),"C",IF(E18<=0.8,"A",IF(E18<=0.95,"B","C"))) -> B | G18: =VLOOKUP(B$4:B$104,I$4:M$104,5,0) -> B | I18: flip желтые | J18: ='Юнит 14'!U15 -> 57 | K18: =J18/J$105 -> 0.019473864 | L18: =L17+K18 -> 0.85138367 | M18: =_xlfn.IFS(L18<80%,"A",L18<=95%,"B",L18>95%,"C") -> B
B19: flip синие | C19: ='Юнит 14'!AO14 -> 21141.184 | D19: =C19/C$105 -> 0.016180948 | E19: =E18+D19 -> 0.9255613 | F19: =IF(AND(E19<=0),"C",IF(E19<=0.8,"A",IF(E19<=0.95,"B","C"))) -> B | G19: =VLOOKUP(B$4:B$104,I$4:M$104,5,0) -> B | I19: flip синие | J19: ='Юнит 14'!U14 -> 55 | K19: =J19/J$105 -> 0.018790571 | L19: =L18+K19 -> 0.87017424 | M19: =_xlfn.IFS(L19<80%,"A",L19<=95%,"B",L19>95%,"C") -> B
B20: wwl8032 хром металл | C20: ='Юнит 14'!AO18 -> 20540.778 | D20: =C20/C$105 -> 0.015721412 | E20: =E19+D20 -> 0.94128271 | F20: =IF(AND(E20<=0),"C",IF(E20<=0.8,"A",IF(E20<=0.95,"B","C"))) -> B | G20: =VLOOKUP(B$4:B$104,I$4:M$104,5,0) -> B | I20: ww 2018 черные | J20: ='Юнит 14'!U49 -> 52 | K20: =J20/J$105 -> 0.01776563 | L20: =L19+K20 -> 0.88793987 | M20: =_xlfn.IFS(L20<80%,"A",L20<=95%,"B",L20>95%,"C") -> B
B21: ww 2018 черные | C21: ='Юнит 14'!AO49 -> 19594.384 | D21: =C21/C$105 -> 0.014997064 | E21: =E20+D21 -> 0.95627977 | F21: =IF(AND(E21<=0),"C",IF(E21<=0.8,"A",IF(E21<=0.95,"B","C"))) -> C | G21: =VLOOKUP(B$4:B$104,I$4:M$104,5,0) -> B | I21: wwl8032 хром металл | J21: ='Юнит 14'!U18 -> 47 | K21: =J21/J$105 -> 0.016057397 | L21: =L20+K21 -> 0.90399727 | M21: =_xlfn.IFS(L21<80%,"A",L21<=95%,"B",L21>95%,"C") -> B
B22: MR8854 C2 Жен | C22: ='Юнит 14'!AO8 -> 17115.246 | D22: =C22/C$105 -> 0.013099593 | E22: =E21+D22 -> 0.96937937 | F22: =IF(AND(E22<=0),"C",IF(E22<=0.8,"A",IF(E22<=0.95,"B","C"))) -> C | G22: =VLOOKUP(B$4:B$104,I$4:M$104,5,0) -> B | I22: MR8854 C2 Жен | J22: ='Юнит 14'!U8 -> 38 | K22: =J22/J$105 -> 0.012982576 | L22: =L21+K22 -> 0.91697984 | M22: =_xlfn.IFS(L22<80%,"A",L22<=95%,"B",L22>95%,"C") -> B
B23: wwl8032 коричневые золото | C23: ='Юнит 14'!AO17 -> 16290.673 | D23: =C23/C$105 -> 0.012468484 | E23: =E22+D23 -> 0.98184785 | F23: =IF(AND(E23<=0),"C",IF(E23<=0.8,"A",IF(E23<=0.95,"B","C"))) -> C | G23: =VLOOKUP(B$4:B$104,I$4:M$104,5,0) -> B | I23: ww 203 черные | J23: ='Юнит 14'!U44 -> 37 | K23: =J23/J$105 -> 0.012640929 | L23: =L22+K23 -> 0.92962077 | M23: =_xlfn.IFS(L23<80%,"A",L23<=95%,"B",L23>95%,"C") -> B
B24: ww 1022 черные | C24: ='Юнит 14'!AO45 -> 13568.885 | D24: =C24/C$105 -> 0.010385294 | E24: =E23+D24 -> 0.99223314 | F24: =IF(AND(E24<=0),"C",IF(E24<=0.8,"A",IF(E24<=0.95,"B","C"))) -> C | G24: =VLOOKUP(B$4:B$104,I$4:M$104,5,0) -> C | I24: wwl8032 коричневые золото | J24: ='Юнит 14'!U17 -> 35 | K24: =J24/J$105 -> 0.011957636 | L24: =L23+K24 -> 0.94157841 | M24: =_xlfn.IFS(L24<80%,"A",L24<=95%,"B",L24>95%,"C") -> B
B25: ww 203 черные | C25: ='Юнит 14'!AO44 -> 11502.142 | D25: =C25/C$105 -> 0.0088034593 | E25: =E24+D25 -> 1.0010366 | F25: =IF(AND(E25<=0),"C",IF(E25<=0.8,"A",IF(E25<=0.95,"B","C"))) -> C | G25: =VLOOKUP(B$4:B$104,I$4:M$104,5,0) -> B | I25: кс_черные_женские | J25: ='Юнит 14'!U102 -> 18 | K25: =J25/J$105 -> 0.0061496413 | L25: =L24+K25 -> 0.94772805 | M25: =_xlfn.IFS(L25<80%,"A",L25<=95%,"B",L25>95%,"C") -> B
B26: MR Р1894 черные | C26: ='Юнит 14'!AO89 -> 3018.3532 | D26: =C26/C$105 -> 0.0023101741 | E26: =E25+D26 -> 1.0033468 | F26: =IF(AND(E26<=0),"C",IF(E26<=0.8,"A",IF(E26<=0.95,"B","C"))) -> C | G26: =VLOOKUP(B$4:B$104,I$4:M$104,5,0) -> C | I26: ww 1022 черные | J26: ='Юнит 14'!U45 -> 17 | K26: =J26/J$105 -> 0.0058079945 | L26: =L25+K26 -> 0.95353604 | M26: =_xlfn.IFS(L26<80%,"A",L26<=95%,"B",L26>95%,"C") -> C
B27: sh1 | C27: ='Юнит 14'!AO26 -> 2261.5307 | D27: =C27/C$105 -> 0.0017309205 | E27: =E26+D27 -> 1.0050777 | F27: =IF(AND(E27<=0),"C",IF(E27<=0.8,"A",IF(E27<=0.95,"B","C"))) -> C | G27: =VLOOKUP(B$4:B$104,I$4:M$104,5,0) -> C | I27: sh1 | J27: ='Юнит 14'!U26 -> 14 | K27: =J27/J$105 -> 0.0047830543 | L27: =L26+K27 -> 0.9583191 | M27: =_xlfn.IFS(L27<80%,"A",L27<=95%,"B",L27>95%,"C") -> C
B28: ЧСЖ_женские | C28: ='Юнит 14'!AO100 -> 2002.1241 | D28: =C28/C$105 -> 0.0015323771 | E28: =E27+D28 -> 1.0066101 | F28: =IF(AND(E28<=0),"C",IF(E28<=0.8,"A",IF(E28<=0.95,"B","C"))) -> C | G28: =VLOOKUP(B$4:B$104,I$4:M$104,5,0) -> C | I28: sports красные | J28: ='Юнит 14'!U22 -> 11 | K28: =J28/J$105 -> 0.0037581141 | L28: =L27+K28 -> 0.96207721 | M28: =_xlfn.IFS(L28<80%,"A",L28<=95%,"B",L28>95%,"C") -> C
B29: sh09 | C29: ='Юнит 14'!AO33 -> 1942.676 | D29: =C29/C$105 -> 0.001486877 | E29: =E28+D29 -> 1.008097 | F29: =IF(AND(E29<=0),"C",IF(E29<=0.8,"A",IF(E29<=0.95,"B","C"))) -> C | G29: =VLOOKUP(B$4:B$104,I$4:M$104,5,0) -> C | I29: sports зеленые | J29: ='Юнит 14'!U21 -> 7 | K29: =J29/J$105 -> 0.0023915272 | L29: =L28+K29 -> 0.96446874 | M29: =_xlfn.IFS(L29<80%,"A",L29<=95%,"B",L29>95%,"C") -> C
B30: Ли Сян ретро серебро | C30: ='Юнит 14'!AO93 -> 1470.7682 | D30: =C30/C$105 -> 0.0011256902 | E30: =E29+D30 -> 1.0092226 | F30: =IF(AND(E30<=0),"C",IF(E30<=0.8,"A",IF(E30<=0.95,"B","C"))) -> C | G30: =VLOOKUP(B$4:B$104,I$4:M$104,5,0) -> C | I30: sh09 | J30: ='Юнит 14'!U33 -> 7 | K30: =J30/J$105 -> 0.0023915272 | L30: =L29+K30 -> 0.96686027 | M30: =_xlfn.IFS(L30<80%,"A",L30<=95%,"B",L30>95%,"C") -> C
B31: Guangdu серебро серая линза | C31: ='Юнит 14'!AO80 -> 1434.6922 | D31: =C31/C$105 -> 0.0010980785 | E31: =E30+D31 -> 1.0103207 | F31: =IF(AND(E31<=0),"C",IF(E31<=0.8,"A",IF(E31<=0.95,"B","C"))) -> C | G31: =VLOOKUP(B$4:B$104,I$4:M$104,5,0) -> C | I31: Chenlong коричневые | J31: ='Юнит 14'!U77 -> 6 | K31: =J31/J$105 -> 0.0020498804 | L31: =L30+K31 -> 0.96891015 | M31: =_xlfn.IFS(L31<80%,"A",L31<=95%,"B",L31>95%,"C") -> C
B32: MANNA2101 | C32: ='Юнит 14'!AO54 -> 1203.7937 | D32: =C32/C$105 -> 0.00092135443 | E32: =E31+D32 -> 1.0112421 | F32: =IF(AND(E32<=0),"C",IF(E32<=0.8,"A",IF(E32<=0.95,"B","C"))) -> C | G32: =VLOOKUP(B$4:B$104,I$4:M$104,5,0) -> C | I32: MR Р1894 черные | J32: ='Юнит 14'!U89 -> 6 | K32: =J32/J$105 -> 0.0020498804 | L32: =L31+K32 -> 0.97096003 | M32: =_xlfn.IFS(L32<80%,"A",L32<=95%,"B",L32>95%,"C") -> C
B33: sports красные | C33: ='Юнит 14'!AO22 -> 983.75182 | D33: =C33/C$105 -> 0.0007529397 | E33: =E32+D33 -> 1.011995 | F33: =IF(AND(E33<=0),"C",IF(E33<=0.8,"A",IF(E33<=0.95,"B","C"))) -> C | G33: =VLOOKUP(B$4:B$104,I$4:M$104,5,0) -> C | I33: sports синие | J33: ='Юнит 14'!U20 -> 5 | K33: =J33/J$105 -> 0.0017082337 | L33: =L32+K33 -> 0.97266826 | M33: =_xlfn.IFS(L33<80%,"A",L33<=95%,"B",L33>95%,"C") -> C
B34: MANNA2117 | C34: ='Юнит 14'!AO70 -> 880.5291 | D34: =C34/C$105 -> 0.00067393554 | E34: =E33+D34 -> 1.012669 | F34: =IF(AND(E34<=0),"C",IF(E34<=0.8,"A",IF(E34<=0.95,"B","C"))) -> C | G34: =VLOOKUP(B$4:B$104,I$4:M$104,5,0) -> C | I34: MANNA2101 | J34: ='Юнит 14'!U54 -> 5 | K34: =J34/J$105 -> 0.0017082337 | L34: =L33+K34 -> 0.97437649 | M34: =_xlfn.IFS(L34<80%,"A",L34<=95%,"B",L34>95%,"C") -> C
B35: Taizhou Rayen sport розовый | C35: ='Юнит 14'!AO90 -> 877.8462 | D35: =C35/C$105 -> 0.00067188212 | E35: =E34+D35 -> 1.0133408 | F35: =IF(AND(E35<=0),"C",IF(E35<=0.8,"A",IF(E35<=0.95,"B","C"))) -> C | G35: =VLOOKUP(B$4:B$104,I$4:M$104,5,0) -> C | I35: MANNA2122 | J35: ='Юнит 14'!U75 -> 5 | K35: =J35/J$105 -> 0.0017082337 | L35: =L34+K35 -> 0.97608473 | M35: =_xlfn.IFS(L35<80%,"A",L35<=95%,"B",L35>95%,"C") -> C
B36: Hengda Optical леопард | C36: ='Юнит 14'!AO82 -> 852.01934 | D36: =C36/C$105 -> 0.00065211486 | E36: =E35+D36 -> 1.0139929 | F36: =IF(AND(E36<=0),"C",IF(E36<=0.8,"A",IF(E36<=0.95,"B","C"))) -> C | G36: =VLOOKUP(B$4:B$104,I$4:M$104,5,0) -> C | I36: Guangdu серебро серая линза | J36: ='Юнит 14'!U80 -> 5 | K36: =J36/J$105 -> 0.0017082337 | L36: =L35+K36 -> 0.97779296 | M36: =_xlfn.IFS(L36<80%,"A",L36<=95%,"B",L36>95%,"C") -> C
B37: sh16 | C37: ='Юнит 14'!AO40 -> 643.78498 | D37: =C37/C$105 -> 0.00049273736 | E37: =E36+D37 -> 1.0144857 | F37: =IF(AND(E37<=0),"C",IF(E37<=0.8,"A",IF(E37<=0.95,"B","C"))) -> C | G37: =VLOOKUP(B$4:B$104,I$4:M$104,5,0) -> C | I37: WW 3055 черный | J37: ='Юнит 14'!U52 -> 4 | K37: =J37/J$105 -> 0.0013665869 | L37: =L36+K37 -> 0.97915955 | M37: =_xlfn.IFS(L37<80%,"A",L37<=95%,"B",L37>95%,"C") -> C
B38: ww 1022 желтые | C38: ='Юнит 14'!AO47 -> 639.45554 | D38: =C38/C$105 -> 0.00048942371 | E38: =E37+D38 -> 1.0149751 | F38: =IF(AND(E38<=0),"C",IF(E38<=0.8,"A",IF(E38<=0.95,"B","C"))) -> C | G38: =VLOOKUP(B$4:B$104,I$4:M$104,5,0) -> C | I38: Chenlong черные | J38: ='Юнит 14'!U76 -> 4 | K38: =J38/J$105 -> 0.0013665869 | L38: =L37+K38 -> 0.98052614 | M38: =_xlfn.IFS(L38<80%,"A",L38<=95%,"B",L38>95%,"C") -> C
B39: sh18 | C39: ='Юнит 14'!AO42 -> 606.24778 | D39: =C39/C$105 -> 0.0004640073 | E39: =E35+D39 -> 1.0138048 | F39: =IF(AND(E39<=0),"C",IF(E39<=0.8,"A",IF(E39<=0.95,"B","C"))) -> C | G39: =VLOOKUP(B$4:B$104,I$4:M$104,5,0) -> C | I39: Qianai коричневые | J39: ='Юнит 14'!U84 -> 4 | K39: =J39/J$105 -> 0.0013665869 | L39: =L35+K39 -> 0.97745132 | M39: =_xlfn.IFS(L39<80%,"A",L39<=95%,"B",L39>95%,"C") -> C
B40: MANNA2116 | C40: ='Юнит 14'!AO69 -> 542.49546 | D40: =C40/C$105 -> 0.00041521282 | E40: =E39+D40 -> 1.0142201 | F40: =IF(AND(E40<=0),"C",IF(E40<=0.8,"A",IF(E40<=0.95,"B","C"))) -> C | G40: =VLOOKUP(B$4:B$104,I$4:M$104,5,0) -> C | I40: ЧСЖ_женские | J40: ='Юнит 14'!U100 -> 4 | K40: =J40/J$105 -> 0.0013665869 | L40: =L39+K40 -> 0.9788179 | M40: =_xlfn.IFS(L40<80%,"A",L40<=95%,"B",L40>95%,"C") -> C
B41: MANNA2108 | C41: ='Юнит 14'!AO61 -> 531.18139 | D41: =C41/C$105 -> 0.00040655331 | E41: =E40+D41 -> 1.0146266 | F41: =IF(AND(E41<=0),"C",IF(E41<=0.8,"A",IF(E41<=0.95,"B","C"))) -> C | G41: =VLOOKUP(B$4:B$104,I$4:M$104,5,0) -> C | I41: sh2 | J41: ='Юнит 14'!U27 -> 3 | K41: =J41/J$105 -> 0.0010249402 | L41: =L40+K41 -> 0.97984284 | M41: =_xlfn.IFS(L41<80%,"A",L41<=95%,"B",L41>95%,"C") -> C
B42: sh19 | C42: ='Юнит 14'!AO43 -> 512.43796 | D42: =C42/C$105 -> 0.00039220754 | E42: =E41+D42 -> 1.0150188 | F42: =IF(AND(E42<=0),"C",IF(E42<=0.8,"A",IF(E42<=0.95,"B","C"))) -> C | G42: =VLOOKUP(B$4:B$104,I$4:M$104,5,0) -> C | I42: sh18 | J42: ='Юнит 14'!U42 -> 3 | K42: =J42/J$105 -> 0.0010249402 | L42: =L41+K42 -> 0.98086778 | M42: =_xlfn.IFS(L42<80%,"A",L42<=95%,"B",L42>95%,"C") -> C
B43: MANNA2122 | C43: ='Юнит 14'!AO75 -> 484.67029 | D43: =C43/C$105 -> 0.00037095484 | E43: =E42+D43 -> 1.0153898 | F43: =IF(AND(E43<=0),"C",IF(E43<=0.8,"A",IF(E43<=0.95,"B","C"))) -> C | G43: =VLOOKUP(B$4:B$104,I$4:M$104,5,0) -> C | I43: ww 1022 желтые | J43: ='Юнит 14'!U47 -> 3 | K43: =J43/J$105 -> 0.0010249402 | L43: =L42+K43 -> 0.98189272 | M43: =_xlfn.IFS(L43<80%,"A",L43<=95%,"B",L43>95%,"C") -> C
B44: MANNA2120 | C44: ='Юнит 14'!AO73 -> 412.72262 | D44: =C44/C$105 -> 0.00031588785 | E44: =E43+D44 -> 1.0157057 | F44: =IF(AND(E44<=0),"C",IF(E44<=0.8,"A",IF(E44<=0.95,"B","C"))) -> C | G44: =VLOOKUP(B$4:B$104,I$4:M$104,5,0) -> C | I44: MANNA2108 | J44: ='Юнит 14'!U61 -> 3 | K44: =J44/J$105 -> 0.0010249402 | L44: =L43+K44 -> 0.98291766 | M44: =_xlfn.IFS(L44<80%,"A",L44<=95%,"B",L44>95%,"C") -> C
B45: sh10 | C45: ='Юнит 14'!AO34 -> 333.24 | D45: =C45/C$105 -> 0.00025505378 | E45: =E44+D45 -> 1.0159607 | F45: =IF(AND(E45<=0),"C",IF(E45<=0.8,"A",IF(E45<=0.95,"B","C"))) -> C | G45: =VLOOKUP(B$4:B$104,I$4:M$104,5,0) -> C | I45: Chenlong белые | J45: ='Юнит 14'!U78 -> 3 | K45: =J45/J$105 -> 0.0010249402 | L45: =L44+K45 -> 0.9839426 | M45: =_xlfn.IFS(L45<80%,"A",L45<=95%,"B",L45>95%,"C") -> C
B46: Qianai черные | C46: ='Юнит 14'!AO83 -> 320.54409 | D46: =C46/C$105 -> 0.00024533664 | E46: =E45+D46 -> 1.016206 | F46: =IF(AND(E46<=0),"C",IF(E46<=0.8,"A",IF(E46<=0.95,"B","C"))) -> C | G46: =VLOOKUP(B$4:B$104,I$4:M$104,5,0) -> C | I46: Guangdu золото серая линза | J46: ='Юнит 14'!U79 -> 3 | K46: =J46/J$105 -> 0.0010249402 | L46: =L45+K46 -> 0.98496754 | M46: =_xlfn.IFS(L46<80%,"A",L46<=95%,"B",L46>95%,"C") -> C
B47: MANNA2119 | C47: ='Юнит 14'!AO72 -> 303.5717 | D47: =C47/C$105 -> 0.00023234639 | E47: =E46+D47 -> 1.0164384 | F47: =IF(AND(E47<=0),"C",IF(E47<=0.8,"A",IF(E47<=0.95,"B","C"))) -> C | G47: =VLOOKUP(B$4:B$104,I$4:M$104,5,0) -> C | I47: Ли Сян ретро серебро | J47: ='Юнит 14'!U93 -> 3 | K47: =J47/J$105 -> 0.0010249402 | L47: =L46+K47 -> 0.98599248 | M47: =_xlfn.IFS(L47<80%,"A",L47<=95%,"B",L47>95%,"C") -> C
B48: sh14 | C48: ='Юнит 14'!AO38 -> 302.82005 | D48: =C48/C$105 -> 0.0002317711 | E48: =E47+D48 -> 1.0166702 | F48: =IF(AND(E48<=0),"C",IF(E48<=0.8,"A",IF(E48<=0.95,"B","C"))) -> C | G48: =VLOOKUP(B$4:B$104,I$4:M$104,5,0) -> C | I48: sh16 | J48: ='Юнит 14'!U40 -> 2 | K48: =J48/J$105 -> 0.00068329347 | L48: =L47+K48 -> 0.98667578 | M48: =_xlfn.IFS(L48<80%,"A",L48<=95%,"B",L48>95%,"C") -> C
B49: Chenlong коричневые | C49: ='Юнит 14'!AO77 -> 231.03733 | D49: =C49/C$105 -> 0.00017683035 | E49: =E48+D49 -> 1.016847 | F49: =IF(AND(E49<=0),"C",IF(E49<=0.8,"A",IF(E49<=0.95,"B","C"))) -> C | G49: =VLOOKUP(B$4:B$104,I$4:M$104,5,0) -> C | I49: sh19 | J49: ='Юнит 14'!U43 -> 2 | K49: =J49/J$105 -> 0.00068329347 | L49: =L48+K49 -> 0.98735907 | M49: =_xlfn.IFS(L49<80%,"A",L49<=95%,"B",L49>95%,"C") -> C
B50: Hengda Optical черные | C50: ='Юнит 14'!AO81 -> 132.24931 | D50: =C50/C$105 -> 0.00010122041 | E50: =E49+D50 -> 1.0169482 | F50: =IF(AND(E50<=0),"C",IF(E50<=0.8,"A",IF(E50<=0.95,"B","C"))) -> C | G50: =VLOOKUP(B$4:B$104,I$4:M$104,5,0) -> C | I50: MANNA2116 | J50: ='Юнит 14'!U69 -> 2 | K50: =J50/J$105 -> 0.00068329347 | L50: =L49+K50 -> 0.98804236 | M50: =_xlfn.IFS(L50<80%,"A",L50<=95%,"B",L50>95%,"C") -> C
B51: YIMEI 2391 C1 | C51: ='Юнит 14'!AO98 -> 73.132482 | D51: =C51/C$105 -> 5.5973822e-05 | E51: =E50+D51 -> 1.0170042 | F51: =IF(AND(E51<=0),"C",IF(E51<=0.8,"A",IF(E51<=0.95,"B","C"))) -> C | G51: =VLOOKUP(B$4:B$104,I$4:M$104,5,0) -> C | I51: MANNA2117 | J51: ='Юнит 14'!U70 -> 2 | K51: =J51/J$105 -> 0.00068329347 | L51: =L50+K51 -> 0.98872566 | M51: =_xlfn.IFS(L51<80%,"A",L51<=95%,"B",L51>95%,"C") -> C
B52: WW 3055 черный | C52: ='Юнит 14'!AO52 -> 60.788196 | D52: =C52/C$105 -> 4.6525805e-05 | E52: =E51+D52 -> 1.0170507 | F52: =IF(AND(E52<=0),"C",IF(E52<=0.8,"A",IF(E52<=0.95,"B","C"))) -> C | G52: =VLOOKUP(B$4:B$104,I$4:M$104,5,0) -> C | I52: MANNA2120 | J52: ='Юнит 14'!U73 -> 2 | K52: =J52/J$105 -> 0.00068329347 | L52: =L51+K52 -> 0.98940895 | M52: =_xlfn.IFS(L52<80%,"A",L52<=95%,"B",L52>95%,"C") -> C
B53: MANNA2118 | C53: ='Юнит 14'!AO71 -> 30.53 | D53: =C53/C$105 -> 2.3366919e-05 | E53: =E52+D53 -> 1.0170741 | F53: =IF(AND(E53<=0),"C",IF(E53<=0.8,"A",IF(E53<=0.95,"B","C"))) -> C | G53: =VLOOKUP(B$4:B$104,I$4:M$104,5,0) -> C | I53: Hengda Optical леопард | J53: ='Юнит 14'!U82 -> 2 | K53: =J53/J$105 -> 0.00068329347 | L53: =L52+K53 -> 0.99009224 | M53: =_xlfn.IFS(L53<80%,"A",L53<=95%,"B",L53>95%,"C") -> C
B54: wwl8032 черные серебро | C54: ='Юнит 14'!AO19 -> 0 | D54: =C54/C$105 -> 0 | E54: =E53+D54 -> 1.0170741 | F54: =IF(AND(E54<=0),"C",IF(E54<=0.8,"A",IF(E54<=0.95,"B","C"))) -> C | G54: =VLOOKUP(B$4:B$104,I$4:M$104,5,0) -> C | I54: Taizhou Rayen sport розовый | J54: ='Юнит 14'!U90 -> 2 | K54: =J54/J$105 -> 0.00068329347 | L54: =L53+K54 -> 0.99077554 | M54: =_xlfn.IFS(L54<80%,"A",L54<=95%,"B",L54>95%,"C") -> C
B55: sportlife черные | C55: ='Юнит 14'!AO23 -> 0 | D55: =C55/C$105 -> 0 | E55: =E54+D55 -> 1.0170741 | F55: =IF(AND(E55<=0),"C",IF(E55<=0.8,"A",IF(E55<=0.95,"B","C"))) -> C | G55: =VLOOKUP(B$4:B$104,I$4:M$104,5,0) -> C | I55: sh10 | J55: ='Юнит 14'!U34 -> 1 | K55: =J55/J$105 -> 0.00034164674 | L55: =L54+K55 -> 0.99111718 | M55: =_xlfn.IFS(L55<80%,"A",L55<=95%,"B",L55>95%,"C") -> C
B56: sportlife синие | C56: ='Юнит 14'!AO24 -> 0 | D56: =C56/C$105 -> 0 | E56: =E55+D56 -> 1.0170741 | F56: =IF(AND(E56<=0),"C",IF(E56<=0.8,"A",IF(E56<=0.95,"B","C"))) -> C | G56: =VLOOKUP(B$4:B$104,I$4:M$104,5,0) -> C | I56: sh14 | J56: ='Юнит 14'!U38 -> 1 | K56: =J56/J$105 -> 0.00034164674 | L56: =L55+K56 -> 0.99145883 | M56: =_xlfn.IFS(L56<80%,"A",L56<=95%,"B",L56>95%,"C") -> C
B57: sportlife красные | C57: ='Юнит 14'!AO25 -> 0 | D57: =C57/C$105 -> 0 | E57: =E56+D57 -> 1.0170741 | F57: =IF(AND(E57<=0),"C",IF(E57<=0.8,"A",IF(E57<=0.95,"B","C"))) -> C | G57: =VLOOKUP(B$4:B$104,I$4:M$104,5,0) -> C | I57: sh15 | J57: ='Юнит 14'!U39 -> 1 | K57: =J57/J$105 -> 0.00034164674 | L57: =L56+K57 -> 0.99180048 | M57: =_xlfn.IFS(L57<80%,"A",L57<=95%,"B",L57>95%,"C") -> C
B58: sh4 | C58: ='Юнит 14'!AO29 -> 0 | D58: =C58/C$105 -> 0 | E58: =E57+D58 -> 1.0170741 | F58: =IF(AND(E58<=0),"C",IF(E58<=0.8,"A",IF(E58<=0.95,"B","C"))) -> C | G58: =VLOOKUP(B$4:B$104,I$4:M$104,5,0) -> C | I58: WW 3055 коричневый | J58: ='Юнит 14'!U53 -> 1 | K58: =J58/J$105 -> 0.00034164674 | L58: =L57+K58 -> 0.99214213 | M58: =_xlfn.IFS(L58<80%,"A",L58<=95%,"B",L58>95%,"C") -> C
B59: sh06 | C59: ='Юнит 14'!AO30 -> 0 | D59: =C59/C$105 -> 0 | E59: =E58+D59 -> 1.0170741 | F59: =IF(AND(E59<=0),"C",IF(E59<=0.8,"A",IF(E59<=0.95,"B","C"))) -> C | G59: =VLOOKUP(B$4:B$104,I$4:M$104,5,0) -> C | I59: MANNA2105 | J59: ='Юнит 14'!U58 -> 1 | K59: =J59/J$105 -> 0.00034164674 | L59: =L58+K59 -> 0.99248377 | M59: =_xlfn.IFS(L59<80%,"A",L59<=95%,"B",L59>95%,"C") -> C
B60: sh07 | C60: ='Юнит 14'!AO31 -> 0 | D60: =C60/C$105 -> 0 | E60: =E59+D60 -> 1.0170741 | F60: =IF(AND(E60<=0),"C",IF(E60<=0.8,"A",IF(E60<=0.95,"B","C"))) -> C | G60: =VLOOKUP(B$4:B$104,I$4:M$104,5,0) -> C | I60: MANNA2118 | J60: ='Юнит 14'!U71 -> 1 | K60: =J60/J$105 -> 0.00034164674 | L60: =L59+K60 -> 0.99282542 | M60: =_xlfn.IFS(L60<80%,"A",L60<=95%,"B",L60>95%,"C") -> C
B61: sh08 | C61: ='Юнит 14'!AO32 -> 0 | D61: =C61/C$105 -> 0 | E61: =E60+D61 -> 1.0170741 | F61: =IF(AND(E61<=0),"C",IF(E61<=0.8,"A",IF(E61<=0.95,"B","C"))) -> C | G61: =VLOOKUP(B$4:B$104,I$4:M$104,5,0) -> C | I61: MANNA2119 | J61: ='Юнит 14'!U72 -> 1 | K61: =J61/J$105 -> 0.00034164674 | L61: =L60+K61 -> 0.99316707 | M61: =_xlfn.IFS(L61<80%,"A",L61<=95%,"B",L61>95%,"C") -> C
B62: sh11 | C62: ='Юнит 14'!AO35 -> 0 | D62: =C62/C$105 -> 0 | E62: =E61+D62 -> 1.0170741 | F62: =IF(AND(E62<=0),"C",IF(E62<=0.8,"A",IF(E62<=0.95,"B","C"))) -> C | G62: =VLOOKUP(B$4:B$104,I$4:M$104,5,0) -> C | I62: Hengda Optical черные | J62: ='Юнит 14'!U81 -> 1 | K62: =J62/J$105 -> 0.00034164674 | L62: =L61+K62 -> 0.99350871 | M62: =_xlfn.IFS(L62<80%,"A",L62<=95%,"B",L62>95%,"C") -> C
B63: sh12 | C63: ='Юнит 14'!AO36 -> 0 | D63: =C63/C$105 -> 0 | E63: =E62+D63 -> 1.0170741 | F63: =IF(AND(E63<=0),"C",IF(E63<=0.8,"A",IF(E63<=0.95,"B","C"))) -> C | G63: =VLOOKUP(B$4:B$104,I$4:M$104,5,0) -> C | I63: Qianai черные | J63: ='Юнит 14'!U83 -> 1 | K63: =J63/J$105 -> 0.00034164674 | L63: =L62+K63 -> 0.99385036 | M63: =_xlfn.IFS(L63<80%,"A",L63<=95%,"B",L63>95%,"C") -> C
B64: ww 1022 черн-серебро | C64: ='Юнит 14'!AO46 -> 0 | D64: =C64/C$105 -> 0 | E64: =E63+D64 -> 1.0170741 | F64: =IF(AND(E64<=0),"C",IF(E64<=0.8,"A",IF(E64<=0.95,"B","C"))) -> C | G64: =VLOOKUP(B$4:B$104,I$4:M$104,5,0) -> C | I64: Linhai Baiyi коричневая линза | J64: ='Юнит 14'!U86 -> 1 | K64: =J64/J$105 -> 0.00034164674 | L64: =L63+K64 -> 0.99419201 | M64: =_xlfn.IFS(L64<80%,"A",L64<=95%,"B",L64>95%,"C") -> C
B65: ww 8010 черные | C65: ='Юнит 14'!AO51 -> 0 | D65: =C65/C$105 -> 0 | E65: =E64+D65 -> 1.0170741 | F65: =IF(AND(E65<=0),"C",IF(E65<=0.8,"A",IF(E65<=0.95,"B","C"))) -> C | G65: =VLOOKUP(B$4:B$104,I$4:M$104,5,0) -> C | I65: Linhai Baiyi серая линза | J65: ='Юнит 14'!U87 -> 1 | K65: =J65/J$105 -> 0.00034164674 | L65: =L64+K65 -> 0.99453365 | M65: =_xlfn.IFS(L65<80%,"A",L65<=95%,"B",L65>95%,"C") -> C
B66: MANNA2103 | C66: ='Юнит 14'!AO56 -> 0 | D66: =C66/C$105 -> 0 | E66: =E65+D66 -> 1.0170741 | F66: =IF(AND(E66<=0),"C",IF(E66<=0.8,"A",IF(E66<=0.95,"B","C"))) -> C | G66: =VLOOKUP(B$4:B$104,I$4:M$104,5,0) -> C | I66: Иу Диту серый | J66: ='Юнит 14'!U91 -> 1 | K66: =J66/J$105 -> 0.00034164674 | L66: =L65+K66 -> 0.9948753 | M66: =_xlfn.IFS(L66<80%,"A",L66<=95%,"B",L66>95%,"C") -> C
B67: MANNA2104 | C67: ='Юнит 14'!AO57 -> 0 | D67: =C67/C$105 -> 0 | E67: =E66+D67 -> 1.0170741 | F67: =IF(AND(E67<=0),"C",IF(E67<=0.8,"A",IF(E67<=0.95,"B","C"))) -> C | G67: =VLOOKUP(B$4:B$104,I$4:M$104,5,0) -> C | I67: Ли Сян ретро золото | J67: ='Юнит 14'!U92 -> 1 | K67: =J67/J$105 -> 0.00034164674 | L67: =L66+K67 -> 0.99521695 | M67: =_xlfn.IFS(L67<80%,"A",L67<=95%,"B",L67>95%,"C") -> C
B68: MANNA2106 | C68: ='Юнит 14'!AO59 -> 0 | D68: =C68/C$105 -> 0 | E68: =E67+D68 -> 1.0170741 | F68: =IF(AND(E68<=0),"C",IF(E68<=0.8,"A",IF(E68<=0.95,"B","C"))) -> C | G68: =VLOOKUP(B$4:B$104,I$4:M$104,5,0) -> C | I68: YIMEI 2391 C1 | J68: ='Юнит 14'!U98 -> 1 | K68: =J68/J$105 -> 0.00034164674 | L68: =L67+K68 -> 0.99555859 | M68: =_xlfn.IFS(L68<80%,"A",L68<=95%,"B",L68>95%,"C") -> C
B69: MANNA2109 | C69: ='Юнит 14'!AO62 -> 0 | D69: =C69/C$105 -> 0 | E69: =E68+D69 -> 1.0170741 | F69: =IF(AND(E69<=0),"C",IF(E69<=0.8,"A",IF(E69<=0.95,"B","C"))) -> C | G69: =VLOOKUP(B$4:B$104,I$4:M$104,5,0) -> C | I69: wwl8032 черные серебро | J69: ='Юнит 14'!U19 -> 0 | K69: =J69/J$105 -> 0 | L69: =L68+K69 -> 0.99555859 | M69: =_xlfn.IFS(L69<80%,"A",L69<=95%,"B",L69>95%,"C") -> C
