Workbook

Sheet Реклама
B2: БАЛАНС | E2: СЧЕТ | H2: ПРОМОБОНУСЫ | K2: Неделя
B3: Номер документа | C3: Сумма | D3: Даты | E3: Номер документа | F3: Сумма | G3: Даты | H3: Номер документа | I3: Сумма | J3: Даты
B4: 277433850 | C4: 1376 | D4: 28-31.12 | E4: 277433847 | F4: 25829 | G4: 28-31.12 | H4: 0 | I4: 109 | J4: 29-31.12 | K4: 1
B5: 277539131 | C5: 1150 | D5: 36951 | E5: 277609313 | F5: 21489 | G5: 36982 | H5: 0 | I5: 363 | J5: 36982
B6: 279208603 | C6: 3455 | D6: 37168 | E6: 279208599 | F6: 51313 | G6: 37199 | H6: 0 | I6: 569 | J6: 37200 | K6: 2
B7: 280269091 | C7: 10268 | D7: 11-18.01 | E7: 280221209 | F7: 99763 | G7: 11-18.01 | H7: 0 | I7: 557 | J7: 12-18.01 | K7: 3
B8: 281267335 | C8: 70408 | D8: 19-25.01 | E8: 281348313 | F8: 67741 | G8: 18-25.01 | H8: 0 | I8: 195 | J8: 19-25.01 | K8: 4
B9: 282258474 | C9: 25521 | D9: 25-31.01 | E9: 282345086 | F9: 133680 | G9: 25-31.01 | H9: 0 | I9: 80 | J9: 26-31.01 | K9: 5
B10: 282365257 | C10: 1268 | D10: 46054 | E10: 282392960 | F10: 4672 | G10: 46054
B11: 283332206 | C11: 111419 | D11: 37469 | E11: 283415801 | F11: 126688 | G11: 37469 | H11: 0 | I11: 3554 | J11: 37440 | K11: 6
B12: 284423647 | C12: 145581 | D12: 08-15.02 | E12: 284416459 | F12: 138670 | G12: 08-15.02 | H12: 0 | I12: 44 | J12: 46063 | K12: 7
B13: 285348588 | C13: 50989 | D13: 15-22.02 | E13: 285348587 | F13: 265182 | G13: 15-22.02 | K13: 8
B14: 286343097 | C14: 232417 | D14: 22-28.02 | E14: 286343091 | F14: 72806 | G14: 22-28.02 | H14: 0 | I14: 26 | J14: 46081 | K14: 9
B15: 286459024 | C15: 1243 | D15: 46082 | E15: 286489905 | F15: 5815 | G15: 46082
B16: 287708507 | C16: 74484 | D16: 01.03-08.03 | E16: 287655729 | F16: 252853 | G16: 01.03-08.03 | K16: 10
H39: .

Sheet Сводная
B2: Период | E2: Дата поступления дс | F2: Итого к перечислению на счет, руб | G2: шт. | J2: ВБ реализовал товар (выручка с СПП) | M2: Выручка до вычета комиссии ВБ | P2: Себестоимость продаж | Q2: Логистика WB | R2: Комиссия WB | S2: Хранение WB | T2: Платная приемка WB | U2: Штрафы WB | V2: Прочие удержания WB | W2: Реклама БАЛАНС | X2: Реклама СЧЕТ | Y2: Блогеры | Z2: Налог | AA2: Прочие поступления WB | AB2: Прибыль до вычета налогов | AC2: Прибыль после вычета налогов | AD2: Итог месяц | AE2: % Cебестоимости | AF2: Маржинальность, % | AG2: Рентабельность, % | AH2: Доля рекламы, %
B3: Месяц | C3: Даты | D3: Нед | G3: Заказы | H3: Продажи | I3: Возвраты | J3: Продажи | K3: Возвраты | L3: Общая | M3: Продажи | N3: Возвраты | O3: Общая
B4: Декабрь очки | C4: 29-31.12 | D4: 1 | F4: =IFERROR(O4-SUM(Q4:W4)+AA4,0) -> 62313.298 | G4: =ДЕКАБРЬ!N100 -> 129 | H4: =ДЕКАБРЬ!S100 -> 127 | I4: =ДЕКАБРЬ!T100 -> -5 | J4: =ДЕКАБРЬ!V100 -> 118047.57 | K4: =ДЕКАБРЬ!W100 -> -6409 | L4: =IFERROR(J4+K4,0) -> 111638.57 | M4: =ДЕКАБРЬ!Y100 -> 138964.57 | N4: =ДЕКАБРЬ!Z100 -> -7526 | O4: =IFERROR(M4+N4,0) -> 131438.57 | P4: =ДЕКАБРЬ!AD100 -> 15240.45 | Q4: =ДЕКАБРЬ!AG100 -> 17381.1 | R4: =ДЕКАБРЬ!AE100 -> 48126.54 | S4: =ДЕКАБРЬ!AL100 -> 3615.9322 | T4: 1.7 | U4: =ДЕКАБРЬ!AM100 -> 0 | W4: =ДЕКАБРЬ!AH100 -> 0 | X4: =ДЕКАБРЬ!AI100 -> 0 | Y4: =ДЕКАБРЬ!AK100 -> 0 | Z4: =ДЕКАБРЬ!AN100 -> 6117.8 | AB4: =O4-SUM(P4:Y4)+AA4 -> 47072.848 | AC4: =O4-SUM(P4:Z4)+AA4 -> 40955.048 | AD4: =SUM(AC4:AC5) -> 40954.76 | AE4: =P4/O4 -> 0.11595112 | AF4: =AC4/P4 -> 2.6872597 | AG4: =AC4/O4 -> 0.31159079 | AH4: =(W4+X4+Y4)/O4 -> 0
B5: Декабрь туники | C5: 29-31.12 | D5: 1 | F5: =IFERROR(O5-SUM(Q5:W5)+AA5,0) -> -0.28775523 | G5: =ДЕКАБРЬ!N108 -> 0 | H5: =ДЕКАБРЬ!S108 -> 0 | I5: =ДЕКАБРЬ!T108 -> 0 | J5: =ДЕКАБРЬ!V108 -> 0 | K5: =ДЕКАБРЬ!W108 -> 0 | L5: =IFERROR(J5+K5,0) -> 0 | M5: =ДЕКАБРЬ!Y108 -> 0 | N5: =ДЕКАБРЬ!Z108 -> 0 | O5: =IFERROR(M5+N5,0) -> 0 | P5: =ДЕКАБРЬ!AD108 -> 0 | Q5: =ДЕКАБРЬ!AG108 -> 0 | R5: =ДЕКАБРЬ!AE108 -> 0 | S5: =ДЕКАБРЬ!AL108 -> 0.28775523 | U5: =ДЕКАБРЬ!AM108 -> 0 | W5: =ДЕКАБРЬ!AH108 -> 0 | X5: =ДЕКАБРЬ!AI108 -> 0 | Y5: =ДЕКАБРЬ!AK108 -> 0 | Z5: =ДЕКАБРЬ!AN108 -> 0 | AB5: =O5-SUM(P5:Y5)+AA5 -> -0.28775523 | AC5: =O5-SUM(P5:Z5)+AA5 -> -0.28775523 | AE5: =P5/O5 -> #DIV/0! | AF5: =AC5/P5 -> #DIV/0! | AG5: =AC5/O5 -> #DIV/0! | AH5: =(W5+X5+Y5)/O5 -> #DIV/0!
B6: Январь очки | C6: 01.01-01.02 | D6: 1-5 | F6: =IFERROR(O6-SUM(Q6:W6)+AA6,0) -> 955718.86 | G6: =ЯНВАРЬ!N100 -> 4961 | H6: =ЯНВАРЬ!S100 -> 2362 | I6: =ЯНВАРЬ!T100 -> -53 | J6: =ЯНВАРЬ!V100 -> 1728382.8 | K6: =ЯНВАРЬ!W100 -> -44657.88 | L6: =IFERROR(J6+K6,0) -> 1683724.9 | M6: =ЯНВАРЬ!Y100 -> 2303342.1 | N6: =ЯНВАРЬ!Z100 -> -58267.04 | O6: =IFERROR(M6+N6,0) -> 2245075 | P6: =ЯНВАРЬ!AD100 -> 292876.64 | Q6: =ЯНВАРЬ!AG100 -> 276475.65 | R6: =ЯНВАРЬ!AE100 -> 833669.77 | S6: =ЯНВАРЬ!AL100 -> 40333.14 | U6: =ЯНВАРЬ!AM100 -> 0 | V6: 25431.6 | W6: =ЯНВАРЬ!AH100 -> 113446 | X6: =ЯНВАРЬ!AI100 -> 404487 | Y6: =ЯНВАРЬ!AK100 -> 0 | Z6: =ЯНВАРЬ!AN100 -> 96625.98 | AB6: =O6-SUM(P6:Y6)+AA6 -> 258355.22 | AC6: =O6-SUM(P6:Z6)+AA6 -> 161729.24 | AD6: =SUM(AC6:AC8) -> 161369.85 | AE6: =P6/O6 -> 0.13045294 | AF6: =AC6/P6 -> 0.55220942 | AG6: =AC6/O6 -> 0.072037343 | AH6: =(W6+X6+Y6)/O6 -> 0.23069741
B7: Январь туники | C7: 01.01-01.02 | D7: 1-5 | F7: =IFERROR(O7-SUM(Q7:W7)+AA7,0) -> -186.4297 | G7: =ЯНВАРЬ!N108 -> 1 | H7: =ЯНВАРЬ!S108 -> 0 | I7: =ЯНВАРЬ!T108 -> 0 | J7: =ЯНВАРЬ!V108 -> 0 | K7: =ЯНВАРЬ!W108 -> 0 | L7: =IFERROR(J7+K7,0) -> 0 | M7: =ЯНВАРЬ!Y108 -> 0 | N7: =ЯНВАРЬ!Z108 -> 0 | O7: =IFERROR(M7+N7,0) -> 0 | P7: =ЯНВАРЬ!AD108 -> 0 | Q7: =ЯНВАРЬ!AG108 -> 183.22 | R7: =ЯНВАРЬ!AE108 -> 0 | S7: =ЯНВАРЬ!AL108 -> 3.209704 | U7: =ЯНВАРЬ!AM108 -> 0 | W7: =ЯНВАРЬ!AH108 -> 0 | X7: =ЯНВАРЬ!AI108 -> 0 | Y7: =ЯНВАРЬ!AK108 -> 0 | Z7: =ЯНВАРЬ!AN108 -> 0 | AB7: =O7-SUM(P7:Y7)+AA7 -> -186.4297 | AC7: =O7-SUM(P7:Z7)+AA7 -> -186.4297 | AE7: =P7/O7 -> #DIV/0! | AF7: =AC7/P7 -> #DIV/0! | AG7: =AC7/O7 -> #DIV/0! | AH7: =(W7+X7+Y7)/O7 -> #DIV/0!
B8: Январь шапки | C8: 01.01-01.02 | D8: 1-5 | F8: =IFERROR(O8-SUM(Q8:W8)+AA8,0) -> -172.96 | G8: =ЯНВАРЬ!N119 -> 0 | H8: =ЯНВАРЬ!S119 -> 0 | I8: =ЯНВАРЬ!T119 -> 0 | J8: =ЯНВАРЬ!V119 -> 0 | K8: =ЯНВАРЬ!W119 -> 0 | L8: =IFERROR(J8+K8,0) -> 0 | M8: =ЯНВАРЬ!Y119 -> 0 | N8: =ЯНВАРЬ!Z119 -> 0 | O8: =IFERROR(M8+N8,0) -> 0 | P8: =ЯНВАРЬ!AD119 -> 0 | Q8: =ЯНВАРЬ!AG119 -> 172.96 | R8: =ЯНВАРЬ!AE119 -> 0 | S8: =ЯНВАРЬ!AL119 -> 0 | U8: =ЯНВАРЬ!AM119 -> 0 | W8: =ЯНВАРЬ!AH119 -> 0 | X8: =ЯНВАРЬ!AI119 -> 0 | Y8: =ЯНВАРЬ!AK119 -> 0 | Z8: =ЯНВАРЬ!AN119 -> 0 | AB8: =O8-SUM(P8:Y8)+AA8 -> -172.96 | AC8: =O8-SUM(P8:Z8)+AA8 -> -172.96 | AE8: =P8/O8 -> #DIV/0! | AF8: =AC8/P8 -> #DIV/0! | AG8: =AC8/O8 -> #DIV/0! | AH8: =(W8+X8+Y8)/O8 -> #DIV/0!
B9: Февраль 1 очки | C9: 02-08.02 | D9: 6 | F9: =IFERROR(O9-SUM(Q9:W9)+AA9,0) -> 539419.19 | G9: ='Юнит 6'!N105 -> 2829 | H9: ='Юнит 6'!S105 -> 1418 | I9: ='Юнит 6'!T105 -> -25 | J9: ='Юнит 6'!V105 -> 894889.93 | K9: ='Юнит 6'!W105 -> -16453.5 | L9: =IFERROR(J9+K9,0) -> 878436.43 | M9: ='Юнит 6'!Y105 -> 1357375 | N9: ='Юнит 6'!Z105 -> -24887.06 | O9: =IFERROR(M9+N9,0) -> 1332487.9 | P9: ='Юнит 6'!AD105 -> 175437.39 | Q9: ='Юнит 6'!AG105 -> 153486.12 | R9: ='Юнит 6'!AE105 -> 495216.11 | S9: ='Юнит 6'!AL105 -> 8160.06 | U9: ='Юнит 6'!AM105 -> 0 | V9: =5797.44+18990 -> 24787.44 | W9: ='Юнит 6'!AH105 -> 111419 | X9: ='Юнит 6'!AI105 -> 126688 | Y9: ='Юнит 6'!AK105 -> 0 | Z9: ='Юнит 6'!AN105 -> 50158.72 | AB9: =O9-SUM(P9:Y9)+AA9 -> 237293.8 | AC9: =O9-SUM(P9:Z9)+AA9 -> 187135.08 | AD9: =SUM(AC9:AC16) -> 1871390.2 | AE9: =P9/O9 -> 0.13166152 | AF9: =AC9/P9 -> 1.0666773 | AG9: =AC9/O9 -> 0.14044036 | AH9: =(W9+X9+Y9)/O9 -> 0.17869355
B10: Февраль 1 туники | C10: 02-08.02 | D10: 6 | F10: =IFERROR(O10-SUM(Q10:W10)+AA10,0) -> 0 | G10: ='Юнит 6'!N113 -> 1 | H10: ='Юнит 6'!S113 -> 0 | I10: ='Юнит 6'!T113 -> 0 | J10: ='Юнит 6'!V113 -> 0 | K10: ='Юнит 6'!W113 -> 0 | L10: =IFERROR(J10+K10,0) -> 0 | M10: ='Юнит 6'!Y113 -> 0 | N10: ='Юнит 6'!Z113 -> 0 | O10: =IFERROR(M10+N10,0) -> 0 | P10: ='Юнит 6'!AD113 -> 0 | Q10: ='Юнит 6'!AG113 -> 0 | R10: ='Юнит 6'!AE113 -> 0 | S10: ='Юнит 6'!AL113 -> 0 | U10: ='Юнит 6'!AM113 -> 0 | W10: ='Юнит 6'!AH113 -> 0 | X10: ='Юнит 6'!AI113 -> 0 | Y10: ='Юнит 6'!AK113 -> 0 | Z10: ='Юнит 6'!AN113 -> 0 | AB10: =O10-SUM(P10:Y10)+AA10 -> 0 | AC10: =O10-SUM(P10:Z10)+AA10 -> 0 | AE10: =P10/O10 -> #DIV/0! | AF10: =AC10/P10 -> #DIV/0! | AG10: =AC10/O10 -> #DIV/0! | AH10: =(W10+X10+Y10)/O10 -> #DIV/0!
B11: Февраль 2 очки | C11: 09-15.02 | D11: 7 | F11: =IFERROR(O11-SUM(Q11:W11)+AA11,0) -> 811496.75 | G11: ='Юнит 7'!N105 -> 3325 | H11: ='Юнит 7'!S105 -> 1882 | I11: ='Юнит 7'!T105 -> -40 | J11: ='Юнит 7'!V105 -> 1236743.8 | K11: ='Юнит 7'!W105 -> -26582.27 | L11: =IFERROR(J11+K11,0) -> 1210161.6 | M11: ='Юнит 7'!Y105 -> 1920260.7 | N11: ='Юнит 7'!Z105 -> -41194.47 | O11: =IFERROR(M11+N11,0) -> 1879066.2 | P11: ='Юнит 7'!AD105 -> 230374.86 | Q11: ='Юнит 7'!AG105 -> 212380.68 | R11: ='Юнит 7'!AE105 -> 695831.51 | S11: ='Юнит 7'!AL105 -> 8132.98 | T11: 30 | U11: ='Юнит 7'!AM105 -> 826 | V11: 4787.28 | W11: ='Юнит 7'!AH105 -> 145581 | X11: ='Юнит 7'!AI105 -> 138670 | Y11: ='Юнит 7'!AK105 -> 0 | Z11: ='Юнит 7'!AN105 -> 69100.226 | AB11: =O11-SUM(P11:Y11)+AA11 -> 442451.89 | AC11: =O11-SUM(P11:Z11)+AA11 -> 373351.66 | AE11: =P11/O11 -> 0.12260072 | AF11: =AC11/P11 -> 1.6206268 | AG11: =AC11/O11 -> 0.19869 | AH11: =(W11+X11+Y11)/O11 -> 0.15127248
B12: Февраль 2 туники | C12: 09-15.02 | D12: 7 | F12: =IFERROR(O12-SUM(Q12:W12)+AA12,0) -> 1191.57 | G12: ='Юнит 7'!N113 -> 0 | H12: ='Юнит 7'!S113 -> 1 | I12: ='Юнит 7'!T113 -> 0 | J12: ='Юнит 7'!V113 -> 1407 | K12: ='Юнит 7'!W113 -> 0 | L12: =IFERROR(J12+K12,0) -> 1407 | M12: ='Юнит 7'!Y113 -> 2079 | N12: ='Юнит 7'!Z113 -> 0 | O12: =IFERROR(M12+N12,0) -> 2079 | P12: ='Юнит 7'!AD113 -> 579.18 | Q12: ='Юнит 7'!AG113 -> 124.34 | R12: ='Юнит 7'!AE113 -> 763.09 | S12: ='Юнит 7'!AL113 -> 0 | U12: ='Юнит 7'!AM113 -> 0 | W12: ='Юнит 7'!AH113 -> 0 | X12: ='Юнит 7'!AI113 -> 0 | Y12: ='Юнит 7'!AK113 -> 0 | Z12: ='Юнит 7'!AN113 -> 80.3397 | AB12: =O12-SUM(P12:Y12)+AA12 -> 612.39 | AC12: =O12-SUM(P12:Z12)+AA12 -> 532.0503 | AE12: =P12/O12 -> 0.27858586 | AF12: =AC12/P12 -> 0.91862685 | AG12: =AC12/O12 -> 0.25591645 | AH12: =(W12+X12+Y12)/O12 -> 0
B13: Февраль 3 очки | C13: 16-22.02 | D13: 8 | F13: =IFERROR(O13-SUM(Q13:W13)+AA13,0) -> 1204943.2 | G13: ='Юнит 8'!N$105 -> 4413 | H13: ='Юнит 8'!S$105 -> 2295 | I13: ='Юнит 8'!T$105 -> -43 | J13: ='Юнит 8'!V$105 -> 1593380.1 | K13: ='Юнит 8'!W$105 -> -29254.63 | L13: =IFERROR(J13+K13,0) -> 1564125.5 | M13: ='Юнит 8'!Y$105 -> 2501418.9 | N13: ='Юнит 8'!Z$105 -> -47007.29 | O13: =IFERROR(M13+N13,0) -> 2454411.6 | P13: ='Юнит 8'!AD$105 -> 280478.83 | Q13: ='Юнит 8'!AG$105 -> 267875.33 | R13: ='Юнит 8'!AE$105 -> 918234.84 | S13: ='Юнит 8'!AL$105 -> 8623.9028 | U13: ='Юнит 8'!AM$105 -> 466 | V13: 3279.36 | W13: ='Юнит 8'!AH$105 -> 50989 | X13: ='Юнит 8'!AI$105 -> 265182 | Y13: ='Юнит 8'!AK$105 -> 0 | Z13: ='Юнит 8'!AN$105 -> 89311.563 | AB13: =O13-SUM(P13:Y13)+AA13 -> 659282.34 | AC13: =O13-SUM(P13:Z13)+AA13 -> 569970.77 | AE13: =P13/O13 -> 0.11427538 | AF13: =AC13/P13 -> 2.0321347 | AG13: =AC13/O13 -> 0.23222298 | AH13: =(W13+X13+Y13)/O13 -> 0.12881743
B14: Февраль 3 туники | C14: 16-22.02 | D14: 8 | F14: =IFERROR(O14-SUM(Q14:W14)+AA14,0) -> -0.86724686 | G14: ='Юнит 8'!N113 -> 0 | H14: ='Юнит 8'!S113 -> 0 | I14: ='Юнит 8'!T113 -> 0 | J14: ='Юнит 8'!V113 -> 0 | K14: ='Юнит 8'!W113 -> 0 | L14: =IFERROR(J14+K14,0) -> 0 | M14: ='Юнит 8'!Y113 -> 0 | N14: ='Юнит 8'!Z113 -> 0 | O14: =IFERROR(M14+N14,0) -> 0 | P14: ='Юнит 8'!AD113 -> 0 | Q14: ='Юнит 8'!AG113 -> 0 | R14: ='Юнит 8'!AE113 -> 0 | S14: ='Юнит 8'!AL113 -> 0.86724686 | U14: ='Юнит 8'!AM113 -> 0 | W14: ='Юнит 8'!AH113 -> 0 | X14: ='Юнит 8'!AI113 -> 0 | Y14: ='Юнит 8'!AK113 -> 0 | Z14: ='Юнит 8'!AN113 -> 0 | AB14: =O14-SUM(P14:Y14)+AA14 -> -0.86724686 | AC14: =O14-SUM(P14:Z14)+AA14 -> -0.86724686 | AE14: =P14/O14 -> #DIV/0! | AF14: =AC14/P14 -> #DIV/0! | AG14: =AC14/O14 -> #DIV/0! | AH14: =(W14+X14+Y14)/O14 -> #DIV/0!
B15: Февраль 4 очки | C15: 23.02-01.03 | D15: 9 | F15: =IFERROR(O15-SUM(Q15:W15)+AA15,0) -> 1208387.9 | G15: ='Юнит 9'!N$105 -> 3950 | H15: ='Юнит 9'!S$105 -> 2372 | I15: ='Юнит 9'!T$105 -> -63 | J15: ='Юнит 9'!V$105 -> 1818463.8 | K15: ='Юнит 9'!W$105 -> -46702.77 | L15: =IFERROR(J15+K15,0) -> 1771761 | M15: ='Юнит 9'!Y$105 -> 2879025.2 | N15: ='Юнит 9'!Z$105 -> -73544.64 | O15: =IFERROR(M15+N15,0) -> 2805480.6 | P15: ='Юнит 9'!AD$105 -> 288027.84 | Q15: ='Юнит 9'!AG$105 -> 299415.53 | R15: ='Юнит 9'!AE$105 -> 1051752.7 | S15: ='Юнит 9'!AL$105 -> 8471.4 | U15: ='Юнит 9'!AM$105 -> 1392.11 | V15: 2400.96 | W15: ='Юнит 9'!AH$105 -> 233660 | X15: ='Юнит 9'!AI$105 -> 78621 | Y15: ='Юнит 9'!AK$105 -> 0 | Z15: ='Юнит 9'!AN$105 -> 101167.55 | AB15: =O15-SUM(P15:Y15)+AA15 -> 841739.09 | AC15: =O15-SUM(P15:Z15)+AA15 -> 740571.54 | AE15: =P15/O15 -> 0.10266613 | AF15: =AC15/P15 -> 2.5711804 | AG15: =AC15/O15 -> 0.26397314 | AH15: =(W15+X15+Y15)/O15 -> 0.11131105
B16: Февраль 4 прочее | C16: 23.02-01.03 | D16: 9 | F16: =IFERROR(O16-SUM(Q16:W16)+AA16,0) -> -170 | Q16: ='Юнит 9'!AG125 -> 170 | AB16: =O16-SUM(P16:Y16)+AA16 -> -170 | AC16: =O16-SUM(P16:Z16)+AA16 -> -170 | AE16: =P16/O16 -> #DIV/0! | AF16: =AC16/P16 -> #DIV/0! | AG16: =AC16/O16 -> #DIV/0! | AH16: =(W16+X16+Y16)/O16 -> #DIV/0!
B17: Март 1 очки | C17: 02-08.02 | D17: 10 | F17: =IFERROR(O17-SUM(Q17:W17)+AA17,0) -> 1238601.7 | G17: ='Юнит 10'!N$105 -> 3795 | H17: ='Юнит 10'!S$105 -> 2096 | I17: ='Юнит 10'!T$105 -> -53 | J17: ='Юнит 10'!V$105 -> 1702514.8 | K17: ='Юнит 10'!W$105 -> -41251 | L17: =IFERROR(J17+K17,0) -> 1661263.8 | M17: ='Юнит 10'!Y$105 -> 2657773.4 | N17: ='Юнит 10'!Z$105 -> -65375.4 | O17: =IFERROR(M17+N17,0) -> 2592398 | P17: ='Юнит 10'!AD$105 -> 254974.68 | Q17: ='Юнит 10'!AG$105 -> 270558.84 | R17: ='Юнит 10'!AE$105 -> 972977.25 | S17: ='Юнит 10'!AL$105 -> 11702.83 | U17: ='Юнит 10'!AM$105 -> 0 | V17: =1083.36+22990 -> 24073.36 | W17: ='Юнит 10'!AH$105 -> 74484 | X17: ='Юнит 10'!AI$105 -> 252853 | Y17: ='Юнит 10'!AK$105 -> 0 | Z17: ='Юнит 10'!AN$105 -> 94858.164 | AB17: =O17-SUM(P17:Y17)+AA17 -> 730774.06 | AC17: =O17-SUM(P17:Z17)+AA17 -> 635915.9 | AE17: =P17/O17 -> 0.098354758 | AF17: =AC17/P17 -> 2.4940355 | AG17: =AC17/O17 -> 0.24530026 | AH17: =(W17+X17+Y17)/O17 -> 0.12626803
AC18: =O18-SUM(P18:Z18)+AA18 -> 0
AB20: =O20-SUM(P20:Y20)+AA20 -> 0 | AC20: =O20-SUM(P20:Z20)+AA20 -> 0 | AE20: =P20/O20 -> #DIV/0! | AF20: =AC20/P20 -> #DIV/0! | AG20: =AC20/O20 -> #DIV/0! | AH20: =(W20+X20+Y20)/O20 -> #DIV/0!
B21: Итого | F21: =SUM(F4:F20) -> 6021542 | G21: =SUM(G4:G20) -> 23404 | H21: =SUM(H4:H20) -> 12553 | I21: =SUM(I4:I20) -> -282 | J21: =SUM(J4:J20) -> 9093829.8 | K21: =SUM(K4:K20) -> -211311.05 | L21: =SUM(L4:L20) -> 8882518.7 | M21: =SUM(M4:M20) -> 13760239 | ... AD21: =SUM(AD4:AD20) -> 2073714.8 | AE21: =P21/O21 -> 0.11441302 | AF21: =AC21/P21 -> 1.7618001 | AG21: =AC21/O21 -> 0.20157288 | AH21: =(W21+X21+Y21)/O21 -> 0.14849093
M22: % от выручки за весь период
N23: =-N21/M21 -> 0.023095667 | P23: =P21/$O$21 -> 0.11441302 | Q23: =Q21/$O$21 -> 0.11145477 | R23: =R21/$O$21 -> 0.37318916 | S23: =S21/$O$21 -> 0.0066241419 | T23: =T21/$O$21 -> 2.3582034e-06 | U23: =U21/$O$21 -> 0.00019967436 | V23: =V21/$O$21 -> 0.0063054043 | W23: =W21/$O$21 -> 0.054274311 | ... Z23: =Z21/$O$21 -> 0.037747646 | AC23: =AC21/P21 -> 1.7618001 | AD23: Маржинальность, %
W24: =(W21+X21)/O21 -> 0.14849093 | AC24: =AC21/O21 -> 0.20157288 | AD24: Рентабельность, %
B25: ЯНВАРЬ очки | G25: =G6 -> 4961 | H25: =H6 -> 2362 | I25: =I6 -> -53 | J25: =J6 -> 1728382.8 | K25: =K6 -> -44657.88 | L25: =L6 -> 1683724.9 | M25: =M6 -> 2303342.1 | N25: =N6 -> -58267.04 | ... AC25: =AC6 -> 161729.24
N26: =-N25/M25 -> 0.025296738 | P26: =P25/$O$25 -> 0.13045294 | Q26: =Q25/$O$25 -> 0.12314762 | R26: =R25/$O$25 -> 0.3713327 | S26: =S25/$O$25 -> 0.017965164 | T26: =T25/$O$25 -> 0 | U26: =U25/$O$25 -> 0 | V26: =V25/$O$25 -> 0.011327728 | W26: =W25/$O$25 -> 0.050531051 | ... AA26: =AA25/$O$25 -> 0 | AC26: =AC25/O25 -> 0.072037343
B28: 7 нед очки | P28: =P11/$O$11 -> 0.12260072 | Q28: =Q11/$O$11 -> 0.11302459 | R28: =R11/$O$11 -> 0.37030708 | S28: =S11/$O$11 -> 0.004328203 | T28: =T11/$O$11 -> 1.5965377e-05 | U28: =U11/$O$11 -> 0.00043958004 | V28: =V11/$O$11 -> 0.002547691 | W28: =W11/$O$11 -> 0.077475184 | ... AB28: =AB11/$O$11 -> 0.23546371 | AC28: =AC11/P11 -> 1.6206268 | AD28: Маржинальность, %
AC29: =AC11/O11 -> 0.19869 | AD29: Рентабельность, %
B31: ФЕВРАЛЬ очки | G31: =G9+G11+G13+G15 -> 14517 | H31: =H9+H11+H13+H15 -> 7967 | I31: =I9+I11+I13+I15 -> -171 | J31: =J9+J11+J13+J15 -> 5543477.6 | K31: =K9+K11+K13+K15 -> -118993.17 | L31: =L9+L11+L13+L15 -> 5424484.4 | M31: =M9+M11+M13+M15 -> 8658079.8 | N31: =N9+N11+N13+N15 -> -186633.46 | ... AC31: =AC9+AC11+AC13+AC15 -> 1871029.1
N32: =-N31/M31 -> 0.021555988 | P32: =P31/$O$31 -> 0.11501211 | Q32: =Q31/$O$31 -> 0.11015329 | R32: =R31/$O$31 -> 0.37313996 | S32: =S31/$O$31 -> 0.0039412801 | T32: =T31/$O$31 -> 3.5413079e-06 | U32: =U31/$O$31 -> 0.000316842 | V32: =V31/$O$31 -> 0.0041616317 | W32: =W31/$O$31 -> 0.063938196 | ... AA32: =AA31/$O$31 -> 0 | AC32: =AC31/O31 -> 0.220863
B34: 9 нед очки | P34: =P15/$O$15 -> 0.10266613 | Q34: =Q15/$O$15 -> 0.10672522 | R34: =R15/$O$15 -> 0.37489216 | S34: =S15/$O$15 -> 0.0030195896 | T34: =T15/$O$15 -> 0 | U34: =U15/$O$15 -> 0.00049621088 | V34: =V15/$O$15 -> 0.00085581058 | W34: =W15/$O$15 -> 0.083286977 | ... AB34: =AB15/$O$15 -> 0.30003383 | AC34: =AC15/P15 -> 2.5711804 | AD34: Маржинальность, %

Sheet АВС 11
B2: ОЧКИ
C3: Прибыль | D3: % прибыль | E3: Доля | F3: ABC прибыль | G3: ABC кол-во | J3: Кол-во | K3: % кол-во | L3: Доля | M3: ABC кол-во
B4: черные с железкой классика | D4: =C4/C$105 -> #DIV/0! | E4: =D4 -> #DIV/0! | F4: =IF(AND(E4<=0),"C",IF(E4<=0.8,"A",IF(E4<=0.95,"B","C"))) -> #DIV/0! | G4: =VLOOKUP(B$4:B$104,I$4:M$104,5,0) -> #DIV/0! | I4: черные с железкой классика | K4: =J4/J$105 -> #DIV/0! | L4: =K4 -> #DIV/0! | M4: =_xlfn.IFS(L4<80%,"A",L4<=95%,"B",L4>95%,"C") -> #DIV/0! | P4: A | Q4: 0.8
B5: QS черные PZ | D5: =C5/C$105 -> #DIV/0! | E5: =E4+D5 -> #DIV/0! | F5: =IF(AND(E5<=0),"C",IF(E5<=0.8,"A",IF(E5<=0.95,"B","C"))) -> #DIV/0! | G5: =VLOOKUP(B$4:B$104,I$4:M$104,5,0) -> #DIV/0! | I5: QS черные PZ | K5: =J5/J$105 -> #DIV/0! | L5: =L4+K5 -> #DIV/0! | M5: =_xlfn.IFS(L5<80%,"A",L5<=95%,"B",L5>95%,"C") -> #DIV/0! | P5: B | Q5: 0.15
B6: QS синие PZ | D6: =C6/C$105 -> #DIV/0! | E6: =E5+D6 -> #DIV/0! | F6: =IF(AND(E6<=0),"C",IF(E6<=0.8,"A",IF(E6<=0.95,"B","C"))) -> #DIV/0! | G6: =VLOOKUP(B$4:B$104,I$4:M$104,5,0) -> #DIV/0! | I6: QS синие PZ | K6: =J6/J$105 -> #DIV/0! | L6: =L5+K6 -> #DIV/0! | M6: =_xlfn.IFS(L6<80%,"A",L6<=95%,"B",L6>95%,"C") -> #DIV/0! | P6: C | Q6: 0.05
B7: QS желтые PZ | D7: =C7/C$105 -> #DIV/0! | E7: =E6+D7 -> #DIV/0! | F7: =IF(AND(E7<=0),"C",IF(E7<=0.8,"A",IF(E7<=0.95,"B","C"))) -> #DIV/0! | G7: =VLOOKUP(B$4:B$104,I$4:M$104,5,0) -> #DIV/0! | I7: QS желтые PZ | K7: =J7/J$105 -> #DIV/0! | L7: =L6+K7 -> #DIV/0! | M7: =_xlfn.IFS(L7<80%,"A",L7<=95%,"B",L7>95%,"C") -> #DIV/0!
B8: QS коричневые PZ | D8: =C8/C$105 -> #DIV/0! | E8: =E7+D8 -> #DIV/0! | F8: =IF(AND(E8<=0),"C",IF(E8<=0.8,"A",IF(E8<=0.95,"B","C"))) -> #DIV/0! | G8: =VLOOKUP(B$4:B$104,I$4:M$104,5,0) -> #DIV/0! | I8: QS коричневые PZ | K8: =J8/J$105 -> #DIV/0! | L8: =L7+K8 -> #DIV/0! | M8: =_xlfn.IFS(L8<80%,"A",L8<=95%,"B",L8>95%,"C") -> #DIV/0!
B9: MR8854 C2 Жен | D9: =C9/C$105 -> #DIV/0! | E9: =E8+D9 -> #DIV/0! | F9: =IF(AND(E9<=0),"C",IF(E9<=0.8,"A",IF(E9<=0.95,"B","C"))) -> #DIV/0! | G9: =VLOOKUP(B$4:B$104,I$4:M$104,5,0) -> #DIV/0! | I9: MR8854 C2 Жен | K9: =J9/J$105 -> #DIV/0! | L9: =L8+K9 -> #DIV/0! | M9: =_xlfn.IFS(L9<80%,"A",L9<=95%,"B",L9>95%,"C") -> #DIV/0!
B10: th черн | D10: =C10/C$105 -> #DIV/0! | E10: =E9+D10 -> #DIV/0! | F10: =IF(AND(E10<=0),"C",IF(E10<=0.8,"A",IF(E10<=0.95,"B","C"))) -> #DIV/0! | G10: =VLOOKUP(B$4:B$104,I$4:M$104,5,0) -> #DIV/0! | I10: th черн | K10: =J10/J$105 -> #DIV/0! | L10: =L9+K10 -> #DIV/0! | M10: =_xlfn.IFS(L10<80%,"A",L10<=95%,"B",L10>95%,"C") -> #DIV/0!
B11: th син | D11: =C11/C$105 -> #DIV/0! | E11: =E10+D11 -> #DIV/0! | F11: =IF(AND(E11<=0),"C",IF(E11<=0.8,"A",IF(E11<=0.95,"B","C"))) -> #DIV/0! | G11: =VLOOKUP(B$4:B$104,I$4:M$104,5,0) -> #DIV/0! | I11: th син | K11: =J11/J$105 -> #DIV/0! | L11: =L10+K11 -> #DIV/0! | M11: =_xlfn.IFS(L11<80%,"A",L11<=95%,"B",L11>95%,"C") -> #DIV/0!
B12: th желт | D12: =C12/C$105 -> #DIV/0! | E12: =E11+D12 -> #DIV/0! | F12: =IF(AND(E12<=0),"C",IF(E12<=0.8,"A",IF(E12<=0.95,"B","C"))) -> #DIV/0! | G12: =VLOOKUP(B$4:B$104,I$4:M$104,5,0) -> #DIV/0! | I12: th желт | K12: =J12/J$105 -> #DIV/0! | L12: =L11+K12 -> #DIV/0! | M12: =_xlfn.IFS(L12<80%,"A",L12<=95%,"B",L12>95%,"C") -> #DIV/0!
B13: th коричн | D13: =C13/C$105 -> #DIV/0! | E13: =E12+D13 -> #DIV/0! | F13: =IF(AND(E13<=0),"C",IF(E13<=0.8,"A",IF(E13<=0.95,"B","C"))) -> #DIV/0! | G13: =VLOOKUP(B$4:B$104,I$4:M$104,5,0) -> #DIV/0! | I13: th коричн | K13: =J13/J$105 -> #DIV/0! | L13: =L12+K13 -> #DIV/0! | M13: =_xlfn.IFS(L13<80%,"A",L13<=95%,"B",L13>95%,"C") -> #DIV/0!
B14: flip черные | D14: =C14/C$105 -> #DIV/0! | E14: =E13+D14 -> #DIV/0! | F14: =IF(AND(E14<=0),"C",IF(E14<=0.8,"A",IF(E14<=0.95,"B","C"))) -> #DIV/0! | G14: =VLOOKUP(B$4:B$104,I$4:M$104,5,0) -> #DIV/0! | I14: flip черные | K14: =J14/J$105 -> #DIV/0! | L14: =L13+K14 -> #DIV/0! | M14: =_xlfn.IFS(L14<80%,"A",L14<=95%,"B",L14>95%,"C") -> #DIV/0!
B15: flip синие | D15: =C15/C$105 -> #DIV/0! | E15: =E14+D15 -> #DIV/0! | F15: =IF(AND(E15<=0),"C",IF(E15<=0.8,"A",IF(E15<=0.95,"B","C"))) -> #DIV/0! | G15: =VLOOKUP(B$4:B$104,I$4:M$104,5,0) -> #DIV/0! | I15: flip синие | K15: =J15/J$105 -> #DIV/0! | L15: =L14+K15 -> #DIV/0! | M15: =_xlfn.IFS(L15<80%,"A",L15<=95%,"B",L15>95%,"C") -> #DIV/0!
B16: flip желтые | D16: =C16/C$105 -> #DIV/0! | E16: =E15+D16 -> #DIV/0! | F16: =IF(AND(E16<=0),"C",IF(E16<=0.8,"A",IF(E16<=0.95,"B","C"))) -> #DIV/0! | G16: =VLOOKUP(B$4:B$104,I$4:M$104,5,0) -> #DIV/0! | I16: flip желтые | K16: =J16/J$105 -> #DIV/0! | L16: =L15+K16 -> #DIV/0! | M16: =_xlfn.IFS(L16<80%,"A",L16<=95%,"B",L16>95%,"C") -> #DIV/0!
B17: flip коричневые | D17: =C17/C$105 -> #DIV/0! | E17: =E16+D17 -> #DIV/0! | F17: =IF(AND(E17<=0),"C",IF(E17<=0.8,"A",IF(E17<=0.95,"B","C"))) -> #DIV/0! | G17: =VLOOKUP(B$4:B$104,I$4:M$104,5,0) -> #DIV/0! | I17: flip коричневые | K17: =J17/J$105 -> #DIV/0! | L17: =L16+K17 -> #DIV/0! | M17: =_xlfn.IFS(L17<80%,"A",L17<=95%,"B",L17>95%,"C") -> #DIV/0!
B18: wwl8032 коричневые золото | D18: =C18/C$105 -> #DIV/0! | E18: =E17+D18 -> #DIV/0! | F18: =IF(AND(E18<=0),"C",IF(E18<=0.8,"A",IF(E18<=0.95,"B","C"))) -> #DIV/0! | G18: =VLOOKUP(B$4:B$104,I$4:M$104,5,0) -> #DIV/0! | I18: wwl8032 коричневые золото | K18: =J18/J$105 -> #DIV/0! | L18: =L17+K18 -> #DIV/0! | M18: =_xlfn.IFS(L18<80%,"A",L18<=95%,"B",L18>95%,"C") -> #DIV/0!
... B38: sh13 | D38: =C38/C$105 -> #DIV/0! | E38: =E37+D38 -> #DIV/0! | F38: =IF(AND(E38<=0),"C",IF(E38<=0.8,"A",IF(E38<=0.95,"B","C"))) -> #DIV/0! | G38: =VLOOKUP(B$4:B$104,I$4:M$104,5,0) -> #DIV/0! | I38: sh13 | K38: =J38/J$105 -> #DIV/0! | L38: =L37+K38 -> #DIV/0! | M38: =_xlfn.IFS(L38<80%,"A",L38<=95%,"B",L38>95%,"C") -> #DIV/0!
B39: sh14 | D39: =C39/C$105 -> #DIV/0! | E39: =E35+D39 -> #DIV/0! | F39: =IF(AND(E39<=0),"C",IF(E39<=0.8,"A",IF(E39<=0.95,"B","C"))) -> #DIV/0! | G39: =VLOOKUP(B$4:B$104,I$4:M$104,5,0) -> #DIV/0! | I39: sh14 | K39: =J39/J$105 -> #DIV/0! | L39: =L35+K39 -> #DIV/0! | M39: =_xlfn.IFS(L39<80%,"A",L39<=95%,"B",L39>95%,"C") -> #DIV/0!
B40: sh15 | D40: =C40/C$105 -> #DIV/0! | E40: =E39+D40 -> #DIV/0! | F40: =IF(AND(E40<=0),"C",IF(E40<=0.8,"A",IF(E40<=0.95,"B","C"))) -> #DIV/0! | G40: =VLOOKUP(B$4:B$104,I$4:M$104,5,0) -> #DIV/0! | I40: sh15 | K40: =J40/J$105 -> #DIV/0! | L40: =L39+K40 -> #DIV/0! | M40: =_xlfn.IFS(L40<80%,"A",L40<=95%,"B",L40>95%,"C") -> #DIV/0!
B41: sh16 | D41: =C41/C$105 -> #DIV/0! | E41: =E40+D41 -> #DIV/0! | F41: =IF(AND(E41<=0),"C",IF(E41<=0.8,"A",IF(E41<=0.95,"B","C"))) -> #DIV/0! | G41: =VLOOKUP(B$4:B$104,I$4:M$104,5,0) -> #DIV/0! | I41: sh16 | K41: =J41/J$105 -> #DIV/0! | L41: =L40+K41 -> #DIV/0! | M41: =_xlfn.IFS(L41<80%,"A",L41<=95%,"B",L41>95%,"C") -> #DIV/0!
B42: sh17 | D42: =C42/C$105 -> #DIV/0! | E42: =E41+D42 -> #DIV/0! | F42: =IF(AND(E42<=0),"C",IF(E42<=0.8,"A",IF(E42<=0.95,"B","C"))) -> #DIV/0! | G42: =VLOOKUP(B$4:B$104,I$4:M$104,5,0) -> #DIV/0! | I42: sh17 | K42: =J42/J$105 -> #DIV/0! | L42: =L41+K42 -> #DIV/0! | M42: =_xlfn.IFS(L42<80%,"A",L42<=95%,"B",L42>95%,"C") -> #DIV/0!
B43: sh18 | D43: =C43/C$105 -> #DIV/0! | E43: =E42+D43 -> #DIV/0! | F43: =IF(AND(E43<=0),"C",IF(E43<=0.8,"A",IF(E43<=0.95,"B","C"))) -> #DIV/0! | G43: =VLOOKUP(B$4:B$104,I$4:M$104,5,0) -> #DIV/0! | I43: sh18 | K43: =J43/J$105 -> #DIV/0! | L43: =L42+K43 -> #DIV/0! | M43: =_xlfn.IFS(L43<80%,"A",L43<=95%,"B",L43>95%,"C") -> #DIV/0!
B44: sh19 | D44: =C44/C$105 -> #DIV/0! | E44: =E43+D44 -> #DIV/0! | F44: =IF(AND(E44<=0),"C",IF(E44<=0.8,"A",IF(E44<=0.95,"B","C"))) -> #DIV/0! | G44: =VLOOKUP(B$4:B$104,I$4:M$104,5,0) -> #DIV/0! | I44: sh19 | K44: =J44/J$105 -> #DIV/0! | L44: =L43+K44 -> #DIV/0! | M44: =_xlfn.IFS(L44<80%,"A",L44<=95%,"B",L44>95%,"C") -> #DIV/0!
B45: ww 203 черные | D45: =C45/C$105 -> #DIV/0! | E45: =E44+D45 -> #DIV/0! | F45: =IF(AND(E45<=0),"C",IF(E45<=0.8,"A",IF(E45<=0.95,"B","C"))) -> #DIV/0! | G45: =VLOOKUP(B$4:B$104,I$4:M$104,5,0) -> #DIV/0! | I45: ww 203 черные | K45: =J45/J$105 -> #DIV/0! | L45: =L44+K45 -> #DIV/0! | M45: =_xlfn.IFS(L45<80%,"A",L45<=95%,"B",L45>95%,"C") -> #DIV/0!
B46: ww 1022 черные | D46: =C46/C$105 -> #DIV/0! | E46: =E45+D46 -> #DIV/0! | F46: =IF(AND(E46<=0),"C",IF(E46<=0.8,"A",IF(E46<=0.95,"B","C"))) -> #DIV/0! | G46: =VLOOKUP(B$4:B$104,I$4:M$104,5,0) -> #DIV/0! | I46: ww 1022 черные | K46: =J46/J$105 -> #DIV/0! | L46: =L45+K46 -> #DIV/0! | M46: =_xlfn.IFS(L46<80%,"A",L46<=95%,"B",L46>95%,"C") -> #DIV/0!
B47: ww 1022 черн-серебро | D47: =C47/C$105 -> #DIV/0! | E47: =E46+D47 -> #DIV/0! | F47: =IF(AND(E47<=0),"C",IF(E47<=0.8,"A",IF(E47<=0.95,"B","C"))) -> #DIV/0! | G47: =VLOOKUP(B$4:B$104,I$4:M$104,5,0) -> #DIV/0! | I47: ww 1022 черн-серебро | K47: =J47/J$105 -> #DIV/0! | L47: =L46+K47 -> #DIV/0! | M47: =_xlfn.IFS(L47<80%,"A",L47<=95%,"B",L47>95%,"C") -> #DIV/0!
B48: ww 1022 желтые | D48: =C48/C$105 -> #DIV/0! | E48: =E47+D48 -> #DIV/0! | F48: =IF(AND(E48<=0),"C",IF(E48<=0.8,"A",IF(E48<=0.95,"B","C"))) -> #DIV/0! | G48: =VLOOKUP(B$4:B$104,I$4:M$104,5,0) -> #DIV/0! | I48: ww 1022 желтые | K48: =J48/J$105 -> #DIV/0! | L48: =L47+K48 -> #DIV/0! | M48: =_xlfn.IFS(L48<80%,"A",L48<=95%,"B",L48>95%,"C") -> #DIV/0!
B49: ww 1022 коричневые | D49: =C49/C$105 -> #DIV/0! | E49: =E48+D49 -> #DIV/0! | F49: =IF(AND(E49<=0),"C",IF(E49<=0.8,"A",IF(E49<=0.95,"B","C"))) -> #DIV/0! | G49: =VLOOKUP(B$4:B$104,I$4:M$104,5,0) -> #DIV/0! | I49: ww 1022 коричневые | K49: =J49/J$105 -> #DIV/0! | L49: =L48+K49 -> #DIV/0! | M49: =_xlfn.IFS(L49<80%,"A",L49<=95%,"B",L49>95%,"C") -> #DIV/0!
B50: ww 2018 черные | D50: =C50/C$105 -> #DIV/0! | E50: =E49+D50 -> #DIV/0! | F50: =IF(AND(E50<=0),"C",IF(E50<=0.8,"A",IF(E50<=0.95,"B","C"))) -> #DIV/0! | G50: =VLOOKUP(B$4:B$104,I$4:M$104,5,0) -> #DIV/0! | I50: ww 2018 черные | K50: =J50/J$105 -> #DIV/0! | L50: =L49+K50 -> #DIV/0! | M50: =_xlfn.IFS(L50<80%,"A",L50<=95%,"B",L50>95%,"C") -> #DIV/0!
B51: ww 2018 желтые | D51: =C51/C$105 -> #DIV/0! | E51: =E50+D51 -> #DIV/0! | F51: =IF(AND(E51<=0),"C",IF(E51<=0.8,"A",IF(E51<=0.95,"B","C"))) -> #DIV/0! | G51: =VLOOKUP(B$4:B$104,I$4:M$104,5,0) -> #DIV/0! | I51: ww 2018 желтые | K51: =J51/J$105 -> #DIV/0! | L51: =L50+K51 -> #DIV/0! | M51: =_xlfn.IFS(L51<80%,"A",L51<=95%,"B",L51>95%,"C") -> #DIV/0!
... B75: MANNA2121 | D75: =C75/C$105 -> #DIV/0! | E75: =E74+D75 -> #DIV/0! | F75: =IF(AND(E75<=0),"C",IF(E75<=0.8,"A",IF(E75<=0.95,"B","C"))) -> #DIV/0! | G75: =VLOOKUP(B$4:B$104,I$4:M$104,5,0) -> #DIV/0! | I75: MANNA2121 | K75: =J75/J$105 -> #DIV/0! | L75: =L74+K75 -> #DIV/0! | M75: =_xlfn.IFS(L75<80%,"A",L75<=95%,"B",L75>95%,"C") -> #DIV/0!
B76: MANNA2122 | D76: =C76/C$105 -> #DIV/0! | E76: =E49+D76 -> #DIV/0! | F76: =IF(AND(E76<=0),"C",IF(E76<=0.8,"A",IF(E76<=0.95,"B","C"))) -> #DIV/0! | G76: =VLOOKUP(B$4:B$104,I$4:M$104,5,0) -> #DIV/0! | I76: MANNA2122 | K76: =J76/J$105 -> #DIV/0! | L76: =L49+K76 -> #DIV/0! | M76: =_xlfn.IFS(L76<80%,"A",L76<=95%,"B",L76>95%,"C") -> #DIV/0!
B77: Chenlong черные | D77: =C77/C$105 -> #DIV/0! | E77: =E76+D77 -> #DIV/0! | F77: =IF(AND(E77<=0),"C",IF(E77<=0.8,"A",IF(E77<=0.95,"B","C"))) -> #DIV/0! | G77: =VLOOKUP(B$4:B$104,I$4:M$104,5,0) -> #DIV/0! | I77: Chenlong черные | K77: =J77/J$105 -> #DIV/0! | L77: =L76+K77 -> #DIV/0! | M77: =_xlfn.IFS(L77<80%,"A",L77<=95%,"B",L77>95%,"C") -> #DIV/0!
B78: Chenlong коричневые | D78: =C78/C$105 -> #DIV/0! | E78: =E77+D78 -> #DIV/0! | F78: =IF(AND(E78<=0),"C",IF(E78<=0.8,"A",IF(E78<=0.95,"B","C"))) -> #DIV/0! | G78: =VLOOKUP(B$4:B$104,I$4:M$104,5,0) -> #DIV/0! | I78: Chenlong коричневые | K78: =J78/J$105 -> #DIV/0! | L78: =L77+K78 -> #DIV/0! | M78: =_xlfn.IFS(L78<80%,"A",L78<=95%,"B",L78>95%,"C") -> #DIV/0!
B79: Chenlong белые | D79: =C79/C$105 -> #DIV/0! | E79: =E78+D79 -> #DIV/0! | F79: =IF(AND(E79<=0),"C",IF(E79<=0.8,"A",IF(E79<=0.95,"B","C"))) -> #DIV/0! | G79: =VLOOKUP(B$4:B$104,I$4:M$104,5,0) -> #DIV/0! | I79: Chenlong белые | K79: =J79/J$105 -> #DIV/0! | L79: =L78+K79 -> #DIV/0! | M79: =_xlfn.IFS(L79<80%,"A",L79<=95%,"B",L79>95%,"C") -> #DIV/0!
B80: Guangdu золото серая линза | D80: =C80/C$105 -> #DIV/0! | E80: =E79+D80 -> #DIV/0! | F80: =IF(AND(E80<=0),"C",IF(E80<=0.8,"A",IF(E80<=0.95,"B","C"))) -> #DIV/0! | G80: =VLOOKUP(B$4:B$104,I$4:M$104,5,0) -> #DIV/0! | I80: Guangdu золото серая линза | K80: =J80/J$105 -> #DIV/0! | L80: =L79+K80 -> #DIV/0! | M80: =_xlfn.IFS(L80<80%,"A",L80<=95%,"B",L80>95%,"C") -> #DIV/0!
B81: Guangdu серебро серая линза | D81: =C81/C$105 -> #DIV/0! | E81: =E80+D81 -> #DIV/0! | F81: =IF(AND(E81<=0),"C",IF(E81<=0.8,"A",IF(E81<=0.95,"B","C"))) -> #DIV/0! | G81: =VLOOKUP(B$4:B$104,I$4:M$104,5,0) -> #DIV/0! | I81: Guangdu серебро серая линза | K81: =J81/J$105 -> #DIV/0! | L81: =L80+K81 -> #DIV/0! | M81: =_xlfn.IFS(L81<80%,"A",L81<=95%,"B",L81>95%,"C") -> #DIV/0!
B82: Hengda Optical черные | D82: =C82/C$105 -> #DIV/0! | E82: =E81+D82 -> #DIV/0! | F82: =IF(AND(E82<=0),"C",IF(E82<=0.8,"A",IF(E82<=0.95,"B","C"))) -> #DIV/0! | G82: =VLOOKUP(B$4:B$104,I$4:M$104,5,0) -> #DIV/0! | I82: Hengda Optical черные | K82: =J82/J$105 -> #DIV/0! | L82: =L81+K82 -> #DIV/0! | M82: =_xlfn.IFS(L82<80%,"A",L82<=95%,"B",L82>95%,"C") -> #DIV/0!
B83: Hengda Optical леопард | D83: =C83/C$105 -> #DIV/0! | E83: =E82+D83 -> #DIV/0! | F83: =IF(AND(E83<=0),"C",IF(E83<=0.8,"A",IF(E83<=0.95,"B","C"))) -> #DIV/0! | G83: =VLOOKUP(B$4:B$104,I$4:M$104,5,0) -> #DIV/0! | I83: Hengda Optical леопард | K83: =J83/J$105 -> #DIV/0! | L83: =L82+K83 -> #DIV/0! | M83: =_xlfn.IFS(L83<80%,"A",L83<=95%,"B",L83>95%,"C") -> #DIV/0!
B84: Qianai черные | D84: =C84/C$105 -> #DIV/0! | E84: =E83+D84 -> #DIV/0! | F84: =IF(AND(E84<=0),"C",IF(E84<=0.8,"A",IF(E84<=0.95,"B","C"))) -> #DIV/0! | G84: =VLOOKUP(B$4:B$104,I$4:M$104,5,0) -> #DIV/0! | I84: Qianai черные | K84: =J84/J$105 -> #DIV/0! | L84: =L83+K84 -> #DIV/0! | M84: =_xlfn.IFS(L84<80%,"A",L84<=95%,"B",L84>95%,"C") -> #DIV/0!
B85: Qianai коричневые | D85: =C85/C$105 -> #DIV/0! | E85: =E84+D85 -> #DIV/0! | F85: =IF(AND(E85<=0),"C",IF(E85<=0.8,"A",IF(E85<=0.95,"B","C"))) -> #DIV/0! | G85: =VLOOKUP(B$4:B$104,I$4:M$104,5,0) -> #DIV/0! | I85: Qianai коричневые | K85: =J85/J$105 -> #DIV/0! | L85: =L84+K85 -> #DIV/0! | M85: =_xlfn.IFS(L85<80%,"A",L85<=95%,"B",L85>95%,"C") -> #DIV/0!
B86: Keming Aishi коричневые | D86: =C86/C$105 -> #DIV/0! | E86: =E85+D86 -> #DIV/0! | F86: =IF(AND(E86<=0),"C",IF(E86<=0.8,"A",IF(E86<=0.95,"B","C"))) -> #DIV/0! | G86: =VLOOKUP(B$4:B$104,I$4:M$104,5,0) -> #DIV/0! | I86: Keming Aishi коричневые | K86: =J86/J$105 -> #DIV/0! | L86: =L85+K86 -> #DIV/0! | M86: =_xlfn.IFS(L86<80%,"A",L86<=95%,"B",L86>95%,"C") -> #DIV/0!
B87: Linhai Baiyi коричневая линза | D87: =C87/C$105 -> #DIV/0! | E87: =E86+D87 -> #DIV/0! | F87: =IF(AND(E87<=0),"C",IF(E87<=0.8,"A",IF(E87<=0.95,"B","C"))) -> #DIV/0! | G87: =VLOOKUP(B$4:B$104,I$4:M$104,5,0) -> #DIV/0! | I87: Linhai Baiyi коричневая линза | K87: =J87/J$105 -> #DIV/0! | L87: =L86+K87 -> #DIV/0! | M87: =_xlfn.IFS(L87<80%,"A",L87<=95%,"B",L87>95%,"C") -> #DIV/0!
B88: Linhai Baiyi серая линза | D88: =C88/C$105 -> #DIV/0! | E88: =E87+D88 -> #DIV/0! | F88: =IF(AND(E88<=0),"C",IF(E88<=0.8,"A",IF(E88<=0.95,"B","C"))) -> #DIV/0! | G88: =VLOOKUP(B$4:B$104,I$4:M$104,5,0) -> #DIV/0! | I88: Linhai Baiyi серая линза | K88: =J88/J$105 -> #DIV/0! | L88: =L87+K88 -> #DIV/0! | M88: =_xlfn.IFS(L88<80%,"A",L88<=95%,"B",L88>95%,"C") -> #DIV/0!
... B98: POMILED 08247 C4-08 | D98: =C98/C$105 -> #DIV/0! | E98: =E97+D98 -> #DIV/0! | F98: =IF(AND(E98<=0),"C",IF(E98<=0.8,"A",IF(E98<=0.95,"B","C"))) -> #DIV/0! | G98: =VLOOKUP(B$4:B$104,I$4:M$104,5,0) -> #DIV/0! | I98: POMILED 08247 C4-08 | K98: =J98/J$105 -> #DIV/0! | L98: =L97+K98 -> #DIV/0! | M98: =_xlfn.IFS(L98<80%,"A",L98<=95%,"B",L98>95%,"C") -> #DIV/0!
B99: YIMEI 2391 C1 | D99: =C99/C$105 -> #DIV/0! | E99: =E93+D99 -> #DIV/0! | F99: =IF(AND(E99<=0),"C",IF(E99<=0.8,"A",IF(E99<=0.95,"B","C"))) -> #DIV/0! | G99: =VLOOKUP(B$4:B$104,I$4:M$104,5,0) -> #DIV/0! | I99: YIMEI 2391 C1 | K99: =J99/J$105 -> #DIV/0! | L99: =L93+K99 -> #DIV/0! | M99: =_xlfn.IFS(L99<80%,"A",L99<=95%,"B",L99>95%,"C") -> #DIV/0!
B100: ЧСЖ_тест | D100: =C100/C$105 -> #DIV/0! | E100: =E94+D100 -> #DIV/0! | F100: =IF(AND(E100<=0),"C",IF(E100<=0.8,"A",IF(E100<=0.95,"B","C"))) -> #DIV/0! | G100: =VLOOKUP(B$4:B$104,I$4:M$104,5,0) -> #DIV/0! | I100: ЧСЖ_тест | K100: =J100/J$105 -> #DIV/0! | L100: =L94+K100 -> #DIV/0! | M100: =_xlfn.IFS(L100<80%,"A",L100<=95%,"B",L100>95%,"C") -> #DIV/0!
B101: ЧСЖ_женские | D101: =C101/C$105 -> #DIV/0! | E101: =E95+D101 -> #DIV/0! | F101: =IF(AND(E101<=0),"C",IF(E101<=0.8,"A",IF(E101<=0.95,"B","C"))) -> #DIV/0! | G101: =VLOOKUP(B$4:B$104,I$4:M$104,5,0) -> #DIV/0! | I101: ЧСЖ_женские | K101: =J101/J$105 -> #DIV/0! | L101: =L95+K101 -> #DIV/0! | M101: =_xlfn.IFS(L101<80%,"A",L101<=95%,"B",L101>95%,"C") -> #DIV/0!
B102: кс_черные_тест | D102: =C102/C$105 -> #DIV/0! | E102: =E96+D102 -> #DIV/0! | F102: =IF(AND(E102<=0),"C",IF(E102<=0.8,"A",IF(E102<=0.95,"B","C"))) -> #DIV/0! | G102: =VLOOKUP(B$4:B$104,I$4:M$104,5,0) -> #DIV/0! | I102: кс_черные_тест | K102: =J102/J$105 -> #DIV/0! | L102: =L96+K102 -> #DIV/0! | M102: =_xlfn.IFS(L102<80%,"A",L102<=95%,"B",L102>95%,"C") -> #DIV/0!
B103: кс_черные_женские | D103: =C103/C$105 -> #DIV/0! | E103: =E97+D103 -> #DIV/0! | F103: =IF(AND(E103<=0),"C",IF(E103<=0.8,"A",IF(E103<=0.95,"B","C"))) -> #DIV/0! | G103: =VLOOKUP(B$4:B$104,I$4:M$104,5,0) -> #DIV/0! | I103: кс_черные_женские | K103: =J103/J$105 -> #DIV/0! | L103: =L97+K103 -> #DIV/0! | M103: =_xlfn.IFS(L103<80%,"A",L103<=95%,"B",L103>95%,"C") -> #DIV/0!
B104: 1022_коричневые_тест | D104: =C104/C$105 -> #DIV/0! | E104: =E98+D104 -> #DIV/0! | F104: =IF(AND(E104<=0),"C",IF(E104<=0.8,"A",IF(E104<=0.95,"B","C"))) -> #DIV/0! | G104: =VLOOKUP(B$4:B$104,I$4:M$104,5,0) -> #DIV/0! | I104: 1022_коричневые_тест | K104: =J104/J$105 -> #DIV/0! | L104: =L98+K104 -> #DIV/0! | M104: =_xlfn.IFS(L104<80%,"A",L104<=95%,"B",L104>95%,"C") -> #DIV/0!
C105: =SUM(C4:C104) -> 0 | D105: =SUM(D4:D104) -> #DIV/0! | J105: =SUM(J4:J104) -> 0 | K105: =SUM(K4:K104) -> #DIV/0!

Sheet АВС 10
B2: ОЧКИ
C3: Прибыль | D3: % прибыль | E3: Доля | F3: ABC прибыль | G3: ABC кол-во | J3: Кол-во | K3: % кол-во | L3: Доля | M3: ABC кол-во
B4: QS черные PZ | C4: ='Юнит 10'!AO4 -> 180713.27 | D4: =C4/C$105 -> 0.27381245 | E4: =D4 -> 0.27381245 | F4: =IF(AND(E4<=0),"C",IF(E4<=0.8,"A",IF(E4<=0.95,"B","C"))) -> A | G4: =VLOOKUP(B$4:B$104,I$4:M$104,5,0) -> A | I4: QS черные PZ | J4: ='Юнит 10'!U4 -> 427 | K4: =J4/J$105 -> 0.20900636 | L4: =K4 -> 0.20900636 | M4: =_xlfn.IFS(L4<80%,"A",L4<=95%,"B",L4>95%,"C") -> A | P4: A | Q4: 0.8
B5: QS синие PZ | C5: ='Юнит 10'!AO5 -> 59221.135 | D5: =C5/C$105 -> 0.089730454 | E5: =E4+D5 -> 0.3635429 | F5: =IF(AND(E5<=0),"C",IF(E5<=0.8,"A",IF(E5<=0.95,"B","C"))) -> A | G5: =VLOOKUP(B$4:B$104,I$4:M$104,5,0) -> A | I5: QS синие PZ | J5: ='Юнит 10'!U5 -> 143 | K5: =J5/J$105 -> 0.069995105 | L5: =L4+K5 -> 0.27900147 | M5: =_xlfn.IFS(L5<80%,"A",L5<=95%,"B",L5>95%,"C") -> A | P5: B | Q5: 0.15
B6: QS коричневые PZ | C6: ='Юнит 10'!AO7 -> 56821.8 | D6: =C6/C$105 -> 0.086095038 | E6: =E5+D6 -> 0.44963794 | F6: =IF(AND(E6<=0),"C",IF(E6<=0.8,"A",IF(E6<=0.95,"B","C"))) -> A | G6: =VLOOKUP(B$4:B$104,I$4:M$104,5,0) -> A | I6: QS коричневые PZ | J6: ='Юнит 10'!U7 -> 139 | K6: =J6/J$105 -> 0.0680372 | L6: =L5+K6 -> 0.34703867 | M6: =_xlfn.IFS(L6<80%,"A",L6<=95%,"B",L6>95%,"C") -> A | P6: C | Q6: 0.05
B7: flip черные | C7: ='Юнит 10'!AO13 -> 48751.577 | D7: =C7/C$105 -> 0.073867228 | E7: =E6+D7 -> 0.52350516 | F7: =IF(AND(E7<=0),"C",IF(E7<=0.8,"A",IF(E7<=0.95,"B","C"))) -> A | G7: =VLOOKUP(B$4:B$104,I$4:M$104,5,0) -> A | I7: flip черные | J7: ='Юнит 10'!U13 -> 132 | K7: =J7/J$105 -> 0.064610866 | L7: =L6+K7 -> 0.41164953 | M7: =_xlfn.IFS(L7<80%,"A",L7<=95%,"B",L7>95%,"C") -> A
B8: th черн | C8: ='Юнит 10'!AO9 -> 38157.585 | D8: =C8/C$105 -> 0.057815464 | E8: =E7+D8 -> 0.58132063 | F8: =IF(AND(E8<=0),"C",IF(E8<=0.8,"A",IF(E8<=0.95,"B","C"))) -> A | G8: =VLOOKUP(B$4:B$104,I$4:M$104,5,0) -> A | I8: sh3 | J8: ='Юнит 10'!U28 -> 112 | K8: =J8/J$105 -> 0.054821341 | L8: =L7+K8 -> 0.46647088 | M8: =_xlfn.IFS(L8<80%,"A",L8<=95%,"B",L8>95%,"C") -> A
B9: flip коричневые | C9: ='Юнит 10'!AO16 -> 36602.996 | D9: =C9/C$105 -> 0.055459987 | E9: =E8+D9 -> 0.63678062 | F9: =IF(AND(E9<=0),"C",IF(E9<=0.8,"A",IF(E9<=0.95,"B","C"))) -> A | G9: =VLOOKUP(B$4:B$104,I$4:M$104,5,0) -> A | I9: th син | J9: ='Юнит 10'!U10 -> 111 | K9: =J9/J$105 -> 0.054331865 | L9: =L8+K9 -> 0.52080274 | M9: =_xlfn.IFS(L9<80%,"A",L9<=95%,"B",L9>95%,"C") -> A
B10: QS желтые PZ | C10: ='Юнит 10'!AO6 -> 35164.892 | D10: =C10/C$105 -> 0.053281007 | E10: =E9+D10 -> 0.69006162 | F10: =IF(AND(E10<=0),"C",IF(E10<=0.8,"A",IF(E10<=0.95,"B","C"))) -> A | G10: =VLOOKUP(B$4:B$104,I$4:M$104,5,0) -> A | I10: flip коричневые | J10: ='Юнит 10'!U16 -> 111 | K10: =J10/J$105 -> 0.054331865 | L10: =L9+K10 -> 0.57513461 | M10: =_xlfn.IFS(L10<80%,"A",L10<=95%,"B",L10>95%,"C") -> A
B11: черные с железкой классика | C11: ='Юнит 10'!AO3 -> 34966.219 | D11: =C11/C$105 -> 0.052979982 | E11: =E10+D11 -> 0.74304161 | F11: =IF(AND(E11<=0),"C",IF(E11<=0.8,"A",IF(E11<=0.95,"B","C"))) -> A | G11: =VLOOKUP(B$4:B$104,I$4:M$104,5,0) -> A | I11: th черн | J11: ='Юнит 10'!U9 -> 107 | K11: =J11/J$105 -> 0.05237396 | L11: =L10+K11 -> 0.62750857 | M11: =_xlfn.IFS(L11<80%,"A",L11<=95%,"B",L11>95%,"C") -> A
B12: sh3 | C12: ='Юнит 10'!AO28 -> 30976.089 | D12: =C12/C$105 -> 0.046934232 | E12: =E11+D12 -> 0.78997584 | F12: =IF(AND(E12<=0),"C",IF(E12<=0.8,"A",IF(E12<=0.95,"B","C"))) -> A | G12: =VLOOKUP(B$4:B$104,I$4:M$104,5,0) -> A | I12: QS желтые PZ | J12: ='Юнит 10'!U6 -> 105 | K12: =J12/J$105 -> 0.051395007 | L12: =L11+K12 -> 0.67890357 | M12: =_xlfn.IFS(L12<80%,"A",L12<=95%,"B",L12>95%,"C") -> A
B13: th желт | C13: ='Юнит 10'!AO11 -> 23552.911 | D13: =C13/C$105 -> 0.03568681 | E13: =E12+D13 -> 0.82566265 | F13: =IF(AND(E13<=0),"C",IF(E13<=0.8,"A",IF(E13<=0.95,"B","C"))) -> B | G13: =VLOOKUP(B$4:B$104,I$4:M$104,5,0) -> A | I13: черные с железкой классика | J13: ='Юнит 10'!U3 -> 101 | K13: =J13/J$105 -> 0.049437102 | L13: =L12+K13 -> 0.72834068 | M13: =_xlfn.IFS(L13<80%,"A",L13<=95%,"B",L13>95%,"C") -> A
B14: th син | C14: ='Юнит 10'!AO10 -> 22578.741 | D14: =C14/C$105 -> 0.03421077 | E14: =E13+D14 -> 0.85987342 | F14: =IF(AND(E14<=0),"C",IF(E14<=0.8,"A",IF(E14<=0.95,"B","C"))) -> B | G14: =VLOOKUP(B$4:B$104,I$4:M$104,5,0) -> A | I14: th желт | J14: ='Юнит 10'!U11 -> 62 | K14: =J14/J$105 -> 0.030347528 | L14: =L13+K14 -> 0.7586882 | M14: =_xlfn.IFS(L14<80%,"A",L14<=95%,"B",L14>95%,"C") -> A
B15: th коричн | C15: ='Юнит 10'!AO12 -> 19945.773 | D15: =C15/C$105 -> 0.03022136 | E15: =E14+D15 -> 0.89009478 | F15: =IF(AND(E15<=0),"C",IF(E15<=0.8,"A",IF(E15<=0.95,"B","C"))) -> B | G15: =VLOOKUP(B$4:B$104,I$4:M$104,5,0) -> A | I15: th коричн | J15: ='Юнит 10'!U12 -> 61 | K15: =J15/J$105 -> 0.029858052 | L15: =L14+K15 -> 0.78854626 | M15: =_xlfn.IFS(L15<80%,"A",L15<=95%,"B",L15>95%,"C") -> A
B16: MR8854 C2 Жен | C16: ='Юнит 10'!AO8 -> 14201.921 | D16: =C16/C$105 -> 0.021518412 | E16: =E15+D16 -> 0.91161319 | F16: =IF(AND(E16<=0),"C",IF(E16<=0.8,"A",IF(E16<=0.95,"B","C"))) -> B | G16: =VLOOKUP(B$4:B$104,I$4:M$104,5,0) -> B | I16: sh1 | J16: ='Юнит 10'!U26 -> 53 | K16: =J16/J$105 -> 0.025942242 | L16: =L15+K16 -> 0.8144885 | M16: =_xlfn.IFS(L16<80%,"A",L16<=95%,"B",L16>95%,"C") -> B
B17: ww 1022 черные | C17: ='Юнит 10'!AO45 -> 13864.821 | D17: =C17/C$105 -> 0.021007647 | E17: =E16+D17 -> 0.93262084 | F17: =IF(AND(E17<=0),"C",IF(E17<=0.8,"A",IF(E17<=0.95,"B","C"))) -> B | G17: =VLOOKUP(B$4:B$104,I$4:M$104,5,0) -> B | I17: MR8854 C2 Жен | J17: ='Юнит 10'!U8 -> 43 | K17: =J17/J$105 -> 0.021047479 | L17: =L16+K17 -> 0.83553598 | M17: =_xlfn.IFS(L17<80%,"A",L17<=95%,"B",L17>95%,"C") -> B
B18: flip синие | C18: ='Юнит 10'!AO14 -> 11037.77 | D18: =C18/C$105 -> 0.016724166 | E18: =E17+D18 -> 0.949345 | F18: =IF(AND(E18<=0),"C",IF(E18<=0.8,"A",IF(E18<=0.95,"B","C"))) -> B | G18: =VLOOKUP(B$4:B$104,I$4:M$104,5,0) -> B | I18: wwl8032 хром металл | J18: ='Юнит 10'!U18 -> 41 | K18: =J18/J$105 -> 0.020068527 | L18: =L17+K18 -> 0.8556045 | M18: =_xlfn.IFS(L18<80%,"A",L18<=95%,"B",L18>95%,"C") -> B
B19: wwl8032 хром металл | C19: ='Юнит 10'!AO18 -> 8534.8232 | D19: =C19/C$105 -> 0.012931761 | E19: =E18+D19 -> 0.96227676 | F19: =IF(AND(E19<=0),"C",IF(E19<=0.8,"A",IF(E19<=0.95,"B","C"))) -> C | G19: =VLOOKUP(B$4:B$104,I$4:M$104,5,0) -> B | I19: ww 1022 черные | J19: ='Юнит 10'!U45 -> 39 | K19: =J19/J$105 -> 0.019089574 | L19: =L18+K19 -> 0.87469408 | M19: =_xlfn.IFS(L19<80%,"A",L19<=95%,"B",L19>95%,"C") -> B
B20: flip желтые | C20: ='Юнит 10'!AO15 -> 8514.253 | D20: =C20/C$105 -> 0.012900593 | E20: =E19+D20 -> 0.97517736 | F20: =IF(AND(E20<=0),"C",IF(E20<=0.8,"A",IF(E20<=0.95,"B","C"))) -> C | G20: =VLOOKUP(B$4:B$104,I$4:M$104,5,0) -> B | I20: flip синие | J20: ='Юнит 10'!U14 -> 35 | K20: =J20/J$105 -> 0.017131669 | L20: =L19+K20 -> 0.89182575 | M20: =_xlfn.IFS(L20<80%,"A",L20<=95%,"B",L20>95%,"C") -> B
B21: ww 1022 коричневые | C21: ='Юнит 10'!AO48 -> 8417.1211 | D21: =C21/C$105 -> 0.012753421 | E21: =E20+D21 -> 0.98793078 | F21: =IF(AND(E21<=0),"C",IF(E21<=0.8,"A",IF(E21<=0.95,"B","C"))) -> C | G21: =VLOOKUP(B$4:B$104,I$4:M$104,5,0) -> B | I21: ww 1022 коричневые | J21: ='Юнит 10'!U48 -> 28 | K21: =J21/J$105 -> 0.013705335 | L21: =L20+K21 -> 0.90553108 | M21: =_xlfn.IFS(L21<80%,"A",L21<=95%,"B",L21>95%,"C") -> B
B22: ww 2018 черные | C22: ='Юнит 10'!AO49 -> 6809.9373 | D22: =C22/C$105 -> 0.010318255 | E22: =E21+D22 -> 0.99824903 | F22: =IF(AND(E22<=0),"C",IF(E22<=0.8,"A",IF(E22<=0.95,"B","C"))) -> C | G22: =VLOOKUP(B$4:B$104,I$4:M$104,5,0) -> B | I22: flip желтые | J22: ='Юнит 10'!U15 -> 25 | K22: =J22/J$105 -> 0.012236907 | L22: =L21+K22 -> 0.91776799 | M22: =_xlfn.IFS(L22<80%,"A",L22<=95%,"B",L22>95%,"C") -> B
B23: wwl8032 коричневые золото | C23: ='Юнит 10'!AO17 -> 6424.1933 | D23: =C23/C$105 -> 0.0097337847 | E23: =E22+D23 -> 1.0079828 | F23: =IF(AND(E23<=0),"C",IF(E23<=0.8,"A",IF(E23<=0.95,"B","C"))) -> C | G23: =VLOOKUP(B$4:B$104,I$4:M$104,5,0) -> B | I23: ww 2018 черные | J23: ='Юнит 10'!U49 -> 25 | K23: =J23/J$105 -> 0.012236907 | L23: =L22+K23 -> 0.93000489 | M23: =_xlfn.IFS(L23<80%,"A",L23<=95%,"B",L23>95%,"C") -> B
B24: ww 1022 желтые | C24: ='Юнит 10'!AO47 -> 4786.2281 | D24: =C24/C$105 -> 0.0072519788 | E24: =E23+D24 -> 1.0152348 | F24: =IF(AND(E24<=0),"C",IF(E24<=0.8,"A",IF(E24<=0.95,"B","C"))) -> C | G24: =VLOOKUP(B$4:B$104,I$4:M$104,5,0) -> C | I24: wwl8032 коричневые золото | J24: ='Юнит 10'!U17 -> 19 | K24: =J24/J$105 -> 0.0093000489 | L24: =L23+K24 -> 0.93930494 | M24: =_xlfn.IFS(L24<80%,"A",L24<=95%,"B",L24>95%,"C") -> B
B25: ww 2018 желтые | C25: ='Юнит 10'!AO50 -> 4625.2657 | D25: =C25/C$105 -> 0.0070080924 | E25: =E24+D25 -> 1.0222429 | F25: =IF(AND(E25<=0),"C",IF(E25<=0.8,"A",IF(E25<=0.95,"B","C"))) -> C | G25: =VLOOKUP(B$4:B$104,I$4:M$104,5,0) -> C | I25: sh19 | J25: ='Юнит 10'!U43 -> 17 | K25: =J25/J$105 -> 0.0083210964 | L25: =L24+K25 -> 0.94762604 | M25: =_xlfn.IFS(L25<80%,"A",L25<=95%,"B",L25>95%,"C") -> B
B26: sh19 | C26: ='Юнит 10'!AO43 -> 3584.3455 | D26: =C26/C$105 -> 0.0054309149 | E26: =E25+D26 -> 1.0276738 | F26: =IF(AND(E26<=0),"C",IF(E26<=0.8,"A",IF(E26<=0.95,"B","C"))) -> C | G26: =VLOOKUP(B$4:B$104,I$4:M$104,5,0) -> B | I26: ww 2018 желтые | J26: ='Юнит 10'!U50 -> 16 | K26: =J26/J$105 -> 0.0078316202 | L26: =L25+K26 -> 0.95545766 | M26: =_xlfn.IFS(L26<80%,"A",L26<=95%,"B",L26>95%,"C") -> C
B27: ww 203 черные | C27: ='Юнит 10'!AO44 -> 2519.735 | D27: =C27/C$105 -> 0.0038178425 | E27: =E26+D27 -> 1.0314916 | F27: =IF(AND(E27<=0),"C",IF(E27<=0.8,"A",IF(E27<=0.95,"B","C"))) -> C | G27: =VLOOKUP(B$4:B$104,I$4:M$104,5,0) -> C | I27: ww 203 черные | J27: ='Юнит 10'!U44 -> 14 | K27: =J27/J$105 -> 0.0068526676 | L27: =L26+K27 -> 0.96231033 | M27: =_xlfn.IFS(L27<80%,"A",L27<=95%,"B",L27>95%,"C") -> C
B28: sh13 | C28: ='Юнит 10'!AO37 -> 1158.0127 | D28: =C28/C$105 -> 0.0017545932 | E28: =E27+D28 -> 1.0332462 | F28: =IF(AND(E28<=0),"C",IF(E28<=0.8,"A",IF(E28<=0.95,"B","C"))) -> C | G28: =VLOOKUP(B$4:B$104,I$4:M$104,5,0) -> C | I28: ww 1022 желтые | J28: ='Юнит 10'!U47 -> 14 | K28: =J28/J$105 -> 0.0068526676 | L28: =L27+K28 -> 0.969163 | M28: =_xlfn.IFS(L28<80%,"A",L28<=95%,"B",L28>95%,"C") -> C
B29: sh18 | C29: ='Юнит 10'!AO42 -> 885.19153 | D29: =C29/C$105 -> 0.0013412211 | E29: =E28+D29 -> 1.0345875 | F29: =IF(AND(E29<=0),"C",IF(E29<=0.8,"A",IF(E29<=0.95,"B","C"))) -> C | G29: =VLOOKUP(B$4:B$104,I$4:M$104,5,0) -> C | I29: sh2 | J29: ='Юнит 10'!U27 -> 10 | K29: =J29/J$105 -> 0.0048947626 | L29: =L28+K29 -> 0.97405776 | M29: =_xlfn.IFS(L29<80%,"A",L29<=95%,"B",L29>95%,"C") -> C
B30: Chenlong черные | C30: ='Юнит 10'!AO76 -> 863.21771 | D30: =C30/C$105 -> 0.0013079269 | E30: =E29+D30 -> 1.0358954 | F30: =IF(AND(E30<=0),"C",IF(E30<=0.8,"A",IF(E30<=0.95,"B","C"))) -> C | G30: =VLOOKUP(B$4:B$104,I$4:M$104,5,0) -> C | I30: Linhai Baiyi серая линза | J30: ='Юнит 10'!U87 -> 8 | K30: =J30/J$105 -> 0.0039158101 | L30: =L29+K30 -> 0.97797357 | M30: =_xlfn.IFS(L30<80%,"A",L30<=95%,"B",L30>95%,"C") -> C
B31: MANNA2119 | C31: ='Юнит 10'!AO72 -> 824.1899 | D31: =C31/C$105 -> 0.0012487929 | E31: =E30+D31 -> 1.0371442 | F31: =IF(AND(E31<=0),"C",IF(E31<=0.8,"A",IF(E31<=0.95,"B","C"))) -> C | G31: =VLOOKUP(B$4:B$104,I$4:M$104,5,0) -> C | I31: sh15 | J31: ='Юнит 10'!U39 -> 7 | K31: =J31/J$105 -> 0.0034263338 | L31: =L30+K31 -> 0.9813999 | M31: =_xlfn.IFS(L31<80%,"A",L31<=95%,"B",L31>95%,"C") -> C
B32: WW 3055 черный | C32: ='Юнит 10'!AO52 -> 644.0974 | D32: =C32/C$105 -> 0.00097592104 | E32: =E31+D32 -> 1.0381201 | F32: =IF(AND(E32<=0),"C",IF(E32<=0.8,"A",IF(E32<=0.95,"B","C"))) -> C | G32: =VLOOKUP(B$4:B$104,I$4:M$104,5,0) -> C | I32: sh13 | J32: ='Юнит 10'!U37 -> 4 | K32: =J32/J$105 -> 0.001957905 | L32: =L31+K32 -> 0.98335781 | M32: =_xlfn.IFS(L32<80%,"A",L32<=95%,"B",L32>95%,"C") -> C
B33: Ли Сян ретро серебро | C33: ='Юнит 10'!AO93 -> 508.58384 | D33: =C33/C$105 -> 0.00077059412 | E33: =E32+D33 -> 1.0388907 | F33: =IF(AND(E33<=0),"C",IF(E33<=0.8,"A",IF(E33<=0.95,"B","C"))) -> C | G33: =VLOOKUP(B$4:B$104,I$4:M$104,5,0) -> C | I33: Hengda Optical черные | J33: ='Юнит 10'!U81 -> 4 | K33: =J33/J$105 -> 0.001957905 | L33: =L32+K33 -> 0.98531571 | M33: =_xlfn.IFS(L33<80%,"A",L33<=95%,"B",L33>95%,"C") -> C
B34: sh17 | C34: ='Юнит 10'!AO41 -> 488.77745 | D34: =C34/C$105 -> 0.00074058395 | E34: =E33+D34 -> 1.0396313 | F34: =IF(AND(E34<=0),"C",IF(E34<=0.8,"A",IF(E34<=0.95,"B","C"))) -> C | G34: =VLOOKUP(B$4:B$104,I$4:M$104,5,0) -> C | I34: кс_черные_женские | J34: ='Юнит 10'!U102 -> 4 | K34: =J34/J$105 -> 0.001957905 | L34: =L33+K34 -> 0.98727362 | M34: =_xlfn.IFS(L34<80%,"A",L34<=95%,"B",L34>95%,"C") -> C
B35: Hengda Optical леопард | C35: ='Юнит 10'!AO82 -> 465.86601 | D35: =C35/C$105 -> 0.00070586908 | E35: =E34+D35 -> 1.0403371 | F35: =IF(AND(E35<=0),"C",IF(E35<=0.8,"A",IF(E35<=0.95,"B","C"))) -> C | G35: =VLOOKUP(B$4:B$104,I$4:M$104,5,0) -> C | I35: MANNA2119 | J35: ='Юнит 10'!U72 -> 3 | K35: =J35/J$105 -> 0.0014684288 | L35: =L34+K35 -> 0.98874205 | M35: =_xlfn.IFS(L35<80%,"A",L35<=95%,"B",L35>95%,"C") -> C
B36: Chenlong коричневые | C36: ='Юнит 10'!AO77 -> 458.66546 | D36: =C36/C$105 -> 0.00069495898 | E36: =E35+D36 -> 1.0410321 | F36: =IF(AND(E36<=0),"C",IF(E36<=0.8,"A",IF(E36<=0.95,"B","C"))) -> C | G36: =VLOOKUP(B$4:B$104,I$4:M$104,5,0) -> C | I36: sh18 | J36: ='Юнит 10'!U42 -> 2 | K36: =J36/J$105 -> 0.00097895252 | L36: =L35+K36 -> 0.989721 | M36: =_xlfn.IFS(L36<80%,"A",L36<=95%,"B",L36>95%,"C") -> C
B37: Linhai Baiyi розовая линза | C37: ='Юнит 10'!AO88 -> 407.6659 | D37: =C37/C$105 -> 0.00061768566 | E37: =E36+D37 -> 1.0416498 | F37: =IF(AND(E37<=0),"C",IF(E37<=0.8,"A",IF(E37<=0.95,"B","C"))) -> C | G37: =VLOOKUP(B$4:B$104,I$4:M$104,5,0) -> C | I37: WW 3055 черный | J37: ='Юнит 10'!U52 -> 2 | K37: =J37/J$105 -> 0.00097895252 | L37: =L36+K37 -> 0.99069995 | M37: =_xlfn.IFS(L37<80%,"A",L37<=95%,"B",L37>95%,"C") -> C
B38: MANNA2114 | C38: ='Юнит 10'!AO67 -> 312.2996 | D38: =C38/C$105 -> 0.00047318892 | E38: =E37+D38 -> 1.042123 | F38: =IF(AND(E38<=0),"C",IF(E38<=0.8,"A",IF(E38<=0.95,"B","C"))) -> C | G38: =VLOOKUP(B$4:B$104,I$4:M$104,5,0) -> C | I38: MANNA2105 | J38: ='Юнит 10'!U58 -> 2 | K38: =J38/J$105 -> 0.00097895252 | L38: =L37+K38 -> 0.9916789 | M38: =_xlfn.IFS(L38<80%,"A",L38<=95%,"B",L38>95%,"C") -> C
B39: sports красные | C39: ='Юнит 10'!AO22 -> 307.2499 | D39: =C39/C$105 -> 0.00046553773 | E39: =E35+D39 -> 1.0408027 | F39: =IF(AND(E39<=0),"C",IF(E39<=0.8,"A",IF(E39<=0.95,"B","C"))) -> C | G39: =VLOOKUP(B$4:B$104,I$4:M$104,5,0) -> C | I39: Chenlong черные | J39: ='Юнит 10'!U76 -> 2 | K39: =J39/J$105 -> 0.00097895252 | L39: =L35+K39 -> 0.989721 | M39: =_xlfn.IFS(L39<80%,"A",L39<=95%,"B",L39>95%,"C") -> C
B40: MANNA2101 | C40: ='Юнит 10'!AO54 -> 194.55241 | D40: =C40/C$105 -> 0.00029478118 | E40: =E39+D40 -> 1.0410975 | F40: =IF(AND(E40<=0),"C",IF(E40<=0.8,"A",IF(E40<=0.95,"B","C"))) -> C | G40: =VLOOKUP(B$4:B$104,I$4:M$104,5,0) -> C | I40: Guangdu серебро серая линза | J40: ='Юнит 10'!U80 -> 2 | K40: =J40/J$105 -> 0.00097895252 | L40: =L39+K40 -> 0.99069995 | M40: =_xlfn.IFS(L40<80%,"A",L40<=95%,"B",L40>95%,"C") -> C
B41: Keming Aishi коричневые | C41: ='Юнит 10'!AO85 -> 185.1204 | D41: =C41/C$105 -> 0.00028049002 | E41: =E40+D41 -> 1.041378 | F41: =IF(AND(E41<=0),"C",IF(E41<=0.8,"A",IF(E41<=0.95,"B","C"))) -> C | G41: =VLOOKUP(B$4:B$104,I$4:M$104,5,0) -> C | I41: Linhai Baiyi розовая линза | J41: ='Юнит 10'!U88 -> 2 | K41: =J41/J$105 -> 0.00097895252 | L41: =L40+K41 -> 0.9916789 | M41: =_xlfn.IFS(L41<80%,"A",L41<=95%,"B",L41>95%,"C") -> C
B42: wwl8032 черные серебро | C42: ='Юнит 10'!AO19 -> 0 | D42: =C42/C$105 -> 0 | E42: =E41+D42 -> 1.041378 | F42: =IF(AND(E42<=0),"C",IF(E42<=0.8,"A",IF(E42<=0.95,"B","C"))) -> C | G42: =VLOOKUP(B$4:B$104,I$4:M$104,5,0) -> C | I42: sports красные | J42: ='Юнит 10'!U22 -> 1 | K42: =J42/J$105 -> 0.00048947626 | L42: =L41+K42 -> 0.99216838 | M42: =_xlfn.IFS(L42<80%,"A",L42<=95%,"B",L42>95%,"C") -> C
B43: sports синие | C43: ='Юнит 10'!AO20 -> 0 | D43: =C43/C$105 -> 0 | E43: =E42+D43 -> 1.041378 | F43: =IF(AND(E43<=0),"C",IF(E43<=0.8,"A",IF(E43<=0.95,"B","C"))) -> C | G43: =VLOOKUP(B$4:B$104,I$4:M$104,5,0) -> C | I43: sh09 | J43: ='Юнит 10'!U33 -> 1 | K43: =J43/J$105 -> 0.00048947626 | L43: =L42+K43 -> 0.99265786 | M43: =_xlfn.IFS(L43<80%,"A",L43<=95%,"B",L43>95%,"C") -> C
B44: sports зеленые | C44: ='Юнит 10'!AO21 -> 0 | D44: =C44/C$105 -> 0 | E44: =E43+D44 -> 1.041378 | F44: =IF(AND(E44<=0),"C",IF(E44<=0.8,"A",IF(E44<=0.95,"B","C"))) -> C | G44: =VLOOKUP(B$4:B$104,I$4:M$104,5,0) -> C | I44: sh17 | J44: ='Юнит 10'!U41 -> 1 | K44: =J44/J$105 -> 0.00048947626 | L44: =L43+K44 -> 0.99314733 | M44: =_xlfn.IFS(L44<80%,"A",L44<=95%,"B",L44>95%,"C") -> C
B45: sportlife черные | C45: ='Юнит 10'!AO23 -> 0 | D45: =C45/C$105 -> 0 | E45: =E44+D45 -> 1.041378 | F45: =IF(AND(E45<=0),"C",IF(E45<=0.8,"A",IF(E45<=0.95,"B","C"))) -> C | G45: =VLOOKUP(B$4:B$104,I$4:M$104,5,0) -> C | I45: MANNA2101 | J45: ='Юнит 10'!U54 -> 1 | K45: =J45/J$105 -> 0.00048947626 | L45: =L44+K45 -> 0.99363681 | M45: =_xlfn.IFS(L45<80%,"A",L45<=95%,"B",L45>95%,"C") -> C
B46: sportlife синие | C46: ='Юнит 10'!AO24 -> 0 | D46: =C46/C$105 -> 0 | E46: =E45+D46 -> 1.041378 | F46: =IF(AND(E46<=0),"C",IF(E46<=0.8,"A",IF(E46<=0.95,"B","C"))) -> C | G46: =VLOOKUP(B$4:B$104,I$4:M$104,5,0) -> C | I46: MANNA2114 | J46: ='Юнит 10'!U67 -> 1 | K46: =J46/J$105 -> 0.00048947626 | L46: =L45+K46 -> 0.99412628 | M46: =_xlfn.IFS(L46<80%,"A",L46<=95%,"B",L46>95%,"C") -> C
B47: sportlife красные | C47: ='Юнит 10'!AO25 -> 0 | D47: =C47/C$105 -> 0 | E47: =E46+D47 -> 1.041378 | F47: =IF(AND(E47<=0),"C",IF(E47<=0.8,"A",IF(E47<=0.95,"B","C"))) -> C | G47: =VLOOKUP(B$4:B$104,I$4:M$104,5,0) -> C | I47: MANNA2120 | J47: ='Юнит 10'!U73 -> 1 | K47: =J47/J$105 -> 0.00048947626 | L47: =L46+K47 -> 0.99461576 | M47: =_xlfn.IFS(L47<80%,"A",L47<=95%,"B",L47>95%,"C") -> C
B48: sh4 | C48: ='Юнит 10'!AO29 -> 0 | D48: =C48/C$105 -> 0 | E48: =E47+D48 -> 1.041378 | F48: =IF(AND(E48<=0),"C",IF(E48<=0.8,"A",IF(E48<=0.95,"B","C"))) -> C | G48: =VLOOKUP(B$4:B$104,I$4:M$104,5,0) -> C | I48: MANNA2122 | J48: ='Юнит 10'!U75 -> 1 | K48: =J48/J$105 -> 0.00048947626 | L48: =L47+K48 -> 0.99510524 | M48: =_xlfn.IFS(L48<80%,"A",L48<=95%,"B",L48>95%,"C") -> C
B49: sh07 | C49: ='Юнит 10'!AO31 -> 0 | D49: =C49/C$105 -> 0 | E49: =E48+D49 -> 1.041378 | F49: =IF(AND(E49<=0),"C",IF(E49<=0.8,"A",IF(E49<=0.95,"B","C"))) -> C | G49: =VLOOKUP(B$4:B$104,I$4:M$104,5,0) -> C | I49: Chenlong коричневые | J49: ='Юнит 10'!U77 -> 1 | K49: =J49/J$105 -> 0.00048947626 | L49: =L48+K49 -> 0.99559471 | M49: =_xlfn.IFS(L49<80%,"A",L49<=95%,"B",L49>95%,"C") -> C
B50: sh08 | C50: ='Юнит 10'!AO32 -> 0 | D50: =C50/C$105 -> 0 | E50: =E49+D50 -> 1.041378 | F50: =IF(AND(E50<=0),"C",IF(E50<=0.8,"A",IF(E50<=0.95,"B","C"))) -> C | G50: =VLOOKUP(B$4:B$104,I$4:M$104,5,0) -> C | I50: Chenlong белые | J50: ='Юнит 10'!U78 -> 1 | K50: =J50/J$105 -> 0.00048947626 | L50: =L49+K50 -> 0.99608419 | M50: =_xlfn.IFS(L50<80%,"A",L50<=95%,"B",L50>95%,"C") -> C
B51: sh11 | C51: ='Юнит 10'!AO35 -> 0 | D51: =C51/C$105 -> 0 | E51: =E50+D51 -> 1.041378 | F51: =IF(AND(E51<=0),"C",IF(E51<=0.8,"A",IF(E51<=0.95,"B","C"))) -> C | G51: =VLOOKUP(B$4:B$104,I$4:M$104,5,0) -> C | I51: Hengda Optical леопард | J51: ='Юнит 10'!U82 -> 1 | K51: =J51/J$105 -> 0.00048947626 | L51: =L50+K51 -> 0.99657367 | M51: =_xlfn.IFS(L51<80%,"A",L51<=95%,"B",L51>95%,"C") -> C
B52: sh12 | C52: ='Юнит 10'!AO36 -> 0 | D52: =C52/C$105 -> 0 | E52: =E51+D52 -> 1.041378 | F52: =IF(AND(E52<=0),"C",IF(E52<=0.8,"A",IF(E52<=0.95,"B","C"))) -> C | G52: =VLOOKUP(B$4:B$104,I$4:M$104,5,0) -> C | I52: Keming Aishi коричневые | J52: ='Юнит 10'!U85 -> 1 | K52: =J52/J$105 -> 0.00048947626 | L52: =L51+K52 -> 0.99706314 | M52: =_xlfn.IFS(L52<80%,"A",L52<=95%,"B",L52>95%,"C") -> C
B53: ww 1022 черн-серебро | C53: ='Юнит 10'!AO46 -> 0 | D53: =C53/C$105 -> 0 | E53: =E52+D53 -> 1.041378 | F53: =IF(AND(E53<=0),"C",IF(E53<=0.8,"A",IF(E53<=0.95,"B","C"))) -> C | G53: =VLOOKUP(B$4:B$104,I$4:M$104,5,0) -> C | I53: Ли Сян ретро серебро | J53: ='Юнит 10'!U93 -> 1 | K53: =J53/J$105 -> 0.00048947626 | L53: =L52+K53 -> 0.99755262 | M53: =_xlfn.IFS(L53<80%,"A",L53<=95%,"B",L53>95%,"C") -> C
B54: MANNA2102 | C54: ='Юнит 10'!AO55 -> 0 | D54: =C54/C$105 -> 0 | E54: =E53+D54 -> 1.041378 | F54: =IF(AND(E54<=0),"C",IF(E54<=0.8,"A",IF(E54<=0.95,"B","C"))) -> C | G54: =VLOOKUP(B$4:B$104,I$4:M$104,5,0) -> C | I54: wwl8032 черные серебро | J54: ='Юнит 10'!U19 -> 0 | K54: =J54/J$105 -> 0 | L54: =L53+K54 -> 0.99755262 | M54: =_xlfn.IFS(L54<80%,"A",L54<=95%,"B",L54>95%,"C") -> C
B55: MANNA2103 | C55: ='Юнит 10'!AO56 -> 0 | D55: =C55/C$105 -> 0 | E55: =E54+D55 -> 1.041378 | F55: =IF(AND(E55<=0),"C",IF(E55<=0.8,"A",IF(E55<=0.95,"B","C"))) -> C | G55: =VLOOKUP(B$4:B$104,I$4:M$104,5,0) -> C | I55: sports синие | J55: ='Юнит 10'!U20 -> 0 | K55: =J55/J$105 -> 0 | L55: =L54+K55 -> 0.99755262 | M55: =_xlfn.IFS(L55<80%,"A",L55<=95%,"B",L55>95%,"C") -> C
B56: MANNA2104 | C56: ='Юнит 10'!AO57 -> 0 | D56: =C56/C$105 -> 0 | E56: =E55+D56 -> 1.041378 | F56: =IF(AND(E56<=0),"C",IF(E56<=0.8,"A",IF(E56<=0.95,"B","C"))) -> C | G56: =VLOOKUP(B$4:B$104,I$4:M$104,5,0) -> C | I56: sports зеленые | J56: ='Юнит 10'!U21 -> 0 | K56: =J56/J$105 -> 0 | L56: =L55+K56 -> 0.99755262 | M56: =_xlfn.IFS(L56<80%,"A",L56<=95%,"B",L56>95%,"C") -> C
B57: MANNA2106 | C57: ='Юнит 10'!AO59 -> 0 | D57: =C57/C$105 -> 0 | E57: =E56+D57 -> 1.041378 | F57: =IF(AND(E57<=0),"C",IF(E57<=0.8,"A",IF(E57<=0.95,"B","C"))) -> C | G57: =VLOOKUP(B$4:B$104,I$4:M$104,5,0) -> C | I57: sportlife черные | J57: ='Юнит 10'!U23 -> 0 | K57: =J57/J$105 -> 0 | L57: =L56+K57 -> 0.99755262 | M57: =_xlfn.IFS(L57<80%,"A",L57<=95%,"B",L57>95%,"C") -> C
B58: MANNA2109 | C58: ='Юнит 10'!AO62 -> 0 | D58: =C58/C$105 -> 0 | E58: =E57+D58 -> 1.041378 | F58: =IF(AND(E58<=0),"C",IF(E58<=0.8,"A",IF(E58<=0.95,"B","C"))) -> C | G58: =VLOOKUP(B$4:B$104,I$4:M$104,5,0) -> C | I58: sportlife синие | J58: ='Юнит 10'!U24 -> 0 | K58: =J58/J$105 -> 0 | L58: =L57+K58 -> 0.99755262 | M58: =_xlfn.IFS(L58<80%,"A",L58<=95%,"B",L58>95%,"C") -> C
B59: MANNA2110 | C59: ='Юнит 10'!AO63 -> 0 | D59: =C59/C$105 -> 0 | E59: =E58+D59 -> 1.041378 | F59: =IF(AND(E59<=0),"C",IF(E59<=0.8,"A",IF(E59<=0.95,"B","C"))) -> C | G59: =VLOOKUP(B$4:B$104,I$4:M$104,5,0) -> C | I59: sportlife красные | J59: ='Юнит 10'!U25 -> 0 | K59: =J59/J$105 -> 0 | L59: =L58+K59 -> 0.99755262 | M59: =_xlfn.IFS(L59<80%,"A",L59<=95%,"B",L59>95%,"C") -> C
B60: MANNA2111 | C60: ='Юнит 10'!AO64 -> 0 | D60: =C60/C$105 -> 0 | E60: =E59+D60 -> 1.041378 | F60: =IF(AND(E60<=0),"C",IF(E60<=0.8,"A",IF(E60<=0.95,"B","C"))) -> C | G60: =VLOOKUP(B$4:B$104,I$4:M$104,5,0) -> C | I60: sh4 | J60: ='Юнит 10'!U29 -> 0 | K60: =J60/J$105 -> 0 | L60: =L59+K60 -> 0.99755262 | M60: =_xlfn.IFS(L60<80%,"A",L60<=95%,"B",L60>95%,"C") -> C
B61: MANNA2115 | C61: ='Юнит 10'!AO68 -> 0 | D61: =C61/C$105 -> 0 | E61: =E60+D61 -> 1.041378 | F61: =IF(AND(E61<=0),"C",IF(E61<=0.8,"A",IF(E61<=0.95,"B","C"))) -> C | G61: =VLOOKUP(B$4:B$104,I$4:M$104,5,0) -> C | I61: sh06 | J61: ='Юнит 10'!U30 -> 0 | K61: =J61/J$105 -> 0 | L61: =L60+K61 -> 0.99755262 | M61: =_xlfn.IFS(L61<80%,"A",L61<=95%,"B",L61>95%,"C") -> C
B62: MAIERSHA 03898 C9-08 | C62: ='Юнит 10'!AO94 -> 0 | D62: =C62/C$105 -> 0 | E62: =E61+D62 -> 1.041378 | F62: =IF(AND(E62<=0),"C",IF(E62<=0.8,"A",IF(E62<=0.95,"B","C"))) -> C | G62: =VLOOKUP(B$4:B$104,I$4:M$104,5,0) -> C | I62: sh07 | J62: ='Юнит 10'!U31 -> 0 | K62: =J62/J$105 -> 0 | L62: =L61+K62 -> 0.99755262 | M62: =_xlfn.IFS(L62<80%,"A",L62<=95%,"B",L62>95%,"C") -> C
B63: MAIERSHA 03914 C9-124 | C63: ='Юнит 10'!AO95 -> 0 | D63: =C63/C$105 -> 0 | E63: =E62+D63 -> 1.041378 | F63: =IF(AND(E63<=0),"C",IF(E63<=0.8,"A",IF(E63<=0.95,"B","C"))) -> C | G63: =VLOOKUP(B$4:B$104,I$4:M$104,5,0) -> C | I63: sh08 | J63: ='Юнит 10'!U32 -> 0 | K63: =J63/J$105 -> 0 | L63: =L62+K63 -> 0.99755262 | M63: =_xlfn.IFS(L63<80%,"A",L63<=95%,"B",L63>95%,"C") -> C
B64: MARSTON 7171 C1 | C64: ='Юнит 10'!AO96 -> 0 | D64: =C64/C$105 -> 0 | E64: =E63+D64 -> 1.041378 | F64: =IF(AND(E64<=0),"C",IF(E64<=0.8,"A",IF(E64<=0.95,"B","C"))) -> C | G64: =VLOOKUP(B$4:B$104,I$4:M$104,5,0) -> C | I64: sh11 | J64: ='Юнит 10'!U35 -> 0 | K64: =J64/J$105 -> 0 | L64: =L63+K64 -> 0.99755262 | M64: =_xlfn.IFS(L64<80%,"A",L64<=95%,"B",L64>95%,"C") -> C
B65: ЧСЖ_тест | C65: ='Юнит 10'!AO99 -> 0 | D65: =C65/C$105 -> 0 | E65: =E64+D65 -> 1.041378 | F65: =IF(AND(E65<=0),"C",IF(E65<=0.8,"A",IF(E65<=0.95,"B","C"))) -> C | G65: =VLOOKUP(B$4:B$104,I$4:M$104,5,0) -> C | I65: sh12 | J65: ='Юнит 10'!U36 -> 0 | K65: =J65/J$105 -> 0 | L65: =L64+K65 -> 0.99755262 | M65: =_xlfn.IFS(L65<80%,"A",L65<=95%,"B",L65>95%,"C") -> C
B66: кс_черные_тест | C66: ='Юнит 10'!AO101 -> 0 | D66: =C66/C$105 -> 0 | E66: =E65+D66 -> 1.041378 | F66: =IF(AND(E66<=0),"C",IF(E66<=0.8,"A",IF(E66<=0.95,"B","C"))) -> C | G66: =VLOOKUP(B$4:B$104,I$4:M$104,5,0) -> C | I66: sh14 | J66: ='Юнит 10'!U38 -> 0 | K66: =J66/J$105 -> 0 | L66: =L65+K66 -> 0.99755262 | M66: =_xlfn.IFS(L66<80%,"A",L66<=95%,"B",L66>95%,"C") -> C
B67: 1022_коричневые_тест | C67: ='Юнит 10'!AO103 -> 0 | D67: =C67/C$105 -> 0 | E67: =E66+D67 -> 1.041378 | F67: =IF(AND(E67<=0),"C",IF(E67<=0.8,"A",IF(E67<=0.95,"B","C"))) -> C | G67: =VLOOKUP(B$4:B$104,I$4:M$104,5,0) -> C | I67: sh16 | J67: ='Юнит 10'!U40 -> 0 | K67: =J67/J$105 -> 0 | L67: =L66+K67 -> 0.99755262 | M67: =_xlfn.IFS(L67<80%,"A",L67<=95%,"B",L67>95%,"C") -> C
B68: MANNA2113 | C68: ='Юнит 10'!AO66 -> -1.0034151 | D68: =C68/C$105 -> -1.5203506e-06 | E68: =E67+D68 -> 1.0413764 | F68: =IF(AND(E68<=0),"C",IF(E68<=0.8,"A",IF(E68<=0.95,"B","C"))) -> C | G68: =VLOOKUP(B$4:B$104,I$4:M$104,5,0) -> C | I68: ww 1022 черн-серебро | J68: ='Юнит 10'!U46 -> 0 | K68: =J68/J$105 -> 0 | L68: =L67+K68 -> 0.99755262 | M68: =_xlfn.IFS(L68<80%,"A",L68<=95%,"B",L68>95%,"C") -> C
B69: ww 8010 черные | C69: ='Юнит 10'!AO51 -> -2.0068301 | D69: =C69/C$105 -> -3.0407012e-06 | E69: =E68+D69 -> 1.0413734 | F69: =IF(AND(E69<=0),"C",IF(E69<=0.8,"A",IF(E69<=0.95,"B","C"))) -> C | G69: =VLOOKUP(B$4:B$104,I$4:M$104,5,0) -> C | I69: ww 8010 черные | J69: ='Юнит 10'!U51 -> 0 | K69: =J69/J$105 -> 0 | L69: =L68+K69 -> 0.99755262 | M69: =_xlfn.IFS(L69<80%,"A",L69<=95%,"B",L69>95%,"C") -> C
B70: POMILED 08247 C4-08 | C70: ='Юнит 10'!AO97 -> -3.0102452 | D70: =C70/C$105 -> -4.5610519e-06 | E70: =E69+D70 -> 1.0413688 | F70: =IF(AND(E70<=0),"C",IF(E70<=0.8,"A",IF(E70<=0.95,"B","C"))) -> C | G70: =VLOOKUP(B$4:B$104,I$4:M$104,5,0) -> C | I70: WW 3055 коричневый | J70: ='Юнит 10'!U53 -> 0 | K70: =J70/J$105 -> 0 | L70: =L69+K70 -> 0.99755262 | M70: =_xlfn.IFS(L70<80%,"A",L70<=95%,"B",L70>95%,"C") -> C
B71: MR Р1894 черные | C71: ='Юнит 10'!AO89 -> -35.119528 | D71: =C71/C$105 -> -5.3212272e-05 | E71: =E70+D71 -> 1.0413156 | F71: =IF(AND(E71<=0),"C",IF(E71<=0.8,"A",IF(E71<=0.95,"B","C"))) -> C | G71: =VLOOKUP(B$4:B$104,I$4:M$104,5,0) -> C | I71: MANNA2102 | J71: ='Юнит 10'!U55 -> 0 | K71: =J71/J$105 -> 0 | L71: =L70+K71 -> 0.99755262 | M71: =_xlfn.IFS(L71<80%,"A",L71<=95%,"B",L71>95%,"C") -> C
B72: Linhai Baiyi коричневая линза | C72: ='Юнит 10'!AO86 -> -44.150263 | D72: =C72/C$105 -> -6.6895427e-05 | E72: =E71+D72 -> 1.0412487 | F72: =IF(AND(E72<=0),"C",IF(E72<=0.8,"A",IF(E72<=0.95,"B","C"))) -> C | G72: =VLOOKUP(B$4:B$104,I$4:M$104,5,0) -> C | I72: MANNA2103 | J72: ='Юнит 10'!U56 -> 0 | K72: =J72/J$105 -> 0 | L72: =L71+K72 -> 0.99755262 | M72: =_xlfn.IFS(L72<80%,"A",L72<=95%,"B",L72>95%,"C") -> C
B73: MANNA2122 | C73: ='Юнит 10'!AO75 -> -44.754156 | D73: =C73/C$105 -> -6.7810432e-05 | E73: =E72+D73 -> 1.0411809 | F73: =IF(AND(E73<=0),"C",IF(E73<=0.8,"A",IF(E73<=0.95,"B","C"))) -> C | G73: =VLOOKUP(B$4:B$104,I$4:M$104,5,0) -> C | I73: MANNA2104 | J73: ='Юнит 10'!U57 -> 0 | K73: =J73/J$105 -> 0 | L73: =L72+K73 -> 0.99755262 | M73: =_xlfn.IFS(L73<80%,"A",L73<=95%,"B",L73>95%,"C") -> C
B74: WW 3055 коричневый | C74: ='Юнит 10'!AO53 -> -45.153678 | D74: =C74/C$105 -> -6.8415778e-05 | E74: =E73+D74 -> 1.0411125 | F74: =IF(AND(E74<=0),"C",IF(E74<=0.8,"A",IF(E74<=0.95,"B","C"))) -> C | G74: =VLOOKUP(B$4:B$104,I$4:M$104,5,0) -> C | I74: MANNA2106 | J74: ='Юнит 10'!U59 -> 0 | K74: =J74/J$105 -> 0 | L74: =L73+K74 -> 0.99755262 | M74: =_xlfn.IFS(L74<80%,"A",L74<=95%,"B",L74>95%,"C") -> C
B75: Qianai коричневые | C75: ='Юнит 10'!AO84 -> -48.163924 | D75: =C75/C$105 -> -7.297683e-05 | E75: =E74+D75 -> 1.0410395 | F75: =IF(AND(E75<=0),"C",IF(E75<=0.8,"A",IF(E75<=0.95,"B","C"))) -> C | G75: =VLOOKUP(B$4:B$104,I$4:M$104,5,0) -> C | I75: MANNA2107 | J75: ='Юнит 10'!U60 -> 0 | K75: =J75/J$105 -> 0 | L75: =L74+K75 -> 0.99755262 | M75: =_xlfn.IFS(L75<80%,"A",L75<=95%,"B",L75>95%,"C") -> C
B76: Taizhou Rayen sport розовый | C76: ='Юнит 10'!AO90 -> -50.170754 | D76: =C76/C$105 -> -7.6017531e-05 | E76: =E49+D76 -> 1.0413019 | F76: =IF(AND(E76<=0),"C",IF(E76<=0.8,"A",IF(E76<=0.95,"B","C"))) -> C | G76: =VLOOKUP(B$4:B$104,I$4:M$104,5,0) -> C | I76: MANNA2108 | J76: ='Юнит 10'!U61 -> 0 | K76: =J76/J$105 -> 0 | L76: =L49+K76 -> 0.99559471 | M76: =_xlfn.IFS(L76<80%,"A",L76<=95%,"B",L76>95%,"C") -> C
B77: sh2 | C77: ='Юнит 10'!AO27 -> -51.820296 | D77: =C77/C$105 -> -7.8516878e-05 | E77: =E76+D77 -> 1.0412234 | F77: =IF(AND(E77<=0),"C",IF(E77<=0.8,"A",IF(E77<=0.95,"B","C"))) -> C | G77: =VLOOKUP(B$4:B$104,I$4:M$104,5,0) -> C | I77: MANNA2109 | J77: ='Юнит 10'!U62 -> 0 | K77: =J77/J$105 -> 0 | L77: =L76+K77 -> 0.99559471 | M77: =_xlfn.IFS(L77<80%,"A",L77<=95%,"B",L77>95%,"C") -> C
B78: Guangdu серебро серая линза | C78: ='Юнит 10'!AO80 -> -69.60402 | D78: =C78/C$105 -> -0.00010546235 | E78: =E77+D78 -> 1.041118 | F78: =IF(AND(E78<=0),"C",IF(E78<=0.8,"A",IF(E78<=0.95,"B","C"))) -> C | G78: =VLOOKUP(B$4:B$104,I$4:M$104,5,0) -> C | I78: MANNA2110 | J78: ='Юнит 10'!U63 -> 0 | K78: =J78/J$105 -> 0 | L78: =L77+K78 -> 0.99559471 | M78: =_xlfn.IFS(L78<80%,"A",L78<=95%,"B",L78>95%,"C") -> C
B79: MANNA2117 | C79: ='Юнит 10'!AO70 -> -100.33025 | D79: =C79/C$105 -> -0.000152018 | E79: =E78+D79 -> 1.0409659 | F79: =IF(AND(E79<=0),"C",IF(E79<=0.8,"A",IF(E79<=0.95,"B","C"))) -> C | G79: =VLOOKUP(B$4:B$104,I$4:M$104,5,0) -> C | I79: MANNA2111 | J79: ='Юнит 10'!U64 -> 0 | K79: =J79/J$105 -> 0 | L79: =L78+K79 -> 0.99559471 | M79: =_xlfn.IFS(L79<80%,"A",L79<=95%,"B",L79>95%,"C") -> C
B80: MANNA2116 | C80: ='Юнит 10'!AO69 -> -105.34732 | D80: =C80/C$105 -> -0.00015961975 | E80: =E79+D80 -> 1.0408063 | F80: =IF(AND(E80<=0),"C",IF(E80<=0.8,"A",IF(E80<=0.95,"B","C"))) -> C | G80: =VLOOKUP(B$4:B$104,I$4:M$104,5,0) -> C | I80: MANNA2112 | J80: ='Юнит 10'!U65 -> 0 | K80: =J80/J$105 -> 0 | L80: =L79+K80 -> 0.99559471 | M80: =_xlfn.IFS(L80<80%,"A",L80<=95%,"B",L80>95%,"C") -> C
B81: MANNA2112 | C81: ='Юнит 10'!AO65 -> -110.16342 | D81: =C81/C$105 -> -0.00016691698 | E81: =E80+D81 -> 1.0406394 | F81: =IF(AND(E81<=0),"C",IF(E81<=0.8,"A",IF(E81<=0.95,"B","C"))) -> C | G81: =VLOOKUP(B$4:B$104,I$4:M$104,5,0) -> C | I81: MANNA2113 | J81: ='Юнит 10'!U66 -> 0 | K81: =J81/J$105 -> 0 | L81: =L80+K81 -> 0.99559471 | M81: =_xlfn.IFS(L81<80%,"A",L81<=95%,"B",L81>95%,"C") -> C
B82: MANNA2121 | C82: ='Юнит 10'!AO74 -> -110.9 | D82: =C82/C$105 -> -0.00016803304 | E82: =E81+D82 -> 1.0404714 | F82: =IF(AND(E82<=0),"C",IF(E82<=0.8,"A",IF(E82<=0.95,"B","C"))) -> C | G82: =VLOOKUP(B$4:B$104,I$4:M$104,5,0) -> C | I82: MANNA2115 | J82: ='Юнит 10'!U68 -> 0 | K82: =J82/J$105 -> 0 | L82: =L81+K82 -> 0.99559471 | M82: =_xlfn.IFS(L82<80%,"A",L82<=95%,"B",L82>95%,"C") -> C
B83: sh06 | C83: ='Юнит 10'!AO30 -> -116.07342 | D83: =C83/C$105 -> -0.00017587167 | E83: =E82+D83 -> 1.0402955 | F83: =IF(AND(E83<=0),"C",IF(E83<=0.8,"A",IF(E83<=0.95,"B","C"))) -> C | G83: =VLOOKUP(B$4:B$104,I$4:M$104,5,0) -> C | I83: MANNA2116 | J83: ='Юнит 10'!U69 -> 0 | K83: =J83/J$105 -> 0 | L83: =L82+K83 -> 0.99559471 | M83: =_xlfn.IFS(L83<80%,"A",L83<=95%,"B",L83>95%,"C") -> C
B84: YIMEI 2391 C1 | C84: ='Юнит 10'!AO98 -> -127.11098 | D84: =C84/C$105 -> -0.00019259553 | E84: =E83+D84 -> 1.0401029 | F84: =IF(AND(E84<=0),"C",IF(E84<=0.8,"A",IF(E84<=0.95,"B","C"))) -> C | G84: =VLOOKUP(B$4:B$104,I$4:M$104,5,0) -> C | I84: MANNA2117 | J84: ='Юнит 10'!U70 -> 0 | K84: =J84/J$105 -> 0 | L84: =L83+K84 -> 0.99559471 | M84: =_xlfn.IFS(L84<80%,"A",L84<=95%,"B",L84>95%,"C") -> C
B85: MANNA2108 | C85: ='Юнит 10'!AO61 -> -161.54983 | D85: =C85/C$105 -> -0.00024477645 | E85: =E84+D85 -> 1.0398581 | F85: =IF(AND(E85<=0),"C",IF(E85<=0.8,"A",IF(E85<=0.95,"B","C"))) -> C | G85: =VLOOKUP(B$4:B$104,I$4:M$104,5,0) -> C | I85: MANNA2118 | J85: ='Юнит 10'!U71 -> 0 | K85: =J85/J$105 -> 0 | L85: =L84+K85 -> 0.99559471 | M85: =_xlfn.IFS(L85<80%,"A",L85<=95%,"B",L85>95%,"C") -> C
B86: sh10 | C86: ='Юнит 10'!AO34 -> -195.3418 | D86: =C86/C$105 -> -0.00029597724 | E86: =E85+D86 -> 1.0395622 | F86: =IF(AND(E86<=0),"C",IF(E86<=0.8,"A",IF(E86<=0.95,"B","C"))) -> C | G86: =VLOOKUP(B$4:B$104,I$4:M$104,5,0) -> C | I86: MANNA2121 | J86: ='Юнит 10'!U74 -> 0 | K86: =J86/J$105 -> 0 | L86: =L85+K86 -> 0.99559471 | M86: =_xlfn.IFS(L86<80%,"A",L86<=95%,"B",L86>95%,"C") -> C
B87: MANNA2107 | C87: ='Юнит 10'!AO60 -> -210.80513 | D87: =C87/C$105 -> -0.00031940691 | E87: =E86+D87 -> 1.0392427 | F87: =IF(AND(E87<=0),"C",IF(E87<=0.8,"A",IF(E87<=0.95,"B","C"))) -> C | G87: =VLOOKUP(B$4:B$104,I$4:M$104,5,0) -> C | I87: Guangdu золото серая линза | J87: ='Юнит 10'!U79 -> 0 | K87: =J87/J$105 -> 0 | L87: =L86+K87 -> 0.99559471 | M87: =_xlfn.IFS(L87<80%,"A",L87<=95%,"B",L87>95%,"C") -> C
B88: Ли Сян ретро золото | C88: ='Юнит 10'!AO92 -> -261.55734 | D88: =C88/C$105 -> -0.00039630545 | E88: =E87+D88 -> 1.0388464 | F88: =IF(AND(E88<=0),"C",IF(E88<=0.8,"A",IF(E88<=0.95,"B","C"))) -> C | G88: =VLOOKUP(B$4:B$104,I$4:M$104,5,0) -> C | I88: Qianai черные | J88: ='Юнит 10'!U83 -> 0 | K88: =J88/J$105 -> 0 | L88: =L87+K88 -> 0.99559471 | M88: =_xlfn.IFS(L88<80%,"A",L88<=95%,"B",L88>95%,"C") -> C
B89: sh14 | C89: ='Юнит 10'!AO38 -> -352.85685 | D89: =C89/C$105 -> -0.00053464029 | E89: =E88+D89 -> 1.0383118 | F89: =IF(AND(E89<=0),"C",IF(E89<=0.8,"A",IF(E89<=0.95,"B","C"))) -> C | G89: =VLOOKUP(B$4:B$104,I$4:M$104,5,0) -> C | I89: Qianai коричневые | J89: ='Юнит 10'!U84 -> 0 | K89: =J89/J$105 -> 0 | L89: =L88+K89 -> 0.99559471 | M89: =_xlfn.IFS(L89<80%,"A",L89<=95%,"B",L89>95%,"C") -> C
B90: Guangdu золото серая линза | C90: ='Юнит 10'!AO79 -> -362.80051 | D90: =C90/C$105 -> -0.00054970669 | E90: =E89+D90 -> 1.0377621 | F90: =IF(AND(E90<=0),"C",IF(E90<=0.8,"A",IF(E90<=0.95,"B","C"))) -> C | G90: =VLOOKUP(B$4:B$104,I$4:M$104,5,0) -> C | I90: Linhai Baiyi коричневая линза | J90: ='Юнит 10'!U86 -> 0 | K90: =J90/J$105 -> 0 | L90: =L89+K90 -> 0.99559471 | M90: =_xlfn.IFS(L90<80%,"A",L90<=95%,"B",L90>95%,"C") -> C
B91: MANNA2120 | C91: ='Юнит 10'!AO73 -> -434.01035 | D91: =C91/C$105 -> -0.00065760214 | E91: =E90+D91 -> 1.0371045 | F91: =IF(AND(E91<=0),"C",IF(E91<=0.8,"A",IF(E91<=0.95,"B","C"))) -> C | G91: =VLOOKUP(B$4:B$104,I$4:M$104,5,0) -> C | I91: MR Р1894 черные | J91: ='Юнит 10'!U89 -> 0 | K91: =J91/J$105 -> 0 | L91: =L90+K91 -> 0.99559471 | M91: =_xlfn.IFS(L91<80%,"A",L91<=95%,"B",L91>95%,"C") -> C
B92: sh16 | C92: ='Юнит 10'!AO40 -> -440.3466 | D92: =C92/C$105 -> -0.00066720268 | E92: =E91+D92 -> 1.0364373 | F92: =IF(AND(E92<=0),"C",IF(E92<=0.8,"A",IF(E92<=0.95,"B","C"))) -> C | G92: =VLOOKUP(B$4:B$104,I$4:M$104,5,0) -> C | I92: Taizhou Rayen sport розовый | J92: ='Юнит 10'!U90 -> 0 | K92: =J92/J$105 -> 0 | L92: =L91+K92 -> 0.99559471 | M92: =_xlfn.IFS(L92<80%,"A",L92<=95%,"B",L92>95%,"C") -> C
B93: Hengda Optical черные | C93: ='Юнит 10'!AO81 -> -471.77429 | D93: =C93/C$105 -> -0.00071482116 | E93: =E92+D93 -> 1.0357225 | F93: =IF(AND(E93<=0),"C",IF(E93<=0.8,"A",IF(E93<=0.95,"B","C"))) -> C | G93: =VLOOKUP(B$4:B$104,I$4:M$104,5,0) -> C | I93: Иу Диту серый | J93: ='Юнит 10'!U91 -> 0 | K93: =J93/J$105 -> 0 | L93: =L92+K93 -> 0.99559471 | M93: =_xlfn.IFS(L93<80%,"A",L93<=95%,"B",L93>95%,"C") -> C
B94: Иу Диту серый | C94: ='Юнит 10'!AO91 -> -496.03245 | D94: =C94/C$105 -> -0.00075157656 | E94: =E93+D94 -> 1.0349709 | F94: =IF(AND(E94<=0),"C",IF(E94<=0.8,"A",IF(E94<=0.95,"B","C"))) -> C | G94: =VLOOKUP(B$4:B$104,I$4:M$104,5,0) -> C | I94: Ли Сян ретро золото | J94: ='Юнит 10'!U92 -> 0 | K94: =J94/J$105 -> 0 | L94: =L93+K94 -> 0.99559471 | M94: =_xlfn.IFS(L94<80%,"A",L94<=95%,"B",L94>95%,"C") -> C
B95: Qianai черные | C95: ='Юнит 10'!AO83 -> -538.70709 | D95: =C95/C$105 -> -0.00081623616 | E95: =E94+D95 -> 1.0341547 | F95: =IF(AND(E95<=0),"C",IF(E95<=0.8,"A",IF(E95<=0.95,"B","C"))) -> C | G95: =VLOOKUP(B$4:B$104,I$4:M$104,5,0) -> C | I95: MAIERSHA 03898 C9-08 | J95: ='Юнит 10'!U94 -> 0 | K95: =J95/J$105 -> 0 | L95: =L94+K95 -> 0.99559471 | M95: =_xlfn.IFS(L95<80%,"A",L95<=95%,"B",L95>95%,"C") -> C
B96: sh09 | C96: ='Юнит 10'!AO33 -> -609.09482 | D96: =C96/C$105 -> -0.00092288596 | E96: =E95+D96 -> 1.0332318 | F96: =IF(AND(E96<=0),"C",IF(E96<=0.8,"A",IF(E96<=0.95,"B","C"))) -> C | G96: =VLOOKUP(B$4:B$104,I$4:M$104,5,0) -> C | I96: MAIERSHA 03914 C9-124 | J96: ='Юнит 10'!U95 -> 0 | K96: =J96/J$105 -> 0 | L96: =L95+K96 -> 0.99559471 | M96: =_xlfn.IFS(L96<80%,"A",L96<=95%,"B",L96>95%,"C") -> C
B97: MANNA2118 | C97: ='Юнит 10'!AO71 -> -724.68683 | D97: =C97/C$105 -> -0.0010980282 | E97: =E96+D97 -> 1.0321337 | F97: =IF(AND(E97<=0),"C",IF(E97<=0.8,"A",IF(E97<=0.95,"B","C"))) -> C | G97: =VLOOKUP(B$4:B$104,I$4:M$104,5,0) -> C | I97: MARSTON 7171 C1 | J97: ='Юнит 10'!U96 -> 0 | K97: =J97/J$105 -> 0 | L97: =L96+K97 -> 0.99559471 | M97: =_xlfn.IFS(L97<80%,"A",L97<=95%,"B",L97>95%,"C") -> C
B98: Chenlong белые | C98: ='Юнит 10'!AO78 -> -726.12724 | D98: =C98/C$105 -> -0.0011002107 | E98: =E97+D98 -> 1.0310335 | F98: =IF(AND(E98<=0),"C",IF(E98<=0.8,"A",IF(E98<=0.95,"B","C"))) -> C | G98: =VLOOKUP(B$4:B$104,I$4:M$104,5,0) -> C | I98: POMILED 08247 C4-08 | J98: ='Юнит 10'!U97 -> 0 | K98: =J98/J$105 -> 0 | L98: =L97+K98 -> 0.99559471 | M98: =_xlfn.IFS(L98<80%,"A",L98<=95%,"B",L98>95%,"C") -> C
B99: MANNA2105 | C99: ='Юнит 10'!AO58 -> -1477.0687 | D99: =C99/C$105 -> -0.0022380193 | E99: =E93+D99 -> 1.0334844 | F99: =IF(AND(E99<=0),"C",IF(E99<=0.8,"A",IF(E99<=0.95,"B","C"))) -> C | G99: =VLOOKUP(B$4:B$104,I$4:M$104,5,0) -> C | I99: YIMEI 2391 C1 | J99: ='Юнит 10'!U98 -> 0 | K99: =J99/J$105 -> 0 | L99: =L93+K99 -> 0.99559471 | M99: =_xlfn.IFS(L99<80%,"A",L99<=95%,"B",L99>95%,"C") -> C
B100: sh15 | C100: ='Юнит 10'!AO39 -> -1657.7054 | D100: =C100/C$105 -> -0.0025117157 | E100: =E94+D100 -> 1.0324592 | F100: =IF(AND(E100<=0),"C",IF(E100<=0.8,"A",IF(E100<=0.95,"B","C"))) -> C | G100: =VLOOKUP(B$4:B$104,I$4:M$104,5,0) -> C | I100: ЧСЖ_тест | J100: ='Юнит 10'!U99 -> 0 | K100: =J100/J$105 -> 0 | L100: =L94+K100 -> 0.99559471 | M100: =_xlfn.IFS(L100<80%,"A",L100<=95%,"B",L100>95%,"C") -> C
B101: ЧСЖ_женские | C101: ='Юнит 10'!AO100 -> -3367.1537 | D101: =C101/C$105 -> -0.005101831 | E101: =E95+D101 -> 1.0290528 | F101: =IF(AND(E101<=0),"C",IF(E101<=0.8,"A",IF(E101<=0.95,"B","C"))) -> C | G101: =VLOOKUP(B$4:B$104,I$4:M$104,5,0) -> C | I101: ЧСЖ_женские | J101: ='Юнит 10'!U100 -> 0 | K101: =J101/J$105 -> 0 | L101: =L95+K101 -> 0.99559471 | M101: =_xlfn.IFS(L101<80%,"A",L101<=95%,"B",L101>95%,"C") -> C
...

Sheet АВС ФЕВРАЛЬ
B2: ОЧКИ
C3: Прибыль | D3: % прибыль | E3: Доля | F3: ABC прибыль | G3: ABC кол-во | J3: Кол-во | K3: % кол-во | L3: Доля | M3: ABC кол-во
B4: QS черные PZ | C4: =ФЕВРАЛЬ!AO4 -> 642368.96 | D4: =C4/C$105 -> 0.33116882 | E4: =D4 -> 0.33116882 | F4: =IF(AND(E4<=0),"C",IF(E4<=0.8,"A",IF(E4<=0.95,"B","C"))) -> A | G4: =VLOOKUP(B$4:B$104,I$4:M$104,5,0) -> A | I4: QS черные PZ | J4: =ФЕВРАЛЬ!U4 -> 1939 | K4: =J4/J$105 -> 0.24871729 | L4: =K4 -> 0.24871729 | M4: =_xlfn.IFS(L4<80%,"A",L4<=95%,"B",L4>95%,"C") -> A | P4: A | Q4: 0.8
B5: QS коричневые PZ | C5: =ФЕВРАЛЬ!AO7 -> 190633.28 | D5: =C5/C$105 -> 0.098279652 | E5: =E4+D5 -> 0.42944847 | F5: =IF(AND(E5<=0),"C",IF(E5<=0.8,"A",IF(E5<=0.95,"B","C"))) -> A | G5: =VLOOKUP(B$4:B$104,I$4:M$104,5,0) -> A | I5: QS коричневые PZ | J5: =ФЕВРАЛЬ!U7 -> 624 | K5: =J5/J$105 -> 0.080041047 | L5: =L4+K5 -> 0.32875834 | M5: =_xlfn.IFS(L5<80%,"A",L5<=95%,"B",L5>95%,"C") -> A | P5: B | Q5: 0.15
B6: QS синие PZ | C6: =ФЕВРАЛЬ!AO5 -> 159526.52 | D6: =C6/C$105 -> 0.082242778 | E6: =E5+D6 -> 0.51169125 | F6: =IF(AND(E6<=0),"C",IF(E6<=0.8,"A",IF(E6<=0.95,"B","C"))) -> A | G6: =VLOOKUP(B$4:B$104,I$4:M$104,5,0) -> A | I6: th син | J6: =ФЕВРАЛЬ!U10 -> 561 | K6: =J6/J$105 -> 0.071959979 | L6: =L5+K6 -> 0.40071832 | M6: =_xlfn.IFS(L6<80%,"A",L6<=95%,"B",L6>95%,"C") -> A | P6: C | Q6: 0.05
B7: th черн | C7: =ФЕВРАЛЬ!AO9 -> 152793.99 | D7: =C7/C$105 -> 0.078771871 | E7: =E6+D7 -> 0.59046312 | F7: =IF(AND(E7<=0),"C",IF(E7<=0.8,"A",IF(E7<=0.95,"B","C"))) -> A | G7: =VLOOKUP(B$4:B$104,I$4:M$104,5,0) -> A | I7: QS синие PZ | J7: =ФЕВРАЛЬ!U5 -> 518 | K7: =J7/J$105 -> 0.06644433 | L7: =L6+K7 -> 0.46716265 | M7: =_xlfn.IFS(L7<80%,"A",L7<=95%,"B",L7>95%,"C") -> A
B8: QS желтые PZ | C8: =ФЕВРАЛЬ!AO6 -> 118776.15 | D8: =C8/C$105 -> 0.061234211 | E8: =E7+D8 -> 0.65169733 | F8: =IF(AND(E8<=0),"C",IF(E8<=0.8,"A",IF(E8<=0.95,"B","C"))) -> A | G8: =VLOOKUP(B$4:B$104,I$4:M$104,5,0) -> A | I8: th черн | J8: =ФЕВРАЛЬ!U9 -> 484 | K8: =J8/J$105 -> 0.06208312 | L8: =L7+K8 -> 0.52924577 | M8: =_xlfn.IFS(L8<80%,"A",L8<=95%,"B",L8>95%,"C") -> A
B9: th син | C9: =ФЕВРАЛЬ!AO10 -> 105223.82 | D9: =C9/C$105 -> 0.054247404 | E9: =E8+D9 -> 0.70594473 | F9: =IF(AND(E9<=0),"C",IF(E9<=0.8,"A",IF(E9<=0.95,"B","C"))) -> A | G9: =VLOOKUP(B$4:B$104,I$4:M$104,5,0) -> A | I9: QS желтые PZ | J9: =ФЕВРАЛЬ!U6 -> 441 | K9: =J9/J$105 -> 0.05656747 | L9: =L8+K9 -> 0.58581324 | M9: =_xlfn.IFS(L9<80%,"A",L9<=95%,"B",L9>95%,"C") -> A
B10: flip коричневые | C10: =ФЕВРАЛЬ!AO16 -> 75909.184 | D10: =C10/C$105 -> 0.039134448 | E10: =E9+D10 -> 0.74507918 | F10: =IF(AND(E10<=0),"C",IF(E10<=0.8,"A",IF(E10<=0.95,"B","C"))) -> A | G10: =VLOOKUP(B$4:B$104,I$4:M$104,5,0) -> A | I10: черные с железкой классика | J10: =ФЕВРАЛЬ!U3 -> 322 | K10: =J10/J$105 -> 0.041303232 | L10: =L9+K10 -> 0.62711647 | M10: =_xlfn.IFS(L10<80%,"A",L10<=95%,"B",L10>95%,"C") -> A
B11: flip черные | C11: =ФЕВРАЛЬ!AO13 -> 75644.626 | D11: =C11/C$105 -> 0.038998057 | E11: =E10+D11 -> 0.78407724 | F11: =IF(AND(E11<=0),"C",IF(E11<=0.8,"A",IF(E11<=0.95,"B","C"))) -> A | G11: =VLOOKUP(B$4:B$104,I$4:M$104,5,0) -> A | I11: sh3 | J11: =ФЕВРАЛЬ!U28 -> 317 | K11: =J11/J$105 -> 0.040661878 | L11: =L10+K11 -> 0.66777835 | M11: =_xlfn.IFS(L11<80%,"A",L11<=95%,"B",L11>95%,"C") -> A
B12: th коричн | C12: =ФЕВРАЛЬ!AO12 -> 68395.947 | D12: =C12/C$105 -> 0.035261051 | E12: =E11+D12 -> 0.81933829 | F12: =IF(AND(E12<=0),"C",IF(E12<=0.8,"A",IF(E12<=0.95,"B","C"))) -> B | G12: =VLOOKUP(B$4:B$104,I$4:M$104,5,0) -> A | I12: flip коричневые | J12: =ФЕВРАЛЬ!U16 -> 301 | K12: =J12/J$105 -> 0.038609543 | L12: =L11+K12 -> 0.70638789 | M12: =_xlfn.IFS(L12<80%,"A",L12<=95%,"B",L12>95%,"C") -> A
B13: th желт | C13: =ФЕВРАЛЬ!AO11 -> 66228.169 | D13: =C13/C$105 -> 0.034143468 | E13: =E12+D13 -> 0.85348176 | F13: =IF(AND(E13<=0),"C",IF(E13<=0.8,"A",IF(E13<=0.95,"B","C"))) -> B | G13: =VLOOKUP(B$4:B$104,I$4:M$104,5,0) -> B | I13: flip черные | J13: =ФЕВРАЛЬ!U13 -> 291 | K13: =J13/J$105 -> 0.037326834 | L13: =L12+K13 -> 0.74371473 | M13: =_xlfn.IFS(L13<80%,"A",L13<=95%,"B",L13>95%,"C") -> A
B14: MR8854 C2 Жен | C14: =ФЕВРАЛЬ!AO8 -> 55608.539 | D14: =C14/C$105 -> 0.028668593 | E14: =E13+D14 -> 0.88215035 | F14: =IF(AND(E14<=0),"C",IF(E14<=0.8,"A",IF(E14<=0.95,"B","C"))) -> B | G14: =VLOOKUP(B$4:B$104,I$4:M$104,5,0) -> B | I14: th коричн | J14: =ФЕВРАЛЬ!U12 -> 257 | K14: =J14/J$105 -> 0.032965623 | L14: =L13+K14 -> 0.77668035 | M14: =_xlfn.IFS(L14<80%,"A",L14<=95%,"B",L14>95%,"C") -> A
B15: черные с железкой классика | C15: =ФЕВРАЛЬ!AO3 -> 53885.692 | D15: =C15/C$105 -> 0.027780391 | E15: =E14+D15 -> 0.90993074 | F15: =IF(AND(E15<=0),"C",IF(E15<=0.8,"A",IF(E15<=0.95,"B","C"))) -> B | G15: =VLOOKUP(B$4:B$104,I$4:M$104,5,0) -> A | I15: MR8854 C2 Жен | J15: =ФЕВРАЛЬ!U8 -> 239 | K15: =J15/J$105 -> 0.030656747 | L15: =L14+K15 -> 0.8073371 | M15: =_xlfn.IFS(L15<80%,"A",L15<=95%,"B",L15>95%,"C") -> B
B16: sh3 | C16: =ФЕВРАЛЬ!AO28 -> 53582.58 | D16: =C16/C$105 -> 0.027624124 | E16: =E15+D16 -> 0.93755486 | F16: =IF(AND(E16<=0),"C",IF(E16<=0.8,"A",IF(E16<=0.95,"B","C"))) -> B | G16: =VLOOKUP(B$4:B$104,I$4:M$104,5,0) -> A | I16: th желт | J16: =ФЕВРАЛЬ!U11 -> 199 | K16: =J16/J$105 -> 0.025525911 | L16: =L15+K16 -> 0.83286301 | M16: =_xlfn.IFS(L16<80%,"A",L16<=95%,"B",L16>95%,"C") -> B
B17: wwl8032 хром металл | C17: =ФЕВРАЛЬ!AO18 -> 37501.645 | D17: =C17/C$105 -> 0.01933371 | E17: =E16+D17 -> 0.95688857 | F17: =IF(AND(E17<=0),"C",IF(E17<=0.8,"A",IF(E17<=0.95,"B","C"))) -> C | G17: =VLOOKUP(B$4:B$104,I$4:M$104,5,0) -> B | I17: ww 1022 черные | J17: =ФЕВРАЛЬ!U45 -> 164 | K17: =J17/J$105 -> 0.021036429 | L17: =L16+K17 -> 0.85389944 | M17: =_xlfn.IFS(L17<80%,"A",L17<=95%,"B",L17>95%,"C") -> B
B18: flip синие | C18: =ФЕВРАЛЬ!AO14 -> 27016.185 | D18: =C18/C$105 -> 0.013928005 | E18: =E17+D18 -> 0.97081658 | F18: =IF(AND(E18<=0),"C",IF(E18<=0.8,"A",IF(E18<=0.95,"B","C"))) -> C | G18: =VLOOKUP(B$4:B$104,I$4:M$104,5,0) -> B | I18: wwl8032 хром металл | J18: =ФЕВРАЛЬ!U18 -> 138 | K18: =J18/J$105 -> 0.017701385 | L18: =L17+K18 -> 0.87160082 | M18: =_xlfn.IFS(L18<80%,"A",L18<=95%,"B",L18>95%,"C") -> B
B19: flip желтые | C19: =ФЕВРАЛЬ!AO15 -> 23950.997 | D19: =C19/C$105 -> 0.012347769 | E19: =E18+D19 -> 0.98316435 | F19: =IF(AND(E19<=0),"C",IF(E19<=0.8,"A",IF(E19<=0.95,"B","C"))) -> C | G19: =VLOOKUP(B$4:B$104,I$4:M$104,5,0) -> B | I19: flip синие | J19: =ФЕВРАЛЬ!U14 -> 129 | K19: =J19/J$105 -> 0.016546947 | L19: =L18+K19 -> 0.88814777 | M19: =_xlfn.IFS(L19<80%,"A",L19<=95%,"B",L19>95%,"C") -> B
B20: wwl8032 коричневые золото | C20: =ФЕВРАЛЬ!AO17 -> 21576.891 | D20: =C20/C$105 -> 0.011123815 | E20: =E19+D20 -> 0.99428816 | F20: =IF(AND(E20<=0),"C",IF(E20<=0.8,"A",IF(E20<=0.95,"B","C"))) -> C | G20: =VLOOKUP(B$4:B$104,I$4:M$104,5,0) -> C | I20: sh1 | J20: =ФЕВРАЛЬ!U26 -> 113 | K20: =J20/J$105 -> 0.014494613 | L20: =L19+K20 -> 0.90264238 | M20: =_xlfn.IFS(L20<80%,"A",L20<=95%,"B",L20>95%,"C") -> B
B21: ww 2018 черные | C21: =ФЕВРАЛЬ!AO49 -> 21492.411 | D21: =C21/C$105 -> 0.011080262 | E21: =E20+D21 -> 1.0053684 | F21: =IF(AND(E21<=0),"C",IF(E21<=0.8,"A",IF(E21<=0.95,"B","C"))) -> C | G21: =VLOOKUP(B$4:B$104,I$4:M$104,5,0) -> B | I21: ww 2018 черные | J21: =ФЕВРАЛЬ!U49 -> 110 | K21: =J21/J$105 -> 0.0141098 | L21: =L20+K21 -> 0.91675218 | M21: =_xlfn.IFS(L21<80%,"A",L21<=95%,"B",L21>95%,"C") -> B
B22: ww 1022 коричневые | C22: =ФЕВРАЛЬ!AO48 -> 21473.242 | D22: =C22/C$105 -> 0.011070379 | E22: =E21+D22 -> 1.0164388 | F22: =IF(AND(E22<=0),"C",IF(E22<=0.8,"A",IF(E22<=0.95,"B","C"))) -> C | G22: =VLOOKUP(B$4:B$104,I$4:M$104,5,0) -> B | I22: flip желтые | J22: =ФЕВРАЛЬ!U15 -> 106 | K22: =J22/J$105 -> 0.013596716 | L22: =L21+K22 -> 0.9303489 | M22: =_xlfn.IFS(L22<80%,"A",L22<=95%,"B",L22>95%,"C") -> B
B23: ww 1022 желтые | C23: =ФЕВРАЛЬ!AO47 -> 14505.736 | D23: =C23/C$105 -> 0.0074783305 | E23: =E22+D23 -> 1.0239171 | F23: =IF(AND(E23<=0),"C",IF(E23<=0.8,"A",IF(E23<=0.95,"B","C"))) -> C | G23: =VLOOKUP(B$4:B$104,I$4:M$104,5,0) -> C | I23: ww 1022 коричневые | J23: =ФЕВРАЛЬ!U48 -> 97 | K23: =J23/J$105 -> 0.012442278 | L23: =L22+K23 -> 0.94279117 | M23: =_xlfn.IFS(L23<80%,"A",L23<=95%,"B",L23>95%,"C") -> B
B24: ww 1022 черные | C24: =ФЕВРАЛЬ!AO45 -> 9240.4663 | D24: =C24/C$105 -> 0.0047638576 | E24: =E23+D24 -> 1.028681 | F24: =IF(AND(E24<=0),"C",IF(E24<=0.8,"A",IF(E24<=0.95,"B","C"))) -> C | G24: =VLOOKUP(B$4:B$104,I$4:M$104,5,0) -> B | I24: wwl8032 коричневые золото | J24: =ФЕВРАЛЬ!U17 -> 82 | K24: =J24/J$105 -> 0.010518214 | L24: =L23+K24 -> 0.95330939 | M24: =_xlfn.IFS(L24<80%,"A",L24<=95%,"B",L24>95%,"C") -> C
B25: ww 203 черные | C25: =ФЕВРАЛЬ!AO44 -> 5282.3881 | D25: =C25/C$105 -> 0.0027232982 | E25: =E24+D25 -> 1.0314043 | F25: =IF(AND(E25<=0),"C",IF(E25<=0.8,"A",IF(E25<=0.95,"B","C"))) -> C | G25: =VLOOKUP(B$4:B$104,I$4:M$104,5,0) -> C | I25: ww 1022 желтые | J25: =ФЕВРАЛЬ!U47 -> 43 | K25: =J25/J$105 -> 0.0055156491 | L25: =L24+K25 -> 0.95882504 | M25: =_xlfn.IFS(L25<80%,"A",L25<=95%,"B",L25>95%,"C") -> C
B26: MR Р1894 черные | C26: =ФЕВРАЛЬ!AO89 -> 4767.6174 | D26: =C26/C$105 -> 0.0024579117 | E26: =E25+D26 -> 1.0338622 | F26: =IF(AND(E26<=0),"C",IF(E26<=0.8,"A",IF(E26<=0.95,"B","C"))) -> C | G26: =VLOOKUP(B$4:B$104,I$4:M$104,5,0) -> C | I26: ww 2018 желтые | J26: =ФЕВРАЛЬ!U50 -> 41 | K26: =J26/J$105 -> 0.0052591072 | L26: =L25+K26 -> 0.96408415 | M26: =_xlfn.IFS(L26<80%,"A",L26<=95%,"B",L26>95%,"C") -> C
B27: sportlife красные | C27: =ФЕВРАЛЬ!AO25 -> 2306.3503 | D27: =C27/C$105 -> 0.0011890227 | E27: =E26+D27 -> 1.0350512 | F27: =IF(AND(E27<=0),"C",IF(E27<=0.8,"A",IF(E27<=0.95,"B","C"))) -> C | G27: =VLOOKUP(B$4:B$104,I$4:M$104,5,0) -> C | I27: ww 203 черные | J27: =ФЕВРАЛЬ!U44 -> 40 | K27: =J27/J$105 -> 0.0051308363 | L27: =L26+K27 -> 0.96921498 | M27: =_xlfn.IFS(L27<80%,"A",L27<=95%,"B",L27>95%,"C") -> C
B28: MANNA2101 | C28: =ФЕВРАЛЬ!AO54 -> 2041.9045 | D28: =C28/C$105 -> 0.0010526896 | E28: =E27+D28 -> 1.0361039 | F28: =IF(AND(E28<=0),"C",IF(E28<=0.8,"A",IF(E28<=0.95,"B","C"))) -> C | G28: =VLOOKUP(B$4:B$104,I$4:M$104,5,0) -> C | I28: sh2 | J28: =ФЕВРАЛЬ!U27 -> 28 | K28: =J28/J$105 -> 0.0035915854 | L28: =L27+K28 -> 0.97280657 | M28: =_xlfn.IFS(L28<80%,"A",L28<=95%,"B",L28>95%,"C") -> C
B29: Linhai Baiyi розовая линза | C29: =ФЕВРАЛЬ!AO88 -> 1953.1918 | D29: =C29/C$105 -> 0.0010069543 | E29: =E28+D29 -> 1.0371109 | F29: =IF(AND(E29<=0),"C",IF(E29<=0.8,"A",IF(E29<=0.95,"B","C"))) -> C | G29: =VLOOKUP(B$4:B$104,I$4:M$104,5,0) -> C | I29: sh10 | J29: =ФЕВРАЛЬ!U34 -> 21 | K29: =J29/J$105 -> 0.0026936891 | L29: =L28+K29 -> 0.97550026 | M29: =_xlfn.IFS(L29<80%,"A",L29<=95%,"B",L29>95%,"C") -> C
B30: sh13 | C30: =ФЕВРАЛЬ!AO37 -> 1856.3228 | D30: =C30/C$105 -> 0.00095701421 | E30: =E29+D30 -> 1.0380679 | F30: =IF(AND(E30<=0),"C",IF(E30<=0.8,"A",IF(E30<=0.95,"B","C"))) -> C | G30: =VLOOKUP(B$4:B$104,I$4:M$104,5,0) -> C | I30: sh09 | J30: =ФЕВРАЛЬ!U33 -> 17 | K30: =J30/J$105 -> 0.0021806054 | L30: =L29+K30 -> 0.97768086 | M30: =_xlfn.IFS(L30<80%,"A",L30<=95%,"B",L30>95%,"C") -> C
B31: MANNA2114 | C31: =ФЕВРАЛЬ!AO67 -> 1839.0117 | D31: =C31/C$105 -> 0.0009480896 | E31: =E30+D31 -> 1.039016 | F31: =IF(AND(E31<=0),"C",IF(E31<=0.8,"A",IF(E31<=0.95,"B","C"))) -> C | G31: =VLOOKUP(B$4:B$104,I$4:M$104,5,0) -> C | I31: Hengda Optical черные | J31: =ФЕВРАЛЬ!U81 -> 16 | K31: =J31/J$105 -> 0.0020523345 | L31: =L30+K31 -> 0.9797332 | M31: =_xlfn.IFS(L31<80%,"A",L31<=95%,"B",L31>95%,"C") -> C
B32: Linhai Baiyi коричневая линза | C32: =ФЕВРАЛЬ!AO86 -> 1106.7935 | D32: =C32/C$105 -> 0.00057059963 | E32: =E31+D32 -> 1.0395866 | F32: =IF(AND(E32<=0),"C",IF(E32<=0.8,"A",IF(E32<=0.95,"B","C"))) -> C | G32: =VLOOKUP(B$4:B$104,I$4:M$104,5,0) -> C | I32: Linhai Baiyi розовая линза | J32: =ФЕВРАЛЬ!U88 -> 15 | K32: =J32/J$105 -> 0.0019240636 | L32: =L31+K32 -> 0.98165726 | M32: =_xlfn.IFS(L32<80%,"A",L32<=95%,"B",L32>95%,"C") -> C
B33: sh10 | C33: =ФЕВРАЛЬ!AO34 -> 1064.1466 | D33: =C33/C$105 -> 0.0005486133 | E33: =E32+D33 -> 1.0401352 | F33: =IF(AND(E33<=0),"C",IF(E33<=0.8,"A",IF(E33<=0.95,"B","C"))) -> C | G33: =VLOOKUP(B$4:B$104,I$4:M$104,5,0) -> C | I33: sh15 | J33: =ФЕВРАЛЬ!U39 -> 11 | K33: =J33/J$105 -> 0.00141098 | L33: =L32+K33 -> 0.98306824 | M33: =_xlfn.IFS(L33<80%,"A",L33<=95%,"B",L33>95%,"C") -> C
B34: Chenlong белые | C34: =ФЕВРАЛЬ!AO78 -> 988.7629 | D34: =C34/C$105 -> 0.00050974978 | E34: =E33+D34 -> 1.0406449 | F34: =IF(AND(E34<=0),"C",IF(E34<=0.8,"A",IF(E34<=0.95,"B","C"))) -> C | G34: =VLOOKUP(B$4:B$104,I$4:M$104,5,0) -> C | I34: ww 8010 черные | J34: =ФЕВРАЛЬ!U51 -> 10 | K34: =J34/J$105 -> 0.0012827091 | L34: =L33+K34 -> 0.98435095 | M34: =_xlfn.IFS(L34<80%,"A",L34<=95%,"B",L34>95%,"C") -> C
B35: Qianai черные | C35: =ФЕВРАЛЬ!AO83 -> 947.5993 | D35: =C35/C$105 -> 0.00048852818 | E35: =E34+D35 -> 1.0411335 | F35: =IF(AND(E35<=0),"C",IF(E35<=0.8,"A",IF(E35<=0.95,"B","C"))) -> C | G35: =VLOOKUP(B$4:B$104,I$4:M$104,5,0) -> C | I35: MANNA2105 | J35: =ФЕВРАЛЬ!U58 -> 9 | K35: =J35/J$105 -> 0.0011544382 | L35: =L34+K35 -> 0.98550539 | M35: =_xlfn.IFS(L35<80%,"A",L35<=95%,"B",L35>95%,"C") -> C
B36: ww 2018 желтые | C36: =ФЕВРАЛЬ!AO50 -> 672.35848 | D36: =C36/C$105 -> 0.0003466297 | E36: =E35+D36 -> 1.0414801 | F36: =IF(AND(E36<=0),"C",IF(E36<=0.8,"A",IF(E36<=0.95,"B","C"))) -> C | G36: =VLOOKUP(B$4:B$104,I$4:M$104,5,0) -> C | I36: sh13 | J36: =ФЕВРАЛЬ!U37 -> 8 | K36: =J36/J$105 -> 0.0010261673 | L36: =L35+K36 -> 0.98653155 | M36: =_xlfn.IFS(L36<80%,"A",L36<=95%,"B",L36>95%,"C") -> C
B37: sh18 | C37: =ФЕВРАЛЬ!AO42 -> 649.0966 | D37: =C37/C$105 -> 0.0003346372 | E37: =E36+D37 -> 1.0418147 | F37: =IF(AND(E37<=0),"C",IF(E37<=0.8,"A",IF(E37<=0.95,"B","C"))) -> C | G37: =VLOOKUP(B$4:B$104,I$4:M$104,5,0) -> C | I37: MR Р1894 черные | J37: =ФЕВРАЛЬ!U89 -> 8 | K37: =J37/J$105 -> 0.0010261673 | L37: =L36+K37 -> 0.98755772 | M37: =_xlfn.IFS(L37<80%,"A",L37<=95%,"B",L37>95%,"C") -> C
B38: кс_черные_тест | C38: =ФЕВРАЛЬ!AO101 -> 617.01293 | D38: =C38/C$105 -> 0.00031809669 | E38: =E37+D38 -> 1.0421328 | F38: =IF(AND(E38<=0),"C",IF(E38<=0.8,"A",IF(E38<=0.95,"B","C"))) -> C | G38: =VLOOKUP(B$4:B$104,I$4:M$104,5,0) -> C | I38: sportlife красные | J38: =ФЕВРАЛЬ!U25 -> 7 | K38: =J38/J$105 -> 0.00089789636 | L38: =L37+K38 -> 0.98845562 | M38: =_xlfn.IFS(L38<80%,"A",L38<=95%,"B",L38>95%,"C") -> C
B39: MAIERSHA 03914 C9-124 | C39: =ФЕВРАЛЬ!AO95 -> 546.1425 | D39: =C39/C$105 -> 0.00028155994 | E39: =E35+D39 -> 1.041415 | F39: =IF(AND(E39<=0),"C",IF(E39<=0.8,"A",IF(E39<=0.95,"B","C"))) -> C | G39: =VLOOKUP(B$4:B$104,I$4:M$104,5,0) -> C | I39: sh19 | J39: =ФЕВРАЛЬ!U43 -> 7 | K39: =J39/J$105 -> 0.00089789636 | L39: =L35+K39 -> 0.98640328 | M39: =_xlfn.IFS(L39<80%,"A",L39<=95%,"B",L39>95%,"C") -> C
B40: WW 3055 коричневый | C40: =ФЕВРАЛЬ!AO53 -> 488.0881 | D40: =C40/C$105 -> 0.0002516304 | E40: =E39+D40 -> 1.0416667 | F40: =IF(AND(E40<=0),"C",IF(E40<=0.8,"A",IF(E40<=0.95,"B","C"))) -> C | G40: =VLOOKUP(B$4:B$104,I$4:M$104,5,0) -> C | I40: MANNA2101 | J40: =ФЕВРАЛЬ!U54 -> 7 | K40: =J40/J$105 -> 0.00089789636 | L40: =L39+K40 -> 0.98730118 | M40: =_xlfn.IFS(L40<80%,"A",L40<=95%,"B",L40>95%,"C") -> C
B41: MANNA2117 | C41: =ФЕВРАЛЬ!AO70 -> 407.9103 | D41: =C41/C$105 -> 0.0002102953 | E41: =E40+D41 -> 1.0418769 | F41: =IF(AND(E41<=0),"C",IF(E41<=0.8,"A",IF(E41<=0.95,"B","C"))) -> C | G41: =VLOOKUP(B$4:B$104,I$4:M$104,5,0) -> C | I41: MANNA2120 | J41: =ФЕВРАЛЬ!U73 -> 7 | K41: =J41/J$105 -> 0.00089789636 | L41: =L40+K41 -> 0.98819908 | M41: =_xlfn.IFS(L41<80%,"A",L41<=95%,"B",L41>95%,"C") -> C
B42: Hengda Optical леопард | C42: =ФЕВРАЛЬ!AO82 -> 398.4729 | D42: =C42/C$105 -> 0.00020542991 | E42: =E41+D42 -> 1.0420824 | F42: =IF(AND(E42<=0),"C",IF(E42<=0.8,"A",IF(E42<=0.95,"B","C"))) -> C | G42: =VLOOKUP(B$4:B$104,I$4:M$104,5,0) -> C | I42: MANNA2114 | J42: =ФЕВРАЛЬ!U67 -> 6 | K42: =J42/J$105 -> 0.00076962545 | L42: =L41+K42 -> 0.9889687 | M42: =_xlfn.IFS(L42<80%,"A",L42<=95%,"B",L42>95%,"C") -> C
B43: sports красные | C43: =ФЕВРАЛЬ!AO22 -> 355.0782 | D43: =C43/C$105 -> 0.00018305808 | E43: =E42+D43 -> 1.0422654 | F43: =IF(AND(E43<=0),"C",IF(E43<=0.8,"A",IF(E43<=0.95,"B","C"))) -> C | G43: =VLOOKUP(B$4:B$104,I$4:M$104,5,0) -> C | I43: MANNA2119 | J43: =ФЕВРАЛЬ!U72 -> 6 | K43: =J43/J$105 -> 0.00076962545 | L43: =L42+K43 -> 0.98973833 | M43: =_xlfn.IFS(L43<80%,"A",L43<=95%,"B",L43>95%,"C") -> C
B44: sh4 | C44: =ФЕВРАЛЬ!AO29 -> 337.5817 | D44: =C44/C$105 -> 0.00017403788 | E44: =E43+D44 -> 1.0424395 | F44: =IF(AND(E44<=0),"C",IF(E44<=0.8,"A",IF(E44<=0.95,"B","C"))) -> C | G44: =VLOOKUP(B$4:B$104,I$4:M$104,5,0) -> C | I44: Guangdu серебро серая линза | J44: =ФЕВРАЛЬ!U80 -> 6 | K44: =J44/J$105 -> 0.00076962545 | L44: =L43+K44 -> 0.99050795 | M44: =_xlfn.IFS(L44<80%,"A",L44<=95%,"B",L44>95%,"C") -> C
B45: sh17 | C45: =ФЕВРАЛЬ!AO41 -> 316.3125 | D45: =C45/C$105 -> 0.00016307269 | E45: =E44+D45 -> 1.0426025 | F45: =IF(AND(E45<=0),"C",IF(E45<=0.8,"A",IF(E45<=0.95,"B","C"))) -> C | G45: =VLOOKUP(B$4:B$104,I$4:M$104,5,0) -> C | I45: MANNA2118 | J45: =ФЕВРАЛЬ!U71 -> 5 | K45: =J45/J$105 -> 0.00064135454 | L45: =L44+K45 -> 0.99114931 | M45: =_xlfn.IFS(L45<80%,"A",L45<=95%,"B",L45>95%,"C") -> C
B46: MANNA2120 | C46: =ФЕВРАЛЬ!AO73 -> 265.4711 | D46: =C46/C$105 -> 0.00013686177 | E46: =E45+D46 -> 1.0427394 | F46: =IF(AND(E46<=0),"C",IF(E46<=0.8,"A",IF(E46<=0.95,"B","C"))) -> C | G46: =VLOOKUP(B$4:B$104,I$4:M$104,5,0) -> C | I46: Chenlong белые | J46: =ФЕВРАЛЬ!U78 -> 4 | K46: =J46/J$105 -> 0.00051308363 | L46: =L45+K46 -> 0.99166239 | M46: =_xlfn.IFS(L46<80%,"A",L46<=95%,"B",L46>95%,"C") -> C
B47: YIMEI 2391 C1 | C47: =ФЕВРАЛЬ!AO98 -> 234.1494 | D47: =C47/C$105 -> 0.00012071408 | E47: =E46+D47 -> 1.0428601 | F47: =IF(AND(E47<=0),"C",IF(E47<=0.8,"A",IF(E47<=0.95,"B","C"))) -> C | G47: =VLOOKUP(B$4:B$104,I$4:M$104,5,0) -> C | I47: sh4 | J47: =ФЕВРАЛЬ!U29 -> 3 | K47: =J47/J$105 -> 0.00038481272 | L47: =L46+K47 -> 0.9920472 | M47: =_xlfn.IFS(L47<80%,"A",L47<=95%,"B",L47>95%,"C") -> C
B48: MANNA2121 | C48: =ФЕВРАЛЬ!AO74 -> 181.9758 | D48: =C48/C$105 -> 9.3816349e-05 | E48: =E47+D48 -> 1.0429539 | F48: =IF(AND(E48<=0),"C",IF(E48<=0.8,"A",IF(E48<=0.95,"B","C"))) -> C | G48: =VLOOKUP(B$4:B$104,I$4:M$104,5,0) -> C | I48: sh06 | J48: =ФЕВРАЛЬ!U30 -> 3 | K48: =J48/J$105 -> 0.00038481272 | L48: =L47+K48 -> 0.99243202 | M48: =_xlfn.IFS(L48<80%,"A",L48<=95%,"B",L48>95%,"C") -> C
B49: MAIERSHA 03898 C9-08 | C49: =ФЕВРАЛЬ!AO94 -> 175.7906 | D49: =C49/C$105 -> 9.0627612e-05 | E49: =E48+D49 -> 1.0430446 | F49: =IF(AND(E49<=0),"C",IF(E49<=0.8,"A",IF(E49<=0.95,"B","C"))) -> C | G49: =VLOOKUP(B$4:B$104,I$4:M$104,5,0) -> C | I49: Linhai Baiyi серая линза | J49: =ФЕВРАЛЬ!U87 -> 3 | K49: =J49/J$105 -> 0.00038481272 | L49: =L48+K49 -> 0.99281683 | M49: =_xlfn.IFS(L49<80%,"A",L49<=95%,"B",L49>95%,"C") -> C
B50: Guangdu золото серая линза | C50: =ФЕВРАЛЬ!AO79 -> 158.2789 | D50: =C50/C$105 -> 8.1599578e-05 | E50: =E49+D50 -> 1.0431262 | F50: =IF(AND(E50<=0),"C",IF(E50<=0.8,"A",IF(E50<=0.95,"B","C"))) -> C | G50: =VLOOKUP(B$4:B$104,I$4:M$104,5,0) -> C | I50: sports красные | J50: =ФЕВРАЛЬ!U22 -> 2 | K50: =J50/J$105 -> 0.00025654182 | L50: =L49+K50 -> 0.99307337 | M50: =_xlfn.IFS(L50<80%,"A",L50<=95%,"B",L50>95%,"C") -> C
B51: MANNA2103 | C51: =ФЕВРАЛЬ!AO56 -> 120.6213 | D51: =C51/C$105 -> 6.2185466e-05 | E51: =E50+D51 -> 1.0431884 | F51: =IF(AND(E51<=0),"C",IF(E51<=0.8,"A",IF(E51<=0.95,"B","C"))) -> C | G51: =VLOOKUP(B$4:B$104,I$4:M$104,5,0) -> C | I51: sh07 | J51: =ФЕВРАЛЬ!U31 -> 2 | K51: =J51/J$105 -> 0.00025654182 | L51: =L50+K51 -> 0.99332991 | M51: =_xlfn.IFS(L51<80%,"A",L51<=95%,"B",L51>95%,"C") -> C
B52: sh08 | C52: =ФЕВРАЛЬ!AO32 -> 12.5521 | D52: =C52/C$105 -> 6.4711472e-06 | E52: =E51+D52 -> 1.0431948 | F52: =IF(AND(E52<=0),"C",IF(E52<=0.8,"A",IF(E52<=0.95,"B","C"))) -> C | G52: =VLOOKUP(B$4:B$104,I$4:M$104,5,0) -> C | I52: sh18 | J52: =ФЕВРАЛЬ!U42 -> 2 | K52: =J52/J$105 -> 0.00025654182 | L52: =L51+K52 -> 0.99358645 | M52: =_xlfn.IFS(L52<80%,"A",L52<=95%,"B",L52>95%,"C") -> C
B53: wwl8032 черные серебро | C53: =ФЕВРАЛЬ!AO19 -> 0 | D53: =C53/C$105 -> 0 | E53: =E52+D53 -> 1.0431948 | F53: =IF(AND(E53<=0),"C",IF(E53<=0.8,"A",IF(E53<=0.95,"B","C"))) -> C | G53: =VLOOKUP(B$4:B$104,I$4:M$104,5,0) -> C | I53: WW 3055 коричневый | J53: =ФЕВРАЛЬ!U53 -> 2 | K53: =J53/J$105 -> 0.00025654182 | L53: =L52+K53 -> 0.993843 | M53: =_xlfn.IFS(L53<80%,"A",L53<=95%,"B",L53>95%,"C") -> C
B54: sports синие | C54: =ФЕВРАЛЬ!AO20 -> 0 | D54: =C54/C$105 -> 0 | E54: =E53+D54 -> 1.0431948 | F54: =IF(AND(E54<=0),"C",IF(E54<=0.8,"A",IF(E54<=0.95,"B","C"))) -> C | G54: =VLOOKUP(B$4:B$104,I$4:M$104,5,0) -> C | I54: MANNA2103 | J54: =ФЕВРАЛЬ!U56 -> 2 | K54: =J54/J$105 -> 0.00025654182 | L54: =L53+K54 -> 0.99409954 | M54: =_xlfn.IFS(L54<80%,"A",L54<=95%,"B",L54>95%,"C") -> C
B55: sportlife черные | C55: =ФЕВРАЛЬ!AO23 -> 0 | D55: =C55/C$105 -> 0 | E55: =E54+D55 -> 1.0431948 | F55: =IF(AND(E55<=0),"C",IF(E55<=0.8,"A",IF(E55<=0.95,"B","C"))) -> C | G55: =VLOOKUP(B$4:B$104,I$4:M$104,5,0) -> C | I55: MANNA2107 | J55: =ФЕВРАЛЬ!U60 -> 2 | K55: =J55/J$105 -> 0.00025654182 | L55: =L54+K55 -> 0.99435608 | M55: =_xlfn.IFS(L55<80%,"A",L55<=95%,"B",L55>95%,"C") -> C
B56: sportlife синие | C56: =ФЕВРАЛЬ!AO24 -> 0 | D56: =C56/C$105 -> 0 | E56: =E55+D56 -> 1.0431948 | F56: =IF(AND(E56<=0),"C",IF(E56<=0.8,"A",IF(E56<=0.95,"B","C"))) -> C | G56: =VLOOKUP(B$4:B$104,I$4:M$104,5,0) -> C | I56: MANNA2117 | J56: =ФЕВРАЛЬ!U70 -> 2 | K56: =J56/J$105 -> 0.00025654182 | L56: =L55+K56 -> 0.99461262 | M56: =_xlfn.IFS(L56<80%,"A",L56<=95%,"B",L56>95%,"C") -> C
B57: sh11 | C57: =ФЕВРАЛЬ!AO35 -> 0 | D57: =C57/C$105 -> 0 | E57: =E56+D57 -> 1.0431948 | F57: =IF(AND(E57<=0),"C",IF(E57<=0.8,"A",IF(E57<=0.95,"B","C"))) -> C | G57: =VLOOKUP(B$4:B$104,I$4:M$104,5,0) -> C | I57: Qianai черные | J57: =ФЕВРАЛЬ!U83 -> 2 | K57: =J57/J$105 -> 0.00025654182 | L57: =L56+K57 -> 0.99486916 | M57: =_xlfn.IFS(L57<80%,"A",L57<=95%,"B",L57>95%,"C") -> C
B58: sh12 | C58: =ФЕВРАЛЬ!AO36 -> 0 | D58: =C58/C$105 -> 0 | E58: =E57+D58 -> 1.0431948 | F58: =IF(AND(E58<=0),"C",IF(E58<=0.8,"A",IF(E58<=0.95,"B","C"))) -> C | G58: =VLOOKUP(B$4:B$104,I$4:M$104,5,0) -> C | I58: Linhai Baiyi коричневая линза | J58: =ФЕВРАЛЬ!U86 -> 2 | K58: =J58/J$105 -> 0.00025654182 | L58: =L57+K58 -> 0.99512571 | M58: =_xlfn.IFS(L58<80%,"A",L58<=95%,"B",L58>95%,"C") -> C
B59: ww 1022 черн-серебро | C59: =ФЕВРАЛЬ!AO46 -> 0 | D59: =C59/C$105 -> 0 | E59: =E58+D59 -> 1.0431948 | F59: =IF(AND(E59<=0),"C",IF(E59<=0.8,"A",IF(E59<=0.95,"B","C"))) -> C | G59: =VLOOKUP(B$4:B$104,I$4:M$104,5,0) -> C | I59: Иу Диту серый | J59: =ФЕВРАЛЬ!U91 -> 2 | K59: =J59/J$105 -> 0.00025654182 | L59: =L58+K59 -> 0.99538225 | M59: =_xlfn.IFS(L59<80%,"A",L59<=95%,"B",L59>95%,"C") -> C
B60: MANNA2104 | C60: =ФЕВРАЛЬ!AO57 -> 0 | D60: =C60/C$105 -> 0 | E60: =E59+D60 -> 1.0431948 | F60: =IF(AND(E60<=0),"C",IF(E60<=0.8,"A",IF(E60<=0.95,"B","C"))) -> C | G60: =VLOOKUP(B$4:B$104,I$4:M$104,5,0) -> C | I60: YIMEI 2391 C1 | J60: =ФЕВРАЛЬ!U98 -> 2 | K60: =J60/J$105 -> 0.00025654182 | L60: =L59+K60 -> 0.99563879 | M60: =_xlfn.IFS(L60<80%,"A",L60<=95%,"B",L60>95%,"C") -> C
B61: MANNA2106 | C61: =ФЕВРАЛЬ!AO59 -> 0 | D61: =C61/C$105 -> 0 | E61: =E60+D61 -> 1.0431948 | F61: =IF(AND(E61<=0),"C",IF(E61<=0.8,"A",IF(E61<=0.95,"B","C"))) -> C | G61: =VLOOKUP(B$4:B$104,I$4:M$104,5,0) -> C | I61: кс_черные_тест | J61: =ФЕВРАЛЬ!U101 -> 2 | K61: =J61/J$105 -> 0.00025654182 | L61: =L60+K61 -> 0.99589533 | M61: =_xlfn.IFS(L61<80%,"A",L61<=95%,"B",L61>95%,"C") -> C
B62: MANNA2109 | C62: =ФЕВРАЛЬ!AO62 -> 0 | D62: =C62/C$105 -> 0 | E62: =E61+D62 -> 1.0431948 | F62: =IF(AND(E62<=0),"C",IF(E62<=0.8,"A",IF(E62<=0.95,"B","C"))) -> C | G62: =VLOOKUP(B$4:B$104,I$4:M$104,5,0) -> C | I62: sh08 | J62: =ФЕВРАЛЬ!U32 -> 1 | K62: =J62/J$105 -> 0.00012827091 | L62: =L61+K62 -> 0.9960236 | M62: =_xlfn.IFS(L62<80%,"A",L62<=95%,"B",L62>95%,"C") -> C
B63: MANNA2110 | C63: =ФЕВРАЛЬ!AO63 -> 0 | D63: =C63/C$105 -> 0 | E63: =E62+D63 -> 1.0431948 | F63: =IF(AND(E63<=0),"C",IF(E63<=0.8,"A",IF(E63<=0.95,"B","C"))) -> C | G63: =VLOOKUP(B$4:B$104,I$4:M$104,5,0) -> C | I63: sh17 | J63: =ФЕВРАЛЬ!U41 -> 1 | K63: =J63/J$105 -> 0.00012827091 | L63: =L62+K63 -> 0.99615187 | M63: =_xlfn.IFS(L63<80%,"A",L63<=95%,"B",L63>95%,"C") -> C
B64: MANNA2111 | C64: =ФЕВРАЛЬ!AO64 -> 0 | D64: =C64/C$105 -> 0 | E64: =E63+D64 -> 1.0431948 | F64: =IF(AND(E64<=0),"C",IF(E64<=0.8,"A",IF(E64<=0.95,"B","C"))) -> C | G64: =VLOOKUP(B$4:B$104,I$4:M$104,5,0) -> C | I64: MANNA2121 | J64: =ФЕВРАЛЬ!U74 -> 1 | K64: =J64/J$105 -> 0.00012827091 | L64: =L63+K64 -> 0.99628014 | M64: =_xlfn.IFS(L64<80%,"A",L64<=95%,"B",L64>95%,"C") -> C
B65: MANNA2113 | C65: =ФЕВРАЛЬ!AO66 -> 0 | D65: =C65/C$105 -> 0 | E65: =E64+D65 -> 1.0431948 | F65: =IF(AND(E65<=0),"C",IF(E65<=0.8,"A",IF(E65<=0.95,"B","C"))) -> C | G65: =VLOOKUP(B$4:B$104,I$4:M$104,5,0) -> C | I65: MANNA2122 | J65: =ФЕВРАЛЬ!U75 -> 1 | K65: =J65/J$105 -> 0.00012827091 | L65: =L64+K65 -> 0.99640841 | M65: =_xlfn.IFS(L65<80%,"A",L65<=95%,"B",L65>95%,"C") -> C
B66: MANNA2115 | C66: =ФЕВРАЛЬ!AO68 -> 0 | D66: =C66/C$105 -> 0 | E66: =E65+D66 -> 1.0431948 | F66: =IF(AND(E66<=0),"C",IF(E66<=0.8,"A",IF(E66<=0.95,"B","C"))) -> C | G66: =VLOOKUP(B$4:B$104,I$4:M$104,5,0) -> C | I66: Chenlong черные | J66: =ФЕВРАЛЬ!U76 -> 1 | K66: =J66/J$105 -> 0.00012827091 | L66: =L65+K66 -> 0.99653669 | M66: =_xlfn.IFS(L66<80%,"A",L66<=95%,"B",L66>95%,"C") -> C
B67: Taizhou Rayen sport розовый | C67: =ФЕВРАЛЬ!AO90 -> 0 | D67: =C67/C$105 -> 0 | E67: =E66+D67 -> 1.0431948 | F67: =IF(AND(E67<=0),"C",IF(E67<=0.8,"A",IF(E67<=0.95,"B","C"))) -> C | G67: =VLOOKUP(B$4:B$104,I$4:M$104,5,0) -> C | I67: Guangdu золото серая линза | J67: =ФЕВРАЛЬ!U79 -> 1 | K67: =J67/J$105 -> 0.00012827091 | L67: =L66+K67 -> 0.99666496 | M67: =_xlfn.IFS(L67<80%,"A",L67<=95%,"B",L67>95%,"C") -> C
B68: MARSTON 7171 C1 | C68: =ФЕВРАЛЬ!AO96 -> 0 | D68: =C68/C$105 -> 0 | E68: =E67+D68 -> 1.0431948 | F68: =IF(AND(E68<=0),"C",IF(E68<=0.8,"A",IF(E68<=0.95,"B","C"))) -> C | G68: =VLOOKUP(B$4:B$104,I$4:M$104,5,0) -> C | I68: Hengda Optical леопард | J68: =ФЕВРАЛЬ!U82 -> 1 | K68: =J68/J$105 -> 0.00012827091 | L68: =L67+K68 -> 0.99679323 | M68: =_xlfn.IFS(L68<80%,"A",L68<=95%,"B",L68>95%,"C") -> C
B69: POMILED 08247 C4-08 | C69: =ФЕВРАЛЬ!AO97 -> 0 | D69: =C69/C$105 -> 0 | E69: =E68+D69 -> 1.0431948 | F69: =IF(AND(E69<=0),"C",IF(E69<=0.8,"A",IF(E69<=0.95,"B","C"))) -> C | G69: =VLOOKUP(B$4:B$104,I$4:M$104,5,0) -> C | I69: MAIERSHA 03898 C9-08 | J69: =ФЕВРАЛЬ!U94 -> 1 | K69: =J69/J$105 -> 0.00012827091 | L69: =L68+K69 -> 0.9969215 | M69: =_xlfn.IFS(L69<80%,"A",L69<=95%,"B",L69>95%,"C") -> C
B70: ЧСЖ_женские | C70: =ФЕВРАЛЬ!AO100 -> 0 | D70: =C70/C$105 -> 0 | E70: =E69+D70 -> 1.0431948 | F70: =IF(AND(E70<=0),"C",IF(E70<=0.8,"A",IF(E70<=0.95,"B","C"))) -> C | G70: =VLOOKUP(B$4:B$104,I$4:M$104,5,0) -> C | I70: MAIERSHA 03914 C9-124 | J70: =ФЕВРАЛЬ!U95 -> 1 | K70: =J70/J$105 -> 0.00012827091 | L70: =L69+K70 -> 0.99704977 | M70: =_xlfn.IFS(L70<80%,"A",L70<=95%,"B",L70>95%,"C") -> C
B71: кс_черные_женские | C71: =ФЕВРАЛЬ!AO102 -> 0 | D71: =C71/C$105 -> 0 | E71: =E70+D71 -> 1.0431948 | F71: =IF(AND(E71<=0),"C",IF(E71<=0.8,"A",IF(E71<=0.95,"B","C"))) -> C | G71: =VLOOKUP(B$4:B$104,I$4:M$104,5,0) -> C | I71: wwl8032 черные серебро | J71: =ФЕВРАЛЬ!U19 -> 0 | K71: =J71/J$105 -> 0 | L71: =L70+K71 -> 0.99704977 | M71: =_xlfn.IFS(L71<80%,"A",L71<=95%,"B",L71>95%,"C") -> C
B72: sh06 | C72: =ФЕВРАЛЬ!AO30 -> -11.4691 | D72: =C72/C$105 -> -5.9128141e-06 | E72: =E71+D72 -> 1.0431889 | F72: =IF(AND(E72<=0),"C",IF(E72<=0.8,"A",IF(E72<=0.95,"B","C"))) -> C | G72: =VLOOKUP(B$4:B$104,I$4:M$104,5,0) -> C | I72: sports синие | J72: =ФЕВРАЛЬ!U20 -> 0 | K72: =J72/J$105 -> 0 | L72: =L71+K72 -> 0.99704977 | M72: =_xlfn.IFS(L72<80%,"A",L72<=95%,"B",L72>95%,"C") -> C
B73: MANNA2122 | C73: =ФЕВРАЛЬ!AO75 -> -68.5476 | D73: =C73/C$105 -> -3.5339235e-05 | E73: =E72+D73 -> 1.0431536 | F73: =IF(AND(E73<=0),"C",IF(E73<=0.8,"A",IF(E73<=0.95,"B","C"))) -> C | G73: =VLOOKUP(B$4:B$104,I$4:M$104,5,0) -> C | I73: sports зеленые | J73: =ФЕВРАЛЬ!U21 -> 0 | K73: =J73/J$105 -> 0 | L73: =L72+K73 -> 0.99704977 | M73: =_xlfn.IFS(L73<80%,"A",L73<=95%,"B",L73>95%,"C") -> C
B74: sports зеленые | C74: =ФЕВРАЛЬ!AO21 -> -79.58 | D74: =C74/C$105 -> -4.1026911e-05 | E74: =E73+D74 -> 1.0431125 | F74: =IF(AND(E74<=0),"C",IF(E74<=0.8,"A",IF(E74<=0.95,"B","C"))) -> C | G74: =VLOOKUP(B$4:B$104,I$4:M$104,5,0) -> C | I74: sportlife черные | J74: =ФЕВРАЛЬ!U23 -> 0 | K74: =J74/J$105 -> 0 | L74: =L73+K74 -> 0.99704977 | M74: =_xlfn.IFS(L74<80%,"A",L74<=95%,"B",L74>95%,"C") -> C
B75: Ли Сян ретро серебро | C75: =ФЕВРАЛЬ!AO93 -> -91.41 | D75: =C75/C$105 -> -4.7125785e-05 | E75: =E74+D75 -> 1.0430654 | F75: =IF(AND(E75<=0),"C",IF(E75<=0.8,"A",IF(E75<=0.95,"B","C"))) -> C | G75: =VLOOKUP(B$4:B$104,I$4:M$104,5,0) -> C | I75: sportlife синие | J75: =ФЕВРАЛЬ!U24 -> 0 | K75: =J75/J$105 -> 0 | L75: =L74+K75 -> 0.99704977 | M75: =_xlfn.IFS(L75<80%,"A",L75<=95%,"B",L75>95%,"C") -> C
B76: MANNA2112 | C76: =ФЕВРАЛЬ!AO65 -> -96.4 | D76: =C76/C$105 -> -4.9698344e-05 | E76: =E49+D76 -> 1.0429949 | F76: =IF(AND(E76<=0),"C",IF(E76<=0.8,"A",IF(E76<=0.95,"B","C"))) -> C | G76: =VLOOKUP(B$4:B$104,I$4:M$104,5,0) -> C | I76: sh11 | J76: =ФЕВРАЛЬ!U35 -> 0 | K76: =J76/J$105 -> 0 | L76: =L49+K76 -> 0.99281683 | M76: =_xlfn.IFS(L76<80%,"A",L76<=95%,"B",L76>95%,"C") -> C
B77: MANNA2102 | C77: =ФЕВРАЛЬ!AO55 -> -97.32 | D77: =C77/C$105 -> -5.0172644e-05 | E77: =E76+D77 -> 1.0429447 | F77: =IF(AND(E77<=0),"C",IF(E77<=0.8,"A",IF(E77<=0.95,"B","C"))) -> C | G77: =VLOOKUP(B$4:B$104,I$4:M$104,5,0) -> C | I77: sh12 | J77: =ФЕВРАЛЬ!U36 -> 0 | K77: =J77/J$105 -> 0 | L77: =L76+K77 -> 0.99281683 | M77: =_xlfn.IFS(L77<80%,"A",L77<=95%,"B",L77>95%,"C") -> C
B78: MANNA2107 | C78: =ФЕВРАЛЬ!AO60 -> -101.0777 | D78: =C78/C$105 -> -5.21099e-05 | E78: =E77+D78 -> 1.0428926 | F78: =IF(AND(E78<=0),"C",IF(E78<=0.8,"A",IF(E78<=0.95,"B","C"))) -> C | G78: =VLOOKUP(B$4:B$104,I$4:M$104,5,0) -> C | I78: sh14 | J78: =ФЕВРАЛЬ!U38 -> 0 | K78: =J78/J$105 -> 0 | L78: =L77+K78 -> 0.99281683 | M78: =_xlfn.IFS(L78<80%,"A",L78<=95%,"B",L78>95%,"C") -> C
B79: Qianai коричневые | C79: =ФЕВРАЛЬ!AO84 -> -108 | D79: =C79/C$105 -> -5.5678643e-05 | E79: =E78+D79 -> 1.0428369 | F79: =IF(AND(E79<=0),"C",IF(E79<=0.8,"A",IF(E79<=0.95,"B","C"))) -> C | G79: =VLOOKUP(B$4:B$104,I$4:M$104,5,0) -> C | I79: sh16 | J79: =ФЕВРАЛЬ!U40 -> 0 | K79: =J79/J$105 -> 0 | L79: =L78+K79 -> 0.99281683 | M79: =_xlfn.IFS(L79<80%,"A",L79<=95%,"B",L79>95%,"C") -> C
B80: Chenlong коричневые | C80: =ФЕВРАЛЬ!AO77 -> -115.07 | D80: =C80/C$105 -> -5.9323532e-05 | E80: =E79+D80 -> 1.0427776 | F80: =IF(AND(E80<=0),"C",IF(E80<=0.8,"A",IF(E80<=0.95,"B","C"))) -> C | G80: =VLOOKUP(B$4:B$104,I$4:M$104,5,0) -> C | I80: ww 1022 черн-серебро | J80: =ФЕВРАЛЬ!U46 -> 0 | K80: =J80/J$105 -> 0 | L80: =L79+K80 -> 0.99281683 | M80: =_xlfn.IFS(L80<80%,"A",L80<=95%,"B",L80>95%,"C") -> C
B81: sh07 | C81: =ФЕВРАЛЬ!AO31 -> -199.8703 | D81: =C81/C$105 -> -0.00010304173 | E81: =E80+D81 -> 1.0426745 | F81: =IF(AND(E81<=0),"C",IF(E81<=0.8,"A",IF(E81<=0.95,"B","C"))) -> C | G81: =VLOOKUP(B$4:B$104,I$4:M$104,5,0) -> C | I81: WW 3055 черный | J81: =ФЕВРАЛЬ!U52 -> 0 | K81: =J81/J$105 -> 0 | L81: =L80+K81 -> 0.99281683 | M81: =_xlfn.IFS(L81<80%,"A",L81<=95%,"B",L81>95%,"C") -> C
B82: MANNA2116 | C82: =ФЕВРАЛЬ!AO69 -> -220.98 | D82: =C82/C$105 -> -0.00011392469 | E82: =E81+D82 -> 1.0425606 | F82: =IF(AND(E82<=0),"C",IF(E82<=0.8,"A",IF(E82<=0.95,"B","C"))) -> C | G82: =VLOOKUP(B$4:B$104,I$4:M$104,5,0) -> C | I82: MANNA2102 | J82: =ФЕВРАЛЬ!U55 -> 0 | K82: =J82/J$105 -> 0 | L82: =L81+K82 -> 0.99281683 | M82: =_xlfn.IFS(L82<80%,"A",L82<=95%,"B",L82>95%,"C") -> C
B83: MANNA2119 | C83: =ФЕВРАЛЬ!AO72 -> -243.9111 | D83: =C83/C$105 -> -0.00012574666 | E83: =E82+D83 -> 1.0424349 | F83: =IF(AND(E83<=0),"C",IF(E83<=0.8,"A",IF(E83<=0.95,"B","C"))) -> C | G83: =VLOOKUP(B$4:B$104,I$4:M$104,5,0) -> C | I83: MANNA2104 | J83: =ФЕВРАЛЬ!U57 -> 0 | K83: =J83/J$105 -> 0 | L83: =L82+K83 -> 0.99281683 | M83: =_xlfn.IFS(L83<80%,"A",L83<=95%,"B",L83>95%,"C") -> C
B84: MANNA2108 | C84: =ФЕВРАЛЬ!AO61 -> -283.83 | D84: =C84/C$105 -> -0.00014632657 | E84: =E83+D84 -> 1.0422885 | F84: =IF(AND(E84<=0),"C",IF(E84<=0.8,"A",IF(E84<=0.95,"B","C"))) -> C | G84: =VLOOKUP(B$4:B$104,I$4:M$104,5,0) -> C | I84: MANNA2106 | J84: =ФЕВРАЛЬ!U59 -> 0 | K84: =J84/J$105 -> 0 | L84: =L83+K84 -> 0.99281683 | M84: =_xlfn.IFS(L84<80%,"A",L84<=95%,"B",L84>95%,"C") -> C
B85: Ли Сян ретро золото | C85: =ФЕВРАЛЬ!AO92 -> -324.84 | D85: =C85/C$105 -> -0.00016746899 | E85: =E84+D85 -> 1.0421211 | F85: =IF(AND(E85<=0),"C",IF(E85<=0.8,"A",IF(E85<=0.95,"B","C"))) -> C | G85: =VLOOKUP(B$4:B$104,I$4:M$104,5,0) -> C | I85: MANNA2108 | J85: =ФЕВРАЛЬ!U61 -> 0 | K85: =J85/J$105 -> 0 | L85: =L84+K85 -> 0.99281683 | M85: =_xlfn.IFS(L85<80%,"A",L85<=95%,"B",L85>95%,"C") -> C
B86: 1022_коричневые_тест | C86: =ФЕВРАЛЬ!AO103 -> -336 | D86: =C86/C$105 -> -0.00017322245 | E86: =E85+D86 -> 1.0419479 | F86: =IF(AND(E86<=0),"C",IF(E86<=0.8,"A",IF(E86<=0.95,"B","C"))) -> C | G86: =VLOOKUP(B$4:B$104,I$4:M$104,5,0) -> C | I86: MANNA2109 | J86: =ФЕВРАЛЬ!U62 -> 0 | K86: =J86/J$105 -> 0 | L86: =L85+K86 -> 0.99281683 | M86: =_xlfn.IFS(L86<80%,"A",L86<=95%,"B",L86>95%,"C") -> C
B87: ЧСЖ_тест | C87: =ФЕВРАЛЬ!AO99 -> -476 | D87: =C87/C$105 -> -0.00024539846 | E87: =E86+D87 -> 1.0417025 | F87: =IF(AND(E87<=0),"C",IF(E87<=0.8,"A",IF(E87<=0.95,"B","C"))) -> C | G87: =VLOOKUP(B$4:B$104,I$4:M$104,5,0) -> C | I87: MANNA2110 | J87: =ФЕВРАЛЬ!U63 -> 0 | K87: =J87/J$105 -> 0 | L87: =L86+K87 -> 0.99281683 | M87: =_xlfn.IFS(L87<80%,"A",L87<=95%,"B",L87>95%,"C") -> C
B88: sh14 | C88: =ФЕВРАЛЬ!AO38 -> -536.63 | D88: =C88/C$105 -> -0.00027665584 | E88: =E87+D88 -> 1.0414258 | F88: =IF(AND(E88<=0),"C",IF(E88<=0.8,"A",IF(E88<=0.95,"B","C"))) -> C | G88: =VLOOKUP(B$4:B$104,I$4:M$104,5,0) -> C | I88: MANNA2111 | J88: =ФЕВРАЛЬ!U64 -> 0 | K88: =J88/J$105 -> 0 | L88: =L87+K88 -> 0.99281683 | M88: =_xlfn.IFS(L88<80%,"A",L88<=95%,"B",L88>95%,"C") -> C
B89: Chenlong черные | C89: =ФЕВРАЛЬ!AO76 -> -816.359 | D89: =C89/C$105 -> -0.00042086816 | E89: =E88+D89 -> 1.0410049 | F89: =IF(AND(E89<=0),"C",IF(E89<=0.8,"A",IF(E89<=0.95,"B","C"))) -> C | G89: =VLOOKUP(B$4:B$104,I$4:M$104,5,0) -> C | I89: MANNA2112 | J89: =ФЕВРАЛЬ!U65 -> 0 | K89: =J89/J$105 -> 0 | L89: =L88+K89 -> 0.99281683 | M89: =_xlfn.IFS(L89<80%,"A",L89<=95%,"B",L89>95%,"C") -> C
B90: WW 3055 черный | C90: =ФЕВРАЛЬ!AO52 -> -839.02 | D90: =C90/C$105 -> -0.00043255088 | E90: =E89+D90 -> 1.0405724 | F90: =IF(AND(E90<=0),"C",IF(E90<=0.8,"A",IF(E90<=0.95,"B","C"))) -> C | G90: =VLOOKUP(B$4:B$104,I$4:M$104,5,0) -> C | I90: MANNA2113 | J90: =ФЕВРАЛЬ!U66 -> 0 | K90: =J90/J$105 -> 0 | L90: =L89+K90 -> 0.99281683 | M90: =_xlfn.IFS(L90<80%,"A",L90<=95%,"B",L90>95%,"C") -> C
B91: sh16 | C91: =ФЕВРАЛЬ!AO40 -> -843.03 | D91: =C91/C$105 -> -0.00043461821 | E91: =E90+D91 -> 1.0401378 | F91: =IF(AND(E91<=0),"C",IF(E91<=0.8,"A",IF(E91<=0.95,"B","C"))) -> C | G91: =VLOOKUP(B$4:B$104,I$4:M$104,5,0) -> C | I91: MANNA2115 | J91: =ФЕВРАЛЬ!U68 -> 0 | K91: =J91/J$105 -> 0 | L91: =L90+K91 -> 0.99281683 | M91: =_xlfn.IFS(L91<80%,"A",L91<=95%,"B",L91>95%,"C") -> C
B92: Иу Диту серый | C92: =ФЕВРАЛЬ!AO91 -> -1212.3358 | D92: =C92/C$105 -> -0.0006250112 | E92: =E91+D92 -> 1.0395128 | F92: =IF(AND(E92<=0),"C",IF(E92<=0.8,"A",IF(E92<=0.95,"B","C"))) -> C | G92: =VLOOKUP(B$4:B$104,I$4:M$104,5,0) -> C | I92: MANNA2116 | J92: =ФЕВРАЛЬ!U69 -> 0 | K92: =J92/J$105 -> 0 | L92: =L91+K92 -> 0.99281683 | M92: =_xlfn.IFS(L92<80%,"A",L92<=95%,"B",L92>95%,"C") -> C
B93: MANNA2118 | C93: =ФЕВРАЛЬ!AO71 -> -1476.2074 | D93: =C93/C$105 -> -0.00076104839 | E93: =E92+D93 -> 1.0387517 | F93: =IF(AND(E93<=0),"C",IF(E93<=0.8,"A",IF(E93<=0.95,"B","C"))) -> C | G93: =VLOOKUP(B$4:B$104,I$4:M$104,5,0) -> C | I93: Chenlong коричневые | J93: =ФЕВРАЛЬ!U77 -> 0 | K93: =J93/J$105 -> 0 | L93: =L92+K93 -> 0.99281683 | M93: =_xlfn.IFS(L93<80%,"A",L93<=95%,"B",L93>95%,"C") -> C
B94: ww 8010 черные | C94: =ФЕВРАЛЬ!AO51 -> -2327.0098 | D94: =C94/C$105 -> -0.0011996736 | E94: =E93+D94 -> 1.037552 | F94: =IF(AND(E94<=0),"C",IF(E94<=0.8,"A",IF(E94<=0.95,"B","C"))) -> C | G94: =VLOOKUP(B$4:B$104,I$4:M$104,5,0) -> C | I94: Qianai коричневые | J94: =ФЕВРАЛЬ!U84 -> 0 | K94: =J94/J$105 -> 0 | L94: =L93+K94 -> 0.99281683 | M94: =_xlfn.IFS(L94<80%,"A",L94<=95%,"B",L94>95%,"C") -> C
B95: Keming Aishi коричневые | C95: =ФЕВРАЛЬ!AO85 -> -2678.8154 | D95: =C95/C$105 -> -0.0013810445 | E95: =E94+D95 -> 1.036171 | F95: =IF(AND(E95<=0),"C",IF(E95<=0.8,"A",IF(E95<=0.95,"B","C"))) -> C | G95: =VLOOKUP(B$4:B$104,I$4:M$104,5,0) -> C | I95: Keming Aishi коричневые | J95: =ФЕВРАЛЬ!U85 -> 0 | K95: =J95/J$105 -> 0 | L95: =L94+K95 -> 0.99281683 | M95: =_xlfn.IFS(L95<80%,"A",L95<=95%,"B",L95>95%,"C") -> C
B96: sh09 | C96: =ФЕВРАЛЬ!AO33 -> -3656.5295 | D96: =C96/C$105 -> -0.0018850982 | E96: =E95+D96 -> 1.0342859 | F96: =IF(AND(E96<=0),"C",IF(E96<=0.8,"A",IF(E96<=0.95,"B","C"))) -> C | G96: =VLOOKUP(B$4:B$104,I$4:M$104,5,0) -> C | I96: Taizhou Rayen sport розовый | J96: =ФЕВРАЛЬ!U90 -> 0 | K96: =J96/J$105 -> 0 | L96: =L95+K96 -> 0.99281683 | M96: =_xlfn.IFS(L96<80%,"A",L96<=95%,"B",L96>95%,"C") -> C
B97: sh15 | C97: =ФЕВРАЛЬ!AO39 -> -3916.2962 | D97: =C97/C$105 -> -0.002019019 | E97: =E96+D97 -> 1.0322669 | F97: =IF(AND(E97<=0),"C",IF(E97<=0.8,"A",IF(E97<=0.95,"B","C"))) -> C | G97: =VLOOKUP(B$4:B$104,I$4:M$104,5,0) -> C | I97: Ли Сян ретро золото | J97: =ФЕВРАЛЬ!U92 -> 0 | K97: =J97/J$105 -> 0 | L97: =L96+K97 -> 0.99281683 | M97: =_xlfn.IFS(L97<80%,"A",L97<=95%,"B",L97>95%,"C") -> C
B98: Linhai Baiyi серая линза | C98: =ФЕВРАЛЬ!AO87 -> -4603.9732 | D98: =C98/C$105 -> -0.0023735461 | E98: =E97+D98 -> 1.0298933 | F98: =IF(AND(E98<=0),"C",IF(E98<=0.8,"A",IF(E98<=0.95,"B","C"))) -> C | G98: =VLOOKUP(B$4:B$104,I$4:M$104,5,0) -> C | I98: Ли Сян ретро серебро | J98: =ФЕВРАЛЬ!U93 -> 0 | K98: =J98/J$105 -> 0 | L98: =L97+K98 -> 0.99281683 | M98: =_xlfn.IFS(L98<80%,"A",L98<=95%,"B",L98>95%,"C") -> C
B99: sh2 | C99: =ФЕВРАЛЬ!AO27 -> -4689.5168 | D99: =C99/C$105 -> -0.0024176475 | E99: =E93+D99 -> 1.0363341 | F99: =IF(AND(E99<=0),"C",IF(E99<=0.8,"A",IF(E99<=0.95,"B","C"))) -> C | G99: =VLOOKUP(B$4:B$104,I$4:M$104,5,0) -> C | I99: MARSTON 7171 C1 | J99: =ФЕВРАЛЬ!U96 -> 0 | K99: =J99/J$105 -> 0 | L99: =L93+K99 -> 0.99281683 | M99: =_xlfn.IFS(L99<80%,"A",L99<=95%,"B",L99>95%,"C") -> C
B100: Guangdu серебро серая линза | C100: =ФЕВРАЛЬ!AO80 -> -4702.0891 | D100: =C100/C$105 -> -0.0024241291 | E100: =E94+D100 -> 1.0351279 | F100: =IF(AND(E100<=0),"C",IF(E100<=0.8,"A",IF(E100<=0.95,"B","C"))) -> C | G100: =VLOOKUP(B$4:B$104,I$4:M$104,5,0) -> C | I100: POMILED 08247 C4-08 | J100: =ФЕВРАЛЬ!U97 -> 0 | K100: =J100/J$105 -> 0 | L100: =L94+K100 -> 0.99281683 | M100: =_xlfn.IFS(L100<80%,"A",L100<=95%,"B",L100>95%,"C") -> C
B101: MANNA2105 | C101: =ФЕВРАЛЬ!AO58 -> -6991.7369 | D101: =C101/C$105 -> -0.003604541 | E101: =E95+D101 -> 1.0325664 | F101: =IF(AND(E101<=0),"C",IF(E101<=0.8,"A",IF(E101<=0.95,"B","C"))) -> C | G101: =VLOOKUP(B$4:B$104,I$4:M$104,5,0) -> C | I101: ЧСЖ_тест | J101: =ФЕВРАЛЬ!U99 -> 0 | K101: =J101/J$105 -> 0 | L101: =L95+K101 -> 0.99281683 | M101: =_xlfn.IFS(L101<80%,"A",L101<=95%,"B",L101>95%,"C") -> C
...

Sheet АВС 9
B2: ОЧКИ
C3: Прибыль | D3: % прибыль | E3: Доля | F3: ABC прибыль | G3: ABC кол-во | J3: Кол-во | K3: % кол-во | L3: Доля | M3: ABC кол-во
B4: QS черные PZ | C4: ='Юнит 9'!AO4 -> 233182.09 | D4: =C4/C$105 -> 0.31385022 | E4: =D4 -> 0.31385022 | F4: =IF(AND(E4<=0),"C",IF(E4<=0.8,"A",IF(E4<=0.95,"B","C"))) -> A | G4: =VLOOKUP(B$4:B$104,I$4:M$104,5,0) -> A | I4: QS черные PZ | J4: ='Юнит 9'!U4 -> 541 | K4: =J4/J$105 -> 0.23430056 | L4: =K4 -> 0.23430056 | M4: =_xlfn.IFS(L4<80%,"A",L4<=95%,"B",L4>95%,"C") -> A | P4: A | Q4: 0.8
B5: QS коричневые PZ | C5: ='Юнит 9'!AO7 -> 69947.749 | D5: =C5/C$105 -> 0.094145812 | E5: =E4+D5 -> 0.40799604 | F5: =IF(AND(E5<=0),"C",IF(E5<=0.8,"A",IF(E5<=0.95,"B","C"))) -> A | G5: =VLOOKUP(B$4:B$104,I$4:M$104,5,0) -> A | I5: QS коричневые PZ | J5: ='Юнит 9'!U7 -> 180 | K5: =J5/J$105 -> 0.077955825 | L5: =L4+K5 -> 0.31225639 | M5: =_xlfn.IFS(L5<80%,"A",L5<=95%,"B",L5>95%,"C") -> A | P5: B | Q5: 0.15
B6: QS синие PZ | C6: ='Юнит 9'!AO5 -> 59062.289 | D6: =C6/C$105 -> 0.079494584 | E6: =E5+D6 -> 0.48749062 | F6: =IF(AND(E6<=0),"C",IF(E6<=0.8,"A",IF(E6<=0.95,"B","C"))) -> A | G6: =VLOOKUP(B$4:B$104,I$4:M$104,5,0) -> A | I6: th син | J6: ='Юнит 9'!U10 -> 156 | K6: =J6/J$105 -> 0.067561715 | L6: =L5+K6 -> 0.3798181 | M6: =_xlfn.IFS(L6<80%,"A",L6<=95%,"B",L6>95%,"C") -> A | P6: C | Q6: 0.05
B7: th черн | C7: ='Юнит 9'!AO9 -> 48626.7 | D7: =C7/C$105 -> 0.065448857 | E7: =E6+D7 -> 0.55293948 | F7: =IF(AND(E7<=0),"C",IF(E7<=0.8,"A",IF(E7<=0.95,"B","C"))) -> A | G7: =VLOOKUP(B$4:B$104,I$4:M$104,5,0) -> A | I7: QS синие PZ | J7: ='Юнит 9'!U5 -> 147 | K7: =J7/J$105 -> 0.063663924 | L7: =L6+K7 -> 0.44348203 | M7: =_xlfn.IFS(L7<80%,"A",L7<=95%,"B",L7>95%,"C") -> A
B8: flip черные | C8: ='Юнит 9'!AO13 -> 38940.896 | D8: =C8/C$105 -> 0.052412299 | E8: =E7+D8 -> 0.60535178 | F8: =IF(AND(E8<=0),"C",IF(E8<=0.8,"A",IF(E8<=0.95,"B","C"))) -> A | G8: =VLOOKUP(B$4:B$104,I$4:M$104,5,0) -> A | I8: th черн | J8: ='Юнит 9'!U9 -> 135 | K8: =J8/J$105 -> 0.058466869 | L8: =L7+K8 -> 0.5019489 | M8: =_xlfn.IFS(L8<80%,"A",L8<=95%,"B",L8>95%,"C") -> A
B9: th син | C9: ='Юнит 9'!AO10 -> 38435.993 | D9: =C9/C$105 -> 0.051732727 | E9: =E8+D9 -> 0.6570845 | F9: =IF(AND(E9<=0),"C",IF(E9<=0.8,"A",IF(E9<=0.95,"B","C"))) -> A | G9: =VLOOKUP(B$4:B$104,I$4:M$104,5,0) -> A | I9: flip черные | J9: ='Юнит 9'!U13 -> 122 | K9: =J9/J$105 -> 0.052836726 | L9: =L8+K9 -> 0.55478562 | M9: =_xlfn.IFS(L9<80%,"A",L9<=95%,"B",L9>95%,"C") -> A
B10: QS желтые PZ | C10: ='Юнит 9'!AO6 -> 36585.85 | D10: =C10/C$105 -> 0.049242536 | E10: =E9+D10 -> 0.70632704 | F10: =IF(AND(E10<=0),"C",IF(E10<=0.8,"A",IF(E10<=0.95,"B","C"))) -> A | G10: =VLOOKUP(B$4:B$104,I$4:M$104,5,0) -> A | I10: QS желтые PZ | J10: ='Юнит 9'!U6 -> 121 | K10: =J10/J$105 -> 0.052403638 | L10: =L9+K10 -> 0.60718926 | M10: =_xlfn.IFS(L10<80%,"A",L10<=95%,"B",L10>95%,"C") -> A
B11: flip коричневые | C11: ='Юнит 9'!AO16 -> 31216.063 | D11: =C11/C$105 -> 0.042015099 | E11: =E10+D11 -> 0.74834214 | F11: =IF(AND(E11<=0),"C",IF(E11<=0.8,"A",IF(E11<=0.95,"B","C"))) -> A | G11: =VLOOKUP(B$4:B$104,I$4:M$104,5,0) -> A | I11: черные с железкой классика | J11: ='Юнит 9'!U3 -> 105 | K11: =J11/J$105 -> 0.045474231 | L11: =L10+K11 -> 0.65266349 | M11: =_xlfn.IFS(L11<80%,"A",L11<=95%,"B",L11>95%,"C") -> A
B12: th желт | C12: ='Юнит 9'!AO11 -> 29898.234 | D12: =C12/C$105 -> 0.040241374 | E12: =E11+D12 -> 0.78858351 | F12: =IF(AND(E12<=0),"C",IF(E12<=0.8,"A",IF(E12<=0.95,"B","C"))) -> A | G12: =VLOOKUP(B$4:B$104,I$4:M$104,5,0) -> A | I12: flip коричневые | J12: ='Юнит 9'!U16 -> 98 | K12: =J12/J$105 -> 0.042442616 | L12: =L11+K12 -> 0.69510611 | M12: =_xlfn.IFS(L12<80%,"A",L12<=95%,"B",L12>95%,"C") -> A
B13: th коричн | C13: ='Юнит 9'!AO12 -> 28687.235 | D13: =C13/C$105 -> 0.038611436 | E13: =E12+D13 -> 0.82719495 | F13: =IF(AND(E13<=0),"C",IF(E13<=0.8,"A",IF(E13<=0.95,"B","C"))) -> B | G13: =VLOOKUP(B$4:B$104,I$4:M$104,5,0) -> A | I13: sh3 | J13: ='Юнит 9'!U28 -> 87 | K13: =J13/J$105 -> 0.037678649 | L13: =L12+K13 -> 0.73278476 | M13: =_xlfn.IFS(L13<80%,"A",L13<=95%,"B",L13>95%,"C") -> A
B14: wwl8032 хром металл | C14: ='Юнит 9'!AO18 -> 20921.802 | D14: =C14/C$105 -> 0.028159591 | E14: =E13+D14 -> 0.85535454 | F14: =IF(AND(E14<=0),"C",IF(E14<=0.8,"A",IF(E14<=0.95,"B","C"))) -> B | G14: =VLOOKUP(B$4:B$104,I$4:M$104,5,0) -> B | I14: th коричн | J14: ='Юнит 9'!U12 -> 79 | K14: =J14/J$105 -> 0.034213945 | L14: =L13+K14 -> 0.7669987 | M14: =_xlfn.IFS(L14<80%,"A",L14<=95%,"B",L14>95%,"C") -> A
B15: черные с железкой классика | C15: ='Юнит 9'!AO3 -> 19130.696 | D15: =C15/C$105 -> 0.025748862 | E15: =E14+D15 -> 0.8811034 | F15: =IF(AND(E15<=0),"C",IF(E15<=0.8,"A",IF(E15<=0.95,"B","C"))) -> B | G15: =VLOOKUP(B$4:B$104,I$4:M$104,5,0) -> A | I15: th желт | J15: ='Юнит 9'!U11 -> 76 | K15: =J15/J$105 -> 0.032914682 | L15: =L14+K15 -> 0.79991338 | M15: =_xlfn.IFS(L15<80%,"A",L15<=95%,"B",L15>95%,"C") -> A
B16: MR8854 C2 Жен | C16: ='Юнит 9'!AO8 -> 18340.696 | D16: =C16/C$105 -> 0.024685565 | E16: =E15+D16 -> 0.90578897 | F16: =IF(AND(E16<=0),"C",IF(E16<=0.8,"A",IF(E16<=0.95,"B","C"))) -> B | G16: =VLOOKUP(B$4:B$104,I$4:M$104,5,0) -> B | I16: MR8854 C2 Жен | J16: ='Юнит 9'!U8 -> 62 | K16: =J16/J$105 -> 0.026851451 | L16: =L15+K16 -> 0.82676483 | M16: =_xlfn.IFS(L16<80%,"A",L16<=95%,"B",L16>95%,"C") -> B
B17: sh3 | C17: ='Юнит 9'!AO28 -> 15602.505 | D17: =C17/C$105 -> 0.021000111 | E17: =E16+D17 -> 0.92678908 | F17: =IF(AND(E17<=0),"C",IF(E17<=0.8,"A",IF(E17<=0.95,"B","C"))) -> B | G17: =VLOOKUP(B$4:B$104,I$4:M$104,5,0) -> A | I17: wwl8032 хром металл | J17: ='Юнит 9'!U18 -> 60 | K17: =J17/J$105 -> 0.025985275 | L17: =L16+K17 -> 0.85275011 | M17: =_xlfn.IFS(L17<80%,"A",L17<=95%,"B",L17>95%,"C") -> B
B18: flip синие | C18: ='Юнит 9'!AO14 -> 11020.92 | D18: =C18/C$105 -> 0.01483355 | E18: =E17+D18 -> 0.94162263 | F18: =IF(AND(E18<=0),"C",IF(E18<=0.8,"A",IF(E18<=0.95,"B","C"))) -> B | G18: =VLOOKUP(B$4:B$104,I$4:M$104,5,0) -> B | I18: ww 1022 черные | J18: ='Юнит 9'!U45 -> 49 | K18: =J18/J$105 -> 0.021221308 | L18: =L17+K18 -> 0.87397142 | M18: =_xlfn.IFS(L18<80%,"A",L18<=95%,"B",L18>95%,"C") -> B
B19: ww 2018 черные | C19: ='Юнит 9'!AO49 -> 9856.2478 | D19: =C19/C$105 -> 0.013265966 | E19: =E18+D19 -> 0.95488859 | F19: =IF(AND(E19<=0),"C",IF(E19<=0.8,"A",IF(E19<=0.95,"B","C"))) -> C | G19: =VLOOKUP(B$4:B$104,I$4:M$104,5,0) -> B | I19: flip синие | J19: ='Юнит 9'!U14 -> 39 | K19: =J19/J$105 -> 0.016890429 | L19: =L18+K19 -> 0.89086184 | M19: =_xlfn.IFS(L19<80%,"A",L19<=95%,"B",L19>95%,"C") -> B
B20: flip желтые | C20: ='Юнит 9'!AO15 -> 8803.0231 | D20: =C20/C$105 -> 0.011848383 | E20: =E19+D20 -> 0.96673698 | F20: =IF(AND(E20<=0),"C",IF(E20<=0.8,"A",IF(E20<=0.95,"B","C"))) -> C | G20: =VLOOKUP(B$4:B$104,I$4:M$104,5,0) -> B | I20: sh1 | J20: ='Юнит 9'!U26 -> 37 | K20: =J20/J$105 -> 0.016024253 | L20: =L19+K20 -> 0.9068861 | M20: =_xlfn.IFS(L20<80%,"A",L20<=95%,"B",L20>95%,"C") -> B
B21: wwl8032 коричневые золото | C21: ='Юнит 9'!AO17 -> 7973.8016 | D21: =C21/C$105 -> 0.010732297 | E21: =E20+D21 -> 0.97746927 | F21: =IF(AND(E21<=0),"C",IF(E21<=0.8,"A",IF(E21<=0.95,"B","C"))) -> C | G21: =VLOOKUP(B$4:B$104,I$4:M$104,5,0) -> C | I21: ww 2018 черные | J21: ='Юнит 9'!U49 -> 36 | K21: =J21/J$105 -> 0.015591165 | L21: =L20+K21 -> 0.92247726 | M21: =_xlfn.IFS(L21<80%,"A",L21<=95%,"B",L21>95%,"C") -> B
B22: ww 1022 черные | C22: ='Юнит 9'!AO45 -> 7667.3949 | D22: =C22/C$105 -> 0.010319891 | E22: =E21+D22 -> 0.98778916 | F22: =IF(AND(E22<=0),"C",IF(E22<=0.8,"A",IF(E22<=0.95,"B","C"))) -> C | G22: =VLOOKUP(B$4:B$104,I$4:M$104,5,0) -> B | I22: flip желтые | J22: ='Юнит 9'!U15 -> 28 | K22: =J22/J$105 -> 0.012126462 | L22: =L21+K22 -> 0.93460372 | M22: =_xlfn.IFS(L22<80%,"A",L22<=95%,"B",L22>95%,"C") -> B
B23: ww 1022 желтые | C23: ='Юнит 9'!AO47 -> 6030.9396 | D23: =C23/C$105 -> 0.008117312 | E23: =E22+D23 -> 0.99590648 | F23: =IF(AND(E23<=0),"C",IF(E23<=0.8,"A",IF(E23<=0.95,"B","C"))) -> C | G23: =VLOOKUP(B$4:B$104,I$4:M$104,5,0) -> C | I23: ww 1022 коричневые | J23: ='Юнит 9'!U48 -> 27 | K23: =J23/J$105 -> 0.011693374 | L23: =L22+K23 -> 0.9462971 | M23: =_xlfn.IFS(L23<80%,"A",L23<=95%,"B",L23>95%,"C") -> B
B24: ww 1022 коричневые | C24: ='Юнит 9'!AO48 -> 5263.0991 | D24: =C24/C$105 -> 0.0070838411 | E24: =E23+D24 -> 1.0029903 | F24: =IF(AND(E24<=0),"C",IF(E24<=0.8,"A",IF(E24<=0.95,"B","C"))) -> C | G24: =VLOOKUP(B$4:B$104,I$4:M$104,5,0) -> B | I24: wwl8032 коричневые золото | J24: ='Юнит 9'!U17 -> 24 | K24: =J24/J$105 -> 0.01039411 | L24: =L23+K24 -> 0.95669121 | M24: =_xlfn.IFS(L24<80%,"A",L24<=95%,"B",L24>95%,"C") -> C
B25: ww 203 черные | C25: ='Юнит 9'!AO44 -> 4550.614 | D25: =C25/C$105 -> 0.0061248754 | E25: =E24+D25 -> 1.0091152 | F25: =IF(AND(E25<=0),"C",IF(E25<=0.8,"A",IF(E25<=0.95,"B","C"))) -> C | G25: =VLOOKUP(B$4:B$104,I$4:M$104,5,0) -> C | I25: ww 203 черные | J25: ='Юнит 9'!U44 -> 18 | K25: =J25/J$105 -> 0.0077955825 | L25: =L24+K25 -> 0.96448679 | M25: =_xlfn.IFS(L25<80%,"A",L25<=95%,"B",L25>95%,"C") -> C
B26: ww 2018 желтые | C26: ='Юнит 9'!AO50 -> 3746.9086 | D26: =C26/C$105 -> 0.0050431323 | E26: =E25+D26 -> 1.0141583 | F26: =IF(AND(E26<=0),"C",IF(E26<=0.8,"A",IF(E26<=0.95,"B","C"))) -> C | G26: =VLOOKUP(B$4:B$104,I$4:M$104,5,0) -> C | I26: ww 1022 желтые | J26: ='Юнит 9'!U47 -> 16 | K26: =J26/J$105 -> 0.0069294067 | L26: =L25+K26 -> 0.9714162 | M26: =_xlfn.IFS(L26<80%,"A",L26<=95%,"B",L26>95%,"C") -> C
B27: sh09 | C27: ='Юнит 9'!AO33 -> 1356.6075 | D27: =C27/C$105 -> 0.0018259189 | E27: =E26+D27 -> 1.0159842 | F27: =IF(AND(E27<=0),"C",IF(E27<=0.8,"A",IF(E27<=0.95,"B","C"))) -> C | G27: =VLOOKUP(B$4:B$104,I$4:M$104,5,0) -> C | I27: ww 2018 желтые | J27: ='Юнит 9'!U50 -> 14 | K27: =J27/J$105 -> 0.0060632308 | L27: =L26+K27 -> 0.97747943 | M27: =_xlfn.IFS(L27<80%,"A",L27<=95%,"B",L27>95%,"C") -> C
B28: sh13 | C28: ='Юнит 9'!AO37 -> 1212.156 | D28: =C28/C$105 -> 0.0016314951 | E28: =E27+D28 -> 1.0176157 | F28: =IF(AND(E28<=0),"C",IF(E28<=0.8,"A",IF(E28<=0.95,"B","C"))) -> C | G28: =VLOOKUP(B$4:B$104,I$4:M$104,5,0) -> C | I28: sh2 | J28: ='Юнит 9'!U27 -> 9 | K28: =J28/J$105 -> 0.0038977913 | L28: =L27+K28 -> 0.98137722 | M28: =_xlfn.IFS(L28<80%,"A",L28<=95%,"B",L28>95%,"C") -> C
B29: MR Р1894 черные | C29: ='Юнит 9'!AO89 -> 1151.2595 | D29: =C29/C$105 -> 0.0015495318 | E29: =E28+D29 -> 1.0191653 | F29: =IF(AND(E29<=0),"C",IF(E29<=0.8,"A",IF(E29<=0.95,"B","C"))) -> C | G29: =VLOOKUP(B$4:B$104,I$4:M$104,5,0) -> C | I29: Hengda Optical черные | J29: ='Юнит 9'!U81 -> 5 | K29: =J29/J$105 -> 0.0021654396 | L29: =L28+K29 -> 0.98354266 | M29: =_xlfn.IFS(L29<80%,"A",L29<=95%,"B",L29>95%,"C") -> C
B30: Qianai черные | C30: ='Юнит 9'!AO83 -> 1136.7326 | D30: =C30/C$105 -> 0.0015299794 | E30: =E29+D30 -> 1.0206953 | F30: =IF(AND(E30<=0),"C",IF(E30<=0.8,"A",IF(E30<=0.95,"B","C"))) -> C | G30: =VLOOKUP(B$4:B$104,I$4:M$104,5,0) -> C | I30: sh13 | J30: ='Юнит 9'!U37 -> 4 | K30: =J30/J$105 -> 0.0017323517 | L30: =L29+K30 -> 0.98527501 | M30: =_xlfn.IFS(L30<80%,"A",L30<=95%,"B",L30>95%,"C") -> C
B31: Linhai Baiyi розовая линза | C31: ='Юнит 9'!AO88 -> 1035.2886 | D31: =C31/C$105 -> 0.0013934414 | E31: =E30+D31 -> 1.0220887 | F31: =IF(AND(E31<=0),"C",IF(E31<=0.8,"A",IF(E31<=0.95,"B","C"))) -> C | G31: =VLOOKUP(B$4:B$104,I$4:M$104,5,0) -> C | I31: MANNA2118 | J31: ='Юнит 9'!U71 -> 4 | K31: =J31/J$105 -> 0.0017323517 | L31: =L30+K31 -> 0.98700736 | M31: =_xlfn.IFS(L31<80%,"A",L31<=95%,"B",L31>95%,"C") -> C
B32: MANNA2101 | C32: ='Юнит 9'!AO54 -> 912.49041 | D32: =C32/C$105 -> 0.0012281618 | E32: =E31+D32 -> 1.0233169 | F32: =IF(AND(E32<=0),"C",IF(E32<=0.8,"A",IF(E32<=0.95,"B","C"))) -> C | G32: =VLOOKUP(B$4:B$104,I$4:M$104,5,0) -> C | I32: Linhai Baiyi розовая линза | J32: ='Юнит 9'!U88 -> 4 | K32: =J32/J$105 -> 0.0017323517 | L32: =L31+K32 -> 0.98873971 | M32: =_xlfn.IFS(L32<80%,"A",L32<=95%,"B",L32>95%,"C") -> C
B33: Guangdu серебро серая линза | C33: ='Юнит 9'!AO80 -> 878.64222 | D33: =C33/C$105 -> 0.001182604 | E33: =E32+D33 -> 1.0244995 | F33: =IF(AND(E33<=0),"C",IF(E33<=0.8,"A",IF(E33<=0.95,"B","C"))) -> C | G33: =VLOOKUP(B$4:B$104,I$4:M$104,5,0) -> C | I33: sh10 | J33: ='Юнит 9'!U34 -> 3 | K33: =J33/J$105 -> 0.0012992638 | L33: =L32+K33 -> 0.99003898 | M33: =_xlfn.IFS(L33<80%,"A",L33<=95%,"B",L33>95%,"C") -> C
B34: ww 8010 черные | C34: ='Юнит 9'!AO51 -> 632.71459 | D34: =C34/C$105 -> 0.00085159894 | E34: =E33+D34 -> 1.0253511 | F34: =IF(AND(E34<=0),"C",IF(E34<=0.8,"A",IF(E34<=0.95,"B","C"))) -> C | G34: =VLOOKUP(B$4:B$104,I$4:M$104,5,0) -> C | I34: MANNA2101 | J34: ='Юнит 9'!U54 -> 3 | K34: =J34/J$105 -> 0.0012992638 | L34: =L33+K34 -> 0.99133824 | M34: =_xlfn.IFS(L34<80%,"A",L34<=95%,"B",L34>95%,"C") -> C
B35: Chenlong белые | C35: ='Юнит 9'!AO78 -> 619.99256 | D35: =C35/C$105 -> 0.00083447579 | E35: =E34+D35 -> 1.0261855 | F35: =IF(AND(E35<=0),"C",IF(E35<=0.8,"A",IF(E35<=0.95,"B","C"))) -> C | G35: =VLOOKUP(B$4:B$104,I$4:M$104,5,0) -> C | I35: Guangdu серебро серая линза | J35: ='Юнит 9'!U80 -> 3 | K35: =J35/J$105 -> 0.0012992638 | L35: =L34+K35 -> 0.99263751 | M35: =_xlfn.IFS(L35<80%,"A",L35<=95%,"B",L35>95%,"C") -> C
B36: Linhai Baiyi коричневая линза | C36: ='Юнит 9'!AO86 -> 565.4607 | D36: =C36/C$105 -> 0.00076107891 | E36: =E35+D36 -> 1.0269466 | F36: =IF(AND(E36<=0),"C",IF(E36<=0.8,"A",IF(E36<=0.95,"B","C"))) -> C | G36: =VLOOKUP(B$4:B$104,I$4:M$104,5,0) -> C | I36: sh09 | J36: ='Юнит 9'!U33 -> 2 | K36: =J36/J$105 -> 0.00086617583 | L36: =L35+K36 -> 0.99350368 | M36: =_xlfn.IFS(L36<80%,"A",L36<=95%,"B",L36>95%,"C") -> C
B37: sh17 | C37: ='Юнит 9'!AO41 -> 488.45121 | D37: =C37/C$105 -> 0.00065742838 | E37: =E36+D37 -> 1.027604 | F37: =IF(AND(E37<=0),"C",IF(E37<=0.8,"A",IF(E37<=0.95,"B","C"))) -> C | G37: =VLOOKUP(B$4:B$104,I$4:M$104,5,0) -> C | I37: sh19 | J37: ='Юнит 9'!U43 -> 2 | K37: =J37/J$105 -> 0.00086617583 | L37: =L36+K37 -> 0.99436986 | M37: =_xlfn.IFS(L37<80%,"A",L37<=95%,"B",L37>95%,"C") -> C
B38: MANNA2103 | C38: ='Юнит 9'!AO56 -> 400.694 | D38: =C38/C$105 -> 0.00053931202 | E38: =E37+D38 -> 1.0281434 | F38: =IF(AND(E38<=0),"C",IF(E38<=0.8,"A",IF(E38<=0.95,"B","C"))) -> C | G38: =VLOOKUP(B$4:B$104,I$4:M$104,5,0) -> C | I38: ww 8010 черные | J38: ='Юнит 9'!U51 -> 2 | K38: =J38/J$105 -> 0.00086617583 | L38: =L37+K38 -> 0.99523603 | M38: =_xlfn.IFS(L38<80%,"A",L38<=95%,"B",L38>95%,"C") -> C
B39: MANNA2117 | C39: ='Юнит 9'!AO70 -> 340.65289 | D39: =C39/C$105 -> 0.0004585 | E39: =E35+D39 -> 1.026644 | F39: =IF(AND(E39<=0),"C",IF(E39<=0.8,"A",IF(E39<=0.95,"B","C"))) -> C | G39: =VLOOKUP(B$4:B$104,I$4:M$104,5,0) -> C | I39: Chenlong белые | J39: ='Юнит 9'!U78 -> 2 | K39: =J39/J$105 -> 0.00086617583 | L39: =L35+K39 -> 0.99350368 | M39: =_xlfn.IFS(L39<80%,"A",L39<=95%,"B",L39>95%,"C") -> C
B40: sh10 | C40: ='Юнит 9'!AO34 -> 176.6307 | D40: =C40/C$105 -> 0.00023773518 | E40: =E39+D40 -> 1.0268818 | F40: =IF(AND(E40<=0),"C",IF(E40<=0.8,"A",IF(E40<=0.95,"B","C"))) -> C | G40: =VLOOKUP(B$4:B$104,I$4:M$104,5,0) -> C | I40: Qianai черные | J40: ='Юнит 9'!U83 -> 2 | K40: =J40/J$105 -> 0.00086617583 | L40: =L39+K40 -> 0.99436986 | M40: =_xlfn.IFS(L40<80%,"A",L40<=95%,"B",L40>95%,"C") -> C
B41: sh2 | C41: ='Юнит 9'!AO27 -> 62.179768 | D41: =C41/C$105 -> 8.3690538e-05 | E41: =E40+D41 -> 1.0269655 | F41: =IF(AND(E41<=0),"C",IF(E41<=0.8,"A",IF(E41<=0.95,"B","C"))) -> C | G41: =VLOOKUP(B$4:B$104,I$4:M$104,5,0) -> C | I41: MR Р1894 черные | J41: ='Юнит 9'!U89 -> 2 | K41: =J41/J$105 -> 0.00086617583 | L41: =L40+K41 -> 0.99523603 | M41: =_xlfn.IFS(L41<80%,"A",L41<=95%,"B",L41>95%,"C") -> C
B42: MANNA2118 | C42: ='Юнит 9'!AO71 -> 7.9990662 | D42: =C42/C$105 -> 1.0766302e-05 | E42: =E41+D42 -> 1.0269762 | F42: =IF(AND(E42<=0),"C",IF(E42<=0.8,"A",IF(E42<=0.95,"B","C"))) -> C | G42: =VLOOKUP(B$4:B$104,I$4:M$104,5,0) -> C | I42: sh15 | J42: ='Юнит 9'!U39 -> 1 | K42: =J42/J$105 -> 0.00043308792 | L42: =L41+K42 -> 0.99566912 | M42: =_xlfn.IFS(L42<80%,"A",L42<=95%,"B",L42>95%,"C") -> C
B43: wwl8032 черные серебро | C43: ='Юнит 9'!AO19 -> 0 | D43: =C43/C$105 -> 0 | E43: =E42+D43 -> 1.0269762 | F43: =IF(AND(E43<=0),"C",IF(E43<=0.8,"A",IF(E43<=0.95,"B","C"))) -> C | G43: =VLOOKUP(B$4:B$104,I$4:M$104,5,0) -> C | I43: sh17 | J43: ='Юнит 9'!U41 -> 1 | K43: =J43/J$105 -> 0.00043308792 | L43: =L42+K43 -> 0.99610221 | M43: =_xlfn.IFS(L43<80%,"A",L43<=95%,"B",L43>95%,"C") -> C
B44: sports синие | C44: ='Юнит 9'!AO20 -> 0 | D44: =C44/C$105 -> 0 | E44: =E43+D44 -> 1.0269762 | F44: =IF(AND(E44<=0),"C",IF(E44<=0.8,"A",IF(E44<=0.95,"B","C"))) -> C | G44: =VLOOKUP(B$4:B$104,I$4:M$104,5,0) -> C | I44: MANNA2103 | J44: ='Юнит 9'!U56 -> 1 | K44: =J44/J$105 -> 0.00043308792 | L44: =L43+K44 -> 0.9965353 | M44: =_xlfn.IFS(L44<80%,"A",L44<=95%,"B",L44>95%,"C") -> C
B45: sports красные | C45: ='Юнит 9'!AO22 -> 0 | D45: =C45/C$105 -> 0 | E45: =E44+D45 -> 1.0269762 | F45: =IF(AND(E45<=0),"C",IF(E45<=0.8,"A",IF(E45<=0.95,"B","C"))) -> C | G45: =VLOOKUP(B$4:B$104,I$4:M$104,5,0) -> C | I45: MANNA2105 | J45: ='Юнит 9'!U58 -> 1 | K45: =J45/J$105 -> 0.00043308792 | L45: =L44+K45 -> 0.99696838 | M45: =_xlfn.IFS(L45<80%,"A",L45<=95%,"B",L45>95%,"C") -> C
B46: sportlife черные | C46: ='Юнит 9'!AO23 -> 0 | D46: =C46/C$105 -> 0 | E46: =E45+D46 -> 1.0269762 | F46: =IF(AND(E46<=0),"C",IF(E46<=0.8,"A",IF(E46<=0.95,"B","C"))) -> C | G46: =VLOOKUP(B$4:B$104,I$4:M$104,5,0) -> C | I46: MANNA2117 | J46: ='Юнит 9'!U70 -> 1 | K46: =J46/J$105 -> 0.00043308792 | L46: =L45+K46 -> 0.99740147 | M46: =_xlfn.IFS(L46<80%,"A",L46<=95%,"B",L46>95%,"C") -> C
B47: sportlife синие | C47: ='Юнит 9'!AO24 -> 0 | D47: =C47/C$105 -> 0 | E47: =E46+D47 -> 1.0269762 | F47: =IF(AND(E47<=0),"C",IF(E47<=0.8,"A",IF(E47<=0.95,"B","C"))) -> C | G47: =VLOOKUP(B$4:B$104,I$4:M$104,5,0) -> C | I47: Linhai Baiyi коричневая линза | J47: ='Юнит 9'!U86 -> 1 | K47: =J47/J$105 -> 0.00043308792 | L47: =L46+K47 -> 0.99783456 | M47: =_xlfn.IFS(L47<80%,"A",L47<=95%,"B",L47>95%,"C") -> C
B48: sportlife красные | C48: ='Юнит 9'!AO25 -> 0 | D48: =C48/C$105 -> 0 | E48: =E47+D48 -> 1.0269762 | F48: =IF(AND(E48<=0),"C",IF(E48<=0.8,"A",IF(E48<=0.95,"B","C"))) -> C | G48: =VLOOKUP(B$4:B$104,I$4:M$104,5,0) -> C | I48: Linhai Baiyi серая линза | J48: ='Юнит 9'!U87 -> 1 | K48: =J48/J$105 -> 0.00043308792 | L48: =L47+K48 -> 0.99826765 | M48: =_xlfn.IFS(L48<80%,"A",L48<=95%,"B",L48>95%,"C") -> C
B49: sh4 | C49: ='Юнит 9'!AO29 -> 0 | D49: =C49/C$105 -> 0 | E49: =E48+D49 -> 1.0269762 | F49: =IF(AND(E49<=0),"C",IF(E49<=0.8,"A",IF(E49<=0.95,"B","C"))) -> C | G49: =VLOOKUP(B$4:B$104,I$4:M$104,5,0) -> C | I49: wwl8032 черные серебро | J49: ='Юнит 9'!U19 -> 0 | K49: =J49/J$105 -> 0 | L49: =L48+K49 -> 0.99826765 | M49: =_xlfn.IFS(L49<80%,"A",L49<=95%,"B",L49>95%,"C") -> C
B50: sh07 | C50: ='Юнит 9'!AO31 -> 0 | D50: =C50/C$105 -> 0 | E50: =E49+D50 -> 1.0269762 | F50: =IF(AND(E50<=0),"C",IF(E50<=0.8,"A",IF(E50<=0.95,"B","C"))) -> C | G50: =VLOOKUP(B$4:B$104,I$4:M$104,5,0) -> C | I50: sports синие | J50: ='Юнит 9'!U20 -> 0 | K50: =J50/J$105 -> 0 | L50: =L49+K50 -> 0.99826765 | M50: =_xlfn.IFS(L50<80%,"A",L50<=95%,"B",L50>95%,"C") -> C
B51: sh08 | C51: ='Юнит 9'!AO32 -> 0 | D51: =C51/C$105 -> 0 | E51: =E50+D51 -> 1.0269762 | F51: =IF(AND(E51<=0),"C",IF(E51<=0.8,"A",IF(E51<=0.95,"B","C"))) -> C | G51: =VLOOKUP(B$4:B$104,I$4:M$104,5,0) -> C | I51: sports зеленые | J51: ='Юнит 9'!U21 -> 0 | K51: =J51/J$105 -> 0 | L51: =L50+K51 -> 0.99826765 | M51: =_xlfn.IFS(L51<80%,"A",L51<=95%,"B",L51>95%,"C") -> C
B52: sh11 | C52: ='Юнит 9'!AO35 -> 0 | D52: =C52/C$105 -> 0 | E52: =E51+D52 -> 1.0269762 | F52: =IF(AND(E52<=0),"C",IF(E52<=0.8,"A",IF(E52<=0.95,"B","C"))) -> C | G52: =VLOOKUP(B$4:B$104,I$4:M$104,5,0) -> C | I52: sports красные | J52: ='Юнит 9'!U22 -> 0 | K52: =J52/J$105 -> 0 | L52: =L51+K52 -> 0.99826765 | M52: =_xlfn.IFS(L52<80%,"A",L52<=95%,"B",L52>95%,"C") -> C
B53: sh12 | C53: ='Юнит 9'!AO36 -> 0 | D53: =C53/C$105 -> 0 | E53: =E52+D53 -> 1.0269762 | F53: =IF(AND(E53<=0),"C",IF(E53<=0.8,"A",IF(E53<=0.95,"B","C"))) -> C | G53: =VLOOKUP(B$4:B$104,I$4:M$104,5,0) -> C | I53: sportlife черные | J53: ='Юнит 9'!U23 -> 0 | K53: =J53/J$105 -> 0 | L53: =L52+K53 -> 0.99826765 | M53: =_xlfn.IFS(L53<80%,"A",L53<=95%,"B",L53>95%,"C") -> C
B54: ww 1022 черн-серебро | C54: ='Юнит 9'!AO46 -> 0 | D54: =C54/C$105 -> 0 | E54: =E53+D54 -> 1.0269762 | F54: =IF(AND(E54<=0),"C",IF(E54<=0.8,"A",IF(E54<=0.95,"B","C"))) -> C | G54: =VLOOKUP(B$4:B$104,I$4:M$104,5,0) -> C | I54: sportlife синие | J54: ='Юнит 9'!U24 -> 0 | K54: =J54/J$105 -> 0 | L54: =L53+K54 -> 0.99826765 | M54: =_xlfn.IFS(L54<80%,"A",L54<=95%,"B",L54>95%,"C") -> C
B55: MANNA2104 | C55: ='Юнит 9'!AO57 -> 0 | D55: =C55/C$105 -> 0 | E55: =E54+D55 -> 1.0269762 | F55: =IF(AND(E55<=0),"C",IF(E55<=0.8,"A",IF(E55<=0.95,"B","C"))) -> C | G55: =VLOOKUP(B$4:B$104,I$4:M$104,5,0) -> C | I55: sportlife красные | J55: ='Юнит 9'!U25 -> 0 | K55: =J55/J$105 -> 0 | L55: =L54+K55 -> 0.99826765 | M55: =_xlfn.IFS(L55<80%,"A",L55<=95%,"B",L55>95%,"C") -> C
B56: MANNA2106 | C56: ='Юнит 9'!AO59 -> 0 | D56: =C56/C$105 -> 0 | E56: =E55+D56 -> 1.0269762 | F56: =IF(AND(E56<=0),"C",IF(E56<=0.8,"A",IF(E56<=0.95,"B","C"))) -> C | G56: =VLOOKUP(B$4:B$104,I$4:M$104,5,0) -> C | I56: sh4 | J56: ='Юнит 9'!U29 -> 0 | K56: =J56/J$105 -> 0 | L56: =L55+K56 -> 0.99826765 | M56: =_xlfn.IFS(L56<80%,"A",L56<=95%,"B",L56>95%,"C") -> C
B57: MANNA2109 | C57: ='Юнит 9'!AO62 -> 0 | D57: =C57/C$105 -> 0 | E57: =E56+D57 -> 1.0269762 | F57: =IF(AND(E57<=0),"C",IF(E57<=0.8,"A",IF(E57<=0.95,"B","C"))) -> C | G57: =VLOOKUP(B$4:B$104,I$4:M$104,5,0) -> C | I57: sh06 | J57: ='Юнит 9'!U30 -> 0 | K57: =J57/J$105 -> 0 | L57: =L56+K57 -> 0.99826765 | M57: =_xlfn.IFS(L57<80%,"A",L57<=95%,"B",L57>95%,"C") -> C
B58: MANNA2110 | C58: ='Юнит 9'!AO63 -> 0 | D58: =C58/C$105 -> 0 | E58: =E57+D58 -> 1.0269762 | F58: =IF(AND(E58<=0),"C",IF(E58<=0.8,"A",IF(E58<=0.95,"B","C"))) -> C | G58: =VLOOKUP(B$4:B$104,I$4:M$104,5,0) -> C | I58: sh07 | J58: ='Юнит 9'!U31 -> 0 | K58: =J58/J$105 -> 0 | L58: =L57+K58 -> 0.99826765 | M58: =_xlfn.IFS(L58<80%,"A",L58<=95%,"B",L58>95%,"C") -> C
B59: MANNA2111 | C59: ='Юнит 9'!AO64 -> 0 | D59: =C59/C$105 -> 0 | E59: =E58+D59 -> 1.0269762 | F59: =IF(AND(E59<=0),"C",IF(E59<=0.8,"A",IF(E59<=0.95,"B","C"))) -> C | G59: =VLOOKUP(B$4:B$104,I$4:M$104,5,0) -> C | I59: sh08 | J59: ='Юнит 9'!U32 -> 0 | K59: =J59/J$105 -> 0 | L59: =L58+K59 -> 0.99826765 | M59: =_xlfn.IFS(L59<80%,"A",L59<=95%,"B",L59>95%,"C") -> C
B60: MANNA2112 | C60: ='Юнит 9'!AO65 -> 0 | D60: =C60/C$105 -> 0 | E60: =E59+D60 -> 1.0269762 | F60: =IF(AND(E60<=0),"C",IF(E60<=0.8,"A",IF(E60<=0.95,"B","C"))) -> C | G60: =VLOOKUP(B$4:B$104,I$4:M$104,5,0) -> C | I60: sh11 | J60: ='Юнит 9'!U35 -> 0 | K60: =J60/J$105 -> 0 | L60: =L59+K60 -> 0.99826765 | M60: =_xlfn.IFS(L60<80%,"A",L60<=95%,"B",L60>95%,"C") -> C
B61: MANNA2115 | C61: ='Юнит 9'!AO68 -> 0 | D61: =C61/C$105 -> 0 | E61: =E60+D61 -> 1.0269762 | F61: =IF(AND(E61<=0),"C",IF(E61<=0.8,"A",IF(E61<=0.95,"B","C"))) -> C | G61: =VLOOKUP(B$4:B$104,I$4:M$104,5,0) -> C | I61: sh12 | J61: ='Юнит 9'!U36 -> 0 | K61: =J61/J$105 -> 0 | L61: =L60+K61 -> 0.99826765 | M61: =_xlfn.IFS(L61<80%,"A",L61<=95%,"B",L61>95%,"C") -> C
B62: MANNA2121 | C62: ='Юнит 9'!AO74 -> 0 | D62: =C62/C$105 -> 0 | E62: =E61+D62 -> 1.0269762 | F62: =IF(AND(E62<=0),"C",IF(E62<=0.8,"A",IF(E62<=0.95,"B","C"))) -> C | G62: =VLOOKUP(B$4:B$104,I$4:M$104,5,0) -> C | I62: sh14 | J62: ='Юнит 9'!U38 -> 0 | K62: =J62/J$105 -> 0 | L62: =L61+K62 -> 0.99826765 | M62: =_xlfn.IFS(L62<80%,"A",L62<=95%,"B",L62>95%,"C") -> C
B63: MAIERSHA 03898 C9-08 | C63: ='Юнит 9'!AO94 -> 0 | D63: =C63/C$105 -> 0 | E63: =E62+D63 -> 1.0269762 | F63: =IF(AND(E63<=0),"C",IF(E63<=0.8,"A",IF(E63<=0.95,"B","C"))) -> C | G63: =VLOOKUP(B$4:B$104,I$4:M$104,5,0) -> C | I63: sh16 | J63: ='Юнит 9'!U40 -> 0 | K63: =J63/J$105 -> 0 | L63: =L62+K63 -> 0.99826765 | M63: =_xlfn.IFS(L63<80%,"A",L63<=95%,"B",L63>95%,"C") -> C
B64: MAIERSHA 03914 C9-124 | C64: ='Юнит 9'!AO95 -> 0 | D64: =C64/C$105 -> 0 | E64: =E63+D64 -> 1.0269762 | F64: =IF(AND(E64<=0),"C",IF(E64<=0.8,"A",IF(E64<=0.95,"B","C"))) -> C | G64: =VLOOKUP(B$4:B$104,I$4:M$104,5,0) -> C | I64: sh18 | J64: ='Юнит 9'!U42 -> 0 | K64: =J64/J$105 -> 0 | L64: =L63+K64 -> 0.99826765 | M64: =_xlfn.IFS(L64<80%,"A",L64<=95%,"B",L64>95%,"C") -> C
B65: MARSTON 7171 C1 | C65: ='Юнит 9'!AO96 -> 0 | D65: =C65/C$105 -> 0 | E65: =E64+D65 -> 1.0269762 | F65: =IF(AND(E65<=0),"C",IF(E65<=0.8,"A",IF(E65<=0.95,"B","C"))) -> C | G65: =VLOOKUP(B$4:B$104,I$4:M$104,5,0) -> C | I65: ww 1022 черн-серебро | J65: ='Юнит 9'!U46 -> 0 | K65: =J65/J$105 -> 0 | L65: =L64+K65 -> 0.99826765 | M65: =_xlfn.IFS(L65<80%,"A",L65<=95%,"B",L65>95%,"C") -> C
B66: ЧСЖ_тест | C66: ='Юнит 9'!AO99 -> 0 | D66: =C66/C$105 -> 0 | E66: =E65+D66 -> 1.0269762 | F66: =IF(AND(E66<=0),"C",IF(E66<=0.8,"A",IF(E66<=0.95,"B","C"))) -> C | G66: =VLOOKUP(B$4:B$104,I$4:M$104,5,0) -> C | I66: WW 3055 черный | J66: ='Юнит 9'!U52 -> 0 | K66: =J66/J$105 -> 0 | L66: =L65+K66 -> 0.99826765 | M66: =_xlfn.IFS(L66<80%,"A",L66<=95%,"B",L66>95%,"C") -> C
B67: кс_черные_тест | C67: ='Юнит 9'!AO101 -> 0 | D67: =C67/C$105 -> 0 | E67: =E66+D67 -> 1.0269762 | F67: =IF(AND(E67<=0),"C",IF(E67<=0.8,"A",IF(E67<=0.95,"B","C"))) -> C | G67: =VLOOKUP(B$4:B$104,I$4:M$104,5,0) -> C | I67: WW 3055 коричневый | J67: ='Юнит 9'!U53 -> 0 | K67: =J67/J$105 -> 0 | L67: =L66+K67 -> 0.99826765 | M67: =_xlfn.IFS(L67<80%,"A",L67<=95%,"B",L67>95%,"C") -> C
B68: 1022_коричневые_тест | C68: ='Юнит 9'!AO103 -> 0 | D68: =C68/C$105 -> 0 | E68: =E67+D68 -> 1.0269762 | F68: =IF(AND(E68<=0),"C",IF(E68<=0.8,"A",IF(E68<=0.95,"B","C"))) -> C | G68: =VLOOKUP(B$4:B$104,I$4:M$104,5,0) -> C | I68: MANNA2102 | J68: ='Юнит 9'!U55 -> 0 | K68: =J68/J$105 -> 0 | L68: =L67+K68 -> 0.99826765 | M68: =_xlfn.IFS(L68<80%,"A",L68<=95%,"B",L68>95%,"C") -> C
B69: MANNA2113 | C69: ='Юнит 9'!AO66 -> -0.66730209 | D69: =C69/C$105 -> -8.981518e-07 | E69: =E68+D69 -> 1.0269753 | F69: =IF(AND(E69<=0),"C",IF(E69<=0.8,"A",IF(E69<=0.95,"B","C"))) -> C | G69: =VLOOKUP(B$4:B$104,I$4:M$104,5,0) -> C | I69: MANNA2104 | J69: ='Юнит 9'!U57 -> 0 | K69: =J69/J$105 -> 0 | L69: =L68+K69 -> 0.99826765 | M69: =_xlfn.IFS(L69<80%,"A",L69<=95%,"B",L69>95%,"C") -> C
B70: POMILED 08247 C4-08 | C70: ='Юнит 9'!AO97 -> -2.0019063 | D70: =C70/C$105 -> -2.6944554e-06 | E70: =E69+D70 -> 1.0269726 | F70: =IF(AND(E70<=0),"C",IF(E70<=0.8,"A",IF(E70<=0.95,"B","C"))) -> C | G70: =VLOOKUP(B$4:B$104,I$4:M$104,5,0) -> C | I70: MANNA2106 | J70: ='Юнит 9'!U59 -> 0 | K70: =J70/J$105 -> 0 | L70: =L69+K70 -> 0.99826765 | M70: =_xlfn.IFS(L70<80%,"A",L70<=95%,"B",L70>95%,"C") -> C
B71: MANNA2116 | C71: ='Юнит 9'!AO69 -> -7.340323 | D71: =C71/C$105 -> -9.8796698e-06 | E71: =E70+D71 -> 1.0269628 | F71: =IF(AND(E71<=0),"C",IF(E71<=0.8,"A",IF(E71<=0.95,"B","C"))) -> C | G71: =VLOOKUP(B$4:B$104,I$4:M$104,5,0) -> C | I71: MANNA2107 | J71: ='Юнит 9'!U60 -> 0 | K71: =J71/J$105 -> 0 | L71: =L70+K71 -> 0.99826765 | M71: =_xlfn.IFS(L71<80%,"A",L71<=95%,"B",L71>95%,"C") -> C
B72: YIMEI 2391 C1 | C72: ='Юнит 9'!AO98 -> -7.340323 | D72: =C72/C$105 -> -9.8796698e-06 | E72: =E71+D72 -> 1.0269529 | F72: =IF(AND(E72<=0),"C",IF(E72<=0.8,"A",IF(E72<=0.95,"B","C"))) -> C | G72: =VLOOKUP(B$4:B$104,I$4:M$104,5,0) -> C | I72: MANNA2108 | J72: ='Юнит 9'!U61 -> 0 | K72: =J72/J$105 -> 0 | L72: =L71+K72 -> 0.99826765 | M72: =_xlfn.IFS(L72<80%,"A",L72<=95%,"B",L72>95%,"C") -> C
B73: sh14 | C73: ='Юнит 9'!AO38 -> -30.028594 | D73: =C73/C$105 -> -4.0416831e-05 | E73: =E72+D73 -> 1.0269125 | F73: =IF(AND(E73<=0),"C",IF(E73<=0.8,"A",IF(E73<=0.95,"B","C"))) -> C | G73: =VLOOKUP(B$4:B$104,I$4:M$104,5,0) -> C | I73: MANNA2109 | J73: ='Юнит 9'!U62 -> 0 | K73: =J73/J$105 -> 0 | L73: =L72+K73 -> 0.99826765 | M73: =_xlfn.IFS(L73<80%,"A",L73<=95%,"B",L73>95%,"C") -> C
B74: Ли Сян ретро серебро | C74: ='Юнит 9'!AO93 -> -30.695896 | D74: =C74/C$105 -> -4.1314983e-05 | E74: =E73+D74 -> 1.0268711 | F74: =IF(AND(E74<=0),"C",IF(E74<=0.8,"A",IF(E74<=0.95,"B","C"))) -> C | G74: =VLOOKUP(B$4:B$104,I$4:M$104,5,0) -> C | I74: MANNA2110 | J74: ='Юнит 9'!U63 -> 0 | K74: =J74/J$105 -> 0 | L74: =L73+K74 -> 0.99826765 | M74: =_xlfn.IFS(L74<80%,"A",L74<=95%,"B",L74>95%,"C") -> C
B75: Hengda Optical леопард | C75: ='Юнит 9'!AO82 -> -32.0305 | D75: =C75/C$105 -> -4.3111286e-05 | E75: =E74+D75 -> 1.026828 | F75: =IF(AND(E75<=0),"C",IF(E75<=0.8,"A",IF(E75<=0.95,"B","C"))) -> C | G75: =VLOOKUP(B$4:B$104,I$4:M$104,5,0) -> C | I75: MANNA2111 | J75: ='Юнит 9'!U64 -> 0 | K75: =J75/J$105 -> 0 | L75: =L74+K75 -> 0.99826765 | M75: =_xlfn.IFS(L75<80%,"A",L75<=95%,"B",L75>95%,"C") -> C
B76: Qianai коричневые | C76: ='Юнит 9'!AO84 -> -32.0305 | D76: =C76/C$105 -> -4.3111286e-05 | E76: =E49+D76 -> 1.0269331 | F76: =IF(AND(E76<=0),"C",IF(E76<=0.8,"A",IF(E76<=0.95,"B","C"))) -> C | G76: =VLOOKUP(B$4:B$104,I$4:M$104,5,0) -> C | I76: MANNA2112 | J76: ='Юнит 9'!U65 -> 0 | K76: =J76/J$105 -> 0 | L76: =L49+K76 -> 0.99826765 | M76: =_xlfn.IFS(L76<80%,"A",L76<=95%,"B",L76>95%,"C") -> C
B77: кс_черные_женские | C77: ='Юнит 9'!AO102 -> -32.697802 | D77: =C77/C$105 -> -4.4009438e-05 | E77: =E76+D77 -> 1.0268891 | F77: =IF(AND(E77<=0),"C",IF(E77<=0.8,"A",IF(E77<=0.95,"B","C"))) -> C | G77: =VLOOKUP(B$4:B$104,I$4:M$104,5,0) -> C | I77: MANNA2113 | J77: ='Юнит 9'!U66 -> 0 | K77: =J77/J$105 -> 0 | L77: =L76+K77 -> 0.99826765 | M77: =_xlfn.IFS(L77<80%,"A",L77<=95%,"B",L77>95%,"C") -> C
B78: Taizhou Rayen sport розовый | C78: ='Юнит 9'!AO90 -> -33.365104 | D78: =C78/C$105 -> -4.490759e-05 | E78: =E77+D78 -> 1.0268442 | F78: =IF(AND(E78<=0),"C",IF(E78<=0.8,"A",IF(E78<=0.95,"B","C"))) -> C | G78: =VLOOKUP(B$4:B$104,I$4:M$104,5,0) -> C | I78: MANNA2114 | J78: ='Юнит 9'!U67 -> 0 | K78: =J78/J$105 -> 0 | L78: =L77+K78 -> 0.99826765 | M78: =_xlfn.IFS(L78<80%,"A",L78<=95%,"B",L78>95%,"C") -> C
B79: ЧСЖ_женские | C79: ='Юнит 9'!AO100 -> -33.365104 | D79: =C79/C$105 -> -4.490759e-05 | E79: =E78+D79 -> 1.0267993 | F79: =IF(AND(E79<=0),"C",IF(E79<=0.8,"A",IF(E79<=0.95,"B","C"))) -> C | G79: =VLOOKUP(B$4:B$104,I$4:M$104,5,0) -> C | I79: MANNA2115 | J79: ='Юнит 9'!U68 -> 0 | K79: =J79/J$105 -> 0 | L79: =L78+K79 -> 0.99826765 | M79: =_xlfn.IFS(L79<80%,"A",L79<=95%,"B",L79>95%,"C") -> C
B80: sports зеленые | C80: ='Юнит 9'!AO21 -> -79.58 | D80: =C80/C$105 -> -0.00010711029 | E80: =E79+D80 -> 1.0266922 | F80: =IF(AND(E80<=0),"C",IF(E80<=0.8,"A",IF(E80<=0.95,"B","C"))) -> C | G80: =VLOOKUP(B$4:B$104,I$4:M$104,5,0) -> C | I80: MANNA2116 | J80: ='Юнит 9'!U69 -> 0 | K80: =J80/J$105 -> 0 | L80: =L79+K80 -> 0.99826765 | M80: =_xlfn.IFS(L80<80%,"A",L80<=95%,"B",L80>95%,"C") -> C
B81: MANNA2114 | C81: ='Юнит 9'!AO67 -> -85.14 | D81: =C81/C$105 -> -0.00011459374 | E81: =E80+D81 -> 1.0265776 | F81: =IF(AND(E81<=0),"C",IF(E81<=0.8,"A",IF(E81<=0.95,"B","C"))) -> C | G81: =VLOOKUP(B$4:B$104,I$4:M$104,5,0) -> C | I81: MANNA2119 | J81: ='Юнит 9'!U72 -> 0 | K81: =J81/J$105 -> 0 | L81: =L80+K81 -> 0.99826765 | M81: =_xlfn.IFS(L81<80%,"A",L81<=95%,"B",L81>95%,"C") -> C
B82: MANNA2102 | C82: ='Юнит 9'!AO55 -> -97.32 | D82: =C82/C$105 -> -0.00013098735 | E82: =E81+D82 -> 1.0264466 | F82: =IF(AND(E82<=0),"C",IF(E82<=0.8,"A",IF(E82<=0.95,"B","C"))) -> C | G82: =VLOOKUP(B$4:B$104,I$4:M$104,5,0) -> C | I82: MANNA2120 | J82: ='Юнит 9'!U73 -> 0 | K82: =J82/J$105 -> 0 | L82: =L81+K82 -> 0.99826765 | M82: =_xlfn.IFS(L82<80%,"A",L82<=95%,"B",L82>95%,"C") -> C
B83: MANNA2108 | C83: ='Юнит 9'!AO61 -> -108.77024 | D83: =C83/C$105 -> -0.00014639874 | E83: =E82+D83 -> 1.0263002 | F83: =IF(AND(E83<=0),"C",IF(E83<=0.8,"A",IF(E83<=0.95,"B","C"))) -> C | G83: =VLOOKUP(B$4:B$104,I$4:M$104,5,0) -> C | I83: MANNA2121 | J83: ='Юнит 9'!U74 -> 0 | K83: =J83/J$105 -> 0 | L83: =L82+K83 -> 0.99826765 | M83: =_xlfn.IFS(L83<80%,"A",L83<=95%,"B",L83>95%,"C") -> C
B84: sh16 | C84: ='Юнит 9'!AO40 -> -126.01399 | D84: =C84/C$105 -> -0.00016960788 | E84: =E83+D84 -> 1.0261306 | F84: =IF(AND(E84<=0),"C",IF(E84<=0.8,"A",IF(E84<=0.95,"B","C"))) -> C | G84: =VLOOKUP(B$4:B$104,I$4:M$104,5,0) -> C | I84: MANNA2122 | J84: ='Юнит 9'!U75 -> 0 | K84: =J84/J$105 -> 0 | L84: =L83+K84 -> 0.99826765 | M84: =_xlfn.IFS(L84<80%,"A",L84<=95%,"B",L84>95%,"C") -> C
B85: sh06 | C85: ='Юнит 9'!AO30 -> -131.32 | D85: =C85/C$105 -> -0.00017674948 | E85: =E84+D85 -> 1.0259538 | F85: =IF(AND(E85<=0),"C",IF(E85<=0.8,"A",IF(E85<=0.95,"B","C"))) -> C | G85: =VLOOKUP(B$4:B$104,I$4:M$104,5,0) -> C | I85: Chenlong коричневые | J85: ='Юнит 9'!U77 -> 0 | K85: =J85/J$105 -> 0 | L85: =L84+K85 -> 0.99826765 | M85: =_xlfn.IFS(L85<80%,"A",L85<=95%,"B",L85>95%,"C") -> C
B86: MANNA2122 | C86: ='Юнит 9'!AO75 -> -133.08716 | D86: =C86/C$105 -> -0.00017912797 | E86: =E85+D86 -> 1.0257747 | F86: =IF(AND(E86<=0),"C",IF(E86<=0.8,"A",IF(E86<=0.95,"B","C"))) -> C | G86: =VLOOKUP(B$4:B$104,I$4:M$104,5,0) -> C | I86: Guangdu золото серая линза | J86: ='Юнит 9'!U79 -> 0 | K86: =J86/J$105 -> 0 | L86: =L85+K86 -> 0.99826765 | M86: =_xlfn.IFS(L86<80%,"A",L86<=95%,"B",L86>95%,"C") -> C
B87: sh18 | C87: ='Юнит 9'!AO42 -> -136.51939 | D87: =C87/C$105 -> -0.00018374756 | E87: =E86+D87 -> 1.025591 | F87: =IF(AND(E87<=0),"C",IF(E87<=0.8,"A",IF(E87<=0.95,"B","C"))) -> C | G87: =VLOOKUP(B$4:B$104,I$4:M$104,5,0) -> C | I87: Hengda Optical леопард | J87: ='Юнит 9'!U82 -> 0 | K87: =J87/J$105 -> 0 | L87: =L86+K87 -> 0.99826765 | M87: =_xlfn.IFS(L87<80%,"A",L87<=95%,"B",L87>95%,"C") -> C
B88: WW 3055 коричневый | C88: ='Юнит 9'!AO53 -> -139.8559 | D88: =C88/C$105 -> -0.00018823832 | E88: =E87+D88 -> 1.0254027 | F88: =IF(AND(E88<=0),"C",IF(E88<=0.8,"A",IF(E88<=0.95,"B","C"))) -> C | G88: =VLOOKUP(B$4:B$104,I$4:M$104,5,0) -> C | I88: Qianai коричневые | J88: ='Юнит 9'!U84 -> 0 | K88: =J88/J$105 -> 0 | L88: =L87+K88 -> 0.99826765 | M88: =_xlfn.IFS(L88<80%,"A",L88<=95%,"B",L88>95%,"C") -> C
B89: Chenlong коричневые | C89: ='Юнит 9'!AO77 -> -140.42748 | D89: =C89/C$105 -> -0.00018900764 | E89: =E88+D89 -> 1.0252137 | F89: =IF(AND(E89<=0),"C",IF(E89<=0.8,"A",IF(E89<=0.95,"B","C"))) -> C | G89: =VLOOKUP(B$4:B$104,I$4:M$104,5,0) -> C | I89: Keming Aishi коричневые | J89: ='Юнит 9'!U85 -> 0 | K89: =J89/J$105 -> 0 | L89: =L88+K89 -> 0.99826765 | M89: =_xlfn.IFS(L89<80%,"A",L89<=95%,"B",L89>95%,"C") -> C
B90: Ли Сян ретро золото | C90: ='Юнит 9'!AO92 -> -140.5232 | D90: =C90/C$105 -> -0.00018913647 | E90: =E89+D90 -> 1.0250246 | F90: =IF(AND(E90<=0),"C",IF(E90<=0.8,"A",IF(E90<=0.95,"B","C"))) -> C | G90: =VLOOKUP(B$4:B$104,I$4:M$104,5,0) -> C | I90: Taizhou Rayen sport розовый | J90: ='Юнит 9'!U90 -> 0 | K90: =J90/J$105 -> 0 | L90: =L89+K90 -> 0.99826765 | M90: =_xlfn.IFS(L90<80%,"A",L90<=95%,"B",L90>95%,"C") -> C
B91: MANNA2107 | C91: ='Юнит 9'!AO60 -> -224.14595 | D91: =C91/C$105 -> -0.00030168809 | E91: =E90+D91 -> 1.0247229 | F91: =IF(AND(E91<=0),"C",IF(E91<=0.8,"A",IF(E91<=0.95,"B","C"))) -> C | G91: =VLOOKUP(B$4:B$104,I$4:M$104,5,0) -> C | I91: Иу Диту серый | J91: ='Юнит 9'!U91 -> 0 | K91: =J91/J$105 -> 0 | L91: =L90+K91 -> 0.99826765 | M91: =_xlfn.IFS(L91<80%,"A",L91<=95%,"B",L91>95%,"C") -> C
B92: WW 3055 черный | C92: ='Юнит 9'!AO52 -> -231.40129 | D92: =C92/C$105 -> -0.00031145337 | E92: =E91+D92 -> 1.0244114 | F92: =IF(AND(E92<=0),"C",IF(E92<=0.8,"A",IF(E92<=0.95,"B","C"))) -> C | G92: =VLOOKUP(B$4:B$104,I$4:M$104,5,0) -> C | I92: Ли Сян ретро золото | J92: ='Юнит 9'!U92 -> 0 | K92: =J92/J$105 -> 0 | L92: =L91+K92 -> 0.99826765 | M92: =_xlfn.IFS(L92<80%,"A",L92<=95%,"B",L92>95%,"C") -> C
B93: Guangdu золото серая линза | C93: ='Юнит 9'!AO79 -> -234.2259 | D93: =C93/C$105 -> -0.00031525514 | E93: =E92+D93 -> 1.0240962 | F93: =IF(AND(E93<=0),"C",IF(E93<=0.8,"A",IF(E93<=0.95,"B","C"))) -> C | G93: =VLOOKUP(B$4:B$104,I$4:M$104,5,0) -> C | I93: Ли Сян ретро серебро | J93: ='Юнит 9'!U93 -> 0 | K93: =J93/J$105 -> 0 | L93: =L92+K93 -> 0.99826765 | M93: =_xlfn.IFS(L93<80%,"A",L93<=95%,"B",L93>95%,"C") -> C
B94: sh15 | C94: ='Юнит 9'!AO39 -> -294.55636 | D94: =C94/C$105 -> -0.00039645662 | E94: =E93+D94 -> 1.0236997 | F94: =IF(AND(E94<=0),"C",IF(E94<=0.8,"A",IF(E94<=0.95,"B","C"))) -> C | G94: =VLOOKUP(B$4:B$104,I$4:M$104,5,0) -> C | I94: MAIERSHA 03898 C9-08 | J94: ='Юнит 9'!U94 -> 0 | K94: =J94/J$105 -> 0 | L94: =L93+K94 -> 0.99826765 | M94: =_xlfn.IFS(L94<80%,"A",L94<=95%,"B",L94>95%,"C") -> C
B95: MANNA2120 | C95: ='Юнит 9'!AO73 -> -455.1 | D95: =C95/C$105 -> -0.0006125395 | E95: =E94+D95 -> 1.0230872 | F95: =IF(AND(E95<=0),"C",IF(E95<=0.8,"A",IF(E95<=0.95,"B","C"))) -> C | G95: =VLOOKUP(B$4:B$104,I$4:M$104,5,0) -> C | I95: MAIERSHA 03914 C9-124 | J95: ='Юнит 9'!U95 -> 0 | K95: =J95/J$105 -> 0 | L95: =L94+K95 -> 0.99826765 | M95: =_xlfn.IFS(L95<80%,"A",L95<=95%,"B",L95>95%,"C") -> C
B96: MANNA2119 | C96: ='Юнит 9'!AO72 -> -574.61 | D96: =C96/C$105 -> -0.00077339337 | E96: =E95+D96 -> 1.0223138 | F96: =IF(AND(E96<=0),"C",IF(E96<=0.8,"A",IF(E96<=0.95,"B","C"))) -> C | G96: =VLOOKUP(B$4:B$104,I$4:M$104,5,0) -> C | I96: MARSTON 7171 C1 | J96: ='Юнит 9'!U96 -> 0 | K96: =J96/J$105 -> 0 | L96: =L95+K96 -> 0.99826765 | M96: =_xlfn.IFS(L96<80%,"A",L96<=95%,"B",L96>95%,"C") -> C
B97: Keming Aishi коричневые | C97: ='Юнит 9'!AO85 -> -575.82478 | D97: =C97/C$105 -> -0.00077502839 | E97: =E96+D97 -> 1.0215388 | F97: =IF(AND(E97<=0),"C",IF(E97<=0.8,"A",IF(E97<=0.95,"B","C"))) -> C | G97: =VLOOKUP(B$4:B$104,I$4:M$104,5,0) -> C | I97: POMILED 08247 C4-08 | J97: ='Юнит 9'!U97 -> 0 | K97: =J97/J$105 -> 0 | L97: =L96+K97 -> 0.99826765 | M97: =_xlfn.IFS(L97<80%,"A",L97<=95%,"B",L97>95%,"C") -> C
B98: Иу Диту серый | C98: ='Юнит 9'!AO91 -> -828.20906 | D98: =C98/C$105 -> -0.0011147237 | E98: =E97+D98 -> 1.020424 | F98: =IF(AND(E98<=0),"C",IF(E98<=0.8,"A",IF(E98<=0.95,"B","C"))) -> C | G98: =VLOOKUP(B$4:B$104,I$4:M$104,5,0) -> C | I98: YIMEI 2391 C1 | J98: ='Юнит 9'!U98 -> 0 | K98: =J98/J$105 -> 0 | L98: =L97+K98 -> 0.99826765 | M98: =_xlfn.IFS(L98<80%,"A",L98<=95%,"B",L98>95%,"C") -> C
B99: Hengda Optical черные | C99: ='Юнит 9'!AO81 -> -1380.5552 | D99: =C99/C$105 -> -0.0018581512 | E99: =E93+D99 -> 1.022238 | F99: =IF(AND(E99<=0),"C",IF(E99<=0.8,"A",IF(E99<=0.95,"B","C"))) -> C | G99: =VLOOKUP(B$4:B$104,I$4:M$104,5,0) -> C | I99: ЧСЖ_тест | J99: ='Юнит 9'!U99 -> 0 | K99: =J99/J$105 -> 0 | L99: =L93+K99 -> 0.99826765 | M99: =_xlfn.IFS(L99<80%,"A",L99<=95%,"B",L99>95%,"C") -> C
B100: Chenlong черные | C100: ='Юнит 9'!AO76 -> -1506.429 | D100: =C100/C$105 -> -0.0020275703 | E100: =E94+D100 -> 1.0216722 | F100: =IF(AND(E100<=0),"C",IF(E100<=0.8,"A",IF(E100<=0.95,"B","C"))) -> C | G100: =VLOOKUP(B$4:B$104,I$4:M$104,5,0) -> C | I100: ЧСЖ_женские | J100: ='Юнит 9'!U100 -> 0 | K100: =J100/J$105 -> 0 | L100: =L94+K100 -> 0.99826765 | M100: =_xlfn.IFS(L100<80%,"A",L100<=95%,"B",L100>95%,"C") -> C
B101: Linhai Baiyi серая линза | C101: ='Юнит 9'!AO87 -> -1531.8312 | D101: =C101/C$105 -> -0.0020617603 | E101: =E95+D101 -> 1.0210254 | F101: =IF(AND(E101<=0),"C",IF(E101<=0.8,"A",IF(E101<=0.95,"B","C"))) -> C | G101: =VLOOKUP(B$4:B$104,I$4:M$104,5,0) -> C | I101: кс_черные_тест | J101: ='Юнит 9'!U101 -> 0 | K101: =J101/J$105 -> 0 | L101: =L95+K101 -> 0.99826765 | M101: =_xlfn.IFS(L101<80%,"A",L101<=95%,"B",L101>95%,"C") -> C
...

Sheet АВС 8
B2: ОЧКИ
C3: Прибыль | D3: % прибыль | E3: Доля | F3: ABC прибыль | G3: ABC кол-во | J3: Кол-во | K3: % кол-во | L3: Доля | M3: ABC кол-во
B4: QS черные PZ | C4: ='Юнит 8'!AO4 -> 187586.52 | D4: =C4/C$105 -> 0.32723328 | E4: =D4 -> 0.32723328 | F4: =IF(AND(E4<=0),"C",IF(E4<=0.8,"A",IF(E4<=0.95,"B","C"))) -> A | G4: =VLOOKUP(B$4:B$104,I$4:M$104,5,0) -> A | I4: QS черные PZ | J4: ='Юнит 8'!U4 -> 553 | K4: =J4/J$105 -> 0.2455595 | L4: =K4 -> 0.2455595 | M4: =_xlfn.IFS(L4<80%,"A",L4<=95%,"B",L4>95%,"C") -> A | P4: A | Q4: 0.8
B5: QS коричневые PZ | C5: ='Юнит 8'!AO7 -> 67172.51 | D5: =C5/C$105 -> 0.11717836 | E5: =E4+D5 -> 0.44441164 | F5: =IF(AND(E5<=0),"C",IF(E5<=0.8,"A",IF(E5<=0.95,"B","C"))) -> A | G5: =VLOOKUP(B$4:B$104,I$4:M$104,5,0) -> A | I5: QS коричневые PZ | J5: ='Юнит 8'!U7 -> 206 | K5: =J5/J$105 -> 0.091474245 | L5: =L4+K5 -> 0.33703375 | M5: =_xlfn.IFS(L5<80%,"A",L5<=95%,"B",L5>95%,"C") -> A | P5: B | Q5: 0.15
B6: th черн | C6: ='Юнит 8'!AO9 -> 42084.801 | D6: =C6/C$105 -> 0.073414376 | E6: =E5+D6 -> 0.51782601 | F6: =IF(AND(E6<=0),"C",IF(E6<=0.8,"A",IF(E6<=0.95,"B","C"))) -> A | G6: =VLOOKUP(B$4:B$104,I$4:M$104,5,0) -> A | I6: th син | J6: ='Юнит 8'!U10 -> 165 | K6: =J6/J$105 -> 0.073268206 | L6: =L5+K6 -> 0.41030195 | M6: =_xlfn.IFS(L6<80%,"A",L6<=95%,"B",L6>95%,"C") -> A | P6: C | Q6: 0.05
B7: QS синие PZ | C7: ='Юнит 8'!AO5 -> 41232.197 | D7: =C7/C$105 -> 0.071927061 | E7: =E6+D7 -> 0.58975308 | F7: =IF(AND(E7<=0),"C",IF(E7<=0.8,"A",IF(E7<=0.95,"B","C"))) -> A | G7: =VLOOKUP(B$4:B$104,I$4:M$104,5,0) -> A | I7: QS синие PZ | J7: ='Юнит 8'!U5 -> 151 | K7: =J7/J$105 -> 0.06705151 | L7: =L6+K7 -> 0.47735346 | M7: =_xlfn.IFS(L7<80%,"A",L7<=95%,"B",L7>95%,"C") -> A
B8: th син | C8: ='Юнит 8'!AO10 -> 35943.92 | D8: =C8/C$105 -> 0.062701983 | E8: =E7+D8 -> 0.65245506 | F8: =IF(AND(E8<=0),"C",IF(E8<=0.8,"A",IF(E8<=0.95,"B","C"))) -> A | G8: =VLOOKUP(B$4:B$104,I$4:M$104,5,0) -> A | I8: th черн | J8: ='Юнит 8'!U9 -> 135 | K8: =J8/J$105 -> 0.059946714 | L8: =L7+K8 -> 0.53730018 | M8: =_xlfn.IFS(L8<80%,"A",L8<=95%,"B",L8>95%,"C") -> A
B9: QS желтые PZ | C9: ='Юнит 8'!AO6 -> 35702.024 | D9: =C9/C$105 -> 0.06228001 | E9: =E8+D9 -> 0.71473507 | F9: =IF(AND(E9<=0),"C",IF(E9<=0.8,"A",IF(E9<=0.95,"B","C"))) -> A | G9: =VLOOKUP(B$4:B$104,I$4:M$104,5,0) -> A | I9: QS желтые PZ | J9: ='Юнит 8'!U6 -> 126 | K9: =J9/J$105 -> 0.055950266 | L9: =L8+K9 -> 0.59325044 | M9: =_xlfn.IFS(L9<80%,"A",L9<=95%,"B",L9>95%,"C") -> A
B10: flip коричневые | C10: ='Юнит 8'!AO16 -> 24641.241 | D10: =C10/C$105 -> 0.042985147 | E10: =E9+D10 -> 0.75772022 | F10: =IF(AND(E10<=0),"C",IF(E10<=0.8,"A",IF(E10<=0.95,"B","C"))) -> A | G10: =VLOOKUP(B$4:B$104,I$4:M$104,5,0) -> A | I10: sh3 | J10: ='Юнит 8'!U28 -> 96 | K10: =J10/J$105 -> 0.042628774 | L10: =L9+K10 -> 0.63587922 | M10: =_xlfn.IFS(L10<80%,"A",L10<=95%,"B",L10>95%,"C") -> A
B11: flip черные | C11: ='Юнит 8'!AO13 -> 22233.993 | D11: =C11/C$105 -> 0.03878585 | E11: =E10+D11 -> 0.79650607 | F11: =IF(AND(E11<=0),"C",IF(E11<=0.8,"A",IF(E11<=0.95,"B","C"))) -> A | G11: =VLOOKUP(B$4:B$104,I$4:M$104,5,0) -> A | I11: flip черные | J11: ='Юнит 8'!U13 -> 92 | K11: =J11/J$105 -> 0.040852575 | L11: =L10+K11 -> 0.67673179 | M11: =_xlfn.IFS(L11<80%,"A",L11<=95%,"B",L11>95%,"C") -> A
B12: sh3 | C12: ='Юнит 8'!AO28 -> 21229.534 | D12: =C12/C$105 -> 0.03703363 | E12: =E11+D12 -> 0.8335397 | F12: =IF(AND(E12<=0),"C",IF(E12<=0.8,"A",IF(E12<=0.95,"B","C"))) -> B | G12: =VLOOKUP(B$4:B$104,I$4:M$104,5,0) -> A | I12: flip коричневые | J12: ='Юнит 8'!U16 -> 85 | K12: =J12/J$105 -> 0.037744227 | L12: =L11+K12 -> 0.71447602 | M12: =_xlfn.IFS(L12<80%,"A",L12<=95%,"B",L12>95%,"C") -> A
B13: th коричн | C13: ='Юнит 8'!AO12 -> 16922.863 | D13: =C13/C$105 -> 0.029520905 | E13: =E12+D13 -> 0.8630606 | F13: =IF(AND(E13<=0),"C",IF(E13<=0.8,"A",IF(E13<=0.95,"B","C"))) -> B | G13: =VLOOKUP(B$4:B$104,I$4:M$104,5,0) -> B | I13: черные с железкой классика | J13: ='Юнит 8'!U3 -> 74 | K13: =J13/J$105 -> 0.03285968 | L13: =L12+K13 -> 0.7473357 | M13: =_xlfn.IFS(L13<80%,"A",L13<=95%,"B",L13>95%,"C") -> A
B14: MR8854 C2 Жен | C14: ='Юнит 8'!AO8 -> 15508.025 | D14: =C14/C$105 -> 0.027052807 | E14: =E13+D14 -> 0.89011341 | F14: =IF(AND(E14<=0),"C",IF(E14<=0.8,"A",IF(E14<=0.95,"B","C"))) -> B | G14: =VLOOKUP(B$4:B$104,I$4:M$104,5,0) -> A | I14: MR8854 C2 Жен | J14: ='Юнит 8'!U8 -> 68 | K14: =J14/J$105 -> 0.030195382 | L14: =L13+K14 -> 0.77753108 | M14: =_xlfn.IFS(L14<80%,"A",L14<=95%,"B",L14>95%,"C") -> A
B15: th желт | C15: ='Юнит 8'!AO11 -> 12076.316 | D15: =C15/C$105 -> 0.021066399 | E15: =E14+D15 -> 0.91117981 | F15: =IF(AND(E15<=0),"C",IF(E15<=0.8,"A",IF(E15<=0.95,"B","C"))) -> B | G15: =VLOOKUP(B$4:B$104,I$4:M$104,5,0) -> B | I15: th коричн | J15: ='Юнит 8'!U12 -> 68 | K15: =J15/J$105 -> 0.030195382 | L15: =L14+K15 -> 0.80772647 | M15: =_xlfn.IFS(L15<80%,"A",L15<=95%,"B",L15>95%,"C") -> B
B16: wwl8032 коричневые золото | C16: ='Юнит 8'!AO17 -> 9301.5132 | D16: =C16/C$105 -> 0.016225924 | E16: =E15+D16 -> 0.92740573 | F16: =IF(AND(E16<=0),"C",IF(E16<=0.8,"A",IF(E16<=0.95,"B","C"))) -> B | G16: =VLOOKUP(B$4:B$104,I$4:M$104,5,0) -> B | I16: ww 1022 черные | J16: ='Юнит 8'!U45 -> 67 | K16: =J16/J$105 -> 0.029751332 | L16: =L15+K16 -> 0.8374778 | M16: =_xlfn.IFS(L16<80%,"A",L16<=95%,"B",L16>95%,"C") -> B
B17: flip синие | C17: ='Юнит 8'!AO14 -> 9186.5031 | D17: =C17/C$105 -> 0.016025296 | E17: =E16+D17 -> 0.94343103 | F17: =IF(AND(E17<=0),"C",IF(E17<=0.8,"A",IF(E17<=0.95,"B","C"))) -> B | G17: =VLOOKUP(B$4:B$104,I$4:M$104,5,0) -> B | I17: th желт | J17: ='Юнит 8'!U11 -> 42 | K17: =J17/J$105 -> 0.018650089 | L17: =L16+K17 -> 0.85612789 | M17: =_xlfn.IFS(L17<80%,"A",L17<=95%,"B",L17>95%,"C") -> B
B18: ww 1022 коричневые | C18: ='Юнит 8'!AO48 -> 9125.125 | D18: =C18/C$105 -> 0.015918226 | E18: =E17+D18 -> 0.95934925 | F18: =IF(AND(E18<=0),"C",IF(E18<=0.8,"A",IF(E18<=0.95,"B","C"))) -> C | G18: =VLOOKUP(B$4:B$104,I$4:M$104,5,0) -> B | I18: wwl8032 хром металл | J18: ='Юнит 8'!U18 -> 41 | K18: =J18/J$105 -> 0.018206039 | L18: =L17+K18 -> 0.87433393 | M18: =_xlfn.IFS(L18<80%,"A",L18<=95%,"B",L18>95%,"C") -> B
B19: ww 1022 черные | C19: ='Юнит 8'!AO45 -> 8595.4514 | D19: =C19/C$105 -> 0.014994242 | E19: =E18+D19 -> 0.97434349 | F19: =IF(AND(E19<=0),"C",IF(E19<=0.8,"A",IF(E19<=0.95,"B","C"))) -> C | G19: =VLOOKUP(B$4:B$104,I$4:M$104,5,0) -> B | I19: flip синие | J19: ='Юнит 8'!U14 -> 34 | K19: =J19/J$105 -> 0.015097691 | L19: =L18+K19 -> 0.88943162 | M19: =_xlfn.IFS(L19<80%,"A",L19<=95%,"B",L19>95%,"C") -> B
B20: wwl8032 хром металл | C20: ='Юнит 8'!AO18 -> 7347.995 | D20: =C20/C$105 -> 0.012818131 | E20: =E19+D20 -> 0.98716162 | F20: =IF(AND(E20<=0),"C",IF(E20<=0.8,"A",IF(E20<=0.95,"B","C"))) -> C | G20: =VLOOKUP(B$4:B$104,I$4:M$104,5,0) -> B | I20: flip желтые | J20: ='Юнит 8'!U15 -> 32 | K20: =J20/J$105 -> 0.014209591 | L20: =L19+K20 -> 0.90364121 | M20: =_xlfn.IFS(L20<80%,"A",L20<=95%,"B",L20>95%,"C") -> B
B21: flip желтые | C21: ='Юнит 8'!AO15 -> 6832.1996 | D21: =C21/C$105 -> 0.011918357 | E21: =E20+D21 -> 0.99907998 | F21: =IF(AND(E21<=0),"C",IF(E21<=0.8,"A",IF(E21<=0.95,"B","C"))) -> C | G21: =VLOOKUP(B$4:B$104,I$4:M$104,5,0) -> B | I21: ww 1022 коричневые | J21: ='Юнит 8'!U48 -> 31 | K21: =J21/J$105 -> 0.013765542 | L21: =L20+K21 -> 0.91740675 | M21: =_xlfn.IFS(L21<80%,"A",L21<=95%,"B",L21>95%,"C") -> B
B22: ww 2018 черные | C22: ='Юнит 8'!AO49 -> 6086.6702 | D22: =C22/C$105 -> 0.010617826 | E22: =E21+D22 -> 1.0096978 | F22: =IF(AND(E22<=0),"C",IF(E22<=0.8,"A",IF(E22<=0.95,"B","C"))) -> C | G22: =VLOOKUP(B$4:B$104,I$4:M$104,5,0) -> B | I22: wwl8032 коричневые золото | J22: ='Юнит 8'!U17 -> 30 | K22: =J22/J$105 -> 0.013321492 | L22: =L21+K22 -> 0.93072824 | M22: =_xlfn.IFS(L22<80%,"A",L22<=95%,"B",L22>95%,"C") -> B
B23: ww 1022 желтые | C23: ='Юнит 8'!AO47 -> 4570.1747 | D23: =C23/C$105 -> 0.0079723919 | E23: =E22+D23 -> 1.0176702 | F23: =IF(AND(E23<=0),"C",IF(E23<=0.8,"A",IF(E23<=0.95,"B","C"))) -> C | G23: =VLOOKUP(B$4:B$104,I$4:M$104,5,0) -> C | I23: ww 2018 черные | J23: ='Юнит 8'!U49 -> 29 | K23: =J23/J$105 -> 0.012877442 | L23: =L22+K23 -> 0.94360568 | M23: =_xlfn.IFS(L23<80%,"A",L23<=95%,"B",L23>95%,"C") -> B
B24: MR Р1894 черные | C24: ='Юнит 8'!AO89 -> 2625.4827 | D24: =C24/C$105 -> 0.004579995 | E24: =E23+D24 -> 1.0222502 | F24: =IF(AND(E24<=0),"C",IF(E24<=0.8,"A",IF(E24<=0.95,"B","C"))) -> C | G24: =VLOOKUP(B$4:B$104,I$4:M$104,5,0) -> C | I24: sh1 | J24: ='Юнит 8'!U26 -> 26 | K24: =J24/J$105 -> 0.011545293 | L24: =L23+K24 -> 0.95515098 | M24: =_xlfn.IFS(L24<80%,"A",L24<=95%,"B",L24>95%,"C") -> C
B25: Chenlong черные | C25: ='Юнит 8'!AO76 -> 945.21524 | D25: =C25/C$105 -> 0.0016488705 | E25: =E24+D25 -> 1.0238991 | F25: =IF(AND(E25<=0),"C",IF(E25<=0.8,"A",IF(E25<=0.95,"B","C"))) -> C | G25: =VLOOKUP(B$4:B$104,I$4:M$104,5,0) -> C | I25: ww 1022 желтые | J25: ='Юнит 8'!U47 -> 13 | K25: =J25/J$105 -> 0.0057726465 | L25: =L24+K25 -> 0.96092362 | M25: =_xlfn.IFS(L25<80%,"A",L25<=95%,"B",L25>95%,"C") -> C
B26: sportlife красные | C26: ='Юнит 8'!AO25 -> 749.7631 | D26: =C26/C$105 -> 0.0013079161 | E26: =E25+D26 -> 1.025207 | F26: =IF(AND(E26<=0),"C",IF(E26<=0.8,"A",IF(E26<=0.95,"B","C"))) -> C | G26: =VLOOKUP(B$4:B$104,I$4:M$104,5,0) -> C | I26: ww 203 черные | J26: ='Юнит 8'!U44 -> 9 | K26: =J26/J$105 -> 0.0039964476 | L26: =L25+K26 -> 0.96492007 | M26: =_xlfn.IFS(L26<80%,"A",L26<=95%,"B",L26>95%,"C") -> C
B27: MANNA2114 | C27: ='Юнит 8'!AO67 -> 701.1945 | D27: =C27/C$105 -> 0.0012231912 | E27: =E26+D27 -> 1.0264302 | F27: =IF(AND(E27<=0),"C",IF(E27<=0.8,"A",IF(E27<=0.95,"B","C"))) -> C | G27: =VLOOKUP(B$4:B$104,I$4:M$104,5,0) -> C | I27: sh09 | J27: ='Юнит 8'!U33 -> 8 | K27: =J27/J$105 -> 0.0035523979 | L27: =L26+K27 -> 0.96847247 | M27: =_xlfn.IFS(L27<80%,"A",L27<=95%,"B",L27>95%,"C") -> C
B28: Linhai Baiyi розовая линза | C28: ='Юнит 8'!AO88 -> 653.61643 | D28: =C28/C$105 -> 0.0011401941 | E28: =E27+D28 -> 1.0275704 | F28: =IF(AND(E28<=0),"C",IF(E28<=0.8,"A",IF(E28<=0.95,"B","C"))) -> C | G28: =VLOOKUP(B$4:B$104,I$4:M$104,5,0) -> C | I28: ww 2018 желтые | J28: ='Юнит 8'!U50 -> 7 | K28: =J28/J$105 -> 0.0031083481 | L28: =L27+K28 -> 0.97158082 | M28: =_xlfn.IFS(L28<80%,"A",L28<=95%,"B",L28>95%,"C") -> C
B29: кс_черные_тест | C29: ='Юнит 8'!AO101 -> 617.01293 | D29: =C29/C$105 -> 0.0010763415 | E29: =E28+D29 -> 1.0286467 | F29: =IF(AND(E29<=0),"C",IF(E29<=0.8,"A",IF(E29<=0.95,"B","C"))) -> C | G29: =VLOOKUP(B$4:B$104,I$4:M$104,5,0) -> C | I29: sh2 | J29: ='Юнит 8'!U27 -> 6 | K29: =J29/J$105 -> 0.0026642984 | L29: =L28+K29 -> 0.97424512 | M29: =_xlfn.IFS(L29<80%,"A",L29<=95%,"B",L29>95%,"C") -> C
B30: MANNA2107 | C30: ='Юнит 8'!AO60 -> 587.15632 | D30: =C30/C$105 -> 0.0010242585 | E30: =E29+D30 -> 1.029671 | F30: =IF(AND(E30<=0),"C",IF(E30<=0.8,"A",IF(E30<=0.95,"B","C"))) -> C | G30: =VLOOKUP(B$4:B$104,I$4:M$104,5,0) -> C | I30: Hengda Optical черные | J30: ='Юнит 8'!U81 -> 6 | K30: =J30/J$105 -> 0.0026642984 | L30: =L29+K30 -> 0.97690941 | M30: =_xlfn.IFS(L30<80%,"A",L30<=95%,"B",L30>95%,"C") -> C
B31: ww 8010 черные | C31: ='Юнит 8'!AO51 -> 506.35831 | D31: =C31/C$105 -> 0.00088331127 | E31: =E30+D31 -> 1.0305543 | F31: =IF(AND(E31<=0),"C",IF(E31<=0.8,"A",IF(E31<=0.95,"B","C"))) -> C | G31: =VLOOKUP(B$4:B$104,I$4:M$104,5,0) -> C | I31: sh10 | J31: ='Юнит 8'!U34 -> 5 | K31: =J31/J$105 -> 0.0022202487 | L31: =L30+K31 -> 0.97912966 | M31: =_xlfn.IFS(L31<80%,"A",L31<=95%,"B",L31>95%,"C") -> C
B32: sh15 | C32: ='Юнит 8'!AO39 -> 506.18738 | D32: =C32/C$105 -> 0.00088301311 | E32: =E31+D32 -> 1.0314373 | F32: =IF(AND(E32<=0),"C",IF(E32<=0.8,"A",IF(E32<=0.95,"B","C"))) -> C | G32: =VLOOKUP(B$4:B$104,I$4:M$104,5,0) -> C | I32: MR Р1894 черные | J32: ='Юнит 8'!U89 -> 4 | K32: =J32/J$105 -> 0.0017761989 | L32: =L31+K32 -> 0.98090586 | M32: =_xlfn.IFS(L32<80%,"A",L32<=95%,"B",L32>95%,"C") -> C
B33: MANNA2119 | C33: ='Юнит 8'!AO72 -> 459.0738 | D33: =C33/C$105 -> 0.00080082633 | E33: =E32+D33 -> 1.0322381 | F33: =IF(AND(E33<=0),"C",IF(E33<=0.8,"A",IF(E33<=0.95,"B","C"))) -> C | G33: =VLOOKUP(B$4:B$104,I$4:M$104,5,0) -> C | I33: MANNA2119 | J33: ='Юнит 8'!U72 -> 3 | K33: =J33/J$105 -> 0.0013321492 | L33: =L32+K33 -> 0.98223801 | M33: =_xlfn.IFS(L33<80%,"A",L33<=95%,"B",L33>95%,"C") -> C
B34: sh09 | C34: ='Юнит 8'!AO33 -> 436.78676 | D34: =C34/C$105 -> 0.00076194794 | E34: =E33+D34 -> 1.0330001 | F34: =IF(AND(E34<=0),"C",IF(E34<=0.8,"A",IF(E34<=0.95,"B","C"))) -> C | G34: =VLOOKUP(B$4:B$104,I$4:M$104,5,0) -> C | I34: MANNA2120 | J34: ='Юнит 8'!U73 -> 3 | K34: =J34/J$105 -> 0.0013321492 | L34: =L33+K34 -> 0.98357016 | M34: =_xlfn.IFS(L34<80%,"A",L34<=95%,"B",L34>95%,"C") -> C
B35: Linhai Baiyi серая линза | C35: ='Юнит 8'!AO87 -> 430.51833 | D35: =C35/C$105 -> 0.00075101305 | E35: =E34+D35 -> 1.0337511 | F35: =IF(AND(E35<=0),"C",IF(E35<=0.8,"A",IF(E35<=0.95,"B","C"))) -> C | G35: =VLOOKUP(B$4:B$104,I$4:M$104,5,0) -> C | I35: Chenlong черные | J35: ='Юнит 8'!U76 -> 3 | K35: =J35/J$105 -> 0.0013321492 | L35: =L34+K35 -> 0.98490231 | M35: =_xlfn.IFS(L35<80%,"A",L35<=95%,"B",L35>95%,"C") -> C
B36: sh19 | C36: ='Юнит 8'!AO43 -> 376.87501 | D36: =C36/C$105 -> 0.00065743554 | E36: =E35+D36 -> 1.0344085 | F36: =IF(AND(E36<=0),"C",IF(E36<=0.8,"A",IF(E36<=0.95,"B","C"))) -> C | G36: =VLOOKUP(B$4:B$104,I$4:M$104,5,0) -> C | I36: Linhai Baiyi розовая линза | J36: ='Юнит 8'!U88 -> 3 | K36: =J36/J$105 -> 0.0013321492 | L36: =L35+K36 -> 0.98623446 | M36: =_xlfn.IFS(L36<80%,"A",L36<=95%,"B",L36>95%,"C") -> C
B37: sh10 | C37: ='Юнит 8'!AO34 -> 370.3062 | D37: =C37/C$105 -> 0.00064597664 | E37: =E36+D37 -> 1.0350545 | F37: =IF(AND(E37<=0),"C",IF(E37<=0.8,"A",IF(E37<=0.95,"B","C"))) -> C | G37: =VLOOKUP(B$4:B$104,I$4:M$104,5,0) -> C | I37: sportlife красные | J37: ='Юнит 8'!U25 -> 2 | K37: =J37/J$105 -> 0.00088809947 | L37: =L36+K37 -> 0.98712256 | M37: =_xlfn.IFS(L37<80%,"A",L37<=95%,"B",L37>95%,"C") -> C
B38: Иу Диту серый | C38: ='Юнит 8'!AO91 -> 324.66858 | D38: =C38/C$105 -> 0.0005663646 | E38: =E37+D38 -> 1.0356209 | F38: =IF(AND(E38<=0),"C",IF(E38<=0.8,"A",IF(E38<=0.95,"B","C"))) -> C | G38: =VLOOKUP(B$4:B$104,I$4:M$104,5,0) -> C | I38: sh07 | J38: ='Юнит 8'!U31 -> 2 | K38: =J38/J$105 -> 0.00088809947 | L38: =L37+K38 -> 0.98801066 | M38: =_xlfn.IFS(L38<80%,"A",L38<=95%,"B",L38>95%,"C") -> C
B39: sports красные | C39: ='Юнит 8'!AO22 -> 319.18295 | D39: =C39/C$105 -> 0.00055679525 | E39: =E35+D39 -> 1.0343079 | F39: =IF(AND(E39<=0),"C",IF(E39<=0.8,"A",IF(E39<=0.95,"B","C"))) -> C | G39: =VLOOKUP(B$4:B$104,I$4:M$104,5,0) -> C | I39: sh15 | J39: ='Юнит 8'!U39 -> 2 | K39: =J39/J$105 -> 0.00088809947 | L39: =L35+K39 -> 0.98579041 | M39: =_xlfn.IFS(L39<80%,"A",L39<=95%,"B",L39>95%,"C") -> C
B40: MANNA2120 | C40: ='Юнит 8'!AO73 -> 293.2309 | D40: =C40/C$105 -> 0.00051152347 | E40: =E39+D40 -> 1.0348194 | F40: =IF(AND(E40<=0),"C",IF(E40<=0.8,"A",IF(E40<=0.95,"B","C"))) -> C | G40: =VLOOKUP(B$4:B$104,I$4:M$104,5,0) -> C | I40: sh19 | J40: ='Юнит 8'!U43 -> 2 | K40: =J40/J$105 -> 0.00088809947 | L40: =L39+K40 -> 0.98667851 | M40: =_xlfn.IFS(L40<80%,"A",L40<=95%,"B",L40>95%,"C") -> C
B41: ww 203 черные | C41: ='Юнит 8'!AO44 -> 285.19976 | D41: =C41/C$105 -> 0.00049751364 | E41: =E40+D41 -> 1.0353169 | F41: =IF(AND(E41<=0),"C",IF(E41<=0.8,"A",IF(E41<=0.95,"B","C"))) -> C | G41: =VLOOKUP(B$4:B$104,I$4:M$104,5,0) -> C | I41: ww 8010 черные | J41: ='Юнит 8'!U51 -> 2 | K41: =J41/J$105 -> 0.00088809947 | L41: =L40+K41 -> 0.98756661 | M41: =_xlfn.IFS(L41<80%,"A",L41<=95%,"B",L41>95%,"C") -> C
B42: MANNA2121 | C42: ='Юнит 8'!AO74 -> 275.4758 | D42: =C42/C$105 -> 0.00048055078 | E42: =E41+D42 -> 1.0357975 | F42: =IF(AND(E42<=0),"C",IF(E42<=0.8,"A",IF(E42<=0.95,"B","C"))) -> C | G42: =VLOOKUP(B$4:B$104,I$4:M$104,5,0) -> C | I42: MANNA2105 | J42: ='Юнит 8'!U58 -> 2 | K42: =J42/J$105 -> 0.00088809947 | L42: =L41+K42 -> 0.98845471 | M42: =_xlfn.IFS(L42<80%,"A",L42<=95%,"B",L42>95%,"C") -> C
B43: sh07 | C43: ='Юнит 8'!AO31 -> 263.4797 | D43: =C43/C$105 -> 0.00045962431 | E43: =E42+D43 -> 1.0362571 | F43: =IF(AND(E43<=0),"C",IF(E43<=0.8,"A",IF(E43<=0.95,"B","C"))) -> C | G43: =VLOOKUP(B$4:B$104,I$4:M$104,5,0) -> C | I43: MANNA2107 | J43: ='Юнит 8'!U60 -> 2 | K43: =J43/J$105 -> 0.00088809947 | L43: =L42+K43 -> 0.98934281 | M43: =_xlfn.IFS(L43<80%,"A",L43<=95%,"B",L43>95%,"C") -> C
B44: WW 3055 коричневый | C44: ='Юнит 8'!AO53 -> 251.9858 | D44: =C44/C$105 -> 0.0004395739 | E44: =E43+D44 -> 1.0366967 | F44: =IF(AND(E44<=0),"C",IF(E44<=0.8,"A",IF(E44<=0.95,"B","C"))) -> C | G44: =VLOOKUP(B$4:B$104,I$4:M$104,5,0) -> C | I44: MANNA2114 | J44: ='Юнит 8'!U67 -> 2 | K44: =J44/J$105 -> 0.00088809947 | L44: =L43+K44 -> 0.99023091 | M44: =_xlfn.IFS(L44<80%,"A",L44<=95%,"B",L44>95%,"C") -> C
B45: Guangdu серебро серая линза | C45: ='Юнит 8'!AO80 -> 236.69479 | D45: =C45/C$105 -> 0.00041289966 | E45: =E44+D45 -> 1.0371096 | F45: =IF(AND(E45<=0),"C",IF(E45<=0.8,"A",IF(E45<=0.95,"B","C"))) -> C | G45: =VLOOKUP(B$4:B$104,I$4:M$104,5,0) -> C | I45: Иу Диту серый | J45: ='Юнит 8'!U91 -> 2 | K45: =J45/J$105 -> 0.00088809947 | L45: =L44+K45 -> 0.99111901 | M45: =_xlfn.IFS(L45<80%,"A",L45<=95%,"B",L45>95%,"C") -> C
B46: YIMEI 2391 C1 | C46: ='Юнит 8'!AO98 -> 225.47693 | D46: =C46/C$105 -> 0.0003933308 | E46: =E45+D46 -> 1.0375029 | F46: =IF(AND(E46<=0),"C",IF(E46<=0.8,"A",IF(E46<=0.95,"B","C"))) -> C | G46: =VLOOKUP(B$4:B$104,I$4:M$104,5,0) -> C | I46: YIMEI 2391 C1 | J46: ='Юнит 8'!U98 -> 2 | K46: =J46/J$105 -> 0.00088809947 | L46: =L45+K46 -> 0.9920071 | M46: =_xlfn.IFS(L46<80%,"A",L46<=95%,"B",L46>95%,"C") -> C
B47: MANNA2103 | C47: ='Юнит 8'!AO56 -> 124.3773 | D47: =C47/C$105 -> 0.00021696864 | E47: =E46+D47 -> 1.0377199 | F47: =IF(AND(E47<=0),"C",IF(E47<=0.8,"A",IF(E47<=0.95,"B","C"))) -> C | G47: =VLOOKUP(B$4:B$104,I$4:M$104,5,0) -> C | I47: кс_черные_тест | J47: ='Юнит 8'!U101 -> 2 | K47: =J47/J$105 -> 0.00088809947 | L47: =L46+K47 -> 0.9928952 | M47: =_xlfn.IFS(L47<80%,"A",L47<=95%,"B",L47>95%,"C") -> C
B48: sh4 | C48: ='Юнит 8'!AO29 -> 122.9223 | D48: =C48/C$105 -> 0.00021443048 | E48: =E47+D48 -> 1.0379343 | F48: =IF(AND(E48<=0),"C",IF(E48<=0.8,"A",IF(E48<=0.95,"B","C"))) -> C | G48: =VLOOKUP(B$4:B$104,I$4:M$104,5,0) -> C | I48: sports красные | J48: ='Юнит 8'!U22 -> 1 | K48: =J48/J$105 -> 0.00044404973 | L48: =L47+K48 -> 0.99333925 | M48: =_xlfn.IFS(L48<80%,"A",L48<=95%,"B",L48>95%,"C") -> C
B49: sh13 | C49: ='Юнит 8'!AO37 -> 87.553266 | D49: =C49/C$105 -> 0.00015273135 | E49: =E48+D49 -> 1.038087 | F49: =IF(AND(E49<=0),"C",IF(E49<=0.8,"A",IF(E49<=0.95,"B","C"))) -> C | G49: =VLOOKUP(B$4:B$104,I$4:M$104,5,0) -> C | I49: sh4 | J49: ='Юнит 8'!U29 -> 1 | K49: =J49/J$105 -> 0.00044404973 | L49: =L48+K49 -> 0.9937833 | M49: =_xlfn.IFS(L49<80%,"A",L49<=95%,"B",L49>95%,"C") -> C
B50: sh06 | C50: ='Юнит 8'!AO30 -> 72.8636 | D50: =C50/C$105 -> 0.00012710612 | E50: =E49+D50 -> 1.0382141 | F50: =IF(AND(E50<=0),"C",IF(E50<=0.8,"A",IF(E50<=0.95,"B","C"))) -> C | G50: =VLOOKUP(B$4:B$104,I$4:M$104,5,0) -> C | I50: sh06 | J50: ='Юнит 8'!U30 -> 1 | K50: =J50/J$105 -> 0.00044404973 | L50: =L49+K50 -> 0.99422735 | M50: =_xlfn.IFS(L50<80%,"A",L50<=95%,"B",L50>95%,"C") -> C
B51: wwl8032 черные серебро | C51: ='Юнит 8'!AO19 -> 0 | D51: =C51/C$105 -> 0 | E51: =E50+D51 -> 1.0382141 | F51: =IF(AND(E51<=0),"C",IF(E51<=0.8,"A",IF(E51<=0.95,"B","C"))) -> C | G51: =VLOOKUP(B$4:B$104,I$4:M$104,5,0) -> C | I51: sh13 | J51: ='Юнит 8'!U37 -> 1 | K51: =J51/J$105 -> 0.00044404973 | L51: =L50+K51 -> 0.9946714 | M51: =_xlfn.IFS(L51<80%,"A",L51<=95%,"B",L51>95%,"C") -> C
B52: sports синие | C52: ='Юнит 8'!AO20 -> 0 | D52: =C52/C$105 -> 0 | E52: =E51+D52 -> 1.0382141 | F52: =IF(AND(E52<=0),"C",IF(E52<=0.8,"A",IF(E52<=0.95,"B","C"))) -> C | G52: =VLOOKUP(B$4:B$104,I$4:M$104,5,0) -> C | I52: WW 3055 коричневый | J52: ='Юнит 8'!U53 -> 1 | K52: =J52/J$105 -> 0.00044404973 | L52: =L51+K52 -> 0.99511545 | M52: =_xlfn.IFS(L52<80%,"A",L52<=95%,"B",L52>95%,"C") -> C
B53: sportlife черные | C53: ='Юнит 8'!AO23 -> 0 | D53: =C53/C$105 -> 0 | E53: =E52+D53 -> 1.0382141 | F53: =IF(AND(E53<=0),"C",IF(E53<=0.8,"A",IF(E53<=0.95,"B","C"))) -> C | G53: =VLOOKUP(B$4:B$104,I$4:M$104,5,0) -> C | I53: MANNA2101 | J53: ='Юнит 8'!U54 -> 1 | K53: =J53/J$105 -> 0.00044404973 | L53: =L52+K53 -> 0.9955595 | M53: =_xlfn.IFS(L53<80%,"A",L53<=95%,"B",L53>95%,"C") -> C
B54: sportlife синие | C54: ='Юнит 8'!AO24 -> 0 | D54: =C54/C$105 -> 0 | E54: =E53+D54 -> 1.0382141 | F54: =IF(AND(E54<=0),"C",IF(E54<=0.8,"A",IF(E54<=0.95,"B","C"))) -> C | G54: =VLOOKUP(B$4:B$104,I$4:M$104,5,0) -> C | I54: MANNA2103 | J54: ='Юнит 8'!U56 -> 1 | K54: =J54/J$105 -> 0.00044404973 | L54: =L53+K54 -> 0.99600355 | M54: =_xlfn.IFS(L54<80%,"A",L54<=95%,"B",L54>95%,"C") -> C
B55: sh08 | C55: ='Юнит 8'!AO32 -> 0 | D55: =C55/C$105 -> 0 | E55: =E54+D55 -> 1.0382141 | F55: =IF(AND(E55<=0),"C",IF(E55<=0.8,"A",IF(E55<=0.95,"B","C"))) -> C | G55: =VLOOKUP(B$4:B$104,I$4:M$104,5,0) -> C | I55: MANNA2118 | J55: ='Юнит 8'!U71 -> 1 | K55: =J55/J$105 -> 0.00044404973 | L55: =L54+K55 -> 0.9964476 | M55: =_xlfn.IFS(L55<80%,"A",L55<=95%,"B",L55>95%,"C") -> C
B56: sh11 | C56: ='Юнит 8'!AO35 -> 0 | D56: =C56/C$105 -> 0 | E56: =E55+D56 -> 1.0382141 | F56: =IF(AND(E56<=0),"C",IF(E56<=0.8,"A",IF(E56<=0.95,"B","C"))) -> C | G56: =VLOOKUP(B$4:B$104,I$4:M$104,5,0) -> C | I56: MANNA2121 | J56: ='Юнит 8'!U74 -> 1 | K56: =J56/J$105 -> 0.00044404973 | L56: =L55+K56 -> 0.99689165 | M56: =_xlfn.IFS(L56<80%,"A",L56<=95%,"B",L56>95%,"C") -> C
B57: sh12 | C57: ='Юнит 8'!AO36 -> 0 | D57: =C57/C$105 -> 0 | E57: =E56+D57 -> 1.0382141 | F57: =IF(AND(E57<=0),"C",IF(E57<=0.8,"A",IF(E57<=0.95,"B","C"))) -> C | G57: =VLOOKUP(B$4:B$104,I$4:M$104,5,0) -> C | I57: Guangdu серебро серая линза | J57: ='Юнит 8'!U80 -> 1 | K57: =J57/J$105 -> 0.00044404973 | L57: =L56+K57 -> 0.9973357 | M57: =_xlfn.IFS(L57<80%,"A",L57<=95%,"B",L57>95%,"C") -> C
B58: ww 1022 черн-серебро | C58: ='Юнит 8'!AO46 -> 0 | D58: =C58/C$105 -> 0 | E58: =E57+D58 -> 1.0382141 | F58: =IF(AND(E58<=0),"C",IF(E58<=0.8,"A",IF(E58<=0.95,"B","C"))) -> C | G58: =VLOOKUP(B$4:B$104,I$4:M$104,5,0) -> C | I58: Linhai Baiyi серая линза | J58: ='Юнит 8'!U87 -> 1 | K58: =J58/J$105 -> 0.00044404973 | L58: =L57+K58 -> 0.99777975 | M58: =_xlfn.IFS(L58<80%,"A",L58<=95%,"B",L58>95%,"C") -> C
B59: MANNA2104 | C59: ='Юнит 8'!AO57 -> 0 | D59: =C59/C$105 -> 0 | E59: =E58+D59 -> 1.0382141 | F59: =IF(AND(E59<=0),"C",IF(E59<=0.8,"A",IF(E59<=0.95,"B","C"))) -> C | G59: =VLOOKUP(B$4:B$104,I$4:M$104,5,0) -> C | I59: wwl8032 черные серебро | J59: ='Юнит 8'!U19 -> 0 | K59: =J59/J$105 -> 0 | L59: =L58+K59 -> 0.99777975 | M59: =_xlfn.IFS(L59<80%,"A",L59<=95%,"B",L59>95%,"C") -> C
B60: MANNA2106 | C60: ='Юнит 8'!AO59 -> 0 | D60: =C60/C$105 -> 0 | E60: =E59+D60 -> 1.0382141 | F60: =IF(AND(E60<=0),"C",IF(E60<=0.8,"A",IF(E60<=0.95,"B","C"))) -> C | G60: =VLOOKUP(B$4:B$104,I$4:M$104,5,0) -> C | I60: sports синие | J60: ='Юнит 8'!U20 -> 0 | K60: =J60/J$105 -> 0 | L60: =L59+K60 -> 0.99777975 | M60: =_xlfn.IFS(L60<80%,"A",L60<=95%,"B",L60>95%,"C") -> C
B61: MANNA2109 | C61: ='Юнит 8'!AO62 -> 0 | D61: =C61/C$105 -> 0 | E61: =E60+D61 -> 1.0382141 | F61: =IF(AND(E61<=0),"C",IF(E61<=0.8,"A",IF(E61<=0.95,"B","C"))) -> C | G61: =VLOOKUP(B$4:B$104,I$4:M$104,5,0) -> C | I61: sports зеленые | J61: ='Юнит 8'!U21 -> 0 | K61: =J61/J$105 -> 0 | L61: =L60+K61 -> 0.99777975 | M61: =_xlfn.IFS(L61<80%,"A",L61<=95%,"B",L61>95%,"C") -> C
B62: MANNA2110 | C62: ='Юнит 8'!AO63 -> 0 | D62: =C62/C$105 -> 0 | E62: =E61+D62 -> 1.0382141 | F62: =IF(AND(E62<=0),"C",IF(E62<=0.8,"A",IF(E62<=0.95,"B","C"))) -> C | G62: =VLOOKUP(B$4:B$104,I$4:M$104,5,0) -> C | I62: sportlife черные | J62: ='Юнит 8'!U23 -> 0 | K62: =J62/J$105 -> 0 | L62: =L61+K62 -> 0.99777975 | M62: =_xlfn.IFS(L62<80%,"A",L62<=95%,"B",L62>95%,"C") -> C
B63: MANNA2111 | C63: ='Юнит 8'!AO64 -> 0 | D63: =C63/C$105 -> 0 | E63: =E62+D63 -> 1.0382141 | F63: =IF(AND(E63<=0),"C",IF(E63<=0.8,"A",IF(E63<=0.95,"B","C"))) -> C | G63: =VLOOKUP(B$4:B$104,I$4:M$104,5,0) -> C | I63: sportlife синие | J63: ='Юнит 8'!U24 -> 0 | K63: =J63/J$105 -> 0 | L63: =L62+K63 -> 0.99777975 | M63: =_xlfn.IFS(L63<80%,"A",L63<=95%,"B",L63>95%,"C") -> C
B64: MANNA2115 | C64: ='Юнит 8'!AO68 -> 0 | D64: =C64/C$105 -> 0 | E64: =E63+D64 -> 1.0382141 | F64: =IF(AND(E64<=0),"C",IF(E64<=0.8,"A",IF(E64<=0.95,"B","C"))) -> C | G64: =VLOOKUP(B$4:B$104,I$4:M$104,5,0) -> C | I64: sh08 | J64: ='Юнит 8'!U32 -> 0 | K64: =J64/J$105 -> 0 | L64: =L63+K64 -> 0.99777975 | M64: =_xlfn.IFS(L64<80%,"A",L64<=95%,"B",L64>95%,"C") -> C
B65: MAIERSHA 03898 C9-08 | C65: ='Юнит 8'!AO94 -> 0 | D65: =C65/C$105 -> 0 | E65: =E64+D65 -> 1.0382141 | F65: =IF(AND(E65<=0),"C",IF(E65<=0.8,"A",IF(E65<=0.95,"B","C"))) -> C | G65: =VLOOKUP(B$4:B$104,I$4:M$104,5,0) -> C | I65: sh11 | J65: ='Юнит 8'!U35 -> 0 | K65: =J65/J$105 -> 0 | L65: =L64+K65 -> 0.99777975 | M65: =_xlfn.IFS(L65<80%,"A",L65<=95%,"B",L65>95%,"C") -> C
B66: MAIERSHA 03914 C9-124 | C66: ='Юнит 8'!AO95 -> 0 | D66: =C66/C$105 -> 0 | E66: =E65+D66 -> 1.0382141 | F66: =IF(AND(E66<=0),"C",IF(E66<=0.8,"A",IF(E66<=0.95,"B","C"))) -> C | G66: =VLOOKUP(B$4:B$104,I$4:M$104,5,0) -> C | I66: sh12 | J66: ='Юнит 8'!U36 -> 0 | K66: =J66/J$105 -> 0 | L66: =L65+K66 -> 0.99777975 | M66: =_xlfn.IFS(L66<80%,"A",L66<=95%,"B",L66>95%,"C") -> C
B67: MARSTON 7171 C1 | C67: ='Юнит 8'!AO96 -> 0 | D67: =C67/C$105 -> 0 | E67: =E66+D67 -> 1.0382141 | F67: =IF(AND(E67<=0),"C",IF(E67<=0.8,"A",IF(E67<=0.95,"B","C"))) -> C | G67: =VLOOKUP(B$4:B$104,I$4:M$104,5,0) -> C | I67: sh14 | J67: ='Юнит 8'!U38 -> 0 | K67: =J67/J$105 -> 0 | L67: =L66+K67 -> 0.99777975 | M67: =_xlfn.IFS(L67<80%,"A",L67<=95%,"B",L67>95%,"C") -> C
B68: ЧСЖ_тест | C68: ='Юнит 8'!AO99 -> 0 | D68: =C68/C$105 -> 0 | E68: =E67+D68 -> 1.0382141 | F68: =IF(AND(E68<=0),"C",IF(E68<=0.8,"A",IF(E68<=0.95,"B","C"))) -> C | G68: =VLOOKUP(B$4:B$104,I$4:M$104,5,0) -> C | I68: sh16 | J68: ='Юнит 8'!U40 -> 0 | K68: =J68/J$105 -> 0 | L68: =L67+K68 -> 0.99777975 | M68: =_xlfn.IFS(L68<80%,"A",L68<=95%,"B",L68>95%,"C") -> C
B69: ЧСЖ_женские | C69: ='Юнит 8'!AO100 -> 0 | D69: =C69/C$105 -> 0 | E69: =E68+D69 -> 1.0382141 | F69: =IF(AND(E69<=0),"C",IF(E69<=0.8,"A",IF(E69<=0.95,"B","C"))) -> C | G69: =VLOOKUP(B$4:B$104,I$4:M$104,5,0) -> C | I69: sh17 | J69: ='Юнит 8'!U41 -> 0 | K69: =J69/J$105 -> 0 | L69: =L68+K69 -> 0.99777975 | M69: =_xlfn.IFS(L69<80%,"A",L69<=95%,"B",L69>95%,"C") -> C
B70: кс_черные_женские | C70: ='Юнит 8'!AO102 -> 0 | D70: =C70/C$105 -> 0 | E70: =E69+D70 -> 1.0382141 | F70: =IF(AND(E70<=0),"C",IF(E70<=0.8,"A",IF(E70<=0.95,"B","C"))) -> C | G70: =VLOOKUP(B$4:B$104,I$4:M$104,5,0) -> C | I70: sh18 | J70: ='Юнит 8'!U42 -> 0 | K70: =J70/J$105 -> 0 | L70: =L69+K70 -> 0.99777975 | M70: =_xlfn.IFS(L70<80%,"A",L70<=95%,"B",L70>95%,"C") -> C
B71: sports зеленые | C71: ='Юнит 8'!AO21 -> -0.86724686 | D71: =C71/C$105 -> -1.5128594e-06 | E71: =E70+D71 -> 1.0382126 | F71: =IF(AND(E71<=0),"C",IF(E71<=0.8,"A",IF(E71<=0.95,"B","C"))) -> C | G71: =VLOOKUP(B$4:B$104,I$4:M$104,5,0) -> C | I71: ww 1022 черн-серебро | J71: ='Юнит 8'!U46 -> 0 | K71: =J71/J$105 -> 0 | L71: =L70+K71 -> 0.99777975 | M71: =_xlfn.IFS(L71<80%,"A",L71<=95%,"B",L71>95%,"C") -> C
B72: MANNA2102 | C72: ='Юнит 8'!AO55 -> -0.86724686 | D72: =C72/C$105 -> -1.5128594e-06 | E72: =E71+D72 -> 1.0382111 | F72: =IF(AND(E72<=0),"C",IF(E72<=0.8,"A",IF(E72<=0.95,"B","C"))) -> C | G72: =VLOOKUP(B$4:B$104,I$4:M$104,5,0) -> C | I72: WW 3055 черный | J72: ='Юнит 8'!U52 -> 0 | K72: =J72/J$105 -> 0 | L72: =L71+K72 -> 0.99777975 | M72: =_xlfn.IFS(L72<80%,"A",L72<=95%,"B",L72>95%,"C") -> C
B73: MANNA2113 | C73: ='Юнит 8'!AO66 -> -0.86724686 | D73: =C73/C$105 -> -1.5128594e-06 | E73: =E72+D73 -> 1.0382096 | F73: =IF(AND(E73<=0),"C",IF(E73<=0.8,"A",IF(E73<=0.95,"B","C"))) -> C | G73: =VLOOKUP(B$4:B$104,I$4:M$104,5,0) -> C | I73: MANNA2102 | J73: ='Юнит 8'!U55 -> 0 | K73: =J73/J$105 -> 0 | L73: =L72+K73 -> 0.99777975 | M73: =_xlfn.IFS(L73<80%,"A",L73<=95%,"B",L73>95%,"C") -> C
B74: POMILED 08247 C4-08 | C74: ='Юнит 8'!AO97 -> -2.6017406 | D74: =C74/C$105 -> -4.5385782e-06 | E74: =E73+D74 -> 1.038205 | F74: =IF(AND(E74<=0),"C",IF(E74<=0.8,"A",IF(E74<=0.95,"B","C"))) -> C | G74: =VLOOKUP(B$4:B$104,I$4:M$104,5,0) -> C | I74: MANNA2104 | J74: ='Юнит 8'!U57 -> 0 | K74: =J74/J$105 -> 0 | L74: =L73+K74 -> 0.99777975 | M74: =_xlfn.IFS(L74<80%,"A",L74<=95%,"B",L74>95%,"C") -> C
B75: MANNA2116 | C75: ='Юнит 8'!AO69 -> -10.406962 | D75: =C75/C$105 -> -1.8154313e-05 | E75: =E74+D75 -> 1.0381869 | F75: =IF(AND(E75<=0),"C",IF(E75<=0.8,"A",IF(E75<=0.95,"B","C"))) -> C | G75: =VLOOKUP(B$4:B$104,I$4:M$104,5,0) -> C | I75: MANNA2106 | J75: ='Юнит 8'!U59 -> 0 | K75: =J75/J$105 -> 0 | L75: =L74+K75 -> 0.99777975 | M75: =_xlfn.IFS(L75<80%,"A",L75<=95%,"B",L75>95%,"C") -> C
B76: Chenlong коричневые | C76: ='Юнит 8'!AO77 -> -33.822627 | D76: =C76/C$105 -> -5.9001517e-05 | E76: =E49+D76 -> 1.038028 | F76: =IF(AND(E76<=0),"C",IF(E76<=0.8,"A",IF(E76<=0.95,"B","C"))) -> C | G76: =VLOOKUP(B$4:B$104,I$4:M$104,5,0) -> C | I76: MANNA2108 | J76: ='Юнит 8'!U61 -> 0 | K76: =J76/J$105 -> 0 | L76: =L49+K76 -> 0.9937833 | M76: =_xlfn.IFS(L76<80%,"A",L76<=95%,"B",L76>95%,"C") -> C
B77: sh17 | C77: ='Юнит 8'!AO41 -> -39.893355 | D77: =C77/C$105 -> -6.9591533e-05 | E77: =E76+D77 -> 1.0379584 | F77: =IF(AND(E77<=0),"C",IF(E77<=0.8,"A",IF(E77<=0.95,"B","C"))) -> C | G77: =VLOOKUP(B$4:B$104,I$4:M$104,5,0) -> C | I77: MANNA2109 | J77: ='Юнит 8'!U62 -> 0 | K77: =J77/J$105 -> 0 | L77: =L76+K77 -> 0.9937833 | M77: =_xlfn.IFS(L77<80%,"A",L77<=95%,"B",L77>95%,"C") -> C
B78: Linhai Baiyi коричневая линза | C78: ='Юнит 8'!AO86 -> -39.893355 | D78: =C78/C$105 -> -6.9591533e-05 | E78: =E77+D78 -> 1.0378888 | F78: =IF(AND(E78<=0),"C",IF(E78<=0.8,"A",IF(E78<=0.95,"B","C"))) -> C | G78: =VLOOKUP(B$4:B$104,I$4:M$104,5,0) -> C | I78: MANNA2110 | J78: ='Юнит 8'!U63 -> 0 | K78: =J78/J$105 -> 0 | L78: =L77+K78 -> 0.9937833 | M78: =_xlfn.IFS(L78<80%,"A",L78<=95%,"B",L78>95%,"C") -> C
B79: Hengda Optical леопард | C79: ='Юнит 8'!AO82 -> -41.627849 | D79: =C79/C$105 -> -7.2617252e-05 | E79: =E78+D79 -> 1.0378162 | F79: =IF(AND(E79<=0),"C",IF(E79<=0.8,"A",IF(E79<=0.95,"B","C"))) -> C | G79: =VLOOKUP(B$4:B$104,I$4:M$104,5,0) -> C | I79: MANNA2111 | J79: ='Юнит 8'!U64 -> 0 | K79: =J79/J$105 -> 0 | L79: =L78+K79 -> 0.9937833 | M79: =_xlfn.IFS(L79<80%,"A",L79<=95%,"B",L79>95%,"C") -> C
B80: Qianai коричневые | C80: ='Юнит 8'!AO84 -> -41.627849 | D80: =C80/C$105 -> -7.2617252e-05 | E80: =E79+D80 -> 1.0377436 | F80: =IF(AND(E80<=0),"C",IF(E80<=0.8,"A",IF(E80<=0.95,"B","C"))) -> C | G80: =VLOOKUP(B$4:B$104,I$4:M$104,5,0) -> C | I80: MANNA2112 | J80: ='Юнит 8'!U65 -> 0 | K80: =J80/J$105 -> 0 | L80: =L79+K80 -> 0.9937833 | M80: =_xlfn.IFS(L80<80%,"A",L80<=95%,"B",L80>95%,"C") -> C
B81: Taizhou Rayen sport розовый | C81: ='Юнит 8'!AO90 -> -43.362343 | D81: =C81/C$105 -> -7.564297e-05 | E81: =E80+D81 -> 1.037668 | F81: =IF(AND(E81<=0),"C",IF(E81<=0.8,"A",IF(E81<=0.95,"B","C"))) -> C | G81: =VLOOKUP(B$4:B$104,I$4:M$104,5,0) -> C | I81: MANNA2113 | J81: ='Юнит 8'!U66 -> 0 | K81: =J81/J$105 -> 0 | L81: =L80+K81 -> 0.9937833 | M81: =_xlfn.IFS(L81<80%,"A",L81<=95%,"B",L81>95%,"C") -> C
B82: MANNA2101 | C82: ='Юнит 8'!AO54 -> -51.169362 | D82: =C82/C$105 -> -8.926184e-05 | E82: =E81+D82 -> 1.0375787 | F82: =IF(AND(E82<=0),"C",IF(E82<=0.8,"A",IF(E82<=0.95,"B","C"))) -> C | G82: =VLOOKUP(B$4:B$104,I$4:M$104,5,0) -> C | I82: MANNA2115 | J82: ='Юнит 8'!U68 -> 0 | K82: =J82/J$105 -> 0 | L82: =L81+K82 -> 0.9937833 | M82: =_xlfn.IFS(L82<80%,"A",L82<=95%,"B",L82>95%,"C") -> C
B83: MANNA2112 | C83: ='Юнит 8'!AO65 -> -97.267247 | D83: =C83/C$105 -> -0.0001696768 | E83: =E82+D83 -> 1.037409 | F83: =IF(AND(E83<=0),"C",IF(E83<=0.8,"A",IF(E83<=0.95,"B","C"))) -> C | G83: =VLOOKUP(B$4:B$104,I$4:M$104,5,0) -> C | I83: MANNA2116 | J83: ='Юнит 8'!U69 -> 0 | K83: =J83/J$105 -> 0 | L83: =L82+K83 -> 0.9937833 | M83: =_xlfn.IFS(L83<80%,"A",L83<=95%,"B",L83>95%,"C") -> C
B84: MANNA2117 | C84: ='Юнит 8'!AO70 -> -101.19623 | D84: =C84/C$105 -> -0.00017653068 | E84: =E83+D84 -> 1.0372325 | F84: =IF(AND(E84<=0),"C",IF(E84<=0.8,"A",IF(E84<=0.95,"B","C"))) -> C | G84: =VLOOKUP(B$4:B$104,I$4:M$104,5,0) -> C | I84: MANNA2117 | J84: ='Юнит 8'!U70 -> 0 | K84: =J84/J$105 -> 0 | L84: =L83+K84 -> 0.9937833 | M84: =_xlfn.IFS(L84<80%,"A",L84<=95%,"B",L84>95%,"C") -> C
B85: sh18 | C85: ='Юнит 8'!AO42 -> -122.09161 | D85: =C85/C$105 -> -0.0002129814 | E85: =E84+D85 -> 1.0370195 | F85: =IF(AND(E85<=0),"C",IF(E85<=0.8,"A",IF(E85<=0.95,"B","C"))) -> C | G85: =VLOOKUP(B$4:B$104,I$4:M$104,5,0) -> C | I85: Chenlong коричневые | J85: ='Юнит 8'!U77 -> 0 | K85: =J85/J$105 -> 0 | L85: =L84+K85 -> 0.9937833 | M85: =_xlfn.IFS(L85<80%,"A",L85<=95%,"B",L85>95%,"C") -> C
B86: Chenlong белые | C86: ='Юнит 8'!AO78 -> -129.39392 | D86: =C86/C$105 -> -0.00022571983 | E86: =E85+D86 -> 1.0367938 | F86: =IF(AND(E86<=0),"C",IF(E86<=0.8,"A",IF(E86<=0.95,"B","C"))) -> C | G86: =VLOOKUP(B$4:B$104,I$4:M$104,5,0) -> C | I86: Chenlong белые | J86: ='Юнит 8'!U78 -> 0 | K86: =J86/J$105 -> 0 | L86: =L85+K86 -> 0.9937833 | M86: =_xlfn.IFS(L86<80%,"A",L86<=95%,"B",L86>95%,"C") -> C
B87: Ли Сян ретро серебро | C87: ='Юнит 8'!AO93 -> -132.1706 | D87: =C87/C$105 -> -0.00023056358 | E87: =E86+D87 -> 1.0365632 | F87: =IF(AND(E87<=0),"C",IF(E87<=0.8,"A",IF(E87<=0.95,"B","C"))) -> C | G87: =VLOOKUP(B$4:B$104,I$4:M$104,5,0) -> C | I87: Guangdu золото серая линза | J87: ='Юнит 8'!U79 -> 0 | K87: =J87/J$105 -> 0 | L87: =L86+K87 -> 0.9937833 | M87: =_xlfn.IFS(L87<80%,"A",L87<=95%,"B",L87>95%,"C") -> C
B88: Guangdu золото серая линза | C88: ='Юнит 8'!AO79 -> -136.75336 | D88: =C88/C$105 -> -0.00023855791 | E88: =E87+D88 -> 1.0363247 | F88: =IF(AND(E88<=0),"C",IF(E88<=0.8,"A",IF(E88<=0.95,"B","C"))) -> C | G88: =VLOOKUP(B$4:B$104,I$4:M$104,5,0) -> C | I88: Hengda Optical леопард | J88: ='Юнит 8'!U82 -> 0 | K88: =J88/J$105 -> 0 | L88: =L87+K88 -> 0.9937833 | M88: =_xlfn.IFS(L88<80%,"A",L88<=95%,"B",L88>95%,"C") -> C
B89: Qianai черные | C89: ='Юнит 8'!AO83 -> -147.60611 | D89: =C89/C$105 -> -0.00025748988 | E89: =E88+D89 -> 1.0360672 | F89: =IF(AND(E89<=0),"C",IF(E89<=0.8,"A",IF(E89<=0.95,"B","C"))) -> C | G89: =VLOOKUP(B$4:B$104,I$4:M$104,5,0) -> C | I89: Qianai черные | J89: ='Юнит 8'!U83 -> 0 | K89: =J89/J$105 -> 0 | L89: =L88+K89 -> 0.9937833 | M89: =_xlfn.IFS(L89<80%,"A",L89<=95%,"B",L89>95%,"C") -> C
B90: Ли Сян ретро золото | C90: ='Юнит 8'!AO92 -> -150.1751 | D90: =C90/C$105 -> -0.00026197132 | E90: =E89+D90 -> 1.0358052 | F90: =IF(AND(E90<=0),"C",IF(E90<=0.8,"A",IF(E90<=0.95,"B","C"))) -> C | G90: =VLOOKUP(B$4:B$104,I$4:M$104,5,0) -> C | I90: Qianai коричневые | J90: ='Юнит 8'!U84 -> 0 | K90: =J90/J$105 -> 0 | L90: =L89+K90 -> 0.9937833 | M90: =_xlfn.IFS(L90<80%,"A",L90<=95%,"B",L90>95%,"C") -> C
B91: Hengda Optical черные | C91: ='Юнит 8'!AO81 -> -179.12462 | D91: =C91/C$105 -> -0.000312472 | E91: =E90+D91 -> 1.0354927 | F91: =IF(AND(E91<=0),"C",IF(E91<=0.8,"A",IF(E91<=0.95,"B","C"))) -> C | G91: =VLOOKUP(B$4:B$104,I$4:M$104,5,0) -> C | I91: Linhai Baiyi коричневая линза | J91: ='Юнит 8'!U86 -> 0 | K91: =J91/J$105 -> 0 | L91: =L90+K91 -> 0.9937833 | M91: =_xlfn.IFS(L91<80%,"A",L91<=95%,"B",L91>95%,"C") -> C
B92: MANNA2108 | C92: ='Юнит 8'!AO61 -> -235.29124 | D92: =C92/C$105 -> -0.00041045126 | E92: =E91+D92 -> 1.0350823 | F92: =IF(AND(E92<=0),"C",IF(E92<=0.8,"A",IF(E92<=0.95,"B","C"))) -> C | G92: =VLOOKUP(B$4:B$104,I$4:M$104,5,0) -> C | I92: Taizhou Rayen sport розовый | J92: ='Юнит 8'!U90 -> 0 | K92: =J92/J$105 -> 0 | L92: =L91+K92 -> 0.9937833 | M92: =_xlfn.IFS(L92<80%,"A",L92<=95%,"B",L92>95%,"C") -> C
B93: ww 2018 желтые | C93: ='Юнит 8'!AO50 -> -240.01393 | D93: =C93/C$105 -> -0.00041868971 | E93: =E92+D93 -> 1.0346636 | F93: =IF(AND(E93<=0),"C",IF(E93<=0.8,"A",IF(E93<=0.95,"B","C"))) -> C | G93: =VLOOKUP(B$4:B$104,I$4:M$104,5,0) -> C | I93: Ли Сян ретро золото | J93: ='Юнит 8'!U92 -> 0 | K93: =J93/J$105 -> 0 | L93: =L92+K93 -> 0.9937833 | M93: =_xlfn.IFS(L93<80%,"A",L93<=95%,"B",L93>95%,"C") -> C
B94: 1022_коричневые_тест | C94: ='Юнит 8'!AO103 -> -336 | D94: =C94/C$105 -> -0.00058613157 | E94: =E93+D94 -> 1.0340775 | F94: =IF(AND(E94<=0),"C",IF(E94<=0.8,"A",IF(E94<=0.95,"B","C"))) -> C | G94: =VLOOKUP(B$4:B$104,I$4:M$104,5,0) -> C | I94: Ли Сян ретро серебро | J94: ='Юнит 8'!U93 -> 0 | K94: =J94/J$105 -> 0 | L94: =L93+K94 -> 0.9937833 | M94: =_xlfn.IFS(L94<80%,"A",L94<=95%,"B",L94>95%,"C") -> C
B95: MANNA2122 | C95: ='Юнит 8'!AO75 -> -352.323 | D95: =C95/C$105 -> -0.00061460605 | E95: =E94+D95 -> 1.0334629 | F95: =IF(AND(E95<=0),"C",IF(E95<=0.8,"A",IF(E95<=0.95,"B","C"))) -> C | G95: =VLOOKUP(B$4:B$104,I$4:M$104,5,0) -> C | I95: MAIERSHA 03898 C9-08 | J95: ='Юнит 8'!U94 -> 0 | K95: =J95/J$105 -> 0 | L95: =L94+K95 -> 0.9937833 | M95: =_xlfn.IFS(L95<80%,"A",L95<=95%,"B",L95>95%,"C") -> C
B96: sh14 | C96: ='Юнит 8'!AO38 -> -360.52336 | D96: =C96/C$105 -> -0.00062891107 | E96: =E95+D96 -> 1.0328339 | F96: =IF(AND(E96<=0),"C",IF(E96<=0.8,"A",IF(E96<=0.95,"B","C"))) -> C | G96: =VLOOKUP(B$4:B$104,I$4:M$104,5,0) -> C | I96: MAIERSHA 03914 C9-124 | J96: ='Юнит 8'!U95 -> 0 | K96: =J96/J$105 -> 0 | L96: =L95+K96 -> 0.9937833 | M96: =_xlfn.IFS(L96<80%,"A",L96<=95%,"B",L96>95%,"C") -> C
B97: MANNA2118 | C97: ='Юнит 8'!AO71 -> -452.54192 | D97: =C97/C$105 -> -0.00078943185 | E97: =E96+D97 -> 1.0320445 | F97: =IF(AND(E97<=0),"C",IF(E97<=0.8,"A",IF(E97<=0.95,"B","C"))) -> C | G97: =VLOOKUP(B$4:B$104,I$4:M$104,5,0) -> C | I97: MARSTON 7171 C1 | J97: ='Юнит 8'!U96 -> 0 | K97: =J97/J$105 -> 0 | L97: =L96+K97 -> 0.9937833 | M97: =_xlfn.IFS(L97<80%,"A",L97<=95%,"B",L97>95%,"C") -> C
B98: WW 3055 черный | C98: ='Юнит 8'!AO52 -> -459.71336 | D98: =C98/C$105 -> -0.00080194199 | E98: =E97+D98 -> 1.0312426 | F98: =IF(AND(E98<=0),"C",IF(E98<=0.8,"A",IF(E98<=0.95,"B","C"))) -> C | G98: =VLOOKUP(B$4:B$104,I$4:M$104,5,0) -> C | I98: POMILED 08247 C4-08 | J98: ='Юнит 8'!U97 -> 0 | K98: =J98/J$105 -> 0 | L98: =L97+K98 -> 0.9937833 | M98: =_xlfn.IFS(L98<80%,"A",L98<=95%,"B",L98>95%,"C") -> C
B99: sh16 | C99: ='Юнит 8'!AO40 -> -467.82712 | D99: =C99/C$105 -> -0.00081609596 | E99: =E93+D99 -> 1.0338475 | F99: =IF(AND(E99<=0),"C",IF(E99<=0.8,"A",IF(E99<=0.95,"B","C"))) -> C | G99: =VLOOKUP(B$4:B$104,I$4:M$104,5,0) -> C | I99: ЧСЖ_тест | J99: ='Юнит 8'!U99 -> 0 | K99: =J99/J$105 -> 0 | L99: =L93+K99 -> 0.9937833 | M99: =_xlfn.IFS(L99<80%,"A",L99<=95%,"B",L99>95%,"C") -> C
B100: sh2 | C100: ='Юнит 8'!AO27 -> -479.23771 | D100: =C100/C$105 -> -0.00083600104 | E100: =E94+D100 -> 1.0332415 | F100: =IF(AND(E100<=0),"C",IF(E100<=0.8,"A",IF(E100<=0.95,"B","C"))) -> C | G100: =VLOOKUP(B$4:B$104,I$4:M$104,5,0) -> C | I100: ЧСЖ_женские | J100: ='Юнит 8'!U100 -> 0 | K100: =J100/J$105 -> 0 | L100: =L94+K100 -> 0.9937833 | M100: =_xlfn.IFS(L100<80%,"A",L100<=95%,"B",L100>95%,"C") -> C
B101: Keming Aishi коричневые | C101: ='Юнит 8'!AO85 -> -894.03443 | D101: =C101/C$105 -> -0.0015595887 | E101: =E95+D101 -> 1.0319033 | F101: =IF(AND(E101<=0),"C",IF(E101<=0.8,"A",IF(E101<=0.95,"B","C"))) -> C | G101: =VLOOKUP(B$4:B$104,I$4:M$104,5,0) -> C | I101: кс_черные_женские | J101: ='Юнит 8'!U102 -> 0 | K101: =J101/J$105 -> 0 | L101: =L95+K101 -> 0.9937833 | M101: =_xlfn.IFS(L101<80%,"A",L101<=95%,"B",L101>95%,"C") -> C
...

Sheet АВС ЯНВАРЬ
B2: ОЧКИ
C3: Прибыль | D3: % прибыль | E3: Доля | F3: ABC прибыль | G3: ABC кол-во | J3: Кол-во | K3: % кол-во | L3: Доля | M3: ABC кол-во
B4: QS черные PZ | C4: =ЯНВАРЬ!AO4 -> 95679.538 | D4: =C4/C$100 -> 0.51121559 | E4: =D4 -> 0.51121559 | F4: =IF(AND(E4<=0),"C",IF(E4<=0.8,"A",IF(E4<=0.95,"B","C"))) -> A | G4: =VLOOKUP(B$4:B$99,I$4:M$99,5,0) -> A | I4: QS черные PZ | J4: =ЯНВАРЬ!U4 -> 602 | K4: =J4/J$100 -> 0.26071893 | L4: =K4 -> 0.26071893 | M4: =_xlfn.IFS(L4<80%,"A",L4<=95%,"B",L4>95%,"C") -> A | P4: A | Q4: 0.8
B5: QS синие PZ | C5: =ЯНВАРЬ!AO5 -> 47568.917 | D5: =C5/C$100 -> 0.25416063 | E5: =E4+D5 -> 0.76537622 | F5: =IF(AND(E5<=0),"C",IF(E5<=0.8,"A",IF(E5<=0.95,"B","C"))) -> A | G5: =VLOOKUP(B$4:B$99,I$4:M$99,5,0) -> A | I5: QS синие PZ | J5: =ЯНВАРЬ!U5 -> 201 | K5: =J5/J$100 -> 0.087050671 | L5: =L4+K5 -> 0.3477696 | M5: =_xlfn.IFS(L5<80%,"A",L5<=95%,"B",L5>95%,"C") -> A | P5: B | Q5: 0.15
B6: QS коричневые PZ | C6: =ЯНВАРЬ!AO7 -> 29165.517 | D6: =C6/C$100 -> 0.1558313 | E6: =E5+D6 -> 0.92120752 | F6: =IF(AND(E6<=0),"C",IF(E6<=0.8,"A",IF(E6<=0.95,"B","C"))) -> B | G6: =VLOOKUP(B$4:B$99,I$4:M$99,5,0) -> A | I6: QS желтые PZ | J6: =ЯНВАРЬ!U6 -> 177 | K6: =J6/J$100 -> 0.076656561 | L6: =L5+K6 -> 0.42442616 | M6: =_xlfn.IFS(L6<80%,"A",L6<=95%,"B",L6>95%,"C") -> A | P6: C | Q6: 0.05
B7: QS желтые PZ | C7: =ЯНВАРЬ!AO6 -> 29310.498 | D7: =C7/C$100 -> 0.15660593 | E7: =E6+D7 -> 1.0778135 | F7: =IF(AND(E7<=0),"C",IF(E7<=0.8,"A",IF(E7<=0.95,"B","C"))) -> C | G7: =VLOOKUP(B$4:B$99,I$4:M$99,5,0) -> A | I7: QS коричневые PZ | J7: =ЯНВАРЬ!U7 -> 159 | K7: =J7/J$100 -> 0.068860979 | L7: =L6+K7 -> 0.49328714 | M7: =_xlfn.IFS(L7<80%,"A",L7<=95%,"B",L7>95%,"C") -> A
B8: черные с железкой классика | C8: =ЯНВАРЬ!AO3 -> 22712.028 | D8: =C8/C$100 -> 0.12135032 | E8: =E7+D8 -> 1.1991638 | F8: =IF(AND(E8<=0),"C",IF(E8<=0.8,"A",IF(E8<=0.95,"B","C"))) -> C | G8: =VLOOKUP(B$4:B$99,I$4:M$99,5,0) -> A | I8: черные с железкой классика | J8: =ЯНВАРЬ!U3 -> 158 | K8: =J8/J$100 -> 0.068427891 | L8: =L7+K8 -> 0.56171503 | M8: =_xlfn.IFS(L8<80%,"A",L8<=95%,"B",L8>95%,"C") -> A
B9: th желт | C9: =ЯНВАРЬ!AO11 -> 15180.484 | D9: =C9/C$100 -> 0.081109298 | E9: =E8+D9 -> 1.2802731 | F9: =IF(AND(E9<=0),"C",IF(E9<=0.8,"A",IF(E9<=0.95,"B","C"))) -> C | G9: =VLOOKUP(B$4:B$99,I$4:M$99,5,0) -> A | I9: th черн | J9: =ЯНВАРЬ!U9 -> 122 | K9: =J9/J$100 -> 0.052836726 | L9: =L8+K9 -> 0.61455175 | M9: =_xlfn.IFS(L9<80%,"A",L9<=95%,"B",L9>95%,"C") -> A
B10: wwl8032 хром металл | C10: =ЯНВАРЬ!AO18 -> 6247.3423 | D10: =C10/C$100 -> 0.033379538 | E10: =E9+D10 -> 1.3136526 | F10: =IF(AND(E10<=0),"C",IF(E10<=0.8,"A",IF(E10<=0.95,"B","C"))) -> C | G10: =VLOOKUP(B$4:B$99,I$4:M$99,5,0) -> B | I10: MR8854 C2 Жен | J10: =ЯНВАРЬ!U8 -> 119 | K10: =J10/J$100 -> 0.051537462 | L10: =L9+K10 -> 0.66608922 | M10: =_xlfn.IFS(L10<80%,"A",L10<=95%,"B",L10>95%,"C") -> A
B11: flip черные | C11: =ЯНВАРЬ!AO13 -> 5851.5908 | D11: =C11/C$100 -> 0.031265038 | E11: =E10+D11 -> 1.3449176 | F11: =IF(AND(E11<=0),"C",IF(E11<=0.8,"A",IF(E11<=0.95,"B","C"))) -> C | G11: =VLOOKUP(B$4:B$99,I$4:M$99,5,0) -> A | I11: th син | J11: =ЯНВАРЬ!U10 -> 88 | K11: =J11/J$100 -> 0.038111737 | L11: =L10+K11 -> 0.70420095 | M11: =_xlfn.IFS(L11<80%,"A",L11<=95%,"B",L11>95%,"C") -> A
B12: th черн | C12: =ЯНВАРЬ!AO9 -> 5673.9035 | D12: =C12/C$100 -> 0.030315655 | E12: =E11+D12 -> 1.3752333 | F12: =IF(AND(E12<=0),"C",IF(E12<=0.8,"A",IF(E12<=0.95,"B","C"))) -> C | G12: =VLOOKUP(B$4:B$99,I$4:M$99,5,0) -> A | I12: th желт | J12: =ЯНВАРЬ!U11 -> 80 | K12: =J12/J$100 -> 0.034647033 | L12: =L11+K12 -> 0.73884799 | M12: =_xlfn.IFS(L12<80%,"A",L12<=95%,"B",L12>95%,"C") -> A
B13: ww 1022 черные | C13: =ЯНВАРЬ!AO45 -> 3513.2311 | D13: =C13/C$100 -> 0.018771187 | E13: =E12+D13 -> 1.3940045 | F13: =IF(AND(E13<=0),"C",IF(E13<=0.8,"A",IF(E13<=0.95,"B","C"))) -> C | G13: =VLOOKUP(B$4:B$99,I$4:M$99,5,0) -> C | I13: flip черные | J13: =ЯНВАРЬ!U13 -> 71 | K13: =J13/J$100 -> 0.030749242 | L13: =L12+K13 -> 0.76959723 | M13: =_xlfn.IFS(L13<80%,"A",L13<=95%,"B",L13>95%,"C") -> A
B14: sportlife красные | C14: =ЯНВАРЬ!AO25 -> 1749.0528 | D14: =C14/C$100 -> 0.0093451859 | E14: =E13+D14 -> 1.4033497 | F14: =IF(AND(E14<=0),"C",IF(E14<=0.8,"A",IF(E14<=0.95,"B","C"))) -> C | G14: =VLOOKUP(B$4:B$99,I$4:M$99,5,0) -> C | I14: sh3 | J14: =ЯНВАРЬ!U28 -> 62 | K14: =J14/J$100 -> 0.026851451 | L14: =L13+K14 -> 0.79644868 | M14: =_xlfn.IFS(L14<80%,"A",L14<=95%,"B",L14>95%,"C") -> A
B15: MANNA2121 | C15: =ЯНВАРЬ!AO74 -> 1377.7544 | D15: =C15/C$100 -> 0.0073613393 | E15: =E14+D15 -> 1.410711 | F15: =IF(AND(E15<=0),"C",IF(E15<=0.8,"A",IF(E15<=0.95,"B","C"))) -> C | G15: =VLOOKUP(B$4:B$99,I$4:M$99,5,0) -> C | I15: flip коричневые | J15: =ЯНВАРЬ!U16 -> 58 | K15: =J15/J$100 -> 0.025119099 | L15: =L14+K15 -> 0.82156778 | M15: =_xlfn.IFS(L15<80%,"A",L15<=95%,"B",L15>95%,"C") -> B
B16: sportlife синие | C16: =ЯНВАРЬ!AO24 -> 1357.3343 | D16: =C16/C$100 -> 0.0072522346 | E16: =E15+D16 -> 1.4179632 | F16: =IF(AND(E16<=0),"C",IF(E16<=0.8,"A",IF(E16<=0.95,"B","C"))) -> C | G16: =VLOOKUP(B$4:B$99,I$4:M$99,5,0) -> C | I16: th коричн | J16: =ЯНВАРЬ!U12 -> 47 | K16: =J16/J$100 -> 0.020355132 | L16: =L15+K16 -> 0.84192291 | M16: =_xlfn.IFS(L16<80%,"A",L16<=95%,"B",L16>95%,"C") -> B
B17: ww 1022 желтые | C17: =ЯНВАРЬ!AO47 -> 1303.6424 | D17: =C17/C$100 -> 0.0069653586 | E17: =E16+D17 -> 1.4249286 | F17: =IF(AND(E17<=0),"C",IF(E17<=0.8,"A",IF(E17<=0.95,"B","C"))) -> C | G17: =VLOOKUP(B$4:B$99,I$4:M$99,5,0) -> C | I17: wwl8032 хром металл | J17: =ЯНВАРЬ!U18 -> 32 | K17: =J17/J$100 -> 0.013858813 | L17: =L16+K17 -> 0.85578172 | M17: =_xlfn.IFS(L17<80%,"A",L17<=95%,"B",L17>95%,"C") -> B
B18: flip коричневые | C18: =ЯНВАРЬ!AO16 -> 1262.8282 | D18: =C18/C$100 -> 0.0067472885 | E18: =E17+D18 -> 1.4316759 | F18: =IF(AND(E18<=0),"C",IF(E18<=0.8,"A",IF(E18<=0.95,"B","C"))) -> C | G18: =VLOOKUP(B$4:B$99,I$4:M$99,5,0) -> B | I18: ww 2018 черные | J18: =ЯНВАРЬ!U49 -> 32 | K18: =J18/J$100 -> 0.013858813 | L18: =L17+K18 -> 0.86964054 | M18: =_xlfn.IFS(L18<80%,"A",L18<=95%,"B",L18>95%,"C") -> B
B19: Linhai Baiyi коричневая линза | C19: =ЯНВАРЬ!AO86 -> 1130.4732 | D19: =C19/C$100 -> 0.0060401161 | E19: =E18+D19 -> 1.437716 | F19: =IF(AND(E19<=0),"C",IF(E19<=0.8,"A",IF(E19<=0.95,"B","C"))) -> C | G19: =VLOOKUP(B$4:B$99,I$4:M$99,5,0) -> C | I19: flip желтые | J19: =ЯНВАРЬ!U15 -> 29 | K19: =J19/J$100 -> 0.01255955 | L19: =L18+K19 -> 0.88220009 | M19: =_xlfn.IFS(L19<80%,"A",L19<=95%,"B",L19>95%,"C") -> B
B20: MANNA2122 | C20: =ЯНВАРЬ!AO75 -> 1060.5313 | D20: =C20/C$100 -> 0.0056664169 | E20: =E19+D20 -> 1.4433824 | F20: =IF(AND(E20<=0),"C",IF(E20<=0.8,"A",IF(E20<=0.95,"B","C"))) -> C | G20: =VLOOKUP(B$4:B$99,I$4:M$99,5,0) -> B | I20: wwl8032 коричневые золото | J20: =ЯНВАРЬ!U17 -> 29 | K20: =J20/J$100 -> 0.01255955 | L20: =L19+K20 -> 0.89475964 | M20: =_xlfn.IFS(L20<80%,"A",L20<=95%,"B",L20>95%,"C") -> B
B21: Linhai Baiyi серая линза | C21: =ЯНВАРЬ!AO87 -> 1014.2073 | D21: =C21/C$100 -> 0.0054189075 | E21: =E20+D21 -> 1.4488013 | F21: =IF(AND(E21<=0),"C",IF(E21<=0.8,"A",IF(E21<=0.95,"B","C"))) -> C | G21: =VLOOKUP(B$4:B$99,I$4:M$99,5,0) -> C | I21: ww 2018 желтые | J21: =ЯНВАРЬ!U50 -> 26 | K21: =J21/J$100 -> 0.011260286 | L21: =L20+K21 -> 0.90601992 | M21: =_xlfn.IFS(L21<80%,"A",L21<=95%,"B",L21>95%,"C") -> B
B22: MANNA2114 | C22: =ЯНВАРЬ!AO67 -> 859.24934 | D22: =C22/C$100 -> 0.0045909675 | E22: =E21+D22 -> 1.4533923 | F22: =IF(AND(E22<=0),"C",IF(E22<=0.8,"A",IF(E22<=0.95,"B","C"))) -> C | G22: =VLOOKUP(B$4:B$99,I$4:M$99,5,0) -> C | I22: flip синие | J22: =ЯНВАРЬ!U14 -> 25 | K22: =J22/J$100 -> 0.010827198 | L22: =L21+K22 -> 0.91684712 | M22: =_xlfn.IFS(L22<80%,"A",L22<=95%,"B",L22>95%,"C") -> B
B23: MANNA2117 | C23: =ЯНВАРЬ!AO70 -> 904.51724 | D23: =C23/C$100 -> 0.0048328338 | E23: =E22+D23 -> 1.4582251 | F23: =IF(AND(E23<=0),"C",IF(E23<=0.8,"A",IF(E23<=0.95,"B","C"))) -> C | G23: =VLOOKUP(B$4:B$99,I$4:M$99,5,0) -> C | I23: MANNA2122 | J23: =ЯНВАРЬ!U75 -> 23 | K23: =J23/J$100 -> 0.0099610221 | L23: =L22+K23 -> 0.92680814 | M23: =_xlfn.IFS(L23<80%,"A",L23<=95%,"B",L23>95%,"C") -> B
B24: sh17 | C24: =ЯНВАРЬ!AO41 -> 766.29906 | D24: =C24/C$100 -> 0.0040943344 | E24: =E23+D24 -> 1.4623195 | F24: =IF(AND(E24<=0),"C",IF(E24<=0.8,"A",IF(E24<=0.95,"B","C"))) -> C | G24: =VLOOKUP(B$4:B$99,I$4:M$99,5,0) -> C | I24: sh1 | J24: =ЯНВАРЬ!U26 -> 22 | K24: =J24/J$100 -> 0.0095279342 | L24: =L23+K24 -> 0.93633608 | M24: =_xlfn.IFS(L24<80%,"A",L24<=95%,"B",L24>95%,"C") -> B
