Workbook

Sheet Реклама
B2: ПЕРИОД | C2: БАЛАНС | F2: СЧЕТ | I2: Неделя
C3: Номер документа | D3: Сумма | E3: Даты | F3: Номер документа | G3: Сумма | H3: Даты
B4: 01-04.01 | F4: 277607349 | G4: 4738 | H4: 01-04.01 | I4: 1
B5: 04-11.01 | F5: 279228154 | G5: 6535 | H5: 04-11.01 | I5: 2
B6: 11-18.01 | C6: 280305485 | D6: 2922 | E6: 14-18.01 | F6: 280297200 | G6: 3464 | H6: 11-17.01 | I6: 3
C7: 0 | D7: 923 | E7: 18.01 | F7: 0 | G7: 114 | H7: 18.01
B8: 18-25.01 | C8: 281290485 | D8: 5916 | E8: 18-23.01 | F8: 281290488 | G8: 2033 | H8: 18-25.01 | I8: 4
C9: 0 | D9: 1216 | E9: 25.01
B10: 25.01-01.02 | C10: 282283796 | D10: 12613 | E10: 27-31.01 | F10: 282343451 | G10: 9553 | H10: 25-31.01 | I10: 5
C11: 282375547 | D11: 1000 | E11: 01.02 | F11: 282385566 | G11: 79 | H11: 01.02
C12: 0 | D12: 1791 | E12: 01.02 | F12: 0 | G12: 539 | H12: 01.02
B13: 01-08.02 | C13: 283356234 | D13: 9526 | E13: 01-04.02 | F13: 283392061 | G13: 17308 | H13: 01-08.02 | I13: 6
F14: 0 | G14: 3305 | H14: 08.02
B15: 08-15.02 | C15: 284419876 | D15: 16968 | E15: 09-12.02 | F15: 284354982 | G15: 25029 | H15: 08-15.02 | I15: 7
F16: 0 | G16: 4431 | H16: 15,02
B17: 15-22.02 | I17: 8
H39: .

Sheet Сводная
B2: Период | E2: Дата поступления дс | F2: Итого к перечислению на счет, руб | G2: шт. | J2: ВБ реализовал товар (выручка с СПП) | M2: Выручка до вычета комиссии ВБ | P2: Себестоимость продаж | Q2: Логистика WB | R2: Комиссия WB | S2: Хранение WB | T2: Платная приемка WB | U2: Штрафы WB | V2: Прочие удержания WB | W2: Реклама БАЛАНС | X2: Реклама СЧЕТ | Y2: Блогеры | Z2: Налог | AA2: Прочие поступления WB | AB2: Прибыль до вычета налогов | AC2: Прибыль после вычета налогов | AD2: Итог месяц | AE2: % Cебестоимости | AF2: Маржинальность, % | AG2: Рентабельность, % | AH2: Доля рекламы, %
B3: Месяц | C3: Даты | D3: Нед | G3: Заказы | H3: Продажи | I3: Возвраты | J3: Продажи | K3: Возвраты | L3: Общая | M3: Продажи | N3: Возвраты | O3: Общая
B4: Январь 1 | C4: 29.12-04.01 | D4: 1 | F4: =IFERROR(O4-SUM(Q4:W4)+AA4,0) -> 29279.64 | G4: ='Юнит 1'!L$17 -> 66 | H4: ='Юнит 1'!Q$17 -> 45 | I4: ='Юнит 1'!R$17 -> 0 | J4: ='Юнит 1'!T$74 -> 46145.63 | K4: ='Юнит 1'!U$74 -> 0 | L4: =IFERROR(J4+K4,0) -> 46145.63 | M4: ='Юнит 1'!W$74 -> 54988.62 | N4: ='Юнит 1'!X$74 -> 0 | O4: =IFERROR(M4+N4,0) -> 54988.62 | P4: ='Юнит 1'!AB$74 -> 5712.21 | Q4: ='Юнит 1'!AE$74 -> 4543.05 | R4: ='Юнит 1'!AC$74 -> 19854.22 | S4: ='Юнит 1'!AI$74 -> 1049.63 | U4: ='Юнит 1'!AJ$74 -> 0 | V4: 262.08 | W4: ='Юнит 1'!AF$74 -> 0 | X4: ='Юнит 1'!AG$74 -> 4738 | Y4: ='Юнит 1'!AH84 -> 0 | Z4: 457.89 | AB4: =O4-SUM(P4:Y4)+AA4 -> 18829.43 | AC4: =O4-SUM(P4:Z4)+AA4 -> 18371.54 | AD4: =SUM(AC4:AC8) -> 67154.08 | AE4: =P4/O4 -> 0.10387986 | AF4: =AC4/P4 -> 3.2161878 | AG4: =AC4/O4 -> 0.33409713 | AH4: =(W4+X4+Y4)/O4 -> 0.086163283
B5: Январь 2 | C5: 05-11.01 | D5: 2 | F5: =IFERROR(O5-SUM(Q5:W5)+AA5,0) -> 25524.23 | G5: ='Юнит 2'!L$17 -> 86 | H5: ='Юнит 2'!Q$17 -> 43 | I5: ='Юнит 2'!R$17 -> -1 | J5: ='Юнит 2'!T$74 -> 43245.32 | K5: ='Юнит 2'!U$74 -> -931 | L5: =IFERROR(J5+K5,0) -> 42314.32 | M5: ='Юнит 2'!W$74 -> 52197.86 | N5: ='Юнит 2'!X$74 -> -1199 | O5: =IFERROR(M5+N5,0) -> 50998.86 | P5: ='Юнит 2'!AB$74 -> 5562.9 | Q5: ='Юнит 2'!AE$74 -> 5752.8 | R5: ='Юнит 2'!AC$74 -> 18463.04 | S5: ='Юнит 2'!AI$74 -> 1083.11 | U5: ='Юнит 2'!AJ$74 -> 0 | V5: 175.68 | W5: ='Юнит 2'!AF$74 -> 0 | X5: ='Юнит 2'!AG$74 -> 6535 | Y5: ='Юнит 2'!AH85 -> 0 | Z5: 416.28 | AB5: =O5-SUM(P5:Y5)+AA5 -> 13426.33 | AC5: =O5-SUM(P5:Z5)+AA5 -> 13010.05 | AE5: =P5/O5 -> 0.10907891 | AF5: =AC5/P5 -> 2.3387172 | AG5: =AC5/O5 -> 0.25510472 | AH5: =(W5+X5+Y5)/O5 -> 0.12814012
B6: Январь 3 | C6: 12-18.01 | D6: 3 | F6: =IFERROR(O6-SUM(Q6:W6)+AA6,0) -> 25982.83 | G6: ='Юнит 3'!L$17 -> 62 | H6: ='Юнит 3'!Q$17 -> 49 | I6: ='Юнит 3'!R$17 -> -1 | J6: ='Юнит 3'!T$74 -> 45785.47 | K6: ='Юнит 3'!U$74 -> -948 | L6: =IFERROR(J6+K6,0) -> 44837.47 | M6: ='Юнит 3'!W$74 -> 56919.74 | N6: ='Юнит 3'!X$74 -> -1174 | O6: =IFERROR(M6+N6,0) -> 55745.74 | P6: ='Юнит 3'!AB$74 -> 6528.42 | Q6: ='Юнит 3'!AE$74 -> 6055.25 | R6: ='Юнит 3'!AC$74 -> 19306.86 | S6: ='Юнит 3'!AI$74 -> 1361.68 | U6: ='Юнит 3'!AJ$74 -> 0 | V6: 117.12 | W6: ='Юнит 3'!AF$74 -> 2922 | X6: ='Юнит 3'!AG$74 -> 3464 | Y6: ='Юнит 3'!AH86 -> 0 | Z6: 467.24 | AB6: =O6-SUM(P6:Y6)+AA6 -> 15990.41 | AC6: =O6-SUM(P6:Z6)+AA6 -> 15523.17 | AE6: =P6/O6 -> 0.11711065 | AF6: =AC6/P6 -> 2.3777836 | AG6: =AC6/O6 -> 0.27846379 | AH6: =(W6+X6+Y6)/O6 -> 0.11455584
B7: Январь 4 | C7: 19-25.01 | D7: 4 | F7: =IFERROR(O7-SUM(Q7:W7)+AA7,0) -> 22836.85 | G7: ='Юнит 4'!L$17 -> 86 | H7: ='Юнит 4'!Q$17 -> 49 | I7: ='Юнит 4'!R$17 -> -2 | J7: ='Юнит 4'!T$74 -> 44338.88 | K7: ='Юнит 4'!U$74 -> -1888 | L7: =IFERROR(J7+K7,0) -> 42450.88 | M7: ='Юнит 4'!W$74 -> 59321.67 | N7: ='Юнит 4'!X$74 -> -2412 | O7: =IFERROR(M7+N7,0) -> 56909.67 | P7: ='Юнит 4'!AB$74 -> 6764.52 | Q7: ='Юнит 4'!AE$74 -> 6115.35 | R7: ='Юнит 4'!AC$74 -> 20543.92 | S7: ='Юнит 4'!AI$74 -> 1438.99 | U7: ='Юнит 4'!AJ$74 -> 0 | V7: 58.56 | W7: ='Юнит 4'!AF$74 -> 5916 | X7: ='Юнит 4'!AG$74 -> 2033 | Y7: ='Юнит 4'!AH87 -> 0 | Z7: 456.13 | AB7: =O7-SUM(P7:Y7)+AA7 -> 14039.33 | AC7: =O7-SUM(P7:Z7)+AA7 -> 13583.2 | AE7: =P7/O7 -> 0.11886416 | AF7: =AC7/P7 -> 2.0080065 | AG7: =AC7/O7 -> 0.23868 | AH7: =(W7+X7+Y7)/O7 -> 0.13967749
B8: Январь 5 | C8: 26.01-01.02 | D8: 5 | F8: =IFERROR(O8-SUM(Q8:W8)+AA8,0) -> 26541.81 | G8: ='Юнит 5'!L$17 -> 157 | H8: ='Юнит 5'!Q$17 -> 70 | I8: ='Юнит 5'!R$17 -> -1 | J8: ='Юнит 5'!T$74 -> 53707.42 | K8: ='Юнит 5'!U$74 -> -813 | L8: =IFERROR(J8+K8,0) -> 52894.42 | M8: ='Юнит 5'!W$74 -> 80352 | N8: ='Юнит 5'!X$74 -> -1238 | O8: =IFERROR(M8+N8,0) -> 79114 | P8: ='Юнит 5'!AB$74 -> 9760.32 | Q8: ='Юнит 5'!AE$74 -> 8509.6 | R8: ='Юнит 5'!AC$74 -> 28720.66 | S8: ='Юнит 5'!AI$74 -> 1377.57 | U8: ='Юнит 5'!AJ$74 -> 0 | V8: 351.36 | W8: ='Юнит 5'!AF$74 -> 13613 | X8: ='Юнит 5'!AG$74 -> 9632 | Y8: ='Юнит 5'!AH88 -> 0 | Z8: 483.37 | AB8: =O8-SUM(P8:Y8)+AA8 -> 7149.49 | AC8: =O8-SUM(P8:Z8)+AA8 -> 6666.12 | AE8: =P8/O8 -> 0.12337033 | AF8: =AC8/P8 -> 0.68298171 | AG8: =AC8/O8 -> 0.084259676 | AH8: =(W8+X8+Y8)/O8 -> 0.29381652
B9: Февраль 1 | C9: 02-08.02 | D9: 6 | F9: =IFERROR(O9-SUM(Q9:W9)+AA9,0) -> 59865 | G9: ='Юнит 6'!L$36 -> 286 | H9: ='Юнит 6'!Q$36 -> 118 | I9: ='Юнит 6'!R$36 -> -1 | J9: ='Юнит 6'!T$93 -> 85982.96 | K9: ='Юнит 6'!U$93 -> -777 | L9: =IFERROR(J9+K9,0) -> 85205.96 | M9: ='Юнит 6'!W$93 -> 132376.93 | N9: ='Юнит 6'!X$93 -> -1238 | O9: =IFERROR(M9+N9,0) -> 131138.93 | P9: ='Юнит 6'!AB$93 -> 15974.01 | Q9: ='Юнит 6'!AE$93 -> 12544.65 | R9: ='Юнит 6'!AC$93 -> 47795.47 | S9: ='Юнит 6'!AI$93 -> 1261.41 | U9: ='Юнит 6'!AJ$93 -> 0 | V9: 146.4 | W9: ='Юнит 6'!AF$93 -> 9526 | X9: ='Юнит 6'!AG$93 -> 17308 | Y9: ='Юнит 6'!AH108 -> 0 | Z9: =IFERROR((L9)*0.01,0) -> 852.0596 | AB9: =O9-SUM(P9:Y9)+AA9 -> 26582.99 | AC9: =O9-SUM(P9:Z9)+AA9 -> 25730.93 | AD9: =SUM(AC9:AC12) -> 77284.918 | AE9: =P9/O9 -> 0.12180982 | AF9: =AC9/P9 -> 1.6107997 | AG9: =AC9/O9 -> 0.19621123 | AH9: =(W9+X9+Y9)/O9 -> 0.20462269
B10: Февраль 2 | C10: 09-15.02 | D10: 7 | F10: =IFERROR(O10-SUM(Q10:W10)+AA10,0) -> 105982.04 | G10: ='Юнит 7'!L$36 -> 388 | H10: ='Юнит 7'!Q$36 -> 212 | I10: ='Юнит 7'!R$36 -> -2 | J10: ='Юнит 7'!T$93 -> 149383.2 | K10: ='Юнит 7'!U$93 -> -1458 | L10: =IFERROR(J10+K10,0) -> 147925.2 | M10: ='Юнит 7'!W$93 -> 234275.74 | N10: ='Юнит 7'!X$93 -> -2388 | O10: =IFERROR(M10+N10,0) -> 231887.74 | P10: ='Юнит 7'!AB$93 -> 27919.8 | Q10: ='Юнит 7'!AE$93 -> 22767.8 | R10: ='Юнит 7'!AC$93 -> 84374.68 | S10: ='Юнит 7'!AI$93 -> 1132.46 | T10: 165 | U10: ='Юнит 7'!AJ$93 -> 0 | V10: 497.76 | W10: ='Юнит 7'!AF$93 -> 16968 | X10: ='Юнит 7'!AG$93 -> 25029 | Y10: ='Юнит 7'!AH109 -> 0 | Z10: =IFERROR((L10)*0.01,0) -> 1479.252 | AB10: =O10-SUM(P10:Y10)+AA10 -> 53033.24 | AC10: =O10-SUM(P10:Z10)+AA10 -> 51553.988 | AE10: =P10/O10 -> 0.12040223 | AF10: =AC10/P10 -> 1.8465028 | AG10: =AC10/O10 -> 0.22232304 | AH10: =(W10+X10+Y10)/O10 -> 0.18110919
B11: Февраль 3 | C11: 16-22.02 | D11: 8 | AB11: =O11-SUM(P11:Y11)+AA11 -> 0 | AC11: =O11-SUM(P11:Z11)+AA11 -> 0 | AE11: =P11/O11 -> #DIV/0! | AF11: =AC11/P11 -> #DIV/0! | AG11: =AC11/O11 -> #DIV/0! | AH11: =(W11+X11+Y11)/O11 -> #DIV/0!
B12: Февраль 4 | C12: 23.02-01.03 | D12: 9 | AB12: =O12-SUM(P12:Y12)+AA12 -> 0 | AC12: =O12-SUM(P12:Z12)+AA12 -> 0 | AE12: =P12/O12 -> #DIV/0! | AF12: =AC12/P12 -> #DIV/0! | AG12: =AC12/O12 -> #DIV/0! | AH12: =(W12+X12+Y12)/O12 -> #DIV/0!
AB13: =O13-SUM(P13:Y13)+AA13 -> 0 | AC13: =O13-SUM(P13:Z13)+AA13 -> 0 | AE13: =P13/O13 -> #DIV/0! | AF13: =AC13/P13 -> #DIV/0! | AG13: =AC13/O13 -> #DIV/0! | AH13: =(W13+X13+Y13)/O13 -> #DIV/0!
B14: Итого | F14: =SUM(F4:F13) -> 296012.4 | G14: =SUM(G4:G13) -> 1131 | H14: =SUM(H4:H13) -> 586 | I14: =SUM(I4:I13) -> -8 | J14: =SUM(J4:J13) -> 468588.88 | K14: =SUM(K4:K13) -> -6815 | L14: =SUM(L4:L13) -> 461773.88 | M14: =SUM(M4:M13) -> 670432.56 | ... AD14: =SUM(AD4:AD13) -> 144439 | AE14: =P14/O14 -> 0.11837791 | AF14: =AC14/P14 -> 1.8465223 | AG14: =AC14/O14 -> 0.21858746 | AH14: =(W14+X14+Y14)/O14 -> 0.17809765
M15: % от выручки за весь период
N16: =-N14/M14 -> 0.014392201 | P16: =P14/$O$14 -> 0.11837791 | Q16: =Q14/$O$14 -> 0.10031802 | R16: =R14/$O$14 -> 0.36178087 | S16: =S14/$O$14 -> 0.013173527 | T16: =T14/$O$14 -> 0.00024970355 | U16: =U14/$O$14 -> 0 | V16: =V14/$O$14 -> 0.0024349274 | W16: =W14/$O$14 -> 0.074071153 | ... Z16: =Z14/$O$14 -> 0.0069799279 | AC16: =AC14/P14 -> 1.8465223 | AD16: Маржинальность, %
W17: =(W14+X14)/O14 -> 0.17809765 | AC17: =AC14/O14 -> 0.21858746 | AD17: Рентабельность, %
B18: ЯНВАРЬ | G18: =SUM(G4:G8) -> 457 | H18: =SUM(H4:H8) -> 256 | I18: =SUM(I4:I8) -> -5 | J18: =SUM(J4:J8) -> 233222.72 | K18: =SUM(K4:K8) -> -4580 | L18: =SUM(L4:L8) -> 228642.72 | M18: =SUM(M4:M8) -> 303779.89 | N18: =SUM(N4:N8) -> -6023 | ... AA18: =SUM(AA4:AA8) -> 0 | AC18: =SUM(AC4:AC8) -> 67154.08 | AD18: =AC14/O14 -> 0.21858746
N19: =-N18/M18 -> 0.019826856 | P19: =P18/$O$14 -> 0.051951005 | Q19: =Q18/$O$14 -> 0.046877755 | R19: =R18/$O$14 -> 0.16176053 | S19: =S18/$O$14 -> 0.0095507521 | T19: =T18/$O$14 -> 0 | U19: =U18/$O$14 -> 0 | V19: =V18/$O$14 -> 0.0014600848 | W19: =W18/$O$14 -> 0.03397633 | ... AA19: =AA18/$O$14 -> 0 | AC19: =AC18/O18 -> 0.22553325

Sheet АВС 8
B2: ОЧКИ
C3: Прибыль | D3: % прибыль | E3: Доля | F3: ABC прибыль | G3: ABC кол-во | J3: Кол-во | K3: % кол-во | L3: Доля | M3: ABC кол-во
B4: Черные с железкой Сул | D4: =C4/C$36 -> #DIV/0! | E4: =D4 -> #DIV/0! | F4: =IF(AND(E4<=0),"C",IF(E4<=0.8,"A",IF(E4<=0.95,"B","C"))) -> #DIV/0! | G4: =VLOOKUP(B$4:B$35,I$4:M$35,5,0) -> #DIV/0! | I4: Черные с железкой Сул | K4: =J4/J$36 -> #DIV/0! | L4: =K4 -> #DIV/0! | M4: =_xlfn.IFS(L4<80%,"A",L4<=95%,"B",L4>95%,"C") -> #DIV/0! | P4: A | Q4: 0.8
B5: Qs черн Сул | D5: =C5/C$36 -> #DIV/0! | E5: =E4+D5 -> #DIV/0! | F5: =IF(AND(E5<=0),"C",IF(E5<=0.8,"A",IF(E5<=0.95,"B","C"))) -> #DIV/0! | G5: =VLOOKUP(B$4:B$35,I$4:M$35,5,0) -> #DIV/0! | I5: Qs черн Сул | K5: =J5/J$36 -> #DIV/0! | L5: =L4+K5 -> #DIV/0! | M5: =_xlfn.IFS(L5<80%,"A",L5<=95%,"B",L5>95%,"C") -> #DIV/0! | P5: B | Q5: 0.15
B6: Qs син Сул | D6: =C6/C$36 -> #DIV/0! | E6: =E5+D6 -> #DIV/0! | F6: =IF(AND(E6<=0),"C",IF(E6<=0.8,"A",IF(E6<=0.95,"B","C"))) -> #DIV/0! | G6: =VLOOKUP(B$4:B$35,I$4:M$35,5,0) -> #DIV/0! | I6: Qs син Сул | K6: =J6/J$36 -> #DIV/0! | L6: =L5+K6 -> #DIV/0! | M6: =_xlfn.IFS(L6<80%,"A",L6<=95%,"B",L6>95%,"C") -> #DIV/0! | P6: C | Q6: 0.05
B7: Qs желт Сул | D7: =C7/C$36 -> #DIV/0! | E7: =E6+D7 -> #DIV/0! | F7: =IF(AND(E7<=0),"C",IF(E7<=0.8,"A",IF(E7<=0.95,"B","C"))) -> #DIV/0! | G7: =VLOOKUP(B$4:B$35,I$4:M$35,5,0) -> #DIV/0! | I7: Qs желт Сул | K7: =J7/J$36 -> #DIV/0! | L7: =L6+K7 -> #DIV/0! | M7: =_xlfn.IFS(L7<80%,"A",L7<=95%,"B",L7>95%,"C") -> #DIV/0!
B8: flip черные Сул | D8: =C8/C$36 -> #DIV/0! | E8: =E7+D8 -> #DIV/0! | F8: =IF(AND(E8<=0),"C",IF(E8<=0.8,"A",IF(E8<=0.95,"B","C"))) -> #DIV/0! | G8: =VLOOKUP(B$4:B$35,I$4:M$35,5,0) -> #DIV/0! | I8: flip черные Сул | K8: =J8/J$36 -> #DIV/0! | L8: =L7+K8 -> #DIV/0! | M8: =_xlfn.IFS(L8<80%,"A",L8<=95%,"B",L8>95%,"C") -> #DIV/0!
B9: flip желтые Сул | D9: =C9/C$36 -> #DIV/0! | E9: =E8+D9 -> #DIV/0! | F9: =IF(AND(E9<=0),"C",IF(E9<=0.8,"A",IF(E9<=0.95,"B","C"))) -> #DIV/0! | G9: =VLOOKUP(B$4:B$35,I$4:M$35,5,0) -> #DIV/0! | I9: flip желтые Сул | K9: =J9/J$36 -> #DIV/0! | L9: =L8+K9 -> #DIV/0! | M9: =_xlfn.IFS(L9<80%,"A",L9<=95%,"B",L9>95%,"C") -> #DIV/0!
B10: MR8854 C2 Сул | D10: =C10/C$36 -> #DIV/0! | E10: =E9+D10 -> #DIV/0! | F10: =IF(AND(E10<=0),"C",IF(E10<=0.8,"A",IF(E10<=0.95,"B","C"))) -> #DIV/0! | G10: =VLOOKUP(B$4:B$35,I$4:M$35,5,0) -> #DIV/0! | I10: MR8854 C2 Сул | K10: =J10/J$36 -> #DIV/0! | L10: =L9+K10 -> #DIV/0! | M10: =_xlfn.IFS(L10<80%,"A",L10<=95%,"B",L10>95%,"C") -> #DIV/0!
B11: MR 1819 черн | D11: =C11/C$36 -> #DIV/0! | E11: =E10+D11 -> #DIV/0! | F11: =IF(AND(E11<=0),"C",IF(E11<=0.8,"A",IF(E11<=0.95,"B","C"))) -> #DIV/0! | G11: =VLOOKUP(B$4:B$35,I$4:M$35,5,0) -> #DIV/0! | I11: MR 1819 черн | K11: =J11/J$36 -> #DIV/0! | L11: =L10+K11 -> #DIV/0! | M11: =_xlfn.IFS(L11<80%,"A",L11<=95%,"B",L11>95%,"C") -> #DIV/0!
B12: MR 1819 корич | D12: =C12/C$36 -> #DIV/0! | E12: =E11+D12 -> #DIV/0! | F12: =IF(AND(E12<=0),"C",IF(E12<=0.8,"A",IF(E12<=0.95,"B","C"))) -> #DIV/0! | G12: =VLOOKUP(B$4:B$35,I$4:M$35,5,0) -> #DIV/0! | I12: MR 1819 корич | K12: =J12/J$36 -> #DIV/0! | L12: =L11+K12 -> #DIV/0! | M12: =_xlfn.IFS(L12<80%,"A",L12<=95%,"B",L12>95%,"C") -> #DIV/0!
B13: MR Р1874 черн | D13: =C13/C$36 -> #DIV/0! | E13: =E12+D13 -> #DIV/0! | F13: =IF(AND(E13<=0),"C",IF(E13<=0.8,"A",IF(E13<=0.95,"B","C"))) -> #DIV/0! | G13: =VLOOKUP(B$4:B$35,I$4:M$35,5,0) -> #DIV/0! | I13: MR Р1874 черн | K13: =J13/J$36 -> #DIV/0! | L13: =L12+K13 -> #DIV/0! | M13: =_xlfn.IFS(L13<80%,"A",L13<=95%,"B",L13>95%,"C") -> #DIV/0!
B14: MR Р1874 корич | D14: =C14/C$36 -> #DIV/0! | E14: =E13+D14 -> #DIV/0! | F14: =IF(AND(E14<=0),"C",IF(E14<=0.8,"A",IF(E14<=0.95,"B","C"))) -> #DIV/0! | G14: =VLOOKUP(B$4:B$35,I$4:M$35,5,0) -> #DIV/0! | I14: MR Р1874 корич | K14: =J14/J$36 -> #DIV/0! | L14: =L13+K14 -> #DIV/0! | M14: =_xlfn.IFS(L14<80%,"A",L14<=95%,"B",L14>95%,"C") -> #DIV/0!
B15: MR Р1886 черн | D15: =C15/C$36 -> #DIV/0! | E15: =E14+D15 -> #DIV/0! | F15: =IF(AND(E15<=0),"C",IF(E15<=0.8,"A",IF(E15<=0.95,"B","C"))) -> #DIV/0! | G15: =VLOOKUP(B$4:B$35,I$4:M$35,5,0) -> #DIV/0! | I15: MR Р1886 черн | K15: =J15/J$36 -> #DIV/0! | L15: =L14+K15 -> #DIV/0! | M15: =_xlfn.IFS(L15<80%,"A",L15<=95%,"B",L15>95%,"C") -> #DIV/0!
B16: MR Р1886 корич | D16: =C16/C$36 -> #DIV/0! | E16: =E15+D16 -> #DIV/0! | F16: =IF(AND(E16<=0),"C",IF(E16<=0.8,"A",IF(E16<=0.95,"B","C"))) -> #DIV/0! | G16: =VLOOKUP(B$4:B$35,I$4:M$35,5,0) -> #DIV/0! | I16: MR Р1886 корич | K16: =J16/J$36 -> #DIV/0! | L16: =L15+K16 -> #DIV/0! | M16: =_xlfn.IFS(L16<80%,"A",L16<=95%,"B",L16>95%,"C") -> #DIV/0!
B17: qs001 | D17: =C17/C$36 -> #DIV/0! | E17: =E16+D17 -> #DIV/0! | F17: =IF(AND(E17<=0),"C",IF(E17<=0.8,"A",IF(E17<=0.95,"B","C"))) -> #DIV/0! | G17: =VLOOKUP(B$4:B$35,I$4:M$35,5,0) -> #DIV/0! | I17: qs001 | K17: =J17/J$36 -> #DIV/0! | L17: =L16+K17 -> #DIV/0! | M17: =_xlfn.IFS(L17<80%,"A",L17<=95%,"B",L17>95%,"C") -> #DIV/0!
B18: qs002 | D18: =C18/C$36 -> #DIV/0! | E18: =E17+D18 -> #DIV/0! | F18: =IF(AND(E18<=0),"C",IF(E18<=0.8,"A",IF(E18<=0.95,"B","C"))) -> #DIV/0! | G18: =VLOOKUP(B$4:B$35,I$4:M$35,5,0) -> #DIV/0! | I18: qs002 | K18: =J18/J$36 -> #DIV/0! | L18: =L17+K18 -> #DIV/0! | M18: =_xlfn.IFS(L18<80%,"A",L18<=95%,"B",L18>95%,"C") -> #DIV/0!
... B35: 6008 | D35: =C35/C$36 -> #DIV/0! | E35: =E34+D35 -> #DIV/0! | F35: =IF(AND(E35<=0),"C",IF(E35<=0.8,"A",IF(E35<=0.95,"B","C"))) -> #DIV/0! | G35: =VLOOKUP(B$4:B$35,I$4:M$35,5,0) -> #DIV/0! | I35: 6008 | K35: =J35/J$36 -> #DIV/0! | L35: =L34+K35 -> #DIV/0! | M35: =_xlfn.IFS(L35<80%,"A",L35<=95%,"B",L35>95%,"C") -> #DIV/0!
C36: =SUM(C4:C16) -> 0 | D36: =SUM(D4:D16) -> #DIV/0! | J36: =SUM(J4:J16) -> 0 | K36: =SUM(K4:K16) -> #DIV/0!

Sheet АВС 7
B2: ОЧКИ
C3: Прибыль | D3: % прибыль | E3: Доля | F3: ABC прибыль | G3: ABC кол-во | J3: Кол-во | K3: % кол-во | L3: Доля | M3: ABC кол-во
B4: Черные с железкой Сул | C4: ='Юнит 7'!AL3 -> 17228.538 | D4: =C4/C$36 -> 0.29979928 | E4: =D4 -> 0.29979928 | F4: =IF(AND(E4<=0),"C",IF(E4<=0.8,"A",IF(E4<=0.95,"B","C"))) -> A | G4: =VLOOKUP(B$4:B$35,I$4:M$35,5,0) -> A | I4: Черные с железкой Сул | J4: ='Юнит 7'!S3 -> 50 | K4: =J4/J$36 -> 0.23809524 | L4: =K4 -> 0.23809524 | M4: =_xlfn.IFS(L4<80%,"A",L4<=95%,"B",L4>95%,"C") -> A | P4: A | Q4: 0.8
B5: Qs черн Сул | C5: ='Юнит 7'!AL4 -> 20125.028 | D5: =C5/C$36 -> 0.35020203 | E5: =E4+D5 -> 0.65000131 | F5: =IF(AND(E5<=0),"C",IF(E5<=0.8,"A",IF(E5<=0.95,"B","C"))) -> A | G5: =VLOOKUP(B$4:B$35,I$4:M$35,5,0) -> A | I5: Qs черн Сул | J5: ='Юнит 7'!S4 -> 72 | K5: =J5/J$36 -> 0.34285714 | L5: =L4+K5 -> 0.58095238 | M5: =_xlfn.IFS(L5<80%,"A",L5<=95%,"B",L5>95%,"C") -> A | P5: B | Q5: 0.15
B6: Qs син Сул | C6: ='Юнит 7'!AL5 -> 428.6604 | D6: =C6/C$36 -> 0.0074592564 | E6: =E5+D6 -> 0.65746056 | F6: =IF(AND(E6<=0),"C",IF(E6<=0.8,"A",IF(E6<=0.95,"B","C"))) -> A | G6: =VLOOKUP(B$4:B$35,I$4:M$35,5,0) -> A | I6: Qs син Сул | J6: ='Юнит 7'!S5 -> 3 | K6: =J6/J$36 -> 0.014285714 | L6: =L5+K6 -> 0.5952381 | M6: =_xlfn.IFS(L6<80%,"A",L6<=95%,"B",L6>95%,"C") -> A | P6: C | Q6: 0.05
B7: Qs желт Сул | C7: ='Юнит 7'!AL6 -> 1904.0494 | D7: =C7/C$36 -> 0.033132971 | E7: =E6+D7 -> 0.69059353 | F7: =IF(AND(E7<=0),"C",IF(E7<=0.8,"A",IF(E7<=0.95,"B","C"))) -> A | G7: =VLOOKUP(B$4:B$35,I$4:M$35,5,0) -> A | I7: Qs желт Сул | J7: ='Юнит 7'!S6 -> 16 | K7: =J7/J$36 -> 0.076190476 | L7: =L6+K7 -> 0.67142857 | M7: =_xlfn.IFS(L7<80%,"A",L7<=95%,"B",L7>95%,"C") -> A
B8: flip черные Сул | C8: ='Юнит 7'!AL7 -> 5729.5206 | D8: =C8/C$36 -> 0.099701216 | E8: =E7+D8 -> 0.79029475 | F8: =IF(AND(E8<=0),"C",IF(E8<=0.8,"A",IF(E8<=0.95,"B","C"))) -> A | G8: =VLOOKUP(B$4:B$35,I$4:M$35,5,0) -> A | I8: flip черные Сул | J8: ='Юнит 7'!S7 -> 22 | K8: =J8/J$36 -> 0.1047619 | L8: =L7+K8 -> 0.77619048 | M8: =_xlfn.IFS(L8<80%,"A",L8<=95%,"B",L8>95%,"C") -> A
B9: flip желтые Сул | C9: ='Юнит 7'!AL8 -> 5902.157 | D9: =C9/C$36 -> 0.10270532 | E9: =E8+D9 -> 0.89300007 | F9: =IF(AND(E9<=0),"C",IF(E9<=0.8,"A",IF(E9<=0.95,"B","C"))) -> B | G9: =VLOOKUP(B$4:B$35,I$4:M$35,5,0) -> B | I9: flip желтые Сул | J9: ='Юнит 7'!S8 -> 24 | K9: =J9/J$36 -> 0.11428571 | L9: =L8+K9 -> 0.89047619 | M9: =_xlfn.IFS(L9<80%,"A",L9<=95%,"B",L9>95%,"C") -> B
B10: MR8854 C2 Сул | C10: ='Юнит 7'!AL9 -> 4814.9045 | D10: =C10/C$36 -> 0.083785689 | E10: =E9+D10 -> 0.97678576 | F10: =IF(AND(E10<=0),"C",IF(E10<=0.8,"A",IF(E10<=0.95,"B","C"))) -> C | G10: =VLOOKUP(B$4:B$35,I$4:M$35,5,0) -> B | I10: MR8854 C2 Сул | J10: ='Юнит 7'!S9 -> 11 | K10: =J10/J$36 -> 0.052380952 | L10: =L9+K10 -> 0.94285714 | M10: =_xlfn.IFS(L10<80%,"A",L10<=95%,"B",L10>95%,"C") -> B
B11: MR 1819 черн | C11: ='Юнит 7'!AL10 -> -2385.838 | D11: =C11/C$36 -> -0.041516728 | E11: =E10+D11 -> 0.93526903 | F11: =IF(AND(E11<=0),"C",IF(E11<=0.8,"A",IF(E11<=0.95,"B","C"))) -> B | G11: =VLOOKUP(B$4:B$35,I$4:M$35,5,0) -> C | I11: MR 1819 черн | J11: ='Юнит 7'!S10 -> 3 | K11: =J11/J$36 -> 0.014285714 | L11: =L10+K11 -> 0.95714286 | M11: =_xlfn.IFS(L11<80%,"A",L11<=95%,"B",L11>95%,"C") -> C
B12: MR 1819 корич | C12: ='Юнит 7'!AL11 -> -135.49913 | D12: =C12/C$36 -> -0.0023578636 | E12: =E11+D12 -> 0.93291116 | F12: =IF(AND(E12<=0),"C",IF(E12<=0.8,"A",IF(E12<=0.95,"B","C"))) -> B | G12: =VLOOKUP(B$4:B$35,I$4:M$35,5,0) -> C | I12: MR 1819 корич | J12: ='Юнит 7'!S11 -> 0 | K12: =J12/J$36 -> 0 | L12: =L11+K12 -> 0.95714286 | M12: =_xlfn.IFS(L12<80%,"A",L12<=95%,"B",L12>95%,"C") -> C
B13: MR Р1874 черн | C13: ='Юнит 7'!AL12 -> 1392.2638 | D13: =C13/C$36 -> 0.024227226 | E13: =E12+D13 -> 0.95713839 | F13: =IF(AND(E13<=0),"C",IF(E13<=0.8,"A",IF(E13<=0.95,"B","C"))) -> C | G13: =VLOOKUP(B$4:B$35,I$4:M$35,5,0) -> C | I13: MR Р1874 черн | J13: ='Юнит 7'!S12 -> 4 | K13: =J13/J$36 -> 0.019047619 | L13: =L12+K13 -> 0.97619048 | M13: =_xlfn.IFS(L13<80%,"A",L13<=95%,"B",L13>95%,"C") -> C
B14: MR Р1874 корич | C14: ='Юнит 7'!AL13 -> 1091.9077 | D14: =C14/C$36 -> 0.019000634 | E14: =E13+D14 -> 0.97613902 | F14: =IF(AND(E14<=0),"C",IF(E14<=0.8,"A",IF(E14<=0.95,"B","C"))) -> C | G14: =VLOOKUP(B$4:B$35,I$4:M$35,5,0) -> C | I14: MR Р1874 корич | J14: ='Юнит 7'!S13 -> 2 | K14: =J14/J$36 -> 0.0095238095 | L14: =L13+K14 -> 0.98571429 | M14: =_xlfn.IFS(L14<80%,"A",L14<=95%,"B",L14>95%,"C") -> C
B15: MR Р1886 черн | C15: ='Юнит 7'!AL14 -> 1055.2304 | D15: =C15/C$36 -> 0.018362401 | E15: =E14+D15 -> 0.99450142 | F15: =IF(AND(E15<=0),"C",IF(E15<=0.8,"A",IF(E15<=0.95,"B","C"))) -> C | G15: =VLOOKUP(B$4:B$35,I$4:M$35,5,0) -> C | I15: MR Р1886 черн | J15: ='Юнит 7'!S14 -> 2 | K15: =J15/J$36 -> 0.0095238095 | L15: =L14+K15 -> 0.9952381 | M15: =_xlfn.IFS(L15<80%,"A",L15<=95%,"B",L15>95%,"C") -> C
B16: MR Р1886 корич | C16: ='Юнит 7'!AL15 -> 315.98611 | D16: =C16/C$36 -> 0.0054985751 | E16: =E15+D16 -> 1 | F16: =IF(AND(E16<=0),"C",IF(E16<=0.8,"A",IF(E16<=0.95,"B","C"))) -> C | G16: =VLOOKUP(B$4:B$35,I$4:M$35,5,0) -> C | I16: MR Р1886 корич | J16: ='Юнит 7'!S15 -> 1 | K16: =J16/J$36 -> 0.0047619048 | L16: =L15+K16 -> 1 | M16: =_xlfn.IFS(L16<80%,"A",L16<=95%,"B",L16>95%,"C") -> C
B17: qs001 | C17: ='Юнит 7'!AL16 -> 0 | D17: =C17/C$36 -> 0 | E17: =E16+D17 -> 1 | F17: =IF(AND(E17<=0),"C",IF(E17<=0.8,"A",IF(E17<=0.95,"B","C"))) -> C | G17: =VLOOKUP(B$4:B$35,I$4:M$35,5,0) -> C | I17: qs001 | J17: ='Юнит 7'!S16 -> 0 | K17: =J17/J$36 -> 0 | L17: =L16+K17 -> 1 | M17: =_xlfn.IFS(L17<80%,"A",L17<=95%,"B",L17>95%,"C") -> C
B18: qs002 | C18: ='Юнит 7'!AL17 -> 0 | D18: =C18/C$36 -> 0 | E18: =E17+D18 -> 1 | F18: =IF(AND(E18<=0),"C",IF(E18<=0.8,"A",IF(E18<=0.95,"B","C"))) -> C | G18: =VLOOKUP(B$4:B$35,I$4:M$35,5,0) -> C | I18: qs002 | J18: ='Юнит 7'!S17 -> 0 | K18: =J18/J$36 -> 0 | L18: =L17+K18 -> 1 | M18: =_xlfn.IFS(L18<80%,"A",L18<=95%,"B",L18>95%,"C") -> C
... B22: qs013 | C22: ='Юнит 7'!AL21 -> 0 | D22: =C22/C$36 -> 0 | E22: =E21+D22 -> 1 | F22: =IF(AND(E22<=0),"C",IF(E22<=0.8,"A",IF(E22<=0.95,"B","C"))) -> C | G22: =VLOOKUP(B$4:B$35,I$4:M$35,5,0) -> C | I22: qs013 | J22: ='Юнит 7'!S21 -> 0 | K22: =J22/J$36 -> 0 | L22: =L21+K22 -> 1 | M22: =_xlfn.IFS(L22<80%,"A",L22<=95%,"B",L22>95%,"C") -> C
B23: qs015 | C23: ='Юнит 7'!AL23 -> 0 | D23: =C23/C$36 -> 0 | E23: =E22+D23 -> 1 | F23: =IF(AND(E23<=0),"C",IF(E23<=0.8,"A",IF(E23<=0.95,"B","C"))) -> C | G23: =VLOOKUP(B$4:B$35,I$4:M$35,5,0) -> C | I23: qs014 | J23: ='Юнит 7'!S22 -> 0 | K23: =J23/J$36 -> 0 | L23: =L22+K23 -> 1 | M23: =_xlfn.IFS(L23<80%,"A",L23<=95%,"B",L23>95%,"C") -> C
B24: qs010ж | C24: ='Юнит 7'!AL25 -> 0 | D24: =C24/C$36 -> 0 | E24: =E23+D24 -> 1 | F24: =IF(AND(E24<=0),"C",IF(E24<=0.8,"A",IF(E24<=0.95,"B","C"))) -> C | G24: =VLOOKUP(B$4:B$35,I$4:M$35,5,0) -> C | I24: qs015 | J24: ='Юнит 7'!S23 -> 0 | K24: =J24/J$36 -> 0 | L24: =L23+K24 -> 1 | M24: =_xlfn.IFS(L24<80%,"A",L24<=95%,"B",L24>95%,"C") -> C
B25: qs011ж | C25: ='Юнит 7'!AL26 -> 0 | D25: =C25/C$36 -> 0 | E25: =E24+D25 -> 1 | F25: =IF(AND(E25<=0),"C",IF(E25<=0.8,"A",IF(E25<=0.95,"B","C"))) -> C | G25: =VLOOKUP(B$4:B$35,I$4:M$35,5,0) -> C | I25: qs001 Ж | J25: ='Юнит 7'!S24 -> 0 | K25: =J25/J$36 -> 0 | L25: =L24+K25 -> 1 | M25: =_xlfn.IFS(L25<80%,"A",L25<=95%,"B",L25>95%,"C") -> C
B26: 2038ч/б | C26: ='Юнит 7'!AL28 -> 0 | D26: =C26/C$36 -> 0 | E26: =E25+D26 -> 1 | F26: =IF(AND(E26<=0),"C",IF(E26<=0.8,"A",IF(E26<=0.95,"B","C"))) -> C | G26: =VLOOKUP(B$4:B$35,I$4:M$35,5,0) -> C | I26: qs010ж | J26: ='Юнит 7'!S25 -> 0 | K26: =J26/J$36 -> 0 | L26: =L25+K26 -> 1 | M26: =_xlfn.IFS(L26<80%,"A",L26<=95%,"B",L26>95%,"C") -> C
B27: 2100красный | C27: ='Юнит 7'!AL31 -> 0 | D27: =C27/C$36 -> 0 | E27: =E26+D27 -> 1 | F27: =IF(AND(E27<=0),"C",IF(E27<=0.8,"A",IF(E27<=0.95,"B","C"))) -> C | G27: =VLOOKUP(B$4:B$35,I$4:M$35,5,0) -> C | I27: qs011ж | J27: ='Юнит 7'!S26 -> 0 | K27: =J27/J$36 -> 0 | L27: =L26+K27 -> 1 | M27: =_xlfn.IFS(L27<80%,"A",L27<=95%,"B",L27>95%,"C") -> C
B28: 2104 | C28: ='Юнит 7'!AL33 -> 0 | D28: =C28/C$36 -> 0 | E28: =E27+D28 -> 1 | F28: =IF(AND(E28<=0),"C",IF(E28<=0.8,"A",IF(E28<=0.95,"B","C"))) -> C | G28: =VLOOKUP(B$4:B$35,I$4:M$35,5,0) -> C | I28: qs012ж | J28: ='Юнит 7'!S27 -> 0 | K28: =J28/J$36 -> 0 | L28: =L27+K28 -> 1 | M28: =_xlfn.IFS(L28<80%,"A",L28<=95%,"B",L28>95%,"C") -> C
B29: 6008 | C29: ='Юнит 7'!AL34 -> 0 | D29: =C29/C$36 -> 0 | E29: =E28+D29 -> 1 | F29: =IF(AND(E29<=0),"C",IF(E29<=0.8,"A",IF(E29<=0.95,"B","C"))) -> C | G29: =VLOOKUP(B$4:B$35,I$4:M$35,5,0) -> C | I29: 2038ч/б | J29: ='Юнит 7'!S28 -> 0 | K29: =J29/J$36 -> 0 | L29: =L28+K29 -> 1 | M29: =_xlfn.IFS(L29<80%,"A",L29<=95%,"B",L29>95%,"C") -> C
B30: qs014 | C30: ='Юнит 7'!AL22 -> -7 | D30: =C30/C$36 -> -0.00012180923 | E30: =E29+D30 -> 0.99987819 | F30: =IF(AND(E30<=0),"C",IF(E30<=0.8,"A",IF(E30<=0.95,"B","C"))) -> C | G30: =VLOOKUP(B$4:B$35,I$4:M$35,5,0) -> C | I30: 2038красный | J30: ='Юнит 7'!S29 -> 0 | K30: =J30/J$36 -> 0 | L30: =L29+K30 -> 1 | M30: =_xlfn.IFS(L30<80%,"A",L30<=95%,"B",L30>95%,"C") -> C
B31: qs012ж | C31: ='Юнит 7'!AL27 -> -376 | D31: =C31/C$36 -> -0.006542896 | E31: =E30+D31 -> 0.99333529 | F31: =IF(AND(E31<=0),"C",IF(E31<=0.8,"A",IF(E31<=0.95,"B","C"))) -> C | G31: =VLOOKUP(B$4:B$35,I$4:M$35,5,0) -> C | I31: 2100черный | J31: ='Юнит 7'!S30 -> 0 | K31: =J31/J$36 -> 0 | L31: =L30+K31 -> 1 | M31: =_xlfn.IFS(L31<80%,"A",L31<=95%,"B",L31>95%,"C") -> C
B32: 2100фиолетовый | C32: ='Юнит 7'!AL32 -> -427 | D32: =C32/C$36 -> -0.0074303632 | E32: =E31+D32 -> 0.98590493 | F32: =IF(AND(E32<=0),"C",IF(E32<=0.8,"A",IF(E32<=0.95,"B","C"))) -> C | G32: =VLOOKUP(B$4:B$35,I$4:M$35,5,0) -> C | I32: 2100красный | J32: ='Юнит 7'!S31 -> 0 | K32: =J32/J$36 -> 0 | L32: =L31+K32 -> 1 | M32: =_xlfn.IFS(L32<80%,"A",L32<=95%,"B",L32>95%,"C") -> C
B33: 2038красный | C33: ='Юнит 7'!AL29 -> -1000 | D33: =C33/C$36 -> -0.017401319 | E33: =E32+D33 -> 0.96850361 | F33: =IF(AND(E33<=0),"C",IF(E33<=0.8,"A",IF(E33<=0.95,"B","C"))) -> C | G33: =VLOOKUP(B$4:B$35,I$4:M$35,5,0) -> C | I33: 2100фиолетовый | J33: ='Юнит 7'!S32 -> 0 | K33: =J33/J$36 -> 0 | L33: =L32+K33 -> 1 | M33: =_xlfn.IFS(L33<80%,"A",L33<=95%,"B",L33>95%,"C") -> C
B34: 2100черный | C34: ='Юнит 7'!AL30 -> -1119 | D34: =C34/C$36 -> -0.019472076 | E34: =E33+D34 -> 0.94903154 | F34: =IF(AND(E34<=0),"C",IF(E34<=0.8,"A",IF(E34<=0.95,"B","C"))) -> B | G34: =VLOOKUP(B$4:B$35,I$4:M$35,5,0) -> C | I34: 2104 | J34: ='Юнит 7'!S33 -> 0 | K34: =J34/J$36 -> 0 | L34: =L33+K34 -> 1 | M34: =_xlfn.IFS(L34<80%,"A",L34<=95%,"B",L34>95%,"C") -> C
B35: qs001 Ж | C35: ='Юнит 7'!AL24 -> -2321.16 | D35: =C35/C$36 -> -0.040391246 | E35: =E34+D35 -> 0.90864029 | F35: =IF(AND(E35<=0),"C",IF(E35<=0.8,"A",IF(E35<=0.95,"B","C"))) -> B | G35: =VLOOKUP(B$4:B$35,I$4:M$35,5,0) -> C | I35: 6008 | J35: ='Юнит 7'!S34 -> 0 | K35: =J35/J$36 -> 0 | L35: =L34+K35 -> 1 | M35: =_xlfn.IFS(L35<80%,"A",L35<=95%,"B",L35>95%,"C") -> C
C36: =SUM(C4:C16) -> 57466.908 | D36: =SUM(D4:D16) -> 1 | J36: =SUM(J4:J16) -> 210 | K36: =SUM(K4:K16) -> 1

Sheet АВС 6
B2: ОЧКИ
C3: Прибыль | D3: % прибыль | E3: Доля | F3: ABC прибыль | G3: ABC кол-во | J3: Кол-во | K3: % кол-во | L3: Доля | M3: ABC кол-во
B4: Черные с железкой Сул | C4: ='Юнит 6'!AL3 -> 9916.5357 | D4: =C4/C$17 -> 0.38321324 | E4: =D4 -> 0.38321324 | F4: =IF(AND(E4<=0),"C",IF(E4<=0.8,"A",IF(E4<=0.95,"B","C"))) -> A | G4: =VLOOKUP(B$4:B$16,I$4:M$16,5,0) -> A | I4: Черные с железкой Сул | J4: ='Юнит 6'!S3 -> 32 | K4: =J4/J$17 -> 0.27350427 | L4: =K4 -> 0.27350427 | M4: =_xlfn.IFS(L4<80%,"A",L4<=95%,"B",L4>95%,"C") -> A | P4: A | Q4: 0.8
B5: flip желтые Сул | C5: ='Юнит 6'!AL8 -> 6651.9986 | D5: =C5/C$17 -> 0.25705892 | E5: =E4+D5 -> 0.64027216 | F5: =IF(AND(E5<=0),"C",IF(E5<=0.8,"A",IF(E5<=0.95,"B","C"))) -> A | G5: =VLOOKUP(B$4:B$16,I$4:M$16,5,0) -> A | I5: Qs черн Сул | J5: ='Юнит 6'!S4 -> 29 | K5: =J5/J$17 -> 0.24786325 | L5: =L4+K5 -> 0.52136752 | M5: =_xlfn.IFS(L5<80%,"A",L5<=95%,"B",L5>95%,"C") -> A | P5: B | Q5: 0.15
B6: MR8854 C2 Сул | C6: ='Юнит 6'!AL9 -> 6205.3623 | D6: =C6/C$17 -> 0.23979917 | E6: =E5+D6 -> 0.88007133 | F6: =IF(AND(E6<=0),"C",IF(E6<=0.8,"A",IF(E6<=0.95,"B","C"))) -> B | G6: =VLOOKUP(B$4:B$16,I$4:M$16,5,0) -> B | I6: flip желтые Сул | J6: ='Юнит 6'!S8 -> 21 | K6: =J6/J$17 -> 0.17948718 | L6: =L5+K6 -> 0.7008547 | M6: =_xlfn.IFS(L6<80%,"A",L6<=95%,"B",L6>95%,"C") -> A | P6: C | Q6: 0.05
B7: Qs черн Сул | C7: ='Юнит 6'!AL4 -> 2677.6761 | D7: =C7/C$17 -> 0.10347575 | E7: =E6+D7 -> 0.98354708 | F7: =IF(AND(E7<=0),"C",IF(E7<=0.8,"A",IF(E7<=0.95,"B","C"))) -> C | G7: =VLOOKUP(B$4:B$16,I$4:M$16,5,0) -> A | I7: MR8854 C2 Сул | J7: ='Юнит 6'!S9 -> 14 | K7: =J7/J$17 -> 0.11965812 | L7: =L6+K7 -> 0.82051282 | M7: =_xlfn.IFS(L7<80%,"A",L7<=95%,"B",L7>95%,"C") -> B
B8: MR Р1886 черн | C8: ='Юнит 6'!AL14 -> 984.5023 | D8: =C8/C$17 -> 0.038044972 | E8: =E7+D8 -> 1.0215921 | F8: =IF(AND(E8<=0),"C",IF(E8<=0.8,"A",IF(E8<=0.95,"B","C"))) -> C | G8: =VLOOKUP(B$4:B$16,I$4:M$16,5,0) -> C | I8: flip черные Сул | J8: ='Юнит 6'!S7 -> 6 | K8: =J8/J$17 -> 0.051282051 | L8: =L7+K8 -> 0.87179487 | M8: =_xlfn.IFS(L8<80%,"A",L8<=95%,"B",L8>95%,"C") -> B
B9: MR 1819 корич | C9: ='Юнит 6'!AL11 -> 468.75573 | D9: =C9/C$17 -> 0.018114532 | E9: =E8+D9 -> 1.0397066 | F9: =IF(AND(E9<=0),"C",IF(E9<=0.8,"A",IF(E9<=0.95,"B","C"))) -> C | G9: =VLOOKUP(B$4:B$16,I$4:M$16,5,0) -> C | I9: Qs желт Сул | J9: ='Юнит 6'!S6 -> 5 | K9: =J9/J$17 -> 0.042735043 | L9: =L8+K9 -> 0.91452991 | M9: =_xlfn.IFS(L9<80%,"A",L9<=95%,"B",L9>95%,"C") -> B
B10: MR Р1874 корич | C10: ='Юнит 6'!AL13 -> 444.23552 | D10: =C10/C$17 -> 0.017166977 | E10: =E9+D10 -> 1.0568736 | F10: =IF(AND(E10<=0),"C",IF(E10<=0.8,"A",IF(E10<=0.95,"B","C"))) -> C | G10: =VLOOKUP(B$4:B$16,I$4:M$16,5,0) -> C | I10: Qs син Сул | J10: ='Юнит 6'!S5 -> 4 | K10: =J10/J$17 -> 0.034188034 | L10: =L9+K10 -> 0.94871795 | M10: =_xlfn.IFS(L10<80%,"A",L10<=95%,"B",L10>95%,"C") -> B
B11: flip черные Сул | C11: ='Юнит 6'!AL7 -> 342.73976 | D11: =C11/C$17 -> 0.013244788 | E11: =E10+D11 -> 1.0701183 | F11: =IF(AND(E11<=0),"C",IF(E11<=0.8,"A",IF(E11<=0.95,"B","C"))) -> C | G11: =VLOOKUP(B$4:B$16,I$4:M$16,5,0) -> B | I11: MR 1819 черн | J11: ='Юнит 6'!S10 -> 2 | K11: =J11/J$17 -> 0.017094017 | L11: =L10+K11 -> 0.96581197 | M11: =_xlfn.IFS(L11<80%,"A",L11<=95%,"B",L11>95%,"C") -> C
B12: Qs син Сул | C12: ='Юнит 6'!AL5 -> 262.77695 | D12: =C12/C$17 -> 0.010154716 | E12: =E11+D12 -> 1.0802731 | F12: =IF(AND(E12<=0),"C",IF(E12<=0.8,"A",IF(E12<=0.95,"B","C"))) -> C | G12: =VLOOKUP(B$4:B$16,I$4:M$16,5,0) -> B | I12: MR Р1886 черн | J12: ='Юнит 6'!S14 -> 2 | K12: =J12/J$17 -> 0.017094017 | L12: =L11+K12 -> 0.98290598 | M12: =_xlfn.IFS(L12<80%,"A",L12<=95%,"B",L12>95%,"C") -> C
B13: MR Р1886 корич | C13: ='Юнит 6'!AL15 -> -21.357206 | D13: =C13/C$17 -> -0.00082532495 | E13: =E12+D13 -> 1.0794477 | F13: =IF(AND(E13<=0),"C",IF(E13<=0.8,"A",IF(E13<=0.95,"B","C"))) -> C | G13: =VLOOKUP(B$4:B$16,I$4:M$16,5,0) -> C | I13: MR 1819 корич | J13: ='Юнит 6'!S11 -> 1 | K13: =J13/J$17 -> 0.0085470085 | L13: =L12+K13 -> 0.99145299 | M13: =_xlfn.IFS(L13<80%,"A",L13<=95%,"B",L13>95%,"C") -> C
B14: MR Р1874 черн | C14: ='Юнит 6'!AL12 -> -133.91392 | D14: =C14/C$17 -> -0.0051749511 | E14: =E13+D14 -> 1.0742728 | F14: =IF(AND(E14<=0),"C",IF(E14<=0.8,"A",IF(E14<=0.95,"B","C"))) -> C | G14: =VLOOKUP(B$4:B$16,I$4:M$16,5,0) -> C | I14: MR Р1874 корич | J14: ='Юнит 6'!S13 -> 1 | K14: =J14/J$17 -> 0.0085470085 | L14: =L13+K14 -> 1 | M14: =_xlfn.IFS(L14<80%,"A",L14<=95%,"B",L14>95%,"C") -> C
B15: Qs желт Сул | C15: ='Юнит 6'!AL6 -> -248.9843 | D15: =C15/C$17 -> -0.0096217151 | E15: =E14+D15 -> 1.0646511 | F15: =IF(AND(E15<=0),"C",IF(E15<=0.8,"A",IF(E15<=0.95,"B","C"))) -> C | G15: =VLOOKUP(B$4:B$16,I$4:M$16,5,0) -> B | I15: MR Р1874 черн | J15: ='Юнит 6'!S12 -> 0 | K15: =J15/J$17 -> 0 | L15: =L14+K15 -> 1 | M15: =_xlfn.IFS(L15<80%,"A",L15<=95%,"B",L15>95%,"C") -> C
B16: MR 1819 черн | C16: ='Юнит 6'!AL10 -> -1672.9972 | D16: =C16/C$17 -> -0.064651074 | E16: =E15+D16 -> 1 | F16: =IF(AND(E16<=0),"C",IF(E16<=0.8,"A",IF(E16<=0.95,"B","C"))) -> C | G16: =VLOOKUP(B$4:B$16,I$4:M$16,5,0) -> C | I16: MR Р1886 корич | J16: ='Юнит 6'!S15 -> 0 | K16: =J16/J$17 -> 0 | L16: =L15+K16 -> 1 | M16: =_xlfn.IFS(L16<80%,"A",L16<=95%,"B",L16>95%,"C") -> C
C17: =SUM(C4:C16) -> 25877.33 | D17: =SUM(D4:D16) -> 1 | J17: =SUM(J4:J16) -> 117 | K17: =SUM(K4:K16) -> 1
C20: Прибыль | D20: % прибыль | E20: Доля | F20: ABC прибыль | G20: ABC кол-во | J20: Кол-во | K20: % кол-во | L20: Доля | M20: ABC кол-во
D21: =C21/C$73 -> #DIV/0! | E21: =D21 -> #DIV/0! | F21: =IF(AND(E21<=0),"C",IF(E21<=0.8,"A",IF(E21<=0.95,"B","C"))) -> #DIV/0! | G21: =VLOOKUP(B21:B72,I$21:M$72,5,0) -> #N/A | K21: =J21/J$73 -> #DIV/0! | L21: =K21 -> #DIV/0! | M21: =_xlfn.IFS(L21<80%,"A",L21<=95%,"B",L21>95%,"C") -> #DIV/0!
D22: =C22/C$73 -> #DIV/0! | E22: =D22+E21 -> #DIV/0! | F22: =IF(AND(E22<=0),"C",IF(E22<=0.8,"A",IF(E22<=0.95,"B","C"))) -> #DIV/0! | G22: =VLOOKUP(B22:B73,I$21:M$72,5,0) -> #N/A | K22: =J22/J$73 -> #DIV/0! | L22: =K22+L21 -> #DIV/0! | M22: =_xlfn.IFS(L22<80%,"A",L22<=95%,"B",L22>95%,"C") -> #DIV/0!
D23: =C23/C$73 -> #DIV/0! | E23: =D23+E22 -> #DIV/0! | F23: =IF(AND(E23<=0),"C",IF(E23<=0.8,"A",IF(E23<=0.95,"B","C"))) -> #DIV/0! | G23: =VLOOKUP(B23:B74,I$21:M$72,5,0) -> #N/A | K23: =J23/J$73 -> #DIV/0! | L23: =K23+L22 -> #DIV/0! | M23: =_xlfn.IFS(L23<80%,"A",L23<=95%,"B",L23>95%,"C") -> #DIV/0!
D24: =C24/C$73 -> #DIV/0! | E24: =D24+E23 -> #DIV/0! | F24: =IF(AND(E24<=0),"C",IF(E24<=0.8,"A",IF(E24<=0.95,"B","C"))) -> #DIV/0! | G24: =VLOOKUP(B24:B75,I$21:M$72,5,0) -> #N/A | K24: =J24/J$73 -> #DIV/0! | L24: =K24+L23 -> #DIV/0! | M24: =_xlfn.IFS(L24<80%,"A",L24<=95%,"B",L24>95%,"C") -> #DIV/0!
D25: =C25/C$73 -> #DIV/0! | E25: =D25+E24 -> #DIV/0! | F25: =IF(AND(E25<=0),"C",IF(E25<=0.8,"A",IF(E25<=0.95,"B","C"))) -> #DIV/0! | G25: =VLOOKUP(B25:B76,I$21:M$72,5,0) -> #N/A | K25: =J25/J$73 -> #DIV/0! | L25: =K25+L24 -> #DIV/0! | M25: =_xlfn.IFS(L25<80%,"A",L25<=95%,"B",L25>95%,"C") -> #DIV/0!
D26: =C26/C$73 -> #DIV/0! | E26: =D26+E25 -> #DIV/0! | F26: =IF(AND(E26<=0),"C",IF(E26<=0.8,"A",IF(E26<=0.95,"B","C"))) -> #DIV/0! | G26: =VLOOKUP(B26:B77,I$21:M$72,5,0) -> #N/A | K26: =J26/J$73 -> #DIV/0! | L26: =K26+L25 -> #DIV/0! | M26: =_xlfn.IFS(L26<80%,"A",L26<=95%,"B",L26>95%,"C") -> #DIV/0!
D27: =C27/C$73 -> #DIV/0! | E27: =D27+E26 -> #DIV/0! | F27: =IF(AND(E27<=0),"C",IF(E27<=0.8,"A",IF(E27<=0.95,"B","C"))) -> #DIV/0! | G27: =VLOOKUP(B27:B78,I$21:M$72,5,0) -> #N/A | K27: =J27/J$73 -> #DIV/0! | L27: =K27+L26 -> #DIV/0! | M27: =_xlfn.IFS(L27<80%,"A",L27<=95%,"B",L27>95%,"C") -> #DIV/0!
D28: =C28/C$73 -> #DIV/0! | E28: =D28+E27 -> #DIV/0! | F28: =IF(AND(E28<=0),"C",IF(E28<=0.8,"A",IF(E28<=0.95,"B","C"))) -> #DIV/0! | G28: =VLOOKUP(B28:B79,I$21:M$72,5,0) -> #N/A | K28: =J28/J$73 -> #DIV/0! | L28: =K28+L27 -> #DIV/0! | M28: =_xlfn.IFS(L28<80%,"A",L28<=95%,"B",L28>95%,"C") -> #DIV/0!
D29: =C29/C$73 -> #DIV/0! | E29: =D29+E28 -> #DIV/0! | F29: =IF(AND(E29<=0),"C",IF(E29<=0.8,"A",IF(E29<=0.95,"B","C"))) -> #DIV/0! | G29: =VLOOKUP(B29:B80,I$21:M$72,5,0) -> #N/A | K29: =J29/J$73 -> #DIV/0! | L29: =K29+L28 -> #DIV/0! | M29: =_xlfn.IFS(L29<80%,"A",L29<=95%,"B",L29>95%,"C") -> #DIV/0!
D30: =C30/C$73 -> #DIV/0! | E30: =D30+E29 -> #DIV/0! | F30: =IF(AND(E30<=0),"C",IF(E30<=0.8,"A",IF(E30<=0.95,"B","C"))) -> #DIV/0! | G30: =VLOOKUP(B30:B81,I$21:M$72,5,0) -> #N/A | K30: =J30/J$73 -> #DIV/0! | L30: =K30+L29 -> #DIV/0! | M30: =_xlfn.IFS(L30<80%,"A",L30<=95%,"B",L30>95%,"C") -> #DIV/0!
D31: =C31/C$73 -> #DIV/0! | E31: =D31+E30 -> #DIV/0! | F31: =IF(AND(E31<=0),"C",IF(E31<=0.8,"A",IF(E31<=0.95,"B","C"))) -> #DIV/0! | G31: =VLOOKUP(B31:B82,I$21:M$72,5,0) -> #N/A | K31: =J31/J$73 -> #DIV/0! | L31: =K31+L30 -> #DIV/0! | M31: =_xlfn.IFS(L31<80%,"A",L31<=95%,"B",L31>95%,"C") -> #DIV/0!
D32: =C32/C$73 -> #DIV/0! | E32: =D32+E31 -> #DIV/0! | F32: =IF(AND(E32<=0),"C",IF(E32<=0.8,"A",IF(E32<=0.95,"B","C"))) -> #DIV/0! | G32: =VLOOKUP(B32:B83,I$21:M$72,5,0) -> #N/A | K32: =J32/J$73 -> #DIV/0! | L32: =K32+L31 -> #DIV/0! | M32: =_xlfn.IFS(L32<80%,"A",L32<=95%,"B",L32>95%,"C") -> #DIV/0!
D33: =C33/C$73 -> #DIV/0! | E33: =D33+E32 -> #DIV/0! | F33: =IF(AND(E33<=0),"C",IF(E33<=0.8,"A",IF(E33<=0.95,"B","C"))) -> #DIV/0! | G33: =VLOOKUP(B33:B84,I$21:M$72,5,0) -> #N/A | K33: =J33/J$73 -> #DIV/0! | L33: =K33+L32 -> #DIV/0! | M33: =_xlfn.IFS(L33<80%,"A",L33<=95%,"B",L33>95%,"C") -> #DIV/0!
... D72: =C72/C$73 -> #DIV/0! | E72: =D72+E71 -> #DIV/0! | F72: =IF(AND(E72<=0),"C",IF(E72<=0.8,"A",IF(E72<=0.95,"B","C"))) -> #DIV/0! | G72: =VLOOKUP(B72:B123,I$21:M$72,5,0) -> #N/A | K72: =J72/J$73 -> #DIV/0! | L72: =K72+L71 -> #DIV/0! | M72: =_xlfn.IFS(L72<80%,"A",L72<=95%,"B",L72>95%,"C") -> #DIV/0!
C73: =SUM(C21:C72) -> 0 | D73: =SUM(D21:D72) -> #DIV/0! | J73: =SUM(J21:J72) -> 0 | K73: =SUM(K21:K72) -> #DIV/0!

Sheet АВС ЯНВАРЬ
B2: ОЧКИ
C3: Прибыль | D3: % прибыль | E3: Доля | F3: ABC прибыль | G3: ABC кол-во | J3: Кол-во | K3: % кол-во | L3: Доля | M3: ABC кол-во
B4: flip желтые Сул | C4: ='Юнит 5'!AL8 -> 2045.1121 | D4: =C4/C$17 -> 0.29333616 | E4: =D4 -> 0.29333616 | F4: =IF(AND(E4<=0),"C",IF(E4<=0.8,"A",IF(E4<=0.95,"B","C"))) -> A | G4: =VLOOKUP(B$4:B$16,I$4:M$16,5,0) -> A | I4: flip желтые Сул | J4: =ЯНВАРЬ!S8 -> 107 | K4: =J4/J$17 -> 0.42629482 | L4: =K4 -> 0.42629482 | M4: =_xlfn.IFS(L4<80%,"A",L4<=95%,"B",L4>95%,"C") -> A | P4: A | Q4: 0.8
B5: Черные с железкой Сул | C5: ='Юнит 5'!AL3 -> 1813.3318 | D5: =C5/C$17 -> 0.26009127 | E5: =E4+D5 -> 0.55342742 | F5: =IF(AND(E5<=0),"C",IF(E5<=0.8,"A",IF(E5<=0.95,"B","C"))) -> A | G5: =VLOOKUP(B$4:B$16,I$4:M$16,5,0) -> A | I5: Черные с железкой Сул | J5: =ЯНВАРЬ!S3 -> 62 | K5: =J5/J$17 -> 0.24701195 | L5: =L4+K5 -> 0.67330677 | M5: =_xlfn.IFS(L5<80%,"A",L5<=95%,"B",L5>95%,"C") -> A | P5: B | Q5: 0.15
B6: Qs желт Сул | C6: ='Юнит 5'!AL6 -> 1154.6045 | D6: =C6/C$17 -> 0.16560816 | E6: =E5+D6 -> 0.71903559 | F6: =IF(AND(E6<=0),"C",IF(E6<=0.8,"A",IF(E6<=0.95,"B","C"))) -> A | G6: =VLOOKUP(B$4:B$16,I$4:M$16,5,0) -> B | I6: MR8854 C2 Сул | J6: =ЯНВАРЬ!S9 -> 26 | K6: =J6/J$17 -> 0.10358566 | L6: =L5+K6 -> 0.77689243 | M6: =_xlfn.IFS(L6<80%,"A",L6<=95%,"B",L6>95%,"C") -> A | P6: C | Q6: 0.05
B7: MR Р1886 черн | C7: ='Юнит 5'!AL14 -> 826.78813 | D7: =C7/C$17 -> 0.11858854 | E7: =E6+D7 -> 0.83762412 | F7: =IF(AND(E7<=0),"C",IF(E7<=0.8,"A",IF(E7<=0.95,"B","C"))) -> B | G7: =VLOOKUP(B$4:B$16,I$4:M$16,5,0) -> B | I7: Qs желт Сул | J7: =ЯНВАРЬ!S6 -> 20 | K7: =J7/J$17 -> 0.079681275 | L7: =L6+K7 -> 0.85657371 | M7: =_xlfn.IFS(L7<80%,"A",L7<=95%,"B",L7>95%,"C") -> B
B8: MR Р1874 черн | C8: ='Юнит 5'!AL12 -> 783.16961 | D8: =C8/C$17 -> 0.11233221 | E8: =E7+D8 -> 0.94995634 | F8: =IF(AND(E8<=0),"C",IF(E8<=0.8,"A",IF(E8<=0.95,"B","C"))) -> B | G8: =VLOOKUP(B$4:B$16,I$4:M$16,5,0) -> C | I8: Qs черн Сул | J8: =ЯНВАРЬ!S4 -> 10 | K8: =J8/J$17 -> 0.039840637 | L8: =L7+K8 -> 0.89641434 | M8: =_xlfn.IFS(L8<80%,"A",L8<=95%,"B",L8>95%,"C") -> B
B9: MR 1819 корич | C9: ='Юнит 5'!AL11 -> 758.76739 | D9: =C9/C$17 -> 0.10883214 | E9: =E8+D9 -> 1.0587885 | F9: =IF(AND(E9<=0),"C",IF(E9<=0.8,"A",IF(E9<=0.95,"B","C"))) -> C | G9: =VLOOKUP(B$4:B$16,I$4:M$16,5,0) -> C | I9: MR Р1886 черн | J9: =ЯНВАРЬ!S14 -> 6 | K9: =J9/J$17 -> 0.023904382 | L9: =L8+K9 -> 0.92031873 | M9: =_xlfn.IFS(L9<80%,"A",L9<=95%,"B",L9>95%,"C") -> B
B10: MR Р1874 корич | C10: ='Юнит 5'!AL13 -> 508.76629 | D10: =C10/C$17 -> 0.072973776 | E10: =E9+D10 -> 1.1317623 | F10: =IF(AND(E10<=0),"C",IF(E10<=0.8,"A",IF(E10<=0.95,"B","C"))) -> C | G10: =VLOOKUP(B$4:B$16,I$4:M$16,5,0) -> C | I10: Qs син Сул | J10: =ЯНВАРЬ!S5 -> 4 | K10: =J10/J$17 -> 0.015936255 | L10: =L9+K10 -> 0.93625498 | M10: =_xlfn.IFS(L10<80%,"A",L10<=95%,"B",L10>95%,"C") -> B
B11: MR 1819 черн | C11: ='Юнит 5'!AL10 -> 398.95943 | D11: =C11/C$17 -> 0.05722387 | E11: =E10+D11 -> 1.1889861 | F11: =IF(AND(E11<=0),"C",IF(E11<=0.8,"A",IF(E11<=0.95,"B","C"))) -> C | G11: =VLOOKUP(B$4:B$16,I$4:M$16,5,0) -> C | I11: MR Р1874 корич | J11: =ЯНВАРЬ!S13 -> 4 | K11: =J11/J$17 -> 0.015936255 | L11: =L10+K11 -> 0.95219124 | M11: =_xlfn.IFS(L11<80%,"A",L11<=95%,"B",L11>95%,"C") -> C
B12: MR8854 C2 Сул | C12: ='Юнит 5'!AL9 -> 297.0268 | D12: =C12/C$17 -> 0.042603387 | E12: =E11+D12 -> 1.2315895 | F12: =IF(AND(E12<=0),"C",IF(E12<=0.8,"A",IF(E12<=0.95,"B","C"))) -> C | G12: =VLOOKUP(B$4:B$16,I$4:M$16,5,0) -> A | I12: MR 1819 корич | J12: =ЯНВАРЬ!S11 -> 3 | K12: =J12/J$17 -> 0.011952191 | L12: =L11+K12 -> 0.96414343 | M12: =_xlfn.IFS(L12<80%,"A",L12<=95%,"B",L12>95%,"C") -> C
B13: Qs черн Сул | C13: ='Юнит 5'!AL4 -> 177.70464 | D13: =C13/C$17 -> 0.025488675 | E13: =E12+D13 -> 1.2570782 | F13: =IF(AND(E13<=0),"C",IF(E13<=0.8,"A",IF(E13<=0.95,"B","C"))) -> C | G13: =VLOOKUP(B$4:B$16,I$4:M$16,5,0) -> B | I13: MR Р1874 черн | J13: =ЯНВАРЬ!S12 -> 3 | K13: =J13/J$17 -> 0.011952191 | L13: =L12+K13 -> 0.97609562 | M13: =_xlfn.IFS(L13<80%,"A",L13<=95%,"B",L13>95%,"C") -> C
B14: MR Р1886 корич | C14: ='Юнит 5'!AL15 -> -22.030753 | D14: =C14/C$17 -> -0.0031599326 | E14: =E13+D14 -> 1.2539182 | F14: =IF(AND(E14<=0),"C",IF(E14<=0.8,"A",IF(E14<=0.95,"B","C"))) -> C | G14: =VLOOKUP(B$4:B$16,I$4:M$16,5,0) -> C | I14: MR Р1886 корич | J14: =ЯНВАРЬ!S15 -> 3 | K14: =J14/J$17 -> 0.011952191 | L14: =L13+K14 -> 0.98804781 | M14: =_xlfn.IFS(L14<80%,"A",L14<=95%,"B",L14>95%,"C") -> C
B15: flip черные Сул | C15: ='Юнит 5'!AL7 -> -852.48176 | D15: =C15/C$17 -> -0.12227385 | E15: =E14+D15 -> 1.1316444 | F15: =IF(AND(E15<=0),"C",IF(E15<=0.8,"A",IF(E15<=0.95,"B","C"))) -> C | G15: =VLOOKUP(B$4:B$16,I$4:M$16,5,0) -> C | I15: MR 1819 черн | J15: =ЯНВАРЬ!S10 -> 2 | K15: =J15/J$17 -> 0.0079681275 | L15: =L14+K15 -> 0.99601594 | M15: =_xlfn.IFS(L15<80%,"A",L15<=95%,"B",L15>95%,"C") -> C
B16: Qs син Сул | C16: ='Юнит 5'!AL5 -> -917.81235 | D16: =C16/C$17 -> -0.1316444 | E16: =E15+D16 -> 1 | F16: =IF(AND(E16<=0),"C",IF(E16<=0.8,"A",IF(E16<=0.95,"B","C"))) -> C | G16: =VLOOKUP(B$4:B$16,I$4:M$16,5,0) -> B | I16: flip черные Сул | J16: =ЯНВАРЬ!S7 -> 1 | K16: =J16/J$17 -> 0.0039840637 | L16: =L15+K16 -> 1 | M16: =_xlfn.IFS(L16<80%,"A",L16<=95%,"B",L16>95%,"C") -> C
C17: =SUM(C4:C16) -> 6971.9058 | D17: =SUM(D4:D16) -> 1 | J17: =SUM(J4:J16) -> 251 | K17: =SUM(K4:K16) -> 1
C20: Прибыль | D20: % прибыль | E20: Доля | F20: ABC прибыль | G20: ABC кол-во | J20: Кол-во | K20: % кол-во | L20: Доля | M20: ABC кол-во
D21: =C21/C$73 -> #DIV/0! | E21: =D21 -> #DIV/0! | F21: =IF(AND(E21<=0),"C",IF(E21<=0.8,"A",IF(E21<=0.95,"B","C"))) -> #DIV/0! | G21: =VLOOKUP(B21:B72,I$21:M$72,5,0) -> #N/A | K21: =J21/J$73 -> #DIV/0! | L21: =K21 -> #DIV/0! | M21: =_xlfn.IFS(L21<80%,"A",L21<=95%,"B",L21>95%,"C") -> #DIV/0!
D22: =C22/C$73 -> #DIV/0! | E22: =D22+E21 -> #DIV/0! | F22: =IF(AND(E22<=0),"C",IF(E22<=0.8,"A",IF(E22<=0.95,"B","C"))) -> #DIV/0! | G22: =VLOOKUP(B22:B73,I$21:M$72,5,0) -> #N/A | K22: =J22/J$73 -> #DIV/0! | L22: =K22+L21 -> #DIV/0! | M22: =_xlfn.IFS(L22<80%,"A",L22<=95%,"B",L22>95%,"C") -> #DIV/0!
D23: =C23/C$73 -> #DIV/0! | E23: =D23+E22 -> #DIV/0! | F23: =IF(AND(E23<=0),"C",IF(E23<=0.8,"A",IF(E23<=0.95,"B","C"))) -> #DIV/0! | G23: =VLOOKUP(B23:B74,I$21:M$72,5,0) -> #N/A | K23: =J23/J$73 -> #DIV/0! | L23: =K23+L22 -> #DIV/0! | M23: =_xlfn.IFS(L23<80%,"A",L23<=95%,"B",L23>95%,"C") -> #DIV/0!
D24: =C24/C$73 -> #DIV/0! | E24: =D24+E23 -> #DIV/0! | F24: =IF(AND(E24<=0),"C",IF(E24<=0.8,"A",IF(E24<=0.95,"B","C"))) -> #DIV/0! | G24: =VLOOKUP(B24:B75,I$21:M$72,5,0) -> #N/A | K24: =J24/J$73 -> #DIV/0! | L24: =K24+L23 -> #DIV/0! | M24: =_xlfn.IFS(L24<80%,"A",L24<=95%,"B",L24>95%,"C") -> #DIV/0!
D25: =C25/C$73 -> #DIV/0! | E25: =D25+E24 -> #DIV/0! | F25: =IF(AND(E25<=0),"C",IF(E25<=0.8,"A",IF(E25<=0.95,"B","C"))) -> #DIV/0! | G25: =VLOOKUP(B25:B76,I$21:M$72,5,0) -> #N/A | K25: =J25/J$73 -> #DIV/0! | L25: =K25+L24 -> #DIV/0! | M25: =_xlfn.IFS(L25<80%,"A",L25<=95%,"B",L25>95%,"C") -> #DIV/0!
D26: =C26/C$73 -> #DIV/0! | E26: =D26+E25 -> #DIV/0! | F26: =IF(AND(E26<=0),"C",IF(E26<=0.8,"A",IF(E26<=0.95,"B","C"))) -> #DIV/0! | G26: =VLOOKUP(B26:B77,I$21:M$72,5,0) -> #N/A | K26: =J26/J$73 -> #DIV/0! | L26: =K26+L25 -> #DIV/0! | M26: =_xlfn.IFS(L26<80%,"A",L26<=95%,"B",L26>95%,"C") -> #DIV/0!
D27: =C27/C$73 -> #DIV/0! | E27: =D27+E26 -> #DIV/0! | F27: =IF(AND(E27<=0),"C",IF(E27<=0.8,"A",IF(E27<=0.95,"B","C"))) -> #DIV/0! | G27: =VLOOKUP(B27:B78,I$21:M$72,5,0) -> #N/A | K27: =J27/J$73 -> #DIV/0! | L27: =K27+L26 -> #DIV/0! | M27: =_xlfn.IFS(L27<80%,"A",L27<=95%,"B",L27>95%,"C") -> #DIV/0!
D28: =C28/C$73 -> #DIV/0! | E28: =D28+E27 -> #DIV/0! | F28: =IF(AND(E28<=0),"C",IF(E28<=0.8,"A",IF(E28<=0.95,"B","C"))) -> #DIV/0! | G28: =VLOOKUP(B28:B79,I$21:M$72,5,0) -> #N/A | K28: =J28/J$73 -> #DIV/0! | L28: =K28+L27 -> #DIV/0! | M28: =_xlfn.IFS(L28<80%,"A",L28<=95%,"B",L28>95%,"C") -> #DIV/0!
D29: =C29/C$73 -> #DIV/0! | E29: =D29+E28 -> #DIV/0! | F29: =IF(AND(E29<=0),"C",IF(E29<=0.8,"A",IF(E29<=0.95,"B","C"))) -> #DIV/0! | G29: =VLOOKUP(B29:B80,I$21:M$72,5,0) -> #N/A | K29: =J29/J$73 -> #DIV/0! | L29: =K29+L28 -> #DIV/0! | M29: =_xlfn.IFS(L29<80%,"A",L29<=95%,"B",L29>95%,"C") -> #DIV/0!
D30: =C30/C$73 -> #DIV/0! | E30: =D30+E29 -> #DIV/0! | F30: =IF(AND(E30<=0),"C",IF(E30<=0.8,"A",IF(E30<=0.95,"B","C"))) -> #DIV/0! | G30: =VLOOKUP(B30:B81,I$21:M$72,5,0) -> #N/A | K30: =J30/J$73 -> #DIV/0! | L30: =K30+L29 -> #DIV/0! | M30: =_xlfn.IFS(L30<80%,"A",L30<=95%,"B",L30>95%,"C") -> #DIV/0!
D31: =C31/C$73 -> #DIV/0! | E31: =D31+E30 -> #DIV/0! | F31: =IF(AND(E31<=0),"C",IF(E31<=0.8,"A",IF(E31<=0.95,"B","C"))) -> #DIV/0! | G31: =VLOOKUP(B31:B82,I$21:M$72,5,0) -> #N/A | K31: =J31/J$73 -> #DIV/0! | L31: =K31+L30 -> #DIV/0! | M31: =_xlfn.IFS(L31<80%,"A",L31<=95%,"B",L31>95%,"C") -> #DIV/0!
D32: =C32/C$73 -> #DIV/0! | E32: =D32+E31 -> #DIV/0! | F32: =IF(AND(E32<=0),"C",IF(E32<=0.8,"A",IF(E32<=0.95,"B","C"))) -> #DIV/0! | G32: =VLOOKUP(B32:B83,I$21:M$72,5,0) -> #N/A | K32: =J32/J$73 -> #DIV/0! | L32: =K32+L31 -> #DIV/0! | M32: =_xlfn.IFS(L32<80%,"A",L32<=95%,"B",L32>95%,"C") -> #DIV/0!
D33: =C33/C$73 -> #DIV/0! | E33: =D33+E32 -> #DIV/0! | F33: =IF(AND(E33<=0),"C",IF(E33<=0.8,"A",IF(E33<=0.95,"B","C"))) -> #DIV/0! | G33: =VLOOKUP(B33:B84,I$21:M$72,5,0) -> #N/A | K33: =J33/J$73 -> #DIV/0! | L33: =K33+L32 -> #DIV/0! | M33: =_xlfn.IFS(L33<80%,"A",L33<=95%,"B",L33>95%,"C") -> #DIV/0!
... D72: =C72/C$73 -> #DIV/0! | E72: =D72+E71 -> #DIV/0! | F72: =IF(AND(E72<=0),"C",IF(E72<=0.8,"A",IF(E72<=0.95,"B","C"))) -> #DIV/0! | G72: =VLOOKUP(B72:B123,I$21:M$72,5,0) -> #N/A | K72: =J72/J$73 -> #DIV/0! | L72: =K72+L71 -> #DIV/0! | M72: =_xlfn.IFS(L72<80%,"A",L72<=95%,"B",L72>95%,"C") -> #DIV/0!
C73: =SUM(C21:C72) -> 0 | D73: =SUM(D21:D72) -> #DIV/0! | J73: =SUM(J21:J72) -> 0 | K73: =SUM(K21:K72) -> #DIV/0!

Sheet АВС 5
B2: ОЧКИ
C3: Прибыль | D3: % прибыль | E3: Доля | F3: ABC прибыль | G3: ABC кол-во | J3: Кол-во | K3: % кол-во | L3: Доля | M3: ABC кол-во
B4: flip желтые Сул | C4: ='Юнит 5'!AL8 -> 2045.1121 | D4: =C4/C$17 -> 0.29333616 | E4: =D4 -> 0.29333616 | F4: =IF(AND(E4<=0),"C",IF(E4<=0.8,"A",IF(E4<=0.95,"B","C"))) -> A | G4: =VLOOKUP(B$4:B$16,I$4:M$16,5,0) -> A | I4: Черные с железкой Сул | J4: ='Юнит 5'!S3 -> 19 | K4: =J4/J$17 -> 0.27536232 | L4: =K4 -> 0.27536232 | M4: =_xlfn.IFS(L4<80%,"A",L4<=95%,"B",L4>95%,"C") -> A | P4: A | Q4: 0.8
B5: Черные с железкой Сул | C5: ='Юнит 5'!AL3 -> 1813.3318 | D5: =C5/C$17 -> 0.26009127 | E5: =E4+D5 -> 0.55342742 | F5: =IF(AND(E5<=0),"C",IF(E5<=0.8,"A",IF(E5<=0.95,"B","C"))) -> A | G5: =VLOOKUP(B$4:B$16,I$4:M$16,5,0) -> A | I5: flip желтые Сул | J5: ='Юнит 5'!S8 -> 14 | K5: =J5/J$17 -> 0.20289855 | L5: =L4+K5 -> 0.47826087 | M5: =_xlfn.IFS(L5<80%,"A",L5<=95%,"B",L5>95%,"C") -> A | P5: B | Q5: 0.15
B6: Qs желт Сул | C6: ='Юнит 5'!AL6 -> 1154.6045 | D6: =C6/C$17 -> 0.16560816 | E6: =E5+D6 -> 0.71903559 | F6: =IF(AND(E6<=0),"C",IF(E6<=0.8,"A",IF(E6<=0.95,"B","C"))) -> A | G6: =VLOOKUP(B$4:B$16,I$4:M$16,5,0) -> B | I6: MR8854 C2 Сул | J6: ='Юнит 5'!S9 -> 11 | K6: =J6/J$17 -> 0.15942029 | L6: =L5+K6 -> 0.63768116 | M6: =_xlfn.IFS(L6<80%,"A",L6<=95%,"B",L6>95%,"C") -> A | P6: C | Q6: 0.05
B7: MR Р1886 черн | C7: ='Юнит 5'!AL14 -> 826.78813 | D7: =C7/C$17 -> 0.11858854 | E7: =E6+D7 -> 0.83762412 | F7: =IF(AND(E7<=0),"C",IF(E7<=0.8,"A",IF(E7<=0.95,"B","C"))) -> B | G7: =VLOOKUP(B$4:B$16,I$4:M$16,5,0) -> C | I7: Qs черн Сул | J7: ='Юнит 5'!S4 -> 10 | K7: =J7/J$17 -> 0.14492754 | L7: =L6+K7 -> 0.7826087 | M7: =_xlfn.IFS(L7<80%,"A",L7<=95%,"B",L7>95%,"C") -> A
B8: MR Р1874 черн | C8: ='Юнит 5'!AL12 -> 783.16961 | D8: =C8/C$17 -> 0.11233221 | E8: =E7+D8 -> 0.94995634 | F8: =IF(AND(E8<=0),"C",IF(E8<=0.8,"A",IF(E8<=0.95,"B","C"))) -> B | G8: =VLOOKUP(B$4:B$16,I$4:M$16,5,0) -> B | I8: Qs син Сул | J8: ='Юнит 5'!S5 -> 3 | K8: =J8/J$17 -> 0.043478261 | L8: =L7+K8 -> 0.82608696 | M8: =_xlfn.IFS(L8<80%,"A",L8<=95%,"B",L8>95%,"C") -> B
B9: MR 1819 корич | C9: ='Юнит 5'!AL11 -> 758.76739 | D9: =C9/C$17 -> 0.10883214 | E9: =E8+D9 -> 1.0587885 | F9: =IF(AND(E9<=0),"C",IF(E9<=0.8,"A",IF(E9<=0.95,"B","C"))) -> C | G9: =VLOOKUP(B$4:B$16,I$4:M$16,5,0) -> B | I9: Qs желт Сул | J9: ='Юнит 5'!S6 -> 3 | K9: =J9/J$17 -> 0.043478261 | L9: =L8+K9 -> 0.86956522 | M9: =_xlfn.IFS(L9<80%,"A",L9<=95%,"B",L9>95%,"C") -> B
B10: MR Р1874 корич | C10: ='Юнит 5'!AL13 -> 508.76629 | D10: =C10/C$17 -> 0.072973776 | E10: =E9+D10 -> 1.1317623 | F10: =IF(AND(E10<=0),"C",IF(E10<=0.8,"A",IF(E10<=0.95,"B","C"))) -> C | G10: =VLOOKUP(B$4:B$16,I$4:M$16,5,0) -> C | I10: MR 1819 корич | J10: ='Юнит 5'!S11 -> 2 | K10: =J10/J$17 -> 0.028985507 | L10: =L9+K10 -> 0.89855072 | M10: =_xlfn.IFS(L10<80%,"A",L10<=95%,"B",L10>95%,"C") -> B
B11: MR 1819 черн | C11: ='Юнит 5'!AL10 -> 398.95943 | D11: =C11/C$17 -> 0.05722387 | E11: =E10+D11 -> 1.1889861 | F11: =IF(AND(E11<=0),"C",IF(E11<=0.8,"A",IF(E11<=0.95,"B","C"))) -> C | G11: =VLOOKUP(B$4:B$16,I$4:M$16,5,0) -> C | I11: MR Р1874 черн | J11: ='Юнит 5'!S12 -> 2 | K11: =J11/J$17 -> 0.028985507 | L11: =L10+K11 -> 0.92753623 | M11: =_xlfn.IFS(L11<80%,"A",L11<=95%,"B",L11>95%,"C") -> B
B12: MR8854 C2 Сул | C12: ='Юнит 5'!AL9 -> 297.0268 | D12: =C12/C$17 -> 0.042603387 | E12: =E11+D12 -> 1.2315895 | F12: =IF(AND(E12<=0),"C",IF(E12<=0.8,"A",IF(E12<=0.95,"B","C"))) -> C | G12: =VLOOKUP(B$4:B$16,I$4:M$16,5,0) -> A | I12: MR Р1886 черн | J12: ='Юнит 5'!S14 -> 2 | K12: =J12/J$17 -> 0.028985507 | L12: =L11+K12 -> 0.95652174 | M12: =_xlfn.IFS(L12<80%,"A",L12<=95%,"B",L12>95%,"C") -> C
B13: Qs черн Сул | C13: ='Юнит 5'!AL4 -> 177.70464 | D13: =C13/C$17 -> 0.025488675 | E13: =E12+D13 -> 1.2570782 | F13: =IF(AND(E13<=0),"C",IF(E13<=0.8,"A",IF(E13<=0.95,"B","C"))) -> C | G13: =VLOOKUP(B$4:B$16,I$4:M$16,5,0) -> A | I13: flip черные Сул | J13: ='Юнит 5'!S7 -> 1 | K13: =J13/J$17 -> 0.014492754 | L13: =L12+K13 -> 0.97101449 | M13: =_xlfn.IFS(L13<80%,"A",L13<=95%,"B",L13>95%,"C") -> C
B14: MR Р1886 корич | C14: ='Юнит 5'!AL15 -> -22.030753 | D14: =C14/C$17 -> -0.0031599326 | E14: =E13+D14 -> 1.2539182 | F14: =IF(AND(E14<=0),"C",IF(E14<=0.8,"A",IF(E14<=0.95,"B","C"))) -> C | G14: =VLOOKUP(B$4:B$16,I$4:M$16,5,0) -> C | I14: MR 1819 черн | J14: ='Юнит 5'!S10 -> 1 | K14: =J14/J$17 -> 0.014492754 | L14: =L13+K14 -> 0.98550725 | M14: =_xlfn.IFS(L14<80%,"A",L14<=95%,"B",L14>95%,"C") -> C
B15: flip черные Сул | C15: ='Юнит 5'!AL7 -> -852.48176 | D15: =C15/C$17 -> -0.12227385 | E15: =E14+D15 -> 1.1316444 | F15: =IF(AND(E15<=0),"C",IF(E15<=0.8,"A",IF(E15<=0.95,"B","C"))) -> C | G15: =VLOOKUP(B$4:B$16,I$4:M$16,5,0) -> C | I15: MR Р1874 корич | J15: ='Юнит 5'!S13 -> 1 | K15: =J15/J$17 -> 0.014492754 | L15: =L14+K15 -> 1 | M15: =_xlfn.IFS(L15<80%,"A",L15<=95%,"B",L15>95%,"C") -> C
B16: Qs син Сул | C16: ='Юнит 5'!AL5 -> -917.81235 | D16: =C16/C$17 -> -0.1316444 | E16: =E15+D16 -> 1 | F16: =IF(AND(E16<=0),"C",IF(E16<=0.8,"A",IF(E16<=0.95,"B","C"))) -> C | G16: =VLOOKUP(B$4:B$16,I$4:M$16,5,0) -> B | I16: MR Р1886 корич | J16: ='Юнит 5'!S15 -> 0 | K16: =J16/J$17 -> 0 | L16: =L15+K16 -> 1 | M16: =_xlfn.IFS(L16<80%,"A",L16<=95%,"B",L16>95%,"C") -> C
C17: =SUM(C4:C16) -> 6971.9058 | D17: =SUM(D4:D16) -> 1 | J17: =SUM(J4:J16) -> 69 | K17: =SUM(K4:K16) -> 1
C20: Прибыль | D20: % прибыль | E20: Доля | F20: ABC прибыль | G20: ABC кол-во | J20: Кол-во | K20: % кол-во | L20: Доля | M20: ABC кол-во
D21: =C21/C$73 -> #DIV/0! | E21: =D21 -> #DIV/0! | F21: =IF(AND(E21<=0),"C",IF(E21<=0.8,"A",IF(E21<=0.95,"B","C"))) -> #DIV/0! | G21: =VLOOKUP(B21:B72,I$21:M$72,5,0) -> #N/A | K21: =J21/J$73 -> #DIV/0! | L21: =K21 -> #DIV/0! | M21: =_xlfn.IFS(L21<80%,"A",L21<=95%,"B",L21>95%,"C") -> #DIV/0!
D22: =C22/C$73 -> #DIV/0! | E22: =D22+E21 -> #DIV/0! | F22: =IF(AND(E22<=0),"C",IF(E22<=0.8,"A",IF(E22<=0.95,"B","C"))) -> #DIV/0! | G22: =VLOOKUP(B22:B73,I$21:M$72,5,0) -> #N/A | K22: =J22/J$73 -> #DIV/0! | L22: =K22+L21 -> #DIV/0! | M22: =_xlfn.IFS(L22<80%,"A",L22<=95%,"B",L22>95%,"C") -> #DIV/0!
D23: =C23/C$73 -> #DIV/0! | E23: =D23+E22 -> #DIV/0! | F23: =IF(AND(E23<=0),"C",IF(E23<=0.8,"A",IF(E23<=0.95,"B","C"))) -> #DIV/0! | G23: =VLOOKUP(B23:B74,I$21:M$72,5,0) -> #N/A | K23: =J23/J$73 -> #DIV/0! | L23: =K23+L22 -> #DIV/0! | M23: =_xlfn.IFS(L23<80%,"A",L23<=95%,"B",L23>95%,"C") -> #DIV/0!
D24: =C24/C$73 -> #DIV/0! | E24: =D24+E23 -> #DIV/0! | F24: =IF(AND(E24<=0),"C",IF(E24<=0.8,"A",IF(E24<=0.95,"B","C"))) -> #DIV/0! | G24: =VLOOKUP(B24:B75,I$21:M$72,5,0) -> #N/A | K24: =J24/J$73 -> #DIV/0! | L24: =K24+L23 -> #DIV/0! | M24: =_xlfn.IFS(L24<80%,"A",L24<=95%,"B",L24>95%,"C") -> #DIV/0!
D25: =C25/C$73 -> #DIV/0! | E25: =D25+E24 -> #DIV/0! | F25: =IF(AND(E25<=0),"C",IF(E25<=0.8,"A",IF(E25<=0.95,"B","C"))) -> #DIV/0! | G25: =VLOOKUP(B25:B76,I$21:M$72,5,0) -> #N/A | K25: =J25/J$73 -> #DIV/0! | L25: =K25+L24 -> #DIV/0! | M25: =_xlfn.IFS(L25<80%,"A",L25<=95%,"B",L25>95%,"C") -> #DIV/0!
D26: =C26/C$73 -> #DIV/0! | E26: =D26+E25 -> #DIV/0! | F26: =IF(AND(E26<=0),"C",IF(E26<=0.8,"A",IF(E26<=0.95,"B","C"))) -> #DIV/0! | G26: =VLOOKUP(B26:B77,I$21:M$72,5,0) -> #N/A | K26: =J26/J$73 -> #DIV/0! | L26: =K26+L25 -> #DIV/0! | M26: =_xlfn.IFS(L26<80%,"A",L26<=95%,"B",L26>95%,"C") -> #DIV/0!
D27: =C27/C$73 -> #DIV/0! | E27: =D27+E26 -> #DIV/0! | F27: =IF(AND(E27<=0),"C",IF(E27<=0.8,"A",IF(E27<=0.95,"B","C"))) -> #DIV/0! | G27: =VLOOKUP(B27:B78,I$21:M$72,5,0) -> #N/A | K27: =J27/J$73 -> #DIV/0! | L27: =K27+L26 -> #DIV/0! | M27: =_xlfn.IFS(L27<80%,"A",L27<=95%,"B",L27>95%,"C") -> #DIV/0!
D28: =C28/C$73 -> #DIV/0! | E28: =D28+E27 -> #DIV/0! | F28: =IF(AND(E28<=0),"C",IF(E28<=0.8,"A",IF(E28<=0.95,"B","C"))) -> #DIV/0! | G28: =VLOOKUP(B28:B79,I$21:M$72,5,0) -> #N/A | K28: =J28/J$73 -> #DIV/0! | L28: =K28+L27 -> #DIV/0! | M28: =_xlfn.IFS(L28<80%,"A",L28<=95%,"B",L28>95%,"C") -> #DIV/0!
D29: =C29/C$73 -> #DIV/0! | E29: =D29+E28 -> #DIV/0! | F29: =IF(AND(E29<=0),"C",IF(E29<=0.8,"A",IF(E29<=0.95,"B","C"))) -> #DIV/0! | G29: =VLOOKUP(B29:B80,I$21:M$72,5,0) -> #N/A | K29: =J29/J$73 -> #DIV/0! | L29: =K29+L28 -> #DIV/0! | M29: =_xlfn.IFS(L29<80%,"A",L29<=95%,"B",L29>95%,"C") -> #DIV/0!
D30: =C30/C$73 -> #DIV/0! | E30: =D30+E29 -> #DIV/0! | F30: =IF(AND(E30<=0),"C",IF(E30<=0.8,"A",IF(E30<=0.95,"B","C"))) -> #DIV/0! | G30: =VLOOKUP(B30:B81,I$21:M$72,5,0) -> #N/A | K30: =J30/J$73 -> #DIV/0! | L30: =K30+L29 -> #DIV/0! | M30: =_xlfn.IFS(L30<80%,"A",L30<=95%,"B",L30>95%,"C") -> #DIV/0!
D31: =C31/C$73 -> #DIV/0! | E31: =D31+E30 -> #DIV/0! | F31: =IF(AND(E31<=0),"C",IF(E31<=0.8,"A",IF(E31<=0.95,"B","C"))) -> #DIV/0! | G31: =VLOOKUP(B31:B82,I$21:M$72,5,0) -> #N/A | K31: =J31/J$73 -> #DIV/0! | L31: =K31+L30 -> #DIV/0! | M31: =_xlfn.IFS(L31<80%,"A",L31<=95%,"B",L31>95%,"C") -> #DIV/0!
D32: =C32/C$73 -> #DIV/0! | E32: =D32+E31 -> #DIV/0! | F32: =IF(AND(E32<=0),"C",IF(E32<=0.8,"A",IF(E32<=0.95,"B","C"))) -> #DIV/0! | G32: =VLOOKUP(B32:B83,I$21:M$72,5,0) -> #N/A | K32: =J32/J$73 -> #DIV/0! | L32: =K32+L31 -> #DIV/0! | M32: =_xlfn.IFS(L32<80%,"A",L32<=95%,"B",L32>95%,"C") -> #DIV/0!
D33: =C33/C$73 -> #DIV/0! | E33: =D33+E32 -> #DIV/0! | F33: =IF(AND(E33<=0),"C",IF(E33<=0.8,"A",IF(E33<=0.95,"B","C"))) -> #DIV/0! | G33: =VLOOKUP(B33:B84,I$21:M$72,5,0) -> #N/A | K33: =J33/J$73 -> #DIV/0! | L33: =K33+L32 -> #DIV/0! | M33: =_xlfn.IFS(L33<80%,"A",L33<=95%,"B",L33>95%,"C") -> #DIV/0!
... D72: =C72/C$73 -> #DIV/0! | E72: =D72+E71 -> #DIV/0! | F72: =IF(AND(E72<=0),"C",IF(E72<=0.8,"A",IF(E72<=0.95,"B","C"))) -> #DIV/0! | G72: =VLOOKUP(B72:B123,I$21:M$72,5,0) -> #N/A | K72: =J72/J$73 -> #DIV/0! | L72: =K72+L71 -> #DIV/0! | M72: =_xlfn.IFS(L72<80%,"A",L72<=95%,"B",L72>95%,"C") -> #DIV/0!
C73: =SUM(C21:C72) -> 0 | D73: =SUM(D21:D72) -> #DIV/0! | J73: =SUM(J21:J72) -> 0 | K73: =SUM(K21:K72) -> #DIV/0!

Sheet АВС 4
B2: ОЧКИ
C3: Прибыль | D3: % прибыль | E3: Доля | F3: ABC прибыль | G3: ABC кол-во | J3: Кол-во | K3: % кол-во | L3: Доля | M3: ABC кол-во
B4: Черные с железкой Сул | C4: ='Юнит 4'!AL3 -> 5677.8442 | D4: =C4/C$17 -> 0.415248 | E4: =D4 -> 0.415248 | F4: =IF(AND(E4<=0),"C",IF(E4<=0.8,"A",IF(E4<=0.95,"B","C"))) -> A | G4: =VLOOKUP(B$4:B$16,I$4:M$16,5,0) -> A | I4: Черные с железкой Сул | J4: ='Юнит 4'!S3 -> 21 | K4: =J4/J$17 -> 0.44680851 | L4: =K4 -> 0.44680851 | M4: =_xlfn.IFS(L4<80%,"A",L4<=95%,"B",L4>95%,"C") -> A | P4: A | Q4: 0.8
B5: flip желтые Сул | C5: ='Юнит 4'!AL8 -> 5497.2061 | D5: =C5/C$17 -> 0.40203707 | E5: =E4+D5 -> 0.81728507 | F5: =IF(AND(E5<=0),"C",IF(E5<=0.8,"A",IF(E5<=0.95,"B","C"))) -> B | G5: =VLOOKUP(B$4:B$16,I$4:M$16,5,0) -> A | I5: flip желтые Сул | J5: ='Юнит 4'!S8 -> 10 | K5: =J5/J$17 -> 0.21276596 | L5: =L4+K5 -> 0.65957447 | M5: =_xlfn.IFS(L5<80%,"A",L5<=95%,"B",L5>95%,"C") -> A | P5: B | Q5: 0.15
B6: Qs желт Сул | C6: ='Юнит 4'!AL6 -> 1821.9753 | D6: =C6/C$17 -> 0.1332498 | E6: =E5+D6 -> 0.95053487 | F6: =IF(AND(E6<=0),"C",IF(E6<=0.8,"A",IF(E6<=0.95,"B","C"))) -> C | G6: =VLOOKUP(B$4:B$16,I$4:M$16,5,0) -> B | I6: MR8854 C2 Сул | J6: ='Юнит 4'!S9 -> 9 | K6: =J6/J$17 -> 0.19148936 | L6: =L5+K6 -> 0.85106383 | M6: =_xlfn.IFS(L6<80%,"A",L6<=95%,"B",L6>95%,"C") -> B | P6: C | Q6: 0.05
B7: MR8854 C2 Сул | C7: ='Юнит 4'!AL9 -> 814.75132 | D7: =C7/C$17 -> 0.059586675 | E7: =E6+D7 -> 1.0101215 | F7: =IF(AND(E7<=0),"C",IF(E7<=0.8,"A",IF(E7<=0.95,"B","C"))) -> C | G7: =VLOOKUP(B$4:B$16,I$4:M$16,5,0) -> B | I7: Qs желт Сул | J7: ='Юнит 4'!S6 -> 4 | K7: =J7/J$17 -> 0.085106383 | L7: =L6+K7 -> 0.93617021 | M7: =_xlfn.IFS(L7<80%,"A",L7<=95%,"B",L7>95%,"C") -> B
B8: MR Р1886 корич | C8: ='Юнит 4'!AL15 -> 550.12526 | D8: =C8/C$17 -> 0.040233301 | E8: =E7+D8 -> 1.0503548 | F8: =IF(AND(E8<=0),"C",IF(E8<=0.8,"A",IF(E8<=0.95,"B","C"))) -> C | G8: =VLOOKUP(B$4:B$16,I$4:M$16,5,0) -> C | I8: MR Р1874 черн | J8: ='Юнит 4'!S12 -> 1 | K8: =J8/J$17 -> 0.021276596 | L8: =L7+K8 -> 0.95744681 | M8: =_xlfn.IFS(L8<80%,"A",L8<=95%,"B",L8>95%,"C") -> C
B9: MR Р1874 черн | C9: ='Юнит 4'!AL12 -> 373.65885 | D9: =C9/C$17 -> 0.027327466 | E9: =E8+D9 -> 1.0776823 | F9: =IF(AND(E9<=0),"C",IF(E9<=0.8,"A",IF(E9<=0.95,"B","C"))) -> C | G9: =VLOOKUP(B$4:B$16,I$4:M$16,5,0) -> C | I9: MR Р1874 корич | J9: ='Юнит 4'!S13 -> 1 | K9: =J9/J$17 -> 0.021276596 | L9: =L8+K9 -> 0.9787234 | M9: =_xlfn.IFS(L9<80%,"A",L9<=95%,"B",L9>95%,"C") -> C
B10: MR Р1874 корич | C10: ='Юнит 4'!AL13 -> 292.29359 | D10: =C10/C$17 -> 0.021376833 | E10: =E9+D10 -> 1.0990591 | F10: =IF(AND(E10<=0),"C",IF(E10<=0.8,"A",IF(E10<=0.95,"B","C"))) -> C | G10: =VLOOKUP(B$4:B$16,I$4:M$16,5,0) -> C | I10: MR Р1886 корич | J10: ='Юнит 4'!S15 -> 1 | K10: =J10/J$17 -> 0.021276596 | L10: =L9+K10 -> 1 | M10: =_xlfn.IFS(L10<80%,"A",L10<=95%,"B",L10>95%,"C") -> C
B11: MR 1819 корич | C11: ='Юнит 4'!AL11 -> -24.942493 | D11: =C11/C$17 -> -0.0018241643 | E11: =E10+D11 -> 1.097235 | F11: =IF(AND(E11<=0),"C",IF(E11<=0.8,"A",IF(E11<=0.95,"B","C"))) -> C | G11: =VLOOKUP(B$4:B$16,I$4:M$16,5,0) -> C | I11: Qs черн Сул | J11: ='Юнит 4'!S4 -> 0 | K11: =J11/J$17 -> 0 | L11: =L10+K11 -> 1 | M11: =_xlfn.IFS(L11<80%,"A",L11<=95%,"B",L11>95%,"C") -> C
B12: MR Р1886 черн | C12: ='Юнит 4'!AL14 -> -37.733516 | D12: =C12/C$17 -> -0.0027596331 | E12: =E11+D12 -> 1.0944753 | F12: =IF(AND(E12<=0),"C",IF(E12<=0.8,"A",IF(E12<=0.95,"B","C"))) -> C | G12: =VLOOKUP(B$4:B$16,I$4:M$16,5,0) -> C | I12: Qs син Сул | J12: ='Юнит 4'!S5 -> 0 | K12: =J12/J$17 -> 0 | L12: =L11+K12 -> 1 | M12: =_xlfn.IFS(L12<80%,"A",L12<=95%,"B",L12>95%,"C") -> C
B13: MR 1819 черн | C13: ='Юнит 4'!AL10 -> -121.34249 | D13: =C13/C$17 -> -0.008874359 | E13: =E12+D13 -> 1.085601 | F13: =IF(AND(E13<=0),"C",IF(E13<=0.8,"A",IF(E13<=0.95,"B","C"))) -> C | G13: =VLOOKUP(B$4:B$16,I$4:M$16,5,0) -> C | I13: flip черные Сул | J13: ='Юнит 4'!S7 -> 0 | K13: =J13/J$17 -> 0 | L13: =L12+K13 -> 1 | M13: =_xlfn.IFS(L13<80%,"A",L13<=95%,"B",L13>95%,"C") -> C
B14: Qs черн Сул | C14: ='Юнит 4'!AL4 -> -294.91162 | D14: =C14/C$17 -> -0.021568302 | E14: =E13+D14 -> 1.0640327 | F14: =IF(AND(E14<=0),"C",IF(E14<=0.8,"A",IF(E14<=0.95,"B","C"))) -> C | G14: =VLOOKUP(B$4:B$16,I$4:M$16,5,0) -> C | I14: MR 1819 черн | J14: ='Юнит 4'!S10 -> 0 | K14: =J14/J$17 -> 0 | L14: =L13+K14 -> 1 | M14: =_xlfn.IFS(L14<80%,"A",L14<=95%,"B",L14>95%,"C") -> C
B15: Qs син Сул | C15: ='Юнит 4'!AL5 -> -383.11077 | D15: =C15/C$17 -> -0.028018729 | E15: =E14+D15 -> 1.036014 | F15: =IF(AND(E15<=0),"C",IF(E15<=0.8,"A",IF(E15<=0.95,"B","C"))) -> C | G15: =VLOOKUP(B$4:B$16,I$4:M$16,5,0) -> C | I15: MR 1819 корич | J15: ='Юнит 4'!S11 -> 0 | K15: =J15/J$17 -> 0 | L15: =L14+K15 -> 1 | M15: =_xlfn.IFS(L15<80%,"A",L15<=95%,"B",L15>95%,"C") -> C
B16: flip черные Сул | C16: ='Юнит 4'!AL7 -> -492.43252 | D16: =C16/C$17 -> -0.036013954 | E16: =E15+D16 -> 1 | F16: =IF(AND(E16<=0),"C",IF(E16<=0.8,"A",IF(E16<=0.95,"B","C"))) -> C | G16: =VLOOKUP(B$4:B$16,I$4:M$16,5,0) -> C | I16: MR Р1886 черн | J16: ='Юнит 4'!S14 -> 0 | K16: =J16/J$17 -> 0 | L16: =L15+K16 -> 1 | M16: =_xlfn.IFS(L16<80%,"A",L16<=95%,"B",L16>95%,"C") -> C
C17: =SUM(C4:C16) -> 13673.381 | D17: =SUM(D4:D16) -> 1 | J17: =SUM(J4:J16) -> 47 | K17: =SUM(K4:K16) -> 1
C20: Прибыль | D20: % прибыль | E20: Доля | F20: ABC прибыль | G20: ABC кол-во | J20: Кол-во | K20: % кол-во | L20: Доля | M20: ABC кол-во
D21: =C21/C$73 -> #DIV/0! | E21: =D21 -> #DIV/0! | F21: =IF(AND(E21<=0),"C",IF(E21<=0.8,"A",IF(E21<=0.95,"B","C"))) -> #DIV/0! | G21: =VLOOKUP(B21:B72,I$21:M$72,5,0) -> #N/A | K21: =J21/J$73 -> #DIV/0! | L21: =K21 -> #DIV/0! | M21: =_xlfn.IFS(L21<80%,"A",L21<=95%,"B",L21>95%,"C") -> #DIV/0!
D22: =C22/C$73 -> #DIV/0! | E22: =D22+E21 -> #DIV/0! | F22: =IF(AND(E22<=0),"C",IF(E22<=0.8,"A",IF(E22<=0.95,"B","C"))) -> #DIV/0! | G22: =VLOOKUP(B22:B73,I$21:M$72,5,0) -> #N/A | K22: =J22/J$73 -> #DIV/0! | L22: =K22+L21 -> #DIV/0! | M22: =_xlfn.IFS(L22<80%,"A",L22<=95%,"B",L22>95%,"C") -> #DIV/0!
D23: =C23/C$73 -> #DIV/0! | E23: =D23+E22 -> #DIV/0! | F23: =IF(AND(E23<=0),"C",IF(E23<=0.8,"A",IF(E23<=0.95,"B","C"))) -> #DIV/0! | G23: =VLOOKUP(B23:B74,I$21:M$72,5,0) -> #N/A | K23: =J23/J$73 -> #DIV/0! | L23: =K23+L22 -> #DIV/0! | M23: =_xlfn.IFS(L23<80%,"A",L23<=95%,"B",L23>95%,"C") -> #DIV/0!
D24: =C24/C$73 -> #DIV/0! | E24: =D24+E23 -> #DIV/0! | F24: =IF(AND(E24<=0),"C",IF(E24<=0.8,"A",IF(E24<=0.95,"B","C"))) -> #DIV/0! | G24: =VLOOKUP(B24:B75,I$21:M$72,5,0) -> #N/A | K24: =J24/J$73 -> #DIV/0! | L24: =K24+L23 -> #DIV/0! | M24: =_xlfn.IFS(L24<80%,"A",L24<=95%,"B",L24>95%,"C") -> #DIV/0!
D25: =C25/C$73 -> #DIV/0! | E25: =D25+E24 -> #DIV/0! | F25: =IF(AND(E25<=0),"C",IF(E25<=0.8,"A",IF(E25<=0.95,"B","C"))) -> #DIV/0! | G25: =VLOOKUP(B25:B76,I$21:M$72,5,0) -> #N/A | K25: =J25/J$73 -> #DIV/0! | L25: =K25+L24 -> #DIV/0! | M25: =_xlfn.IFS(L25<80%,"A",L25<=95%,"B",L25>95%,"C") -> #DIV/0!
D26: =C26/C$73 -> #DIV/0! | E26: =D26+E25 -> #DIV/0! | F26: =IF(AND(E26<=0),"C",IF(E26<=0.8,"A",IF(E26<=0.95,"B","C"))) -> #DIV/0! | G26: =VLOOKUP(B26:B77,I$21:M$72,5,0) -> #N/A | K26: =J26/J$73 -> #DIV/0! | L26: =K26+L25 -> #DIV/0! | M26: =_xlfn.IFS(L26<80%,"A",L26<=95%,"B",L26>95%,"C") -> #DIV/0!
D27: =C27/C$73 -> #DIV/0! | E27: =D27+E26 -> #DIV/0! | F27: =IF(AND(E27<=0),"C",IF(E27<=0.8,"A",IF(E27<=0.95,"B","C"))) -> #DIV/0! | G27: =VLOOKUP(B27:B78,I$21:M$72,5,0) -> #N/A | K27: =J27/J$73 -> #DIV/0! | L27: =K27+L26 -> #DIV/0! | M27: =_xlfn.IFS(L27<80%,"A",L27<=95%,"B",L27>95%,"C") -> #DIV/0!
D28: =C28/C$73 -> #DIV/0! | E28: =D28+E27 -> #DIV/0! | F28: =IF(AND(E28<=0),"C",IF(E28<=0.8,"A",IF(E28<=0.95,"B","C"))) -> #DIV/0! | G28: =VLOOKUP(B28:B79,I$21:M$72,5,0) -> #N/A | K28: =J28/J$73 -> #DIV/0! | L28: =K28+L27 -> #DIV/0! | M28: =_xlfn.IFS(L28<80%,"A",L28<=95%,"B",L28>95%,"C") -> #DIV/0!
D29: =C29/C$73 -> #DIV/0! | E29: =D29+E28 -> #DIV/0! | F29: =IF(AND(E29<=0),"C",IF(E29<=0.8,"A",IF(E29<=0.95,"B","C"))) -> #DIV/0! | G29: =VLOOKUP(B29:B80,I$21:M$72,5,0) -> #N/A | K29: =J29/J$73 -> #DIV/0! | L29: =K29+L28 -> #DIV/0! | M29: =_xlfn.IFS(L29<80%,"A",L29<=95%,"B",L29>95%,"C") -> #DIV/0!
D30: =C30/C$73 -> #DIV/0! | E30: =D30+E29 -> #DIV/0! | F30: =IF(AND(E30<=0),"C",IF(E30<=0.8,"A",IF(E30<=0.95,"B","C"))) -> #DIV/0! | G30: =VLOOKUP(B30:B81,I$21:M$72,5,0) -> #N/A | K30: =J30/J$73 -> #DIV/0! | L30: =K30+L29 -> #DIV/0! | M30: =_xlfn.IFS(L30<80%,"A",L30<=95%,"B",L30>95%,"C") -> #DIV/0!
D31: =C31/C$73 -> #DIV/0! | E31: =D31+E30 -> #DIV/0! | F31: =IF(AND(E31<=0),"C",IF(E31<=0.8,"A",IF(E31<=0.95,"B","C"))) -> #DIV/0! | G31: =VLOOKUP(B31:B82,I$21:M$72,5,0) -> #N/A | K31: =J31/J$73 -> #DIV/0! | L31: =K31+L30 -> #DIV/0! | M31: =_xlfn.IFS(L31<80%,"A",L31<=95%,"B",L31>95%,"C") -> #DIV/0!
D32: =C32/C$73 -> #DIV/0! | E32: =D32+E31 -> #DIV/0! | F32: =IF(AND(E32<=0),"C",IF(E32<=0.8,"A",IF(E32<=0.95,"B","C"))) -> #DIV/0! | G32: =VLOOKUP(B32:B83,I$21:M$72,5,0) -> #N/A | K32: =J32/J$73 -> #DIV/0! | L32: =K32+L31 -> #DIV/0! | M32: =_xlfn.IFS(L32<80%,"A",L32<=95%,"B",L32>95%,"C") -> #DIV/0!
D33: =C33/C$73 -> #DIV/0! | E33: =D33+E32 -> #DIV/0! | F33: =IF(AND(E33<=0),"C",IF(E33<=0.8,"A",IF(E33<=0.95,"B","C"))) -> #DIV/0! | G33: =VLOOKUP(B33:B84,I$21:M$72,5,0) -> #N/A | K33: =J33/J$73 -> #DIV/0! | L33: =K33+L32 -> #DIV/0! | M33: =_xlfn.IFS(L33<80%,"A",L33<=95%,"B",L33>95%,"C") -> #DIV/0!
... D72: =C72/C$73 -> #DIV/0! | E72: =D72+E71 -> #DIV/0! | F72: =IF(AND(E72<=0),"C",IF(E72<=0.8,"A",IF(E72<=0.95,"B","C"))) -> #DIV/0! | G72: =VLOOKUP(B72:B123,I$21:M$72,5,0) -> #N/A | K72: =J72/J$73 -> #DIV/0! | L72: =K72+L71 -> #DIV/0! | M72: =_xlfn.IFS(L72<80%,"A",L72<=95%,"B",L72>95%,"C") -> #DIV/0!
C73: =SUM(C21:C72) -> 0 | D73: =SUM(D21:D72) -> #DIV/0! | J73: =SUM(J21:J72) -> 0 | K73: =SUM(K21:K72) -> #DIV/0!

Sheet АВС 3
B2: ОЧКИ
C3: Прибыль | D3: % прибыль | E3: Доля | F3: ABC прибыль | G3: ABC кол-во | J3: Кол-во | K3: % кол-во | L3: Доля | M3: ABC кол-во
B4: flip желтые Сул | C4: ='Юнит 3'!AL8 -> 9416.7452 | D4: =C4/C$17 -> 0.60135716 | E4: =D4 -> 0.60135716 | F4: =IF(AND(E4<=0),"C",IF(E4<=0.8,"A",IF(E4<=0.95,"B","C"))) -> A | G4: =VLOOKUP(B$4:B$16,I$4:M$16,5,0) -> A | I4: flip желтые Сул | J4: ='Юнит 3'!S8 -> 22 | K4: =J4/J$17 -> 0.45833333 | L4: =K4 -> 0.45833333 | M4: =_xlfn.IFS(L4<80%,"A",L4<=95%,"B",L4>95%,"C") -> A | P4: A | Q4: 0.8
B5: Черные с железкой Сул | C5: ='Юнит 3'!AL3 -> 2756.9039 | D5: =C5/C$17 -> 0.176057 | E5: =E4+D5 -> 0.77741417 | F5: =IF(AND(E5<=0),"C",IF(E5<=0.8,"A",IF(E5<=0.95,"B","C"))) -> A | G5: =VLOOKUP(B$4:B$16,I$4:M$16,5,0) -> A | I5: Черные с железкой Сул | J5: ='Юнит 3'!S3 -> 10 | K5: =J5/J$17 -> 0.20833333 | L5: =L4+K5 -> 0.66666667 | M5: =_xlfn.IFS(L5<80%,"A",L5<=95%,"B",L5>95%,"C") -> A | P5: B | Q5: 0.15
B6: Qs желт Сул | C6: ='Юнит 3'!AL6 -> 1819.1694 | D6: =C6/C$17 -> 0.1161729 | E6: =E5+D6 -> 0.89358706 | F6: =IF(AND(E6<=0),"C",IF(E6<=0.8,"A",IF(E6<=0.95,"B","C"))) -> B | G6: =VLOOKUP(B$4:B$16,I$4:M$16,5,0) -> A | I6: Qs желт Сул | J6: ='Юнит 3'!S6 -> 6 | K6: =J6/J$17 -> 0.125 | L6: =L5+K6 -> 0.79166667 | M6: =_xlfn.IFS(L6<80%,"A",L6<=95%,"B",L6>95%,"C") -> A | P6: C | Q6: 0.05
B7: MR Р1886 черн | C7: ='Юнит 3'!AL14 -> 1226.3922 | D7: =C7/C$17 -> 0.078317901 | E7: =E6+D7 -> 0.97190497 | F7: =IF(AND(E7<=0),"C",IF(E7<=0.8,"A",IF(E7<=0.95,"B","C"))) -> C | G7: =VLOOKUP(B$4:B$16,I$4:M$16,5,0) -> B | I7: MR8854 C2 Сул | J7: ='Юнит 3'!S9 -> 3 | K7: =J7/J$17 -> 0.0625 | L7: =L6+K7 -> 0.85416667 | M7: =_xlfn.IFS(L7<80%,"A",L7<=95%,"B",L7>95%,"C") -> B
B8: MR Р1886 корич | C8: ='Юнит 3'!AL15 -> 494.45817 | D8: =C8/C$17 -> 0.031576299 | E8: =E7+D8 -> 1.0034813 | F8: =IF(AND(E8<=0),"C",IF(E8<=0.8,"A",IF(E8<=0.95,"B","C"))) -> C | G8: =VLOOKUP(B$4:B$16,I$4:M$16,5,0) -> C | I8: MR Р1886 черн | J8: ='Юнит 3'!S14 -> 3 | K8: =J8/J$17 -> 0.0625 | L8: =L7+K8 -> 0.91666667 | M8: =_xlfn.IFS(L8<80%,"A",L8<=95%,"B",L8>95%,"C") -> B
B9: MR Р1874 корич | C9: ='Юнит 3'!AL13 -> 500.15133 | D9: =C9/C$17 -> 0.031939867 | E9: =E8+D9 -> 1.0354211 | F9: =IF(AND(E9<=0),"C",IF(E9<=0.8,"A",IF(E9<=0.95,"B","C"))) -> C | G9: =VLOOKUP(B$4:B$16,I$4:M$16,5,0) -> C | I9: Qs син Сул | J9: ='Юнит 3'!S5 -> 1 | K9: =J9/J$17 -> 0.020833333 | L9: =L8+K9 -> 0.9375 | M9: =_xlfn.IFS(L9<80%,"A",L9<=95%,"B",L9>95%,"C") -> B
B10: Qs син Сул | C10: ='Юнит 3'!AL5 -> 470.44553 | D10: =C10/C$17 -> 0.030042842 | E10: =E9+D10 -> 1.065464 | F10: =IF(AND(E10<=0),"C",IF(E10<=0.8,"A",IF(E10<=0.95,"B","C"))) -> C | G10: =VLOOKUP(B$4:B$16,I$4:M$16,5,0) -> B | I10: MR 1819 черн | J10: ='Юнит 3'!S10 -> 1 | K10: =J10/J$17 -> 0.020833333 | L10: =L9+K10 -> 0.95833333 | M10: =_xlfn.IFS(L10<80%,"A",L10<=95%,"B",L10>95%,"C") -> C
B11: MR 1819 черн | C11: ='Юнит 3'!AL10 -> 371.88742 | D11: =C11/C$17 -> 0.023748881 | E11: =E10+D11 -> 1.0892129 | F11: =IF(AND(E11<=0),"C",IF(E11<=0.8,"A",IF(E11<=0.95,"B","C"))) -> C | G11: =VLOOKUP(B$4:B$16,I$4:M$16,5,0) -> C | I11: MR Р1874 корич | J11: ='Юнит 3'!S13 -> 1 | K11: =J11/J$17 -> 0.020833333 | L11: =L10+K11 -> 0.97916667 | M11: =_xlfn.IFS(L11<80%,"A",L11<=95%,"B",L11>95%,"C") -> C
B12: MR 1819 корич | C12: ='Юнит 3'!AL11 -> -130.29333 | D12: =C12/C$17 -> -0.0083205849 | E12: =E11+D12 -> 1.0808923 | F12: =IF(AND(E12<=0),"C",IF(E12<=0.8,"A",IF(E12<=0.95,"B","C"))) -> C | G12: =VLOOKUP(B$4:B$16,I$4:M$16,5,0) -> C | I12: Qs черн Сул | J12: ='Юнит 3'!S4 -> 0 | K12: =J12/J$17 -> 0 | L12: =L11+K12 -> 0.97916667 | M12: =_xlfn.IFS(L12<80%,"A",L12<=95%,"B",L12>95%,"C") -> C
B13: Qs черн Сул | C13: ='Юнит 3'!AL4 -> -170.3584 | D13: =C13/C$17 -> -0.010879156 | E13: =E12+D13 -> 1.0700131 | F13: =IF(AND(E13<=0),"C",IF(E13<=0.8,"A",IF(E13<=0.95,"B","C"))) -> C | G13: =VLOOKUP(B$4:B$16,I$4:M$16,5,0) -> C | I13: flip черные Сул | J13: ='Юнит 3'!S7 -> 0 | K13: =J13/J$17 -> 0 | L13: =L12+K13 -> 0.97916667 | M13: =_xlfn.IFS(L13<80%,"A",L13<=95%,"B",L13>95%,"C") -> C
B14: MR Р1874 черн | C14: ='Юнит 3'!AL12 -> -236.5805 | D14: =C14/C$17 -> -0.015108126 | E14: =E13+D14 -> 1.054905 | F14: =IF(AND(E14<=0),"C",IF(E14<=0.8,"A",IF(E14<=0.95,"B","C"))) -> C | G14: =VLOOKUP(B$4:B$16,I$4:M$16,5,0) -> C | I14: MR 1819 корич | J14: ='Юнит 3'!S11 -> 0 | K14: =J14/J$17 -> 0 | L14: =L13+K14 -> 0.97916667 | M14: =_xlfn.IFS(L14<80%,"A",L14<=95%,"B",L14>95%,"C") -> C
B15: flip черные Сул | C15: ='Юнит 3'!AL7 -> -293.38406 | D15: =C15/C$17 -> -0.018735625 | E15: =E14+D15 -> 1.0361694 | F15: =IF(AND(E15<=0),"C",IF(E15<=0.8,"A",IF(E15<=0.95,"B","C"))) -> C | G15: =VLOOKUP(B$4:B$16,I$4:M$16,5,0) -> C | I15: MR Р1874 черн | J15: ='Юнит 3'!S12 -> 0 | K15: =J15/J$17 -> 0 | L15: =L14+K15 -> 0.97916667 | M15: =_xlfn.IFS(L15<80%,"A",L15<=95%,"B",L15>95%,"C") -> C
B16: MR8854 C2 Сул | C16: ='Юнит 3'!AL9 -> -566.38165 | D16: =C16/C$17 -> -0.036169361 | E16: =E15+D16 -> 1 | F16: =IF(AND(E16<=0),"C",IF(E16<=0.8,"A",IF(E16<=0.95,"B","C"))) -> C | G16: =VLOOKUP(B$4:B$16,I$4:M$16,5,0) -> B | I16: MR Р1886 корич | J16: ='Юнит 3'!S15 -> 1 | K16: =J16/J$17 -> 0.020833333 | L16: =L15+K16 -> 1 | M16: =_xlfn.IFS(L16<80%,"A",L16<=95%,"B",L16>95%,"C") -> C
C17: =SUM(C4:C16) -> 15659.155 | D17: =SUM(D4:D16) -> 1 | J17: =SUM(J4:J16) -> 48 | K17: =SUM(K4:K16) -> 1
C20: Прибыль | D20: % прибыль | E20: Доля | F20: ABC прибыль | G20: ABC кол-во | J20: Кол-во | K20: % кол-во | L20: Доля | M20: ABC кол-во
D21: =C21/C$73 -> #DIV/0! | E21: =D21 -> #DIV/0! | F21: =IF(AND(E21<=0),"C",IF(E21<=0.8,"A",IF(E21<=0.95,"B","C"))) -> #DIV/0! | G21: =VLOOKUP(B21:B72,I$21:M$72,5,0) -> #N/A | K21: =J21/J$73 -> #DIV/0! | L21: =K21 -> #DIV/0! | M21: =_xlfn.IFS(L21<80%,"A",L21<=95%,"B",L21>95%,"C") -> #DIV/0!
D22: =C22/C$73 -> #DIV/0! | E22: =D22+E21 -> #DIV/0! | F22: =IF(AND(E22<=0),"C",IF(E22<=0.8,"A",IF(E22<=0.95,"B","C"))) -> #DIV/0! | G22: =VLOOKUP(B22:B73,I$21:M$72,5,0) -> #N/A | K22: =J22/J$73 -> #DIV/0! | L22: =K22+L21 -> #DIV/0! | M22: =_xlfn.IFS(L22<80%,"A",L22<=95%,"B",L22>95%,"C") -> #DIV/0!
D23: =C23/C$73 -> #DIV/0! | E23: =D23+E22 -> #DIV/0! | F23: =IF(AND(E23<=0),"C",IF(E23<=0.8,"A",IF(E23<=0.95,"B","C"))) -> #DIV/0! | G23: =VLOOKUP(B23:B74,I$21:M$72,5,0) -> #N/A | K23: =J23/J$73 -> #DIV/0! | L23: =K23+L22 -> #DIV/0! | M23: =_xlfn.IFS(L23<80%,"A",L23<=95%,"B",L23>95%,"C") -> #DIV/0!
D24: =C24/C$73 -> #DIV/0! | E24: =D24+E23 -> #DIV/0! | F24: =IF(AND(E24<=0),"C",IF(E24<=0.8,"A",IF(E24<=0.95,"B","C"))) -> #DIV/0! | G24: =VLOOKUP(B24:B75,I$21:M$72,5,0) -> #N/A | K24: =J24/J$73 -> #DIV/0! | L24: =K24+L23 -> #DIV/0! | M24: =_xlfn.IFS(L24<80%,"A",L24<=95%,"B",L24>95%,"C") -> #DIV/0!
D25: =C25/C$73 -> #DIV/0! | E25: =D25+E24 -> #DIV/0! | F25: =IF(AND(E25<=0),"C",IF(E25<=0.8,"A",IF(E25<=0.95,"B","C"))) -> #DIV/0! | G25: =VLOOKUP(B25:B76,I$21:M$72,5,0) -> #N/A | K25: =J25/J$73 -> #DIV/0! | L25: =K25+L24 -> #DIV/0! | M25: =_xlfn.IFS(L25<80%,"A",L25<=95%,"B",L25>95%,"C") -> #DIV/0!
D26: =C26/C$73 -> #DIV/0! | E26: =D26+E25 -> #DIV/0! | F26: =IF(AND(E26<=0),"C",IF(E26<=0.8,"A",IF(E26<=0.95,"B","C"))) -> #DIV/0! | G26: =VLOOKUP(B26:B77,I$21:M$72,5,0) -> #N/A | K26: =J26/J$73 -> #DIV/0! | L26: =K26+L25 -> #DIV/0! | M26: =_xlfn.IFS(L26<80%,"A",L26<=95%,"B",L26>95%,"C") -> #DIV/0!
D27: =C27/C$73 -> #DIV/0! | E27: =D27+E26 -> #DIV/0! | F27: =IF(AND(E27<=0),"C",IF(E27<=0.8,"A",IF(E27<=0.95,"B","C"))) -> #DIV/0! | G27: =VLOOKUP(B27:B78,I$21:M$72,5,0) -> #N/A | K27: =J27/J$73 -> #DIV/0! | L27: =K27+L26 -> #DIV/0! | M27: =_xlfn.IFS(L27<80%,"A",L27<=95%,"B",L27>95%,"C") -> #DIV/0!
D28: =C28/C$73 -> #DIV/0! | E28: =D28+E27 -> #DIV/0! | F28: =IF(AND(E28<=0),"C",IF(E28<=0.8,"A",IF(E28<=0.95,"B","C"))) -> #DIV/0! | G28: =VLOOKUP(B28:B79,I$21:M$72,5,0) -> #N/A | K28: =J28/J$73 -> #DIV/0! | L28: =K28+L27 -> #DIV/0! | M28: =_xlfn.IFS(L28<80%,"A",L28<=95%,"B",L28>95%,"C") -> #DIV/0!
D29: =C29/C$73 -> #DIV/0! | E29: =D29+E28 -> #DIV/0! | F29: =IF(AND(E29<=0),"C",IF(E29<=0.8,"A",IF(E29<=0.95,"B","C"))) -> #DIV/0! | G29: =VLOOKUP(B29:B80,I$21:M$72,5,0) -> #N/A | K29: =J29/J$73 -> #DIV/0! | L29: =K29+L28 -> #DIV/0! | M29: =_xlfn.IFS(L29<80%,"A",L29<=95%,"B",L29>95%,"C") -> #DIV/0!
D30: =C30/C$73 -> #DIV/0! | E30: =D30+E29 -> #DIV/0! | F30: =IF(AND(E30<=0),"C",IF(E30<=0.8,"A",IF(E30<=0.95,"B","C"))) -> #DIV/0! | G30: =VLOOKUP(B30:B81,I$21:M$72,5,0) -> #N/A | K30: =J30/J$73 -> #DIV/0! | L30: =K30+L29 -> #DIV/0! | M30: =_xlfn.IFS(L30<80%,"A",L30<=95%,"B",L30>95%,"C") -> #DIV/0!
D31: =C31/C$73 -> #DIV/0! | E31: =D31+E30 -> #DIV/0! | F31: =IF(AND(E31<=0),"C",IF(E31<=0.8,"A",IF(E31<=0.95,"B","C"))) -> #DIV/0! | G31: =VLOOKUP(B31:B82,I$21:M$72,5,0) -> #N/A | K31: =J31/J$73 -> #DIV/0! | L31: =K31+L30 -> #DIV/0! | M31: =_xlfn.IFS(L31<80%,"A",L31<=95%,"B",L31>95%,"C") -> #DIV/0!
D32: =C32/C$73 -> #DIV/0! | E32: =D32+E31 -> #DIV/0! | F32: =IF(AND(E32<=0),"C",IF(E32<=0.8,"A",IF(E32<=0.95,"B","C"))) -> #DIV/0! | G32: =VLOOKUP(B32:B83,I$21:M$72,5,0) -> #N/A | K32: =J32/J$73 -> #DIV/0! | L32: =K32+L31 -> #DIV/0! | M32: =_xlfn.IFS(L32<80%,"A",L32<=95%,"B",L32>95%,"C") -> #DIV/0!
D33: =C33/C$73 -> #DIV/0! | E33: =D33+E32 -> #DIV/0! | F33: =IF(AND(E33<=0),"C",IF(E33<=0.8,"A",IF(E33<=0.95,"B","C"))) -> #DIV/0! | G33: =VLOOKUP(B33:B84,I$21:M$72,5,0) -> #N/A | K33: =J33/J$73 -> #DIV/0! | L33: =K33+L32 -> #DIV/0! | M33: =_xlfn.IFS(L33<80%,"A",L33<=95%,"B",L33>95%,"C") -> #DIV/0!
... D72: =C72/C$73 -> #DIV/0! | E72: =D72+E71 -> #DIV/0! | F72: =IF(AND(E72<=0),"C",IF(E72<=0.8,"A",IF(E72<=0.95,"B","C"))) -> #DIV/0! | G72: =VLOOKUP(B72:B123,I$21:M$72,5,0) -> #N/A | K72: =J72/J$73 -> #DIV/0! | L72: =K72+L71 -> #DIV/0! | M72: =_xlfn.IFS(L72<80%,"A",L72<=95%,"B",L72>95%,"C") -> #DIV/0!
C73: =SUM(C21:C72) -> 0 | D73: =SUM(D21:D72) -> #DIV/0! | J73: =SUM(J21:J72) -> 0 | K73: =SUM(K21:K72) -> #DIV/0!

Sheet АВС 2
B2: ОЧКИ
C3: Прибыль | D3: % прибыль | E3: Доля | F3: ABC прибыль | G3: ABC кол-во | J3: Кол-во | K3: % кол-во | L3: Доля | M3: ABC кол-во
B4: flip желтые Сул | C4: ='Юнит 2'!AL8 -> 10465.83 | D4: =C4/C$17 -> 0.79413735 | E4: =D4 -> 0.79413735 | F4: =IF(AND(E4<=0),"C",IF(E4<=0.8,"A",IF(E4<=0.95,"B","C"))) -> A | G4: =VLOOKUP(B$4:B$16,I$4:M$16,5,0) -> A | I4: flip желтые Сул | J4: ='Юнит 2'!S8 -> 26 | K4: =J4/J$17 -> 0.61904762 | L4: =K4 -> 0.61904762 | M4: =_xlfn.IFS(L4<80%,"A",L4<=95%,"B",L4>95%,"C") -> A | P4: A | Q4: 0.8
B5: Черные с железкой Сул | C5: ='Юнит 2'!AL3 -> 2587.3534 | D5: =C5/C$17 -> 0.19632594 | E5: =E4+D5 -> 0.9904633 | F5: =IF(AND(E5<=0),"C",IF(E5<=0.8,"A",IF(E5<=0.95,"B","C"))) -> C | G5: =VLOOKUP(B$4:B$16,I$4:M$16,5,0) -> B | I5: Черные с железкой Сул | J5: ='Юнит 2'!S3 -> 8 | K5: =J5/J$17 -> 0.19047619 | L5: =L4+K5 -> 0.80952381 | M5: =_xlfn.IFS(L5<80%,"A",L5<=95%,"B",L5>95%,"C") -> B | P5: B | Q5: 0.15
B6: MR Р1886 корич | C6: ='Юнит 2'!AL15 -> 522.96997 | D6: =C6/C$17 -> 0.039682469 | E6: =E5+D6 -> 1.0301458 | F6: =IF(AND(E6<=0),"C",IF(E6<=0.8,"A",IF(E6<=0.95,"B","C"))) -> C | G6: =VLOOKUP(B$4:B$16,I$4:M$16,5,0) -> C | I6: Qs желт Сул | J6: ='Юнит 2'!S6 -> 3 | K6: =J6/J$17 -> 0.071428571 | L6: =L5+K6 -> 0.88095238 | M6: =_xlfn.IFS(L6<80%,"A",L6<=95%,"B",L6>95%,"C") -> B | P6: C | Q6: 0.05
B7: MR Р1874 корич | C7: ='Юнит 2'!AL13 -> 499.52107 | D7: =C7/C$17 -> 0.037903188 | E7: =E6+D7 -> 1.068049 | F7: =IF(AND(E7<=0),"C",IF(E7<=0.8,"A",IF(E7<=0.95,"B","C"))) -> C | G7: =VLOOKUP(B$4:B$16,I$4:M$16,5,0) -> C | I7: MR8854 C2 Сул | J7: ='Юнит 2'!S9 -> 2 | K7: =J7/J$17 -> 0.047619048 | L7: =L6+K7 -> 0.92857143 | M7: =_xlfn.IFS(L7<80%,"A",L7<=95%,"B",L7>95%,"C") -> B
B8: MR Р1886 черн | C8: ='Юнит 2'!AL14 -> 480.04914 | D8: =C8/C$17 -> 0.036425677 | E8: =E7+D8 -> 1.1044746 | F8: =IF(AND(E8<=0),"C",IF(E8<=0.8,"A",IF(E8<=0.95,"B","C"))) -> C | G8: =VLOOKUP(B$4:B$16,I$4:M$16,5,0) -> C | I8: MR Р1874 корич | J8: ='Юнит 2'!S13 -> 1 | K8: =J8/J$17 -> 0.023809524 | L8: =L7+K8 -> 0.95238095 | M8: =_xlfn.IFS(L8<80%,"A",L8<=95%,"B",L8>95%,"C") -> C
B9: Qs желт Сул | C9: ='Юнит 2'!AL6 -> 251.54918 | D9: =C9/C$17 -> 0.019087315 | E9: =E8+D9 -> 1.1235619 | F9: =IF(AND(E9<=0),"C",IF(E9<=0.8,"A",IF(E9<=0.95,"B","C"))) -> C | G9: =VLOOKUP(B$4:B$16,I$4:M$16,5,0) -> B | I9: MR Р1886 черн | J9: ='Юнит 2'!S14 -> 1 | K9: =J9/J$17 -> 0.023809524 | L9: =L8+K9 -> 0.97619048 | M9: =_xlfn.IFS(L9<80%,"A",L9<=95%,"B",L9>95%,"C") -> C
B10: MR 1819 корич | C10: ='Юнит 2'!AL11 -> -17.763004 | D10: =C10/C$17 -> -0.00134784 | E10: =E9+D10 -> 1.1222141 | F10: =IF(AND(E10<=0),"C",IF(E10<=0.8,"A",IF(E10<=0.95,"B","C"))) -> C | G10: =VLOOKUP(B$4:B$16,I$4:M$16,5,0) -> C | I10: MR Р1886 корич | J10: ='Юнит 2'!S15 -> 1 | K10: =J10/J$17 -> 0.023809524 | L10: =L9+K10 -> 1 | M10: =_xlfn.IFS(L10<80%,"A",L10<=95%,"B",L10>95%,"C") -> C
B11: MR 1819 черн | C11: ='Юнит 2'!AL10 -> -114.59625 | D11: =C11/C$17 -> -0.0086954554 | E11: =E10+D11 -> 1.1135187 | F11: =IF(AND(E11<=0),"C",IF(E11<=0.8,"A",IF(E11<=0.95,"B","C"))) -> C | G11: =VLOOKUP(B$4:B$16,I$4:M$16,5,0) -> C | I11: Qs черн Сул | J11: ='Юнит 2'!S4 -> 0 | K11: =J11/J$17 -> 0 | L11: =L10+K11 -> 1 | M11: =_xlfn.IFS(L11<80%,"A",L11<=95%,"B",L11>95%,"C") -> C
B12: MR Р1874 черн | C12: ='Юнит 2'!AL12 -> -126.47922 | D12: =C12/C$17 -> -0.0095971244 | E12: =E11+D12 -> 1.1039215 | F12: =IF(AND(E12<=0),"C",IF(E12<=0.8,"A",IF(E12<=0.95,"B","C"))) -> C | G12: =VLOOKUP(B$4:B$16,I$4:M$16,5,0) -> C | I12: Qs син Сул | J12: ='Юнит 2'!S5 -> 0 | K12: =J12/J$17 -> 0 | L12: =L11+K12 -> 1 | M12: =_xlfn.IFS(L12<80%,"A",L12<=95%,"B",L12>95%,"C") -> C
B13: Qs син Сул | C13: ='Юнит 2'!AL5 -> -164.19948 | D13: =C13/C$17 -> -0.012459302 | E13: =E12+D13 -> 1.0914622 | F13: =IF(AND(E13<=0),"C",IF(E13<=0.8,"A",IF(E13<=0.95,"B","C"))) -> C | G13: =VLOOKUP(B$4:B$16,I$4:M$16,5,0) -> C | I13: flip черные Сул | J13: ='Юнит 2'!S7 -> 0 | K13: =J13/J$17 -> 0 | L13: =L12+K13 -> 1 | M13: =_xlfn.IFS(L13<80%,"A",L13<=95%,"B",L13>95%,"C") -> C
B14: flip черные Сул | C14: ='Юнит 2'!AL7 -> -229.5913 | D14: =C14/C$17 -> -0.017421171 | E14: =E13+D14 -> 1.0740411 | F14: =IF(AND(E14<=0),"C",IF(E14<=0.8,"A",IF(E14<=0.95,"B","C"))) -> C | G14: =VLOOKUP(B$4:B$16,I$4:M$16,5,0) -> C | I14: MR 1819 черн | J14: ='Юнит 2'!S10 -> 0 | K14: =J14/J$17 -> 0 | L14: =L13+K14 -> 1 | M14: =_xlfn.IFS(L14<80%,"A",L14<=95%,"B",L14>95%,"C") -> C
B15: Qs черн Сул | C15: ='Юнит 2'!AL4 -> -238.2913 | D15: =C15/C$17 -> -0.018081319 | E15: =E14+D15 -> 1.0559597 | F15: =IF(AND(E15<=0),"C",IF(E15<=0.8,"A",IF(E15<=0.95,"B","C"))) -> C | G15: =VLOOKUP(B$4:B$16,I$4:M$16,5,0) -> C | I15: MR 1819 корич | J15: ='Юнит 2'!S11 -> 0 | K15: =J15/J$17 -> 0 | L15: =L14+K15 -> 1 | M15: =_xlfn.IFS(L15<80%,"A",L15<=95%,"B",L15>95%,"C") -> C
B16: MR8854 C2 Сул | C16: ='Юнит 2'!AL9 -> -737.48588 | D16: =C16/C$17 -> -0.055959734 | E16: =E15+D16 -> 1 | F16: =IF(AND(E16<=0),"C",IF(E16<=0.8,"A",IF(E16<=0.95,"B","C"))) -> C | G16: =VLOOKUP(B$4:B$16,I$4:M$16,5,0) -> B | I16: MR Р1874 черн | J16: ='Юнит 2'!S12 -> 0 | K16: =J16/J$17 -> 0 | L16: =L15+K16 -> 1 | M16: =_xlfn.IFS(L16<80%,"A",L16<=95%,"B",L16>95%,"C") -> C
C17: =SUM(C4:C16) -> 13178.867 | D17: =SUM(D4:D16) -> 1 | J17: =SUM(J4:J16) -> 42 | K17: =SUM(K4:K16) -> 1
C20: Прибыль | D20: % прибыль | E20: Доля | F20: ABC прибыль | G20: ABC кол-во | J20: Кол-во | K20: % кол-во | L20: Доля | M20: ABC кол-во
D21: =C21/C$73 -> #DIV/0! | E21: =D21 -> #DIV/0! | F21: =IF(AND(E21<=0),"C",IF(E21<=0.8,"A",IF(E21<=0.95,"B","C"))) -> #DIV/0! | G21: =VLOOKUP(B21:B72,I$21:M$72,5,0) -> #N/A | K21: =J21/J$73 -> #DIV/0! | L21: =K21 -> #DIV/0! | M21: =_xlfn.IFS(L21<80%,"A",L21<=95%,"B",L21>95%,"C") -> #DIV/0!
D22: =C22/C$73 -> #DIV/0! | E22: =D22+E21 -> #DIV/0! | F22: =IF(AND(E22<=0),"C",IF(E22<=0.8,"A",IF(E22<=0.95,"B","C"))) -> #DIV/0! | G22: =VLOOKUP(B22:B73,I$21:M$72,5,0) -> #N/A | K22: =J22/J$73 -> #DIV/0! | L22: =K22+L21 -> #DIV/0! | M22: =_xlfn.IFS(L22<80%,"A",L22<=95%,"B",L22>95%,"C") -> #DIV/0!
D23: =C23/C$73 -> #DIV/0! | E23: =D23+E22 -> #DIV/0! | F23: =IF(AND(E23<=0),"C",IF(E23<=0.8,"A",IF(E23<=0.95,"B","C"))) -> #DIV/0! | G23: =VLOOKUP(B23:B74,I$21:M$72,5,0) -> #N/A | K23: =J23/J$73 -> #DIV/0! | L23: =K23+L22 -> #DIV/0! | M23: =_xlfn.IFS(L23<80%,"A",L23<=95%,"B",L23>95%,"C") -> #DIV/0!
D24: =C24/C$73 -> #DIV/0! | E24: =D24+E23 -> #DIV/0! | F24: =IF(AND(E24<=0),"C",IF(E24<=0.8,"A",IF(E24<=0.95,"B","C"))) -> #DIV/0! | G24: =VLOOKUP(B24:B75,I$21:M$72,5,0) -> #N/A | K24: =J24/J$73 -> #DIV/0! | L24: =K24+L23 -> #DIV/0! | M24: =_xlfn.IFS(L24<80%,"A",L24<=95%,"B",L24>95%,"C") -> #DIV/0!
D25: =C25/C$73 -> #DIV/0! | E25: =D25+E24 -> #DIV/0! | F25: =IF(AND(E25<=0),"C",IF(E25<=0.8,"A",IF(E25<=0.95,"B","C"))) -> #DIV/0! | G25: =VLOOKUP(B25:B76,I$21:M$72,5,0) -> #N/A | K25: =J25/J$73 -> #DIV/0! | L25: =K25+L24 -> #DIV/0! | M25: =_xlfn.IFS(L25<80%,"A",L25<=95%,"B",L25>95%,"C") -> #DIV/0!
D26: =C26/C$73 -> #DIV/0! | E26: =D26+E25 -> #DIV/0! | F26: =IF(AND(E26<=0),"C",IF(E26<=0.8,"A",IF(E26<=0.95,"B","C"))) -> #DIV/0! | G26: =VLOOKUP(B26:B77,I$21:M$72,5,0) -> #N/A | K26: =J26/J$73 -> #DIV/0! | L26: =K26+L25 -> #DIV/0! | M26: =_xlfn.IFS(L26<80%,"A",L26<=95%,"B",L26>95%,"C") -> #DIV/0!
D27: =C27/C$73 -> #DIV/0! | E27: =D27+E26 -> #DIV/0! | F27: =IF(AND(E27<=0),"C",IF(E27<=0.8,"A",IF(E27<=0.95,"B","C"))) -> #DIV/0! | G27: =VLOOKUP(B27:B78,I$21:M$72,5,0) -> #N/A | K27: =J27/J$73 -> #DIV/0! | L27: =K27+L26 -> #DIV/0! | M27: =_xlfn.IFS(L27<80%,"A",L27<=95%,"B",L27>95%,"C") -> #DIV/0!
D28: =C28/C$73 -> #DIV/0! | E28: =D28+E27 -> #DIV/0! | F28: =IF(AND(E28<=0),"C",IF(E28<=0.8,"A",IF(E28<=0.95,"B","C"))) -> #DIV/0! | G28: =VLOOKUP(B28:B79,I$21:M$72,5,0) -> #N/A | K28: =J28/J$73 -> #DIV/0! | L28: =K28+L27 -> #DIV/0! | M28: =_xlfn.IFS(L28<80%,"A",L28<=95%,"B",L28>95%,"C") -> #DIV/0!
D29: =C29/C$73 -> #DIV/0! | E29: =D29+E28 -> #DIV/0! | F29: =IF(AND(E29<=0),"C",IF(E29<=0.8,"A",IF(E29<=0.95,"B","C"))) -> #DIV/0! | G29: =VLOOKUP(B29:B80,I$21:M$72,5,0) -> #N/A | K29: =J29/J$73 -> #DIV/0! | L29: =K29+L28 -> #DIV/0! | M29: =_xlfn.IFS(L29<80%,"A",L29<=95%,"B",L29>95%,"C") -> #DIV/0!
D30: =C30/C$73 -> #DIV/0! | E30: =D30+E29 -> #DIV/0! | F30: =IF(AND(E30<=0),"C",IF(E30<=0.8,"A",IF(E30<=0.95,"B","C"))) -> #DIV/0! | G30: =VLOOKUP(B30:B81,I$21:M$72,5,0) -> #N/A | K30: =J30/J$73 -> #DIV/0! | L30: =K30+L29 -> #DIV/0! | M30: =_xlfn.IFS(L30<80%,"A",L30<=95%,"B",L30>95%,"C") -> #DIV/0!
D31: =C31/C$73 -> #DIV/0! | E31: =D31+E30 -> #DIV/0! | F31: =IF(AND(E31<=0),"C",IF(E31<=0.8,"A",IF(E31<=0.95,"B","C"))) -> #DIV/0! | G31: =VLOOKUP(B31:B82,I$21:M$72,5,0) -> #N/A | K31: =J31/J$73 -> #DIV/0! | L31: =K31+L30 -> #DIV/0! | M31: =_xlfn.IFS(L31<80%,"A",L31<=95%,"B",L31>95%,"C") -> #DIV/0!
D32: =C32/C$73 -> #DIV/0! | E32: =D32+E31 -> #DIV/0! | F32: =IF(AND(E32<=0),"C",IF(E32<=0.8,"A",IF(E32<=0.95,"B","C"))) -> #DIV/0! | G32: =VLOOKUP(B32:B83,I$21:M$72,5,0) -> #N/A | K32: =J32/J$73 -> #DIV/0! | L32: =K32+L31 -> #DIV/0! | M32: =_xlfn.IFS(L32<80%,"A",L32<=95%,"B",L32>95%,"C") -> #DIV/0!
D33: =C33/C$73 -> #DIV/0! | E33: =D33+E32 -> #DIV/0! | F33: =IF(AND(E33<=0),"C",IF(E33<=0.8,"A",IF(E33<=0.95,"B","C"))) -> #DIV/0! | G33: =VLOOKUP(B33:B84,I$21:M$72,5,0) -> #N/A | K33: =J33/J$73 -> #DIV/0! | L33: =K33+L32 -> #DIV/0! | M33: =_xlfn.IFS(L33<80%,"A",L33<=95%,"B",L33>95%,"C") -> #DIV/0!
... D72: =C72/C$73 -> #DIV/0! | E72: =D72+E71 -> #DIV/0! | F72: =IF(AND(E72<=0),"C",IF(E72<=0.8,"A",IF(E72<=0.95,"B","C"))) -> #DIV/0! | G72: =VLOOKUP(B72:B123,I$21:M$72,5,0) -> #N/A | K72: =J72/J$73 -> #DIV/0! | L72: =K72+L71 -> #DIV/0! | M72: =_xlfn.IFS(L72<80%,"A",L72<=95%,"B",L72>95%,"C") -> #DIV/0!
C73: =SUM(C21:C72) -> 0 | D73: =SUM(D21:D72) -> #DIV/0! | J73: =SUM(J21:J72) -> 0 | K73: =SUM(K21:K72) -> #DIV/0!

Sheet АВС 1
B2: ОЧКИ
C3: Прибыль | D3: % прибыль | E3: Доля | F3: ABC прибыль | G3: ABC кол-во | J3: Кол-во | K3: % кол-во | L3: Доля | M3: ABC кол-во
B4: flip желтые Сул | C4: ='Юнит 1'!AL8 -> 15664.998 | D4: =C4/C$17 -> 0.84084557 | E4: =D4 -> 0.84084557 | F4: =IF(AND(E4<=0),"C",IF(E4<=0.8,"A",IF(E4<=0.95,"B","C"))) -> B | G4: =VLOOKUP(B$4:B$16,I$4:M$16,5,0) -> A | I4: flip желтые Сул | J4: ='Юнит 1'!S8 -> 35 | K4: =J4/J$17 -> 0.77777778 | L4: =K4 -> 0.77777778 | M4: =_xlfn.IFS(L4<80%,"A",L4<=95%,"B",L4>95%,"C") -> A | P4: A | Q4: 0.8
B5: Qs желт Сул | C5: ='Юнит 1'!AL6 -> 1928.0439 | D5: =C5/C$17 -> 0.10349105 | E5: =E4+D5 -> 0.94433662 | F5: =IF(AND(E5<=0),"C",IF(E5<=0.8,"A",IF(E5<=0.95,"B","C"))) -> B | G5: =VLOOKUP(B$4:B$16,I$4:M$16,5,0) -> C | I5: Черные с железкой Сул | J5: ='Юнит 1'!S3 -> 4 | K5: =J5/J$17 -> 0.088888889 | L5: =L4+K5 -> 0.86666667 | M5: =_xlfn.IFS(L5<80%,"A",L5<=95%,"B",L5>95%,"C") -> B | P5: B | Q5: 0.15
B6: Черные с железкой Сул | C6: ='Юнит 1'!AL3 -> 1194.2557 | D6: =C6/C$17 -> 0.064103715 | E6: =E5+D6 -> 1.0084403 | F6: =IF(AND(E6<=0),"C",IF(E6<=0.8,"A",IF(E6<=0.95,"B","C"))) -> C | G6: =VLOOKUP(B$4:B$16,I$4:M$16,5,0) -> B | I6: Qs желт Сул | J6: ='Юнит 1'!S6 -> 4 | K6: =J6/J$17 -> 0.088888889 | L6: =L5+K6 -> 0.95555556 | M6: =_xlfn.IFS(L6<80%,"A",L6<=95%,"B",L6>95%,"C") -> C | P6: C | Q6: 0.05
B7: MR 1819 корич | C7: ='Юнит 1'!AL11 -> 478.82607 | D7: =C7/C$17 -> 0.025701808 | E7: =E6+D7 -> 1.0341421 | F7: =IF(AND(E7<=0),"C",IF(E7<=0.8,"A",IF(E7<=0.95,"B","C"))) -> C | G7: =VLOOKUP(B$4:B$16,I$4:M$16,5,0) -> C | I7: MR8854 C2 Сул | J7: ='Юнит 1'!S9 -> 1 | K7: =J7/J$17 -> 0.022222222 | L7: =L6+K7 -> 0.97777778 | M7: =_xlfn.IFS(L7<80%,"A",L7<=95%,"B",L7>95%,"C") -> C
B8: MR Р1874 корич | C8: ='Юнит 1'!AL13 -> -5.038224 | D8: =C8/C$17 -> -0.00027043529 | E8: =E7+D8 -> 1.0338717 | F8: =IF(AND(E8<=0),"C",IF(E8<=0.8,"A",IF(E8<=0.95,"B","C"))) -> C | G8: =VLOOKUP(B$4:B$16,I$4:M$16,5,0) -> C | I8: MR 1819 корич | J8: ='Юнит 1'!S11 -> 1 | K8: =J8/J$17 -> 0.022222222 | L8: =L7+K8 -> 1 | M8: =_xlfn.IFS(L8<80%,"A",L8<=95%,"B",L8>95%,"C") -> C
B9: MR Р1886 корич | C9: ='Юнит 1'!AL15 -> -15.534524 | D9: =C9/C$17 -> -0.00083384215 | E9: =E8+D9 -> 1.0330379 | F9: =IF(AND(E9<=0),"C",IF(E9<=0.8,"A",IF(E9<=0.95,"B","C"))) -> C | G9: =VLOOKUP(B$4:B$16,I$4:M$16,5,0) -> C | I9: Qs черн Сул | J9: ='Юнит 1'!S4 -> 0 | K9: =J9/J$17 -> 0 | L9: =L8+K9 -> 1 | M9: =_xlfn.IFS(L9<80%,"A",L9<=95%,"B",L9>95%,"C") -> C
B10: MR 1819 черн | C10: ='Юнит 1'!AL10 -> -17.633784 | D10: =C10/C$17 -> -0.00094652352 | E10: =E9+D10 -> 1.0320913 | F10: =IF(AND(E10<=0),"C",IF(E10<=0.8,"A",IF(E10<=0.95,"B","C"))) -> C | G10: =VLOOKUP(B$4:B$16,I$4:M$16,5,0) -> C | I10: Qs син Сул | J10: ='Юнит 1'!S5 -> 0 | K10: =J10/J$17 -> 0 | L10: =L9+K10 -> 1 | M10: =_xlfn.IFS(L10<80%,"A",L10<=95%,"B",L10>95%,"C") -> C
B11: MR Р1874 черн | C11: ='Юнит 1'!AL12 -> -19.313192 | D11: =C11/C$17 -> -0.0010366686 | E11: =E10+D11 -> 1.0310547 | F11: =IF(AND(E11<=0),"C",IF(E11<=0.8,"A",IF(E11<=0.95,"B","C"))) -> C | G11: =VLOOKUP(B$4:B$16,I$4:M$16,5,0) -> C | I11: flip черные Сул | J11: ='Юнит 1'!S7 -> 0 | K11: =J11/J$17 -> 0 | L11: =L10+K11 -> 1 | M11: =_xlfn.IFS(L11<80%,"A",L11<=95%,"B",L11>95%,"C") -> C
B12: MR Р1886 черн | C12: ='Юнит 1'!AL14 -> -27.29038 | D12: =C12/C$17 -> -0.0014648578 | E12: =E11+D12 -> 1.0295898 | F12: =IF(AND(E12<=0),"C",IF(E12<=0.8,"A",IF(E12<=0.95,"B","C"))) -> C | G12: =VLOOKUP(B$4:B$16,I$4:M$16,5,0) -> C | I12: MR 1819 черн | J12: ='Юнит 1'!S10 -> 0 | K12: =J12/J$17 -> 0 | L12: =L11+K12 -> 1 | M12: =_xlfn.IFS(L12<80%,"A",L12<=95%,"B",L12>95%,"C") -> C
B13: Qs черн Сул | C13: ='Юнит 1'!AL4 -> -120.23797 | D13: =C13/C$17 -> -0.0064539786 | E13: =E12+D13 -> 1.0231358 | F13: =IF(AND(E13<=0),"C",IF(E13<=0.8,"A",IF(E13<=0.95,"B","C"))) -> C | G13: =VLOOKUP(B$4:B$16,I$4:M$16,5,0) -> C | I13: MR Р1874 черн | J13: ='Юнит 1'!S12 -> 0 | K13: =J13/J$17 -> 0 | L13: =L12+K13 -> 1 | M13: =_xlfn.IFS(L13<80%,"A",L13<=95%,"B",L13>95%,"C") -> C
B14: flip черные Сул | C14: ='Юнит 1'!AL7 -> -120.23797 | D14: =C14/C$17 -> -0.0064539786 | E14: =E13+D14 -> 1.0166819 | F14: =IF(AND(E14<=0),"C",IF(E14<=0.8,"A",IF(E14<=0.95,"B","C"))) -> C | G14: =VLOOKUP(B$4:B$16,I$4:M$16,5,0) -> C | I14: MR Р1874 корич | J14: ='Юнит 1'!S13 -> 0 | K14: =J14/J$17 -> 0 | L14: =L13+K14 -> 1 | M14: =_xlfn.IFS(L14<80%,"A",L14<=95%,"B",L14>95%,"C") -> C
B15: MR8854 C2 Сул | C15: ='Юнит 1'!AL9 -> -151.66004 | D15: =C15/C$17 -> -0.0081406121 | E15: =E14+D15 -> 1.0085412 | F15: =IF(AND(E15<=0),"C",IF(E15<=0.8,"A",IF(E15<=0.95,"B","C"))) -> C | G15: =VLOOKUP(B$4:B$16,I$4:M$16,5,0) -> C | I15: MR Р1886 черн | J15: ='Юнит 1'!S14 -> 0 | K15: =J15/J$17 -> 0 | L15: =L14+K15 -> 1 | M15: =_xlfn.IFS(L15<80%,"A",L15<=95%,"B",L15>95%,"C") -> C
B16: Qs син Сул | C16: ='Юнит 1'!AL5 -> -159.12391 | D16: =C16/C$17 -> -0.008541248 | E16: =E15+D16 -> 1 | F16: =IF(AND(E16<=0),"C",IF(E16<=0.8,"A",IF(E16<=0.95,"B","C"))) -> C | G16: =VLOOKUP(B$4:B$16,I$4:M$16,5,0) -> C | I16: MR Р1886 корич | J16: ='Юнит 1'!S15 -> 0 | K16: =J16/J$17 -> 0 | L16: =L15+K16 -> 1 | M16: =_xlfn.IFS(L16<80%,"A",L16<=95%,"B",L16>95%,"C") -> C
C17: =SUM(C4:C16) -> 18630.054 | D17: =SUM(D4:D16) -> 1 | J17: =SUM(J4:J16) -> 45 | K17: =SUM(K4:K16) -> 1
C20: Прибыль | D20: % прибыль | E20: Доля | F20: ABC прибыль | G20: ABC кол-во | J20: Кол-во | K20: % кол-во | L20: Доля | M20: ABC кол-во
D21: =C21/C$73 -> #DIV/0! | E21: =D21 -> #DIV/0! | F21: =IF(AND(E21<=0),"C",IF(E21<=0.8,"A",IF(E21<=0.95,"B","C"))) -> #DIV/0! | G21: =VLOOKUP(B21:B72,I$21:M$72,5,0) -> #N/A | K21: =J21/J$73 -> #DIV/0! | L21: =K21 -> #DIV/0! | M21: =_xlfn.IFS(L21<80%,"A",L21<=95%,"B",L21>95%,"C") -> #DIV/0!
D22: =C22/C$73 -> #DIV/0! | E22: =D22+E21 -> #DIV/0! | F22: =IF(AND(E22<=0),"C",IF(E22<=0.8,"A",IF(E22<=0.95,"B","C"))) -> #DIV/0! | G22: =VLOOKUP(B22:B73,I$21:M$72,5,0) -> #N/A | K22: =J22/J$73 -> #DIV/0! | L22: =K22+L21 -> #DIV/0! | M22: =_xlfn.IFS(L22<80%,"A",L22<=95%,"B",L22>95%,"C") -> #DIV/0!
D23: =C23/C$73 -> #DIV/0! | E23: =D23+E22 -> #DIV/0! | F23: =IF(AND(E23<=0),"C",IF(E23<=0.8,"A",IF(E23<=0.95,"B","C"))) -> #DIV/0! | G23: =VLOOKUP(B23:B74,I$21:M$72,5,0) -> #N/A | K23: =J23/J$73 -> #DIV/0! | L23: =K23+L22 -> #DIV/0! | M23: =_xlfn.IFS(L23<80%,"A",L23<=95%,"B",L23>95%,"C") -> #DIV/0!
D24: =C24/C$73 -> #DIV/0! | E24: =D24+E23 -> #DIV/0! | F24: =IF(AND(E24<=0),"C",IF(E24<=0.8,"A",IF(E24<=0.95,"B","C"))) -> #DIV/0! | G24: =VLOOKUP(B24:B75,I$21:M$72,5,0) -> #N/A | K24: =J24/J$73 -> #DIV/0! | L24: =K24+L23 -> #DIV/0! | M24: =_xlfn.IFS(L24<80%,"A",L24<=95%,"B",L24>95%,"C") -> #DIV/0!
D25: =C25/C$73 -> #DIV/0! | E25: =D25+E24 -> #DIV/0! | F25: =IF(AND(E25<=0),"C",IF(E25<=0.8,"A",IF(E25<=0.95,"B","C"))) -> #DIV/0! | G25: =VLOOKUP(B25:B76,I$21:M$72,5,0) -> #N/A | K25: =J25/J$73 -> #DIV/0! | L25: =K25+L24 -> #DIV/0! | M25: =_xlfn.IFS(L25<80%,"A",L25<=95%,"B",L25>95%,"C") -> #DIV/0!
D26: =C26/C$73 -> #DIV/0! | E26: =D26+E25 -> #DIV/0! | F26: =IF(AND(E26<=0),"C",IF(E26<=0.8,"A",IF(E26<=0.95,"B","C"))) -> #DIV/0! | G26: =VLOOKUP(B26:B77,I$21:M$72,5,0) -> #N/A | K26: =J26/J$73 -> #DIV/0! | L26: =K26+L25 -> #DIV/0! | M26: =_xlfn.IFS(L26<80%,"A",L26<=95%,"B",L26>95%,"C") -> #DIV/0!
D27: =C27/C$73 -> #DIV/0! | E27: =D27+E26 -> #DIV/0! | F27: =IF(AND(E27<=0),"C",IF(E27<=0.8,"A",IF(E27<=0.95,"B","C"))) -> #DIV/0! | G27: =VLOOKUP(B27:B78,I$21:M$72,5,0) -> #N/A | K27: =J27/J$73 -> #DIV/0! | L27: =K27+L26 -> #DIV/0! | M27: =_xlfn.IFS(L27<80%,"A",L27<=95%,"B",L27>95%,"C") -> #DIV/0!
D28: =C28/C$73 -> #DIV/0! | E28: =D28+E27 -> #DIV/0! | F28: =IF(AND(E28<=0),"C",IF(E28<=0.8,"A",IF(E28<=0.95,"B","C"))) -> #DIV/0! | G28: =VLOOKUP(B28:B79,I$21:M$72,5,0) -> #N/A | K28: =J28/J$73 -> #DIV/0! | L28: =K28+L27 -> #DIV/0! | M28: =_xlfn.IFS(L28<80%,"A",L28<=95%,"B",L28>95%,"C") -> #DIV/0!
D29: =C29/C$73 -> #DIV/0! | E29: =D29+E28 -> #DIV/0! | F29: =IF(AND(E29<=0),"C",IF(E29<=0.8,"A",IF(E29<=0.95,"B","C"))) -> #DIV/0! | G29: =VLOOKUP(B29:B80,I$21:M$72,5,0) -> #N/A | K29: =J29/J$73 -> #DIV/0! | L29: =K29+L28 -> #DIV/0! | M29: =_xlfn.IFS(L29<80%,"A",L29<=95%,"B",L29>95%,"C") -> #DIV/0!
D30: =C30/C$73 -> #DIV/0! | E30: =D30+E29 -> #DIV/0! | F30: =IF(AND(E30<=0),"C",IF(E30<=0.8,"A",IF(E30<=0.95,"B","C"))) -> #DIV/0! | G30: =VLOOKUP(B30:B81,I$21:M$72,5,0) -> #N/A | K30: =J30/J$73 -> #DIV/0! | L30: =K30+L29 -> #DIV/0! | M30: =_xlfn.IFS(L30<80%,"A",L30<=95%,"B",L30>95%,"C") -> #DIV/0!
D31: =C31/C$73 -> #DIV/0! | E31: =D31+E30 -> #DIV/0! | F31: =IF(AND(E31<=0),"C",IF(E31<=0.8,"A",IF(E31<=0.95,"B","C"))) -> #DIV/0! | G31: =VLOOKUP(B31:B82,I$21:M$72,5,0) -> #N/A | K31: =J31/J$73 -> #DIV/0! | L31: =K31+L30 -> #DIV/0! | M31: =_xlfn.IFS(L31<80%,"A",L31<=95%,"B",L31>95%,"C") -> #DIV/0!
D32: =C32/C$73 -> #DIV/0! | E32: =D32+E31 -> #DIV/0! | F32: =IF(AND(E32<=0),"C",IF(E32<=0.8,"A",IF(E32<=0.95,"B","C"))) -> #DIV/0! | G32: =VLOOKUP(B32:B83,I$21:M$72,5,0) -> #N/A | K32: =J32/J$73 -> #DIV/0! | L32: =K32+L31 -> #DIV/0! | M32: =_xlfn.IFS(L32<80%,"A",L32<=95%,"B",L32>95%,"C") -> #DIV/0!
D33: =C33/C$73 -> #DIV/0! | E33: =D33+E32 -> #DIV/0! | F33: =IF(AND(E33<=0),"C",IF(E33<=0.8,"A",IF(E33<=0.95,"B","C"))) -> #DIV/0! | G33: =VLOOKUP(B33:B84,I$21:M$72,5,0) -> #N/A | K33: =J33/J$73 -> #DIV/0! | L33: =K33+L32 -> #DIV/0! | M33: =_xlfn.IFS(L33<80%,"A",L33<=95%,"B",L33>95%,"C") -> #DIV/0!
... D72: =C72/C$73 -> #DIV/0! | E72: =D72+E71 -> #DIV/0! | F72: =IF(AND(E72<=0),"C",IF(E72<=0.8,"A",IF(E72<=0.95,"B","C"))) -> #DIV/0! | G72: =VLOOKUP(B72:B123,I$21:M$72,5,0) -> #N/A | K72: =J72/J$73 -> #DIV/0! | L72: =K72+L71 -> #DIV/0! | M72: =_xlfn.IFS(L72<80%,"A",L72<=95%,"B",L72>95%,"C") -> #DIV/0!
C73: =SUM(C21:C72) -> 0 | D73: =SUM(D21:D72) -> #DIV/0! | J73: =SUM(J21:J72) -> 0 | K73: =SUM(K21:K72) -> #DIV/0!

Sheet ФЕВРАЛЬ
A1: 02.02-01.03_6-9 нед | F1: Отчет по остаткам 3,4,5 | K1: Цены и скидки 6 | L1: Воронка продаж 16,50,32 | AI1: Вставить в Итого | AN1: на 1 единицу проданного товара
A2: Бренд | B2: SKU | C2: Артикул поставщика | D2: Предмет | E2: Остаток на 02.03 | F2: В пути до клиента | G2: В пути от клиента | H2: Итого по складам ВБ | I2: Себетоимость на 1 ед на 29.09.25 | J2: Себестоимость остатков | K2: Оборачива-емость, дн | L2: Заказы, шт 7 дней | M2: Средняя цена, руб | N2: % выкупа за 7 дней | O2: Скорость заказов | P2: Скорость продаж | Q2: Кол-во ПРОДАЖИ | R2: Кол-во ВОЗВРАТЫ | S2: Кол-во ПРОДАЖИ-ВОЗВРАТЫ | T2: Выручка ВБ ПРОДАЖИ | U2: Выручка ВБ ВОЗВРАТЫ | V2: Выручка с учетом СПП ПРОДАЖИ - ВОЗВРАТЫ | W2: Выручка ПРОДАЖИ | X2: Выручка ВОЗВРАТЫ | Y2: Выручка с учетом согласованной скидки ПРОДАЖИ - ВОЗВРАТЫ | Z2: Выручка потенциальная | AA2: Доля выручки, % от общего объема | AB2: Себестоимость продаж | AC2: Комиссия, руб | AD2: Комиссия, % | AE2: Логистика | AF2: Реклама БАЛАНС | AG2: Реклама СЧЕТ | AH2: Блогеры | AI2: Хранение | AJ2: Штрафы | AK2: Налог 1% | AL2: Прибыль | AN2: Выручка на 1 ед (средняя цена продажи со скидкой) | AO2: Себестоимость на 1 ед | AP2: Комиссия на 1 ед | AQ2: Логистика на 1 ед | AR2: Реклама на 1 ед | AS2: Прибыль на 1 ед | AT2: Маржиналь-ность, % | AU2: Рентабель-ность, % | AW2: Прибыль с остатков
B3: 341479791 | C3: Черные с железкой Сул | D3: Солнцезащитные очки | E3: ='Юнит 9'!E3 -> 0 | F3: ='Юнит 9'!F3 -> 0 | G3: ='Юнит 9'!G3 -> 0 | H3: ='Юнит 9'!H3 -> 0 | I3: 142.98 | J3: =E3*I3 -> 0 | K3: ='Юнит 9'!K3 -> 0 | L3: ='Юнит 6'!L3+'Юнит 7'!L3+'Юнит 8'!L3+'Юнит 9'!L3 -> 148 | O3: =L3/7 -> 21.142857 | P3: =S3/7 -> 11.714286 | Q3: ='Юнит 6'!Q3+'Юнит 7'!Q3+'Юнит 8'!Q3+'Юнит 9'!Q3 -> 84 | R3: ='Юнит 6'!R3+'Юнит 7'!R3+'Юнит 8'!R3+'Юнит 9'!R3 -> -2 | S3: =Q3+R3 -> 82 | T3: ='Юнит 6'!T3+'Юнит 7'!T3+'Юнит 8'!T3+'Юнит 9'!T3 -> 66076.52 | U3: ='Юнит 6'!U3+'Юнит 7'!U3+'Юнит 8'!U3+'Юнит 9'!U3 -> -1530 | V3: =T3+U3 -> 64546.52 | W3: ='Юнит 6'!W3+'Юнит 7'!W3+'Юнит 8'!W3+'Юнит 9'!W3 -> 103992.78 | X3: ='Юнит 6'!X3+'Юнит 7'!X3+'Юнит 8'!X3+'Юнит 9'!X3 -> -2476 | Y3: =W3+X3 -> 101516.78 | Z3: =L3*M3*N3/100 -> 0 | AA3: =Y3/$Y$93 -> 0.27964001 | AB3: =S3*I3 -> 11724.36 | AC3: ='Юнит 6'!AC3+'Юнит 7'!AC3+'Юнит 8'!AC3+'Юнит 9'!AC3 -> 36824.01 | AD3: =IF(Y3=0,0,AC3/Y3) -> 0.36273816 | AE3: 0 | AF3: 0 | AG3: 0 | AH3: 0 | AI3: 0 | AJ3: 0 | AK3: =V3*1% -> 645.4652 | AL3: =Y3-AB3-AC3-AE3-AF3-AG3-AH3-AI3-AK3-AJ3 -> 52322.945 | AN3: =IF(S3=0,0,Y3/S3) -> 1238.0095 | AO3: =I3 -> 142.98 | AP3: =IF(S3=0,0,AC3/S3) -> 449.07329 | AQ3: =IF(Q3=0,AE3/1,AE3/Q3) -> 0 | AR3: =IF(Q3=0,0,(AF3+AG3)/Q3) -> 0 | AS3: =_xlfn.IFS(S3=0,AL3,S3<0,AL3/-S3,S3>0,AL3/S3) -> 638.08469 | AT3: =IF(AN3=0,0,AS3/AN3) -> 0.51541179 | AU3: =IF(AO3=0,0,AS3/AO3) -> 4.4627549 | AW3: =AS3*E3 -> 0
B4: 340343575 | C4: Qs черн Сул | D4: Солнцезащитные очки | E4: ='Юнит 9'!E4 -> 0 | F4: ='Юнит 9'!F4 -> 0 | G4: ='Юнит 9'!G4 -> 0 | H4: ='Юнит 9'!H4 -> 0 | I4: 123.09 | J4: =E4*I4 -> 0 | K4: ='Юнит 9'!K4 -> 0 | L4: ='Юнит 6'!L4+'Юнит 7'!L4+'Юнит 8'!L4+'Юнит 9'!L4 -> 224 | O4: =L4/7 -> 32 | P4: =S4/7 -> 14.428571 | Q4: ='Юнит 6'!Q4+'Юнит 7'!Q4+'Юнит 8'!Q4+'Юнит 9'!Q4 -> 101 | R4: ='Юнит 6'!R4+'Юнит 7'!R4+'Юнит 8'!R4+'Юнит 9'!R4 -> 0 | S4: =Q4+R4 -> 101 | T4: ='Юнит 6'!T4+'Юнит 7'!T4+'Юнит 8'!T4+'Юнит 9'!T4 -> 62940.23 | U4: ='Юнит 6'!U4+'Юнит 7'!U4+'Юнит 8'!U4+'Юнит 9'!U4 -> 0 | V4: =T4+U4 -> 62940.23 | W4: ='Юнит 6'!W4+'Юнит 7'!W4+'Юнит 8'!W4+'Юнит 9'!W4 -> 94191.1 | X4: ='Юнит 6'!X4+'Юнит 7'!X4+'Юнит 8'!X4+'Юнит 9'!X4 -> 0 | Y4: =W4+X4 -> 94191.1 | Z4: =L4*M4*N4/100 -> 0 | AA4: =Y4/$Y$93 -> 0.25946055 | AB4: =S4*I4 -> 12432.09 | AC4: ='Юнит 6'!AC4+'Юнит 7'!AC4+'Юнит 8'!AC4+'Юнит 9'!AC4 -> 34292.63 | AD4: =IF(Y4=0,0,AC4/Y4) -> 0.36407506 | AE4: 0 | AF4: 0 | AG4: 0 | AH4: 0 | AI4: 0 | AJ4: 0 | AK4: =V4*1% -> 629.4023 | AL4: =Y4-AB4-AC4-AE4-AF4-AG4-AH4-AI4-AK4-AJ4 -> 46836.978 | AN4: =IF(S4=0,0,Y4/S4) -> 932.58515 | AO4: =I4 -> 123.09 | AP4: =IF(S4=0,0,AC4/S4) -> 339.53099 | AQ4: =IF(Q4=0,AE4/1,AE4/Q4) -> 0 | AR4: =IF(Q4=0,0,(AF4+AG4)/Q4) -> 0 | AS4: {=_xlfn.IFS(S4=0,AL4,S4<0,AL4/-S4,S4>0,AL4/S4)} -> 463.73245 | AT4: =IF(AN4=0,0,AS4/AN4) -> 0.49725481 | AU4: =IF(AO4=0,0,AS4/AO4) -> 3.7674259 | AW4: =AS4*E4 -> 0
B5: 340332621 | C5: Qs син Сул | D5: Солнцезащитные очки | E5: ='Юнит 9'!E5 -> 0 | F5: ='Юнит 9'!F5 -> 0 | G5: ='Юнит 9'!G5 -> 0 | H5: ='Юнит 9'!H5 -> 0 | I5: 123.09 | J5: =E5*I5 -> 0 | K5: ='Юнит 9'!K5 -> 0 | L5: ='Юнит 6'!L5+'Юнит 7'!L5+'Юнит 8'!L5+'Юнит 9'!L5 -> 14 | O5: =L5/7 -> 2 | P5: =S5/7 -> 1 | Q5: ='Юнит 6'!Q5+'Юнит 7'!Q5+'Юнит 8'!Q5+'Юнит 9'!Q5 -> 7 | R5: ='Юнит 6'!R5+'Юнит 7'!R5+'Юнит 8'!R5+'Юнит 9'!R5 -> 0 | S5: =Q5+R5 -> 7 | T5: ='Юнит 6'!T5+'Юнит 7'!T5+'Юнит 8'!T5+'Юнит 9'!T5 -> 4632 | U5: ='Юнит 6'!U5+'Юнит 7'!U5+'Юнит 8'!U5+'Юнит 9'!U5 -> 0 | V5: =T5+U5 -> 4632 | W5: ='Юнит 6'!W5+'Юнит 7'!W5+'Юнит 8'!W5+'Юнит 9'!W5 -> 7612 | X5: ='Юнит 6'!X5+'Юнит 7'!X5+'Юнит 8'!X5+'Юнит 9'!X5 -> 0 | Y5: =W5+X5 -> 7612 | Z5: =L5*M5*N5/100 -> 0 | AA5: =Y5/$Y$93 -> 0.020968156 | AB5: =S5*I5 -> 861.63 | AC5: ='Юнит 6'!AC5+'Юнит 7'!AC5+'Юнит 8'!AC5+'Юнит 9'!AC5 -> 2781.55 | AD5: =IF(Y5=0,0,AC5/Y5) -> 0.36541645 | AE5: 0 | AF5: 0 | AG5: 0 | AH5: 0 | AI5: 0 | AJ5: 0 | AK5: =V5*1% -> 46.32 | AL5: =Y5-AB5-AC5-AE5-AF5-AG5-AH5-AI5-AK5-AJ5 -> 3922.5 | AN5: =IF(S5=0,0,Y5/S5) -> 1087.4286 | AO5: =I5 -> 123.09 | AP5: =IF(S5=0,0,AC5/S5) -> 397.36429 | AQ5: =IF(Q5=0,AE5/1,AE5/Q5) -> 0 | AR5: =IF(Q5=0,0,(AF5+AG5)/Q5) -> 0 | AS5: {=_xlfn.IFS(S5=0,AL5,S5<0,AL5/-S5,S5>0,AL5/S5)} -> 560.35714 | AT5: =IF(AN5=0,0,AS5/AN5) -> 0.51530478 | AU5: =IF(AO5=0,0,AS5/AO5) -> 4.5524181 | AW5: =AS5*E5 -> 0
B6: 340341838 | C6: Qs желт Сул | D6: Солнцезащитные очки | E6: ='Юнит 9'!E6 -> 0 | F6: ='Юнит 9'!F6 -> 0 | G6: ='Юнит 9'!G6 -> 0 | H6: ='Юнит 9'!H6 -> 0 | I6: 123.09 | J6: =E6*I6 -> 0 | K6: ='Юнит 9'!K6 -> 0 | L6: ='Юнит 6'!L6+'Юнит 7'!L6+'Юнит 8'!L6+'Юнит 9'!L6 -> 42 | O6: =L6/7 -> 6 | P6: =S6/7 -> 3 | Q6: ='Юнит 6'!Q6+'Юнит 7'!Q6+'Юнит 8'!Q6+'Юнит 9'!Q6 -> 21 | R6: ='Юнит 6'!R6+'Юнит 7'!R6+'Юнит 8'!R6+'Юнит 9'!R6 -> 0 | S6: =Q6+R6 -> 21 | T6: ='Юнит 6'!T6+'Юнит 7'!T6+'Юнит 8'!T6+'Юнит 9'!T6 -> 15272.94 | U6: ='Юнит 6'!U6+'Юнит 7'!U6+'Юнит 8'!U6+'Юнит 9'!U6 -> 0 | V6: =T6+U6 -> 15272.94 | W6: ='Юнит 6'!W6+'Юнит 7'!W6+'Юнит 8'!W6+'Юнит 9'!W6 -> 24448.1 | X6: ='Юнит 6'!X6+'Юнит 7'!X6+'Юнит 8'!X6+'Юнит 9'!X6 -> 0 | Y6: =W6+X6 -> 24448.1 | Z6: =L6*M6*N6/100 -> 0 | AA6: =Y6/$Y$93 -> 0.06734519 | AB6: =S6*I6 -> 2584.89 | AC6: ='Юнит 6'!AC6+'Юнит 7'!AC6+'Юнит 8'!AC6+'Юнит 9'!AC6 -> 8865.71 | AD6: =IF(Y6=0,0,AC6/Y6) -> 0.36263391 | AE6: 0 | AF6: 0 | AG6: 0 | AH6: 0 | AI6: 0 | AJ6: 0 | AK6: =V6*1% -> 152.7294 | AL6: =Y6-AB6-AC6-AE6-AF6-AG6-AH6-AI6-AK6-AJ6 -> 12844.771 | AN6: =IF(S6=0,0,Y6/S6) -> 1164.1952 | AO6: =I6 -> 123.09 | AP6: =IF(S6=0,0,AC6/S6) -> 422.17667 | AQ6: =IF(Q6=0,AE6/1,AE6/Q6) -> 0 | AR6: =IF(Q6=0,0,(AF6+AG6)/Q6) -> 0 | AS6: {=_xlfn.IFS(S6=0,AL6,S6<0,AL6/-S6,S6>0,AL6/S6)} -> 611.65574 | AT6: =IF(AN6=0,0,AS6/AN6) -> 0.52538932 | AU6: =IF(AO6=0,0,AS6/AO6) -> 4.9691749 | AW6: =AS6*E6 -> 0
B7: 445291724 | C7: flip черные Сул | D7: Солнцезащитные очки | E7: ='Юнит 9'!E7 -> 0 | F7: ='Юнит 9'!F7 -> 0 | G7: ='Юнит 9'!G7 -> 0 | H7: ='Юнит 9'!H7 -> 0 | I7: 123.09 | J7: =E7*I7 -> 0 | K7: ='Юнит 9'!K7 -> 0 | L7: ='Юнит 6'!L7+'Юнит 7'!L7+'Юнит 8'!L7+'Юнит 9'!L7 -> 60 | O7: =L7/7 -> 8.5714286 | P7: =S7/7 -> 4 | Q7: ='Юнит 6'!Q7+'Юнит 7'!Q7+'Юнит 8'!Q7+'Юнит 9'!Q7 -> 28 | R7: ='Юнит 6'!R7+'Юнит 7'!R7+'Юнит 8'!R7+'Юнит 9'!R7 -> 0 | S7: =Q7+R7 -> 28 | T7: ='Юнит 6'!T7+'Юнит 7'!T7+'Юнит 8'!T7+'Юнит 9'!T7 -> 19832 | U7: ='Юнит 6'!U7+'Юнит 7'!U7+'Юнит 8'!U7+'Юнит 9'!U7 -> 0 | V7: =T7+U7 -> 19832 | W7: ='Юнит 6'!W7+'Юнит 7'!W7+'Юнит 8'!W7+'Юнит 9'!W7 -> 31845 | X7: ='Юнит 6'!X7+'Юнит 7'!X7+'Юнит 8'!X7+'Юнит 9'!X7 -> 0 | Y7: =W7+X7 -> 31845 | Z7: =L7*M7*N7/100 -> 0 | AA7: =Y7/$Y$93 -> 0.087720828 | AB7: =S7*I7 -> 3446.52 | AC7: ='Юнит 6'!AC7+'Юнит 7'!AC7+'Юнит 8'!AC7+'Юнит 9'!AC7 -> 11612.73 | AD7: =IF(Y7=0,0,AC7/Y7) -> 0.36466415 | AE7: 0 | AF7: 0 | AG7: 0 | AH7: 0 | AI7: 0 | AJ7: 0 | AK7: =V7*1% -> 198.32 | AL7: =Y7-AB7-AC7-AE7-AF7-AG7-AH7-AI7-AK7-AJ7 -> 16587.43 | AN7: =IF(S7=0,0,Y7/S7) -> 1137.3214 | AO7: =I7 -> 123.09 | AP7: =IF(S7=0,0,AC7/S7) -> 414.74036 | AQ7: =IF(Q7=0,AE7/1,AE7/Q7) -> 0 | AR7: =IF(Q7=0,0,(AF7+AG7)/Q7) -> 0 | AS7: {=_xlfn.IFS(S7=0,AL7,S7<0,AL7/-S7,S7>0,AL7/S7)} -> 592.40821 | AT7: =IF(AN7=0,0,AS7/AN7) -> 0.5208802 | AU7: =IF(AO7=0,0,AS7/AO7) -> 4.8128054 | AW7: =AS7*E7 -> 0
B8: 445336740 | C8: flip желтые Сул | D8: Солнцезащитные очки | E8: ='Юнит 9'!E8 -> 0 | F8: ='Юнит 9'!F8 -> 0 | G8: ='Юнит 9'!G8 -> 0 | H8: ='Юнит 9'!H8 -> 0 | I8: 123.09 | J8: =E8*I8 -> 0 | K8: ='Юнит 9'!K8 -> 0 | L8: ='Юнит 6'!L8+'Юнит 7'!L8+'Юнит 8'!L8+'Юнит 9'!L8 -> 62 | O8: =L8/7 -> 8.8571429 | P8: =S8/7 -> 6.4285714 | Q8: ='Юнит 6'!Q8+'Юнит 7'!Q8+'Юнит 8'!Q8+'Юнит 9'!Q8 -> 46 | R8: ='Юнит 6'!R8+'Юнит 7'!R8+'Юнит 8'!R8+'Юнит 9'!R8 -> -1 | S8: =Q8+R8 -> 45 | T8: ='Юнит 6'!T8+'Юнит 7'!T8+'Юнит 8'!T8+'Юнит 9'!T8 -> 33829.47 | U8: ='Юнит 6'!U8+'Юнит 7'!U8+'Юнит 8'!U8+'Юнит 9'!U8 -> -705 | V8: =T8+U8 -> 33124.47 | W8: ='Юнит 6'!W8+'Юнит 7'!W8+'Юнит 8'!W8+'Юнит 9'!W8 -> 52973.33 | X8: ='Юнит 6'!X8+'Юнит 7'!X8+'Юнит 8'!X8+'Юнит 9'!X8 -> -1150 | Y8: =W8+X8 -> 51823.33 | Z8: =L8*M8*N8/100 -> 0 | AA8: =Y8/$Y$93 -> 0.14275351 | AB8: =S8*I8 -> 5539.05 | AC8: ='Юнит 6'!AC8+'Юнит 7'!AC8+'Юнит 8'!AC8+'Юнит 9'!AC8 -> 18954.21 | AD8: =IF(Y8=0,0,AC8/Y8) -> 0.36574666 | AE8: 0 | AF8: 0 | AG8: 0 | AH8: 0 | AI8: 0 | AJ8: 0 | AK8: =V8*1% -> 331.2447 | AL8: =Y8-AB8-AC8-AE8-AF8-AG8-AH8-AI8-AK8-AJ8 -> 26998.825 | AN8: =IF(S8=0,0,Y8/S8) -> 1151.6296 | AO8: =I8 -> 123.09 | AP8: =IF(S8=0,0,AC8/S8) -> 421.20467 | AQ8: =IF(Q8=0,AE8/1,AE8/Q8) -> 0 | AR8: =IF(Q8=0,0,(AF8+AG8)/Q8) -> 0 | AS8: {=_xlfn.IFS(S8=0,AL8,S8<0,AL8/-S8,S8>0,AL8/S8)} -> 599.9739 | AT8: =IF(AN8=0,0,AS8/AN8) -> 0.5209782 | AU8: =IF(AO8=0,0,AS8/AO8) -> 4.87427 | AW8: =AS8*E8 -> 0
B9: 445341507 | C9: MR8854 C2 Сул | D9: Солнцезащитные очки | E9: ='Юнит 9'!E9 -> 0 | F9: ='Юнит 9'!F9 -> 0 | G9: ='Юнит 9'!G9 -> 0 | H9: ='Юнит 9'!H9 -> 0 | I9: 169.89 | J9: =E9*I9 -> 0 | K9: ='Юнит 9'!K9 -> 0 | L9: ='Юнит 6'!L9+'Юнит 7'!L9+'Юнит 8'!L9+'Юнит 9'!L9 -> 42 | O9: =L9/7 -> 6 | P9: =S9/7 -> 3.5714286 | Q9: ='Юнит 6'!Q9+'Юнит 7'!Q9+'Юнит 8'!Q9+'Юнит 9'!Q9 -> 25 | R9: ='Юнит 6'!R9+'Юнит 7'!R9+'Юнит 8'!R9+'Юнит 9'!R9 -> 0 | S9: =Q9+R9 -> 25 | T9: ='Юнит 6'!T9+'Юнит 7'!T9+'Юнит 8'!T9+'Юнит 9'!T9 -> 18968.36 | U9: ='Юнит 6'!U9+'Юнит 7'!U9+'Юнит 8'!U9+'Юнит 9'!U9 -> 0 | V9: =T9+U9 -> 18968.36 | W9: ='Юнит 6'!W9+'Юнит 7'!W9+'Юнит 8'!W9+'Юнит 9'!W9 -> 29685.77 | X9: ='Юнит 6'!X9+'Юнит 7'!X9+'Юнит 8'!X9+'Юнит 9'!X9 -> 0 | Y9: =W9+X9 -> 29685.77 | Z9: =L9*M9*N9/100 -> 0 | AA9: =Y9/$Y$93 -> 0.081772973 | AB9: =S9*I9 -> 4247.25 | AC9: ='Юнит 6'!AC9+'Юнит 7'!AC9+'Юнит 8'!AC9+'Юнит 9'!AC9 -> 10855.44 | AD9: =IF(Y9=0,0,AC9/Y9) -> 0.36567824 | AE9: 0 | AF9: 0 | AG9: 0 | AH9: 0 | AI9: 0 | AJ9: 0 | AK9: =V9*1% -> 189.6836 | AL9: =Y9-AB9-AC9-AE9-AF9-AG9-AH9-AI9-AK9-AJ9 -> 14393.396 | AN9: =IF(S9=0,0,Y9/S9) -> 1187.4308 | AO9: =I9 -> 169.89 | AP9: =IF(S9=0,0,AC9/S9) -> 434.2176 | AQ9: =IF(Q9=0,AE9/1,AE9/Q9) -> 0 | AR9: =IF(Q9=0,0,(AF9+AG9)/Q9) -> 0 | AS9: {=_xlfn.IFS(S9=0,AL9,S9<0,AL9/-S9,S9>0,AL9/S9)} -> 575.73586 | AT9: =IF(AN9=0,0,AS9/AN9) -> 0.48485845 | AU9: =IF(AO9=0,0,AS9/AO9) -> 3.3888743 | AW9: =AS9*E9 -> 0
B10: 497825485 | C10: MR 1819 черн | D10: Солнцезащитные очки | E10: ='Юнит 9'!E10 -> 0 | F10: ='Юнит 9'!F10 -> 0 | G10: ='Юнит 9'!G10 -> 0 | H10: ='Юнит 9'!H10 -> 0 | I10: 169.89 | J10: =E10*I10 -> 0 | K10: ='Юнит 9'!K10 -> 0 | L10: ='Юнит 6'!L10+'Юнит 7'!L10+'Юнит 8'!L10+'Юнит 9'!L10 -> 19 | O10: =L10/7 -> 2.7142857 | P10: =S10/7 -> 0.71428571 | Q10: ='Юнит 6'!Q10+'Юнит 7'!Q10+'Юнит 8'!Q10+'Юнит 9'!Q10 -> 5 | R10: ='Юнит 6'!R10+'Юнит 7'!R10+'Юнит 8'!R10+'Юнит 9'!R10 -> 0 | S10: =Q10+R10 -> 5 | T10: ='Юнит 6'!T10+'Юнит 7'!T10+'Юнит 8'!T10+'Юнит 9'!T10 -> 4088.64 | U10: ='Юнит 6'!U10+'Юнит 7'!U10+'Юнит 8'!U10+'Юнит 9'!U10 -> 0 | V10: =T10+U10 -> 4088.64 | W10: ='Юнит 6'!W10+'Юнит 7'!W10+'Юнит 8'!W10+'Юнит 9'!W10 -> 6104.59 | X10: ='Юнит 6'!X10+'Юнит 7'!X10+'Юнит 8'!X10+'Юнит 9'!X10 -> 0 | Y10: =W10+X10 -> 6104.59 | Z10: =L10*M10*N10/100 -> 0 | AA10: =Y10/$Y$93 -> 0.016815817 | AB10: =S10*I10 -> 849.45 | AC10: ='Юнит 6'!AC10+'Юнит 7'!AC10+'Юнит 8'!AC10+'Юнит 9'!AC10 -> 2234.34 | AD10: =IF(Y10=0,0,AC10/Y10) -> 0.36600984 | AE10: 0 | AF10: 0 | AG10: 0 | AH10: 0 | AI10: 0 | AJ10: 0 | AK10: =V10*1% -> 40.8864 | AL10: =Y10-AB10-AC10-AE10-AF10-AG10-AH10-AI10-AK10-AJ10 -> 2979.9136 | AN10: =IF(S10=0,0,Y10/S10) -> 1220.918 | AO10: =I10 -> 169.89 | AP10: =IF(S10=0,0,AC10/S10) -> 446.868 | AQ10: =IF(Q10=0,AE10/1,AE10/Q10) -> 0 | AR10: =IF(Q10=0,0,(AF10+AG10)/Q10) -> 0 | AS10: {=_xlfn.IFS(S10=0,AL10,S10<0,AL10/-S10,S10>0,AL10/S10)} -> 595.98272 | AT10: =IF(AN10=0,0,AS10/AN10) -> 0.48814312 | AU10: =IF(AO10=0,0,AS10/AO10) -> 3.5080506 | AW10: =AS10*E10 -> 0
B11: 497825962 | C11: MR 1819 корич | D11: Солнцезащитные очки | E11: ='Юнит 9'!E11 -> 0 | F11: ='Юнит 9'!F11 -> 0 | G11: ='Юнит 9'!G11 -> 0 | H11: ='Юнит 9'!H11 -> 0 | I11: 169.89 | J11: =E11*I11 -> 0 | K11: ='Юнит 9'!K11 -> 0 | L11: ='Юнит 6'!L11+'Юнит 7'!L11+'Юнит 8'!L11+'Юнит 9'!L11 -> 3 | O11: =L11/7 -> 0.42857143 | P11: =S11/7 -> 0.14285714 | Q11: ='Юнит 6'!Q11+'Юнит 7'!Q11+'Юнит 8'!Q11+'Юнит 9'!Q11 -> 1 | R11: ='Юнит 6'!R11+'Юнит 7'!R11+'Юнит 8'!R11+'Юнит 9'!R11 -> 0 | S11: =Q11+R11 -> 1 | T11: ='Юнит 6'!T11+'Юнит 7'!T11+'Юнит 8'!T11+'Юнит 9'!T11 -> 708 | U11: ='Юнит 6'!U11+'Юнит 7'!U11+'Юнит 8'!U11+'Юнит 9'!U11 -> 0 | V11: =T11+U11 -> 708 | W11: ='Юнит 6'!W11+'Юнит 7'!W11+'Юнит 8'!W11+'Юнит 9'!W11 -> 1145 | X11: ='Юнит 6'!X11+'Юнит 7'!X11+'Юнит 8'!X11+'Юнит 9'!X11 -> 0 | Y11: =W11+X11 -> 1145 | Z11: =L11*M11*N11/100 -> 0 | AA11: =Y11/$Y$93 -> 0.0031540382 | AB11: =S11*I11 -> 169.89 | AC11: ='Юнит 6'!AC11+'Юнит 7'!AC11+'Юнит 8'!AC11+'Юнит 9'!AC11 -> 418.03 | AD11: =IF(Y11=0,0,AC11/Y11) -> 0.3650917 | AE11: 0 | AF11: 0 | AG11: 0 | AH11: 0 | AI11: 0 | AJ11: 0 | AK11: =V11*1% -> 7.08 | AL11: =Y11-AB11-AC11-AE11-AF11-AG11-AH11-AI11-AK11-AJ11 -> 550 | AN11: =IF(S11=0,0,Y11/S11) -> 1145 | AO11: =I11 -> 169.89 | AP11: =IF(S11=0,0,AC11/S11) -> 418.03 | AQ11: =IF(Q11=0,AE11/1,AE11/Q11) -> 0 | AR11: =IF(Q11=0,0,(AF11+AG11)/Q11) -> 0 | AS11: {=_xlfn.IFS(S11=0,AL11,S11<0,AL11/-S11,S11>0,AL11/S11)} -> 550 | AT11: =IF(AN11=0,0,AS11/AN11) -> 0.48034934 | AU11: =IF(AO11=0,0,AS11/AO11) -> 3.2373889 | AW11: =AS11*E11 -> 0
B12: 497821775 | C12: MR Р1874 черн | D12: Солнцезащитные очки | E12: ='Юнит 9'!E12 -> 0 | F12: ='Юнит 9'!F12 -> 0 | G12: ='Юнит 9'!G12 -> 0 | H12: ='Юнит 9'!H12 -> 0 | I12: 169.89 | J12: =E12*I12 -> 0 | K12: ='Юнит 9'!K12 -> 0 | L12: ='Юнит 6'!L12+'Юнит 7'!L12+'Юнит 8'!L12+'Юнит 9'!L12 -> 13 | O12: =L12/7 -> 1.8571429 | P12: =S12/7 -> 0.57142857 | Q12: ='Юнит 6'!Q12+'Юнит 7'!Q12+'Юнит 8'!Q12+'Юнит 9'!Q12 -> 4 | R12: ='Юнит 6'!R12+'Юнит 7'!R12+'Юнит 8'!R12+'Юнит 9'!R12 -> 0 | S12: =Q12+R12 -> 4 | T12: ='Юнит 6'!T12+'Юнит 7'!T12+'Юнит 8'!T12+'Юнит 9'!T12 -> 2911 | U12: ='Юнит 6'!U12+'Юнит 7'!U12+'Юнит 8'!U12+'Юнит 9'!U12 -> 0 | V12: =T12+U12 -> 2911 | W12: ='Юнит 6'!W12+'Юнит 7'!W12+'Юнит 8'!W12+'Юнит 9'!W12 -> 4664 | X12: ='Юнит 6'!X12+'Юнит 7'!X12+'Юнит 8'!X12+'Юнит 9'!X12 -> 0 | Y12: =W12+X12 -> 4664 | Z12: =L12*M12*N12/100 -> 0 | AA12: =Y12/$Y$93 -> 0.012847541 | AB12: =S12*I12 -> 679.56 | AC12: ='Юнит 6'!AC12+'Юнит 7'!AC12+'Юнит 8'!AC12+'Юнит 9'!AC12 -> 1709.04 | AD12: =IF(Y12=0,0,AC12/Y12) -> 0.36643225 | AE12: 0 | AF12: 0 | AG12: 0 | AH12: 0 | AI12: 0 | AJ12: 0 | AK12: =V12*1% -> 29.11 | AL12: =Y12-AB12-AC12-AE12-AF12-AG12-AH12-AI12-AK12-AJ12 -> 2246.29 | AN12: =IF(S12=0,0,Y12/S12) -> 1166 | AO12: =I12 -> 169.89 | AP12: =IF(S12=0,0,AC12/S12) -> 427.26 | AQ12: =IF(Q12=0,AE12/1,AE12/Q12) -> 0 | AR12: =IF(Q12=0,0,(AF12+AG12)/Q12) -> 0 | AS12: {=_xlfn.IFS(S12=0,AL12,S12<0,AL12/-S12,S12>0,AL12/S12)} -> 561.5725 | AT12: =IF(AN12=0,0,AS12/AN12) -> 0.48162307 | AU12: =IF(AO12=0,0,AS12/AO12) -> 3.3055065 | AW12: =AS12*E12 -> 0
B13: 497823770 | C13: MR Р1874 корич | D13: Солнцезащитные очки | E13: ='Юнит 9'!E13 -> 0 | F13: ='Юнит 9'!F13 -> 0 | G13: ='Юнит 9'!G13 -> 0 | H13: ='Юнит 9'!H13 -> 0 | I13: 169.89 | J13: =E13*I13 -> 0 | K13: ='Юнит 9'!K13 -> 0 | L13: ='Юнит 6'!L13+'Юнит 7'!L13+'Юнит 8'!L13+'Юнит 9'!L13 -> 4 | O13: =L13/7 -> 0.57142857 | P13: =S13/7 -> 0.42857143 | Q13: ='Юнит 6'!Q13+'Юнит 7'!Q13+'Юнит 8'!Q13+'Юнит 9'!Q13 -> 3 | R13: ='Юнит 6'!R13+'Юнит 7'!R13+'Юнит 8'!R13+'Юнит 9'!R13 -> 0 | S13: =Q13+R13 -> 3 | T13: ='Юнит 6'!T13+'Юнит 7'!T13+'Юнит 8'!T13+'Юнит 9'!T13 -> 2222 | U13: ='Юнит 6'!U13+'Юнит 7'!U13+'Юнит 8'!U13+'Юнит 9'!U13 -> 0 | V13: =T13+U13 -> 2222 | W13: ='Юнит 6'!W13+'Юнит 7'!W13+'Юнит 8'!W13+'Юнит 9'!W13 -> 3663 | X13: ='Юнит 6'!X13+'Юнит 7'!X13+'Юнит 8'!X13+'Юнит 9'!X13 -> 0 | Y13: =W13+X13 -> 3663 | Z13: =L13*M13*N13/100 -> 0 | AA13: =Y13/$Y$93 -> 0.010090168 | AB13: =S13*I13 -> 509.67 | AC13: ='Юнит 6'!AC13+'Юнит 7'!AC13+'Юнит 8'!AC13+'Юнит 9'!AC13 -> 1335.93 | AD13: =IF(Y13=0,0,AC13/Y13) -> 0.36470925 | AE13: 0 | AF13: 0 | AG13: 0 | AH13: 0 | AI13: 0 | AJ13: 0 | AK13: =V13*1% -> 22.22 | AL13: =Y13-AB13-AC13-AE13-AF13-AG13-AH13-AI13-AK13-AJ13 -> 1795.18 | AN13: =IF(S13=0,0,Y13/S13) -> 1221 | AO13: =I13 -> 169.89 | AP13: =IF(S13=0,0,AC13/S13) -> 445.31 | AQ13: =IF(Q13=0,AE13/1,AE13/Q13) -> 0 | AR13: =IF(Q13=0,0,(AF13+AG13)/Q13) -> 0 | AS13: {=_xlfn.IFS(S13=0,AL13,S13<0,AL13/-S13,S13>0,AL13/S13)} -> 598.39333 | AT13: =IF(AN13=0,0,AS13/AN13) -> 0.49008463 | AU13: =IF(AO13=0,0,AS13/AO13) -> 3.5222399 | AW13: =AS13*E13 -> 0
B14: 497824253 | C14: MR Р1886 черн | D14: Солнцезащитные очки | E14: ='Юнит 9'!E14 -> 0 | F14: ='Юнит 9'!F14 -> 0 | G14: ='Юнит 9'!G14 -> 0 | H14: ='Юнит 9'!H14 -> 0 | I14: 169.89 | J14: =E14*I14 -> 0 | K14: ='Юнит 9'!K14 -> 0 | L14: ='Юнит 6'!L14+'Юнит 7'!L14+'Юнит 8'!L14+'Юнит 9'!L14 -> 9 | O14: =L14/7 -> 1.2857143 | P14: =S14/7 -> 0.57142857 | Q14: ='Юнит 6'!Q14+'Юнит 7'!Q14+'Юнит 8'!Q14+'Юнит 9'!Q14 -> 4 | R14: ='Юнит 6'!R14+'Юнит 7'!R14+'Юнит 8'!R14+'Юнит 9'!R14 -> 0 | S14: =Q14+R14 -> 4 | T14: ='Юнит 6'!T14+'Юнит 7'!T14+'Юнит 8'!T14+'Юнит 9'!T14 -> 3142 | U14: ='Юнит 6'!U14+'Юнит 7'!U14+'Юнит 8'!U14+'Юнит 9'!U14 -> 0 | V14: =T14+U14 -> 3142 | W14: ='Юнит 6'!W14+'Юнит 7'!W14+'Юнит 8'!W14+'Юнит 9'!W14 -> 5096 | X14: ='Юнит 6'!X14+'Юнит 7'!X14+'Юнит 8'!X14+'Юнит 9'!X14 -> 0 | Y14: =W14+X14 -> 5096 | Z14: =L14*M14*N14/100 -> 0 | AA14: =Y14/$Y$93 -> 0.014037536 | AB14: =S14*I14 -> 679.56 | AC14: ='Юнит 6'!AC14+'Юнит 7'!AC14+'Юнит 8'!AC14+'Юнит 9'!AC14 -> 1837.34 | AD14: =IF(Y14=0,0,AC14/Y14) -> 0.36054553 | AE14: 0 | AF14: 0 | AG14: 0 | AH14: 0 | AI14: 0 | AJ14: 0 | AK14: =V14*1% -> 31.42 | AL14: =Y14-AB14-AC14-AE14-AF14-AG14-AH14-AI14-AK14-AJ14 -> 2547.68 | AN14: =IF(S14=0,0,Y14/S14) -> 1274 | AO14: =I14 -> 169.89 | AP14: =IF(S14=0,0,AC14/S14) -> 459.335 | AQ14: =IF(Q14=0,AE14/1,AE14/Q14) -> 0 | AR14: =IF(Q14=0,0,(AF14+AG14)/Q14) -> 0 | AS14: {=_xlfn.IFS(S14=0,AL14,S14<0,AL14/-S14,S14>0,AL14/S14)} -> 636.92 | AT14: =IF(AN14=0,0,AS14/AN14) -> 0.49993721 | AU14: =IF(AO14=0,0,AS14/AO14) -> 3.7490141 | AW14: =AS14*E14 -> 0
B15: 497824944 | C15: MR Р1886 корич | D15: Солнцезащитные очки | E15: ='Юнит 9'!E15 -> 0 | F15: ='Юнит 9'!F15 -> 0 | G15: ='Юнит 9'!G15 -> 0 | H15: ='Юнит 9'!H15 -> 0 | I15: 169.89 | J15: =E15*I15 -> 0 | K15: ='Юнит 9'!K15 -> 0 | L15: ='Юнит 6'!L15+'Юнит 7'!L15+'Юнит 8'!L15+'Юнит 9'!L15 -> 5 | O15: =L15/7 -> 0.71428571 | P15: =S15/7 -> 0.14285714 | Q15: ='Юнит 6'!Q15+'Юнит 7'!Q15+'Юнит 8'!Q15+'Юнит 9'!Q15 -> 1 | R15: ='Юнит 6'!R15+'Юнит 7'!R15+'Юнит 8'!R15+'Юнит 9'!R15 -> 0 | S15: =Q15+R15 -> 1 | T15: ='Юнит 6'!T15+'Юнит 7'!T15+'Юнит 8'!T15+'Юнит 9'!T15 -> 743 | U15: ='Юнит 6'!U15+'Юнит 7'!U15+'Юнит 8'!U15+'Юнит 9'!U15 -> 0 | V15: =T15+U15 -> 743 | W15: ='Юнит 6'!W15+'Юнит 7'!W15+'Юнит 8'!W15+'Юнит 9'!W15 -> 1232 | X15: ='Юнит 6'!X15+'Юнит 7'!X15+'Юнит 8'!X15+'Юнит 9'!X15 -> 0 | Y15: =W15+X15 -> 1232 | Z15: =L15*M15*N15/100 -> 0 | AA15: =Y15/$Y$93 -> 0.0033936901 | AB15: =S15*I15 -> 169.89 | AC15: ='Юнит 6'!AC15+'Юнит 7'!AC15+'Юнит 8'!AC15+'Юнит 9'!AC15 -> 449.19 | AD15: =IF(Y15=0,0,AC15/Y15) -> 0.36460227 | AE15: 0 | AF15: 0 | AG15: 0 | AH15: 0 | AI15: 0 | AJ15: 0 | AK15: =V15*1% -> 7.43 | AL15: =Y15-AB15-AC15-AE15-AF15-AG15-AH15-AI15-AK15-AJ15 -> 605.49 | AN15: =IF(S15=0,0,Y15/S15) -> 1232 | AO15: =I15 -> 169.89 | AP15: =IF(S15=0,0,AC15/S15) -> 449.19 | AQ15: =IF(Q15=0,AE15/1,AE15/Q15) -> 0 | AR15: =IF(Q15=0,0,(AF15+AG15)/Q15) -> 0 | AS15: {=_xlfn.IFS(S15=0,AL15,S15<0,AL15/-S15,S15>0,AL15/S15)} -> 605.49 | AT15: =IF(AN15=0,0,AS15/AN15) -> 0.49146916 | AU15: =IF(AO15=0,0,AS15/AO15) -> 3.564012 | AW15: =AS15*E15 -> 0
... B34: 804691336 | C34: 6008 | D34: Солнцезащитные очки | E34: ='Юнит 9'!E34 -> 0 | F34: ='Юнит 9'!F34 -> 0 | G34: ='Юнит 9'!G34 -> 0 | H34: ='Юнит 9'!H34 -> 0 | I34: 178.89 | J34: =E34*I34 -> 0 | K34: ='Юнит 9'!K34 -> 0 | L34: ='Юнит 6'!L34+'Юнит 7'!L34+'Юнит 8'!L34+'Юнит 9'!L34 -> 0 | O34: =L34/7 -> 0 | P34: =S34/7 -> 0 | Q34: ='Юнит 6'!Q34+'Юнит 7'!Q34+'Юнит 8'!Q34+'Юнит 9'!Q34 -> 0 | R34: ='Юнит 6'!R34+'Юнит 7'!R34+'Юнит 8'!R34+'Юнит 9'!R34 -> 0 | S34: =Q34+R34 -> 0 | T34: ='Юнит 6'!T34+'Юнит 7'!T34+'Юнит 8'!T34+'Юнит 9'!T34 -> 0 | U34: ='Юнит 6'!U34+'Юнит 7'!U34+'Юнит 8'!U34+'Юнит 9'!U34 -> 0 | V34: =T34+U34 -> 0 | W34: ='Юнит 6'!W34+'Юнит 7'!W34+'Юнит 8'!W34+'Юнит 9'!W34 -> 0 | X34: ='Юнит 6'!X34+'Юнит 7'!X34+'Юнит 8'!X34+'Юнит 9'!X34 -> 0 | Y34: =W34+X34 -> 0 | Z34: =L34*M34*N34/100 -> 0 | AA34: =Y34/$Y$93 -> 0 | AB34: =S34*I34 -> 0 | AC34: ='Юнит 6'!AC34+'Юнит 7'!AC34+'Юнит 8'!AC34+'Юнит 9'!AC34 -> 0 | AD34: =IF(Y34=0,0,AC34/Y34) -> 0 | AE34: 0 | AF34: 0 | AG34: 0 | AH34: 0 | AI34: 0 | AJ34: 0 | AK34: =V34*1% -> 0 | AL34: =Y34-AB34-AC34-AE34-AF34-AG34-AH34-AI34-AK34-AJ34 -> 0 | AN34: =IF(S34=0,0,Y34/S34) -> 0 | AO34: =I34 -> 178.89 | AP34: =IF(S34=0,0,AC34/S34) -> 0 | AQ34: =IF(Q34=0,AE34/1,AE34/Q34) -> 0 | AR34: =IF(Q34=0,0,(AF34+AG34)/Q34) -> 0 | AS34: {=_xlfn.IFS(S34=0,AL34,S34<0,AL34/-S34,S34>0,AL34/S34)} -> 0 | AT34: =IF(AN34=0,0,AS34/AN34) -> 0 | AU34: =IF(AO34=0,0,AS34/AO34) -> 0 | AW34: =AS34*E34 -> 0
AN35: =AVERAGE(AN3:AN6) -> 1105.5546 | AO35: =AVERAGE(AO3:AO6) -> 128.0625 | AP35: =AVERAGE(AP3:AP6) -> 402.03631 | AQ35: =AVERAGE(AQ3:AQ6) -> 0 | AR35: =AVERAGE(AR3:AR6) -> 0 | AS35: =AVERAGE(AS3:AS6) -> 568.45751 | AT35: =AVERAGE(AT3:AT6) -> 0.51334017 | AU35: =AVERAGE(AU3:AU6) -> 4.4379434
A36: Итого очки | E36: =SUM(E3:E34) -> 0 | F36: =SUM(F3:F34) -> 0 | G36: =SUM(G3:G34) -> 0 | H36: =SUM(H3:H34) -> 0 | J36: =SUM(J3:J34) -> 0 | L36: =SUM(L3:L34) -> 674 | Q36: =SUM(Q3:Q34) -> 330 | R36: =SUM(R3:R34) -> -3 | S36: =SUM(S3:S34) -> 327 | T36: =SUM(T3:T34) -> 235366.16 | U36: =SUM(U3:U34) -> -2235 | V36: =SUM(V3:V34) -> 233131.16 | W36: =SUM(W3:W34) -> 366652.67 | X36: =SUM(X3:X34) -> -3626 | ... AC36: =SUM(AC3:AC34) -> 132170.15 | AD36: =AC36/Y36 -> 0.36407835 | AE36: =SUM(AE3:AE34) -> 0 | AF36: =SUM(AF3:AF34) -> 0 | AG36: =SUM(AG3:AG34) -> 0 | AH36: =SUM(AH3:AH34) -> 0 | AI36: =SUM(AI3:AI34) -> 0 | AJ36: =SUM(AJ3:AJ34) -> 0 | AK36: =SUM(AK3:AK34) -> 2331.3116 | AL36: =SUM(AL3:AL34) -> 184631.4 | AR36: =(AF36+AG36)/Q36 -> 0 | AW36: =SUM(AW3:AW6) -> 0
E38: =SUM(F38:H38) -> 0 | J38: =E38*I38 -> 0 | O38: =L38/7 -> 0 | P38: =S38/7 -> 0 | S38: =Q38+R38 -> 0 | V38: =T38+U38 -> 0 | Y38: =W38+X38 -> 0 | Z38: =L38*M38*N38/100 -> 0 | AA38: =Y38/$Y$93 -> 0 | AB38: =S38*I38 -> 0 | AD38: =IF(Y38=0,0,AC38/Y38) -> 0 | AK38: =V38*1% -> 0 | AL38: =Y38-AB38-AC38-AE38-AF38-AG38-AH38-AI38-AK38-AJ38 -> 0 | AN38: =IF(S38=0,0,Y38/S38) -> 0 | AO38: =I38 -> 0 | AP38: =IF(S38=0,0,AC38/S38) -> 0 | AQ38: =IF(Q38=0,AE38/1,AE38/Q38) -> 0 | AR38: =IF(Q38=0,0,(AF38+AG38)/Q38) -> 0 | AS38: {=_xlfn.IFS(S38=0,AL38,S38<0,AL38/-S38,S38>0,AL38/S38)} -> 0 | AT38: =IF(AN38=0,0,AS38/AN38) -> 0 | AU38: =IF(AO38=0,0,AS38/AO38) -> 0 | AW38: =AS38*E38 -> 0
E39: =SUM(F39:H39) -> 0 | J39: =E39*I39 -> 0 | O39: =L39/7 -> 0 | P39: =S39/7 -> 0 | S39: =Q39+R39 -> 0 | V39: =T39+U39 -> 0 | Y39: =W39+X39 -> 0 | Z39: =L39*M39*N39/100 -> 0 | AA39: =Y39/$Y$93 -> 0 | AB39: =S39*I39 -> 0 | AD39: =IF(Y39=0,0,AC39/Y39) -> 0 | AK39: =V39*1% -> 0 | AL39: =Y39-AB39-AC39-AE39-AF39-AG39-AH39-AI39-AK39-AJ39 -> 0 | AN39: =IF(S39=0,0,Y39/S39) -> 0 | AO39: =I39 -> 0 | AP39: =IF(S39=0,0,AC39/S39) -> 0 | AQ39: =IF(Q39=0,AE39/1,AE39/Q39) -> 0 | AR39: =IF(Q39=0,0,(AF39+AG39)/Q39) -> 0 | AS39: {=_xlfn.IFS(S39=0,AL39,S39<0,AL39/-S39,S39>0,AL39/S39)} -> 0 | AT39: =IF(AN39=0,0,AS39/AN39) -> 0 | AU39: =IF(AO39=0,0,AS39/AO39) -> 0 | AW39: =AS39*E39 -> 0
E40: =SUM(F40:H40) -> 0 | J40: =E40*I40 -> 0 | O40: =L40/7 -> 0 | P40: =S40/7 -> 0 | S40: =Q40+R40 -> 0 | V40: =T40+U40 -> 0 | Y40: =W40+X40 -> 0 | Z40: =L40*M40*N40/100 -> 0 | AA40: =Y40/$Y$93 -> 0 | AB40: =S40*I40 -> 0 | AD40: =IF(Y40=0,0,AC40/Y40) -> 0 | AK40: =V40*1% -> 0 | AL40: =Y40-AB40-AC40-AE40-AF40-AG40-AH40-AI40-AK40-AJ40 -> 0 | AN40: =IF(S40=0,0,Y40/S40) -> 0 | AO40: =I40 -> 0 | AP40: =IF(S40=0,0,AC40/S40) -> 0 | AQ40: =IF(Q40=0,AE40/1,AE40/Q40) -> 0 | AR40: =IF(Q40=0,0,(AF40+AG40)/Q40) -> 0 | AS40: {=_xlfn.IFS(S40=0,AL40,S40<0,AL40/-S40,S40>0,AL40/S40)} -> 0 | AT40: =IF(AN40=0,0,AS40/AN40) -> 0 | AU40: =IF(AO40=0,0,AS40/AO40) -> 0 | AW40: =AS40*E40 -> 0
E41: =SUM(F41:H41) -> 0 | J41: =E41*I41 -> 0 | O41: =L41/7 -> 0 | P41: =S41/7 -> 0 | S41: =Q41+R41 -> 0 | V41: =T41+U41 -> 0 | Y41: =W41+X41 -> 0 | Z41: =L41*M41*N41/100 -> 0 | AA41: =Y41/$Y$93 -> 0 | AB41: =S41*I41 -> 0 | AD41: =IF(Y41=0,0,AC41/Y41) -> 0 | AK41: =V41*1% -> 0 | AL41: =Y41-AB41-AC41-AE41-AF41-AG41-AH41-AI41-AK41-AJ41 -> 0 | AN41: =IF(S41=0,0,Y41/S41) -> 0 | AO41: =I41 -> 0 | AP41: =IF(S41=0,0,AC41/S41) -> 0 | AQ41: =IF(Q41=0,AE41/1,AE41/Q41) -> 0 | AR41: =IF(Q41=0,0,(AF41+AG41)/Q41) -> 0 | AS41: {=_xlfn.IFS(S41=0,AL41,S41<0,AL41/-S41,S41>0,AL41/S41)} -> 0 | AT41: =IF(AN41=0,0,AS41/AN41) -> 0 | AU41: =IF(AO41=0,0,AS41/AO41) -> 0 | AW41: =AS41*E41 -> 0
E42: =SUM(F42:H42) -> 0 | J42: =E42*I42 -> 0 | O42: =L42/7 -> 0 | P42: =S42/7 -> 0 | S42: =Q42+R42 -> 0 | V42: =T42+U42 -> 0 | Y42: =W42+X42 -> 0 | Z42: =L42*M42*N42/100 -> 0 | AA42: =Y42/$Y$93 -> 0 | AB42: =S42*I42 -> 0 | AD42: =IF(Y42=0,0,AC42/Y42) -> 0 | AK42: =V42*1% -> 0 | AL42: =Y42-AB42-AC42-AE42-AF42-AG42-AH42-AI42-AK42-AJ42 -> 0 | AN42: =IF(S42=0,0,Y42/S42) -> 0 | AO42: =I42 -> 0 | AP42: =IF(S42=0,0,AC42/S42) -> 0 | AQ42: =IF(Q42=0,AE42/1,AE42/Q42) -> 0 | AR42: =IF(Q42=0,0,(AF42+AG42)/Q42) -> 0 | AS42: {=_xlfn.IFS(S42=0,AL42,S42<0,AL42/-S42,S42>0,AL42/S42)} -> 0 | AT42: =IF(AN42=0,0,AS42/AN42) -> 0 | AU42: =IF(AO42=0,0,AS42/AO42) -> 0 | AW42: =AS42*E42 -> 0
E43: =SUM(F43:H43) -> 0 | J43: =E43*I43 -> 0 | O43: =L43/7 -> 0 | P43: =S43/7 -> 0 | S43: =Q43+R43 -> 0 | V43: =T43+U43 -> 0 | Y43: =W43+X43 -> 0 | Z43: =L43*M43*N43/100 -> 0 | AA43: =Y43/$Y$93 -> 0 | AB43: =S43*I43 -> 0 | AD43: =IF(Y43=0,0,AC43/Y43) -> 0 | AK43: =V43*1% -> 0 | AL43: =Y43-AB43-AC43-AE43-AF43-AG43-AH43-AI43-AK43-AJ43 -> 0 | AN43: =IF(S43=0,0,Y43/S43) -> 0 | AO43: =I43 -> 0 | AP43: =IF(S43=0,0,AC43/S43) -> 0 | AQ43: =IF(Q43=0,AE43/1,AE43/Q43) -> 0 | AR43: =IF(Q43=0,0,(AF43+AG43)/Q43) -> 0 | AS43: {=_xlfn.IFS(S43=0,AL43,S43<0,AL43/-S43,S43>0,AL43/S43)} -> 0 | AT43: =IF(AN43=0,0,AS43/AN43) -> 0 | AU43: =IF(AO43=0,0,AS43/AO43) -> 0 | AW43: =AS43*E43 -> 0
E44: =SUM(F44:H44) -> 0 | J44: =E44*I44 -> 0 | O44: =L44/7 -> 0 | P44: =S44/7 -> 0 | S44: =Q44+R44 -> 0 | V44: =T44+U44 -> 0 | Y44: =W44+X44 -> 0 | Z44: =L44*M44*N44/100 -> 0 | AA44: =Y44/$Y$93 -> 0 | AB44: =S44*I44 -> 0 | AD44: =IF(Y44=0,0,AC44/Y44) -> 0 | AK44: =V44*1% -> 0 | AL44: =Y44-AB44-AC44-AE44-AF44-AG44-AH44-AI44-AK44-AJ44 -> 0 | AN44: =IF(S44=0,0,Y44/S44) -> 0 | AO44: =I44 -> 0 | AP44: =IF(S44=0,0,AC44/S44) -> 0 | AQ44: =IF(Q44=0,AE44/1,AE44/Q44) -> 0 | AR44: =IF(Q44=0,0,(AF44+AG44)/Q44) -> 0 | AS44: {=_xlfn.IFS(S44=0,AL44,S44<0,AL44/-S44,S44>0,AL44/S44)} -> 0 | AT44: =IF(AN44=0,0,AS44/AN44) -> 0 | AU44: =IF(AO44=0,0,AS44/AO44) -> 0 | AW44: =AS44*E44 -> 0
E45: =SUM(F45:H45) -> 0 | J45: =E45*I45 -> 0 | O45: =L45/7 -> 0 | P45: =S45/7 -> 0 | S45: =Q45+R45 -> 0 | V45: =T45+U45 -> 0 | Y45: =W45+X45 -> 0 | Z45: =L45*M45*N45/100 -> 0 | AA45: =Y45/$Y$93 -> 0 | AB45: =S45*I45 -> 0 | AD45: =IF(Y45=0,0,AC45/Y45) -> 0 | AK45: =V45*1% -> 0 | AL45: =Y45-AB45-AC45-AE45-AF45-AG45-AH45-AI45-AK45-AJ45 -> 0 | AN45: =IF(S45=0,0,Y45/S45) -> 0 | AO45: =I45 -> 0 | AP45: =IF(S45=0,0,AC45/S45) -> 0 | AQ45: =IF(Q45=0,AE45/1,AE45/Q45) -> 0 | AR45: =IF(Q45=0,0,(AF45+AG45)/Q45) -> 0 | AS45: {=_xlfn.IFS(S45=0,AL45,S45<0,AL45/-S45,S45>0,AL45/S45)} -> 0 | AT45: =IF(AN45=0,0,AS45/AN45) -> 0 | AU45: =IF(AO45=0,0,AS45/AO45) -> 0 | AW45: =AS45*E45 -> 0
E46: =SUM(F46:H46) -> 0 | J46: =E46*I46 -> 0 | O46: =L46/7 -> 0 | P46: =S46/7 -> 0 | S46: =Q46+R46 -> 0 | V46: =T46+U46 -> 0 | Y46: =W46+X46 -> 0 | Z46: =L46*M46*N46/100 -> 0 | AA46: =Y46/$Y$93 -> 0 | AB46: =S46*I46 -> 0 | AD46: =IF(Y46=0,0,AC46/Y46) -> 0 | AK46: =V46*1% -> 0 | AL46: =Y46-AB46-AC46-AE46-AF46-AG46-AH46-AI46-AK46-AJ46 -> 0 | AN46: =IF(S46=0,0,Y46/S46) -> 0 | AO46: =I46 -> 0 | AP46: =IF(S46=0,0,AC46/S46) -> 0 | AQ46: =IF(Q46=0,AE46/1,AE46/Q46) -> 0 | AR46: =IF(Q46=0,0,(AF46+AG46)/Q46) -> 0 | AS46: {=_xlfn.IFS(S46=0,AL46,S46<0,AL46/-S46,S46>0,AL46/S46)} -> 0 | AT46: =IF(AN46=0,0,AS46/AN46) -> 0 | AU46: =IF(AO46=0,0,AS46/AO46) -> 0 | AW46: =AS46*E46 -> 0
E47: =SUM(F47:H47) -> 0 | J47: =E47*I47 -> 0 | O47: =L47/7 -> 0 | P47: =S47/7 -> 0 | S47: =Q47+R47 -> 0 | V47: =T47+U47 -> 0 | Y47: =W47+X47 -> 0 | Z47: =L47*M47*N47/100 -> 0 | AA47: =Y47/$Y$93 -> 0 | AB47: =S47*I47 -> 0 | AD47: =IF(Y47=0,0,AC47/Y47) -> 0 | AK47: =V47*1% -> 0 | AL47: =Y47-AB47-AC47-AE47-AF47-AG47-AH47-AI47-AK47-AJ47 -> 0 | AN47: =IF(S47=0,0,Y47/S47) -> 0 | AO47: =I47 -> 0 | AP47: =IF(S47=0,0,AC47/S47) -> 0 | AQ47: =IF(Q47=0,AE47/1,AE47/Q47) -> 0 | AR47: =IF(Q47=0,0,(AF47+AG47)/Q47) -> 0 | AS47: {=_xlfn.IFS(S47=0,AL47,S47<0,AL47/-S47,S47>0,AL47/S47)} -> 0 | AT47: =IF(AN47=0,0,AS47/AN47) -> 0 | AU47: =IF(AO47=0,0,AS47/AO47) -> 0 | AW47: =AS47*E47 -> 0
E48: =SUM(F48:H48) -> 0 | J48: =E48*I48 -> 0 | O48: =L48/7 -> 0 | P48: =S48/7 -> 0 | S48: =Q48+R48 -> 0 | V48: =T48+U48 -> 0 | Y48: =W48+X48 -> 0 | Z48: =L48*M48*N48/100 -> 0 | AA48: =Y48/$Y$93 -> 0 | AB48: =S48*I48 -> 0 | AD48: =IF(Y48=0,0,AC48/Y48) -> 0 | AK48: =V48*1% -> 0 | AL48: =Y48-AB48-AC48-AE48-AF48-AG48-AH48-AI48-AK48-AJ48 -> 0 | AN48: =IF(S48=0,0,Y48/S48) -> 0 | AO48: =I48 -> 0 | AP48: =IF(S48=0,0,AC48/S48) -> 0 | AQ48: =IF(Q48=0,AE48/1,AE48/Q48) -> 0 | AR48: =IF(Q48=0,0,(AF48+AG48)/Q48) -> 0 | AS48: {=_xlfn.IFS(S48=0,AL48,S48<0,AL48/-S48,S48>0,AL48/S48)} -> 0 | AT48: =IF(AN48=0,0,AS48/AN48) -> 0 | AU48: =IF(AO48=0,0,AS48/AO48) -> 0 | AW48: =AS48*E48 -> 0
E49: =SUM(F49:H49) -> 0 | J49: =E49*I49 -> 0 | O49: =L49/7 -> 0 | P49: =S49/7 -> 0 | S49: =Q49+R49 -> 0 | V49: =T49+U49 -> 0 | Y49: =W49+X49 -> 0 | Z49: =L49*M49*N49/100 -> 0 | AA49: =Y49/$Y$93 -> 0 | AB49: =S49*I49 -> 0 | AD49: =IF(Y49=0,0,AC49/Y49) -> 0 | AK49: =V49*1% -> 0 | AL49: =Y49-AB49-AC49-AE49-AF49-AG49-AH49-AI49-AK49-AJ49 -> 0 | AN49: =IF(S49=0,0,Y49/S49) -> 0 | AO49: =I49 -> 0 | AP49: =IF(S49=0,0,AC49/S49) -> 0 | AQ49: =IF(Q49=0,AE49/1,AE49/Q49) -> 0 | AR49: =IF(Q49=0,0,(AF49+AG49)/Q49) -> 0 | AS49: {=_xlfn.IFS(S49=0,AL49,S49<0,AL49/-S49,S49>0,AL49/S49)} -> 0 | AT49: =IF(AN49=0,0,AS49/AN49) -> 0 | AU49: =IF(AO49=0,0,AS49/AO49) -> 0 | AW49: =AS49*E49 -> 0
... E89: =SUM(F89:H89) -> 0 | J89: =E89*I89 -> 0 | O89: =L89/7 -> 0 | P89: =S89/7 -> 0 | S89: =Q89+R89 -> 0 | V89: =T89+U89 -> 0 | Y89: =W89+X89 -> 0 | Z89: =L89*M89*N89/100 -> 0 | AA89: =Y89/$Y$93 -> 0 | AB89: =S89*I89 -> 0 | AD89: =IF(Y89=0,0,AC89/Y89) -> 0 | AK89: =V89*1% -> 0 | AL89: =Y89-AB89-AC89-AE89-AF89-AG89-AH89-AI89-AK89-AJ89 -> 0 | AN89: =IF(S89=0,0,Y89/S89) -> 0 | AO89: =I89 -> 0 | AP89: =IF(S89=0,0,AC89/S89) -> 0 | AQ89: =IF(Q89=0,AE89/1,AE89/Q89) -> 0 | AR89: =IF(Q89=0,0,(AF89+AG89)/Q89) -> 0 | AS89: {=_xlfn.IFS(S89=0,AL89,S89<0,AL89/-S89,S89>0,AL89/S89)} -> 0 | AT89: =IF(AN89=0,0,AS89/AN89) -> 0 | AU89: =IF(AO89=0,0,AS89/AO89) -> 0 | AW89: =AS89*E89 -> 0
AN90: =AVERAGE(AN38:AN89) -> 0 | AO90: =AVERAGE(AO38:AO89) -> 0 | AP90: =AVERAGE(AP38:AP89) -> 0 | AQ90: =AVERAGE(AQ38:AQ89) -> 0 | AR90: =AVERAGE(AR38:AR89) -> 0 | AS90: =AVERAGE(AS38:AS89) -> 0 | AT90: =AVERAGE(AT38:AT89) -> 0 | AU90: =AVERAGE(AU38:AU89) -> 0
A91: Итого ___ | E91: =SUM(E38:E89) -> 0 | F91: =SUM(F38:F89) -> 0 | G91: =SUM(G38:G89) -> 0 | H91: =SUM(H38:H89) -> 0 | J91: =SUM(J38:J89) -> 0 | L91: =SUM(L38:L89) -> 0 | Q91: =SUM(Q38:Q89) -> 0 | R91: =SUM(R38:R89) -> 0 | S91: =SUM(S38:S89) -> 0 | T91: =SUM(T38:T89) -> 0 | U91: =SUM(U38:U89) -> 0 | V91: =SUM(V38:V89) -> 0 | W91: =SUM(W38:W89) -> 0 | X91: =SUM(X38:X89) -> 0 | ... AC91: =SUM(AC38:AC89) -> 0 | AD91: =AC91/Y91 -> #DIV/0! | AE91: =SUM(AE38:AE89) -> 0 | AF91: =SUM(AF38:AF89) -> 0 | AG91: =SUM(AG38:AG89) -> 0 | AH91: =SUM(AH38:AH89) -> 0 | AI91: =SUM(AI38:AI89) -> 0 | AJ91: =SUM(AJ38:AJ89) -> 0 | AK91: =SUM(AK38:AK89) -> 0 | AL91: =SUM(AL38:AL89) -> 0 | AR91: =(AF91+AG91)/Q91 -> #DIV/0! | AW91: =SUM(AW38:AW89) -> 0
A93: ИТОГО | E93: =E36+E91 -> 0 | F93: =F36+F91 -> 0 | G93: =G36+G91 -> 0 | H93: =H36+H91 -> 0 | I93: =I36+I91 -> 0 | J93: =J36+J91 -> 0 | K93: =K36+K91 -> 0 | L93: =L36+L91 -> 674 | ... AC93: =AC36+AC91 -> 132170.15 | AD93: =AC93/Y93 -> 0.36407835 | AE93: =AE36+AE91 -> 0 | AF93: =AF36+AF91 -> 0 | AG93: =AG36+AG91 -> 0 | AH93: =AH36+AH91 -> 0 | AI93: =AI36+AI91 -> 0 | AJ93: =AJ36+AJ91 -> 0 | AK93: =AK36+AK91 -> 2331.3116 | AL93: =AL36+AL91 -> 184631.4 | AR93: =(AF93+AG93)/Q93 -> 0 | AW93: =AW36+AW91 -> 0
AL94: =Сводная!AD14+Сводная!V14 -> 146047.96

Sheet Юнит 9
A1: 23.02-01.03_9 нед | F1: Отчет по остаткам 3,4,5 | K1: Цены и скидки 6 | L1: Воронка продаж 16,50,32 | AI1: Вставить в Итого | AN1: на 1 единицу проданного товара
A2: Бренд | B2: SKU | C2: Артикул поставщика | D2: Предмет | E2: Остаток на 02.03 | F2: В пути до клиента | G2: В пути от клиента | H2: Итого по складам ВБ | I2: Себетоимость на 1 ед на 29.09.25 | J2: Себестоимость остатков | K2: Оборачива-емость, дн | L2: Заказы, шт 7 дней | M2: Средняя цена, руб | N2: % выкупа за 7 дней | O2: Скорость заказов | P2: Скорость продаж | Q2: Кол-во ПРОДАЖИ | R2: Кол-во ВОЗВРАТЫ | S2: Кол-во ПРОДАЖИ-ВОЗВРАТЫ | T2: Выручка ВБ ПРОДАЖИ | U2: Выручка ВБ ВОЗВРАТЫ | V2: Выручка с учетом СПП ПРОДАЖИ - ВОЗВРАТЫ | W2: Выручка ПРОДАЖИ | X2: Выручка ВОЗВРАТЫ | Y2: Выручка с учетом согласованной скидки ПРОДАЖИ - ВОЗВРАТЫ | Z2: Выручка потенциальная | AA2: Доля выручки, % от общего объема | AB2: Себестоимость продаж | AC2: Комиссия, руб | AD2: Комиссия, % | AE2: Логистика | AF2: Реклама БАЛАНС | AG2: Реклама СЧЕТ | AH2: Блогеры | AI2: Хранение | AJ2: Штрафы | AK2: Налог 1% | AL2: Прибыль | AN2: Выручка на 1 ед (средняя цена продажи со скидкой) | AO2: Себестоимость на 1 ед | AP2: Комиссия на 1 ед | AQ2: Логистика на 1 ед | AR2: Реклама на 1 ед | AS2: Прибыль на 1 ед | AT2: Маржиналь-ность, % | AU2: Рентабель-ность, % | AW2: Прибыль с остатков
B3: 341479791 | C3: Черные с железкой Сул | D3: Солнцезащитные очки | E3: =F3+G3+H3 -> 0 | I3: 142.98 | J3: =E3*I3 -> 0 | O3: =L3/7 -> 0 | P3: =S3/7 -> 0 | S3: =Q3+R3 -> 0 | V3: =T3+U3 -> 0 | Y3: =W3+X3 -> 0 | Z3: =L3*M3*N3/100 -> 0 | AA3: =Y3/$Y$93 -> #DIV/0! | AB3: =S3*I3 -> 0 | AD3: =IF(Y3=0,0,AC3/Y3) -> 0 | AI3: =IFERROR($AI$93*H3/$H$93,0) -> 0 | AK3: =V3*1% -> 0 | AL3: =Y3-AB3-AC3-AE3-AF3-AG3-AH3-AI3-AK3-AJ3 -> 0 | AN3: =IF(S3=0,0,Y3/S3) -> 0 | AO3: =I3 -> 142.98 | AP3: =IF(S3=0,0,AC3/S3) -> 0 | AQ3: =IF(Q3=0,AE3/1,AE3/Q3) -> 0 | AR3: =IF(Q3=0,0,(AF3+AG3)/Q3) -> 0 | AS3: =_xlfn.IFS(S3=0,AL3,S3<0,AL3/-S3,S3>0,AL3/S3) -> 0 | AT3: =IF(AN3=0,0,AS3/AN3) -> 0 | AU3: =IF(AO3=0,0,AS3/AO3) -> 0 | AW3: =AS3*E3 -> 0
B4: 340343575 | C4: Qs черн Сул | D4: Солнцезащитные очки | E4: =F4+G4+H4 -> 0 | I4: 123.09 | J4: =E4*I4 -> 0 | O4: =L4/7 -> 0 | P4: =S4/7 -> 0 | S4: =Q4+R4 -> 0 | V4: =T4+U4 -> 0 | Y4: =W4+X4 -> 0 | Z4: =L4*M4*N4/100 -> 0 | AA4: =Y4/$Y$93 -> #DIV/0! | AB4: =S4*I4 -> 0 | AD4: =IF(Y4=0,0,AC4/Y4) -> 0 | AI4: =IFERROR($AI$93*H4/$H$93,0) -> 0 | AK4: =V4*1% -> 0 | AL4: =Y4-AB4-AC4-AE4-AF4-AG4-AH4-AI4-AK4-AJ4 -> 0 | AN4: =IF(S4=0,0,Y4/S4) -> 0 | AO4: =I4 -> 123.09 | AP4: =IF(S4=0,0,AC4/S4) -> 0 | AQ4: =IF(Q4=0,AE4/1,AE4/Q4) -> 0 | AR4: =IF(Q4=0,0,(AF4+AG4)/Q4) -> 0 | AS4: {=_xlfn.IFS(S4=0,AL4,S4<0,AL4/-S4,S4>0,AL4/S4)} -> 0 | AT4: =IF(AN4=0,0,AS4/AN4) -> 0 | AU4: =IF(AO4=0,0,AS4/AO4) -> 0 | AW4: =AS4*E4 -> 0
B5: 340332621 | C5: Qs син Сул | D5: Солнцезащитные очки | E5: =F5+G5+H5 -> 0 | I5: 123.09 | J5: =E5*I5 -> 0 | O5: =L5/7 -> 0 | P5: =S5/7 -> 0 | S5: =Q5+R5 -> 0 | V5: =T5+U5 -> 0 | Y5: =W5+X5 -> 0 | Z5: =L5*M5*N5/100 -> 0 | AA5: =Y5/$Y$93 -> #DIV/0! | AB5: =S5*I5 -> 0 | AD5: =IF(Y5=0,0,AC5/Y5) -> 0 | AI5: =IFERROR($AI$93*H5/$H$93,0) -> 0 | AK5: =V5*1% -> 0 | AL5: =Y5-AB5-AC5-AE5-AF5-AG5-AH5-AI5-AK5-AJ5 -> 0 | AN5: =IF(S5=0,0,Y5/S5) -> 0 | AO5: =I5 -> 123.09 | AP5: =IF(S5=0,0,AC5/S5) -> 0 | AQ5: =IF(Q5=0,AE5/1,AE5/Q5) -> 0 | AR5: =IF(Q5=0,0,(AF5+AG5)/Q5) -> 0 | AS5: {=_xlfn.IFS(S5=0,AL5,S5<0,AL5/-S5,S5>0,AL5/S5)} -> 0 | AT5: =IF(AN5=0,0,AS5/AN5) -> 0 | AU5: =IF(AO5=0,0,AS5/AO5) -> 0 | AW5: =AS5*E5 -> 0
B6: 340341838 | C6: Qs желт Сул | D6: Солнцезащитные очки | E6: =F6+G6+H6 -> 0 | I6: 123.09 | J6: =E6*I6 -> 0 | O6: =L6/7 -> 0 | P6: =S6/7 -> 0 | S6: =Q6+R6 -> 0 | V6: =T6+U6 -> 0 | Y6: =W6+X6 -> 0 | Z6: =L6*M6*N6/100 -> 0 | AA6: =Y6/$Y$93 -> #DIV/0! | AB6: =S6*I6 -> 0 | AD6: =IF(Y6=0,0,AC6/Y6) -> 0 | AI6: =IFERROR($AI$93*H6/$H$93,0) -> 0 | AK6: =V6*1% -> 0 | AL6: =Y6-AB6-AC6-AE6-AF6-AG6-AH6-AI6-AK6-AJ6 -> 0 | AN6: =IF(S6=0,0,Y6/S6) -> 0 | AO6: =I6 -> 123.09 | AP6: =IF(S6=0,0,AC6/S6) -> 0 | AQ6: =IF(Q6=0,AE6/1,AE6/Q6) -> 0 | AR6: =IF(Q6=0,0,(AF6+AG6)/Q6) -> 0 | AS6: {=_xlfn.IFS(S6=0,AL6,S6<0,AL6/-S6,S6>0,AL6/S6)} -> 0 | AT6: =IF(AN6=0,0,AS6/AN6) -> 0 | AU6: =IF(AO6=0,0,AS6/AO6) -> 0 | AW6: =AS6*E6 -> 0
B7: 445291724 | C7: flip черные Сул | D7: Солнцезащитные очки | E7: =F7+G7+H7 -> 0 | I7: 123.09 | J7: =E7*I7 -> 0 | O7: =L7/7 -> 0 | P7: =S7/7 -> 0 | S7: =Q7+R7 -> 0 | V7: =T7+U7 -> 0 | Y7: =W7+X7 -> 0 | Z7: =L7*M7*N7/100 -> 0 | AA7: =Y7/$Y$93 -> #DIV/0! | AB7: =S7*I7 -> 0 | AD7: =IF(Y7=0,0,AC7/Y7) -> 0 | AI7: =IFERROR($AI$93*H7/$H$93,0) -> 0 | AK7: =V7*1% -> 0 | AL7: =Y7-AB7-AC7-AE7-AF7-AG7-AH7-AI7-AK7-AJ7 -> 0 | AN7: =IF(S7=0,0,Y7/S7) -> 0 | AO7: =I7 -> 123.09 | AP7: =IF(S7=0,0,AC7/S7) -> 0 | AQ7: =IF(Q7=0,AE7/1,AE7/Q7) -> 0 | AR7: =IF(Q7=0,0,(AF7+AG7)/Q7) -> 0 | AS7: {=_xlfn.IFS(S7=0,AL7,S7<0,AL7/-S7,S7>0,AL7/S7)} -> 0 | AT7: =IF(AN7=0,0,AS7/AN7) -> 0 | AU7: =IF(AO7=0,0,AS7/AO7) -> 0 | AW7: =AS7*E7 -> 0
B8: 445336740 | C8: flip желтые Сул | D8: Солнцезащитные очки | E8: =F8+G8+H8 -> 0 | I8: 123.09 | J8: =E8*I8 -> 0 | O8: =L8/7 -> 0 | P8: =S8/7 -> 0 | S8: =Q8+R8 -> 0 | V8: =T8+U8 -> 0 | Y8: =W8+X8 -> 0 | Z8: =L8*M8*N8/100 -> 0 | AA8: =Y8/$Y$93 -> #DIV/0! | AB8: =S8*I8 -> 0 | AD8: =IF(Y8=0,0,AC8/Y8) -> 0 | AI8: =IFERROR($AI$93*H8/$H$93,0) -> 0 | AK8: =V8*1% -> 0 | AL8: =Y8-AB8-AC8-AE8-AF8-AG8-AH8-AI8-AK8-AJ8 -> 0 | AN8: =IF(S8=0,0,Y8/S8) -> 0 | AO8: =I8 -> 123.09 | AP8: =IF(S8=0,0,AC8/S8) -> 0 | AQ8: =IF(Q8=0,AE8/1,AE8/Q8) -> 0 | AR8: =IF(Q8=0,0,(AF8+AG8)/Q8) -> 0 | AS8: {=_xlfn.IFS(S8=0,AL8,S8<0,AL8/-S8,S8>0,AL8/S8)} -> 0 | AT8: =IF(AN8=0,0,AS8/AN8) -> 0 | AU8: =IF(AO8=0,0,AS8/AO8) -> 0 | AW8: =AS8*E8 -> 0
B9: 445341507 | C9: MR8854 C2 Сул | D9: Солнцезащитные очки | E9: =F9+G9+H9 -> 0 | I9: 169.89 | J9: =E9*I9 -> 0 | O9: =L9/7 -> 0 | P9: =S9/7 -> 0 | S9: =Q9+R9 -> 0 | V9: =T9+U9 -> 0 | Y9: =W9+X9 -> 0 | Z9: =L9*M9*N9/100 -> 0 | AA9: =Y9/$Y$93 -> #DIV/0! | AB9: =S9*I9 -> 0 | AD9: =IF(Y9=0,0,AC9/Y9) -> 0 | AI9: =IFERROR($AI$93*H9/$H$93,0) -> 0 | AK9: =V9*1% -> 0 | AL9: =Y9-AB9-AC9-AE9-AF9-AG9-AH9-AI9-AK9-AJ9 -> 0 | AN9: =IF(S9=0,0,Y9/S9) -> 0 | AO9: =I9 -> 169.89 | AP9: =IF(S9=0,0,AC9/S9) -> 0 | AQ9: =IF(Q9=0,AE9/1,AE9/Q9) -> 0 | AR9: =IF(Q9=0,0,(AF9+AG9)/Q9) -> 0 | AS9: {=_xlfn.IFS(S9=0,AL9,S9<0,AL9/-S9,S9>0,AL9/S9)} -> 0 | AT9: =IF(AN9=0,0,AS9/AN9) -> 0 | AU9: =IF(AO9=0,0,AS9/AO9) -> 0 | AW9: =AS9*E9 -> 0
B10: 497825485 | C10: MR 1819 черн | D10: Солнцезащитные очки | E10: =F10+G10+H10 -> 0 | I10: 169.89 | J10: =E10*I10 -> 0 | O10: =L10/7 -> 0 | P10: =S10/7 -> 0 | S10: =Q10+R10 -> 0 | V10: =T10+U10 -> 0 | Y10: =W10+X10 -> 0 | Z10: =L10*M10*N10/100 -> 0 | AA10: =Y10/$Y$93 -> #DIV/0! | AB10: =S10*I10 -> 0 | AD10: =IF(Y10=0,0,AC10/Y10) -> 0 | AI10: =IFERROR($AI$93*H10/$H$93,0) -> 0 | AK10: =V10*1% -> 0 | AL10: =Y10-AB10-AC10-AE10-AF10-AG10-AH10-AI10-AK10-AJ10 -> 0 | AN10: =IF(S10=0,0,Y10/S10) -> 0 | AO10: =I10 -> 169.89 | AP10: =IF(S10=0,0,AC10/S10) -> 0 | AQ10: =IF(Q10=0,AE10/1,AE10/Q10) -> 0 | AR10: =IF(Q10=0,0,(AF10+AG10)/Q10) -> 0 | AS10: {=_xlfn.IFS(S10=0,AL10,S10<0,AL10/-S10,S10>0,AL10/S10)} -> 0 | AT10: =IF(AN10=0,0,AS10/AN10) -> 0 | AU10: =IF(AO10=0,0,AS10/AO10) -> 0 | AW10: =AS10*E10 -> 0
B11: 497825962 | C11: MR 1819 корич | D11: Солнцезащитные очки | E11: =F11+G11+H11 -> 0 | I11: 169.89 | J11: =E11*I11 -> 0 | O11: =L11/7 -> 0 | P11: =S11/7 -> 0 | S11: =Q11+R11 -> 0 | V11: =T11+U11 -> 0 | Y11: =W11+X11 -> 0 | Z11: =L11*M11*N11/100 -> 0 | AA11: =Y11/$Y$93 -> #DIV/0! | AB11: =S11*I11 -> 0 | AD11: =IF(Y11=0,0,AC11/Y11) -> 0 | AI11: =IFERROR($AI$93*H11/$H$93,0) -> 0 | AK11: =V11*1% -> 0 | AL11: =Y11-AB11-AC11-AE11-AF11-AG11-AH11-AI11-AK11-AJ11 -> 0 | AN11: =IF(S11=0,0,Y11/S11) -> 0 | AO11: =I11 -> 169.89 | AP11: =IF(S11=0,0,AC11/S11) -> 0 | AQ11: =IF(Q11=0,AE11/1,AE11/Q11) -> 0 | AR11: =IF(Q11=0,0,(AF11+AG11)/Q11) -> 0 | AS11: {=_xlfn.IFS(S11=0,AL11,S11<0,AL11/-S11,S11>0,AL11/S11)} -> 0 | AT11: =IF(AN11=0,0,AS11/AN11) -> 0 | AU11: =IF(AO11=0,0,AS11/AO11) -> 0 | AW11: =AS11*E11 -> 0
B12: 497821775 | C12: MR Р1874 черн | D12: Солнцезащитные очки | E12: =F12+G12+H12 -> 0 | I12: 169.89 | J12: =E12*I12 -> 0 | O12: =L12/7 -> 0 | P12: =S12/7 -> 0 | S12: =Q12+R12 -> 0 | V12: =T12+U12 -> 0 | Y12: =W12+X12 -> 0 | Z12: =L12*M12*N12/100 -> 0 | AA12: =Y12/$Y$93 -> #DIV/0! | AB12: =S12*I12 -> 0 | AD12: =IF(Y12=0,0,AC12/Y12) -> 0 | AI12: =IFERROR($AI$93*H12/$H$93,0) -> 0 | AK12: =V12*1% -> 0 | AL12: =Y12-AB12-AC12-AE12-AF12-AG12-AH12-AI12-AK12-AJ12 -> 0 | AN12: =IF(S12=0,0,Y12/S12) -> 0 | AO12: =I12 -> 169.89 | AP12: =IF(S12=0,0,AC12/S12) -> 0 | AQ12: =IF(Q12=0,AE12/1,AE12/Q12) -> 0 | AR12: =IF(Q12=0,0,(AF12+AG12)/Q12) -> 0 | AS12: {=_xlfn.IFS(S12=0,AL12,S12<0,AL12/-S12,S12>0,AL12/S12)} -> 0 | AT12: =IF(AN12=0,0,AS12/AN12) -> 0 | AU12: =IF(AO12=0,0,AS12/AO12) -> 0 | AW12: =AS12*E12 -> 0
B13: 497823770 | C13: MR Р1874 корич | D13: Солнцезащитные очки | E13: =F13+G13+H13 -> 0 | I13: 169.89 | J13: =E13*I13 -> 0 | O13: =L13/7 -> 0 | P13: =S13/7 -> 0 | S13: =Q13+R13 -> 0 | V13: =T13+U13 -> 0 | Y13: =W13+X13 -> 0 | Z13: =L13*M13*N13/100 -> 0 | AA13: =Y13/$Y$93 -> #DIV/0! | AB13: =S13*I13 -> 0 | AD13: =IF(Y13=0,0,AC13/Y13) -> 0 | AI13: =IFERROR($AI$93*H13/$H$93,0) -> 0 | AK13: =V13*1% -> 0 | AL13: =Y13-AB13-AC13-AE13-AF13-AG13-AH13-AI13-AK13-AJ13 -> 0 | AN13: =IF(S13=0,0,Y13/S13) -> 0 | AO13: =I13 -> 169.89 | AP13: =IF(S13=0,0,AC13/S13) -> 0 | AQ13: =IF(Q13=0,AE13/1,AE13/Q13) -> 0 | AR13: =IF(Q13=0,0,(AF13+AG13)/Q13) -> 0 | AS13: {=_xlfn.IFS(S13=0,AL13,S13<0,AL13/-S13,S13>0,AL13/S13)} -> 0 | AT13: =IF(AN13=0,0,AS13/AN13) -> 0 | AU13: =IF(AO13=0,0,AS13/AO13) -> 0 | AW13: =AS13*E13 -> 0
B14: 497824253 | C14: MR Р1886 черн | D14: Солнцезащитные очки | E14: =F14+G14+H14 -> 0 | I14: 169.89 | J14: =E14*I14 -> 0 | O14: =L14/7 -> 0 | P14: =S14/7 -> 0 | S14: =Q14+R14 -> 0 | V14: =T14+U14 -> 0 | Y14: =W14+X14 -> 0 | Z14: =L14*M14*N14/100 -> 0 | AA14: =Y14/$Y$93 -> #DIV/0! | AB14: =S14*I14 -> 0 | AD14: =IF(Y14=0,0,AC14/Y14) -> 0 | AI14: =IFERROR($AI$93*H14/$H$93,0) -> 0 | AK14: =V14*1% -> 0 | AL14: =Y14-AB14-AC14-AE14-AF14-AG14-AH14-AI14-AK14-AJ14 -> 0 | AN14: =IF(S14=0,0,Y14/S14) -> 0 | AO14: =I14 -> 169.89 | AP14: =IF(S14=0,0,AC14/S14) -> 0 | AQ14: =IF(Q14=0,AE14/1,AE14/Q14) -> 0 | AR14: =IF(Q14=0,0,(AF14+AG14)/Q14) -> 0 | AS14: {=_xlfn.IFS(S14=0,AL14,S14<0,AL14/-S14,S14>0,AL14/S14)} -> 0 | AT14: =IF(AN14=0,0,AS14/AN14) -> 0 | AU14: =IF(AO14=0,0,AS14/AO14) -> 0 | AW14: =AS14*E14 -> 0
B15: 497824944 | C15: MR Р1886 корич | D15: Солнцезащитные очки | E15: =F15+G15+H15 -> 0 | I15: 169.89 | J15: =E15*I15 -> 0 | O15: =L15/7 -> 0 | P15: =S15/7 -> 0 | S15: =Q15+R15 -> 0 | V15: =T15+U15 -> 0 | Y15: =W15+X15 -> 0 | Z15: =L15*M15*N15/100 -> 0 | AA15: =Y15/$Y$93 -> #DIV/0! | AB15: =S15*I15 -> 0 | AD15: =IF(Y15=0,0,AC15/Y15) -> 0 | AI15: =IFERROR($AI$93*H15/$H$93,0) -> 0 | AK15: =V15*1% -> 0 | AL15: =Y15-AB15-AC15-AE15-AF15-AG15-AH15-AI15-AK15-AJ15 -> 0 | AN15: =IF(S15=0,0,Y15/S15) -> 0 | AO15: =I15 -> 169.89 | AP15: =IF(S15=0,0,AC15/S15) -> 0 | AQ15: =IF(Q15=0,AE15/1,AE15/Q15) -> 0 | AR15: =IF(Q15=0,0,(AF15+AG15)/Q15) -> 0 | AS15: {=_xlfn.IFS(S15=0,AL15,S15<0,AL15/-S15,S15>0,AL15/S15)} -> 0 | AT15: =IF(AN15=0,0,AS15/AN15) -> 0 | AU15: =IF(AO15=0,0,AS15/AO15) -> 0 | AW15: =AS15*E15 -> 0
... B34: 804691336 | C34: 6008 | D34: Солнцезащитные очки | E34: =F34+G34+H34 -> 0 | I34: 178.89 | J34: =E34*I34 -> 0 | O34: =L34/7 -> 0 | P34: =S34/7 -> 0 | S34: =Q34+R34 -> 0 | V34: =T34+U34 -> 0 | Y34: =W34+X34 -> 0 | Z34: =L34*M34*N34/100 -> 0 | AA34: =Y34/$Y$93 -> #DIV/0! | AB34: =S34*I34 -> 0 | AD34: =IF(Y34=0,0,AC34/Y34) -> 0 | AI34: =IFERROR($AI$93*H34/$H$93,0) -> 0 | AK34: =V34*1% -> 0 | AL34: =Y34-AB34-AC34-AE34-AF34-AG34-AH34-AI34-AK34-AJ34 -> 0 | AN34: =IF(S34=0,0,Y34/S34) -> 0 | AO34: =I34 -> 178.89 | AP34: =IF(S34=0,0,AC34/S34) -> 0 | AQ34: =IF(Q34=0,AE34/1,AE34/Q34) -> 0 | AR34: =IF(Q34=0,0,(AF34+AG34)/Q34) -> 0 | AS34: {=_xlfn.IFS(S34=0,AL34,S34<0,AL34/-S34,S34>0,AL34/S34)} -> 0 | AT34: =IF(AN34=0,0,AS34/AN34) -> 0 | AU34: =IF(AO34=0,0,AS34/AO34) -> 0 | AW34: =AS34*E34 -> 0
AN35: =AVERAGE(AN3:AN6) -> 0 | AO35: =AVERAGE(AO3:AO6) -> 128.0625 | AP35: =AVERAGE(AP3:AP6) -> 0 | AQ35: =AVERAGE(AQ3:AQ6) -> 0 | AR35: =AVERAGE(AR3:AR6) -> 0 | AS35: =AVERAGE(AS3:AS6) -> 0 | AT35: =AVERAGE(AT3:AT6) -> 0 | AU35: =AVERAGE(AU3:AU6) -> 0
A36: Итого очки | E36: =SUM(E3:E34) -> 0 | F36: =SUM(F3:F34) -> 0 | G36: =SUM(G3:G34) -> 0 | H36: =SUM(H3:H34) -> 0 | J36: =SUM(J3:J34) -> 0 | L36: =SUM(L3:L34) -> 0 | Q36: =SUM(Q3:Q34) -> 0 | R36: =SUM(R3:R34) -> 0 | S36: =SUM(S3:S34) -> 0 | T36: =SUM(T3:T34) -> 0 | U36: =SUM(U3:U34) -> 0 | V36: =SUM(V3:V34) -> 0 | W36: =SUM(W3:W34) -> 0 | X36: =SUM(X3:X34) -> 0 | ... AC36: =SUM(AC3:AC34) -> 0 | AD36: =AC36/Y36 -> #DIV/0! | AE36: =SUM(AE3:AE34) -> 0 | AF36: =SUM(AF3:AF34) -> 0 | AG36: =SUM(AG3:AG34) -> 0 | AH36: =SUM(AH3:AH34) -> 0 | AI36: =SUM(AI3:AI34) -> 0 | AJ36: =SUM(AJ3:AJ34) -> 0 | AK36: =SUM(AK3:AK34) -> 0 | AL36: =SUM(AL3:AL34) -> 0 | AR36: =(AF36+AG36)/Q36 -> #DIV/0! | AW36: =SUM(AW3:AW6) -> 0
E38: =SUM(F38:H38) -> 0 | J38: =E38*I38 -> 0 | O38: =L38/7 -> 0 | P38: =S38/7 -> 0 | S38: =Q38+R38 -> 0 | V38: =T38+U38 -> 0 | Y38: =W38+X38 -> 0 | Z38: =L38*M38*N38/100 -> 0 | AA38: =Y38/$Y$93 -> #DIV/0! | AB38: =S38*I38 -> 0 | AD38: =IF(Y38=0,0,AC38/Y38) -> 0 | AI38: =$AI$93*H38/$H$93 -> #DIV/0! | AK38: =V38*1% -> 0 | AL38: =Y38-AB38-AC38-AE38-AF38-AG38-AH38-AI38-AK38-AJ38 -> #DIV/0! | AN38: =IF(S38=0,0,Y38/S38) -> 0 | AO38: =I38 -> 0 | AP38: =IF(S38=0,0,AC38/S38) -> 0 | AQ38: =IF(Q38=0,AE38/1,AE38/Q38) -> 0 | AR38: =IF(Q38=0,0,(AF38+AG38)/Q38) -> 0 | AS38: {=_xlfn.IFS(S38=0,AL38,S38<0,AL38/-S38,S38>0,AL38/S38)} -> #DIV/0! | AT38: =IF(AN38=0,0,AS38/AN38) -> 0 | AU38: =IF(AO38=0,0,AS38/AO38) -> 0 | AW38: =AS38*E38 -> #DIV/0!
E39: =SUM(F39:H39) -> 0 | J39: =E39*I39 -> 0 | O39: =L39/7 -> 0 | P39: =S39/7 -> 0 | S39: =Q39+R39 -> 0 | V39: =T39+U39 -> 0 | Y39: =W39+X39 -> 0 | Z39: =L39*M39*N39/100 -> 0 | AA39: =Y39/$Y$93 -> #DIV/0! | AB39: =S39*I39 -> 0 | AD39: =IF(Y39=0,0,AC39/Y39) -> 0 | AI39: =$AI$93*H39/$H$93 -> #DIV/0! | AK39: =V39*1% -> 0 | AL39: =Y39-AB39-AC39-AE39-AF39-AG39-AH39-AI39-AK39-AJ39 -> #DIV/0! | AN39: =IF(S39=0,0,Y39/S39) -> 0 | AO39: =I39 -> 0 | AP39: =IF(S39=0,0,AC39/S39) -> 0 | AQ39: =IF(Q39=0,AE39/1,AE39/Q39) -> 0 | AR39: =IF(Q39=0,0,(AF39+AG39)/Q39) -> 0 | AS39: {=_xlfn.IFS(S39=0,AL39,S39<0,AL39/-S39,S39>0,AL39/S39)} -> #DIV/0! | AT39: =IF(AN39=0,0,AS39/AN39) -> 0 | AU39: =IF(AO39=0,0,AS39/AO39) -> 0 | AW39: =AS39*E39 -> #DIV/0!
E40: =SUM(F40:H40) -> 0 | J40: =E40*I40 -> 0 | O40: =L40/7 -> 0 | P40: =S40/7 -> 0 | S40: =Q40+R40 -> 0 | V40: =T40+U40 -> 0 | Y40: =W40+X40 -> 0 | Z40: =L40*M40*N40/100 -> 0 | AA40: =Y40/$Y$93 -> #DIV/0! | AB40: =S40*I40 -> 0 | AD40: =IF(Y40=0,0,AC40/Y40) -> 0 | AI40: =$AI$93*H40/$H$93 -> #DIV/0! | AK40: =V40*1% -> 0 | AL40: =Y40-AB40-AC40-AE40-AF40-AG40-AH40-AI40-AK40-AJ40 -> #DIV/0! | AN40: =IF(S40=0,0,Y40/S40) -> 0 | AO40: =I40 -> 0 | AP40: =IF(S40=0,0,AC40/S40) -> 0 | AQ40: =IF(Q40=0,AE40/1,AE40/Q40) -> 0 | AR40: =IF(Q40=0,0,(AF40+AG40)/Q40) -> 0 | AS40: {=_xlfn.IFS(S40=0,AL40,S40<0,AL40/-S40,S40>0,AL40/S40)} -> #DIV/0! | AT40: =IF(AN40=0,0,AS40/AN40) -> 0 | AU40: =IF(AO40=0,0,AS40/AO40) -> 0 | AW40: =AS40*E40 -> #DIV/0!
E41: =SUM(F41:H41) -> 0 | J41: =E41*I41 -> 0 | O41: =L41/7 -> 0 | P41: =S41/7 -> 0 | S41: =Q41+R41 -> 0 | V41: =T41+U41 -> 0 | Y41: =W41+X41 -> 0 | Z41: =L41*M41*N41/100 -> 0 | AA41: =Y41/$Y$93 -> #DIV/0! | AB41: =S41*I41 -> 0 | AD41: =IF(Y41=0,0,AC41/Y41) -> 0 | AI41: =$AI$93*H41/$H$93 -> #DIV/0! | AK41: =V41*1% -> 0 | AL41: =Y41-AB41-AC41-AE41-AF41-AG41-AH41-AI41-AK41-AJ41 -> #DIV/0! | AN41: =IF(S41=0,0,Y41/S41) -> 0 | AO41: =I41 -> 0 | AP41: =IF(S41=0,0,AC41/S41) -> 0 | AQ41: =IF(Q41=0,AE41/1,AE41/Q41) -> 0 | AR41: =IF(Q41=0,0,(AF41+AG41)/Q41) -> 0 | AS41: {=_xlfn.IFS(S41=0,AL41,S41<0,AL41/-S41,S41>0,AL41/S41)} -> #DIV/0! | AT41: =IF(AN41=0,0,AS41/AN41) -> 0 | AU41: =IF(AO41=0,0,AS41/AO41) -> 0 | AW41: =AS41*E41 -> #DIV/0!
E42: =SUM(F42:H42) -> 0 | J42: =E42*I42 -> 0 | O42: =L42/7 -> 0 | P42: =S42/7 -> 0 | S42: =Q42+R42 -> 0 | V42: =T42+U42 -> 0 | Y42: =W42+X42 -> 0 | Z42: =L42*M42*N42/100 -> 0 | AA42: =Y42/$Y$93 -> #DIV/0! | AB42: =S42*I42 -> 0 | AD42: =IF(Y42=0,0,AC42/Y42) -> 0 | AI42: =$AI$93*H42/$H$93 -> #DIV/0! | AK42: =V42*1% -> 0 | AL42: =Y42-AB42-AC42-AE42-AF42-AG42-AH42-AI42-AK42-AJ42 -> #DIV/0! | AN42: =IF(S42=0,0,Y42/S42) -> 0 | AO42: =I42 -> 0 | AP42: =IF(S42=0,0,AC42/S42) -> 0 | AQ42: =IF(Q42=0,AE42/1,AE42/Q42) -> 0 | AR42: =IF(Q42=0,0,(AF42+AG42)/Q42) -> 0 | AS42: {=_xlfn.IFS(S42=0,AL42,S42<0,AL42/-S42,S42>0,AL42/S42)} -> #DIV/0! | AT42: =IF(AN42=0,0,AS42/AN42) -> 0 | AU42: =IF(AO42=0,0,AS42/AO42) -> 0 | AW42: =AS42*E42 -> #DIV/0!
E43: =SUM(F43:H43) -> 0 | J43: =E43*I43 -> 0 | O43: =L43/7 -> 0 | P43: =S43/7 -> 0 | S43: =Q43+R43 -> 0 | V43: =T43+U43 -> 0 | Y43: =W43+X43 -> 0 | Z43: =L43*M43*N43/100 -> 0 | AA43: =Y43/$Y$93 -> #DIV/0! | AB43: =S43*I43 -> 0 | AD43: =IF(Y43=0,0,AC43/Y43) -> 0 | AI43: =$AI$93*H43/$H$93 -> #DIV/0! | AK43: =V43*1% -> 0 | AL43: =Y43-AB43-AC43-AE43-AF43-AG43-AH43-AI43-AK43-AJ43 -> #DIV/0! | AN43: =IF(S43=0,0,Y43/S43) -> 0 | AO43: =I43 -> 0 | AP43: =IF(S43=0,0,AC43/S43) -> 0 | AQ43: =IF(Q43=0,AE43/1,AE43/Q43) -> 0 | AR43: =IF(Q43=0,0,(AF43+AG43)/Q43) -> 0 | AS43: {=_xlfn.IFS(S43=0,AL43,S43<0,AL43/-S43,S43>0,AL43/S43)} -> #DIV/0! | AT43: =IF(AN43=0,0,AS43/AN43) -> 0 | AU43: =IF(AO43=0,0,AS43/AO43) -> 0 | AW43: =AS43*E43 -> #DIV/0!
E44: =SUM(F44:H44) -> 0 | J44: =E44*I44 -> 0 | O44: =L44/7 -> 0 | P44: =S44/7 -> 0 | S44: =Q44+R44 -> 0 | V44: =T44+U44 -> 0 | Y44: =W44+X44 -> 0 | Z44: =L44*M44*N44/100 -> 0 | AA44: =Y44/$Y$93 -> #DIV/0! | AB44: =S44*I44 -> 0 | AD44: =IF(Y44=0,0,AC44/Y44) -> 0 | AI44: =$AI$93*H44/$H$93 -> #DIV/0! | AK44: =V44*1% -> 0 | AL44: =Y44-AB44-AC44-AE44-AF44-AG44-AH44-AI44-AK44-AJ44 -> #DIV/0! | AN44: =IF(S44=0,0,Y44/S44) -> 0 | AO44: =I44 -> 0 | AP44: =IF(S44=0,0,AC44/S44) -> 0 | AQ44: =IF(Q44=0,AE44/1,AE44/Q44) -> 0 | AR44: =IF(Q44=0,0,(AF44+AG44)/Q44) -> 0 | AS44: {=_xlfn.IFS(S44=0,AL44,S44<0,AL44/-S44,S44>0,AL44/S44)} -> #DIV/0! | AT44: =IF(AN44=0,0,AS44/AN44) -> 0 | AU44: =IF(AO44=0,0,AS44/AO44) -> 0 | AW44: =AS44*E44 -> #DIV/0!
E45: =SUM(F45:H45) -> 0 | J45: =E45*I45 -> 0 | O45: =L45/7 -> 0 | P45: =S45/7 -> 0 | S45: =Q45+R45 -> 0 | V45: =T45+U45 -> 0 | Y45: =W45+X45 -> 0 | Z45: =L45*M45*N45/100 -> 0 | AA45: =Y45/$Y$93 -> #DIV/0! | AB45: =S45*I45 -> 0 | AD45: =IF(Y45=0,0,AC45/Y45) -> 0 | AI45: =$AI$93*H45/$H$93 -> #DIV/0! | AK45: =V45*1% -> 0 | AL45: =Y45-AB45-AC45-AE45-AF45-AG45-AH45-AI45-AK45-AJ45 -> #DIV/0! | AN45: =IF(S45=0,0,Y45/S45) -> 0 | AO45: =I45 -> 0 | AP45: =IF(S45=0,0,AC45/S45) -> 0 | AQ45: =IF(Q45=0,AE45/1,AE45/Q45) -> 0 | AR45: =IF(Q45=0,0,(AF45+AG45)/Q45) -> 0 | AS45: {=_xlfn.IFS(S45=0,AL45,S45<0,AL45/-S45,S45>0,AL45/S45)} -> #DIV/0! | AT45: =IF(AN45=0,0,AS45/AN45) -> 0 | AU45: =IF(AO45=0,0,AS45/AO45) -> 0 | AW45: =AS45*E45 -> #DIV/0!
E46: =SUM(F46:H46) -> 0 | J46: =E46*I46 -> 0 | O46: =L46/7 -> 0 | P46: =S46/7 -> 0 | S46: =Q46+R46 -> 0 | V46: =T46+U46 -> 0 | Y46: =W46+X46 -> 0 | Z46: =L46*M46*N46/100 -> 0 | AA46: =Y46/$Y$93 -> #DIV/0! | AB46: =S46*I46 -> 0 | AD46: =IF(Y46=0,0,AC46/Y46) -> 0 | AI46: =$AI$93*H46/$H$93 -> #DIV/0! | AK46: =V46*1% -> 0 | AL46: =Y46-AB46-AC46-AE46-AF46-AG46-AH46-AI46-AK46-AJ46 -> #DIV/0! | AN46: =IF(S46=0,0,Y46/S46) -> 0 | AO46: =I46 -> 0 | AP46: =IF(S46=0,0,AC46/S46) -> 0 | AQ46: =IF(Q46=0,AE46/1,AE46/Q46) -> 0 | AR46: =IF(Q46=0,0,(AF46+AG46)/Q46) -> 0 | AS46: {=_xlfn.IFS(S46=0,AL46,S46<0,AL46/-S46,S46>0,AL46/S46)} -> #DIV/0! | AT46: =IF(AN46=0,0,AS46/AN46) -> 0 | AU46: =IF(AO46=0,0,AS46/AO46) -> 0 | AW46: =AS46*E46 -> #DIV/0!
E47: =SUM(F47:H47) -> 0 | J47: =E47*I47 -> 0 | O47: =L47/7 -> 0 | P47: =S47/7 -> 0 | S47: =Q47+R47 -> 0 | V47: =T47+U47 -> 0 | Y47: =W47+X47 -> 0 | Z47: =L47*M47*N47/100 -> 0 | AA47: =Y47/$Y$93 -> #DIV/0! | AB47: =S47*I47 -> 0 | AD47: =IF(Y47=0,0,AC47/Y47) -> 0 | AI47: =$AI$93*H47/$H$93 -> #DIV/0! | AK47: =V47*1% -> 0 | AL47: =Y47-AB47-AC47-AE47-AF47-AG47-AH47-AI47-AK47-AJ47 -> #DIV/0! | AN47: =IF(S47=0,0,Y47/S47) -> 0 | AO47: =I47 -> 0 | AP47: =IF(S47=0,0,AC47/S47) -> 0 | AQ47: =IF(Q47=0,AE47/1,AE47/Q47) -> 0 | AR47: =IF(Q47=0,0,(AF47+AG47)/Q47) -> 0 | AS47: {=_xlfn.IFS(S47=0,AL47,S47<0,AL47/-S47,S47>0,AL47/S47)} -> #DIV/0! | AT47: =IF(AN47=0,0,AS47/AN47) -> 0 | AU47: =IF(AO47=0,0,AS47/AO47) -> 0 | AW47: =AS47*E47 -> #DIV/0!
E48: =SUM(F48:H48) -> 0 | J48: =E48*I48 -> 0 | O48: =L48/7 -> 0 | P48: =S48/7 -> 0 | S48: =Q48+R48 -> 0 | V48: =T48+U48 -> 0 | Y48: =W48+X48 -> 0 | Z48: =L48*M48*N48/100 -> 0 | AA48: =Y48/$Y$93 -> #DIV/0! | AB48: =S48*I48 -> 0 | AD48: =IF(Y48=0,0,AC48/Y48) -> 0 | AI48: =$AI$93*H48/$H$93 -> #DIV/0! | AK48: =V48*1% -> 0 | AL48: =Y48-AB48-AC48-AE48-AF48-AG48-AH48-AI48-AK48-AJ48 -> #DIV/0! | AN48: =IF(S48=0,0,Y48/S48) -> 0 | AO48: =I48 -> 0 | AP48: =IF(S48=0,0,AC48/S48) -> 0 | AQ48: =IF(Q48=0,AE48/1,AE48/Q48) -> 0 | AR48: =IF(Q48=0,0,(AF48+AG48)/Q48) -> 0 | AS48: {=_xlfn.IFS(S48=0,AL48,S48<0,AL48/-S48,S48>0,AL48/S48)} -> #DIV/0! | AT48: =IF(AN48=0,0,AS48/AN48) -> 0 | AU48: =IF(AO48=0,0,AS48/AO48) -> 0 | AW48: =AS48*E48 -> #DIV/0!
E49: =SUM(F49:H49) -> 0 | J49: =E49*I49 -> 0 | O49: =L49/7 -> 0 | P49: =S49/7 -> 0 | S49: =Q49+R49 -> 0 | V49: =T49+U49 -> 0 | Y49: =W49+X49 -> 0 | Z49: =L49*M49*N49/100 -> 0 | AA49: =Y49/$Y$93 -> #DIV/0! | AB49: =S49*I49 -> 0 | AD49: =IF(Y49=0,0,AC49/Y49) -> 0 | AI49: =$AI$93*H49/$H$93 -> #DIV/0! | AK49: =V49*1% -> 0 | AL49: =Y49-AB49-AC49-AE49-AF49-AG49-AH49-AI49-AK49-AJ49 -> #DIV/0! | AN49: =IF(S49=0,0,Y49/S49) -> 0 | AO49: =I49 -> 0 | AP49: =IF(S49=0,0,AC49/S49) -> 0 | AQ49: =IF(Q49=0,AE49/1,AE49/Q49) -> 0 | AR49: =IF(Q49=0,0,(AF49+AG49)/Q49) -> 0 | AS49: {=_xlfn.IFS(S49=0,AL49,S49<0,AL49/-S49,S49>0,AL49/S49)} -> #DIV/0! | AT49: =IF(AN49=0,0,AS49/AN49) -> 0 | AU49: =IF(AO49=0,0,AS49/AO49) -> 0 | AW49: =AS49*E49 -> #DIV/0!
... E89: =SUM(F89:H89) -> 0 | J89: =E89*I89 -> 0 | O89: =L89/7 -> 0 | P89: =S89/7 -> 0 | S89: =Q89+R89 -> 0 | V89: =T89+U89 -> 0 | Y89: =W89+X89 -> 0 | Z89: =L89*M89*N89/100 -> 0 | AA89: =Y89/$Y$93 -> #DIV/0! | AB89: =S89*I89 -> 0 | AD89: =IF(Y89=0,0,AC89/Y89) -> 0 | AI89: =$AI$93*H89/$H$93 -> #DIV/0! | AK89: =V89*1% -> 0 | AL89: =Y89-AB89-AC89-AE89-AF89-AG89-AH89-AI89-AK89-AJ89 -> #DIV/0! | AN89: =IF(S89=0,0,Y89/S89) -> 0 | AO89: =I89 -> 0 | AP89: =IF(S89=0,0,AC89/S89) -> 0 | AQ89: =IF(Q89=0,AE89/1,AE89/Q89) -> 0 | AR89: =IF(Q89=0,0,(AF89+AG89)/Q89) -> 0 | AS89: {=_xlfn.IFS(S89=0,AL89,S89<0,AL89/-S89,S89>0,AL89/S89)} -> #DIV/0! | AT89: =IF(AN89=0,0,AS89/AN89) -> 0 | AU89: =IF(AO89=0,0,AS89/AO89) -> 0 | AW89: =AS89*E89 -> #DIV/0!
AN90: =AVERAGE(AN38:AN89) -> 0 | AO90: =AVERAGE(AO38:AO89) -> 0 | AP90: =AVERAGE(AP38:AP89) -> 0 | AQ90: =AVERAGE(AQ38:AQ89) -> 0 | AR90: =AVERAGE(AR38:AR89) -> 0 | AS90: =AVERAGE(AS38:AS89) -> #DIV/0! | AT90: =AVERAGE(AT38:AT89) -> 0 | AU90: =AVERAGE(AU38:AU89) -> 0
A91: Итого ___ | E91: =SUM(E38:E89) -> 0 | F91: =SUM(F38:F89) -> 0 | G91: =SUM(G38:G89) -> 0 | H91: =SUM(H38:H89) -> 0 | J91: =SUM(J38:J89) -> 0 | L91: =SUM(L38:L89) -> 0 | Q91: =SUM(Q38:Q89) -> 0 | R91: =SUM(R38:R89) -> 0 | S91: =SUM(S38:S89) -> 0 | T91: =SUM(T38:T89) -> 0 | U91: =SUM(U38:U89) -> 0 | V91: =SUM(V38:V89) -> 0 | W91: =SUM(W38:W89) -> 0 | X91: =SUM(X38:X89) -> 0 | ... AC91: =SUM(AC38:AC89) -> 0 | AD91: =AC91/Y91 -> #DIV/0! | AE91: =SUM(AE38:AE89) -> 0 | AF91: =SUM(AF38:AF89) -> 0 | AG91: =SUM(AG38:AG89) -> 0 | AH91: =SUM(AH38:AH89) -> 0 | AI91: =SUM(AI38:AI89) -> #DIV/0! | AJ91: =SUM(AJ38:AJ89) -> 0 | AK91: =SUM(AK38:AK89) -> 0 | AL91: =SUM(AL38:AL89) -> #DIV/0! | AR91: =(AF91+AG91)/Q91 -> #DIV/0! | AW91: =SUM(AW38:AW89) -> #DIV/0!
A93: ИТОГО | E93: =E36+E91 -> 0 | F93: =F36+F91 -> 0 | G93: =G36+G91 -> 0 | H93: =H36+H91 -> 0 | I93: =I36+I91 -> 0 | J93: =J36+J91 -> 0 | K93: =K36+K91 -> 0 | L93: =L36+L91 -> 0 | ... AC93: =AC36+AC91 -> 0 | AD93: =AC93/Y93 -> #DIV/0! | AE93: =AE36+AE91 -> 0 | AF93: =AF36+AF91 -> 0 | AG93: =AG36+AG91 -> 0 | AH93: =AH36+AH91 -> 0 | AJ93: =AJ36+AJ91 -> 0 | AK93: =AK36+AK91 -> 0 | AL93: =AL36+AL91 -> #DIV/0! | AR93: =(AF93+AG93)/Q93 -> #DIV/0! | AW93: =AW36+AW91 -> #DIV/0!
AF94: =AF37+AF92 -> 0

Sheet Юнит 8
A1: 16-22.02_8 нед | F1: Отчет по остаткам 3,4,5 | K1: Цены и скидки 6 | L1: Воронка продаж 16,50,32 | AI1: Вставить в Итого | AN1: на 1 единицу проданного товара
A2: Бренд | B2: SKU | C2: Артикул поставщика | D2: Предмет | E2: Остаток на 23.02 | F2: В пути до клиента | G2: В пути от клиента | H2: Итого по складам ВБ | I2: Себетоимость на 1 ед на 29.09.25 | J2: Себестоимость остатков | K2: Оборачива-емость, дн | L2: Заказы, шт 7 дней | M2: Средняя цена, руб | N2: % выкупа за 7 дней | O2: Скорость заказов | P2: Скорость продаж | Q2: Кол-во ПРОДАЖИ | R2: Кол-во ВОЗВРАТЫ | S2: Кол-во ПРОДАЖИ-ВОЗВРАТЫ | T2: Выручка ВБ ПРОДАЖИ | U2: Выручка ВБ ВОЗВРАТЫ | V2: Выручка с учетом СПП ПРОДАЖИ - ВОЗВРАТЫ | W2: Выручка ПРОДАЖИ | X2: Выручка ВОЗВРАТЫ | Y2: Выручка с учетом согласованной скидки ПРОДАЖИ - ВОЗВРАТЫ | Z2: Выручка потенциальная | AA2: Доля выручки, % от общего объема | AB2: Себестоимость продаж | AC2: Комиссия, руб | AD2: Комиссия, % | AE2: Логистика | AF2: Реклама БАЛАНС | AG2: Реклама СЧЕТ | AH2: Блогеры | AI2: Хранение | AJ2: Штрафы | AK2: Налог 1% | AL2: Прибыль | AN2: Выручка на 1 ед (средняя цена продажи со скидкой) | AO2: Себестоимость на 1 ед | AP2: Комиссия на 1 ед | AQ2: Логистика на 1 ед | AR2: Реклама на 1 ед | AS2: Прибыль на 1 ед | AT2: Маржиналь-ность, % | AU2: Рентабель-ность, % | AW2: Прибыль с остатков
B3: 341479791 | C3: Черные с железкой Сул | D3: Солнцезащитные очки | E3: =F3+G3+H3 -> 0 | I3: 142.98 | J3: =E3*I3 -> 0 | O3: =L3/7 -> 0 | P3: =S3/7 -> 0 | S3: =Q3+R3 -> 0 | V3: =T3+U3 -> 0 | Y3: =W3+X3 -> 0 | Z3: =L3*M3*N3/100 -> 0 | AA3: =Y3/$Y$93 -> #DIV/0! | AB3: =S3*I3 -> 0 | AD3: =IF(Y3=0,0,AC3/Y3) -> 0 | AI3: =IFERROR($AI$93*H3/$H$93,0) -> 0 | AK3: =V3*1% -> 0 | AL3: =Y3-AB3-AC3-AE3-AF3-AG3-AH3-AI3-AK3-AJ3 -> 0 | AN3: =IF(S3=0,0,Y3/S3) -> 0 | AO3: =I3 -> 142.98 | AP3: =IF(S3=0,0,AC3/S3) -> 0 | AQ3: =IF(Q3=0,AE3/1,AE3/Q3) -> 0 | AR3: =IF(Q3=0,0,(AF3+AG3)/Q3) -> 0 | AS3: =_xlfn.IFS(S3=0,AL3,S3<0,AL3/-S3,S3>0,AL3/S3) -> 0 | AT3: =IF(AN3=0,0,AS3/AN3) -> 0 | AU3: =IF(AO3=0,0,AS3/AO3) -> 0 | AW3: =AS3*E3 -> 0
B4: 340343575 | C4: Qs черн Сул | D4: Солнцезащитные очки | E4: =F4+G4+H4 -> 0 | I4: 123.09 | J4: =E4*I4 -> 0 | O4: =L4/7 -> 0 | P4: =S4/7 -> 0 | S4: =Q4+R4 -> 0 | V4: =T4+U4 -> 0 | Y4: =W4+X4 -> 0 | Z4: =L4*M4*N4/100 -> 0 | AA4: =Y4/$Y$93 -> #DIV/0! | AB4: =S4*I4 -> 0 | AD4: =IF(Y4=0,0,AC4/Y4) -> 0 | AI4: =IFERROR($AI$93*H4/$H$93,0) -> 0 | AK4: =V4*1% -> 0 | AL4: =Y4-AB4-AC4-AE4-AF4-AG4-AH4-AI4-AK4-AJ4 -> 0 | AN4: =IF(S4=0,0,Y4/S4) -> 0 | AO4: =I4 -> 123.09 | AP4: =IF(S4=0,0,AC4/S4) -> 0 | AQ4: =IF(Q4=0,AE4/1,AE4/Q4) -> 0 | AR4: =IF(Q4=0,0,(AF4+AG4)/Q4) -> 0 | AS4: {=_xlfn.IFS(S4=0,AL4,S4<0,AL4/-S4,S4>0,AL4/S4)} -> 0 | AT4: =IF(AN4=0,0,AS4/AN4) -> 0 | AU4: =IF(AO4=0,0,AS4/AO4) -> 0 | AW4: =AS4*E4 -> 0
B5: 340332621 | C5: Qs син Сул | D5: Солнцезащитные очки | E5: =F5+G5+H5 -> 0 | I5: 123.09 | J5: =E5*I5 -> 0 | O5: =L5/7 -> 0 | P5: =S5/7 -> 0 | S5: =Q5+R5 -> 0 | V5: =T5+U5 -> 0 | Y5: =W5+X5 -> 0 | Z5: =L5*M5*N5/100 -> 0 | AA5: =Y5/$Y$93 -> #DIV/0! | AB5: =S5*I5 -> 0 | AD5: =IF(Y5=0,0,AC5/Y5) -> 0 | AI5: =IFERROR($AI$93*H5/$H$93,0) -> 0 | AK5: =V5*1% -> 0 | AL5: =Y5-AB5-AC5-AE5-AF5-AG5-AH5-AI5-AK5-AJ5 -> 0 | AN5: =IF(S5=0,0,Y5/S5) -> 0 | AO5: =I5 -> 123.09 | AP5: =IF(S5=0,0,AC5/S5) -> 0 | AQ5: =IF(Q5=0,AE5/1,AE5/Q5) -> 0 | AR5: =IF(Q5=0,0,(AF5+AG5)/Q5) -> 0 | AS5: {=_xlfn.IFS(S5=0,AL5,S5<0,AL5/-S5,S5>0,AL5/S5)} -> 0 | AT5: =IF(AN5=0,0,AS5/AN5) -> 0 | AU5: =IF(AO5=0,0,AS5/AO5) -> 0 | AW5: =AS5*E5 -> 0
B6: 340341838 | C6: Qs желт Сул | D6: Солнцезащитные очки | E6: =F6+G6+H6 -> 0 | I6: 123.09 | J6: =E6*I6 -> 0 | O6: =L6/7 -> 0 | P6: =S6/7 -> 0 | S6: =Q6+R6 -> 0 | V6: =T6+U6 -> 0 | Y6: =W6+X6 -> 0 | Z6: =L6*M6*N6/100 -> 0 | AA6: =Y6/$Y$93 -> #DIV/0! | AB6: =S6*I6 -> 0 | AD6: =IF(Y6=0,0,AC6/Y6) -> 0 | AI6: =IFERROR($AI$93*H6/$H$93,0) -> 0 | AK6: =V6*1% -> 0 | AL6: =Y6-AB6-AC6-AE6-AF6-AG6-AH6-AI6-AK6-AJ6 -> 0 | AN6: =IF(S6=0,0,Y6/S6) -> 0 | AO6: =I6 -> 123.09 | AP6: =IF(S6=0,0,AC6/S6) -> 0 | AQ6: =IF(Q6=0,AE6/1,AE6/Q6) -> 0 | AR6: =IF(Q6=0,0,(AF6+AG6)/Q6) -> 0 | AS6: {=_xlfn.IFS(S6=0,AL6,S6<0,AL6/-S6,S6>0,AL6/S6)} -> 0 | AT6: =IF(AN6=0,0,AS6/AN6) -> 0 | AU6: =IF(AO6=0,0,AS6/AO6) -> 0 | AW6: =AS6*E6 -> 0
B7: 445291724 | C7: flip черные Сул | D7: Солнцезащитные очки | E7: =F7+G7+H7 -> 0 | I7: 123.09 | J7: =E7*I7 -> 0 | O7: =L7/7 -> 0 | P7: =S7/7 -> 0 | S7: =Q7+R7 -> 0 | V7: =T7+U7 -> 0 | Y7: =W7+X7 -> 0 | Z7: =L7*M7*N7/100 -> 0 | AA7: =Y7/$Y$93 -> #DIV/0! | AB7: =S7*I7 -> 0 | AD7: =IF(Y7=0,0,AC7/Y7) -> 0 | AI7: =IFERROR($AI$93*H7/$H$93,0) -> 0 | AK7: =V7*1% -> 0 | AL7: =Y7-AB7-AC7-AE7-AF7-AG7-AH7-AI7-AK7-AJ7 -> 0 | AN7: =IF(S7=0,0,Y7/S7) -> 0 | AO7: =I7 -> 123.09 | AP7: =IF(S7=0,0,AC7/S7) -> 0 | AQ7: =IF(Q7=0,AE7/1,AE7/Q7) -> 0 | AR7: =IF(Q7=0,0,(AF7+AG7)/Q7) -> 0 | AS7: {=_xlfn.IFS(S7=0,AL7,S7<0,AL7/-S7,S7>0,AL7/S7)} -> 0 | AT7: =IF(AN7=0,0,AS7/AN7) -> 0 | AU7: =IF(AO7=0,0,AS7/AO7) -> 0 | AW7: =AS7*E7 -> 0
B8: 445336740 | C8: flip желтые Сул | D8: Солнцезащитные очки | E8: =F8+G8+H8 -> 0 | I8: 123.09 | J8: =E8*I8 -> 0 | O8: =L8/7 -> 0 | P8: =S8/7 -> 0 | S8: =Q8+R8 -> 0 | V8: =T8+U8 -> 0 | Y8: =W8+X8 -> 0 | Z8: =L8*M8*N8/100 -> 0 | AA8: =Y8/$Y$93 -> #DIV/0! | AB8: =S8*I8 -> 0 | AD8: =IF(Y8=0,0,AC8/Y8) -> 0 | AI8: =IFERROR($AI$93*H8/$H$93,0) -> 0 | AK8: =V8*1% -> 0 | AL8: =Y8-AB8-AC8-AE8-AF8-AG8-AH8-AI8-AK8-AJ8 -> 0 | AN8: =IF(S8=0,0,Y8/S8) -> 0 | AO8: =I8 -> 123.09 | AP8: =IF(S8=0,0,AC8/S8) -> 0 | AQ8: =IF(Q8=0,AE8/1,AE8/Q8) -> 0 | AR8: =IF(Q8=0,0,(AF8+AG8)/Q8) -> 0 | AS8: {=_xlfn.IFS(S8=0,AL8,S8<0,AL8/-S8,S8>0,AL8/S8)} -> 0 | AT8: =IF(AN8=0,0,AS8/AN8) -> 0 | AU8: =IF(AO8=0,0,AS8/AO8) -> 0 | AW8: =AS8*E8 -> 0
B9: 445341507 | C9: MR8854 C2 Сул | D9: Солнцезащитные очки | E9: =F9+G9+H9 -> 0 | I9: 169.89 | J9: =E9*I9 -> 0 | O9: =L9/7 -> 0 | P9: =S9/7 -> 0 | S9: =Q9+R9 -> 0 | V9: =T9+U9 -> 0 | Y9: =W9+X9 -> 0 | Z9: =L9*M9*N9/100 -> 0 | AA9: =Y9/$Y$93 -> #DIV/0! | AB9: =S9*I9 -> 0 | AD9: =IF(Y9=0,0,AC9/Y9) -> 0 | AI9: =IFERROR($AI$93*H9/$H$93,0) -> 0 | AK9: =V9*1% -> 0 | AL9: =Y9-AB9-AC9-AE9-AF9-AG9-AH9-AI9-AK9-AJ9 -> 0 | AN9: =IF(S9=0,0,Y9/S9) -> 0 | AO9: =I9 -> 169.89 | AP9: =IF(S9=0,0,AC9/S9) -> 0 | AQ9: =IF(Q9=0,AE9/1,AE9/Q9) -> 0 | AR9: =IF(Q9=0,0,(AF9+AG9)/Q9) -> 0 | AS9: {=_xlfn.IFS(S9=0,AL9,S9<0,AL9/-S9,S9>0,AL9/S9)} -> 0 | AT9: =IF(AN9=0,0,AS9/AN9) -> 0 | AU9: =IF(AO9=0,0,AS9/AO9) -> 0 | AW9: =AS9*E9 -> 0
B10: 497825485 | C10: MR 1819 черн | D10: Солнцезащитные очки | E10: =F10+G10+H10 -> 0 | I10: 169.89 | J10: =E10*I10 -> 0 | O10: =L10/7 -> 0 | P10: =S10/7 -> 0 | S10: =Q10+R10 -> 0 | V10: =T10+U10 -> 0 | Y10: =W10+X10 -> 0 | Z10: =L10*M10*N10/100 -> 0 | AA10: =Y10/$Y$93 -> #DIV/0! | AB10: =S10*I10 -> 0 | AD10: =IF(Y10=0,0,AC10/Y10) -> 0 | AI10: =IFERROR($AI$93*H10/$H$93,0) -> 0 | AK10: =V10*1% -> 0 | AL10: =Y10-AB10-AC10-AE10-AF10-AG10-AH10-AI10-AK10-AJ10 -> 0 | AN10: =IF(S10=0,0,Y10/S10) -> 0 | AO10: =I10 -> 169.89 | AP10: =IF(S10=0,0,AC10/S10) -> 0 | AQ10: =IF(Q10=0,AE10/1,AE10/Q10) -> 0 | AR10: =IF(Q10=0,0,(AF10+AG10)/Q10) -> 0 | AS10: {=_xlfn.IFS(S10=0,AL10,S10<0,AL10/-S10,S10>0,AL10/S10)} -> 0 | AT10: =IF(AN10=0,0,AS10/AN10) -> 0 | AU10: =IF(AO10=0,0,AS10/AO10) -> 0 | AW10: =AS10*E10 -> 0
B11: 497825962 | C11: MR 1819 корич | D11: Солнцезащитные очки | E11: =F11+G11+H11 -> 0 | I11: 169.89 | J11: =E11*I11 -> 0 | O11: =L11/7 -> 0 | P11: =S11/7 -> 0 | S11: =Q11+R11 -> 0 | V11: =T11+U11 -> 0 | Y11: =W11+X11 -> 0 | Z11: =L11*M11*N11/100 -> 0 | AA11: =Y11/$Y$93 -> #DIV/0! | AB11: =S11*I11 -> 0 | AD11: =IF(Y11=0,0,AC11/Y11) -> 0 | AI11: =IFERROR($AI$93*H11/$H$93,0) -> 0 | AK11: =V11*1% -> 0 | AL11: =Y11-AB11-AC11-AE11-AF11-AG11-AH11-AI11-AK11-AJ11 -> 0 | AN11: =IF(S11=0,0,Y11/S11) -> 0 | AO11: =I11 -> 169.89 | AP11: =IF(S11=0,0,AC11/S11) -> 0 | AQ11: =IF(Q11=0,AE11/1,AE11/Q11) -> 0 | AR11: =IF(Q11=0,0,(AF11+AG11)/Q11) -> 0 | AS11: {=_xlfn.IFS(S11=0,AL11,S11<0,AL11/-S11,S11>0,AL11/S11)} -> 0 | AT11: =IF(AN11=0,0,AS11/AN11) -> 0 | AU11: =IF(AO11=0,0,AS11/AO11) -> 0 | AW11: =AS11*E11 -> 0
B12: 497821775 | C12: MR Р1874 черн | D12: Солнцезащитные очки | E12: =F12+G12+H12 -> 0 | I12: 169.89 | J12: =E12*I12 -> 0 | O12: =L12/7 -> 0 | P12: =S12/7 -> 0 | S12: =Q12+R12 -> 0 | V12: =T12+U12 -> 0 | Y12: =W12+X12 -> 0 | Z12: =L12*M12*N12/100 -> 0 | AA12: =Y12/$Y$93 -> #DIV/0! | AB12: =S12*I12 -> 0 | AD12: =IF(Y12=0,0,AC12/Y12) -> 0 | AI12: =IFERROR($AI$93*H12/$H$93,0) -> 0 | AK12: =V12*1% -> 0 | AL12: =Y12-AB12-AC12-AE12-AF12-AG12-AH12-AI12-AK12-AJ12 -> 0 | AN12: =IF(S12=0,0,Y12/S12) -> 0 | AO12: =I12 -> 169.89 | AP12: =IF(S12=0,0,AC12/S12) -> 0 | AQ12: =IF(Q12=0,AE12/1,AE12/Q12) -> 0 | AR12: =IF(Q12=0,0,(AF12+AG12)/Q12) -> 0 | AS12: {=_xlfn.IFS(S12=0,AL12,S12<0,AL12/-S12,S12>0,AL12/S12)} -> 0 | AT12: =IF(AN12=0,0,AS12/AN12) -> 0 | AU12: =IF(AO12=0,0,AS12/AO12) -> 0 | AW12: =AS12*E12 -> 0
B13: 497823770 | C13: MR Р1874 корич | D13: Солнцезащитные очки | E13: =F13+G13+H13 -> 0 | I13: 169.89 | J13: =E13*I13 -> 0 | O13: =L13/7 -> 0 | P13: =S13/7 -> 0 | S13: =Q13+R13 -> 0 | V13: =T13+U13 -> 0 | Y13: =W13+X13 -> 0 | Z13: =L13*M13*N13/100 -> 0 | AA13: =Y13/$Y$93 -> #DIV/0! | AB13: =S13*I13 -> 0 | AD13: =IF(Y13=0,0,AC13/Y13) -> 0 | AI13: =IFERROR($AI$93*H13/$H$93,0) -> 0 | AK13: =V13*1% -> 0 | AL13: =Y13-AB13-AC13-AE13-AF13-AG13-AH13-AI13-AK13-AJ13 -> 0 | AN13: =IF(S13=0,0,Y13/S13) -> 0 | AO13: =I13 -> 169.89 | AP13: =IF(S13=0,0,AC13/S13) -> 0 | AQ13: =IF(Q13=0,AE13/1,AE13/Q13) -> 0 | AR13: =IF(Q13=0,0,(AF13+AG13)/Q13) -> 0 | AS13: {=_xlfn.IFS(S13=0,AL13,S13<0,AL13/-S13,S13>0,AL13/S13)} -> 0 | AT13: =IF(AN13=0,0,AS13/AN13) -> 0 | AU13: =IF(AO13=0,0,AS13/AO13) -> 0 | AW13: =AS13*E13 -> 0
B14: 497824253 | C14: MR Р1886 черн | D14: Солнцезащитные очки | E14: =F14+G14+H14 -> 0 | I14: 169.89 | J14: =E14*I14 -> 0 | O14: =L14/7 -> 0 | P14: =S14/7 -> 0 | S14: =Q14+R14 -> 0 | V14: =T14+U14 -> 0 | Y14: =W14+X14 -> 0 | Z14: =L14*M14*N14/100 -> 0 | AA14: =Y14/$Y$93 -> #DIV/0! | AB14: =S14*I14 -> 0 | AD14: =IF(Y14=0,0,AC14/Y14) -> 0 | AI14: =IFERROR($AI$93*H14/$H$93,0) -> 0 | AK14: =V14*1% -> 0 | AL14: =Y14-AB14-AC14-AE14-AF14-AG14-AH14-AI14-AK14-AJ14 -> 0 | AN14: =IF(S14=0,0,Y14/S14) -> 0 | AO14: =I14 -> 169.89 | AP14: =IF(S14=0,0,AC14/S14) -> 0 | AQ14: =IF(Q14=0,AE14/1,AE14/Q14) -> 0 | AR14: =IF(Q14=0,0,(AF14+AG14)/Q14) -> 0 | AS14: {=_xlfn.IFS(S14=0,AL14,S14<0,AL14/-S14,S14>0,AL14/S14)} -> 0 | AT14: =IF(AN14=0,0,AS14/AN14) -> 0 | AU14: =IF(AO14=0,0,AS14/AO14) -> 0 | AW14: =AS14*E14 -> 0
B15: 497824944 | C15: MR Р1886 корич | D15: Солнцезащитные очки | E15: =F15+G15+H15 -> 0 | I15: 169.89 | J15: =E15*I15 -> 0 | O15: =L15/7 -> 0 | P15: =S15/7 -> 0 | S15: =Q15+R15 -> 0 | V15: =T15+U15 -> 0 | Y15: =W15+X15 -> 0 | Z15: =L15*M15*N15/100 -> 0 | AA15: =Y15/$Y$93 -> #DIV/0! | AB15: =S15*I15 -> 0 | AD15: =IF(Y15=0,0,AC15/Y15) -> 0 | AI15: =IFERROR($AI$93*H15/$H$93,0) -> 0 | AK15: =V15*1% -> 0 | AL15: =Y15-AB15-AC15-AE15-AF15-AG15-AH15-AI15-AK15-AJ15 -> 0 | AN15: =IF(S15=0,0,Y15/S15) -> 0 | AO15: =I15 -> 169.89 | AP15: =IF(S15=0,0,AC15/S15) -> 0 | AQ15: =IF(Q15=0,AE15/1,AE15/Q15) -> 0 | AR15: =IF(Q15=0,0,(AF15+AG15)/Q15) -> 0 | AS15: {=_xlfn.IFS(S15=0,AL15,S15<0,AL15/-S15,S15>0,AL15/S15)} -> 0 | AT15: =IF(AN15=0,0,AS15/AN15) -> 0 | AU15: =IF(AO15=0,0,AS15/AO15) -> 0 | AW15: =AS15*E15 -> 0
... B34: 804691336 | C34: 6008 | D34: Солнцезащитные очки | E34: =F34+G34+H34 -> 0 | I34: 178.89 | J34: =E34*I34 -> 0 | O34: =L34/7 -> 0 | P34: =S34/7 -> 0 | S34: =Q34+R34 -> 0 | V34: =T34+U34 -> 0 | Y34: =W34+X34 -> 0 | Z34: =L34*M34*N34/100 -> 0 | AA34: =Y34/$Y$93 -> #DIV/0! | AB34: =S34*I34 -> 0 | AD34: =IF(Y34=0,0,AC34/Y34) -> 0 | AI34: =IFERROR($AI$93*H34/$H$93,0) -> 0 | AK34: =V34*1% -> 0 | AL34: =Y34-AB34-AC34-AE34-AF34-AG34-AH34-AI34-AK34-AJ34 -> 0 | AN34: =IF(S34=0,0,Y34/S34) -> 0 | AO34: =I34 -> 178.89 | AP34: =IF(S34=0,0,AC34/S34) -> 0 | AQ34: =IF(Q34=0,AE34/1,AE34/Q34) -> 0 | AR34: =IF(Q34=0,0,(AF34+AG34)/Q34) -> 0 | AS34: {=_xlfn.IFS(S34=0,AL34,S34<0,AL34/-S34,S34>0,AL34/S34)} -> 0 | AT34: =IF(AN34=0,0,AS34/AN34) -> 0 | AU34: =IF(AO34=0,0,AS34/AO34) -> 0 | AW34: =AS34*E34 -> 0
AN35: =AVERAGE(AN3:AN6) -> 0 | AO35: =AVERAGE(AO3:AO6) -> 128.0625 | AP35: =AVERAGE(AP3:AP6) -> 0 | AQ35: =AVERAGE(AQ3:AQ6) -> 0 | AR35: =AVERAGE(AR3:AR6) -> 0 | AS35: =AVERAGE(AS3:AS6) -> 0 | AT35: =AVERAGE(AT3:AT6) -> 0 | AU35: =AVERAGE(AU3:AU6) -> 0
A36: Итого очки | E36: =SUM(E3:E34) -> 0 | F36: =SUM(F3:F34) -> 0 | G36: =SUM(G3:G34) -> 0 | H36: =SUM(H3:H34) -> 0 | J36: =SUM(J3:J34) -> 0 | L36: =SUM(L3:L34) -> 0 | Q36: =SUM(Q3:Q34) -> 0 | R36: =SUM(R3:R34) -> 0 | S36: =SUM(S3:S34) -> 0 | T36: =SUM(T3:T34) -> 0 | U36: =SUM(U3:U34) -> 0 | V36: =SUM(V3:V34) -> 0 | W36: =SUM(W3:W34) -> 0 | X36: =SUM(X3:X34) -> 0 | ... AC36: =SUM(AC3:AC34) -> 0 | AD36: =AC36/Y36 -> #DIV/0! | AE36: =SUM(AE3:AE34) -> 0 | AF36: =SUM(AF3:AF34) -> 0 | AG36: =SUM(AG3:AG34) -> 0 | AH36: =SUM(AH3:AH34) -> 0 | AI36: =SUM(AI3:AI34) -> 0 | AJ36: =SUM(AJ3:AJ34) -> 0 | AK36: =SUM(AK3:AK34) -> 0 | AL36: =SUM(AL3:AL34) -> 0 | AR36: =(AF36+AG36)/Q36 -> #DIV/0! | AW36: =SUM(AW3:AW6) -> 0
E38: =SUM(F38:H38) -> 0 | J38: =E38*I38 -> 0 | O38: =L38/7 -> 0 | P38: =S38/7 -> 0 | S38: =Q38+R38 -> 0 | V38: =T38+U38 -> 0 | Y38: =W38+X38 -> 0 | Z38: =L38*M38*N38/100 -> 0 | AA38: =Y38/$Y$93 -> #DIV/0! | AB38: =S38*I38 -> 0 | AD38: =IF(Y38=0,0,AC38/Y38) -> 0 | AI38: =$AI$93*H38/$H$93 -> #DIV/0! | AK38: =V38*1% -> 0 | AL38: =Y38-AB38-AC38-AE38-AF38-AG38-AH38-AI38-AK38-AJ38 -> #DIV/0! | AN38: =IF(S38=0,0,Y38/S38) -> 0 | AO38: =I38 -> 0 | AP38: =IF(S38=0,0,AC38/S38) -> 0 | AQ38: =IF(Q38=0,AE38/1,AE38/Q38) -> 0 | AR38: =IF(Q38=0,0,(AF38+AG38)/Q38) -> 0 | AS38: {=_xlfn.IFS(S38=0,AL38,S38<0,AL38/-S38,S38>0,AL38/S38)} -> #DIV/0! | AT38: =IF(AN38=0,0,AS38/AN38) -> 0 | AU38: =IF(AO38=0,0,AS38/AO38) -> 0 | AW38: =AS38*E38 -> #DIV/0!
E39: =SUM(F39:H39) -> 0 | J39: =E39*I39 -> 0 | O39: =L39/7 -> 0 | P39: =S39/7 -> 0 | S39: =Q39+R39 -> 0 | V39: =T39+U39 -> 0 | Y39: =W39+X39 -> 0 | Z39: =L39*M39*N39/100 -> 0 | AA39: =Y39/$Y$93 -> #DIV/0! | AB39: =S39*I39 -> 0 | AD39: =IF(Y39=0,0,AC39/Y39) -> 0 | AI39: =$AI$93*H39/$H$93 -> #DIV/0! | AK39: =V39*1% -> 0 | AL39: =Y39-AB39-AC39-AE39-AF39-AG39-AH39-AI39-AK39-AJ39 -> #DIV/0! | AN39: =IF(S39=0,0,Y39/S39) -> 0 | AO39: =I39 -> 0 | AP39: =IF(S39=0,0,AC39/S39) -> 0 | AQ39: =IF(Q39=0,AE39/1,AE39/Q39) -> 0 | AR39: =IF(Q39=0,0,(AF39+AG39)/Q39) -> 0 | AS39: {=_xlfn.IFS(S39=0,AL39,S39<0,AL39/-S39,S39>0,AL39/S39)} -> #DIV/0! | AT39: =IF(AN39=0,0,AS39/AN39) -> 0 | AU39: =IF(AO39=0,0,AS39/AO39) -> 0 | AW39: =AS39*E39 -> #DIV/0!
E40: =SUM(F40:H40) -> 0 | J40: =E40*I40 -> 0 | O40: =L40/7 -> 0 | P40: =S40/7 -> 0 | S40: =Q40+R40 -> 0 | V40: =T40+U40 -> 0 | Y40: =W40+X40 -> 0 | Z40: =L40*M40*N40/100 -> 0 | AA40: =Y40/$Y$93 -> #DIV/0! | AB40: =S40*I40 -> 0 | AD40: =IF(Y40=0,0,AC40/Y40) -> 0 | AI40: =$AI$93*H40/$H$93 -> #DIV/0! | AK40: =V40*1% -> 0 | AL40: =Y40-AB40-AC40-AE40-AF40-AG40-AH40-AI40-AK40-AJ40 -> #DIV/0! | AN40: =IF(S40=0,0,Y40/S40) -> 0 | AO40: =I40 -> 0 | AP40: =IF(S40=0,0,AC40/S40) -> 0 | AQ40: =IF(Q40=0,AE40/1,AE40/Q40) -> 0 | AR40: =IF(Q40=0,0,(AF40+AG40)/Q40) -> 0 | AS40: {=_xlfn.IFS(S40=0,AL40,S40<0,AL40/-S40,S40>0,AL40/S40)} -> #DIV/0! | AT40: =IF(AN40=0,0,AS40/AN40) -> 0 | AU40: =IF(AO40=0,0,AS40/AO40) -> 0 | AW40: =AS40*E40 -> #DIV/0!
E41: =SUM(F41:H41) -> 0 | J41: =E41*I41 -> 0 | O41: =L41/7 -> 0 | P41: =S41/7 -> 0 | S41: =Q41+R41 -> 0 | V41: =T41+U41 -> 0 | Y41: =W41+X41 -> 0 | Z41: =L41*M41*N41/100 -> 0 | AA41: =Y41/$Y$93 -> #DIV/0! | AB41: =S41*I41 -> 0 | AD41: =IF(Y41=0,0,AC41/Y41) -> 0 | AI41: =$AI$93*H41/$H$93 -> #DIV/0! | AK41: =V41*1% -> 0 | AL41: =Y41-AB41-AC41-AE41-AF41-AG41-AH41-AI41-AK41-AJ41 -> #DIV/0! | AN41: =IF(S41=0,0,Y41/S41) -> 0 | AO41: =I41 -> 0 | AP41: =IF(S41=0,0,AC41/S41) -> 0 | AQ41: =IF(Q41=0,AE41/1,AE41/Q41) -> 0 | AR41: =IF(Q41=0,0,(AF41+AG41)/Q41) -> 0 | AS41: {=_xlfn.IFS(S41=0,AL41,S41<0,AL41/-S41,S41>0,AL41/S41)} -> #DIV/0! | AT41: =IF(AN41=0,0,AS41/AN41) -> 0 | AU41: =IF(AO41=0,0,AS41/AO41) -> 0 | AW41: =AS41*E41 -> #DIV/0!
E42: =SUM(F42:H42) -> 0 | J42: =E42*I42 -> 0 | O42: =L42/7 -> 0 | P42: =S42/7 -> 0 | S42: =Q42+R42 -> 0 | V42: =T42+U42 -> 0 | Y42: =W42+X42 -> 0 | Z42: =L42*M42*N42/100 -> 0 | AA42: =Y42/$Y$93 -> #DIV/0! | AB42: =S42*I42 -> 0 | AD42: =IF(Y42=0,0,AC42/Y42) -> 0 | AI42: =$AI$93*H42/$H$93 -> #DIV/0! | AK42: =V42*1% -> 0 | AL42: =Y42-AB42-AC42-AE42-AF42-AG42-AH42-AI42-AK42-AJ42 -> #DIV/0! | AN42: =IF(S42=0,0,Y42/S42) -> 0 | AO42: =I42 -> 0 | AP42: =IF(S42=0,0,AC42/S42) -> 0 | AQ42: =IF(Q42=0,AE42/1,AE42/Q42) -> 0 | AR42: =IF(Q42=0,0,(AF42+AG42)/Q42) -> 0 | AS42: {=_xlfn.IFS(S42=0,AL42,S42<0,AL42/-S42,S42>0,AL42/S42)} -> #DIV/0! | AT42: =IF(AN42=0,0,AS42/AN42) -> 0 | AU42: =IF(AO42=0,0,AS42/AO42) -> 0 | AW42: =AS42*E42 -> #DIV/0!
E43: =SUM(F43:H43) -> 0 | J43: =E43*I43 -> 0 | O43: =L43/7 -> 0 | P43: =S43/7 -> 0 | S43: =Q43+R43 -> 0 | V43: =T43+U43 -> 0 | Y43: =W43+X43 -> 0 | Z43: =L43*M43*N43/100 -> 0 | AA43: =Y43/$Y$93 -> #DIV/0! | AB43: =S43*I43 -> 0 | AD43: =IF(Y43=0,0,AC43/Y43) -> 0 | AI43: =$AI$93*H43/$H$93 -> #DIV/0! | AK43: =V43*1% -> 0 | AL43: =Y43-AB43-AC43-AE43-AF43-AG43-AH43-AI43-AK43-AJ43 -> #DIV/0! | AN43: =IF(S43=0,0,Y43/S43) -> 0 | AO43: =I43 -> 0 | AP43: =IF(S43=0,0,AC43/S43) -> 0 | AQ43: =IF(Q43=0,AE43/1,AE43/Q43) -> 0 | AR43: =IF(Q43=0,0,(AF43+AG43)/Q43) -> 0 | AS43: {=_xlfn.IFS(S43=0,AL43,S43<0,AL43/-S43,S43>0,AL43/S43)} -> #DIV/0! | AT43: =IF(AN43=0,0,AS43/AN43) -> 0 | AU43: =IF(AO43=0,0,AS43/AO43) -> 0 | AW43: =AS43*E43 -> #DIV/0!
E44: =SUM(F44:H44) -> 0 | J44: =E44*I44 -> 0 | O44: =L44/7 -> 0 | P44: =S44/7 -> 0 | S44: =Q44+R44 -> 0 | V44: =T44+U44 -> 0 | Y44: =W44+X44 -> 0 | Z44: =L44*M44*N44/100 -> 0 | AA44: =Y44/$Y$93 -> #DIV/0! | AB44: =S44*I44 -> 0 | AD44: =IF(Y44=0,0,AC44/Y44) -> 0 | AI44: =$AI$93*H44/$H$93 -> #DIV/0! | AK44: =V44*1% -> 0 | AL44: =Y44-AB44-AC44-AE44-AF44-AG44-AH44-AI44-AK44-AJ44 -> #DIV/0! | AN44: =IF(S44=0,0,Y44/S44) -> 0 | AO44: =I44 -> 0 | AP44: =IF(S44=0,0,AC44/S44) -> 0 | AQ44: =IF(Q44=0,AE44/1,AE44/Q44) -> 0 | AR44: =IF(Q44=0,0,(AF44+AG44)/Q44) -> 0 | AS44: {=_xlfn.IFS(S44=0,AL44,S44<0,AL44/-S44,S44>0,AL44/S44)} -> #DIV/0! | AT44: =IF(AN44=0,0,AS44/AN44) -> 0 | AU44: =IF(AO44=0,0,AS44/AO44) -> 0 | AW44: =AS44*E44 -> #DIV/0!
E45: =SUM(F45:H45) -> 0 | J45: =E45*I45 -> 0 | O45: =L45/7 -> 0 | P45: =S45/7 -> 0 | S45: =Q45+R45 -> 0 | V45: =T45+U45 -> 0 | Y45: =W45+X45 -> 0 | Z45: =L45*M45*N45/100 -> 0 | AA45: =Y45/$Y$93 -> #DIV/0! | AB45: =S45*I45 -> 0 | AD45: =IF(Y45=0,0,AC45/Y45) -> 0 | AI45: =$AI$93*H45/$H$93 -> #DIV/0! | AK45: =V45*1% -> 0 | AL45: =Y45-AB45-AC45-AE45-AF45-AG45-AH45-AI45-AK45-AJ45 -> #DIV/0! | AN45: =IF(S45=0,0,Y45/S45) -> 0 | AO45: =I45 -> 0 | AP45: =IF(S45=0,0,AC45/S45) -> 0 | AQ45: =IF(Q45=0,AE45/1,AE45/Q45) -> 0 | AR45: =IF(Q45=0,0,(AF45+AG45)/Q45) -> 0 | AS45: {=_xlfn.IFS(S45=0,AL45,S45<0,AL45/-S45,S45>0,AL45/S45)} -> #DIV/0! | AT45: =IF(AN45=0,0,AS45/AN45) -> 0 | AU45: =IF(AO45=0,0,AS45/AO45) -> 0 | AW45: =AS45*E45 -> #DIV/0!
E46: =SUM(F46:H46) -> 0 | J46: =E46*I46 -> 0 | O46: =L46/7 -> 0 | P46: =S46/7 -> 0 | S46: =Q46+R46 -> 0 | V46: =T46+U46 -> 0 | Y46: =W46+X46 -> 0 | Z46: =L46*M46*N46/100 -> 0 | AA46: =Y46/$Y$93 -> #DIV/0! | AB46: =S46*I46 -> 0 | AD46: =IF(Y46=0,0,AC46/Y46) -> 0 | AI46: =$AI$93*H46/$H$93 -> #DIV/0! | AK46: =V46*1% -> 0 | AL46: =Y46-AB46-AC46-AE46-AF46-AG46-AH46-AI46-AK46-AJ46 -> #DIV/0! | AN46: =IF(S46=0,0,Y46/S46) -> 0 | AO46: =I46 -> 0 | AP46: =IF(S46=0,0,AC46/S46) -> 0 | AQ46: =IF(Q46=0,AE46/1,AE46/Q46) -> 0 | AR46: =IF(Q46=0,0,(AF46+AG46)/Q46) -> 0 | AS46: {=_xlfn.IFS(S46=0,AL46,S46<0,AL46/-S46,S46>0,AL46/S46)} -> #DIV/0! | AT46: =IF(AN46=0,0,AS46/AN46) -> 0 | AU46: =IF(AO46=0,0,AS46/AO46) -> 0 | AW46: =AS46*E46 -> #DIV/0!
E47: =SUM(F47:H47) -> 0 | J47: =E47*I47 -> 0 | O47: =L47/7 -> 0 | P47: =S47/7 -> 0 | S47: =Q47+R47 -> 0 | V47: =T47+U47 -> 0 | Y47: =W47+X47 -> 0 | Z47: =L47*M47*N47/100 -> 0 | AA47: =Y47/$Y$93 -> #DIV/0! | AB47: =S47*I47 -> 0 | AD47: =IF(Y47=0,0,AC47/Y47) -> 0 | AI47: =$AI$93*H47/$H$93 -> #DIV/0! | AK47: =V47*1% -> 0 | AL47: =Y47-AB47-AC47-AE47-AF47-AG47-AH47-AI47-AK47-AJ47 -> #DIV/0! | AN47: =IF(S47=0,0,Y47/S47) -> 0 | AO47: =I47 -> 0 | AP47: =IF(S47=0,0,AC47/S47) -> 0 | AQ47: =IF(Q47=0,AE47/1,AE47/Q47) -> 0 | AR47: =IF(Q47=0,0,(AF47+AG47)/Q47) -> 0 | AS47: {=_xlfn.IFS(S47=0,AL47,S47<0,AL47/-S47,S47>0,AL47/S47)} -> #DIV/0! | AT47: =IF(AN47=0,0,AS47/AN47) -> 0 | AU47: =IF(AO47=0,0,AS47/AO47) -> 0 | AW47: =AS47*E47 -> #DIV/0!
E48: =SUM(F48:H48) -> 0 | J48: =E48*I48 -> 0 | O48: =L48/7 -> 0 | P48: =S48/7 -> 0 | S48: =Q48+R48 -> 0 | V48: =T48+U48 -> 0 | Y48: =W48+X48 -> 0 | Z48: =L48*M48*N48/100 -> 0 | AA48: =Y48/$Y$93 -> #DIV/0! | AB48: =S48*I48 -> 0 | AD48: =IF(Y48=0,0,AC48/Y48) -> 0 | AI48: =$AI$93*H48/$H$93 -> #DIV/0! | AK48: =V48*1% -> 0 | AL48: =Y48-AB48-AC48-AE48-AF48-AG48-AH48-AI48-AK48-AJ48 -> #DIV/0! | AN48: =IF(S48=0,0,Y48/S48) -> 0 | AO48: =I48 -> 0 | AP48: =IF(S48=0,0,AC48/S48) -> 0 | AQ48: =IF(Q48=0,AE48/1,AE48/Q48) -> 0 | AR48: =IF(Q48=0,0,(AF48+AG48)/Q48) -> 0 | AS48: {=_xlfn.IFS(S48=0,AL48,S48<0,AL48/-S48,S48>0,AL48/S48)} -> #DIV/0! | AT48: =IF(AN48=0,0,AS48/AN48) -> 0 | AU48: =IF(AO48=0,0,AS48/AO48) -> 0 | AW48: =AS48*E48 -> #DIV/0!
E49: =SUM(F49:H49) -> 0 | J49: =E49*I49 -> 0 | O49: =L49/7 -> 0 | P49: =S49/7 -> 0 | S49: =Q49+R49 -> 0 | V49: =T49+U49 -> 0 | Y49: =W49+X49 -> 0 | Z49: =L49*M49*N49/100 -> 0 | AA49: =Y49/$Y$93 -> #DIV/0! | AB49: =S49*I49 -> 0 | AD49: =IF(Y49=0,0,AC49/Y49) -> 0 | AI49: =$AI$93*H49/$H$93 -> #DIV/0! | AK49: =V49*1% -> 0 | AL49: =Y49-AB49-AC49-AE49-AF49-AG49-AH49-AI49-AK49-AJ49 -> #DIV/0! | AN49: =IF(S49=0,0,Y49/S49) -> 0 | AO49: =I49 -> 0 | AP49: =IF(S49=0,0,AC49/S49) -> 0 | AQ49: =IF(Q49=0,AE49/1,AE49/Q49) -> 0 | AR49: =IF(Q49=0,0,(AF49+AG49)/Q49) -> 0 | AS49: {=_xlfn.IFS(S49=0,AL49,S49<0,AL49/-S49,S49>0,AL49/S49)} -> #DIV/0! | AT49: =IF(AN49=0,0,AS49/AN49) -> 0 | AU49: =IF(AO49=0,0,AS49/AO49) -> 0 | AW49: =AS49*E49 -> #DIV/0!
... E89: =SUM(F89:H89) -> 0 | J89: =E89*I89 -> 0 | O89: =L89/7 -> 0 | P89: =S89/7 -> 0 | S89: =Q89+R89 -> 0 | V89: =T89+U89 -> 0 | Y89: =W89+X89 -> 0 | Z89: =L89*M89*N89/100 -> 0 | AA89: =Y89/$Y$93 -> #DIV/0! | AB89: =S89*I89 -> 0 | AD89: =IF(Y89=0,0,AC89/Y89) -> 0 | AI89: =$AI$93*H89/$H$93 -> #DIV/0! | AK89: =V89*1% -> 0 | AL89: =Y89-AB89-AC89-AE89-AF89-AG89-AH89-AI89-AK89-AJ89 -> #DIV/0! | AN89: =IF(S89=0,0,Y89/S89) -> 0 | AO89: =I89 -> 0 | AP89: =IF(S89=0,0,AC89/S89) -> 0 | AQ89: =IF(Q89=0,AE89/1,AE89/Q89) -> 0 | AR89: =IF(Q89=0,0,(AF89+AG89)/Q89) -> 0 | AS89: {=_xlfn.IFS(S89=0,AL89,S89<0,AL89/-S89,S89>0,AL89/S89)} -> #DIV/0! | AT89: =IF(AN89=0,0,AS89/AN89) -> 0 | AU89: =IF(AO89=0,0,AS89/AO89) -> 0 | AW89: =AS89*E89 -> #DIV/0!
AN90: =AVERAGE(AN38:AN89) -> 0 | AO90: =AVERAGE(AO38:AO89) -> 0 | AP90: =AVERAGE(AP38:AP89) -> 0 | AQ90: =AVERAGE(AQ38:AQ89) -> 0 | AR90: =AVERAGE(AR38:AR89) -> 0 | AS90: =AVERAGE(AS38:AS89) -> #DIV/0! | AT90: =AVERAGE(AT38:AT89) -> 0 | AU90: =AVERAGE(AU38:AU89) -> 0
A91: Итого ___ | E91: =SUM(E38:E89) -> 0 | F91: =SUM(F38:F89) -> 0 | G91: =SUM(G38:G89) -> 0 | H91: =SUM(H38:H89) -> 0 | J91: =SUM(J38:J89) -> 0 | L91: =SUM(L38:L89) -> 0 | Q91: =SUM(Q38:Q89) -> 0 | R91: =SUM(R38:R89) -> 0 | S91: =SUM(S38:S89) -> 0 | T91: =SUM(T38:T89) -> 0 | U91: =SUM(U38:U89) -> 0 | V91: =SUM(V38:V89) -> 0 | W91: =SUM(W38:W89) -> 0 | X91: =SUM(X38:X89) -> 0 | ... AC91: =SUM(AC38:AC89) -> 0 | AD91: =AC91/Y91 -> #DIV/0! | AE91: =SUM(AE38:AE89) -> 0 | AF91: =SUM(AF38:AF89) -> 0 | AG91: =SUM(AG38:AG89) -> 0 | AH91: =SUM(AH38:AH89) -> 0 | AI91: =SUM(AI38:AI89) -> #DIV/0! | AJ91: =SUM(AJ38:AJ89) -> 0 | AK91: =SUM(AK38:AK89) -> 0 | AL91: =SUM(AL38:AL89) -> #DIV/0! | AR91: =(AF91+AG91)/Q91 -> #DIV/0! | AW91: =SUM(AW38:AW89) -> #DIV/0!
A93: ИТОГО | E93: =E36+E91 -> 0 | F93: =F36+F91 -> 0 | G93: =G36+G91 -> 0 | H93: =H36+H91 -> 0 | I93: =I36+I91 -> 0 | J93: =J36+J91 -> 0 | K93: =K36+K91 -> 0 | L93: =L36+L91 -> 0 | ... AC93: =AC36+AC91 -> 0 | AD93: =AC93/Y93 -> #DIV/0! | AE93: =AE36+AE91 -> 0 | AF93: =AF36+AF91 -> 0 | AG93: =AG36+AG91 -> 0 | AH93: =AH36+AH91 -> 0 | AJ93: =AJ36+AJ91 -> 0 | AK93: =AK36+AK91 -> 0 | AL93: =AL36+AL91 -> #DIV/0! | AR93: =(AF93+AG93)/Q93 -> #DIV/0! | AW93: =AW36+AW91 -> #DIV/0!
AF94: =AF37+AF92 -> 0

Sheet Юнит 7
A1: 09-15.02_7 нед | F1: Отчет по остаткам 3,4,5 | K1: Цены и скидки 6 | L1: Воронка продаж 16,50,32 | AI1: Вставить в Итого | AN1: на 1 единицу проданного товара
A2: Бренд | B2: SKU | C2: Артикул поставщика | D2: Предмет | E2: Остаток на 16.02 | F2: В пути до клиента | G2: В пути от клиента | H2: Итого по складам ВБ | I2: Себетоимость на 1 ед на 29.09.25 | J2: Себестоимость остатков | K2: Оборачива-емость, дн | L2: Заказы, шт 7 дней | M2: Средняя цена, руб | N2: % выкупа за 7 дней | O2: Скорость заказов | P2: Скорость продаж | Q2: Кол-во ПРОДАЖИ | R2: Кол-во ВОЗВРАТЫ | S2: Кол-во ПРОДАЖИ-ВОЗВРАТЫ | T2: Выручка ВБ ПРОДАЖИ | U2: Выручка ВБ ВОЗВРАТЫ | V2: Выручка с учетом СПП ПРОДАЖИ - ВОЗВРАТЫ | W2: Выручка ПРОДАЖИ | X2: Выручка ВОЗВРАТЫ | Y2: Выручка с учетом согласованной скидки ПРОДАЖИ - ВОЗВРАТЫ | Z2: Выручка потенциальная | AA2: Доля выручки, % от общего объема | AB2: Себестоимость продаж | AC2: Комиссия, руб | AD2: Комиссия, % | AE2: Логистика | AF2: Реклама БАЛАНС | AG2: Реклама СЧЕТ | AH2: Блогеры | AI2: Хранение | AJ2: Штрафы | AK2: Налог 1% | AL2: Прибыль | AN2: Выручка на 1 ед (средняя цена продажи со скидкой) | AO2: Себестоимость на 1 ед | AP2: Комиссия на 1 ед | AQ2: Логистика на 1 ед | AR2: Реклама на 1 ед | AS2: Прибыль на 1 ед | AT2: Маржиналь-ность, % | AU2: Рентабель-ность, % | AW2: Прибыль с остатков
B3: 341479791 | C3: Черные с железкой Сул | D3: Солнцезащитные очки | E3: =F3+G3+H3 -> 388 | F3: 55 | G3: 14 | H3: 319 | I3: 142.98 | J3: =E3*I3 -> 55476.24 | K3: 58 | L3: 73 | M3: 1238 | N3: 67 | O3: =L3/7 -> 10.428571 | P3: =S3/7 -> 7.1428571 | Q3: 51 | R3: -1 | S3: =Q3+R3 -> 50 | T3: 39799.06 | U3: -753 | V3: =T3+U3 -> 39046.06 | W3: 63138.92 | X3: -1238 | Y3: =W3+X3 -> 61900.92 | Z3: =L3*M3*N3/100 -> 60550.58 | AA3: =Y3/$Y$93 -> 0.26694348 | AB3: =S3*I3 -> 7149 | AC3: 22440.45 | AD3: =IF(Y3=0,0,AC3/Y3) -> 0.36252208 | AE3: 5848.39 | AF3: 3000 | AG3: 5657 | AI3: =IFERROR($AI$93*H3/$H$93,0) -> 187.08169 | AJ3: 0 | AK3: =V3*1% -> 390.4606 | AL3: =Y3-AB3-AC3-AE3-AF3-AG3-AH3-AI3-AK3-AJ3 -> 17228.538 | AN3: =IF(S3=0,0,Y3/S3) -> 1238.0184 | AO3: =I3 -> 142.98 | AP3: =IF(S3=0,0,AC3/S3) -> 448.809 | AQ3: =IF(Q3=0,AE3/1,AE3/Q3) -> 114.67431 | AR3: =IF(Q3=0,0,(AF3+AG3)/Q3) -> 169.7451 | AS3: =_xlfn.IFS(S3=0,AL3,S3<0,AL3/-S3,S3>0,AL3/S3) -> 344.57075 | AT3: =IF(AN3=0,0,AS3/AN3) -> 0.27832442 | AU3: =IF(AO3=0,0,AS3/AO3) -> 2.4099227 | AW3: =AS3*E3 -> 133693.45
B4: 340343575 | C4: Qs черн Сул | D4: Солнцезащитные очки | E4: =F4+G4+H4 -> 254 | F4: 100 | G4: 9 | H4: 145 | I4: 123.09 | J4: =E4*I4 -> 31264.86 | K4: 33 | L4: 135 | M4: 933 | N4: 83 | O4: =L4/7 -> 19.285714 | P4: =S4/7 -> 10.285714 | Q4: 72 | R4: 0 | S4: =Q4+R4 -> 72 | T4: 44541.53 | U4: 0 | V4: =T4+U4 -> 44541.53 | W4: 67252.19 | X4: 0 | Y4: =W4+X4 -> 67252.19 | Z4: =L4*M4*N4/100 -> 104542.65 | AA4: =Y4/$Y$93 -> 0.29002046 | AB4: =S4*I4 -> 8862.48 | AC4: 24473.61 | AD4: =IF(Y4=0,0,AC4/Y4) -> 0.363908 | AE4: 6260.62 | AF4: 3000 | AG4: 4000 | AI4: =IFERROR($AI$93*H4/$H$93,0) -> 85.037131 | AJ4: 0 | AK4: =V4*1% -> 445.4153 | AL4: =Y4-AB4-AC4-AE4-AF4-AG4-AH4-AI4-AK4-AJ4 -> 20125.028 | AN4: =IF(S4=0,0,Y4/S4) -> 934.05819 | AO4: =I4 -> 123.09 | AP4: =IF(S4=0,0,AC4/S4) -> 339.91125 | AQ4: =IF(Q4=0,AE4/1,AE4/Q4) -> 86.953056 | AR4: =IF(Q4=0,0,(AF4+AG4)/Q4) -> 97.222222 | AS4: {=_xlfn.IFS(S4=0,AL4,S4<0,AL4/-S4,S4>0,AL4/S4)} -> 279.51427 | AT4: =IF(AN4=0,0,AS4/AN4) -> 0.29924717 | AU4: =IF(AO4=0,0,AS4/AO4) -> 2.2708122 | AW4: =AS4*E4 -> 70996.625
B5: 340332621 | C5: Qs син Сул | D5: Солнцезащитные очки | E5: =F5+G5+H5 -> 368 | F5: 6 | G5: 0 | H5: 362 | I5: 123.09 | J5: =E5*I5 -> 45297.12 | K5: 698 | L5: 8 | M5: 1137 | N5: 75 | O5: =L5/7 -> 1.1428571 | P5: =S5/7 -> 0.42857143 | Q5: 3 | R5: 0 | S5: =Q5+R5 -> 3 | T5: 1968 | U5: 0 | V5: =T5+U5 -> 1968 | W5: 3342 | X5: 0 | Y5: =W5+X5 -> 3342 | Z5: =L5*M5*N5/100 -> 6822 | AA5: =Y5/$Y$93 -> 0.014412146 | AB5: =S5*I5 -> 369.27 | AC5: 1216.95 | AD5: =IF(Y5=0,0,AC5/Y5) -> 0.36413824 | AE5: 380.14 | AG5: 715 | AI5: =IFERROR($AI$93*H5/$H$93,0) -> 212.2996 | AJ5: 0 | AK5: =V5*1% -> 19.68 | AL5: =Y5-AB5-AC5-AE5-AF5-AG5-AH5-AI5-AK5-AJ5 -> 428.6604 | AN5: =IF(S5=0,0,Y5/S5) -> 1114 | AO5: =I5 -> 123.09 | AP5: =IF(S5=0,0,AC5/S5) -> 405.65 | AQ5: =IF(Q5=0,AE5/1,AE5/Q5) -> 126.71333 | AR5: =IF(Q5=0,0,(AF5+AG5)/Q5) -> 238.33333 | AS5: {=_xlfn.IFS(S5=0,AL5,S5<0,AL5/-S5,S5>0,AL5/S5)} -> 142.8868 | AT5: =IF(AN5=0,0,AS5/AN5) -> 0.12826463 | AU5: =IF(AO5=0,0,AS5/AO5) -> 1.1608319 | AW5: =AS5*E5 -> 52582.343
B6: 340341838 | C6: Qs желт Сул | D6: Солнцезащитные очки | E6: =F6+G6+H6 -> 326 | F6: 16 | G6: 5 | H6: 305 | I6: 123.09 | J6: =E6*I6 -> 40127.34 | K6: 240 | L6: 24 | M6: 1176 | N6: 70 | O6: =L6/7 -> 3.4285714 | P6: =S6/7 -> 2.2857143 | Q6: 16 | R6: 0 | S6: =Q6+R6 -> 16 | T6: 11758.94 | U6: 0 | V6: =T6+U6 -> 11758.94 | W6: 18692.1 | X6: 0 | Y6: =W6+X6 -> 18692.1 | Z6: =L6*M6*N6/100 -> 19756.8 | AA6: =Y6/$Y$93 -> 0.080608401 | AB6: =S6*I6 -> 1969.44 | AC6: 6766.64 | AD6: =IF(Y6=0,0,AC6/Y6) -> 0.36200534 | AE6: 1845.51 | AF6: 3000 | AG6: 2910 | AI6: =IFERROR($AI$93*H6/$H$93,0) -> 178.87121 | AJ6: 0 | AK6: =V6*1% -> 117.5894 | AL6: =Y6-AB6-AC6-AE6-AF6-AG6-AH6-AI6-AK6-AJ6 -> 1904.0494 | AN6: =IF(S6=0,0,Y6/S6) -> 1168.2562 | AO6: =I6 -> 123.09 | AP6: =IF(S6=0,0,AC6/S6) -> 422.915 | AQ6: =IF(Q6=0,AE6/1,AE6/Q6) -> 115.34437 | AR6: =IF(Q6=0,0,(AF6+AG6)/Q6) -> 369.375 | AS6: {=_xlfn.IFS(S6=0,AL6,S6<0,AL6/-S6,S6>0,AL6/S6)} -> 119.00309 | AT6: =IF(AN6=0,0,AS6/AN6) -> 0.10186386 | AU6: =IF(AO6=0,0,AS6/AO6) -> 0.96679736 | AW6: =AS6*E6 -> 38795.006
B7: 445291724 | C7: flip черные Сул | D7: Солнцезащитные очки | E7: =F7+G7+H7 -> 255 | F7: 17 | G7: 6 | H7: 232 | I7: 123.09 | J7: =E7*I7 -> 31387.95 | K7: 154 | L7: 30 | M7: 1150 | N7: 63 | O7: =L7/7 -> 4.2857143 | P7: =S7/7 -> 3.1428571 | Q7: 22 | R7: 0 | S7: =Q7+R7 -> 22 | T7: 15477 | U7: 0 | V7: =T7+U7 -> 15477 | W7: 25229 | X7: 0 | Y7: =W7+X7 -> 25229 | Z7: =L7*M7*N7/100 -> 21735 | AA7: =Y7/$Y$93 -> 0.10879833 | AB7: =S7*I7 -> 2707.98 | AC7: 9211.85 | AD7: =IF(Y7=0,0,AC7/Y7) -> 0.36512941 | AE7: 2288.82 | AF7: 1000 | AG7: 4000 | AI7: =IFERROR($AI$93*H7/$H$93,0) -> 136.05941 | AJ7: 0 | AK7: =V7*1% -> 154.77 | AL7: =Y7-AB7-AC7-AE7-AF7-AG7-AH7-AI7-AK7-AJ7 -> 5729.5206 | AN7: =IF(S7=0,0,Y7/S7) -> 1146.7727 | AO7: =I7 -> 123.09 | AP7: =IF(S7=0,0,AC7/S7) -> 418.72045 | AQ7: =IF(Q7=0,AE7/1,AE7/Q7) -> 104.03727 | AR7: =IF(Q7=0,0,(AF7+AG7)/Q7) -> 227.27273 | AS7: {=_xlfn.IFS(S7=0,AL7,S7<0,AL7/-S7,S7>0,AL7/S7)} -> 260.43275 | AT7: =IF(AN7=0,0,AS7/AN7) -> 0.22710058 | AU7: =IF(AO7=0,0,AS7/AO7) -> 2.1157913 | AW7: =AS7*E7 -> 66410.352
B8: 445336740 | C8: flip желтые Сул | D8: Солнцезащитные очки | E8: =F8+G8+H8 -> 212 | F8: 21 | G8: 8 | H8: 183 | I8: 123.09 | J8: =E8*I8 -> 26095.08 | K8: 35 | L8: 42 | M8: 1150 | N8: 74 | O8: =L8/7 -> 6 | P8: =S8/7 -> 3.4285714 | Q8: 25 | R8: -1 | S8: =Q8+R8 -> 24 | T8: 18225.03 | U8: -705 | V8: =T8+U8 -> 17520.03 | W8: 28750.94 | X8: -1150 | Y8: =W8+X8 -> 27600.94 | Z8: =L8*M8*N8/100 -> 35742 | AA8: =Y8/$Y$93 -> 0.11902716 | AB8: =S8*I8 -> 2954.16 | AC8: 10103.95 | AD8: =IF(Y8=0,0,AC8/Y8) -> 0.36607268 | AE8: 2390.15 | AF8: 2968 | AG8: 3000 | AI8: =IFERROR($AI$93*H8/$H$93,0) -> 107.32272 | AJ8: 0 | AK8: =V8*1% -> 175.2003 | AL8: =Y8-AB8-AC8-AE8-AF8-AG8-AH8-AI8-AK8-AJ8 -> 5902.157 | AN8: =IF(S8=0,0,Y8/S8) -> 1150.0392 | AO8: =I8 -> 123.09 | AP8: =IF(S8=0,0,AC8/S8) -> 420.99792 | AQ8: =IF(Q8=0,AE8/1,AE8/Q8) -> 95.606 | AR8: =IF(Q8=0,0,(AF8+AG8)/Q8) -> 238.72 | AS8: {=_xlfn.IFS(S8=0,AL8,S8<0,AL8/-S8,S8>0,AL8/S8)} -> 245.92321 | AT8: =IF(AN8=0,0,AS8/AN8) -> 0.21383898 | AU8: =IF(AO8=0,0,AS8/AO8) -> 1.9979138 | AW8: =AS8*E8 -> 52135.72
B9: 445341507 | C9: MR8854 C2 Сул | D9: Солнцезащитные очки | E9: =F9+G9+H9 -> 223 | F9: 16 | G9: 5 | H9: 202 | I9: 169.89 | J9: =E9*I9 -> 37885.47 | K9: 123 | L9: 18 | M9: 1230 | N9: 50 | O9: =L9/7 -> 2.5714286 | P9: =S9/7 -> 1.5714286 | Q9: 11 | R9: 0 | S9: =Q9+R9 -> 11 | T9: 8339 | U9: 0 | V9: =T9+U9 -> 8339 | W9: 13250 | X9: 0 | Y9: =W9+X9 -> 13250 | Z9: =L9*M9*N9/100 -> 11070 | AA9: =Y9/$Y$93 -> 0.057139718 | AB9: =S9*I9 -> 1868.79 | AC9: 4838.16 | AD9: =IF(Y9=0,0,AC9/Y9) -> 0.36514415 | AE9: 1526.29 | AI9: =IFERROR($AI$93*H9/$H$93,0) -> 118.46552 | AJ9: 0 | AK9: =V9*1% -> 83.39 | AL9: =Y9-AB9-AC9-AE9-AF9-AG9-AH9-AI9-AK9-AJ9 -> 4814.9045 | AN9: =IF(S9=0,0,Y9/S9) -> 1204.5455 | AO9: =I9 -> 169.89 | AP9: =IF(S9=0,0,AC9/S9) -> 439.83273 | AQ9: =IF(Q9=0,AE9/1,AE9/Q9) -> 138.75364 | AR9: =IF(Q9=0,0,(AF9+AG9)/Q9) -> 0 | AS9: {=_xlfn.IFS(S9=0,AL9,S9<0,AL9/-S9,S9>0,AL9/S9)} -> 437.71859 | AT9: =IF(AN9=0,0,AS9/AN9) -> 0.36338902 | AU9: =IF(AO9=0,0,AS9/AO9) -> 2.5764824 | AW9: =AS9*E9 -> 97611.245
B10: 497825485 | C10: MR 1819 черн | D10: Солнцезащитные очки | E10: =F10+G10+H10 -> 35 | F10: 7 | G10: 3 | H10: 25 | I10: 169.89 | J10: =E10*I10 -> 5946.15 | K10: 71 | L10: 8 | M10: 1254 | N10: 33 | O10: =L10/7 -> 1.1428571 | P10: =S10/7 -> 0.42857143 | Q10: 3 | R10: 0 | S10: =Q10+R10 -> 3 | T10: 2532.64 | U10: 0 | V10: =T10+U10 -> 2532.64 | W10: 3706.59 | X10: 0 | Y10: =W10+X10 -> 3706.59 | Z10: =L10*M10*N10/100 -> 3310.56 | AA10: =Y10/$Y$93 -> 0.015984416 | AB10: =S10*I10 -> 509.67 | AC10: 1350.84 | AD10: =IF(Y10=0,0,AC10/Y10) -> 0.36444279 | AE10: 585.93 | AF10: 2000 | AG10: 1606 | AI10: =IFERROR($AI$93*H10/$H$93,0) -> 14.661574 | AJ10: 0 | AK10: =V10*1% -> 25.3264 | AL10: =Y10-AB10-AC10-AE10-AF10-AG10-AH10-AI10-AK10-AJ10 -> -2385.838 | AN10: =IF(S10=0,0,Y10/S10) -> 1235.53 | AO10: =I10 -> 169.89 | AP10: =IF(S10=0,0,AC10/S10) -> 450.28 | AQ10: =IF(Q10=0,AE10/1,AE10/Q10) -> 195.31 | AR10: =IF(Q10=0,0,(AF10+AG10)/Q10) -> 1202 | AS10: {=_xlfn.IFS(S10=0,AL10,S10<0,AL10/-S10,S10>0,AL10/S10)} -> -795.27932 | AT10: =IF(AN10=0,0,AS10/AN10) -> -0.64367464 | AU10: =IF(AO10=0,0,AS10/AO10) -> -4.6811426 | AW10: =AS10*E10 -> -27834.776
B11: 497825962 | C11: MR 1819 корич | D11: Солнцезащитные очки | E11: =F11+G11+H11 -> 38 | F11: 1 | G11: 0 | H11: 37 | I11: 169.89 | J11: =E11*I11 -> 6455.82 | K11: 384 | L11: 1 | M11: 1145 | N11: 0 | O11: =L11/7 -> 0.14285714 | P11: =S11/7 -> 0 | Q11: 0 | R11: 0 | S11: =Q11+R11 -> 0 | T11: 0 | U11: 0 | V11: =T11+U11 -> 0 | W11: 0 | X11: 0 | Y11: =W11+X11 -> 0 | Z11: =L11*M11*N11/100 -> 0 | AA11: =Y11/$Y$93 -> 0 | AB11: =S11*I11 -> 0 | AC11: 0 | AD11: =IF(Y11=0,0,AC11/Y11) -> 0 | AE11: 113.8 | AI11: =IFERROR($AI$93*H11/$H$93,0) -> 21.69913 | AJ11: 0 | AK11: =V11*1% -> 0 | AL11: =Y11-AB11-AC11-AE11-AF11-AG11-AH11-AI11-AK11-AJ11 -> -135.49913 | AN11: =IF(S11=0,0,Y11/S11) -> 0 | AO11: =I11 -> 169.89 | AP11: =IF(S11=0,0,AC11/S11) -> 0 | AQ11: =IF(Q11=0,AE11/1,AE11/Q11) -> 113.8 | AR11: =IF(Q11=0,0,(AF11+AG11)/Q11) -> 0 | AS11: {=_xlfn.IFS(S11=0,AL11,S11<0,AL11/-S11,S11>0,AL11/S11)} -> -135.49913 | AT11: =IF(AN11=0,0,AS11/AN11) -> 0 | AU11: =IF(AO11=0,0,AS11/AO11) -> -0.79756978 | AW11: =AS11*E11 -> -5148.9669
B12: 497821775 | C12: MR Р1874 черн | D12: Солнцезащитные очки | E12: =F12+G12+H12 -> 40 | F12: 2 | G12: 3 | H12: 35 | I12: 169.89 | J12: =E12*I12 -> 6795.6 | K12: 136 | L12: 10 | M12: 1166 | N12: 33 | O12: =L12/7 -> 1.4285714 | P12: =S12/7 -> 0.57142857 | Q12: 4 | R12: 0 | S12: =Q12+R12 -> 4 | T12: 2911 | U12: 0 | V12: =T12+U12 -> 2911 | W12: 4664 | X12: 0 | Y12: =W12+X12 -> 4664 | Z12: =L12*M12*N12/100 -> 3847.8 | AA12: =Y12/$Y$93 -> 0.020113181 | AB12: =S12*I12 -> 679.56 | AC12: 1709.04 | AD12: =IF(Y12=0,0,AC12/Y12) -> 0.36643225 | AE12: 833.5 | AI12: =IFERROR($AI$93*H12/$H$93,0) -> 20.526204 | AJ12: 0 | AK12: =V12*1% -> 29.11 | AL12: =Y12-AB12-AC12-AE12-AF12-AG12-AH12-AI12-AK12-AJ12 -> 1392.2638 | AN12: =IF(S12=0,0,Y12/S12) -> 1166 | AO12: =I12 -> 169.89 | AP12: =IF(S12=0,0,AC12/S12) -> 427.26 | AQ12: =IF(Q12=0,AE12/1,AE12/Q12) -> 208.375 | AR12: =IF(Q12=0,0,(AF12+AG12)/Q12) -> 0 | AS12: {=_xlfn.IFS(S12=0,AL12,S12<0,AL12/-S12,S12>0,AL12/S12)} -> 348.06595 | AT12: =IF(AN12=0,0,AS12/AN12) -> 0.29851282 | AU12: =IF(AO12=0,0,AS12/AO12) -> 2.0487724 | AW12: =AS12*E12 -> 13922.638
B13: 497823770 | C13: MR Р1874 корич | D13: Солнцезащитные очки | E13: =F13+G13+H13 -> 5 | F13: 0 | G13: 0 | H13: 5 | I13: 169.89 | J13: =E13*I13 -> 849.45 | K13: 74 | L13: 2 | M13: 1221 | N13: 100 | O13: =L13/7 -> 0.28571429 | P13: =S13/7 -> 0.28571429 | Q13: 2 | R13: 0 | S13: =Q13+R13 -> 2 | T13: 1479 | U13: 0 | V13: =T13+U13 -> 1479 | W13: 2442 | X13: 0 | Y13: =W13+X13 -> 2442 | Z13: =L13*M13*N13/100 -> 2442 | AA13: =Y13/$Y$93 -> 0.010530958 | AB13: =S13*I13 -> 339.78 | AC13: 890.54 | AD13: =IF(Y13=0,0,AC13/Y13) -> 0.36467649 | AE13: 102.05 | AI13: =IFERROR($AI$93*H13/$H$93,0) -> 2.9323149 | AJ13: 0 | AK13: =V13*1% -> 14.79 | AL13: =Y13-AB13-AC13-AE13-AF13-AG13-AH13-AI13-AK13-AJ13 -> 1091.9077 | AN13: =IF(S13=0,0,Y13/S13) -> 1221 | AO13: =I13 -> 169.89 | AP13: =IF(S13=0,0,AC13/S13) -> 445.27 | AQ13: =IF(Q13=0,AE13/1,AE13/Q13) -> 51.025 | AR13: =IF(Q13=0,0,(AF13+AG13)/Q13) -> 0 | AS13: {=_xlfn.IFS(S13=0,AL13,S13<0,AL13/-S13,S13>0,AL13/S13)} -> 545.95384 | AT13: =IF(AN13=0,0,AS13/AN13) -> 0.44713664 | AU13: =IF(AO13=0,0,AS13/AO13) -> 3.2135726 | AW13: =AS13*E13 -> 2729.7692
B14: 497824253 | C14: MR Р1886 черн | D14: Солнцезащитные очки | E14: =F14+G14+H14 -> 55 | F14: 4 | G14: 0 | H14: 51 | I14: 169.89 | J14: =E14*I14 -> 9343.95 | K14: 245 | L14: 5 | M14: 1288 | N14: 100 | O14: =L14/7 -> 0.71428571 | P14: =S14/7 -> 0.28571429 | Q14: 2 | R14: 0 | S14: =Q14+R14 -> 2 | T14: 1609 | U14: 0 | V14: =T14+U14 -> 1609 | W14: 2576 | X14: 0 | Y14: =W14+X14 -> 2576 | Z14: =L14*M14*N14/100 -> 6440 | AA14: =Y14/$Y$93 -> 0.011108824 | AB14: =S14*I14 -> 339.78 | AC14: 923.46 | AD14: =IF(Y14=0,0,AC14/Y14) -> 0.35848602 | AE14: 211.53 | AI14: =IFERROR($AI$93*H14/$H$93,0) -> 29.909612 | AJ14: 0 | AK14: =V14*1% -> 16.09 | AL14: =Y14-AB14-AC14-AE14-AF14-AG14-AH14-AI14-AK14-AJ14 -> 1055.2304 | AN14: =IF(S14=0,0,Y14/S14) -> 1288 | AO14: =I14 -> 169.89 | AP14: =IF(S14=0,0,AC14/S14) -> 461.73 | AQ14: =IF(Q14=0,AE14/1,AE14/Q14) -> 105.765 | AR14: =IF(Q14=0,0,(AF14+AG14)/Q14) -> 0 | AS14: {=_xlfn.IFS(S14=0,AL14,S14<0,AL14/-S14,S14>0,AL14/S14)} -> 527.61519 | AT14: =IF(AN14=0,0,AS14/AN14) -> 0.40963913 | AU14: =IF(AO14=0,0,AS14/AO14) -> 3.1056283 | AW14: =AS14*E14 -> 29018.836
B15: 497824944 | C15: MR Р1886 корич | D15: Солнцезащитные очки | E15: =F15+G15+H15 -> 33 | F15: 2 | G15: 1 | H15: 30 | I15: 169.89 | J15: =E15*I15 -> 5606.37 | K15: 200 | L15: 3 | M15: 1232 | N15: 50 | O15: =L15/7 -> 0.42857143 | P15: =S15/7 -> 0.14285714 | Q15: 1 | R15: 0 | S15: =Q15+R15 -> 1 | T15: 743 | U15: 0 | V15: =T15+U15 -> 743 | W15: 1232 | X15: 0 | Y15: =W15+X15 -> 1232 | Z15: =L15*M15*N15/100 -> 1848 | AA15: =Y15/$Y$93 -> 0.0053129156 | AB15: =S15*I15 -> 169.89 | AC15: 449.19 | AD15: =IF(Y15=0,0,AC15/Y15) -> 0.36460227 | AE15: 271.91 | AI15: =IFERROR($AI$93*H15/$H$93,0) -> 17.593889 | AJ15: 0 | AK15: =V15*1% -> 7.43 | AL15: =Y15-AB15-AC15-AE15-AF15-AG15-AH15-AI15-AK15-AJ15 -> 315.98611 | AN15: =IF(S15=0,0,Y15/S15) -> 1232 | AO15: =I15 -> 169.89 | AP15: =IF(S15=0,0,AC15/S15) -> 449.19 | AQ15: =IF(Q15=0,AE15/1,AE15/Q15) -> 271.91 | AR15: =IF(Q15=0,0,(AF15+AG15)/Q15) -> 0 | AS15: {=_xlfn.IFS(S15=0,AL15,S15<0,AL15/-S15,S15>0,AL15/S15)} -> 315.98611 | AT15: =IF(AN15=0,0,AS15/AN15) -> 0.25648223 | AU15: =IF(AO15=0,0,AS15/AO15) -> 1.8599453 | AW15: =AS15*E15 -> 10427.542
B16: 806868318 | C16: qs001 | D16: Солнцезащитные очки | E16: =F16+G16+H16 -> 0 | F16: 0 | G16: 0 | H16: 0 | I16: 129.46 | J16: =E16*I16 -> 0 | L16: 0 | M16: 0 | N16: 0 | O16: =L16/7 -> 0 | P16: =S16/7 -> 0 | Q16: 0 | R16: 0 | S16: =Q16+R16 -> 0 | T16: 0 | U16: 0 | V16: =T16+U16 -> 0 | W16: 0 | X16: 0 | Y16: =W16+X16 -> 0 | Z16: =L16*M16*N16/100 -> 0 | AA16: =Y16/$Y$93 -> 0 | AB16: =S16*I16 -> 0 | AC16: 0 | AD16: =IF(Y16=0,0,AC16/Y16) -> 0 | AE16: 0 | AI16: =IFERROR($AI$93*H16/$H$93,0) -> 0 | AJ16: 0 | AK16: =V16*1% -> 0 | AL16: =Y16-AB16-AC16-AE16-AF16-AG16-AH16-AI16-AK16-AJ16 -> 0 | AN16: =IF(S16=0,0,Y16/S16) -> 0 | AO16: =I16 -> 129.46 | AP16: =IF(S16=0,0,AC16/S16) -> 0 | AQ16: =IF(Q16=0,AE16/1,AE16/Q16) -> 0 | AR16: =IF(Q16=0,0,(AF16+AG16)/Q16) -> 0 | AS16: {=_xlfn.IFS(S16=0,AL16,S16<0,AL16/-S16,S16>0,AL16/S16)} -> 0 | AT16: =IF(AN16=0,0,AS16/AN16) -> 0 | AU16: =IF(AO16=0,0,AS16/AO16) -> 0 | AW16: =AS16*E16 -> 0
B17: 806885508 | C17: qs002 | D17: Солнцезащитные очки | E17: =F17+G17+H17 -> 0 | F17: 0 | G17: 0 | H17: 0 | I17: 117.76 | J17: =E17*I17 -> 0 | L17: 2 | M17: 1350 | N17: 0 | O17: =L17/7 -> 0.28571429 | P17: =S17/7 -> 0 | Q17: 0 | R17: 0 | S17: =Q17+R17 -> 0 | T17: 0 | U17: 0 | V17: =T17+U17 -> 0 | W17: 0 | X17: 0 | Y17: =W17+X17 -> 0 | Z17: =L17*M17*N17/100 -> 0 | AA17: =Y17/$Y$93 -> 0 | AB17: =S17*I17 -> 0 | AC17: 0 | AD17: =IF(Y17=0,0,AC17/Y17) -> 0 | AE17: 0 | AI17: =IFERROR($AI$93*H17/$H$93,0) -> 0 | AJ17: 0 | AK17: =V17*1% -> 0 | AL17: =Y17-AB17-AC17-AE17-AF17-AG17-AH17-AI17-AK17-AJ17 -> 0 | AN17: =IF(S17=0,0,Y17/S17) -> 0 | AO17: =I17 -> 117.76 | AP17: =IF(S17=0,0,AC17/S17) -> 0 | AQ17: =IF(Q17=0,AE17/1,AE17/Q17) -> 0 | AR17: =IF(Q17=0,0,(AF17+AG17)/Q17) -> 0 | AS17: {=_xlfn.IFS(S17=0,AL17,S17<0,AL17/-S17,S17>0,AL17/S17)} -> 0 | AT17: =IF(AN17=0,0,AS17/AN17) -> 0 | AU17: =IF(AO17=0,0,AS17/AO17) -> 0 | AW17: =AS17*E17 -> 0
B18: 807019357 | C18: qs003 | D18: Солнцезащитные очки | E18: =F18+G18+H18 -> 0 | F18: 0 | G18: 0 | H18: 0 | I18: 129.46 | J18: =E18*I18 -> 0 | L18: 0 | M18: 0 | N18: 0 | O18: =L18/7 -> 0 | P18: =S18/7 -> 0 | Q18: 0 | R18: 0 | S18: =Q18+R18 -> 0 | T18: 0 | U18: 0 | V18: =T18+U18 -> 0 | W18: 0 | X18: 0 | Y18: =W18+X18 -> 0 | Z18: =L18*M18*N18/100 -> 0 | AA18: =Y18/$Y$93 -> 0 | AB18: =S18*I18 -> 0 | AC18: 0 | AD18: =IF(Y18=0,0,AC18/Y18) -> 0 | AE18: 0 | AI18: =IFERROR($AI$93*H18/$H$93,0) -> 0 | AJ18: 0 | AK18: =V18*1% -> 0 | AL18: =Y18-AB18-AC18-AE18-AF18-AG18-AH18-AI18-AK18-AJ18 -> 0 | AN18: =IF(S18=0,0,Y18/S18) -> 0 | AO18: =I18 -> 129.46 | AP18: =IF(S18=0,0,AC18/S18) -> 0 | AQ18: =IF(Q18=0,AE18/1,AE18/Q18) -> 0 | AR18: =IF(Q18=0,0,(AF18+AG18)/Q18) -> 0 | AS18: {=_xlfn.IFS(S18=0,AL18,S18<0,AL18/-S18,S18>0,AL18/S18)} -> 0 | AT18: =IF(AN18=0,0,AS18/AN18) -> 0 | AU18: =IF(AO18=0,0,AS18/AO18) -> 0 | AW18: =AS18*E18 -> 0
B19: 807030321 | C19: qs005 | D19: Солнцезащитные очки | E19: =F19+G19+H19 -> 0 | F19: 0 | G19: 0 | H19: 0 | I19: 129.46 | J19: =E19*I19 -> 0 | L19: 0 | M19: 0 | N19: 0 | O19: =L19/7 -> 0 | P19: =S19/7 -> 0 | Q19: 0 | R19: 0 | S19: =Q19+R19 -> 0 | T19: 0 | U19: 0 | V19: =T19+U19 -> 0 | W19: 0 | X19: 0 | Y19: =W19+X19 -> 0 | Z19: =L19*M19*N19/100 -> 0 | AA19: =Y19/$Y$93 -> 0 | AB19: =S19*I19 -> 0 | AC19: 0 | AD19: =IF(Y19=0,0,AC19/Y19) -> 0 | AE19: 0 | AI19: =IFERROR($AI$93*H19/$H$93,0) -> 0 | AJ19: 0 | AK19: =V19*1% -> 0 | AL19: =Y19-AB19-AC19-AE19-AF19-AG19-AH19-AI19-AK19-AJ19 -> 0 | AN19: =IF(S19=0,0,Y19/S19) -> 0 | AO19: =I19 -> 129.46 | AP19: =IF(S19=0,0,AC19/S19) -> 0 | AQ19: =IF(Q19=0,AE19/1,AE19/Q19) -> 0 | AR19: =IF(Q19=0,0,(AF19+AG19)/Q19) -> 0 | AS19: {=_xlfn.IFS(S19=0,AL19,S19<0,AL19/-S19,S19>0,AL19/S19)} -> 0 | AT19: =IF(AN19=0,0,AS19/AN19) -> 0 | AU19: =IF(AO19=0,0,AS19/AO19) -> 0 | AW19: =AS19*E19 -> 0
B20: 807031830 | C20: qs006 | D20: Солнцезащитные очки | E20: =F20+G20+H20 -> 0 | F20: 0 | G20: 0 | H20: 0 | I20: 129.46 | J20: =E20*I20 -> 0 | L20: 0 | M20: 0 | N20: 0 | O20: =L20/7 -> 0 | P20: =S20/7 -> 0 | Q20: 0 | R20: 0 | S20: =Q20+R20 -> 0 | T20: 0 | U20: 0 | V20: =T20+U20 -> 0 | W20: 0 | X20: 0 | Y20: =W20+X20 -> 0 | Z20: =L20*M20*N20/100 -> 0 | AA20: =Y20/$Y$93 -> 0 | AB20: =S20*I20 -> 0 | AC20: 0 | AD20: =IF(Y20=0,0,AC20/Y20) -> 0 | AE20: 0 | AI20: =IFERROR($AI$93*H20/$H$93,0) -> 0 | AJ20: 0 | AK20: =V20*1% -> 0 | AL20: =Y20-AB20-AC20-AE20-AF20-AG20-AH20-AI20-AK20-AJ20 -> 0 | AN20: =IF(S20=0,0,Y20/S20) -> 0 | AO20: =I20 -> 129.46 | AP20: =IF(S20=0,0,AC20/S20) -> 0 | AQ20: =IF(Q20=0,AE20/1,AE20/Q20) -> 0 | AR20: =IF(Q20=0,0,(AF20+AG20)/Q20) -> 0 | AS20: {=_xlfn.IFS(S20=0,AL20,S20<0,AL20/-S20,S20>0,AL20/S20)} -> 0 | AT20: =IF(AN20=0,0,AS20/AN20) -> 0 | AU20: =IF(AO20=0,0,AS20/AO20) -> 0 | AW20: =AS20*E20 -> 0
B21: 806776658 | C21: qs013 | D21: Солнцезащитные очки | E21: =F21+G21+H21 -> 0 | F21: 0 | G21: 0 | H21: 0 | I21: 135.31 | J21: =E21*I21 -> 0 | L21: 1 | M21: 990 | N21: 0 | O21: =L21/7 -> 0.14285714 | P21: =S21/7 -> 0 | Q21: 0 | R21: 0 | S21: =Q21+R21 -> 0 | T21: 0 | U21: 0 | V21: =T21+U21 -> 0 | W21: 0 | X21: 0 | Y21: =W21+X21 -> 0 | Z21: =L21*M21*N21/100 -> 0 | AA21: =Y21/$Y$93 -> 0 | AB21: =S21*I21 -> 0 | AC21: 0 | AD21: =IF(Y21=0,0,AC21/Y21) -> 0 | AE21: 0 | AI21: =IFERROR($AI$93*H21/$H$93,0) -> 0 | AJ21: 0 | AK21: =V21*1% -> 0 | AL21: =Y21-AB21-AC21-AE21-AF21-AG21-AH21-AI21-AK21-AJ21 -> 0 | AN21: =IF(S21=0,0,Y21/S21) -> 0 | AO21: =I21 -> 135.31 | AP21: =IF(S21=0,0,AC21/S21) -> 0 | AQ21: =IF(Q21=0,AE21/1,AE21/Q21) -> 0 | AR21: =IF(Q21=0,0,(AF21+AG21)/Q21) -> 0 | AS21: {=_xlfn.IFS(S21=0,AL21,S21<0,AL21/-S21,S21>0,AL21/S21)} -> 0 | AT21: =IF(AN21=0,0,AS21/AN21) -> 0 | AU21: =IF(AO21=0,0,AS21/AO21) -> 0 | AW21: =AS21*E21 -> 0
B22: 806769378 | C22: qs014 | D22: Солнцезащитные очки | E22: =F22+G22+H22 -> 0 | F22: 0 | G22: 0 | H22: 0 | I22: 135.31 | J22: =E22*I22 -> 0 | L22: 3 | M22: 1100 | N22: 0 | O22: =L22/7 -> 0.42857143 | P22: =S22/7 -> 0 | Q22: 0 | R22: 0 | S22: =Q22+R22 -> 0 | T22: 0 | U22: 0 | V22: =T22+U22 -> 0 | W22: 0 | X22: 0 | Y22: =W22+X22 -> 0 | Z22: =L22*M22*N22/100 -> 0 | AA22: =Y22/$Y$93 -> 0 | AB22: =S22*I22 -> 0 | AC22: 0 | AD22: =IF(Y22=0,0,AC22/Y22) -> 0 | AE22: 0 | AG22: 7 | AI22: =IFERROR($AI$93*H22/$H$93,0) -> 0 | AJ22: 0 | AK22: =V22*1% -> 0 | AL22: =Y22-AB22-AC22-AE22-AF22-AG22-AH22-AI22-AK22-AJ22 -> -7 | AN22: =IF(S22=0,0,Y22/S22) -> 0 | AO22: =I22 -> 135.31 | AP22: =IF(S22=0,0,AC22/S22) -> 0 | AQ22: =IF(Q22=0,AE22/1,AE22/Q22) -> 0 | AR22: =IF(Q22=0,0,(AF22+AG22)/Q22) -> 0 | AS22: {=_xlfn.IFS(S22=0,AL22,S22<0,AL22/-S22,S22>0,AL22/S22)} -> -7 | AT22: =IF(AN22=0,0,AS22/AN22) -> 0 | AU22: =IF(AO22=0,0,AS22/AO22) -> -0.051733057 | AW22: =AS22*E22 -> 0
B23: 806737023 | C23: qs015 | D23: Солнцезащитные очки | E23: =F23+G23+H23 -> 0 | F23: 0 | G23: 0 | H23: 0 | I23: 135.31 | J23: =E23*I23 -> 0 | L23: 3 | M23: 2900 | N23: 0 | O23: =L23/7 -> 0.42857143 | P23: =S23/7 -> 0 | Q23: 0 | R23: 0 | S23: =Q23+R23 -> 0 | T23: 0 | U23: 0 | V23: =T23+U23 -> 0 | W23: 0 | X23: 0 | Y23: =W23+X23 -> 0 | Z23: =L23*M23*N23/100 -> 0 | AA23: =Y23/$Y$93 -> 0 | AB23: =S23*I23 -> 0 | AC23: 0 | AD23: =IF(Y23=0,0,AC23/Y23) -> 0 | AE23: 0 | AI23: =IFERROR($AI$93*H23/$H$93,0) -> 0 | AJ23: 0 | AK23: =V23*1% -> 0 | AL23: =Y23-AB23-AC23-AE23-AF23-AG23-AH23-AI23-AK23-AJ23 -> 0 | AN23: =IF(S23=0,0,Y23/S23) -> 0 | AO23: =I23 -> 135.31 | AP23: =IF(S23=0,0,AC23/S23) -> 0 | AQ23: =IF(Q23=0,AE23/1,AE23/Q23) -> 0 | AR23: =IF(Q23=0,0,(AF23+AG23)/Q23) -> 0 | AS23: {=_xlfn.IFS(S23=0,AL23,S23<0,AL23/-S23,S23>0,AL23/S23)} -> 0 | AT23: =IF(AN23=0,0,AS23/AN23) -> 0 | AU23: =IF(AO23=0,0,AS23/AO23) -> 0 | AW23: =AS23*E23 -> 0
