Workbook

Sheet Сводная
A1: Период | D1: Итого к перечислению на счет, руб | E1: шт. | H1: Выручка | K1: Себестоимость продаж | L1: Логистика | M1: Комиссия | N1: Хранение | O1: Платная приемка | P1: Штрафы | Q1: Реклама Ozon | R1: Другие услуги и штрафы | S1: Услуги агентов | T1: Услуги FBO | U1: Компенсировано | V1: Пополнение рекламного кабинета | W1: ЕАЭС | X1: Налог | Y1: Прибыль до вычета налогов | Z1: Прибыль после вычета налогов | AA1: Итог месяц | AB1: % Cебестоимости | AC1: Маржинальность, % | AD1: Рентабельность, % | AE1: Доля рекламы, % | AG1: Данные для построения диаграмм
A2: Месяц | B2: Даты | C2: Нед | E2: Заказы | F2: Продажи | G2: Возвраты | H2: Продажи | I2: Возвраты | J2: Общая | AG2: Нед | AH2: По магазину | AI2: По очкам | AJ2: По туникам
A3: Январь | B3: 01-04.01 очки | D3: =J3-SUM(L3:T3)+U3+V3 -> 6689.7486 | E3: ='Юнит 01-04.01'!K$26 -> 44 | F3: ='Юнит 01-04.01'!P$26 -> 28 | G3: ='Юнит 01-04.01'!Q$26 -> 0 | H3: ='Юнит 01-04.01'!S$26 -> 45978 | I3: ='Юнит 01-04.01'!T$26 -> 0 | J3: =H3+I3 -> 45978 | K3: ='Юнит 01-04.01'!W$26 -> 4528.66 | L3: ='Юнит 01-04.01'!Z$26 -> 3709.34 | M3: ='Юнит 01-04.01'!X$26 -> 19770.54 | Q3: ='Юнит 01-04.01'!AA$26 -> 14387.481 | S3: 808.39 | T3: 612.5 | W3: 2545 | X3: =2656.15*J3/SUM($J$3:$J$12) -> 193.86959 | Y3: =J3-SUM(L3:T3)-K3-V3+U3+W3 -> 4706.0886 | Z3: =Y3-X3 -> 4512.219 | AA3: =SUM(Z3:Z12) -> 53230.01 | AB3: =K3/J3 -> 0.098496237 | AC3: =Z3/K3 -> 0.99636957 | AD3: =Z3/J3 -> 0.098138654 | AE3: =Q3/J3 -> 0.31292099
B4: 01-04.01 туники | D4: =J4-SUM(L4:T4)+U4+V4+W4 -> 1720.7514 | E4: ='Юнит 01-04.01'!K$49 -> 5 | F4: ='Юнит 01-04.01'!P$49 -> 1 | G4: ='Юнит 01-04.01'!Q$49 -> 0 | H4: ='Юнит 01-04.01'!S$49 -> 4247 | I4: ='Юнит 01-04.01'!T$49 -> 0 | J4: =H4+I4 -> 4247 | K4: ='Юнит 01-04.01'!W$49 -> 597 | L4: ='Юнит 01-04.01'!Z$49 -> 186.2 | M4: ='Юнит 01-04.01'!X$49 -> 1826.21 | Q4: ='Юнит 01-04.01'!AA$49 -> 513.83862 | X4: =2656.15*J4/SUM($J$3:$J$12) -> 17.907785 | Y4: =J4-SUM(L4:T4)-K4-V4+U4+W4 -> 1123.7514 | Z4: =Y4-X4 -> 1105.8436 | AB4: =K4/J4 -> 0.14056981 | AC4: =Z4/K4 -> 1.8523343 | AD4: =Z4/J4 -> 0.26038229 | AE4: =Q4/J4 -> 0.12098861
B5: 05-11.01 очки | D5: =J5-SUM(L5:T5)+U5+V5+W5 -> 15120.024 | E5: ='Юнит 05-11.01'!K$26 -> 74 | F5: ='Юнит 05-11.01'!P$26 -> 58 | G5: ='Юнит 05-11.01'!Q$26 -> 4 | H5: ='Юнит 05-11.01'!S$26 -> 92160 | I5: ='Юнит 05-11.01'!T$26 -> -6799 | J5: =H5+I5 -> 85361 | K5: ='Юнит 05-11.01'!W$26 -> 7651.8 | L5: ='Юнит 05-11.01'!Z$26 -> 9950.27 | M5: ='Юнит 05-11.01'!X$26 -> 36705.23 | Q5: ='Юнит 05-11.01'!AA$26 -> 20346.216 | R5: 5 | S5: 1918.46 | T5: 1315.8 | X5: =2656.15*J5/SUM($J$3:$J$12) -> 359.93088 | Y5: =J5-SUM(L5:T5)-K5-V5+U5+W5 -> 7468.2237 | Z5: =Y5-X5 -> 7108.2928 | AB5: =K5/J5 -> 0.089640468 | AC5: =Z5/K5 -> 0.92897002 | AD5: =Z5/J5 -> 0.083273307 | AE5: =Q5/J5 -> 0.23835494
B6: 05-11.01 туники | D6: =J6-SUM(L6:T6)+U6+V6+W6 -> 4389.7863 | E6: ='Юнит 05-11.01'!K$49 -> 4 | F6: ='Юнит 05-11.01'!P$49 -> 2 | G6: ='Юнит 05-11.01'!Q$49 -> 0 | H6: ='Юнит 05-11.01'!S$49 -> 10524 | I6: ='Юнит 05-11.01'!T$49 -> 0 | J6: =H6+I6 -> 10524 | K6: ='Юнит 05-11.01'!W$49 -> 1329 | L6: ='Юнит 05-11.01'!Z$49 -> 907.3 | M6: ='Юнит 05-11.01'!X$49 -> 4525.32 | Q6: ='Юнит 05-11.01'!AA$49 -> 701.59367 | X6: =2656.15*J6/SUM($J$3:$J$12) -> 44.375213 | Y6: =J6-SUM(L6:T6)-K6-V6+U6+W6 -> 3060.7863 | Z6: =Y6-X6 -> 3016.4111 | AB6: =K6/J6 -> 0.12628278 | AC6: =Z6/K6 -> 2.2696848 | AD6: =Z6/J6 -> 0.28662211 | AE6: =Q6/J6 -> 0.066666065
B7: 12-18.01 очки | D7: =J7-SUM(L7:T7)+U7+V7+W7 -> 25837.298 | E7: ='Юнит 12-18.01'!K$26 -> 96 | F7: ='Юнит 12-18.01'!P$26 -> 56 | G7: ='Юнит 12-18.01'!Q$26 -> 0 | H7: ='Юнит 12-18.01'!S$26 -> 91762 | I7: ='Юнит 12-18.01'!T$26 -> 0 | J7: =H7+I7 -> 91762 | K7: ='Юнит 12-18.01'!W$26 -> 7841.91 | L7: ='Юнит 12-18.01'!Z$26 -> 9811.64 | M7: ='Юнит 12-18.01'!X$26 -> 39457.66 | Q7: ='Юнит 12-18.01'!AA$26 -> 22526.532 | S7: 2168.87 | T7: 800 | V7: 7000 | W7: 1840 | X7: =2656.15*J7/SUM($J$3:$J$12) -> 386.92116 | Y7: =J7-SUM(L7:T7)-K7-V7+U7+W7 -> 3995.3875 | Z7: =Y7-X7 -> 3608.4664 | AB7: =K7/J7 -> 0.085459231 | AC7: =Z7/K7 -> 0.46015147 | AD7: =Z7/J7 -> 0.039324191 | AE7: =Q7/J7 -> 0.24548868
B8: 12-18.01 туники | D8: =J8-SUM(L8:T8)+U8+V8+W8 -> 8441.1125 | E8: ='Юнит 12-18.01'!K$49 -> 30 | F8: ='Юнит 12-18.01'!P$49 -> 5 | G8: ='Юнит 12-18.01'!Q$49 -> 0 | H8: ='Юнит 12-18.01'!S$49 -> 21020 | I8: ='Юнит 12-18.01'!T$49 -> 0 | J8: =H8+I8 -> 21020 | K8: ='Юнит 12-18.01'!W$49 -> 3435 | L8: ='Юнит 12-18.01'!Z$49 -> 1528.99 | M8: ='Юнит 12-18.01'!X$49 -> 9038.6 | Q8: ='Юнит 12-18.01'!AA$49 -> 2011.2975 | X8: =2656.15*J8/SUM($J$3:$J$12) -> 88.632363 | Y8: =J8-SUM(L8:T8)-K8-V8+U8+W8 -> 5006.1125 | Z8: =Y8-X8 -> 4917.4801 | AB8: =K8/J8 -> 0.16341579 | AC8: =Z8/K8 -> 1.4315808 | AD8: =Z8/J8 -> 0.23394292 | AE8: =Q8/J8 -> 0.095684945
B9: 19-25.01 очки | D9: =J9-SUM(L9:T9)+U9+V9+W9 -> 15283.413 | E9: ='Юнит 19-25.01'!K$26 -> 119 | F9: ='Юнит 19-25.01'!P$26 -> 64 | G9: ='Юнит 19-25.01'!Q$26 -> 1 | H9: ='Юнит 19-25.01'!S$26 -> 104586 | I9: ='Юнит 19-25.01'!T$26 -> -1670 | J9: =H9+I9 -> 102916 | K9: ='Юнит 19-25.01'!W$26 -> 9494.98 | L9: ='Юнит 19-25.01'!Z$26 -> 12870.13 | M9: ='Юнит 19-25.01'!X$26 -> 44253.88 | Q9: ='Юнит 19-25.01'!AA$26 -> 31721.257 | R9: 15 | S9: 3536.42 | T9: 2235.9 | V9: 7000 | X9: =2656.15*J9/SUM($J$3:$J$12) -> 433.95282 | Y9: =J9-SUM(L9:T9)-K9-V9+U9+W9 -> -8211.5666 | Z9: =Y9-X9 -> -8645.5194 | AB9: =K9/J9 -> 0.092259513 | AC9: =Z9/K9 -> -0.91053582 | AD9: =Z9/J9 -> -0.084005591 | AE9: =Q9/J9 -> 0.30822473
B10: 19-25.01 туники | D10: =J10-SUM(L10:T10)+U10+V10+W10 -> 20301.697 | E10: ='Юнит 19-25.01'!K$49 -> 66 | F10: ='Юнит 19-25.01'!P$49 -> 18 | G10: ='Юнит 19-25.01'!Q$49 -> 4 | H10: ='Юнит 19-25.01'!S$49 -> 80413 | I10: ='Юнит 19-25.01'!T$49 -> -17932 | J10: =H10+I10 -> 62481 | K10: ='Юнит 19-25.01'!W$49 -> 9468 | L10: ='Юнит 19-25.01'!Z$49 -> 6390.87 | M10: ='Юнит 19-25.01'!X$49 -> 26866.83 | Q10: ='Юнит 19-25.01'!AA$49 -> 8921.6034 | X10: =2656.15*J10/SUM($J$3:$J$12) -> 263.45569 | Y10: =J10-SUM(L10:T10)-K10-V10+U10+W10 -> 10833.697 | Z10: =Y10-X10 -> 10570.241 | AB10: =K10/J10 -> 0.15153407 | AC10: =Z10/K10 -> 1.1164175 | AD10: =Z10/J10 -> 0.16917528 | AE10: =Q10/J10 -> 0.14278906
B11: 26-31.01 очки | D11: =J11-SUM(L11:T11)+U11+V11+W11 -> 17829.042 | E11: ='Юнит 26-31.01'!K$26 -> 100 | F11: ='Юнит 26-31.01'!P$26 -> 72 | G11: ='Юнит 26-31.01'!Q$26 -> 3 | H11: ='Юнит 26-31.01'!S$26 -> 120331 | I11: ='Юнит 26-31.01'!T$26 -> -4419 | J11: =H11+I11 -> 115912 | K11: ='Юнит 26-31.01'!W$26 -> 10470.94 | L11: ='Юнит 26-31.01'!Z$26 -> 13196.61 | M11: ='Юнит 26-31.01'!X$26 -> 49842.16 | Q11: ='Юнит 26-31.01'!AA$26 -> 25632.258 | R11: 25 | S11: 2141.43 | T11: 7245.5 | X11: =2656.15*J11/SUM($J$3:$J$12) -> 488.7514 | Y11: =J11-SUM(L11:T11)-K11-V11+U11+W11 -> 7358.1017 | Z11: =Y11-X11 -> 6869.3503 | AB11: =K11/J11 -> 0.090335254 | AC11: =Z11/K11 -> 0.65603951 | AD11: =Z11/J11 -> 0.059263496 | AE11: =Q11/J11 -> 0.2211355
B12: 26-31.01 туники | D12: =J12-SUM(L12:T12)+U12+V12+W12 -> 33880.578 | E12: ='Юнит 26-31.01'!K$49 -> 60 | F12: ='Юнит 26-31.01'!P$49 -> 20 | G12: ='Юнит 26-31.01'!Q$49 -> 0 | H12: ='Юнит 26-31.01'!S$49 -> 89730 | I12: ='Юнит 26-31.01'!T$49 -> 0 | J12: =H12+I12 -> 89730 | K12: ='Юнит 26-31.01'!W$49 -> 13335 | L12: ='Юнит 26-31.01'!Z$49 -> 8653.99 | M12: ='Юнит 26-31.01'!X$49 -> 38583.9 | Q12: ='Юнит 26-31.01'!AA$49 -> 7120.0717 | S12: 1491.46 | X12: =2656.15*J12/SUM($J$3:$J$12) -> 378.35309 | Y12: =J12-SUM(L12:T12)-K12-V12+U12+W12 -> 20545.578 | Z12: =Y12-X12 -> 20167.225 | AB12: =K12/J12 -> 0.1486125 | AC12: =Z12/K12 -> 1.5123528 | AD12: =Z12/J12 -> 0.22475454 | AE12: =Q12/J12 -> 0.079349958
A13: Февраль | B13: 01.02 очки | D13: =J13-SUM(L13:T13)+U13+V13 -> -2468.0211 | E13: ='Юнит 01.02'!K$26 -> 19 | F13: ='Юнит 01.02'!P$26 -> 8 | G13: ='Юнит 01.02'!Q$26 -> 1 | H13: ='Юнит 01.02'!S$26 -> 13169 | I13: ='Юнит 01.02'!T$26 -> -1655 | J13: =H13+I13 -> 11514 | K13: ='Юнит 01.02'!W$26 -> 1054.68 | L13: ='Юнит 01.02'!Z$26 -> 1614.84 | M13: ='Юнит 01.02'!X$26 -> 4951.02 | Q13: ='Юнит 01.02'!AA$26 -> 7028.3911 | S13: 387.77 | T13: 0 | W13: 902 | X13: ='Юнит 01.02'!AD26 -> 52.608637 | Y13: =J13-SUM(L13:T13)-K13-V13+U13+W13 -> -2620.7011 | Z13: =J13-SUM(L13:T13)-K13-X13+U13+W13-V13 -> -2673.3097 | AA13: =SUM(Z13:Z22) -> 104464.56 | AB13: =K13/J13 -> 0.091599792 | AC13: =Z13/K13 -> -2.5347117 | AD13: =Z13/J13 -> -0.23217906 | AE13: =Q13/J13 -> 0.61042132
B14: 01.02 туники | D14: =J14-SUM(L14:T14)+U14+V14+W14 -> 42.021111 | E14: ='Юнит 01.02'!K$49 -> 7 | F14: ='Юнит 01.02'!P$49 -> 1 | G14: ='Юнит 01.02'!Q$49 -> 0 | H14: ='Юнит 01.02'!S$49 -> 4940 | I14: ='Юнит 01.02'!T$49 -> 0 | J14: =H14+I14 -> 4940 | K14: ='Юнит 01.02'!W$49 -> 687 | L14: ='Юнит 01.02'!Z$49 -> 1483.67 | M14: ='Юнит 01.02'!X$49 -> 2124.2 | Q14: ='Юнит 01.02'!AA$49 -> 878.54889 | R14: 5 | S14: 406.56 | X14: ='Юнит 01.02'!AD49 -> 22.571363 | Y14: =J14-SUM(L14:T14)-K14-V14+U14+W14 -> -644.97889 | Z14: =J14-SUM(L14:T14)-K14-X14+U14+W14-V14 -> -667.55025 | AB14: =K14/J14 -> 0.13906883 | AC14: =Z14/K14 -> -0.97168887 | AD14: =Z14/J14 -> -0.13513163 | AE14: =Q14/J14 -> 0.1778439
B15: 02-08.02 очки | D15: =J15-SUM(L15:T15)+U15+V15 -> 11894.962 | E15: ='Юнит 02-08.02'!K$26 -> 131 | F15: ='Юнит 02-08.02'!P$26 -> 65 | G15: ='Юнит 02-08.02'!Q$26 -> 5 | H15: ='Юнит 02-08.02'!S$26 -> 119818 | I15: ='Юнит 02-08.02'!T$26 -> -9187 | J15: =H15+I15 -> 110631 | K15: ='Юнит 02-08.02'!W$26 -> 9043.72 | L15: ='Юнит 02-08.02'!Z$26 -> 13862.81 | M15: ='Юнит 02-08.02'!X$26 -> 47571.33 | Q15: ='Юнит 02-08.02'!AA$26 -> 34221.478 | S15: 3080.42 | T15: 0 | X15: ='Юнит 02-08.02'!AD26 -> 495.41892 | Y15: =J15-SUM(L15:T15)-K15-V15+U15+W15 -> 2851.2425 | Z15: =J15-SUM(L15:T15)-K15-X15+U15+W15-V15 -> 2355.8235 | AB15: =K15/J15 -> 0.081746708 | AC15: =Z15/K15 -> 0.26049276 | AD15: =Z15/J15 -> 0.021294425 | AE15: =Q15/J15 -> 0.30932991
B16: 02-08.02 туники | D16: =J16-SUM(L16:T16)+U16+V16+W16 -> 36220.938 | E16: ='Юнит 02-08.02'!K$49 -> 68 | F16: ='Юнит 02-08.02'!P$49 -> 24 | G16: ='Юнит 02-08.02'!Q$49 -> 1 | H16: ='Юнит 02-08.02'!S$49 -> 114048 | I16: ='Юнит 02-08.02'!T$49 -> -4178 | J16: =H16+I16 -> 109870 | K16: ='Юнит 02-08.02'!W$49 -> 14496 | L16: ='Юнит 02-08.02'!Z$49 -> 11481.36 | M16: ='Юнит 02-08.02'!X$49 -> 47244.1 | Q16: ='Юнит 02-08.02'!AA$49 -> 12635.622 | R16: 20 | S16: 2267.98 | T16: 0 | X16: ='Юнит 02-08.02'!AD49 -> 492.01108 | Y16: =J16-SUM(L16:T16)-K16-V16+U16+W16 -> 21724.938 | Z16: =J16-SUM(L16:T16)-K16-X16+U16+W16-V16 -> 21232.926 | AB16: =K16/J16 -> 0.13193774 | AC16: =Z16/K16 -> 1.4647438 | AD16: =Z16/J16 -> 0.193255 | AE16: =Q16/J16 -> 0.11500521
B17: 09-15.02 очки | D17: =J17-SUM(L17:T17)+U17+V17 -> 16731.718 | E17: ='Юнит 09-15.02'!K$26 -> 121 | F17: ='Юнит 09-15.02'!P$26 -> 60 | G17: ='Юнит 09-15.02'!Q$26 -> 2 | H17: ='Юнит 09-15.02'!S$26 -> 125456 | I17: ='Юнит 09-15.02'!T$26 -> -4877 | J17: =H17+I17 -> 120579 | K17: ='Юнит 09-15.02'!W$26 -> 7423.19 | L17: ='Юнит 09-15.02'!Z$26 -> 13659.9 | M17: ='Юнит 09-15.02'!X$26 -> 51848.97 | Q17: ='Юнит 09-15.02'!AA$26 -> 32650.368 | S17: 3309.41 | T17: =3250.8*F17/(F17+F18) -> 2378.6341 | X17: ='Юнит 09-15.02'!AD26 -> 529.24794 | Y17: =J17-SUM(L17:T17)-K17-V17+U17+W17 -> 9308.5276 | Z17: =J17-SUM(L17:T17)-K17-X17+U17+W17-V17 -> 8779.2796 | AB17: =K17/J17 -> 0.061562876 | AC17: =Z17/K17 -> 1.1826829 | AD17: =Z17/J17 -> 0.072809358 | AE17: =Q17/J17 -> 0.27077989
B18: 09-15.02 туники | D18: =J18-SUM(L18:T18)+U18+V18+W18 -> 34546.812 | E18: ='Юнит 09-15.02'!K$49 -> 54 | F18: ='Юнит 09-15.02'!P$49 -> 22 | G18: ='Юнит 09-15.02'!Q$49 -> 2 | H18: ='Юнит 09-15.02'!S$49 -> 110799 | I18: ='Юнит 09-15.02'!T$49 -> -9047 | J18: =H18+I18 -> 101752 | K18: ='Юнит 09-15.02'!W$49 -> 13275 | L18: ='Юнит 09-15.02'!Z$49 -> 8720.99 | M18: ='Юнит 09-15.02'!X$49 -> 43753.36 | Q18: ='Юнит 09-15.02'!AA$49 -> 11971.802 | R18: 25 | S18: 1861.87 | T18: =3250.8*F18/(F17+F18) -> 872.16585 | X18: ='Юнит 09-15.02'!AD49 -> 446.61206 | Y18: =J18-SUM(L18:T18)-K18-V18+U18+W18 -> 21271.812 | Z18: =J18-SUM(L18:T18)-K18-X18+U18+W18-V18 -> 20825.2 | AB18: =K18/J18 -> 0.13046427 | AC18: =Z18/K18 -> 1.5687533 | AD18: =Z18/J18 -> 0.20466625 | AE18: =Q18/J18 -> 0.11765667
B19: 16-22.02 очки | D19: =J19-SUM(L19:T19)+U19+V19 -> 31466.122 | E19: ='Юнит 16-22.02'!K$26 -> 172 | F19: ='Юнит 16-22.02'!P$26 -> 79 | G19: ='Юнит 16-22.02'!Q$26 -> 2 | H19: ='Юнит 16-22.02'!S$26 -> 173410 | I19: ='Юнит 16-22.02'!T$26 -> -4800 | J19: =H19+I19 -> 168610 | K19: ='Юнит 16-22.02'!W$26 -> 11163.54 | L19: ='Юнит 16-22.02'!Z$26 -> 17063.86 | M19: ='Юнит 16-22.02'!X$26 -> 72502.3 | Q19: ='Юнит 16-22.02'!AA$26 -> 43572.808 | S19: 4004.91 | T19: 0 | W19: 4158 | X19: ='Юнит 16-22.02'!AD$26 -> 745.37032 | Y19: =J19-SUM(L19:T19)-K19-V19+U19+W19 -> 24460.582 | Z19: =J19-SUM(L19:T19)-K19-X19+U19+W19-V19 -> 23715.212 | AB19: =K19/J19 -> 0.06620924 | AC19: =Z19/K19 -> 2.1243451 | AD19: =Z19/J19 -> 0.14065128 | AE19: =Q19/J19 -> 0.25842363
B20: 16-22.02 туники | D20: =J20-SUM(L20:T20)+U20+V20+W20 -> 46897.758 | E20: ='Юнит 16-22.02'!K$49 -> 78 | F20: ='Юнит 16-22.02'!P$49 -> 27 | G20: ='Юнит 16-22.02'!Q$49 -> 2 | H20: ='Юнит 16-22.02'!S$49 -> 141378 | I20: ='Юнит 16-22.02'!T$49 -> -10000 | J20: =H20+I20 -> 131378 | K20: ='Юнит 16-22.02'!W$49 -> 15420 | L20: ='Юнит 16-22.02'!Z$49 -> 10936.38 | M20: ='Юнит 16-22.02'!X$49 -> 56492.54 | Q20: ='Юнит 16-22.02'!AA$49 -> 14891.972 | R20: 20 | S20: 2139.35 | T20: 0 | X20: ='Юнит 16-22.02'!AD$49 -> 580.77968 | Y20: =J20-SUM(L20:T20)-K20-V20+U20+W20 -> 31477.758 | Z20: =J20-SUM(L20:T20)-K20-X20+U20+W20-V20 -> 30896.978 | AB20: =K20/J20 -> 0.11737125 | AC20: =Z20/K20 -> 2.0036951 | AD20: =Z20/J20 -> 0.23517619 | AE20: =Q20/J20 -> 0.1133521
B21: 23-28.02 очки | X21: ='Юнит 23-28.02'!AD26 -> #DIV/0!
B22: 23-28.02 туники | X22: ='Юнит 23-28.02'!AD49 -> #DIV/0!
A23: Итого | D23: =SUM(D3:D22) -> 324825.76 | E23: =SUM(E3:E22) -> 1248 | F23: =SUM(F3:F22) -> 610 | G23: =SUM(G3:G22) -> 27 | H23: =SUM(H3:H22) -> 1463769 | I23: =SUM(I3:I22) -> -74564 | J23: =SUM(J3:J22) -> 1389205 | K23: =SUM(K3:K22) -> 140715.42 | ... AA23: =SUM(AA3:AA22) -> 157694.57 | AB23: =K23/J23 -> 0.10129205 | AC23: =Z23/K23 -> 1.120663 | AD23: =Z23/J23 -> 0.11351425 | AE23: =Q23/J23 -> 0.21000006
H24: % от выручки за весь период
I25: =-I23/H23 -> 0.050939732 | J25: 0 | K25: =K23/$J$23 -> 0.10129205 | L25: =L23/$J$23 -> 0.10511706 | M25: =M23/$J$23 -> 0.43 | Q25: =Q23/$J$23 -> 0.21000006 | R25: =R23/$J$23 -> 8.2781159e-05 | S25: =S23/$J$23 -> 0.021251939 | T25: =T23/$J$23 -> 0.011129027 | U25: =U23/$J$23 -> 0 | V25: =V23/$J$23 -> 0.010077706 | X25: =X23/$J$23 -> #DIV/0! | Z25: =Z23/K23 -> 1.120663 | AA25: Маржинальность, %
A27: январь очки | D27: =D3+D5+D7+D9+D11 -> 80759.525 | E27: =E3+E5+E7+E9+E11 -> 433 | F27: =F3+F5+F7+F9+F11 -> 278 | G27: =G3+G5+G7+G9+G11 -> 8 | H27: =H3+H5+H7+H9+H11 -> 454817 | I27: =I3+I5+I7+I9+I11 -> -12888 | J27: =J3+J5+J7+J9+J11 -> 441929 | K27: =K3+K5+K7+K9+K11 -> 39988.29 | ... Z27: =Z3+Z5+Z7+Z9+Z11 -> 13452.809 | AA27: =Z23/J23 -> 0.11351425
A28: январь туники | D28: =D4+D6+D8+D10+D12 -> 68733.925 | E28: =E4+E6+E8+E10+E12 -> 165 | F28: =F4+F6+F8+F10+F12 -> 46 | G28: =G4+G6+G8+G10+G12 -> 4 | H28: =H4+H6+H8+H10+H12 -> 205934 | I28: =I4+I6+I8+I10+I12 -> -17932 | J28: =J4+J6+J8+J10+J12 -> 188002 | K28: =K4+K6+K8+K10+K12 -> 28164 | ... Z28: =Z4+Z6+Z8+Z10+Z12 -> 39777.201
A29: январь итого | D29: =D27+D28 -> 149493.45 | E29: =E27+E28 -> 598 | F29: =F27+F28 -> 324 | G29: =G27+G28 -> 12 | H29: =H27+H28 -> 660751 | I29: =I27+I28 -> -30820 | J29: =J27+J28 -> 629931 | K29: =K27+K28 -> 68152.29 | ... Z29: =Z27+Z28 -> 53230.01
A31: 5 неделя очки | K31: =(K11+K13)/($J$11+$J$13) -> 0.090449516 | L31: =(L11+L13)/($J$11+$J$13) -> 0.1162357 | M31: =(M11+M13)/($J$11+$J$13) -> 0.43 | N31: =(N11+N13)/($J$11+$J$13) -> 0 | O31: =(O11+O13)/($J$11+$J$13) -> 0 | P31: =(P11+P13)/($J$11+$J$13) -> 0 | Q31: =(Q11+Q13)/($J$11+$J$13) -> 0.25631072 | R31: =(R11+S11+T11+R13+S13+T13)/($J$11+$J$13) -> 0.076905027 | U31: =(U11+U13)/($J$11+$J$13) -> 0 | V31: =(V11+V13)/($J$11+$J$13) -> 0 | W31: =(W11+W13)/($J$11+$J$13) -> 0.0070786182 | X31: =(X11+X13)/($J$11+$J$13) -> 0.0042484268 | Y31: =(Y11+Y13)/($J$11+$J$13) -> 0.037177661 | Z31: =(Z11+Z13)/($J$11+$J$13) -> 0.032929234
A32: 6 неделя очки | K32: =K15/$J$15 -> 0.081746708 | L32: =L15/$J$15 -> 0.12530674 | M32: =M15/$J$15 -> 0.43 | Q32: =Q15/$J$15 -> 0.30932991 | R32: =(R15+S15+T15)/$J$15 -> 0.027844094 | U32: =U15/$J$15 -> 0 | V32: =V15/$J$15 -> 0 | X32: =X15/$J$15 -> 0.0044781203 | Z32: =Z15/K15 -> 0.26049276
A33: 7 неделя очки | K33: =K17/$J$17 -> 0.061562876 | L33: =L17/$J$17 -> 0.1132859 | M33: =M17/$J$17 -> 0.43 | Q33: =Q17/$J$17 -> 0.27077989 | R33: =(R17+S17+T17)/$J$17 -> 0.047172759 | U33: =U17/$J$17 -> 0 | V33: =V17/$J$17 -> 0 | X33: =X17/$J$17 -> 0.0043892215 | Z33: =Z17/K17 -> 1.1826829
A34: 8 неделя очки | K34: =K19/$J$19 -> 0.06620924 | L34: =L19/$J$19 -> 0.10120313 | M34: =M19/$J$19 -> 0.43 | Q34: =Q19/$J$19 -> 0.25842363 | R34: =(R19+S19+T19)/$J$19 -> 0.023752506 | U34: =U19/$J$19 -> 0 | V34: =V19/$J$19 -> 0 | X34: =X19/$J$19 -> 0.0044206768 | Z34: =Z19/K19 -> 2.1243451

Sheet АВС 16-22.02
B2: ОЧКИ
C3: Прибыль | D3: % прибыль | E3: Доля | F3: ABC прибыль | G3: ABC кол-во | J3: Кол-во | K3: % кол-во | L3: Доля | M3: ABC кол-во
B4: черные с железкой классика | D4: =C4/C$26 -> #DIV/0! | E4: =D4 -> #DIV/0! | F4: =IF(AND(E4<=0),"C",IF(E4<=0.8,"A",IF(E4<=0.95,"B","C"))) -> #DIV/0! | G4: =VLOOKUP(B$4:B$25,I$4:M$25,5,0) -> #DIV/0! | I4: черные с железкой классика | K4: =J4/J$26 -> #DIV/0! | L4: =K4 -> #DIV/0! | M4: =_xlfn.IFS(L4<80%,"A",L4<=95%,"B",L4>95%,"C") -> #DIV/0!
B5: qs черные | D5: =C5/C$26 -> #DIV/0! | E5: =D5+E4 -> #DIV/0! | F5: =IF(AND(E5<=0),"C",IF(E5<=0.8,"A",IF(E5<=0.95,"B","C"))) -> #DIV/0! | G5: =VLOOKUP(B$4:B$25,I$4:M$25,5,0) -> #DIV/0! | I5: qs черные | K5: =J5/J$26 -> #DIV/0! | L5: =K5+L4 -> #DIV/0! | M5: =_xlfn.IFS(L5<80%,"A",L5<=95%,"B",L5>95%,"C") -> #DIV/0!
B6: qs синие | D6: =C6/C$26 -> #DIV/0! | E6: =D6+E5 -> #DIV/0! | F6: =IF(AND(E6<=0),"C",IF(E6<=0.8,"A",IF(E6<=0.95,"B","C"))) -> #DIV/0! | G6: =VLOOKUP(B$4:B$25,I$4:M$25,5,0) -> #DIV/0! | I6: qs синие | K6: =J6/J$26 -> #DIV/0! | L6: =K6+L5 -> #DIV/0! | M6: =_xlfn.IFS(L6<80%,"A",L6<=95%,"B",L6>95%,"C") -> #DIV/0!
B7: qs желтые | D7: =C7/C$26 -> #DIV/0! | E7: =D7+E6 -> #DIV/0! | F7: =IF(AND(E7<=0),"C",IF(E7<=0.8,"A",IF(E7<=0.95,"B","C"))) -> #DIV/0! | G7: =VLOOKUP(B$4:B$25,I$4:M$25,5,0) -> #DIV/0! | I7: qs желтые | K7: =J7/J$26 -> #DIV/0! | L7: =K7+L6 -> #DIV/0! | M7: =_xlfn.IFS(L7<80%,"A",L7<=95%,"B",L7>95%,"C") -> #DIV/0!
B8: qs коричневые | D8: =C8/C$26 -> #DIV/0! | E8: =D8+E7 -> #DIV/0! | F8: =IF(AND(E8<=0),"C",IF(E8<=0.8,"A",IF(E8<=0.95,"B","C"))) -> #DIV/0! | G8: =VLOOKUP(B$4:B$25,I$4:M$25,5,0) -> #DIV/0! | I8: qs коричневые | K8: =J8/J$26 -> #DIV/0! | L8: =K8+L7 -> #DIV/0! | M8: =_xlfn.IFS(L8<80%,"A",L8<=95%,"B",L8>95%,"C") -> #DIV/0!
B9: th желтый Сул | D9: =C9/C$26 -> #DIV/0! | E9: =D9+E8 -> #DIV/0! | F9: =IF(AND(E9<=0),"C",IF(E9<=0.8,"A",IF(E9<=0.95,"B","C"))) -> #DIV/0! | G9: =VLOOKUP(B$4:B$25,I$4:M$25,5,0) -> #DIV/0! | I9: th желтый Сул | K9: =J9/J$26 -> #DIV/0! | L9: =K9+L8 -> #DIV/0! | M9: =_xlfn.IFS(L9<80%,"A",L9<=95%,"B",L9>95%,"C") -> #DIV/0!
B10: flip желтые Сул | D10: =C10/C$26 -> #DIV/0! | E10: =D10+E9 -> #DIV/0! | F10: =IF(AND(E10<=0),"C",IF(E10<=0.8,"A",IF(E10<=0.95,"B","C"))) -> #DIV/0! | G10: =VLOOKUP(B$4:B$25,I$4:M$25,5,0) -> #DIV/0! | I10: flip желтые Сул | K10: =J10/J$26 -> #DIV/0! | L10: =K10+L9 -> #DIV/0! | M10: =_xlfn.IFS(L10<80%,"A",L10<=95%,"B",L10>95%,"C") -> #DIV/0!
B11: MR8854 C2 | D11: =C11/C$26 -> #DIV/0! | E11: =D11+E8 -> #DIV/0! | F11: =IF(AND(E11<=0),"C",IF(E11<=0.8,"A",IF(E11<=0.95,"B","C"))) -> #DIV/0! | G11: =VLOOKUP(B$4:B$25,I$4:M$25,5,0) -> #DIV/0! | I11: MR8854 C2 | K11: =J11/J$26 -> #DIV/0! | L11: =K11+L8 -> #DIV/0! | M11: =_xlfn.IFS(L11<80%,"A",L11<=95%,"B",L11>95%,"C") -> #DIV/0!
B12: MR 1819 черн | D12: =C12/C$26 -> #DIV/0! | E12: =D12+E11 -> #DIV/0! | F12: =IF(AND(E12<=0),"C",IF(E12<=0.8,"A",IF(E12<=0.95,"B","C"))) -> #DIV/0! | G12: =VLOOKUP(B$4:B$25,I$4:M$25,5,0) -> #DIV/0! | I12: MR 1819 черн | K12: =J12/J$26 -> #DIV/0! | L12: =K12+L11 -> #DIV/0! | M12: =_xlfn.IFS(L12<80%,"A",L12<=95%,"B",L12>95%,"C") -> #DIV/0!
B13: MR 1819 корич | D13: =C13/C$26 -> #DIV/0! | E13: =D13+E12 -> #DIV/0! | F13: =IF(AND(E13<=0),"C",IF(E13<=0.8,"A",IF(E13<=0.95,"B","C"))) -> #DIV/0! | G13: =VLOOKUP(B$4:B$25,I$4:M$25,5,0) -> #DIV/0! | I13: MR 1819 корич | K13: =J13/J$26 -> #DIV/0! | L13: =K13+L12 -> #DIV/0! | M13: =_xlfn.IFS(L13<80%,"A",L13<=95%,"B",L13>95%,"C") -> #DIV/0! | P13: A | Q13: 0.8
B14: MR Р1874 черн | D14: =C14/C$26 -> #DIV/0! | E14: =D14+E13 -> #DIV/0! | F14: =IF(AND(E14<=0),"C",IF(E14<=0.8,"A",IF(E14<=0.95,"B","C"))) -> #DIV/0! | G14: =VLOOKUP(B$4:B$25,I$4:M$25,5,0) -> #DIV/0! | I14: MR Р1874 черн | K14: =J14/J$26 -> #DIV/0! | L14: =K14+L13 -> #DIV/0! | M14: =_xlfn.IFS(L14<80%,"A",L14<=95%,"B",L14>95%,"C") -> #DIV/0! | P14: B | Q14: 0.15
B15: MR Р1874 корич | D15: =C15/C$26 -> #DIV/0! | E15: =D15+E14 -> #DIV/0! | F15: =IF(AND(E15<=0),"C",IF(E15<=0.8,"A",IF(E15<=0.95,"B","C"))) -> #DIV/0! | G15: =VLOOKUP(B$4:B$25,I$4:M$25,5,0) -> #DIV/0! | I15: MR Р1874 корич | K15: =J15/J$26 -> #DIV/0! | L15: =K15+L14 -> #DIV/0! | M15: =_xlfn.IFS(L15<80%,"A",L15<=95%,"B",L15>95%,"C") -> #DIV/0! | P15: C | Q15: 0.05
B16: MR Р1886 черн глянец | D16: =C16/C$26 -> #DIV/0! | E16: =D16+E15 -> #DIV/0! | F16: =IF(AND(E16<=0),"C",IF(E16<=0.8,"A",IF(E16<=0.95,"B","C"))) -> #DIV/0! | G16: =VLOOKUP(B$4:B$25,I$4:M$25,5,0) -> #DIV/0! | I16: MR Р1886 черн глянец | K16: =J16/J$26 -> #DIV/0! | L16: =K16+L15 -> #DIV/0! | M16: =_xlfn.IFS(L16<80%,"A",L16<=95%,"B",L16>95%,"C") -> #DIV/0!
B17: MR Р1886 корич | D17: =C17/C$26 -> #DIV/0! | E17: =D17+E16 -> #DIV/0! | F17: =IF(AND(E17<=0),"C",IF(E17<=0.8,"A",IF(E17<=0.95,"B","C"))) -> #DIV/0! | G17: =VLOOKUP(B$4:B$25,I$4:M$25,5,0) -> #DIV/0! | I17: MR Р1886 корич | K17: =J17/J$26 -> #DIV/0! | L17: =K17+L16 -> #DIV/0! | M17: =_xlfn.IFS(L17<80%,"A",L17<=95%,"B",L17>95%,"C") -> #DIV/0!
B18: lux1 | D18: =C18/C$26 -> #DIV/0! | E18: =D18+E17 -> #DIV/0! | F18: =IF(AND(E18<=0),"C",IF(E18<=0.8,"A",IF(E18<=0.95,"B","C"))) -> #DIV/0! | G18: =VLOOKUP(B$4:B$25,I$4:M$25,5,0) -> #DIV/0! | I18: lux1 | K18: =J18/J$26 -> #DIV/0! | L18: =K18+L17 -> #DIV/0! | M18: =_xlfn.IFS(L18<80%,"A",L18<=95%,"B",L18>95%,"C") -> #DIV/0!
B19: lux2 | D19: =C19/C$26 -> #DIV/0! | E19: =D19+E18 -> #DIV/0! | F19: =IF(AND(E19<=0),"C",IF(E19<=0.8,"A",IF(E19<=0.95,"B","C"))) -> #DIV/0! | G19: =VLOOKUP(B$4:B$25,I$4:M$25,5,0) -> #DIV/0! | I19: lux2 | K19: =J19/J$26 -> #DIV/0! | L19: =K19+L18 -> #DIV/0! | M19: =_xlfn.IFS(L19<80%,"A",L19<=95%,"B",L19>95%,"C") -> #DIV/0!
B20: lux3 | D20: =C20/C$26 -> #DIV/0! | E20: =D20+E19 -> #DIV/0! | F20: =IF(AND(E20<=0),"C",IF(E20<=0.8,"A",IF(E20<=0.95,"B","C"))) -> #DIV/0! | G20: =VLOOKUP(B$4:B$25,I$4:M$25,5,0) -> #DIV/0! | I20: lux3 | K20: =J20/J$26 -> #DIV/0! | L20: =K20+L19 -> #DIV/0! | M20: =_xlfn.IFS(L20<80%,"A",L20<=95%,"B",L20>95%,"C") -> #DIV/0!
B21: lux4 | D21: =C21/C$26 -> #DIV/0! | E21: =D21+E20 -> #DIV/0! | F21: =IF(AND(E21<=0),"C",IF(E21<=0.8,"A",IF(E21<=0.95,"B","C"))) -> #DIV/0! | G21: =VLOOKUP(B$4:B$25,I$4:M$25,5,0) -> #DIV/0! | I21: lux4 | K21: =J21/J$26 -> #DIV/0! | L21: =K21+L20 -> #DIV/0! | M21: =_xlfn.IFS(L21<80%,"A",L21<=95%,"B",L21>95%,"C") -> #DIV/0!
B22: lux5 | D22: =C22/C$26 -> #DIV/0! | E22: =D22+E21 -> #DIV/0! | F22: =IF(AND(E22<=0),"C",IF(E22<=0.8,"A",IF(E22<=0.95,"B","C"))) -> #DIV/0! | G22: =VLOOKUP(B$4:B$25,I$4:M$25,5,0) -> #DIV/0! | I22: lux5 | K22: =J22/J$26 -> #DIV/0! | L22: =K22+L21 -> #DIV/0! | M22: =_xlfn.IFS(L22<80%,"A",L22<=95%,"B",L22>95%,"C") -> #DIV/0!
B23: lux6 | D23: =C23/C$26 -> #DIV/0! | E23: =D23+E22 -> #DIV/0! | F23: =IF(AND(E23<=0),"C",IF(E23<=0.8,"A",IF(E23<=0.95,"B","C"))) -> #DIV/0! | G23: =VLOOKUP(B$4:B$25,I$4:M$25,5,0) -> #DIV/0! | I23: lux6 | K23: =J23/J$26 -> #DIV/0! | L23: =K23+L22 -> #DIV/0! | M23: =_xlfn.IFS(L23<80%,"A",L23<=95%,"B",L23>95%,"C") -> #DIV/0!
B24: lux7 | D24: =C24/C$26 -> #DIV/0! | E24: =D24+E23 -> #DIV/0! | F24: =IF(AND(E24<=0),"C",IF(E24<=0.8,"A",IF(E24<=0.95,"B","C"))) -> #DIV/0! | G24: =VLOOKUP(B$4:B$25,I$4:M$25,5,0) -> #DIV/0! | I24: lux7 | K24: =J24/J$26 -> #DIV/0! | L24: =K24+L23 -> #DIV/0! | M24: =_xlfn.IFS(L24<80%,"A",L24<=95%,"B",L24>95%,"C") -> #DIV/0!
B25: lux8 | D25: =C25/C$26 -> #DIV/0! | E25: =D25+E24 -> #DIV/0! | F25: =IF(AND(E25<=0),"C",IF(E25<=0.8,"A",IF(E25<=0.95,"B","C"))) -> #DIV/0! | G25: =VLOOKUP(B$4:B$25,I$4:M$25,5,0) -> #DIV/0! | I25: lux8 | K25: =J25/J$26 -> #DIV/0! | L25: =K25+L24 -> #DIV/0! | M25: =_xlfn.IFS(L25<80%,"A",L25<=95%,"B",L25>95%,"C") -> #DIV/0!
C26: =SUM(C4:C25) -> 0 | D26: =SUM(D4:D25) -> #DIV/0! | J26: =SUM(J4:J25) -> 0 | K26: =SUM(K4:K25) -> #DIV/0!
B28: ТУНИКИ
C29: Прибыль | D29: % прибыль | E29: Доля | F29: ABC прибыль | G29: ABC кол-во | J29: Кол-во | K29: % кол-во | L29: Доля | M29: ABC кол-во
B30: tunika02 оливковая с руч вышивкой | D30: =C30/C$50 -> #DIV/0! | E30: =D30 -> #DIV/0! | F30: =IF(AND(E30<=0),"C",IF(E30<=0.8,"A",IF(E30<=0.95,"B","C"))) -> #DIV/0! | G30: =VLOOKUP(B$30:B$50,I$30:M$50,5,0) -> #DIV/0! | I30: tunika02 оливковая с руч вышивкой | K30: =J30/J$50 -> #DIV/0! | L30: =K30 -> #DIV/0! | M30: =_xlfn.IFS(L30<80%,"A",L30<=95%,"B",L30>95%,"C") -> #DIV/0!
B31: tunika03 черная распашная | D31: =C31/C$50 -> #DIV/0! | E31: =D31+E30 -> #DIV/0! | F31: =IF(AND(E31<=0),"C",IF(E31<=0.8,"A",IF(E31<=0.95,"B","C"))) -> #DIV/0! | G31: =VLOOKUP(B$30:B$50,I$30:M$50,5,0) -> #DIV/0! | I31: tunika03 черная распашная | K31: =J31/J$50 -> #DIV/0! | L31: =K31+L30 -> #DIV/0! | M31: =_xlfn.IFS(L31<80%,"A",L31<=95%,"B",L31>95%,"C") -> #DIV/0!
B32: tunika05 белая распашная | D32: =C32/C$50 -> #DIV/0! | E32: =D32+E31 -> #DIV/0! | F32: =IF(AND(E32<=0),"C",IF(E32<=0.8,"A",IF(E32<=0.95,"B","C"))) -> #DIV/0! | G32: =VLOOKUP(B$30:B$50,I$30:M$50,5,0) -> #DIV/0! | I32: tunika05 белая распашная | K32: =J32/J$50 -> #DIV/0! | L32: =K32+L31 -> #DIV/0! | M32: =_xlfn.IFS(L32<80%,"A",L32<=95%,"B",L32>95%,"C") -> #DIV/0!
B33: tunika06 белая | D33: =C33/C$50 -> #DIV/0! | E33: =D33+E32 -> #DIV/0! | F33: =IF(AND(E33<=0),"C",IF(E33<=0.8,"A",IF(E33<=0.95,"B","C"))) -> #DIV/0! | G33: =VLOOKUP(B$30:B$50,I$30:M$50,5,0) -> #DIV/0! | I33: tunika06 белая | K33: =J33/J$50 -> #DIV/0! | L33: =K33+L32 -> #DIV/0! | M33: =_xlfn.IFS(L33<80%,"A",L33<=95%,"B",L33>95%,"C") -> #DIV/0!
B34: tunika06 черная | D34: =C34/C$50 -> #DIV/0! | E34: =D34+E33 -> #DIV/0! | F34: =IF(AND(E34<=0),"C",IF(E34<=0.8,"A",IF(E34<=0.95,"B","C"))) -> #DIV/0! | G34: =VLOOKUP(B$30:B$50,I$30:M$50,5,0) -> #DIV/0! | I34: tunika06 черная | K34: =J34/J$50 -> #DIV/0! | L34: =K34+L33 -> #DIV/0! | M34: =_xlfn.IFS(L34<80%,"A",L34<=95%,"B",L34>95%,"C") -> #DIV/0!
B35: tunika07 кружево | D35: =C35/C$50 -> #DIV/0! | E35: =D35+E34 -> #DIV/0! | F35: =IF(AND(E35<=0),"C",IF(E35<=0.8,"A",IF(E35<=0.95,"B","C"))) -> #DIV/0! | G35: =VLOOKUP(B$30:B$50,I$30:M$50,5,0) -> #DIV/0! | I35: tunika07 кружево | K35: =J35/J$50 -> #DIV/0! | L35: =K35+L34 -> #DIV/0! | M35: =_xlfn.IFS(L35<80%,"A",L35<=95%,"B",L35>95%,"C") -> #DIV/0!
B36: tunika08 белая | D36: =C36/C$50 -> #DIV/0! | E36: =D36+E35 -> #DIV/0! | F36: =IF(AND(E36<=0),"C",IF(E36<=0.8,"A",IF(E36<=0.95,"B","C"))) -> #DIV/0! | G36: =VLOOKUP(B$30:B$50,I$30:M$50,5,0) -> #DIV/0! | I36: tunika08 белая | K36: =J36/J$50 -> #DIV/0! | L36: =K36+L35 -> #DIV/0! | M36: =_xlfn.IFS(L36<80%,"A",L36<=95%,"B",L36>95%,"C") -> #DIV/0!
B37: tunika08 черная | D37: =C37/C$50 -> #DIV/0! | E37: =D37+E36 -> #DIV/0! | F37: =IF(AND(E37<=0),"C",IF(E37<=0.8,"A",IF(E37<=0.95,"B","C"))) -> #DIV/0! | G37: =VLOOKUP(B$30:B$50,I$30:M$50,5,0) -> #DIV/0! | I37: tunika08 черная | K37: =J37/J$50 -> #DIV/0! | L37: =K37+L36 -> #DIV/0! | M37: =_xlfn.IFS(L37<80%,"A",L37<=95%,"B",L37>95%,"C") -> #DIV/0!
B38: tunika08 зеленая | D38: =C38/C$50 -> #DIV/0! | E38: =D38+E37 -> #DIV/0! | F38: =IF(AND(E38<=0),"C",IF(E38<=0.8,"A",IF(E38<=0.95,"B","C"))) -> #DIV/0! | G38: =VLOOKUP(B$30:B$50,I$30:M$50,5,0) -> #DIV/0! | I38: tunika08 зеленая | K38: =J38/J$50 -> #DIV/0! | L38: =K38+L37 -> #DIV/0! | M38: =_xlfn.IFS(L38<80%,"A",L38<=95%,"B",L38>95%,"C") -> #DIV/0!
B39: tunika09 кимоно | D39: =C39/C$50 -> #DIV/0! | E39: =D39+E38 -> #DIV/0! | F39: =IF(AND(E39<=0),"C",IF(E39<=0.8,"A",IF(E39<=0.95,"B","C"))) -> #DIV/0! | G39: =VLOOKUP(B$30:B$50,I$30:M$50,5,0) -> #DIV/0! | I39: tunika09 кимоно | K39: =J39/J$50 -> #DIV/0! | L39: =K39+L38 -> #DIV/0! | M39: =_xlfn.IFS(L39<80%,"A",L39<=95%,"B",L39>95%,"C") -> #DIV/0!
B40: tunika10 кимоно ч/б | D40: =C40/C$50 -> #DIV/0! | E40: =D40+E39 -> #DIV/0! | F40: =IF(AND(E40<=0),"C",IF(E40<=0.8,"A",IF(E40<=0.95,"B","C"))) -> #DIV/0! | G40: =VLOOKUP(B$30:B$50,I$30:M$50,5,0) -> #DIV/0! | I40: tunika10 кимоно ч/б | K40: =J40/J$50 -> #DIV/0! | L40: =K40+L39 -> #DIV/0! | M40: =_xlfn.IFS(L40<80%,"A",L40<=95%,"B",L40>95%,"C") -> #DIV/0!
B41: tunika11 халат зеленая | D41: =C41/C$50 -> #DIV/0! | E41: =D41+E40 -> #DIV/0! | F41: =IF(AND(E41<=0),"C",IF(E41<=0.8,"A",IF(E41<=0.95,"B","C"))) -> #DIV/0! | G41: =VLOOKUP(B$30:B$50,I$30:M$50,5,0) -> #DIV/0! | I41: tunika11 халат зеленая | K41: =J41/J$50 -> #DIV/0! | L41: =K41+L40 -> #DIV/0! | M41: =_xlfn.IFS(L41<80%,"A",L41<=95%,"B",L41>95%,"C") -> #DIV/0!
B42: tunika12 халат белая | D42: =C42/C$50 -> #DIV/0! | E42: =D42+E41 -> #DIV/0! | F42: =IF(AND(E42<=0),"C",IF(E42<=0.8,"A",IF(E42<=0.95,"B","C"))) -> #DIV/0! | G42: =VLOOKUP(B$30:B$50,I$30:M$50,5,0) -> #DIV/0! | I42: tunika12 халат белая | K42: =J42/J$50 -> #DIV/0! | L42: =K42+L41 -> #DIV/0! | M42: =_xlfn.IFS(L42<80%,"A",L42<=95%,"B",L42>95%,"C") -> #DIV/0!
... B49: tunika16 сетка черная | D49: =C49/C$50 -> #DIV/0! | E49: =D49+E48 -> #DIV/0! | F49: =IF(AND(E49<=0),"C",IF(E49<=0.8,"A",IF(E49<=0.95,"B","C"))) -> #DIV/0! | G49: =VLOOKUP(B$30:B$50,I$30:M$50,5,0) -> #DIV/0! | I49: tunika16 сетка черная | K49: =J49/J$50 -> #DIV/0! | L49: =K49+L48 -> #DIV/0! | M49: =_xlfn.IFS(L49<80%,"A",L49<=95%,"B",L49>95%,"C") -> #DIV/0!
C50: =SUM(C30:C49) -> 0 | D50: =SUM(D30:D49) -> #DIV/0! | J50: =SUM(J30:J49) -> 0 | K50: =SUM(K30:K49) -> #DIV/0!

Sheet АВС 09-15.02
B2: ОЧКИ
C3: Прибыль | D3: % прибыль | E3: Доля | F3: ABC прибыль | G3: ABC кол-во | J3: Кол-во | K3: % кол-во | L3: Доля | M3: ABC кол-во
B4: черные с железкой классика | C4: ='Юнит 09-15.02'!AE3 -> 18261.877 | D4: =C4/C$26 -> 0.9050678 | E4: =D4 -> 0.9050678 | F4: =IF(AND(E4<=0),"C",IF(E4<=0.8,"A",IF(E4<=0.95,"B","C"))) -> B | G4: =VLOOKUP(B$4:B$25,I$4:M$25,5,0) -> A | I4: черные с железкой классика | J4: ='Юнит 09-15.02'!R3 -> 40 | K4: =J4/J$26 -> 0.68965517 | L4: =K4 -> 0.68965517 | M4: =_xlfn.IFS(L4<80%,"A",L4<=95%,"B",L4>95%,"C") -> A
B5: qs коричневые | C5: ='Юнит 09-15.02'!AE7 -> 2261.0319 | D5: =C5/C$26 -> 0.11205787 | E5: =D5+E4 -> 1.0171257 | F5: =IF(AND(E5<=0),"C",IF(E5<=0.8,"A",IF(E5<=0.95,"B","C"))) -> C | G5: =VLOOKUP(B$4:B$25,I$4:M$25,5,0) -> A | I5: qs коричневые | J5: ='Юнит 09-15.02'!R7 -> 5 | K5: =J5/J$26 -> 0.086206897 | L5: =K5+L4 -> 0.77586207 | M5: =_xlfn.IFS(L5<80%,"A",L5<=95%,"B",L5>95%,"C") -> A
B6: flip желтые Сул | C6: ='Юнит 09-15.02'!AE9 -> 1236.572 | D6: =C6/C$26 -> 0.061285126 | E6: =D6+E5 -> 1.0784108 | F6: =IF(AND(E6<=0),"C",IF(E6<=0.8,"A",IF(E6<=0.95,"B","C"))) -> C | G6: =VLOOKUP(B$4:B$25,I$4:M$25,5,0) -> B | I6: flip желтые Сул | J6: ='Юнит 09-15.02'!R9 -> 5 | K6: =J6/J$26 -> 0.086206897 | L6: =K6+L5 -> 0.86206897 | M6: =_xlfn.IFS(L6<80%,"A",L6<=95%,"B",L6>95%,"C") -> B
B7: qs черные | C7: ='Юнит 09-15.02'!AE4 -> 873.30156 | D7: =C7/C$26 -> 0.043281263 | E7: =D7+E6 -> 1.1216921 | F7: =IF(AND(E7<=0),"C",IF(E7<=0.8,"A",IF(E7<=0.95,"B","C"))) -> C | G7: =VLOOKUP(B$4:B$25,I$4:M$25,5,0) -> B | I7: MR8854 C2 | J7: ='Юнит 09-15.02'!R10 -> 4 | K7: =J7/J$26 -> 0.068965517 | L7: =K7+L6 -> 0.93103448 | M7: =_xlfn.IFS(L7<80%,"A",L7<=95%,"B",L7>95%,"C") -> B
B8: MR8854 C2 | C8: ='Юнит 09-15.02'!AE10 -> 827.0756 | D8: =C8/C$26 -> 0.040990281 | E8: =D8+E7 -> 1.1626823 | F8: =IF(AND(E8<=0),"C",IF(E8<=0.8,"A",IF(E8<=0.95,"B","C"))) -> C | G8: =VLOOKUP(B$4:B$25,I$4:M$25,5,0) -> B | I8: qs черные | J8: ='Юнит 09-15.02'!R4 -> 1 | K8: =J8/J$26 -> 0.017241379 | L8: =K8+L7 -> 0.94827586 | M8: =_xlfn.IFS(L8<80%,"A",L8<=95%,"B",L8>95%,"C") -> B
B9: MR 1819 корич | C9: ='Юнит 09-15.02'!AE12 -> 329.21308 | D9: =C9/C$26 -> 0.016315965 | E9: =D9+E8 -> 1.1789983 | F9: =IF(AND(E9<=0),"C",IF(E9<=0.8,"A",IF(E9<=0.95,"B","C"))) -> C | G9: =VLOOKUP(B$4:B$25,I$4:M$25,5,0) -> C | I9: qs синие | J9: ='Юнит 09-15.02'!R5 -> 1 | K9: =J9/J$26 -> 0.017241379 | L9: =K9+L8 -> 0.96551724 | M9: =_xlfn.IFS(L9<80%,"A",L9<=95%,"B",L9>95%,"C") -> C
B10: qs синие | C10: ='Юнит 09-15.02'!AE5 -> 310.95156 | D10: =C10/C$26 -> 0.015410915 | E10: =D10+E9 -> 1.1944092 | F10: =IF(AND(E10<=0),"C",IF(E10<=0.8,"A",IF(E10<=0.95,"B","C"))) -> C | G10: =VLOOKUP(B$4:B$25,I$4:M$25,5,0) -> C | I10: MR 1819 корич | J10: ='Юнит 09-15.02'!R12 -> 1 | K10: =J10/J$26 -> 0.017241379 | L10: =K10+L9 -> 0.98275862 | M10: =_xlfn.IFS(L10<80%,"A",L10<=95%,"B",L10>95%,"C") -> C
B11: MR Р1874 черн | C11: ='Юнит 09-15.02'!AE13 -> 142.4794 | D11: =C11/C$26 -> 0.0070613505 | E11: =D11+E8 -> 1.1697437 | F11: =IF(AND(E11<=0),"C",IF(E11<=0.8,"A",IF(E11<=0.95,"B","C"))) -> C | G11: =VLOOKUP(B$4:B$25,I$4:M$25,5,0) -> C | I11: MR Р1874 черн | J11: ='Юнит 09-15.02'!R13 -> 1 | K11: =J11/J$26 -> 0.017241379 | L11: =K11+L8 -> 0.96551724 | M11: =_xlfn.IFS(L11<80%,"A",L11<=95%,"B",L11>95%,"C") -> C
B12: lux1 | C12: ='Юнит 09-15.02'!AE17 -> 0 | D12: =C12/C$26 -> 0 | E12: =D12+E11 -> 1.1697437 | F12: =IF(AND(E12<=0),"C",IF(E12<=0.8,"A",IF(E12<=0.95,"B","C"))) -> C | G12: =VLOOKUP(B$4:B$25,I$4:M$25,5,0) -> C | I12: MR Р1886 черн глянец | J12: ='Юнит 09-15.02'!R15 -> 1 | K12: =J12/J$26 -> 0.017241379 | L12: =K12+L11 -> 0.98275862 | M12: =_xlfn.IFS(L12<80%,"A",L12<=95%,"B",L12>95%,"C") -> C
B13: lux2 | C13: ='Юнит 09-15.02'!AE18 -> 0 | D13: =C13/C$26 -> 0 | E13: =D13+E12 -> 1.1697437 | F13: =IF(AND(E13<=0),"C",IF(E13<=0.8,"A",IF(E13<=0.95,"B","C"))) -> C | G13: =VLOOKUP(B$4:B$25,I$4:M$25,5,0) -> C | I13: qs желтые | J13: ='Юнит 09-15.02'!R6 -> 0 | K13: =J13/J$26 -> 0 | L13: =K13+L12 -> 0.98275862 | M13: =_xlfn.IFS(L13<80%,"A",L13<=95%,"B",L13>95%,"C") -> C | P13: A | Q13: 0.8
B14: lux3 | C14: ='Юнит 09-15.02'!AE19 -> 0 | D14: =C14/C$26 -> 0 | E14: =D14+E13 -> 1.1697437 | F14: =IF(AND(E14<=0),"C",IF(E14<=0.8,"A",IF(E14<=0.95,"B","C"))) -> C | G14: =VLOOKUP(B$4:B$25,I$4:M$25,5,0) -> C | I14: th желтый Сул | J14: ='Юнит 09-15.02'!R8 -> 0 | K14: =J14/J$26 -> 0 | L14: =K14+L13 -> 0.98275862 | M14: =_xlfn.IFS(L14<80%,"A",L14<=95%,"B",L14>95%,"C") -> C | P14: B | Q14: 0.15
B15: lux5 | C15: ='Юнит 09-15.02'!AE21 -> 0 | D15: =C15/C$26 -> 0 | E15: =D15+E14 -> 1.1697437 | F15: =IF(AND(E15<=0),"C",IF(E15<=0.8,"A",IF(E15<=0.95,"B","C"))) -> C | G15: =VLOOKUP(B$4:B$25,I$4:M$25,5,0) -> C | I15: MR 1819 черн | J15: ='Юнит 09-15.02'!R11 -> 0 | K15: =J15/J$26 -> 0 | L15: =K15+L14 -> 0.98275862 | M15: =_xlfn.IFS(L15<80%,"A",L15<=95%,"B",L15>95%,"C") -> C | P15: C | Q15: 0.05
B16: lux6 | C16: ='Юнит 09-15.02'!AE22 -> 0 | D16: =C16/C$26 -> 0 | E16: =D16+E15 -> 1.1697437 | F16: =IF(AND(E16<=0),"C",IF(E16<=0.8,"A",IF(E16<=0.95,"B","C"))) -> C | G16: =VLOOKUP(B$4:B$25,I$4:M$25,5,0) -> C | I16: MR Р1874 корич | J16: ='Юнит 09-15.02'!R14 -> 0 | K16: =J16/J$26 -> 0 | L16: =K16+L15 -> 0.98275862 | M16: =_xlfn.IFS(L16<80%,"A",L16<=95%,"B",L16>95%,"C") -> C
B17: lux7 | C17: ='Юнит 09-15.02'!AE23 -> 0 | D17: =C17/C$26 -> 0 | E17: =D17+E16 -> 1.1697437 | F17: =IF(AND(E17<=0),"C",IF(E17<=0.8,"A",IF(E17<=0.95,"B","C"))) -> C | G17: =VLOOKUP(B$4:B$25,I$4:M$25,5,0) -> C | I17: MR Р1886 корич | J17: ='Юнит 09-15.02'!R16 -> 0 | K17: =J17/J$26 -> 0 | L17: =K17+L16 -> 0.98275862 | M17: =_xlfn.IFS(L17<80%,"A",L17<=95%,"B",L17>95%,"C") -> C
B18: lux8 | C18: ='Юнит 09-15.02'!AE24 -> 0 | D18: =C18/C$26 -> 0 | E18: =D18+E17 -> 1.1697437 | F18: =IF(AND(E18<=0),"C",IF(E18<=0.8,"A",IF(E18<=0.95,"B","C"))) -> C | G18: =VLOOKUP(B$4:B$25,I$4:M$25,5,0) -> C | I18: lux1 | J18: ='Юнит 09-15.02'!R17 -> 0 | K18: =J18/J$26 -> 0 | L18: =K18+L17 -> 0.98275862 | M18: =_xlfn.IFS(L18<80%,"A",L18<=95%,"B",L18>95%,"C") -> C
B19: MR Р1886 черн глянец | C19: ='Юнит 09-15.02'!AE15 -> -119.58737 | D19: =C19/C$26 -> -0.0059268098 | E19: =D19+E18 -> 1.1638169 | F19: =IF(AND(E19<=0),"C",IF(E19<=0.8,"A",IF(E19<=0.95,"B","C"))) -> C | G19: =VLOOKUP(B$4:B$25,I$4:M$25,5,0) -> C | I19: lux2 | J19: ='Юнит 09-15.02'!R18 -> 0 | K19: =J19/J$26 -> 0 | L19: =K19+L18 -> 0.98275862 | M19: =_xlfn.IFS(L19<80%,"A",L19<=95%,"B",L19>95%,"C") -> C
B20: MR 1819 черн | C20: ='Юнит 09-15.02'!AE11 -> -187.08 | D20: =C20/C$26 -> -0.0092717786 | E20: =D20+E19 -> 1.1545451 | F20: =IF(AND(E20<=0),"C",IF(E20<=0.8,"A",IF(E20<=0.95,"B","C"))) -> C | G20: =VLOOKUP(B$4:B$25,I$4:M$25,5,0) -> C | I20: lux3 | J20: ='Юнит 09-15.02'!R19 -> 0 | K20: =J20/J$26 -> 0 | L20: =K20+L19 -> 0.98275862 | M20: =_xlfn.IFS(L20<80%,"A",L20<=95%,"B",L20>95%,"C") -> C
B21: MR Р1874 корич | C21: ='Юнит 09-15.02'!AE14 -> -387.09 | D21: =C21/C$26 -> -0.019184374 | E21: =D21+E20 -> 1.1353607 | F21: =IF(AND(E21<=0),"C",IF(E21<=0.8,"A",IF(E21<=0.95,"B","C"))) -> C | G21: =VLOOKUP(B$4:B$25,I$4:M$25,5,0) -> C | I21: lux5 | J21: ='Юнит 09-15.02'!R21 -> 0 | K21: =J21/J$26 -> 0 | L21: =K21+L20 -> 0.98275862 | M21: =_xlfn.IFS(L21<80%,"A",L21<=95%,"B",L21>95%,"C") -> C
B22: th желтый Сул | C22: ='Юнит 09-15.02'!AE8 -> -425.04 | D22: =C22/C$26 -> -0.021065195 | E22: =D22+E21 -> 1.1142955 | F22: =IF(AND(E22<=0),"C",IF(E22<=0.8,"A",IF(E22<=0.95,"B","C"))) -> C | G22: =VLOOKUP(B$4:B$25,I$4:M$25,5,0) -> C | I22: lux6 | J22: ='Юнит 09-15.02'!R22 -> 0 | K22: =J22/J$26 -> 0 | L22: =K22+L21 -> 0.98275862 | M22: =_xlfn.IFS(L22<80%,"A",L22<=95%,"B",L22>95%,"C") -> C
B23: MR Р1886 корич | C23: ='Юнит 09-15.02'!AE16 -> -569.18 | D23: =C23/C$26 -> -0.028208846 | E23: =D23+E22 -> 1.0860867 | F23: =IF(AND(E23<=0),"C",IF(E23<=0.8,"A",IF(E23<=0.95,"B","C"))) -> C | G23: =VLOOKUP(B$4:B$25,I$4:M$25,5,0) -> C | I23: lux7 | J23: ='Юнит 09-15.02'!R23 -> 0 | K23: =J23/J$26 -> 0 | L23: =K23+L22 -> 0.98275862 | M23: =_xlfn.IFS(L23<80%,"A",L23<=95%,"B",L23>95%,"C") -> C
B24: lux4 | C24: ='Юнит 09-15.02'!AE20 -> -925.79033 | D24: =C24/C$26 -> -0.045882633 | E24: =D24+E23 -> 1.0402041 | F24: =IF(AND(E24<=0),"C",IF(E24<=0.8,"A",IF(E24<=0.95,"B","C"))) -> C | G24: =VLOOKUP(B$4:B$25,I$4:M$25,5,0) -> C | I24: lux8 | J24: ='Юнит 09-15.02'!R24 -> 0 | K24: =J24/J$26 -> 0 | L24: =K24+L23 -> 0.98275862 | M24: =_xlfn.IFS(L24<80%,"A",L24<=95%,"B",L24>95%,"C") -> C
B25: qs желтые | C25: ='Юнит 09-15.02'!AE6 -> -1451.3763 | D25: =C25/C$26 -> -0.071930937 | E25: =D25+E24 -> 0.96827312 | F25: =IF(AND(E25<=0),"C",IF(E25<=0.8,"A",IF(E25<=0.95,"B","C"))) -> C | G25: =VLOOKUP(B$4:B$25,I$4:M$25,5,0) -> C | I25: lux4 | J25: ='Юнит 09-15.02'!R20 -> -1 | K25: =J25/J$26 -> -0.017241379 | L25: =K25+L24 -> 0.96551724 | M25: =_xlfn.IFS(L25<80%,"A",L25<=95%,"B",L25>95%,"C") -> C
C26: =SUM(C4:C25) -> 20177.358 | D26: =SUM(D4:D25) -> 1 | J26: =SUM(J4:J25) -> 58 | K26: =SUM(K4:K25) -> 1
B28: ТУНИКИ
C29: Прибыль | D29: % прибыль | E29: Доля | F29: ABC прибыль | G29: ABC кол-во | J29: Кол-во | K29: % кол-во | L29: Доля | M29: ABC кол-во
B30: tunika15 кимоно бирюза | C30: ='Юнит 09-15.02'!AE44 -> 7055.3882 | D30: =C30/C$50 -> 0.39472445 | E30: =D30 -> 0.39472445 | F30: =IF(AND(E30<=0),"C",IF(E30<=0.8,"A",IF(E30<=0.95,"B","C"))) -> A | G30: =VLOOKUP(B$30:B$50,I$30:M$50,5,0) -> A | I30: tunika15 кимоно бирюза | J30: ='Юнит 09-15.02'!R44 -> 7 | K30: =J30/J$50 -> 0.35 | L30: =K30 -> 0.35 | M30: =_xlfn.IFS(L30<80%,"A",L30<=95%,"B",L30>95%,"C") -> A
B31: tunika09 кимоно | C31: ='Юнит 09-15.02'!AE37 -> 5645.122 | D31: =C31/C$50 -> 0.31582495 | E31: =D31+E30 -> 0.7105494 | F31: =IF(AND(E31<=0),"C",IF(E31<=0.8,"A",IF(E31<=0.95,"B","C"))) -> A | G31: =VLOOKUP(B$30:B$50,I$30:M$50,5,0) -> A | I31: tunika15 кимоно песочная | J31: ='Юнит 09-15.02'!R45 -> 4 | K31: =J31/J$50 -> 0.2 | L31: =K31+L30 -> 0.55 | M31: =_xlfn.IFS(L31<80%,"A",L31<=95%,"B",L31>95%,"C") -> A
B32: tunika15 кимоно песочная | C32: ='Юнит 09-15.02'!AE45 -> 4691.1462 | D32: =C32/C$50 -> 0.26245332 | E32: =D32+E31 -> 0.97300272 | F32: =IF(AND(E32<=0),"C",IF(E32<=0.8,"A",IF(E32<=0.95,"B","C"))) -> C | G32: =VLOOKUP(B$30:B$50,I$30:M$50,5,0) -> A | I32: tunika09 кимоно | J32: ='Юнит 09-15.02'!R37 -> 3 | K32: =J32/J$50 -> 0.15 | L32: =K32+L31 -> 0.7 | M32: =_xlfn.IFS(L32<80%,"A",L32<=95%,"B",L32>95%,"C") -> A
B33: tunika03 черная распашная | C33: ='Юнит 09-15.02'!AE29 -> 1950.7439 | D33: =C33/C$50 -> 0.10913734 | E33: =D33+E32 -> 1.0821401 | F33: =IF(AND(E33<=0),"C",IF(E33<=0.8,"A",IF(E33<=0.95,"B","C"))) -> C | G33: =VLOOKUP(B$30:B$50,I$30:M$50,5,0) -> B | I33: tunika07 кружево | J33: ='Юнит 09-15.02'!R33 -> 2 | K33: =J33/J$50 -> 0.1 | L33: =K33+L32 -> 0.8 | M33: =_xlfn.IFS(L33<80%,"A",L33<=95%,"B",L33>95%,"C") -> B
B34: tunika07 кружево | C34: ='Юнит 09-15.02'!AE33 -> 1741.132 | D34: =C34/C$50 -> 0.097410283 | E34: =D34+E33 -> 1.1795503 | F34: =IF(AND(E34<=0),"C",IF(E34<=0.8,"A",IF(E34<=0.95,"B","C"))) -> C | G34: =VLOOKUP(B$30:B$50,I$30:M$50,5,0) -> B | I34: tunika14 халат с разрезами белая | J34: ='Юнит 09-15.02'!R42 -> 2 | K34: =J34/J$50 -> 0.1 | L34: =K34+L33 -> 0.9 | M34: =_xlfn.IFS(L34<80%,"A",L34<=95%,"B",L34>95%,"C") -> B
B35: tunika06 белая | C35: ='Юнит 09-15.02'!AE31 -> 1628.7063 | D35: =C35/C$50 -> 0.091120459 | E35: =D35+E34 -> 1.2706708 | F35: =IF(AND(E35<=0),"C",IF(E35<=0.8,"A",IF(E35<=0.95,"B","C"))) -> C | G35: =VLOOKUP(B$30:B$50,I$30:M$50,5,0) -> C | I35: tunika03 черная распашная | J35: ='Юнит 09-15.02'!R29 -> 1 | K35: =J35/J$50 -> 0.05 | L35: =K35+L34 -> 0.95 | M35: =_xlfn.IFS(L35<80%,"A",L35<=95%,"B",L35>95%,"C") -> B
B36: tunika14 халат с разрезами белая | C36: ='Юнит 09-15.02'!AE42 -> 1576.2627 | D36: =C36/C$50 -> 0.088186419 | E36: =D36+E35 -> 1.3588572 | F36: =IF(AND(E36<=0),"C",IF(E36<=0.8,"A",IF(E36<=0.95,"B","C"))) -> C | G36: =VLOOKUP(B$30:B$50,I$30:M$50,5,0) -> B | I36: tunika06 белая | J36: ='Юнит 09-15.02'!R31 -> 1 | K36: =J36/J$50 -> 0.05 | L36: =K36+L35 -> 1 | M36: =_xlfn.IFS(L36<80%,"A",L36<=95%,"B",L36>95%,"C") -> C
B37: tunika02 оливковая с руч вышивкой | C37: ='Юнит 09-15.02'!AE28 -> 0 | D37: =C37/C$50 -> 0 | E37: =D37+E36 -> 1.3588572 | F37: =IF(AND(E37<=0),"C",IF(E37<=0.8,"A",IF(E37<=0.95,"B","C"))) -> C | G37: =VLOOKUP(B$30:B$50,I$30:M$50,5,0) -> C | I37: tunika16 сетка белая | J37: ='Юнит 09-15.02'!R46 -> 1 | K37: =J37/J$50 -> 0.05 | L37: =K37+L36 -> 1.05 | M37: =_xlfn.IFS(L37<80%,"A",L37<=95%,"B",L37>95%,"C") -> C
B38: tunika06 черная | C38: ='Юнит 09-15.02'!AE32 -> 0 | D38: =C38/C$50 -> 0 | E38: =D38+E37 -> 1.3588572 | F38: =IF(AND(E38<=0),"C",IF(E38<=0.8,"A",IF(E38<=0.95,"B","C"))) -> C | G38: =VLOOKUP(B$30:B$50,I$30:M$50,5,0) -> C | I38: tunika02 оливковая с руч вышивкой | J38: ='Юнит 09-15.02'!R28 -> 0 | K38: =J38/J$50 -> 0 | L38: =K38+L37 -> 1.05 | M38: =_xlfn.IFS(L38<80%,"A",L38<=95%,"B",L38>95%,"C") -> C
B39: tunika08 белая | C39: ='Юнит 09-15.02'!AE34 -> 0 | D39: =C39/C$50 -> 0 | E39: =D39+E38 -> 1.3588572 | F39: =IF(AND(E39<=0),"C",IF(E39<=0.8,"A",IF(E39<=0.95,"B","C"))) -> C | G39: =VLOOKUP(B$30:B$50,I$30:M$50,5,0) -> C | I39: tunika05 белая распашная | J39: ='Юнит 09-15.02'!R30 -> 0 | K39: =J39/J$50 -> 0 | L39: =K39+L38 -> 1.05 | M39: =_xlfn.IFS(L39<80%,"A",L39<=95%,"B",L39>95%,"C") -> C
B40: tunika08 черная | C40: ='Юнит 09-15.02'!AE35 -> 0 | D40: =C40/C$50 -> 0 | E40: =D40+E39 -> 1.3588572 | F40: =IF(AND(E40<=0),"C",IF(E40<=0.8,"A",IF(E40<=0.95,"B","C"))) -> C | G40: =VLOOKUP(B$30:B$50,I$30:M$50,5,0) -> C | I40: tunika06 черная | J40: ='Юнит 09-15.02'!R32 -> 0 | K40: =J40/J$50 -> 0 | L40: =K40+L39 -> 1.05 | M40: =_xlfn.IFS(L40<80%,"A",L40<=95%,"B",L40>95%,"C") -> C
B41: tunika11 халат зеленая | C41: ='Юнит 09-15.02'!AE39 -> 0 | D41: =C41/C$50 -> 0 | E41: =D41+E40 -> 1.3588572 | F41: =IF(AND(E41<=0),"C",IF(E41<=0.8,"A",IF(E41<=0.95,"B","C"))) -> C | G41: =VLOOKUP(B$30:B$50,I$30:M$50,5,0) -> C | I41: tunika08 белая | J41: ='Юнит 09-15.02'!R34 -> 0 | K41: =J41/J$50 -> 0 | L41: =K41+L40 -> 1.05 | M41: =_xlfn.IFS(L41<80%,"A",L41<=95%,"B",L41>95%,"C") -> C
B42: tunika12 халат белая | C42: ='Юнит 09-15.02'!AE40 -> 0 | D42: =C42/C$50 -> 0 | E42: =D42+E41 -> 1.3588572 | F42: =IF(AND(E42<=0),"C",IF(E42<=0.8,"A",IF(E42<=0.95,"B","C"))) -> C | G42: =VLOOKUP(B$30:B$50,I$30:M$50,5,0) -> C | I42: tunika08 черная | J42: ='Юнит 09-15.02'!R35 -> 0 | K42: =J42/J$50 -> 0 | L42: =K42+L41 -> 1.05 | M42: =_xlfn.IFS(L42<80%,"A",L42<=95%,"B",L42>95%,"C") -> C
B43: tunika13 халат черная | C43: ='Юнит 09-15.02'!AE41 -> 0 | D43: =C43/C$50 -> 0 | E43: =D43+E42 -> 1.3588572 | F43: =IF(AND(E43<=0),"C",IF(E43<=0.8,"A",IF(E43<=0.95,"B","C"))) -> C | G43: =VLOOKUP(B$30:B$50,I$30:M$50,5,0) -> C | I43: tunika08 зеленая | J43: ='Юнит 09-15.02'!R36 -> 0 | K43: =J43/J$50 -> 0 | L43: =K43+L42 -> 1.05 | M43: =_xlfn.IFS(L43<80%,"A",L43<=95%,"B",L43>95%,"C") -> C
B44: tunika05 белая распашная | C44: ='Юнит 09-15.02'!AE30 -> -113.88 | D44: =C44/C$50 -> -0.0063711902 | E44: =D44+E43 -> 1.352486 | F44: =IF(AND(E44<=0),"C",IF(E44<=0.8,"A",IF(E44<=0.95,"B","C"))) -> C | G44: =VLOOKUP(B$30:B$50,I$30:M$50,5,0) -> C | I44: tunika11 халат зеленая | J44: ='Юнит 09-15.02'!R39 -> 0 | K44: =J44/J$50 -> 0 | L44: =K44+L43 -> 1.05 | M44: =_xlfn.IFS(L44<80%,"A",L44<=95%,"B",L44>95%,"C") -> C
B45: tunika14 халат с разрезами черный | C45: ='Юнит 09-15.02'!AE43 -> -113.88 | D45: =C45/C$50 -> -0.0063711902 | E45: =D45+E44 -> 1.3461148 | F45: =IF(AND(E45<=0),"C",IF(E45<=0.8,"A",IF(E45<=0.95,"B","C"))) -> C | G45: =VLOOKUP(B$30:B$50,I$30:M$50,5,0) -> C | I45: tunika12 халат белая | J45: ='Юнит 09-15.02'!R40 -> 0 | K45: =J45/J$50 -> 0 | L45: =K45+L44 -> 1.05 | M45: =_xlfn.IFS(L45<80%,"A",L45<=95%,"B",L45>95%,"C") -> C
B46: tunika08 зеленая | C46: ='Юнит 09-15.02'!AE36 -> -227.76 | D46: =C46/C$50 -> -0.01274238 | E46: =D46+E45 -> 1.3333725 | F46: =IF(AND(E46<=0),"C",IF(E46<=0.8,"A",IF(E46<=0.95,"B","C"))) -> C | G46: =VLOOKUP(B$30:B$50,I$30:M$50,5,0) -> C | I46: tunika13 халат черная | J46: ='Юнит 09-15.02'!R41 -> 0 | K46: =J46/J$50 -> 0 | L46: =K46+L45 -> 1.05 | M46: =_xlfn.IFS(L46<80%,"A",L46<=95%,"B",L46>95%,"C") -> C
B47: tunika16 сетка черная | C47: ='Юнит 09-15.02'!AE47 -> -227.76 | D47: =C47/C$50 -> -0.01274238 | E47: =D47+E46 -> 1.3206301 | F47: =IF(AND(E47<=0),"C",IF(E47<=0.8,"A",IF(E47<=0.95,"B","C"))) -> C | G47: =VLOOKUP(B$30:B$50,I$30:M$50,5,0) -> C | I47: tunika14 халат с разрезами черный | J47: ='Юнит 09-15.02'!R43 -> 0 | K47: =J47/J$50 -> 0 | L47: =K47+L46 -> 1.05 | M47: =_xlfn.IFS(L47<80%,"A",L47<=95%,"B",L47>95%,"C") -> C
B48: tunika10 кимоно ч/б | C48: ='Юнит 09-15.02'!AE38 -> -1425.9352 | D48: =C48/C$50 -> -0.079776117 | E48: =D48+E47 -> 1.240854 | F48: =IF(AND(E48<=0),"C",IF(E48<=0.8,"A",IF(E48<=0.95,"B","C"))) -> C | G48: =VLOOKUP(B$30:B$50,I$30:M$50,5,0) -> C | I48: tunika16 сетка черная | J48: ='Юнит 09-15.02'!R47 -> 0 | K48: =J48/J$50 -> 0 | L48: =K48+L47 -> 1.05 | M48: =_xlfn.IFS(L48<80%,"A",L48<=95%,"B",L48>95%,"C") -> C
B49: tunika16 сетка белая | C49: ='Юнит 09-15.02'!AE46 -> -4305.0747 | D49: =C49/C$50 -> -0.24085396 | E49: =D49+E48 -> 1 | F49: =IF(AND(E49<=0),"C",IF(E49<=0.8,"A",IF(E49<=0.95,"B","C"))) -> C | G49: =VLOOKUP(B$30:B$50,I$30:M$50,5,0) -> C | I49: tunika10 кимоно ч/б | J49: ='Юнит 09-15.02'!R38 -> -1 | K49: =J49/J$50 -> -0.05 | L49: =K49+L48 -> 1 | M49: =_xlfn.IFS(L49<80%,"A",L49<=95%,"B",L49>95%,"C") -> C
C50: =SUM(C30:C49) -> 17874.211 | D50: =SUM(D30:D49) -> 1 | J50: =SUM(J30:J49) -> 20 | K50: =SUM(K30:K49) -> 1

Sheet АВС 02-08.02
B2: ОЧКИ
C3: Прибыль | D3: % прибыль | E3: Доля | F3: ABC прибыль | G3: ABC кол-во | J3: Кол-во | K3: % кол-во | L3: Доля | M3: ABC кол-во
B4: черные с железкой классика | C4: ='Юнит 02-08.02'!AE3 -> 10282.202 | D4: =C4/C$26 -> 0.80310383 | E4: =D4 -> 0.80310383 | F4: =IF(AND(E4<=0),"C",IF(E4<=0.8,"A",IF(E4<=0.95,"B","C"))) -> B | G4: =VLOOKUP(B$4:B$25,I$4:M$25,5,0) -> A | I4: черные с железкой классика | J4: ='Юнит 02-08.02'!R3 -> 38 | K4: =J4/J$26 -> 0.63333333 | L4: =K4 -> 0.63333333 | M4: =_xlfn.IFS(L4<80%,"A",L4<=95%,"B",L4>95%,"C") -> A
B5: flip желтые Сул | C5: ='Юнит 02-08.02'!AE9 -> 2101.7612 | D5: =C5/C$26 -> 0.16416061 | E5: =D5+E4 -> 0.96726444 | F5: =IF(AND(E5<=0),"C",IF(E5<=0.8,"A",IF(E5<=0.95,"B","C"))) -> C | G5: =VLOOKUP(B$4:B$25,I$4:M$25,5,0) -> B | I5: qs коричневые | J5: ='Юнит 02-08.02'!R7 -> 8 | K5: =J5/J$26 -> 0.13333333 | L5: =K5+L4 -> 0.76666667 | M5: =_xlfn.IFS(L5<80%,"A",L5<=95%,"B",L5>95%,"C") -> A
B6: lux4 | C6: ='Юнит 02-08.02'!AE20 -> 647.32719 | D6: =C6/C$26 -> 0.050560274 | E6: =D6+E5 -> 1.0178247 | F6: =IF(AND(E6<=0),"C",IF(E6<=0.8,"A",IF(E6<=0.95,"B","C"))) -> C | G6: =VLOOKUP(B$4:B$25,I$4:M$25,5,0) -> B | I6: flip желтые Сул | J6: ='Юнит 02-08.02'!R9 -> 5 | K6: =J6/J$26 -> 0.083333333 | L6: =K6+L5 -> 0.85 | M6: =_xlfn.IFS(L6<80%,"A",L6<=95%,"B",L6>95%,"C") -> B
B7: qs черные | C7: ='Юнит 02-08.02'!AE4 -> 601.7972 | D7: =C7/C$26 -> 0.047004099 | E7: =D7+E6 -> 1.0648288 | F7: =IF(AND(E7<=0),"C",IF(E7<=0.8,"A",IF(E7<=0.95,"B","C"))) -> C | G7: =VLOOKUP(B$4:B$25,I$4:M$25,5,0) -> C | I7: MR Р1874 черн | J7: ='Юнит 02-08.02'!R13 -> 3 | K7: =J7/J$26 -> 0.05 | L7: =K7+L6 -> 0.9 | M7: =_xlfn.IFS(L7<80%,"A",L7<=95%,"B",L7>95%,"C") -> B
B8: qs синие | C8: ='Юнит 02-08.02'!AE5 -> 549.23742 | D8: =C8/C$26 -> 0.042898854 | E8: =D8+E7 -> 1.1077277 | F8: =IF(AND(E8<=0),"C",IF(E8<=0.8,"A",IF(E8<=0.95,"B","C"))) -> C | G8: =VLOOKUP(B$4:B$25,I$4:M$25,5,0) -> B | I8: qs синие | J8: ='Юнит 02-08.02'!R5 -> 2 | K8: =J8/J$26 -> 0.033333333 | L8: =K8+L7 -> 0.93333333 | M8: =_xlfn.IFS(L8<80%,"A",L8<=95%,"B",L8>95%,"C") -> B
B9: th желтый Сул | C9: ='Юнит 02-08.02'!AE8 -> 119.68725 | D9: =C9/C$26 -> 0.009348318 | E9: =D9+E8 -> 1.117076 | F9: =IF(AND(E9<=0),"C",IF(E9<=0.8,"A",IF(E9<=0.95,"B","C"))) -> C | G9: =VLOOKUP(B$4:B$25,I$4:M$25,5,0) -> C | I9: th желтый Сул | J9: ='Юнит 02-08.02'!R8 -> 2 | K9: =J9/J$26 -> 0.033333333 | L9: =K9+L8 -> 0.96666667 | M9: =_xlfn.IFS(L9<80%,"A",L9<=95%,"B",L9>95%,"C") -> C
B10: MR Р1886 корич | C10: ='Юнит 02-08.02'!AE16 -> 0 | D10: =C10/C$26 -> 0 | E10: =D10+E9 -> 1.117076 | F10: =IF(AND(E10<=0),"C",IF(E10<=0.8,"A",IF(E10<=0.95,"B","C"))) -> C | G10: =VLOOKUP(B$4:B$25,I$4:M$25,5,0) -> B | I10: qs черные | J10: ='Юнит 02-08.02'!R4 -> 1 | K10: =J10/J$26 -> 0.016666667 | L10: =K10+L9 -> 0.98333333 | M10: =_xlfn.IFS(L10<80%,"A",L10<=95%,"B",L10>95%,"C") -> C
B11: lux1 | C11: ='Юнит 02-08.02'!AE17 -> 0 | D11: =C11/C$26 -> 0 | E11: =D11+E8 -> 1.1077277 | F11: =IF(AND(E11<=0),"C",IF(E11<=0.8,"A",IF(E11<=0.95,"B","C"))) -> C | G11: =VLOOKUP(B$4:B$25,I$4:M$25,5,0) -> B | I11: lux4 | J11: ='Юнит 02-08.02'!R20 -> 1 | K11: =J11/J$26 -> 0.016666667 | L11: =K11+L8 -> 0.95 | M11: =_xlfn.IFS(L11<80%,"A",L11<=95%,"B",L11>95%,"C") -> B
B12: lux2 | C12: ='Юнит 02-08.02'!AE18 -> 0 | D12: =C12/C$26 -> 0 | E12: =D12+E11 -> 1.1077277 | F12: =IF(AND(E12<=0),"C",IF(E12<=0.8,"A",IF(E12<=0.95,"B","C"))) -> C | G12: =VLOOKUP(B$4:B$25,I$4:M$25,5,0) -> B | I12: qs желтые | J12: ='Юнит 02-08.02'!R6 -> 0 | K12: =J12/J$26 -> 0 | L12: =K12+L11 -> 0.95 | M12: =_xlfn.IFS(L12<80%,"A",L12<=95%,"B",L12>95%,"C") -> B
B13: lux5 | C13: ='Юнит 02-08.02'!AE21 -> 0 | D13: =C13/C$26 -> 0 | E13: =D13+E12 -> 1.1077277 | F13: =IF(AND(E13<=0),"C",IF(E13<=0.8,"A",IF(E13<=0.95,"B","C"))) -> C | G13: =VLOOKUP(B$4:B$25,I$4:M$25,5,0) -> B | I13: MR8854 C2 | J13: ='Юнит 02-08.02'!R10 -> 0 | K13: =J13/J$26 -> 0 | L13: =K13+L12 -> 0.95 | M13: =_xlfn.IFS(L13<80%,"A",L13<=95%,"B",L13>95%,"C") -> B | P13: A | Q13: 0.8
B14: lux6 | C14: ='Юнит 02-08.02'!AE22 -> 0 | D14: =C14/C$26 -> 0 | E14: =D14+E13 -> 1.1077277 | F14: =IF(AND(E14<=0),"C",IF(E14<=0.8,"A",IF(E14<=0.95,"B","C"))) -> C | G14: =VLOOKUP(B$4:B$25,I$4:M$25,5,0) -> B | I14: MR 1819 черн | J14: ='Юнит 02-08.02'!R11 -> 0 | K14: =J14/J$26 -> 0 | L14: =K14+L13 -> 0.95 | M14: =_xlfn.IFS(L14<80%,"A",L14<=95%,"B",L14>95%,"C") -> B | P14: B | Q14: 0.15
B15: lux7 | C15: ='Юнит 02-08.02'!AE23 -> 0 | D15: =C15/C$26 -> 0 | E15: =D15+E14 -> 1.1077277 | F15: =IF(AND(E15<=0),"C",IF(E15<=0.8,"A",IF(E15<=0.95,"B","C"))) -> C | G15: =VLOOKUP(B$4:B$25,I$4:M$25,5,0) -> B | I15: MR 1819 корич | J15: ='Юнит 02-08.02'!R12 -> 0 | K15: =J15/J$26 -> 0 | L15: =K15+L14 -> 0.95 | M15: =_xlfn.IFS(L15<80%,"A",L15<=95%,"B",L15>95%,"C") -> B | P15: C | Q15: 0.05
B16: lux8 | C16: ='Юнит 02-08.02'!AE24 -> 0 | D16: =C16/C$26 -> 0 | E16: =D16+E15 -> 1.1077277 | F16: =IF(AND(E16<=0),"C",IF(E16<=0.8,"A",IF(E16<=0.95,"B","C"))) -> C | G16: =VLOOKUP(B$4:B$25,I$4:M$25,5,0) -> B | I16: MR Р1874 корич | J16: ='Юнит 02-08.02'!R14 -> 0 | K16: =J16/J$26 -> 0 | L16: =K16+L15 -> 0.95 | M16: =_xlfn.IFS(L16<80%,"A",L16<=95%,"B",L16>95%,"C") -> B
B17: MR 1819 черн | C17: ='Юнит 02-08.02'!AE11 -> -93.54 | D17: =C17/C$26 -> -0.0073060551 | E17: =D17+E16 -> 1.1004216 | F17: =IF(AND(E17<=0),"C",IF(E17<=0.8,"A",IF(E17<=0.95,"B","C"))) -> C | G17: =VLOOKUP(B$4:B$25,I$4:M$25,5,0) -> B | I17: MR Р1886 черн глянец | J17: ='Юнит 02-08.02'!R15 -> 0 | K17: =J17/J$26 -> 0 | L17: =K17+L16 -> 0.95 | M17: =_xlfn.IFS(L17<80%,"A",L17<=95%,"B",L17>95%,"C") -> B
B18: MR 1819 корич | C18: ='Юнит 02-08.02'!AE12 -> -93.54 | D18: =C18/C$26 -> -0.0073060551 | E18: =D18+E17 -> 1.0931156 | F18: =IF(AND(E18<=0),"C",IF(E18<=0.8,"A",IF(E18<=0.95,"B","C"))) -> C | G18: =VLOOKUP(B$4:B$25,I$4:M$25,5,0) -> B | I18: MR Р1886 корич | J18: ='Юнит 02-08.02'!R16 -> 0 | K18: =J18/J$26 -> 0 | L18: =K18+L17 -> 0.95 | M18: =_xlfn.IFS(L18<80%,"A",L18<=95%,"B",L18>95%,"C") -> B
B19: MR Р1874 корич | C19: ='Юнит 02-08.02'!AE14 -> -93.54 | D19: =C19/C$26 -> -0.0073060551 | E19: =D19+E18 -> 1.0858095 | F19: =IF(AND(E19<=0),"C",IF(E19<=0.8,"A",IF(E19<=0.95,"B","C"))) -> C | G19: =VLOOKUP(B$4:B$25,I$4:M$25,5,0) -> B | I19: lux1 | J19: ='Юнит 02-08.02'!R17 -> 0 | K19: =J19/J$26 -> 0 | L19: =K19+L18 -> 0.95 | M19: =_xlfn.IFS(L19<80%,"A",L19<=95%,"B",L19>95%,"C") -> B
B20: MR Р1886 черн глянец | C20: ='Юнит 02-08.02'!AE15 -> -93.54 | D20: =C20/C$26 -> -0.0073060551 | E20: =D20+E19 -> 1.0785034 | F20: =IF(AND(E20<=0),"C",IF(E20<=0.8,"A",IF(E20<=0.95,"B","C"))) -> C | G20: =VLOOKUP(B$4:B$25,I$4:M$25,5,0) -> B | I20: lux2 | J20: ='Юнит 02-08.02'!R18 -> 0 | K20: =J20/J$26 -> 0 | L20: =K20+L19 -> 0.95 | M20: =_xlfn.IFS(L20<80%,"A",L20<=95%,"B",L20>95%,"C") -> B
B21: qs коричневые | C21: ='Юнит 02-08.02'!AE7 -> -28.274503 | D21: =C21/C$26 -> -0.0022084143 | E21: =D21+E20 -> 1.076295 | F21: =IF(AND(E21<=0),"C",IF(E21<=0.8,"A",IF(E21<=0.95,"B","C"))) -> C | G21: =VLOOKUP(B$4:B$25,I$4:M$25,5,0) -> A | I21: lux3 | J21: ='Юнит 02-08.02'!R19 -> 0 | K21: =J21/J$26 -> 0 | L21: =K21+L20 -> 0.95 | M21: =_xlfn.IFS(L21<80%,"A",L21<=95%,"B",L21>95%,"C") -> B
B22: lux3 | C22: ='Юнит 02-08.02'!AE19 -> -113.88 | D22: =C22/C$26 -> -0.0088947354 | E22: =D22+E21 -> 1.0674003 | F22: =IF(AND(E22<=0),"C",IF(E22<=0.8,"A",IF(E22<=0.95,"B","C"))) -> C | G22: =VLOOKUP(B$4:B$25,I$4:M$25,5,0) -> B | I22: lux5 | J22: ='Юнит 02-08.02'!R21 -> 0 | K22: =J22/J$26 -> 0 | L22: =K22+L21 -> 0.95 | M22: =_xlfn.IFS(L22<80%,"A",L22<=95%,"B",L22>95%,"C") -> B
B23: qs желтые | C23: ='Юнит 02-08.02'!AE6 -> -263.94 | D23: =C23/C$26 -> -0.020615354 | E23: =D23+E22 -> 1.0467849 | F23: =IF(AND(E23<=0),"C",IF(E23<=0.8,"A",IF(E23<=0.95,"B","C"))) -> C | G23: =VLOOKUP(B$4:B$25,I$4:M$25,5,0) -> B | I23: lux6 | J23: ='Юнит 02-08.02'!R22 -> 0 | K23: =J23/J$26 -> 0 | L23: =K23+L22 -> 0.95 | M23: =_xlfn.IFS(L23<80%,"A",L23<=95%,"B",L23>95%,"C") -> B
B24: MR Р1874 черн | C24: ='Юнит 02-08.02'!AE13 -> -258.67858 | D24: =C24/C$26 -> -0.020204404 | E24: =D24+E23 -> 1.0265805 | F24: =IF(AND(E24<=0),"C",IF(E24<=0.8,"A",IF(E24<=0.95,"B","C"))) -> C | G24: =VLOOKUP(B$4:B$25,I$4:M$25,5,0) -> B | I24: lux7 | J24: ='Юнит 02-08.02'!R23 -> 0 | K24: =J24/J$26 -> 0 | L24: =K24+L23 -> 0.95 | M24: =_xlfn.IFS(L24<80%,"A",L24<=95%,"B",L24>95%,"C") -> B
B25: MR8854 C2 | C25: ='Юнит 02-08.02'!AE10 -> -460 | D25: =C25/C$26 -> -0.035928857 | E25: =D25+E24 -> 0.99065168 | F25: =IF(AND(E25<=0),"C",IF(E25<=0.8,"A",IF(E25<=0.95,"B","C"))) -> C | G25: =VLOOKUP(B$4:B$25,I$4:M$25,5,0) -> B | I25: lux8 | J25: ='Юнит 02-08.02'!R24 -> 0 | K25: =J25/J$26 -> 0 | L25: =K25+L24 -> 0.95 | M25: =_xlfn.IFS(L25<80%,"A",L25<=95%,"B",L25>95%,"C") -> B
C26: =SUM(C4:C25) -> 12803.079 | D26: =SUM(D4:D25) -> 1 | J26: =SUM(J4:J25) -> 60 | K26: =SUM(K4:K25) -> 1
B28: ТУНИКИ
C29: Прибыль | D29: % прибыль | E29: Доля | F29: ABC прибыль | G29: ABC кол-во | J29: Кол-во | K29: % кол-во | L29: Доля | M29: ABC кол-во
B30: tunika16 сетка белая | C30: ='Юнит 02-08.02'!AE46 -> 7804.8634 | D30: =C30/C$50 -> 0.48315587 | E30: =D30 -> 0.48315587 | F30: =IF(AND(E30<=0),"C",IF(E30<=0.8,"A",IF(E30<=0.95,"B","C"))) -> A | G30: =VLOOKUP(B$30:B$50,I$30:M$50,5,0) -> A | I30: tunika16 сетка белая | J30: ='Юнит 02-08.02'!R46 -> 7 | K30: =J30/J$50 -> 0.30434783 | L30: =K30 -> 0.30434783 | M30: =_xlfn.IFS(L30<80%,"A",L30<=95%,"B",L30>95%,"C") -> A
B31: tunika08 белая | C31: ='Юнит 02-08.02'!AE34 -> 3279.9222 | D31: =C31/C$50 -> 0.20304182 | E31: =D31+E30 -> 0.68619769 | F31: =IF(AND(E31<=0),"C",IF(E31<=0.8,"A",IF(E31<=0.95,"B","C"))) -> A | G31: =VLOOKUP(B$30:B$50,I$30:M$50,5,0) -> A | I31: tunika15 кимоно бирюза | J31: ='Юнит 02-08.02'!R44 -> 6 | K31: =J31/J$50 -> 0.26086957 | L31: =K31+L30 -> 0.56521739 | M31: =_xlfn.IFS(L31<80%,"A",L31<=95%,"B",L31>95%,"C") -> A
B32: tunika09 кимоно | C32: ='Юнит 02-08.02'!AE37 -> 3060.0832 | D32: =C32/C$50 -> 0.1894328 | E32: =D32+E31 -> 0.87563049 | F32: =IF(AND(E32<=0),"C",IF(E32<=0.8,"A",IF(E32<=0.95,"B","C"))) -> B | G32: =VLOOKUP(B$30:B$50,I$30:M$50,5,0) -> A | I32: tunika08 белая | J32: ='Юнит 02-08.02'!R34 -> 2 | K32: =J32/J$50 -> 0.086956522 | L32: =K32+L31 -> 0.65217391 | M32: =_xlfn.IFS(L32<80%,"A",L32<=95%,"B",L32>95%,"C") -> A
B33: tunika14 халат с разрезами черный | C33: ='Юнит 02-08.02'!AE43 -> 1455.7641 | D33: =C33/C$50 -> 0.090118292 | E33: =D33+E32 -> 0.96574878 | F33: =IF(AND(E33<=0),"C",IF(E33<=0.8,"A",IF(E33<=0.95,"B","C"))) -> C | G33: =VLOOKUP(B$30:B$50,I$30:M$50,5,0) -> C | I33: tunika09 кимоно | J33: ='Юнит 02-08.02'!R37 -> 2 | K33: =J33/J$50 -> 0.086956522 | L33: =K33+L32 -> 0.73913043 | M33: =_xlfn.IFS(L33<80%,"A",L33<=95%,"B",L33>95%,"C") -> A
B34: tunika15 кимоно бирюза | C34: ='Юнит 02-08.02'!AE44 -> 1463.1582 | D34: =C34/C$50 -> 0.09057602 | E34: =D34+E33 -> 1.0563248 | F34: =IF(AND(E34<=0),"C",IF(E34<=0.8,"A",IF(E34<=0.95,"B","C"))) -> C | G34: =VLOOKUP(B$30:B$50,I$30:M$50,5,0) -> A | I34: tunika15 кимоно песочная | J34: ='Юнит 02-08.02'!R45 -> 2 | K34: =J34/J$50 -> 0.086956522 | L34: =K34+L33 -> 0.82608696 | M34: =_xlfn.IFS(L34<80%,"A",L34<=95%,"B",L34>95%,"C") -> B
B35: tunika11 халат зеленая | C35: ='Юнит 02-08.02'!AE39 -> 1145.3411 | D35: =C35/C$50 -> 0.070901722 | E35: =D35+E34 -> 1.1272265 | F35: =IF(AND(E35<=0),"C",IF(E35<=0.8,"A",IF(E35<=0.95,"B","C"))) -> C | G35: =VLOOKUP(B$30:B$50,I$30:M$50,5,0) -> B | I35: tunika10 кимоно ч/б | J35: ='Юнит 02-08.02'!R38 -> 1 | K35: =J35/J$50 -> 0.043478261 | L35: =K35+L34 -> 0.86956522 | M35: =_xlfn.IFS(L35<80%,"A",L35<=95%,"B",L35>95%,"C") -> B
B36: tunika15 кимоно песочная | C36: ='Юнит 02-08.02'!AE45 -> 1169.3962 | D36: =C36/C$50 -> 0.072390845 | E36: =D36+E35 -> 1.1996174 | F36: =IF(AND(E36<=0),"C",IF(E36<=0.8,"A",IF(E36<=0.95,"B","C"))) -> C | G36: =VLOOKUP(B$30:B$50,I$30:M$50,5,0) -> B | I36: tunika11 халат зеленая | J36: ='Юнит 02-08.02'!R39 -> 1 | K36: =J36/J$50 -> 0.043478261 | L36: =K36+L35 -> 0.91304348 | M36: =_xlfn.IFS(L36<80%,"A",L36<=95%,"B",L36>95%,"C") -> B
B37: tunika10 кимоно ч/б | C37: ='Юнит 02-08.02'!AE38 -> 947.91203 | D37: =C37/C$50 -> 0.058679984 | E37: =D37+E36 -> 1.2582974 | F37: =IF(AND(E37<=0),"C",IF(E37<=0.8,"A",IF(E37<=0.95,"B","C"))) -> C | G37: =VLOOKUP(B$30:B$50,I$30:M$50,5,0) -> B | I37: tunika14 халат с разрезами белая | J37: ='Юнит 02-08.02'!R42 -> 1 | K37: =J37/J$50 -> 0.043478261 | L37: =K37+L36 -> 0.95652174 | M37: =_xlfn.IFS(L37<80%,"A",L37<=95%,"B",L37>95%,"C") -> C
B38: tunika05 белая распашная | C38: ='Юнит 02-08.02'!AE30 -> 0 | D38: =C38/C$50 -> 0 | E38: =D38+E37 -> 1.2582974 | F38: =IF(AND(E38<=0),"C",IF(E38<=0.8,"A",IF(E38<=0.95,"B","C"))) -> C | G38: =VLOOKUP(B$30:B$50,I$30:M$50,5,0) -> C | I38: tunika14 халат с разрезами черный | J38: ='Юнит 02-08.02'!R43 -> 1 | K38: =J38/J$50 -> 0.043478261 | L38: =K38+L37 -> 1 | M38: =_xlfn.IFS(L38<80%,"A",L38<=95%,"B",L38>95%,"C") -> C
B39: tunika06 белая | C39: ='Юнит 02-08.02'!AE31 -> 0 | D39: =C39/C$50 -> 0 | E39: =D39+E38 -> 1.2582974 | F39: =IF(AND(E39<=0),"C",IF(E39<=0.8,"A",IF(E39<=0.95,"B","C"))) -> C | G39: =VLOOKUP(B$30:B$50,I$30:M$50,5,0) -> C | I39: tunika02 оливковая с руч вышивкой | J39: ='Юнит 02-08.02'!R28 -> 0 | K39: =J39/J$50 -> 0 | L39: =K39+L38 -> 1 | M39: =_xlfn.IFS(L39<80%,"A",L39<=95%,"B",L39>95%,"C") -> C
B40: tunika06 черная | C40: ='Юнит 02-08.02'!AE32 -> 0 | D40: =C40/C$50 -> 0 | E40: =D40+E39 -> 1.2582974 | F40: =IF(AND(E40<=0),"C",IF(E40<=0.8,"A",IF(E40<=0.95,"B","C"))) -> C | G40: =VLOOKUP(B$30:B$50,I$30:M$50,5,0) -> C | I40: tunika03 черная распашная | J40: ='Юнит 02-08.02'!R29 -> 0 | K40: =J40/J$50 -> 0 | L40: =K40+L39 -> 1 | M40: =_xlfn.IFS(L40<80%,"A",L40<=95%,"B",L40>95%,"C") -> C
B41: tunika08 черная | C41: ='Юнит 02-08.02'!AE35 -> 0 | D41: =C41/C$50 -> 0 | E41: =D41+E40 -> 1.2582974 | F41: =IF(AND(E41<=0),"C",IF(E41<=0.8,"A",IF(E41<=0.95,"B","C"))) -> C | G41: =VLOOKUP(B$30:B$50,I$30:M$50,5,0) -> C | I41: tunika05 белая распашная | J41: ='Юнит 02-08.02'!R30 -> 0 | K41: =J41/J$50 -> 0 | L41: =K41+L40 -> 1 | M41: =_xlfn.IFS(L41<80%,"A",L41<=95%,"B",L41>95%,"C") -> C
B42: tunika12 халат белая | C42: ='Юнит 02-08.02'!AE40 -> 0 | D42: =C42/C$50 -> 0 | E42: =D42+E41 -> 1.2582974 | F42: =IF(AND(E42<=0),"C",IF(E42<=0.8,"A",IF(E42<=0.95,"B","C"))) -> C | G42: =VLOOKUP(B$30:B$50,I$30:M$50,5,0) -> C | I42: tunika06 белая | J42: ='Юнит 02-08.02'!R31 -> 0 | K42: =J42/J$50 -> 0 | L42: =K42+L41 -> 1 | M42: =_xlfn.IFS(L42<80%,"A",L42<=95%,"B",L42>95%,"C") -> C
B43: tunika13 халат черная | C43: ='Юнит 02-08.02'!AE41 -> 0 | D43: =C43/C$50 -> 0 | E43: =D43+E42 -> 1.2582974 | F43: =IF(AND(E43<=0),"C",IF(E43<=0.8,"A",IF(E43<=0.95,"B","C"))) -> C | G43: =VLOOKUP(B$30:B$50,I$30:M$50,5,0) -> C | I43: tunika06 черная | J43: ='Юнит 02-08.02'!R32 -> 0 | K43: =J43/J$50 -> 0 | L43: =K43+L42 -> 1 | M43: =_xlfn.IFS(L43<80%,"A",L43<=95%,"B",L43>95%,"C") -> C
B44: tunika02 оливковая с руч вышивкой | C44: ='Юнит 02-08.02'!AE28 -> -113.88 | D44: =C44/C$50 -> -0.0070496801 | E44: =D44+E43 -> 1.2512477 | F44: =IF(AND(E44<=0),"C",IF(E44<=0.8,"A",IF(E44<=0.95,"B","C"))) -> C | G44: =VLOOKUP(B$30:B$50,I$30:M$50,5,0) -> C | I44: tunika07 кружево | J44: ='Юнит 02-08.02'!R33 -> 0 | K44: =J44/J$50 -> 0 | L44: =K44+L43 -> 1 | M44: =_xlfn.IFS(L44<80%,"A",L44<=95%,"B",L44>95%,"C") -> C
B45: tunika03 черная распашная | C45: ='Юнит 02-08.02'!AE29 -> -113.88 | D45: =C45/C$50 -> -0.0070496801 | E45: =D45+E44 -> 1.244198 | F45: =IF(AND(E45<=0),"C",IF(E45<=0.8,"A",IF(E45<=0.95,"B","C"))) -> C | G45: =VLOOKUP(B$30:B$50,I$30:M$50,5,0) -> C | I45: tunika08 черная | J45: ='Юнит 02-08.02'!R35 -> 0 | K45: =J45/J$50 -> 0 | L45: =K45+L44 -> 1 | M45: =_xlfn.IFS(L45<80%,"A",L45<=95%,"B",L45>95%,"C") -> C
B46: tunika08 зеленая | C46: ='Юнит 02-08.02'!AE36 -> -113.88 | D46: =C46/C$50 -> -0.0070496801 | E46: =D46+E45 -> 1.2371483 | F46: =IF(AND(E46<=0),"C",IF(E46<=0.8,"A",IF(E46<=0.95,"B","C"))) -> C | G46: =VLOOKUP(B$30:B$50,I$30:M$50,5,0) -> C | I46: tunika08 зеленая | J46: ='Юнит 02-08.02'!R36 -> 0 | K46: =J46/J$50 -> 0 | L46: =K46+L45 -> 1 | M46: =_xlfn.IFS(L46<80%,"A",L46<=95%,"B",L46>95%,"C") -> C
B47: tunika16 сетка черная | C47: ='Юнит 02-08.02'!AE47 -> -113.88 | D47: =C47/C$50 -> -0.0070496801 | E47: =D47+E46 -> 1.2300986 | F47: =IF(AND(E47<=0),"C",IF(E47<=0.8,"A",IF(E47<=0.95,"B","C"))) -> C | G47: =VLOOKUP(B$30:B$50,I$30:M$50,5,0) -> C | I47: tunika12 халат белая | J47: ='Юнит 02-08.02'!R40 -> 0 | K47: =J47/J$50 -> 0 | L47: =K47+L46 -> 1 | M47: =_xlfn.IFS(L47<80%,"A",L47<=95%,"B",L47>95%,"C") -> C
B48: tunika07 кружево | C48: ='Юнит 02-08.02'!AE33 -> -227.76 | D48: =C48/C$50 -> -0.01409936 | E48: =D48+E47 -> 1.2159993 | F48: =IF(AND(E48<=0),"C",IF(E48<=0.8,"A",IF(E48<=0.95,"B","C"))) -> C | G48: =VLOOKUP(B$30:B$50,I$30:M$50,5,0) -> C | I48: tunika13 халат черная | J48: ='Юнит 02-08.02'!R41 -> 0 | K48: =J48/J$50 -> 0 | L48: =K48+L47 -> 1 | M48: =_xlfn.IFS(L48<80%,"A",L48<=95%,"B",L48>95%,"C") -> C
B49: tunika14 халат с разрезами белая | C49: ='Юнит 02-08.02'!AE42 -> -3489.2359 | D49: =C49/C$50 -> -0.21599927 | E49: =D49+E48 -> 1 | F49: =IF(AND(E49<=0),"C",IF(E49<=0.8,"A",IF(E49<=0.95,"B","C"))) -> C | G49: =VLOOKUP(B$30:B$50,I$30:M$50,5,0) -> C | I49: tunika16 сетка черная | J49: ='Юнит 02-08.02'!R47 -> 0 | K49: =J49/J$50 -> 0 | L49: =K49+L48 -> 1 | M49: =_xlfn.IFS(L49<80%,"A",L49<=95%,"B",L49>95%,"C") -> C
C50: =SUM(C30:C49) -> 16153.924 | D50: =SUM(D30:D49) -> 1 | J50: =SUM(J30:J49) -> 23 | K50: =SUM(K30:K49) -> 1

Sheet АВС ЯНВАРЬ
B2: ОЧКИ
C3: Прибыль | D3: % прибыль | E3: Доля | F3: ABC прибыль | G3: ABC кол-во | J3: Кол-во | K3: % кол-во | L3: Доля | M3: ABC кол-во
B4: черные с железкой классика | C4: =ЯНВАРЬ!AE3 -> 40731.919 | D4: =C4/C$26 -> 0.63166595 | E4: =D4 -> 0.63166595 | F4: =IF(AND(E4<=0),"C",IF(E4<=0.8,"A",IF(E4<=0.95,"B","C"))) -> A | G4: =VLOOKUP(B$4:B$25,I$4:M$25,5,0) -> A | I4: черные с железкой классика | J4: =ЯНВАРЬ!R3 -> 174 | K4: =J4/J$26 -> 0.64444444 | L4: =K4 -> 0.64444444 | M4: =_xlfn.IFS(L4<80%,"A",L4<=95%,"B",L4>95%,"C") -> A
B5: qs желтые | C5: =ЯНВАРЬ!AE6 -> 7328.9101 | D5: =C5/C$26 -> 0.1136559 | E5: =D5+E4 -> 0.74532185 | F5: =IF(AND(E5<=0),"C",IF(E5<=0.8,"A",IF(E5<=0.95,"B","C"))) -> A | G5: =VLOOKUP(B$4:B$25,I$4:M$25,5,0) -> A | I5: qs желтые | J5: =ЯНВАРЬ!R6 -> 33 | K5: =J5/J$26 -> 0.12222222 | L5: =K5+L4 -> 0.76666667 | M5: =_xlfn.IFS(L5<80%,"A",L5<=95%,"B",L5>95%,"C") -> A
B6: qs коричневые | C6: =ЯНВАРЬ!AE7 -> 5299.7732 | D6: =C6/C$26 -> 0.082188278 | E6: =D6+E5 -> 0.82751013 | F6: =IF(AND(E6<=0),"C",IF(E6<=0.8,"A",IF(E6<=0.95,"B","C"))) -> B | G6: =VLOOKUP(B$4:B$25,I$4:M$25,5,0) -> B | I6: qs коричневые | J6: =ЯНВАРЬ!R7 -> 12 | K6: =J6/J$26 -> 0.044444444 | L6: =K6+L5 -> 0.81111111 | M6: =_xlfn.IFS(L6<80%,"A",L6<=95%,"B",L6>95%,"C") -> B
B7: th желтый Сул | C7: =ЯНВАРЬ!AE8 -> 1731.7421 | D7: =C7/C$26 -> 0.026855658 | E7: =D7+E6 -> 0.85436579 | F7: =IF(AND(E7<=0),"C",IF(E7<=0.8,"A",IF(E7<=0.95,"B","C"))) -> B | G7: =VLOOKUP(B$4:B$25,I$4:M$25,5,0) -> B | I7: flip желтые Сул | J7: =ЯНВАРЬ!R9 -> 11 | K7: =J7/J$26 -> 0.040740741 | L7: =K7+L6 -> 0.85185185 | M7: =_xlfn.IFS(L7<80%,"A",L7<=95%,"B",L7>95%,"C") -> B
B8: qs синие | C8: =ЯНВАРЬ!AE5 -> 1728.3093 | D8: =C8/C$26 -> 0.026802423 | E8: =D8+E7 -> 0.88116821 | F8: =IF(AND(E8<=0),"C",IF(E8<=0.8,"A",IF(E8<=0.95,"B","C"))) -> B | G8: =VLOOKUP(B$4:B$25,I$4:M$25,5,0) -> B | I8: qs черные | J8: =ЯНВАРЬ!R4 -> 9 | K8: =J8/J$26 -> 0.033333333 | L8: =K8+L7 -> 0.88518519 | M8: =_xlfn.IFS(L8<80%,"A",L8<=95%,"B",L8>95%,"C") -> B
B9: lux4 | C9: =ЯНВАРЬ!AE20 -> 1673.6071 | D9: =C9/C$26 -> 0.025954108 | E9: =D9+E8 -> 0.90712232 | F9: =IF(AND(E9<=0),"C",IF(E9<=0.8,"A",IF(E9<=0.95,"B","C"))) -> B | G9: =VLOOKUP(B$4:B$25,I$4:M$25,5,0) -> C | I9: MR Р1874 черн | J9: =ЯНВАРЬ!R13 -> 5 | K9: =J9/J$26 -> 0.018518519 | L9: =K9+L8 -> 0.9037037 | M9: =_xlfn.IFS(L9<80%,"A",L9<=95%,"B",L9>95%,"C") -> B
B10: MR Р1874 корич | C10: =ЯНВАРЬ!AE14 -> 1541.0226 | D10: =C10/C$26 -> 0.023898002 | E10: =D10+E9 -> 0.93102032 | F10: =IF(AND(E10<=0),"C",IF(E10<=0.8,"A",IF(E10<=0.95,"B","C"))) -> B | G10: =VLOOKUP(B$4:B$25,I$4:M$25,5,0) -> B | I10: MR Р1874 корич | J10: =ЯНВАРЬ!R14 -> 5 | K10: =J10/J$26 -> 0.018518519 | L10: =K10+L9 -> 0.92222222 | M10: =_xlfn.IFS(L10<80%,"A",L10<=95%,"B",L10>95%,"C") -> B
B11: MR 1819 корич | C11: =ЯНВАРЬ!AE12 -> 1475.3244 | D11: =C11/C$26 -> 0.022879162 | E11: =D11+E8 -> 0.90404737 | F11: =IF(AND(E11<=0),"C",IF(E11<=0.8,"A",IF(E11<=0.95,"B","C"))) -> B | G11: =VLOOKUP(B$4:B$25,I$4:M$25,5,0) -> B | I11: qs синие | J11: =ЯНВАРЬ!R5 -> 4 | K11: =J11/J$26 -> 0.014814815 | L11: =K11+L8 -> 0.9 | M11: =_xlfn.IFS(L11<80%,"A",L11<=95%,"B",L11>95%,"C") -> B
B12: MR Р1886 корич | C12: =ЯНВАРЬ!AE16 -> 1147.4324 | D12: =C12/C$26 -> 0.01779425 | E12: =D12+E11 -> 0.92184162 | F12: =IF(AND(E12<=0),"C",IF(E12<=0.8,"A",IF(E12<=0.95,"B","C"))) -> B | G12: =VLOOKUP(B$4:B$25,I$4:M$25,5,0) -> B | I12: MR 1819 корич | J12: =ЯНВАРЬ!R12 -> 4 | K12: =J12/J$26 -> 0.014814815 | L12: =K12+L11 -> 0.91481481 | M12: =_xlfn.IFS(L12<80%,"A",L12<=95%,"B",L12>95%,"C") -> B
B13: lux3 | C13: =ЯНВАРЬ!AE19 -> 935.83469 | D13: =C13/C$26 -> 0.014512818 | E13: =D13+E12 -> 0.93635444 | F13: =IF(AND(E13<=0),"C",IF(E13<=0.8,"A",IF(E13<=0.95,"B","C"))) -> B | G13: =VLOOKUP(B$4:B$25,I$4:M$25,5,0) -> C | I13: MR Р1886 корич | J13: =ЯНВАРЬ!R16 -> 4 | K13: =J13/J$26 -> 0.014814815 | L13: =K13+L12 -> 0.92962963 | M13: =_xlfn.IFS(L13<80%,"A",L13<=95%,"B",L13>95%,"C") -> B | P13: A | Q13: 0.8
B14: MR Р1874 черн | C14: =ЯНВАРЬ!AE13 -> 775.66419 | D14: =C14/C$26 -> 0.012028912 | E14: =D14+E13 -> 0.94838335 | F14: =IF(AND(E14<=0),"C",IF(E14<=0.8,"A",IF(E14<=0.95,"B","C"))) -> B | G14: =VLOOKUP(B$4:B$25,I$4:M$25,5,0) -> B | I14: th желтый Сул | J14: =ЯНВАРЬ!R8 -> 3 | K14: =J14/J$26 -> 0.011111111 | L14: =K14+L13 -> 0.94074074 | M14: =_xlfn.IFS(L14<80%,"A",L14<=95%,"B",L14>95%,"C") -> B | P14: B | Q14: 0.15
B15: lux2 | C15: =ЯНВАРЬ!AE18 -> 703.75084 | D15: =C15/C$26 -> 0.010913688 | E15: =D15+E14 -> 0.95929704 | F15: =IF(AND(E15<=0),"C",IF(E15<=0.8,"A",IF(E15<=0.95,"B","C"))) -> C | G15: =VLOOKUP(B$4:B$25,I$4:M$25,5,0) -> C | I15: MR Р1886 черн глянец | J15: =ЯНВАРЬ!R15 -> 2 | K15: =J15/J$26 -> 0.0074074074 | L15: =K15+L14 -> 0.94814815 | M15: =_xlfn.IFS(L15<80%,"A",L15<=95%,"B",L15>95%,"C") -> B | P15: C | Q15: 0.05
B16: qs черные | C16: =ЯНВАРЬ!AE4 -> 368.94685 | D16: =C16/C$26 -> 0.0057215855 | E16: =D16+E15 -> 0.96501862 | F16: =IF(AND(E16<=0),"C",IF(E16<=0.8,"A",IF(E16<=0.95,"B","C"))) -> C | G16: =VLOOKUP(B$4:B$25,I$4:M$25,5,0) -> B | I16: MR8854 C2 | J16: =ЯНВАРЬ!R10 -> 1 | K16: =J16/J$26 -> 0.0037037037 | L16: =K16+L15 -> 0.95185185 | M16: =_xlfn.IFS(L16<80%,"A",L16<=95%,"B",L16>95%,"C") -> C
B17: MR8854 C2 | C17: =ЯНВАРЬ!AE10 -> 285.93544 | D17: =C17/C$26 -> 0.0044342542 | E17: =D17+E16 -> 0.96945288 | F17: =IF(AND(E17<=0),"C",IF(E17<=0.8,"A",IF(E17<=0.95,"B","C"))) -> C | G17: =VLOOKUP(B$4:B$25,I$4:M$25,5,0) -> C | I17: lux2 | J17: =ЯНВАРЬ!R18 -> 1 | K17: =J17/J$26 -> 0.0037037037 | L17: =K17+L16 -> 0.95555556 | M17: =_xlfn.IFS(L17<80%,"A",L17<=95%,"B",L17>95%,"C") -> C
B18: lux1 | C18: =ЯНВАРЬ!AE17 -> 0 | D18: =C18/C$26 -> 0 | E18: =D18+E17 -> 0.96945288 | F18: =IF(AND(E18<=0),"C",IF(E18<=0.8,"A",IF(E18<=0.95,"B","C"))) -> C | G18: =VLOOKUP(B$4:B$25,I$4:M$25,5,0) -> C | I18: lux3 | J18: =ЯНВАРЬ!R19 -> 1 | K18: =J18/J$26 -> 0.0037037037 | L18: =K18+L17 -> 0.95925926 | M18: =_xlfn.IFS(L18<80%,"A",L18<=95%,"B",L18>95%,"C") -> C
B19: lux5 | C19: =ЯНВАРЬ!AE21 -> 0 | D19: =C19/C$26 -> 0 | E19: =D19+E18 -> 0.96945288 | F19: =IF(AND(E19<=0),"C",IF(E19<=0.8,"A",IF(E19<=0.95,"B","C"))) -> C | G19: =VLOOKUP(B$4:B$25,I$4:M$25,5,0) -> C | I19: lux4 | J19: =ЯНВАРЬ!R20 -> 1 | K19: =J19/J$26 -> 0.0037037037 | L19: =K19+L18 -> 0.96296296 | M19: =_xlfn.IFS(L19<80%,"A",L19<=95%,"B",L19>95%,"C") -> C
B20: lux6 | C20: =ЯНВАРЬ!AE22 -> 0 | D20: =C20/C$26 -> 0 | E20: =D20+E19 -> 0.96945288 | F20: =IF(AND(E20<=0),"C",IF(E20<=0.8,"A",IF(E20<=0.95,"B","C"))) -> C | G20: =VLOOKUP(B$4:B$25,I$4:M$25,5,0) -> C | I20: MR 1819 черн | J20: =ЯНВАРЬ!R11 -> 0 | K20: =J20/J$26 -> 0 | L20: =K20+L19 -> 0.96296296 | M20: =_xlfn.IFS(L20<80%,"A",L20<=95%,"B",L20>95%,"C") -> C
B21: lux7 | C21: =ЯНВАРЬ!AE23 -> 0 | D21: =C21/C$26 -> 0 | E21: =D21+E20 -> 0.96945288 | F21: =IF(AND(E21<=0),"C",IF(E21<=0.8,"A",IF(E21<=0.95,"B","C"))) -> C | G21: =VLOOKUP(B$4:B$25,I$4:M$25,5,0) -> C | I21: lux1 | J21: =ЯНВАРЬ!R17 -> 0 | K21: =J21/J$26 -> 0 | L21: =K21+L20 -> 0.96296296 | M21: =_xlfn.IFS(L21<80%,"A",L21<=95%,"B",L21>95%,"C") -> C
B22: lux8 | C22: =ЯНВАРЬ!AE24 -> 0 | D22: =C22/C$26 -> 0 | E22: =D22+E21 -> 0.96945288 | F22: =IF(AND(E22<=0),"C",IF(E22<=0.8,"A",IF(E22<=0.95,"B","C"))) -> C | G22: =VLOOKUP(B$4:B$25,I$4:M$25,5,0) -> C | I22: lux5 | J22: =ЯНВАРЬ!R21 -> 0 | K22: =J22/J$26 -> 0 | L22: =K22+L21 -> 0.96296296 | M22: =_xlfn.IFS(L22<80%,"A",L22<=95%,"B",L22>95%,"C") -> C
B23: MR 1819 черн | C23: =ЯНВАРЬ!AE11 -> -93.54 | D23: =C23/C$26 -> -0.0014506076 | E23: =D23+E22 -> 0.96800227 | F23: =IF(AND(E23<=0),"C",IF(E23<=0.8,"A",IF(E23<=0.95,"B","C"))) -> C | G23: =VLOOKUP(B$4:B$25,I$4:M$25,5,0) -> C | I23: lux6 | J23: =ЯНВАРЬ!R22 -> 0 | K23: =J23/J$26 -> 0 | L23: =K23+L22 -> 0.96296296 | M23: =_xlfn.IFS(L23<80%,"A",L23<=95%,"B",L23>95%,"C") -> C
B24: flip желтые Сул | C24: =ЯНВАРЬ!AE9 -> -210.09145 | D24: =C24/C$26 -> -0.0032580742 | E24: =D24+E23 -> 0.96474419 | F24: =IF(AND(E24<=0),"C",IF(E24<=0.8,"A",IF(E24<=0.95,"B","C"))) -> C | G24: =VLOOKUP(B$4:B$25,I$4:M$25,5,0) -> B | I24: lux7 | J24: =ЯНВАРЬ!R23 -> 0 | K24: =J24/J$26 -> 0 | L24: =K24+L23 -> 0.96296296 | M24: =_xlfn.IFS(L24<80%,"A",L24<=95%,"B",L24>95%,"C") -> C
B25: MR Р1886 черн глянец | C25: =ЯНВАРЬ!AE15 -> -941.21825 | D25: =C25/C$26 -> -0.014596305 | E25: =D25+E24 -> 0.95014789 | F25: =IF(AND(E25<=0),"C",IF(E25<=0.8,"A",IF(E25<=0.95,"B","C"))) -> C | G25: =VLOOKUP(B$4:B$25,I$4:M$25,5,0) -> B | I25: lux8 | J25: =ЯНВАРЬ!R24 -> 0 | K25: =J25/J$26 -> 0 | L25: =K25+L24 -> 0.96296296 | M25: =_xlfn.IFS(L25<80%,"A",L25<=95%,"B",L25>95%,"C") -> C
C26: =SUM(C4:C25) -> 64483.322 | D26: =SUM(D4:D25) -> 1 | J26: =SUM(J4:J25) -> 270 | K26: =SUM(K4:K25) -> 1
B28: ТУНИКИ
C29: Прибыль | D29: % прибыль | E29: Доля | F29: ABC прибыль | G29: ABC кол-во | J29: Кол-во | K29: % кол-во | L29: Доля | M29: ABC кол-во
B30: tunika15 кимоно песочная | C30: =ЯНВАРЬ!AE45 -> 14105.949 | D30: =C30/C$50 -> 0.61469287 | E30: =D30 -> 0.61469287 | F30: =IF(AND(E30<=0),"C",IF(E30<=0.8,"A",IF(E30<=0.95,"B","C"))) -> A | G30: =VLOOKUP(B$30:B$50,I$30:M$50,5,0) -> A | I30: tunika15 кимоно песочная | J30: =ЯНВАРЬ!R45 -> 17 | K30: =J30/J$50 -> 0.4047619 | L30: =K30 -> 0.4047619 | M30: =_xlfn.IFS(L30<80%,"A",L30<=95%,"B",L30>95%,"C") -> A
B31: tunika09 кимоно | C31: =ЯНВАРЬ!AE37 -> 4099.5304 | D31: =C31/C$50 -> 0.17864464 | E31: =D31+E30 -> 0.79333751 | F31: =IF(AND(E31<=0),"C",IF(E31<=0.8,"A",IF(E31<=0.95,"B","C"))) -> A | G31: =VLOOKUP(B$30:B$50,I$30:M$50,5,0) -> B | I31: tunika15 кимоно бирюза | J31: =ЯНВАРЬ!R44 -> 15 | K31: =J31/J$50 -> 0.35714286 | L31: =K31+L30 -> 0.76190476 | M31: =_xlfn.IFS(L31<80%,"A",L31<=95%,"B",L31>95%,"C") -> A
B32: tunika15 кимоно бирюза | C32: =ЯНВАРЬ!AE44 -> 2904.6308 | D32: =C32/C$50 -> 0.12657467 | E32: =D32+E31 -> 0.91991219 | F32: =IF(AND(E32<=0),"C",IF(E32<=0.8,"A",IF(E32<=0.95,"B","C"))) -> B | G32: =VLOOKUP(B$30:B$50,I$30:M$50,5,0) -> A | I32: tunika09 кимоно | J32: =ЯНВАРЬ!R37 -> 3 | K32: =J32/J$50 -> 0.071428571 | L32: =K32+L31 -> 0.83333333 | M32: =_xlfn.IFS(L32<80%,"A",L32<=95%,"B",L32>95%,"C") -> B
B33: tunika08 черная | C33: =ЯНВАРЬ!AE35 -> 2517.4305 | D33: =C33/C$50 -> 0.1097017 | E33: =D33+E32 -> 1.0296139 | F33: =IF(AND(E33<=0),"C",IF(E33<=0.8,"A",IF(E33<=0.95,"B","C"))) -> C | G33: =VLOOKUP(B$30:B$50,I$30:M$50,5,0) -> B | I33: tunika08 черная | J33: =ЯНВАРЬ!R35 -> 2 | K33: =J33/J$50 -> 0.047619048 | L33: =K33+L32 -> 0.88095238 | M33: =_xlfn.IFS(L33<80%,"A",L33<=95%,"B",L33>95%,"C") -> B
B34: tunika08 белая | C34: =ЯНВАРЬ!AE34 -> 1619.6822 | D34: =C34/C$50 -> 0.070580657 | E34: =D34+E33 -> 1.1001945 | F34: =IF(AND(E34<=0),"C",IF(E34<=0.8,"A",IF(E34<=0.95,"B","C"))) -> C | G34: =VLOOKUP(B$30:B$50,I$30:M$50,5,0) -> C | I34: tunika06 белая | J34: =ЯНВАРЬ!R31 -> 1 | K34: =J34/J$50 -> 0.023809524 | L34: =K34+L33 -> 0.9047619 | M34: =_xlfn.IFS(L34<80%,"A",L34<=95%,"B",L34>95%,"C") -> B
B35: tunika06 белая | C35: =ЯНВАРЬ!AE31 -> 1255.3137 | D35: =C35/C$50 -> 0.054702624 | E35: =D35+E34 -> 1.1548972 | F35: =IF(AND(E35<=0),"C",IF(E35<=0.8,"A",IF(E35<=0.95,"B","C"))) -> C | G35: =VLOOKUP(B$30:B$50,I$30:M$50,5,0) -> B | I35: tunika07 кружево | J35: =ЯНВАРЬ!R33 -> 1 | K35: =J35/J$50 -> 0.023809524 | L35: =K35+L34 -> 0.92857143 | M35: =_xlfn.IFS(L35<80%,"A",L35<=95%,"B",L35>95%,"C") -> B
B36: tunika07 кружево | C36: =ЯНВАРЬ!AE33 -> 866.25296 | D36: =C36/C$50 -> 0.037748579 | E36: =D36+E35 -> 1.1926457 | F36: =IF(AND(E36<=0),"C",IF(E36<=0.8,"A",IF(E36<=0.95,"B","C"))) -> C | G36: =VLOOKUP(B$30:B$50,I$30:M$50,5,0) -> B | I36: tunika08 белая | J36: =ЯНВАРЬ!R34 -> 1 | K36: =J36/J$50 -> 0.023809524 | L36: =K36+L35 -> 0.95238095 | M36: =_xlfn.IFS(L36<80%,"A",L36<=95%,"B",L36>95%,"C") -> C
B37: tunika14 халат с разрезами белая | C37: =ЯНВАРЬ!AE42 -> 469.31251 | D37: =C37/C$50 -> 0.020451163 | E37: =D37+E36 -> 1.2130969 | F37: =IF(AND(E37<=0),"C",IF(E37<=0.8,"A",IF(E37<=0.95,"B","C"))) -> C | G37: =VLOOKUP(B$30:B$50,I$30:M$50,5,0) -> C | I37: tunika14 халат с разрезами белая | J37: =ЯНВАРЬ!R42 -> 1 | K37: =J37/J$50 -> 0.023809524 | L37: =K37+L36 -> 0.97619048 | M37: =_xlfn.IFS(L37<80%,"A",L37<=95%,"B",L37>95%,"C") -> C
B38: tunika06 черная | C38: =ЯНВАРЬ!AE32 -> 0 | D38: =C38/C$50 -> 0 | E38: =D38+E37 -> 1.2130969 | F38: =IF(AND(E38<=0),"C",IF(E38<=0.8,"A",IF(E38<=0.95,"B","C"))) -> C | G38: =VLOOKUP(B$30:B$50,I$30:M$50,5,0) -> C | I38: tunika16 сетка белая | J38: =ЯНВАРЬ!R46 -> 1 | K38: =J38/J$50 -> 0.023809524 | L38: =K38+L37 -> 1 | M38: =_xlfn.IFS(L38<80%,"A",L38<=95%,"B",L38>95%,"C") -> C
B39: tunika11 халат зеленая | C39: =ЯНВАРЬ!AE39 -> 0 | D39: =C39/C$50 -> 0 | E39: =D39+E38 -> 1.2130969 | F39: =IF(AND(E39<=0),"C",IF(E39<=0.8,"A",IF(E39<=0.95,"B","C"))) -> C | G39: =VLOOKUP(B$30:B$50,I$30:M$50,5,0) -> C | I39: tunika02 оливковая с руч вышивкой | J39: =ЯНВАРЬ!R28 -> 0 | K39: =J39/J$50 -> 0 | L39: =K39+L38 -> 1 | M39: =_xlfn.IFS(L39<80%,"A",L39<=95%,"B",L39>95%,"C") -> C
B40: tunika12 халат белая | C40: =ЯНВАРЬ!AE40 -> 0 | D40: =C40/C$50 -> 0 | E40: =D40+E39 -> 1.2130969 | F40: =IF(AND(E40<=0),"C",IF(E40<=0.8,"A",IF(E40<=0.95,"B","C"))) -> C | G40: =VLOOKUP(B$30:B$50,I$30:M$50,5,0) -> C | I40: tunika03 черная распашная | J40: =ЯНВАРЬ!R29 -> 0 | K40: =J40/J$50 -> 0 | L40: =K40+L39 -> 1 | M40: =_xlfn.IFS(L40<80%,"A",L40<=95%,"B",L40>95%,"C") -> C
B41: tunika13 халат черная | C41: =ЯНВАРЬ!AE41 -> 0 | D41: =C41/C$50 -> 0 | E41: =D41+E40 -> 1.2130969 | F41: =IF(AND(E41<=0),"C",IF(E41<=0.8,"A",IF(E41<=0.95,"B","C"))) -> C | G41: =VLOOKUP(B$30:B$50,I$30:M$50,5,0) -> C | I41: tunika05 белая распашная | J41: =ЯНВАРЬ!R30 -> 0 | K41: =J41/J$50 -> 0 | L41: =K41+L40 -> 1 | M41: =_xlfn.IFS(L41<80%,"A",L41<=95%,"B",L41>95%,"C") -> C
B42: tunika16 сетка черная | C42: =ЯНВАРЬ!AE47 -> 0 | D42: =C42/C$50 -> 0 | E42: =D42+E41 -> 1.2130969 | F42: =IF(AND(E42<=0),"C",IF(E42<=0.8,"A",IF(E42<=0.95,"B","C"))) -> C | G42: =VLOOKUP(B$30:B$50,I$30:M$50,5,0) -> C | I42: tunika06 черная | J42: =ЯНВАРЬ!R32 -> 0 | K42: =J42/J$50 -> 0 | L42: =K42+L41 -> 1 | M42: =_xlfn.IFS(L42<80%,"A",L42<=95%,"B",L42>95%,"C") -> C
B43: tunika03 черная распашная | C43: =ЯНВАРЬ!AE29 -> -113.88 | D43: =C43/C$50 -> -0.0049625322 | E43: =D43+E42 -> 1.2081344 | F43: =IF(AND(E43<=0),"C",IF(E43<=0.8,"A",IF(E43<=0.95,"B","C"))) -> C | G43: =VLOOKUP(B$30:B$50,I$30:M$50,5,0) -> C | I43: tunika08 зеленая | J43: =ЯНВАРЬ!R36 -> 0 | K43: =J43/J$50 -> 0 | L43: =K43+L42 -> 1 | M43: =_xlfn.IFS(L43<80%,"A",L43<=95%,"B",L43>95%,"C") -> C
B44: tunika05 белая распашная | C44: =ЯНВАРЬ!AE30 -> -113.88 | D44: =C44/C$50 -> -0.0049625322 | E44: =D44+E43 -> 1.2031718 | F44: =IF(AND(E44<=0),"C",IF(E44<=0.8,"A",IF(E44<=0.95,"B","C"))) -> C | G44: =VLOOKUP(B$30:B$50,I$30:M$50,5,0) -> C | I44: tunika10 кимоно ч/б | J44: =ЯНВАРЬ!R38 -> 0 | K44: =J44/J$50 -> 0 | L44: =K44+L43 -> 1 | M44: =_xlfn.IFS(L44<80%,"A",L44<=95%,"B",L44>95%,"C") -> C
B45: tunika08 зеленая | C45: =ЯНВАРЬ!AE36 -> -113.88 | D45: =C45/C$50 -> -0.0049625322 | E45: =D45+E44 -> 1.1982093 | F45: =IF(AND(E45<=0),"C",IF(E45<=0.8,"A",IF(E45<=0.95,"B","C"))) -> C | G45: =VLOOKUP(B$30:B$50,I$30:M$50,5,0) -> C | I45: tunika11 халат зеленая | J45: =ЯНВАРЬ!R39 -> 0 | K45: =J45/J$50 -> 0 | L45: =K45+L44 -> 1 | M45: =_xlfn.IFS(L45<80%,"A",L45<=95%,"B",L45>95%,"C") -> C
B46: tunika14 халат с разрезами черный | C46: =ЯНВАРЬ!AE43 -> -227.76 | D46: =C46/C$50 -> -0.0099250645 | E46: =D46+E45 -> 1.1882843 | F46: =IF(AND(E46<=0),"C",IF(E46<=0.8,"A",IF(E46<=0.95,"B","C"))) -> C | G46: =VLOOKUP(B$30:B$50,I$30:M$50,5,0) -> C | I46: tunika12 халат белая | J46: =ЯНВАРЬ!R40 -> 0 | K46: =J46/J$50 -> 0 | L46: =K46+L45 -> 1 | M46: =_xlfn.IFS(L46<80%,"A",L46<=95%,"B",L46>95%,"C") -> C
B47: tunika10 кимоно ч/б | C47: =ЯНВАРЬ!AE38 -> -432.27 | D47: =C47/C$50 -> -0.018836967 | E47: =D47+E46 -> 1.1694473 | F47: =IF(AND(E47<=0),"C",IF(E47<=0.8,"A",IF(E47<=0.95,"B","C"))) -> C | G47: =VLOOKUP(B$30:B$50,I$30:M$50,5,0) -> C | I47: tunika13 халат черная | J47: =ЯНВАРЬ!R41 -> 0 | K47: =J47/J$50 -> 0 | L47: =K47+L46 -> 1 | M47: =_xlfn.IFS(L47<80%,"A",L47<=95%,"B",L47>95%,"C") -> C
B48: tunika02 оливковая с руч вышивкой | C48: =ЯНВАРЬ!AE28 -> -1090.7745 | D48: =C48/C$50 -> -0.047532523 | E48: =D48+E47 -> 1.1219148 | F48: =IF(AND(E48<=0),"C",IF(E48<=0.8,"A",IF(E48<=0.95,"B","C"))) -> C | G48: =VLOOKUP(B$30:B$50,I$30:M$50,5,0) -> C | I48: tunika14 халат с разрезами черный | J48: =ЯНВАРЬ!R43 -> 0 | K48: =J48/J$50 -> 0 | L48: =K48+L47 -> 1 | M48: =_xlfn.IFS(L48<80%,"A",L48<=95%,"B",L48>95%,"C") -> C
B49: tunika16 сетка белая | C49: =ЯНВАРЬ!AE46 -> -2797.6952 | D49: =C49/C$50 -> -0.12191476 | E49: =D49+E48 -> 1 | F49: =IF(AND(E49<=0),"C",IF(E49<=0.8,"A",IF(E49<=0.95,"B","C"))) -> C | G49: =VLOOKUP(B$30:B$50,I$30:M$50,5,0) -> C | I49: tunika16 сетка черная | J49: =ЯНВАРЬ!R47 -> 0 | K49: =J49/J$50 -> 0 | L49: =K49+L48 -> 1 | M49: =_xlfn.IFS(L49<80%,"A",L49<=95%,"B",L49>95%,"C") -> C
C50: =SUM(C30:C49) -> 22947.962 | D50: =SUM(D30:D49) -> 1 | J50: =SUM(J30:J49) -> 42 | K50: =SUM(K30:K49) -> 1

Sheet АВС 26.01-01.02
B2: ОЧКИ
C3: Прибыль | D3: % прибыль | E3: Доля | F3: ABC прибыль | G3: ABC кол-во | J3: Кол-во | K3: % кол-во | L3: Доля | M3: ABC кол-во
B4: черные с железкой классика | C4: ='Юнит 26.01-01.02'!AE3 -> 15483.42 | D4: =C4/C$26 -> 0.69780888 | E4: =D4 -> 0.69780888 | F4: =IF(AND(E4<=0),"C",IF(E4<=0.8,"A",IF(E4<=0.95,"B","C"))) -> A | G4: =VLOOKUP(B$4:B$25,I$4:M$25,5,0) -> A | I4: черные с железкой классика | J4: ='Юнит 26.01-01.02'!R3 -> 52 | K4: =J4/J$26 -> 0.68421053 | L4: =K4 -> 0.68421053 | M4: =_xlfn.IFS(L4<80%,"A",L4<=95%,"B",L4>95%,"C") -> A
B5: qs коричневые | C5: ='Юнит 26.01-01.02'!AE7 -> 1981.02 | D5: =C5/C$26 -> 0.089280877 | E5: =D5+E4 -> 0.78708976 | F5: =IF(AND(E5<=0),"C",IF(E5<=0.8,"A",IF(E5<=0.95,"B","C"))) -> A | G5: =VLOOKUP(B$4:B$25,I$4:M$25,5,0) -> B | I5: flip желтые Сул | J5: ='Юнит 26.01-01.02'!R9 -> 5 | K5: =J5/J$26 -> 0.065789474 | L5: =K5+L4 -> 0.75 | M5: =_xlfn.IFS(L5<80%,"A",L5<=95%,"B",L5>95%,"C") -> A
B6: th желтый Сул | C6: ='Юнит 26.01-01.02'!AE8 -> 1098.34 | D6: =C6/C$26 -> 0.049500136 | E6: =D6+E5 -> 0.83658989 | F6: =IF(AND(E6<=0),"C",IF(E6<=0.8,"A",IF(E6<=0.95,"B","C"))) -> B | G6: =VLOOKUP(B$4:B$25,I$4:M$25,5,0) -> B | I6: qs коричневые | J6: ='Юнит 26.01-01.02'!R7 -> 4 | K6: =J6/J$26 -> 0.052631579 | L6: =K6+L5 -> 0.80263158 | M6: =_xlfn.IFS(L6<80%,"A",L6<=95%,"B",L6>95%,"C") -> B
B7: MR Р1874 черн | C7: ='Юнит 26.01-01.02'!AE13 -> 951.36 | D7: =C7/C$26 -> 0.042876021 | E7: =D7+E6 -> 0.87946592 | F7: =IF(AND(E7<=0),"C",IF(E7<=0.8,"A",IF(E7<=0.95,"B","C"))) -> B | G7: =VLOOKUP(B$4:B$25,I$4:M$25,5,0) -> B | I7: qs желтые | J7: ='Юнит 26.01-01.02'!R6 -> 3 | K7: =J7/J$26 -> 0.039473684 | L7: =K7+L6 -> 0.84210526 | M7: =_xlfn.IFS(L7<80%,"A",L7<=95%,"B",L7>95%,"C") -> B
B8: qs желтые | C8: ='Юнит 26.01-01.02'!AE6 -> 762.93 | D8: =C8/C$26 -> 0.034383832 | E8: =D8+E7 -> 0.91384975 | F8: =IF(AND(E8<=0),"C",IF(E8<=0.8,"A",IF(E8<=0.95,"B","C"))) -> B | G8: =VLOOKUP(B$4:B$25,I$4:M$25,5,0) -> B | I8: MR Р1874 черн | J8: ='Юнит 26.01-01.02'!R13 -> 3 | K8: =J8/J$26 -> 0.039473684 | L8: =K8+L7 -> 0.88157895 | M8: =_xlfn.IFS(L8<80%,"A",L8<=95%,"B",L8>95%,"C") -> B
B9: MR Р1874 корич | C9: ='Юнит 26.01-01.02'!AE14 -> 727.95 | D9: =C9/C$26 -> 0.032807349 | E9: =D9+E8 -> 0.9466571 | F9: =IF(AND(E9<=0),"C",IF(E9<=0.8,"A",IF(E9<=0.95,"B","C"))) -> B | G9: =VLOOKUP(B$4:B$25,I$4:M$25,5,0) -> B | I9: MR Р1874 корич | J9: ='Юнит 26.01-01.02'!R14 -> 3 | K9: =J9/J$26 -> 0.039473684 | L9: =K9+L8 -> 0.92105263 | M9: =_xlfn.IFS(L9<80%,"A",L9<=95%,"B",L9>95%,"C") -> B
B10: lux2 | C10: ='Юнит 26.01-01.02'!AE18 -> 684.92 | D10: =C10/C$26 -> 0.030868067 | E10: =D10+E9 -> 0.97752516 | F10: =IF(AND(E10<=0),"C",IF(E10<=0.8,"A",IF(E10<=0.95,"B","C"))) -> C | G10: =VLOOKUP(B$4:B$25,I$4:M$25,5,0) -> B | I10: th желтый Сул | J10: ='Юнит 26.01-01.02'!R8 -> 2 | K10: =J10/J$26 -> 0.026315789 | L10: =K10+L9 -> 0.94736842 | M10: =_xlfn.IFS(L10<80%,"A",L10<=95%,"B",L10>95%,"C") -> B
B11: MR8854 C2 | C11: ='Юнит 26.01-01.02'!AE10 -> 556.66 | D11: =C11/C$26 -> 0.025087628 | E11: =D11+E8 -> 0.93893738 | F11: =IF(AND(E11<=0),"C",IF(E11<=0.8,"A",IF(E11<=0.95,"B","C"))) -> B | G11: =VLOOKUP(B$4:B$25,I$4:M$25,5,0) -> B | I11: qs черные | J11: ='Юнит 26.01-01.02'!R4 -> 1 | K11: =J11/J$26 -> 0.013157895 | L11: =K11+L8 -> 0.89473684 | M11: =_xlfn.IFS(L11<80%,"A",L11<=95%,"B",L11>95%,"C") -> B
B12: MR 1819 корич | C12: ='Юнит 26.01-01.02'!AE12 -> 428.41 | D12: =C12/C$26 -> 0.01930764 | E12: =D12+E11 -> 0.95824502 | F12: =IF(AND(E12<=0),"C",IF(E12<=0.8,"A",IF(E12<=0.95,"B","C"))) -> C | G12: =VLOOKUP(B$4:B$25,I$4:M$25,5,0) -> B | I12: MR8854 C2 | J12: ='Юнит 26.01-01.02'!R10 -> 1 | K12: =J12/J$26 -> 0.013157895 | L12: =K12+L11 -> 0.90789474 | M12: =_xlfn.IFS(L12<80%,"A",L12<=95%,"B",L12>95%,"C") -> B
B13: flip желтые Сул | C13: ='Юнит 26.01-01.02'!AE9 -> 292.20371 | D13: =C13/C$26 -> 0.013169076 | E13: =D13+E12 -> 0.97141409 | F13: =IF(AND(E13<=0),"C",IF(E13<=0.8,"A",IF(E13<=0.95,"B","C"))) -> C | G13: =VLOOKUP(B$4:B$25,I$4:M$25,5,0) -> A | I13: MR 1819 корич | J13: ='Юнит 26.01-01.02'!R12 -> 1 | K13: =J13/J$26 -> 0.013157895 | L13: =K13+L12 -> 0.92105263 | M13: =_xlfn.IFS(L13<80%,"A",L13<=95%,"B",L13>95%,"C") -> B | P13: A | Q13: 0.8
B14: qs черные | C14: ='Юнит 26.01-01.02'!AE4 -> 156.78202 | D14: =C14/C$26 -> 0.0070658731 | E14: =D14+E13 -> 0.97847997 | F14: =IF(AND(E14<=0),"C",IF(E14<=0.8,"A",IF(E14<=0.95,"B","C"))) -> C | G14: =VLOOKUP(B$4:B$25,I$4:M$25,5,0) -> B | I14: lux2 | J14: ='Юнит 26.01-01.02'!R18 -> 1 | K14: =J14/J$26 -> 0.013157895 | L14: =K14+L13 -> 0.93421053 | M14: =_xlfn.IFS(L14<80%,"A",L14<=95%,"B",L14>95%,"C") -> B | P14: B | Q14: 0.15
B15: MR 1819 черн | C15: ='Юнит 26.01-01.02'!AE11 -> 0 | D15: =C15/C$26 -> 0 | E15: =D15+E14 -> 0.97847997 | F15: =IF(AND(E15<=0),"C",IF(E15<=0.8,"A",IF(E15<=0.95,"B","C"))) -> C | G15: =VLOOKUP(B$4:B$25,I$4:M$25,5,0) -> B | I15: qs синие | J15: ='Юнит 26.01-01.02'!R5 -> 0 | K15: =J15/J$26 -> 0 | L15: =K15+L14 -> 0.93421053 | M15: =_xlfn.IFS(L15<80%,"A",L15<=95%,"B",L15>95%,"C") -> B | P15: C | Q15: 0.05
B16: lux1 | C16: ='Юнит 26.01-01.02'!AE17 -> 0 | D16: =C16/C$26 -> 0 | E16: =D16+E15 -> 0.97847997 | F16: =IF(AND(E16<=0),"C",IF(E16<=0.8,"A",IF(E16<=0.95,"B","C"))) -> C | G16: =VLOOKUP(B$4:B$25,I$4:M$25,5,0) -> B | I16: MR 1819 черн | J16: ='Юнит 26.01-01.02'!R11 -> 0 | K16: =J16/J$26 -> 0 | L16: =K16+L15 -> 0.93421053 | M16: =_xlfn.IFS(L16<80%,"A",L16<=95%,"B",L16>95%,"C") -> B
B17: lux3 | C17: ='Юнит 26.01-01.02'!AE19 -> 0 | D17: =C17/C$26 -> 0 | E17: =D17+E16 -> 0.97847997 | F17: =IF(AND(E17<=0),"C",IF(E17<=0.8,"A",IF(E17<=0.95,"B","C"))) -> C | G17: =VLOOKUP(B$4:B$25,I$4:M$25,5,0) -> B | I17: MR Р1886 черн глянец | J17: ='Юнит 26.01-01.02'!R15 -> 0 | K17: =J17/J$26 -> 0 | L17: =K17+L16 -> 0.93421053 | M17: =_xlfn.IFS(L17<80%,"A",L17<=95%,"B",L17>95%,"C") -> B
B18: lux4 | C18: ='Юнит 26.01-01.02'!AE20 -> 0 | D18: =C18/C$26 -> 0 | E18: =D18+E17 -> 0.97847997 | F18: =IF(AND(E18<=0),"C",IF(E18<=0.8,"A",IF(E18<=0.95,"B","C"))) -> C | G18: =VLOOKUP(B$4:B$25,I$4:M$25,5,0) -> B | I18: MR Р1886 корич | J18: ='Юнит 26.01-01.02'!R16 -> 0 | K18: =J18/J$26 -> 0 | L18: =K18+L17 -> 0.93421053 | M18: =_xlfn.IFS(L18<80%,"A",L18<=95%,"B",L18>95%,"C") -> B
B19: lux5 | C19: ='Юнит 26.01-01.02'!AE21 -> 0 | D19: =C19/C$26 -> 0 | E19: =D19+E18 -> 0.97847997 | F19: =IF(AND(E19<=0),"C",IF(E19<=0.8,"A",IF(E19<=0.95,"B","C"))) -> C | G19: =VLOOKUP(B$4:B$25,I$4:M$25,5,0) -> B | I19: lux1 | J19: ='Юнит 26.01-01.02'!R17 -> 0 | K19: =J19/J$26 -> 0 | L19: =K19+L18 -> 0.93421053 | M19: =_xlfn.IFS(L19<80%,"A",L19<=95%,"B",L19>95%,"C") -> B
B20: lux6 | C20: ='Юнит 26.01-01.02'!AE22 -> 0 | D20: =C20/C$26 -> 0 | E20: =D20+E19 -> 0.97847997 | F20: =IF(AND(E20<=0),"C",IF(E20<=0.8,"A",IF(E20<=0.95,"B","C"))) -> C | G20: =VLOOKUP(B$4:B$25,I$4:M$25,5,0) -> B | I20: lux3 | J20: ='Юнит 26.01-01.02'!R19 -> 0 | K20: =J20/J$26 -> 0 | L20: =K20+L19 -> 0.93421053 | M20: =_xlfn.IFS(L20<80%,"A",L20<=95%,"B",L20>95%,"C") -> B
B21: lux7 | C21: ='Юнит 26.01-01.02'!AE23 -> 0 | D21: =C21/C$26 -> 0 | E21: =D21+E20 -> 0.97847997 | F21: =IF(AND(E21<=0),"C",IF(E21<=0.8,"A",IF(E21<=0.95,"B","C"))) -> C | G21: =VLOOKUP(B$4:B$25,I$4:M$25,5,0) -> B | I21: lux4 | J21: ='Юнит 26.01-01.02'!R20 -> 0 | K21: =J21/J$26 -> 0 | L21: =K21+L20 -> 0.93421053 | M21: =_xlfn.IFS(L21<80%,"A",L21<=95%,"B",L21>95%,"C") -> B
B22: lux8 | C22: ='Юнит 26.01-01.02'!AE24 -> 0 | D22: =C22/C$26 -> 0 | E22: =D22+E21 -> 0.97847997 | F22: =IF(AND(E22<=0),"C",IF(E22<=0.8,"A",IF(E22<=0.95,"B","C"))) -> C | G22: =VLOOKUP(B$4:B$25,I$4:M$25,5,0) -> B | I22: lux5 | J22: ='Юнит 26.01-01.02'!R21 -> 0 | K22: =J22/J$26 -> 0 | L22: =K22+L21 -> 0.93421053 | M22: =_xlfn.IFS(L22<80%,"A",L22<=95%,"B",L22>95%,"C") -> B
B23: MR Р1886 корич | C23: ='Юнит 26.01-01.02'!AE16 -> -93.54 | D23: =C23/C$26 -> -0.0042156734 | E23: =D23+E22 -> 0.97426429 | F23: =IF(AND(E23<=0),"C",IF(E23<=0.8,"A",IF(E23<=0.95,"B","C"))) -> C | G23: =VLOOKUP(B$4:B$25,I$4:M$25,5,0) -> B | I23: lux6 | J23: ='Юнит 26.01-01.02'!R22 -> 0 | K23: =J23/J$26 -> 0 | L23: =K23+L22 -> 0.93421053 | M23: =_xlfn.IFS(L23<80%,"A",L23<=95%,"B",L23>95%,"C") -> B
B24: qs синие | C24: ='Юнит 26.01-01.02'!AE5 -> -141.32 | D24: =C24/C$26 -> -0.0063690289 | E24: =D24+E23 -> 0.96789526 | F24: =IF(AND(E24<=0),"C",IF(E24<=0.8,"A",IF(E24<=0.95,"B","C"))) -> C | G24: =VLOOKUP(B$4:B$25,I$4:M$25,5,0) -> B | I24: lux7 | J24: ='Юнит 26.01-01.02'!R23 -> 0 | K24: =J24/J$26 -> 0 | L24: =K24+L23 -> 0.93421053 | M24: =_xlfn.IFS(L24<80%,"A",L24<=95%,"B",L24>95%,"C") -> B
B25: MR Р1886 черн глянец | C25: ='Юнит 26.01-01.02'!AE15 -> -700.51 | D25: =C25/C$26 -> -0.031570679 | E25: =D25+E24 -> 0.93632458 | F25: =IF(AND(E25<=0),"C",IF(E25<=0.8,"A",IF(E25<=0.95,"B","C"))) -> B | G25: =VLOOKUP(B$4:B$25,I$4:M$25,5,0) -> B | I25: lux8 | J25: ='Юнит 26.01-01.02'!R24 -> 0 | K25: =J25/J$26 -> 0 | L25: =K25+L24 -> 0.93421053 | M25: =_xlfn.IFS(L25<80%,"A",L25<=95%,"B",L25>95%,"C") -> B
C26: =SUM(C4:C25) -> 22188.626 | D26: =SUM(D4:D25) -> 1 | J26: =SUM(J4:J25) -> 76 | K26: =SUM(K4:K25) -> 1
B28: ТУНИКИ
C29: Прибыль | D29: % прибыль | E29: Доля | F29: ABC прибыль | G29: ABC кол-во | J29: Кол-во | K29: % кол-во | L29: Доля | M29: ABC кол-во
B30: tunika15 кимоно песочная | C30: ='Юнит 26.01-01.02'!AE45 -> 7813.19 | D30: =C30/C$50 -> 0.70841512 | E30: =D30 -> 0.70841512 | F30: =IF(AND(E30<=0),"C",IF(E30<=0.8,"A",IF(E30<=0.95,"B","C"))) -> A | G30: =VLOOKUP(B$30:B$50,I$30:M$50,5,0) -> B | I30: tunika15 кимоно бирюза | J30: ='Юнит 26.01-01.02'!R44 -> 9 | K30: =J30/J$50 -> 0.42857143 | L30: =K30 -> 0.42857143 | M30: =_xlfn.IFS(L30<80%,"A",L30<=95%,"B",L30>95%,"C") -> A
B31: tunika15 кимоно бирюза | C31: ='Юнит 26.01-01.02'!AE44 -> 4264.5832 | D31: =C31/C$50 -> 0.38666604 | E31: =D31+E30 -> 1.0950812 | F31: =IF(AND(E31<=0),"C",IF(E31<=0.8,"A",IF(E31<=0.95,"B","C"))) -> C | G31: =VLOOKUP(B$30:B$50,I$30:M$50,5,0) -> A | I31: tunika15 кимоно песочная | J31: ='Юнит 26.01-01.02'!R45 -> 8 | K31: =J31/J$50 -> 0.38095238 | L31: =K31+L30 -> 0.80952381 | M31: =_xlfn.IFS(L31<80%,"A",L31<=95%,"B",L31>95%,"C") -> B
B32: tunika08 черная | C32: ='Юнит 26.01-01.02'!AE35 -> 2359.18 | D32: =C32/C$50 -> 0.21390479 | E32: =D32+E31 -> 1.3089859 | F32: =IF(AND(E32<=0),"C",IF(E32<=0.8,"A",IF(E32<=0.95,"B","C"))) -> C | G32: =VLOOKUP(B$30:B$50,I$30:M$50,5,0) -> B | I32: tunika08 черная | J32: ='Юнит 26.01-01.02'!R35 -> 2 | K32: =J32/J$50 -> 0.095238095 | L32: =K32+L31 -> 0.9047619 | M32: =_xlfn.IFS(L32<80%,"A",L32<=95%,"B",L32>95%,"C") -> B
B33: tunika09 кимоно | C33: ='Юнит 26.01-01.02'!AE37 -> 1447.09 | D33: =C33/C$50 -> 0.13120639 | E33: =D33+E32 -> 1.4401923 | F33: =IF(AND(E33<=0),"C",IF(E33<=0.8,"A",IF(E33<=0.95,"B","C"))) -> C | G33: =VLOOKUP(B$30:B$50,I$30:M$50,5,0) -> C | I33: tunika09 кимоно | J33: ='Юнит 26.01-01.02'!R37 -> 1 | K33: =J33/J$50 -> 0.047619048 | L33: =K33+L32 -> 0.95238095 | M33: =_xlfn.IFS(L33<80%,"A",L33<=95%,"B",L33>95%,"C") -> C
B34: tunika06 белая | C34: ='Юнит 26.01-01.02'!AE31 -> 0 | D34: =C34/C$50 -> 0 | E34: =D34+E33 -> 1.4401923 | F34: =IF(AND(E34<=0),"C",IF(E34<=0.8,"A",IF(E34<=0.95,"B","C"))) -> C | G34: =VLOOKUP(B$30:B$50,I$30:M$50,5,0) -> C | I34: tunika16 сетка белая | J34: ='Юнит 26.01-01.02'!R46 -> 1 | K34: =J34/J$50 -> 0.047619048 | L34: =K34+L33 -> 1 | M34: =_xlfn.IFS(L34<80%,"A",L34<=95%,"B",L34>95%,"C") -> C
B35: tunika06 черная | C35: ='Юнит 26.01-01.02'!AE32 -> 0 | D35: =C35/C$50 -> 0 | E35: =D35+E34 -> 1.4401923 | F35: =IF(AND(E35<=0),"C",IF(E35<=0.8,"A",IF(E35<=0.95,"B","C"))) -> C | G35: =VLOOKUP(B$30:B$50,I$30:M$50,5,0) -> C | I35: tunika02 оливковая с руч вышивкой | J35: ='Юнит 26.01-01.02'!R28 -> 0 | K35: =J35/J$50 -> 0 | L35: =K35+L34 -> 1 | M35: =_xlfn.IFS(L35<80%,"A",L35<=95%,"B",L35>95%,"C") -> C
B36: tunika07 кружево | C36: ='Юнит 26.01-01.02'!AE33 -> 0 | D36: =C36/C$50 -> 0 | E36: =D36+E35 -> 1.4401923 | F36: =IF(AND(E36<=0),"C",IF(E36<=0.8,"A",IF(E36<=0.95,"B","C"))) -> C | G36: =VLOOKUP(B$30:B$50,I$30:M$50,5,0) -> C | I36: tunika03 черная распашная | J36: ='Юнит 26.01-01.02'!R29 -> 0 | K36: =J36/J$50 -> 0 | L36: =K36+L35 -> 1 | M36: =_xlfn.IFS(L36<80%,"A",L36<=95%,"B",L36>95%,"C") -> C
B37: tunika13 халат черная | C37: ='Юнит 26.01-01.02'!AE41 -> 0 | D37: =C37/C$50 -> 0 | E37: =D37+E36 -> 1.4401923 | F37: =IF(AND(E37<=0),"C",IF(E37<=0.8,"A",IF(E37<=0.95,"B","C"))) -> C | G37: =VLOOKUP(B$30:B$50,I$30:M$50,5,0) -> C | I37: tunika05 белая распашная | J37: ='Юнит 26.01-01.02'!R30 -> 0 | K37: =J37/J$50 -> 0 | L37: =K37+L36 -> 1 | M37: =_xlfn.IFS(L37<80%,"A",L37<=95%,"B",L37>95%,"C") -> C
B38: tunika14 халат с разрезами белая | C38: ='Юнит 26.01-01.02'!AE42 -> 0 | D38: =C38/C$50 -> 0 | E38: =D38+E37 -> 1.4401923 | F38: =IF(AND(E38<=0),"C",IF(E38<=0.8,"A",IF(E38<=0.95,"B","C"))) -> C | G38: =VLOOKUP(B$30:B$50,I$30:M$50,5,0) -> C | I38: tunika06 белая | J38: ='Юнит 26.01-01.02'!R31 -> 0 | K38: =J38/J$50 -> 0 | L38: =K38+L37 -> 1 | M38: =_xlfn.IFS(L38<80%,"A",L38<=95%,"B",L38>95%,"C") -> C
B39: tunika16 сетка черная | C39: ='Юнит 26.01-01.02'!AE47 -> 0 | D39: =C39/C$50 -> 0 | E39: =D39+E38 -> 1.4401923 | F39: =IF(AND(E39<=0),"C",IF(E39<=0.8,"A",IF(E39<=0.95,"B","C"))) -> C | G39: =VLOOKUP(B$30:B$50,I$30:M$50,5,0) -> C | I39: tunika06 черная | J39: ='Юнит 26.01-01.02'!R32 -> 0 | K39: =J39/J$50 -> 0 | L39: =K39+L38 -> 1 | M39: =_xlfn.IFS(L39<80%,"A",L39<=95%,"B",L39>95%,"C") -> C
B40: tunika03 черная распашная | C40: ='Юнит 26.01-01.02'!AE29 -> -113.88 | D40: =C40/C$50 -> -0.0103254 | E40: =D40+E39 -> 1.4298669 | F40: =IF(AND(E40<=0),"C",IF(E40<=0.8,"A",IF(E40<=0.95,"B","C"))) -> C | G40: =VLOOKUP(B$30:B$50,I$30:M$50,5,0) -> C | I40: tunika07 кружево | J40: ='Юнит 26.01-01.02'!R33 -> 0 | K40: =J40/J$50 -> 0 | L40: =K40+L39 -> 1 | M40: =_xlfn.IFS(L40<80%,"A",L40<=95%,"B",L40>95%,"C") -> C
B41: tunika05 белая распашная | C41: ='Юнит 26.01-01.02'!AE30 -> -113.88 | D41: =C41/C$50 -> -0.0103254 | E41: =D41+E40 -> 1.4195415 | F41: =IF(AND(E41<=0),"C",IF(E41<=0.8,"A",IF(E41<=0.95,"B","C"))) -> C | G41: =VLOOKUP(B$30:B$50,I$30:M$50,5,0) -> C | I41: tunika08 белая | J41: ='Юнит 26.01-01.02'!R34 -> 0 | K41: =J41/J$50 -> 0 | L41: =K41+L40 -> 1 | M41: =_xlfn.IFS(L41<80%,"A",L41<=95%,"B",L41>95%,"C") -> C
B42: tunika08 белая | C42: ='Юнит 26.01-01.02'!AE34 -> -113.88 | D42: =C42/C$50 -> -0.0103254 | E42: =D42+E41 -> 1.4092161 | F42: =IF(AND(E42<=0),"C",IF(E42<=0.8,"A",IF(E42<=0.95,"B","C"))) -> C | G42: =VLOOKUP(B$30:B$50,I$30:M$50,5,0) -> C | I42: tunika08 зеленая | J42: ='Юнит 26.01-01.02'!R36 -> 0 | K42: =J42/J$50 -> 0 | L42: =K42+L41 -> 1 | M42: =_xlfn.IFS(L42<80%,"A",L42<=95%,"B",L42>95%,"C") -> C
B43: tunika08 зеленая | C43: ='Юнит 26.01-01.02'!AE36 -> -113.88 | D43: =C43/C$50 -> -0.0103254 | E43: =D43+E42 -> 1.3988907 | F43: =IF(AND(E43<=0),"C",IF(E43<=0.8,"A",IF(E43<=0.95,"B","C"))) -> C | G43: =VLOOKUP(B$30:B$50,I$30:M$50,5,0) -> C | I43: tunika10 кимоно ч/б | J43: ='Юнит 26.01-01.02'!R38 -> 0 | K43: =J43/J$50 -> 0 | L43: =K43+L42 -> 1 | M43: =_xlfn.IFS(L43<80%,"A",L43<=95%,"B",L43>95%,"C") -> C
B44: tunika11 халат зеленая | C44: ='Юнит 26.01-01.02'!AE39 -> -113.88 | D44: =C44/C$50 -> -0.0103254 | E44: =D44+E43 -> 1.3885653 | F44: =IF(AND(E44<=0),"C",IF(E44<=0.8,"A",IF(E44<=0.95,"B","C"))) -> C | G44: =VLOOKUP(B$30:B$50,I$30:M$50,5,0) -> C | I44: tunika11 халат зеленая | J44: ='Юнит 26.01-01.02'!R39 -> 0 | K44: =J44/J$50 -> 0 | L44: =K44+L43 -> 1 | M44: =_xlfn.IFS(L44<80%,"A",L44<=95%,"B",L44>95%,"C") -> C
B45: tunika12 халат белая | C45: ='Юнит 26.01-01.02'!AE40 -> -113.88 | D45: =C45/C$50 -> -0.0103254 | E45: =D45+E44 -> 1.3782399 | F45: =IF(AND(E45<=0),"C",IF(E45<=0.8,"A",IF(E45<=0.95,"B","C"))) -> C | G45: =VLOOKUP(B$30:B$50,I$30:M$50,5,0) -> C | I45: tunika12 халат белая | J45: ='Юнит 26.01-01.02'!R40 -> 0 | K45: =J45/J$50 -> 0 | L45: =K45+L44 -> 1 | M45: =_xlfn.IFS(L45<80%,"A",L45<=95%,"B",L45>95%,"C") -> C
B46: tunika14 халат с разрезами черный | C46: ='Юнит 26.01-01.02'!AE43 -> -227.76 | D46: =C46/C$50 -> -0.0206508 | E46: =D46+E45 -> 1.3575891 | F46: =IF(AND(E46<=0),"C",IF(E46<=0.8,"A",IF(E46<=0.95,"B","C"))) -> C | G46: =VLOOKUP(B$30:B$50,I$30:M$50,5,0) -> C | I46: tunika13 халат черная | J46: ='Юнит 26.01-01.02'!R41 -> 0 | K46: =J46/J$50 -> 0 | L46: =K46+L45 -> 1 | M46: =_xlfn.IFS(L46<80%,"A",L46<=95%,"B",L46>95%,"C") -> C
B47: tunika10 кимоно ч/б | C47: ='Юнит 26.01-01.02'!AE38 -> -284.7 | D47: =C47/C$50 -> -0.0258135 | E47: =D47+E46 -> 1.3317756 | F47: =IF(AND(E47<=0),"C",IF(E47<=0.8,"A",IF(E47<=0.95,"B","C"))) -> C | G47: =VLOOKUP(B$30:B$50,I$30:M$50,5,0) -> C | I47: tunika14 халат с разрезами белая | J47: ='Юнит 26.01-01.02'!R42 -> 0 | K47: =J47/J$50 -> 0 | L47: =K47+L46 -> 1 | M47: =_xlfn.IFS(L47<80%,"A",L47<=95%,"B",L47>95%,"C") -> C
B48: tunika02 оливковая с руч вышивкой | C48: ='Юнит 26.01-01.02'!AE28 -> -980.66758 | D48: =C48/C$50 -> -0.088916273 | E48: =D48+E47 -> 1.2428594 | F48: =IF(AND(E48<=0),"C",IF(E48<=0.8,"A",IF(E48<=0.95,"B","C"))) -> C | G48: =VLOOKUP(B$30:B$50,I$30:M$50,5,0) -> C | I48: tunika14 халат с разрезами черный | J48: ='Юнит 26.01-01.02'!R43 -> 0 | K48: =J48/J$50 -> 0 | L48: =K48+L47 -> 1 | M48: =_xlfn.IFS(L48<80%,"A",L48<=95%,"B",L48>95%,"C") -> C
B49: tunika16 сетка белая | C49: ='Юнит 26.01-01.02'!AE46 -> -2678.5232 | D49: =C49/C$50 -> -0.24285936 | E49: =D49+E48 -> 1 | F49: =IF(AND(E49<=0),"C",IF(E49<=0.8,"A",IF(E49<=0.95,"B","C"))) -> C | G49: =VLOOKUP(B$30:B$50,I$30:M$50,5,0) -> C | I49: tunika16 сетка черная | J49: ='Юнит 26.01-01.02'!R47 -> 0 | K49: =J49/J$50 -> 0 | L49: =K49+L48 -> 1 | M49: =_xlfn.IFS(L49<80%,"A",L49<=95%,"B",L49>95%,"C") -> C
C50: =SUM(C30:C49) -> 11029.112 | D50: =SUM(D30:D49) -> 1 | J50: =SUM(J30:J49) -> 21 | K50: =SUM(K30:K49) -> 1

Sheet АВС 19-25.01
B2: ОЧКИ
C3: Прибыль | D3: % прибыль | E3: Доля | F3: ABC прибыль | G3: ABC кол-во | J3: Кол-во | K3: % кол-во | L3: Доля | M3: ABC кол-во
B4: черные с железкой классика | C4: ='Юнит 19-25.01'!AE3 -> 5864.4518 | D4: =C4/C$26 -> 0.58621262 | E4: =D4 -> 0.58621262 | F4: =IF(AND(E4<=0),"C",IF(E4<=0.8,"A",IF(E4<=0.95,"B","C"))) -> A | G4: =VLOOKUP(B$4:B$25,I$4:M$25,5,0) -> A | I4: черные с железкой классика | J4: ='Юнит 19-25.01'!R3 -> 38 | K4: =J4/J$26 -> 0.6031746 | L4: =K4 -> 0.6031746 | M4: =_xlfn.IFS(L4<80%,"A",L4<=95%,"B",L4>95%,"C") -> A
B5: qs коричневые | C5: ='Юнит 19-25.01'!AE7 -> 2637.98 | D5: =C5/C$26 -> 0.26369339 | E5: =D5+E4 -> 0.84990601 | F5: =IF(AND(E5<=0),"C",IF(E5<=0.8,"A",IF(E5<=0.95,"B","C"))) -> B | G5: =VLOOKUP(B$4:B$25,I$4:M$25,5,0) -> A | I5: qs коричневые | J5: ='Юнит 19-25.01'!R7 -> 6 | K5: =J5/J$26 -> 0.095238095 | L5: =K5+L4 -> 0.6984127 | M5: =_xlfn.IFS(L5<80%,"A",L5<=95%,"B",L5>95%,"C") -> A
B6: lux3 | C6: ='Юнит 19-25.01'!AE19 -> 914.65 | D6: =C6/C$26 -> 0.091428728 | E6: =D6+E5 -> 0.94133474 | F6: =IF(AND(E6<=0),"C",IF(E6<=0.8,"A",IF(E6<=0.95,"B","C"))) -> B | G6: =VLOOKUP(B$4:B$25,I$4:M$25,5,0) -> C | I6: qs черные | J6: ='Юнит 19-25.01'!R4 -> 5 | K6: =J6/J$26 -> 0.079365079 | L6: =K6+L5 -> 0.77777778 | M6: =_xlfn.IFS(L6<80%,"A",L6<=95%,"B",L6>95%,"C") -> A
B7: th желтый Сул | C7: ='Юнит 19-25.01'!AE8 -> 606.7 | D7: =C7/C$26 -> 0.060645941 | E7: =D7+E6 -> 1.0019807 | F7: =IF(AND(E7<=0),"C",IF(E7<=0.8,"A",IF(E7<=0.95,"B","C"))) -> C | G7: =VLOOKUP(B$4:B$25,I$4:M$25,5,0) -> C | I7: flip желтые Сул | J7: ='Юнит 19-25.01'!R9 -> 5 | K7: =J7/J$26 -> 0.079365079 | L7: =K7+L6 -> 0.85714286 | M7: =_xlfn.IFS(L7<80%,"A",L7<=95%,"B",L7>95%,"C") -> B
B8: MR Р1874 корич | C8: ='Юнит 19-25.01'!AE14 -> 490.89 | D8: =C8/C$26 -> 0.049069533 | E8: =D8+E7 -> 1.0510502 | F8: =IF(AND(E8<=0),"C",IF(E8<=0.8,"A",IF(E8<=0.95,"B","C"))) -> C | G8: =VLOOKUP(B$4:B$25,I$4:M$25,5,0) -> B | I8: MR Р1874 черн | J8: ='Юнит 19-25.01'!R13 -> 3 | K8: =J8/J$26 -> 0.047619048 | L8: =K8+L7 -> 0.9047619 | M8: =_xlfn.IFS(L8<80%,"A",L8<=95%,"B",L8>95%,"C") -> B
B9: MR 1819 корич | C9: ='Юнит 19-25.01'!AE12 -> 322.02 | D9: =C9/C$26 -> 0.03218923 | E9: =D9+E8 -> 1.0832394 | F9: =IF(AND(E9<=0),"C",IF(E9<=0.8,"A",IF(E9<=0.95,"B","C"))) -> C | G9: =VLOOKUP(B$4:B$25,I$4:M$25,5,0) -> B | I9: qs желтые | J9: ='Юнит 19-25.01'!R6 -> 2 | K9: =J9/J$26 -> 0.031746032 | L9: =K9+L8 -> 0.93650794 | M9: =_xlfn.IFS(L9<80%,"A",L9<=95%,"B",L9>95%,"C") -> B
B10: MR Р1874 черн | C10: ='Юнит 19-25.01'!AE13 -> 420.19 | D10: =C10/C$26 -> 0.042002337 | E10: =D10+E9 -> 1.1252418 | F10: =IF(AND(E10<=0),"C",IF(E10<=0.8,"A",IF(E10<=0.95,"B","C"))) -> C | G10: =VLOOKUP(B$4:B$25,I$4:M$25,5,0) -> B | I10: th желтый Сул | J10: ='Юнит 19-25.01'!R8 -> 1 | K10: =J10/J$26 -> 0.015873016 | L10: =K10+L9 -> 0.95238095 | M10: =_xlfn.IFS(L10<80%,"A",L10<=95%,"B",L10>95%,"C") -> C
B11: qs черные | C11: ='Юнит 19-25.01'!AE4 -> 591.94117 | D11: =C11/C$26 -> 0.059170643 | E11: =D11+E8 -> 1.1102209 | F11: =IF(AND(E11<=0),"C",IF(E11<=0.8,"A",IF(E11<=0.95,"B","C"))) -> C | G11: =VLOOKUP(B$4:B$25,I$4:M$25,5,0) -> A | I11: MR 1819 корич | J11: ='Юнит 19-25.01'!R12 -> 1 | K11: =J11/J$26 -> 0.015873016 | L11: =K11+L8 -> 0.92063492 | M11: =_xlfn.IFS(L11<80%,"A",L11<=95%,"B",L11>95%,"C") -> B
B12: qs синие | C12: ='Юнит 19-25.01'!AE5 -> 0 | D12: =C12/C$26 -> 0 | E12: =D12+E11 -> 1.1102209 | F12: =IF(AND(E12<=0),"C",IF(E12<=0.8,"A",IF(E12<=0.95,"B","C"))) -> C | G12: =VLOOKUP(B$4:B$25,I$4:M$25,5,0) -> C | I12: MR Р1874 корич | J12: ='Юнит 19-25.01'!R14 -> 1 | K12: =J12/J$26 -> 0.015873016 | L12: =K12+L11 -> 0.93650794 | M12: =_xlfn.IFS(L12<80%,"A",L12<=95%,"B",L12>95%,"C") -> B
B13: lux1 | C13: ='Юнит 19-25.01'!AE17 -> 0 | D13: =C13/C$26 -> 0 | E13: =D13+E12 -> 1.1102209 | F13: =IF(AND(E13<=0),"C",IF(E13<=0.8,"A",IF(E13<=0.95,"B","C"))) -> C | G13: =VLOOKUP(B$4:B$25,I$4:M$25,5,0) -> C | I13: lux3 | J13: ='Юнит 19-25.01'!R19 -> 1 | K13: =J13/J$26 -> 0.015873016 | L13: =K13+L12 -> 0.95238095 | M13: =_xlfn.IFS(L13<80%,"A",L13<=95%,"B",L13>95%,"C") -> C | P13: A | Q13: 0.8
B14: lux2 | C14: ='Юнит 19-25.01'!AE18 -> 0 | D14: =C14/C$26 -> 0 | E14: =D14+E13 -> 1.1102209 | F14: =IF(AND(E14<=0),"C",IF(E14<=0.8,"A",IF(E14<=0.95,"B","C"))) -> C | G14: =VLOOKUP(B$4:B$25,I$4:M$25,5,0) -> C | I14: qs синие | J14: ='Юнит 19-25.01'!R5 -> 0 | K14: =J14/J$26 -> 0 | L14: =K14+L13 -> 0.95238095 | M14: =_xlfn.IFS(L14<80%,"A",L14<=95%,"B",L14>95%,"C") -> C | P14: B | Q14: 0.15
B15: lux4 | C15: ='Юнит 19-25.01'!AE20 -> 0 | D15: =C15/C$26 -> 0 | E15: =D15+E14 -> 1.1102209 | F15: =IF(AND(E15<=0),"C",IF(E15<=0.8,"A",IF(E15<=0.95,"B","C"))) -> C | G15: =VLOOKUP(B$4:B$25,I$4:M$25,5,0) -> C | I15: MR8854 C2 | J15: ='Юнит 19-25.01'!R10 -> 0 | K15: =J15/J$26 -> 0 | L15: =K15+L14 -> 0.95238095 | M15: =_xlfn.IFS(L15<80%,"A",L15<=95%,"B",L15>95%,"C") -> C | P15: C | Q15: 0.05
B16: lux5 | C16: ='Юнит 19-25.01'!AE21 -> 0 | D16: =C16/C$26 -> 0 | E16: =D16+E15 -> 1.1102209 | F16: =IF(AND(E16<=0),"C",IF(E16<=0.8,"A",IF(E16<=0.95,"B","C"))) -> C | G16: =VLOOKUP(B$4:B$25,I$4:M$25,5,0) -> C | I16: MR 1819 черн | J16: ='Юнит 19-25.01'!R11 -> 0 | K16: =J16/J$26 -> 0 | L16: =K16+L15 -> 0.95238095 | M16: =_xlfn.IFS(L16<80%,"A",L16<=95%,"B",L16>95%,"C") -> C
B17: lux6 | C17: ='Юнит 19-25.01'!AE22 -> 0 | D17: =C17/C$26 -> 0 | E17: =D17+E16 -> 1.1102209 | F17: =IF(AND(E17<=0),"C",IF(E17<=0.8,"A",IF(E17<=0.95,"B","C"))) -> C | G17: =VLOOKUP(B$4:B$25,I$4:M$25,5,0) -> C | I17: MR Р1886 черн глянец | J17: ='Юнит 19-25.01'!R15 -> 0 | K17: =J17/J$26 -> 0 | L17: =K17+L16 -> 0.95238095 | M17: =_xlfn.IFS(L17<80%,"A",L17<=95%,"B",L17>95%,"C") -> C
B18: lux7 | C18: ='Юнит 19-25.01'!AE23 -> 0 | D18: =C18/C$26 -> 0 | E18: =D18+E17 -> 1.1102209 | F18: =IF(AND(E18<=0),"C",IF(E18<=0.8,"A",IF(E18<=0.95,"B","C"))) -> C | G18: =VLOOKUP(B$4:B$25,I$4:M$25,5,0) -> C | I18: MR Р1886 корич | J18: ='Юнит 19-25.01'!R16 -> 0 | K18: =J18/J$26 -> 0 | L18: =K18+L17 -> 0.95238095 | M18: =_xlfn.IFS(L18<80%,"A",L18<=95%,"B",L18>95%,"C") -> C
B19: lux8 | C19: ='Юнит 19-25.01'!AE24 -> 0 | D19: =C19/C$26 -> 0 | E19: =D19+E18 -> 1.1102209 | F19: =IF(AND(E19<=0),"C",IF(E19<=0.8,"A",IF(E19<=0.95,"B","C"))) -> C | G19: =VLOOKUP(B$4:B$25,I$4:M$25,5,0) -> C | I19: lux1 | J19: ='Юнит 19-25.01'!R17 -> 0 | K19: =J19/J$26 -> 0 | L19: =K19+L18 -> 0.95238095 | M19: =_xlfn.IFS(L19<80%,"A",L19<=95%,"B",L19>95%,"C") -> C
B20: MR8854 C2 | C20: ='Юнит 19-25.01'!AE10 -> -93.54 | D20: =C20/C$26 -> -0.0093502906 | E20: =D20+E19 -> 1.1008706 | F20: =IF(AND(E20<=0),"C",IF(E20<=0.8,"A",IF(E20<=0.95,"B","C"))) -> C | G20: =VLOOKUP(B$4:B$25,I$4:M$25,5,0) -> C | I20: lux2 | J20: ='Юнит 19-25.01'!R18 -> 0 | K20: =J20/J$26 -> 0 | L20: =K20+L19 -> 0.95238095 | M20: =_xlfn.IFS(L20<80%,"A",L20<=95%,"B",L20>95%,"C") -> C
B21: MR 1819 черн | C21: ='Юнит 19-25.01'!AE11 -> -93.54 | D21: =C21/C$26 -> -0.0093502906 | E21: =D21+E20 -> 1.0915203 | F21: =IF(AND(E21<=0),"C",IF(E21<=0.8,"A",IF(E21<=0.95,"B","C"))) -> C | G21: =VLOOKUP(B$4:B$25,I$4:M$25,5,0) -> C | I21: lux4 | J21: ='Юнит 19-25.01'!R20 -> 0 | K21: =J21/J$26 -> 0 | L21: =K21+L20 -> 0.95238095 | M21: =_xlfn.IFS(L21<80%,"A",L21<=95%,"B",L21>95%,"C") -> C
B22: MR Р1886 черн глянец | C22: ='Юнит 19-25.01'!AE15 -> -93.54 | D22: =C22/C$26 -> -0.0093502906 | E22: =D22+E21 -> 1.08217 | F22: =IF(AND(E22<=0),"C",IF(E22<=0.8,"A",IF(E22<=0.95,"B","C"))) -> C | G22: =VLOOKUP(B$4:B$25,I$4:M$25,5,0) -> C | I22: lux5 | J22: ='Юнит 19-25.01'!R21 -> 0 | K22: =J22/J$26 -> 0 | L22: =K22+L21 -> 0.95238095 | M22: =_xlfn.IFS(L22<80%,"A",L22<=95%,"B",L22>95%,"C") -> C
B23: MR Р1886 корич | C23: ='Юнит 19-25.01'!AE16 -> -328.67 | D23: =C23/C$26 -> -0.032853966 | E23: =D23+E22 -> 1.049316 | F23: =IF(AND(E23<=0),"C",IF(E23<=0.8,"A",IF(E23<=0.95,"B","C"))) -> C | G23: =VLOOKUP(B$4:B$25,I$4:M$25,5,0) -> C | I23: lux6 | J23: ='Юнит 19-25.01'!R22 -> 0 | K23: =J23/J$26 -> 0 | L23: =K23+L22 -> 0.95238095 | M23: =_xlfn.IFS(L23<80%,"A",L23<=95%,"B",L23>95%,"C") -> C
B24: flip желтые Сул | C24: ='Юнит 19-25.01'!AE9 -> 72.94261 | D24: =C24/C$26 -> 0.0072913684 | E24: =D24+E23 -> 1.0566074 | F24: =IF(AND(E24<=0),"C",IF(E24<=0.8,"A",IF(E24<=0.95,"B","C"))) -> C | G24: =VLOOKUP(B$4:B$25,I$4:M$25,5,0) -> B | I24: lux7 | J24: ='Юнит 19-25.01'!R23 -> 0 | K24: =J24/J$26 -> 0 | L24: =K24+L23 -> 0.95238095 | M24: =_xlfn.IFS(L24<80%,"A",L24<=95%,"B",L24>95%,"C") -> C
B25: qs желтые | C25: ='Юнит 19-25.01'!AE6 -> -1308.5084 | D25: =C25/C$26 -> -0.13079895 | E25: =D25+E24 -> 0.92580843 | F25: =IF(AND(E25<=0),"C",IF(E25<=0.8,"A",IF(E25<=0.95,"B","C"))) -> B | G25: =VLOOKUP(B$4:B$25,I$4:M$25,5,0) -> B | I25: lux8 | J25: ='Юнит 19-25.01'!R24 -> 0 | K25: =J25/J$26 -> 0 | L25: =K25+L24 -> 0.95238095 | M25: =_xlfn.IFS(L25<80%,"A",L25<=95%,"B",L25>95%,"C") -> C
C26: =SUM(C4:C25) -> 10003.967 | D26: =SUM(D4:D25) -> 1 | J26: =SUM(J4:J25) -> 63 | K26: =SUM(K4:K25) -> 1
B28: ТУНИКИ
C29: Прибыль | D29: % прибыль | E29: Доля | F29: ABC прибыль | G29: ABC кол-во | J29: Кол-во | K29: % кол-во | L29: Доля | M29: ABC кол-во
B30: tunika15 кимоно песочная | C30: ='Юнит 19-25.01'!AE45 -> 6439.7034 | D30: =C30/C$50 -> 1.6022372 | E30: =D30 -> 1.6022372 | F30: =IF(AND(E30<=0),"C",IF(E30<=0.8,"A",IF(E30<=0.95,"B","C"))) -> C | G30: =VLOOKUP(B$30:B$50,I$30:M$50,5,0) -> A | I30: tunika15 кимоно песочная | J30: ='Юнит 19-25.01'!R45 -> 8 | K30: =J30/J$50 -> 0.57142857 | L30: =K30 -> 0.57142857 | M30: =_xlfn.IFS(L30<80%,"A",L30<=95%,"B",L30>95%,"C") -> A
B31: tunika09 кимоно | C31: ='Юнит 19-25.01'!AE37 -> 2688.14 | D31: =C31/C$50 -> 0.6688255 | E31: =D31+E30 -> 2.2710627 | F31: =IF(AND(E31<=0),"C",IF(E31<=0.8,"A",IF(E31<=0.95,"B","C"))) -> C | G31: =VLOOKUP(B$30:B$50,I$30:M$50,5,0) -> B | I31: tunika15 кимоно бирюза | J31: ='Юнит 19-25.01'!R44 -> 3 | K31: =J31/J$50 -> 0.21428571 | L31: =K31+L30 -> 0.78571429 | M31: =_xlfn.IFS(L31<80%,"A",L31<=95%,"B",L31>95%,"C") -> A
B32: tunika06 белая | C32: ='Юнит 19-25.01'!AE31 -> 1234.21 | D32: =C32/C$50 -> 0.30707892 | E32: =D32+E31 -> 2.5781416 | F32: =IF(AND(E32<=0),"C",IF(E32<=0.8,"A",IF(E32<=0.95,"B","C"))) -> C | G32: =VLOOKUP(B$30:B$50,I$30:M$50,5,0) -> C | I32: tunika09 кимоно | J32: ='Юнит 19-25.01'!R37 -> 2 | K32: =J32/J$50 -> 0.14285714 | L32: =K32+L31 -> 0.92857143 | M32: =_xlfn.IFS(L32<80%,"A",L32<=95%,"B",L32>95%,"C") -> B
B33: tunika07 кружево | C33: ='Юнит 19-25.01'!AE33 -> 848.44 | D33: =C33/C$50 -> 0.21109701 | E33: =D33+E32 -> 2.7892386 | F33: =IF(AND(E33<=0),"C",IF(E33<=0.8,"A",IF(E33<=0.95,"B","C"))) -> C | G33: =VLOOKUP(B$30:B$50,I$30:M$50,5,0) -> C | I33: tunika06 белая | J33: ='Юнит 19-25.01'!R31 -> 1 | K33: =J33/J$50 -> 0.071428571 | L33: =K33+L32 -> 1 | M33: =_xlfn.IFS(L33<80%,"A",L33<=95%,"B",L33>95%,"C") -> C
B34: tunika03 черная распашная | C34: ='Юнит 19-25.01'!AE29 -> 0 | D34: =C34/C$50 -> 0 | E34: =D34+E33 -> 2.7892386 | F34: =IF(AND(E34<=0),"C",IF(E34<=0.8,"A",IF(E34<=0.95,"B","C"))) -> C | G34: =VLOOKUP(B$30:B$50,I$30:M$50,5,0) -> C | I34: tunika07 кружево | J34: ='Юнит 19-25.01'!R33 -> 1 | K34: =J34/J$50 -> 0.071428571 | L34: =K34+L33 -> 1.0714286 | M34: =_xlfn.IFS(L34<80%,"A",L34<=95%,"B",L34>95%,"C") -> C
B35: tunika05 белая распашная | C35: ='Юнит 19-25.01'!AE30 -> 0 | D35: =C35/C$50 -> 0 | E35: =D35+E34 -> 2.7892386 | F35: =IF(AND(E35<=0),"C",IF(E35<=0.8,"A",IF(E35<=0.95,"B","C"))) -> C | G35: =VLOOKUP(B$30:B$50,I$30:M$50,5,0) -> C | I35: tunika02 оливковая с руч вышивкой | J35: ='Юнит 19-25.01'!R28 -> 0 | K35: =J35/J$50 -> 0 | L35: =K35+L34 -> 1.0714286 | M35: =_xlfn.IFS(L35<80%,"A",L35<=95%,"B",L35>95%,"C") -> C
B36: tunika06 черная | C36: ='Юнит 19-25.01'!AE32 -> 0 | D36: =C36/C$50 -> 0 | E36: =D36+E35 -> 2.7892386 | F36: =IF(AND(E36<=0),"C",IF(E36<=0.8,"A",IF(E36<=0.95,"B","C"))) -> C | G36: =VLOOKUP(B$30:B$50,I$30:M$50,5,0) -> C | I36: tunika03 черная распашная | J36: ='Юнит 19-25.01'!R29 -> 0 | K36: =J36/J$50 -> 0 | L36: =K36+L35 -> 1.0714286 | M36: =_xlfn.IFS(L36<80%,"A",L36<=95%,"B",L36>95%,"C") -> C
B37: tunika08 белая | C37: ='Юнит 19-25.01'!AE34 -> 0 | D37: =C37/C$50 -> 0 | E37: =D37+E36 -> 2.7892386 | F37: =IF(AND(E37<=0),"C",IF(E37<=0.8,"A",IF(E37<=0.95,"B","C"))) -> C | G37: =VLOOKUP(B$30:B$50,I$30:M$50,5,0) -> C | I37: tunika05 белая распашная | J37: ='Юнит 19-25.01'!R30 -> 0 | K37: =J37/J$50 -> 0 | L37: =K37+L36 -> 1.0714286 | M37: =_xlfn.IFS(L37<80%,"A",L37<=95%,"B",L37>95%,"C") -> C
B38: tunika08 черная | C38: ='Юнит 19-25.01'!AE35 -> 0 | D38: =C38/C$50 -> 0 | E38: =D38+E37 -> 2.7892386 | F38: =IF(AND(E38<=0),"C",IF(E38<=0.8,"A",IF(E38<=0.95,"B","C"))) -> C | G38: =VLOOKUP(B$30:B$50,I$30:M$50,5,0) -> C | I38: tunika06 черная | J38: ='Юнит 19-25.01'!R32 -> 0 | K38: =J38/J$50 -> 0 | L38: =K38+L37 -> 1.0714286 | M38: =_xlfn.IFS(L38<80%,"A",L38<=95%,"B",L38>95%,"C") -> C
B39: tunika11 халат зеленая | C39: ='Юнит 19-25.01'!AE39 -> 0 | D39: =C39/C$50 -> 0 | E39: =D39+E38 -> 2.7892386 | F39: =IF(AND(E39<=0),"C",IF(E39<=0.8,"A",IF(E39<=0.95,"B","C"))) -> C | G39: =VLOOKUP(B$30:B$50,I$30:M$50,5,0) -> C | I39: tunika08 белая | J39: ='Юнит 19-25.01'!R34 -> 0 | K39: =J39/J$50 -> 0 | L39: =K39+L38 -> 1.0714286 | M39: =_xlfn.IFS(L39<80%,"A",L39<=95%,"B",L39>95%,"C") -> C
B40: tunika12 халат белая | C40: ='Юнит 19-25.01'!AE40 -> 0 | D40: =C40/C$50 -> 0 | E40: =D40+E39 -> 2.7892386 | F40: =IF(AND(E40<=0),"C",IF(E40<=0.8,"A",IF(E40<=0.95,"B","C"))) -> C | G40: =VLOOKUP(B$30:B$50,I$30:M$50,5,0) -> C | I40: tunika08 черная | J40: ='Юнит 19-25.01'!R35 -> 0 | K40: =J40/J$50 -> 0 | L40: =K40+L39 -> 1.0714286 | M40: =_xlfn.IFS(L40<80%,"A",L40<=95%,"B",L40>95%,"C") -> C
B41: tunika13 халат черная | C41: ='Юнит 19-25.01'!AE41 -> 0 | D41: =C41/C$50 -> 0 | E41: =D41+E40 -> 2.7892386 | F41: =IF(AND(E41<=0),"C",IF(E41<=0.8,"A",IF(E41<=0.95,"B","C"))) -> C | G41: =VLOOKUP(B$30:B$50,I$30:M$50,5,0) -> C | I41: tunika08 зеленая | J41: ='Юнит 19-25.01'!R36 -> 0 | K41: =J41/J$50 -> 0 | L41: =K41+L40 -> 1.0714286 | M41: =_xlfn.IFS(L41<80%,"A",L41<=95%,"B",L41>95%,"C") -> C
B42: tunika14 халат с разрезами белая | C42: ='Юнит 19-25.01'!AE42 -> 0 | D42: =C42/C$50 -> 0 | E42: =D42+E41 -> 2.7892386 | F42: =IF(AND(E42<=0),"C",IF(E42<=0.8,"A",IF(E42<=0.95,"B","C"))) -> C | G42: =VLOOKUP(B$30:B$50,I$30:M$50,5,0) -> C | I42: tunika11 халат зеленая | J42: ='Юнит 19-25.01'!R39 -> 0 | K42: =J42/J$50 -> 0 | L42: =K42+L41 -> 1.0714286 | M42: =_xlfn.IFS(L42<80%,"A",L42<=95%,"B",L42>95%,"C") -> C
B43: tunika14 халат с разрезами черный | C43: ='Юнит 19-25.01'!AE43 -> 0 | D43: =C43/C$50 -> 0 | E43: =D43+E42 -> 2.7892386 | F43: =IF(AND(E43<=0),"C",IF(E43<=0.8,"A",IF(E43<=0.95,"B","C"))) -> C | G43: =VLOOKUP(B$30:B$50,I$30:M$50,5,0) -> C | I43: tunika12 халат белая | J43: ='Юнит 19-25.01'!R40 -> 0 | K43: =J43/J$50 -> 0 | L43: =K43+L42 -> 1.0714286 | M43: =_xlfn.IFS(L43<80%,"A",L43<=95%,"B",L43>95%,"C") -> C
B44: tunika16 сетка черная | C44: ='Юнит 19-25.01'!AE47 -> 0 | D44: =C44/C$50 -> 0 | E44: =D44+E43 -> 2.7892386 | F44: =IF(AND(E44<=0),"C",IF(E44<=0.8,"A",IF(E44<=0.95,"B","C"))) -> C | G44: =VLOOKUP(B$30:B$50,I$30:M$50,5,0) -> C | I44: tunika13 халат черная | J44: ='Юнит 19-25.01'!R41 -> 0 | K44: =J44/J$50 -> 0 | L44: =K44+L43 -> 1.0714286 | M44: =_xlfn.IFS(L44<80%,"A",L44<=95%,"B",L44>95%,"C") -> C
B45: tunika08 зеленая | C45: ='Юнит 19-25.01'!AE36 -> -113.88 | D45: =C45/C$50 -> -0.028334033 | E45: =D45+E44 -> 2.7609046 | F45: =IF(AND(E45<=0),"C",IF(E45<=0.8,"A",IF(E45<=0.95,"B","C"))) -> C | G45: =VLOOKUP(B$30:B$50,I$30:M$50,5,0) -> C | I45: tunika14 халат с разрезами белая | J45: ='Юнит 19-25.01'!R42 -> 0 | K45: =J45/J$50 -> 0 | L45: =K45+L44 -> 1.0714286 | M45: =_xlfn.IFS(L45<80%,"A",L45<=95%,"B",L45>95%,"C") -> C
B46: tunika02 оливковая с руч вышивкой | C46: ='Юнит 19-25.01'!AE28 -> -537.70695 | D46: =C46/C$50 -> -0.13378474 | E46: =D46+E45 -> 2.6271198 | F46: =IF(AND(E46<=0),"C",IF(E46<=0.8,"A",IF(E46<=0.95,"B","C"))) -> C | G46: =VLOOKUP(B$30:B$50,I$30:M$50,5,0) -> C | I46: tunika14 халат с разрезами черный | J46: ='Юнит 19-25.01'!R43 -> 0 | K46: =J46/J$50 -> 0 | L46: =K46+L45 -> 1.0714286 | M46: =_xlfn.IFS(L46<80%,"A",L46<=95%,"B",L46>95%,"C") -> C
B47: tunika16 сетка белая | C47: ='Юнит 19-25.01'!AE46 -> -810.57043 | D47: =C47/C$50 -> -0.20167483 | E47: =D47+E46 -> 2.425445 | F47: =IF(AND(E47<=0),"C",IF(E47<=0.8,"A",IF(E47<=0.95,"B","C"))) -> C | G47: =VLOOKUP(B$30:B$50,I$30:M$50,5,0) -> C | I47: tunika16 сетка белая | J47: ='Юнит 19-25.01'!R46 -> 0 | K47: =J47/J$50 -> 0 | L47: =K47+L46 -> 1.0714286 | M47: =_xlfn.IFS(L47<80%,"A",L47<=95%,"B",L47>95%,"C") -> C
B48: tunika10 кимоно ч/б | C48: ='Юнит 19-25.01'!AE38 -> -1412.64 | D48: =C48/C$50 -> -0.35147338 | E48: =D48+E47 -> 2.0739716 | F48: =IF(AND(E48<=0),"C",IF(E48<=0.8,"A",IF(E48<=0.95,"B","C"))) -> C | G48: =VLOOKUP(B$30:B$50,I$30:M$50,5,0) -> C | I48: tunika16 сетка черная | J48: ='Юнит 19-25.01'!R47 -> 0 | K48: =J48/J$50 -> 0 | L48: =K48+L47 -> 1.0714286 | M48: =_xlfn.IFS(L48<80%,"A",L48<=95%,"B",L48>95%,"C") -> C
B49: tunika15 кимоно бирюза | C49: ='Юнит 19-25.01'!AE44 -> -4316.5012 | D49: =C49/C$50 -> -1.0739716 | E49: =D49+E48 -> 1 | F49: =IF(AND(E49<=0),"C",IF(E49<=0.8,"A",IF(E49<=0.95,"B","C"))) -> C | G49: =VLOOKUP(B$30:B$50,I$30:M$50,5,0) -> A | I49: tunika10 кимоно ч/б | J49: ='Юнит 19-25.01'!R38 -> -1 | K49: =J49/J$50 -> -0.071428571 | L49: =K49+L48 -> 1 | M49: =_xlfn.IFS(L49<80%,"A",L49<=95%,"B",L49>95%,"C") -> C
C50: =SUM(C30:C49) -> 4019.1948 | D50: =SUM(D30:D49) -> 1 | J50: =SUM(J30:J49) -> 14 | K50: =SUM(K30:K49) -> 1

Sheet АВС 12-18.01
B2: ОЧКИ
C3: Прибыль | D3: % прибыль | E3: Доля | F3: ABC прибыль | G3: ABC кол-во | J3: Кол-во | K3: % кол-во | L3: Доля | M3: ABC кол-во
B4: черные с железкой классика | C4: ='Юнит 12-18.01'!AE3 -> 11137.395 | D4: =C4/C$26 -> 0.74671755 | E4: =D4 -> 0.74671755 | F4: =IF(AND(E4<=0),"C",IF(E4<=0.8,"A",IF(E4<=0.95,"B","C"))) -> A | G4: =VLOOKUP(B$4:B$25,I$4:M$25,5,0) -> A | I4: черные с железкой классика | J4: ='Юнит 12-18.01'!R3 -> 43 | K4: =J4/J$26 -> 0.76785714 | L4: =K4 -> 0.76785714 | M4: =_xlfn.IFS(L4<80%,"A",L4<=95%,"B",L4>95%,"C") -> A
B5: qs желтые | C5: ='Юнит 12-18.01'!AE6 -> 3561.2513 | D5: =C5/C$26 -> 0.23876757 | E5: =D5+E4 -> 0.98548513 | F5: =IF(AND(E5<=0),"C",IF(E5<=0.8,"A",IF(E5<=0.95,"B","C"))) -> C | G5: =VLOOKUP(B$4:B$25,I$4:M$25,5,0) -> B | I5: qs желтые | J5: ='Юнит 12-18.01'!R6 -> 7 | K5: =J5/J$26 -> 0.125 | L5: =K5+L4 -> 0.89285714 | M5: =_xlfn.IFS(L5<80%,"A",L5<=95%,"B",L5>95%,"C") -> B
B6: qs синие | C6: ='Юнит 12-18.01'!AE5 -> 881.45 | D6: =C6/C$26 -> 0.059097676 | E6: =D6+E5 -> 1.0445828 | F6: =IF(AND(E6<=0),"C",IF(E6<=0.8,"A",IF(E6<=0.95,"B","C"))) -> C | G6: =VLOOKUP(B$4:B$25,I$4:M$25,5,0) -> C | I6: qs черные | J6: ='Юнит 12-18.01'!R4 -> 2 | K6: =J6/J$26 -> 0.035714286 | L6: =K6+L5 -> 0.92857143 | M6: =_xlfn.IFS(L6<80%,"A",L6<=95%,"B",L6>95%,"C") -> B
B7: MR Р1886 корич | C7: ='Юнит 12-18.01'!AE16 -> 861.87 | D7: =C7/C$26 -> 0.057784916 | E7: =D7+E6 -> 1.1023677 | F7: =IF(AND(E7<=0),"C",IF(E7<=0.8,"A",IF(E7<=0.95,"B","C"))) -> C | G7: =VLOOKUP(B$4:B$25,I$4:M$25,5,0) -> C | I7: qs синие | J7: ='Юнит 12-18.01'!R5 -> 2 | K7: =J7/J$26 -> 0.035714286 | L7: =K7+L6 -> 0.96428571 | M7: =_xlfn.IFS(L7<80%,"A",L7<=95%,"B",L7>95%,"C") -> C
B8: qs коричневые | C8: ='Юнит 12-18.01'!AE7 -> 0 | D8: =C8/C$26 -> 0 | E8: =D8+E7 -> 1.1023677 | F8: =IF(AND(E8<=0),"C",IF(E8<=0.8,"A",IF(E8<=0.95,"B","C"))) -> C | G8: =VLOOKUP(B$4:B$25,I$4:M$25,5,0) -> C | I8: MR Р1886 корич | J8: ='Юнит 12-18.01'!R16 -> 2 | K8: =J8/J$26 -> 0.035714286 | L8: =K8+L7 -> 1 | M8: =_xlfn.IFS(L8<80%,"A",L8<=95%,"B",L8>95%,"C") -> C
B9: th желтый Сул | C9: ='Юнит 12-18.01'!AE8 -> 0 | D9: =C9/C$26 -> 0 | E9: =D9+E8 -> 1.1023677 | F9: =IF(AND(E9<=0),"C",IF(E9<=0.8,"A",IF(E9<=0.95,"B","C"))) -> C | G9: =VLOOKUP(B$4:B$25,I$4:M$25,5,0) -> C | I9: qs коричневые | J9: ='Юнит 12-18.01'!R7 -> 0 | K9: =J9/J$26 -> 0 | L9: =K9+L8 -> 1 | M9: =_xlfn.IFS(L9<80%,"A",L9<=95%,"B",L9>95%,"C") -> C
B10: MR 1819 черн | C10: ='Юнит 12-18.01'!AE11 -> 0 | D10: =C10/C$26 -> 0 | E10: =D10+E9 -> 1.1023677 | F10: =IF(AND(E10<=0),"C",IF(E10<=0.8,"A",IF(E10<=0.95,"B","C"))) -> C | G10: =VLOOKUP(B$4:B$25,I$4:M$25,5,0) -> C | I10: th желтый Сул | J10: ='Юнит 12-18.01'!R8 -> 0 | K10: =J10/J$26 -> 0 | L10: =K10+L9 -> 1 | M10: =_xlfn.IFS(L10<80%,"A",L10<=95%,"B",L10>95%,"C") -> C
B11: MR 1819 корич | C11: ='Юнит 12-18.01'!AE12 -> 0 | D11: =C11/C$26 -> 0 | E11: =D11+E8 -> 1.1023677 | F11: =IF(AND(E11<=0),"C",IF(E11<=0.8,"A",IF(E11<=0.95,"B","C"))) -> C | G11: =VLOOKUP(B$4:B$25,I$4:M$25,5,0) -> C | I11: flip желтые Сул | J11: ='Юнит 12-18.01'!R9 -> 0 | K11: =J11/J$26 -> 0 | L11: =K11+L8 -> 1 | M11: =_xlfn.IFS(L11<80%,"A",L11<=95%,"B",L11>95%,"C") -> C
B12: MR Р1874 корич | C12: ='Юнит 12-18.01'!AE14 -> 0 | D12: =C12/C$26 -> 0 | E12: =D12+E11 -> 1.1023677 | F12: =IF(AND(E12<=0),"C",IF(E12<=0.8,"A",IF(E12<=0.95,"B","C"))) -> C | G12: =VLOOKUP(B$4:B$25,I$4:M$25,5,0) -> C | I12: MR8854 C2 | J12: ='Юнит 12-18.01'!R10 -> 0 | K12: =J12/J$26 -> 0 | L12: =K12+L11 -> 1 | M12: =_xlfn.IFS(L12<80%,"A",L12<=95%,"B",L12>95%,"C") -> C
B13: MR Р1886 черн глянец | C13: ='Юнит 12-18.01'!AE15 -> 0 | D13: =C13/C$26 -> 0 | E13: =D13+E12 -> 1.1023677 | F13: =IF(AND(E13<=0),"C",IF(E13<=0.8,"A",IF(E13<=0.95,"B","C"))) -> C | G13: =VLOOKUP(B$4:B$25,I$4:M$25,5,0) -> C | I13: MR 1819 черн | J13: ='Юнит 12-18.01'!R11 -> 0 | K13: =J13/J$26 -> 0 | L13: =K13+L12 -> 1 | M13: =_xlfn.IFS(L13<80%,"A",L13<=95%,"B",L13>95%,"C") -> C | P13: A | Q13: 0.8
B14: lux1 | C14: ='Юнит 12-18.01'!AE17 -> 0 | D14: =C14/C$26 -> 0 | E14: =D14+E13 -> 1.1023677 | F14: =IF(AND(E14<=0),"C",IF(E14<=0.8,"A",IF(E14<=0.95,"B","C"))) -> C | G14: =VLOOKUP(B$4:B$25,I$4:M$25,5,0) -> C | I14: MR 1819 корич | J14: ='Юнит 12-18.01'!R12 -> 0 | K14: =J14/J$26 -> 0 | L14: =K14+L13 -> 1 | M14: =_xlfn.IFS(L14<80%,"A",L14<=95%,"B",L14>95%,"C") -> C | P14: B | Q14: 0.15
B15: lux2 | C15: ='Юнит 12-18.01'!AE18 -> 0 | D15: =C15/C$26 -> 0 | E15: =D15+E14 -> 1.1023677 | F15: =IF(AND(E15<=0),"C",IF(E15<=0.8,"A",IF(E15<=0.95,"B","C"))) -> C | G15: =VLOOKUP(B$4:B$25,I$4:M$25,5,0) -> C | I15: MR Р1874 черн | J15: ='Юнит 12-18.01'!R13 -> 0 | K15: =J15/J$26 -> 0 | L15: =K15+L14 -> 1 | M15: =_xlfn.IFS(L15<80%,"A",L15<=95%,"B",L15>95%,"C") -> C | P15: C | Q15: 0.05
B16: lux3 | C16: ='Юнит 12-18.01'!AE19 -> 0 | D16: =C16/C$26 -> 0 | E16: =D16+E15 -> 1.1023677 | F16: =IF(AND(E16<=0),"C",IF(E16<=0.8,"A",IF(E16<=0.95,"B","C"))) -> C | G16: =VLOOKUP(B$4:B$25,I$4:M$25,5,0) -> C | I16: MR Р1874 корич | J16: ='Юнит 12-18.01'!R14 -> 0 | K16: =J16/J$26 -> 0 | L16: =K16+L15 -> 1 | M16: =_xlfn.IFS(L16<80%,"A",L16<=95%,"B",L16>95%,"C") -> C
B17: lux4 | C17: ='Юнит 12-18.01'!AE20 -> 0 | D17: =C17/C$26 -> 0 | E17: =D17+E16 -> 1.1023677 | F17: =IF(AND(E17<=0),"C",IF(E17<=0.8,"A",IF(E17<=0.95,"B","C"))) -> C | G17: =VLOOKUP(B$4:B$25,I$4:M$25,5,0) -> C | I17: MR Р1886 черн глянец | J17: ='Юнит 12-18.01'!R15 -> 0 | K17: =J17/J$26 -> 0 | L17: =K17+L16 -> 1 | M17: =_xlfn.IFS(L17<80%,"A",L17<=95%,"B",L17>95%,"C") -> C
B18: lux5 | C18: ='Юнит 12-18.01'!AE21 -> 0 | D18: =C18/C$26 -> 0 | E18: =D18+E17 -> 1.1023677 | F18: =IF(AND(E18<=0),"C",IF(E18<=0.8,"A",IF(E18<=0.95,"B","C"))) -> C | G18: =VLOOKUP(B$4:B$25,I$4:M$25,5,0) -> C | I18: lux1 | J18: ='Юнит 12-18.01'!R17 -> 0 | K18: =J18/J$26 -> 0 | L18: =K18+L17 -> 1 | M18: =_xlfn.IFS(L18<80%,"A",L18<=95%,"B",L18>95%,"C") -> C
B19: lux6 | C19: ='Юнит 12-18.01'!AE22 -> 0 | D19: =C19/C$26 -> 0 | E19: =D19+E18 -> 1.1023677 | F19: =IF(AND(E19<=0),"C",IF(E19<=0.8,"A",IF(E19<=0.95,"B","C"))) -> C | G19: =VLOOKUP(B$4:B$25,I$4:M$25,5,0) -> C | I19: lux2 | J19: ='Юнит 12-18.01'!R18 -> 0 | K19: =J19/J$26 -> 0 | L19: =K19+L18 -> 1 | M19: =_xlfn.IFS(L19<80%,"A",L19<=95%,"B",L19>95%,"C") -> C
B20: lux7 | C20: ='Юнит 12-18.01'!AE23 -> 0 | D20: =C20/C$26 -> 0 | E20: =D20+E19 -> 1.1023677 | F20: =IF(AND(E20<=0),"C",IF(E20<=0.8,"A",IF(E20<=0.95,"B","C"))) -> C | G20: =VLOOKUP(B$4:B$25,I$4:M$25,5,0) -> C | I20: lux3 | J20: ='Юнит 12-18.01'!R19 -> 0 | K20: =J20/J$26 -> 0 | L20: =K20+L19 -> 1 | M20: =_xlfn.IFS(L20<80%,"A",L20<=95%,"B",L20>95%,"C") -> C
B21: lux8 | C21: ='Юнит 12-18.01'!AE24 -> 0 | D21: =C21/C$26 -> 0 | E21: =D21+E20 -> 1.1023677 | F21: =IF(AND(E21<=0),"C",IF(E21<=0.8,"A",IF(E21<=0.95,"B","C"))) -> C | G21: =VLOOKUP(B$4:B$25,I$4:M$25,5,0) -> C | I21: lux4 | J21: ='Юнит 12-18.01'!R20 -> 0 | K21: =J21/J$26 -> 0 | L21: =K21+L20 -> 1 | M21: =_xlfn.IFS(L21<80%,"A",L21<=95%,"B",L21>95%,"C") -> C
B22: MR8854 C2 | C22: ='Юнит 12-18.01'!AE10 -> -93.54 | D22: =C22/C$26 -> -0.0062714806 | E22: =D22+E21 -> 1.0960962 | F22: =IF(AND(E22<=0),"C",IF(E22<=0.8,"A",IF(E22<=0.95,"B","C"))) -> C | G22: =VLOOKUP(B$4:B$25,I$4:M$25,5,0) -> C | I22: lux5 | J22: ='Юнит 12-18.01'!R21 -> 0 | K22: =J22/J$26 -> 0 | L22: =K22+L21 -> 1 | M22: =_xlfn.IFS(L22<80%,"A",L22<=95%,"B",L22>95%,"C") -> C
B23: MR Р1874 черн | C23: ='Юнит 12-18.01'!AE13 -> -93.54 | D23: =C23/C$26 -> -0.0062714806 | E23: =D23+E22 -> 1.0898248 | F23: =IF(AND(E23<=0),"C",IF(E23<=0.8,"A",IF(E23<=0.95,"B","C"))) -> C | G23: =VLOOKUP(B$4:B$25,I$4:M$25,5,0) -> C | I23: lux6 | J23: ='Юнит 12-18.01'!R22 -> 0 | K23: =J23/J$26 -> 0 | L23: =K23+L22 -> 1 | M23: =_xlfn.IFS(L23<80%,"A",L23<=95%,"B",L23>95%,"C") -> C
B24: flip желтые Сул | C24: ='Юнит 12-18.01'!AE9 -> -429.25019 | D24: =C24/C$26 -> -0.028779498 | E24: =D24+E23 -> 1.0610453 | F24: =IF(AND(E24<=0),"C",IF(E24<=0.8,"A",IF(E24<=0.95,"B","C"))) -> C | G24: =VLOOKUP(B$4:B$25,I$4:M$25,5,0) -> C | I24: lux7 | J24: ='Юнит 12-18.01'!R23 -> 0 | K24: =J24/J$26 -> 0 | L24: =K24+L23 -> 1 | M24: =_xlfn.IFS(L24<80%,"A",L24<=95%,"B",L24>95%,"C") -> C
B25: qs черные | C25: ='Юнит 12-18.01'!AE4 -> -910.4985 | D25: =C25/C$26 -> -0.061045261 | E25: =D25+E24 -> 1 | F25: =IF(AND(E25<=0),"C",IF(E25<=0.8,"A",IF(E25<=0.95,"B","C"))) -> C | G25: =VLOOKUP(B$4:B$25,I$4:M$25,5,0) -> B | I25: lux8 | J25: ='Юнит 12-18.01'!R24 -> 0 | K25: =J25/J$26 -> 0 | L25: =K25+L24 -> 1 | M25: =_xlfn.IFS(L25<80%,"A",L25<=95%,"B",L25>95%,"C") -> C
C26: =SUM(C4:C25) -> 14915.138 | D26: =SUM(D4:D25) -> 1 | J26: =SUM(J4:J25) -> 56 | K26: =SUM(K4:K25) -> 1
B28: ТУНИКИ
C29: Прибыль | D29: % прибыль | E29: Доля | F29: ABC прибыль | G29: ABC кол-во | J29: Кол-во | K29: % кол-во | L29: Доля | M29: ABC кол-во
B30: tunika10 кимоно ч/б | C30: ='Юнит 12-18.01'!AE38 -> 1094.25 | D30: =C30/C$50 -> 1.0062694 | E30: =D30 -> 1.0062694 | F30: =IF(AND(E30<=0),"C",IF(E30<=0.8,"A",IF(E30<=0.95,"B","C"))) -> C | G30: =VLOOKUP(B$30:B$50,I$30:M$50,5,0) -> B | I30: tunika15 кимоно бирюза | J30: ='Юнит 12-18.01'!R44 -> 3 | K30: =J30/J$50 -> 0.6 | L30: =K30 -> 0.6 | M30: =_xlfn.IFS(L30<80%,"A",L30<=95%,"B",L30>95%,"C") -> A
B31: tunika15 кимоно бирюза | C31: ='Юнит 12-18.01'!AE44 -> 1366.2751 | D31: =C31/C$50 -> 1.256423 | E31: =D31+E30 -> 2.2626925 | F31: =IF(AND(E31<=0),"C",IF(E31<=0.8,"A",IF(E31<=0.95,"B","C"))) -> C | G31: =VLOOKUP(B$30:B$50,I$30:M$50,5,0) -> A | I31: tunika10 кимоно ч/б | J31: ='Юнит 12-18.01'!R38 -> 1 | K31: =J31/J$50 -> 0.2 | L31: =K31+L30 -> 0.8 | M31: =_xlfn.IFS(L31<80%,"A",L31<=95%,"B",L31>95%,"C") -> B
B32: tunika02 оливковая с руч вышивкой | C32: ='Юнит 12-18.01'!AE28 -> 0 | D32: =C32/C$50 -> 0 | E32: =D32+E31 -> 2.2626925 | F32: =IF(AND(E32<=0),"C",IF(E32<=0.8,"A",IF(E32<=0.95,"B","C"))) -> C | G32: =VLOOKUP(B$30:B$50,I$30:M$50,5,0) -> C | I32: tunika15 кимоно песочная | J32: ='Юнит 12-18.01'!R45 -> 1 | K32: =J32/J$50 -> 0.2 | L32: =K32+L31 -> 1 | M32: =_xlfn.IFS(L32<80%,"A",L32<=95%,"B",L32>95%,"C") -> C
B33: tunika03 черная распашная | C33: ='Юнит 12-18.01'!AE29 -> 0 | D33: =C33/C$50 -> 0 | E33: =D33+E32 -> 2.2626925 | F33: =IF(AND(E33<=0),"C",IF(E33<=0.8,"A",IF(E33<=0.95,"B","C"))) -> C | G33: =VLOOKUP(B$30:B$50,I$30:M$50,5,0) -> C | I33: tunika02 оливковая с руч вышивкой | J33: ='Юнит 12-18.01'!R28 -> 0 | K33: =J33/J$50 -> 0 | L33: =K33+L32 -> 1 | M33: =_xlfn.IFS(L33<80%,"A",L33<=95%,"B",L33>95%,"C") -> C
B34: tunika05 белая распашная | C34: ='Юнит 12-18.01'!AE30 -> 0 | D34: =C34/C$50 -> 0 | E34: =D34+E33 -> 2.2626925 | F34: =IF(AND(E34<=0),"C",IF(E34<=0.8,"A",IF(E34<=0.95,"B","C"))) -> C | G34: =VLOOKUP(B$30:B$50,I$30:M$50,5,0) -> C | I34: tunika03 черная распашная | J34: ='Юнит 12-18.01'!R29 -> 0 | K34: =J34/J$50 -> 0 | L34: =K34+L33 -> 1 | M34: =_xlfn.IFS(L34<80%,"A",L34<=95%,"B",L34>95%,"C") -> C
B35: tunika06 белая | C35: ='Юнит 12-18.01'!AE31 -> 0 | D35: =C35/C$50 -> 0 | E35: =D35+E34 -> 2.2626925 | F35: =IF(AND(E35<=0),"C",IF(E35<=0.8,"A",IF(E35<=0.95,"B","C"))) -> C | G35: =VLOOKUP(B$30:B$50,I$30:M$50,5,0) -> C | I35: tunika05 белая распашная | J35: ='Юнит 12-18.01'!R30 -> 0 | K35: =J35/J$50 -> 0 | L35: =K35+L34 -> 1 | M35: =_xlfn.IFS(L35<80%,"A",L35<=95%,"B",L35>95%,"C") -> C
B36: tunika06 черная | C36: ='Юнит 12-18.01'!AE32 -> 0 | D36: =C36/C$50 -> 0 | E36: =D36+E35 -> 2.2626925 | F36: =IF(AND(E36<=0),"C",IF(E36<=0.8,"A",IF(E36<=0.95,"B","C"))) -> C | G36: =VLOOKUP(B$30:B$50,I$30:M$50,5,0) -> C | I36: tunika06 белая | J36: ='Юнит 12-18.01'!R31 -> 0 | K36: =J36/J$50 -> 0 | L36: =K36+L35 -> 1 | M36: =_xlfn.IFS(L36<80%,"A",L36<=95%,"B",L36>95%,"C") -> C
B37: tunika07 кружево | C37: ='Юнит 12-18.01'!AE33 -> 0 | D37: =C37/C$50 -> 0 | E37: =D37+E36 -> 2.2626925 | F37: =IF(AND(E37<=0),"C",IF(E37<=0.8,"A",IF(E37<=0.95,"B","C"))) -> C | G37: =VLOOKUP(B$30:B$50,I$30:M$50,5,0) -> C | I37: tunika06 черная | J37: ='Юнит 12-18.01'!R32 -> 0 | K37: =J37/J$50 -> 0 | L37: =K37+L36 -> 1 | M37: =_xlfn.IFS(L37<80%,"A",L37<=95%,"B",L37>95%,"C") -> C
B38: tunika08 белая | C38: ='Юнит 12-18.01'!AE34 -> 0 | D38: =C38/C$50 -> 0 | E38: =D38+E37 -> 2.2626925 | F38: =IF(AND(E38<=0),"C",IF(E38<=0.8,"A",IF(E38<=0.95,"B","C"))) -> C | G38: =VLOOKUP(B$30:B$50,I$30:M$50,5,0) -> C | I38: tunika07 кружево | J38: ='Юнит 12-18.01'!R33 -> 0 | K38: =J38/J$50 -> 0 | L38: =K38+L37 -> 1 | M38: =_xlfn.IFS(L38<80%,"A",L38<=95%,"B",L38>95%,"C") -> C
B39: tunika08 черная | C39: ='Юнит 12-18.01'!AE35 -> 0 | D39: =C39/C$50 -> 0 | E39: =D39+E38 -> 2.2626925 | F39: =IF(AND(E39<=0),"C",IF(E39<=0.8,"A",IF(E39<=0.95,"B","C"))) -> C | G39: =VLOOKUP(B$30:B$50,I$30:M$50,5,0) -> C | I39: tunika08 белая | J39: ='Юнит 12-18.01'!R34 -> 0 | K39: =J39/J$50 -> 0 | L39: =K39+L38 -> 1 | M39: =_xlfn.IFS(L39<80%,"A",L39<=95%,"B",L39>95%,"C") -> C
B40: tunika08 зеленая | C40: ='Юнит 12-18.01'!AE36 -> 0 | D40: =C40/C$50 -> 0 | E40: =D40+E39 -> 2.2626925 | F40: =IF(AND(E40<=0),"C",IF(E40<=0.8,"A",IF(E40<=0.95,"B","C"))) -> C | G40: =VLOOKUP(B$30:B$50,I$30:M$50,5,0) -> C | I40: tunika08 черная | J40: ='Юнит 12-18.01'!R35 -> 0 | K40: =J40/J$50 -> 0 | L40: =K40+L39 -> 1 | M40: =_xlfn.IFS(L40<80%,"A",L40<=95%,"B",L40>95%,"C") -> C
B41: tunika09 кимоно | C41: ='Юнит 12-18.01'!AE37 -> 0 | D41: =C41/C$50 -> 0 | E41: =D41+E40 -> 2.2626925 | F41: =IF(AND(E41<=0),"C",IF(E41<=0.8,"A",IF(E41<=0.95,"B","C"))) -> C | G41: =VLOOKUP(B$30:B$50,I$30:M$50,5,0) -> C | I41: tunika08 зеленая | J41: ='Юнит 12-18.01'!R36 -> 0 | K41: =J41/J$50 -> 0 | L41: =K41+L40 -> 1 | M41: =_xlfn.IFS(L41<80%,"A",L41<=95%,"B",L41>95%,"C") -> C
B42: tunika11 халат зеленая | C42: ='Юнит 12-18.01'!AE39 -> 0 | D42: =C42/C$50 -> 0 | E42: =D42+E41 -> 2.2626925 | F42: =IF(AND(E42<=0),"C",IF(E42<=0.8,"A",IF(E42<=0.95,"B","C"))) -> C | G42: =VLOOKUP(B$30:B$50,I$30:M$50,5,0) -> C | I42: tunika09 кимоно | J42: ='Юнит 12-18.01'!R37 -> 0 | K42: =J42/J$50 -> 0 | L42: =K42+L41 -> 1 | M42: =_xlfn.IFS(L42<80%,"A",L42<=95%,"B",L42>95%,"C") -> C
B43: tunika12 халат белая | C43: ='Юнит 12-18.01'!AE40 -> 0 | D43: =C43/C$50 -> 0 | E43: =D43+E42 -> 2.2626925 | F43: =IF(AND(E43<=0),"C",IF(E43<=0.8,"A",IF(E43<=0.95,"B","C"))) -> C | G43: =VLOOKUP(B$30:B$50,I$30:M$50,5,0) -> C | I43: tunika11 халат зеленая | J43: ='Юнит 12-18.01'!R39 -> 0 | K43: =J43/J$50 -> 0 | L43: =K43+L42 -> 1 | M43: =_xlfn.IFS(L43<80%,"A",L43<=95%,"B",L43>95%,"C") -> C
B44: tunika13 халат черная | C44: ='Юнит 12-18.01'!AE41 -> 0 | D44: =C44/C$50 -> 0 | E44: =D44+E43 -> 2.2626925 | F44: =IF(AND(E44<=0),"C",IF(E44<=0.8,"A",IF(E44<=0.95,"B","C"))) -> C | G44: =VLOOKUP(B$30:B$50,I$30:M$50,5,0) -> C | I44: tunika12 халат белая | J44: ='Юнит 12-18.01'!R40 -> 0 | K44: =J44/J$50 -> 0 | L44: =K44+L43 -> 1 | M44: =_xlfn.IFS(L44<80%,"A",L44<=95%,"B",L44>95%,"C") -> C
B45: tunika14 халат с разрезами белая | C45: ='Юнит 12-18.01'!AE42 -> 0 | D45: =C45/C$50 -> 0 | E45: =D45+E44 -> 2.2626925 | F45: =IF(AND(E45<=0),"C",IF(E45<=0.8,"A",IF(E45<=0.95,"B","C"))) -> C | G45: =VLOOKUP(B$30:B$50,I$30:M$50,5,0) -> C | I45: tunika13 халат черная | J45: ='Юнит 12-18.01'!R41 -> 0 | K45: =J45/J$50 -> 0 | L45: =K45+L44 -> 1 | M45: =_xlfn.IFS(L45<80%,"A",L45<=95%,"B",L45>95%,"C") -> C
B46: tunika14 халат с разрезами черный | C46: ='Юнит 12-18.01'!AE43 -> 0 | D46: =C46/C$50 -> 0 | E46: =D46+E45 -> 2.2626925 | F46: =IF(AND(E46<=0),"C",IF(E46<=0.8,"A",IF(E46<=0.95,"B","C"))) -> C | G46: =VLOOKUP(B$30:B$50,I$30:M$50,5,0) -> C | I46: tunika14 халат с разрезами белая | J46: ='Юнит 12-18.01'!R42 -> 0 | K46: =J46/J$50 -> 0 | L46: =K46+L45 -> 1 | M46: =_xlfn.IFS(L46<80%,"A",L46<=95%,"B",L46>95%,"C") -> C
B47: tunika16 сетка белая | C47: ='Юнит 12-18.01'!AE46 -> 0 | D47: =C47/C$50 -> 0 | E47: =D47+E46 -> 2.2626925 | F47: =IF(AND(E47<=0),"C",IF(E47<=0.8,"A",IF(E47<=0.95,"B","C"))) -> C | G47: =VLOOKUP(B$30:B$50,I$30:M$50,5,0) -> C | I47: tunika14 халат с разрезами черный | J47: ='Юнит 12-18.01'!R43 -> 0 | K47: =J47/J$50 -> 0 | L47: =K47+L46 -> 1 | M47: =_xlfn.IFS(L47<80%,"A",L47<=95%,"B",L47>95%,"C") -> C
B48: tunika16 сетка черная | C48: ='Юнит 12-18.01'!AE47 -> 0 | D48: =C48/C$50 -> 0 | E48: =D48+E47 -> 2.2626925 | F48: =IF(AND(E48<=0),"C",IF(E48<=0.8,"A",IF(E48<=0.95,"B","C"))) -> C | G48: =VLOOKUP(B$30:B$50,I$30:M$50,5,0) -> C | I48: tunika16 сетка белая | J48: ='Юнит 12-18.01'!R46 -> 0 | K48: =J48/J$50 -> 0 | L48: =K48+L47 -> 1 | M48: =_xlfn.IFS(L48<80%,"A",L48<=95%,"B",L48>95%,"C") -> C
B49: tunika15 кимоно песочная | C49: ='Юнит 12-18.01'!AE45 -> -1373.0927 | D49: =C49/C$50 -> -1.2626925 | E49: =D49+E48 -> 1 | F49: =IF(AND(E49<=0),"C",IF(E49<=0.8,"A",IF(E49<=0.95,"B","C"))) -> C | G49: =VLOOKUP(B$30:B$50,I$30:M$50,5,0) -> C | I49: tunika16 сетка черная | J49: ='Юнит 12-18.01'!R47 -> 0 | K49: =J49/J$50 -> 0 | L49: =K49+L48 -> 1 | M49: =_xlfn.IFS(L49<80%,"A",L49<=95%,"B",L49>95%,"C") -> C
C50: =SUM(C30:C49) -> 1087.4324 | D50: =SUM(D30:D49) -> 1 | J50: =SUM(J30:J49) -> 5 | K50: =SUM(K30:K49) -> 1

Sheet АВС 05-11.01
B2: ОЧКИ
C3: Прибыль | D3: % прибыль | E3: Доля | F3: ABC прибыль | G3: ABC кол-во | J3: Кол-во | K3: % кол-во | L3: Доля | M3: ABC кол-во
B4: черные с железкой классика | C4: ='Юнит 05-11.01'!AE3 -> 6568.9867 | D4: =C4/C$26 -> 0.64827525 | E4: =D4 -> 0.64827525 | F4: =IF(AND(E4<=0),"C",IF(E4<=0.8,"A",IF(E4<=0.95,"B","C"))) -> A | G4: =VLOOKUP(B$4:B$25,I$4:M$25,5,0) -> A | I4: черные с железкой классика | J4: ='Юнит 05-11.01'!R3 -> 32 | K4: =J4/J$26 -> 0.59259259 | L4: =K4 -> 0.59259259 | M4: =_xlfn.IFS(L4<80%,"A",L4<=95%,"B",L4>95%,"C") -> A
B5: MR 1819 корич | C5: ='Юнит 05-11.01'!AE12 -> 698.36 | D5: =C5/C$26 -> 0.06891923 | E5: =D5+E4 -> 0.71719448 | F5: =IF(AND(E5<=0),"C",IF(E5<=0.8,"A",IF(E5<=0.95,"B","C"))) -> A | G5: =VLOOKUP(B$4:B$25,I$4:M$25,5,0) -> B | I5: qs желтые | J5: ='Юнит 05-11.01'!R6 -> 11 | K5: =J5/J$26 -> 0.2037037 | L5: =K5+L4 -> 0.7962963 | M5: =_xlfn.IFS(L5<80%,"A",L5<=95%,"B",L5>95%,"C") -> A
B6: qs желтые | C6: ='Юнит 05-11.01'!AE6 -> 1305.2943 | D6: =C6/C$26 -> 0.12881591 | E6: =D6+E5 -> 0.84601039 | F6: =IF(AND(E6<=0),"C",IF(E6<=0.8,"A",IF(E6<=0.95,"B","C"))) -> B | G6: =VLOOKUP(B$4:B$25,I$4:M$25,5,0) -> A | I6: MR 1819 корич | J6: ='Юнит 05-11.01'!R12 -> 2 | K6: =J6/J$26 -> 0.037037037 | L6: =K6+L5 -> 0.83333333 | M6: =_xlfn.IFS(L6<80%,"A",L6<=95%,"B",L6>95%,"C") -> B
B7: MR Р1886 корич | C7: ='Юнит 05-11.01'!AE16 -> 584.28 | D7: =C7/C$26 -> 0.057660988 | E7: =D7+E6 -> 0.90367138 | F7: =IF(AND(E7<=0),"C",IF(E7<=0.8,"A",IF(E7<=0.95,"B","C"))) -> B | G7: =VLOOKUP(B$4:B$25,I$4:M$25,5,0) -> B | I7: MR Р1886 черн глянец | J7: ='Юнит 05-11.01'!R15 -> 2 | K7: =J7/J$26 -> 0.037037037 | L7: =K7+L6 -> 0.87037037 | M7: =_xlfn.IFS(L7<80%,"A",L7<=95%,"B",L7>95%,"C") -> B
B8: MR Р1874 черн | C8: ='Юнит 05-11.01'!AE13 -> 497.35 | D8: =C8/C$26 -> 0.049082105 | E8: =D8+E7 -> 0.95275349 | F8: =IF(AND(E8<=0),"C",IF(E8<=0.8,"A",IF(E8<=0.95,"B","C"))) -> C | G8: =VLOOKUP(B$4:B$25,I$4:M$25,5,0) -> B | I8: MR Р1886 корич | J8: ='Юнит 05-11.01'!R16 -> 2 | K8: =J8/J$26 -> 0.037037037 | L8: =K8+L7 -> 0.90740741 | M8: =_xlfn.IFS(L8<80%,"A",L8<=95%,"B",L8>95%,"C") -> B
B9: qs синие | C9: ='Юнит 05-11.01'!AE5 -> 360.57 | D9: =C9/C$26 -> 0.035583663 | E9: =D9+E8 -> 0.98833715 | F9: =IF(AND(E9<=0),"C",IF(E9<=0.8,"A",IF(E9<=0.95,"B","C"))) -> C | G9: =VLOOKUP(B$4:B$25,I$4:M$25,5,0) -> B | I9: qs синие | J9: ='Юнит 05-11.01'!R5 -> 1 | K9: =J9/J$26 -> 0.018518519 | L9: =K9+L8 -> 0.92592593 | M9: =_xlfn.IFS(L9<80%,"A",L9<=95%,"B",L9>95%,"C") -> B
B10: MR Р1874 корич | C10: ='Юнит 05-11.01'!AE14 -> 280.86 | D10: =C10/C$26 -> 0.027717302 | E10: =D10+E9 -> 1.0160545 | F10: =IF(AND(E10<=0),"C",IF(E10<=0.8,"A",IF(E10<=0.95,"B","C"))) -> C | G10: =VLOOKUP(B$4:B$25,I$4:M$25,5,0) -> C | I10: qs коричневые | J10: ='Юнит 05-11.01'!R7 -> 1 | K10: =J10/J$26 -> 0.018518519 | L10: =K10+L9 -> 0.94444444 | M10: =_xlfn.IFS(L10<80%,"A",L10<=95%,"B",L10>95%,"C") -> B
B11: MR Р1886 черн глянец | C11: ='Юнит 05-11.01'!AE15 -> 132.94 | D11: =C11/C$26 -> 0.013119483 | E11: =D11+E8 -> 0.96587297 | F11: =IF(AND(E11<=0),"C",IF(E11<=0.8,"A",IF(E11<=0.95,"B","C"))) -> C | G11: =VLOOKUP(B$4:B$25,I$4:M$25,5,0) -> B | I11: flip желтые Сул | J11: ='Юнит 05-11.01'!R9 -> 1 | K11: =J11/J$26 -> 0.018518519 | L11: =K11+L8 -> 0.92592593 | M11: =_xlfn.IFS(L11<80%,"A",L11<=95%,"B",L11>95%,"C") -> B
B12: qs черные | C12: ='Юнит 05-11.01'!AE4 -> 0 | D12: =C12/C$26 -> 0 | E12: =D12+E11 -> 0.96587297 | F12: =IF(AND(E12<=0),"C",IF(E12<=0.8,"A",IF(E12<=0.95,"B","C"))) -> C | G12: =VLOOKUP(B$4:B$25,I$4:M$25,5,0) -> C | I12: MR Р1874 черн | J12: ='Юнит 05-11.01'!R13 -> 1 | K12: =J12/J$26 -> 0.018518519 | L12: =K12+L11 -> 0.94444444 | M12: =_xlfn.IFS(L12<80%,"A",L12<=95%,"B",L12>95%,"C") -> B
B13: th желтый Сул | C13: ='Юнит 05-11.01'!AE8 -> 0 | D13: =C13/C$26 -> 0 | E13: =D13+E12 -> 0.96587297 | F13: =IF(AND(E13<=0),"C",IF(E13<=0.8,"A",IF(E13<=0.95,"B","C"))) -> C | G13: =VLOOKUP(B$4:B$25,I$4:M$25,5,0) -> C | I13: MR Р1874 корич | J13: ='Юнит 05-11.01'!R14 -> 1 | K13: =J13/J$26 -> 0.018518519 | L13: =K13+L12 -> 0.96296296 | M13: =_xlfn.IFS(L13<80%,"A",L13<=95%,"B",L13>95%,"C") -> C | P13: A | Q13: 0.8
B14: MR 1819 черн | C14: ='Юнит 05-11.01'!AE11 -> 0 | D14: =C14/C$26 -> 0 | E14: =D14+E13 -> 0.96587297 | F14: =IF(AND(E14<=0),"C",IF(E14<=0.8,"A",IF(E14<=0.95,"B","C"))) -> C | G14: =VLOOKUP(B$4:B$25,I$4:M$25,5,0) -> C | I14: qs черные | J14: ='Юнит 05-11.01'!R4 -> 0 | K14: =J14/J$26 -> 0 | L14: =K14+L13 -> 0.96296296 | M14: =_xlfn.IFS(L14<80%,"A",L14<=95%,"B",L14>95%,"C") -> C | P14: B | Q14: 0.15
B15: lux1 | C15: ='Юнит 05-11.01'!AE17 -> 0 | D15: =C15/C$26 -> 0 | E15: =D15+E14 -> 0.96587297 | F15: =IF(AND(E15<=0),"C",IF(E15<=0.8,"A",IF(E15<=0.95,"B","C"))) -> C | G15: =VLOOKUP(B$4:B$25,I$4:M$25,5,0) -> C | I15: th желтый Сул | J15: ='Юнит 05-11.01'!R8 -> 0 | K15: =J15/J$26 -> 0 | L15: =K15+L14 -> 0.96296296 | M15: =_xlfn.IFS(L15<80%,"A",L15<=95%,"B",L15>95%,"C") -> C | P15: C | Q15: 0.05
B16: lux2 | C16: ='Юнит 05-11.01'!AE18 -> 0 | D16: =C16/C$26 -> 0 | E16: =D16+E15 -> 0.96587297 | F16: =IF(AND(E16<=0),"C",IF(E16<=0.8,"A",IF(E16<=0.95,"B","C"))) -> C | G16: =VLOOKUP(B$4:B$25,I$4:M$25,5,0) -> C | I16: MR8854 C2 | J16: ='Юнит 05-11.01'!R10 -> 0 | K16: =J16/J$26 -> 0 | L16: =K16+L15 -> 0.96296296 | M16: =_xlfn.IFS(L16<80%,"A",L16<=95%,"B",L16>95%,"C") -> C
B17: lux3 | C17: ='Юнит 05-11.01'!AE19 -> 0 | D17: =C17/C$26 -> 0 | E17: =D17+E16 -> 0.96587297 | F17: =IF(AND(E17<=0),"C",IF(E17<=0.8,"A",IF(E17<=0.95,"B","C"))) -> C | G17: =VLOOKUP(B$4:B$25,I$4:M$25,5,0) -> C | I17: MR 1819 черн | J17: ='Юнит 05-11.01'!R11 -> 0 | K17: =J17/J$26 -> 0 | L17: =K17+L16 -> 0.96296296 | M17: =_xlfn.IFS(L17<80%,"A",L17<=95%,"B",L17>95%,"C") -> C
B18: lux4 | C18: ='Юнит 05-11.01'!AE20 -> 0 | D18: =C18/C$26 -> 0 | E18: =D18+E17 -> 0.96587297 | F18: =IF(AND(E18<=0),"C",IF(E18<=0.8,"A",IF(E18<=0.95,"B","C"))) -> C | G18: =VLOOKUP(B$4:B$25,I$4:M$25,5,0) -> C | I18: lux1 | J18: ='Юнит 05-11.01'!R17 -> 0 | K18: =J18/J$26 -> 0 | L18: =K18+L17 -> 0.96296296 | M18: =_xlfn.IFS(L18<80%,"A",L18<=95%,"B",L18>95%,"C") -> C
B19: lux5 | C19: ='Юнит 05-11.01'!AE21 -> 0 | D19: =C19/C$26 -> 0 | E19: =D19+E18 -> 0.96587297 | F19: =IF(AND(E19<=0),"C",IF(E19<=0.8,"A",IF(E19<=0.95,"B","C"))) -> C | G19: =VLOOKUP(B$4:B$25,I$4:M$25,5,0) -> C | I19: lux2 | J19: ='Юнит 05-11.01'!R18 -> 0 | K19: =J19/J$26 -> 0 | L19: =K19+L18 -> 0.96296296 | M19: =_xlfn.IFS(L19<80%,"A",L19<=95%,"B",L19>95%,"C") -> C
B20: lux6 | C20: ='Юнит 05-11.01'!AE22 -> 0 | D20: =C20/C$26 -> 0 | E20: =D20+E19 -> 0.96587297 | F20: =IF(AND(E20<=0),"C",IF(E20<=0.8,"A",IF(E20<=0.95,"B","C"))) -> C | G20: =VLOOKUP(B$4:B$25,I$4:M$25,5,0) -> C | I20: lux3 | J20: ='Юнит 05-11.01'!R19 -> 0 | K20: =J20/J$26 -> 0 | L20: =K20+L19 -> 0.96296296 | M20: =_xlfn.IFS(L20<80%,"A",L20<=95%,"B",L20>95%,"C") -> C
B21: lux7 | C21: ='Юнит 05-11.01'!AE23 -> 0 | D21: =C21/C$26 -> 0 | E21: =D21+E20 -> 0.96587297 | F21: =IF(AND(E21<=0),"C",IF(E21<=0.8,"A",IF(E21<=0.95,"B","C"))) -> C | G21: =VLOOKUP(B$4:B$25,I$4:M$25,5,0) -> C | I21: lux4 | J21: ='Юнит 05-11.01'!R20 -> 0 | K21: =J21/J$26 -> 0 | L21: =K21+L20 -> 0.96296296 | M21: =_xlfn.IFS(L21<80%,"A",L21<=95%,"B",L21>95%,"C") -> C
B22: lux8 | C22: ='Юнит 05-11.01'!AE24 -> 0 | D22: =C22/C$26 -> 0 | E22: =D22+E21 -> 0.96587297 | F22: =IF(AND(E22<=0),"C",IF(E22<=0.8,"A",IF(E22<=0.95,"B","C"))) -> C | G22: =VLOOKUP(B$4:B$25,I$4:M$25,5,0) -> C | I22: lux5 | J22: ='Юнит 05-11.01'!R21 -> 0 | K22: =J22/J$26 -> 0 | L22: =K22+L21 -> 0.96296296 | M22: =_xlfn.IFS(L22<80%,"A",L22<=95%,"B",L22>95%,"C") -> C
B23: qs коричневые | C23: ='Юнит 05-11.01'!AE7 -> -11.197255 | D23: =C23/C$26 -> -0.0011050263 | E23: =D23+E22 -> 0.96476794 | F23: =IF(AND(E23<=0),"C",IF(E23<=0.8,"A",IF(E23<=0.95,"B","C"))) -> C | G23: =VLOOKUP(B$4:B$25,I$4:M$25,5,0) -> B | I23: lux6 | J23: ='Юнит 05-11.01'!R22 -> 0 | K23: =J23/J$26 -> 0 | L23: =K23+L22 -> 0.96296296 | M23: =_xlfn.IFS(L23<80%,"A",L23<=95%,"B",L23>95%,"C") -> C
B24: MR8854 C2 | C24: ='Юнит 05-11.01'!AE10 -> -93.54 | D24: =C24/C$26 -> -0.0092312057 | E24: =D24+E23 -> 0.95553674 | F24: =IF(AND(E24<=0),"C",IF(E24<=0.8,"A",IF(E24<=0.95,"B","C"))) -> C | G24: =VLOOKUP(B$4:B$25,I$4:M$25,5,0) -> C | I24: lux7 | J24: ='Юнит 05-11.01'!R23 -> 0 | K24: =J24/J$26 -> 0 | L24: =K24+L23 -> 0.96296296 | M24: =_xlfn.IFS(L24<80%,"A",L24<=95%,"B",L24>95%,"C") -> C
B25: flip желтые Сул | C25: ='Юнит 05-11.01'!AE9 -> -190.88285 | D25: =C25/C$26 -> -0.018837704 | E25: =D25+E24 -> 0.93669904 | F25: =IF(AND(E25<=0),"C",IF(E25<=0.8,"A",IF(E25<=0.95,"B","C"))) -> B | G25: =VLOOKUP(B$4:B$25,I$4:M$25,5,0) -> B | I25: lux8 | J25: ='Юнит 05-11.01'!R24 -> 0 | K25: =J25/J$26 -> 0 | L25: =K25+L24 -> 0.96296296 | M25: =_xlfn.IFS(L25<80%,"A",L25<=95%,"B",L25>95%,"C") -> C
C26: =SUM(C4:C25) -> 10133.021 | D26: =SUM(D4:D25) -> 1 | J26: =SUM(J4:J25) -> 54 | K26: =SUM(K4:K25) -> 1
B28: ТУНИКИ
C29: Прибыль | D29: % прибыль | E29: Доля | F29: ABC прибыль | G29: ABC кол-во | J29: Кол-во | K29: % кол-во | L29: Доля | M29: ABC кол-во
B30: tunika14 халат с разрезами белая | C30: ='Юнит 05-11.01'!AE42 -> 1422.85 | D30: =C30/C$50 -> 0.53163259 | E30: =D30 -> 0.53163259 | F30: =IF(AND(E30<=0),"C",IF(E30<=0.8,"A",IF(E30<=0.95,"B","C"))) -> A | G30: =VLOOKUP(B$30:B$50,I$30:M$50,5,0) -> A | I30: tunika14 халат с разрезами белая | J30: ='Юнит 05-11.01'!R42 -> 1 | K30: =J30/J$50 -> 0.5 | L30: =K30 -> 0.5 | M30: =_xlfn.IFS(L30<80%,"A",L30<=95%,"B",L30>95%,"C") -> A
B31: tunika15 кимоно песочная | C31: ='Юнит 05-11.01'!AE45 -> 1481.2884 | D31: =C31/C$50 -> 0.55346748 | E31: =D31+E30 -> 1.0851001 | F31: =IF(AND(E31<=0),"C",IF(E31<=0.8,"A",IF(E31<=0.95,"B","C"))) -> C | G31: =VLOOKUP(B$30:B$50,I$30:M$50,5,0) -> C | I31: tunika15 кимоно песочная | J31: ='Юнит 05-11.01'!R45 -> 1 | K31: =J31/J$50 -> 0.5 | L31: =K31+L30 -> 1 | M31: =_xlfn.IFS(L31<80%,"A",L31<=95%,"B",L31>95%,"C") -> C
B32: tunika02 оливковая с руч вышивкой | C32: ='Юнит 05-11.01'!AE28 -> 0 | D32: =C32/C$50 -> 0 | E32: =D32+E31 -> 1.0851001 | F32: =IF(AND(E32<=0),"C",IF(E32<=0.8,"A",IF(E32<=0.95,"B","C"))) -> C | G32: =VLOOKUP(B$30:B$50,I$30:M$50,5,0) -> C | I32: tunika02 оливковая с руч вышивкой | J32: ='Юнит 05-11.01'!R28 -> 0 | K32: =J32/J$50 -> 0 | L32: =K32+L31 -> 1 | M32: =_xlfn.IFS(L32<80%,"A",L32<=95%,"B",L32>95%,"C") -> C
B33: tunika03 черная распашная | C33: ='Юнит 05-11.01'!AE29 -> 0 | D33: =C33/C$50 -> 0 | E33: =D33+E32 -> 1.0851001 | F33: =IF(AND(E33<=0),"C",IF(E33<=0.8,"A",IF(E33<=0.95,"B","C"))) -> C | G33: =VLOOKUP(B$30:B$50,I$30:M$50,5,0) -> C | I33: tunika03 черная распашная | J33: ='Юнит 05-11.01'!R29 -> 0 | K33: =J33/J$50 -> 0 | L33: =K33+L32 -> 1 | M33: =_xlfn.IFS(L33<80%,"A",L33<=95%,"B",L33>95%,"C") -> C
B34: tunika05 белая распашная | C34: ='Юнит 05-11.01'!AE30 -> 0 | D34: =C34/C$50 -> 0 | E34: =D34+E33 -> 1.0851001 | F34: =IF(AND(E34<=0),"C",IF(E34<=0.8,"A",IF(E34<=0.95,"B","C"))) -> C | G34: =VLOOKUP(B$30:B$50,I$30:M$50,5,0) -> C | I34: tunika05 белая распашная | J34: ='Юнит 05-11.01'!R30 -> 0 | K34: =J34/J$50 -> 0 | L34: =K34+L33 -> 1 | M34: =_xlfn.IFS(L34<80%,"A",L34<=95%,"B",L34>95%,"C") -> C
B35: tunika06 белая | C35: ='Юнит 05-11.01'!AE31 -> 0 | D35: =C35/C$50 -> 0 | E35: =D35+E34 -> 1.0851001 | F35: =IF(AND(E35<=0),"C",IF(E35<=0.8,"A",IF(E35<=0.95,"B","C"))) -> C | G35: =VLOOKUP(B$30:B$50,I$30:M$50,5,0) -> C | I35: tunika06 белая | J35: ='Юнит 05-11.01'!R31 -> 0 | K35: =J35/J$50 -> 0 | L35: =K35+L34 -> 1 | M35: =_xlfn.IFS(L35<80%,"A",L35<=95%,"B",L35>95%,"C") -> C
B36: tunika06 черная | C36: ='Юнит 05-11.01'!AE32 -> 0 | D36: =C36/C$50 -> 0 | E36: =D36+E35 -> 1.0851001 | F36: =IF(AND(E36<=0),"C",IF(E36<=0.8,"A",IF(E36<=0.95,"B","C"))) -> C | G36: =VLOOKUP(B$30:B$50,I$30:M$50,5,0) -> C | I36: tunika06 черная | J36: ='Юнит 05-11.01'!R32 -> 0 | K36: =J36/J$50 -> 0 | L36: =K36+L35 -> 1 | M36: =_xlfn.IFS(L36<80%,"A",L36<=95%,"B",L36>95%,"C") -> C
B37: tunika07 кружево | C37: ='Юнит 05-11.01'!AE33 -> 0 | D37: =C37/C$50 -> 0 | E37: =D37+E36 -> 1.0851001 | F37: =IF(AND(E37<=0),"C",IF(E37<=0.8,"A",IF(E37<=0.95,"B","C"))) -> C | G37: =VLOOKUP(B$30:B$50,I$30:M$50,5,0) -> C | I37: tunika07 кружево | J37: ='Юнит 05-11.01'!R33 -> 0 | K37: =J37/J$50 -> 0 | L37: =K37+L36 -> 1 | M37: =_xlfn.IFS(L37<80%,"A",L37<=95%,"B",L37>95%,"C") -> C
B38: tunika08 белая | C38: ='Юнит 05-11.01'!AE34 -> 0 | D38: =C38/C$50 -> 0 | E38: =D38+E37 -> 1.0851001 | F38: =IF(AND(E38<=0),"C",IF(E38<=0.8,"A",IF(E38<=0.95,"B","C"))) -> C | G38: =VLOOKUP(B$30:B$50,I$30:M$50,5,0) -> C | I38: tunika08 белая | J38: ='Юнит 05-11.01'!R34 -> 0 | K38: =J38/J$50 -> 0 | L38: =K38+L37 -> 1 | M38: =_xlfn.IFS(L38<80%,"A",L38<=95%,"B",L38>95%,"C") -> C
B39: tunika08 черная | C39: ='Юнит 05-11.01'!AE35 -> 0 | D39: =C39/C$50 -> 0 | E39: =D39+E38 -> 1.0851001 | F39: =IF(AND(E39<=0),"C",IF(E39<=0.8,"A",IF(E39<=0.95,"B","C"))) -> C | G39: =VLOOKUP(B$30:B$50,I$30:M$50,5,0) -> C | I39: tunika08 черная | J39: ='Юнит 05-11.01'!R35 -> 0 | K39: =J39/J$50 -> 0 | L39: =K39+L38 -> 1 | M39: =_xlfn.IFS(L39<80%,"A",L39<=95%,"B",L39>95%,"C") -> C
B40: tunika08 зеленая | C40: ='Юнит 05-11.01'!AE36 -> 0 | D40: =C40/C$50 -> 0 | E40: =D40+E39 -> 1.0851001 | F40: =IF(AND(E40<=0),"C",IF(E40<=0.8,"A",IF(E40<=0.95,"B","C"))) -> C | G40: =VLOOKUP(B$30:B$50,I$30:M$50,5,0) -> C | I40: tunika08 зеленая | J40: ='Юнит 05-11.01'!R36 -> 0 | K40: =J40/J$50 -> 0 | L40: =K40+L39 -> 1 | M40: =_xlfn.IFS(L40<80%,"A",L40<=95%,"B",L40>95%,"C") -> C
B41: tunika10 кимоно ч/б | C41: ='Юнит 05-11.01'!AE38 -> 0 | D41: =C41/C$50 -> 0 | E41: =D41+E40 -> 1.0851001 | F41: =IF(AND(E41<=0),"C",IF(E41<=0.8,"A",IF(E41<=0.95,"B","C"))) -> C | G41: =VLOOKUP(B$30:B$50,I$30:M$50,5,0) -> C | I41: tunika09 кимоно | J41: ='Юнит 05-11.01'!R37 -> 0 | K41: =J41/J$50 -> 0 | L41: =K41+L40 -> 1 | M41: =_xlfn.IFS(L41<80%,"A",L41<=95%,"B",L41>95%,"C") -> C
B42: tunika11 халат зеленая | C42: ='Юнит 05-11.01'!AE39 -> 0 | D42: =C42/C$50 -> 0 | E42: =D42+E41 -> 1.0851001 | F42: =IF(AND(E42<=0),"C",IF(E42<=0.8,"A",IF(E42<=0.95,"B","C"))) -> C | G42: =VLOOKUP(B$30:B$50,I$30:M$50,5,0) -> C | I42: tunika10 кимоно ч/б | J42: ='Юнит 05-11.01'!R38 -> 0 | K42: =J42/J$50 -> 0 | L42: =K42+L41 -> 1 | M42: =_xlfn.IFS(L42<80%,"A",L42<=95%,"B",L42>95%,"C") -> C
B43: tunika12 халат белая | C43: ='Юнит 05-11.01'!AE40 -> 0 | D43: =C43/C$50 -> 0 | E43: =D43+E42 -> 1.0851001 | F43: =IF(AND(E43<=0),"C",IF(E43<=0.8,"A",IF(E43<=0.95,"B","C"))) -> C | G43: =VLOOKUP(B$30:B$50,I$30:M$50,5,0) -> C | I43: tunika11 халат зеленая | J43: ='Юнит 05-11.01'!R39 -> 0 | K43: =J43/J$50 -> 0 | L43: =K43+L42 -> 1 | M43: =_xlfn.IFS(L43<80%,"A",L43<=95%,"B",L43>95%,"C") -> C
B44: tunika13 халат черная | C44: ='Юнит 05-11.01'!AE41 -> 0 | D44: =C44/C$50 -> 0 | E44: =D44+E43 -> 1.0851001 | F44: =IF(AND(E44<=0),"C",IF(E44<=0.8,"A",IF(E44<=0.95,"B","C"))) -> C | G44: =VLOOKUP(B$30:B$50,I$30:M$50,5,0) -> C | I44: tunika12 халат белая | J44: ='Юнит 05-11.01'!R40 -> 0 | K44: =J44/J$50 -> 0 | L44: =K44+L43 -> 1 | M44: =_xlfn.IFS(L44<80%,"A",L44<=95%,"B",L44>95%,"C") -> C
B45: tunika14 халат с разрезами черный | C45: ='Юнит 05-11.01'!AE43 -> 0 | D45: =C45/C$50 -> 0 | E45: =D45+E44 -> 1.0851001 | F45: =IF(AND(E45<=0),"C",IF(E45<=0.8,"A",IF(E45<=0.95,"B","C"))) -> C | G45: =VLOOKUP(B$30:B$50,I$30:M$50,5,0) -> C | I45: tunika13 халат черная | J45: ='Юнит 05-11.01'!R41 -> 0 | K45: =J45/J$50 -> 0 | L45: =K45+L44 -> 1 | M45: =_xlfn.IFS(L45<80%,"A",L45<=95%,"B",L45>95%,"C") -> C
B46: tunika15 кимоно бирюза | C46: ='Юнит 05-11.01'!AE44 -> 0 | D46: =C46/C$50 -> 0 | E46: =D46+E45 -> 1.0851001 | F46: =IF(AND(E46<=0),"C",IF(E46<=0.8,"A",IF(E46<=0.95,"B","C"))) -> C | G46: =VLOOKUP(B$30:B$50,I$30:M$50,5,0) -> C | I46: tunika14 халат с разрезами черный | J46: ='Юнит 05-11.01'!R43 -> 0 | K46: =J46/J$50 -> 0 | L46: =K46+L45 -> 1 | M46: =_xlfn.IFS(L46<80%,"A",L46<=95%,"B",L46>95%,"C") -> C
B47: tunika16 сетка черная | C47: ='Юнит 05-11.01'!AE47 -> 0 | D47: =C47/C$50 -> 0 | E47: =D47+E46 -> 1.0851001 | F47: =IF(AND(E47<=0),"C",IF(E47<=0.8,"A",IF(E47<=0.95,"B","C"))) -> C | G47: =VLOOKUP(B$30:B$50,I$30:M$50,5,0) -> C | I47: tunika15 кимоно бирюза | J47: ='Юнит 05-11.01'!R44 -> 0 | K47: =J47/J$50 -> 0 | L47: =K47+L46 -> 1 | M47: =_xlfn.IFS(L47<80%,"A",L47<=95%,"B",L47>95%,"C") -> C
B48: tunika09 кимоно | C48: ='Юнит 05-11.01'!AE37 -> -113.88 | D48: =C48/C$50 -> -0.042550036 | E48: =D48+E47 -> 1.04255 | F48: =IF(AND(E48<=0),"C",IF(E48<=0.8,"A",IF(E48<=0.95,"B","C"))) -> C | G48: =VLOOKUP(B$30:B$50,I$30:M$50,5,0) -> C | I48: tunika16 сетка белая | J48: ='Юнит 05-11.01'!R46 -> 0 | K48: =J48/J$50 -> 0 | L48: =K48+L47 -> 1 | M48: =_xlfn.IFS(L48<80%,"A",L48<=95%,"B",L48>95%,"C") -> C
B49: tunika16 сетка белая | C49: ='Юнит 05-11.01'!AE46 -> -113.88 | D49: =C49/C$50 -> -0.042550036 | E49: =D49+E48 -> 1 | F49: =IF(AND(E49<=0),"C",IF(E49<=0.8,"A",IF(E49<=0.95,"B","C"))) -> C | G49: =VLOOKUP(B$30:B$50,I$30:M$50,5,0) -> C | I49: tunika16 сетка черная | J49: ='Юнит 05-11.01'!R47 -> 0 | K49: =J49/J$50 -> 0 | L49: =K49+L48 -> 1 | M49: =_xlfn.IFS(L49<80%,"A",L49<=95%,"B",L49>95%,"C") -> C
C50: =SUM(C30:C49) -> 2676.3784 | D50: =SUM(D30:D49) -> 1 | J50: =SUM(J30:J49) -> 2 | K50: =SUM(K30:K49) -> 1

Sheet АВС 01-04.01
B2: ОЧКИ
C3: Прибыль | D3: % прибыль | E3: Доля | F3: ABC прибыль | G3: ABC кол-во | J3: Кол-во | K3: % кол-во | L3: Доля | M3: ABC кол-во
B4: qs желтые | C4: ='Юнит 01-04.01'!AE6 -> 2714.1158 | D4: =C4/C$26 -> 0.52947686 | E4: =D4 -> 0.52947686 | F4: =IF(AND(E4<=0),"C",IF(E4<=0.8,"A",IF(E4<=0.95,"B","C"))) -> A | G4: =VLOOKUP(B$4:B$25,I$4:M$25,5,0) -> B | I4: черные с железкой классика | J4: ='Юнит 01-04.01'!R3 -> 14 | K4: =J4/J$26 -> 0.5 | L4: =K4 -> 0.5 | M4: =_xlfn.IFS(L4<80%,"A",L4<=95%,"B",L4>95%,"C") -> A
B5: lux4 | C5: ='Юнит 01-04.01'!AE20 -> 1644.69 | D5: =C5/C$26 -> 0.32085046 | E5: =D5+E4 -> 0.85032732 | F5: =IF(AND(E5<=0),"C",IF(E5<=0.8,"A",IF(E5<=0.95,"B","C"))) -> B | G5: =VLOOKUP(B$4:B$25,I$4:M$25,5,0) -> C | I5: qs желтые | J5: ='Юнит 01-04.01'!R6 -> 10 | K5: =J5/J$26 -> 0.35714286 | L5: =K5+L4 -> 0.85714286 | M5: =_xlfn.IFS(L5<80%,"A",L5<=95%,"B",L5>95%,"C") -> B
B6: qs коричневые | C6: ='Юнит 01-04.01'!AE7 -> 576.14 | D6: =C6/C$26 -> 0.11239491 | E6: =D6+E5 -> 0.96272223 | F6: =IF(AND(E6<=0),"C",IF(E6<=0.8,"A",IF(E6<=0.95,"B","C"))) -> C | G6: =VLOOKUP(B$4:B$25,I$4:M$25,5,0) -> C | I6: qs черные | J6: ='Юнит 01-04.01'!R4 -> 1 | K6: =J6/J$26 -> 0.035714286 | L6: =K6+L5 -> 0.89285714 | M6: =_xlfn.IFS(L6<80%,"A",L6<=95%,"B",L6>95%,"C") -> B
B7: qs синие | C7: ='Юнит 01-04.01'!AE5 -> 458.39 | D7: =C7/C$26 -> 0.089423928 | E7: =D7+E6 -> 1.0521462 | F7: =IF(AND(E7<=0),"C",IF(E7<=0.8,"A",IF(E7<=0.95,"B","C"))) -> C | G7: =VLOOKUP(B$4:B$25,I$4:M$25,5,0) -> B | I7: qs синие | J7: ='Юнит 01-04.01'!R5 -> 1 | K7: =J7/J$26 -> 0.035714286 | L7: =K7+L6 -> 0.92857143 | M7: =_xlfn.IFS(L7<80%,"A",L7<=95%,"B",L7>95%,"C") -> B
B8: qs черные | C8: ='Юнит 01-04.01'!AE4 -> 448.21 | D8: =C8/C$26 -> 0.087437987 | E8: =D8+E7 -> 1.1395841 | F8: =IF(AND(E8<=0),"C",IF(E8<=0.8,"A",IF(E8<=0.95,"B","C"))) -> C | G8: =VLOOKUP(B$4:B$25,I$4:M$25,5,0) -> B | I8: qs коричневые | J8: ='Юнит 01-04.01'!R7 -> 1 | K8: =J8/J$26 -> 0.035714286 | L8: =K8+L7 -> 0.96428571 | M8: =_xlfn.IFS(L8<80%,"A",L8<=95%,"B",L8>95%,"C") -> C
B9: th желтый Сул | C9: ='Юнит 01-04.01'!AE8 -> 0 | D9: =C9/C$26 -> 0 | E9: =D9+E8 -> 1.1395841 | F9: =IF(AND(E9<=0),"C",IF(E9<=0.8,"A",IF(E9<=0.95,"B","C"))) -> C | G9: =VLOOKUP(B$4:B$25,I$4:M$25,5,0) -> C | I9: lux4 | J9: ='Юнит 01-04.01'!R20 -> 1 | K9: =J9/J$26 -> 0.035714286 | L9: =K9+L8 -> 1 | M9: =_xlfn.IFS(L9<80%,"A",L9<=95%,"B",L9>95%,"C") -> C
B10: MR8854 C2 | C10: ='Юнит 01-04.01'!AE10 -> 0 | D10: =C10/C$26 -> 0 | E10: =D10+E9 -> 1.1395841 | F10: =IF(AND(E10<=0),"C",IF(E10<=0.8,"A",IF(E10<=0.95,"B","C"))) -> C | G10: =VLOOKUP(B$4:B$25,I$4:M$25,5,0) -> C | I10: th желтый Сул | J10: ='Юнит 01-04.01'!R8 -> 0 | K10: =J10/J$26 -> 0 | L10: =K10+L9 -> 1 | M10: =_xlfn.IFS(L10<80%,"A",L10<=95%,"B",L10>95%,"C") -> C
B11: MR 1819 черн | C11: ='Юнит 01-04.01'!AE11 -> 0 | D11: =C11/C$26 -> 0 | E11: =D11+E8 -> 1.1395841 | F11: =IF(AND(E11<=0),"C",IF(E11<=0.8,"A",IF(E11<=0.95,"B","C"))) -> C | G11: =VLOOKUP(B$4:B$25,I$4:M$25,5,0) -> C | I11: flip желтые Сул | J11: ='Юнит 01-04.01'!R9 -> 0 | K11: =J11/J$26 -> 0 | L11: =K11+L8 -> 0.96428571 | M11: =_xlfn.IFS(L11<80%,"A",L11<=95%,"B",L11>95%,"C") -> C
B12: MR 1819 корич | C12: ='Юнит 01-04.01'!AE12 -> 0 | D12: =C12/C$26 -> 0 | E12: =D12+E11 -> 1.1395841 | F12: =IF(AND(E12<=0),"C",IF(E12<=0.8,"A",IF(E12<=0.95,"B","C"))) -> C | G12: =VLOOKUP(B$4:B$25,I$4:M$25,5,0) -> C | I12: MR8854 C2 | J12: ='Юнит 01-04.01'!R10 -> 0 | K12: =J12/J$26 -> 0 | L12: =K12+L11 -> 0.96428571 | M12: =_xlfn.IFS(L12<80%,"A",L12<=95%,"B",L12>95%,"C") -> C
B13: MR Р1874 корич | C13: ='Юнит 01-04.01'!AE14 -> 0 | D13: =C13/C$26 -> 0 | E13: =D13+E12 -> 1.1395841 | F13: =IF(AND(E13<=0),"C",IF(E13<=0.8,"A",IF(E13<=0.95,"B","C"))) -> C | G13: =VLOOKUP(B$4:B$25,I$4:M$25,5,0) -> C | I13: MR 1819 черн | J13: ='Юнит 01-04.01'!R11 -> 0 | K13: =J13/J$26 -> 0 | L13: =K13+L12 -> 0.96428571 | M13: =_xlfn.IFS(L13<80%,"A",L13<=95%,"B",L13>95%,"C") -> C | P13: A | Q13: 0.8
B14: MR Р1886 корич | C14: ='Юнит 01-04.01'!AE16 -> 0 | D14: =C14/C$26 -> 0 | E14: =D14+E13 -> 1.1395841 | F14: =IF(AND(E14<=0),"C",IF(E14<=0.8,"A",IF(E14<=0.95,"B","C"))) -> C | G14: =VLOOKUP(B$4:B$25,I$4:M$25,5,0) -> C | I14: MR 1819 корич | J14: ='Юнит 01-04.01'!R12 -> 0 | K14: =J14/J$26 -> 0 | L14: =K14+L13 -> 0.96428571 | M14: =_xlfn.IFS(L14<80%,"A",L14<=95%,"B",L14>95%,"C") -> C | P14: B | Q14: 0.15
B15: lux1 | C15: ='Юнит 01-04.01'!AE17 -> 0 | D15: =C15/C$26 -> 0 | E15: =D15+E14 -> 1.1395841 | F15: =IF(AND(E15<=0),"C",IF(E15<=0.8,"A",IF(E15<=0.95,"B","C"))) -> C | G15: =VLOOKUP(B$4:B$25,I$4:M$25,5,0) -> C | I15: MR Р1874 черн | J15: ='Юнит 01-04.01'!R13 -> 0 | K15: =J15/J$26 -> 0 | L15: =K15+L14 -> 0.96428571 | M15: =_xlfn.IFS(L15<80%,"A",L15<=95%,"B",L15>95%,"C") -> C | P15: C | Q15: 0.05
B16: lux2 | C16: ='Юнит 01-04.01'!AE18 -> 0 | D16: =C16/C$26 -> 0 | E16: =D16+E15 -> 1.1395841 | F16: =IF(AND(E16<=0),"C",IF(E16<=0.8,"A",IF(E16<=0.95,"B","C"))) -> C | G16: =VLOOKUP(B$4:B$25,I$4:M$25,5,0) -> C | I16: MR Р1874 корич | J16: ='Юнит 01-04.01'!R14 -> 0 | K16: =J16/J$26 -> 0 | L16: =K16+L15 -> 0.96428571 | M16: =_xlfn.IFS(L16<80%,"A",L16<=95%,"B",L16>95%,"C") -> C
B17: lux3 | C17: ='Юнит 01-04.01'!AE19 -> 0 | D17: =C17/C$26 -> 0 | E17: =D17+E16 -> 1.1395841 | F17: =IF(AND(E17<=0),"C",IF(E17<=0.8,"A",IF(E17<=0.95,"B","C"))) -> C | G17: =VLOOKUP(B$4:B$25,I$4:M$25,5,0) -> C | I17: MR Р1886 черн глянец | J17: ='Юнит 01-04.01'!R15 -> 0 | K17: =J17/J$26 -> 0 | L17: =K17+L16 -> 0.96428571 | M17: =_xlfn.IFS(L17<80%,"A",L17<=95%,"B",L17>95%,"C") -> C
B18: lux5 | C18: ='Юнит 01-04.01'!AE21 -> 0 | D18: =C18/C$26 -> 0 | E18: =D18+E17 -> 1.1395841 | F18: =IF(AND(E18<=0),"C",IF(E18<=0.8,"A",IF(E18<=0.95,"B","C"))) -> C | G18: =VLOOKUP(B$4:B$25,I$4:M$25,5,0) -> C | I18: MR Р1886 корич | J18: ='Юнит 01-04.01'!R16 -> 0 | K18: =J18/J$26 -> 0 | L18: =K18+L17 -> 0.96428571 | M18: =_xlfn.IFS(L18<80%,"A",L18<=95%,"B",L18>95%,"C") -> C
B19: lux6 | C19: ='Юнит 01-04.01'!AE22 -> 0 | D19: =C19/C$26 -> 0 | E19: =D19+E18 -> 1.1395841 | F19: =IF(AND(E19<=0),"C",IF(E19<=0.8,"A",IF(E19<=0.95,"B","C"))) -> C | G19: =VLOOKUP(B$4:B$25,I$4:M$25,5,0) -> C | I19: lux1 | J19: ='Юнит 01-04.01'!R17 -> 0 | K19: =J19/J$26 -> 0 | L19: =K19+L18 -> 0.96428571 | M19: =_xlfn.IFS(L19<80%,"A",L19<=95%,"B",L19>95%,"C") -> C
B20: lux7 | C20: ='Юнит 01-04.01'!AE23 -> 0 | D20: =C20/C$26 -> 0 | E20: =D20+E19 -> 1.1395841 | F20: =IF(AND(E20<=0),"C",IF(E20<=0.8,"A",IF(E20<=0.95,"B","C"))) -> C | G20: =VLOOKUP(B$4:B$25,I$4:M$25,5,0) -> C | I20: lux2 | J20: ='Юнит 01-04.01'!R18 -> 0 | K20: =J20/J$26 -> 0 | L20: =K20+L19 -> 0.96428571 | M20: =_xlfn.IFS(L20<80%,"A",L20<=95%,"B",L20>95%,"C") -> C
B21: lux8 | C21: ='Юнит 01-04.01'!AE24 -> 0 | D21: =C21/C$26 -> 0 | E21: =D21+E20 -> 1.1395841 | F21: =IF(AND(E21<=0),"C",IF(E21<=0.8,"A",IF(E21<=0.95,"B","C"))) -> C | G21: =VLOOKUP(B$4:B$25,I$4:M$25,5,0) -> C | I21: lux3 | J21: ='Юнит 01-04.01'!R19 -> 0 | K21: =J21/J$26 -> 0 | L21: =K21+L20 -> 0.96428571 | M21: =_xlfn.IFS(L21<80%,"A",L21<=95%,"B",L21>95%,"C") -> C
B22: MR Р1874 черн | C22: ='Юнит 01-04.01'!AE13 -> -93.54 | D22: =C22/C$26 -> -0.018248029 | E22: =D22+E21 -> 1.1213361 | F22: =IF(AND(E22<=0),"C",IF(E22<=0.8,"A",IF(E22<=0.95,"B","C"))) -> C | G22: =VLOOKUP(B$4:B$25,I$4:M$25,5,0) -> C | I22: lux5 | J22: ='Юнит 01-04.01'!R21 -> 0 | K22: =J22/J$26 -> 0 | L22: =K22+L21 -> 0.96428571 | M22: =_xlfn.IFS(L22<80%,"A",L22<=95%,"B",L22>95%,"C") -> C
B23: MR Р1886 черн глянец | C23: ='Юнит 01-04.01'!AE15 -> -295.55 | D23: =C23/C$26 -> -0.057656672 | E23: =D23+E22 -> 1.0636794 | F23: =IF(AND(E23<=0),"C",IF(E23<=0.8,"A",IF(E23<=0.95,"B","C"))) -> C | G23: =VLOOKUP(B$4:B$25,I$4:M$25,5,0) -> C | I23: lux6 | J23: ='Юнит 01-04.01'!R22 -> 0 | K23: =J23/J$26 -> 0 | L23: =K23+L22 -> 0.96428571 | M23: =_xlfn.IFS(L23<80%,"A",L23<=95%,"B",L23>95%,"C") -> C
B24: flip желтые Сул | C24: ='Юнит 01-04.01'!AE9 -> -509.46505 | D24: =C24/C$26 -> -0.099387784 | E24: =D24+E23 -> 0.96429165 | F24: =IF(AND(E24<=0),"C",IF(E24<=0.8,"A",IF(E24<=0.95,"B","C"))) -> C | G24: =VLOOKUP(B$4:B$25,I$4:M$25,5,0) -> C | I24: lux7 | J24: ='Юнит 01-04.01'!R23 -> 0 | K24: =J24/J$26 -> 0 | L24: =K24+L23 -> 0.96428571 | M24: =_xlfn.IFS(L24<80%,"A",L24<=95%,"B",L24>95%,"C") -> C
B25: черные с железкой классика | C25: ='Юнит 01-04.01'!AE3 -> 183.04216 | D25: =C25/C$26 -> 0.035708346 | E25: =D25+E24 -> 1 | F25: =IF(AND(E25<=0),"C",IF(E25<=0.8,"A",IF(E25<=0.95,"B","C"))) -> C | G25: =VLOOKUP(B$4:B$25,I$4:M$25,5,0) -> A | I25: lux8 | J25: ='Юнит 01-04.01'!R24 -> 0 | K25: =J25/J$26 -> 0 | L25: =K25+L24 -> 0.96428571 | M25: =_xlfn.IFS(L25<80%,"A",L25<=95%,"B",L25>95%,"C") -> C
C26: =SUM(C4:C25) -> 5126.0329 | D26: =SUM(D4:D25) -> 1 | J26: =SUM(J4:J25) -> 28 | K26: =SUM(K4:K25) -> 1
B28: ТУНИКИ
C29: Прибыль | D29: % прибыль | E29: Доля | F29: ABC прибыль | G29: ABC кол-во | J29: Кол-во | K29: % кол-во | L29: Доля | M29: ABC кол-во
B30: tunika08 белая | C30: ='Юнит 01-04.01'!AE34 -> 1595.12 | D30: =C30/C$50 -> -1.7269284 | E30: =D30 -> -1.7269284 | F30: =IF(AND(E30<=0),"C",IF(E30<=0.8,"A",IF(E30<=0.95,"B","C"))) -> C | G30: =VLOOKUP(B$30:B$50,I$30:M$50,5,0) -> C | I30: tunika08 белая | J30: ='Юнит 01-04.01'!R34 -> 1 | K30: =J30/J$50 -> 1 | L30: =K30 -> 1 | M30: =_xlfn.IFS(L30<80%,"A",L30<=95%,"B",L30>95%,"C") -> C
B31: tunika02 оливковая с руч вышивкой | C31: ='Юнит 01-04.01'!AE28 -> 0 | D31: =C31/C$50 -> 0 | E31: =D31+E30 -> -1.7269284 | F31: =IF(AND(E31<=0),"C",IF(E31<=0.8,"A",IF(E31<=0.95,"B","C"))) -> C | G31: =VLOOKUP(B$30:B$50,I$30:M$50,5,0) -> C | I31: tunika02 оливковая с руч вышивкой | J31: ='Юнит 01-04.01'!R28 -> 0 | K31: =J31/J$50 -> 0 | L31: =K31+L30 -> 1 | M31: =_xlfn.IFS(L31<80%,"A",L31<=95%,"B",L31>95%,"C") -> C
B32: tunika03 черная распашная | C32: ='Юнит 01-04.01'!AE29 -> 0 | D32: =C32/C$50 -> 0 | E32: =D32+E31 -> -1.7269284 | F32: =IF(AND(E32<=0),"C",IF(E32<=0.8,"A",IF(E32<=0.95,"B","C"))) -> C | G32: =VLOOKUP(B$30:B$50,I$30:M$50,5,0) -> C | I32: tunika03 черная распашная | J32: ='Юнит 01-04.01'!R29 -> 0 | K32: =J32/J$50 -> 0 | L32: =K32+L31 -> 1 | M32: =_xlfn.IFS(L32<80%,"A",L32<=95%,"B",L32>95%,"C") -> C
B33: tunika05 белая распашная | C33: ='Юнит 01-04.01'!AE30 -> 0 | D33: =C33/C$50 -> 0 | E33: =D33+E32 -> -1.7269284 | F33: =IF(AND(E33<=0),"C",IF(E33<=0.8,"A",IF(E33<=0.95,"B","C"))) -> C | G33: =VLOOKUP(B$30:B$50,I$30:M$50,5,0) -> C | I33: tunika05 белая распашная | J33: ='Юнит 01-04.01'!R30 -> 0 | K33: =J33/J$50 -> 0 | L33: =K33+L32 -> 1 | M33: =_xlfn.IFS(L33<80%,"A",L33<=95%,"B",L33>95%,"C") -> C
B34: tunika06 белая | C34: ='Юнит 01-04.01'!AE31 -> 0 | D34: =C34/C$50 -> 0 | E34: =D34+E33 -> -1.7269284 | F34: =IF(AND(E34<=0),"C",IF(E34<=0.8,"A",IF(E34<=0.95,"B","C"))) -> C | G34: =VLOOKUP(B$30:B$50,I$30:M$50,5,0) -> C | I34: tunika06 белая | J34: ='Юнит 01-04.01'!R31 -> 0 | K34: =J34/J$50 -> 0 | L34: =K34+L33 -> 1 | M34: =_xlfn.IFS(L34<80%,"A",L34<=95%,"B",L34>95%,"C") -> C
B35: tunika06 черная | C35: ='Юнит 01-04.01'!AE32 -> 0 | D35: =C35/C$50 -> 0 | E35: =D35+E34 -> -1.7269284 | F35: =IF(AND(E35<=0),"C",IF(E35<=0.8,"A",IF(E35<=0.95,"B","C"))) -> C | G35: =VLOOKUP(B$30:B$50,I$30:M$50,5,0) -> C | I35: tunika06 черная | J35: ='Юнит 01-04.01'!R32 -> 0 | K35: =J35/J$50 -> 0 | L35: =K35+L34 -> 1 | M35: =_xlfn.IFS(L35<80%,"A",L35<=95%,"B",L35>95%,"C") -> C
B36: tunika07 кружево | C36: ='Юнит 01-04.01'!AE33 -> 0 | D36: =C36/C$50 -> 0 | E36: =D36+E35 -> -1.7269284 | F36: =IF(AND(E36<=0),"C",IF(E36<=0.8,"A",IF(E36<=0.95,"B","C"))) -> C | G36: =VLOOKUP(B$30:B$50,I$30:M$50,5,0) -> C | I36: tunika07 кружево | J36: ='Юнит 01-04.01'!R33 -> 0 | K36: =J36/J$50 -> 0 | L36: =K36+L35 -> 1 | M36: =_xlfn.IFS(L36<80%,"A",L36<=95%,"B",L36>95%,"C") -> C
B37: tunika08 черная | C37: ='Юнит 01-04.01'!AE35 -> 0 | D37: =C37/C$50 -> 0 | E37: =D37+E36 -> -1.7269284 | F37: =IF(AND(E37<=0),"C",IF(E37<=0.8,"A",IF(E37<=0.95,"B","C"))) -> C | G37: =VLOOKUP(B$30:B$50,I$30:M$50,5,0) -> C | I37: tunika08 черная | J37: ='Юнит 01-04.01'!R35 -> 0 | K37: =J37/J$50 -> 0 | L37: =K37+L36 -> 1 | M37: =_xlfn.IFS(L37<80%,"A",L37<=95%,"B",L37>95%,"C") -> C
B38: tunika08 зеленая | C38: ='Юнит 01-04.01'!AE36 -> 0 | D38: =C38/C$50 -> 0 | E38: =D38+E37 -> -1.7269284 | F38: =IF(AND(E38<=0),"C",IF(E38<=0.8,"A",IF(E38<=0.95,"B","C"))) -> C | G38: =VLOOKUP(B$30:B$50,I$30:M$50,5,0) -> C | I38: tunika08 зеленая | J38: ='Юнит 01-04.01'!R36 -> 0 | K38: =J38/J$50 -> 0 | L38: =K38+L37 -> 1 | M38: =_xlfn.IFS(L38<80%,"A",L38<=95%,"B",L38>95%,"C") -> C
B39: tunika09 кимоно | C39: ='Юнит 01-04.01'!AE37 -> 0 | D39: =C39/C$50 -> 0 | E39: =D39+E38 -> -1.7269284 | F39: =IF(AND(E39<=0),"C",IF(E39<=0.8,"A",IF(E39<=0.95,"B","C"))) -> C | G39: =VLOOKUP(B$30:B$50,I$30:M$50,5,0) -> C | I39: tunika09 кимоно | J39: ='Юнит 01-04.01'!R37 -> 0 | K39: =J39/J$50 -> 0 | L39: =K39+L38 -> 1 | M39: =_xlfn.IFS(L39<80%,"A",L39<=95%,"B",L39>95%,"C") -> C
B40: tunika10 кимоно ч/б | C40: ='Юнит 01-04.01'!AE38 -> 0 | D40: =C40/C$50 -> 0 | E40: =D40+E39 -> -1.7269284 | F40: =IF(AND(E40<=0),"C",IF(E40<=0.8,"A",IF(E40<=0.95,"B","C"))) -> C | G40: =VLOOKUP(B$30:B$50,I$30:M$50,5,0) -> C | I40: tunika10 кимоно ч/б | J40: ='Юнит 01-04.01'!R38 -> 0 | K40: =J40/J$50 -> 0 | L40: =K40+L39 -> 1 | M40: =_xlfn.IFS(L40<80%,"A",L40<=95%,"B",L40>95%,"C") -> C
B41: tunika11 халат зеленая | C41: ='Юнит 01-04.01'!AE39 -> 0 | D41: =C41/C$50 -> 0 | E41: =D41+E40 -> -1.7269284 | F41: =IF(AND(E41<=0),"C",IF(E41<=0.8,"A",IF(E41<=0.95,"B","C"))) -> C | G41: =VLOOKUP(B$30:B$50,I$30:M$50,5,0) -> C | I41: tunika11 халат зеленая | J41: ='Юнит 01-04.01'!R39 -> 0 | K41: =J41/J$50 -> 0 | L41: =K41+L40 -> 1 | M41: =_xlfn.IFS(L41<80%,"A",L41<=95%,"B",L41>95%,"C") -> C
B42: tunika12 халат белая | C42: ='Юнит 01-04.01'!AE40 -> 0 | D42: =C42/C$50 -> 0 | E42: =D42+E41 -> -1.7269284 | F42: =IF(AND(E42<=0),"C",IF(E42<=0.8,"A",IF(E42<=0.95,"B","C"))) -> C | G42: =VLOOKUP(B$30:B$50,I$30:M$50,5,0) -> C | I42: tunika12 халат белая | J42: ='Юнит 01-04.01'!R40 -> 0 | K42: =J42/J$50 -> 0 | L42: =K42+L41 -> 1 | M42: =_xlfn.IFS(L42<80%,"A",L42<=95%,"B",L42>95%,"C") -> C
B43: tunika13 халат черная | C43: ='Юнит 01-04.01'!AE41 -> 0 | D43: =C43/C$50 -> 0 | E43: =D43+E42 -> -1.7269284 | F43: =IF(AND(E43<=0),"C",IF(E43<=0.8,"A",IF(E43<=0.95,"B","C"))) -> C | G43: =VLOOKUP(B$30:B$50,I$30:M$50,5,0) -> C | I43: tunika13 халат черная | J43: ='Юнит 01-04.01'!R41 -> 0 | K43: =J43/J$50 -> 0 | L43: =K43+L42 -> 1 | M43: =_xlfn.IFS(L43<80%,"A",L43<=95%,"B",L43>95%,"C") -> C
B44: tunika14 халат с разрезами черный | C44: ='Юнит 01-04.01'!AE43 -> 0 | D44: =C44/C$50 -> 0 | E44: =D44+E43 -> -1.7269284 | F44: =IF(AND(E44<=0),"C",IF(E44<=0.8,"A",IF(E44<=0.95,"B","C"))) -> C | G44: =VLOOKUP(B$30:B$50,I$30:M$50,5,0) -> C | I44: tunika14 халат с разрезами белая | J44: ='Юнит 01-04.01'!R42 -> 0 | K44: =J44/J$50 -> 0 | L44: =K44+L43 -> 1 | M44: =_xlfn.IFS(L44<80%,"A",L44<=95%,"B",L44>95%,"C") -> C
B45: tunika16 сетка черная | C45: ='Юнит 01-04.01'!AE47 -> 0 | D45: =C45/C$50 -> 0 | E45: =D45+E44 -> -1.7269284 | F45: =IF(AND(E45<=0),"C",IF(E45<=0.8,"A",IF(E45<=0.95,"B","C"))) -> C | G45: =VLOOKUP(B$30:B$50,I$30:M$50,5,0) -> C | I45: tunika14 халат с разрезами черный | J45: ='Юнит 01-04.01'!R43 -> 0 | K45: =J45/J$50 -> 0 | L45: =K45+L44 -> 1 | M45: =_xlfn.IFS(L45<80%,"A",L45<=95%,"B",L45>95%,"C") -> C
B46: tunika16 сетка белая | C46: ='Юнит 01-04.01'!AE46 -> -124.26224 | D46: =C46/C$50 -> 0.13453031 | E46: =D46+E45 -> -1.5923981 | F46: =IF(AND(E46<=0),"C",IF(E46<=0.8,"A",IF(E46<=0.95,"B","C"))) -> C | G46: =VLOOKUP(B$30:B$50,I$30:M$50,5,0) -> C | I46: tunika15 кимоно бирюза | J46: ='Юнит 01-04.01'!R44 -> 0 | K46: =J46/J$50 -> 0 | L46: =K46+L45 -> 1 | M46: =_xlfn.IFS(L46<80%,"A",L46<=95%,"B",L46>95%,"C") -> C
B47: tunika15 кимоно бирюза | C47: ='Юнит 01-04.01'!AE44 -> -149.55252 | D47: =C47/C$50 -> 0.16191038 | E47: =D47+E46 -> -1.4304877 | F47: =IF(AND(E47<=0),"C",IF(E47<=0.8,"A",IF(E47<=0.95,"B","C"))) -> C | G47: =VLOOKUP(B$30:B$50,I$30:M$50,5,0) -> C | I47: tunika15 кимоно песочная | J47: ='Юнит 01-04.01'!R45 -> 0 | K47: =J47/J$50 -> 0 | L47: =K47+L46 -> 1 | M47: =_xlfn.IFS(L47<80%,"A",L47<=95%,"B",L47>95%,"C") -> C
B48: tunika14 халат с разрезами белая | C48: ='Юнит 01-04.01'!AE42 -> -976.81 | D48: =C48/C$50 -> 1.057526 | E48: =D48+E47 -> -0.37296166 | F48: =IF(AND(E48<=0),"C",IF(E48<=0.8,"A",IF(E48<=0.95,"B","C"))) -> C | G48: =VLOOKUP(B$30:B$50,I$30:M$50,5,0) -> C | I48: tunika16 сетка белая | J48: ='Юнит 01-04.01'!R46 -> 0 | K48: =J48/J$50 -> 0 | L48: =K48+L47 -> 1 | M48: =_xlfn.IFS(L48<80%,"A",L48<=95%,"B",L48>95%,"C") -> C
B49: tunika15 кимоно песочная | C49: ='Юнит 01-04.01'!AE45 -> -1268.1699 | D49: =C49/C$50 -> 1.3729617 | E49: =D49+E48 -> 1 | F49: =IF(AND(E49<=0),"C",IF(E49<=0.8,"A",IF(E49<=0.95,"B","C"))) -> C | G49: =VLOOKUP(B$30:B$50,I$30:M$50,5,0) -> C | I49: tunika16 сетка черная | J49: ='Юнит 01-04.01'!R47 -> 0 | K49: =J49/J$50 -> 0 | L49: =K49+L48 -> 1 | M49: =_xlfn.IFS(L49<80%,"A",L49<=95%,"B",L49>95%,"C") -> C
C50: =SUM(C30:C49) -> -923.67467 | D50: =SUM(D30:D49) -> 1 | J50: =SUM(J30:J49) -> 1 | K50: =SUM(K30:K49) -> 1

Sheet Юнит 01.03
B1: 01.03 | N1: число дней | O1: 1 | AA1: Примерная налогооблагаемая база | AE1: =U51/AD1 -> #DIV/0! | AG1: на 1 единицу проданного товара
B2: Артикул поставщика | C2: Остаток на 02.03 Отчет 23 | D2: В пути до клиента | E2: В пути от клиента | F2: Итого по складам ВБ | G2: Остаток на нашем складе на 02.09 | H2: Себетоимость на 1 ед на 29.09.25 | I2: Себестоимость остатков | J2: Оборачиваемость, дн | K2: Заказы, шт 01.03 | L2: Средняя цена, руб (столбец 32, AG) | M2: % выкупа за 7 дней (столбец 23, X) | N2: Скорость заказов | O2: Скорость продаж | P2: Кол-во ПРОДАЖИ | Q2: Кол-во ВОЗВРАТЫ | R2: Кол-во ПРОДАЖИ-ВОЗВРАТЫ | S2: Выручка ПРОДАЖИ | T2: Выручка ВОЗВРАТЫ | U2: Выручка с учетом согласованной скидки ПРОДАЖИ - ВОЗВРАТЫ | V2: Доля выручки, % от общего объема | W2: Себестоимость продаж | X2: Комиссия, руб | Y2: Комиссия, % | Z2: Логистика | AA2: Реклама | AB2: Хранение | AC2: Штрафы | AD2: Налог 1% | AE2: Прибыль | AG2: Выручка на 1 ед (средняя цена продажи со скидкой) | AH2: Себестоимость на 1 ед | AI2: Комиссия на 1 ед | AJ2: Логистика на 1 ед | AK2: Реклама на 1 ед | AL2: Прибыль на 1 ед | AM2: Маржинальность, % | AN2: Рентабельность, % | AP2: Прибыль с остатков
A3: 2638219896 | B3: черные с железкой классика | H3: 142.98 | I3: =C3*H3 -> 0 | N3: =K3/$O$1 -> 0 | O3: =R3/$O$1 -> 0 | P3: =SUMIFS('Отчет 23-28.02'!H:H,'Отчет 23-28.02'!D:D,"Выручка",'Отчет 23-28.02'!E:E,B3) -> 0 | Q3: =SUMIFS('Отчет 23-28.02'!H:H,'Отчет 23-28.02'!D:D,"Возврат выручки",'Отчет 23-28.02'!E:E,B3) -> 0 | R3: =P3-Q3 -> 0 | S3: =SUMIFS('Отчет 23-28.02'!P:P,'Отчет 23-28.02'!C:C,"Продажи",'Отчет 23-28.02'!E:E,B3) -> 0 | T3: =SUMIFS('Отчет 23-28.02'!P:P,'Отчет 23-28.02'!C:C,"Возвраты",'Отчет 23-28.02'!E:E,B3) -> 0 | U3: =S3+T3 -> 0 | V3: =U3/$U$51 -> #DIV/0! | W3: =R3*H3 -> 0 | X3: =-SUMIFS('Отчет 23-28.02'!P:P,'Отчет 23-28.02'!C:C,"Вознаграждение Ozon",'Отчет 23-28.02'!E:E,B3) -> 0 | Y3: =IF(U3=0,0,X3/U3) -> 0 | Z3: =-SUMIFS('Отчет 23-28.02'!P:P,'Отчет 23-28.02'!C:C,"Услуги доставки",'Отчет 23-28.02'!E:E,B3) -> 0 | AD3: =U3*1%/$AE$1 -> #DIV/0! | AE3: =U3-W3-X3-Z3-AA3-AB3-AC3-AD3 -> #DIV/0! | AG3: =IF(R3=0,0,U3/R3) -> 0 | AH3: =H3 -> 142.98 | AI3: =IF(R3=0,0,X3/R3) -> 0 | AJ3: =IF(P3=0,Z3/1,Z3/P3) -> 0 | AK3: =IF(P3=0,0,AA3/P3) -> 0 | AL3: =_xlfn.IFS(R3=0,AE3,R3<0,AE3/-R3,R3>0,AE3/R3) -> #DIV/0! | AM3: =IF(AG3=0,0,AL3/AG3) -> 0 | AN3: =IF(AH3=0,0,AL3/AH3) -> #DIV/0! | AP3: =AL3*C3 -> #DIV/0!
A4: 2638638550 | B4: qs черные | H4: 123.09 | I4: =C4*H4 -> 0 | N4: =K4/$O$1 -> 0 | O4: =R4/$O$1 -> 0 | P4: =SUMIFS('Отчет 23-28.02'!H:H,'Отчет 23-28.02'!D:D,"Выручка",'Отчет 23-28.02'!E:E,B4) -> 0 | Q4: =SUMIFS('Отчет 23-28.02'!H:H,'Отчет 23-28.02'!D:D,"Возврат выручки",'Отчет 23-28.02'!E:E,B4) -> 0 | R4: =P4-Q4 -> 0 | S4: =SUMIFS('Отчет 23-28.02'!P:P,'Отчет 23-28.02'!C:C,"Продажи",'Отчет 23-28.02'!E:E,B4) -> 0 | T4: =SUMIFS('Отчет 23-28.02'!P:P,'Отчет 23-28.02'!C:C,"Возвраты",'Отчет 23-28.02'!E:E,B4) -> 0 | U4: =S4+T4 -> 0 | V4: =U4/$U$51 -> #DIV/0! | W4: =R4*H4 -> 0 | X4: =-SUMIFS('Отчет 23-28.02'!P:P,'Отчет 23-28.02'!C:C,"Вознаграждение Ozon",'Отчет 23-28.02'!E:E,B4) -> 0 | Y4: =IF(U4=0,0,X4/U4) -> 0 | Z4: =-SUMIFS('Отчет 23-28.02'!P:P,'Отчет 23-28.02'!C:C,"Услуги доставки",'Отчет 23-28.02'!E:E,B4) -> 0 | AD4: =U4*1%/$AE$1 -> #DIV/0! | AE4: =U4-W4-X4-Z4-AA4-AB4-AC4-AD4 -> #DIV/0! | AG4: =IF(R4=0,0,U4/R4) -> 0 | AH4: =H4 -> 123.09 | AI4: =IF(R4=0,0,X4/R4) -> 0 | AJ4: =IF(P4=0,Z4/1,Z4/P4) -> 0 | AK4: =IF(P4=0,0,AA4/P4) -> 0 | AL4: {=_xlfn.IFS(R4=0,AE4,R4<0,AE4/-R4,R4>0,AE4/R4)} -> #DIV/0! | AM4: =IF(AG4=0,0,AL4/AG4) -> 0 | AN4: =IF(AH4=0,0,AL4/AH4) -> #DIV/0! | AP4: =AL4*C4 -> #DIV/0!
A5: 2638691131 | B5: qs синие | H5: 123.09 | I5: =C5*H5 -> 0 | N5: =K5/$O$1 -> 0 | O5: =R5/$O$1 -> 0 | P5: =SUMIFS('Отчет 23-28.02'!H:H,'Отчет 23-28.02'!D:D,"Выручка",'Отчет 23-28.02'!E:E,B5) -> 0 | Q5: =SUMIFS('Отчет 23-28.02'!H:H,'Отчет 23-28.02'!D:D,"Возврат выручки",'Отчет 23-28.02'!E:E,B5) -> 0 | R5: =P5-Q5 -> 0 | S5: =SUMIFS('Отчет 23-28.02'!P:P,'Отчет 23-28.02'!C:C,"Продажи",'Отчет 23-28.02'!E:E,B5) -> 0 | T5: =SUMIFS('Отчет 23-28.02'!P:P,'Отчет 23-28.02'!C:C,"Возвраты",'Отчет 23-28.02'!E:E,B5) -> 0 | U5: =S5+T5 -> 0 | V5: =U5/$U$51 -> #DIV/0! | W5: =R5*H5 -> 0 | X5: =-SUMIFS('Отчет 23-28.02'!P:P,'Отчет 23-28.02'!C:C,"Вознаграждение Ozon",'Отчет 23-28.02'!E:E,B5) -> 0 | Y5: =IF(U5=0,0,X5/U5) -> 0 | Z5: =-SUMIFS('Отчет 23-28.02'!P:P,'Отчет 23-28.02'!C:C,"Услуги доставки",'Отчет 23-28.02'!E:E,B5) -> 0 | AD5: =U5*1%/$AE$1 -> #DIV/0! | AE5: =U5-W5-X5-Z5-AA5-AB5-AC5-AD5 -> #DIV/0! | AG5: =IF(R5=0,0,U5/R5) -> 0 | AH5: =H5 -> 123.09 | AI5: =IF(R5=0,0,X5/R5) -> 0 | AJ5: =IF(P5=0,Z5/1,Z5/P5) -> 0 | AK5: =IF(P5=0,0,AA5/P5) -> 0 | AL5: {=_xlfn.IFS(R5=0,AE5,R5<0,AE5/-R5,R5>0,AE5/R5)} -> #DIV/0! | AM5: =IF(AG5=0,0,AL5/AG5) -> 0 | AN5: =IF(AH5=0,0,AL5/AH5) -> #DIV/0! | AP5: =AL5*C5 -> #DIV/0!
A6: 2638382749 | B6: qs желтые | H6: 123.09 | I6: =C6*H6 -> 0 | N6: =K6/$O$1 -> 0 | O6: =R6/$O$1 -> 0 | P6: =SUMIFS('Отчет 23-28.02'!H:H,'Отчет 23-28.02'!D:D,"Выручка",'Отчет 23-28.02'!E:E,B6) -> 0 | Q6: =SUMIFS('Отчет 23-28.02'!H:H,'Отчет 23-28.02'!D:D,"Возврат выручки",'Отчет 23-28.02'!E:E,B6) -> 0 | R6: =P6-Q6 -> 0 | S6: =SUMIFS('Отчет 23-28.02'!P:P,'Отчет 23-28.02'!C:C,"Продажи",'Отчет 23-28.02'!E:E,B6) -> 0 | T6: =SUMIFS('Отчет 23-28.02'!P:P,'Отчет 23-28.02'!C:C,"Возвраты",'Отчет 23-28.02'!E:E,B6) -> 0 | U6: =S6+T6 -> 0 | V6: =U6/$U$51 -> #DIV/0! | W6: =R6*H6 -> 0 | X6: =-SUMIFS('Отчет 23-28.02'!P:P,'Отчет 23-28.02'!C:C,"Вознаграждение Ozon",'Отчет 23-28.02'!E:E,B6) -> 0 | Y6: =IF(U6=0,0,X6/U6) -> 0 | Z6: =-SUMIFS('Отчет 23-28.02'!P:P,'Отчет 23-28.02'!C:C,"Услуги доставки",'Отчет 23-28.02'!E:E,B6) -> 0 | AD6: =U6*1%/$AE$1 -> #DIV/0! | AE6: =U6-W6-X6-Z6-AA6-AB6-AC6-AD6 -> #DIV/0! | AG6: =IF(R6=0,0,U6/R6) -> 0 | AH6: =H6 -> 123.09 | AI6: =IF(R6=0,0,X6/R6) -> 0 | AJ6: =IF(P6=0,Z6/1,Z6/P6) -> 0 | AK6: =IF(P6=0,0,AA6/P6) -> 0 | AL6: {=_xlfn.IFS(R6=0,AE6,R6<0,AE6/-R6,R6>0,AE6/R6)} -> #DIV/0! | AM6: =IF(AG6=0,0,AL6/AG6) -> 0 | AN6: =IF(AH6=0,0,AL6/AH6) -> #DIV/0! | AP6: =AL6*C6 -> #DIV/0!
A7: 2638569317 | B7: qs коричневые | H7: 117.24 | I7: =C7*H7 -> 0 | N7: =K7/$O$1 -> 0 | O7: =R7/$O$1 -> 0 | P7: =SUMIFS('Отчет 23-28.02'!H:H,'Отчет 23-28.02'!D:D,"Выручка",'Отчет 23-28.02'!E:E,B7) -> 0 | Q7: =SUMIFS('Отчет 23-28.02'!H:H,'Отчет 23-28.02'!D:D,"Возврат выручки",'Отчет 23-28.02'!E:E,B7) -> 0 | R7: =P7-Q7 -> 0 | S7: =SUMIFS('Отчет 23-28.02'!P:P,'Отчет 23-28.02'!C:C,"Продажи",'Отчет 23-28.02'!E:E,B7) -> 0 | T7: =SUMIFS('Отчет 23-28.02'!P:P,'Отчет 23-28.02'!C:C,"Возвраты",'Отчет 23-28.02'!E:E,B7) -> 0 | U7: =S7+T7 -> 0 | V7: =U7/$U$51 -> #DIV/0! | W7: =R7*H7 -> 0 | X7: =-SUMIFS('Отчет 23-28.02'!P:P,'Отчет 23-28.02'!C:C,"Вознаграждение Ozon",'Отчет 23-28.02'!E:E,B7) -> 0 | Y7: =IF(U7=0,0,X7/U7) -> 0 | Z7: =-SUMIFS('Отчет 23-28.02'!P:P,'Отчет 23-28.02'!C:C,"Услуги доставки",'Отчет 23-28.02'!E:E,B7) -> 0 | AD7: =U7*1%/$AE$1 -> #DIV/0! | AE7: =U7-W7-X7-Z7-AA7-AB7-AC7-AD7 -> #DIV/0! | AG7: =IF(R7=0,0,U7/R7) -> 0 | AH7: =H7 -> 117.24 | AI7: =IF(R7=0,0,X7/R7) -> 0 | AJ7: =IF(P7=0,Z7/1,Z7/P7) -> 0 | AK7: =IF(P7=0,0,AA7/P7) -> 0 | AL7: {=_xlfn.IFS(R7=0,AE7,R7<0,AE7/-R7,R7>0,AE7/R7)} -> #DIV/0! | AM7: =IF(AG7=0,0,AL7/AG7) -> 0 | AN7: =IF(AH7=0,0,AL7/AH7) -> #DIV/0! | AP7: =AL7*C7 -> #DIV/0!
A8: 3064334128 | B8: th желтый Сул | H8: 123 | I8: =C8*H8 -> 0 | N8: =K8/$O$1 -> 0 | O8: =R8/$O$1 -> 0 | P8: =SUMIFS('Отчет 23-28.02'!H:H,'Отчет 23-28.02'!D:D,"Выручка",'Отчет 23-28.02'!E:E,B8) -> 0 | Q8: =SUMIFS('Отчет 23-28.02'!H:H,'Отчет 23-28.02'!D:D,"Возврат выручки",'Отчет 23-28.02'!E:E,B8) -> 0 | R8: =P8-Q8 -> 0 | S8: =SUMIFS('Отчет 23-28.02'!P:P,'Отчет 23-28.02'!C:C,"Продажи",'Отчет 23-28.02'!E:E,B8) -> 0 | T8: =SUMIFS('Отчет 23-28.02'!P:P,'Отчет 23-28.02'!C:C,"Возвраты",'Отчет 23-28.02'!E:E,B8) -> 0 | U8: =S8+T8 -> 0 | V8: =U8/$U$51 -> #DIV/0! | W8: =R8*H8 -> 0 | X8: =-SUMIFS('Отчет 23-28.02'!P:P,'Отчет 23-28.02'!C:C,"Вознаграждение Ozon",'Отчет 23-28.02'!E:E,B8) -> 0 | Y8: =IF(U8=0,0,X8/U8) -> 0 | Z8: =-SUMIFS('Отчет 23-28.02'!P:P,'Отчет 23-28.02'!C:C,"Услуги доставки",'Отчет 23-28.02'!E:E,B8) -> 0 | AD8: =U8*1%/$AE$1 -> #DIV/0! | AE8: =U8-W8-X8-Z8-AA8-AB8-AC8-AD8 -> #DIV/0! | AG8: =IF(R8=0,0,U8/R8) -> 0 | AH8: =H8 -> 123 | AI8: =IF(R8=0,0,X8/R8) -> 0 | AJ8: =IF(P8=0,Z8/1,Z8/P8) -> 0 | AK8: =IF(P8=0,0,AA8/P8) -> 0 | AL8: {=_xlfn.IFS(R8=0,AE8,R8<0,AE8/-R8,R8>0,AE8/R8)} -> #DIV/0! | AM8: =IF(AG8=0,0,AL8/AG8) -> 0 | AN8: =IF(AH8=0,0,AL8/AH8) -> #DIV/0! | AP8: =AL8*C8 -> #DIV/0!
A9: 3064334311 | B9: flip желтые Сул | H9: 123 | I9: =C9*H9 -> 0 | N9: =K9/$O$1 -> 0 | O9: =R9/$O$1 -> 0 | P9: =SUMIFS('Отчет 23-28.02'!H:H,'Отчет 23-28.02'!D:D,"Выручка",'Отчет 23-28.02'!E:E,B9) -> 0 | Q9: =SUMIFS('Отчет 23-28.02'!H:H,'Отчет 23-28.02'!D:D,"Возврат выручки",'Отчет 23-28.02'!E:E,B9) -> 0 | R9: =P9-Q9 -> 0 | S9: =SUMIFS('Отчет 23-28.02'!P:P,'Отчет 23-28.02'!C:C,"Продажи",'Отчет 23-28.02'!E:E,B9) -> 0 | T9: =SUMIFS('Отчет 23-28.02'!P:P,'Отчет 23-28.02'!C:C,"Возвраты",'Отчет 23-28.02'!E:E,B9) -> 0 | U9: =S9+T9 -> 0 | V9: =U9/$U$51 -> #DIV/0! | W9: =R9*H9 -> 0 | X9: =-SUMIFS('Отчет 23-28.02'!P:P,'Отчет 23-28.02'!C:C,"Вознаграждение Ozon",'Отчет 23-28.02'!E:E,B9) -> 0 | Y9: =IF(U9=0,0,X9/U9) -> 0 | Z9: =-SUMIFS('Отчет 23-28.02'!P:P,'Отчет 23-28.02'!C:C,"Услуги доставки",'Отчет 23-28.02'!E:E,B9) -> 0 | AD9: =U9*1%/$AE$1 -> #DIV/0! | AE9: =U9-W9-X9-Z9-AA9-AB9-AC9-AD9 -> #DIV/0! | AG9: =IF(R9=0,0,U9/R9) -> 0 | AH9: =H9 -> 123 | AI9: =IF(R9=0,0,X9/R9) -> 0 | AJ9: =IF(P9=0,Z9/1,Z9/P9) -> 0 | AK9: =IF(P9=0,0,AA9/P9) -> 0 | AL9: {=_xlfn.IFS(R9=0,AE9,R9<0,AE9/-R9,R9>0,AE9/R9)} -> #DIV/0! | AM9: =IF(AG9=0,0,AL9/AG9) -> 0 | AN9: =IF(AH9=0,0,AL9/AH9) -> #DIV/0! | AP9: =AL9*C9 -> #DIV/0!
A10: 2638291563 | B10: MR8854 C2 | H10: 169.89 | I10: =C10*H10 -> 0 | N10: =K10/$O$1 -> 0 | O10: =R10/$O$1 -> 0 | P10: =SUMIFS('Отчет 23-28.02'!H:H,'Отчет 23-28.02'!D:D,"Выручка",'Отчет 23-28.02'!E:E,B10) -> 0 | Q10: =SUMIFS('Отчет 23-28.02'!H:H,'Отчет 23-28.02'!D:D,"Возврат выручки",'Отчет 23-28.02'!E:E,B10) -> 0 | R10: =P10-Q10 -> 0 | S10: =SUMIFS('Отчет 23-28.02'!P:P,'Отчет 23-28.02'!C:C,"Продажи",'Отчет 23-28.02'!E:E,B10) -> 0 | T10: =SUMIFS('Отчет 23-28.02'!P:P,'Отчет 23-28.02'!C:C,"Возвраты",'Отчет 23-28.02'!E:E,B10) -> 0 | U10: =S10+T10 -> 0 | V10: =U10/$U$51 -> #DIV/0! | W10: =R10*H10 -> 0 | X10: =-SUMIFS('Отчет 23-28.02'!P:P,'Отчет 23-28.02'!C:C,"Вознаграждение Ozon",'Отчет 23-28.02'!E:E,B10) -> 0 | Y10: =IF(U10=0,0,X10/U10) -> 0 | Z10: =-SUMIFS('Отчет 23-28.02'!P:P,'Отчет 23-28.02'!C:C,"Услуги доставки",'Отчет 23-28.02'!E:E,B10) -> 0 | AD10: =U10*1%/$AE$1 -> #DIV/0! | AE10: =U10-W10-X10-Z10-AA10-AB10-AC10-AD10 -> #DIV/0! | AG10: =IF(R10=0,0,U10/R10) -> 0 | AH10: =H10 -> 169.89 | AI10: =IF(R10=0,0,X10/R10) -> 0 | AJ10: =IF(P10=0,Z10/1,Z10/P10) -> 0 | AK10: =IF(P10=0,0,AA10/P10) -> 0 | AL10: {=_xlfn.IFS(R10=0,AE10,R10<0,AE10/-R10,R10>0,AE10/R10)} -> #DIV/0! | AM10: =IF(AG10=0,0,AL10/AG10) -> 0 | AN10: =IF(AH10=0,0,AL10/AH10) -> #DIV/0! | AP10: =AL10*C10 -> #DIV/0!
A11: 2730130733 | B11: MR 1819 черн | H11: 169.89 | I11: =C11*H11 -> 0 | N11: =K11/$O$1 -> 0 | O11: =R11/$O$1 -> 0 | P11: =SUMIFS('Отчет 23-28.02'!H:H,'Отчет 23-28.02'!D:D,"Выручка",'Отчет 23-28.02'!E:E,B11) -> 0 | Q11: =SUMIFS('Отчет 23-28.02'!H:H,'Отчет 23-28.02'!D:D,"Возврат выручки",'Отчет 23-28.02'!E:E,B11) -> 0 | R11: =P11-Q11 -> 0 | S11: =SUMIFS('Отчет 23-28.02'!P:P,'Отчет 23-28.02'!C:C,"Продажи",'Отчет 23-28.02'!E:E,B11) -> 0 | T11: =SUMIFS('Отчет 23-28.02'!P:P,'Отчет 23-28.02'!C:C,"Возвраты",'Отчет 23-28.02'!E:E,B11) -> 0 | U11: =S11+T11 -> 0 | V11: =U11/$U$51 -> #DIV/0! | W11: =R11*H11 -> 0 | X11: =-SUMIFS('Отчет 23-28.02'!P:P,'Отчет 23-28.02'!C:C,"Вознаграждение Ozon",'Отчет 23-28.02'!E:E,B11) -> 0 | Y11: =IF(U11=0,0,X11/U11) -> 0 | Z11: =-SUMIFS('Отчет 23-28.02'!P:P,'Отчет 23-28.02'!C:C,"Услуги доставки",'Отчет 23-28.02'!E:E,B11) -> 0 | AD11: =U11*1%/$AE$1 -> #DIV/0! | AE11: =U11-W11-X11-Z11-AA11-AB11-AC11-AD11 -> #DIV/0! | AG11: =IF(R11=0,0,U11/R11) -> 0 | AH11: =H11 -> 169.89 | AI11: =IF(R11=0,0,X11/R11) -> 0 | AJ11: =IF(P11=0,Z11/1,Z11/P11) -> 0 | AK11: =IF(P11=0,0,AA11/P11) -> 0 | AL11: {=_xlfn.IFS(R11=0,AE11,R11<0,AE11/-R11,R11>0,AE11/R11)} -> #DIV/0! | AM11: =IF(AG11=0,0,AL11/AG11) -> 0 | AN11: =IF(AH11=0,0,AL11/AH11) -> #DIV/0! | AP11: =AL11*C11 -> #DIV/0!
A12: 2730131249 | B12: MR 1819 корич | H12: 169.89 | I12: =C12*H12 -> 0 | N12: =K12/$O$1 -> 0 | O12: =R12/$O$1 -> 0 | P12: =SUMIFS('Отчет 23-28.02'!H:H,'Отчет 23-28.02'!D:D,"Выручка",'Отчет 23-28.02'!E:E,B12) -> 0 | Q12: =SUMIFS('Отчет 23-28.02'!H:H,'Отчет 23-28.02'!D:D,"Возврат выручки",'Отчет 23-28.02'!E:E,B12) -> 0 | R12: =P12-Q12 -> 0 | S12: =SUMIFS('Отчет 23-28.02'!P:P,'Отчет 23-28.02'!C:C,"Продажи",'Отчет 23-28.02'!E:E,B12) -> 0 | T12: =SUMIFS('Отчет 23-28.02'!P:P,'Отчет 23-28.02'!C:C,"Возвраты",'Отчет 23-28.02'!E:E,B12) -> 0 | U12: =S12+T12 -> 0 | V12: =U12/$U$51 -> #DIV/0! | W12: =R12*H12 -> 0 | X12: =-SUMIFS('Отчет 23-28.02'!P:P,'Отчет 23-28.02'!C:C,"Вознаграждение Ozon",'Отчет 23-28.02'!E:E,B12) -> 0 | Y12: =IF(U12=0,0,X12/U12) -> 0 | Z12: =-SUMIFS('Отчет 23-28.02'!P:P,'Отчет 23-28.02'!C:C,"Услуги доставки",'Отчет 23-28.02'!E:E,B12) -> 0 | AD12: =U12*1%/$AE$1 -> #DIV/0! | AE12: =U12-W12-X12-Z12-AA12-AB12-AC12-AD12 -> #DIV/0! | AG12: =IF(R12=0,0,U12/R12) -> 0 | AH12: =H12 -> 169.89 | AI12: =IF(R12=0,0,X12/R12) -> 0 | AJ12: =IF(P12=0,Z12/1,Z12/P12) -> 0 | AK12: =IF(P12=0,0,AA12/P12) -> 0 | AL12: {=_xlfn.IFS(R12=0,AE12,R12<0,AE12/-R12,R12>0,AE12/R12)} -> #DIV/0! | AM12: =IF(AG12=0,0,AL12/AG12) -> 0 | AN12: =IF(AH12=0,0,AL12/AH12) -> #DIV/0! | AP12: =AL12*C12 -> #DIV/0!
A13: 2730130553 | B13: MR Р1874 черн | H13: 169.89 | I13: =C13*H13 -> 0 | N13: =K13/$O$1 -> 0 | O13: =R13/$O$1 -> 0 | P13: =SUMIFS('Отчет 23-28.02'!H:H,'Отчет 23-28.02'!D:D,"Выручка",'Отчет 23-28.02'!E:E,B13) -> 0 | Q13: =SUMIFS('Отчет 23-28.02'!H:H,'Отчет 23-28.02'!D:D,"Возврат выручки",'Отчет 23-28.02'!E:E,B13) -> 0 | R13: =P13-Q13 -> 0 | S13: =SUMIFS('Отчет 23-28.02'!P:P,'Отчет 23-28.02'!C:C,"Продажи",'Отчет 23-28.02'!E:E,B13) -> 0 | T13: =SUMIFS('Отчет 23-28.02'!P:P,'Отчет 23-28.02'!C:C,"Возвраты",'Отчет 23-28.02'!E:E,B13) -> 0 | U13: =S13+T13 -> 0 | V13: =U13/$U$51 -> #DIV/0! | W13: =R13*H13 -> 0 | X13: =-SUMIFS('Отчет 23-28.02'!P:P,'Отчет 23-28.02'!C:C,"Вознаграждение Ozon",'Отчет 23-28.02'!E:E,B13) -> 0 | Y13: =IF(U13=0,0,X13/U13) -> 0 | Z13: =-SUMIFS('Отчет 23-28.02'!P:P,'Отчет 23-28.02'!C:C,"Услуги доставки",'Отчет 23-28.02'!E:E,B13) -> 0 | AD13: =U13*1%/$AE$1 -> #DIV/0! | AE13: =U13-W13-X13-Z13-AA13-AB13-AC13-AD13 -> #DIV/0! | AG13: =IF(R13=0,0,U13/R13) -> 0 | AH13: =H13 -> 169.89 | AI13: =IF(R13=0,0,X13/R13) -> 0 | AJ13: =IF(P13=0,Z13/1,Z13/P13) -> 0 | AK13: =IF(P13=0,0,AA13/P13) -> 0 | AL13: {=_xlfn.IFS(R13=0,AE13,R13<0,AE13/-R13,R13>0,AE13/R13)} -> #DIV/0! | AM13: =IF(AG13=0,0,AL13/AG13) -> 0 | AN13: =IF(AH13=0,0,AL13/AH13) -> #DIV/0! | AP13: =AL13*C13 -> #DIV/0!
A14: 2730129638 | B14: MR Р1874 корич | H14: 169.89 | I14: =C14*H14 -> 0 | N14: =K14/$O$1 -> 0 | O14: =R14/$O$1 -> 0 | P14: =SUMIFS('Отчет 23-28.02'!H:H,'Отчет 23-28.02'!D:D,"Выручка",'Отчет 23-28.02'!E:E,B14) -> 0 | Q14: =SUMIFS('Отчет 23-28.02'!H:H,'Отчет 23-28.02'!D:D,"Возврат выручки",'Отчет 23-28.02'!E:E,B14) -> 0 | R14: =P14-Q14 -> 0 | S14: =SUMIFS('Отчет 23-28.02'!P:P,'Отчет 23-28.02'!C:C,"Продажи",'Отчет 23-28.02'!E:E,B14) -> 0 | T14: =SUMIFS('Отчет 23-28.02'!P:P,'Отчет 23-28.02'!C:C,"Возвраты",'Отчет 23-28.02'!E:E,B14) -> 0 | U14: =S14+T14 -> 0 | V14: =U14/$U$51 -> #DIV/0! | W14: =R14*H14 -> 0 | X14: =-SUMIFS('Отчет 23-28.02'!P:P,'Отчет 23-28.02'!C:C,"Вознаграждение Ozon",'Отчет 23-28.02'!E:E,B14) -> 0 | Y14: =IF(U14=0,0,X14/U14) -> 0 | Z14: =-SUMIFS('Отчет 23-28.02'!P:P,'Отчет 23-28.02'!C:C,"Услуги доставки",'Отчет 23-28.02'!E:E,B14) -> 0 | AD14: =U14*1%/$AE$1 -> #DIV/0! | AE14: =U14-W14-X14-Z14-AA14-AB14-AC14-AD14 -> #DIV/0! | AG14: =IF(R14=0,0,U14/R14) -> 0 | AH14: =H14 -> 169.89 | AI14: =IF(R14=0,0,X14/R14) -> 0 | AJ14: =IF(P14=0,Z14/1,Z14/P14) -> 0 | AK14: =IF(P14=0,0,AA14/P14) -> 0 | AL14: {=_xlfn.IFS(R14=0,AE14,R14<0,AE14/-R14,R14>0,AE14/R14)} -> #DIV/0! | AM14: =IF(AG14=0,0,AL14/AG14) -> 0 | AN14: =IF(AH14=0,0,AL14/AH14) -> #DIV/0! | AP14: =AL14*C14 -> #DIV/0!
A15: 2730130141 | B15: MR Р1886 черн глянец | H15: 169.89 | I15: =C15*H15 -> 0 | N15: =K15/$O$1 -> 0 | O15: =R15/$O$1 -> 0 | P15: =SUMIFS('Отчет 23-28.02'!H:H,'Отчет 23-28.02'!D:D,"Выручка",'Отчет 23-28.02'!E:E,B15) -> 0 | Q15: =SUMIFS('Отчет 23-28.02'!H:H,'Отчет 23-28.02'!D:D,"Возврат выручки",'Отчет 23-28.02'!E:E,B15) -> 0 | R15: =P15-Q15 -> 0 | S15: =SUMIFS('Отчет 23-28.02'!P:P,'Отчет 23-28.02'!C:C,"Продажи",'Отчет 23-28.02'!E:E,B15) -> 0 | T15: =SUMIFS('Отчет 23-28.02'!P:P,'Отчет 23-28.02'!C:C,"Возвраты",'Отчет 23-28.02'!E:E,B15) -> 0 | U15: =S15+T15 -> 0 | V15: =U15/$U$51 -> #DIV/0! | W15: =R15*H15 -> 0 | X15: =-SUMIFS('Отчет 23-28.02'!P:P,'Отчет 23-28.02'!C:C,"Вознаграждение Ozon",'Отчет 23-28.02'!E:E,B15) -> 0 | Y15: =IF(U15=0,0,X15/U15) -> 0 | Z15: =-SUMIFS('Отчет 23-28.02'!P:P,'Отчет 23-28.02'!C:C,"Услуги доставки",'Отчет 23-28.02'!E:E,B15) -> 0 | AD15: =U15*1%/$AE$1 -> #DIV/0! | AE15: =U15-W15-X15-Z15-AA15-AB15-AC15-AD15 -> #DIV/0! | AG15: =IF(R15=0,0,U15/R15) -> 0 | AH15: =H15 -> 169.89 | AI15: =IF(R15=0,0,X15/R15) -> 0 | AJ15: =IF(P15=0,Z15/1,Z15/P15) -> 0 | AK15: =IF(P15=0,0,AA15/P15) -> 0 | AL15: {=_xlfn.IFS(R15=0,AE15,R15<0,AE15/-R15,R15>0,AE15/R15)} -> #DIV/0! | AM15: =IF(AG15=0,0,AL15/AG15) -> 0 | AN15: =IF(AH15=0,0,AL15/AH15) -> #DIV/0! | AP15: =AL15*C15 -> #DIV/0!
... A24: 2807226146 | B24: lux8 | H24: 991.12 | I24: =C24*H24 -> 0 | N24: =K24/$O$1 -> 0 | O24: =R24/$O$1 -> 0 | P24: =SUMIFS('Отчет 23-28.02'!H:H,'Отчет 23-28.02'!D:D,"Выручка",'Отчет 23-28.02'!E:E,B24) -> 0 | Q24: =SUMIFS('Отчет 23-28.02'!H:H,'Отчет 23-28.02'!D:D,"Возврат выручки",'Отчет 23-28.02'!E:E,B24) -> 0 | R24: =P24-Q24 -> 0 | S24: =SUMIFS('Отчет 23-28.02'!P:P,'Отчет 23-28.02'!C:C,"Продажи",'Отчет 23-28.02'!E:E,B24) -> 0 | T24: =SUMIFS('Отчет 23-28.02'!P:P,'Отчет 23-28.02'!C:C,"Возвраты",'Отчет 23-28.02'!E:E,B24) -> 0 | U24: =S24+T24 -> 0 | V24: =U24/$U$51 -> #DIV/0! | W24: =R24*H24 -> 0 | X24: =-SUMIFS('Отчет 23-28.02'!P:P,'Отчет 23-28.02'!C:C,"Вознаграждение Ozon",'Отчет 23-28.02'!E:E,B24) -> 0 | Y24: =IF(U24=0,0,X24/U24) -> 0 | Z24: =-SUMIFS('Отчет 23-28.02'!P:P,'Отчет 23-28.02'!C:C,"Услуги доставки",'Отчет 23-28.02'!E:E,B24) -> 0 | AD24: =U24*1%/$AE$1 -> #DIV/0! | AE24: =U24-W24-X24-Z24-AA24-AB24-AC24-AD24 -> #DIV/0! | AG24: =IF(R24=0,0,U24/R24) -> 0 | AH24: =H24 -> 991.12 | AI24: =IF(R24=0,0,X24/R24) -> 0 | AJ24: =IF(P24=0,Z24/1,Z24/P24) -> 0 | AK24: =IF(P24=0,0,AA24/P24) -> 0 | AL24: {=_xlfn.IFS(R24=0,AE24,R24<0,AE24/-R24,R24>0,AE24/R24)} -> #DIV/0! | AM24: =IF(AG24=0,0,AL24/AG24) -> 0 | AN24: =IF(AH24=0,0,AL24/AH24) -> #DIV/0! | AP24: =AL24*C24 -> #DIV/0!
AG25: =AVERAGEIF(AG3:AG24,"<>0",AG3:AG24) -> #DIV/0! | AH25: =AVERAGEIF(AH3:AH24,"<>0",AH3:AH24) -> 447.87636 | AI25: =AVERAGEIF(AI3:AI24,"<>0",AI3:AI24) -> #DIV/0! | AJ25: =AVERAGEIF(AJ3:AJ24,"<>0",AJ3:AJ24) -> #DIV/0! | AK25: =AVERAGEIF(AK3:AK24,"<>0",AK3:AK24) -> #DIV/0! | AL25: =AVERAGEIF(AL3:AL24,"<>0",AL3:AL24) -> #DIV/0! | AM25: =AVERAGEIF(AM3:AM24,"<>0",AM3:AM24) -> #DIV/0! | AN25: =AVERAGEIF(AN3:AN24,"<>0",AN3:AN24) -> #DIV/0!
A26: Итого очки | C26: =SUM(C3:C24) -> 0 | E26: 108496 | F26: 597 | G26: 295 | I26: =SUM(I3:I24) -> 0 | K26: =SUM(K3:K24) -> 0 | P26: =SUM(P3:P24) -> 0 | Q26: =SUM(Q3:Q24) -> 0 | R26: =SUM(R3:R24) -> 0 | S26: =SUM(S3:S24) -> 0 | T26: =SUM(T3:T24) -> 0 | U26: =SUM(U3:U24) -> 0 | V26: =SUM(V3:V24) -> #DIV/0! | W26: =SUM(W3:W24) -> 0 | X26: =SUM(X3:X24) -> 0 | Y26: =IF(U26=0,0,X26/U26) -> 0 | Z26: =SUM(Z3:Z24) -> 0 | AA26: =IFERROR(P26*AA51/P51,0) -> 0 | AB26: =SUM(AB3:AB24) -> 0 | AC26: =SUM(AC3:AC24) -> 0 | AD26: =SUM(AD3:AD24) -> #DIV/0! | AE26: =SUM(AE3:AE24) -> #DIV/0! | AP26: =SUM(AP3:AP24) -> #DIV/0! | AZ26: 18592777
AA27: =SUM(AA3:AA24) -> 0
A28: 2774708536 | B28: tunika02 оливковая с руч вышивкой | H28: 672 | I28: =C28*H28 -> 0 | N28: =K28/$O$1 -> 0 | O28: =R28/$O$1 -> 0 | P28: =SUMIFS('Отчет 23-28.02'!H:H,'Отчет 23-28.02'!D:D,"Выручка",'Отчет 23-28.02'!E:E,B28) -> 0 | Q28: =SUMIFS('Отчет 23-28.02'!H:H,'Отчет 23-28.02'!D:D,"Возврат выручки",'Отчет 23-28.02'!E:E,B28) -> 0 | R28: =P28-Q28 -> 0 | S28: =SUMIFS('Отчет 23-28.02'!P:P,'Отчет 23-28.02'!C:C,"Продажи",'Отчет 23-28.02'!E:E,B28) -> 0 | T28: =SUMIFS('Отчет 23-28.02'!P:P,'Отчет 23-28.02'!C:C,"Возвраты",'Отчет 23-28.02'!E:E,B28) -> 0 | U28: =S28+T28 -> 0 | V28: =U28/$U$51 -> #DIV/0! | W28: =R28*H28 -> 0 | X28: =-SUMIFS('Отчет 23-28.02'!P:P,'Отчет 23-28.02'!C:C,"Вознаграждение Ozon",'Отчет 23-28.02'!E:E,B28) -> 0 | Y28: =IF(U28=0,0,X28/U28) -> 0 | Z28: =-SUMIFS('Отчет 23-28.02'!P:P,'Отчет 23-28.02'!C:C,"Услуги доставки",'Отчет 23-28.02'!E:E,B28) -> 0 | AD28: =U28*1%/$AE$1 -> #DIV/0! | AE28: =U28-W28-X28-Z28-AA28-AB28-AC28-AD28 -> #DIV/0! | AG28: =IF(R28=0,0,U28/R28) -> 0 | AH28: =H28 -> 672 | AI28: =IF(R28=0,0,X28/R28) -> 0 | AJ28: =IF(P28=0,Z28/1,Z28/P28) -> 0 | AK28: =IF(P28=0,0,AA28/P28) -> 0 | AL28: {=_xlfn.IFS(R28=0,AE28,R28<0,AE28/-R28,R28>0,AE28/R28)} -> #DIV/0! | AM28: =IF(AG28=0,0,AL28/AG28) -> 0 | AN28: =IF(AH28=0,0,AL28/AH28) -> #DIV/0! | AP28: =AL28*C28 -> #DIV/0!
A29: 2774708622 | B29: tunika03 черная распашная | H29: 627 | I29: =C29*H29 -> 0 | N29: =K29/$O$1 -> 0 | O29: =R29/$O$1 -> 0 | P29: =SUMIFS('Отчет 23-28.02'!H:H,'Отчет 23-28.02'!D:D,"Выручка",'Отчет 23-28.02'!E:E,B29) -> 0 | Q29: =SUMIFS('Отчет 23-28.02'!H:H,'Отчет 23-28.02'!D:D,"Возврат выручки",'Отчет 23-28.02'!E:E,B29) -> 0 | R29: =P29-Q29 -> 0 | S29: =SUMIFS('Отчет 23-28.02'!P:P,'Отчет 23-28.02'!C:C,"Продажи",'Отчет 23-28.02'!E:E,B29) -> 0 | T29: =SUMIFS('Отчет 23-28.02'!P:P,'Отчет 23-28.02'!C:C,"Возвраты",'Отчет 23-28.02'!E:E,B29) -> 0 | U29: =S29+T29 -> 0 | V29: =U29/$U$51 -> #DIV/0! | W29: =R29*H29 -> 0 | X29: =-SUMIFS('Отчет 23-28.02'!P:P,'Отчет 23-28.02'!C:C,"Вознаграждение Ozon",'Отчет 23-28.02'!E:E,B29) -> 0 | Y29: =IF(U29=0,0,X29/U29) -> 0 | Z29: =-SUMIFS('Отчет 23-28.02'!P:P,'Отчет 23-28.02'!C:C,"Услуги доставки",'Отчет 23-28.02'!E:E,B29) -> 0 | AD29: =U29*1%/$AE$1 -> #DIV/0! | AE29: =U29-W29-X29-Z29-AA29-AB29-AC29-AD29 -> #DIV/0! | AG29: =IF(R29=0,0,U29/R29) -> 0 | AH29: =H29 -> 627 | AI29: =IF(R29=0,0,X29/R29) -> 0 | AJ29: =IF(P29=0,Z29/1,Z29/P29) -> 0 | AK29: =IF(P29=0,0,AA29/P29) -> 0 | AL29: {=_xlfn.IFS(R29=0,AE29,R29<0,AE29/-R29,R29>0,AE29/R29)} -> #DIV/0! | AM29: =IF(AG29=0,0,AL29/AG29) -> 0 | AN29: =IF(AH29=0,0,AL29/AH29) -> #DIV/0! | AP29: =AL29*C29 -> #DIV/0!
A30: 2774709606 | B30: tunika05 белая распашная | H30: 627 | I30: =C30*H30 -> 0 | N30: =K30/$O$1 -> 0 | O30: =R30/$O$1 -> 0 | P30: =SUMIFS('Отчет 23-28.02'!H:H,'Отчет 23-28.02'!D:D,"Выручка",'Отчет 23-28.02'!E:E,B30) -> 0 | Q30: =SUMIFS('Отчет 23-28.02'!H:H,'Отчет 23-28.02'!D:D,"Возврат выручки",'Отчет 23-28.02'!E:E,B30) -> 0 | R30: =P30-Q30 -> 0 | S30: =SUMIFS('Отчет 23-28.02'!P:P,'Отчет 23-28.02'!C:C,"Продажи",'Отчет 23-28.02'!E:E,B30) -> 0 | T30: =SUMIFS('Отчет 23-28.02'!P:P,'Отчет 23-28.02'!C:C,"Возвраты",'Отчет 23-28.02'!E:E,B30) -> 0 | U30: =S30+T30 -> 0 | V30: =U30/$U$51 -> #DIV/0! | W30: =R30*H30 -> 0 | X30: =-SUMIFS('Отчет 23-28.02'!P:P,'Отчет 23-28.02'!C:C,"Вознаграждение Ozon",'Отчет 23-28.02'!E:E,B30) -> 0 | Y30: =IF(U30=0,0,X30/U30) -> 0 | Z30: =-SUMIFS('Отчет 23-28.02'!P:P,'Отчет 23-28.02'!C:C,"Услуги доставки",'Отчет 23-28.02'!E:E,B30) -> 0 | AD30: =U30*1%/$AE$1 -> #DIV/0! | AE30: =U30-W30-X30-Z30-AA30-AB30-AC30-AD30 -> #DIV/0! | AG30: =IF(R30=0,0,U30/R30) -> 0 | AH30: =H30 -> 627 | AI30: =IF(R30=0,0,X30/R30) -> 0 | AJ30: =IF(P30=0,Z30/1,Z30/P30) -> 0 | AK30: =IF(P30=0,0,AA30/P30) -> 0 | AL30: {=_xlfn.IFS(R30=0,AE30,R30<0,AE30/-R30,R30>0,AE30/R30)} -> #DIV/0! | AM30: =IF(AG30=0,0,AL30/AG30) -> 0 | AN30: =IF(AH30=0,0,AL30/AH30) -> #DIV/0! | AP30: =AL30*C30 -> #DIV/0!
A31: 2774720465 | B31: tunika06 белая | H31: 567 | I31: =C31*H31 -> 0 | N31: =K31/$O$1 -> 0 | O31: =R31/$O$1 -> 0 | P31: =SUMIFS('Отчет 23-28.02'!H:H,'Отчет 23-28.02'!D:D,"Выручка",'Отчет 23-28.02'!E:E,B31) -> 0 | Q31: =SUMIFS('Отчет 23-28.02'!H:H,'Отчет 23-28.02'!D:D,"Возврат выручки",'Отчет 23-28.02'!E:E,B31) -> 0 | R31: =P31-Q31 -> 0 | S31: =SUMIFS('Отчет 23-28.02'!P:P,'Отчет 23-28.02'!C:C,"Продажи",'Отчет 23-28.02'!E:E,B31) -> 0 | T31: =SUMIFS('Отчет 23-28.02'!P:P,'Отчет 23-28.02'!C:C,"Возвраты",'Отчет 23-28.02'!E:E,B31) -> 0 | U31: =S31+T31 -> 0 | V31: =U31/$U$51 -> #DIV/0! | W31: =R31*H31 -> 0 | X31: =-SUMIFS('Отчет 23-28.02'!P:P,'Отчет 23-28.02'!C:C,"Вознаграждение Ozon",'Отчет 23-28.02'!E:E,B31) -> 0 | Y31: =IF(U31=0,0,X31/U31) -> 0 | Z31: =-SUMIFS('Отчет 23-28.02'!P:P,'Отчет 23-28.02'!C:C,"Услуги доставки",'Отчет 23-28.02'!E:E,B31) -> 0 | AD31: =U31*1%/$AE$1 -> #DIV/0! | AE31: =U31-W31-X31-Z31-AA31-AB31-AC31-AD31 -> #DIV/0! | AG31: =IF(R31=0,0,U31/R31) -> 0 | AH31: =H31 -> 567 | AI31: =IF(R31=0,0,X31/R31) -> 0 | AJ31: =IF(P31=0,Z31/1,Z31/P31) -> 0 | AK31: =IF(P31=0,0,AA31/P31) -> 0 | AL31: {=_xlfn.IFS(R31=0,AE31,R31<0,AE31/-R31,R31>0,AE31/R31)} -> #DIV/0! | AM31: =IF(AG31=0,0,AL31/AG31) -> 0 | AN31: =IF(AH31=0,0,AL31/AH31) -> #DIV/0! | AP31: =AL31*C31 -> #DIV/0!
A32: 2774718470 | B32: tunika06 черная | H32: 567 | I32: =C32*H32 -> 0 | N32: =K32/$O$1 -> 0 | O32: =R32/$O$1 -> 0 | P32: =SUMIFS('Отчет 23-28.02'!H:H,'Отчет 23-28.02'!D:D,"Выручка",'Отчет 23-28.02'!E:E,B32) -> 0 | Q32: =SUMIFS('Отчет 23-28.02'!H:H,'Отчет 23-28.02'!D:D,"Возврат выручки",'Отчет 23-28.02'!E:E,B32) -> 0 | R32: =P32-Q32 -> 0 | S32: =SUMIFS('Отчет 23-28.02'!P:P,'Отчет 23-28.02'!C:C,"Продажи",'Отчет 23-28.02'!E:E,B32) -> 0 | T32: =SUMIFS('Отчет 23-28.02'!P:P,'Отчет 23-28.02'!C:C,"Возвраты",'Отчет 23-28.02'!E:E,B32) -> 0 | U32: =S32+T32 -> 0 | V32: =U32/$U$51 -> #DIV/0! | W32: =R32*H32 -> 0 | X32: =-SUMIFS('Отчет 23-28.02'!P:P,'Отчет 23-28.02'!C:C,"Вознаграждение Ozon",'Отчет 23-28.02'!E:E,B32) -> 0 | Y32: =IF(U32=0,0,X32/U32) -> 0 | Z32: =-SUMIFS('Отчет 23-28.02'!P:P,'Отчет 23-28.02'!C:C,"Услуги доставки",'Отчет 23-28.02'!E:E,B32) -> 0 | AD32: =U32*1%/$AE$1 -> #DIV/0! | AE32: =U32-W32-X32-Z32-AA32-AB32-AC32-AD32 -> #DIV/0! | AG32: =IF(R32=0,0,U32/R32) -> 0 | AH32: =H32 -> 567 | AI32: =IF(R32=0,0,X32/R32) -> 0 | AJ32: =IF(P32=0,Z32/1,Z32/P32) -> 0 | AK32: =IF(P32=0,0,AA32/P32) -> 0 | AL32: {=_xlfn.IFS(R32=0,AE32,R32<0,AE32/-R32,R32>0,AE32/R32)} -> #DIV/0! | AM32: =IF(AG32=0,0,AL32/AG32) -> 0 | AN32: =IF(AH32=0,0,AL32/AH32) -> #DIV/0! | AP32: =AL32*C32 -> #DIV/0!
A33: 2774719022 | B33: tunika07 кружево | H33: 657 | I33: =C33*H33 -> 0 | N33: =K33/$O$1 -> 0 | O33: =R33/$O$1 -> 0 | P33: =SUMIFS('Отчет 23-28.02'!H:H,'Отчет 23-28.02'!D:D,"Выручка",'Отчет 23-28.02'!E:E,B33) -> 0 | Q33: =SUMIFS('Отчет 23-28.02'!H:H,'Отчет 23-28.02'!D:D,"Возврат выручки",'Отчет 23-28.02'!E:E,B33) -> 0 | R33: =P33-Q33 -> 0 | S33: =SUMIFS('Отчет 23-28.02'!P:P,'Отчет 23-28.02'!C:C,"Продажи",'Отчет 23-28.02'!E:E,B33) -> 0 | T33: =SUMIFS('Отчет 23-28.02'!P:P,'Отчет 23-28.02'!C:C,"Возвраты",'Отчет 23-28.02'!E:E,B33) -> 0 | U33: =S33+T33 -> 0 | V33: =U33/$U$51 -> #DIV/0! | W33: =R33*H33 -> 0 | X33: =-SUMIFS('Отчет 23-28.02'!P:P,'Отчет 23-28.02'!C:C,"Вознаграждение Ozon",'Отчет 23-28.02'!E:E,B33) -> 0 | Y33: =IF(U33=0,0,X33/U33) -> 0 | Z33: =-SUMIFS('Отчет 23-28.02'!P:P,'Отчет 23-28.02'!C:C,"Услуги доставки",'Отчет 23-28.02'!E:E,B33) -> 0 | AD33: =U33*1%/$AE$1 -> #DIV/0! | AE33: =U33-W33-X33-Z33-AA33-AB33-AC33-AD33 -> #DIV/0! | AG33: =IF(R33=0,0,U33/R33) -> 0 | AH33: =H33 -> 657 | AI33: =IF(R33=0,0,X33/R33) -> 0 | AJ33: =IF(P33=0,Z33/1,Z33/P33) -> 0 | AK33: =IF(P33=0,0,AA33/P33) -> 0 | AL33: {=_xlfn.IFS(R33=0,AE33,R33<0,AE33/-R33,R33>0,AE33/R33)} -> #DIV/0! | AM33: =IF(AG33=0,0,AL33/AG33) -> 0 | AN33: =IF(AH33=0,0,AL33/AH33) -> #DIV/0! | AP33: =AL33*C33 -> #DIV/0!
A34: 2774719501 | B34: tunika08 белая | H34: 597 | I34: =C34*H34 -> 0 | N34: =K34/$O$1 -> 0 | O34: =R34/$O$1 -> 0 | P34: =SUMIFS('Отчет 23-28.02'!H:H,'Отчет 23-28.02'!D:D,"Выручка",'Отчет 23-28.02'!E:E,B34) -> 0 | Q34: =SUMIFS('Отчет 23-28.02'!H:H,'Отчет 23-28.02'!D:D,"Возврат выручки",'Отчет 23-28.02'!E:E,B34) -> 0 | R34: =P34-Q34 -> 0 | S34: =SUMIFS('Отчет 23-28.02'!P:P,'Отчет 23-28.02'!C:C,"Продажи",'Отчет 23-28.02'!E:E,B34) -> 0 | T34: =SUMIFS('Отчет 23-28.02'!P:P,'Отчет 23-28.02'!C:C,"Возвраты",'Отчет 23-28.02'!E:E,B34) -> 0 | U34: =S34+T34 -> 0 | V34: =U34/$U$51 -> #DIV/0! | W34: =R34*H34 -> 0 | X34: =-SUMIFS('Отчет 23-28.02'!P:P,'Отчет 23-28.02'!C:C,"Вознаграждение Ozon",'Отчет 23-28.02'!E:E,B34) -> 0 | Y34: =IF(U34=0,0,X34/U34) -> 0 | Z34: =-SUMIFS('Отчет 23-28.02'!P:P,'Отчет 23-28.02'!C:C,"Услуги доставки",'Отчет 23-28.02'!E:E,B34) -> 0 | AD34: =U34*1%/$AE$1 -> #DIV/0! | AE34: =U34-W34-X34-Z34-AA34-AB34-AC34-AD34 -> #DIV/0! | AG34: =IF(R34=0,0,U34/R34) -> 0 | AH34: =H34 -> 597 | AI34: =IF(R34=0,0,X34/R34) -> 0 | AJ34: =IF(P34=0,Z34/1,Z34/P34) -> 0 | AK34: =IF(P34=0,0,AA34/P34) -> 0 | AL34: {=_xlfn.IFS(R34=0,AE34,R34<0,AE34/-R34,R34>0,AE34/R34)} -> #DIV/0! | AM34: =IF(AG34=0,0,AL34/AG34) -> 0 | AN34: =IF(AH34=0,0,AL34/AH34) -> #DIV/0! | AP34: =AL34*C34 -> #DIV/0!
A35: 2774714412 | B35: tunika08 черная | H35: 552 | I35: =C35*H35 -> 0 | N35: =K35/$O$1 -> 0 | O35: =R35/$O$1 -> 0 | P35: =SUMIFS('Отчет 23-28.02'!H:H,'Отчет 23-28.02'!D:D,"Выручка",'Отчет 23-28.02'!E:E,B35) -> 0 | Q35: =SUMIFS('Отчет 23-28.02'!H:H,'Отчет 23-28.02'!D:D,"Возврат выручки",'Отчет 23-28.02'!E:E,B35) -> 0 | R35: =P35-Q35 -> 0 | S35: =SUMIFS('Отчет 23-28.02'!P:P,'Отчет 23-28.02'!C:C,"Продажи",'Отчет 23-28.02'!E:E,B35) -> 0 | T35: =SUMIFS('Отчет 23-28.02'!P:P,'Отчет 23-28.02'!C:C,"Возвраты",'Отчет 23-28.02'!E:E,B35) -> 0 | U35: =S35+T35 -> 0 | V35: =U35/$U$51 -> #DIV/0! | W35: =R35*H35 -> 0 | X35: =-SUMIFS('Отчет 23-28.02'!P:P,'Отчет 23-28.02'!C:C,"Вознаграждение Ozon",'Отчет 23-28.02'!E:E,B35) -> 0 | Y35: =IF(U35=0,0,X35/U35) -> 0 | Z35: =-SUMIFS('Отчет 23-28.02'!P:P,'Отчет 23-28.02'!C:C,"Услуги доставки",'Отчет 23-28.02'!E:E,B35) -> 0 | AD35: =U35*1%/$AE$1 -> #DIV/0! | AE35: =U35-W35-X35-Z35-AA35-AB35-AC35-AD35 -> #DIV/0! | AG35: =IF(R35=0,0,U35/R35) -> 0 | AH35: =H35 -> 552 | AI35: =IF(R35=0,0,X35/R35) -> 0 | AJ35: =IF(P35=0,Z35/1,Z35/P35) -> 0 | AK35: =IF(P35=0,0,AA35/P35) -> 0 | AL35: {=_xlfn.IFS(R35=0,AE35,R35<0,AE35/-R35,R35>0,AE35/R35)} -> #DIV/0! | AM35: =IF(AG35=0,0,AL35/AG35) -> 0 | AN35: =IF(AH35=0,0,AL35/AH35) -> #DIV/0! | AP35: =AL35*C35 -> #DIV/0!
A36: 2774710430 | B36: tunika08 зеленая | H36: 552 | I36: =C36*H36 -> 0 | N36: =K36/$O$1 -> 0 | O36: =R36/$O$1 -> 0 | P36: =SUMIFS('Отчет 23-28.02'!H:H,'Отчет 23-28.02'!D:D,"Выручка",'Отчет 23-28.02'!E:E,B36) -> 0 | Q36: =SUMIFS('Отчет 23-28.02'!H:H,'Отчет 23-28.02'!D:D,"Возврат выручки",'Отчет 23-28.02'!E:E,B36) -> 0 | R36: =P36-Q36 -> 0 | S36: =SUMIFS('Отчет 23-28.02'!P:P,'Отчет 23-28.02'!C:C,"Продажи",'Отчет 23-28.02'!E:E,B36) -> 0 | T36: =SUMIFS('Отчет 23-28.02'!P:P,'Отчет 23-28.02'!C:C,"Возвраты",'Отчет 23-28.02'!E:E,B36) -> 0 | U36: =S36+T36 -> 0 | V36: =U36/$U$51 -> #DIV/0! | W36: =R36*H36 -> 0 | X36: =-SUMIFS('Отчет 23-28.02'!P:P,'Отчет 23-28.02'!C:C,"Вознаграждение Ozon",'Отчет 23-28.02'!E:E,B36) -> 0 | Y36: =IF(U36=0,0,X36/U36) -> 0 | Z36: =-SUMIFS('Отчет 23-28.02'!P:P,'Отчет 23-28.02'!C:C,"Услуги доставки",'Отчет 23-28.02'!E:E,B36) -> 0 | AD36: =U36*1%/$AE$1 -> #DIV/0! | AE36: =U36-W36-X36-Z36-AA36-AB36-AC36-AD36 -> #DIV/0! | AG36: =IF(R36=0,0,U36/R36) -> 0 | AH36: =H36 -> 552 | AI36: =IF(R36=0,0,X36/R36) -> 0 | AJ36: =IF(P36=0,Z36/1,Z36/P36) -> 0 | AK36: =IF(P36=0,0,AA36/P36) -> 0 | AL36: {=_xlfn.IFS(R36=0,AE36,R36<0,AE36/-R36,R36>0,AE36/R36)} -> #DIV/0! | AM36: =IF(AG36=0,0,AL36/AG36) -> 0 | AN36: =IF(AH36=0,0,AL36/AH36) -> #DIV/0! | AP36: =AL36*C36 -> #DIV/0!
