Workbook

Sheet Реклама
B2: ПЕРИОД | C2: БАЛАНС | F2: СЧЕТ | I2: Неделя
C3: Номер документа | D3: Сумма | E3: Даты | F3: Номер документа | G3: Сумма | H3: Даты
B4: 01-04.01 | F4: 277607349 | G4: 4738 | H4: 01-04.01 | I4: 1
B5: 04-11.01 | F5: 279228154 | G5: 6535 | H5: 04-11.01 | I5: 2
B6: 11-18.01 | C6: 280305485 | D6: 2922 | E6: 14-18.01 | F6: 280297200 | G6: 3464 | H6: 11-17.01 | I6: 3
C7: 0 | D7: 923 | E7: 18.01 | F7: 0 | G7: 114 | H7: 18.01
B8: 18-25.01 | C8: 281290485 | D8: 5916 | E8: 18-23.01 | F8: 281290488 | G8: 2033 | H8: 18-25.01 | I8: 4
C9: 0 | D9: 1216 | E9: 25.01
B10: 25.01-01.02 | C10: 282283796 | D10: 12613 | E10: 27-31.01 | F10: 282343451 | G10: 9553 | H10: 25-31.01 | I10: 5
C11: 282375547 | D11: 1000 | E11: 01.02
C12: 0 | D12: 1791 | E12: 01.02 | F12: 0 | G12: 539 | H12: 01.02
H39: .

Sheet Сводная
B2: Период | E2: Дата поступления дс | F2: Итого к перечислению на счет, руб | G2: шт. | J2: ВБ реализовал товар (выручка с СПП) | M2: Выручка до вычета комиссии ВБ | P2: Себестоимость продаж | Q2: Логистика WB | R2: Комиссия WB | S2: Хранение WB | T2: Платная приемка WB | U2: Штрафы WB | V2: Прочие удержания WB | W2: Реклама БАЛАНС | X2: Реклама СЧЕТ | Y2: Блогеры | Z2: Налог | AA2: Прочие поступления WB | AB2: Итого | AC2: Итог месяц | AD2: % Cебестоимости | AE2: Маржинальность, % | AF2: Рентабельность, % | AG2: Доля рекламы, %
B3: Месяц | C3: Даты | D3: Нед | G3: Заказы | H3: Продажи | I3: Возвраты | J3: Продажи | K3: Возвраты | L3: Общая | M3: Продажи | N3: Возвраты | O3: Общая
B4: Январь 1 | C4: 29.12-04.01 | D4: 1 | F4: =IFERROR(O4-SUM(Q4:W4)+AA4,0) -> 29279.64 | G4: ='Юнит 1'!L$17 -> 66 | H4: ='Юнит 1'!Q$17 -> 45 | I4: ='Юнит 1'!R$17 -> 0 | J4: ='Юнит 1'!T$74 -> 46145.63 | K4: ='Юнит 1'!U$74 -> 0 | L4: =IFERROR(J4+K4,0) -> 46145.63 | M4: ='Юнит 1'!W$74 -> 54988.62 | N4: ='Юнит 1'!X$74 -> 0 | O4: =IFERROR(M4+N4,0) -> 54988.62 | P4: ='Юнит 1'!AB$74 -> 5712.21 | Q4: ='Юнит 1'!AE$74 -> 4543.05 | R4: ='Юнит 1'!AC$74 -> 19854.22 | S4: ='Юнит 1'!AI$74 -> 1049.63 | U4: ='Юнит 1'!AJ$74 -> 0 | V4: 262.08 | W4: ='Юнит 1'!AF$74 -> 0 | X4: ='Юнит 1'!AG$74 -> 4738 | Y4: ='Юнит 1'!AH84 -> 0 | Z4: =IFERROR((L4)*0.01,0) -> 461.4563 | AB4: =O4-SUM(P4:Z4)+AA4-Y4 -> 18367.974 | AC4: =SUM(AB4:AB8) -> 67227.563 | AD4: =P4/O4 -> 0.10387986 | AE4: =AB4/P4 -> 3.2155635 | AF4: =AB4/O4 -> 0.33403227 | AG4: =(W4+X4+Y4)/O4 -> 0.086163283
B5: Январь 2 | C5: 05-11.01 | D5: 2 | F5: =IFERROR(O5-SUM(Q5:W5)+AA5,0) -> 25524.23 | G5: ='Юнит 2'!L$17 -> 86 | H5: ='Юнит 2'!Q$17 -> 43 | I5: ='Юнит 2'!R$17 -> -1 | J5: ='Юнит 2'!T$74 -> 43245.32 | K5: ='Юнит 2'!U$74 -> -931 | L5: =IFERROR(J5+K5,0) -> 42314.32 | M5: ='Юнит 2'!W$74 -> 52197.86 | N5: ='Юнит 2'!X$74 -> -1199 | O5: =IFERROR(M5+N5,0) -> 50998.86 | P5: ='Юнит 2'!AB$74 -> 5562.9 | Q5: ='Юнит 2'!AE$74 -> 5752.8 | R5: ='Юнит 2'!AC$74 -> 18463.04 | S5: ='Юнит 2'!AI$74 -> 1083.11 | U5: ='Юнит 2'!AJ$74 -> 0 | V5: 175.68 | W5: ='Юнит 2'!AF$74 -> 0 | X5: ='Юнит 2'!AG$74 -> 6535 | Y5: ='Юнит 2'!AH85 -> 0 | Z5: =IFERROR((L5)*0.01,0) -> 423.1432 | AB5: =O5-SUM(P5:Z5)+AA5-Y5 -> 13003.187 | AD5: =P5/O5 -> 0.10907891 | AE5: =AB5/P5 -> 2.3374835 | AF5: =AB5/O5 -> 0.25497015 | AG5: =(W5+X5+Y5)/O5 -> 0.12814012
B6: Январь 3 | C6: 12-18.01 | D6: 3 | F6: =IFERROR(O6-SUM(Q6:W6)+AA6,0) -> 25982.83 | G6: ='Юнит 3'!L$17 -> 62 | H6: ='Юнит 3'!Q$17 -> 49 | I6: ='Юнит 3'!R$17 -> -1 | J6: ='Юнит 3'!T$74 -> 45785.47 | K6: ='Юнит 3'!U$74 -> -948 | L6: =IFERROR(J6+K6,0) -> 44837.47 | M6: ='Юнит 3'!W$74 -> 56919.74 | N6: ='Юнит 3'!X$74 -> -1174 | O6: =IFERROR(M6+N6,0) -> 55745.74 | P6: ='Юнит 3'!AB$74 -> 6528.42 | Q6: ='Юнит 3'!AE$74 -> 6055.25 | R6: ='Юнит 3'!AC$74 -> 19306.86 | S6: ='Юнит 3'!AI$74 -> 1361.68 | U6: ='Юнит 3'!AJ$74 -> 0 | V6: 117.12 | W6: ='Юнит 3'!AF$74 -> 2922 | X6: ='Юнит 3'!AG$74 -> 3464 | Y6: ='Юнит 3'!AH86 -> 0 | Z6: =IFERROR((L6)*0.01,0) -> 448.3747 | AB6: =O6-SUM(P6:Z6)+AA6-Y6 -> 15542.035 | AD6: =P6/O6 -> 0.11711065 | AE6: =AB6/P6 -> 2.3806733 | AF6: =AB6/O6 -> 0.27880221 | AG6: =(W6+X6+Y6)/O6 -> 0.11455584
B7: Январь 4 | C7: 19-25.01 | D7: 4 | F7: =IFERROR(O7-SUM(Q7:W7)+AA7,0) -> 22836.85 | G7: ='Юнит 4'!L$17 -> 86 | H7: ='Юнит 4'!Q$17 -> 49 | I7: ='Юнит 4'!R$17 -> -2 | J7: ='Юнит 4'!T$74 -> 44338.88 | K7: ='Юнит 4'!U$74 -> -1888 | L7: =IFERROR(J7+K7,0) -> 42450.88 | M7: ='Юнит 4'!W$74 -> 59321.67 | N7: ='Юнит 4'!X$74 -> -2412 | O7: =IFERROR(M7+N7,0) -> 56909.67 | P7: ='Юнит 4'!AB$74 -> 6764.52 | Q7: ='Юнит 4'!AE$74 -> 6115.35 | R7: ='Юнит 4'!AC$74 -> 20543.92 | S7: ='Юнит 4'!AI$74 -> 1438.99 | U7: ='Юнит 4'!AJ$74 -> 0 | V7: 58.56 | W7: ='Юнит 4'!AF$74 -> 5916 | X7: ='Юнит 4'!AG$74 -> 2033 | Y7: ='Юнит 4'!AH87 -> 0 | Z7: =IFERROR((L7)*0.01,0) -> 424.5088 | AB7: =O7-SUM(P7:Z7)+AA7-Y7 -> 13614.821 | AD7: =P7/O7 -> 0.11886416 | AE7: =AB7/P7 -> 2.012681 | AF7: =AB7/O7 -> 0.23923564 | AG7: =(W7+X7+Y7)/O7 -> 0.13967749
B8: Январь 5 | C8: 26.01-01.02 | D8: 5 | F8: =IFERROR(O8-SUM(Q8:W8)+AA8,0) -> 26541.81 | G8: ='Юнит 5'!L$17 -> 157 | H8: ='Юнит 5'!Q$17 -> 70 | I8: ='Юнит 5'!R$17 -> -1 | J8: ='Юнит 5'!T$74 -> 53707.42 | K8: ='Юнит 5'!U$74 -> -813 | L8: =IFERROR(J8+K8,0) -> 52894.42 | M8: ='Юнит 5'!W$74 -> 80352 | N8: ='Юнит 5'!X$74 -> -1238 | O8: =IFERROR(M8+N8,0) -> 79114 | P8: ='Юнит 5'!AB$74 -> 9760.32 | Q8: ='Юнит 5'!AE$74 -> 8509.6 | R8: ='Юнит 5'!AC$74 -> 28720.66 | S8: ='Юнит 5'!AI$74 -> 1377.57 | U8: ='Юнит 5'!AJ$74 -> 0 | V8: 351.36 | W8: ='Юнит 5'!AF$74 -> 13613 | X8: ='Юнит 5'!AG$74 -> 9553 | Y8: ='Юнит 5'!AH88 -> 0 | Z8: =IFERROR((L8)*0.01,0) -> 528.9442 | AB8: =O8-SUM(P8:Z8)+AA8-Y8 -> 6699.5458 | AD8: =P8/O8 -> 0.12337033 | AE8: =AB8/P8 -> 0.68640637 | AF8: =AB8/O8 -> 0.084682178 | AG8: =(W8+X8+Y8)/O8 -> 0.29281796
B9: Итого | F9: =SUM(F4:F8) -> 130165.36 | G9: =SUM(G4:G8) -> 457 | H9: =SUM(H4:H8) -> 256 | I9: =SUM(I4:I8) -> -5 | J9: =SUM(J4:J8) -> 233222.72 | K9: =SUM(K4:K8) -> -4580 | L9: =SUM(L4:L8) -> 228642.72 | M9: =SUM(M4:M8) -> 303779.89 | ... AC9: =SUM(AC4:AC8) -> 67227.563 | AD9: =P9/O9 -> 0.11528993 | AE9: =AB9/P9 -> 1.9583675 | AF9: =AB9/O9 -> 0.22578004 | AG9: =(W9+X9+Y9)/O9 -> 0.16380477
M10: % от выручки за весь период
N11: =-N9/M9 -> 0.019826856 | P11: =P9/$O$9 -> 0.11528993 | Q11: =Q9/$O$9 -> 0.10403135 | R11: =R9/$O$9 -> 0.35897977 | S11: =S9/$O$9 -> 0.021195076 | U11: =U9/$O$9 -> 0 | V11: =V9/$O$9 -> 0.0032402273 | W11: =W9/$O$9 -> 0.075400438 | Z11: =Z9/$O$9 -> 0.0076788389 | AB11: =AB9/P9 -> 1.9583675 | AC11: Маржинальность, %
AB12: =AB9/O9 -> 0.22578004 | AC12: Рентабельность, %

Sheet АВС 6
B2: ОЧКИ
C3: Прибыль | D3: % прибыль | E3: Доля | F3: ABC прибыль | G3: ABC кол-во | J3: Кол-во | K3: % кол-во | L3: Доля | M3: ABC кол-во
B4: Черные с железкой Сул | D4: =C4/C$17 -> #DIV/0! | E4: =D4 -> #DIV/0! | F4: =IF(AND(E4<=0),"C",IF(E4<=0.8,"A",IF(E4<=0.95,"B","C"))) -> #DIV/0! | G4: =VLOOKUP(B$4:B$16,I$4:M$16,5,0) -> #DIV/0! | I4: Черные с железкой Сул | K4: =J4/J$17 -> #DIV/0! | L4: =K4 -> #DIV/0! | M4: =_xlfn.IFS(L4<80%,"A",L4<=95%,"B",L4>95%,"C") -> #DIV/0! | P4: A | Q4: 0.8
B5: Qs черн Сул | D5: =C5/C$17 -> #DIV/0! | E5: =E4+D5 -> #DIV/0! | F5: =IF(AND(E5<=0),"C",IF(E5<=0.8,"A",IF(E5<=0.95,"B","C"))) -> #DIV/0! | G5: =VLOOKUP(B$4:B$16,I$4:M$16,5,0) -> #DIV/0! | I5: Qs черн Сул | K5: =J5/J$17 -> #DIV/0! | L5: =L4+K5 -> #DIV/0! | M5: =_xlfn.IFS(L5<80%,"A",L5<=95%,"B",L5>95%,"C") -> #DIV/0! | P5: B | Q5: 0.15
B6: Qs син Сул | D6: =C6/C$17 -> #DIV/0! | E6: =E5+D6 -> #DIV/0! | F6: =IF(AND(E6<=0),"C",IF(E6<=0.8,"A",IF(E6<=0.95,"B","C"))) -> #DIV/0! | G6: =VLOOKUP(B$4:B$16,I$4:M$16,5,0) -> #DIV/0! | I6: Qs син Сул | K6: =J6/J$17 -> #DIV/0! | L6: =L5+K6 -> #DIV/0! | M6: =_xlfn.IFS(L6<80%,"A",L6<=95%,"B",L6>95%,"C") -> #DIV/0! | P6: C | Q6: 0.05
B7: Qs желт Сул | D7: =C7/C$17 -> #DIV/0! | E7: =E6+D7 -> #DIV/0! | F7: =IF(AND(E7<=0),"C",IF(E7<=0.8,"A",IF(E7<=0.95,"B","C"))) -> #DIV/0! | G7: =VLOOKUP(B$4:B$16,I$4:M$16,5,0) -> #DIV/0! | I7: Qs желт Сул | K7: =J7/J$17 -> #DIV/0! | L7: =L6+K7 -> #DIV/0! | M7: =_xlfn.IFS(L7<80%,"A",L7<=95%,"B",L7>95%,"C") -> #DIV/0!
B8: flip черные Сул | D8: =C8/C$17 -> #DIV/0! | E8: =E7+D8 -> #DIV/0! | F8: =IF(AND(E8<=0),"C",IF(E8<=0.8,"A",IF(E8<=0.95,"B","C"))) -> #DIV/0! | G8: =VLOOKUP(B$4:B$16,I$4:M$16,5,0) -> #DIV/0! | I8: flip черные Сул | K8: =J8/J$17 -> #DIV/0! | L8: =L7+K8 -> #DIV/0! | M8: =_xlfn.IFS(L8<80%,"A",L8<=95%,"B",L8>95%,"C") -> #DIV/0!
B9: flip желтые Сул | D9: =C9/C$17 -> #DIV/0! | E9: =E8+D9 -> #DIV/0! | F9: =IF(AND(E9<=0),"C",IF(E9<=0.8,"A",IF(E9<=0.95,"B","C"))) -> #DIV/0! | G9: =VLOOKUP(B$4:B$16,I$4:M$16,5,0) -> #DIV/0! | I9: flip желтые Сул | K9: =J9/J$17 -> #DIV/0! | L9: =L8+K9 -> #DIV/0! | M9: =_xlfn.IFS(L9<80%,"A",L9<=95%,"B",L9>95%,"C") -> #DIV/0!
B10: MR8854 C2 Сул | D10: =C10/C$17 -> #DIV/0! | E10: =E9+D10 -> #DIV/0! | F10: =IF(AND(E10<=0),"C",IF(E10<=0.8,"A",IF(E10<=0.95,"B","C"))) -> #DIV/0! | G10: =VLOOKUP(B$4:B$16,I$4:M$16,5,0) -> #DIV/0! | I10: MR8854 C2 Сул | K10: =J10/J$17 -> #DIV/0! | L10: =L9+K10 -> #DIV/0! | M10: =_xlfn.IFS(L10<80%,"A",L10<=95%,"B",L10>95%,"C") -> #DIV/0!
B11: MR 1819 черн | D11: =C11/C$17 -> #DIV/0! | E11: =E10+D11 -> #DIV/0! | F11: =IF(AND(E11<=0),"C",IF(E11<=0.8,"A",IF(E11<=0.95,"B","C"))) -> #DIV/0! | G11: =VLOOKUP(B$4:B$16,I$4:M$16,5,0) -> #DIV/0! | I11: MR 1819 черн | K11: =J11/J$17 -> #DIV/0! | L11: =L10+K11 -> #DIV/0! | M11: =_xlfn.IFS(L11<80%,"A",L11<=95%,"B",L11>95%,"C") -> #DIV/0!
B12: MR 1819 корич | D12: =C12/C$17 -> #DIV/0! | E12: =E11+D12 -> #DIV/0! | F12: =IF(AND(E12<=0),"C",IF(E12<=0.8,"A",IF(E12<=0.95,"B","C"))) -> #DIV/0! | G12: =VLOOKUP(B$4:B$16,I$4:M$16,5,0) -> #DIV/0! | I12: MR 1819 корич | K12: =J12/J$17 -> #DIV/0! | L12: =L11+K12 -> #DIV/0! | M12: =_xlfn.IFS(L12<80%,"A",L12<=95%,"B",L12>95%,"C") -> #DIV/0!
B13: MR Р1874 черн | D13: =C13/C$17 -> #DIV/0! | E13: =E12+D13 -> #DIV/0! | F13: =IF(AND(E13<=0),"C",IF(E13<=0.8,"A",IF(E13<=0.95,"B","C"))) -> #DIV/0! | G13: =VLOOKUP(B$4:B$16,I$4:M$16,5,0) -> #DIV/0! | I13: MR Р1874 черн | K13: =J13/J$17 -> #DIV/0! | L13: =L12+K13 -> #DIV/0! | M13: =_xlfn.IFS(L13<80%,"A",L13<=95%,"B",L13>95%,"C") -> #DIV/0!
B14: MR Р1874 корич | D14: =C14/C$17 -> #DIV/0! | E14: =E13+D14 -> #DIV/0! | F14: =IF(AND(E14<=0),"C",IF(E14<=0.8,"A",IF(E14<=0.95,"B","C"))) -> #DIV/0! | G14: =VLOOKUP(B$4:B$16,I$4:M$16,5,0) -> #DIV/0! | I14: MR Р1874 корич | K14: =J14/J$17 -> #DIV/0! | L14: =L13+K14 -> #DIV/0! | M14: =_xlfn.IFS(L14<80%,"A",L14<=95%,"B",L14>95%,"C") -> #DIV/0!
B15: MR Р1886 черн | D15: =C15/C$17 -> #DIV/0! | E15: =E14+D15 -> #DIV/0! | F15: =IF(AND(E15<=0),"C",IF(E15<=0.8,"A",IF(E15<=0.95,"B","C"))) -> #DIV/0! | G15: =VLOOKUP(B$4:B$16,I$4:M$16,5,0) -> #DIV/0! | I15: MR Р1886 черн | K15: =J15/J$17 -> #DIV/0! | L15: =L14+K15 -> #DIV/0! | M15: =_xlfn.IFS(L15<80%,"A",L15<=95%,"B",L15>95%,"C") -> #DIV/0!
B16: MR Р1886 корич | D16: =C16/C$17 -> #DIV/0! | E16: =E15+D16 -> #DIV/0! | F16: =IF(AND(E16<=0),"C",IF(E16<=0.8,"A",IF(E16<=0.95,"B","C"))) -> #DIV/0! | G16: =VLOOKUP(B$4:B$16,I$4:M$16,5,0) -> #DIV/0! | I16: MR Р1886 корич | K16: =J16/J$17 -> #DIV/0! | L16: =L15+K16 -> #DIV/0! | M16: =_xlfn.IFS(L16<80%,"A",L16<=95%,"B",L16>95%,"C") -> #DIV/0!
C17: =SUM(C4:C16) -> 0 | D17: =SUM(D4:D16) -> #DIV/0! | J17: =SUM(J4:J16) -> 0 | K17: =SUM(K4:K16) -> #DIV/0!
C20: Прибыль | D20: % прибыль | E20: Доля | F20: ABC прибыль | G20: ABC кол-во | J20: Кол-во | K20: % кол-во | L20: Доля | M20: ABC кол-во
D21: =C21/C$73 -> #DIV/0! | E21: =D21 -> #DIV/0! | F21: =IF(AND(E21<=0),"C",IF(E21<=0.8,"A",IF(E21<=0.95,"B","C"))) -> #DIV/0! | G21: =VLOOKUP(B21:B72,I$21:M$72,5,0) -> #N/A | K21: =J21/J$73 -> #DIV/0! | L21: =K21 -> #DIV/0! | M21: =_xlfn.IFS(L21<80%,"A",L21<=95%,"B",L21>95%,"C") -> #DIV/0!
D22: =C22/C$73 -> #DIV/0! | E22: =D22+E21 -> #DIV/0! | F22: =IF(AND(E22<=0),"C",IF(E22<=0.8,"A",IF(E22<=0.95,"B","C"))) -> #DIV/0! | G22: =VLOOKUP(B22:B73,I$21:M$72,5,0) -> #N/A | K22: =J22/J$73 -> #DIV/0! | L22: =K22+L21 -> #DIV/0! | M22: =_xlfn.IFS(L22<80%,"A",L22<=95%,"B",L22>95%,"C") -> #DIV/0!
D23: =C23/C$73 -> #DIV/0! | E23: =D23+E22 -> #DIV/0! | F23: =IF(AND(E23<=0),"C",IF(E23<=0.8,"A",IF(E23<=0.95,"B","C"))) -> #DIV/0! | G23: =VLOOKUP(B23:B74,I$21:M$72,5,0) -> #N/A | K23: =J23/J$73 -> #DIV/0! | L23: =K23+L22 -> #DIV/0! | M23: =_xlfn.IFS(L23<80%,"A",L23<=95%,"B",L23>95%,"C") -> #DIV/0!
D24: =C24/C$73 -> #DIV/0! | E24: =D24+E23 -> #DIV/0! | F24: =IF(AND(E24<=0),"C",IF(E24<=0.8,"A",IF(E24<=0.95,"B","C"))) -> #DIV/0! | G24: =VLOOKUP(B24:B75,I$21:M$72,5,0) -> #N/A | K24: =J24/J$73 -> #DIV/0! | L24: =K24+L23 -> #DIV/0! | M24: =_xlfn.IFS(L24<80%,"A",L24<=95%,"B",L24>95%,"C") -> #DIV/0!
D25: =C25/C$73 -> #DIV/0! | E25: =D25+E24 -> #DIV/0! | F25: =IF(AND(E25<=0),"C",IF(E25<=0.8,"A",IF(E25<=0.95,"B","C"))) -> #DIV/0! | G25: =VLOOKUP(B25:B76,I$21:M$72,5,0) -> #N/A | K25: =J25/J$73 -> #DIV/0! | L25: =K25+L24 -> #DIV/0! | M25: =_xlfn.IFS(L25<80%,"A",L25<=95%,"B",L25>95%,"C") -> #DIV/0!
D26: =C26/C$73 -> #DIV/0! | E26: =D26+E25 -> #DIV/0! | F26: =IF(AND(E26<=0),"C",IF(E26<=0.8,"A",IF(E26<=0.95,"B","C"))) -> #DIV/0! | G26: =VLOOKUP(B26:B77,I$21:M$72,5,0) -> #N/A | K26: =J26/J$73 -> #DIV/0! | L26: =K26+L25 -> #DIV/0! | M26: =_xlfn.IFS(L26<80%,"A",L26<=95%,"B",L26>95%,"C") -> #DIV/0!
D27: =C27/C$73 -> #DIV/0! | E27: =D27+E26 -> #DIV/0! | F27: =IF(AND(E27<=0),"C",IF(E27<=0.8,"A",IF(E27<=0.95,"B","C"))) -> #DIV/0! | G27: =VLOOKUP(B27:B78,I$21:M$72,5,0) -> #N/A | K27: =J27/J$73 -> #DIV/0! | L27: =K27+L26 -> #DIV/0! | M27: =_xlfn.IFS(L27<80%,"A",L27<=95%,"B",L27>95%,"C") -> #DIV/0!
D28: =C28/C$73 -> #DIV/0! | E28: =D28+E27 -> #DIV/0! | F28: =IF(AND(E28<=0),"C",IF(E28<=0.8,"A",IF(E28<=0.95,"B","C"))) -> #DIV/0! | G28: =VLOOKUP(B28:B79,I$21:M$72,5,0) -> #N/A | K28: =J28/J$73 -> #DIV/0! | L28: =K28+L27 -> #DIV/0! | M28: =_xlfn.IFS(L28<80%,"A",L28<=95%,"B",L28>95%,"C") -> #DIV/0!
D29: =C29/C$73 -> #DIV/0! | E29: =D29+E28 -> #DIV/0! | F29: =IF(AND(E29<=0),"C",IF(E29<=0.8,"A",IF(E29<=0.95,"B","C"))) -> #DIV/0! | G29: =VLOOKUP(B29:B80,I$21:M$72,5,0) -> #N/A | K29: =J29/J$73 -> #DIV/0! | L29: =K29+L28 -> #DIV/0! | M29: =_xlfn.IFS(L29<80%,"A",L29<=95%,"B",L29>95%,"C") -> #DIV/0!
D30: =C30/C$73 -> #DIV/0! | E30: =D30+E29 -> #DIV/0! | F30: =IF(AND(E30<=0),"C",IF(E30<=0.8,"A",IF(E30<=0.95,"B","C"))) -> #DIV/0! | G30: =VLOOKUP(B30:B81,I$21:M$72,5,0) -> #N/A | K30: =J30/J$73 -> #DIV/0! | L30: =K30+L29 -> #DIV/0! | M30: =_xlfn.IFS(L30<80%,"A",L30<=95%,"B",L30>95%,"C") -> #DIV/0!
D31: =C31/C$73 -> #DIV/0! | E31: =D31+E30 -> #DIV/0! | F31: =IF(AND(E31<=0),"C",IF(E31<=0.8,"A",IF(E31<=0.95,"B","C"))) -> #DIV/0! | G31: =VLOOKUP(B31:B82,I$21:M$72,5,0) -> #N/A | K31: =J31/J$73 -> #DIV/0! | L31: =K31+L30 -> #DIV/0! | M31: =_xlfn.IFS(L31<80%,"A",L31<=95%,"B",L31>95%,"C") -> #DIV/0!
D32: =C32/C$73 -> #DIV/0! | E32: =D32+E31 -> #DIV/0! | F32: =IF(AND(E32<=0),"C",IF(E32<=0.8,"A",IF(E32<=0.95,"B","C"))) -> #DIV/0! | G32: =VLOOKUP(B32:B83,I$21:M$72,5,0) -> #N/A | K32: =J32/J$73 -> #DIV/0! | L32: =K32+L31 -> #DIV/0! | M32: =_xlfn.IFS(L32<80%,"A",L32<=95%,"B",L32>95%,"C") -> #DIV/0!
D33: =C33/C$73 -> #DIV/0! | E33: =D33+E32 -> #DIV/0! | F33: =IF(AND(E33<=0),"C",IF(E33<=0.8,"A",IF(E33<=0.95,"B","C"))) -> #DIV/0! | G33: =VLOOKUP(B33:B84,I$21:M$72,5,0) -> #N/A | K33: =J33/J$73 -> #DIV/0! | L33: =K33+L32 -> #DIV/0! | M33: =_xlfn.IFS(L33<80%,"A",L33<=95%,"B",L33>95%,"C") -> #DIV/0!
... D72: =C72/C$73 -> #DIV/0! | E72: =D72+E71 -> #DIV/0! | F72: =IF(AND(E72<=0),"C",IF(E72<=0.8,"A",IF(E72<=0.95,"B","C"))) -> #DIV/0! | G72: =VLOOKUP(B72:B123,I$21:M$72,5,0) -> #N/A | K72: =J72/J$73 -> #DIV/0! | L72: =K72+L71 -> #DIV/0! | M72: =_xlfn.IFS(L72<80%,"A",L72<=95%,"B",L72>95%,"C") -> #DIV/0!
C73: =SUM(C21:C72) -> 0 | D73: =SUM(D21:D72) -> #DIV/0! | J73: =SUM(J21:J72) -> 0 | K73: =SUM(K21:K72) -> #DIV/0!

Sheet АВС ЯНВАРЬ
B2: ОЧКИ
C3: Прибыль | D3: % прибыль | E3: Доля | F3: ABC прибыль | G3: ABC кол-во | J3: Кол-во | K3: % кол-во | L3: Доля | M3: ABC кол-во
B4: flip желтые Сул | C4: ='Юнит 5'!AL8 -> 2045.1121 | D4: =C4/C$17 -> 0.29004955 | E4: =D4 -> 0.29004955 | F4: =IF(AND(E4<=0),"C",IF(E4<=0.8,"A",IF(E4<=0.95,"B","C"))) -> A | G4: =VLOOKUP(B$4:B$16,I$4:M$16,5,0) -> A | I4: flip желтые Сул | J4: =ЯНВАРЬ!S8 -> 107 | K4: =J4/J$17 -> 0.42629482 | L4: =K4 -> 0.42629482 | M4: =_xlfn.IFS(L4<80%,"A",L4<=95%,"B",L4>95%,"C") -> A | P4: A | Q4: 0.8
B5: Черные с железкой Сул | C5: ='Юнит 5'!AL3 -> 1813.3318 | D5: =C5/C$17 -> 0.25717714 | E5: =E4+D5 -> 0.54722669 | F5: =IF(AND(E5<=0),"C",IF(E5<=0.8,"A",IF(E5<=0.95,"B","C"))) -> A | G5: =VLOOKUP(B$4:B$16,I$4:M$16,5,0) -> A | I5: Черные с железкой Сул | J5: =ЯНВАРЬ!S3 -> 62 | K5: =J5/J$17 -> 0.24701195 | L5: =L4+K5 -> 0.67330677 | M5: =_xlfn.IFS(L5<80%,"A",L5<=95%,"B",L5>95%,"C") -> A | P5: B | Q5: 0.15
B6: Qs желт Сул | C6: ='Юнит 5'!AL6 -> 1154.6045 | D6: =C6/C$17 -> 0.16375265 | E6: =E5+D6 -> 0.71097934 | F6: =IF(AND(E6<=0),"C",IF(E6<=0.8,"A",IF(E6<=0.95,"B","C"))) -> A | G6: =VLOOKUP(B$4:B$16,I$4:M$16,5,0) -> B | I6: MR8854 C2 Сул | J6: =ЯНВАРЬ!S9 -> 26 | K6: =J6/J$17 -> 0.10358566 | L6: =L5+K6 -> 0.77689243 | M6: =_xlfn.IFS(L6<80%,"A",L6<=95%,"B",L6>95%,"C") -> A | P6: C | Q6: 0.05
B7: MR Р1886 черн | C7: ='Юнит 5'!AL14 -> 826.78813 | D7: =C7/C$17 -> 0.11725985 | E7: =E6+D7 -> 0.82823919 | F7: =IF(AND(E7<=0),"C",IF(E7<=0.8,"A",IF(E7<=0.95,"B","C"))) -> B | G7: =VLOOKUP(B$4:B$16,I$4:M$16,5,0) -> B | I7: Qs желт Сул | J7: =ЯНВАРЬ!S6 -> 20 | K7: =J7/J$17 -> 0.079681275 | L7: =L6+K7 -> 0.85657371 | M7: =_xlfn.IFS(L7<80%,"A",L7<=95%,"B",L7>95%,"C") -> B
B8: MR Р1874 черн | C8: ='Юнит 5'!AL12 -> 783.16961 | D8: =C8/C$17 -> 0.11107362 | E8: =E7+D8 -> 0.93931281 | F8: =IF(AND(E8<=0),"C",IF(E8<=0.8,"A",IF(E8<=0.95,"B","C"))) -> B | G8: =VLOOKUP(B$4:B$16,I$4:M$16,5,0) -> C | I8: Qs черн Сул | J8: =ЯНВАРЬ!S4 -> 10 | K8: =J8/J$17 -> 0.039840637 | L8: =L7+K8 -> 0.89641434 | M8: =_xlfn.IFS(L8<80%,"A",L8<=95%,"B",L8>95%,"C") -> B
B9: MR 1819 корич | C9: ='Юнит 5'!AL11 -> 758.76739 | D9: =C9/C$17 -> 0.10761275 | E9: =E8+D9 -> 1.0469256 | F9: =IF(AND(E9<=0),"C",IF(E9<=0.8,"A",IF(E9<=0.95,"B","C"))) -> C | G9: =VLOOKUP(B$4:B$16,I$4:M$16,5,0) -> C | I9: MR Р1886 черн | J9: =ЯНВАРЬ!S14 -> 6 | K9: =J9/J$17 -> 0.023904382 | L9: =L8+K9 -> 0.92031873 | M9: =_xlfn.IFS(L9<80%,"A",L9<=95%,"B",L9>95%,"C") -> B
B10: MR Р1874 корич | C10: ='Юнит 5'!AL13 -> 508.76629 | D10: =C10/C$17 -> 0.072156161 | E10: =E9+D10 -> 1.1190817 | F10: =IF(AND(E10<=0),"C",IF(E10<=0.8,"A",IF(E10<=0.95,"B","C"))) -> C | G10: =VLOOKUP(B$4:B$16,I$4:M$16,5,0) -> C | I10: Qs син Сул | J10: =ЯНВАРЬ!S5 -> 4 | K10: =J10/J$17 -> 0.015936255 | L10: =L9+K10 -> 0.93625498 | M10: =_xlfn.IFS(L10<80%,"A",L10<=95%,"B",L10>95%,"C") -> B
B11: MR 1819 черн | C11: ='Юнит 5'!AL10 -> 398.95943 | D11: =C11/C$17 -> 0.05658272 | E11: =E10+D11 -> 1.1756644 | F11: =IF(AND(E11<=0),"C",IF(E11<=0.8,"A",IF(E11<=0.95,"B","C"))) -> C | G11: =VLOOKUP(B$4:B$16,I$4:M$16,5,0) -> C | I11: MR Р1874 корич | J11: =ЯНВАРЬ!S13 -> 4 | K11: =J11/J$17 -> 0.015936255 | L11: =L10+K11 -> 0.95219124 | M11: =_xlfn.IFS(L11<80%,"A",L11<=95%,"B",L11>95%,"C") -> C
B12: MR8854 C2 Сул | C12: ='Юнит 5'!AL9 -> 297.0268 | D12: =C12/C$17 -> 0.042126049 | E12: =E11+D12 -> 1.2177905 | F12: =IF(AND(E12<=0),"C",IF(E12<=0.8,"A",IF(E12<=0.95,"B","C"))) -> C | G12: =VLOOKUP(B$4:B$16,I$4:M$16,5,0) -> A | I12: MR 1819 корич | J12: =ЯНВАРЬ!S11 -> 3 | K12: =J12/J$17 -> 0.011952191 | L12: =L11+K12 -> 0.96414343 | M12: =_xlfn.IFS(L12<80%,"A",L12<=95%,"B",L12>95%,"C") -> C
B13: Qs черн Сул | C13: ='Юнит 5'!AL4 -> 177.70464 | D13: =C13/C$17 -> 0.025203094 | E13: =E12+D13 -> 1.2429936 | F13: =IF(AND(E13<=0),"C",IF(E13<=0.8,"A",IF(E13<=0.95,"B","C"))) -> C | G13: =VLOOKUP(B$4:B$16,I$4:M$16,5,0) -> B | I13: MR Р1874 черн | J13: =ЯНВАРЬ!S12 -> 3 | K13: =J13/J$17 -> 0.011952191 | L13: =L12+K13 -> 0.97609562 | M13: =_xlfn.IFS(L13<80%,"A",L13<=95%,"B",L13>95%,"C") -> C
B14: MR Р1886 корич | C14: ='Юнит 5'!AL15 -> -22.030753 | D14: =C14/C$17 -> -0.003124528 | E14: =E13+D14 -> 1.2398691 | F14: =IF(AND(E14<=0),"C",IF(E14<=0.8,"A",IF(E14<=0.95,"B","C"))) -> C | G14: =VLOOKUP(B$4:B$16,I$4:M$16,5,0) -> C | I14: MR Р1886 корич | J14: =ЯНВАРЬ!S15 -> 3 | K14: =J14/J$17 -> 0.011952191 | L14: =L13+K14 -> 0.98804781 | M14: =_xlfn.IFS(L14<80%,"A",L14<=95%,"B",L14>95%,"C") -> C
B15: flip черные Сул | C15: ='Юнит 5'!AL7 -> -773.48176 | D15: =C15/C$17 -> -0.10969963 | E15: =E14+D15 -> 1.1301694 | F15: =IF(AND(E15<=0),"C",IF(E15<=0.8,"A",IF(E15<=0.95,"B","C"))) -> C | G15: =VLOOKUP(B$4:B$16,I$4:M$16,5,0) -> C | I15: MR 1819 черн | J15: =ЯНВАРЬ!S10 -> 2 | K15: =J15/J$17 -> 0.0079681275 | L15: =L14+K15 -> 0.99601594 | M15: =_xlfn.IFS(L15<80%,"A",L15<=95%,"B",L15>95%,"C") -> C
B16: Qs син Сул | C16: ='Юнит 5'!AL5 -> -917.81235 | D16: =C16/C$17 -> -0.13016942 | E16: =E15+D16 -> 1 | F16: =IF(AND(E16<=0),"C",IF(E16<=0.8,"A",IF(E16<=0.95,"B","C"))) -> C | G16: =VLOOKUP(B$4:B$16,I$4:M$16,5,0) -> B | I16: flip черные Сул | J16: =ЯНВАРЬ!S7 -> 1 | K16: =J16/J$17 -> 0.0039840637 | L16: =L15+K16 -> 1 | M16: =_xlfn.IFS(L16<80%,"A",L16<=95%,"B",L16>95%,"C") -> C
C17: =SUM(C4:C16) -> 7050.9058 | D17: =SUM(D4:D16) -> 1 | J17: =SUM(J4:J16) -> 251 | K17: =SUM(K4:K16) -> 1
C20: Прибыль | D20: % прибыль | E20: Доля | F20: ABC прибыль | G20: ABC кол-во | J20: Кол-во | K20: % кол-во | L20: Доля | M20: ABC кол-во
D21: =C21/C$73 -> #DIV/0! | E21: =D21 -> #DIV/0! | F21: =IF(AND(E21<=0),"C",IF(E21<=0.8,"A",IF(E21<=0.95,"B","C"))) -> #DIV/0! | G21: =VLOOKUP(B21:B72,I$21:M$72,5,0) -> #N/A | K21: =J21/J$73 -> #DIV/0! | L21: =K21 -> #DIV/0! | M21: =_xlfn.IFS(L21<80%,"A",L21<=95%,"B",L21>95%,"C") -> #DIV/0!
D22: =C22/C$73 -> #DIV/0! | E22: =D22+E21 -> #DIV/0! | F22: =IF(AND(E22<=0),"C",IF(E22<=0.8,"A",IF(E22<=0.95,"B","C"))) -> #DIV/0! | G22: =VLOOKUP(B22:B73,I$21:M$72,5,0) -> #N/A | K22: =J22/J$73 -> #DIV/0! | L22: =K22+L21 -> #DIV/0! | M22: =_xlfn.IFS(L22<80%,"A",L22<=95%,"B",L22>95%,"C") -> #DIV/0!
D23: =C23/C$73 -> #DIV/0! | E23: =D23+E22 -> #DIV/0! | F23: =IF(AND(E23<=0),"C",IF(E23<=0.8,"A",IF(E23<=0.95,"B","C"))) -> #DIV/0! | G23: =VLOOKUP(B23:B74,I$21:M$72,5,0) -> #N/A | K23: =J23/J$73 -> #DIV/0! | L23: =K23+L22 -> #DIV/0! | M23: =_xlfn.IFS(L23<80%,"A",L23<=95%,"B",L23>95%,"C") -> #DIV/0!
D24: =C24/C$73 -> #DIV/0! | E24: =D24+E23 -> #DIV/0! | F24: =IF(AND(E24<=0),"C",IF(E24<=0.8,"A",IF(E24<=0.95,"B","C"))) -> #DIV/0! | G24: =VLOOKUP(B24:B75,I$21:M$72,5,0) -> #N/A | K24: =J24/J$73 -> #DIV/0! | L24: =K24+L23 -> #DIV/0! | M24: =_xlfn.IFS(L24<80%,"A",L24<=95%,"B",L24>95%,"C") -> #DIV/0!
D25: =C25/C$73 -> #DIV/0! | E25: =D25+E24 -> #DIV/0! | F25: =IF(AND(E25<=0),"C",IF(E25<=0.8,"A",IF(E25<=0.95,"B","C"))) -> #DIV/0! | G25: =VLOOKUP(B25:B76,I$21:M$72,5,0) -> #N/A | K25: =J25/J$73 -> #DIV/0! | L25: =K25+L24 -> #DIV/0! | M25: =_xlfn.IFS(L25<80%,"A",L25<=95%,"B",L25>95%,"C") -> #DIV/0!
D26: =C26/C$73 -> #DIV/0! | E26: =D26+E25 -> #DIV/0! | F26: =IF(AND(E26<=0),"C",IF(E26<=0.8,"A",IF(E26<=0.95,"B","C"))) -> #DIV/0! | G26: =VLOOKUP(B26:B77,I$21:M$72,5,0) -> #N/A | K26: =J26/J$73 -> #DIV/0! | L26: =K26+L25 -> #DIV/0! | M26: =_xlfn.IFS(L26<80%,"A",L26<=95%,"B",L26>95%,"C") -> #DIV/0!
D27: =C27/C$73 -> #DIV/0! | E27: =D27+E26 -> #DIV/0! | F27: =IF(AND(E27<=0),"C",IF(E27<=0.8,"A",IF(E27<=0.95,"B","C"))) -> #DIV/0! | G27: =VLOOKUP(B27:B78,I$21:M$72,5,0) -> #N/A | K27: =J27/J$73 -> #DIV/0! | L27: =K27+L26 -> #DIV/0! | M27: =_xlfn.IFS(L27<80%,"A",L27<=95%,"B",L27>95%,"C") -> #DIV/0!
D28: =C28/C$73 -> #DIV/0! | E28: =D28+E27 -> #DIV/0! | F28: =IF(AND(E28<=0),"C",IF(E28<=0.8,"A",IF(E28<=0.95,"B","C"))) -> #DIV/0! | G28: =VLOOKUP(B28:B79,I$21:M$72,5,0) -> #N/A | K28: =J28/J$73 -> #DIV/0! | L28: =K28+L27 -> #DIV/0! | M28: =_xlfn.IFS(L28<80%,"A",L28<=95%,"B",L28>95%,"C") -> #DIV/0!
D29: =C29/C$73 -> #DIV/0! | E29: =D29+E28 -> #DIV/0! | F29: =IF(AND(E29<=0),"C",IF(E29<=0.8,"A",IF(E29<=0.95,"B","C"))) -> #DIV/0! | G29: =VLOOKUP(B29:B80,I$21:M$72,5,0) -> #N/A | K29: =J29/J$73 -> #DIV/0! | L29: =K29+L28 -> #DIV/0! | M29: =_xlfn.IFS(L29<80%,"A",L29<=95%,"B",L29>95%,"C") -> #DIV/0!
D30: =C30/C$73 -> #DIV/0! | E30: =D30+E29 -> #DIV/0! | F30: =IF(AND(E30<=0),"C",IF(E30<=0.8,"A",IF(E30<=0.95,"B","C"))) -> #DIV/0! | G30: =VLOOKUP(B30:B81,I$21:M$72,5,0) -> #N/A | K30: =J30/J$73 -> #DIV/0! | L30: =K30+L29 -> #DIV/0! | M30: =_xlfn.IFS(L30<80%,"A",L30<=95%,"B",L30>95%,"C") -> #DIV/0!
D31: =C31/C$73 -> #DIV/0! | E31: =D31+E30 -> #DIV/0! | F31: =IF(AND(E31<=0),"C",IF(E31<=0.8,"A",IF(E31<=0.95,"B","C"))) -> #DIV/0! | G31: =VLOOKUP(B31:B82,I$21:M$72,5,0) -> #N/A | K31: =J31/J$73 -> #DIV/0! | L31: =K31+L30 -> #DIV/0! | M31: =_xlfn.IFS(L31<80%,"A",L31<=95%,"B",L31>95%,"C") -> #DIV/0!
D32: =C32/C$73 -> #DIV/0! | E32: =D32+E31 -> #DIV/0! | F32: =IF(AND(E32<=0),"C",IF(E32<=0.8,"A",IF(E32<=0.95,"B","C"))) -> #DIV/0! | G32: =VLOOKUP(B32:B83,I$21:M$72,5,0) -> #N/A | K32: =J32/J$73 -> #DIV/0! | L32: =K32+L31 -> #DIV/0! | M32: =_xlfn.IFS(L32<80%,"A",L32<=95%,"B",L32>95%,"C") -> #DIV/0!
D33: =C33/C$73 -> #DIV/0! | E33: =D33+E32 -> #DIV/0! | F33: =IF(AND(E33<=0),"C",IF(E33<=0.8,"A",IF(E33<=0.95,"B","C"))) -> #DIV/0! | G33: =VLOOKUP(B33:B84,I$21:M$72,5,0) -> #N/A | K33: =J33/J$73 -> #DIV/0! | L33: =K33+L32 -> #DIV/0! | M33: =_xlfn.IFS(L33<80%,"A",L33<=95%,"B",L33>95%,"C") -> #DIV/0!
... D72: =C72/C$73 -> #DIV/0! | E72: =D72+E71 -> #DIV/0! | F72: =IF(AND(E72<=0),"C",IF(E72<=0.8,"A",IF(E72<=0.95,"B","C"))) -> #DIV/0! | G72: =VLOOKUP(B72:B123,I$21:M$72,5,0) -> #N/A | K72: =J72/J$73 -> #DIV/0! | L72: =K72+L71 -> #DIV/0! | M72: =_xlfn.IFS(L72<80%,"A",L72<=95%,"B",L72>95%,"C") -> #DIV/0!
C73: =SUM(C21:C72) -> 0 | D73: =SUM(D21:D72) -> #DIV/0! | J73: =SUM(J21:J72) -> 0 | K73: =SUM(K21:K72) -> #DIV/0!

Sheet АВС 5
B2: ОЧКИ
C3: Прибыль | D3: % прибыль | E3: Доля | F3: ABC прибыль | G3: ABC кол-во | J3: Кол-во | K3: % кол-во | L3: Доля | M3: ABC кол-во
B4: flip желтые Сул | C4: ='Юнит 5'!AL8 -> 2045.1121 | D4: =C4/C$17 -> 0.29004955 | E4: =D4 -> 0.29004955 | F4: =IF(AND(E4<=0),"C",IF(E4<=0.8,"A",IF(E4<=0.95,"B","C"))) -> A | G4: =VLOOKUP(B$4:B$16,I$4:M$16,5,0) -> A | I4: Черные с железкой Сул | J4: ='Юнит 5'!S3 -> 19 | K4: =J4/J$17 -> 0.27536232 | L4: =K4 -> 0.27536232 | M4: =_xlfn.IFS(L4<80%,"A",L4<=95%,"B",L4>95%,"C") -> A | P4: A | Q4: 0.8
B5: Черные с железкой Сул | C5: ='Юнит 5'!AL3 -> 1813.3318 | D5: =C5/C$17 -> 0.25717714 | E5: =E4+D5 -> 0.54722669 | F5: =IF(AND(E5<=0),"C",IF(E5<=0.8,"A",IF(E5<=0.95,"B","C"))) -> A | G5: =VLOOKUP(B$4:B$16,I$4:M$16,5,0) -> A | I5: flip желтые Сул | J5: ='Юнит 5'!S8 -> 14 | K5: =J5/J$17 -> 0.20289855 | L5: =L4+K5 -> 0.47826087 | M5: =_xlfn.IFS(L5<80%,"A",L5<=95%,"B",L5>95%,"C") -> A | P5: B | Q5: 0.15
B6: Qs желт Сул | C6: ='Юнит 5'!AL6 -> 1154.6045 | D6: =C6/C$17 -> 0.16375265 | E6: =E5+D6 -> 0.71097934 | F6: =IF(AND(E6<=0),"C",IF(E6<=0.8,"A",IF(E6<=0.95,"B","C"))) -> A | G6: =VLOOKUP(B$4:B$16,I$4:M$16,5,0) -> B | I6: MR8854 C2 Сул | J6: ='Юнит 5'!S9 -> 11 | K6: =J6/J$17 -> 0.15942029 | L6: =L5+K6 -> 0.63768116 | M6: =_xlfn.IFS(L6<80%,"A",L6<=95%,"B",L6>95%,"C") -> A | P6: C | Q6: 0.05
B7: MR Р1886 черн | C7: ='Юнит 5'!AL14 -> 826.78813 | D7: =C7/C$17 -> 0.11725985 | E7: =E6+D7 -> 0.82823919 | F7: =IF(AND(E7<=0),"C",IF(E7<=0.8,"A",IF(E7<=0.95,"B","C"))) -> B | G7: =VLOOKUP(B$4:B$16,I$4:M$16,5,0) -> C | I7: Qs черн Сул | J7: ='Юнит 5'!S4 -> 10 | K7: =J7/J$17 -> 0.14492754 | L7: =L6+K7 -> 0.7826087 | M7: =_xlfn.IFS(L7<80%,"A",L7<=95%,"B",L7>95%,"C") -> A
B8: MR Р1874 черн | C8: ='Юнит 5'!AL12 -> 783.16961 | D8: =C8/C$17 -> 0.11107362 | E8: =E7+D8 -> 0.93931281 | F8: =IF(AND(E8<=0),"C",IF(E8<=0.8,"A",IF(E8<=0.95,"B","C"))) -> B | G8: =VLOOKUP(B$4:B$16,I$4:M$16,5,0) -> B | I8: Qs син Сул | J8: ='Юнит 5'!S5 -> 3 | K8: =J8/J$17 -> 0.043478261 | L8: =L7+K8 -> 0.82608696 | M8: =_xlfn.IFS(L8<80%,"A",L8<=95%,"B",L8>95%,"C") -> B
B9: MR 1819 корич | C9: ='Юнит 5'!AL11 -> 758.76739 | D9: =C9/C$17 -> 0.10761275 | E9: =E8+D9 -> 1.0469256 | F9: =IF(AND(E9<=0),"C",IF(E9<=0.8,"A",IF(E9<=0.95,"B","C"))) -> C | G9: =VLOOKUP(B$4:B$16,I$4:M$16,5,0) -> B | I9: Qs желт Сул | J9: ='Юнит 5'!S6 -> 3 | K9: =J9/J$17 -> 0.043478261 | L9: =L8+K9 -> 0.86956522 | M9: =_xlfn.IFS(L9<80%,"A",L9<=95%,"B",L9>95%,"C") -> B
B10: MR Р1874 корич | C10: ='Юнит 5'!AL13 -> 508.76629 | D10: =C10/C$17 -> 0.072156161 | E10: =E9+D10 -> 1.1190817 | F10: =IF(AND(E10<=0),"C",IF(E10<=0.8,"A",IF(E10<=0.95,"B","C"))) -> C | G10: =VLOOKUP(B$4:B$16,I$4:M$16,5,0) -> C | I10: MR 1819 корич | J10: ='Юнит 5'!S11 -> 2 | K10: =J10/J$17 -> 0.028985507 | L10: =L9+K10 -> 0.89855072 | M10: =_xlfn.IFS(L10<80%,"A",L10<=95%,"B",L10>95%,"C") -> B
B11: MR 1819 черн | C11: ='Юнит 5'!AL10 -> 398.95943 | D11: =C11/C$17 -> 0.05658272 | E11: =E10+D11 -> 1.1756644 | F11: =IF(AND(E11<=0),"C",IF(E11<=0.8,"A",IF(E11<=0.95,"B","C"))) -> C | G11: =VLOOKUP(B$4:B$16,I$4:M$16,5,0) -> C | I11: MR Р1874 черн | J11: ='Юнит 5'!S12 -> 2 | K11: =J11/J$17 -> 0.028985507 | L11: =L10+K11 -> 0.92753623 | M11: =_xlfn.IFS(L11<80%,"A",L11<=95%,"B",L11>95%,"C") -> B
B12: MR8854 C2 Сул | C12: ='Юнит 5'!AL9 -> 297.0268 | D12: =C12/C$17 -> 0.042126049 | E12: =E11+D12 -> 1.2177905 | F12: =IF(AND(E12<=0),"C",IF(E12<=0.8,"A",IF(E12<=0.95,"B","C"))) -> C | G12: =VLOOKUP(B$4:B$16,I$4:M$16,5,0) -> A | I12: MR Р1886 черн | J12: ='Юнит 5'!S14 -> 2 | K12: =J12/J$17 -> 0.028985507 | L12: =L11+K12 -> 0.95652174 | M12: =_xlfn.IFS(L12<80%,"A",L12<=95%,"B",L12>95%,"C") -> C
B13: Qs черн Сул | C13: ='Юнит 5'!AL4 -> 177.70464 | D13: =C13/C$17 -> 0.025203094 | E13: =E12+D13 -> 1.2429936 | F13: =IF(AND(E13<=0),"C",IF(E13<=0.8,"A",IF(E13<=0.95,"B","C"))) -> C | G13: =VLOOKUP(B$4:B$16,I$4:M$16,5,0) -> A | I13: flip черные Сул | J13: ='Юнит 5'!S7 -> 1 | K13: =J13/J$17 -> 0.014492754 | L13: =L12+K13 -> 0.97101449 | M13: =_xlfn.IFS(L13<80%,"A",L13<=95%,"B",L13>95%,"C") -> C
B14: MR Р1886 корич | C14: ='Юнит 5'!AL15 -> -22.030753 | D14: =C14/C$17 -> -0.003124528 | E14: =E13+D14 -> 1.2398691 | F14: =IF(AND(E14<=0),"C",IF(E14<=0.8,"A",IF(E14<=0.95,"B","C"))) -> C | G14: =VLOOKUP(B$4:B$16,I$4:M$16,5,0) -> C | I14: MR 1819 черн | J14: ='Юнит 5'!S10 -> 1 | K14: =J14/J$17 -> 0.014492754 | L14: =L13+K14 -> 0.98550725 | M14: =_xlfn.IFS(L14<80%,"A",L14<=95%,"B",L14>95%,"C") -> C
B15: flip черные Сул | C15: ='Юнит 5'!AL7 -> -773.48176 | D15: =C15/C$17 -> -0.10969963 | E15: =E14+D15 -> 1.1301694 | F15: =IF(AND(E15<=0),"C",IF(E15<=0.8,"A",IF(E15<=0.95,"B","C"))) -> C | G15: =VLOOKUP(B$4:B$16,I$4:M$16,5,0) -> C | I15: MR Р1874 корич | J15: ='Юнит 5'!S13 -> 1 | K15: =J15/J$17 -> 0.014492754 | L15: =L14+K15 -> 1 | M15: =_xlfn.IFS(L15<80%,"A",L15<=95%,"B",L15>95%,"C") -> C
B16: Qs син Сул | C16: ='Юнит 5'!AL5 -> -917.81235 | D16: =C16/C$17 -> -0.13016942 | E16: =E15+D16 -> 1 | F16: =IF(AND(E16<=0),"C",IF(E16<=0.8,"A",IF(E16<=0.95,"B","C"))) -> C | G16: =VLOOKUP(B$4:B$16,I$4:M$16,5,0) -> B | I16: MR Р1886 корич | J16: ='Юнит 5'!S15 -> 0 | K16: =J16/J$17 -> 0 | L16: =L15+K16 -> 1 | M16: =_xlfn.IFS(L16<80%,"A",L16<=95%,"B",L16>95%,"C") -> C
C17: =SUM(C4:C16) -> 7050.9058 | D17: =SUM(D4:D16) -> 1 | J17: =SUM(J4:J16) -> 69 | K17: =SUM(K4:K16) -> 1
C20: Прибыль | D20: % прибыль | E20: Доля | F20: ABC прибыль | G20: ABC кол-во | J20: Кол-во | K20: % кол-во | L20: Доля | M20: ABC кол-во
D21: =C21/C$73 -> #DIV/0! | E21: =D21 -> #DIV/0! | F21: =IF(AND(E21<=0),"C",IF(E21<=0.8,"A",IF(E21<=0.95,"B","C"))) -> #DIV/0! | G21: =VLOOKUP(B21:B72,I$21:M$72,5,0) -> #N/A | K21: =J21/J$73 -> #DIV/0! | L21: =K21 -> #DIV/0! | M21: =_xlfn.IFS(L21<80%,"A",L21<=95%,"B",L21>95%,"C") -> #DIV/0!
D22: =C22/C$73 -> #DIV/0! | E22: =D22+E21 -> #DIV/0! | F22: =IF(AND(E22<=0),"C",IF(E22<=0.8,"A",IF(E22<=0.95,"B","C"))) -> #DIV/0! | G22: =VLOOKUP(B22:B73,I$21:M$72,5,0) -> #N/A | K22: =J22/J$73 -> #DIV/0! | L22: =K22+L21 -> #DIV/0! | M22: =_xlfn.IFS(L22<80%,"A",L22<=95%,"B",L22>95%,"C") -> #DIV/0!
D23: =C23/C$73 -> #DIV/0! | E23: =D23+E22 -> #DIV/0! | F23: =IF(AND(E23<=0),"C",IF(E23<=0.8,"A",IF(E23<=0.95,"B","C"))) -> #DIV/0! | G23: =VLOOKUP(B23:B74,I$21:M$72,5,0) -> #N/A | K23: =J23/J$73 -> #DIV/0! | L23: =K23+L22 -> #DIV/0! | M23: =_xlfn.IFS(L23<80%,"A",L23<=95%,"B",L23>95%,"C") -> #DIV/0!
D24: =C24/C$73 -> #DIV/0! | E24: =D24+E23 -> #DIV/0! | F24: =IF(AND(E24<=0),"C",IF(E24<=0.8,"A",IF(E24<=0.95,"B","C"))) -> #DIV/0! | G24: =VLOOKUP(B24:B75,I$21:M$72,5,0) -> #N/A | K24: =J24/J$73 -> #DIV/0! | L24: =K24+L23 -> #DIV/0! | M24: =_xlfn.IFS(L24<80%,"A",L24<=95%,"B",L24>95%,"C") -> #DIV/0!
D25: =C25/C$73 -> #DIV/0! | E25: =D25+E24 -> #DIV/0! | F25: =IF(AND(E25<=0),"C",IF(E25<=0.8,"A",IF(E25<=0.95,"B","C"))) -> #DIV/0! | G25: =VLOOKUP(B25:B76,I$21:M$72,5,0) -> #N/A | K25: =J25/J$73 -> #DIV/0! | L25: =K25+L24 -> #DIV/0! | M25: =_xlfn.IFS(L25<80%,"A",L25<=95%,"B",L25>95%,"C") -> #DIV/0!
D26: =C26/C$73 -> #DIV/0! | E26: =D26+E25 -> #DIV/0! | F26: =IF(AND(E26<=0),"C",IF(E26<=0.8,"A",IF(E26<=0.95,"B","C"))) -> #DIV/0! | G26: =VLOOKUP(B26:B77,I$21:M$72,5,0) -> #N/A | K26: =J26/J$73 -> #DIV/0! | L26: =K26+L25 -> #DIV/0! | M26: =_xlfn.IFS(L26<80%,"A",L26<=95%,"B",L26>95%,"C") -> #DIV/0!
D27: =C27/C$73 -> #DIV/0! | E27: =D27+E26 -> #DIV/0! | F27: =IF(AND(E27<=0),"C",IF(E27<=0.8,"A",IF(E27<=0.95,"B","C"))) -> #DIV/0! | G27: =VLOOKUP(B27:B78,I$21:M$72,5,0) -> #N/A | K27: =J27/J$73 -> #DIV/0! | L27: =K27+L26 -> #DIV/0! | M27: =_xlfn.IFS(L27<80%,"A",L27<=95%,"B",L27>95%,"C") -> #DIV/0!
D28: =C28/C$73 -> #DIV/0! | E28: =D28+E27 -> #DIV/0! | F28: =IF(AND(E28<=0),"C",IF(E28<=0.8,"A",IF(E28<=0.95,"B","C"))) -> #DIV/0! | G28: =VLOOKUP(B28:B79,I$21:M$72,5,0) -> #N/A | K28: =J28/J$73 -> #DIV/0! | L28: =K28+L27 -> #DIV/0! | M28: =_xlfn.IFS(L28<80%,"A",L28<=95%,"B",L28>95%,"C") -> #DIV/0!
D29: =C29/C$73 -> #DIV/0! | E29: =D29+E28 -> #DIV/0! | F29: =IF(AND(E29<=0),"C",IF(E29<=0.8,"A",IF(E29<=0.95,"B","C"))) -> #DIV/0! | G29: =VLOOKUP(B29:B80,I$21:M$72,5,0) -> #N/A | K29: =J29/J$73 -> #DIV/0! | L29: =K29+L28 -> #DIV/0! | M29: =_xlfn.IFS(L29<80%,"A",L29<=95%,"B",L29>95%,"C") -> #DIV/0!
D30: =C30/C$73 -> #DIV/0! | E30: =D30+E29 -> #DIV/0! | F30: =IF(AND(E30<=0),"C",IF(E30<=0.8,"A",IF(E30<=0.95,"B","C"))) -> #DIV/0! | G30: =VLOOKUP(B30:B81,I$21:M$72,5,0) -> #N/A | K30: =J30/J$73 -> #DIV/0! | L30: =K30+L29 -> #DIV/0! | M30: =_xlfn.IFS(L30<80%,"A",L30<=95%,"B",L30>95%,"C") -> #DIV/0!
D31: =C31/C$73 -> #DIV/0! | E31: =D31+E30 -> #DIV/0! | F31: =IF(AND(E31<=0),"C",IF(E31<=0.8,"A",IF(E31<=0.95,"B","C"))) -> #DIV/0! | G31: =VLOOKUP(B31:B82,I$21:M$72,5,0) -> #N/A | K31: =J31/J$73 -> #DIV/0! | L31: =K31+L30 -> #DIV/0! | M31: =_xlfn.IFS(L31<80%,"A",L31<=95%,"B",L31>95%,"C") -> #DIV/0!
D32: =C32/C$73 -> #DIV/0! | E32: =D32+E31 -> #DIV/0! | F32: =IF(AND(E32<=0),"C",IF(E32<=0.8,"A",IF(E32<=0.95,"B","C"))) -> #DIV/0! | G32: =VLOOKUP(B32:B83,I$21:M$72,5,0) -> #N/A | K32: =J32/J$73 -> #DIV/0! | L32: =K32+L31 -> #DIV/0! | M32: =_xlfn.IFS(L32<80%,"A",L32<=95%,"B",L32>95%,"C") -> #DIV/0!
D33: =C33/C$73 -> #DIV/0! | E33: =D33+E32 -> #DIV/0! | F33: =IF(AND(E33<=0),"C",IF(E33<=0.8,"A",IF(E33<=0.95,"B","C"))) -> #DIV/0! | G33: =VLOOKUP(B33:B84,I$21:M$72,5,0) -> #N/A | K33: =J33/J$73 -> #DIV/0! | L33: =K33+L32 -> #DIV/0! | M33: =_xlfn.IFS(L33<80%,"A",L33<=95%,"B",L33>95%,"C") -> #DIV/0!
... D72: =C72/C$73 -> #DIV/0! | E72: =D72+E71 -> #DIV/0! | F72: =IF(AND(E72<=0),"C",IF(E72<=0.8,"A",IF(E72<=0.95,"B","C"))) -> #DIV/0! | G72: =VLOOKUP(B72:B123,I$21:M$72,5,0) -> #N/A | K72: =J72/J$73 -> #DIV/0! | L72: =K72+L71 -> #DIV/0! | M72: =_xlfn.IFS(L72<80%,"A",L72<=95%,"B",L72>95%,"C") -> #DIV/0!
C73: =SUM(C21:C72) -> 0 | D73: =SUM(D21:D72) -> #DIV/0! | J73: =SUM(J21:J72) -> 0 | K73: =SUM(K21:K72) -> #DIV/0!

Sheet АВС 4
B2: ОЧКИ
C3: Прибыль | D3: % прибыль | E3: Доля | F3: ABC прибыль | G3: ABC кол-во | J3: Кол-во | K3: % кол-во | L3: Доля | M3: ABC кол-во
B4: Черные с железкой Сул | C4: ='Юнит 4'!AL3 -> 5677.8442 | D4: =C4/C$17 -> 0.415248 | E4: =D4 -> 0.415248 | F4: =IF(AND(E4<=0),"C",IF(E4<=0.8,"A",IF(E4<=0.95,"B","C"))) -> A | G4: =VLOOKUP(B$4:B$16,I$4:M$16,5,0) -> A | I4: Черные с железкой Сул | J4: ='Юнит 4'!S3 -> 21 | K4: =J4/J$17 -> 0.44680851 | L4: =K4 -> 0.44680851 | M4: =_xlfn.IFS(L4<80%,"A",L4<=95%,"B",L4>95%,"C") -> A | P4: A | Q4: 0.8
B5: flip желтые Сул | C5: ='Юнит 4'!AL8 -> 5497.2061 | D5: =C5/C$17 -> 0.40203707 | E5: =E4+D5 -> 0.81728507 | F5: =IF(AND(E5<=0),"C",IF(E5<=0.8,"A",IF(E5<=0.95,"B","C"))) -> B | G5: =VLOOKUP(B$4:B$16,I$4:M$16,5,0) -> A | I5: flip желтые Сул | J5: ='Юнит 4'!S8 -> 10 | K5: =J5/J$17 -> 0.21276596 | L5: =L4+K5 -> 0.65957447 | M5: =_xlfn.IFS(L5<80%,"A",L5<=95%,"B",L5>95%,"C") -> A | P5: B | Q5: 0.15
B6: Qs желт Сул | C6: ='Юнит 4'!AL6 -> 1821.9753 | D6: =C6/C$17 -> 0.1332498 | E6: =E5+D6 -> 0.95053487 | F6: =IF(AND(E6<=0),"C",IF(E6<=0.8,"A",IF(E6<=0.95,"B","C"))) -> C | G6: =VLOOKUP(B$4:B$16,I$4:M$16,5,0) -> B | I6: MR8854 C2 Сул | J6: ='Юнит 4'!S9 -> 9 | K6: =J6/J$17 -> 0.19148936 | L6: =L5+K6 -> 0.85106383 | M6: =_xlfn.IFS(L6<80%,"A",L6<=95%,"B",L6>95%,"C") -> B | P6: C | Q6: 0.05
B7: MR8854 C2 Сул | C7: ='Юнит 4'!AL9 -> 814.75132 | D7: =C7/C$17 -> 0.059586675 | E7: =E6+D7 -> 1.0101215 | F7: =IF(AND(E7<=0),"C",IF(E7<=0.8,"A",IF(E7<=0.95,"B","C"))) -> C | G7: =VLOOKUP(B$4:B$16,I$4:M$16,5,0) -> B | I7: Qs желт Сул | J7: ='Юнит 4'!S6 -> 4 | K7: =J7/J$17 -> 0.085106383 | L7: =L6+K7 -> 0.93617021 | M7: =_xlfn.IFS(L7<80%,"A",L7<=95%,"B",L7>95%,"C") -> B
B8: MR Р1886 корич | C8: ='Юнит 4'!AL15 -> 550.12526 | D8: =C8/C$17 -> 0.040233301 | E8: =E7+D8 -> 1.0503548 | F8: =IF(AND(E8<=0),"C",IF(E8<=0.8,"A",IF(E8<=0.95,"B","C"))) -> C | G8: =VLOOKUP(B$4:B$16,I$4:M$16,5,0) -> C | I8: MR Р1874 черн | J8: ='Юнит 4'!S12 -> 1 | K8: =J8/J$17 -> 0.021276596 | L8: =L7+K8 -> 0.95744681 | M8: =_xlfn.IFS(L8<80%,"A",L8<=95%,"B",L8>95%,"C") -> C
B9: MR Р1874 черн | C9: ='Юнит 4'!AL12 -> 373.65885 | D9: =C9/C$17 -> 0.027327466 | E9: =E8+D9 -> 1.0776823 | F9: =IF(AND(E9<=0),"C",IF(E9<=0.8,"A",IF(E9<=0.95,"B","C"))) -> C | G9: =VLOOKUP(B$4:B$16,I$4:M$16,5,0) -> C | I9: MR Р1874 корич | J9: ='Юнит 4'!S13 -> 1 | K9: =J9/J$17 -> 0.021276596 | L9: =L8+K9 -> 0.9787234 | M9: =_xlfn.IFS(L9<80%,"A",L9<=95%,"B",L9>95%,"C") -> C
B10: MR Р1874 корич | C10: ='Юнит 4'!AL13 -> 292.29359 | D10: =C10/C$17 -> 0.021376833 | E10: =E9+D10 -> 1.0990591 | F10: =IF(AND(E10<=0),"C",IF(E10<=0.8,"A",IF(E10<=0.95,"B","C"))) -> C | G10: =VLOOKUP(B$4:B$16,I$4:M$16,5,0) -> C | I10: MR Р1886 корич | J10: ='Юнит 4'!S15 -> 1 | K10: =J10/J$17 -> 0.021276596 | L10: =L9+K10 -> 1 | M10: =_xlfn.IFS(L10<80%,"A",L10<=95%,"B",L10>95%,"C") -> C
B11: MR 1819 корич | C11: ='Юнит 4'!AL11 -> -24.942493 | D11: =C11/C$17 -> -0.0018241643 | E11: =E10+D11 -> 1.097235 | F11: =IF(AND(E11<=0),"C",IF(E11<=0.8,"A",IF(E11<=0.95,"B","C"))) -> C | G11: =VLOOKUP(B$4:B$16,I$4:M$16,5,0) -> C | I11: Qs черн Сул | J11: ='Юнит 4'!S4 -> 0 | K11: =J11/J$17 -> 0 | L11: =L10+K11 -> 1 | M11: =_xlfn.IFS(L11<80%,"A",L11<=95%,"B",L11>95%,"C") -> C
B12: MR Р1886 черн | C12: ='Юнит 4'!AL14 -> -37.733516 | D12: =C12/C$17 -> -0.0027596331 | E12: =E11+D12 -> 1.0944753 | F12: =IF(AND(E12<=0),"C",IF(E12<=0.8,"A",IF(E12<=0.95,"B","C"))) -> C | G12: =VLOOKUP(B$4:B$16,I$4:M$16,5,0) -> C | I12: Qs син Сул | J12: ='Юнит 4'!S5 -> 0 | K12: =J12/J$17 -> 0 | L12: =L11+K12 -> 1 | M12: =_xlfn.IFS(L12<80%,"A",L12<=95%,"B",L12>95%,"C") -> C
B13: MR 1819 черн | C13: ='Юнит 4'!AL10 -> -121.34249 | D13: =C13/C$17 -> -0.008874359 | E13: =E12+D13 -> 1.085601 | F13: =IF(AND(E13<=0),"C",IF(E13<=0.8,"A",IF(E13<=0.95,"B","C"))) -> C | G13: =VLOOKUP(B$4:B$16,I$4:M$16,5,0) -> C | I13: flip черные Сул | J13: ='Юнит 4'!S7 -> 0 | K13: =J13/J$17 -> 0 | L13: =L12+K13 -> 1 | M13: =_xlfn.IFS(L13<80%,"A",L13<=95%,"B",L13>95%,"C") -> C
B14: Qs черн Сул | C14: ='Юнит 4'!AL4 -> -294.91162 | D14: =C14/C$17 -> -0.021568302 | E14: =E13+D14 -> 1.0640327 | F14: =IF(AND(E14<=0),"C",IF(E14<=0.8,"A",IF(E14<=0.95,"B","C"))) -> C | G14: =VLOOKUP(B$4:B$16,I$4:M$16,5,0) -> C | I14: MR 1819 черн | J14: ='Юнит 4'!S10 -> 0 | K14: =J14/J$17 -> 0 | L14: =L13+K14 -> 1 | M14: =_xlfn.IFS(L14<80%,"A",L14<=95%,"B",L14>95%,"C") -> C
B15: Qs син Сул | C15: ='Юнит 4'!AL5 -> -383.11077 | D15: =C15/C$17 -> -0.028018729 | E15: =E14+D15 -> 1.036014 | F15: =IF(AND(E15<=0),"C",IF(E15<=0.8,"A",IF(E15<=0.95,"B","C"))) -> C | G15: =VLOOKUP(B$4:B$16,I$4:M$16,5,0) -> C | I15: MR 1819 корич | J15: ='Юнит 4'!S11 -> 0 | K15: =J15/J$17 -> 0 | L15: =L14+K15 -> 1 | M15: =_xlfn.IFS(L15<80%,"A",L15<=95%,"B",L15>95%,"C") -> C
B16: flip черные Сул | C16: ='Юнит 4'!AL7 -> -492.43252 | D16: =C16/C$17 -> -0.036013954 | E16: =E15+D16 -> 1 | F16: =IF(AND(E16<=0),"C",IF(E16<=0.8,"A",IF(E16<=0.95,"B","C"))) -> C | G16: =VLOOKUP(B$4:B$16,I$4:M$16,5,0) -> C | I16: MR Р1886 черн | J16: ='Юнит 4'!S14 -> 0 | K16: =J16/J$17 -> 0 | L16: =L15+K16 -> 1 | M16: =_xlfn.IFS(L16<80%,"A",L16<=95%,"B",L16>95%,"C") -> C
C17: =SUM(C4:C16) -> 13673.381 | D17: =SUM(D4:D16) -> 1 | J17: =SUM(J4:J16) -> 47 | K17: =SUM(K4:K16) -> 1
C20: Прибыль | D20: % прибыль | E20: Доля | F20: ABC прибыль | G20: ABC кол-во | J20: Кол-во | K20: % кол-во | L20: Доля | M20: ABC кол-во
D21: =C21/C$73 -> #DIV/0! | E21: =D21 -> #DIV/0! | F21: =IF(AND(E21<=0),"C",IF(E21<=0.8,"A",IF(E21<=0.95,"B","C"))) -> #DIV/0! | G21: =VLOOKUP(B21:B72,I$21:M$72,5,0) -> #N/A | K21: =J21/J$73 -> #DIV/0! | L21: =K21 -> #DIV/0! | M21: =_xlfn.IFS(L21<80%,"A",L21<=95%,"B",L21>95%,"C") -> #DIV/0!
D22: =C22/C$73 -> #DIV/0! | E22: =D22+E21 -> #DIV/0! | F22: =IF(AND(E22<=0),"C",IF(E22<=0.8,"A",IF(E22<=0.95,"B","C"))) -> #DIV/0! | G22: =VLOOKUP(B22:B73,I$21:M$72,5,0) -> #N/A | K22: =J22/J$73 -> #DIV/0! | L22: =K22+L21 -> #DIV/0! | M22: =_xlfn.IFS(L22<80%,"A",L22<=95%,"B",L22>95%,"C") -> #DIV/0!
D23: =C23/C$73 -> #DIV/0! | E23: =D23+E22 -> #DIV/0! | F23: =IF(AND(E23<=0),"C",IF(E23<=0.8,"A",IF(E23<=0.95,"B","C"))) -> #DIV/0! | G23: =VLOOKUP(B23:B74,I$21:M$72,5,0) -> #N/A | K23: =J23/J$73 -> #DIV/0! | L23: =K23+L22 -> #DIV/0! | M23: =_xlfn.IFS(L23<80%,"A",L23<=95%,"B",L23>95%,"C") -> #DIV/0!
D24: =C24/C$73 -> #DIV/0! | E24: =D24+E23 -> #DIV/0! | F24: =IF(AND(E24<=0),"C",IF(E24<=0.8,"A",IF(E24<=0.95,"B","C"))) -> #DIV/0! | G24: =VLOOKUP(B24:B75,I$21:M$72,5,0) -> #N/A | K24: =J24/J$73 -> #DIV/0! | L24: =K24+L23 -> #DIV/0! | M24: =_xlfn.IFS(L24<80%,"A",L24<=95%,"B",L24>95%,"C") -> #DIV/0!
D25: =C25/C$73 -> #DIV/0! | E25: =D25+E24 -> #DIV/0! | F25: =IF(AND(E25<=0),"C",IF(E25<=0.8,"A",IF(E25<=0.95,"B","C"))) -> #DIV/0! | G25: =VLOOKUP(B25:B76,I$21:M$72,5,0) -> #N/A | K25: =J25/J$73 -> #DIV/0! | L25: =K25+L24 -> #DIV/0! | M25: =_xlfn.IFS(L25<80%,"A",L25<=95%,"B",L25>95%,"C") -> #DIV/0!
D26: =C26/C$73 -> #DIV/0! | E26: =D26+E25 -> #DIV/0! | F26: =IF(AND(E26<=0),"C",IF(E26<=0.8,"A",IF(E26<=0.95,"B","C"))) -> #DIV/0! | G26: =VLOOKUP(B26:B77,I$21:M$72,5,0) -> #N/A | K26: =J26/J$73 -> #DIV/0! | L26: =K26+L25 -> #DIV/0! | M26: =_xlfn.IFS(L26<80%,"A",L26<=95%,"B",L26>95%,"C") -> #DIV/0!
D27: =C27/C$73 -> #DIV/0! | E27: =D27+E26 -> #DIV/0! | F27: =IF(AND(E27<=0),"C",IF(E27<=0.8,"A",IF(E27<=0.95,"B","C"))) -> #DIV/0! | G27: =VLOOKUP(B27:B78,I$21:M$72,5,0) -> #N/A | K27: =J27/J$73 -> #DIV/0! | L27: =K27+L26 -> #DIV/0! | M27: =_xlfn.IFS(L27<80%,"A",L27<=95%,"B",L27>95%,"C") -> #DIV/0!
D28: =C28/C$73 -> #DIV/0! | E28: =D28+E27 -> #DIV/0! | F28: =IF(AND(E28<=0),"C",IF(E28<=0.8,"A",IF(E28<=0.95,"B","C"))) -> #DIV/0! | G28: =VLOOKUP(B28:B79,I$21:M$72,5,0) -> #N/A | K28: =J28/J$73 -> #DIV/0! | L28: =K28+L27 -> #DIV/0! | M28: =_xlfn.IFS(L28<80%,"A",L28<=95%,"B",L28>95%,"C") -> #DIV/0!
D29: =C29/C$73 -> #DIV/0! | E29: =D29+E28 -> #DIV/0! | F29: =IF(AND(E29<=0),"C",IF(E29<=0.8,"A",IF(E29<=0.95,"B","C"))) -> #DIV/0! | G29: =VLOOKUP(B29:B80,I$21:M$72,5,0) -> #N/A | K29: =J29/J$73 -> #DIV/0! | L29: =K29+L28 -> #DIV/0! | M29: =_xlfn.IFS(L29<80%,"A",L29<=95%,"B",L29>95%,"C") -> #DIV/0!
D30: =C30/C$73 -> #DIV/0! | E30: =D30+E29 -> #DIV/0! | F30: =IF(AND(E30<=0),"C",IF(E30<=0.8,"A",IF(E30<=0.95,"B","C"))) -> #DIV/0! | G30: =VLOOKUP(B30:B81,I$21:M$72,5,0) -> #N/A | K30: =J30/J$73 -> #DIV/0! | L30: =K30+L29 -> #DIV/0! | M30: =_xlfn.IFS(L30<80%,"A",L30<=95%,"B",L30>95%,"C") -> #DIV/0!
D31: =C31/C$73 -> #DIV/0! | E31: =D31+E30 -> #DIV/0! | F31: =IF(AND(E31<=0),"C",IF(E31<=0.8,"A",IF(E31<=0.95,"B","C"))) -> #DIV/0! | G31: =VLOOKUP(B31:B82,I$21:M$72,5,0) -> #N/A | K31: =J31/J$73 -> #DIV/0! | L31: =K31+L30 -> #DIV/0! | M31: =_xlfn.IFS(L31<80%,"A",L31<=95%,"B",L31>95%,"C") -> #DIV/0!
D32: =C32/C$73 -> #DIV/0! | E32: =D32+E31 -> #DIV/0! | F32: =IF(AND(E32<=0),"C",IF(E32<=0.8,"A",IF(E32<=0.95,"B","C"))) -> #DIV/0! | G32: =VLOOKUP(B32:B83,I$21:M$72,5,0) -> #N/A | K32: =J32/J$73 -> #DIV/0! | L32: =K32+L31 -> #DIV/0! | M32: =_xlfn.IFS(L32<80%,"A",L32<=95%,"B",L32>95%,"C") -> #DIV/0!
D33: =C33/C$73 -> #DIV/0! | E33: =D33+E32 -> #DIV/0! | F33: =IF(AND(E33<=0),"C",IF(E33<=0.8,"A",IF(E33<=0.95,"B","C"))) -> #DIV/0! | G33: =VLOOKUP(B33:B84,I$21:M$72,5,0) -> #N/A | K33: =J33/J$73 -> #DIV/0! | L33: =K33+L32 -> #DIV/0! | M33: =_xlfn.IFS(L33<80%,"A",L33<=95%,"B",L33>95%,"C") -> #DIV/0!
... D72: =C72/C$73 -> #DIV/0! | E72: =D72+E71 -> #DIV/0! | F72: =IF(AND(E72<=0),"C",IF(E72<=0.8,"A",IF(E72<=0.95,"B","C"))) -> #DIV/0! | G72: =VLOOKUP(B72:B123,I$21:M$72,5,0) -> #N/A | K72: =J72/J$73 -> #DIV/0! | L72: =K72+L71 -> #DIV/0! | M72: =_xlfn.IFS(L72<80%,"A",L72<=95%,"B",L72>95%,"C") -> #DIV/0!
C73: =SUM(C21:C72) -> 0 | D73: =SUM(D21:D72) -> #DIV/0! | J73: =SUM(J21:J72) -> 0 | K73: =SUM(K21:K72) -> #DIV/0!

Sheet АВС 3
B2: ОЧКИ
C3: Прибыль | D3: % прибыль | E3: Доля | F3: ABC прибыль | G3: ABC кол-во | J3: Кол-во | K3: % кол-во | L3: Доля | M3: ABC кол-во
B4: flip желтые Сул | C4: ='Юнит 3'!AL8 -> 9416.7452 | D4: =C4/C$17 -> 0.60135716 | E4: =D4 -> 0.60135716 | F4: =IF(AND(E4<=0),"C",IF(E4<=0.8,"A",IF(E4<=0.95,"B","C"))) -> A | G4: =VLOOKUP(B$4:B$16,I$4:M$16,5,0) -> A | I4: flip желтые Сул | J4: ='Юнит 3'!S8 -> 22 | K4: =J4/J$17 -> 0.45833333 | L4: =K4 -> 0.45833333 | M4: =_xlfn.IFS(L4<80%,"A",L4<=95%,"B",L4>95%,"C") -> A | P4: A | Q4: 0.8
B5: Черные с железкой Сул | C5: ='Юнит 3'!AL3 -> 2756.9039 | D5: =C5/C$17 -> 0.176057 | E5: =E4+D5 -> 0.77741417 | F5: =IF(AND(E5<=0),"C",IF(E5<=0.8,"A",IF(E5<=0.95,"B","C"))) -> A | G5: =VLOOKUP(B$4:B$16,I$4:M$16,5,0) -> A | I5: Черные с железкой Сул | J5: ='Юнит 3'!S3 -> 10 | K5: =J5/J$17 -> 0.20833333 | L5: =L4+K5 -> 0.66666667 | M5: =_xlfn.IFS(L5<80%,"A",L5<=95%,"B",L5>95%,"C") -> A | P5: B | Q5: 0.15
B6: Qs желт Сул | C6: ='Юнит 3'!AL6 -> 1819.1694 | D6: =C6/C$17 -> 0.1161729 | E6: =E5+D6 -> 0.89358706 | F6: =IF(AND(E6<=0),"C",IF(E6<=0.8,"A",IF(E6<=0.95,"B","C"))) -> B | G6: =VLOOKUP(B$4:B$16,I$4:M$16,5,0) -> A | I6: Qs желт Сул | J6: ='Юнит 3'!S6 -> 6 | K6: =J6/J$17 -> 0.125 | L6: =L5+K6 -> 0.79166667 | M6: =_xlfn.IFS(L6<80%,"A",L6<=95%,"B",L6>95%,"C") -> A | P6: C | Q6: 0.05
B7: MR Р1886 черн | C7: ='Юнит 3'!AL14 -> 1226.3922 | D7: =C7/C$17 -> 0.078317901 | E7: =E6+D7 -> 0.97190497 | F7: =IF(AND(E7<=0),"C",IF(E7<=0.8,"A",IF(E7<=0.95,"B","C"))) -> C | G7: =VLOOKUP(B$4:B$16,I$4:M$16,5,0) -> B | I7: MR8854 C2 Сул | J7: ='Юнит 3'!S9 -> 3 | K7: =J7/J$17 -> 0.0625 | L7: =L6+K7 -> 0.85416667 | M7: =_xlfn.IFS(L7<80%,"A",L7<=95%,"B",L7>95%,"C") -> B
B8: MR Р1886 корич | C8: ='Юнит 3'!AL15 -> 494.45817 | D8: =C8/C$17 -> 0.031576299 | E8: =E7+D8 -> 1.0034813 | F8: =IF(AND(E8<=0),"C",IF(E8<=0.8,"A",IF(E8<=0.95,"B","C"))) -> C | G8: =VLOOKUP(B$4:B$16,I$4:M$16,5,0) -> C | I8: MR Р1886 черн | J8: ='Юнит 3'!S14 -> 3 | K8: =J8/J$17 -> 0.0625 | L8: =L7+K8 -> 0.91666667 | M8: =_xlfn.IFS(L8<80%,"A",L8<=95%,"B",L8>95%,"C") -> B
B9: MR Р1874 корич | C9: ='Юнит 3'!AL13 -> 500.15133 | D9: =C9/C$17 -> 0.031939867 | E9: =E8+D9 -> 1.0354211 | F9: =IF(AND(E9<=0),"C",IF(E9<=0.8,"A",IF(E9<=0.95,"B","C"))) -> C | G9: =VLOOKUP(B$4:B$16,I$4:M$16,5,0) -> C | I9: Qs син Сул | J9: ='Юнит 3'!S5 -> 1 | K9: =J9/J$17 -> 0.020833333 | L9: =L8+K9 -> 0.9375 | M9: =_xlfn.IFS(L9<80%,"A",L9<=95%,"B",L9>95%,"C") -> B
B10: Qs син Сул | C10: ='Юнит 3'!AL5 -> 470.44553 | D10: =C10/C$17 -> 0.030042842 | E10: =E9+D10 -> 1.065464 | F10: =IF(AND(E10<=0),"C",IF(E10<=0.8,"A",IF(E10<=0.95,"B","C"))) -> C | G10: =VLOOKUP(B$4:B$16,I$4:M$16,5,0) -> B | I10: MR 1819 черн | J10: ='Юнит 3'!S10 -> 1 | K10: =J10/J$17 -> 0.020833333 | L10: =L9+K10 -> 0.95833333 | M10: =_xlfn.IFS(L10<80%,"A",L10<=95%,"B",L10>95%,"C") -> C
B11: MR 1819 черн | C11: ='Юнит 3'!AL10 -> 371.88742 | D11: =C11/C$17 -> 0.023748881 | E11: =E10+D11 -> 1.0892129 | F11: =IF(AND(E11<=0),"C",IF(E11<=0.8,"A",IF(E11<=0.95,"B","C"))) -> C | G11: =VLOOKUP(B$4:B$16,I$4:M$16,5,0) -> C | I11: MR Р1874 корич | J11: ='Юнит 3'!S13 -> 1 | K11: =J11/J$17 -> 0.020833333 | L11: =L10+K11 -> 0.97916667 | M11: =_xlfn.IFS(L11<80%,"A",L11<=95%,"B",L11>95%,"C") -> C
B12: MR 1819 корич | C12: ='Юнит 3'!AL11 -> -130.29333 | D12: =C12/C$17 -> -0.0083205849 | E12: =E11+D12 -> 1.0808923 | F12: =IF(AND(E12<=0),"C",IF(E12<=0.8,"A",IF(E12<=0.95,"B","C"))) -> C | G12: =VLOOKUP(B$4:B$16,I$4:M$16,5,0) -> C | I12: Qs черн Сул | J12: ='Юнит 3'!S4 -> 0 | K12: =J12/J$17 -> 0 | L12: =L11+K12 -> 0.97916667 | M12: =_xlfn.IFS(L12<80%,"A",L12<=95%,"B",L12>95%,"C") -> C
B13: Qs черн Сул | C13: ='Юнит 3'!AL4 -> -170.3584 | D13: =C13/C$17 -> -0.010879156 | E13: =E12+D13 -> 1.0700131 | F13: =IF(AND(E13<=0),"C",IF(E13<=0.8,"A",IF(E13<=0.95,"B","C"))) -> C | G13: =VLOOKUP(B$4:B$16,I$4:M$16,5,0) -> C | I13: flip черные Сул | J13: ='Юнит 3'!S7 -> 0 | K13: =J13/J$17 -> 0 | L13: =L12+K13 -> 0.97916667 | M13: =_xlfn.IFS(L13<80%,"A",L13<=95%,"B",L13>95%,"C") -> C
B14: MR Р1874 черн | C14: ='Юнит 3'!AL12 -> -236.5805 | D14: =C14/C$17 -> -0.015108126 | E14: =E13+D14 -> 1.054905 | F14: =IF(AND(E14<=0),"C",IF(E14<=0.8,"A",IF(E14<=0.95,"B","C"))) -> C | G14: =VLOOKUP(B$4:B$16,I$4:M$16,5,0) -> C | I14: MR 1819 корич | J14: ='Юнит 3'!S11 -> 0 | K14: =J14/J$17 -> 0 | L14: =L13+K14 -> 0.97916667 | M14: =_xlfn.IFS(L14<80%,"A",L14<=95%,"B",L14>95%,"C") -> C
B15: flip черные Сул | C15: ='Юнит 3'!AL7 -> -293.38406 | D15: =C15/C$17 -> -0.018735625 | E15: =E14+D15 -> 1.0361694 | F15: =IF(AND(E15<=0),"C",IF(E15<=0.8,"A",IF(E15<=0.95,"B","C"))) -> C | G15: =VLOOKUP(B$4:B$16,I$4:M$16,5,0) -> C | I15: MR Р1874 черн | J15: ='Юнит 3'!S12 -> 0 | K15: =J15/J$17 -> 0 | L15: =L14+K15 -> 0.97916667 | M15: =_xlfn.IFS(L15<80%,"A",L15<=95%,"B",L15>95%,"C") -> C
B16: MR8854 C2 Сул | C16: ='Юнит 3'!AL9 -> -566.38165 | D16: =C16/C$17 -> -0.036169361 | E16: =E15+D16 -> 1 | F16: =IF(AND(E16<=0),"C",IF(E16<=0.8,"A",IF(E16<=0.95,"B","C"))) -> C | G16: =VLOOKUP(B$4:B$16,I$4:M$16,5,0) -> B | I16: MR Р1886 корич | J16: ='Юнит 3'!S15 -> 1 | K16: =J16/J$17 -> 0.020833333 | L16: =L15+K16 -> 1 | M16: =_xlfn.IFS(L16<80%,"A",L16<=95%,"B",L16>95%,"C") -> C
C17: =SUM(C4:C16) -> 15659.155 | D17: =SUM(D4:D16) -> 1 | J17: =SUM(J4:J16) -> 48 | K17: =SUM(K4:K16) -> 1
C20: Прибыль | D20: % прибыль | E20: Доля | F20: ABC прибыль | G20: ABC кол-во | J20: Кол-во | K20: % кол-во | L20: Доля | M20: ABC кол-во
D21: =C21/C$73 -> #DIV/0! | E21: =D21 -> #DIV/0! | F21: =IF(AND(E21<=0),"C",IF(E21<=0.8,"A",IF(E21<=0.95,"B","C"))) -> #DIV/0! | G21: =VLOOKUP(B21:B72,I$21:M$72,5,0) -> #N/A | K21: =J21/J$73 -> #DIV/0! | L21: =K21 -> #DIV/0! | M21: =_xlfn.IFS(L21<80%,"A",L21<=95%,"B",L21>95%,"C") -> #DIV/0!
D22: =C22/C$73 -> #DIV/0! | E22: =D22+E21 -> #DIV/0! | F22: =IF(AND(E22<=0),"C",IF(E22<=0.8,"A",IF(E22<=0.95,"B","C"))) -> #DIV/0! | G22: =VLOOKUP(B22:B73,I$21:M$72,5,0) -> #N/A | K22: =J22/J$73 -> #DIV/0! | L22: =K22+L21 -> #DIV/0! | M22: =_xlfn.IFS(L22<80%,"A",L22<=95%,"B",L22>95%,"C") -> #DIV/0!
D23: =C23/C$73 -> #DIV/0! | E23: =D23+E22 -> #DIV/0! | F23: =IF(AND(E23<=0),"C",IF(E23<=0.8,"A",IF(E23<=0.95,"B","C"))) -> #DIV/0! | G23: =VLOOKUP(B23:B74,I$21:M$72,5,0) -> #N/A | K23: =J23/J$73 -> #DIV/0! | L23: =K23+L22 -> #DIV/0! | M23: =_xlfn.IFS(L23<80%,"A",L23<=95%,"B",L23>95%,"C") -> #DIV/0!
D24: =C24/C$73 -> #DIV/0! | E24: =D24+E23 -> #DIV/0! | F24: =IF(AND(E24<=0),"C",IF(E24<=0.8,"A",IF(E24<=0.95,"B","C"))) -> #DIV/0! | G24: =VLOOKUP(B24:B75,I$21:M$72,5,0) -> #N/A | K24: =J24/J$73 -> #DIV/0! | L24: =K24+L23 -> #DIV/0! | M24: =_xlfn.IFS(L24<80%,"A",L24<=95%,"B",L24>95%,"C") -> #DIV/0!
D25: =C25/C$73 -> #DIV/0! | E25: =D25+E24 -> #DIV/0! | F25: =IF(AND(E25<=0),"C",IF(E25<=0.8,"A",IF(E25<=0.95,"B","C"))) -> #DIV/0! | G25: =VLOOKUP(B25:B76,I$21:M$72,5,0) -> #N/A | K25: =J25/J$73 -> #DIV/0! | L25: =K25+L24 -> #DIV/0! | M25: =_xlfn.IFS(L25<80%,"A",L25<=95%,"B",L25>95%,"C") -> #DIV/0!
D26: =C26/C$73 -> #DIV/0! | E26: =D26+E25 -> #DIV/0! | F26: =IF(AND(E26<=0),"C",IF(E26<=0.8,"A",IF(E26<=0.95,"B","C"))) -> #DIV/0! | G26: =VLOOKUP(B26:B77,I$21:M$72,5,0) -> #N/A | K26: =J26/J$73 -> #DIV/0! | L26: =K26+L25 -> #DIV/0! | M26: =_xlfn.IFS(L26<80%,"A",L26<=95%,"B",L26>95%,"C") -> #DIV/0!
D27: =C27/C$73 -> #DIV/0! | E27: =D27+E26 -> #DIV/0! | F27: =IF(AND(E27<=0),"C",IF(E27<=0.8,"A",IF(E27<=0.95,"B","C"))) -> #DIV/0! | G27: =VLOOKUP(B27:B78,I$21:M$72,5,0) -> #N/A | K27: =J27/J$73 -> #DIV/0! | L27: =K27+L26 -> #DIV/0! | M27: =_xlfn.IFS(L27<80%,"A",L27<=95%,"B",L27>95%,"C") -> #DIV/0!
D28: =C28/C$73 -> #DIV/0! | E28: =D28+E27 -> #DIV/0! | F28: =IF(AND(E28<=0),"C",IF(E28<=0.8,"A",IF(E28<=0.95,"B","C"))) -> #DIV/0! | G28: =VLOOKUP(B28:B79,I$21:M$72,5,0) -> #N/A | K28: =J28/J$73 -> #DIV/0! | L28: =K28+L27 -> #DIV/0! | M28: =_xlfn.IFS(L28<80%,"A",L28<=95%,"B",L28>95%,"C") -> #DIV/0!
D29: =C29/C$73 -> #DIV/0! | E29: =D29+E28 -> #DIV/0! | F29: =IF(AND(E29<=0),"C",IF(E29<=0.8,"A",IF(E29<=0.95,"B","C"))) -> #DIV/0! | G29: =VLOOKUP(B29:B80,I$21:M$72,5,0) -> #N/A | K29: =J29/J$73 -> #DIV/0! | L29: =K29+L28 -> #DIV/0! | M29: =_xlfn.IFS(L29<80%,"A",L29<=95%,"B",L29>95%,"C") -> #DIV/0!
D30: =C30/C$73 -> #DIV/0! | E30: =D30+E29 -> #DIV/0! | F30: =IF(AND(E30<=0),"C",IF(E30<=0.8,"A",IF(E30<=0.95,"B","C"))) -> #DIV/0! | G30: =VLOOKUP(B30:B81,I$21:M$72,5,0) -> #N/A | K30: =J30/J$73 -> #DIV/0! | L30: =K30+L29 -> #DIV/0! | M30: =_xlfn.IFS(L30<80%,"A",L30<=95%,"B",L30>95%,"C") -> #DIV/0!
D31: =C31/C$73 -> #DIV/0! | E31: =D31+E30 -> #DIV/0! | F31: =IF(AND(E31<=0),"C",IF(E31<=0.8,"A",IF(E31<=0.95,"B","C"))) -> #DIV/0! | G31: =VLOOKUP(B31:B82,I$21:M$72,5,0) -> #N/A | K31: =J31/J$73 -> #DIV/0! | L31: =K31+L30 -> #DIV/0! | M31: =_xlfn.IFS(L31<80%,"A",L31<=95%,"B",L31>95%,"C") -> #DIV/0!
D32: =C32/C$73 -> #DIV/0! | E32: =D32+E31 -> #DIV/0! | F32: =IF(AND(E32<=0),"C",IF(E32<=0.8,"A",IF(E32<=0.95,"B","C"))) -> #DIV/0! | G32: =VLOOKUP(B32:B83,I$21:M$72,5,0) -> #N/A | K32: =J32/J$73 -> #DIV/0! | L32: =K32+L31 -> #DIV/0! | M32: =_xlfn.IFS(L32<80%,"A",L32<=95%,"B",L32>95%,"C") -> #DIV/0!
D33: =C33/C$73 -> #DIV/0! | E33: =D33+E32 -> #DIV/0! | F33: =IF(AND(E33<=0),"C",IF(E33<=0.8,"A",IF(E33<=0.95,"B","C"))) -> #DIV/0! | G33: =VLOOKUP(B33:B84,I$21:M$72,5,0) -> #N/A | K33: =J33/J$73 -> #DIV/0! | L33: =K33+L32 -> #DIV/0! | M33: =_xlfn.IFS(L33<80%,"A",L33<=95%,"B",L33>95%,"C") -> #DIV/0!
... D72: =C72/C$73 -> #DIV/0! | E72: =D72+E71 -> #DIV/0! | F72: =IF(AND(E72<=0),"C",IF(E72<=0.8,"A",IF(E72<=0.95,"B","C"))) -> #DIV/0! | G72: =VLOOKUP(B72:B123,I$21:M$72,5,0) -> #N/A | K72: =J72/J$73 -> #DIV/0! | L72: =K72+L71 -> #DIV/0! | M72: =_xlfn.IFS(L72<80%,"A",L72<=95%,"B",L72>95%,"C") -> #DIV/0!
C73: =SUM(C21:C72) -> 0 | D73: =SUM(D21:D72) -> #DIV/0! | J73: =SUM(J21:J72) -> 0 | K73: =SUM(K21:K72) -> #DIV/0!

Sheet АВС 2
B2: ОЧКИ
C3: Прибыль | D3: % прибыль | E3: Доля | F3: ABC прибыль | G3: ABC кол-во | J3: Кол-во | K3: % кол-во | L3: Доля | M3: ABC кол-во
B4: flip желтые Сул | C4: ='Юнит 2'!AL8 -> 10465.83 | D4: =C4/C$17 -> 0.79413735 | E4: =D4 -> 0.79413735 | F4: =IF(AND(E4<=0),"C",IF(E4<=0.8,"A",IF(E4<=0.95,"B","C"))) -> A | G4: =VLOOKUP(B$4:B$16,I$4:M$16,5,0) -> A | I4: flip желтые Сул | J4: ='Юнит 2'!S8 -> 26 | K4: =J4/J$17 -> 0.61904762 | L4: =K4 -> 0.61904762 | M4: =_xlfn.IFS(L4<80%,"A",L4<=95%,"B",L4>95%,"C") -> A | P4: A | Q4: 0.8
B5: Черные с железкой Сул | C5: ='Юнит 2'!AL3 -> 2587.3534 | D5: =C5/C$17 -> 0.19632594 | E5: =E4+D5 -> 0.9904633 | F5: =IF(AND(E5<=0),"C",IF(E5<=0.8,"A",IF(E5<=0.95,"B","C"))) -> C | G5: =VLOOKUP(B$4:B$16,I$4:M$16,5,0) -> B | I5: Черные с железкой Сул | J5: ='Юнит 2'!S3 -> 8 | K5: =J5/J$17 -> 0.19047619 | L5: =L4+K5 -> 0.80952381 | M5: =_xlfn.IFS(L5<80%,"A",L5<=95%,"B",L5>95%,"C") -> B | P5: B | Q5: 0.15
B6: MR Р1886 корич | C6: ='Юнит 2'!AL15 -> 522.96997 | D6: =C6/C$17 -> 0.039682469 | E6: =E5+D6 -> 1.0301458 | F6: =IF(AND(E6<=0),"C",IF(E6<=0.8,"A",IF(E6<=0.95,"B","C"))) -> C | G6: =VLOOKUP(B$4:B$16,I$4:M$16,5,0) -> C | I6: Qs желт Сул | J6: ='Юнит 2'!S6 -> 3 | K6: =J6/J$17 -> 0.071428571 | L6: =L5+K6 -> 0.88095238 | M6: =_xlfn.IFS(L6<80%,"A",L6<=95%,"B",L6>95%,"C") -> B | P6: C | Q6: 0.05
B7: MR Р1874 корич | C7: ='Юнит 2'!AL13 -> 499.52107 | D7: =C7/C$17 -> 0.037903188 | E7: =E6+D7 -> 1.068049 | F7: =IF(AND(E7<=0),"C",IF(E7<=0.8,"A",IF(E7<=0.95,"B","C"))) -> C | G7: =VLOOKUP(B$4:B$16,I$4:M$16,5,0) -> C | I7: MR8854 C2 Сул | J7: ='Юнит 2'!S9 -> 2 | K7: =J7/J$17 -> 0.047619048 | L7: =L6+K7 -> 0.92857143 | M7: =_xlfn.IFS(L7<80%,"A",L7<=95%,"B",L7>95%,"C") -> B
B8: MR Р1886 черн | C8: ='Юнит 2'!AL14 -> 480.04914 | D8: =C8/C$17 -> 0.036425677 | E8: =E7+D8 -> 1.1044746 | F8: =IF(AND(E8<=0),"C",IF(E8<=0.8,"A",IF(E8<=0.95,"B","C"))) -> C | G8: =VLOOKUP(B$4:B$16,I$4:M$16,5,0) -> C | I8: MR Р1874 корич | J8: ='Юнит 2'!S13 -> 1 | K8: =J8/J$17 -> 0.023809524 | L8: =L7+K8 -> 0.95238095 | M8: =_xlfn.IFS(L8<80%,"A",L8<=95%,"B",L8>95%,"C") -> C
B9: Qs желт Сул | C9: ='Юнит 2'!AL6 -> 251.54918 | D9: =C9/C$17 -> 0.019087315 | E9: =E8+D9 -> 1.1235619 | F9: =IF(AND(E9<=0),"C",IF(E9<=0.8,"A",IF(E9<=0.95,"B","C"))) -> C | G9: =VLOOKUP(B$4:B$16,I$4:M$16,5,0) -> B | I9: MR Р1886 черн | J9: ='Юнит 2'!S14 -> 1 | K9: =J9/J$17 -> 0.023809524 | L9: =L8+K9 -> 0.97619048 | M9: =_xlfn.IFS(L9<80%,"A",L9<=95%,"B",L9>95%,"C") -> C
B10: MR 1819 корич | C10: ='Юнит 2'!AL11 -> -17.763004 | D10: =C10/C$17 -> -0.00134784 | E10: =E9+D10 -> 1.1222141 | F10: =IF(AND(E10<=0),"C",IF(E10<=0.8,"A",IF(E10<=0.95,"B","C"))) -> C | G10: =VLOOKUP(B$4:B$16,I$4:M$16,5,0) -> C | I10: MR Р1886 корич | J10: ='Юнит 2'!S15 -> 1 | K10: =J10/J$17 -> 0.023809524 | L10: =L9+K10 -> 1 | M10: =_xlfn.IFS(L10<80%,"A",L10<=95%,"B",L10>95%,"C") -> C
B11: MR 1819 черн | C11: ='Юнит 2'!AL10 -> -114.59625 | D11: =C11/C$17 -> -0.0086954554 | E11: =E10+D11 -> 1.1135187 | F11: =IF(AND(E11<=0),"C",IF(E11<=0.8,"A",IF(E11<=0.95,"B","C"))) -> C | G11: =VLOOKUP(B$4:B$16,I$4:M$16,5,0) -> C | I11: Qs черн Сул | J11: ='Юнит 2'!S4 -> 0 | K11: =J11/J$17 -> 0 | L11: =L10+K11 -> 1 | M11: =_xlfn.IFS(L11<80%,"A",L11<=95%,"B",L11>95%,"C") -> C
B12: MR Р1874 черн | C12: ='Юнит 2'!AL12 -> -126.47922 | D12: =C12/C$17 -> -0.0095971244 | E12: =E11+D12 -> 1.1039215 | F12: =IF(AND(E12<=0),"C",IF(E12<=0.8,"A",IF(E12<=0.95,"B","C"))) -> C | G12: =VLOOKUP(B$4:B$16,I$4:M$16,5,0) -> C | I12: Qs син Сул | J12: ='Юнит 2'!S5 -> 0 | K12: =J12/J$17 -> 0 | L12: =L11+K12 -> 1 | M12: =_xlfn.IFS(L12<80%,"A",L12<=95%,"B",L12>95%,"C") -> C
B13: Qs син Сул | C13: ='Юнит 2'!AL5 -> -164.19948 | D13: =C13/C$17 -> -0.012459302 | E13: =E12+D13 -> 1.0914622 | F13: =IF(AND(E13<=0),"C",IF(E13<=0.8,"A",IF(E13<=0.95,"B","C"))) -> C | G13: =VLOOKUP(B$4:B$16,I$4:M$16,5,0) -> C | I13: flip черные Сул | J13: ='Юнит 2'!S7 -> 0 | K13: =J13/J$17 -> 0 | L13: =L12+K13 -> 1 | M13: =_xlfn.IFS(L13<80%,"A",L13<=95%,"B",L13>95%,"C") -> C
B14: flip черные Сул | C14: ='Юнит 2'!AL7 -> -229.5913 | D14: =C14/C$17 -> -0.017421171 | E14: =E13+D14 -> 1.0740411 | F14: =IF(AND(E14<=0),"C",IF(E14<=0.8,"A",IF(E14<=0.95,"B","C"))) -> C | G14: =VLOOKUP(B$4:B$16,I$4:M$16,5,0) -> C | I14: MR 1819 черн | J14: ='Юнит 2'!S10 -> 0 | K14: =J14/J$17 -> 0 | L14: =L13+K14 -> 1 | M14: =_xlfn.IFS(L14<80%,"A",L14<=95%,"B",L14>95%,"C") -> C
B15: Qs черн Сул | C15: ='Юнит 2'!AL4 -> -238.2913 | D15: =C15/C$17 -> -0.018081319 | E15: =E14+D15 -> 1.0559597 | F15: =IF(AND(E15<=0),"C",IF(E15<=0.8,"A",IF(E15<=0.95,"B","C"))) -> C | G15: =VLOOKUP(B$4:B$16,I$4:M$16,5,0) -> C | I15: MR 1819 корич | J15: ='Юнит 2'!S11 -> 0 | K15: =J15/J$17 -> 0 | L15: =L14+K15 -> 1 | M15: =_xlfn.IFS(L15<80%,"A",L15<=95%,"B",L15>95%,"C") -> C
B16: MR8854 C2 Сул | C16: ='Юнит 2'!AL9 -> -737.48588 | D16: =C16/C$17 -> -0.055959734 | E16: =E15+D16 -> 1 | F16: =IF(AND(E16<=0),"C",IF(E16<=0.8,"A",IF(E16<=0.95,"B","C"))) -> C | G16: =VLOOKUP(B$4:B$16,I$4:M$16,5,0) -> B | I16: MR Р1874 черн | J16: ='Юнит 2'!S12 -> 0 | K16: =J16/J$17 -> 0 | L16: =L15+K16 -> 1 | M16: =_xlfn.IFS(L16<80%,"A",L16<=95%,"B",L16>95%,"C") -> C
C17: =SUM(C4:C16) -> 13178.867 | D17: =SUM(D4:D16) -> 1 | J17: =SUM(J4:J16) -> 42 | K17: =SUM(K4:K16) -> 1
C20: Прибыль | D20: % прибыль | E20: Доля | F20: ABC прибыль | G20: ABC кол-во | J20: Кол-во | K20: % кол-во | L20: Доля | M20: ABC кол-во
D21: =C21/C$73 -> #DIV/0! | E21: =D21 -> #DIV/0! | F21: =IF(AND(E21<=0),"C",IF(E21<=0.8,"A",IF(E21<=0.95,"B","C"))) -> #DIV/0! | G21: =VLOOKUP(B21:B72,I$21:M$72,5,0) -> #N/A | K21: =J21/J$73 -> #DIV/0! | L21: =K21 -> #DIV/0! | M21: =_xlfn.IFS(L21<80%,"A",L21<=95%,"B",L21>95%,"C") -> #DIV/0!
D22: =C22/C$73 -> #DIV/0! | E22: =D22+E21 -> #DIV/0! | F22: =IF(AND(E22<=0),"C",IF(E22<=0.8,"A",IF(E22<=0.95,"B","C"))) -> #DIV/0! | G22: =VLOOKUP(B22:B73,I$21:M$72,5,0) -> #N/A | K22: =J22/J$73 -> #DIV/0! | L22: =K22+L21 -> #DIV/0! | M22: =_xlfn.IFS(L22<80%,"A",L22<=95%,"B",L22>95%,"C") -> #DIV/0!
D23: =C23/C$73 -> #DIV/0! | E23: =D23+E22 -> #DIV/0! | F23: =IF(AND(E23<=0),"C",IF(E23<=0.8,"A",IF(E23<=0.95,"B","C"))) -> #DIV/0! | G23: =VLOOKUP(B23:B74,I$21:M$72,5,0) -> #N/A | K23: =J23/J$73 -> #DIV/0! | L23: =K23+L22 -> #DIV/0! | M23: =_xlfn.IFS(L23<80%,"A",L23<=95%,"B",L23>95%,"C") -> #DIV/0!
D24: =C24/C$73 -> #DIV/0! | E24: =D24+E23 -> #DIV/0! | F24: =IF(AND(E24<=0),"C",IF(E24<=0.8,"A",IF(E24<=0.95,"B","C"))) -> #DIV/0! | G24: =VLOOKUP(B24:B75,I$21:M$72,5,0) -> #N/A | K24: =J24/J$73 -> #DIV/0! | L24: =K24+L23 -> #DIV/0! | M24: =_xlfn.IFS(L24<80%,"A",L24<=95%,"B",L24>95%,"C") -> #DIV/0!
D25: =C25/C$73 -> #DIV/0! | E25: =D25+E24 -> #DIV/0! | F25: =IF(AND(E25<=0),"C",IF(E25<=0.8,"A",IF(E25<=0.95,"B","C"))) -> #DIV/0! | G25: =VLOOKUP(B25:B76,I$21:M$72,5,0) -> #N/A | K25: =J25/J$73 -> #DIV/0! | L25: =K25+L24 -> #DIV/0! | M25: =_xlfn.IFS(L25<80%,"A",L25<=95%,"B",L25>95%,"C") -> #DIV/0!
D26: =C26/C$73 -> #DIV/0! | E26: =D26+E25 -> #DIV/0! | F26: =IF(AND(E26<=0),"C",IF(E26<=0.8,"A",IF(E26<=0.95,"B","C"))) -> #DIV/0! | G26: =VLOOKUP(B26:B77,I$21:M$72,5,0) -> #N/A | K26: =J26/J$73 -> #DIV/0! | L26: =K26+L25 -> #DIV/0! | M26: =_xlfn.IFS(L26<80%,"A",L26<=95%,"B",L26>95%,"C") -> #DIV/0!
D27: =C27/C$73 -> #DIV/0! | E27: =D27+E26 -> #DIV/0! | F27: =IF(AND(E27<=0),"C",IF(E27<=0.8,"A",IF(E27<=0.95,"B","C"))) -> #DIV/0! | G27: =VLOOKUP(B27:B78,I$21:M$72,5,0) -> #N/A | K27: =J27/J$73 -> #DIV/0! | L27: =K27+L26 -> #DIV/0! | M27: =_xlfn.IFS(L27<80%,"A",L27<=95%,"B",L27>95%,"C") -> #DIV/0!
D28: =C28/C$73 -> #DIV/0! | E28: =D28+E27 -> #DIV/0! | F28: =IF(AND(E28<=0),"C",IF(E28<=0.8,"A",IF(E28<=0.95,"B","C"))) -> #DIV/0! | G28: =VLOOKUP(B28:B79,I$21:M$72,5,0) -> #N/A | K28: =J28/J$73 -> #DIV/0! | L28: =K28+L27 -> #DIV/0! | M28: =_xlfn.IFS(L28<80%,"A",L28<=95%,"B",L28>95%,"C") -> #DIV/0!
D29: =C29/C$73 -> #DIV/0! | E29: =D29+E28 -> #DIV/0! | F29: =IF(AND(E29<=0),"C",IF(E29<=0.8,"A",IF(E29<=0.95,"B","C"))) -> #DIV/0! | G29: =VLOOKUP(B29:B80,I$21:M$72,5,0) -> #N/A | K29: =J29/J$73 -> #DIV/0! | L29: =K29+L28 -> #DIV/0! | M29: =_xlfn.IFS(L29<80%,"A",L29<=95%,"B",L29>95%,"C") -> #DIV/0!
D30: =C30/C$73 -> #DIV/0! | E30: =D30+E29 -> #DIV/0! | F30: =IF(AND(E30<=0),"C",IF(E30<=0.8,"A",IF(E30<=0.95,"B","C"))) -> #DIV/0! | G30: =VLOOKUP(B30:B81,I$21:M$72,5,0) -> #N/A | K30: =J30/J$73 -> #DIV/0! | L30: =K30+L29 -> #DIV/0! | M30: =_xlfn.IFS(L30<80%,"A",L30<=95%,"B",L30>95%,"C") -> #DIV/0!
D31: =C31/C$73 -> #DIV/0! | E31: =D31+E30 -> #DIV/0! | F31: =IF(AND(E31<=0),"C",IF(E31<=0.8,"A",IF(E31<=0.95,"B","C"))) -> #DIV/0! | G31: =VLOOKUP(B31:B82,I$21:M$72,5,0) -> #N/A | K31: =J31/J$73 -> #DIV/0! | L31: =K31+L30 -> #DIV/0! | M31: =_xlfn.IFS(L31<80%,"A",L31<=95%,"B",L31>95%,"C") -> #DIV/0!
D32: =C32/C$73 -> #DIV/0! | E32: =D32+E31 -> #DIV/0! | F32: =IF(AND(E32<=0),"C",IF(E32<=0.8,"A",IF(E32<=0.95,"B","C"))) -> #DIV/0! | G32: =VLOOKUP(B32:B83,I$21:M$72,5,0) -> #N/A | K32: =J32/J$73 -> #DIV/0! | L32: =K32+L31 -> #DIV/0! | M32: =_xlfn.IFS(L32<80%,"A",L32<=95%,"B",L32>95%,"C") -> #DIV/0!
D33: =C33/C$73 -> #DIV/0! | E33: =D33+E32 -> #DIV/0! | F33: =IF(AND(E33<=0),"C",IF(E33<=0.8,"A",IF(E33<=0.95,"B","C"))) -> #DIV/0! | G33: =VLOOKUP(B33:B84,I$21:M$72,5,0) -> #N/A | K33: =J33/J$73 -> #DIV/0! | L33: =K33+L32 -> #DIV/0! | M33: =_xlfn.IFS(L33<80%,"A",L33<=95%,"B",L33>95%,"C") -> #DIV/0!
... D72: =C72/C$73 -> #DIV/0! | E72: =D72+E71 -> #DIV/0! | F72: =IF(AND(E72<=0),"C",IF(E72<=0.8,"A",IF(E72<=0.95,"B","C"))) -> #DIV/0! | G72: =VLOOKUP(B72:B123,I$21:M$72,5,0) -> #N/A | K72: =J72/J$73 -> #DIV/0! | L72: =K72+L71 -> #DIV/0! | M72: =_xlfn.IFS(L72<80%,"A",L72<=95%,"B",L72>95%,"C") -> #DIV/0!
C73: =SUM(C21:C72) -> 0 | D73: =SUM(D21:D72) -> #DIV/0! | J73: =SUM(J21:J72) -> 0 | K73: =SUM(K21:K72) -> #DIV/0!

Sheet АВС 1
B2: ОЧКИ
C3: Прибыль | D3: % прибыль | E3: Доля | F3: ABC прибыль | G3: ABC кол-во | J3: Кол-во | K3: % кол-во | L3: Доля | M3: ABC кол-во
B4: flip желтые Сул | C4: ='Юнит 1'!AL8 -> 15664.998 | D4: =C4/C$17 -> 0.84084557 | E4: =D4 -> 0.84084557 | F4: =IF(AND(E4<=0),"C",IF(E4<=0.8,"A",IF(E4<=0.95,"B","C"))) -> B | G4: =VLOOKUP(B$4:B$16,I$4:M$16,5,0) -> A | I4: flip желтые Сул | J4: ='Юнит 1'!S8 -> 35 | K4: =J4/J$17 -> 0.77777778 | L4: =K4 -> 0.77777778 | M4: =_xlfn.IFS(L4<80%,"A",L4<=95%,"B",L4>95%,"C") -> A | P4: A | Q4: 0.8
B5: Qs желт Сул | C5: ='Юнит 1'!AL6 -> 1928.0439 | D5: =C5/C$17 -> 0.10349105 | E5: =E4+D5 -> 0.94433662 | F5: =IF(AND(E5<=0),"C",IF(E5<=0.8,"A",IF(E5<=0.95,"B","C"))) -> B | G5: =VLOOKUP(B$4:B$16,I$4:M$16,5,0) -> C | I5: Черные с железкой Сул | J5: ='Юнит 1'!S3 -> 4 | K5: =J5/J$17 -> 0.088888889 | L5: =L4+K5 -> 0.86666667 | M5: =_xlfn.IFS(L5<80%,"A",L5<=95%,"B",L5>95%,"C") -> B | P5: B | Q5: 0.15
B6: Черные с железкой Сул | C6: ='Юнит 1'!AL3 -> 1194.2557 | D6: =C6/C$17 -> 0.064103715 | E6: =E5+D6 -> 1.0084403 | F6: =IF(AND(E6<=0),"C",IF(E6<=0.8,"A",IF(E6<=0.95,"B","C"))) -> C | G6: =VLOOKUP(B$4:B$16,I$4:M$16,5,0) -> B | I6: Qs желт Сул | J6: ='Юнит 1'!S6 -> 4 | K6: =J6/J$17 -> 0.088888889 | L6: =L5+K6 -> 0.95555556 | M6: =_xlfn.IFS(L6<80%,"A",L6<=95%,"B",L6>95%,"C") -> C | P6: C | Q6: 0.05
B7: MR 1819 корич | C7: ='Юнит 1'!AL11 -> 478.82607 | D7: =C7/C$17 -> 0.025701808 | E7: =E6+D7 -> 1.0341421 | F7: =IF(AND(E7<=0),"C",IF(E7<=0.8,"A",IF(E7<=0.95,"B","C"))) -> C | G7: =VLOOKUP(B$4:B$16,I$4:M$16,5,0) -> C | I7: MR8854 C2 Сул | J7: ='Юнит 1'!S9 -> 1 | K7: =J7/J$17 -> 0.022222222 | L7: =L6+K7 -> 0.97777778 | M7: =_xlfn.IFS(L7<80%,"A",L7<=95%,"B",L7>95%,"C") -> C
B8: MR Р1874 корич | C8: ='Юнит 1'!AL13 -> -5.038224 | D8: =C8/C$17 -> -0.00027043529 | E8: =E7+D8 -> 1.0338717 | F8: =IF(AND(E8<=0),"C",IF(E8<=0.8,"A",IF(E8<=0.95,"B","C"))) -> C | G8: =VLOOKUP(B$4:B$16,I$4:M$16,5,0) -> C | I8: MR 1819 корич | J8: ='Юнит 1'!S11 -> 1 | K8: =J8/J$17 -> 0.022222222 | L8: =L7+K8 -> 1 | M8: =_xlfn.IFS(L8<80%,"A",L8<=95%,"B",L8>95%,"C") -> C
B9: MR Р1886 корич | C9: ='Юнит 1'!AL15 -> -15.534524 | D9: =C9/C$17 -> -0.00083384215 | E9: =E8+D9 -> 1.0330379 | F9: =IF(AND(E9<=0),"C",IF(E9<=0.8,"A",IF(E9<=0.95,"B","C"))) -> C | G9: =VLOOKUP(B$4:B$16,I$4:M$16,5,0) -> C | I9: Qs черн Сул | J9: ='Юнит 1'!S4 -> 0 | K9: =J9/J$17 -> 0 | L9: =L8+K9 -> 1 | M9: =_xlfn.IFS(L9<80%,"A",L9<=95%,"B",L9>95%,"C") -> C
B10: MR 1819 черн | C10: ='Юнит 1'!AL10 -> -17.633784 | D10: =C10/C$17 -> -0.00094652352 | E10: =E9+D10 -> 1.0320913 | F10: =IF(AND(E10<=0),"C",IF(E10<=0.8,"A",IF(E10<=0.95,"B","C"))) -> C | G10: =VLOOKUP(B$4:B$16,I$4:M$16,5,0) -> C | I10: Qs син Сул | J10: ='Юнит 1'!S5 -> 0 | K10: =J10/J$17 -> 0 | L10: =L9+K10 -> 1 | M10: =_xlfn.IFS(L10<80%,"A",L10<=95%,"B",L10>95%,"C") -> C
B11: MR Р1874 черн | C11: ='Юнит 1'!AL12 -> -19.313192 | D11: =C11/C$17 -> -0.0010366686 | E11: =E10+D11 -> 1.0310547 | F11: =IF(AND(E11<=0),"C",IF(E11<=0.8,"A",IF(E11<=0.95,"B","C"))) -> C | G11: =VLOOKUP(B$4:B$16,I$4:M$16,5,0) -> C | I11: flip черные Сул | J11: ='Юнит 1'!S7 -> 0 | K11: =J11/J$17 -> 0 | L11: =L10+K11 -> 1 | M11: =_xlfn.IFS(L11<80%,"A",L11<=95%,"B",L11>95%,"C") -> C
B12: MR Р1886 черн | C12: ='Юнит 1'!AL14 -> -27.29038 | D12: =C12/C$17 -> -0.0014648578 | E12: =E11+D12 -> 1.0295898 | F12: =IF(AND(E12<=0),"C",IF(E12<=0.8,"A",IF(E12<=0.95,"B","C"))) -> C | G12: =VLOOKUP(B$4:B$16,I$4:M$16,5,0) -> C | I12: MR 1819 черн | J12: ='Юнит 1'!S10 -> 0 | K12: =J12/J$17 -> 0 | L12: =L11+K12 -> 1 | M12: =_xlfn.IFS(L12<80%,"A",L12<=95%,"B",L12>95%,"C") -> C
B13: Qs черн Сул | C13: ='Юнит 1'!AL4 -> -120.23797 | D13: =C13/C$17 -> -0.0064539786 | E13: =E12+D13 -> 1.0231358 | F13: =IF(AND(E13<=0),"C",IF(E13<=0.8,"A",IF(E13<=0.95,"B","C"))) -> C | G13: =VLOOKUP(B$4:B$16,I$4:M$16,5,0) -> C | I13: MR Р1874 черн | J13: ='Юнит 1'!S12 -> 0 | K13: =J13/J$17 -> 0 | L13: =L12+K13 -> 1 | M13: =_xlfn.IFS(L13<80%,"A",L13<=95%,"B",L13>95%,"C") -> C
B14: flip черные Сул | C14: ='Юнит 1'!AL7 -> -120.23797 | D14: =C14/C$17 -> -0.0064539786 | E14: =E13+D14 -> 1.0166819 | F14: =IF(AND(E14<=0),"C",IF(E14<=0.8,"A",IF(E14<=0.95,"B","C"))) -> C | G14: =VLOOKUP(B$4:B$16,I$4:M$16,5,0) -> C | I14: MR Р1874 корич | J14: ='Юнит 1'!S13 -> 0 | K14: =J14/J$17 -> 0 | L14: =L13+K14 -> 1 | M14: =_xlfn.IFS(L14<80%,"A",L14<=95%,"B",L14>95%,"C") -> C
B15: MR8854 C2 Сул | C15: ='Юнит 1'!AL9 -> -151.66004 | D15: =C15/C$17 -> -0.0081406121 | E15: =E14+D15 -> 1.0085412 | F15: =IF(AND(E15<=0),"C",IF(E15<=0.8,"A",IF(E15<=0.95,"B","C"))) -> C | G15: =VLOOKUP(B$4:B$16,I$4:M$16,5,0) -> C | I15: MR Р1886 черн | J15: ='Юнит 1'!S14 -> 0 | K15: =J15/J$17 -> 0 | L15: =L14+K15 -> 1 | M15: =_xlfn.IFS(L15<80%,"A",L15<=95%,"B",L15>95%,"C") -> C
B16: Qs син Сул | C16: ='Юнит 1'!AL5 -> -159.12391 | D16: =C16/C$17 -> -0.008541248 | E16: =E15+D16 -> 1 | F16: =IF(AND(E16<=0),"C",IF(E16<=0.8,"A",IF(E16<=0.95,"B","C"))) -> C | G16: =VLOOKUP(B$4:B$16,I$4:M$16,5,0) -> C | I16: MR Р1886 корич | J16: ='Юнит 1'!S15 -> 0 | K16: =J16/J$17 -> 0 | L16: =L15+K16 -> 1 | M16: =_xlfn.IFS(L16<80%,"A",L16<=95%,"B",L16>95%,"C") -> C
C17: =SUM(C4:C16) -> 18630.054 | D17: =SUM(D4:D16) -> 1 | J17: =SUM(J4:J16) -> 45 | K17: =SUM(K4:K16) -> 1
C20: Прибыль | D20: % прибыль | E20: Доля | F20: ABC прибыль | G20: ABC кол-во | J20: Кол-во | K20: % кол-во | L20: Доля | M20: ABC кол-во
D21: =C21/C$73 -> #DIV/0! | E21: =D21 -> #DIV/0! | F21: =IF(AND(E21<=0),"C",IF(E21<=0.8,"A",IF(E21<=0.95,"B","C"))) -> #DIV/0! | G21: =VLOOKUP(B21:B72,I$21:M$72,5,0) -> #N/A | K21: =J21/J$73 -> #DIV/0! | L21: =K21 -> #DIV/0! | M21: =_xlfn.IFS(L21<80%,"A",L21<=95%,"B",L21>95%,"C") -> #DIV/0!
D22: =C22/C$73 -> #DIV/0! | E22: =D22+E21 -> #DIV/0! | F22: =IF(AND(E22<=0),"C",IF(E22<=0.8,"A",IF(E22<=0.95,"B","C"))) -> #DIV/0! | G22: =VLOOKUP(B22:B73,I$21:M$72,5,0) -> #N/A | K22: =J22/J$73 -> #DIV/0! | L22: =K22+L21 -> #DIV/0! | M22: =_xlfn.IFS(L22<80%,"A",L22<=95%,"B",L22>95%,"C") -> #DIV/0!
D23: =C23/C$73 -> #DIV/0! | E23: =D23+E22 -> #DIV/0! | F23: =IF(AND(E23<=0),"C",IF(E23<=0.8,"A",IF(E23<=0.95,"B","C"))) -> #DIV/0! | G23: =VLOOKUP(B23:B74,I$21:M$72,5,0) -> #N/A | K23: =J23/J$73 -> #DIV/0! | L23: =K23+L22 -> #DIV/0! | M23: =_xlfn.IFS(L23<80%,"A",L23<=95%,"B",L23>95%,"C") -> #DIV/0!
D24: =C24/C$73 -> #DIV/0! | E24: =D24+E23 -> #DIV/0! | F24: =IF(AND(E24<=0),"C",IF(E24<=0.8,"A",IF(E24<=0.95,"B","C"))) -> #DIV/0! | G24: =VLOOKUP(B24:B75,I$21:M$72,5,0) -> #N/A | K24: =J24/J$73 -> #DIV/0! | L24: =K24+L23 -> #DIV/0! | M24: =_xlfn.IFS(L24<80%,"A",L24<=95%,"B",L24>95%,"C") -> #DIV/0!
D25: =C25/C$73 -> #DIV/0! | E25: =D25+E24 -> #DIV/0! | F25: =IF(AND(E25<=0),"C",IF(E25<=0.8,"A",IF(E25<=0.95,"B","C"))) -> #DIV/0! | G25: =VLOOKUP(B25:B76,I$21:M$72,5,0) -> #N/A | K25: =J25/J$73 -> #DIV/0! | L25: =K25+L24 -> #DIV/0! | M25: =_xlfn.IFS(L25<80%,"A",L25<=95%,"B",L25>95%,"C") -> #DIV/0!
D26: =C26/C$73 -> #DIV/0! | E26: =D26+E25 -> #DIV/0! | F26: =IF(AND(E26<=0),"C",IF(E26<=0.8,"A",IF(E26<=0.95,"B","C"))) -> #DIV/0! | G26: =VLOOKUP(B26:B77,I$21:M$72,5,0) -> #N/A | K26: =J26/J$73 -> #DIV/0! | L26: =K26+L25 -> #DIV/0! | M26: =_xlfn.IFS(L26<80%,"A",L26<=95%,"B",L26>95%,"C") -> #DIV/0!
D27: =C27/C$73 -> #DIV/0! | E27: =D27+E26 -> #DIV/0! | F27: =IF(AND(E27<=0),"C",IF(E27<=0.8,"A",IF(E27<=0.95,"B","C"))) -> #DIV/0! | G27: =VLOOKUP(B27:B78,I$21:M$72,5,0) -> #N/A | K27: =J27/J$73 -> #DIV/0! | L27: =K27+L26 -> #DIV/0! | M27: =_xlfn.IFS(L27<80%,"A",L27<=95%,"B",L27>95%,"C") -> #DIV/0!
D28: =C28/C$73 -> #DIV/0! | E28: =D28+E27 -> #DIV/0! | F28: =IF(AND(E28<=0),"C",IF(E28<=0.8,"A",IF(E28<=0.95,"B","C"))) -> #DIV/0! | G28: =VLOOKUP(B28:B79,I$21:M$72,5,0) -> #N/A | K28: =J28/J$73 -> #DIV/0! | L28: =K28+L27 -> #DIV/0! | M28: =_xlfn.IFS(L28<80%,"A",L28<=95%,"B",L28>95%,"C") -> #DIV/0!
D29: =C29/C$73 -> #DIV/0! | E29: =D29+E28 -> #DIV/0! | F29: =IF(AND(E29<=0),"C",IF(E29<=0.8,"A",IF(E29<=0.95,"B","C"))) -> #DIV/0! | G29: =VLOOKUP(B29:B80,I$21:M$72,5,0) -> #N/A | K29: =J29/J$73 -> #DIV/0! | L29: =K29+L28 -> #DIV/0! | M29: =_xlfn.IFS(L29<80%,"A",L29<=95%,"B",L29>95%,"C") -> #DIV/0!
D30: =C30/C$73 -> #DIV/0! | E30: =D30+E29 -> #DIV/0! | F30: =IF(AND(E30<=0),"C",IF(E30<=0.8,"A",IF(E30<=0.95,"B","C"))) -> #DIV/0! | G30: =VLOOKUP(B30:B81,I$21:M$72,5,0) -> #N/A | K30: =J30/J$73 -> #DIV/0! | L30: =K30+L29 -> #DIV/0! | M30: =_xlfn.IFS(L30<80%,"A",L30<=95%,"B",L30>95%,"C") -> #DIV/0!
D31: =C31/C$73 -> #DIV/0! | E31: =D31+E30 -> #DIV/0! | F31: =IF(AND(E31<=0),"C",IF(E31<=0.8,"A",IF(E31<=0.95,"B","C"))) -> #DIV/0! | G31: =VLOOKUP(B31:B82,I$21:M$72,5,0) -> #N/A | K31: =J31/J$73 -> #DIV/0! | L31: =K31+L30 -> #DIV/0! | M31: =_xlfn.IFS(L31<80%,"A",L31<=95%,"B",L31>95%,"C") -> #DIV/0!
D32: =C32/C$73 -> #DIV/0! | E32: =D32+E31 -> #DIV/0! | F32: =IF(AND(E32<=0),"C",IF(E32<=0.8,"A",IF(E32<=0.95,"B","C"))) -> #DIV/0! | G32: =VLOOKUP(B32:B83,I$21:M$72,5,0) -> #N/A | K32: =J32/J$73 -> #DIV/0! | L32: =K32+L31 -> #DIV/0! | M32: =_xlfn.IFS(L32<80%,"A",L32<=95%,"B",L32>95%,"C") -> #DIV/0!
D33: =C33/C$73 -> #DIV/0! | E33: =D33+E32 -> #DIV/0! | F33: =IF(AND(E33<=0),"C",IF(E33<=0.8,"A",IF(E33<=0.95,"B","C"))) -> #DIV/0! | G33: =VLOOKUP(B33:B84,I$21:M$72,5,0) -> #N/A | K33: =J33/J$73 -> #DIV/0! | L33: =K33+L32 -> #DIV/0! | M33: =_xlfn.IFS(L33<80%,"A",L33<=95%,"B",L33>95%,"C") -> #DIV/0!
... D72: =C72/C$73 -> #DIV/0! | E72: =D72+E71 -> #DIV/0! | F72: =IF(AND(E72<=0),"C",IF(E72<=0.8,"A",IF(E72<=0.95,"B","C"))) -> #DIV/0! | G72: =VLOOKUP(B72:B123,I$21:M$72,5,0) -> #N/A | K72: =J72/J$73 -> #DIV/0! | L72: =K72+L71 -> #DIV/0! | M72: =_xlfn.IFS(L72<80%,"A",L72<=95%,"B",L72>95%,"C") -> #DIV/0!
C73: =SUM(C21:C72) -> 0 | D73: =SUM(D21:D72) -> #DIV/0! | J73: =SUM(J21:J72) -> 0 | K73: =SUM(K21:K72) -> #DIV/0!

Sheet Юнит 6
A1: 26.01-01.02_5 нед | F1: Отчет по остаткам 3,4,5 | K1: Цены и скидки 6 | L1: Воронка продаж 16,50,32 | AI1: Вставить в Итого | AN1: на 1 единицу проданного товара
A2: Бренд | B2: SKU | C2: Артикул поставщика | D2: Предмет | E2: Остаток на 02.02 | F2: В пути до клиента | G2: В пути от клиента | H2: Итого по складам ВБ | I2: Себетоимость на 1 ед на 29.09.25 | J2: Себестоимость остатков | K2: Оборачива-емость, дн | L2: Заказы, шт 7 дней | M2: Средняя цена, руб | N2: % выкупа за 7 дней | O2: Скорость заказов | P2: Скорость продаж | Q2: Кол-во ПРОДАЖИ | R2: Кол-во ВОЗВРАТЫ | S2: Кол-во ПРОДАЖИ-ВОЗВРАТЫ | T2: Выручка ВБ ПРОДАЖИ | U2: Выручка ВБ ВОЗВРАТЫ | V2: Выручка с учетом СПП ПРОДАЖИ - ВОЗВРАТЫ | W2: Выручка ПРОДАЖИ | X2: Выручка ВОЗВРАТЫ | Y2: Выручка с учетом согласованной скидки ПРОДАЖИ - ВОЗВРАТЫ | Z2: Выручка потенциальная | AA2: Доля выручки, % от общего объема | AB2: Себестоимость продаж | AC2: Комиссия, руб | AD2: Комиссия, % | AE2: Логистика | AF2: Реклама БАЛАНС | AG2: Реклама СЧЕТ | AH2: Блогеры | AI2: Хранение | AJ2: Штрафы | AK2: Налог 1% | AL2: Прибыль | AN2: Выручка на 1 ед (средняя цена продажи со скидкой) | AO2: Себестоимость на 1 ед | AP2: Комиссия на 1 ед | AQ2: Логистика на 1 ед | AR2: Реклама на 1 ед | AS2: Прибыль на 1 ед | AT2: Маржиналь-ность, % | AU2: Рентабель-ность, % | AW2: Прибыль с остатков
B3: 341479791 | C3: Черные с железкой Сул | D3: Солнцезащитные очки | I3: 142.98 | J3: =E3*I3 -> 0 | O3: =L3/7 -> 0 | P3: =S3/7 -> 0 | S3: =Q3+R3 -> 0 | V3: =T3+U3 -> 0 | Y3: =W3+X3 -> 0 | Z3: =L3*M3*N3/100 -> 0 | AA3: =Y3/$Y$74 -> #DIV/0! | AB3: =S3*I3 -> 0 | AD3: =IF(Y3=0,0,AC3/Y3) -> 0 | AI3: =IFERROR($AI$74*H3/$H$74,0) -> 0 | AK3: =V3*1% -> 0 | AL3: =Y3-AB3-AC3-AE3-AF3-AG3-AH3-AI3-AK3-AJ3 -> 0 | AN3: =IF(S3=0,0,Y3/S3) -> 0 | AO3: =I3 -> 142.98 | AP3: =IF(S3=0,0,AC3/S3) -> 0 | AQ3: =IF(Q3=0,AE3/1,AE3/Q3) -> 0 | AR3: =IF(Q3=0,0,(AF3+AG3)/Q3) -> 0 | AS3: =_xlfn.IFS(S3=0,AL3,S3<0,AL3/-S3,S3>0,AL3/S3) -> 0 | AT3: =IF(AN3=0,0,AS3/AN3) -> 0 | AU3: =IF(AO3=0,0,AS3/AO3) -> 0 | AW3: =AS3*E3 -> 0
B4: 340343575 | C4: Qs черн Сул | D4: Солнцезащитные очки | I4: 123.09 | J4: =E4*I4 -> 0 | O4: =L4/7 -> 0 | P4: =S4/7 -> 0 | S4: =Q4+R4 -> 0 | V4: =T4+U4 -> 0 | Y4: =W4+X4 -> 0 | Z4: =L4*M4*N4/100 -> 0 | AA4: =Y4/$Y$74 -> #DIV/0! | AB4: =S4*I4 -> 0 | AD4: =IF(Y4=0,0,AC4/Y4) -> 0 | AI4: =IFERROR($AI$74*H4/$H$74,0) -> 0 | AK4: =V4*1% -> 0 | AL4: =Y4-AB4-AC4-AE4-AF4-AG4-AH4-AI4-AK4-AJ4 -> 0 | AN4: =IF(S4=0,0,Y4/S4) -> 0 | AO4: =I4 -> 123.09 | AP4: =IF(S4=0,0,AC4/S4) -> 0 | AQ4: =IF(Q4=0,AE4/1,AE4/Q4) -> 0 | AR4: =IF(Q4=0,0,(AF4+AG4)/Q4) -> 0 | AS4: {=_xlfn.IFS(S4=0,AL4,S4<0,AL4/-S4,S4>0,AL4/S4)} -> 0 | AT4: =IF(AN4=0,0,AS4/AN4) -> 0 | AU4: =IF(AO4=0,0,AS4/AO4) -> 0 | AW4: =AS4*E4 -> 0
B5: 340332621 | C5: Qs син Сул | D5: Солнцезащитные очки | I5: 123.09 | J5: =E5*I5 -> 0 | O5: =L5/7 -> 0 | P5: =S5/7 -> 0 | S5: =Q5+R5 -> 0 | V5: =T5+U5 -> 0 | Y5: =W5+X5 -> 0 | Z5: =L5*M5*N5/100 -> 0 | AA5: =Y5/$Y$74 -> #DIV/0! | AB5: =S5*I5 -> 0 | AD5: =IF(Y5=0,0,AC5/Y5) -> 0 | AI5: =IFERROR($AI$74*H5/$H$74,0) -> 0 | AK5: =V5*1% -> 0 | AL5: =Y5-AB5-AC5-AE5-AF5-AG5-AH5-AI5-AK5-AJ5 -> 0 | AN5: =IF(S5=0,0,Y5/S5) -> 0 | AO5: =I5 -> 123.09 | AP5: =IF(S5=0,0,AC5/S5) -> 0 | AQ5: =IF(Q5=0,AE5/1,AE5/Q5) -> 0 | AR5: =IF(Q5=0,0,(AF5+AG5)/Q5) -> 0 | AS5: {=_xlfn.IFS(S5=0,AL5,S5<0,AL5/-S5,S5>0,AL5/S5)} -> 0 | AT5: =IF(AN5=0,0,AS5/AN5) -> 0 | AU5: =IF(AO5=0,0,AS5/AO5) -> 0 | AW5: =AS5*E5 -> 0
B6: 340341838 | C6: Qs желт Сул | D6: Солнцезащитные очки | I6: 123.09 | J6: =E6*I6 -> 0 | O6: =L6/7 -> 0 | P6: =S6/7 -> 0 | S6: =Q6+R6 -> 0 | V6: =T6+U6 -> 0 | Y6: =W6+X6 -> 0 | Z6: =L6*M6*N6/100 -> 0 | AA6: =Y6/$Y$74 -> #DIV/0! | AB6: =S6*I6 -> 0 | AD6: =IF(Y6=0,0,AC6/Y6) -> 0 | AI6: =IFERROR($AI$74*H6/$H$74,0) -> 0 | AK6: =V6*1% -> 0 | AL6: =Y6-AB6-AC6-AE6-AF6-AG6-AH6-AI6-AK6-AJ6 -> 0 | AN6: =IF(S6=0,0,Y6/S6) -> 0 | AO6: =I6 -> 123.09 | AP6: =IF(S6=0,0,AC6/S6) -> 0 | AQ6: =IF(Q6=0,AE6/1,AE6/Q6) -> 0 | AR6: =IF(Q6=0,0,(AF6+AG6)/Q6) -> 0 | AS6: {=_xlfn.IFS(S6=0,AL6,S6<0,AL6/-S6,S6>0,AL6/S6)} -> 0 | AT6: =IF(AN6=0,0,AS6/AN6) -> 0 | AU6: =IF(AO6=0,0,AS6/AO6) -> 0 | AW6: =AS6*E6 -> 0
B7: 445291724 | C7: flip черные Сул | D7: Солнцезащитные очки | I7: 123.09 | J7: =E7*I7 -> 0 | O7: =L7/7 -> 0 | P7: =S7/7 -> 0 | S7: =Q7+R7 -> 0 | V7: =T7+U7 -> 0 | Y7: =W7+X7 -> 0 | Z7: =L7*M7*N7/100 -> 0 | AA7: =Y7/$Y$74 -> #DIV/0! | AB7: =S7*I7 -> 0 | AD7: =IF(Y7=0,0,AC7/Y7) -> 0 | AI7: =IFERROR($AI$74*H7/$H$74,0) -> 0 | AK7: =V7*1% -> 0 | AL7: =Y7-AB7-AC7-AE7-AF7-AG7-AH7-AI7-AK7-AJ7 -> 0 | AN7: =IF(S7=0,0,Y7/S7) -> 0 | AO7: =I7 -> 123.09 | AP7: =IF(S7=0,0,AC7/S7) -> 0 | AQ7: =IF(Q7=0,AE7/1,AE7/Q7) -> 0 | AR7: =IF(Q7=0,0,(AF7+AG7)/Q7) -> 0 | AS7: {=_xlfn.IFS(S7=0,AL7,S7<0,AL7/-S7,S7>0,AL7/S7)} -> 0 | AT7: =IF(AN7=0,0,AS7/AN7) -> 0 | AU7: =IF(AO7=0,0,AS7/AO7) -> 0 | AW7: =AS7*E7 -> 0
B8: 445336740 | C8: flip желтые Сул | D8: Солнцезащитные очки | I8: 123.09 | J8: =E8*I8 -> 0 | O8: =L8/7 -> 0 | P8: =S8/7 -> 0 | S8: =Q8+R8 -> 0 | V8: =T8+U8 -> 0 | Y8: =W8+X8 -> 0 | Z8: =L8*M8*N8/100 -> 0 | AA8: =Y8/$Y$74 -> #DIV/0! | AB8: =S8*I8 -> 0 | AD8: =IF(Y8=0,0,AC8/Y8) -> 0 | AI8: =IFERROR($AI$74*H8/$H$74,0) -> 0 | AK8: =V8*1% -> 0 | AL8: =Y8-AB8-AC8-AE8-AF8-AG8-AH8-AI8-AK8-AJ8 -> 0 | AN8: =IF(S8=0,0,Y8/S8) -> 0 | AO8: =I8 -> 123.09 | AP8: =IF(S8=0,0,AC8/S8) -> 0 | AQ8: =IF(Q8=0,AE8/1,AE8/Q8) -> 0 | AR8: =IF(Q8=0,0,(AF8+AG8)/Q8) -> 0 | AS8: {=_xlfn.IFS(S8=0,AL8,S8<0,AL8/-S8,S8>0,AL8/S8)} -> 0 | AT8: =IF(AN8=0,0,AS8/AN8) -> 0 | AU8: =IF(AO8=0,0,AS8/AO8) -> 0 | AW8: =AS8*E8 -> 0
B9: 445341507 | C9: MR8854 C2 Сул | D9: Солнцезащитные очки | I9: 169.89 | J9: =E9*I9 -> 0 | O9: =L9/7 -> 0 | P9: =S9/7 -> 0 | S9: =Q9+R9 -> 0 | V9: =T9+U9 -> 0 | Y9: =W9+X9 -> 0 | Z9: =L9*M9*N9/100 -> 0 | AA9: =Y9/$Y$74 -> #DIV/0! | AB9: =S9*I9 -> 0 | AD9: =IF(Y9=0,0,AC9/Y9) -> 0 | AI9: =IFERROR($AI$74*H9/$H$74,0) -> 0 | AK9: =V9*1% -> 0 | AL9: =Y9-AB9-AC9-AE9-AF9-AG9-AH9-AI9-AK9-AJ9 -> 0 | AN9: =IF(S9=0,0,Y9/S9) -> 0 | AO9: =I9 -> 169.89 | AP9: =IF(S9=0,0,AC9/S9) -> 0 | AQ9: =IF(Q9=0,AE9/1,AE9/Q9) -> 0 | AR9: =IF(Q9=0,0,(AF9+AG9)/Q9) -> 0 | AS9: {=_xlfn.IFS(S9=0,AL9,S9<0,AL9/-S9,S9>0,AL9/S9)} -> 0 | AT9: =IF(AN9=0,0,AS9/AN9) -> 0 | AU9: =IF(AO9=0,0,AS9/AO9) -> 0 | AW9: =AS9*E9 -> 0
B10: 497825485 | C10: MR 1819 черн | D10: Солнцезащитные очки | I10: 169.89 | J10: =E10*I10 -> 0 | O10: =L10/7 -> 0 | P10: =S10/7 -> 0 | S10: =Q10+R10 -> 0 | V10: =T10+U10 -> 0 | Y10: =W10+X10 -> 0 | Z10: =L10*M10*N10/100 -> 0 | AA10: =Y10/$Y$74 -> #DIV/0! | AB10: =S10*I10 -> 0 | AD10: =IF(Y10=0,0,AC10/Y10) -> 0 | AI10: =IFERROR($AI$74*H10/$H$74,0) -> 0 | AK10: =V10*1% -> 0 | AL10: =Y10-AB10-AC10-AE10-AF10-AG10-AH10-AI10-AK10-AJ10 -> 0 | AN10: =IF(S10=0,0,Y10/S10) -> 0 | AO10: =I10 -> 169.89 | AP10: =IF(S10=0,0,AC10/S10) -> 0 | AQ10: =IF(Q10=0,AE10/1,AE10/Q10) -> 0 | AR10: =IF(Q10=0,0,(AF10+AG10)/Q10) -> 0 | AS10: {=_xlfn.IFS(S10=0,AL10,S10<0,AL10/-S10,S10>0,AL10/S10)} -> 0 | AT10: =IF(AN10=0,0,AS10/AN10) -> 0 | AU10: =IF(AO10=0,0,AS10/AO10) -> 0 | AW10: =AS10*E10 -> 0
B11: 497825962 | C11: MR 1819 корич | D11: Солнцезащитные очки | I11: 169.89 | J11: =E11*I11 -> 0 | O11: =L11/7 -> 0 | P11: =S11/7 -> 0 | S11: =Q11+R11 -> 0 | V11: =T11+U11 -> 0 | Y11: =W11+X11 -> 0 | Z11: =L11*M11*N11/100 -> 0 | AA11: =Y11/$Y$74 -> #DIV/0! | AB11: =S11*I11 -> 0 | AD11: =IF(Y11=0,0,AC11/Y11) -> 0 | AI11: =IFERROR($AI$74*H11/$H$74,0) -> 0 | AK11: =V11*1% -> 0 | AL11: =Y11-AB11-AC11-AE11-AF11-AG11-AH11-AI11-AK11-AJ11 -> 0 | AN11: =IF(S11=0,0,Y11/S11) -> 0 | AO11: =I11 -> 169.89 | AP11: =IF(S11=0,0,AC11/S11) -> 0 | AQ11: =IF(Q11=0,AE11/1,AE11/Q11) -> 0 | AR11: =IF(Q11=0,0,(AF11+AG11)/Q11) -> 0 | AS11: {=_xlfn.IFS(S11=0,AL11,S11<0,AL11/-S11,S11>0,AL11/S11)} -> 0 | AT11: =IF(AN11=0,0,AS11/AN11) -> 0 | AU11: =IF(AO11=0,0,AS11/AO11) -> 0 | AW11: =AS11*E11 -> 0
B12: 497821775 | C12: MR Р1874 черн | D12: Солнцезащитные очки | I12: 169.89 | J12: =E12*I12 -> 0 | O12: =L12/7 -> 0 | P12: =S12/7 -> 0 | S12: =Q12+R12 -> 0 | V12: =T12+U12 -> 0 | Y12: =W12+X12 -> 0 | Z12: =L12*M12*N12/100 -> 0 | AA12: =Y12/$Y$74 -> #DIV/0! | AB12: =S12*I12 -> 0 | AD12: =IF(Y12=0,0,AC12/Y12) -> 0 | AI12: =IFERROR($AI$74*H12/$H$74,0) -> 0 | AK12: =V12*1% -> 0 | AL12: =Y12-AB12-AC12-AE12-AF12-AG12-AH12-AI12-AK12-AJ12 -> 0 | AN12: =IF(S12=0,0,Y12/S12) -> 0 | AO12: =I12 -> 169.89 | AP12: =IF(S12=0,0,AC12/S12) -> 0 | AQ12: =IF(Q12=0,AE12/1,AE12/Q12) -> 0 | AR12: =IF(Q12=0,0,(AF12+AG12)/Q12) -> 0 | AS12: {=_xlfn.IFS(S12=0,AL12,S12<0,AL12/-S12,S12>0,AL12/S12)} -> 0 | AT12: =IF(AN12=0,0,AS12/AN12) -> 0 | AU12: =IF(AO12=0,0,AS12/AO12) -> 0 | AW12: =AS12*E12 -> 0
B13: 497823770 | C13: MR Р1874 корич | D13: Солнцезащитные очки | I13: 169.89 | J13: =E13*I13 -> 0 | O13: =L13/7 -> 0 | P13: =S13/7 -> 0 | S13: =Q13+R13 -> 0 | V13: =T13+U13 -> 0 | Y13: =W13+X13 -> 0 | Z13: =L13*M13*N13/100 -> 0 | AA13: =Y13/$Y$74 -> #DIV/0! | AB13: =S13*I13 -> 0 | AD13: =IF(Y13=0,0,AC13/Y13) -> 0 | AI13: =IFERROR($AI$74*H13/$H$74,0) -> 0 | AK13: =V13*1% -> 0 | AL13: =Y13-AB13-AC13-AE13-AF13-AG13-AH13-AI13-AK13-AJ13 -> 0 | AN13: =IF(S13=0,0,Y13/S13) -> 0 | AO13: =I13 -> 169.89 | AP13: =IF(S13=0,0,AC13/S13) -> 0 | AQ13: =IF(Q13=0,AE13/1,AE13/Q13) -> 0 | AR13: =IF(Q13=0,0,(AF13+AG13)/Q13) -> 0 | AS13: {=_xlfn.IFS(S13=0,AL13,S13<0,AL13/-S13,S13>0,AL13/S13)} -> 0 | AT13: =IF(AN13=0,0,AS13/AN13) -> 0 | AU13: =IF(AO13=0,0,AS13/AO13) -> 0 | AW13: =AS13*E13 -> 0
B14: 497824253 | C14: MR Р1886 черн | D14: Солнцезащитные очки | I14: 169.89 | J14: =E14*I14 -> 0 | O14: =L14/7 -> 0 | P14: =S14/7 -> 0 | S14: =Q14+R14 -> 0 | V14: =T14+U14 -> 0 | Y14: =W14+X14 -> 0 | Z14: =L14*M14*N14/100 -> 0 | AA14: =Y14/$Y$74 -> #DIV/0! | AB14: =S14*I14 -> 0 | AD14: =IF(Y14=0,0,AC14/Y14) -> 0 | AI14: =IFERROR($AI$74*H14/$H$74,0) -> 0 | AK14: =V14*1% -> 0 | AL14: =Y14-AB14-AC14-AE14-AF14-AG14-AH14-AI14-AK14-AJ14 -> 0 | AN14: =IF(S14=0,0,Y14/S14) -> 0 | AO14: =I14 -> 169.89 | AP14: =IF(S14=0,0,AC14/S14) -> 0 | AQ14: =IF(Q14=0,AE14/1,AE14/Q14) -> 0 | AR14: =IF(Q14=0,0,(AF14+AG14)/Q14) -> 0 | AS14: {=_xlfn.IFS(S14=0,AL14,S14<0,AL14/-S14,S14>0,AL14/S14)} -> 0 | AT14: =IF(AN14=0,0,AS14/AN14) -> 0 | AU14: =IF(AO14=0,0,AS14/AO14) -> 0 | AW14: =AS14*E14 -> 0
B15: 497824944 | C15: MR Р1886 корич | D15: Солнцезащитные очки | I15: 169.89 | J15: =E15*I15 -> 0 | O15: =L15/7 -> 0 | P15: =S15/7 -> 0 | S15: =Q15+R15 -> 0 | V15: =T15+U15 -> 0 | Y15: =W15+X15 -> 0 | Z15: =L15*M15*N15/100 -> 0 | AA15: =Y15/$Y$74 -> #DIV/0! | AB15: =S15*I15 -> 0 | AD15: =IF(Y15=0,0,AC15/Y15) -> 0 | AI15: =IFERROR($AI$74*H15/$H$74,0) -> 0 | AK15: =V15*1% -> 0 | AL15: =Y15-AB15-AC15-AE15-AF15-AG15-AH15-AI15-AK15-AJ15 -> 0 | AN15: =IF(S15=0,0,Y15/S15) -> 0 | AO15: =I15 -> 169.89 | AP15: =IF(S15=0,0,AC15/S15) -> 0 | AQ15: =IF(Q15=0,AE15/1,AE15/Q15) -> 0 | AR15: =IF(Q15=0,0,(AF15+AG15)/Q15) -> 0 | AS15: {=_xlfn.IFS(S15=0,AL15,S15<0,AL15/-S15,S15>0,AL15/S15)} -> 0 | AT15: =IF(AN15=0,0,AS15/AN15) -> 0 | AU15: =IF(AO15=0,0,AS15/AO15) -> 0 | AW15: =AS15*E15 -> 0
AN16: =AVERAGE(AN3:AN6) -> 0 | AO16: =AVERAGE(AO3:AO6) -> 128.0625 | AP16: =AVERAGE(AP3:AP6) -> 0 | AQ16: =AVERAGE(AQ3:AQ6) -> 0 | AR16: =AVERAGE(AR3:AR6) -> 0 | AS16: =AVERAGE(AS3:AS6) -> 0 | AT16: =AVERAGE(AT3:AT6) -> 0 | AU16: =AVERAGE(AU3:AU6) -> 0
A17: Итого очки | E17: =SUM(E3:E15) -> 0 | F17: =SUM(F3:F15) -> 0 | G17: =SUM(G3:G15) -> 0 | H17: =SUM(H3:H15) -> 0 | J17: =SUM(J3:J15) -> 0 | L17: =SUM(L3:L15) -> 0 | Q17: =SUM(Q3:Q15) -> 0 | R17: =SUM(R3:R15) -> 0 | S17: =SUM(S3:S15) -> 0 | T17: =SUM(T3:T15) -> 0 | U17: =SUM(U3:U15) -> 0 | V17: =SUM(V3:V15) -> 0 | W17: =SUM(W3:W15) -> 0 | X17: =SUM(X3:X15) -> 0 | ... AC17: =SUM(AC3:AC15) -> 0 | AD17: =AC17/Y17 -> #DIV/0! | AE17: =SUM(AE3:AE15) -> 0 | AF17: =SUM(AF3:AF15) -> 0 | AG17: =SUM(AG3:AG15) -> 0 | AH17: =SUM(AH3:AH15) -> 0 | AI17: =SUM(AI3:AI15) -> 0 | AJ17: =SUM(AJ3:AJ15) -> 0 | AK17: =SUM(AK3:AK15) -> 0 | AL17: =SUM(AL3:AL15) -> 0 | AR17: =(AF17+AG17)/Q17 -> #DIV/0! | AW17: =SUM(AW3:AW6) -> 0
E19: =SUM(F19:H19) -> 0 | J19: =E19*I19 -> 0 | O19: =L19/7 -> 0 | P19: =S19/7 -> 0 | S19: =Q19+R19 -> 0 | V19: =T19+U19 -> 0 | Y19: =W19+X19 -> 0 | Z19: =L19*M19*N19/100 -> 0 | AA19: =Y19/$Y$74 -> #DIV/0! | AB19: =S19*I19 -> 0 | AD19: =IF(Y19=0,0,AC19/Y19) -> 0 | AI19: =$AI$74*H19/$H$74 -> #DIV/0! | AK19: =V19*1% -> 0 | AL19: =Y19-AB19-AC19-AE19-AF19-AG19-AH19-AI19-AK19-AJ19 -> #DIV/0! | AN19: =IF(S19=0,0,Y19/S19) -> 0 | AO19: =I19 -> 0 | AP19: =IF(S19=0,0,AC19/S19) -> 0 | AQ19: =IF(Q19=0,AE19/1,AE19/Q19) -> 0 | AR19: =IF(Q19=0,0,(AF19+AG19)/Q19) -> 0 | AS19: {=_xlfn.IFS(S19=0,AL19,S19<0,AL19/-S19,S19>0,AL19/S19)} -> #DIV/0! | AT19: =IF(AN19=0,0,AS19/AN19) -> 0 | AU19: =IF(AO19=0,0,AS19/AO19) -> 0 | AW19: =AS19*E19 -> #DIV/0!
E20: =SUM(F20:H20) -> 0 | J20: =E20*I20 -> 0 | O20: =L20/7 -> 0 | P20: =S20/7 -> 0 | S20: =Q20+R20 -> 0 | V20: =T20+U20 -> 0 | Y20: =W20+X20 -> 0 | Z20: =L20*M20*N20/100 -> 0 | AA20: =Y20/$Y$74 -> #DIV/0! | AB20: =S20*I20 -> 0 | AD20: =IF(Y20=0,0,AC20/Y20) -> 0 | AI20: =$AI$74*H20/$H$74 -> #DIV/0! | AK20: =V20*1% -> 0 | AL20: =Y20-AB20-AC20-AE20-AF20-AG20-AH20-AI20-AK20-AJ20 -> #DIV/0! | AN20: =IF(S20=0,0,Y20/S20) -> 0 | AO20: =I20 -> 0 | AP20: =IF(S20=0,0,AC20/S20) -> 0 | AQ20: =IF(Q20=0,AE20/1,AE20/Q20) -> 0 | AR20: =IF(Q20=0,0,(AF20+AG20)/Q20) -> 0 | AS20: {=_xlfn.IFS(S20=0,AL20,S20<0,AL20/-S20,S20>0,AL20/S20)} -> #DIV/0! | AT20: =IF(AN20=0,0,AS20/AN20) -> 0 | AU20: =IF(AO20=0,0,AS20/AO20) -> 0 | AW20: =AS20*E20 -> #DIV/0!
E21: =SUM(F21:H21) -> 0 | J21: =E21*I21 -> 0 | O21: =L21/7 -> 0 | P21: =S21/7 -> 0 | S21: =Q21+R21 -> 0 | V21: =T21+U21 -> 0 | Y21: =W21+X21 -> 0 | Z21: =L21*M21*N21/100 -> 0 | AA21: =Y21/$Y$74 -> #DIV/0! | AB21: =S21*I21 -> 0 | AD21: =IF(Y21=0,0,AC21/Y21) -> 0 | AI21: =$AI$74*H21/$H$74 -> #DIV/0! | AK21: =V21*1% -> 0 | AL21: =Y21-AB21-AC21-AE21-AF21-AG21-AH21-AI21-AK21-AJ21 -> #DIV/0! | AN21: =IF(S21=0,0,Y21/S21) -> 0 | AO21: =I21 -> 0 | AP21: =IF(S21=0,0,AC21/S21) -> 0 | AQ21: =IF(Q21=0,AE21/1,AE21/Q21) -> 0 | AR21: =IF(Q21=0,0,(AF21+AG21)/Q21) -> 0 | AS21: {=_xlfn.IFS(S21=0,AL21,S21<0,AL21/-S21,S21>0,AL21/S21)} -> #DIV/0! | AT21: =IF(AN21=0,0,AS21/AN21) -> 0 | AU21: =IF(AO21=0,0,AS21/AO21) -> 0 | AW21: =AS21*E21 -> #DIV/0!
E22: =SUM(F22:H22) -> 0 | J22: =E22*I22 -> 0 | O22: =L22/7 -> 0 | P22: =S22/7 -> 0 | S22: =Q22+R22 -> 0 | V22: =T22+U22 -> 0 | Y22: =W22+X22 -> 0 | Z22: =L22*M22*N22/100 -> 0 | AA22: =Y22/$Y$74 -> #DIV/0! | AB22: =S22*I22 -> 0 | AD22: =IF(Y22=0,0,AC22/Y22) -> 0 | AI22: =$AI$74*H22/$H$74 -> #DIV/0! | AK22: =V22*1% -> 0 | AL22: =Y22-AB22-AC22-AE22-AF22-AG22-AH22-AI22-AK22-AJ22 -> #DIV/0! | AN22: =IF(S22=0,0,Y22/S22) -> 0 | AO22: =I22 -> 0 | AP22: =IF(S22=0,0,AC22/S22) -> 0 | AQ22: =IF(Q22=0,AE22/1,AE22/Q22) -> 0 | AR22: =IF(Q22=0,0,(AF22+AG22)/Q22) -> 0 | AS22: {=_xlfn.IFS(S22=0,AL22,S22<0,AL22/-S22,S22>0,AL22/S22)} -> #DIV/0! | AT22: =IF(AN22=0,0,AS22/AN22) -> 0 | AU22: =IF(AO22=0,0,AS22/AO22) -> 0 | AW22: =AS22*E22 -> #DIV/0!
E23: =SUM(F23:H23) -> 0 | J23: =E23*I23 -> 0 | O23: =L23/7 -> 0 | P23: =S23/7 -> 0 | S23: =Q23+R23 -> 0 | V23: =T23+U23 -> 0 | Y23: =W23+X23 -> 0 | Z23: =L23*M23*N23/100 -> 0 | AA23: =Y23/$Y$74 -> #DIV/0! | AB23: =S23*I23 -> 0 | AD23: =IF(Y23=0,0,AC23/Y23) -> 0 | AI23: =$AI$74*H23/$H$74 -> #DIV/0! | AK23: =V23*1% -> 0 | AL23: =Y23-AB23-AC23-AE23-AF23-AG23-AH23-AI23-AK23-AJ23 -> #DIV/0! | AN23: =IF(S23=0,0,Y23/S23) -> 0 | AO23: =I23 -> 0 | AP23: =IF(S23=0,0,AC23/S23) -> 0 | AQ23: =IF(Q23=0,AE23/1,AE23/Q23) -> 0 | AR23: =IF(Q23=0,0,(AF23+AG23)/Q23) -> 0 | AS23: {=_xlfn.IFS(S23=0,AL23,S23<0,AL23/-S23,S23>0,AL23/S23)} -> #DIV/0! | AT23: =IF(AN23=0,0,AS23/AN23) -> 0 | AU23: =IF(AO23=0,0,AS23/AO23) -> 0 | AW23: =AS23*E23 -> #DIV/0!
E24: =SUM(F24:H24) -> 0 | J24: =E24*I24 -> 0 | O24: =L24/7 -> 0 | P24: =S24/7 -> 0 | S24: =Q24+R24 -> 0 | V24: =T24+U24 -> 0 | Y24: =W24+X24 -> 0 | Z24: =L24*M24*N24/100 -> 0 | AA24: =Y24/$Y$74 -> #DIV/0! | AB24: =S24*I24 -> 0 | AD24: =IF(Y24=0,0,AC24/Y24) -> 0 | AI24: =$AI$74*H24/$H$74 -> #DIV/0! | AK24: =V24*1% -> 0 | AL24: =Y24-AB24-AC24-AE24-AF24-AG24-AH24-AI24-AK24-AJ24 -> #DIV/0! | AN24: =IF(S24=0,0,Y24/S24) -> 0 | AO24: =I24 -> 0 | AP24: =IF(S24=0,0,AC24/S24) -> 0 | AQ24: =IF(Q24=0,AE24/1,AE24/Q24) -> 0 | AR24: =IF(Q24=0,0,(AF24+AG24)/Q24) -> 0 | AS24: {=_xlfn.IFS(S24=0,AL24,S24<0,AL24/-S24,S24>0,AL24/S24)} -> #DIV/0! | AT24: =IF(AN24=0,0,AS24/AN24) -> 0 | AU24: =IF(AO24=0,0,AS24/AO24) -> 0 | AW24: =AS24*E24 -> #DIV/0!
E25: =SUM(F25:H25) -> 0 | J25: =E25*I25 -> 0 | O25: =L25/7 -> 0 | P25: =S25/7 -> 0 | S25: =Q25+R25 -> 0 | V25: =T25+U25 -> 0 | Y25: =W25+X25 -> 0 | Z25: =L25*M25*N25/100 -> 0 | AA25: =Y25/$Y$74 -> #DIV/0! | AB25: =S25*I25 -> 0 | AD25: =IF(Y25=0,0,AC25/Y25) -> 0 | AI25: =$AI$74*H25/$H$74 -> #DIV/0! | AK25: =V25*1% -> 0 | AL25: =Y25-AB25-AC25-AE25-AF25-AG25-AH25-AI25-AK25-AJ25 -> #DIV/0! | AN25: =IF(S25=0,0,Y25/S25) -> 0 | AO25: =I25 -> 0 | AP25: =IF(S25=0,0,AC25/S25) -> 0 | AQ25: =IF(Q25=0,AE25/1,AE25/Q25) -> 0 | AR25: =IF(Q25=0,0,(AF25+AG25)/Q25) -> 0 | AS25: {=_xlfn.IFS(S25=0,AL25,S25<0,AL25/-S25,S25>0,AL25/S25)} -> #DIV/0! | AT25: =IF(AN25=0,0,AS25/AN25) -> 0 | AU25: =IF(AO25=0,0,AS25/AO25) -> 0 | AW25: =AS25*E25 -> #DIV/0!
E26: =SUM(F26:H26) -> 0 | J26: =E26*I26 -> 0 | O26: =L26/7 -> 0 | P26: =S26/7 -> 0 | S26: =Q26+R26 -> 0 | V26: =T26+U26 -> 0 | Y26: =W26+X26 -> 0 | Z26: =L26*M26*N26/100 -> 0 | AA26: =Y26/$Y$74 -> #DIV/0! | AB26: =S26*I26 -> 0 | AD26: =IF(Y26=0,0,AC26/Y26) -> 0 | AI26: =$AI$74*H26/$H$74 -> #DIV/0! | AK26: =V26*1% -> 0 | AL26: =Y26-AB26-AC26-AE26-AF26-AG26-AH26-AI26-AK26-AJ26 -> #DIV/0! | AN26: =IF(S26=0,0,Y26/S26) -> 0 | AO26: =I26 -> 0 | AP26: =IF(S26=0,0,AC26/S26) -> 0 | AQ26: =IF(Q26=0,AE26/1,AE26/Q26) -> 0 | AR26: =IF(Q26=0,0,(AF26+AG26)/Q26) -> 0 | AS26: {=_xlfn.IFS(S26=0,AL26,S26<0,AL26/-S26,S26>0,AL26/S26)} -> #DIV/0! | AT26: =IF(AN26=0,0,AS26/AN26) -> 0 | AU26: =IF(AO26=0,0,AS26/AO26) -> 0 | AW26: =AS26*E26 -> #DIV/0!
E27: =SUM(F27:H27) -> 0 | J27: =E27*I27 -> 0 | O27: =L27/7 -> 0 | P27: =S27/7 -> 0 | S27: =Q27+R27 -> 0 | V27: =T27+U27 -> 0 | Y27: =W27+X27 -> 0 | Z27: =L27*M27*N27/100 -> 0 | AA27: =Y27/$Y$74 -> #DIV/0! | AB27: =S27*I27 -> 0 | AD27: =IF(Y27=0,0,AC27/Y27) -> 0 | AI27: =$AI$74*H27/$H$74 -> #DIV/0! | AK27: =V27*1% -> 0 | AL27: =Y27-AB27-AC27-AE27-AF27-AG27-AH27-AI27-AK27-AJ27 -> #DIV/0! | AN27: =IF(S27=0,0,Y27/S27) -> 0 | AO27: =I27 -> 0 | AP27: =IF(S27=0,0,AC27/S27) -> 0 | AQ27: =IF(Q27=0,AE27/1,AE27/Q27) -> 0 | AR27: =IF(Q27=0,0,(AF27+AG27)/Q27) -> 0 | AS27: {=_xlfn.IFS(S27=0,AL27,S27<0,AL27/-S27,S27>0,AL27/S27)} -> #DIV/0! | AT27: =IF(AN27=0,0,AS27/AN27) -> 0 | AU27: =IF(AO27=0,0,AS27/AO27) -> 0 | AW27: =AS27*E27 -> #DIV/0!
E28: =SUM(F28:H28) -> 0 | J28: =E28*I28 -> 0 | O28: =L28/7 -> 0 | P28: =S28/7 -> 0 | S28: =Q28+R28 -> 0 | V28: =T28+U28 -> 0 | Y28: =W28+X28 -> 0 | Z28: =L28*M28*N28/100 -> 0 | AA28: =Y28/$Y$74 -> #DIV/0! | AB28: =S28*I28 -> 0 | AD28: =IF(Y28=0,0,AC28/Y28) -> 0 | AI28: =$AI$74*H28/$H$74 -> #DIV/0! | AK28: =V28*1% -> 0 | AL28: =Y28-AB28-AC28-AE28-AF28-AG28-AH28-AI28-AK28-AJ28 -> #DIV/0! | AN28: =IF(S28=0,0,Y28/S28) -> 0 | AO28: =I28 -> 0 | AP28: =IF(S28=0,0,AC28/S28) -> 0 | AQ28: =IF(Q28=0,AE28/1,AE28/Q28) -> 0 | AR28: =IF(Q28=0,0,(AF28+AG28)/Q28) -> 0 | AS28: {=_xlfn.IFS(S28=0,AL28,S28<0,AL28/-S28,S28>0,AL28/S28)} -> #DIV/0! | AT28: =IF(AN28=0,0,AS28/AN28) -> 0 | AU28: =IF(AO28=0,0,AS28/AO28) -> 0 | AW28: =AS28*E28 -> #DIV/0!
E29: =SUM(F29:H29) -> 0 | J29: =E29*I29 -> 0 | O29: =L29/7 -> 0 | P29: =S29/7 -> 0 | S29: =Q29+R29 -> 0 | V29: =T29+U29 -> 0 | Y29: =W29+X29 -> 0 | Z29: =L29*M29*N29/100 -> 0 | AA29: =Y29/$Y$74 -> #DIV/0! | AB29: =S29*I29 -> 0 | AD29: =IF(Y29=0,0,AC29/Y29) -> 0 | AI29: =$AI$74*H29/$H$74 -> #DIV/0! | AK29: =V29*1% -> 0 | AL29: =Y29-AB29-AC29-AE29-AF29-AG29-AH29-AI29-AK29-AJ29 -> #DIV/0! | AN29: =IF(S29=0,0,Y29/S29) -> 0 | AO29: =I29 -> 0 | AP29: =IF(S29=0,0,AC29/S29) -> 0 | AQ29: =IF(Q29=0,AE29/1,AE29/Q29) -> 0 | AR29: =IF(Q29=0,0,(AF29+AG29)/Q29) -> 0 | AS29: {=_xlfn.IFS(S29=0,AL29,S29<0,AL29/-S29,S29>0,AL29/S29)} -> #DIV/0! | AT29: =IF(AN29=0,0,AS29/AN29) -> 0 | AU29: =IF(AO29=0,0,AS29/AO29) -> 0 | AW29: =AS29*E29 -> #DIV/0!
E30: =SUM(F30:H30) -> 0 | J30: =E30*I30 -> 0 | O30: =L30/7 -> 0 | P30: =S30/7 -> 0 | S30: =Q30+R30 -> 0 | V30: =T30+U30 -> 0 | Y30: =W30+X30 -> 0 | Z30: =L30*M30*N30/100 -> 0 | AA30: =Y30/$Y$74 -> #DIV/0! | AB30: =S30*I30 -> 0 | AD30: =IF(Y30=0,0,AC30/Y30) -> 0 | AI30: =$AI$74*H30/$H$74 -> #DIV/0! | AK30: =V30*1% -> 0 | AL30: =Y30-AB30-AC30-AE30-AF30-AG30-AH30-AI30-AK30-AJ30 -> #DIV/0! | AN30: =IF(S30=0,0,Y30/S30) -> 0 | AO30: =I30 -> 0 | AP30: =IF(S30=0,0,AC30/S30) -> 0 | AQ30: =IF(Q30=0,AE30/1,AE30/Q30) -> 0 | AR30: =IF(Q30=0,0,(AF30+AG30)/Q30) -> 0 | AS30: {=_xlfn.IFS(S30=0,AL30,S30<0,AL30/-S30,S30>0,AL30/S30)} -> #DIV/0! | AT30: =IF(AN30=0,0,AS30/AN30) -> 0 | AU30: =IF(AO30=0,0,AS30/AO30) -> 0 | AW30: =AS30*E30 -> #DIV/0!
... E70: =SUM(F70:H70) -> 0 | J70: =E70*I70 -> 0 | O70: =L70/7 -> 0 | P70: =S70/7 -> 0 | S70: =Q70+R70 -> 0 | V70: =T70+U70 -> 0 | Y70: =W70+X70 -> 0 | Z70: =L70*M70*N70/100 -> 0 | AA70: =Y70/$Y$74 -> #DIV/0! | AB70: =S70*I70 -> 0 | AD70: =IF(Y70=0,0,AC70/Y70) -> 0 | AI70: =$AI$74*H70/$H$74 -> #DIV/0! | AK70: =V70*1% -> 0 | AL70: =Y70-AB70-AC70-AE70-AF70-AG70-AH70-AI70-AK70-AJ70 -> #DIV/0! | AN70: =IF(S70=0,0,Y70/S70) -> 0 | AO70: =I70 -> 0 | AP70: =IF(S70=0,0,AC70/S70) -> 0 | AQ70: =IF(Q70=0,AE70/1,AE70/Q70) -> 0 | AR70: =IF(Q70=0,0,(AF70+AG70)/Q70) -> 0 | AS70: {=_xlfn.IFS(S70=0,AL70,S70<0,AL70/-S70,S70>0,AL70/S70)} -> #DIV/0! | AT70: =IF(AN70=0,0,AS70/AN70) -> 0 | AU70: =IF(AO70=0,0,AS70/AO70) -> 0 | AW70: =AS70*E70 -> #DIV/0!
AN71: =AVERAGE(AN19:AN70) -> 0 | AO71: =AVERAGE(AO19:AO70) -> 0 | AP71: =AVERAGE(AP19:AP70) -> 0 | AQ71: =AVERAGE(AQ19:AQ70) -> 0 | AR71: =AVERAGE(AR19:AR70) -> 0 | AS71: =AVERAGE(AS19:AS70) -> #DIV/0! | AT71: =AVERAGE(AT19:AT70) -> 0 | AU71: =AVERAGE(AU19:AU70) -> 0
A72: Итого ___ | E72: =SUM(E19:E70) -> 0 | F72: =SUM(F19:F70) -> 0 | G72: =SUM(G19:G70) -> 0 | H72: =SUM(H19:H70) -> 0 | J72: =SUM(J19:J70) -> 0 | L72: =SUM(L19:L70) -> 0 | Q72: =SUM(Q19:Q70) -> 0 | R72: =SUM(R19:R70) -> 0 | S72: =SUM(S19:S70) -> 0 | T72: =SUM(T19:T70) -> 0 | U72: =SUM(U19:U70) -> 0 | V72: =SUM(V19:V70) -> 0 | W72: =SUM(W19:W70) -> 0 | X72: =SUM(X19:X70) -> 0 | ... AC72: =SUM(AC19:AC70) -> 0 | AD72: =AC72/Y72 -> #DIV/0! | AE72: =SUM(AE19:AE70) -> 0 | AF72: =SUM(AF19:AF70) -> 0 | AG72: =SUM(AG19:AG70) -> 0 | AH72: =SUM(AH19:AH70) -> 0 | AI72: =SUM(AI19:AI70) -> #DIV/0! | AJ72: =SUM(AJ19:AJ70) -> 0 | AK72: =SUM(AK19:AK70) -> 0 | AL72: =SUM(AL19:AL70) -> #DIV/0! | AR72: =(AF72+AG72)/Q72 -> #DIV/0! | AW72: =SUM(AW19:AW70) -> #DIV/0!
A74: ИТОГО | E74: =E17+E72 -> 0 | F74: =F17+F72 -> 0 | G74: =G17+G72 -> 0 | H74: =H17+H72 -> 0 | I74: =I17+I72 -> 0 | J74: =J17+J72 -> 0 | K74: =K17+K72 -> 0 | L74: =L17+L72 -> 0 | ... AC74: =AC17+AC72 -> 0 | AD74: =AC74/Y74 -> #DIV/0! | AE74: =AE17+AE72 -> 0 | AF74: =AF17+AF72 -> 0 | AG74: =AG17+AG72 -> 0 | AH74: =AH17+AH72 -> 0 | AJ74: =AJ17+AJ72 -> 0 | AK74: =AK17+AK72 -> 0 | AL74: =AL17+AL72 -> #DIV/0! | AR74: =(AF74+AG74)/Q74 -> #DIV/0! | AW74: =AW17+AW72 -> #DIV/0!
AF75: =AF18+AF73 -> 0

Sheet ЯНВАРЬ
A1: 29.12-01.02_1-5 нед | F1: Отчет по остаткам 3,4,5 | K1: Цены и скидки 6 | L1: Воронка продаж 16,50,32 | AI1: Вставить в Итого | AN1: на 1 единицу проданного товара
A2: Бренд | B2: SKU | C2: Артикул поставщика | D2: Предмет | E2: Остаток на 02.02 | F2: В пути до клиента | G2: В пути от клиента | H2: Итого по складам ВБ | I2: Себетоимость на 1 ед на 29.09.25 | J2: Себестоимость остатков | K2: Оборачива-емость, дн | L2: Заказы, шт 7 дней | M2: Средняя цена, руб | N2: % выкупа за 7 дней | O2: Скорость заказов | P2: Скорость продаж | Q2: Кол-во ПРОДАЖИ | R2: Кол-во ВОЗВРАТЫ | S2: Кол-во ПРОДАЖИ-ВОЗВРАТЫ | T2: Выручка ВБ ПРОДАЖИ | U2: Выручка ВБ ВОЗВРАТЫ | V2: Выручка с учетом СПП ПРОДАЖИ - ВОЗВРАТЫ | W2: Выручка ПРОДАЖИ | X2: Выручка ВОЗВРАТЫ | Y2: Выручка с учетом согласованной скидки ПРОДАЖИ - ВОЗВРАТЫ | Z2: Выручка потенциальная | AA2: Доля выручки, % от общего объема | AB2: Себестоимость продаж | AC2: Комиссия, руб | AD2: Комиссия, % | AE2: Логистика | AF2: Реклама БАЛАНС | AG2: Реклама СЧЕТ | AH2: Блогеры | AI2: Хранение | AJ2: Штрафы | AK2: Налог 1% | AL2: Прибыль | AN2: Выручка на 1 ед (средняя цена продажи со скидкой) | AO2: Себестоимость на 1 ед | AP2: Комиссия на 1 ед | AQ2: Логистика на 1 ед | AR2: Реклама на 1 ед | AS2: Прибыль на 1 ед | AT2: Маржиналь-ность, % | AU2: Рентабель-ность, % | AW2: Прибыль с остатков
B3: 341479791 | C3: Черные с железкой Сул | D3: Солнцезащитные очки | E3: ='Юнит 5'!E3 -> 0 | F3: ='Юнит 5'!F3 -> 36 | G3: ='Юнит 5'!G3 -> 5 | H3: ='Юнит 5'!H3 -> 349 | I3: 142.98 | J3: =E3*I3 -> 0 | K3: ='Юнит 5'!K3 -> 133 | L3: ='Юнит 1'!L3+'Юнит 2'!L3+'Юнит 3'!L3+'Юнит 4'!L3+'Юнит 5'!L3 -> 137 | M3: ='Юнит 1'!M3+'Юнит 2'!M3+'Юнит 3'!M3+'Юнит 4'!M3+'Юнит 5'!M3 -> 6268 | N3: ='Юнит 1'!N3+'Юнит 2'!N3+'Юнит 3'!N3+'Юнит 4'!N3+'Юнит 5'!N3 -> 329 | O3: =L3/7 -> 19.571429 | P3: =S3/7 -> 8.8571429 | Q3: ='Юнит 1'!Q3+'Юнит 2'!Q3+'Юнит 3'!Q3+'Юнит 4'!Q3+'Юнит 5'!Q3 -> 64 | R3: ='Юнит 1'!R3+'Юнит 2'!R3+'Юнит 3'!R3+'Юнит 4'!R3+'Юнит 5'!R3 -> -2 | S3: =Q3+R3 -> 62 | T3: ='Юнит 1'!T3+'Юнит 2'!T3+'Юнит 3'!T3+'Юнит 4'!T3+'Юнит 5'!T3 -> 59784.03 | U3: ='Юнит 1'!U3+'Юнит 2'!U3+'Юнит 3'!U3+'Юнит 4'!U3+'Юнит 5'!U3 -> -1870 | V3: =T3+U3 -> 57914.03 | W3: ='Юнит 1'!W3+'Юнит 2'!W3+'Юнит 3'!W3+'Юнит 4'!W3+'Юнит 5'!W3 -> 79728.06 | X3: ='Юнит 1'!X3+'Юнит 2'!X3+'Юнит 3'!X3+'Юнит 4'!X3+'Юнит 5'!X3 -> -2476 | Y3: =W3+X3 -> 77252.06 | Z3: =L3*M3*N3/100 -> 2825175.6 | AA3: =Y3/$Y$74 -> 0.25944676 | AB3: =S3*I3 -> 8864.76 | AC3: ='Юнит 1'!AC3+'Юнит 2'!AC3+'Юнит 3'!AC3+'Юнит 4'!AC3+'Юнит 5'!AC3 -> 27903.82 | AD3: =IF(Y3=0,0,AC3/Y3) -> 0.36120487 | AE3: ='Юнит 1'!AE3+'Юнит 2'!AE3+'Юнит 3'!AE3+'Юнит 4'!AE3+'Юнит 5'!AE3 -> 8098.55 | AF3: ='Юнит 1'!AF3+'Юнит 2'!AF3+'Юнит 3'!AF3+'Юнит 4'!AF3+'Юнит 5'!AF3 -> 9000 | AG3: ='Юнит 1'!AG3+'Юнит 2'!AG3+'Юнит 3'!AG3+'Юнит 4'!AG3+'Юнит 5'!AG3 -> 7676 | AH3: ='Юнит 1'!AH3+'Юнит 2'!AH3+'Юнит 3'!AH3+'Юнит 4'!AH3+'Юнит 5'!AH3 -> 0 | AI3: ='Юнит 1'!AI3+'Юнит 2'!AI3+'Юнит 3'!AI3+'Юнит 4'!AI3+'Юнит 5'!AI3 -> 1100.1007 | AJ3: ='Юнит 1'!AJ3+'Юнит 2'!AJ3+'Юнит 3'!AJ3+'Юнит 4'!AJ3+'Юнит 5'!AJ3 -> 0 | AK3: =V3*1% -> 579.1403 | AL3: =Y3-AB3-AC3-AE3-AF3-AG3-AH3-AI3-AK3-AJ3 -> 14029.689 | AN3: =IF(S3=0,0,Y3/S3) -> 1246.001 | AO3: =I3 -> 142.98 | AP3: =IF(S3=0,0,AC3/S3) -> 450.06161 | AQ3: =IF(Q3=0,AE3/1,AE3/Q3) -> 126.53984 | AR3: =IF(Q3=0,0,(AF3+AG3)/Q3) -> 260.5625 | AS3: =_xlfn.IFS(S3=0,AL3,S3<0,AL3/-S3,S3>0,AL3/S3) -> 226.28531 | AT3: =IF(AN3=0,0,AS3/AN3) -> 0.18160925 | AU3: =IF(AO3=0,0,AS3/AO3) -> 1.5826361 | AW3: =AS3*E3 -> 0
B4: 340343575 | C4: Qs черн Сул | D4: Солнцезащитные очки | E4: ='Юнит 5'!E4 -> 0 | F4: ='Юнит 5'!F4 -> 15 | G4: ='Юнит 5'!G4 -> 4 | H4: ='Юнит 5'!H4 -> 260 | I4: 123.09 | J4: =E4*I4 -> 0 | K4: ='Юнит 5'!K4 -> 314 | L4: ='Юнит 1'!L4+'Юнит 2'!L4+'Юнит 3'!L4+'Юнит 4'!L4+'Юнит 5'!L4 -> 31 | M4: ='Юнит 1'!M4+'Юнит 2'!M4+'Юнит 3'!M4+'Юнит 4'!M4+'Юнит 5'!M4 -> 2910 | N4: ='Юнит 1'!N4+'Юнит 2'!N4+'Юнит 3'!N4+'Юнит 4'!N4+'Юнит 5'!N4 -> 60 | O4: =L4/7 -> 4.4285714 | P4: =S4/7 -> 1.4285714 | Q4: ='Юнит 1'!Q4+'Юнит 2'!Q4+'Юнит 3'!Q4+'Юнит 4'!Q4+'Юнит 5'!Q4 -> 10 | R4: ='Юнит 1'!R4+'Юнит 2'!R4+'Юнит 3'!R4+'Юнит 4'!R4+'Юнит 5'!R4 -> 0 | S4: =Q4+R4 -> 10 | T4: ='Юнит 1'!T4+'Юнит 2'!T4+'Юнит 3'!T4+'Юнит 4'!T4+'Юнит 5'!T4 -> 6321.49 | U4: ='Юнит 1'!U4+'Юнит 2'!U4+'Юнит 3'!U4+'Юнит 4'!U4+'Юнит 5'!U4 -> 0 | V4: =T4+U4 -> 6321.49 | W4: ='Юнит 1'!W4+'Юнит 2'!W4+'Юнит 3'!W4+'Юнит 4'!W4+'Юнит 5'!W4 -> 9289.38 | X4: ='Юнит 1'!X4+'Юнит 2'!X4+'Юнит 3'!X4+'Юнит 4'!X4+'Юнит 5'!X4 -> 0 | Y4: =W4+X4 -> 9289.38 | Z4: =L4*M4*N4/100 -> 54126 | AA4: =Y4/$Y$74 -> 0.031197867 | AB4: =S4*I4 -> 1230.9 | AC4: ='Юнит 1'!AC4+'Юнит 2'!AC4+'Юнит 3'!AC4+'Юнит 4'!AC4+'Юнит 5'!AC4 -> 3407.19 | AD4: =IF(Y4=0,0,AC4/Y4) -> 0.36678336 | AE4: ='Юнит 1'!AE4+'Юнит 2'!AE4+'Юнит 3'!AE4+'Юнит 4'!AE4+'Юнит 5'!AE4 -> 1151.15 | AF4: ='Юнит 1'!AF4+'Юнит 2'!AF4+'Юнит 3'!AF4+'Юнит 4'!AF4+'Юнит 5'!AF4 -> 892 | AG4: ='Юнит 1'!AG4+'Юнит 2'!AG4+'Юнит 3'!AG4+'Юнит 4'!AG4+'Юнит 5'!AG4 -> 2427 | AH4: ='Юнит 1'!AH4+'Юнит 2'!AH4+'Юнит 3'!AH4+'Юнит 4'!AH4+'Юнит 5'!AH4 -> 0 | AI4: ='Юнит 1'!AI4+'Юнит 2'!AI4+'Юнит 3'!AI4+'Юнит 4'!AI4+'Юнит 5'!AI4 -> 764.01974 | AJ4: ='Юнит 1'!AJ4+'Юнит 2'!AJ4+'Юнит 3'!AJ4+'Юнит 4'!AJ4+'Юнит 5'!AJ4 -> 0 | AK4: =V4*1% -> 63.2149 | AL4: =Y4-AB4-AC4-AE4-AF4-AG4-AH4-AI4-AK4-AJ4 -> -646.09464 | AN4: =IF(S4=0,0,Y4/S4) -> 928.938 | AO4: =I4 -> 123.09 | AP4: =IF(S4=0,0,AC4/S4) -> 340.719 | AQ4: =IF(Q4=0,AE4/1,AE4/Q4) -> 115.115 | AR4: =IF(Q4=0,0,(AF4+AG4)/Q4) -> 331.9 | AS4: {=_xlfn.IFS(S4=0,AL4,S4<0,AL4/-S4,S4>0,AL4/S4)} -> -64.609464 | AT4: =IF(AN4=0,0,AS4/AN4) -> -0.069551966 | AU4: =IF(AO4=0,0,AS4/AO4) -> -0.52489612 | AW4: =AS4*E4 -> 0
B5: 340332621 | C5: Qs син Сул | D5: Солнцезащитные очки | E5: ='Юнит 5'!E5 -> 0 | F5: ='Юнит 5'!F5 -> 3 | G5: ='Юнит 5'!G5 | H5: ='Юнит 5'!H5 -> 372 | I5: 123.09 | J5: =E5*I5 -> 0 | K5: ='Юнит 5'!K5 -> 999 | L5: ='Юнит 1'!L5+'Юнит 2'!L5+'Юнит 3'!L5+'Юнит 4'!L5+'Юнит 5'!L5 -> 6 | M5: ='Юнит 1'!M5+'Юнит 2'!M5+'Юнит 3'!M5+'Юнит 4'!M5+'Юнит 5'!M5 -> 2104 | N5: ='Юнит 1'!N5+'Юнит 2'!N5+'Юнит 3'!N5+'Юнит 4'!N5+'Юнит 5'!N5 -> 100 | O5: =L5/7 -> 0.85714286 | P5: =S5/7 -> 0.57142857 | Q5: ='Юнит 1'!Q5+'Юнит 2'!Q5+'Юнит 3'!Q5+'Юнит 4'!Q5+'Юнит 5'!Q5 -> 4 | R5: ='Юнит 1'!R5+'Юнит 2'!R5+'Юнит 3'!R5+'Юнит 4'!R5+'Юнит 5'!R5 -> 0 | S5: =Q5+R5 -> 4 | T5: ='Юнит 1'!T5+'Юнит 2'!T5+'Юнит 3'!T5+'Юнит 4'!T5+'Юнит 5'!T5 -> 2054 | U5: ='Юнит 1'!U5+'Юнит 2'!U5+'Юнит 3'!U5+'Юнит 4'!U5+'Юнит 5'!U5 -> 0 | V5: =T5+U5 -> 2054 | W5: ='Юнит 1'!W5+'Юнит 2'!W5+'Юнит 3'!W5+'Юнит 4'!W5+'Юнит 5'!W5 -> 3156 | X5: ='Юнит 1'!X5+'Юнит 2'!X5+'Юнит 3'!X5+'Юнит 4'!X5+'Юнит 5'!X5 -> 0 | Y5: =W5+X5 -> 3156 | Z5: =L5*M5*N5/100 -> 12624 | AA5: =Y5/$Y$74 -> 0.010599251 | AB5: =S5*I5 -> 492.36 | AC5: ='Юнит 1'!AC5+'Юнит 2'!AC5+'Юнит 3'!AC5+'Юнит 4'!AC5+'Юнит 5'!AC5 -> 332 | AD5: =IF(Y5=0,0,AC5/Y5) -> 0.10519645 | AE5: ='Юнит 1'!AE5+'Юнит 2'!AE5+'Юнит 3'!AE5+'Юнит 4'!AE5+'Юнит 5'!AE5 -> 187.05 | AF5: ='Юнит 1'!AF5+'Юнит 2'!AF5+'Юнит 3'!AF5+'Юнит 4'!AF5+'Юнит 5'!AF5 -> 1691 | AG5: ='Юнит 1'!AG5+'Юнит 2'!AG5+'Юнит 3'!AG5+'Юнит 4'!AG5+'Юнит 5'!AG5 -> 557 | AH5: ='Юнит 1'!AH5+'Юнит 2'!AH5+'Юнит 3'!AH5+'Юнит 4'!AH5+'Юнит 5'!AH5 -> 0 | AI5: ='Юнит 1'!AI5+'Юнит 2'!AI5+'Юнит 3'!AI5+'Юнит 4'!AI5+'Юнит 5'!AI5 -> 1029.851 | AJ5: ='Юнит 1'!AJ5+'Юнит 2'!AJ5+'Юнит 3'!AJ5+'Юнит 4'!AJ5+'Юнит 5'!AJ5 -> 0 | AK5: =V5*1% -> 20.54 | AL5: =Y5-AB5-AC5-AE5-AF5-AG5-AH5-AI5-AK5-AJ5 -> -1153.801 | AN5: =IF(S5=0,0,Y5/S5) -> 789 | AO5: =I5 -> 123.09 | AP5: =IF(S5=0,0,AC5/S5) -> 83 | AQ5: =IF(Q5=0,AE5/1,AE5/Q5) -> 46.7625 | AR5: =IF(Q5=0,0,(AF5+AG5)/Q5) -> 562 | AS5: {=_xlfn.IFS(S5=0,AL5,S5<0,AL5/-S5,S5>0,AL5/S5)} -> -288.45024 | AT5: =IF(AN5=0,0,AS5/AN5) -> -0.36558966 | AU5: =IF(AO5=0,0,AS5/AO5) -> -2.3434092 | AW5: =AS5*E5 -> 0
B6: 340341838 | C6: Qs желт Сул | D6: Солнцезащитные очки | E6: ='Юнит 5'!E6 -> 0 | F6: ='Юнит 5'!F6 -> 4 | G6: ='Юнит 5'!G6 -> 2 | H6: ='Юнит 5'!H6 -> 341 | I6: 123.09 | J6: =E6*I6 -> 0 | K6: ='Юнит 5'!K6 -> 551 | L6: ='Юнит 1'!L6+'Юнит 2'!L6+'Юнит 3'!L6+'Юнит 4'!L6+'Юнит 5'!L6 -> 34 | M6: ='Юнит 1'!M6+'Юнит 2'!M6+'Юнит 3'!M6+'Юнит 4'!M6+'Юнит 5'!M6 -> 5772 | N6: ='Юнит 1'!N6+'Юнит 2'!N6+'Юнит 3'!N6+'Юнит 4'!N6+'Юнит 5'!N6 -> 435 | O6: =L6/7 -> 4.8571429 | P6: =S6/7 -> 2.8571429 | Q6: ='Юнит 1'!Q6+'Юнит 2'!Q6+'Юнит 3'!Q6+'Юнит 4'!Q6+'Юнит 5'!Q6 -> 20 | R6: ='Юнит 1'!R6+'Юнит 2'!R6+'Юнит 3'!R6+'Юнит 4'!R6+'Юнит 5'!R6 -> 0 | S6: =Q6+R6 -> 20 | T6: ='Юнит 1'!T6+'Юнит 2'!T6+'Юнит 3'!T6+'Юнит 4'!T6+'Юнит 5'!T6 -> 17923 | U6: ='Юнит 1'!U6+'Юнит 2'!U6+'Юнит 3'!U6+'Юнит 4'!U6+'Юнит 5'!U6 -> 0 | V6: =T6+U6 -> 17923 | W6: ='Юнит 1'!W6+'Юнит 2'!W6+'Юнит 3'!W6+'Юнит 4'!W6+'Юнит 5'!W6 -> 23148 | X6: ='Юнит 1'!X6+'Юнит 2'!X6+'Юнит 3'!X6+'Юнит 4'!X6+'Юнит 5'!X6 -> 0 | Y6: =W6+X6 -> 23148 | Z6: =L6*M6*N6/100 -> 853678.8 | AA6: =Y6/$Y$74 -> 0.077741274 | AB6: =S6*I6 -> 2461.8 | AC6: ='Юнит 1'!AC6+'Юнит 2'!AC6+'Юнит 3'!AC6+'Юнит 4'!AC6+'Юнит 5'!AC6 -> 8382.6 | AD6: =IF(Y6=0,0,AC6/Y6) -> 0.36213064 | AE6: ='Юнит 1'!AE6+'Юнит 2'!AE6+'Юнит 3'!AE6+'Юнит 4'!AE6+'Юнит 5'!AE6 -> 2398.1 | AF6: ='Юнит 1'!AF6+'Юнит 2'!AF6+'Юнит 3'!AF6+'Юнит 4'!AF6+'Юнит 5'!AF6 -> 412 | AG6: ='Юнит 1'!AG6+'Юнит 2'!AG6+'Юнит 3'!AG6+'Юнит 4'!AG6+'Юнит 5'!AG6 -> 1379 | AH6: ='Юнит 1'!AH6+'Юнит 2'!AH6+'Юнит 3'!AH6+'Юнит 4'!AH6+'Юнит 5'!AH6 -> 0 | AI6: ='Юнит 1'!AI6+'Юнит 2'!AI6+'Юнит 3'!AI6+'Юнит 4'!AI6+'Юнит 5'!AI6 -> 959.92768 | AJ6: ='Юнит 1'!AJ6+'Юнит 2'!AJ6+'Юнит 3'!AJ6+'Юнит 4'!AJ6+'Юнит 5'!AJ6 -> 0 | AK6: =V6*1% -> 179.23 | AL6: =Y6-AB6-AC6-AE6-AF6-AG6-AH6-AI6-AK6-AJ6 -> 6975.3423 | AN6: =IF(S6=0,0,Y6/S6) -> 1157.4 | AO6: =I6 -> 123.09 | AP6: =IF(S6=0,0,AC6/S6) -> 419.13 | AQ6: =IF(Q6=0,AE6/1,AE6/Q6) -> 119.905 | AR6: =IF(Q6=0,0,(AF6+AG6)/Q6) -> 89.55 | AS6: {=_xlfn.IFS(S6=0,AL6,S6<0,AL6/-S6,S6>0,AL6/S6)} -> 348.76712 | AT6: =IF(AN6=0,0,AS6/AN6) -> 0.30133672 | AU6: =IF(AO6=0,0,AS6/AO6) -> 2.8334318 | AW6: =AS6*E6 -> 0
B7: 445291724 | C7: flip черные Сул | D7: Солнцезащитные очки | E7: ='Юнит 5'!E7 -> 0 | F7: ='Юнит 5'!F7 -> 4 | G7: ='Юнит 5'!G7 | H7: ='Юнит 5'!H7 -> 279 | I7: 123.09 | J7: =E7*I7 -> 0 | K7: ='Юнит 5'!K7 -> 999 | L7: ='Юнит 1'!L7+'Юнит 2'!L7+'Юнит 3'!L7+'Юнит 4'!L7+'Юнит 5'!L7 -> 7 | M7: ='Юнит 1'!M7+'Юнит 2'!M7+'Юнит 3'!M7+'Юнит 4'!M7+'Юнит 5'!M7 -> 3237 | N7: ='Юнит 1'!N7+'Юнит 2'!N7+'Юнит 3'!N7+'Юнит 4'!N7+'Юнит 5'!N7 -> 100 | O7: =L7/7 -> 1 | P7: =S7/7 -> 0.14285714 | Q7: ='Юнит 1'!Q7+'Юнит 2'!Q7+'Юнит 3'!Q7+'Юнит 4'!Q7+'Юнит 5'!Q7 -> 1 | R7: ='Юнит 1'!R7+'Юнит 2'!R7+'Юнит 3'!R7+'Юнит 4'!R7+'Юнит 5'!R7 -> 0 | S7: =Q7+R7 -> 1 | T7: ='Юнит 1'!T7+'Юнит 2'!T7+'Юнит 3'!T7+'Юнит 4'!T7+'Юнит 5'!T7 -> 672 | U7: ='Юнит 1'!U7+'Юнит 2'!U7+'Юнит 3'!U7+'Юнит 4'!U7+'Юнит 5'!U7 -> 0 | V7: =T7+U7 -> 672 | W7: ='Юнит 1'!W7+'Юнит 2'!W7+'Юнит 3'!W7+'Юнит 4'!W7+'Юнит 5'!W7 -> 1079 | X7: ='Юнит 1'!X7+'Юнит 2'!X7+'Юнит 3'!X7+'Юнит 4'!X7+'Юнит 5'!X7 -> 0 | Y7: =W7+X7 -> 1079 | Z7: =L7*M7*N7/100 -> 22659 | AA7: =Y7/$Y$74 -> 0.0036237617 | AB7: =S7*I7 -> 123.09 | AC7: ='Юнит 1'!AC7+'Юнит 2'!AC7+'Юнит 3'!AC7+'Юнит 4'!AC7+'Юнит 5'!AC7 -> 394.09 | AD7: =IF(Y7=0,0,AC7/Y7) -> 0.36523633 | AE7: ='Юнит 1'!AE7+'Юнит 2'!AE7+'Юнит 3'!AE7+'Юнит 4'!AE7+'Юнит 5'!AE7 -> 380.55 | AF7: ='Юнит 1'!AF7+'Юнит 2'!AF7+'Юнит 3'!AF7+'Юнит 4'!AF7+'Юнит 5'!AF7 -> 1094 | AG7: ='Юнит 1'!AG7+'Юнит 2'!AG7+'Юнит 3'!AG7+'Юнит 4'!AG7+'Юнит 5'!AG7 -> 217 | AH7: ='Юнит 1'!AH7+'Юнит 2'!AH7+'Юнит 3'!AH7+'Юнит 4'!AH7+'Юнит 5'!AH7 -> 0 | AI7: ='Юнит 1'!AI7+'Юнит 2'!AI7+'Юнит 3'!AI7+'Юнит 4'!AI7+'Юнит 5'!AI7 -> 772.67761 | AJ7: ='Юнит 1'!AJ7+'Юнит 2'!AJ7+'Юнит 3'!AJ7+'Юнит 4'!AJ7+'Юнит 5'!AJ7 -> 0 | AK7: =V7*1% -> 6.72 | AL7: =Y7-AB7-AC7-AE7-AF7-AG7-AH7-AI7-AK7-AJ7 -> -1909.1276 | AN7: =IF(S7=0,0,Y7/S7) -> 1079 | AO7: =I7 -> 123.09 | AP7: =IF(S7=0,0,AC7/S7) -> 394.09 | AQ7: =IF(Q7=0,AE7/1,AE7/Q7) -> 380.55 | AR7: =IF(Q7=0,0,(AF7+AG7)/Q7) -> 1311 | AS7: {=_xlfn.IFS(S7=0,AL7,S7<0,AL7/-S7,S7>0,AL7/S7)} -> -1909.1276 | AT7: =IF(AN7=0,0,AS7/AN7) -> -1.769349 | AU7: =IF(AO7=0,0,AS7/AO7) -> -15.510014 | AW7: =AS7*E7 -> 0
B8: 445336740 | C8: flip желтые Сул | D8: Солнцезащитные очки | E8: ='Юнит 5'!E8 -> 0 | F8: ='Юнит 5'!F8 -> 23 | G8: ='Юнит 5'!G8 -> 1 | H8: ='Юнит 5'!H8 -> 75 | I8: 123.09 | J8: =E8*I8 -> 0 | K8: ='Юнит 5'!K8 -> 50 | L8: ='Юнит 1'!L8+'Юнит 2'!L8+'Юнит 3'!L8+'Юнит 4'!L8+'Юнит 5'!L8 -> 136 | M8: ='Юнит 1'!M8+'Юнит 2'!M8+'Юнит 3'!M8+'Юнит 4'!M8+'Юнит 5'!M8 -> 5948 | N8: ='Юнит 1'!N8+'Юнит 2'!N8+'Юнит 3'!N8+'Юнит 4'!N8+'Юнит 5'!N8 -> 378 | O8: =L8/7 -> 19.428571 | P8: =S8/7 -> 15.285714 | Q8: ='Юнит 1'!Q8+'Юнит 2'!Q8+'Юнит 3'!Q8+'Юнит 4'!Q8+'Юнит 5'!Q8 -> 107 | R8: ='Юнит 1'!R8+'Юнит 2'!R8+'Юнит 3'!R8+'Юнит 4'!R8+'Юнит 5'!R8 -> 0 | S8: =Q8+R8 -> 107 | T8: ='Юнит 1'!T8+'Юнит 2'!T8+'Юнит 3'!T8+'Юнит 4'!T8+'Юнит 5'!T8 -> 103064.24 | U8: ='Юнит 1'!U8+'Юнит 2'!U8+'Юнит 3'!U8+'Юнит 4'!U8+'Юнит 5'!U8 -> 0 | V8: =T8+U8 -> 103064.24 | W8: ='Юнит 1'!W8+'Юнит 2'!W8+'Юнит 3'!W8+'Юнит 4'!W8+'Юнит 5'!W8 -> 128447.72 | X8: ='Юнит 1'!X8+'Юнит 2'!X8+'Юнит 3'!X8+'Юнит 4'!X8+'Юнит 5'!X8 -> 0 | Y8: =W8+X8 -> 128447.72 | Z8: =L8*M8*N8/100 -> 3057747.8 | AA8: =Y8/$Y$74 -> 0.43138454 | AB8: =S8*I8 -> 13170.63 | AC8: ='Юнит 1'!AC8+'Юнит 2'!AC8+'Юнит 3'!AC8+'Юнит 4'!AC8+'Юнит 5'!AC8 -> 46443.6 | AD8: =IF(Y8=0,0,AC8/Y8) -> 0.3615759 | AE8: ='Юнит 1'!AE8+'Юнит 2'!AE8+'Юнит 3'!AE8+'Юнит 4'!AE8+'Юнит 5'!AE8 -> 10755.05 | AF8: ='Юнит 1'!AF8+'Юнит 2'!AF8+'Юнит 3'!AF8+'Юнит 4'!AF8+'Юнит 5'!AF8 -> 5362 | AG8: ='Юнит 1'!AG8+'Юнит 2'!AG8+'Юнит 3'!AG8+'Юнит 4'!AG8+'Юнит 5'!AG8 -> 8225 | AH8: ='Юнит 1'!AH8+'Юнит 2'!AH8+'Юнит 3'!AH8+'Юнит 4'!AH8+'Юнит 5'!AH8 -> 0 | AI8: ='Юнит 1'!AI8+'Юнит 2'!AI8+'Юнит 3'!AI8+'Юнит 4'!AI8+'Юнит 5'!AI8 -> 370.90573 | AJ8: ='Юнит 1'!AJ8+'Юнит 2'!AJ8+'Юнит 3'!AJ8+'Юнит 4'!AJ8+'Юнит 5'!AJ8 -> 0 | AK8: =V8*1% -> 1030.6424 | AL8: =Y8-AB8-AC8-AE8-AF8-AG8-AH8-AI8-AK8-AJ8 -> 43089.892 | AN8: =IF(S8=0,0,Y8/S8) -> 1200.446 | AO8: =I8 -> 123.09 | AP8: =IF(S8=0,0,AC8/S8) -> 434.05234 | AQ8: =IF(Q8=0,AE8/1,AE8/Q8) -> 100.51449 | AR8: =IF(Q8=0,0,(AF8+AG8)/Q8) -> 126.98131 | AS8: {=_xlfn.IFS(S8=0,AL8,S8<0,AL8/-S8,S8>0,AL8/S8)} -> 402.70927 | AT8: =IF(AN8=0,0,AS8/AN8) -> 0.33546638 | AU8: =IF(AO8=0,0,AS8/AO8) -> 3.2716652 | AW8: =AS8*E8 -> 0
B9: 445341507 | C9: MR8854 C2 Сул | D9: Солнцезащитные очки | E9: ='Юнит 5'!E9 -> 0 | F9: ='Юнит 5'!F9 -> 14 | G9: ='Юнит 5'!G9 -> 4 | H9: ='Юнит 5'!H9 -> 229 | I9: 169.89 | J9: =E9*I9 -> 0 | K9: ='Юнит 5'!K9 -> 207 | L9: ='Юнит 1'!L9+'Юнит 2'!L9+'Юнит 3'!L9+'Юнит 4'!L9+'Юнит 5'!L9 -> 69 | M9: ='Юнит 1'!M9+'Юнит 2'!M9+'Юнит 3'!M9+'Юнит 4'!M9+'Юнит 5'!M9 -> 5945 | N9: ='Юнит 1'!N9+'Юнит 2'!N9+'Юнит 3'!N9+'Юнит 4'!N9+'Юнит 5'!N9 -> 287 | O9: =L9/7 -> 9.8571429 | P9: =S9/7 -> 3.7142857 | Q9: ='Юнит 1'!Q9+'Юнит 2'!Q9+'Юнит 3'!Q9+'Юнит 4'!Q9+'Юнит 5'!Q9 -> 28 | R9: ='Юнит 1'!R9+'Юнит 2'!R9+'Юнит 3'!R9+'Юнит 4'!R9+'Юнит 5'!R9 -> -2 | S9: =Q9+R9 -> 26 | T9: ='Юнит 1'!T9+'Юнит 2'!T9+'Юнит 3'!T9+'Юнит 4'!T9+'Юнит 5'!T9 -> 23712.96 | U9: ='Юнит 1'!U9+'Юнит 2'!U9+'Юнит 3'!U9+'Юнит 4'!U9+'Юнит 5'!U9 -> -1779 | V9: =T9+U9 -> 21933.96 | W9: ='Юнит 1'!W9+'Юнит 2'!W9+'Юнит 3'!W9+'Юнит 4'!W9+'Юнит 5'!W9 -> 32983.73 | X9: ='Юнит 1'!X9+'Юнит 2'!X9+'Юнит 3'!X9+'Юнит 4'!X9+'Юнит 5'!X9 -> -2348 | Y9: =W9+X9 -> 30635.73 | Z9: =L9*M9*N9/100 -> 1177288.4 | AA9: =Y9/$Y$74 -> 0.1028884 | AB9: =S9*I9 -> 4417.14 | AC9: ='Юнит 1'!AC9+'Юнит 2'!AC9+'Юнит 3'!AC9+'Юнит 4'!AC9+'Юнит 5'!AC9 -> 11062.14 | AD9: =IF(Y9=0,0,AC9/Y9) -> 0.36108622 | AE9: ='Юнит 1'!AE9+'Юнит 2'!AE9+'Юнит 3'!AE9+'Юнит 4'!AE9+'Юнит 5'!AE9 -> 4747.2 | AF9: ='Юнит 1'!AF9+'Юнит 2'!AF9+'Юнит 3'!AF9+'Юнит 4'!AF9+'Юнит 5'!AF9 -> 4000 | AG9: ='Юнит 1'!AG9+'Юнит 2'!AG9+'Юнит 3'!AG9+'Юнит 4'!AG9+'Юнит 5'!AG9 -> 5842 | AH9: ='Юнит 1'!AH9+'Юнит 2'!AH9+'Юнит 3'!AH9+'Юнит 4'!AH9+'Юнит 5'!AH9 -> 0 | AI9: ='Юнит 1'!AI9+'Юнит 2'!AI9+'Юнит 3'!AI9+'Юнит 4'!AI9+'Юнит 5'!AI9 -> 691.65984 | AJ9: ='Юнит 1'!AJ9+'Юнит 2'!AJ9+'Юнит 3'!AJ9+'Юнит 4'!AJ9+'Юнит 5'!AJ9 -> 0 | AK9: =V9*1% -> 219.3396 | AL9: =Y9-AB9-AC9-AE9-AF9-AG9-AH9-AI9-AK9-AJ9 -> -343.74944 | AN9: =IF(S9=0,0,Y9/S9) -> 1178.2973 | AO9: =I9 -> 169.89 | AP9: =IF(S9=0,0,AC9/S9) -> 425.46692 | AQ9: =IF(Q9=0,AE9/1,AE9/Q9) -> 169.54286 | AR9: =IF(Q9=0,0,(AF9+AG9)/Q9) -> 351.5 | AS9: {=_xlfn.IFS(S9=0,AL9,S9<0,AL9/-S9,S9>0,AL9/S9)} -> -13.221132 | AT9: =IF(AN9=0,0,AS9/AN9) -> -0.01122054 | AU9: =IF(AO9=0,0,AS9/AO9) -> -0.077821722 | AW9: =AS9*E9 -> 0
B10: 497825485 | C10: MR 1819 черн | D10: Солнцезащитные очки | E10: ='Юнит 5'!E10 -> 0 | F10: ='Юнит 5'!F10 | G10: ='Юнит 5'!G10 -> 1 | H10: ='Юнит 5'!H10 -> 39 | I10: 169.89 | J10: =E10*I10 -> 0 | K10: ='Юнит 5'!K10 -> 399 | L10: ='Юнит 1'!L10+'Юнит 2'!L10+'Юнит 3'!L10+'Юнит 4'!L10+'Юнит 5'!L10 -> 6 | M10: ='Юнит 1'!M10+'Юнит 2'!M10+'Юнит 3'!M10+'Юнит 4'!M10+'Юнит 5'!M10 -> 4715 | N10: ='Юнит 1'!N10+'Юнит 2'!N10+'Юнит 3'!N10+'Юнит 4'!N10+'Юнит 5'!N10 -> 100 | O10: =L10/7 -> 0.85714286 | P10: =S10/7 -> 0.28571429 | Q10: ='Юнит 1'!Q10+'Юнит 2'!Q10+'Юнит 3'!Q10+'Юнит 4'!Q10+'Юнит 5'!Q10 -> 3 | R10: ='Юнит 1'!R10+'Юнит 2'!R10+'Юнит 3'!R10+'Юнит 4'!R10+'Юнит 5'!R10 -> -1 | S10: =Q10+R10 -> 2 | T10: ='Юнит 1'!T10+'Юнит 2'!T10+'Юнит 3'!T10+'Юнит 4'!T10+'Юнит 5'!T10 -> 2726 | U10: ='Юнит 1'!U10+'Юнит 2'!U10+'Юнит 3'!U10+'Юнит 4'!U10+'Юнит 5'!U10 -> -931 | V10: =T10+U10 -> 1795 | W10: ='Юнит 1'!W10+'Юнит 2'!W10+'Юнит 3'!W10+'Юнит 4'!W10+'Юнит 5'!W10 -> 3543 | X10: ='Юнит 1'!X10+'Юнит 2'!X10+'Юнит 3'!X10+'Юнит 4'!X10+'Юнит 5'!X10 -> -1199 | Y10: =W10+X10 -> 2344 | Z10: =L10*M10*N10/100 -> 28290 | AA10: =Y10/$Y$74 -> 0.007872194 | AB10: =S10*I10 -> 339.78 | AC10: ='Юнит 1'!AC10+'Юнит 2'!AC10+'Юнит 3'!AC10+'Юнит 4'!AC10+'Юнит 5'!AC10 -> 852.14 | AD10: =IF(Y10=0,0,AC10/Y10) -> 0.36354096 | AE10: ='Юнит 1'!AE10+'Юнит 2'!AE10+'Юнит 3'!AE10+'Юнит 4'!AE10+'Юнит 5'!AE10 -> 508.85 | AF10: ='Юнит 1'!AF10+'Юнит 2'!AF10+'Юнит 3'!AF10+'Юнит 4'!AF10+'Юнит 5'!AF10 -> 0 | AG10: ='Юнит 1'!AG10+'Юнит 2'!AG10+'Юнит 3'!AG10+'Юнит 4'!AG10+'Юнит 5'!AG10 -> 0 | AH10: ='Юнит 1'!AH10+'Юнит 2'!AH10+'Юнит 3'!AH10+'Юнит 4'!AH10+'Юнит 5'!AH10 -> 0 | AI10: ='Юнит 1'!AI10+'Юнит 2'!AI10+'Юнит 3'!AI10+'Юнит 4'!AI10+'Юнит 5'!AI10 -> 108.00568 | AJ10: ='Юнит 1'!AJ10+'Юнит 2'!AJ10+'Юнит 3'!AJ10+'Юнит 4'!AJ10+'Юнит 5'!AJ10 -> 0 | AK10: =V10*1% -> 17.95 | AL10: =Y10-AB10-AC10-AE10-AF10-AG10-AH10-AI10-AK10-AJ10 -> 517.27432 | AN10: =IF(S10=0,0,Y10/S10) -> 1172 | AO10: =I10 -> 169.89 | AP10: =IF(S10=0,0,AC10/S10) -> 426.07 | AQ10: =IF(Q10=0,AE10/1,AE10/Q10) -> 169.61667 | AR10: =IF(Q10=0,0,(AF10+AG10)/Q10) -> 0 | AS10: {=_xlfn.IFS(S10=0,AL10,S10<0,AL10/-S10,S10>0,AL10/S10)} -> 258.63716 | AT10: =IF(AN10=0,0,AS10/AN10) -> 0.22068017 | AU10: =IF(AO10=0,0,AS10/AO10) -> 1.5223801 | AW10: =AS10*E10 -> 0
B11: 497825962 | C11: MR 1819 корич | D11: Солнцезащитные очки | E11: ='Юнит 5'!E11 -> 0 | F11: ='Юнит 5'!F11 | G11: ='Юнит 5'!G11 -> 1 | H11: ='Юнит 5'!H11 -> 38 | I11: 169.89 | J11: =E11*I11 -> 0 | K11: ='Юнит 5'!K11 -> 399 | L11: ='Юнит 1'!L11+'Юнит 2'!L11+'Юнит 3'!L11+'Юнит 4'!L11+'Юнит 5'!L11 -> 5 | M11: ='Юнит 1'!M11+'Юнит 2'!M11+'Юнит 3'!M11+'Юнит 4'!M11+'Юнит 5'!M11 -> 3380 | N11: ='Юнит 1'!N11+'Юнит 2'!N11+'Юнит 3'!N11+'Юнит 4'!N11+'Юнит 5'!N11 -> 50 | O11: =L11/7 -> 0.71428571 | P11: =S11/7 -> 0.42857143 | Q11: ='Юнит 1'!Q11+'Юнит 2'!Q11+'Юнит 3'!Q11+'Юнит 4'!Q11+'Юнит 5'!Q11 -> 3 | R11: ='Юнит 1'!R11+'Юнит 2'!R11+'Юнит 3'!R11+'Юнит 4'!R11+'Юнит 5'!R11 -> 0 | S11: =Q11+R11 -> 3 | T11: ='Юнит 1'!T11+'Юнит 2'!T11+'Юнит 3'!T11+'Юнит 4'!T11+'Юнит 5'!T11 -> 2507 | U11: ='Юнит 1'!U11+'Юнит 2'!U11+'Юнит 3'!U11+'Юнит 4'!U11+'Юнит 5'!U11 -> 0 | V11: =T11+U11 -> 2507 | W11: ='Юнит 1'!W11+'Юнит 2'!W11+'Юнит 3'!W11+'Юнит 4'!W11+'Юнит 5'!W11 -> 3435 | X11: ='Юнит 1'!X11+'Юнит 2'!X11+'Юнит 3'!X11+'Юнит 4'!X11+'Юнит 5'!X11 -> 0 | Y11: =W11+X11 -> 3435 | Z11: =L11*M11*N11/100 -> 8450 | AA11: =Y11/$Y$74 -> 0.011536257 | AB11: =S11*I11 -> 509.67 | AC11: ='Юнит 1'!AC11+'Юнит 2'!AC11+'Юнит 3'!AC11+'Юнит 4'!AC11+'Юнит 5'!AC11 -> 1230.83 | AD11: =IF(Y11=0,0,AC11/Y11) -> 0.35832023 | AE11: ='Юнит 1'!AE11+'Юнит 2'!AE11+'Юнит 3'!AE11+'Юнит 4'!AE11+'Юнит 5'!AE11 -> 496.55 | AF11: ='Юнит 1'!AF11+'Юнит 2'!AF11+'Юнит 3'!AF11+'Юнит 4'!AF11+'Юнит 5'!AF11 -> 0 | AG11: ='Юнит 1'!AG11+'Юнит 2'!AG11+'Юнит 3'!AG11+'Юнит 4'!AG11+'Юнит 5'!AG11 -> 0 | AH11: ='Юнит 1'!AH11+'Юнит 2'!AH11+'Юнит 3'!AH11+'Юнит 4'!AH11+'Юнит 5'!AH11 -> 0 | AI11: ='Юнит 1'!AI11+'Юнит 2'!AI11+'Юнит 3'!AI11+'Юнит 4'!AI11+'Юнит 5'!AI11 -> 108.28537 | AJ11: ='Юнит 1'!AJ11+'Юнит 2'!AJ11+'Юнит 3'!AJ11+'Юнит 4'!AJ11+'Юнит 5'!AJ11 -> 0 | AK11: =V11*1% -> 25.07 | AL11: =Y11-AB11-AC11-AE11-AF11-AG11-AH11-AI11-AK11-AJ11 -> 1064.5946 | AN11: =IF(S11=0,0,Y11/S11) -> 1145 | AO11: =I11 -> 169.89 | AP11: =IF(S11=0,0,AC11/S11) -> 410.27667 | AQ11: =IF(Q11=0,AE11/1,AE11/Q11) -> 165.51667 | AR11: =IF(Q11=0,0,(AF11+AG11)/Q11) -> 0 | AS11: {=_xlfn.IFS(S11=0,AL11,S11<0,AL11/-S11,S11>0,AL11/S11)} -> 354.86488 | AT11: =IF(AN11=0,0,AS11/AN11) -> 0.30992566 | AU11: =IF(AO11=0,0,AS11/AO11) -> 2.088792 | AW11: =AS11*E11 -> 0
B12: 497821775 | C12: MR Р1874 черн | D12: Солнцезащитные очки | E12: ='Юнит 5'!E12 -> 0 | F12: ='Юнит 5'!F12 | G12: ='Юнит 5'!G12 | H12: ='Юнит 5'!H12 -> 44 | I12: 169.89 | J12: =E12*I12 -> 0 | K12: ='Юнит 5'!K12 -> 264 | L12: ='Юнит 1'!L12+'Юнит 2'!L12+'Юнит 3'!L12+'Юнит 4'!L12+'Юнит 5'!L12 -> 9 | M12: ='Юнит 1'!M12+'Юнит 2'!M12+'Юнит 3'!M12+'Юнит 4'!M12+'Юнит 5'!M12 -> 3470 | N12: ='Юнит 1'!N12+'Юнит 2'!N12+'Юнит 3'!N12+'Юнит 4'!N12+'Юнит 5'!N12 -> 0 | O12: =L12/7 -> 1.2857143 | P12: =S12/7 -> 0.42857143 | Q12: ='Юнит 1'!Q12+'Юнит 2'!Q12+'Юнит 3'!Q12+'Юнит 4'!Q12+'Юнит 5'!Q12 -> 3 | R12: ='Юнит 1'!R12+'Юнит 2'!R12+'Юнит 3'!R12+'Юнит 4'!R12+'Юнит 5'!R12 -> 0 | S12: =Q12+R12 -> 3 | T12: ='Юнит 1'!T12+'Юнит 2'!T12+'Юнит 3'!T12+'Юнит 4'!T12+'Юнит 5'!T12 -> 2738 | U12: ='Юнит 1'!U12+'Юнит 2'!U12+'Юнит 3'!U12+'Юнит 4'!U12+'Юнит 5'!U12 -> 0 | V12: =T12+U12 -> 2738 | W12: ='Юнит 1'!W12+'Юнит 2'!W12+'Юнит 3'!W12+'Юнит 4'!W12+'Юнит 5'!W12 -> 3498 | X12: ='Юнит 1'!X12+'Юнит 2'!X12+'Юнит 3'!X12+'Юнит 4'!X12+'Юнит 5'!X12 -> 0 | Y12: =W12+X12 -> 3498 | Z12: =L12*M12*N12/100 -> 0 | AA12: =Y12/$Y$74 -> 0.011747839 | AB12: =S12*I12 -> 509.67 | AC12: ='Юнит 1'!AC12+'Юнит 2'!AC12+'Юнит 3'!AC12+'Юнит 4'!AC12+'Юнит 5'!AC12 -> 1259.45 | AD12: =IF(Y12=0,0,AC12/Y12) -> 0.3600486 | AE12: ='Юнит 1'!AE12+'Юнит 2'!AE12+'Юнит 3'!AE12+'Юнит 4'!AE12+'Юнит 5'!AE12 -> 807.5 | AF12: ='Юнит 1'!AF12+'Юнит 2'!AF12+'Юнит 3'!AF12+'Юнит 4'!AF12+'Юнит 5'!AF12 -> 0 | AG12: ='Юнит 1'!AG12+'Юнит 2'!AG12+'Юнит 3'!AG12+'Юнит 4'!AG12+'Юнит 5'!AG12 -> 0 | AH12: ='Юнит 1'!AH12+'Юнит 2'!AH12+'Юнит 3'!AH12+'Юнит 4'!AH12+'Юнит 5'!AH12 -> 0 | AI12: ='Юнит 1'!AI12+'Юнит 2'!AI12+'Юнит 3'!AI12+'Юнит 4'!AI12+'Юнит 5'!AI12 -> 119.54445 | AJ12: ='Юнит 1'!AJ12+'Юнит 2'!AJ12+'Юнит 3'!AJ12+'Юнит 4'!AJ12+'Юнит 5'!AJ12 -> 0 | AK12: =V12*1% -> 27.38 | AL12: =Y12-AB12-AC12-AE12-AF12-AG12-AH12-AI12-AK12-AJ12 -> 774.45555 | AN12: =IF(S12=0,0,Y12/S12) -> 1166 | AO12: =I12 -> 169.89 | AP12: =IF(S12=0,0,AC12/S12) -> 419.81667 | AQ12: =IF(Q12=0,AE12/1,AE12/Q12) -> 269.16667 | AR12: =IF(Q12=0,0,(AF12+AG12)/Q12) -> 0 | AS12: {=_xlfn.IFS(S12=0,AL12,S12<0,AL12/-S12,S12>0,AL12/S12)} -> 258.15185 | AT12: =IF(AN12=0,0,AS12/AN12) -> 0.22139953 | AU12: =IF(AO12=0,0,AS12/AO12) -> 1.5195235 | AW12: =AS12*E12 -> 0
B13: 497823770 | C13: MR Р1874 корич | D13: Солнцезащитные очки | E13: ='Юнит 5'!E13 -> 0 | F13: ='Юнит 5'!F13 | G13: ='Юнит 5'!G13 | H13: ='Юнит 5'!H13 -> 8 | I13: 169.89 | J13: =E13*I13 -> 0 | K13: ='Юнит 5'!K13 -> 92 | L13: ='Юнит 1'!L13+'Юнит 2'!L13+'Юнит 3'!L13+'Юнит 4'!L13+'Юнит 5'!L13 -> 5 | M13: ='Юнит 1'!M13+'Юнит 2'!M13+'Юнит 3'!M13+'Юнит 4'!M13+'Юнит 5'!M13 -> 3498 | N13: ='Юнит 1'!N13+'Юнит 2'!N13+'Юнит 3'!N13+'Юнит 4'!N13+'Юнит 5'!N13 -> 200 | O13: =L13/7 -> 0.71428571 | P13: =S13/7 -> 0.57142857 | Q13: ='Юнит 1'!Q13+'Юнит 2'!Q13+'Юнит 3'!Q13+'Юнит 4'!Q13+'Юнит 5'!Q13 -> 4 | R13: ='Юнит 1'!R13+'Юнит 2'!R13+'Юнит 3'!R13+'Юнит 4'!R13+'Юнит 5'!R13 -> 0 | S13: =Q13+R13 -> 4 | T13: ='Юнит 1'!T13+'Юнит 2'!T13+'Юнит 3'!T13+'Юнит 4'!T13+'Юнит 5'!T13 -> 3700 | U13: ='Юнит 1'!U13+'Юнит 2'!U13+'Юнит 3'!U13+'Юнит 4'!U13+'Юнит 5'!U13 -> 0 | V13: =T13+U13 -> 3700 | W13: ='Юнит 1'!W13+'Юнит 2'!W13+'Юнит 3'!W13+'Юнит 4'!W13+'Юнит 5'!W13 -> 4664 | X13: ='Юнит 1'!X13+'Юнит 2'!X13+'Юнит 3'!X13+'Юнит 4'!X13+'Юнит 5'!X13 -> 0 | Y13: =W13+X13 -> 4664 | Z13: =L13*M13*N13/100 -> 34980 | AA13: =Y13/$Y$74 -> 0.015663785 | AB13: =S13*I13 -> 679.56 | AC13: ='Юнит 1'!AC13+'Юнит 2'!AC13+'Юнит 3'!AC13+'Юнит 4'!AC13+'Юнит 5'!AC13 -> 1697.31 | AD13: =IF(Y13=0,0,AC13/Y13) -> 0.36391724 | AE13: ='Юнит 1'!AE13+'Юнит 2'!AE13+'Юнит 3'!AE13+'Юнит 4'!AE13+'Юнит 5'!AE13 -> 429.15 | AF13: ='Юнит 1'!AF13+'Юнит 2'!AF13+'Юнит 3'!AF13+'Юнит 4'!AF13+'Юнит 5'!AF13 -> 0 | AG13: ='Юнит 1'!AG13+'Юнит 2'!AG13+'Юнит 3'!AG13+'Юнит 4'!AG13+'Юнит 5'!AG13 -> 0 | AH13: ='Юнит 1'!AH13+'Юнит 2'!AH13+'Юнит 3'!AH13+'Юнит 4'!AH13+'Юнит 5'!AH13 -> 0 | AI13: ='Юнит 1'!AI13+'Юнит 2'!AI13+'Юнит 3'!AI13+'Юнит 4'!AI13+'Юнит 5'!AI13 -> 25.285933 | AJ13: ='Юнит 1'!AJ13+'Юнит 2'!AJ13+'Юнит 3'!AJ13+'Юнит 4'!AJ13+'Юнит 5'!AJ13 -> 0 | AK13: =V13*1% -> 37 | AL13: =Y13-AB13-AC13-AE13-AF13-AG13-AH13-AI13-AK13-AJ13 -> 1795.6941 | AN13: =IF(S13=0,0,Y13/S13) -> 1166 | AO13: =I13 -> 169.89 | AP13: =IF(S13=0,0,AC13/S13) -> 424.3275 | AQ13: =IF(Q13=0,AE13/1,AE13/Q13) -> 107.2875 | AR13: =IF(Q13=0,0,(AF13+AG13)/Q13) -> 0 | AS13: {=_xlfn.IFS(S13=0,AL13,S13<0,AL13/-S13,S13>0,AL13/S13)} -> 448.92352 | AT13: =IF(AN13=0,0,AS13/AN13) -> 0.38501159 | AU13: =IF(AO13=0,0,AS13/AO13) -> 2.6424364 | AW13: =AS13*E13 -> 0
B14: 497824253 | C14: MR Р1886 черн | D14: Солнцезащитные очки | E14: ='Юнит 5'!E14 -> 0 | F14: ='Юнит 5'!F14 | G14: ='Юнит 5'!G14 -> 1 | H14: ='Юнит 5'!H14 -> 58 | I14: 169.89 | J14: =E14*I14 -> 0 | K14: ='Юнит 5'!K14 -> 259 | L14: ='Юнит 1'!L14+'Юнит 2'!L14+'Юнит 3'!L14+'Юнит 4'!L14+'Юнит 5'!L14 -> 10 | M14: ='Юнит 1'!M14+'Юнит 2'!M14+'Юнит 3'!M14+'Юнит 4'!M14+'Юнит 5'!M14 -> 4844 | N14: ='Юнит 1'!N14+'Юнит 2'!N14+'Юнит 3'!N14+'Юнит 4'!N14+'Юнит 5'!N14 -> 250 | O14: =L14/7 -> 1.4285714 | P14: =S14/7 -> 0.85714286 | Q14: ='Юнит 1'!Q14+'Юнит 2'!Q14+'Юнит 3'!Q14+'Юнит 4'!Q14+'Юнит 5'!Q14 -> 6 | R14: ='Юнит 1'!R14+'Юнит 2'!R14+'Юнит 3'!R14+'Юнит 4'!R14+'Юнит 5'!R14 -> 0 | S14: =Q14+R14 -> 6 | T14: ='Юнит 1'!T14+'Юнит 2'!T14+'Юнит 3'!T14+'Юнит 4'!T14+'Юнит 5'!T14 -> 5086 | U14: ='Юнит 1'!U14+'Юнит 2'!U14+'Юнит 3'!U14+'Юнит 4'!U14+'Юнит 5'!U14 -> 0 | V14: =T14+U14 -> 5086 | W14: ='Юнит 1'!W14+'Юнит 2'!W14+'Юнит 3'!W14+'Юнит 4'!W14+'Юнит 5'!W14 -> 7168 | X14: ='Юнит 1'!X14+'Юнит 2'!X14+'Юнит 3'!X14+'Юнит 4'!X14+'Юнит 5'!X14 -> 0 | Y14: =W14+X14 -> 7168 | Z14: =L14*M14*N14/100 -> 121100 | AA14: =Y14/$Y$74 -> 0.02407333 | AB14: =S14*I14 -> 1019.34 | AC14: ='Юнит 1'!AC14+'Юнит 2'!AC14+'Юнит 3'!AC14+'Юнит 4'!AC14+'Юнит 5'!AC14 -> 2604.65 | AD14: =IF(Y14=0,0,AC14/Y14) -> 0.36337193 | AE14: ='Юнит 1'!AE14+'Юнит 2'!AE14+'Юнит 3'!AE14+'Юнит 4'!AE14+'Юнит 5'!AE14 -> 859.75 | AF14: ='Юнит 1'!AF14+'Юнит 2'!AF14+'Юнит 3'!AF14+'Юнит 4'!AF14+'Юнит 5'!AF14 -> 0 | AG14: ='Юнит 1'!AG14+'Юнит 2'!AG14+'Юнит 3'!AG14+'Юнит 4'!AG14+'Юнит 5'!AG14 -> 0 | AH14: ='Юнит 1'!AH14+'Юнит 2'!AH14+'Юнит 3'!AH14+'Юнит 4'!AH14+'Юнит 5'!AH14 -> 0 | AI14: ='Юнит 1'!AI14+'Юнит 2'!AI14+'Юнит 3'!AI14+'Юнит 4'!AI14+'Юнит 5'!AI14 -> 165.19446 | AJ14: ='Юнит 1'!AJ14+'Юнит 2'!AJ14+'Юнит 3'!AJ14+'Юнит 4'!AJ14+'Юнит 5'!AJ14 -> 0 | AK14: =V14*1% -> 50.86 | AL14: =Y14-AB14-AC14-AE14-AF14-AG14-AH14-AI14-AK14-AJ14 -> 2468.2055 | AN14: =IF(S14=0,0,Y14/S14) -> 1194.6667 | AO14: =I14 -> 169.89 | AP14: =IF(S14=0,0,AC14/S14) -> 434.10833 | AQ14: =IF(Q14=0,AE14/1,AE14/Q14) -> 143.29167 | AR14: =IF(Q14=0,0,(AF14+AG14)/Q14) -> 0 | AS14: {=_xlfn.IFS(S14=0,AL14,S14<0,AL14/-S14,S14>0,AL14/S14)} -> 411.36759 | AT14: =IF(AN14=0,0,AS14/AN14) -> 0.34433671 | AU14: =IF(AO14=0,0,AS14/AO14) -> 2.4213761 | AW14: =AS14*E14 -> 0
B15: 497824944 | C15: MR Р1886 корич | D15: Солнцезащитные очки | E15: ='Юнит 5'!E15 -> 0 | F15: ='Юнит 5'!F15 | G15: ='Юнит 5'!G15 | H15: ='Юнит 5'!H15 -> 34 | I15: 169.89 | J15: =E15*I15 -> 0 | K15: ='Юнит 5'!K15 -> 524 | L15: ='Юнит 1'!L15+'Юнит 2'!L15+'Юнит 3'!L15+'Юнит 4'!L15+'Юнит 5'!L15 -> 2 | M15: ='Юнит 1'!M15+'Юнит 2'!M15+'Юнит 3'!M15+'Юнит 4'!M15+'Юнит 5'!M15 -> 1204 | N15: ='Юнит 1'!N15+'Юнит 2'!N15+'Юнит 3'!N15+'Юнит 4'!N15+'Юнит 5'!N15 -> 100 | O15: =L15/7 -> 0.28571429 | P15: =S15/7 -> 0.42857143 | Q15: ='Юнит 1'!Q15+'Юнит 2'!Q15+'Юнит 3'!Q15+'Юнит 4'!Q15+'Юнит 5'!Q15 -> 3 | R15: ='Юнит 1'!R15+'Юнит 2'!R15+'Юнит 3'!R15+'Юнит 4'!R15+'Юнит 5'!R15 -> 0 | S15: =Q15+R15 -> 3 | T15: ='Юнит 1'!T15+'Юнит 2'!T15+'Юнит 3'!T15+'Юнит 4'!T15+'Юнит 5'!T15 -> 2934 | U15: ='Юнит 1'!U15+'Юнит 2'!U15+'Юнит 3'!U15+'Юнит 4'!U15+'Юнит 5'!U15 -> 0 | V15: =T15+U15 -> 2934 | W15: ='Юнит 1'!W15+'Юнит 2'!W15+'Юнит 3'!W15+'Юнит 4'!W15+'Юнит 5'!W15 -> 3640 | X15: ='Юнит 1'!X15+'Юнит 2'!X15+'Юнит 3'!X15+'Юнит 4'!X15+'Юнит 5'!X15 -> 0 | Y15: =W15+X15 -> 3640 | Z15: =L15*M15*N15/100 -> 2408 | AA15: =Y15/$Y$74 -> 0.012224738 | AB15: =S15*I15 -> 509.67 | AC15: ='Юнит 1'!AC15+'Юнит 2'!AC15+'Юнит 3'!AC15+'Юнит 4'!AC15+'Юнит 5'!AC15 -> 1318.88 | AD15: =IF(Y15=0,0,AC15/Y15) -> 0.36232967 | AE15: ='Юнит 1'!AE15+'Юнит 2'!AE15+'Юнит 3'!AE15+'Юнит 4'!AE15+'Юнит 5'!AE15 -> 156.6 | AF15: ='Юнит 1'!AF15+'Юнит 2'!AF15+'Юнит 3'!AF15+'Юнит 4'!AF15+'Юнит 5'!AF15 -> 0 | AG15: ='Юнит 1'!AG15+'Юнит 2'!AG15+'Юнит 3'!AG15+'Юнит 4'!AG15+'Юнит 5'!AG15 -> 0 | AH15: ='Юнит 1'!AH15+'Юнит 2'!AH15+'Юнит 3'!AH15+'Юнит 4'!AH15+'Юнит 5'!AH15 -> 0 | AI15: ='Юнит 1'!AI15+'Юнит 2'!AI15+'Юнит 3'!AI15+'Юнит 4'!AI15+'Юнит 5'!AI15 -> 95.521873 | AJ15: ='Юнит 1'!AJ15+'Юнит 2'!AJ15+'Юнит 3'!AJ15+'Юнит 4'!AJ15+'Юнит 5'!AJ15 -> 0 | AK15: =V15*1% -> 29.34 | AL15: =Y15-AB15-AC15-AE15-AF15-AG15-AH15-AI15-AK15-AJ15 -> 1529.9881 | AN15: =IF(S15=0,0,Y15/S15) -> 1213.3333 | AO15: =I15 -> 169.89 | AP15: =IF(S15=0,0,AC15/S15) -> 439.62667 | AQ15: =IF(Q15=0,AE15/1,AE15/Q15) -> 52.2 | AR15: =IF(Q15=0,0,(AF15+AG15)/Q15) -> 0 | AS15: {=_xlfn.IFS(S15=0,AL15,S15<0,AL15/-S15,S15>0,AL15/S15)} -> 509.99604 | AT15: =IF(AN15=0,0,AS15/AN15) -> 0.42032641 | AU15: =IF(AO15=0,0,AS15/AO15) -> 3.0019191 | AW15: =AS15*E15 -> 0
AN16: =AVERAGE(AN3:AN6) -> 1030.3347 | AO16: =AVERAGE(AO3:AO6) -> 128.0625 | AP16: =AVERAGE(AP3:AP6) -> 323.22765 | AQ16: =AVERAGE(AQ3:AQ6) -> 102.08059 | AR16: =AVERAGE(AR3:AR6) -> 311.00313 | AS16: =AVERAGE(AS3:AS6) -> 55.498179 | AT16: =AVERAGE(AT3:AT6) -> 0.011951086 | AU16: =AVERAGE(AU3:AU6) -> 0.38694062
A17: Итого очки | E17: =SUM(E3:E15) -> 0 | F17: =SUM(F3:F15) -> 99 | G17: =SUM(G3:G15) -> 19 | H17: =SUM(H3:H15) -> 2126 | J17: =SUM(J3:J15) -> 0 | L17: =SUM(L3:L15) -> 457 | Q17: =SUM(Q3:Q15) -> 256 | R17: =SUM(R3:R15) -> -5 | S17: =SUM(S3:S15) -> 251 | T17: =SUM(T3:T15) -> 233222.72 | U17: =SUM(U3:U15) -> -4580 | V17: =SUM(V3:V15) -> 228642.72 | W17: =SUM(W3:W15) -> 303779.89 | X17: =SUM(X3:X15) -> -6023 | ... AC17: =SUM(AC3:AC15) -> 106888.7 | AD17: =AC17/Y17 -> 0.35897977 | AE17: =SUM(AE3:AE15) -> 30976.05 | AF17: =SUM(AF3:AF15) -> 22451 | AG17: =SUM(AG3:AG15) -> 26323 | AH17: =SUM(AH3:AH15) -> 0 | AI17: =SUM(AI3:AI15) -> 6310.98 | AJ17: =SUM(AJ3:AJ15) -> 0 | AK17: =SUM(AK3:AK15) -> 2286.4272 | AL17: =SUM(AL3:AL15) -> 68192.363 | AR17: =(AF17+AG17)/Q17 -> 190.52344 | AW17: =SUM(AW3:AW6) -> 0
E19: =SUM(F19:H19) -> 0 | J19: =E19*I19 -> 0 | O19: =L19/7 -> 0 | P19: =S19/7 -> 0 | S19: =Q19+R19 -> 0 | V19: =T19+U19 -> 0 | Y19: =W19+X19 -> 0 | Z19: =L19*M19*N19/100 -> 0 | AA19: =Y19/$Y$74 -> 0 | AB19: =S19*I19 -> 0 | AD19: =IF(Y19=0,0,AC19/Y19) -> 0 | AK19: =V19*1% -> 0 | AL19: =Y19-AB19-AC19-AE19-AF19-AG19-AH19-AI19-AK19-AJ19 -> 0 | AN19: =IF(S19=0,0,Y19/S19) -> 0 | AO19: =I19 -> 0 | AP19: =IF(S19=0,0,AC19/S19) -> 0 | AQ19: =IF(Q19=0,AE19/1,AE19/Q19) -> 0 | AR19: =IF(Q19=0,0,(AF19+AG19)/Q19) -> 0 | AS19: {=_xlfn.IFS(S19=0,AL19,S19<0,AL19/-S19,S19>0,AL19/S19)} -> 0 | AT19: =IF(AN19=0,0,AS19/AN19) -> 0 | AU19: =IF(AO19=0,0,AS19/AO19) -> 0 | AW19: =AS19*E19 -> 0
E20: =SUM(F20:H20) -> 0 | J20: =E20*I20 -> 0 | O20: =L20/7 -> 0 | P20: =S20/7 -> 0 | S20: =Q20+R20 -> 0 | V20: =T20+U20 -> 0 | Y20: =W20+X20 -> 0 | Z20: =L20*M20*N20/100 -> 0 | AA20: =Y20/$Y$74 -> 0 | AB20: =S20*I20 -> 0 | AD20: =IF(Y20=0,0,AC20/Y20) -> 0 | AK20: =V20*1% -> 0 | AL20: =Y20-AB20-AC20-AE20-AF20-AG20-AH20-AI20-AK20-AJ20 -> 0 | AN20: =IF(S20=0,0,Y20/S20) -> 0 | AO20: =I20 -> 0 | AP20: =IF(S20=0,0,AC20/S20) -> 0 | AQ20: =IF(Q20=0,AE20/1,AE20/Q20) -> 0 | AR20: =IF(Q20=0,0,(AF20+AG20)/Q20) -> 0 | AS20: {=_xlfn.IFS(S20=0,AL20,S20<0,AL20/-S20,S20>0,AL20/S20)} -> 0 | AT20: =IF(AN20=0,0,AS20/AN20) -> 0 | AU20: =IF(AO20=0,0,AS20/AO20) -> 0 | AW20: =AS20*E20 -> 0
E21: =SUM(F21:H21) -> 0 | J21: =E21*I21 -> 0 | O21: =L21/7 -> 0 | P21: =S21/7 -> 0 | S21: =Q21+R21 -> 0 | V21: =T21+U21 -> 0 | Y21: =W21+X21 -> 0 | Z21: =L21*M21*N21/100 -> 0 | AA21: =Y21/$Y$74 -> 0 | AB21: =S21*I21 -> 0 | AD21: =IF(Y21=0,0,AC21/Y21) -> 0 | AK21: =V21*1% -> 0 | AL21: =Y21-AB21-AC21-AE21-AF21-AG21-AH21-AI21-AK21-AJ21 -> 0 | AN21: =IF(S21=0,0,Y21/S21) -> 0 | AO21: =I21 -> 0 | AP21: =IF(S21=0,0,AC21/S21) -> 0 | AQ21: =IF(Q21=0,AE21/1,AE21/Q21) -> 0 | AR21: =IF(Q21=0,0,(AF21+AG21)/Q21) -> 0 | AS21: {=_xlfn.IFS(S21=0,AL21,S21<0,AL21/-S21,S21>0,AL21/S21)} -> 0 | AT21: =IF(AN21=0,0,AS21/AN21) -> 0 | AU21: =IF(AO21=0,0,AS21/AO21) -> 0 | AW21: =AS21*E21 -> 0
E22: =SUM(F22:H22) -> 0 | J22: =E22*I22 -> 0 | O22: =L22/7 -> 0 | P22: =S22/7 -> 0 | S22: =Q22+R22 -> 0 | V22: =T22+U22 -> 0 | Y22: =W22+X22 -> 0 | Z22: =L22*M22*N22/100 -> 0 | AA22: =Y22/$Y$74 -> 0 | AB22: =S22*I22 -> 0 | AD22: =IF(Y22=0,0,AC22/Y22) -> 0 | AK22: =V22*1% -> 0 | AL22: =Y22-AB22-AC22-AE22-AF22-AG22-AH22-AI22-AK22-AJ22 -> 0 | AN22: =IF(S22=0,0,Y22/S22) -> 0 | AO22: =I22 -> 0 | AP22: =IF(S22=0,0,AC22/S22) -> 0 | AQ22: =IF(Q22=0,AE22/1,AE22/Q22) -> 0 | AR22: =IF(Q22=0,0,(AF22+AG22)/Q22) -> 0 | AS22: {=_xlfn.IFS(S22=0,AL22,S22<0,AL22/-S22,S22>0,AL22/S22)} -> 0 | AT22: =IF(AN22=0,0,AS22/AN22) -> 0 | AU22: =IF(AO22=0,0,AS22/AO22) -> 0 | AW22: =AS22*E22 -> 0
E23: =SUM(F23:H23) -> 0 | J23: =E23*I23 -> 0 | O23: =L23/7 -> 0 | P23: =S23/7 -> 0 | S23: =Q23+R23 -> 0 | V23: =T23+U23 -> 0 | Y23: =W23+X23 -> 0 | Z23: =L23*M23*N23/100 -> 0 | AA23: =Y23/$Y$74 -> 0 | AB23: =S23*I23 -> 0 | AD23: =IF(Y23=0,0,AC23/Y23) -> 0 | AK23: =V23*1% -> 0 | AL23: =Y23-AB23-AC23-AE23-AF23-AG23-AH23-AI23-AK23-AJ23 -> 0 | AN23: =IF(S23=0,0,Y23/S23) -> 0 | AO23: =I23 -> 0 | AP23: =IF(S23=0,0,AC23/S23) -> 0 | AQ23: =IF(Q23=0,AE23/1,AE23/Q23) -> 0 | AR23: =IF(Q23=0,0,(AF23+AG23)/Q23) -> 0 | AS23: {=_xlfn.IFS(S23=0,AL23,S23<0,AL23/-S23,S23>0,AL23/S23)} -> 0 | AT23: =IF(AN23=0,0,AS23/AN23) -> 0 | AU23: =IF(AO23=0,0,AS23/AO23) -> 0 | AW23: =AS23*E23 -> 0
E24: =SUM(F24:H24) -> 0 | J24: =E24*I24 -> 0 | O24: =L24/7 -> 0 | P24: =S24/7 -> 0 | S24: =Q24+R24 -> 0 | V24: =T24+U24 -> 0 | Y24: =W24+X24 -> 0 | Z24: =L24*M24*N24/100 -> 0 | AA24: =Y24/$Y$74 -> 0 | AB24: =S24*I24 -> 0 | AD24: =IF(Y24=0,0,AC24/Y24) -> 0 | AK24: =V24*1% -> 0 | AL24: =Y24-AB24-AC24-AE24-AF24-AG24-AH24-AI24-AK24-AJ24 -> 0 | AN24: =IF(S24=0,0,Y24/S24) -> 0 | AO24: =I24 -> 0 | AP24: =IF(S24=0,0,AC24/S24) -> 0 | AQ24: =IF(Q24=0,AE24/1,AE24/Q24) -> 0 | AR24: =IF(Q24=0,0,(AF24+AG24)/Q24) -> 0 | AS24: {=_xlfn.IFS(S24=0,AL24,S24<0,AL24/-S24,S24>0,AL24/S24)} -> 0 | AT24: =IF(AN24=0,0,AS24/AN24) -> 0 | AU24: =IF(AO24=0,0,AS24/AO24) -> 0 | AW24: =AS24*E24 -> 0
E25: =SUM(F25:H25) -> 0 | J25: =E25*I25 -> 0 | O25: =L25/7 -> 0 | P25: =S25/7 -> 0 | S25: =Q25+R25 -> 0 | V25: =T25+U25 -> 0 | Y25: =W25+X25 -> 0 | Z25: =L25*M25*N25/100 -> 0 | AA25: =Y25/$Y$74 -> 0 | AB25: =S25*I25 -> 0 | AD25: =IF(Y25=0,0,AC25/Y25) -> 0 | AK25: =V25*1% -> 0 | AL25: =Y25-AB25-AC25-AE25-AF25-AG25-AH25-AI25-AK25-AJ25 -> 0 | AN25: =IF(S25=0,0,Y25/S25) -> 0 | AO25: =I25 -> 0 | AP25: =IF(S25=0,0,AC25/S25) -> 0 | AQ25: =IF(Q25=0,AE25/1,AE25/Q25) -> 0 | AR25: =IF(Q25=0,0,(AF25+AG25)/Q25) -> 0 | AS25: {=_xlfn.IFS(S25=0,AL25,S25<0,AL25/-S25,S25>0,AL25/S25)} -> 0 | AT25: =IF(AN25=0,0,AS25/AN25) -> 0 | AU25: =IF(AO25=0,0,AS25/AO25) -> 0 | AW25: =AS25*E25 -> 0
E26: =SUM(F26:H26) -> 0 | J26: =E26*I26 -> 0 | O26: =L26/7 -> 0 | P26: =S26/7 -> 0 | S26: =Q26+R26 -> 0 | V26: =T26+U26 -> 0 | Y26: =W26+X26 -> 0 | Z26: =L26*M26*N26/100 -> 0 | AA26: =Y26/$Y$74 -> 0 | AB26: =S26*I26 -> 0 | AD26: =IF(Y26=0,0,AC26/Y26) -> 0 | AK26: =V26*1% -> 0 | AL26: =Y26-AB26-AC26-AE26-AF26-AG26-AH26-AI26-AK26-AJ26 -> 0 | AN26: =IF(S26=0,0,Y26/S26) -> 0 | AO26: =I26 -> 0 | AP26: =IF(S26=0,0,AC26/S26) -> 0 | AQ26: =IF(Q26=0,AE26/1,AE26/Q26) -> 0 | AR26: =IF(Q26=0,0,(AF26+AG26)/Q26) -> 0 | AS26: {=_xlfn.IFS(S26=0,AL26,S26<0,AL26/-S26,S26>0,AL26/S26)} -> 0 | AT26: =IF(AN26=0,0,AS26/AN26) -> 0 | AU26: =IF(AO26=0,0,AS26/AO26) -> 0 | AW26: =AS26*E26 -> 0
E27: =SUM(F27:H27) -> 0 | J27: =E27*I27 -> 0 | O27: =L27/7 -> 0 | P27: =S27/7 -> 0 | S27: =Q27+R27 -> 0 | V27: =T27+U27 -> 0 | Y27: =W27+X27 -> 0 | Z27: =L27*M27*N27/100 -> 0 | AA27: =Y27/$Y$74 -> 0 | AB27: =S27*I27 -> 0 | AD27: =IF(Y27=0,0,AC27/Y27) -> 0 | AK27: =V27*1% -> 0 | AL27: =Y27-AB27-AC27-AE27-AF27-AG27-AH27-AI27-AK27-AJ27 -> 0 | AN27: =IF(S27=0,0,Y27/S27) -> 0 | AO27: =I27 -> 0 | AP27: =IF(S27=0,0,AC27/S27) -> 0 | AQ27: =IF(Q27=0,AE27/1,AE27/Q27) -> 0 | AR27: =IF(Q27=0,0,(AF27+AG27)/Q27) -> 0 | AS27: {=_xlfn.IFS(S27=0,AL27,S27<0,AL27/-S27,S27>0,AL27/S27)} -> 0 | AT27: =IF(AN27=0,0,AS27/AN27) -> 0 | AU27: =IF(AO27=0,0,AS27/AO27) -> 0 | AW27: =AS27*E27 -> 0
E28: =SUM(F28:H28) -> 0 | J28: =E28*I28 -> 0 | O28: =L28/7 -> 0 | P28: =S28/7 -> 0 | S28: =Q28+R28 -> 0 | V28: =T28+U28 -> 0 | Y28: =W28+X28 -> 0 | Z28: =L28*M28*N28/100 -> 0 | AA28: =Y28/$Y$74 -> 0 | AB28: =S28*I28 -> 0 | AD28: =IF(Y28=0,0,AC28/Y28) -> 0 | AK28: =V28*1% -> 0 | AL28: =Y28-AB28-AC28-AE28-AF28-AG28-AH28-AI28-AK28-AJ28 -> 0 | AN28: =IF(S28=0,0,Y28/S28) -> 0 | AO28: =I28 -> 0 | AP28: =IF(S28=0,0,AC28/S28) -> 0 | AQ28: =IF(Q28=0,AE28/1,AE28/Q28) -> 0 | AR28: =IF(Q28=0,0,(AF28+AG28)/Q28) -> 0 | AS28: {=_xlfn.IFS(S28=0,AL28,S28<0,AL28/-S28,S28>0,AL28/S28)} -> 0 | AT28: =IF(AN28=0,0,AS28/AN28) -> 0 | AU28: =IF(AO28=0,0,AS28/AO28) -> 0 | AW28: =AS28*E28 -> 0
E29: =SUM(F29:H29) -> 0 | J29: =E29*I29 -> 0 | O29: =L29/7 -> 0 | P29: =S29/7 -> 0 | S29: =Q29+R29 -> 0 | V29: =T29+U29 -> 0 | Y29: =W29+X29 -> 0 | Z29: =L29*M29*N29/100 -> 0 | AA29: =Y29/$Y$74 -> 0 | AB29: =S29*I29 -> 0 | AD29: =IF(Y29=0,0,AC29/Y29) -> 0 | AK29: =V29*1% -> 0 | AL29: =Y29-AB29-AC29-AE29-AF29-AG29-AH29-AI29-AK29-AJ29 -> 0 | AN29: =IF(S29=0,0,Y29/S29) -> 0 | AO29: =I29 -> 0 | AP29: =IF(S29=0,0,AC29/S29) -> 0 | AQ29: =IF(Q29=0,AE29/1,AE29/Q29) -> 0 | AR29: =IF(Q29=0,0,(AF29+AG29)/Q29) -> 0 | AS29: {=_xlfn.IFS(S29=0,AL29,S29<0,AL29/-S29,S29>0,AL29/S29)} -> 0 | AT29: =IF(AN29=0,0,AS29/AN29) -> 0 | AU29: =IF(AO29=0,0,AS29/AO29) -> 0 | AW29: =AS29*E29 -> 0
E30: =SUM(F30:H30) -> 0 | J30: =E30*I30 -> 0 | O30: =L30/7 -> 0 | P30: =S30/7 -> 0 | S30: =Q30+R30 -> 0 | V30: =T30+U30 -> 0 | Y30: =W30+X30 -> 0 | Z30: =L30*M30*N30/100 -> 0 | AA30: =Y30/$Y$74 -> 0 | AB30: =S30*I30 -> 0 | AD30: =IF(Y30=0,0,AC30/Y30) -> 0 | AK30: =V30*1% -> 0 | AL30: =Y30-AB30-AC30-AE30-AF30-AG30-AH30-AI30-AK30-AJ30 -> 0 | AN30: =IF(S30=0,0,Y30/S30) -> 0 | AO30: =I30 -> 0 | AP30: =IF(S30=0,0,AC30/S30) -> 0 | AQ30: =IF(Q30=0,AE30/1,AE30/Q30) -> 0 | AR30: =IF(Q30=0,0,(AF30+AG30)/Q30) -> 0 | AS30: {=_xlfn.IFS(S30=0,AL30,S30<0,AL30/-S30,S30>0,AL30/S30)} -> 0 | AT30: =IF(AN30=0,0,AS30/AN30) -> 0 | AU30: =IF(AO30=0,0,AS30/AO30) -> 0 | AW30: =AS30*E30 -> 0
... E70: =SUM(F70:H70) -> 0 | J70: =E70*I70 -> 0 | O70: =L70/7 -> 0 | P70: =S70/7 -> 0 | S70: =Q70+R70 -> 0 | V70: =T70+U70 -> 0 | Y70: =W70+X70 -> 0 | Z70: =L70*M70*N70/100 -> 0 | AA70: =Y70/$Y$74 -> 0 | AB70: =S70*I70 -> 0 | AD70: =IF(Y70=0,0,AC70/Y70) -> 0 | AK70: =V70*1% -> 0 | AL70: =Y70-AB70-AC70-AE70-AF70-AG70-AH70-AI70-AK70-AJ70 -> 0 | AN70: =IF(S70=0,0,Y70/S70) -> 0 | AO70: =I70 -> 0 | AP70: =IF(S70=0,0,AC70/S70) -> 0 | AQ70: =IF(Q70=0,AE70/1,AE70/Q70) -> 0 | AR70: =IF(Q70=0,0,(AF70+AG70)/Q70) -> 0 | AS70: {=_xlfn.IFS(S70=0,AL70,S70<0,AL70/-S70,S70>0,AL70/S70)} -> 0 | AT70: =IF(AN70=0,0,AS70/AN70) -> 0 | AU70: =IF(AO70=0,0,AS70/AO70) -> 0 | AW70: =AS70*E70 -> 0
AN71: =AVERAGE(AN19:AN70) -> 0 | AO71: =AVERAGE(AO19:AO70) -> 0 | AP71: =AVERAGE(AP19:AP70) -> 0 | AQ71: =AVERAGE(AQ19:AQ70) -> 0 | AR71: =AVERAGE(AR19:AR70) -> 0 | AS71: =AVERAGE(AS19:AS70) -> 0 | AT71: =AVERAGE(AT19:AT70) -> 0 | AU71: =AVERAGE(AU19:AU70) -> 0
A72: Итого ___ | E72: =SUM(E19:E70) -> 0 | F72: =SUM(F19:F70) -> 0 | G72: =SUM(G19:G70) -> 0 | H72: =SUM(H19:H70) -> 0 | J72: =SUM(J19:J70) -> 0 | L72: =SUM(L19:L70) -> 0 | Q72: =SUM(Q19:Q70) -> 0 | R72: =SUM(R19:R70) -> 0 | S72: =SUM(S19:S70) -> 0 | T72: =SUM(T19:T70) -> 0 | U72: =SUM(U19:U70) -> 0 | V72: =SUM(V19:V70) -> 0 | W72: =SUM(W19:W70) -> 0 | X72: =SUM(X19:X70) -> 0 | ... AC72: =SUM(AC19:AC70) -> 0 | AD72: =AC72/Y72 -> #DIV/0! | AE72: =SUM(AE19:AE70) -> 0 | AF72: =SUM(AF19:AF70) -> 0 | AG72: =SUM(AG19:AG70) -> 0 | AH72: =SUM(AH19:AH70) -> 0 | AI72: =SUM(AI19:AI70) -> 0 | AJ72: =SUM(AJ19:AJ70) -> 0 | AK72: =SUM(AK19:AK70) -> 0 | AL72: =SUM(AL19:AL70) -> 0 | AR72: =(AF72+AG72)/Q72 -> #DIV/0! | AW72: =SUM(AW19:AW70) -> 0
A74: ИТОГО | E74: =E17+E72 -> 0 | F74: =F17+F72 -> 99 | G74: =G17+G72 -> 19 | H74: =H17+H72 -> 2126 | I74: =I17+I72 -> 0 | J74: =J17+J72 -> 0 | K74: =K17+K72 -> 0 | L74: =L17+L72 -> 457 | ... AC74: =AC17+AC72 -> 106888.7 | AD74: =AC74/Y74 -> 0.35897977 | AE74: =AE17+AE72 -> 30976.05 | AF74: =AF17+AF72 -> 22451 | AG74: =AG17+AG72 -> 26323 | AH74: =AH17+AH72 -> 0 | AI74: =AI17+AI72 -> 6310.98 | AJ74: =AJ17+AJ72 -> 0 | AK74: =AK17+AK72 -> 2286.4272 | AL74: =AL17+AL72 -> 68192.363 | AR74: =(AF74+AG74)/Q74 -> 190.52344 | AW74: =AW17+AW72 -> 0
AL75: =Сводная!AC9+Сводная!V9 -> 68192.363

Sheet Юнит 5
A1: 26.01-01.02_5 нед | F1: Отчет по остаткам 3,4,5 | K1: Цены и скидки 6 | L1: Воронка продаж 16,50,32 | AI1: Вставить в Итого | AN1: на 1 единицу проданного товара
A2: Бренд | B2: SKU | C2: Артикул поставщика | D2: Предмет | E2: Остаток на 02.02 | F2: В пути до клиента | G2: В пути от клиента | H2: Итого по складам ВБ | I2: Себетоимость на 1 ед на 29.09.25 | J2: Себестоимость остатков | K2: Оборачива-емость, дн | L2: Заказы, шт 7 дней | M2: Средняя цена, руб | N2: % выкупа за 7 дней | O2: Скорость заказов | P2: Скорость продаж | Q2: Кол-во ПРОДАЖИ | R2: Кол-во ВОЗВРАТЫ | S2: Кол-во ПРОДАЖИ-ВОЗВРАТЫ | T2: Выручка ВБ ПРОДАЖИ | U2: Выручка ВБ ВОЗВРАТЫ | V2: Выручка с учетом СПП ПРОДАЖИ - ВОЗВРАТЫ | W2: Выручка ПРОДАЖИ | X2: Выручка ВОЗВРАТЫ | Y2: Выручка с учетом согласованной скидки ПРОДАЖИ - ВОЗВРАТЫ | Z2: Выручка потенциальная | AA2: Доля выручки, % от общего объема | AB2: Себестоимость продаж | AC2: Комиссия, руб | AD2: Комиссия, % | AE2: Логистика | AF2: Реклама БАЛАНС | AG2: Реклама СЧЕТ | AH2: Блогеры | AI2: Хранение | AJ2: Штрафы | AK2: Налог 1% | AL2: Прибыль | AN2: Выручка на 1 ед (средняя цена продажи со скидкой) | AO2: Себестоимость на 1 ед | AP2: Комиссия на 1 ед | AQ2: Логистика на 1 ед | AR2: Реклама на 1 ед | AS2: Прибыль на 1 ед | AT2: Маржиналь-ность, % | AU2: Рентабель-ность, % | AW2: Прибыль с остатков
B3: 341479791 | C3: Черные с железкой Сул | D3: Солнцезащитные очки | F3: 36 | G3: 5 | H3: 349 | I3: 142.98 | J3: =E3*I3 -> 0 | K3: 133 | L3: 51 | M3: 1238 | N3: 59 | O3: =L3/7 -> 7.2857143 | P3: =S3/7 -> 2.7142857 | Q3: 20 | R3: -1 | S3: =Q3+R3 -> 19 | T3: 16491.9 | U3: -813 | V3: =T3+U3 -> 15678.9 | W3: 24760.02 | X3: -1238 | Y3: =W3+X3 -> 23522.02 | Z3: =L3*M3*N3/100 -> 37251.42 | AA3: =Y3/$Y$74 -> 0.29731805 | AB3: =S3*I3 -> 2716.62 | AC3: 8499.44 | AD3: =IF(Y3=0,0,AC3/Y3) -> 0.36133971 | AE3: 2693.7 | AF3: =3000+1000 -> 4000 | AG3: 3416 | AI3: =IFERROR($AI$74*H3/$H$74,0) -> 226.1392 | AJ3: 0 | AK3: =V3*1% -> 156.789 | AL3: =Y3-AB3-AC3-AE3-AF3-AG3-AH3-AI3-AK3-AJ3 -> 1813.3318 | AN3: =IF(S3=0,0,Y3/S3) -> 1238.0011 | AO3: =I3 -> 142.98 | AP3: =IF(S3=0,0,AC3/S3) -> 447.33895 | AQ3: =IF(Q3=0,AE3/1,AE3/Q3) -> 134.685 | AR3: =IF(Q3=0,0,(AF3+AG3)/Q3) -> 370.8 | AS3: =_xlfn.IFS(S3=0,AL3,S3<0,AL3/-S3,S3>0,AL3/S3) -> 95.438516 | AT3: =IF(AN3=0,0,AS3/AN3) -> 0.07709082 | AU3: =IF(AO3=0,0,AS3/AO3) -> 0.66749557 | AW3: =AS3*E3 -> 0
B4: 340343575 | C4: Qs черн Сул | D4: Солнцезащитные очки | F4: 15 | G4: 4 | H4: 260 | I4: 123.09 | J4: =E4*I4 -> 0 | K4: 314 | L4: 29 | M4: 929 | N4: 60 | O4: =L4/7 -> 4.1428571 | P4: =S4/7 -> 1.4285714 | Q4: 10 | R4: 0 | S4: =Q4+R4 -> 10 | T4: 6321.49 | U4: 0 | V4: =T4+U4 -> 6321.49 | W4: 9289.38 | X4: 0 | Y4: =W4+X4 -> 9289.38 | Z4: =L4*M4*N4/100 -> 16164.6 | AA4: =Y4/$Y$74 -> 0.11741765 | AB4: =S4*I4 -> 1230.9 | AC4: 3407.19 | AD4: =IF(Y4=0,0,AC4/Y4) -> 0.36678336 | AE4: 1035.9 | AF4: 892 | AG4: 2314 | AI4: =IFERROR($AI$74*H4/$H$74,0) -> 168.47046 | AJ4: 0 | AK4: =V4*1% -> 63.2149 | AL4: =Y4-AB4-AC4-AE4-AF4-AG4-AH4-AI4-AK4-AJ4 -> 177.70464 | AN4: =IF(S4=0,0,Y4/S4) -> 928.938 | AO4: =I4 -> 123.09 | AP4: =IF(S4=0,0,AC4/S4) -> 340.719 | AQ4: =IF(Q4=0,AE4/1,AE4/Q4) -> 103.59 | AR4: =IF(Q4=0,0,(AF4+AG4)/Q4) -> 320.6 | AS4: {=_xlfn.IFS(S4=0,AL4,S4<0,AL4/-S4,S4>0,AL4/S4)} -> 17.770464 | AT4: =IF(AN4=0,0,AS4/AN4) -> 0.019129871 | AU4: =IF(AO4=0,0,AS4/AO4) -> 0.14436968 | AW4: =AS4*E4 -> 0
B5: 340332621 | C5: Qs син Сул | D5: Солнцезащитные очки | F5: 3 | H5: 372 | I5: 123.09 | J5: =E5*I5 -> 0 | K5: 999 | L5: 5 | M5: 1052 | N5: 100 | O5: =L5/7 -> 0.71428571 | P5: =S5/7 -> 0.42857143 | Q5: 3 | R5: 0 | S5: =Q5+R5 -> 3 | T5: 2054 | U5: 0 | V5: =T5+U5 -> 2054 | W5: 3156 | X5: 0 | Y5: =W5+X5 -> 3156 | Z5: =L5*M5*N5/100 -> 5260 | AA5: =Y5/$Y$74 -> 0.039891802 | AB5: =S5*I5 -> 369.27 | AC5: 1149.91 | AD5: =IF(Y5=0,0,AC5/Y5) -> 0.36435678 | AE5: 187.05 | AF5: 1691 | AG5: =309+106 -> 415 | AI5: =IFERROR($AI$74*H5/$H$74,0) -> 241.04235 | AJ5: 0 | AK5: =V5*1% -> 20.54 | AL5: =Y5-AB5-AC5-AE5-AF5-AG5-AH5-AI5-AK5-AJ5 -> -917.81235 | AN5: =IF(S5=0,0,Y5/S5) -> 1052 | AO5: =I5 -> 123.09 | AP5: =IF(S5=0,0,AC5/S5) -> 383.30333 | AQ5: =IF(Q5=0,AE5/1,AE5/Q5) -> 62.35 | AR5: =IF(Q5=0,0,(AF5+AG5)/Q5) -> 702 | AS5: {=_xlfn.IFS(S5=0,AL5,S5<0,AL5/-S5,S5>0,AL5/S5)} -> -305.93745 | AT5: =IF(AN5=0,0,AS5/AN5) -> -0.29081507 | AU5: =IF(AO5=0,0,AS5/AO5) -> -2.4854777 | AW5: =AS5*E5 -> 0
B6: 340341838 | C6: Qs желт Сул | D6: Солнцезащитные очки | F6: 4 | G6: 2 | H6: 341 | I6: 123.09 | J6: =E6*I6 -> 0 | K6: 551 | L6: 7 | M6: 1158 | N6: 100 | O6: =L6/7 -> 1 | P6: =S6/7 -> 0.42857143 | Q6: 3 | R6: 0 | S6: =Q6+R6 -> 3 | T6: 2282 | U6: 0 | V6: =T6+U6 -> 2282 | W6: 3466 | X6: 0 | Y6: =W6+X6 -> 3466 | Z6: =L6*M6*N6/100 -> 8106 | AA6: =Y6/$Y$74 -> 0.043810198 | AB6: =S6*I6 -> 369.27 | AC6: 1258.35 | AD6: =IF(Y6=0,0,AC6/Y6) -> 0.3630554 | AE6: 440 | AI6: =IFERROR($AI$74*H6/$H$74,0) -> 220.95549 | AJ6: 0 | AK6: =V6*1% -> 22.82 | AL6: =Y6-AB6-AC6-AE6-AF6-AG6-AH6-AI6-AK6-AJ6 -> 1154.6045 | AN6: =IF(S6=0,0,Y6/S6) -> 1155.3333 | AO6: =I6 -> 123.09 | AP6: =IF(S6=0,0,AC6/S6) -> 419.45 | AQ6: =IF(Q6=0,AE6/1,AE6/Q6) -> 146.66667 | AR6: =IF(Q6=0,0,(AF6+AG6)/Q6) -> 0 | AS6: {=_xlfn.IFS(S6=0,AL6,S6<0,AL6/-S6,S6>0,AL6/S6)} -> 384.86817 | AT6: =IF(AN6=0,0,AS6/AN6) -> 0.33312306 | AU6: =IF(AO6=0,0,AS6/AO6) -> 3.1267217 | AW6: =AS6*E6 -> 0
B7: 445291724 | C7: flip черные Сул | D7: Солнцезащитные очки | F7: 4 | H7: 279 | I7: 123.09 | J7: =E7*I7 -> 0 | K7: 999 | L7: 4 | M7: 1079 | N7: 100 | O7: =L7/7 -> 0.57142857 | P7: =S7/7 -> 0.14285714 | Q7: 1 | R7: 0 | S7: =Q7+R7 -> 1 | T7: 672 | U7: 0 | V7: =T7+U7 -> 672 | W7: 1079 | X7: 0 | Y7: =W7+X7 -> 1079 | Z7: =L7*M7*N7/100 -> 4316 | AA7: =Y7/$Y$74 -> 0.013638547 | AB7: =S7*I7 -> 123.09 | AC7: 394.09 | AD7: =IF(Y7=0,0,AC7/Y7) -> 0.36523633 | AE7: 63.8 | AF7: 1067 | AG7: 17 | AI7: =IFERROR($AI$74*H7/$H$74,0) -> 180.78176 | AJ7: 0 | AK7: =V7*1% -> 6.72 | AL7: =Y7-AB7-AC7-AE7-AF7-AG7-AH7-AI7-AK7-AJ7 -> -773.48176 | AN7: =IF(S7=0,0,Y7/S7) -> 1079 | AO7: =I7 -> 123.09 | AP7: =IF(S7=0,0,AC7/S7) -> 394.09 | AQ7: =IF(Q7=0,AE7/1,AE7/Q7) -> 63.8 | AR7: =IF(Q7=0,0,(AF7+AG7)/Q7) -> 1084 | AS7: {=_xlfn.IFS(S7=0,AL7,S7<0,AL7/-S7,S7>0,AL7/S7)} -> -773.48176 | AT7: =IF(AN7=0,0,AS7/AN7) -> -0.71685057 | AU7: =IF(AO7=0,0,AS7/AO7) -> -6.2838717 | AW7: =AS7*E7 -> 0
B8: 445336740 | C8: flip желтые Сул | D8: Солнцезащитные очки | F8: 23 | G8: 1 | H8: 75 | I8: 123.09 | J8: =E8*I8 -> 0 | K8: 50 | L8: 31 | M8: 1150 | N8: 71 | O8: =L8/7 -> 4.4285714 | P8: =S8/7 -> 2 | Q8: 14 | R8: 0 | S8: =Q8+R8 -> 14 | T8: 10725.07 | U8: 0 | V8: =T8+U8 -> 10725.07 | W8: 16236.87 | X8: 0 | Y8: =W8+X8 -> 16236.87 | Z8: =L8*M8*N8/100 -> 25311.5 | AA8: =Y8/$Y$74 -> 0.20523384 | AB8: =S8*I8 -> 1723.26 | AC8: 5923.75 | AD8: =IF(Y8=0,0,AC8/Y8) -> 0.36483325 | AE8: 1425.9 | AF8: 3963 | AG8: 1000 | AI8: =IFERROR($AI$74*H8/$H$74,0) -> 48.597248 | AJ8: 0 | AK8: =V8*1% -> 107.2507 | AL8: =Y8-AB8-AC8-AE8-AF8-AG8-AH8-AI8-AK8-AJ8 -> 2045.1121 | AN8: =IF(S8=0,0,Y8/S8) -> 1159.7764 | AO8: =I8 -> 123.09 | AP8: =IF(S8=0,0,AC8/S8) -> 423.125 | AQ8: =IF(Q8=0,AE8/1,AE8/Q8) -> 101.85 | AR8: =IF(Q8=0,0,(AF8+AG8)/Q8) -> 354.5 | AS8: {=_xlfn.IFS(S8=0,AL8,S8<0,AL8/-S8,S8>0,AL8/S8)} -> 146.07943 | AT8: =IF(AN8=0,0,AS8/AN8) -> 0.12595482 | AU8: =IF(AO8=0,0,AS8/AO8) -> 1.1867693 | AW8: =AS8*E8 -> 0
B9: 445341507 | C9: MR8854 C2 Сул | D9: Солнцезащитные очки | F9: 14 | G9: 4 | H9: 229 | I9: 169.89 | J9: =E9*I9 -> 0 | K9: 207 | L9: 26 | M9: 1174 | N9: 64 | O9: =L9/7 -> 3.7142857 | P9: =S9/7 -> 1.5714286 | Q9: 11 | R9: 0 | S9: =Q9+R9 -> 11 | T9: 8595.96 | U9: 0 | V9: =T9+U9 -> 8595.96 | W9: 12913.73 | X9: 0 | Y9: =W9+X9 -> 12913.73 | Z9: =L9*M9*N9/100 -> 19535.36 | AA9: =Y9/$Y$74 -> 0.16322939 | AB9: =S9*I9 -> 1868.79 | AC9: 4666.27 | AD9: =IF(Y9=0,0,AC9/Y9) -> 0.36134177 | AE9: 1456.3 | AF9: 2000 | AG9: 2391 | AI9: =IFERROR($AI$74*H9/$H$74,0) -> 148.3836 | AJ9: 0 | AK9: =V9*1% -> 85.9596 | AL9: =Y9-AB9-AC9-AE9-AF9-AG9-AH9-AI9-AK9-AJ9 -> 297.0268 | AN9: =IF(S9=0,0,Y9/S9) -> 1173.9755 | AO9: =I9 -> 169.89 | AP9: =IF(S9=0,0,AC9/S9) -> 424.20636 | AQ9: =IF(Q9=0,AE9/1,AE9/Q9) -> 132.39091 | AR9: =IF(Q9=0,0,(AF9+AG9)/Q9) -> 399.18182 | AS9: {=_xlfn.IFS(S9=0,AL9,S9<0,AL9/-S9,S9>0,AL9/S9)} -> 27.002437 | AT9: =IF(AN9=0,0,AS9/AN9) -> 0.023000853 | AU9: =IF(AO9=0,0,AS9/AO9) -> 0.15894071 | AW9: =AS9*E9 -> 0
B10: 497825485 | C10: MR 1819 черн | D10: Солнцезащитные очки | G10: 1 | H10: 39 | I10: 169.89 | J10: =E10*I10 -> 0 | K10: 399 | L10: 0 | M10: 0 | N10: 0 | O10: =L10/7 -> 0 | P10: =S10/7 -> 0.14285714 | Q10: 1 | R10: 0 | S10: =Q10+R10 -> 1 | T10: 876 | U10: 0 | V10: =T10+U10 -> 876 | W10: 1199 | X10: 0 | Y10: =W10+X10 -> 1199 | Z10: =L10*M10*N10/100 -> 0 | AA10: =Y10/$Y$74 -> 0.015155345 | AB10: =S10*I10 -> 169.89 | AC10: 433.02 | AD10: =IF(Y10=0,0,AC10/Y10) -> 0.36115096 | AE10: 163.1 | AI10: =IFERROR($AI$74*H10/$H$74,0) -> 25.270569 | AJ10: 0 | AK10: =V10*1% -> 8.76 | AL10: =Y10-AB10-AC10-AE10-AF10-AG10-AH10-AI10-AK10-AJ10 -> 398.95943 | AN10: =IF(S10=0,0,Y10/S10) -> 1199 | AO10: =I10 -> 169.89 | AP10: =IF(S10=0,0,AC10/S10) -> 433.02 | AQ10: =IF(Q10=0,AE10/1,AE10/Q10) -> 163.1 | AR10: =IF(Q10=0,0,(AF10+AG10)/Q10) -> 0 | AS10: {=_xlfn.IFS(S10=0,AL10,S10<0,AL10/-S10,S10>0,AL10/S10)} -> 398.95943 | AT10: =IF(AN10=0,0,AS10/AN10) -> 0.33274348 | AU10: =IF(AO10=0,0,AS10/AO10) -> 2.3483397 | AW10: =AS10*E10 -> 0
B11: 497825962 | C11: MR 1819 корич | D11: Солнцезащитные очки | G11: 1 | H11: 38 | I11: 169.89 | J11: =E11*I11 -> 0 | K11: 399 | L11: 2 | M11: 1145 | N11: 50 | O11: =L11/7 -> 0.28571429 | P11: =S11/7 -> 0.28571429 | Q11: 2 | R11: 0 | S11: =Q11+R11 -> 2 | T11: 1563 | U11: 0 | V11: =T11+U11 -> 1563 | W11: 2290 | X11: 0 | Y11: =W11+X11 -> 2290 | Z11: =L11*M11*N11/100 -> 1145 | AA11: =Y11/$Y$74 -> 0.028945572 | AB11: =S11*I11 -> 339.78 | AC11: 817.75 | AD11: =IF(Y11=0,0,AC11/Y11) -> 0.35709607 | AE11: 333.45 | AI11: =IFERROR($AI$74*H11/$H$74,0) -> 24.622606 | AJ11: 0 | AK11: =V11*1% -> 15.63 | AL11: =Y11-AB11-AC11-AE11-AF11-AG11-AH11-AI11-AK11-AJ11 -> 758.76739 | AN11: =IF(S11=0,0,Y11/S11) -> 1145 | AO11: =I11 -> 169.89 | AP11: =IF(S11=0,0,AC11/S11) -> 408.875 | AQ11: =IF(Q11=0,AE11/1,AE11/Q11) -> 166.725 | AR11: =IF(Q11=0,0,(AF11+AG11)/Q11) -> 0 | AS11: {=_xlfn.IFS(S11=0,AL11,S11<0,AL11/-S11,S11>0,AL11/S11)} -> 379.3837 | AT11: =IF(AN11=0,0,AS11/AN11) -> 0.33133947 | AU11: =IF(AO11=0,0,AS11/AO11) -> 2.2331138 | AW11: =AS11*E11 -> 0
B12: 497821775 | C12: MR Р1874 черн | D12: Солнцезащитные очки | H12: 44 | I12: 169.89 | J12: =E12*I12 -> 0 | K12: 264 | L12: 0 | M12: 0 | N12: 0 | O12: =L12/7 -> 0 | P12: =S12/7 -> 0.28571429 | Q12: 2 | R12: 0 | S12: =Q12+R12 -> 2 | T12: 1779 | U12: 0 | V12: =T12+U12 -> 1779 | W12: 2332 | X12: 0 | Y12: =W12+X12 -> 2332 | Z12: =L12*M12*N12/100 -> 0 | AA12: =Y12/$Y$74 -> 0.029476452 | AB12: =S12*I12 -> 339.78 | AC12: 836.55 | AD12: =IF(Y12=0,0,AC12/Y12) -> 0.35872642 | AE12: 326.2 | AI12: =IFERROR($AI$74*H12/$H$74,0) -> 28.510386 | AJ12: 0 | AK12: =V12*1% -> 17.79 | AL12: =Y12-AB12-AC12-AE12-AF12-AG12-AH12-AI12-AK12-AJ12 -> 783.16961 | AN12: =IF(S12=0,0,Y12/S12) -> 1166 | AO12: =I12 -> 169.89 | AP12: =IF(S12=0,0,AC12/S12) -> 418.275 | AQ12: =IF(Q12=0,AE12/1,AE12/Q12) -> 163.1 | AR12: =IF(Q12=0,0,(AF12+AG12)/Q12) -> 0 | AS12: {=_xlfn.IFS(S12=0,AL12,S12<0,AL12/-S12,S12>0,AL12/S12)} -> 391.58481 | AT12: =IF(AN12=0,0,AS12/AN12) -> 0.33583603 | AU12: =IF(AO12=0,0,AS12/AO12) -> 2.3049315 | AW12: =AS12*E12 -> 0
B13: 497823770 | C13: MR Р1874 корич | D13: Солнцезащитные очки | H13: 8 | I13: 169.89 | J13: =E13*I13 -> 0 | K13: 92 | L13: 0 | M13: 0 | N13: 0 | O13: =L13/7 -> 0 | P13: =S13/7 -> 0.14285714 | Q13: 1 | R13: 0 | S13: =Q13+R13 -> 1 | T13: 788 | U13: 0 | V13: =T13+U13 -> 788 | W13: 1166 | X13: 0 | Y13: =W13+X13 -> 1166 | Z13: =L13*M13*N13/100 -> 0 | AA13: =Y13/$Y$74 -> 0.014738226 | AB13: =S13*I13 -> 169.89 | AC13: 427.88 | AD13: =IF(Y13=0,0,AC13/Y13) -> 0.36696398 | AE13: 46.4 | AI13: =IFERROR($AI$74*H13/$H$74,0) -> 5.1837065 | AJ13: 0 | AK13: =V13*1% -> 7.88 | AL13: =Y13-AB13-AC13-AE13-AF13-AG13-AH13-AI13-AK13-AJ13 -> 508.76629 | AN13: =IF(S13=0,0,Y13/S13) -> 1166 | AO13: =I13 -> 169.89 | AP13: =IF(S13=0,0,AC13/S13) -> 427.88 | AQ13: =IF(Q13=0,AE13/1,AE13/Q13) -> 46.4 | AR13: =IF(Q13=0,0,(AF13+AG13)/Q13) -> 0 | AS13: {=_xlfn.IFS(S13=0,AL13,S13<0,AL13/-S13,S13>0,AL13/S13)} -> 508.76629 | AT13: =IF(AN13=0,0,AS13/AN13) -> 0.43633473 | AU13: =IF(AO13=0,0,AS13/AO13) -> 2.9946806 | AW13: =AS13*E13 -> 0
B14: 497824253 | C14: MR Р1886 черн | D14: Солнцезащитные очки | G14: 1 | H14: 58 | I14: 169.89 | J14: =E14*I14 -> 0 | K14: 259 | L14: 2 | M14: 1232 | N14: 100 | O14: =L14/7 -> 0.28571429 | P14: =S14/7 -> 0.28571429 | Q14: 2 | R14: 0 | S14: =Q14+R14 -> 2 | T14: 1559 | U14: 0 | V14: =T14+U14 -> 1559 | W14: 2464 | X14: 0 | Y14: =W14+X14 -> 2464 | Z14: =L14*M14*N14/100 -> 2464 | AA14: =Y14/$Y$74 -> 0.03114493 | AB14: =S14*I14 -> 339.78 | AC14: 906.46 | AD14: =IF(Y14=0,0,AC14/Y14) -> 0.36788149 | AE14: 337.8 | AI14: =IFERROR($AI$74*H14/$H$74,0) -> 37.581872 | AJ14: 0 | AK14: =V14*1% -> 15.59 | AL14: =Y14-AB14-AC14-AE14-AF14-AG14-AH14-AI14-AK14-AJ14 -> 826.78813 | AN14: =IF(S14=0,0,Y14/S14) -> 1232 | AO14: =I14 -> 169.89 | AP14: =IF(S14=0,0,AC14/S14) -> 453.23 | AQ14: =IF(Q14=0,AE14/1,AE14/Q14) -> 168.9 | AR14: =IF(Q14=0,0,(AF14+AG14)/Q14) -> 0 | AS14: {=_xlfn.IFS(S14=0,AL14,S14<0,AL14/-S14,S14>0,AL14/S14)} -> 413.39406 | AT14: =IF(AN14=0,0,AS14/AN14) -> 0.33554713 | AU14: =IF(AO14=0,0,AS14/AO14) -> 2.4333043 | AW14: =AS14*E14 -> 0
B15: 497824944 | C15: MR Р1886 корич | D15: Солнцезащитные очки | H15: 34 | I15: 169.89 | J15: =E15*I15 -> 0 | K15: 524 | L15: 0 | M15: 0 | N15: 0 | O15: =L15/7 -> 0 | P15: =S15/7 -> 0 | Q15: 0 | R15: 0 | S15: =Q15+R15 -> 0 | T15: 0 | U15: 0 | V15: =T15+U15 -> 0 | W15: 0 | X15: 0 | Y15: =W15+X15 -> 0 | Z15: =L15*M15*N15/100 -> 0 | AA15: =Y15/$Y$74 -> 0 | AB15: =S15*I15 -> 0 | AC15: 0 | AD15: =IF(Y15=0,0,AC15/Y15) -> 0 | AE15: 0 | AI15: =IFERROR($AI$74*H15/$H$74,0) -> 22.030753 | AJ15: 0 | AK15: =V15*1% -> 0 | AL15: =Y15-AB15-AC15-AE15-AF15-AG15-AH15-AI15-AK15-AJ15 -> -22.030753 | AN15: =IF(S15=0,0,Y15/S15) -> 0 | AO15: =I15 -> 169.89 | AP15: =IF(S15=0,0,AC15/S15) -> 0 | AQ15: =IF(Q15=0,AE15/1,AE15/Q15) -> 0 | AR15: =IF(Q15=0,0,(AF15+AG15)/Q15) -> 0 | AS15: {=_xlfn.IFS(S15=0,AL15,S15<0,AL15/-S15,S15>0,AL15/S15)} -> -22.030753 | AT15: =IF(AN15=0,0,AS15/AN15) -> 0 | AU15: =IF(AO15=0,0,AS15/AO15) -> -0.12967657 | AW15: =AS15*E15 -> 0
AN16: =AVERAGE(AN3:AN6) -> 1093.5681 | AO16: =AVERAGE(AO3:AO6) -> 128.0625 | AP16: =AVERAGE(AP3:AP6) -> 397.70282 | AQ16: =AVERAGE(AQ3:AQ6) -> 111.82292 | AR16: =AVERAGE(AR3:AR6) -> 348.35 | AS16: =AVERAGE(AS3:AS6) -> 48.034925 | AT16: =AVERAGE(AT3:AT6) -> 0.03463217 | AU16: =AVERAGE(AU3:AU6) -> 0.3632773
A17: Итого очки | E17: =SUM(E3:E15) -> 0 | F17: =SUM(F3:F15) -> 99 | G17: =SUM(G3:G15) -> 19 | H17: =SUM(H3:H15) -> 2126 | J17: =SUM(J3:J15) -> 0 | L17: =SUM(L3:L15) -> 157 | Q17: =SUM(Q3:Q15) -> 70 | R17: =SUM(R3:R15) -> -1 | S17: =SUM(S3:S15) -> 69 | T17: =SUM(T3:T15) -> 53707.42 | U17: =SUM(U3:U15) -> -813 | V17: =SUM(V3:V15) -> 52894.42 | W17: =SUM(W3:W15) -> 80352 | X17: =SUM(X3:X15) -> -1238 | ... AC17: =SUM(AC3:AC15) -> 28720.66 | AD17: =AC17/Y17 -> 0.36302879 | AE17: =SUM(AE3:AE15) -> 8509.6 | AF17: =SUM(AF3:AF15) -> 13613 | AG17: =SUM(AG3:AG15) -> 9553 | AH17: =SUM(AH3:AH15) -> 0 | AI17: =SUM(AI3:AI15) -> 1377.57 | AJ17: =SUM(AJ3:AJ15) -> 0 | AK17: =SUM(AK3:AK15) -> 528.9442 | AL17: =SUM(AL3:AL15) -> 7050.9058 | AR17: =(AF17+AG17)/Q17 -> 330.94286 | AW17: =SUM(AW3:AW6) -> 0
E19: =SUM(F19:H19) -> 0 | J19: =E19*I19 -> 0 | O19: =L19/7 -> 0 | P19: =S19/7 -> 0 | S19: =Q19+R19 -> 0 | V19: =T19+U19 -> 0 | Y19: =W19+X19 -> 0 | Z19: =L19*M19*N19/100 -> 0 | AA19: =Y19/$Y$74 -> 0 | AB19: =S19*I19 -> 0 | AD19: =IF(Y19=0,0,AC19/Y19) -> 0 | AI19: =$AI$74*H19/$H$74 -> 0 | AK19: =V19*1% -> 0 | AL19: =Y19-AB19-AC19-AE19-AF19-AG19-AH19-AI19-AK19-AJ19 -> 0 | AN19: =IF(S19=0,0,Y19/S19) -> 0 | AO19: =I19 -> 0 | AP19: =IF(S19=0,0,AC19/S19) -> 0 | AQ19: =IF(Q19=0,AE19/1,AE19/Q19) -> 0 | AR19: =IF(Q19=0,0,(AF19+AG19)/Q19) -> 0 | AS19: {=_xlfn.IFS(S19=0,AL19,S19<0,AL19/-S19,S19>0,AL19/S19)} -> 0 | AT19: =IF(AN19=0,0,AS19/AN19) -> 0 | AU19: =IF(AO19=0,0,AS19/AO19) -> 0 | AW19: =AS19*E19 -> 0
E20: =SUM(F20:H20) -> 0 | J20: =E20*I20 -> 0 | O20: =L20/7 -> 0 | P20: =S20/7 -> 0 | S20: =Q20+R20 -> 0 | V20: =T20+U20 -> 0 | Y20: =W20+X20 -> 0 | Z20: =L20*M20*N20/100 -> 0 | AA20: =Y20/$Y$74 -> 0 | AB20: =S20*I20 -> 0 | AD20: =IF(Y20=0,0,AC20/Y20) -> 0 | AI20: =$AI$74*H20/$H$74 -> 0 | AK20: =V20*1% -> 0 | AL20: =Y20-AB20-AC20-AE20-AF20-AG20-AH20-AI20-AK20-AJ20 -> 0 | AN20: =IF(S20=0,0,Y20/S20) -> 0 | AO20: =I20 -> 0 | AP20: =IF(S20=0,0,AC20/S20) -> 0 | AQ20: =IF(Q20=0,AE20/1,AE20/Q20) -> 0 | AR20: =IF(Q20=0,0,(AF20+AG20)/Q20) -> 0 | AS20: {=_xlfn.IFS(S20=0,AL20,S20<0,AL20/-S20,S20>0,AL20/S20)} -> 0 | AT20: =IF(AN20=0,0,AS20/AN20) -> 0 | AU20: =IF(AO20=0,0,AS20/AO20) -> 0 | AW20: =AS20*E20 -> 0
E21: =SUM(F21:H21) -> 0 | J21: =E21*I21 -> 0 | O21: =L21/7 -> 0 | P21: =S21/7 -> 0 | S21: =Q21+R21 -> 0 | V21: =T21+U21 -> 0 | Y21: =W21+X21 -> 0 | Z21: =L21*M21*N21/100 -> 0 | AA21: =Y21/$Y$74 -> 0 | AB21: =S21*I21 -> 0 | AD21: =IF(Y21=0,0,AC21/Y21) -> 0 | AI21: =$AI$74*H21/$H$74 -> 0 | AK21: =V21*1% -> 0 | AL21: =Y21-AB21-AC21-AE21-AF21-AG21-AH21-AI21-AK21-AJ21 -> 0 | AN21: =IF(S21=0,0,Y21/S21) -> 0 | AO21: =I21 -> 0 | AP21: =IF(S21=0,0,AC21/S21) -> 0 | AQ21: =IF(Q21=0,AE21/1,AE21/Q21) -> 0 | AR21: =IF(Q21=0,0,(AF21+AG21)/Q21) -> 0 | AS21: {=_xlfn.IFS(S21=0,AL21,S21<0,AL21/-S21,S21>0,AL21/S21)} -> 0 | AT21: =IF(AN21=0,0,AS21/AN21) -> 0 | AU21: =IF(AO21=0,0,AS21/AO21) -> 0 | AW21: =AS21*E21 -> 0
E22: =SUM(F22:H22) -> 0 | J22: =E22*I22 -> 0 | O22: =L22/7 -> 0 | P22: =S22/7 -> 0 | S22: =Q22+R22 -> 0 | V22: =T22+U22 -> 0 | Y22: =W22+X22 -> 0 | Z22: =L22*M22*N22/100 -> 0 | AA22: =Y22/$Y$74 -> 0 | AB22: =S22*I22 -> 0 | AD22: =IF(Y22=0,0,AC22/Y22) -> 0 | AI22: =$AI$74*H22/$H$74 -> 0 | AK22: =V22*1% -> 0 | AL22: =Y22-AB22-AC22-AE22-AF22-AG22-AH22-AI22-AK22-AJ22 -> 0 | AN22: =IF(S22=0,0,Y22/S22) -> 0 | AO22: =I22 -> 0 | AP22: =IF(S22=0,0,AC22/S22) -> 0 | AQ22: =IF(Q22=0,AE22/1,AE22/Q22) -> 0 | AR22: =IF(Q22=0,0,(AF22+AG22)/Q22) -> 0 | AS22: {=_xlfn.IFS(S22=0,AL22,S22<0,AL22/-S22,S22>0,AL22/S22)} -> 0 | AT22: =IF(AN22=0,0,AS22/AN22) -> 0 | AU22: =IF(AO22=0,0,AS22/AO22) -> 0 | AW22: =AS22*E22 -> 0
E23: =SUM(F23:H23) -> 0 | J23: =E23*I23 -> 0 | O23: =L23/7 -> 0 | P23: =S23/7 -> 0 | S23: =Q23+R23 -> 0 | V23: =T23+U23 -> 0 | Y23: =W23+X23 -> 0 | Z23: =L23*M23*N23/100 -> 0 | AA23: =Y23/$Y$74 -> 0 | AB23: =S23*I23 -> 0 | AD23: =IF(Y23=0,0,AC23/Y23) -> 0 | AI23: =$AI$74*H23/$H$74 -> 0 | AK23: =V23*1% -> 0 | AL23: =Y23-AB23-AC23-AE23-AF23-AG23-AH23-AI23-AK23-AJ23 -> 0 | AN23: =IF(S23=0,0,Y23/S23) -> 0 | AO23: =I23 -> 0 | AP23: =IF(S23=0,0,AC23/S23) -> 0 | AQ23: =IF(Q23=0,AE23/1,AE23/Q23) -> 0 | AR23: =IF(Q23=0,0,(AF23+AG23)/Q23) -> 0 | AS23: {=_xlfn.IFS(S23=0,AL23,S23<0,AL23/-S23,S23>0,AL23/S23)} -> 0 | AT23: =IF(AN23=0,0,AS23/AN23) -> 0 | AU23: =IF(AO23=0,0,AS23/AO23) -> 0 | AW23: =AS23*E23 -> 0
E24: =SUM(F24:H24) -> 0 | J24: =E24*I24 -> 0 | O24: =L24/7 -> 0 | P24: =S24/7 -> 0 | S24: =Q24+R24 -> 0 | V24: =T24+U24 -> 0 | Y24: =W24+X24 -> 0 | Z24: =L24*M24*N24/100 -> 0 | AA24: =Y24/$Y$74 -> 0 | AB24: =S24*I24 -> 0 | AD24: =IF(Y24=0,0,AC24/Y24) -> 0 | AI24: =$AI$74*H24/$H$74 -> 0 | AK24: =V24*1% -> 0 | AL24: =Y24-AB24-AC24-AE24-AF24-AG24-AH24-AI24-AK24-AJ24 -> 0 | AN24: =IF(S24=0,0,Y24/S24) -> 0 | AO24: =I24 -> 0 | AP24: =IF(S24=0,0,AC24/S24) -> 0 | AQ24: =IF(Q24=0,AE24/1,AE24/Q24) -> 0 | AR24: =IF(Q24=0,0,(AF24+AG24)/Q24) -> 0 | AS24: {=_xlfn.IFS(S24=0,AL24,S24<0,AL24/-S24,S24>0,AL24/S24)} -> 0 | AT24: =IF(AN24=0,0,AS24/AN24) -> 0 | AU24: =IF(AO24=0,0,AS24/AO24) -> 0 | AW24: =AS24*E24 -> 0
E25: =SUM(F25:H25) -> 0 | J25: =E25*I25 -> 0 | O25: =L25/7 -> 0 | P25: =S25/7 -> 0 | S25: =Q25+R25 -> 0 | V25: =T25+U25 -> 0 | Y25: =W25+X25 -> 0 | Z25: =L25*M25*N25/100 -> 0 | AA25: =Y25/$Y$74 -> 0 | AB25: =S25*I25 -> 0 | AD25: =IF(Y25=0,0,AC25/Y25) -> 0 | AI25: =$AI$74*H25/$H$74 -> 0 | AK25: =V25*1% -> 0 | AL25: =Y25-AB25-AC25-AE25-AF25-AG25-AH25-AI25-AK25-AJ25 -> 0 | AN25: =IF(S25=0,0,Y25/S25) -> 0 | AO25: =I25 -> 0 | AP25: =IF(S25=0,0,AC25/S25) -> 0 | AQ25: =IF(Q25=0,AE25/1,AE25/Q25) -> 0 | AR25: =IF(Q25=0,0,(AF25+AG25)/Q25) -> 0 | AS25: {=_xlfn.IFS(S25=0,AL25,S25<0,AL25/-S25,S25>0,AL25/S25)} -> 0 | AT25: =IF(AN25=0,0,AS25/AN25) -> 0 | AU25: =IF(AO25=0,0,AS25/AO25) -> 0 | AW25: =AS25*E25 -> 0
E26: =SUM(F26:H26) -> 0 | J26: =E26*I26 -> 0 | O26: =L26/7 -> 0 | P26: =S26/7 -> 0 | S26: =Q26+R26 -> 0 | V26: =T26+U26 -> 0 | Y26: =W26+X26 -> 0 | Z26: =L26*M26*N26/100 -> 0 | AA26: =Y26/$Y$74 -> 0 | AB26: =S26*I26 -> 0 | AD26: =IF(Y26=0,0,AC26/Y26) -> 0 | AI26: =$AI$74*H26/$H$74 -> 0 | AK26: =V26*1% -> 0 | AL26: =Y26-AB26-AC26-AE26-AF26-AG26-AH26-AI26-AK26-AJ26 -> 0 | AN26: =IF(S26=0,0,Y26/S26) -> 0 | AO26: =I26 -> 0 | AP26: =IF(S26=0,0,AC26/S26) -> 0 | AQ26: =IF(Q26=0,AE26/1,AE26/Q26) -> 0 | AR26: =IF(Q26=0,0,(AF26+AG26)/Q26) -> 0 | AS26: {=_xlfn.IFS(S26=0,AL26,S26<0,AL26/-S26,S26>0,AL26/S26)} -> 0 | AT26: =IF(AN26=0,0,AS26/AN26) -> 0 | AU26: =IF(AO26=0,0,AS26/AO26) -> 0 | AW26: =AS26*E26 -> 0
E27: =SUM(F27:H27) -> 0 | J27: =E27*I27 -> 0 | O27: =L27/7 -> 0 | P27: =S27/7 -> 0 | S27: =Q27+R27 -> 0 | V27: =T27+U27 -> 0 | Y27: =W27+X27 -> 0 | Z27: =L27*M27*N27/100 -> 0 | AA27: =Y27/$Y$74 -> 0 | AB27: =S27*I27 -> 0 | AD27: =IF(Y27=0,0,AC27/Y27) -> 0 | AI27: =$AI$74*H27/$H$74 -> 0 | AK27: =V27*1% -> 0 | AL27: =Y27-AB27-AC27-AE27-AF27-AG27-AH27-AI27-AK27-AJ27 -> 0 | AN27: =IF(S27=0,0,Y27/S27) -> 0 | AO27: =I27 -> 0 | AP27: =IF(S27=0,0,AC27/S27) -> 0 | AQ27: =IF(Q27=0,AE27/1,AE27/Q27) -> 0 | AR27: =IF(Q27=0,0,(AF27+AG27)/Q27) -> 0 | AS27: {=_xlfn.IFS(S27=0,AL27,S27<0,AL27/-S27,S27>0,AL27/S27)} -> 0 | AT27: =IF(AN27=0,0,AS27/AN27) -> 0 | AU27: =IF(AO27=0,0,AS27/AO27) -> 0 | AW27: =AS27*E27 -> 0
E28: =SUM(F28:H28) -> 0 | J28: =E28*I28 -> 0 | O28: =L28/7 -> 0 | P28: =S28/7 -> 0 | S28: =Q28+R28 -> 0 | V28: =T28+U28 -> 0 | Y28: =W28+X28 -> 0 | Z28: =L28*M28*N28/100 -> 0 | AA28: =Y28/$Y$74 -> 0 | AB28: =S28*I28 -> 0 | AD28: =IF(Y28=0,0,AC28/Y28) -> 0 | AI28: =$AI$74*H28/$H$74 -> 0 | AK28: =V28*1% -> 0 | AL28: =Y28-AB28-AC28-AE28-AF28-AG28-AH28-AI28-AK28-AJ28 -> 0 | AN28: =IF(S28=0,0,Y28/S28) -> 0 | AO28: =I28 -> 0 | AP28: =IF(S28=0,0,AC28/S28) -> 0 | AQ28: =IF(Q28=0,AE28/1,AE28/Q28) -> 0 | AR28: =IF(Q28=0,0,(AF28+AG28)/Q28) -> 0 | AS28: {=_xlfn.IFS(S28=0,AL28,S28<0,AL28/-S28,S28>0,AL28/S28)} -> 0 | AT28: =IF(AN28=0,0,AS28/AN28) -> 0 | AU28: =IF(AO28=0,0,AS28/AO28) -> 0 | AW28: =AS28*E28 -> 0
E29: =SUM(F29:H29) -> 0 | J29: =E29*I29 -> 0 | O29: =L29/7 -> 0 | P29: =S29/7 -> 0 | S29: =Q29+R29 -> 0 | V29: =T29+U29 -> 0 | Y29: =W29+X29 -> 0 | Z29: =L29*M29*N29/100 -> 0 | AA29: =Y29/$Y$74 -> 0 | AB29: =S29*I29 -> 0 | AD29: =IF(Y29=0,0,AC29/Y29) -> 0 | AI29: =$AI$74*H29/$H$74 -> 0 | AK29: =V29*1% -> 0 | AL29: =Y29-AB29-AC29-AE29-AF29-AG29-AH29-AI29-AK29-AJ29 -> 0 | AN29: =IF(S29=0,0,Y29/S29) -> 0 | AO29: =I29 -> 0 | AP29: =IF(S29=0,0,AC29/S29) -> 0 | AQ29: =IF(Q29=0,AE29/1,AE29/Q29) -> 0 | AR29: =IF(Q29=0,0,(AF29+AG29)/Q29) -> 0 | AS29: {=_xlfn.IFS(S29=0,AL29,S29<0,AL29/-S29,S29>0,AL29/S29)} -> 0 | AT29: =IF(AN29=0,0,AS29/AN29) -> 0 | AU29: =IF(AO29=0,0,AS29/AO29) -> 0 | AW29: =AS29*E29 -> 0
E30: =SUM(F30:H30) -> 0 | J30: =E30*I30 -> 0 | O30: =L30/7 -> 0 | P30: =S30/7 -> 0 | S30: =Q30+R30 -> 0 | V30: =T30+U30 -> 0 | Y30: =W30+X30 -> 0 | Z30: =L30*M30*N30/100 -> 0 | AA30: =Y30/$Y$74 -> 0 | AB30: =S30*I30 -> 0 | AD30: =IF(Y30=0,0,AC30/Y30) -> 0 | AI30: =$AI$74*H30/$H$74 -> 0 | AK30: =V30*1% -> 0 | AL30: =Y30-AB30-AC30-AE30-AF30-AG30-AH30-AI30-AK30-AJ30 -> 0 | AN30: =IF(S30=0,0,Y30/S30) -> 0 | AO30: =I30 -> 0 | AP30: =IF(S30=0,0,AC30/S30) -> 0 | AQ30: =IF(Q30=0,AE30/1,AE30/Q30) -> 0 | AR30: =IF(Q30=0,0,(AF30+AG30)/Q30) -> 0 | AS30: {=_xlfn.IFS(S30=0,AL30,S30<0,AL30/-S30,S30>0,AL30/S30)} -> 0 | AT30: =IF(AN30=0,0,AS30/AN30) -> 0 | AU30: =IF(AO30=0,0,AS30/AO30) -> 0 | AW30: =AS30*E30 -> 0
... E70: =SUM(F70:H70) -> 0 | J70: =E70*I70 -> 0 | O70: =L70/7 -> 0 | P70: =S70/7 -> 0 | S70: =Q70+R70 -> 0 | V70: =T70+U70 -> 0 | Y70: =W70+X70 -> 0 | Z70: =L70*M70*N70/100 -> 0 | AA70: =Y70/$Y$74 -> 0 | AB70: =S70*I70 -> 0 | AD70: =IF(Y70=0,0,AC70/Y70) -> 0 | AI70: =$AI$74*H70/$H$74 -> 0 | AK70: =V70*1% -> 0 | AL70: =Y70-AB70-AC70-AE70-AF70-AG70-AH70-AI70-AK70-AJ70 -> 0 | AN70: =IF(S70=0,0,Y70/S70) -> 0 | AO70: =I70 -> 0 | AP70: =IF(S70=0,0,AC70/S70) -> 0 | AQ70: =IF(Q70=0,AE70/1,AE70/Q70) -> 0 | AR70: =IF(Q70=0,0,(AF70+AG70)/Q70) -> 0 | AS70: {=_xlfn.IFS(S70=0,AL70,S70<0,AL70/-S70,S70>0,AL70/S70)} -> 0 | AT70: =IF(AN70=0,0,AS70/AN70) -> 0 | AU70: =IF(AO70=0,0,AS70/AO70) -> 0 | AW70: =AS70*E70 -> 0
AN71: =AVERAGE(AN19:AN70) -> 0 | AO71: =AVERAGE(AO19:AO70) -> 0 | AP71: =AVERAGE(AP19:AP70) -> 0 | AQ71: =AVERAGE(AQ19:AQ70) -> 0 | AR71: =AVERAGE(AR19:AR70) -> 0 | AS71: =AVERAGE(AS19:AS70) -> 0 | AT71: =AVERAGE(AT19:AT70) -> 0 | AU71: =AVERAGE(AU19:AU70) -> 0
A72: Итого ___ | E72: =SUM(E19:E70) -> 0 | F72: =SUM(F19:F70) -> 0 | G72: =SUM(G19:G70) -> 0 | H72: =SUM(H19:H70) -> 0 | J72: =SUM(J19:J70) -> 0 | L72: =SUM(L19:L70) -> 0 | Q72: =SUM(Q19:Q70) -> 0 | R72: =SUM(R19:R70) -> 0 | S72: =SUM(S19:S70) -> 0 | T72: =SUM(T19:T70) -> 0 | U72: =SUM(U19:U70) -> 0 | V72: =SUM(V19:V70) -> 0 | W72: =SUM(W19:W70) -> 0 | X72: =SUM(X19:X70) -> 0 | ... AC72: =SUM(AC19:AC70) -> 0 | AD72: =AC72/Y72 -> #DIV/0! | AE72: =SUM(AE19:AE70) -> 0 | AF72: =SUM(AF19:AF70) -> 0 | AG72: =SUM(AG19:AG70) -> 0 | AH72: =SUM(AH19:AH70) -> 0 | AI72: =SUM(AI19:AI70) -> 0 | AJ72: =SUM(AJ19:AJ70) -> 0 | AK72: =SUM(AK19:AK70) -> 0 | AL72: =SUM(AL19:AL70) -> 0 | AR72: =(AF72+AG72)/Q72 -> #DIV/0! | AW72: =SUM(AW19:AW70) -> 0
A74: ИТОГО | E74: =E17+E72 -> 0 | F74: =F17+F72 -> 99 | G74: =G17+G72 -> 19 | H74: =H17+H72 -> 2126 | I74: =I17+I72 -> 0 | J74: =J17+J72 -> 0 | K74: =K17+K72 -> 0 | L74: =L17+L72 -> 157 | ... AC74: =AC17+AC72 -> 28720.66 | AD74: =AC74/Y74 -> 0.36302879 | AE74: =AE17+AE72 -> 8509.6 | AF74: =AF17+AF72 -> 13613 | AG74: =AG17+AG72 -> 9553 | AH74: =AH17+AH72 -> 0 | AI74: 1377.57 | AJ74: =AJ17+AJ72 -> 0 | AK74: =AK17+AK72 -> 528.9442 | AL74: =AL17+AL72 -> 7050.9058 | AR74: =(AF74+AG74)/Q74 -> 330.94286 | AW74: =AW17+AW72 -> 0
AF75: =AF18+AF73 -> 0

Sheet Юнит 4
A1: 19-25.01_4 нед | F1: Отчет по остаткам 3,4,5 | K1: Цены и скидки 6 | L1: Воронка продаж 16,50,32 | AI1: Вставить в Итого | AN1: на 1 единицу проданного товара
A2: Бренд | B2: SKU | C2: Артикул поставщика | D2: Предмет | E2: Остаток на 26.01 | F2: В пути до клиента | G2: В пути от клиента | H2: Итого по складам ВБ | I2: Себетоимость на 1 ед на 29.09.25 | J2: Себестоимость остатков | K2: Оборачива-емость, дн | L2: Заказы, шт 7 дней | M2: Средняя цена, руб | N2: % выкупа за 7 дней | O2: Скорость заказов | P2: Скорость продаж | Q2: Кол-во ПРОДАЖИ | R2: Кол-во ВОЗВРАТЫ | S2: Кол-во ПРОДАЖИ-ВОЗВРАТЫ | T2: Выручка ВБ ПРОДАЖИ | U2: Выручка ВБ ВОЗВРАТЫ | V2: Выручка с учетом СПП ПРОДАЖИ - ВОЗВРАТЫ | W2: Выручка ПРОДАЖИ | X2: Выручка ВОЗВРАТЫ | Y2: Выручка с учетом согласованной скидки ПРОДАЖИ - ВОЗВРАТЫ | Z2: Выручка потенциальная | AA2: Доля выручки, % от общего объема | AB2: Себестоимость продаж | AC2: Комиссия, руб | AD2: Комиссия, % | AE2: Логистика | AF2: Реклама БАЛАНС | AG2: Реклама СЧЕТ | AH2: Блогеры | AI2: Хранение | AJ2: Штрафы | AK2: Налог 1% | AL2: Прибыль | AN2: Выручка на 1 ед (средняя цена продажи со скидкой) | AO2: Себестоимость на 1 ед | AP2: Комиссия на 1 ед | AQ2: Логистика на 1 ед | AR2: Реклама на 1 ед | AS2: Прибыль на 1 ед | AT2: Маржиналь-ность, % | AU2: Рентабель-ность, % | AW2: Прибыль с остатков
B3: 341479791 | C3: Черные с железкой Сул | D3: Солнцезащитные очки | E3: =SUM(F3:H3) -> 407 | F3: 16 | G3: 3 | H3: 388 | I3: 142.98 | J3: =E3*I3 -> 58192.86 | K3: 232 | L3: 32 | M3: 1238 | N3: 77 | O3: =L3/7 -> 4.5714286 | P3: =S3/7 -> 3 | Q3: 22 | R3: -1 | S3: =Q3+R3 -> 21 | T3: 20652 | U3: -1057 | V3: =T3+U3 -> 19595 | W3: 27236 | X3: -1238 | Y3: =W3+X3 -> 25998 | Z3: =L3*M3*N3/100 -> 30504.32 | AA3: =Y3/$Y$74 -> 0.45682922 | AB3: =S3*I3 -> 3002.58 | AC3: 9406.63 | AD3: =IF(Y3=0,0,AC3/Y3) -> 0.36182129 | AE3: 2466.85 | AF3: 4000 | AG3: 1000 | AH3: 0 | AI3: =IFERROR($AI$74*H3/$H$74,0) -> 248.14583 | AJ3: 0 | AK3: =V3*1% -> 195.95 | AL3: =Y3-AB3-AC3-AE3-AF3-AG3-AH3-AI3-AK3-AJ3 -> 5677.8442 | AN3: =IF(S3=0,0,Y3/S3) -> 1238 | AO3: =I3 -> 142.98 | AP3: =IF(S3=0,0,AC3/S3) -> 447.93476 | AQ3: =IF(Q3=0,AE3/1,AE3/Q3) -> 112.12955 | AR3: =IF(Q3=0,0,(AF3+AG3)/Q3) -> 227.27273 | AS3: =_xlfn.IFS(S3=0,AL3,S3<0,AL3/-S3,S3>0,AL3/S3) -> 270.37353 | AT3: =IF(AN3=0,0,AS3/AN3) -> 0.21839542 | AU3: =IF(AO3=0,0,AS3/AO3) -> 1.8909885 | AW3: =AS3*E3 -> 110042.03
B4: 340343575 | C4: Qs черн Сул | D4: Солнцезащитные очки | E4: =SUM(F4:H4) -> 289 | F4: 1 | G4: 2 | H4: 286 | I4: 123.09 | J4: =E4*I4 -> 35573.01 | K4: 999 | L4: 1 | M4: 929 | N4: 0 | O4: =L4/7 -> 0.14285714 | P4: =S4/7 -> 0 | Q4: 0 | R4: 0 | S4: =Q4+R4 -> 0 | T4: 0 | U4: 0 | V4: =T4+U4 -> 0 | W4: 0 | X4: 0 | Y4: =W4+X4 -> 0 | Z4: =L4*M4*N4/100 -> 0 | AA4: =Y4/$Y$74 -> 0 | AB4: =S4*I4 -> 0 | AC4: 0 | AD4: =IF(Y4=0,0,AC4/Y4) -> 0 | AE4: 0 | AG4: 112 | AH4: 0 | AI4: =IFERROR($AI$74*H4/$H$74,0) -> 182.91162 | AJ4: 0 | AK4: =V4*1% -> 0 | AL4: =Y4-AB4-AC4-AE4-AF4-AG4-AH4-AI4-AK4-AJ4 -> -294.91162 | AN4: =IF(S4=0,0,Y4/S4) -> 0 | AO4: =I4 -> 123.09 | AP4: =IF(S4=0,0,AC4/S4) -> 0 | AQ4: =IF(Q4=0,AE4/1,AE4/Q4) -> 0 | AR4: =IF(Q4=0,0,(AF4+AG4)/Q4) -> 0 | AS4: {=_xlfn.IFS(S4=0,AL4,S4<0,AL4/-S4,S4>0,AL4/S4)} -> -294.91162 | AT4: =IF(AN4=0,0,AS4/AN4) -> 0 | AU4: =IF(AO4=0,0,AS4/AO4) -> -2.3959023 | AW4: =AS4*E4 -> -85229.458
B5: 340332621 | C5: Qs син Сул | D5: Солнцезащитные очки | E5: =SUM(F5:H5) -> 378 | F5: 1 | H5: 377 | I5: 123.09 | J5: =E5*I5 -> 46528.02 | K5: 999 | L5: 1 | M5: 1052 | N5: 0 | O5: =L5/7 -> 0.14285714 | P5: =S5/7 -> 0 | Q5: 0 | R5: 0 | S5: =Q5+R5 -> 0 | T5: 0 | U5: 0 | V5: =T5+U5 -> 0 | W5: 0 | X5: 0 | Y5: =W5+X5 -> 0 | Z5: =L5*M5*N5/100 -> 0 | AA5: =Y5/$Y$74 -> 0 | AB5: =S5*I5 -> 0 | AC5: 0 | AD5: =IF(Y5=0,0,AC5/Y5) -> 0 | AE5: 0 | AG5: 142 | AH5: 0 | AI5: =IFERROR($AI$74*H5/$H$74,0) -> 241.11077 | AJ5: 0 | AK5: =V5*1% -> 0 | AL5: =Y5-AB5-AC5-AE5-AF5-AG5-AH5-AI5-AK5-AJ5 -> -383.11077 | AN5: =IF(S5=0,0,Y5/S5) -> 0 | AO5: =I5 -> 123.09 | AP5: =IF(S5=0,0,AC5/S5) -> 0 | AQ5: =IF(Q5=0,AE5/1,AE5/Q5) -> 0 | AR5: =IF(Q5=0,0,(AF5+AG5)/Q5) -> 0 | AS5: {=_xlfn.IFS(S5=0,AL5,S5<0,AL5/-S5,S5>0,AL5/S5)} -> -383.11077 | AT5: =IF(AN5=0,0,AS5/AN5) -> 0 | AU5: =IF(AO5=0,0,AS5/AO5) -> -3.1124443 | AW5: =AS5*E5 -> -144815.87
B6: 340341838 | C6: Qs желт Сул | D6: Солнцезащитные очки | E6: =SUM(F6:H6) -> 350 | F6: 3 | G6: 1 | H6: 346 | I6: 123.09 | J6: =E6*I6 -> 43081.5 | K6: 392 | L6: 5 | M6: 1176 | N6: 100 | O6: =L6/7 -> 0.71428571 | P6: =S6/7 -> 0.57142857 | Q6: 4 | R6: 0 | S6: =Q6+R6 -> 4 | T6: 3391 | U6: 0 | V6: =T6+U6 -> 3391 | W6: 4704 | X6: 0 | Y6: =W6+X6 -> 4704 | Z6: =L6*M6*N6/100 -> 5880 | AA6: =Y6/$Y$74 -> 0.082657306 | AB6: =S6*I6 -> 492.36 | AC6: 1704.37 | AD6: =IF(Y6=0,0,AC6/Y6) -> 0.36232355 | AE6: 427.1 | AF6: 3 | AH6: 0 | AI6: =IFERROR($AI$74*H6/$H$74,0) -> 221.28468 | AJ6: 0 | AK6: =V6*1% -> 33.91 | AL6: =Y6-AB6-AC6-AE6-AF6-AG6-AH6-AI6-AK6-AJ6 -> 1821.9753 | AN6: =IF(S6=0,0,Y6/S6) -> 1176 | AO6: =I6 -> 123.09 | AP6: =IF(S6=0,0,AC6/S6) -> 426.0925 | AQ6: =IF(Q6=0,AE6/1,AE6/Q6) -> 106.775 | AR6: =IF(Q6=0,0,(AF6+AG6)/Q6) -> 0.75 | AS6: {=_xlfn.IFS(S6=0,AL6,S6<0,AL6/-S6,S6>0,AL6/S6)} -> 455.49383 | AT6: =IF(AN6=0,0,AS6/AN6) -> 0.38732468 | AU6: =IF(AO6=0,0,AS6/AO6) -> 3.7004942 | AW6: =AS6*E6 -> 159422.84
B7: 445291724 | C7: flip черные Сул | D7: Солнцезащитные очки | E7: =SUM(F7:H7) -> 284 | H7: 284 | I7: 123.09 | J7: =E7*I7 -> 34957.56 | K7: 999 | L7: 0 | M7: 0 | N7: 0 | O7: =L7/7 -> 0 | P7: =S7/7 -> 0 | Q7: 0 | R7: 0 | S7: =Q7+R7 -> 0 | T7: 0 | U7: 0 | V7: =T7+U7 -> 0 | W7: 0 | X7: 0 | Y7: =W7+X7 -> 0 | Z7: =L7*M7*N7/100 -> 0 | AA7: =Y7/$Y$74 -> 0 | AB7: =S7*I7 -> 0 | AC7: 0 | AD7: =IF(Y7=0,0,AC7/Y7) -> 0 | AE7: 113.8 | AF7: 27 | AG7: 170 | AH7: 0 | AI7: =IFERROR($AI$74*H7/$H$74,0) -> 181.63252 | AJ7: 0 | AK7: =V7*1% -> 0 | AL7: =Y7-AB7-AC7-AE7-AF7-AG7-AH7-AI7-AK7-AJ7 -> -492.43252 | AN7: =IF(S7=0,0,Y7/S7) -> 0 | AO7: =I7 -> 123.09 | AP7: =IF(S7=0,0,AC7/S7) -> 0 | AQ7: =IF(Q7=0,AE7/1,AE7/Q7) -> 113.8 | AR7: =IF(Q7=0,0,(AF7+AG7)/Q7) -> 0 | AS7: {=_xlfn.IFS(S7=0,AL7,S7<0,AL7/-S7,S7>0,AL7/S7)} -> -492.43252 | AT7: =IF(AN7=0,0,AS7/AN7) -> 0 | AU7: =IF(AO7=0,0,AS7/AO7) -> -4.0005891 | AW7: =AS7*E7 -> -139850.83
B8: 445336740 | C8: flip желтые Сул | D8: Солнцезащитные очки | E8: =SUM(F8:H8) -> 113 | F8: 12 | G8: 1 | H8: 100 | I8: 123.09 | J8: =E8*I8 -> 13909.17 | K8: 46 | L8: 15 | M8: 1212 | N8: 83 | O8: =L8/7 -> 2.1428571 | P8: =S8/7 -> 1.4285714 | Q8: 10 | R8: 0 | S8: =Q8+R8 -> 10 | T8: 9131.88 | U8: 0 | V8: =T8+U8 -> 9131.88 | W8: 12077.67 | X8: 0 | Y8: =W8+X8 -> 12077.67 | Z8: =L8*M8*N8/100 -> 15089.4 | AA8: =Y8/$Y$74 -> 0.21222527 | AB8: =S8*I8 -> 1230.9 | AC8: 4334.49 | AD8: =IF(Y8=0,0,AC8/Y8) -> 0.35888462 | AE8: 822.8 | AF8: 37 | AH8: 0 | AI8: =IFERROR($AI$74*H8/$H$74,0) -> 63.955111 | AJ8: 0 | AK8: =V8*1% -> 91.3188 | AL8: =Y8-AB8-AC8-AE8-AF8-AG8-AH8-AI8-AK8-AJ8 -> 5497.2061 | AN8: =IF(S8=0,0,Y8/S8) -> 1207.767 | AO8: =I8 -> 123.09 | AP8: =IF(S8=0,0,AC8/S8) -> 433.449 | AQ8: =IF(Q8=0,AE8/1,AE8/Q8) -> 82.28 | AR8: =IF(Q8=0,0,(AF8+AG8)/Q8) -> 3.7 | AS8: {=_xlfn.IFS(S8=0,AL8,S8<0,AL8/-S8,S8>0,AL8/S8)} -> 549.72061 | AT8: =IF(AN8=0,0,AS8/AN8) -> 0.45515452 | AU8: =IF(AO8=0,0,AS8/AO8) -> 4.4660054 | AW8: =AS8*E8 -> 62118.429
B9: 445341507 | C9: MR8854 C2 Сул | D9: Солнцезащитные очки | E9: =SUM(F9:H9) -> 259 | F9: 8 | G9: 3 | H9: 248 | I9: 169.89 | J9: =E9*I9 -> 44001.51 | K9: 290 | L9: 21 | M9: 1174 | N9: 62 | O9: =L9/7 -> 3 | P9: =S9/7 -> 1.2857143 | Q9: 10 | R9: -1 | S9: =Q9+R9 -> 9 | T9: 8390 | U9: -831 | V9: =T9+U9 -> 7559 | W9: 11740 | X9: -1174 | Y9: =W9+X9 -> 10566 | Z9: =L9*M9*N9/100 -> 15285.48 | AA9: =Y9/$Y$74 -> 0.18566265 | AB9: =S9*I9 -> 1529.01 | AC9: 3809.19 | AD9: =IF(Y9=0,0,AC9/Y9) -> 0.36051391 | AE9: 1720.85 | AF9: 1849 | AG9: 609 | AH9: 0 | AI9: =IFERROR($AI$74*H9/$H$74,0) -> 158.60868 | AJ9: 0 | AK9: =V9*1% -> 75.59 | AL9: =Y9-AB9-AC9-AE9-AF9-AG9-AH9-AI9-AK9-AJ9 -> 814.75132 | AN9: =IF(S9=0,0,Y9/S9) -> 1174 | AO9: =I9 -> 169.89 | AP9: =IF(S9=0,0,AC9/S9) -> 423.24333 | AQ9: =IF(Q9=0,AE9/1,AE9/Q9) -> 172.085 | AR9: =IF(Q9=0,0,(AF9+AG9)/Q9) -> 245.8 | AS9: {=_xlfn.IFS(S9=0,AL9,S9<0,AL9/-S9,S9>0,AL9/S9)} -> 90.527925 | AT9: =IF(AN9=0,0,AS9/AN9) -> 0.077110669 | AU9: =IF(AO9=0,0,AS9/AO9) -> 0.532862 | AW9: =AS9*E9 -> 23446.733
B10: 497825485 | C10: MR 1819 черн | D10: Солнцезащитные очки | E10: =SUM(F10:H10) -> 41 | F10: 2 | H10: 39 | I10: 169.89 | J10: =E10*I10 -> 6965.49 | K10: 406 | L10: 2 | M10: 1199 | N10: 0 | O10: =L10/7 -> 0.28571429 | P10: =S10/7 -> 0 | Q10: 0 | R10: 0 | S10: =Q10+R10 -> 0 | T10: 0 | U10: 0 | V10: =T10+U10 -> 0 | W10: 0 | X10: 0 | Y10: =W10+X10 -> 0 | Z10: =L10*M10*N10/100 -> 0 | AA10: =Y10/$Y$74 -> 0 | AB10: =S10*I10 -> 0 | AC10: 0 | AD10: =IF(Y10=0,0,AC10/Y10) -> 0 | AE10: 96.4 | AH10: 0 | AI10: =IFERROR($AI$74*H10/$H$74,0) -> 24.942493 | AJ10: 0 | AK10: =V10*1% -> 0 | AL10: =Y10-AB10-AC10-AE10-AF10-AG10-AH10-AI10-AK10-AJ10 -> -121.34249 | AN10: =IF(S10=0,0,Y10/S10) -> 0 | AO10: =I10 -> 169.89 | AP10: =IF(S10=0,0,AC10/S10) -> 0 | AQ10: =IF(Q10=0,AE10/1,AE10/Q10) -> 96.4 | AR10: =IF(Q10=0,0,(AF10+AG10)/Q10) -> 0 | AS10: {=_xlfn.IFS(S10=0,AL10,S10<0,AL10/-S10,S10>0,AL10/S10)} -> -121.34249 | AT10: =IF(AN10=0,0,AS10/AN10) -> 0 | AU10: =IF(AO10=0,0,AS10/AO10) -> -0.71424153 | AW10: =AS10*E10 -> -4975.0422
B11: 497825962 | C11: MR 1819 корич | D11: Солнцезащитные очки | E11: =SUM(F11:H11) -> 41 | F11: 2 | H11: 39 | I11: 169.89 | J11: =E11*I11 -> 6965.49 | K11: 609 | L11: 2 | M11: 1145 | N11: 0 | O11: =L11/7 -> 0.28571429 | P11: =S11/7 -> 0 | Q11: 0 | R11: 0 | S11: =Q11+R11 -> 0 | T11: 0 | U11: 0 | V11: =T11+U11 -> 0 | W11: 0 | X11: 0 | Y11: =W11+X11 -> 0 | Z11: =L11*M11*N11/100 -> 0 | AA11: =Y11/$Y$74 -> 0 | AB11: =S11*I11 -> 0 | AC11: 0 | AD11: =IF(Y11=0,0,AC11/Y11) -> 0 | AE11: 0 | AH11: 0 | AI11: =IFERROR($AI$74*H11/$H$74,0) -> 24.942493 | AJ11: 0 | AK11: =V11*1% -> 0 | AL11: =Y11-AB11-AC11-AE11-AF11-AG11-AH11-AI11-AK11-AJ11 -> -24.942493 | AN11: =IF(S11=0,0,Y11/S11) -> 0 | AO11: =I11 -> 169.89 | AP11: =IF(S11=0,0,AC11/S11) -> 0 | AQ11: =IF(Q11=0,AE11/1,AE11/Q11) -> 0 | AR11: =IF(Q11=0,0,(AF11+AG11)/Q11) -> 0 | AS11: {=_xlfn.IFS(S11=0,AL11,S11<0,AL11/-S11,S11>0,AL11/S11)} -> -24.942493 | AT11: =IF(AN11=0,0,AS11/AN11) -> 0 | AU11: =IF(AO11=0,0,AS11/AO11) -> -0.14681555 | AW11: =AS11*E11 -> -1022.6422
B12: 497821775 | C12: MR Р1874 черн | D12: Солнцезащитные очки | E12: =SUM(F12:H12) -> 46 | F12: 4 | H12: 42 | I12: 169.89 | J12: =E12*I12 -> 7814.94 | K12: 270 | L12: 3 | M12: 1166 | N12: 0 | O12: =L12/7 -> 0.42857143 | P12: =S12/7 -> 0.14285714 | Q12: 1 | R12: 0 | S12: =Q12+R12 -> 1 | T12: 959 | U12: 0 | V12: =T12+U12 -> 959 | W12: 1166 | X12: 0 | Y12: =W12+X12 -> 1166 | Z12: =L12*M12*N12/100 -> 0 | AA12: =Y12/$Y$74 -> 0.020488609 | AB12: =S12*I12 -> 169.89 | AC12: 422.9 | AD12: =IF(Y12=0,0,AC12/Y12) -> 0.36269297 | AE12: 163.1 | AH12: 0 | AI12: =IFERROR($AI$74*H12/$H$74,0) -> 26.861147 | AJ12: 0 | AK12: =V12*1% -> 9.59 | AL12: =Y12-AB12-AC12-AE12-AF12-AG12-AH12-AI12-AK12-AJ12 -> 373.65885 | AN12: =IF(S12=0,0,Y12/S12) -> 1166 | AO12: =I12 -> 169.89 | AP12: =IF(S12=0,0,AC12/S12) -> 422.9 | AQ12: =IF(Q12=0,AE12/1,AE12/Q12) -> 163.1 | AR12: =IF(Q12=0,0,(AF12+AG12)/Q12) -> 0 | AS12: {=_xlfn.IFS(S12=0,AL12,S12<0,AL12/-S12,S12>0,AL12/S12)} -> 373.65885 | AT12: =IF(AN12=0,0,AS12/AN12) -> 0.32046214 | AU12: =IF(AO12=0,0,AS12/AO12) -> 2.1994164 | AW12: =AS12*E12 -> 17188.307
B13: 497823770 | C13: MR Р1874 корич | D13: Солнцезащитные очки | E13: =SUM(F13:H13) -> 9 | F13: 1 | H13: 8 | I13: 169.89 | J13: =E13*I13 -> 1529.01 | K13: 74 | L13: 2 | M13: 1166 | N13: 100 | O13: =L13/7 -> 0.28571429 | P13: =S13/7 -> 0.14285714 | Q13: 1 | R13: 0 | S13: =Q13+R13 -> 1 | T13: 850 | U13: 0 | V13: =T13+U13 -> 850 | W13: 1166 | X13: 0 | Y13: =W13+X13 -> 1166 | Z13: =L13*M13*N13/100 -> 2332 | AA13: =Y13/$Y$74 -> 0.020488609 | AB13: =S13*I13 -> 169.89 | AC13: 420.55 | AD13: =IF(Y13=0,0,AC13/Y13) -> 0.36067753 | AE13: 269.65 | AH13: 0 | AI13: =IFERROR($AI$74*H13/$H$74,0) -> 5.1164089 | AJ13: 0 | AK13: =V13*1% -> 8.5 | AL13: =Y13-AB13-AC13-AE13-AF13-AG13-AH13-AI13-AK13-AJ13 -> 292.29359 | AN13: =IF(S13=0,0,Y13/S13) -> 1166 | AO13: =I13 -> 169.89 | AP13: =IF(S13=0,0,AC13/S13) -> 420.55 | AQ13: =IF(Q13=0,AE13/1,AE13/Q13) -> 269.65 | AR13: =IF(Q13=0,0,(AF13+AG13)/Q13) -> 0 | AS13: {=_xlfn.IFS(S13=0,AL13,S13<0,AL13/-S13,S13>0,AL13/S13)} -> 292.29359 | AT13: =IF(AN13=0,0,AS13/AN13) -> 0.25068061 | AU13: =IF(AO13=0,0,AS13/AO13) -> 1.7204873 | AW13: =AS13*E13 -> 2630.6423
B14: 497824253 | C14: MR Р1886 черн | D14: Солнцезащитные очки | E14: =SUM(F14:H14) -> 61 | F14: 2 | H14: 59 | I14: 169.89 | J14: =E14*I14 -> 10363.29 | K14: 265 | L14: 2 | M14: 1232 | N14: 0 | O14: =L14/7 -> 0.28571429 | P14: =S14/7 -> 0 | Q14: 0 | R14: 0 | S14: =Q14+R14 -> 0 | T14: 0 | U14: 0 | V14: =T14+U14 -> 0 | W14: 0 | X14: 0 | Y14: =W14+X14 -> 0 | Z14: =L14*M14*N14/100 -> 0 | AA14: =Y14/$Y$74 -> 0 | AB14: =S14*I14 -> 0 | AC14: 0 | AD14: =IF(Y14=0,0,AC14/Y14) -> 0 | AE14: 0 | AH14: 0 | AI14: =IFERROR($AI$74*H14/$H$74,0) -> 37.733516 | AJ14: 0 | AK14: =V14*1% -> 0 | AL14: =Y14-AB14-AC14-AE14-AF14-AG14-AH14-AI14-AK14-AJ14 -> -37.733516 | AN14: =IF(S14=0,0,Y14/S14) -> 0 | AO14: =I14 -> 169.89 | AP14: =IF(S14=0,0,AC14/S14) -> 0 | AQ14: =IF(Q14=0,AE14/1,AE14/Q14) -> 0 | AR14: =IF(Q14=0,0,(AF14+AG14)/Q14) -> 0 | AS14: {=_xlfn.IFS(S14=0,AL14,S14<0,AL14/-S14,S14>0,AL14/S14)} -> -37.733516 | AT14: =IF(AN14=0,0,AS14/AN14) -> 0 | AU14: =IF(AO14=0,0,AS14/AO14) -> -0.22210557 | AW14: =AS14*E14 -> -2301.7444
B15: 497824944 | C15: MR Р1886 корич | D15: Солнцезащитные очки | E15: =SUM(F15:H15) -> 34 | H15: 34 | I15: 169.89 | J15: =E15*I15 -> 5776.26 | K15: 531 | L15: 0 | M15: 0 | N15: 0 | O15: =L15/7 -> 0 | P15: =S15/7 -> 0.14285714 | Q15: 1 | R15: 0 | S15: =Q15+R15 -> 1 | T15: 965 | U15: 0 | V15: =T15+U15 -> 965 | W15: 1232 | X15: 0 | Y15: =W15+X15 -> 1232 | Z15: =L15*M15*N15/100 -> 0 | AA15: =Y15/$Y$74 -> 0.021648342 | AB15: =S15*I15 -> 169.89 | AC15: 445.79 | AD15: =IF(Y15=0,0,AC15/Y15) -> 0.36184253 | AE15: 34.8 | AH15: 0 | AI15: =IFERROR($AI$74*H15/$H$74,0) -> 21.744738 | AJ15: 0 | AK15: =V15*1% -> 9.65 | AL15: =Y15-AB15-AC15-AE15-AF15-AG15-AH15-AI15-AK15-AJ15 -> 550.12526 | AN15: =IF(S15=0,0,Y15/S15) -> 1232 | AO15: =I15 -> 169.89 | AP15: =IF(S15=0,0,AC15/S15) -> 445.79 | AQ15: =IF(Q15=0,AE15/1,AE15/Q15) -> 34.8 | AR15: =IF(Q15=0,0,(AF15+AG15)/Q15) -> 0 | AS15: {=_xlfn.IFS(S15=0,AL15,S15<0,AL15/-S15,S15>0,AL15/S15)} -> 550.12526 | AT15: =IF(AN15=0,0,AS15/AN15) -> 0.44653025 | AU15: =IF(AO15=0,0,AS15/AO15) -> 3.2381262 | AW15: =AS15*E15 -> 18704.259
AN16: =AVERAGE(AN3:AN6) -> 603.5 | AO16: =AVERAGE(AO3:AO6) -> 128.0625 | AP16: =AVERAGE(AP3:AP6) -> 218.50682 | AQ16: =AVERAGE(AQ3:AQ6) -> 54.726136 | AR16: =AVERAGE(AR3:AR6) -> 57.005682 | AS16: =AVERAGE(AS3:AS6) -> 11.961244 | AT16: =AVERAGE(AT3:AT6) -> 0.15143003 | AU16: =AVERAGE(AU3:AU6) -> 0.020784006
A17: Итого очки | E17: =SUM(E3:E15) -> 2312 | F17: =SUM(F3:F15) -> 52 | G17: =SUM(G3:G15) -> 10 | H17: =SUM(H3:H15) -> 2250 | J17: =SUM(J3:J15) -> 315658.11 | L17: =SUM(L3:L15) -> 86 | Q17: =SUM(Q3:Q15) -> 49 | R17: =SUM(R3:R15) -> -2 | S17: =SUM(S3:S15) -> 47 | T17: =SUM(T3:T15) -> 44338.88 | U17: =SUM(U3:U15) -> -1888 | V17: =SUM(V3:V15) -> 42450.88 | W17: =SUM(W3:W15) -> 59321.67 | X17: =SUM(X3:X15) -> -2412 | ... AC17: =SUM(AC3:AC15) -> 20543.92 | AD17: =AC17/Y17 -> 0.36099173 | AE17: =SUM(AE3:AE15) -> 6115.35 | AF17: =SUM(AF3:AF15) -> 5916 | AG17: =SUM(AG3:AG15) -> 2033 | AH17: =SUM(AH3:AH15) -> 0 | AI17: =SUM(AI3:AI15) -> 1438.99 | AJ17: =SUM(AJ3:AJ15) -> 0 | AK17: =SUM(AK3:AK15) -> 424.5088 | AL17: =SUM(AL3:AL15) -> 13673.381 | AR17: =(AF17+AG17)/Q17 -> 162.22449 | AW17: =SUM(AW3:AW6) -> 39419.539
E19: =SUM(F19:H19) -> 0 | J19: =E19*I19 -> 0 | O19: =L19/7 -> 0 | P19: =S19/7 -> 0 | S19: =Q19+R19 -> 0 | V19: =T19+U19 -> 0 | Y19: =W19+X19 -> 0 | Z19: =L19*M19*N19/100 -> 0 | AA19: =Y19/$Y$74 -> 0 | AB19: =S19*I19 -> 0 | AD19: =IF(Y19=0,0,AC19/Y19) -> 0 | AI19: =$AI$74*H19/$H$74 -> 0 | AK19: =V19*1% -> 0 | AL19: =Y19-AB19-AC19-AE19-AF19-AG19-AH19-AI19-AK19-AJ19 -> 0 | AN19: =IF(S19=0,0,Y19/S19) -> 0 | AO19: =I19 -> 0 | AP19: =IF(S19=0,0,AC19/S19) -> 0 | AQ19: =IF(Q19=0,AE19/1,AE19/Q19) -> 0 | AR19: =IF(Q19=0,0,(AF19+AG19)/Q19) -> 0 | AS19: {=_xlfn.IFS(S19=0,AL19,S19<0,AL19/-S19,S19>0,AL19/S19)} -> 0 | AT19: =IF(AN19=0,0,AS19/AN19) -> 0 | AU19: =IF(AO19=0,0,AS19/AO19) -> 0 | AW19: =AS19*E19 -> 0
E20: =SUM(F20:H20) -> 0 | J20: =E20*I20 -> 0 | O20: =L20/7 -> 0 | P20: =S20/7 -> 0 | S20: =Q20+R20 -> 0 | V20: =T20+U20 -> 0 | Y20: =W20+X20 -> 0 | Z20: =L20*M20*N20/100 -> 0 | AA20: =Y20/$Y$74 -> 0 | AB20: =S20*I20 -> 0 | AD20: =IF(Y20=0,0,AC20/Y20) -> 0 | AI20: =$AI$74*H20/$H$74 -> 0 | AK20: =V20*1% -> 0 | AL20: =Y20-AB20-AC20-AE20-AF20-AG20-AH20-AI20-AK20-AJ20 -> 0 | AN20: =IF(S20=0,0,Y20/S20) -> 0 | AO20: =I20 -> 0 | AP20: =IF(S20=0,0,AC20/S20) -> 0 | AQ20: =IF(Q20=0,AE20/1,AE20/Q20) -> 0 | AR20: =IF(Q20=0,0,(AF20+AG20)/Q20) -> 0 | AS20: {=_xlfn.IFS(S20=0,AL20,S20<0,AL20/-S20,S20>0,AL20/S20)} -> 0 | AT20: =IF(AN20=0,0,AS20/AN20) -> 0 | AU20: =IF(AO20=0,0,AS20/AO20) -> 0 | AW20: =AS20*E20 -> 0
E21: =SUM(F21:H21) -> 0 | J21: =E21*I21 -> 0 | O21: =L21/7 -> 0 | P21: =S21/7 -> 0 | S21: =Q21+R21 -> 0 | V21: =T21+U21 -> 0 | Y21: =W21+X21 -> 0 | Z21: =L21*M21*N21/100 -> 0 | AA21: =Y21/$Y$74 -> 0 | AB21: =S21*I21 -> 0 | AD21: =IF(Y21=0,0,AC21/Y21) -> 0 | AI21: =$AI$74*H21/$H$74 -> 0 | AK21: =V21*1% -> 0 | AL21: =Y21-AB21-AC21-AE21-AF21-AG21-AH21-AI21-AK21-AJ21 -> 0 | AN21: =IF(S21=0,0,Y21/S21) -> 0 | AO21: =I21 -> 0 | AP21: =IF(S21=0,0,AC21/S21) -> 0 | AQ21: =IF(Q21=0,AE21/1,AE21/Q21) -> 0 | AR21: =IF(Q21=0,0,(AF21+AG21)/Q21) -> 0 | AS21: {=_xlfn.IFS(S21=0,AL21,S21<0,AL21/-S21,S21>0,AL21/S21)} -> 0 | AT21: =IF(AN21=0,0,AS21/AN21) -> 0 | AU21: =IF(AO21=0,0,AS21/AO21) -> 0 | AW21: =AS21*E21 -> 0
E22: =SUM(F22:H22) -> 0 | J22: =E22*I22 -> 0 | O22: =L22/7 -> 0 | P22: =S22/7 -> 0 | S22: =Q22+R22 -> 0 | V22: =T22+U22 -> 0 | Y22: =W22+X22 -> 0 | Z22: =L22*M22*N22/100 -> 0 | AA22: =Y22/$Y$74 -> 0 | AB22: =S22*I22 -> 0 | AD22: =IF(Y22=0,0,AC22/Y22) -> 0 | AI22: =$AI$74*H22/$H$74 -> 0 | AK22: =V22*1% -> 0 | AL22: =Y22-AB22-AC22-AE22-AF22-AG22-AH22-AI22-AK22-AJ22 -> 0 | AN22: =IF(S22=0,0,Y22/S22) -> 0 | AO22: =I22 -> 0 | AP22: =IF(S22=0,0,AC22/S22) -> 0 | AQ22: =IF(Q22=0,AE22/1,AE22/Q22) -> 0 | AR22: =IF(Q22=0,0,(AF22+AG22)/Q22) -> 0 | AS22: {=_xlfn.IFS(S22=0,AL22,S22<0,AL22/-S22,S22>0,AL22/S22)} -> 0 | AT22: =IF(AN22=0,0,AS22/AN22) -> 0 | AU22: =IF(AO22=0,0,AS22/AO22) -> 0 | AW22: =AS22*E22 -> 0
E23: =SUM(F23:H23) -> 0 | J23: =E23*I23 -> 0 | O23: =L23/7 -> 0 | P23: =S23/7 -> 0 | S23: =Q23+R23 -> 0 | V23: =T23+U23 -> 0 | Y23: =W23+X23 -> 0 | Z23: =L23*M23*N23/100 -> 0 | AA23: =Y23/$Y$74 -> 0 | AB23: =S23*I23 -> 0 | AD23: =IF(Y23=0,0,AC23/Y23) -> 0 | AI23: =$AI$74*H23/$H$74 -> 0 | AK23: =V23*1% -> 0 | AL23: =Y23-AB23-AC23-AE23-AF23-AG23-AH23-AI23-AK23-AJ23 -> 0 | AN23: =IF(S23=0,0,Y23/S23) -> 0 | AO23: =I23 -> 0 | AP23: =IF(S23=0,0,AC23/S23) -> 0 | AQ23: =IF(Q23=0,AE23/1,AE23/Q23) -> 0 | AR23: =IF(Q23=0,0,(AF23+AG23)/Q23) -> 0 | AS23: {=_xlfn.IFS(S23=0,AL23,S23<0,AL23/-S23,S23>0,AL23/S23)} -> 0 | AT23: =IF(AN23=0,0,AS23/AN23) -> 0 | AU23: =IF(AO23=0,0,AS23/AO23) -> 0 | AW23: =AS23*E23 -> 0
E24: =SUM(F24:H24) -> 0 | J24: =E24*I24 -> 0 | O24: =L24/7 -> 0 | P24: =S24/7 -> 0 | S24: =Q24+R24 -> 0 | V24: =T24+U24 -> 0 | Y24: =W24+X24 -> 0 | Z24: =L24*M24*N24/100 -> 0 | AA24: =Y24/$Y$74 -> 0 | AB24: =S24*I24 -> 0 | AD24: =IF(Y24=0,0,AC24/Y24) -> 0 | AI24: =$AI$74*H24/$H$74 -> 0 | AK24: =V24*1% -> 0 | AL24: =Y24-AB24-AC24-AE24-AF24-AG24-AH24-AI24-AK24-AJ24 -> 0 | AN24: =IF(S24=0,0,Y24/S24) -> 0 | AO24: =I24 -> 0 | AP24: =IF(S24=0,0,AC24/S24) -> 0 | AQ24: =IF(Q24=0,AE24/1,AE24/Q24) -> 0 | AR24: =IF(Q24=0,0,(AF24+AG24)/Q24) -> 0 | AS24: {=_xlfn.IFS(S24=0,AL24,S24<0,AL24/-S24,S24>0,AL24/S24)} -> 0 | AT24: =IF(AN24=0,0,AS24/AN24) -> 0 | AU24: =IF(AO24=0,0,AS24/AO24) -> 0 | AW24: =AS24*E24 -> 0
E25: =SUM(F25:H25) -> 0 | J25: =E25*I25 -> 0 | O25: =L25/7 -> 0 | P25: =S25/7 -> 0 | S25: =Q25+R25 -> 0 | V25: =T25+U25 -> 0 | Y25: =W25+X25 -> 0 | Z25: =L25*M25*N25/100 -> 0 | AA25: =Y25/$Y$74 -> 0 | AB25: =S25*I25 -> 0 | AD25: =IF(Y25=0,0,AC25/Y25) -> 0 | AI25: =$AI$74*H25/$H$74 -> 0 | AK25: =V25*1% -> 0 | AL25: =Y25-AB25-AC25-AE25-AF25-AG25-AH25-AI25-AK25-AJ25 -> 0 | AN25: =IF(S25=0,0,Y25/S25) -> 0 | AO25: =I25 -> 0 | AP25: =IF(S25=0,0,AC25/S25) -> 0 | AQ25: =IF(Q25=0,AE25/1,AE25/Q25) -> 0 | AR25: =IF(Q25=0,0,(AF25+AG25)/Q25) -> 0 | AS25: {=_xlfn.IFS(S25=0,AL25,S25<0,AL25/-S25,S25>0,AL25/S25)} -> 0 | AT25: =IF(AN25=0,0,AS25/AN25) -> 0 | AU25: =IF(AO25=0,0,AS25/AO25) -> 0 | AW25: =AS25*E25 -> 0
E26: =SUM(F26:H26) -> 0 | J26: =E26*I26 -> 0 | O26: =L26/7 -> 0 | P26: =S26/7 -> 0 | S26: =Q26+R26 -> 0 | V26: =T26+U26 -> 0 | Y26: =W26+X26 -> 0 | Z26: =L26*M26*N26/100 -> 0 | AA26: =Y26/$Y$74 -> 0 | AB26: =S26*I26 -> 0 | AD26: =IF(Y26=0,0,AC26/Y26) -> 0 | AI26: =$AI$74*H26/$H$74 -> 0 | AK26: =V26*1% -> 0 | AL26: =Y26-AB26-AC26-AE26-AF26-AG26-AH26-AI26-AK26-AJ26 -> 0 | AN26: =IF(S26=0,0,Y26/S26) -> 0 | AO26: =I26 -> 0 | AP26: =IF(S26=0,0,AC26/S26) -> 0 | AQ26: =IF(Q26=0,AE26/1,AE26/Q26) -> 0 | AR26: =IF(Q26=0,0,(AF26+AG26)/Q26) -> 0 | AS26: {=_xlfn.IFS(S26=0,AL26,S26<0,AL26/-S26,S26>0,AL26/S26)} -> 0 | AT26: =IF(AN26=0,0,AS26/AN26) -> 0 | AU26: =IF(AO26=0,0,AS26/AO26) -> 0 | AW26: =AS26*E26 -> 0
E27: =SUM(F27:H27) -> 0 | J27: =E27*I27 -> 0 | O27: =L27/7 -> 0 | P27: =S27/7 -> 0 | S27: =Q27+R27 -> 0 | V27: =T27+U27 -> 0 | Y27: =W27+X27 -> 0 | Z27: =L27*M27*N27/100 -> 0 | AA27: =Y27/$Y$74 -> 0 | AB27: =S27*I27 -> 0 | AD27: =IF(Y27=0,0,AC27/Y27) -> 0 | AI27: =$AI$74*H27/$H$74 -> 0 | AK27: =V27*1% -> 0 | AL27: =Y27-AB27-AC27-AE27-AF27-AG27-AH27-AI27-AK27-AJ27 -> 0 | AN27: =IF(S27=0,0,Y27/S27) -> 0 | AO27: =I27 -> 0 | AP27: =IF(S27=0,0,AC27/S27) -> 0 | AQ27: =IF(Q27=0,AE27/1,AE27/Q27) -> 0 | AR27: =IF(Q27=0,0,(AF27+AG27)/Q27) -> 0 | AS27: {=_xlfn.IFS(S27=0,AL27,S27<0,AL27/-S27,S27>0,AL27/S27)} -> 0 | AT27: =IF(AN27=0,0,AS27/AN27) -> 0 | AU27: =IF(AO27=0,0,AS27/AO27) -> 0 | AW27: =AS27*E27 -> 0
E28: =SUM(F28:H28) -> 0 | J28: =E28*I28 -> 0 | O28: =L28/7 -> 0 | P28: =S28/7 -> 0 | S28: =Q28+R28 -> 0 | V28: =T28+U28 -> 0 | Y28: =W28+X28 -> 0 | Z28: =L28*M28*N28/100 -> 0 | AA28: =Y28/$Y$74 -> 0 | AB28: =S28*I28 -> 0 | AD28: =IF(Y28=0,0,AC28/Y28) -> 0 | AI28: =$AI$74*H28/$H$74 -> 0 | AK28: =V28*1% -> 0 | AL28: =Y28-AB28-AC28-AE28-AF28-AG28-AH28-AI28-AK28-AJ28 -> 0 | AN28: =IF(S28=0,0,Y28/S28) -> 0 | AO28: =I28 -> 0 | AP28: =IF(S28=0,0,AC28/S28) -> 0 | AQ28: =IF(Q28=0,AE28/1,AE28/Q28) -> 0 | AR28: =IF(Q28=0,0,(AF28+AG28)/Q28) -> 0 | AS28: {=_xlfn.IFS(S28=0,AL28,S28<0,AL28/-S28,S28>0,AL28/S28)} -> 0 | AT28: =IF(AN28=0,0,AS28/AN28) -> 0 | AU28: =IF(AO28=0,0,AS28/AO28) -> 0 | AW28: =AS28*E28 -> 0
E29: =SUM(F29:H29) -> 0 | J29: =E29*I29 -> 0 | O29: =L29/7 -> 0 | P29: =S29/7 -> 0 | S29: =Q29+R29 -> 0 | V29: =T29+U29 -> 0 | Y29: =W29+X29 -> 0 | Z29: =L29*M29*N29/100 -> 0 | AA29: =Y29/$Y$74 -> 0 | AB29: =S29*I29 -> 0 | AD29: =IF(Y29=0,0,AC29/Y29) -> 0 | AI29: =$AI$74*H29/$H$74 -> 0 | AK29: =V29*1% -> 0 | AL29: =Y29-AB29-AC29-AE29-AF29-AG29-AH29-AI29-AK29-AJ29 -> 0 | AN29: =IF(S29=0,0,Y29/S29) -> 0 | AO29: =I29 -> 0 | AP29: =IF(S29=0,0,AC29/S29) -> 0 | AQ29: =IF(Q29=0,AE29/1,AE29/Q29) -> 0 | AR29: =IF(Q29=0,0,(AF29+AG29)/Q29) -> 0 | AS29: {=_xlfn.IFS(S29=0,AL29,S29<0,AL29/-S29,S29>0,AL29/S29)} -> 0 | AT29: =IF(AN29=0,0,AS29/AN29) -> 0 | AU29: =IF(AO29=0,0,AS29/AO29) -> 0 | AW29: =AS29*E29 -> 0
E30: =SUM(F30:H30) -> 0 | J30: =E30*I30 -> 0 | O30: =L30/7 -> 0 | P30: =S30/7 -> 0 | S30: =Q30+R30 -> 0 | V30: =T30+U30 -> 0 | Y30: =W30+X30 -> 0 | Z30: =L30*M30*N30/100 -> 0 | AA30: =Y30/$Y$74 -> 0 | AB30: =S30*I30 -> 0 | AD30: =IF(Y30=0,0,AC30/Y30) -> 0 | AI30: =$AI$74*H30/$H$74 -> 0 | AK30: =V30*1% -> 0 | AL30: =Y30-AB30-AC30-AE30-AF30-AG30-AH30-AI30-AK30-AJ30 -> 0 | AN30: =IF(S30=0,0,Y30/S30) -> 0 | AO30: =I30 -> 0 | AP30: =IF(S30=0,0,AC30/S30) -> 0 | AQ30: =IF(Q30=0,AE30/1,AE30/Q30) -> 0 | AR30: =IF(Q30=0,0,(AF30+AG30)/Q30) -> 0 | AS30: {=_xlfn.IFS(S30=0,AL30,S30<0,AL30/-S30,S30>0,AL30/S30)} -> 0 | AT30: =IF(AN30=0,0,AS30/AN30) -> 0 | AU30: =IF(AO30=0,0,AS30/AO30) -> 0 | AW30: =AS30*E30 -> 0
... E70: =SUM(F70:H70) -> 0 | J70: =E70*I70 -> 0 | O70: =L70/7 -> 0 | P70: =S70/7 -> 0 | S70: =Q70+R70 -> 0 | V70: =T70+U70 -> 0 | Y70: =W70+X70 -> 0 | Z70: =L70*M70*N70/100 -> 0 | AA70: =Y70/$Y$74 -> 0 | AB70: =S70*I70 -> 0 | AD70: =IF(Y70=0,0,AC70/Y70) -> 0 | AI70: =$AI$74*H70/$H$74 -> 0 | AK70: =V70*1% -> 0 | AL70: =Y70-AB70-AC70-AE70-AF70-AG70-AH70-AI70-AK70-AJ70 -> 0 | AN70: =IF(S70=0,0,Y70/S70) -> 0 | AO70: =I70 -> 0 | AP70: =IF(S70=0,0,AC70/S70) -> 0 | AQ70: =IF(Q70=0,AE70/1,AE70/Q70) -> 0 | AR70: =IF(Q70=0,0,(AF70+AG70)/Q70) -> 0 | AS70: {=_xlfn.IFS(S70=0,AL70,S70<0,AL70/-S70,S70>0,AL70/S70)} -> 0 | AT70: =IF(AN70=0,0,AS70/AN70) -> 0 | AU70: =IF(AO70=0,0,AS70/AO70) -> 0 | AW70: =AS70*E70 -> 0
AN71: =AVERAGE(AN19:AN70) -> 0 | AO71: =AVERAGE(AO19:AO70) -> 0 | AP71: =AVERAGE(AP19:AP70) -> 0 | AQ71: =AVERAGE(AQ19:AQ70) -> 0 | AR71: =AVERAGE(AR19:AR70) -> 0 | AS71: =AVERAGE(AS19:AS70) -> 0 | AT71: =AVERAGE(AT19:AT70) -> 0 | AU71: =AVERAGE(AU19:AU70) -> 0
A72: Итого ___ | E72: =SUM(E19:E70) -> 0 | F72: =SUM(F19:F70) -> 0 | G72: =SUM(G19:G70) -> 0 | H72: =SUM(H19:H70) -> 0 | J72: =SUM(J19:J70) -> 0 | L72: =SUM(L19:L70) -> 0 | Q72: =SUM(Q19:Q70) -> 0 | R72: =SUM(R19:R70) -> 0 | S72: =SUM(S19:S70) -> 0 | T72: =SUM(T19:T70) -> 0 | U72: =SUM(U19:U70) -> 0 | V72: =SUM(V19:V70) -> 0 | W72: =SUM(W19:W70) -> 0 | X72: =SUM(X19:X70) -> 0 | ... AC72: =SUM(AC19:AC70) -> 0 | AD72: =AC72/Y72 -> #DIV/0! | AE72: =SUM(AE19:AE70) -> 0 | AF72: =SUM(AF19:AF70) -> 0 | AG72: =SUM(AG19:AG70) -> 0 | AH72: =SUM(AH19:AH70) -> 0 | AI72: =SUM(AI19:AI70) -> 0 | AJ72: =SUM(AJ19:AJ70) -> 0 | AK72: =SUM(AK19:AK70) -> 0 | AL72: =SUM(AL19:AL70) -> 0 | AR72: =(AF72+AG72)/Q72 -> #DIV/0! | AW72: =SUM(AW19:AW70) -> 0
A74: ИТОГО | E74: =E17+E72 -> 2312 | F74: =F17+F72 -> 52 | G74: =G17+G72 -> 10 | H74: =H17+H72 -> 2250 | I74: =I17+I72 -> 0 | J74: =J17+J72 -> 315658.11 | K74: =K17+K72 -> 0 | L74: =L17+L72 -> 86 | ... AC74: =AC17+AC72 -> 20543.92 | AD74: =AC74/Y74 -> 0.36099173 | AE74: =AE17+AE72 -> 6115.35 | AF74: =AF17+AF72 -> 5916 | AG74: =AG17+AG72 -> 2033 | AH74: =AH17+AH72 -> 0 | AI74: 1438.99 | AJ74: =AJ17+AJ72 -> 0 | AK74: =AK17+AK72 -> 424.5088 | AL74: =AL17+AL72 -> 13673.381 | AR74: =(AF74+AG74)/Q74 -> 162.22449 | AW74: =AW17+AW72 -> 39419.539
AF75: =AF18+AF73 -> 0

Sheet Юнит 3
A1: 12-18.01_3 нед | F1: Отчет по остаткам 3,4,5 | K1: Цены и скидки 6 | L1: Воронка продаж 16,50,32 | AI1: Вставить в Итого | AN1: на 1 единицу проданного товара
A2: Бренд | B2: SKU | C2: Артикул поставщика | D2: Предмет | E2: Остаток на | F2: В пути до клиента | G2: В пути от клиента | H2: Итого по складам ВБ | I2: Себетоимость на 1 ед на 29.09.25 | J2: Себестоимость остатков | K2: Оборачива-емость, дн | L2: Заказы, шт 7 дней | M2: Средняя цена, руб | N2: % выкупа за 7 дней | O2: Скорость заказов | P2: Скорость продаж | Q2: Кол-во ПРОДАЖИ | R2: Кол-во ВОЗВРАТЫ | S2: Кол-во ПРОДАЖИ-ВОЗВРАТЫ | T2: Выручка ВБ ПРОДАЖИ | U2: Выручка ВБ ВОЗВРАТЫ | V2: Выручка с учетом СПП ПРОДАЖИ - ВОЗВРАТЫ | W2: Выручка ПРОДАЖИ | X2: Выручка ВОЗВРАТЫ | Y2: Выручка с учетом согласованной скидки ПРОДАЖИ - ВОЗВРАТЫ | Z2: Выручка потенциальная | AA2: Доля выручки, % от общего объема | AB2: Себестоимость продаж | AC2: Комиссия, руб | AD2: Комиссия, % | AE2: Логистика | AF2: Реклама БАЛАНС | AG2: Реклама СЧЕТ | AH2: Блогеры | AI2: Хранение | AJ2: Штрафы | AK2: Налог 1% | AL2: Прибыль | AN2: Выручка на 1 ед (средняя цена продажи со скидкой) | AO2: Себестоимость на 1 ед | AP2: Комиссия на 1 ед | AQ2: Логистика на 1 ед | AR2: Реклама на 1 ед | AS2: Прибыль на 1 ед | AT2: Маржиналь-ность, % | AU2: Рентабель-ность, % | AW2: Прибыль с остатков
B3: 341479791 | C3: Черные с железкой Сул | D3: Солнцезащитные очки | E3: =SUM(F3:H3) -> 430 | F3: 19 | G3: 2 | H3: 409 | I3: 142.98 | J3: =E3*I3 -> 61481.4 | K3: 262 | L3: 21 | M3: 1238 | N3: 80 | O3: =L3/7 -> 3 | P3: =S3/7 -> 1.4285714 | Q3: 10 | R3: 0 | S3: =Q3+R3 -> 10 | T3: 10062.05 | U3: 0 | V3: =T3+U3 -> 10062.05 | W3: 12442.27 | X3: 0 | Y3: =W3+X3 -> 12442.27 | Z3: =L3*M3*N3/100 -> 20798.4 | AA3: =Y3/$Y$74 -> 0.22319679 | AB3: =S3*I3 -> 1429.8 | AC3: 4457.02 | AD3: =IF(Y3=0,0,AC3/Y3) -> 0.35821598 | AE3: 1259.15 | AF3: 1000 | AG3: 1196 | AI3: =IFERROR($AI$74*H3/$H$74,0) -> 242.77555 | AJ3: 0 | AK3: =V3*1% -> 100.6205 | AL3: =Y3-AB3-AC3-AE3-AF3-AG3-AH3-AI3-AK3-AJ3 -> 2756.9039 | AN3: =IF(S3=0,0,Y3/S3) -> 1244.227 | AO3: =I3 -> 142.98 | AP3: =IF(S3=0,0,AC3/S3) -> 445.702 | AQ3: =IF(Q3=0,AE3/1,AE3/Q3) -> 125.915 | AR3: =IF(Q3=0,0,(AF3+AG3)/Q3) -> 219.6 | AS3: =_xlfn.IFS(S3=0,AL3,S3<0,AL3/-S3,S3>0,AL3/S3) -> 275.69039 | AT3: =IF(AN3=0,0,AS3/AN3) -> 0.22157564 | AU3: =IF(AO3=0,0,AS3/AO3) -> 1.9281745 | AW3: =AS3*E3 -> 118546.87
B4: 340343575 | C4: Qs черн Сул | D4: Солнцезащитные очки | E4: =SUM(F4:H4) -> 289 | G4: 2 | H4: 287 | I4: 123.09 | J4: =E4*I4 -> 35573.01 | K4: 999 | L4: 0 | M4: 0 | N4: 0 | O4: =L4/7 -> 0 | P4: =S4/7 -> 0 | Q4: 0 | R4: 0 | S4: =Q4+R4 -> 0 | T4: 0 | U4: 0 | V4: =T4+U4 -> 0 | W4: 0 | X4: 0 | Y4: =W4+X4 -> 0 | Z4: =L4*M4*N4/100 -> 0 | AA4: =Y4/$Y$74 -> 0 | AB4: =S4*I4 -> 0 | AC4: 0 | AD4: =IF(Y4=0,0,AC4/Y4) -> 0 | AE4: 0 | AI4: =IFERROR($AI$74*H4/$H$74,0) -> 170.3584 | AJ4: 0 | AK4: =V4*1% -> 0 | AL4: =Y4-AB4-AC4-AE4-AF4-AG4-AH4-AI4-AK4-AJ4 -> -170.3584 | AN4: =IF(S4=0,0,Y4/S4) -> 0 | AO4: =I4 -> 123.09 | AP4: =IF(S4=0,0,AC4/S4) -> 0 | AQ4: =IF(Q4=0,AE4/1,AE4/Q4) -> 0 | AR4: =IF(Q4=0,0,(AF4+AG4)/Q4) -> 0 | AS4: {=_xlfn.IFS(S4=0,AL4,S4<0,AL4/-S4,S4>0,AL4/S4)} -> -170.3584 | AT4: =IF(AN4=0,0,AS4/AN4) -> 0 | AU4: =IF(AO4=0,0,AS4/AO4) -> -1.3840149 | AW4: =AS4*E4 -> -49233.576
B5: 340332621 | C5: Qs син Сул | D5: Солнцезащитные очки | E5: =SUM(F5:H5) -> 378 | H5: 378 | I5: 123.09 | J5: =E5*I5 -> 46528.02 | K5: 999 | L5: 0 | M5: 0 | N5: 0 | O5: =L5/7 -> 0 | P5: =S5/7 -> 0.14285714 | Q5: 1 | R5: 0 | S5: =Q5+R5 -> 1 | T5: 0 | U5: 0 | V5: =T5+U5 -> 0 | W5: 0 | X5: 0 | Y5: =W5+X5 -> 0 | Z5: =L5*M5*N5/100 -> 0 | AA5: =Y5/$Y$74 -> 0 | AB5: =S5*I5 -> 123.09 | AC5: -817.91 | AD5: =IF(Y5=0,0,AC5/Y5) -> 0 | AE5: 0 | AI5: =IFERROR($AI$74*H5/$H$74,0) -> 224.37447 | AJ5: 0 | AK5: =V5*1% -> 0 | AL5: =Y5-AB5-AC5-AE5-AF5-AG5-AH5-AI5-AK5-AJ5 -> 470.44553 | AN5: =IF(S5=0,0,Y5/S5) -> 0 | AO5: =I5 -> 123.09 | AP5: =IF(S5=0,0,AC5/S5) -> -817.91 | AQ5: =IF(Q5=0,AE5/1,AE5/Q5) -> 0 | AR5: =IF(Q5=0,0,(AF5+AG5)/Q5) -> 0 | AS5: {=_xlfn.IFS(S5=0,AL5,S5<0,AL5/-S5,S5>0,AL5/S5)} -> 470.44553 | AT5: =IF(AN5=0,0,AS5/AN5) -> 0 | AU5: =IF(AO5=0,0,AS5/AO5) -> 3.8219638 | AW5: =AS5*E5 -> 177828.41
B6: 340341838 | C6: Qs желт Сул | D6: Солнцезащитные очки | E6: =SUM(F6:H6) -> 355 | F6: 4 | G6: 2 | H6: 349 | I6: 123.09 | J6: =E6*I6 -> 43696.95 | K6: 564 | L6: 4 | M6: 1114 | N6: 100 | O6: =L6/7 -> 0.57142857 | P6: =S6/7 -> 0.85714286 | Q6: 6 | R6: 0 | S6: =Q6+R6 -> 6 | T6: 5408 | U6: 0 | V6: =T6+U6 -> 5408 | W6: 6746 | X6: 0 | Y6: =W6+X6 -> 6746 | Z6: =L6*M6*N6/100 -> 4456 | AA6: =Y6/$Y$74 -> 0.12101373 | AB6: =S6*I6 -> 738.54 | AC6: 2452.45 | AD6: =IF(Y6=0,0,AC6/Y6) -> 0.36354136 | AE6: 654.6 | AF6: 409 | AG6: 411 | AI6: =IFERROR($AI$74*H6/$H$74,0) -> 207.16056 | AJ6: 0 | AK6: =V6*1% -> 54.08 | AL6: =Y6-AB6-AC6-AE6-AF6-AG6-AH6-AI6-AK6-AJ6 -> 1819.1694 | AN6: =IF(S6=0,0,Y6/S6) -> 1124.3333 | AO6: =I6 -> 123.09 | AP6: =IF(S6=0,0,AC6/S6) -> 408.74167 | AQ6: =IF(Q6=0,AE6/1,AE6/Q6) -> 109.1 | AR6: =IF(Q6=0,0,(AF6+AG6)/Q6) -> 136.66667 | AS6: {=_xlfn.IFS(S6=0,AL6,S6<0,AL6/-S6,S6>0,AL6/S6)} -> 303.19491 | AT6: =IF(AN6=0,0,AS6/AN6) -> 0.26966639 | AU6: =IF(AO6=0,0,AS6/AO6) -> 2.4631969 | AW6: =AS6*E6 -> 107634.19
B7: 445291724 | C7: flip черные Сул | D7: Солнцезащитные очки | E7: =SUM(F7:H7) -> 285 | F7: 1 | G7: 1 | H7: 283 | I7: 123.09 | J7: =E7*I7 -> 35080.65 | K7: 999 | L7: 2 | M7: 1079 | N7: 0 | O7: =L7/7 -> 0.28571429 | P7: =S7/7 -> 0 | Q7: 0 | R7: 0 | S7: =Q7+R7 -> 0 | T7: 0 | U7: 0 | V7: =T7+U7 -> 0 | W7: 0 | X7: 0 | Y7: =W7+X7 -> 0 | Z7: =L7*M7*N7/100 -> 0 | AA7: =Y7/$Y$74 -> 0 | AB7: =S7*I7 -> 0 | AC7: 0 | AD7: =IF(Y7=0,0,AC7/Y7) -> 0 | AE7: 96.4 | AG7: 29 | AI7: =IFERROR($AI$74*H7/$H$74,0) -> 167.98406 | AJ7: 0 | AK7: =V7*1% -> 0 | AL7: =Y7-AB7-AC7-AE7-AF7-AG7-AH7-AI7-AK7-AJ7 -> -293.38406 | AN7: =IF(S7=0,0,Y7/S7) -> 0 | AO7: =I7 -> 123.09 | AP7: =IF(S7=0,0,AC7/S7) -> 0 | AQ7: =IF(Q7=0,AE7/1,AE7/Q7) -> 96.4 | AR7: =IF(Q7=0,0,(AF7+AG7)/Q7) -> 0 | AS7: {=_xlfn.IFS(S7=0,AL7,S7<0,AL7/-S7,S7>0,AL7/S7)} -> -293.38406 | AT7: =IF(AN7=0,0,AS7/AN7) -> 0 | AU7: =IF(AO7=0,0,AS7/AO7) -> -2.3834923 | AW7: =AS7*E7 -> -83614.458
B8: 445336740 | C8: flip желтые Сул | D8: Солнцезащитные очки | E8: =SUM(F8:H8) -> 123 | F8: 10 | G8: 4 | H8: 109 | I8: 123.09 | J8: =E8*I8 -> 15140.07 | K8: 37 | L8: 16 | M8: 1191 | N8: 88 | O8: =L8/7 -> 2.2857143 | P8: =S8/7 -> 3.1428571 | Q8: 22 | R8: 0 | S8: =Q8+R8 -> 22 | T8: 21017.42 | U8: 0 | V8: =T8+U8 -> 21017.42 | W8: 26020.47 | X8: 0 | Y8: =W8+X8 -> 26020.47 | Z8: =L8*M8*N8/100 -> 16769.28 | AA8: =Y8/$Y$74 -> 0.46677056 | AB8: =S8*I8 -> 2707.98 | AC8: 9396.67 | AD8: =IF(Y8=0,0,AC8/Y8) -> 0.36112607 | AE8: 2224.2 | AF8: 1362 | AG8: 638 | AI8: =IFERROR($AI$74*H8/$H$74,0) -> 64.700575 | AJ8: 0 | AK8: =V8*1% -> 210.1742 | AL8: =Y8-AB8-AC8-AE8-AF8-AG8-AH8-AI8-AK8-AJ8 -> 9416.7452 | AN8: =IF(S8=0,0,Y8/S8) -> 1182.7486 | AO8: =I8 -> 123.09 | AP8: =IF(S8=0,0,AC8/S8) -> 427.12136 | AQ8: =IF(Q8=0,AE8/1,AE8/Q8) -> 101.1 | AR8: =IF(Q8=0,0,(AF8+AG8)/Q8) -> 90.909091 | AS8: {=_xlfn.IFS(S8=0,AL8,S8<0,AL8/-S8,S8>0,AL8/S8)} -> 428.03387 | AT8: =IF(AN8=0,0,AS8/AN8) -> 0.36189758 | AU8: =IF(AO8=0,0,AS8/AO8) -> 3.4774058 | AW8: =AS8*E8 -> 52648.166
B9: 445341507 | C9: MR8854 C2 Сул | D9: Солнцезащитные очки | E9: =SUM(F9:H9) -> 268 | F9: 7 | G9: 1 | H9: 260 | I9: 169.89 | J9: =E9*I9 -> 45530.52 | K9: 569 | L9: 6 | M9: 1183 | N9: 100 | O9: =L9/7 -> 0.85714286 | P9: =S9/7 -> 0.42857143 | Q9: 4 | R9: -1 | S9: =Q9+R9 -> 3 | T9: 3752 | U9: -948 | V9: =T9+U9 -> 2804 | W9: 4696 | X9: -1174 | Y9: =W9+X9 -> 3522 | Z9: =L9*M9*N9/100 -> 7098 | AA9: =Y9/$Y$74 -> 0.063179716 | AB9: =S9*I9 -> 509.67 | AC9: 1275.39 | AD9: =IF(Y9=0,0,AC9/Y9) -> 0.36212095 | AE9: 779.95 | AF9: 151 | AG9: 1190 | AI9: =IFERROR($AI$74*H9/$H$74,0) -> 154.33165 | AJ9: 0 | AK9: =V9*1% -> 28.04 | AL9: =Y9-AB9-AC9-AE9-AF9-AG9-AH9-AI9-AK9-AJ9 -> -566.38165 | AN9: =IF(S9=0,0,Y9/S9) -> 1174 | AO9: =I9 -> 169.89 | AP9: =IF(S9=0,0,AC9/S9) -> 425.13 | AQ9: =IF(Q9=0,AE9/1,AE9/Q9) -> 194.9875 | AR9: =IF(Q9=0,0,(AF9+AG9)/Q9) -> 335.25 | AS9: {=_xlfn.IFS(S9=0,AL9,S9<0,AL9/-S9,S9>0,AL9/S9)} -> -188.79388 | AT9: =IF(AN9=0,0,AS9/AN9) -> -0.16081251 | AU9: =IF(AO9=0,0,AS9/AO9) -> -1.1112713 | AW9: =AS9*E9 -> -50596.761
