Workbook

Sheet Сводная
A1: Период | D1: Дата поступления дс | E1: Итого к перечислению на счет, руб | F1: шт. | I1: Выручка | L1: Себестоимость продаж | M1: Логистика | N1: Комиссия | O1: Хранение | P1: Платная приемка | Q1: Штрафы | R1: Реклама Ozon | S1: Прочее | T1: Доп. услуги | U1: Услуги FBO | V1: Компенсировано | W1: Пополнение рекламного кабинета | X1: Прочие начисления | Y1: Налог | Z1: Итого | AA1: Итог месяц | AB1: % Cебестоимости | AC1: Маржинальность, % | AD1: Рентабельность, % | AE1: Доля рекламы, % | AG1: Данные для построения диаграмм
A2: Месяц | B2: Даты | C2: Нед | F2: Заказы | G2: Продажи | H2: Возвраты | I2: Продажи | J2: Возвраты | K2: Общая | AG2: Нед | AH2: По магазину | AI2: По очкам | AJ2: По туникам
A3: Январь | B3: 01-04.01 очки | E3: =K3-SUM(M3:U3)+V3+W3+X3 -> 6689.7486 | F3: ='Юнит 01-04.01'!K$26 -> 44 | G3: ='Юнит 01-04.01'!P$26 -> 28 | H3: ='Юнит 01-04.01'!Q$26 -> 0 | I3: ='Юнит 01-04.01'!S$26 -> 45978 | J3: ='Юнит 01-04.01'!T$26 -> 0 | K3: =I3+J3 -> 45978 | L3: ='Юнит 01-04.01'!W$26 -> 4528.66 | M3: ='Юнит 01-04.01'!Z$26 -> 3709.34 | N3: ='Юнит 01-04.01'!X$26 -> 19770.54 | R3: ='Юнит 01-04.01'!AA$26 -> 14387.481 | T3: 808.39 | U3: 612.5 | Y3: =(K3)*0.01 -> 459.78 | Z3: =K3-SUM(M3:U3)-L3-Y3+V3+X3 -> 1701.3086 | AA3: =SUM(Z3:Z12) -> 33354.59 | AB3: =L3/K3 -> 0.098496237 | AC3: =Z3/L3 -> 0.37567594 | AD3: =Z3/K3 -> 0.037002667 | AE3: =R3/K3 -> 0.31292099
B4: 01-04.01 туники | E4: =K4-SUM(M4:U4)+V4+W4+X4 -> 1720.7514 | F4: ='Юнит 01-04.01'!K$49 -> 5 | G4: ='Юнит 01-04.01'!P$49 -> 1 | H4: ='Юнит 01-04.01'!Q$49 -> 0 | I4: ='Юнит 01-04.01'!S$49 -> 4247 | J4: ='Юнит 01-04.01'!T$49 -> 0 | K4: =I4+J4 -> 4247 | L4: ='Юнит 01-04.01'!W$49 -> 597 | M4: ='Юнит 01-04.01'!Z$49 -> 186.2 | N4: ='Юнит 01-04.01'!X$49 -> 1826.21 | R4: ='Юнит 01-04.01'!AA$49 -> 513.83862 | Y4: =(K4)*0.01 -> 42.47 | Z4: =K4-SUM(M4:U4)-L4-Y4+V4+X4 -> 1081.2814 | AB4: =L4/K4 -> 0.14056981 | AC4: =Z4/L4 -> 1.8111916 | AD4: =Z4/K4 -> 0.25459886 | AE4: =R4/K4 -> 0.12098861
B5: 05-11.01 очки | E5: =K5-SUM(M5:U5)+V5+W5+X5 -> 15120.024 | F5: ='Юнит 05-11.01'!K$26 -> 74 | G5: ='Юнит 05-11.01'!P$26 -> 58 | H5: ='Юнит 05-11.01'!Q$26 -> 4 | I5: ='Юнит 05-11.01'!S$26 -> 92160 | J5: ='Юнит 05-11.01'!T$26 -> -6799 | K5: =I5+J5 -> 85361 | L5: ='Юнит 05-11.01'!W$26 -> 7651.8 | M5: ='Юнит 05-11.01'!Z$26 -> 9950.27 | N5: ='Юнит 05-11.01'!X$26 -> 36705.23 | R5: ='Юнит 05-11.01'!AA$26 -> 20346.216 | S5: 5 | T5: 1918.46 | U5: 1315.8 | Y5: =(K5)*0.01 -> 853.61 | Z5: =K5-SUM(M5:U5)-L5-Y5+V5+X5 -> 6614.6137 | AB5: =L5/K5 -> 0.089640468 | AC5: =Z5/L5 -> 0.86445198 | AD5: =Z5/K5 -> 0.07748988 | AE5: =R5/K5 -> 0.23835494
B6: 05-11.01 туники | E6: =K6-SUM(M6:U6)+V6+W6+X6 -> 4389.7863 | F6: ='Юнит 05-11.01'!K$49 -> 4 | G6: ='Юнит 05-11.01'!P$49 -> 2 | H6: ='Юнит 05-11.01'!Q$49 -> 0 | I6: ='Юнит 05-11.01'!S$49 -> 10524 | J6: ='Юнит 05-11.01'!T$49 -> 0 | K6: =I6+J6 -> 10524 | L6: ='Юнит 05-11.01'!W$49 -> 1329 | M6: ='Юнит 05-11.01'!Z$49 -> 907.3 | N6: ='Юнит 05-11.01'!X$49 -> 4525.32 | R6: ='Юнит 05-11.01'!AA$49 -> 701.59367 | Y6: =(K6)*0.01 -> 105.24 | Z6: =K6-SUM(M6:U6)-L6-Y6+V6+X6 -> 2955.5463 | AB6: =L6/K6 -> 0.12628278 | AC6: =Z6/L6 -> 2.2238874 | AD6: =Z6/K6 -> 0.28083869 | AE6: =R6/K6 -> 0.066666065
B7: 12-18.01 очки | E7: =K7-SUM(M7:U7)+V7+W7+X7 -> 23997.298 | F7: ='Юнит 12-18.01'!K$26 -> 96 | G7: ='Юнит 12-18.01'!P$26 -> 56 | H7: ='Юнит 12-18.01'!Q$26 -> 0 | I7: ='Юнит 12-18.01'!S$26 -> 91762 | J7: ='Юнит 12-18.01'!T$26 -> 0 | K7: =I7+J7 -> 91762 | L7: ='Юнит 12-18.01'!W$26 -> 7841.91 | M7: ='Юнит 12-18.01'!Z$26 -> 9811.64 | N7: ='Юнит 12-18.01'!X$26 -> 39457.66 | R7: ='Юнит 12-18.01'!AA$26 -> 22526.532 | T7: 2168.87 | U7: 800 | W7: 7000 | Y7: =(K7)*0.01 -> 917.62 | Z7: =K7-SUM(M7:U7)-L7-Y7+V7+X7 -> 8237.7675 | AB7: =L7/K7 -> 0.085459231 | AC7: =Z7/L7 -> 1.0504797 | AD7: =Z7/K7 -> 0.089773191 | AE7: =R7/K7 -> 0.24548868
B8: 12-18.01 туники | E8: =K8-SUM(M8:U8)+V8+W8+X8 -> 8441.1125 | F8: ='Юнит 12-18.01'!K$49 -> 30 | G8: ='Юнит 12-18.01'!P$49 -> 5 | H8: ='Юнит 12-18.01'!Q$49 -> 0 | I8: ='Юнит 12-18.01'!S$49 -> 21020 | J8: ='Юнит 12-18.01'!T$49 -> 0 | K8: =I8+J8 -> 21020 | L8: ='Юнит 12-18.01'!W$49 -> 3435 | M8: ='Юнит 12-18.01'!Z$49 -> 1528.99 | N8: ='Юнит 12-18.01'!X$49 -> 9038.6 | R8: ='Юнит 12-18.01'!AA$49 -> 2011.2975 | Y8: =(K8)*0.01 -> 210.2 | Z8: =K8-SUM(M8:U8)-L8-Y8+V8+X8 -> 4795.9125 | AB8: =L8/K8 -> 0.16341579 | AC8: =Z8/L8 -> 1.3961899 | AD8: =Z8/K8 -> 0.22815949 | AE8: =R8/K8 -> 0.095684945
B9: 19-25.01 очки | E9: =K9-SUM(M9:U9)+V9+W9+X9 -> 15283.413 | F9: ='Юнит 19-25.01'!K$26 -> 119 | G9: ='Юнит 19-25.01'!P$26 -> 64 | H9: ='Юнит 19-25.01'!Q$26 -> 1 | I9: ='Юнит 19-25.01'!S$26 -> 104586 | J9: ='Юнит 19-25.01'!T$26 -> -1670 | K9: =I9+J9 -> 102916 | L9: ='Юнит 19-25.01'!W$26 -> 9494.98 | M9: ='Юнит 19-25.01'!Z$26 -> 12870.13 | N9: ='Юнит 19-25.01'!X$26 -> 44253.88 | R9: ='Юнит 19-25.01'!AA$26 -> 31721.257 | S9: 15 | T9: 3536.42 | U9: 2235.9 | W9: 7000 | Y9: =(K9)*0.01 -> 1029.16 | Z9: =K9-SUM(M9:U9)-L9-Y9+V9+X9 -> -2240.7266 | AB9: =L9/K9 -> 0.092259513 | AC9: =Z9/L9 -> -0.23599066 | AD9: =Z9/K9 -> -0.021772383 | AE9: =R9/K9 -> 0.30822473
B10: 19-25.01 туники | E10: =K10-SUM(M10:U10)+V10+W10+X10 -> 20301.697 | F10: ='Юнит 19-25.01'!K$49 -> 66 | G10: ='Юнит 19-25.01'!P$49 -> 18 | H10: ='Юнит 19-25.01'!Q$49 -> 4 | I10: ='Юнит 19-25.01'!S$49 -> 80413 | J10: ='Юнит 19-25.01'!T$49 -> -17932 | K10: =I10+J10 -> 62481 | L10: ='Юнит 19-25.01'!W$49 -> 9468 | M10: ='Юнит 19-25.01'!Z$49 -> 6390.87 | N10: ='Юнит 19-25.01'!X$49 -> 26866.83 | R10: ='Юнит 19-25.01'!AA$49 -> 8921.6034 | Y10: =(K10)*0.01 -> 624.81 | Z10: =K10-SUM(M10:U10)-L10-Y10+V10+X10 -> 10208.887 | AB10: =L10/K10 -> 0.15153407 | AC10: =Z10/L10 -> 1.0782516 | AD10: =Z10/K10 -> 0.16339186 | AE10: =R10/K10 -> 0.14278906
B11: 26-31.01 очки | E11: =K11-SUM(M11:U11)+V11+W11+X11 -> 0 | F11: ='Юнит 26-31.01'!K$26 -> 0 | G11: ='Юнит 26-31.01'!P$26 -> 0 | H11: ='Юнит 26-31.01'!Q$26 -> 0 | I11: ='Юнит 26-31.01'!S$26 -> 0 | J11: ='Юнит 26-31.01'!T$26 -> 0 | K11: =I11+J11 -> 0 | L11: ='Юнит 26-31.01'!W$26 -> 0 | M11: ='Юнит 26-31.01'!Z$26 -> 0 | N11: ='Юнит 26-31.01'!X$26 -> 0 | R11: ='Юнит 26-31.01'!AA$26 -> 0 | Y11: =(K11)*0.01 -> 0 | Z11: =K11-SUM(M11:U11)-L11-Y11+V11+X11 -> 0 | AB11: =L11/K11 -> #DIV/0! | AC11: =Z11/L11 -> #DIV/0! | AD11: =Z11/K11 -> #DIV/0! | AE11: =R11/K11 -> #DIV/0!
B12: 26-31.01 туники | E12: =K12-SUM(M12:U12)+V12+W12+X12 -> 0 | F12: ='Юнит 26-31.01'!K$49 -> 0 | G12: ='Юнит 26-31.01'!P$49 -> 0 | H12: ='Юнит 26-31.01'!Q$49 -> 0 | I12: ='Юнит 26-31.01'!S$49 -> 0 | J12: ='Юнит 26-31.01'!T$49 -> 0 | K12: =I12+J12 -> 0 | L12: ='Юнит 26-31.01'!W$26 -> 0 | M12: ='Юнит 26-31.01'!Z$49 -> 0 | N12: ='Юнит 26-31.01'!X$49 -> 0 | R12: ='Юнит 26-31.01'!AA$49 -> 0 | Y12: =(K12)*0.01 -> 0 | Z12: =K12-SUM(M12:U12)-L12-Y12+V12+X12 -> 0 | AB12: =L12/K12 -> #DIV/0! | AC12: =Z12/L12 -> #DIV/0! | AD12: =Z12/K12 -> #DIV/0! | AE12: =R12/K12 -> #DIV/0!
A13: Итого | E13: =SUM(E3:E12) -> 95943.83 | F13: =SUM(F3:F12) -> 438 | G13: =SUM(G3:G12) -> 232 | H13: =SUM(H3:H12) -> 9 | I13: =SUM(I3:I12) -> 450690 | J13: =SUM(J3:J12) -> -26401 | K13: =SUM(K3:K12) -> 424289 | L13: =SUM(L3:L12) -> 44346.35 | ... V13: =SUM(V3:V12) -> 0 | X13: =SUM(X3:X12) -> 0 | Y13: =SUM(Y3:Y12) -> 4242.89 | Z13: =SUM(Z3:Z12) -> 33354.59 | AA13: =SUM(AA3:AA12) -> 33354.59 | AB13: =L13/K13 -> 0.10451921 | AC13: =Z13/L13 -> 0.75213834 | AD13: =Z13/K13 -> 0.078612903 | AE13: =R13/K13 -> 0.23835127
I14: % от выручки за весь период
J15: =-J13/I13 -> 0.058579068 | K15: 0 | L15: =L13/$K$13 -> 0.10451921 | M15: =M13/$K$13 -> 0.10689587 | N15: =N13/$K$13 -> 0.43 | R15: =R13/$K$13 -> 0.23835127 | Y15: =Y13/$K$13 -> 0.01 | Z15: =Z13/L13 -> 0.75213834 | AA15: Маржинальность, %

Sheet АВС 01.02
B2: ОЧКИ
C3: Прибыль | D3: % прибыль | E3: Доля | F3: ABC прибыль | G3: ABC кол-во | J3: Кол-во | K3: % кол-во | L3: Доля | M3: ABC кол-во
B4: черные с железкой классика | D4: =C4/C$26 -> #DIV/0! | E4: =D4 -> #DIV/0! | F4: =IF(AND(E4<=0),"C",IF(E4<=0.8,"A",IF(E4<=0.95,"B","C"))) -> #DIV/0! | G4: =VLOOKUP(B$4:B$25,I$4:M$25,5,0) -> #DIV/0! | I4: черные с железкой классика | K4: =J4/J$26 -> #DIV/0! | L4: =K4 -> #DIV/0! | M4: =_xlfn.IFS(L4<80%,"A",L4<=95%,"B",L4>95%,"C") -> #DIV/0!
B5: qs черные | D5: =C5/C$26 -> #DIV/0! | E5: =D5+E4 -> #DIV/0! | F5: =IF(AND(E5<=0),"C",IF(E5<=0.8,"A",IF(E5<=0.95,"B","C"))) -> #DIV/0! | G5: =VLOOKUP(B$4:B$25,I$4:M$25,5,0) -> #DIV/0! | I5: qs черные | K5: =J5/J$26 -> #DIV/0! | L5: =K5+L4 -> #DIV/0! | M5: =_xlfn.IFS(L5<80%,"A",L5<=95%,"B",L5>95%,"C") -> #DIV/0!
B6: qs синие | D6: =C6/C$26 -> #DIV/0! | E6: =D6+E5 -> #DIV/0! | F6: =IF(AND(E6<=0),"C",IF(E6<=0.8,"A",IF(E6<=0.95,"B","C"))) -> #DIV/0! | G6: =VLOOKUP(B$4:B$25,I$4:M$25,5,0) -> #DIV/0! | I6: qs синие | K6: =J6/J$26 -> #DIV/0! | L6: =K6+L5 -> #DIV/0! | M6: =_xlfn.IFS(L6<80%,"A",L6<=95%,"B",L6>95%,"C") -> #DIV/0!
B7: qs желтые | D7: =C7/C$26 -> #DIV/0! | E7: =D7+E6 -> #DIV/0! | F7: =IF(AND(E7<=0),"C",IF(E7<=0.8,"A",IF(E7<=0.95,"B","C"))) -> #DIV/0! | G7: =VLOOKUP(B$4:B$25,I$4:M$25,5,0) -> #DIV/0! | I7: qs желтые | K7: =J7/J$26 -> #DIV/0! | L7: =K7+L6 -> #DIV/0! | M7: =_xlfn.IFS(L7<80%,"A",L7<=95%,"B",L7>95%,"C") -> #DIV/0!
B8: qs коричневые | D8: =C8/C$26 -> #DIV/0! | E8: =D8+E7 -> #DIV/0! | F8: =IF(AND(E8<=0),"C",IF(E8<=0.8,"A",IF(E8<=0.95,"B","C"))) -> #DIV/0! | G8: =VLOOKUP(B$4:B$25,I$4:M$25,5,0) -> #DIV/0! | I8: qs коричневые | K8: =J8/J$26 -> #DIV/0! | L8: =K8+L7 -> #DIV/0! | M8: =_xlfn.IFS(L8<80%,"A",L8<=95%,"B",L8>95%,"C") -> #DIV/0!
B9: th желтый Сул | D9: =C9/C$26 -> #DIV/0! | E9: =D9+E8 -> #DIV/0! | F9: =IF(AND(E9<=0),"C",IF(E9<=0.8,"A",IF(E9<=0.95,"B","C"))) -> #DIV/0! | G9: =VLOOKUP(B$4:B$25,I$4:M$25,5,0) -> #DIV/0! | I9: th желтый Сул | K9: =J9/J$26 -> #DIV/0! | L9: =K9+L8 -> #DIV/0! | M9: =_xlfn.IFS(L9<80%,"A",L9<=95%,"B",L9>95%,"C") -> #DIV/0!
B10: flip желтые Сул | D10: =C10/C$26 -> #DIV/0! | E10: =D10+E9 -> #DIV/0! | F10: =IF(AND(E10<=0),"C",IF(E10<=0.8,"A",IF(E10<=0.95,"B","C"))) -> #DIV/0! | G10: =VLOOKUP(B$4:B$25,I$4:M$25,5,0) -> #DIV/0! | I10: flip желтые Сул | K10: =J10/J$26 -> #DIV/0! | L10: =K10+L9 -> #DIV/0! | M10: =_xlfn.IFS(L10<80%,"A",L10<=95%,"B",L10>95%,"C") -> #DIV/0!
B11: MR8854 C2 | D11: =C11/C$26 -> #DIV/0! | E11: =D11+E8 -> #DIV/0! | F11: =IF(AND(E11<=0),"C",IF(E11<=0.8,"A",IF(E11<=0.95,"B","C"))) -> #DIV/0! | G11: =VLOOKUP(B$4:B$25,I$4:M$25,5,0) -> #DIV/0! | I11: MR8854 C2 | K11: =J11/J$26 -> #DIV/0! | L11: =K11+L8 -> #DIV/0! | M11: =_xlfn.IFS(L11<80%,"A",L11<=95%,"B",L11>95%,"C") -> #DIV/0!
B12: MR 1819 черн | D12: =C12/C$26 -> #DIV/0! | E12: =D12+E11 -> #DIV/0! | F12: =IF(AND(E12<=0),"C",IF(E12<=0.8,"A",IF(E12<=0.95,"B","C"))) -> #DIV/0! | G12: =VLOOKUP(B$4:B$25,I$4:M$25,5,0) -> #DIV/0! | I12: MR 1819 черн | K12: =J12/J$26 -> #DIV/0! | L12: =K12+L11 -> #DIV/0! | M12: =_xlfn.IFS(L12<80%,"A",L12<=95%,"B",L12>95%,"C") -> #DIV/0!
B13: MR 1819 корич | D13: =C13/C$26 -> #DIV/0! | E13: =D13+E12 -> #DIV/0! | F13: =IF(AND(E13<=0),"C",IF(E13<=0.8,"A",IF(E13<=0.95,"B","C"))) -> #DIV/0! | G13: =VLOOKUP(B$4:B$25,I$4:M$25,5,0) -> #DIV/0! | I13: MR 1819 корич | K13: =J13/J$26 -> #DIV/0! | L13: =K13+L12 -> #DIV/0! | M13: =_xlfn.IFS(L13<80%,"A",L13<=95%,"B",L13>95%,"C") -> #DIV/0! | P13: A | Q13: 0.8
B14: MR Р1874 черн | D14: =C14/C$26 -> #DIV/0! | E14: =D14+E13 -> #DIV/0! | F14: =IF(AND(E14<=0),"C",IF(E14<=0.8,"A",IF(E14<=0.95,"B","C"))) -> #DIV/0! | G14: =VLOOKUP(B$4:B$25,I$4:M$25,5,0) -> #DIV/0! | I14: MR Р1874 черн | K14: =J14/J$26 -> #DIV/0! | L14: =K14+L13 -> #DIV/0! | M14: =_xlfn.IFS(L14<80%,"A",L14<=95%,"B",L14>95%,"C") -> #DIV/0! | P14: B | Q14: 0.15
B15: MR Р1874 корич | D15: =C15/C$26 -> #DIV/0! | E15: =D15+E14 -> #DIV/0! | F15: =IF(AND(E15<=0),"C",IF(E15<=0.8,"A",IF(E15<=0.95,"B","C"))) -> #DIV/0! | G15: =VLOOKUP(B$4:B$25,I$4:M$25,5,0) -> #DIV/0! | I15: MR Р1874 корич | K15: =J15/J$26 -> #DIV/0! | L15: =K15+L14 -> #DIV/0! | M15: =_xlfn.IFS(L15<80%,"A",L15<=95%,"B",L15>95%,"C") -> #DIV/0! | P15: C | Q15: 0.05
B16: MR Р1886 черн глянец | D16: =C16/C$26 -> #DIV/0! | E16: =D16+E15 -> #DIV/0! | F16: =IF(AND(E16<=0),"C",IF(E16<=0.8,"A",IF(E16<=0.95,"B","C"))) -> #DIV/0! | G16: =VLOOKUP(B$4:B$25,I$4:M$25,5,0) -> #DIV/0! | I16: MR Р1886 черн глянец | K16: =J16/J$26 -> #DIV/0! | L16: =K16+L15 -> #DIV/0! | M16: =_xlfn.IFS(L16<80%,"A",L16<=95%,"B",L16>95%,"C") -> #DIV/0!
B17: MR Р1886 корич | D17: =C17/C$26 -> #DIV/0! | E17: =D17+E16 -> #DIV/0! | F17: =IF(AND(E17<=0),"C",IF(E17<=0.8,"A",IF(E17<=0.95,"B","C"))) -> #DIV/0! | G17: =VLOOKUP(B$4:B$25,I$4:M$25,5,0) -> #DIV/0! | I17: MR Р1886 корич | K17: =J17/J$26 -> #DIV/0! | L17: =K17+L16 -> #DIV/0! | M17: =_xlfn.IFS(L17<80%,"A",L17<=95%,"B",L17>95%,"C") -> #DIV/0!
B18: lux1 | D18: =C18/C$26 -> #DIV/0! | E18: =D18+E17 -> #DIV/0! | F18: =IF(AND(E18<=0),"C",IF(E18<=0.8,"A",IF(E18<=0.95,"B","C"))) -> #DIV/0! | G18: =VLOOKUP(B$4:B$25,I$4:M$25,5,0) -> #DIV/0! | I18: lux1 | K18: =J18/J$26 -> #DIV/0! | L18: =K18+L17 -> #DIV/0! | M18: =_xlfn.IFS(L18<80%,"A",L18<=95%,"B",L18>95%,"C") -> #DIV/0!
B19: lux2 | D19: =C19/C$26 -> #DIV/0! | E19: =D19+E18 -> #DIV/0! | F19: =IF(AND(E19<=0),"C",IF(E19<=0.8,"A",IF(E19<=0.95,"B","C"))) -> #DIV/0! | G19: =VLOOKUP(B$4:B$25,I$4:M$25,5,0) -> #DIV/0! | I19: lux2 | K19: =J19/J$26 -> #DIV/0! | L19: =K19+L18 -> #DIV/0! | M19: =_xlfn.IFS(L19<80%,"A",L19<=95%,"B",L19>95%,"C") -> #DIV/0!
B20: lux3 | D20: =C20/C$26 -> #DIV/0! | E20: =D20+E19 -> #DIV/0! | F20: =IF(AND(E20<=0),"C",IF(E20<=0.8,"A",IF(E20<=0.95,"B","C"))) -> #DIV/0! | G20: =VLOOKUP(B$4:B$25,I$4:M$25,5,0) -> #DIV/0! | I20: lux3 | K20: =J20/J$26 -> #DIV/0! | L20: =K20+L19 -> #DIV/0! | M20: =_xlfn.IFS(L20<80%,"A",L20<=95%,"B",L20>95%,"C") -> #DIV/0!
B21: lux4 | D21: =C21/C$26 -> #DIV/0! | E21: =D21+E20 -> #DIV/0! | F21: =IF(AND(E21<=0),"C",IF(E21<=0.8,"A",IF(E21<=0.95,"B","C"))) -> #DIV/0! | G21: =VLOOKUP(B$4:B$25,I$4:M$25,5,0) -> #DIV/0! | I21: lux4 | K21: =J21/J$26 -> #DIV/0! | L21: =K21+L20 -> #DIV/0! | M21: =_xlfn.IFS(L21<80%,"A",L21<=95%,"B",L21>95%,"C") -> #DIV/0!
B22: lux5 | D22: =C22/C$26 -> #DIV/0! | E22: =D22+E21 -> #DIV/0! | F22: =IF(AND(E22<=0),"C",IF(E22<=0.8,"A",IF(E22<=0.95,"B","C"))) -> #DIV/0! | G22: =VLOOKUP(B$4:B$25,I$4:M$25,5,0) -> #DIV/0! | I22: lux5 | K22: =J22/J$26 -> #DIV/0! | L22: =K22+L21 -> #DIV/0! | M22: =_xlfn.IFS(L22<80%,"A",L22<=95%,"B",L22>95%,"C") -> #DIV/0!
B23: lux6 | D23: =C23/C$26 -> #DIV/0! | E23: =D23+E22 -> #DIV/0! | F23: =IF(AND(E23<=0),"C",IF(E23<=0.8,"A",IF(E23<=0.95,"B","C"))) -> #DIV/0! | G23: =VLOOKUP(B$4:B$25,I$4:M$25,5,0) -> #DIV/0! | I23: lux6 | K23: =J23/J$26 -> #DIV/0! | L23: =K23+L22 -> #DIV/0! | M23: =_xlfn.IFS(L23<80%,"A",L23<=95%,"B",L23>95%,"C") -> #DIV/0!
B24: lux7 | D24: =C24/C$26 -> #DIV/0! | E24: =D24+E23 -> #DIV/0! | F24: =IF(AND(E24<=0),"C",IF(E24<=0.8,"A",IF(E24<=0.95,"B","C"))) -> #DIV/0! | G24: =VLOOKUP(B$4:B$25,I$4:M$25,5,0) -> #DIV/0! | I24: lux7 | K24: =J24/J$26 -> #DIV/0! | L24: =K24+L23 -> #DIV/0! | M24: =_xlfn.IFS(L24<80%,"A",L24<=95%,"B",L24>95%,"C") -> #DIV/0!
B25: lux8 | D25: =C25/C$26 -> #DIV/0! | E25: =D25+E24 -> #DIV/0! | F25: =IF(AND(E25<=0),"C",IF(E25<=0.8,"A",IF(E25<=0.95,"B","C"))) -> #DIV/0! | G25: =VLOOKUP(B$4:B$25,I$4:M$25,5,0) -> #DIV/0! | I25: lux8 | K25: =J25/J$26 -> #DIV/0! | L25: =K25+L24 -> #DIV/0! | M25: =_xlfn.IFS(L25<80%,"A",L25<=95%,"B",L25>95%,"C") -> #DIV/0!
C26: =SUM(C4:C25) -> 0 | D26: =SUM(D4:D25) -> #DIV/0! | J26: =SUM(J4:J25) -> 0 | K26: =SUM(K4:K25) -> #DIV/0!
B28: ТУНИКИ
C29: Прибыль | D29: % прибыль | E29: Доля | F29: ABC прибыль | G29: ABC кол-во | J29: Кол-во | K29: % кол-во | L29: Доля | M29: ABC кол-во
B30: tunika02 оливковая с руч вышивкой | D30: =C30/C$50 -> #DIV/0! | E30: =D30 -> #DIV/0! | F30: =IF(AND(E30<=0),"C",IF(E30<=0.8,"A",IF(E30<=0.95,"B","C"))) -> #DIV/0! | G30: =VLOOKUP(B$30:B$50,I$30:M$50,5,0) -> #DIV/0! | I30: tunika02 оливковая с руч вышивкой | K30: =J30/J$50 -> #DIV/0! | L30: =K30 -> #DIV/0! | M30: =_xlfn.IFS(L30<80%,"A",L30<=95%,"B",L30>95%,"C") -> #DIV/0!
B31: tunika03 черная распашная | D31: =C31/C$50 -> #DIV/0! | E31: =D31+E30 -> #DIV/0! | F31: =IF(AND(E31<=0),"C",IF(E31<=0.8,"A",IF(E31<=0.95,"B","C"))) -> #DIV/0! | G31: =VLOOKUP(B$30:B$50,I$30:M$50,5,0) -> #DIV/0! | I31: tunika03 черная распашная | K31: =J31/J$50 -> #DIV/0! | L31: =K31+L30 -> #DIV/0! | M31: =_xlfn.IFS(L31<80%,"A",L31<=95%,"B",L31>95%,"C") -> #DIV/0!
B32: tunika05 белая распашная | D32: =C32/C$50 -> #DIV/0! | E32: =D32+E31 -> #DIV/0! | F32: =IF(AND(E32<=0),"C",IF(E32<=0.8,"A",IF(E32<=0.95,"B","C"))) -> #DIV/0! | G32: =VLOOKUP(B$30:B$50,I$30:M$50,5,0) -> #DIV/0! | I32: tunika05 белая распашная | K32: =J32/J$50 -> #DIV/0! | L32: =K32+L31 -> #DIV/0! | M32: =_xlfn.IFS(L32<80%,"A",L32<=95%,"B",L32>95%,"C") -> #DIV/0!
B33: tunika06 белая | D33: =C33/C$50 -> #DIV/0! | E33: =D33+E32 -> #DIV/0! | F33: =IF(AND(E33<=0),"C",IF(E33<=0.8,"A",IF(E33<=0.95,"B","C"))) -> #DIV/0! | G33: =VLOOKUP(B$30:B$50,I$30:M$50,5,0) -> #DIV/0! | I33: tunika06 белая | K33: =J33/J$50 -> #DIV/0! | L33: =K33+L32 -> #DIV/0! | M33: =_xlfn.IFS(L33<80%,"A",L33<=95%,"B",L33>95%,"C") -> #DIV/0!
B34: tunika06 черная | D34: =C34/C$50 -> #DIV/0! | E34: =D34+E33 -> #DIV/0! | F34: =IF(AND(E34<=0),"C",IF(E34<=0.8,"A",IF(E34<=0.95,"B","C"))) -> #DIV/0! | G34: =VLOOKUP(B$30:B$50,I$30:M$50,5,0) -> #DIV/0! | I34: tunika06 черная | K34: =J34/J$50 -> #DIV/0! | L34: =K34+L33 -> #DIV/0! | M34: =_xlfn.IFS(L34<80%,"A",L34<=95%,"B",L34>95%,"C") -> #DIV/0!
B35: tunika07 кружево | D35: =C35/C$50 -> #DIV/0! | E35: =D35+E34 -> #DIV/0! | F35: =IF(AND(E35<=0),"C",IF(E35<=0.8,"A",IF(E35<=0.95,"B","C"))) -> #DIV/0! | G35: =VLOOKUP(B$30:B$50,I$30:M$50,5,0) -> #DIV/0! | I35: tunika07 кружево | K35: =J35/J$50 -> #DIV/0! | L35: =K35+L34 -> #DIV/0! | M35: =_xlfn.IFS(L35<80%,"A",L35<=95%,"B",L35>95%,"C") -> #DIV/0!
B36: tunika08 белая | D36: =C36/C$50 -> #DIV/0! | E36: =D36+E35 -> #DIV/0! | F36: =IF(AND(E36<=0),"C",IF(E36<=0.8,"A",IF(E36<=0.95,"B","C"))) -> #DIV/0! | G36: =VLOOKUP(B$30:B$50,I$30:M$50,5,0) -> #DIV/0! | I36: tunika08 белая | K36: =J36/J$50 -> #DIV/0! | L36: =K36+L35 -> #DIV/0! | M36: =_xlfn.IFS(L36<80%,"A",L36<=95%,"B",L36>95%,"C") -> #DIV/0!
B37: tunika08 черная | D37: =C37/C$50 -> #DIV/0! | E37: =D37+E36 -> #DIV/0! | F37: =IF(AND(E37<=0),"C",IF(E37<=0.8,"A",IF(E37<=0.95,"B","C"))) -> #DIV/0! | G37: =VLOOKUP(B$30:B$50,I$30:M$50,5,0) -> #DIV/0! | I37: tunika08 черная | K37: =J37/J$50 -> #DIV/0! | L37: =K37+L36 -> #DIV/0! | M37: =_xlfn.IFS(L37<80%,"A",L37<=95%,"B",L37>95%,"C") -> #DIV/0!
B38: tunika08 зеленая | D38: =C38/C$50 -> #DIV/0! | E38: =D38+E37 -> #DIV/0! | F38: =IF(AND(E38<=0),"C",IF(E38<=0.8,"A",IF(E38<=0.95,"B","C"))) -> #DIV/0! | G38: =VLOOKUP(B$30:B$50,I$30:M$50,5,0) -> #DIV/0! | I38: tunika08 зеленая | K38: =J38/J$50 -> #DIV/0! | L38: =K38+L37 -> #DIV/0! | M38: =_xlfn.IFS(L38<80%,"A",L38<=95%,"B",L38>95%,"C") -> #DIV/0!
B39: tunika09 кимоно | D39: =C39/C$50 -> #DIV/0! | E39: =D39+E38 -> #DIV/0! | F39: =IF(AND(E39<=0),"C",IF(E39<=0.8,"A",IF(E39<=0.95,"B","C"))) -> #DIV/0! | G39: =VLOOKUP(B$30:B$50,I$30:M$50,5,0) -> #DIV/0! | I39: tunika09 кимоно | K39: =J39/J$50 -> #DIV/0! | L39: =K39+L38 -> #DIV/0! | M39: =_xlfn.IFS(L39<80%,"A",L39<=95%,"B",L39>95%,"C") -> #DIV/0!
B40: tunika10 кимоно ч/б | D40: =C40/C$50 -> #DIV/0! | E40: =D40+E39 -> #DIV/0! | F40: =IF(AND(E40<=0),"C",IF(E40<=0.8,"A",IF(E40<=0.95,"B","C"))) -> #DIV/0! | G40: =VLOOKUP(B$30:B$50,I$30:M$50,5,0) -> #DIV/0! | I40: tunika10 кимоно ч/б | K40: =J40/J$50 -> #DIV/0! | L40: =K40+L39 -> #DIV/0! | M40: =_xlfn.IFS(L40<80%,"A",L40<=95%,"B",L40>95%,"C") -> #DIV/0!
B41: tunika11 халат зеленая | D41: =C41/C$50 -> #DIV/0! | E41: =D41+E40 -> #DIV/0! | F41: =IF(AND(E41<=0),"C",IF(E41<=0.8,"A",IF(E41<=0.95,"B","C"))) -> #DIV/0! | G41: =VLOOKUP(B$30:B$50,I$30:M$50,5,0) -> #DIV/0! | I41: tunika11 халат зеленая | K41: =J41/J$50 -> #DIV/0! | L41: =K41+L40 -> #DIV/0! | M41: =_xlfn.IFS(L41<80%,"A",L41<=95%,"B",L41>95%,"C") -> #DIV/0!
B42: tunika12 халат белая | D42: =C42/C$50 -> #DIV/0! | E42: =D42+E41 -> #DIV/0! | F42: =IF(AND(E42<=0),"C",IF(E42<=0.8,"A",IF(E42<=0.95,"B","C"))) -> #DIV/0! | G42: =VLOOKUP(B$30:B$50,I$30:M$50,5,0) -> #DIV/0! | I42: tunika12 халат белая | K42: =J42/J$50 -> #DIV/0! | L42: =K42+L41 -> #DIV/0! | M42: =_xlfn.IFS(L42<80%,"A",L42<=95%,"B",L42>95%,"C") -> #DIV/0!
... B49: tunika16 сетка черная | D49: =C49/C$50 -> #DIV/0! | E49: =D49+E48 -> #DIV/0! | F49: =IF(AND(E49<=0),"C",IF(E49<=0.8,"A",IF(E49<=0.95,"B","C"))) -> #DIV/0! | G49: =VLOOKUP(B$30:B$50,I$30:M$50,5,0) -> #DIV/0! | I49: tunika16 сетка черная | K49: =J49/J$50 -> #DIV/0! | L49: =K49+L48 -> #DIV/0! | M49: =_xlfn.IFS(L49<80%,"A",L49<=95%,"B",L49>95%,"C") -> #DIV/0!
C50: =SUM(C30:C49) -> 0 | D50: =SUM(D30:D49) -> #DIV/0! | J50: =SUM(J30:J49) -> 0 | K50: =SUM(K30:K49) -> #DIV/0!

Sheet АВС ЯНВАРЬ
B2: ОЧКИ
C3: Прибыль | D3: % прибыль | E3: Доля | F3: ABC прибыль | G3: ABC кол-во | J3: Кол-во | K3: % кол-во | L3: Доля | M3: ABC кол-во
B4: черные с железкой классика | D4: =C4/C$26 -> #DIV/0! | E4: =D4 -> #DIV/0! | F4: =IF(AND(E4<=0),"C",IF(E4<=0.8,"A",IF(E4<=0.95,"B","C"))) -> #DIV/0! | G4: =VLOOKUP(B$4:B$25,I$4:M$25,5,0) -> #DIV/0! | I4: черные с железкой классика | K4: =J4/J$26 -> #DIV/0! | L4: =K4 -> #DIV/0! | M4: =_xlfn.IFS(L4<80%,"A",L4<=95%,"B",L4>95%,"C") -> #DIV/0!
B5: qs черные | D5: =C5/C$26 -> #DIV/0! | E5: =D5+E4 -> #DIV/0! | F5: =IF(AND(E5<=0),"C",IF(E5<=0.8,"A",IF(E5<=0.95,"B","C"))) -> #DIV/0! | G5: =VLOOKUP(B$4:B$25,I$4:M$25,5,0) -> #DIV/0! | I5: qs черные | K5: =J5/J$26 -> #DIV/0! | L5: =K5+L4 -> #DIV/0! | M5: =_xlfn.IFS(L5<80%,"A",L5<=95%,"B",L5>95%,"C") -> #DIV/0!
B6: qs синие | D6: =C6/C$26 -> #DIV/0! | E6: =D6+E5 -> #DIV/0! | F6: =IF(AND(E6<=0),"C",IF(E6<=0.8,"A",IF(E6<=0.95,"B","C"))) -> #DIV/0! | G6: =VLOOKUP(B$4:B$25,I$4:M$25,5,0) -> #DIV/0! | I6: qs синие | K6: =J6/J$26 -> #DIV/0! | L6: =K6+L5 -> #DIV/0! | M6: =_xlfn.IFS(L6<80%,"A",L6<=95%,"B",L6>95%,"C") -> #DIV/0!
B7: qs желтые | D7: =C7/C$26 -> #DIV/0! | E7: =D7+E6 -> #DIV/0! | F7: =IF(AND(E7<=0),"C",IF(E7<=0.8,"A",IF(E7<=0.95,"B","C"))) -> #DIV/0! | G7: =VLOOKUP(B$4:B$25,I$4:M$25,5,0) -> #DIV/0! | I7: qs желтые | K7: =J7/J$26 -> #DIV/0! | L7: =K7+L6 -> #DIV/0! | M7: =_xlfn.IFS(L7<80%,"A",L7<=95%,"B",L7>95%,"C") -> #DIV/0!
B8: qs коричневые | D8: =C8/C$26 -> #DIV/0! | E8: =D8+E7 -> #DIV/0! | F8: =IF(AND(E8<=0),"C",IF(E8<=0.8,"A",IF(E8<=0.95,"B","C"))) -> #DIV/0! | G8: =VLOOKUP(B$4:B$25,I$4:M$25,5,0) -> #DIV/0! | I8: qs коричневые | K8: =J8/J$26 -> #DIV/0! | L8: =K8+L7 -> #DIV/0! | M8: =_xlfn.IFS(L8<80%,"A",L8<=95%,"B",L8>95%,"C") -> #DIV/0!
B9: th желтый Сул | D9: =C9/C$26 -> #DIV/0! | E9: =D9+E8 -> #DIV/0! | F9: =IF(AND(E9<=0),"C",IF(E9<=0.8,"A",IF(E9<=0.95,"B","C"))) -> #DIV/0! | G9: =VLOOKUP(B$4:B$25,I$4:M$25,5,0) -> #DIV/0! | I9: th желтый Сул | K9: =J9/J$26 -> #DIV/0! | L9: =K9+L8 -> #DIV/0! | M9: =_xlfn.IFS(L9<80%,"A",L9<=95%,"B",L9>95%,"C") -> #DIV/0!
B10: flip желтые Сул | D10: =C10/C$26 -> #DIV/0! | E10: =D10+E9 -> #DIV/0! | F10: =IF(AND(E10<=0),"C",IF(E10<=0.8,"A",IF(E10<=0.95,"B","C"))) -> #DIV/0! | G10: =VLOOKUP(B$4:B$25,I$4:M$25,5,0) -> #DIV/0! | I10: flip желтые Сул | K10: =J10/J$26 -> #DIV/0! | L10: =K10+L9 -> #DIV/0! | M10: =_xlfn.IFS(L10<80%,"A",L10<=95%,"B",L10>95%,"C") -> #DIV/0!
B11: MR8854 C2 | D11: =C11/C$26 -> #DIV/0! | E11: =D11+E8 -> #DIV/0! | F11: =IF(AND(E11<=0),"C",IF(E11<=0.8,"A",IF(E11<=0.95,"B","C"))) -> #DIV/0! | G11: =VLOOKUP(B$4:B$25,I$4:M$25,5,0) -> #DIV/0! | I11: MR8854 C2 | K11: =J11/J$26 -> #DIV/0! | L11: =K11+L8 -> #DIV/0! | M11: =_xlfn.IFS(L11<80%,"A",L11<=95%,"B",L11>95%,"C") -> #DIV/0!
B12: MR 1819 черн | D12: =C12/C$26 -> #DIV/0! | E12: =D12+E11 -> #DIV/0! | F12: =IF(AND(E12<=0),"C",IF(E12<=0.8,"A",IF(E12<=0.95,"B","C"))) -> #DIV/0! | G12: =VLOOKUP(B$4:B$25,I$4:M$25,5,0) -> #DIV/0! | I12: MR 1819 черн | K12: =J12/J$26 -> #DIV/0! | L12: =K12+L11 -> #DIV/0! | M12: =_xlfn.IFS(L12<80%,"A",L12<=95%,"B",L12>95%,"C") -> #DIV/0!
B13: MR 1819 корич | D13: =C13/C$26 -> #DIV/0! | E13: =D13+E12 -> #DIV/0! | F13: =IF(AND(E13<=0),"C",IF(E13<=0.8,"A",IF(E13<=0.95,"B","C"))) -> #DIV/0! | G13: =VLOOKUP(B$4:B$25,I$4:M$25,5,0) -> #DIV/0! | I13: MR 1819 корич | K13: =J13/J$26 -> #DIV/0! | L13: =K13+L12 -> #DIV/0! | M13: =_xlfn.IFS(L13<80%,"A",L13<=95%,"B",L13>95%,"C") -> #DIV/0! | P13: A | Q13: 0.8
B14: MR Р1874 черн | D14: =C14/C$26 -> #DIV/0! | E14: =D14+E13 -> #DIV/0! | F14: =IF(AND(E14<=0),"C",IF(E14<=0.8,"A",IF(E14<=0.95,"B","C"))) -> #DIV/0! | G14: =VLOOKUP(B$4:B$25,I$4:M$25,5,0) -> #DIV/0! | I14: MR Р1874 черн | K14: =J14/J$26 -> #DIV/0! | L14: =K14+L13 -> #DIV/0! | M14: =_xlfn.IFS(L14<80%,"A",L14<=95%,"B",L14>95%,"C") -> #DIV/0! | P14: B | Q14: 0.15
B15: MR Р1874 корич | D15: =C15/C$26 -> #DIV/0! | E15: =D15+E14 -> #DIV/0! | F15: =IF(AND(E15<=0),"C",IF(E15<=0.8,"A",IF(E15<=0.95,"B","C"))) -> #DIV/0! | G15: =VLOOKUP(B$4:B$25,I$4:M$25,5,0) -> #DIV/0! | I15: MR Р1874 корич | K15: =J15/J$26 -> #DIV/0! | L15: =K15+L14 -> #DIV/0! | M15: =_xlfn.IFS(L15<80%,"A",L15<=95%,"B",L15>95%,"C") -> #DIV/0! | P15: C | Q15: 0.05
B16: MR Р1886 черн глянец | D16: =C16/C$26 -> #DIV/0! | E16: =D16+E15 -> #DIV/0! | F16: =IF(AND(E16<=0),"C",IF(E16<=0.8,"A",IF(E16<=0.95,"B","C"))) -> #DIV/0! | G16: =VLOOKUP(B$4:B$25,I$4:M$25,5,0) -> #DIV/0! | I16: MR Р1886 черн глянец | K16: =J16/J$26 -> #DIV/0! | L16: =K16+L15 -> #DIV/0! | M16: =_xlfn.IFS(L16<80%,"A",L16<=95%,"B",L16>95%,"C") -> #DIV/0!
B17: MR Р1886 корич | D17: =C17/C$26 -> #DIV/0! | E17: =D17+E16 -> #DIV/0! | F17: =IF(AND(E17<=0),"C",IF(E17<=0.8,"A",IF(E17<=0.95,"B","C"))) -> #DIV/0! | G17: =VLOOKUP(B$4:B$25,I$4:M$25,5,0) -> #DIV/0! | I17: MR Р1886 корич | K17: =J17/J$26 -> #DIV/0! | L17: =K17+L16 -> #DIV/0! | M17: =_xlfn.IFS(L17<80%,"A",L17<=95%,"B",L17>95%,"C") -> #DIV/0!
B18: lux1 | D18: =C18/C$26 -> #DIV/0! | E18: =D18+E17 -> #DIV/0! | F18: =IF(AND(E18<=0),"C",IF(E18<=0.8,"A",IF(E18<=0.95,"B","C"))) -> #DIV/0! | G18: =VLOOKUP(B$4:B$25,I$4:M$25,5,0) -> #DIV/0! | I18: lux1 | K18: =J18/J$26 -> #DIV/0! | L18: =K18+L17 -> #DIV/0! | M18: =_xlfn.IFS(L18<80%,"A",L18<=95%,"B",L18>95%,"C") -> #DIV/0!
B19: lux2 | D19: =C19/C$26 -> #DIV/0! | E19: =D19+E18 -> #DIV/0! | F19: =IF(AND(E19<=0),"C",IF(E19<=0.8,"A",IF(E19<=0.95,"B","C"))) -> #DIV/0! | G19: =VLOOKUP(B$4:B$25,I$4:M$25,5,0) -> #DIV/0! | I19: lux2 | K19: =J19/J$26 -> #DIV/0! | L19: =K19+L18 -> #DIV/0! | M19: =_xlfn.IFS(L19<80%,"A",L19<=95%,"B",L19>95%,"C") -> #DIV/0!
B20: lux3 | D20: =C20/C$26 -> #DIV/0! | E20: =D20+E19 -> #DIV/0! | F20: =IF(AND(E20<=0),"C",IF(E20<=0.8,"A",IF(E20<=0.95,"B","C"))) -> #DIV/0! | G20: =VLOOKUP(B$4:B$25,I$4:M$25,5,0) -> #DIV/0! | I20: lux3 | K20: =J20/J$26 -> #DIV/0! | L20: =K20+L19 -> #DIV/0! | M20: =_xlfn.IFS(L20<80%,"A",L20<=95%,"B",L20>95%,"C") -> #DIV/0!
B21: lux4 | D21: =C21/C$26 -> #DIV/0! | E21: =D21+E20 -> #DIV/0! | F21: =IF(AND(E21<=0),"C",IF(E21<=0.8,"A",IF(E21<=0.95,"B","C"))) -> #DIV/0! | G21: =VLOOKUP(B$4:B$25,I$4:M$25,5,0) -> #DIV/0! | I21: lux4 | K21: =J21/J$26 -> #DIV/0! | L21: =K21+L20 -> #DIV/0! | M21: =_xlfn.IFS(L21<80%,"A",L21<=95%,"B",L21>95%,"C") -> #DIV/0!
B22: lux5 | D22: =C22/C$26 -> #DIV/0! | E22: =D22+E21 -> #DIV/0! | F22: =IF(AND(E22<=0),"C",IF(E22<=0.8,"A",IF(E22<=0.95,"B","C"))) -> #DIV/0! | G22: =VLOOKUP(B$4:B$25,I$4:M$25,5,0) -> #DIV/0! | I22: lux5 | K22: =J22/J$26 -> #DIV/0! | L22: =K22+L21 -> #DIV/0! | M22: =_xlfn.IFS(L22<80%,"A",L22<=95%,"B",L22>95%,"C") -> #DIV/0!
B23: lux6 | D23: =C23/C$26 -> #DIV/0! | E23: =D23+E22 -> #DIV/0! | F23: =IF(AND(E23<=0),"C",IF(E23<=0.8,"A",IF(E23<=0.95,"B","C"))) -> #DIV/0! | G23: =VLOOKUP(B$4:B$25,I$4:M$25,5,0) -> #DIV/0! | I23: lux6 | K23: =J23/J$26 -> #DIV/0! | L23: =K23+L22 -> #DIV/0! | M23: =_xlfn.IFS(L23<80%,"A",L23<=95%,"B",L23>95%,"C") -> #DIV/0!
B24: lux7 | D24: =C24/C$26 -> #DIV/0! | E24: =D24+E23 -> #DIV/0! | F24: =IF(AND(E24<=0),"C",IF(E24<=0.8,"A",IF(E24<=0.95,"B","C"))) -> #DIV/0! | G24: =VLOOKUP(B$4:B$25,I$4:M$25,5,0) -> #DIV/0! | I24: lux7 | K24: =J24/J$26 -> #DIV/0! | L24: =K24+L23 -> #DIV/0! | M24: =_xlfn.IFS(L24<80%,"A",L24<=95%,"B",L24>95%,"C") -> #DIV/0!
B25: lux8 | D25: =C25/C$26 -> #DIV/0! | E25: =D25+E24 -> #DIV/0! | F25: =IF(AND(E25<=0),"C",IF(E25<=0.8,"A",IF(E25<=0.95,"B","C"))) -> #DIV/0! | G25: =VLOOKUP(B$4:B$25,I$4:M$25,5,0) -> #DIV/0! | I25: lux8 | K25: =J25/J$26 -> #DIV/0! | L25: =K25+L24 -> #DIV/0! | M25: =_xlfn.IFS(L25<80%,"A",L25<=95%,"B",L25>95%,"C") -> #DIV/0!
C26: =SUM(C4:C25) -> 0 | D26: =SUM(D4:D25) -> #DIV/0! | J26: =SUM(J4:J25) -> 0 | K26: =SUM(K4:K25) -> #DIV/0!
B28: ТУНИКИ
C29: Прибыль | D29: % прибыль | E29: Доля | F29: ABC прибыль | G29: ABC кол-во | J29: Кол-во | K29: % кол-во | L29: Доля | M29: ABC кол-во
B30: tunika02 оливковая с руч вышивкой | D30: =C30/C$50 -> #DIV/0! | E30: =D30 -> #DIV/0! | F30: =IF(AND(E30<=0),"C",IF(E30<=0.8,"A",IF(E30<=0.95,"B","C"))) -> #DIV/0! | G30: =VLOOKUP(B$30:B$50,I$30:M$50,5,0) -> #DIV/0! | I30: tunika02 оливковая с руч вышивкой | K30: =J30/J$50 -> #DIV/0! | L30: =K30 -> #DIV/0! | M30: =_xlfn.IFS(L30<80%,"A",L30<=95%,"B",L30>95%,"C") -> #DIV/0!
B31: tunika03 черная распашная | D31: =C31/C$50 -> #DIV/0! | E31: =D31+E30 -> #DIV/0! | F31: =IF(AND(E31<=0),"C",IF(E31<=0.8,"A",IF(E31<=0.95,"B","C"))) -> #DIV/0! | G31: =VLOOKUP(B$30:B$50,I$30:M$50,5,0) -> #DIV/0! | I31: tunika03 черная распашная | K31: =J31/J$50 -> #DIV/0! | L31: =K31+L30 -> #DIV/0! | M31: =_xlfn.IFS(L31<80%,"A",L31<=95%,"B",L31>95%,"C") -> #DIV/0!
B32: tunika05 белая распашная | D32: =C32/C$50 -> #DIV/0! | E32: =D32+E31 -> #DIV/0! | F32: =IF(AND(E32<=0),"C",IF(E32<=0.8,"A",IF(E32<=0.95,"B","C"))) -> #DIV/0! | G32: =VLOOKUP(B$30:B$50,I$30:M$50,5,0) -> #DIV/0! | I32: tunika05 белая распашная | K32: =J32/J$50 -> #DIV/0! | L32: =K32+L31 -> #DIV/0! | M32: =_xlfn.IFS(L32<80%,"A",L32<=95%,"B",L32>95%,"C") -> #DIV/0!
B33: tunika06 белая | D33: =C33/C$50 -> #DIV/0! | E33: =D33+E32 -> #DIV/0! | F33: =IF(AND(E33<=0),"C",IF(E33<=0.8,"A",IF(E33<=0.95,"B","C"))) -> #DIV/0! | G33: =VLOOKUP(B$30:B$50,I$30:M$50,5,0) -> #DIV/0! | I33: tunika06 белая | K33: =J33/J$50 -> #DIV/0! | L33: =K33+L32 -> #DIV/0! | M33: =_xlfn.IFS(L33<80%,"A",L33<=95%,"B",L33>95%,"C") -> #DIV/0!
B34: tunika06 черная | D34: =C34/C$50 -> #DIV/0! | E34: =D34+E33 -> #DIV/0! | F34: =IF(AND(E34<=0),"C",IF(E34<=0.8,"A",IF(E34<=0.95,"B","C"))) -> #DIV/0! | G34: =VLOOKUP(B$30:B$50,I$30:M$50,5,0) -> #DIV/0! | I34: tunika06 черная | K34: =J34/J$50 -> #DIV/0! | L34: =K34+L33 -> #DIV/0! | M34: =_xlfn.IFS(L34<80%,"A",L34<=95%,"B",L34>95%,"C") -> #DIV/0!
B35: tunika07 кружево | D35: =C35/C$50 -> #DIV/0! | E35: =D35+E34 -> #DIV/0! | F35: =IF(AND(E35<=0),"C",IF(E35<=0.8,"A",IF(E35<=0.95,"B","C"))) -> #DIV/0! | G35: =VLOOKUP(B$30:B$50,I$30:M$50,5,0) -> #DIV/0! | I35: tunika07 кружево | K35: =J35/J$50 -> #DIV/0! | L35: =K35+L34 -> #DIV/0! | M35: =_xlfn.IFS(L35<80%,"A",L35<=95%,"B",L35>95%,"C") -> #DIV/0!
B36: tunika08 белая | D36: =C36/C$50 -> #DIV/0! | E36: =D36+E35 -> #DIV/0! | F36: =IF(AND(E36<=0),"C",IF(E36<=0.8,"A",IF(E36<=0.95,"B","C"))) -> #DIV/0! | G36: =VLOOKUP(B$30:B$50,I$30:M$50,5,0) -> #DIV/0! | I36: tunika08 белая | K36: =J36/J$50 -> #DIV/0! | L36: =K36+L35 -> #DIV/0! | M36: =_xlfn.IFS(L36<80%,"A",L36<=95%,"B",L36>95%,"C") -> #DIV/0!
B37: tunika08 черная | D37: =C37/C$50 -> #DIV/0! | E37: =D37+E36 -> #DIV/0! | F37: =IF(AND(E37<=0),"C",IF(E37<=0.8,"A",IF(E37<=0.95,"B","C"))) -> #DIV/0! | G37: =VLOOKUP(B$30:B$50,I$30:M$50,5,0) -> #DIV/0! | I37: tunika08 черная | K37: =J37/J$50 -> #DIV/0! | L37: =K37+L36 -> #DIV/0! | M37: =_xlfn.IFS(L37<80%,"A",L37<=95%,"B",L37>95%,"C") -> #DIV/0!
B38: tunika08 зеленая | D38: =C38/C$50 -> #DIV/0! | E38: =D38+E37 -> #DIV/0! | F38: =IF(AND(E38<=0),"C",IF(E38<=0.8,"A",IF(E38<=0.95,"B","C"))) -> #DIV/0! | G38: =VLOOKUP(B$30:B$50,I$30:M$50,5,0) -> #DIV/0! | I38: tunika08 зеленая | K38: =J38/J$50 -> #DIV/0! | L38: =K38+L37 -> #DIV/0! | M38: =_xlfn.IFS(L38<80%,"A",L38<=95%,"B",L38>95%,"C") -> #DIV/0!
B39: tunika09 кимоно | D39: =C39/C$50 -> #DIV/0! | E39: =D39+E38 -> #DIV/0! | F39: =IF(AND(E39<=0),"C",IF(E39<=0.8,"A",IF(E39<=0.95,"B","C"))) -> #DIV/0! | G39: =VLOOKUP(B$30:B$50,I$30:M$50,5,0) -> #DIV/0! | I39: tunika09 кимоно | K39: =J39/J$50 -> #DIV/0! | L39: =K39+L38 -> #DIV/0! | M39: =_xlfn.IFS(L39<80%,"A",L39<=95%,"B",L39>95%,"C") -> #DIV/0!
B40: tunika10 кимоно ч/б | D40: =C40/C$50 -> #DIV/0! | E40: =D40+E39 -> #DIV/0! | F40: =IF(AND(E40<=0),"C",IF(E40<=0.8,"A",IF(E40<=0.95,"B","C"))) -> #DIV/0! | G40: =VLOOKUP(B$30:B$50,I$30:M$50,5,0) -> #DIV/0! | I40: tunika10 кимоно ч/б | K40: =J40/J$50 -> #DIV/0! | L40: =K40+L39 -> #DIV/0! | M40: =_xlfn.IFS(L40<80%,"A",L40<=95%,"B",L40>95%,"C") -> #DIV/0!
B41: tunika11 халат зеленая | D41: =C41/C$50 -> #DIV/0! | E41: =D41+E40 -> #DIV/0! | F41: =IF(AND(E41<=0),"C",IF(E41<=0.8,"A",IF(E41<=0.95,"B","C"))) -> #DIV/0! | G41: =VLOOKUP(B$30:B$50,I$30:M$50,5,0) -> #DIV/0! | I41: tunika11 халат зеленая | K41: =J41/J$50 -> #DIV/0! | L41: =K41+L40 -> #DIV/0! | M41: =_xlfn.IFS(L41<80%,"A",L41<=95%,"B",L41>95%,"C") -> #DIV/0!
B42: tunika12 халат белая | D42: =C42/C$50 -> #DIV/0! | E42: =D42+E41 -> #DIV/0! | F42: =IF(AND(E42<=0),"C",IF(E42<=0.8,"A",IF(E42<=0.95,"B","C"))) -> #DIV/0! | G42: =VLOOKUP(B$30:B$50,I$30:M$50,5,0) -> #DIV/0! | I42: tunika12 халат белая | K42: =J42/J$50 -> #DIV/0! | L42: =K42+L41 -> #DIV/0! | M42: =_xlfn.IFS(L42<80%,"A",L42<=95%,"B",L42>95%,"C") -> #DIV/0!
... B49: tunika16 сетка черная | D49: =C49/C$50 -> #DIV/0! | E49: =D49+E48 -> #DIV/0! | F49: =IF(AND(E49<=0),"C",IF(E49<=0.8,"A",IF(E49<=0.95,"B","C"))) -> #DIV/0! | G49: =VLOOKUP(B$30:B$50,I$30:M$50,5,0) -> #DIV/0! | I49: tunika16 сетка черная | K49: =J49/J$50 -> #DIV/0! | L49: =K49+L48 -> #DIV/0! | M49: =_xlfn.IFS(L49<80%,"A",L49<=95%,"B",L49>95%,"C") -> #DIV/0!
C50: =SUM(C30:C49) -> 0 | D50: =SUM(D30:D49) -> #DIV/0! | J50: =SUM(J30:J49) -> 0 | K50: =SUM(K30:K49) -> #DIV/0!

Sheet АВС 26-31.01
B2: ОЧКИ
C3: Прибыль | D3: % прибыль | E3: Доля | F3: ABC прибыль | G3: ABC кол-во | J3: Кол-во | K3: % кол-во | L3: Доля | M3: ABC кол-во
B4: черные с железкой классика | D4: =C4/C$26 -> #DIV/0! | E4: =D4 -> #DIV/0! | F4: =IF(AND(E4<=0),"C",IF(E4<=0.8,"A",IF(E4<=0.95,"B","C"))) -> #DIV/0! | G4: =VLOOKUP(B$4:B$25,I$4:M$25,5,0) -> #DIV/0! | I4: черные с железкой классика | K4: =J4/J$26 -> #DIV/0! | L4: =K4 -> #DIV/0! | M4: =_xlfn.IFS(L4<80%,"A",L4<=95%,"B",L4>95%,"C") -> #DIV/0!
B5: qs черные | D5: =C5/C$26 -> #DIV/0! | E5: =D5+E4 -> #DIV/0! | F5: =IF(AND(E5<=0),"C",IF(E5<=0.8,"A",IF(E5<=0.95,"B","C"))) -> #DIV/0! | G5: =VLOOKUP(B$4:B$25,I$4:M$25,5,0) -> #DIV/0! | I5: qs черные | K5: =J5/J$26 -> #DIV/0! | L5: =K5+L4 -> #DIV/0! | M5: =_xlfn.IFS(L5<80%,"A",L5<=95%,"B",L5>95%,"C") -> #DIV/0!
B6: qs синие | D6: =C6/C$26 -> #DIV/0! | E6: =D6+E5 -> #DIV/0! | F6: =IF(AND(E6<=0),"C",IF(E6<=0.8,"A",IF(E6<=0.95,"B","C"))) -> #DIV/0! | G6: =VLOOKUP(B$4:B$25,I$4:M$25,5,0) -> #DIV/0! | I6: qs синие | K6: =J6/J$26 -> #DIV/0! | L6: =K6+L5 -> #DIV/0! | M6: =_xlfn.IFS(L6<80%,"A",L6<=95%,"B",L6>95%,"C") -> #DIV/0!
B7: qs желтые | D7: =C7/C$26 -> #DIV/0! | E7: =D7+E6 -> #DIV/0! | F7: =IF(AND(E7<=0),"C",IF(E7<=0.8,"A",IF(E7<=0.95,"B","C"))) -> #DIV/0! | G7: =VLOOKUP(B$4:B$25,I$4:M$25,5,0) -> #DIV/0! | I7: qs желтые | K7: =J7/J$26 -> #DIV/0! | L7: =K7+L6 -> #DIV/0! | M7: =_xlfn.IFS(L7<80%,"A",L7<=95%,"B",L7>95%,"C") -> #DIV/0!
B8: qs коричневые | D8: =C8/C$26 -> #DIV/0! | E8: =D8+E7 -> #DIV/0! | F8: =IF(AND(E8<=0),"C",IF(E8<=0.8,"A",IF(E8<=0.95,"B","C"))) -> #DIV/0! | G8: =VLOOKUP(B$4:B$25,I$4:M$25,5,0) -> #DIV/0! | I8: qs коричневые | K8: =J8/J$26 -> #DIV/0! | L8: =K8+L7 -> #DIV/0! | M8: =_xlfn.IFS(L8<80%,"A",L8<=95%,"B",L8>95%,"C") -> #DIV/0!
B9: th желтый Сул | D9: =C9/C$26 -> #DIV/0! | E9: =D9+E8 -> #DIV/0! | F9: =IF(AND(E9<=0),"C",IF(E9<=0.8,"A",IF(E9<=0.95,"B","C"))) -> #DIV/0! | G9: =VLOOKUP(B$4:B$25,I$4:M$25,5,0) -> #DIV/0! | I9: th желтый Сул | K9: =J9/J$26 -> #DIV/0! | L9: =K9+L8 -> #DIV/0! | M9: =_xlfn.IFS(L9<80%,"A",L9<=95%,"B",L9>95%,"C") -> #DIV/0!
B10: flip желтые Сул | D10: =C10/C$26 -> #DIV/0! | E10: =D10+E9 -> #DIV/0! | F10: =IF(AND(E10<=0),"C",IF(E10<=0.8,"A",IF(E10<=0.95,"B","C"))) -> #DIV/0! | G10: =VLOOKUP(B$4:B$25,I$4:M$25,5,0) -> #DIV/0! | I10: flip желтые Сул | K10: =J10/J$26 -> #DIV/0! | L10: =K10+L9 -> #DIV/0! | M10: =_xlfn.IFS(L10<80%,"A",L10<=95%,"B",L10>95%,"C") -> #DIV/0!
B11: MR8854 C2 | D11: =C11/C$26 -> #DIV/0! | E11: =D11+E8 -> #DIV/0! | F11: =IF(AND(E11<=0),"C",IF(E11<=0.8,"A",IF(E11<=0.95,"B","C"))) -> #DIV/0! | G11: =VLOOKUP(B$4:B$25,I$4:M$25,5,0) -> #DIV/0! | I11: MR8854 C2 | K11: =J11/J$26 -> #DIV/0! | L11: =K11+L8 -> #DIV/0! | M11: =_xlfn.IFS(L11<80%,"A",L11<=95%,"B",L11>95%,"C") -> #DIV/0!
B12: MR 1819 черн | D12: =C12/C$26 -> #DIV/0! | E12: =D12+E11 -> #DIV/0! | F12: =IF(AND(E12<=0),"C",IF(E12<=0.8,"A",IF(E12<=0.95,"B","C"))) -> #DIV/0! | G12: =VLOOKUP(B$4:B$25,I$4:M$25,5,0) -> #DIV/0! | I12: MR 1819 черн | K12: =J12/J$26 -> #DIV/0! | L12: =K12+L11 -> #DIV/0! | M12: =_xlfn.IFS(L12<80%,"A",L12<=95%,"B",L12>95%,"C") -> #DIV/0!
B13: MR 1819 корич | D13: =C13/C$26 -> #DIV/0! | E13: =D13+E12 -> #DIV/0! | F13: =IF(AND(E13<=0),"C",IF(E13<=0.8,"A",IF(E13<=0.95,"B","C"))) -> #DIV/0! | G13: =VLOOKUP(B$4:B$25,I$4:M$25,5,0) -> #DIV/0! | I13: MR 1819 корич | K13: =J13/J$26 -> #DIV/0! | L13: =K13+L12 -> #DIV/0! | M13: =_xlfn.IFS(L13<80%,"A",L13<=95%,"B",L13>95%,"C") -> #DIV/0! | P13: A | Q13: 0.8
B14: MR Р1874 черн | D14: =C14/C$26 -> #DIV/0! | E14: =D14+E13 -> #DIV/0! | F14: =IF(AND(E14<=0),"C",IF(E14<=0.8,"A",IF(E14<=0.95,"B","C"))) -> #DIV/0! | G14: =VLOOKUP(B$4:B$25,I$4:M$25,5,0) -> #DIV/0! | I14: MR Р1874 черн | K14: =J14/J$26 -> #DIV/0! | L14: =K14+L13 -> #DIV/0! | M14: =_xlfn.IFS(L14<80%,"A",L14<=95%,"B",L14>95%,"C") -> #DIV/0! | P14: B | Q14: 0.15
B15: MR Р1874 корич | D15: =C15/C$26 -> #DIV/0! | E15: =D15+E14 -> #DIV/0! | F15: =IF(AND(E15<=0),"C",IF(E15<=0.8,"A",IF(E15<=0.95,"B","C"))) -> #DIV/0! | G15: =VLOOKUP(B$4:B$25,I$4:M$25,5,0) -> #DIV/0! | I15: MR Р1874 корич | K15: =J15/J$26 -> #DIV/0! | L15: =K15+L14 -> #DIV/0! | M15: =_xlfn.IFS(L15<80%,"A",L15<=95%,"B",L15>95%,"C") -> #DIV/0! | P15: C | Q15: 0.05
B16: MR Р1886 черн глянец | D16: =C16/C$26 -> #DIV/0! | E16: =D16+E15 -> #DIV/0! | F16: =IF(AND(E16<=0),"C",IF(E16<=0.8,"A",IF(E16<=0.95,"B","C"))) -> #DIV/0! | G16: =VLOOKUP(B$4:B$25,I$4:M$25,5,0) -> #DIV/0! | I16: MR Р1886 черн глянец | K16: =J16/J$26 -> #DIV/0! | L16: =K16+L15 -> #DIV/0! | M16: =_xlfn.IFS(L16<80%,"A",L16<=95%,"B",L16>95%,"C") -> #DIV/0!
B17: MR Р1886 корич | D17: =C17/C$26 -> #DIV/0! | E17: =D17+E16 -> #DIV/0! | F17: =IF(AND(E17<=0),"C",IF(E17<=0.8,"A",IF(E17<=0.95,"B","C"))) -> #DIV/0! | G17: =VLOOKUP(B$4:B$25,I$4:M$25,5,0) -> #DIV/0! | I17: MR Р1886 корич | K17: =J17/J$26 -> #DIV/0! | L17: =K17+L16 -> #DIV/0! | M17: =_xlfn.IFS(L17<80%,"A",L17<=95%,"B",L17>95%,"C") -> #DIV/0!
B18: lux1 | D18: =C18/C$26 -> #DIV/0! | E18: =D18+E17 -> #DIV/0! | F18: =IF(AND(E18<=0),"C",IF(E18<=0.8,"A",IF(E18<=0.95,"B","C"))) -> #DIV/0! | G18: =VLOOKUP(B$4:B$25,I$4:M$25,5,0) -> #DIV/0! | I18: lux1 | K18: =J18/J$26 -> #DIV/0! | L18: =K18+L17 -> #DIV/0! | M18: =_xlfn.IFS(L18<80%,"A",L18<=95%,"B",L18>95%,"C") -> #DIV/0!
B19: lux2 | D19: =C19/C$26 -> #DIV/0! | E19: =D19+E18 -> #DIV/0! | F19: =IF(AND(E19<=0),"C",IF(E19<=0.8,"A",IF(E19<=0.95,"B","C"))) -> #DIV/0! | G19: =VLOOKUP(B$4:B$25,I$4:M$25,5,0) -> #DIV/0! | I19: lux2 | K19: =J19/J$26 -> #DIV/0! | L19: =K19+L18 -> #DIV/0! | M19: =_xlfn.IFS(L19<80%,"A",L19<=95%,"B",L19>95%,"C") -> #DIV/0!
B20: lux3 | D20: =C20/C$26 -> #DIV/0! | E20: =D20+E19 -> #DIV/0! | F20: =IF(AND(E20<=0),"C",IF(E20<=0.8,"A",IF(E20<=0.95,"B","C"))) -> #DIV/0! | G20: =VLOOKUP(B$4:B$25,I$4:M$25,5,0) -> #DIV/0! | I20: lux3 | K20: =J20/J$26 -> #DIV/0! | L20: =K20+L19 -> #DIV/0! | M20: =_xlfn.IFS(L20<80%,"A",L20<=95%,"B",L20>95%,"C") -> #DIV/0!
B21: lux4 | D21: =C21/C$26 -> #DIV/0! | E21: =D21+E20 -> #DIV/0! | F21: =IF(AND(E21<=0),"C",IF(E21<=0.8,"A",IF(E21<=0.95,"B","C"))) -> #DIV/0! | G21: =VLOOKUP(B$4:B$25,I$4:M$25,5,0) -> #DIV/0! | I21: lux4 | K21: =J21/J$26 -> #DIV/0! | L21: =K21+L20 -> #DIV/0! | M21: =_xlfn.IFS(L21<80%,"A",L21<=95%,"B",L21>95%,"C") -> #DIV/0!
B22: lux5 | D22: =C22/C$26 -> #DIV/0! | E22: =D22+E21 -> #DIV/0! | F22: =IF(AND(E22<=0),"C",IF(E22<=0.8,"A",IF(E22<=0.95,"B","C"))) -> #DIV/0! | G22: =VLOOKUP(B$4:B$25,I$4:M$25,5,0) -> #DIV/0! | I22: lux5 | K22: =J22/J$26 -> #DIV/0! | L22: =K22+L21 -> #DIV/0! | M22: =_xlfn.IFS(L22<80%,"A",L22<=95%,"B",L22>95%,"C") -> #DIV/0!
B23: lux6 | D23: =C23/C$26 -> #DIV/0! | E23: =D23+E22 -> #DIV/0! | F23: =IF(AND(E23<=0),"C",IF(E23<=0.8,"A",IF(E23<=0.95,"B","C"))) -> #DIV/0! | G23: =VLOOKUP(B$4:B$25,I$4:M$25,5,0) -> #DIV/0! | I23: lux6 | K23: =J23/J$26 -> #DIV/0! | L23: =K23+L22 -> #DIV/0! | M23: =_xlfn.IFS(L23<80%,"A",L23<=95%,"B",L23>95%,"C") -> #DIV/0!
B24: lux7 | D24: =C24/C$26 -> #DIV/0! | E24: =D24+E23 -> #DIV/0! | F24: =IF(AND(E24<=0),"C",IF(E24<=0.8,"A",IF(E24<=0.95,"B","C"))) -> #DIV/0! | G24: =VLOOKUP(B$4:B$25,I$4:M$25,5,0) -> #DIV/0! | I24: lux7 | K24: =J24/J$26 -> #DIV/0! | L24: =K24+L23 -> #DIV/0! | M24: =_xlfn.IFS(L24<80%,"A",L24<=95%,"B",L24>95%,"C") -> #DIV/0!
B25: lux8 | D25: =C25/C$26 -> #DIV/0! | E25: =D25+E24 -> #DIV/0! | F25: =IF(AND(E25<=0),"C",IF(E25<=0.8,"A",IF(E25<=0.95,"B","C"))) -> #DIV/0! | G25: =VLOOKUP(B$4:B$25,I$4:M$25,5,0) -> #DIV/0! | I25: lux8 | K25: =J25/J$26 -> #DIV/0! | L25: =K25+L24 -> #DIV/0! | M25: =_xlfn.IFS(L25<80%,"A",L25<=95%,"B",L25>95%,"C") -> #DIV/0!
C26: =SUM(C4:C25) -> 0 | D26: =SUM(D4:D25) -> #DIV/0! | J26: =SUM(J4:J25) -> 0 | K26: =SUM(K4:K25) -> #DIV/0!
B28: ТУНИКИ
C29: Прибыль | D29: % прибыль | E29: Доля | F29: ABC прибыль | G29: ABC кол-во | J29: Кол-во | K29: % кол-во | L29: Доля | M29: ABC кол-во
B30: tunika02 оливковая с руч вышивкой | D30: =C30/C$50 -> #DIV/0! | E30: =D30 -> #DIV/0! | F30: =IF(AND(E30<=0),"C",IF(E30<=0.8,"A",IF(E30<=0.95,"B","C"))) -> #DIV/0! | G30: =VLOOKUP(B$30:B$50,I$30:M$50,5,0) -> #DIV/0! | I30: tunika02 оливковая с руч вышивкой | K30: =J30/J$50 -> #DIV/0! | L30: =K30 -> #DIV/0! | M30: =_xlfn.IFS(L30<80%,"A",L30<=95%,"B",L30>95%,"C") -> #DIV/0!
B31: tunika03 черная распашная | D31: =C31/C$50 -> #DIV/0! | E31: =D31+E30 -> #DIV/0! | F31: =IF(AND(E31<=0),"C",IF(E31<=0.8,"A",IF(E31<=0.95,"B","C"))) -> #DIV/0! | G31: =VLOOKUP(B$30:B$50,I$30:M$50,5,0) -> #DIV/0! | I31: tunika03 черная распашная | K31: =J31/J$50 -> #DIV/0! | L31: =K31+L30 -> #DIV/0! | M31: =_xlfn.IFS(L31<80%,"A",L31<=95%,"B",L31>95%,"C") -> #DIV/0!
B32: tunika05 белая распашная | D32: =C32/C$50 -> #DIV/0! | E32: =D32+E31 -> #DIV/0! | F32: =IF(AND(E32<=0),"C",IF(E32<=0.8,"A",IF(E32<=0.95,"B","C"))) -> #DIV/0! | G32: =VLOOKUP(B$30:B$50,I$30:M$50,5,0) -> #DIV/0! | I32: tunika05 белая распашная | K32: =J32/J$50 -> #DIV/0! | L32: =K32+L31 -> #DIV/0! | M32: =_xlfn.IFS(L32<80%,"A",L32<=95%,"B",L32>95%,"C") -> #DIV/0!
B33: tunika06 белая | D33: =C33/C$50 -> #DIV/0! | E33: =D33+E32 -> #DIV/0! | F33: =IF(AND(E33<=0),"C",IF(E33<=0.8,"A",IF(E33<=0.95,"B","C"))) -> #DIV/0! | G33: =VLOOKUP(B$30:B$50,I$30:M$50,5,0) -> #DIV/0! | I33: tunika06 белая | K33: =J33/J$50 -> #DIV/0! | L33: =K33+L32 -> #DIV/0! | M33: =_xlfn.IFS(L33<80%,"A",L33<=95%,"B",L33>95%,"C") -> #DIV/0!
B34: tunika06 черная | D34: =C34/C$50 -> #DIV/0! | E34: =D34+E33 -> #DIV/0! | F34: =IF(AND(E34<=0),"C",IF(E34<=0.8,"A",IF(E34<=0.95,"B","C"))) -> #DIV/0! | G34: =VLOOKUP(B$30:B$50,I$30:M$50,5,0) -> #DIV/0! | I34: tunika06 черная | K34: =J34/J$50 -> #DIV/0! | L34: =K34+L33 -> #DIV/0! | M34: =_xlfn.IFS(L34<80%,"A",L34<=95%,"B",L34>95%,"C") -> #DIV/0!
B35: tunika07 кружево | D35: =C35/C$50 -> #DIV/0! | E35: =D35+E34 -> #DIV/0! | F35: =IF(AND(E35<=0),"C",IF(E35<=0.8,"A",IF(E35<=0.95,"B","C"))) -> #DIV/0! | G35: =VLOOKUP(B$30:B$50,I$30:M$50,5,0) -> #DIV/0! | I35: tunika07 кружево | K35: =J35/J$50 -> #DIV/0! | L35: =K35+L34 -> #DIV/0! | M35: =_xlfn.IFS(L35<80%,"A",L35<=95%,"B",L35>95%,"C") -> #DIV/0!
B36: tunika08 белая | D36: =C36/C$50 -> #DIV/0! | E36: =D36+E35 -> #DIV/0! | F36: =IF(AND(E36<=0),"C",IF(E36<=0.8,"A",IF(E36<=0.95,"B","C"))) -> #DIV/0! | G36: =VLOOKUP(B$30:B$50,I$30:M$50,5,0) -> #DIV/0! | I36: tunika08 белая | K36: =J36/J$50 -> #DIV/0! | L36: =K36+L35 -> #DIV/0! | M36: =_xlfn.IFS(L36<80%,"A",L36<=95%,"B",L36>95%,"C") -> #DIV/0!
B37: tunika08 черная | D37: =C37/C$50 -> #DIV/0! | E37: =D37+E36 -> #DIV/0! | F37: =IF(AND(E37<=0),"C",IF(E37<=0.8,"A",IF(E37<=0.95,"B","C"))) -> #DIV/0! | G37: =VLOOKUP(B$30:B$50,I$30:M$50,5,0) -> #DIV/0! | I37: tunika08 черная | K37: =J37/J$50 -> #DIV/0! | L37: =K37+L36 -> #DIV/0! | M37: =_xlfn.IFS(L37<80%,"A",L37<=95%,"B",L37>95%,"C") -> #DIV/0!
B38: tunika08 зеленая | D38: =C38/C$50 -> #DIV/0! | E38: =D38+E37 -> #DIV/0! | F38: =IF(AND(E38<=0),"C",IF(E38<=0.8,"A",IF(E38<=0.95,"B","C"))) -> #DIV/0! | G38: =VLOOKUP(B$30:B$50,I$30:M$50,5,0) -> #DIV/0! | I38: tunika08 зеленая | K38: =J38/J$50 -> #DIV/0! | L38: =K38+L37 -> #DIV/0! | M38: =_xlfn.IFS(L38<80%,"A",L38<=95%,"B",L38>95%,"C") -> #DIV/0!
B39: tunika09 кимоно | D39: =C39/C$50 -> #DIV/0! | E39: =D39+E38 -> #DIV/0! | F39: =IF(AND(E39<=0),"C",IF(E39<=0.8,"A",IF(E39<=0.95,"B","C"))) -> #DIV/0! | G39: =VLOOKUP(B$30:B$50,I$30:M$50,5,0) -> #DIV/0! | I39: tunika09 кимоно | K39: =J39/J$50 -> #DIV/0! | L39: =K39+L38 -> #DIV/0! | M39: =_xlfn.IFS(L39<80%,"A",L39<=95%,"B",L39>95%,"C") -> #DIV/0!
B40: tunika10 кимоно ч/б | D40: =C40/C$50 -> #DIV/0! | E40: =D40+E39 -> #DIV/0! | F40: =IF(AND(E40<=0),"C",IF(E40<=0.8,"A",IF(E40<=0.95,"B","C"))) -> #DIV/0! | G40: =VLOOKUP(B$30:B$50,I$30:M$50,5,0) -> #DIV/0! | I40: tunika10 кимоно ч/б | K40: =J40/J$50 -> #DIV/0! | L40: =K40+L39 -> #DIV/0! | M40: =_xlfn.IFS(L40<80%,"A",L40<=95%,"B",L40>95%,"C") -> #DIV/0!
B41: tunika11 халат зеленая | D41: =C41/C$50 -> #DIV/0! | E41: =D41+E40 -> #DIV/0! | F41: =IF(AND(E41<=0),"C",IF(E41<=0.8,"A",IF(E41<=0.95,"B","C"))) -> #DIV/0! | G41: =VLOOKUP(B$30:B$50,I$30:M$50,5,0) -> #DIV/0! | I41: tunika11 халат зеленая | K41: =J41/J$50 -> #DIV/0! | L41: =K41+L40 -> #DIV/0! | M41: =_xlfn.IFS(L41<80%,"A",L41<=95%,"B",L41>95%,"C") -> #DIV/0!
B42: tunika12 халат белая | D42: =C42/C$50 -> #DIV/0! | E42: =D42+E41 -> #DIV/0! | F42: =IF(AND(E42<=0),"C",IF(E42<=0.8,"A",IF(E42<=0.95,"B","C"))) -> #DIV/0! | G42: =VLOOKUP(B$30:B$50,I$30:M$50,5,0) -> #DIV/0! | I42: tunika12 халат белая | K42: =J42/J$50 -> #DIV/0! | L42: =K42+L41 -> #DIV/0! | M42: =_xlfn.IFS(L42<80%,"A",L42<=95%,"B",L42>95%,"C") -> #DIV/0!
... B49: tunika16 сетка черная | D49: =C49/C$50 -> #DIV/0! | E49: =D49+E48 -> #DIV/0! | F49: =IF(AND(E49<=0),"C",IF(E49<=0.8,"A",IF(E49<=0.95,"B","C"))) -> #DIV/0! | G49: =VLOOKUP(B$30:B$50,I$30:M$50,5,0) -> #DIV/0! | I49: tunika16 сетка черная | K49: =J49/J$50 -> #DIV/0! | L49: =K49+L48 -> #DIV/0! | M49: =_xlfn.IFS(L49<80%,"A",L49<=95%,"B",L49>95%,"C") -> #DIV/0!
C50: =SUM(C30:C49) -> 0 | D50: =SUM(D30:D49) -> #DIV/0! | J50: =SUM(J30:J49) -> 0 | K50: =SUM(K30:K49) -> #DIV/0!

Sheet АВС 19-25.01
B2: ОЧКИ
C3: Прибыль | D3: % прибыль | E3: Доля | F3: ABC прибыль | G3: ABC кол-во | J3: Кол-во | K3: % кол-во | L3: Доля | M3: ABC кол-во
B4: черные с железкой классика | C4: ='Юнит 19-25.01'!AE3 -> 5864.4518 | D4: =C4/C$26 -> 0.58621262 | E4: =D4 -> 0.58621262 | F4: =IF(AND(E4<=0),"C",IF(E4<=0.8,"A",IF(E4<=0.95,"B","C"))) -> A | G4: =VLOOKUP(B$4:B$25,I$4:M$25,5,0) -> A | I4: черные с железкой классика | J4: ='Юнит 19-25.01'!R3 -> 38 | K4: =J4/J$26 -> 0.6031746 | L4: =K4 -> 0.6031746 | M4: =_xlfn.IFS(L4<80%,"A",L4<=95%,"B",L4>95%,"C") -> A
B5: qs коричневые | C5: ='Юнит 19-25.01'!AE7 -> 2637.98 | D5: =C5/C$26 -> 0.26369339 | E5: =D5+E4 -> 0.84990601 | F5: =IF(AND(E5<=0),"C",IF(E5<=0.8,"A",IF(E5<=0.95,"B","C"))) -> B | G5: =VLOOKUP(B$4:B$25,I$4:M$25,5,0) -> A | I5: qs коричневые | J5: ='Юнит 19-25.01'!R7 -> 6 | K5: =J5/J$26 -> 0.095238095 | L5: =K5+L4 -> 0.6984127 | M5: =_xlfn.IFS(L5<80%,"A",L5<=95%,"B",L5>95%,"C") -> A
B6: lux3 | C6: ='Юнит 19-25.01'!AE19 -> 914.65 | D6: =C6/C$26 -> 0.091428728 | E6: =D6+E5 -> 0.94133474 | F6: =IF(AND(E6<=0),"C",IF(E6<=0.8,"A",IF(E6<=0.95,"B","C"))) -> B | G6: =VLOOKUP(B$4:B$25,I$4:M$25,5,0) -> C | I6: qs черные | J6: ='Юнит 19-25.01'!R4 -> 5 | K6: =J6/J$26 -> 0.079365079 | L6: =K6+L5 -> 0.77777778 | M6: =_xlfn.IFS(L6<80%,"A",L6<=95%,"B",L6>95%,"C") -> A
B7: th желтый Сул | C7: ='Юнит 19-25.01'!AE8 -> 606.7 | D7: =C7/C$26 -> 0.060645941 | E7: =D7+E6 -> 1.0019807 | F7: =IF(AND(E7<=0),"C",IF(E7<=0.8,"A",IF(E7<=0.95,"B","C"))) -> C | G7: =VLOOKUP(B$4:B$25,I$4:M$25,5,0) -> C | I7: flip желтые Сул | J7: ='Юнит 19-25.01'!R9 -> 5 | K7: =J7/J$26 -> 0.079365079 | L7: =K7+L6 -> 0.85714286 | M7: =_xlfn.IFS(L7<80%,"A",L7<=95%,"B",L7>95%,"C") -> B
B8: MR Р1874 корич | C8: ='Юнит 19-25.01'!AE14 -> 490.89 | D8: =C8/C$26 -> 0.049069533 | E8: =D8+E7 -> 1.0510502 | F8: =IF(AND(E8<=0),"C",IF(E8<=0.8,"A",IF(E8<=0.95,"B","C"))) -> C | G8: =VLOOKUP(B$4:B$25,I$4:M$25,5,0) -> B | I8: MR Р1874 черн | J8: ='Юнит 19-25.01'!R13 -> 3 | K8: =J8/J$26 -> 0.047619048 | L8: =K8+L7 -> 0.9047619 | M8: =_xlfn.IFS(L8<80%,"A",L8<=95%,"B",L8>95%,"C") -> B
B9: MR 1819 корич | C9: ='Юнит 19-25.01'!AE12 -> 322.02 | D9: =C9/C$26 -> 0.03218923 | E9: =D9+E8 -> 1.0832394 | F9: =IF(AND(E9<=0),"C",IF(E9<=0.8,"A",IF(E9<=0.95,"B","C"))) -> C | G9: =VLOOKUP(B$4:B$25,I$4:M$25,5,0) -> B | I9: qs желтые | J9: ='Юнит 19-25.01'!R6 -> 2 | K9: =J9/J$26 -> 0.031746032 | L9: =K9+L8 -> 0.93650794 | M9: =_xlfn.IFS(L9<80%,"A",L9<=95%,"B",L9>95%,"C") -> B
B10: MR Р1874 черн | C10: ='Юнит 19-25.01'!AE13 -> 420.19 | D10: =C10/C$26 -> 0.042002337 | E10: =D10+E9 -> 1.1252418 | F10: =IF(AND(E10<=0),"C",IF(E10<=0.8,"A",IF(E10<=0.95,"B","C"))) -> C | G10: =VLOOKUP(B$4:B$25,I$4:M$25,5,0) -> B | I10: th желтый Сул | J10: ='Юнит 19-25.01'!R8 -> 1 | K10: =J10/J$26 -> 0.015873016 | L10: =K10+L9 -> 0.95238095 | M10: =_xlfn.IFS(L10<80%,"A",L10<=95%,"B",L10>95%,"C") -> C
B11: qs черные | C11: ='Юнит 19-25.01'!AE4 -> 591.94117 | D11: =C11/C$26 -> 0.059170643 | E11: =D11+E8 -> 1.1102209 | F11: =IF(AND(E11<=0),"C",IF(E11<=0.8,"A",IF(E11<=0.95,"B","C"))) -> C | G11: =VLOOKUP(B$4:B$25,I$4:M$25,5,0) -> A | I11: MR 1819 корич | J11: ='Юнит 19-25.01'!R12 -> 1 | K11: =J11/J$26 -> 0.015873016 | L11: =K11+L8 -> 0.92063492 | M11: =_xlfn.IFS(L11<80%,"A",L11<=95%,"B",L11>95%,"C") -> B
B12: qs синие | C12: ='Юнит 19-25.01'!AE5 -> 0 | D12: =C12/C$26 -> 0 | E12: =D12+E11 -> 1.1102209 | F12: =IF(AND(E12<=0),"C",IF(E12<=0.8,"A",IF(E12<=0.95,"B","C"))) -> C | G12: =VLOOKUP(B$4:B$25,I$4:M$25,5,0) -> C | I12: MR Р1874 корич | J12: ='Юнит 19-25.01'!R14 -> 1 | K12: =J12/J$26 -> 0.015873016 | L12: =K12+L11 -> 0.93650794 | M12: =_xlfn.IFS(L12<80%,"A",L12<=95%,"B",L12>95%,"C") -> B
B13: lux1 | C13: ='Юнит 19-25.01'!AE17 -> 0 | D13: =C13/C$26 -> 0 | E13: =D13+E12 -> 1.1102209 | F13: =IF(AND(E13<=0),"C",IF(E13<=0.8,"A",IF(E13<=0.95,"B","C"))) -> C | G13: =VLOOKUP(B$4:B$25,I$4:M$25,5,0) -> C | I13: lux3 | J13: ='Юнит 19-25.01'!R19 -> 1 | K13: =J13/J$26 -> 0.015873016 | L13: =K13+L12 -> 0.95238095 | M13: =_xlfn.IFS(L13<80%,"A",L13<=95%,"B",L13>95%,"C") -> C | P13: A | Q13: 0.8
B14: lux2 | C14: ='Юнит 19-25.01'!AE18 -> 0 | D14: =C14/C$26 -> 0 | E14: =D14+E13 -> 1.1102209 | F14: =IF(AND(E14<=0),"C",IF(E14<=0.8,"A",IF(E14<=0.95,"B","C"))) -> C | G14: =VLOOKUP(B$4:B$25,I$4:M$25,5,0) -> C | I14: qs синие | J14: ='Юнит 19-25.01'!R5 -> 0 | K14: =J14/J$26 -> 0 | L14: =K14+L13 -> 0.95238095 | M14: =_xlfn.IFS(L14<80%,"A",L14<=95%,"B",L14>95%,"C") -> C | P14: B | Q14: 0.15
B15: lux4 | C15: ='Юнит 19-25.01'!AE20 -> 0 | D15: =C15/C$26 -> 0 | E15: =D15+E14 -> 1.1102209 | F15: =IF(AND(E15<=0),"C",IF(E15<=0.8,"A",IF(E15<=0.95,"B","C"))) -> C | G15: =VLOOKUP(B$4:B$25,I$4:M$25,5,0) -> C | I15: MR8854 C2 | J15: ='Юнит 19-25.01'!R10 -> 0 | K15: =J15/J$26 -> 0 | L15: =K15+L14 -> 0.95238095 | M15: =_xlfn.IFS(L15<80%,"A",L15<=95%,"B",L15>95%,"C") -> C | P15: C | Q15: 0.05
B16: lux5 | C16: ='Юнит 19-25.01'!AE21 -> 0 | D16: =C16/C$26 -> 0 | E16: =D16+E15 -> 1.1102209 | F16: =IF(AND(E16<=0),"C",IF(E16<=0.8,"A",IF(E16<=0.95,"B","C"))) -> C | G16: =VLOOKUP(B$4:B$25,I$4:M$25,5,0) -> C | I16: MR 1819 черн | J16: ='Юнит 19-25.01'!R11 -> 0 | K16: =J16/J$26 -> 0 | L16: =K16+L15 -> 0.95238095 | M16: =_xlfn.IFS(L16<80%,"A",L16<=95%,"B",L16>95%,"C") -> C
B17: lux6 | C17: ='Юнит 19-25.01'!AE22 -> 0 | D17: =C17/C$26 -> 0 | E17: =D17+E16 -> 1.1102209 | F17: =IF(AND(E17<=0),"C",IF(E17<=0.8,"A",IF(E17<=0.95,"B","C"))) -> C | G17: =VLOOKUP(B$4:B$25,I$4:M$25,5,0) -> C | I17: MR Р1886 черн глянец | J17: ='Юнит 19-25.01'!R15 -> 0 | K17: =J17/J$26 -> 0 | L17: =K17+L16 -> 0.95238095 | M17: =_xlfn.IFS(L17<80%,"A",L17<=95%,"B",L17>95%,"C") -> C
B18: lux7 | C18: ='Юнит 19-25.01'!AE23 -> 0 | D18: =C18/C$26 -> 0 | E18: =D18+E17 -> 1.1102209 | F18: =IF(AND(E18<=0),"C",IF(E18<=0.8,"A",IF(E18<=0.95,"B","C"))) -> C | G18: =VLOOKUP(B$4:B$25,I$4:M$25,5,0) -> C | I18: MR Р1886 корич | J18: ='Юнит 19-25.01'!R16 -> 0 | K18: =J18/J$26 -> 0 | L18: =K18+L17 -> 0.95238095 | M18: =_xlfn.IFS(L18<80%,"A",L18<=95%,"B",L18>95%,"C") -> C
B19: lux8 | C19: ='Юнит 19-25.01'!AE24 -> 0 | D19: =C19/C$26 -> 0 | E19: =D19+E18 -> 1.1102209 | F19: =IF(AND(E19<=0),"C",IF(E19<=0.8,"A",IF(E19<=0.95,"B","C"))) -> C | G19: =VLOOKUP(B$4:B$25,I$4:M$25,5,0) -> C | I19: lux1 | J19: ='Юнит 19-25.01'!R17 -> 0 | K19: =J19/J$26 -> 0 | L19: =K19+L18 -> 0.95238095 | M19: =_xlfn.IFS(L19<80%,"A",L19<=95%,"B",L19>95%,"C") -> C
B20: MR8854 C2 | C20: ='Юнит 19-25.01'!AE10 -> -93.54 | D20: =C20/C$26 -> -0.0093502906 | E20: =D20+E19 -> 1.1008706 | F20: =IF(AND(E20<=0),"C",IF(E20<=0.8,"A",IF(E20<=0.95,"B","C"))) -> C | G20: =VLOOKUP(B$4:B$25,I$4:M$25,5,0) -> C | I20: lux2 | J20: ='Юнит 19-25.01'!R18 -> 0 | K20: =J20/J$26 -> 0 | L20: =K20+L19 -> 0.95238095 | M20: =_xlfn.IFS(L20<80%,"A",L20<=95%,"B",L20>95%,"C") -> C
B21: MR 1819 черн | C21: ='Юнит 19-25.01'!AE11 -> -93.54 | D21: =C21/C$26 -> -0.0093502906 | E21: =D21+E20 -> 1.0915203 | F21: =IF(AND(E21<=0),"C",IF(E21<=0.8,"A",IF(E21<=0.95,"B","C"))) -> C | G21: =VLOOKUP(B$4:B$25,I$4:M$25,5,0) -> C | I21: lux4 | J21: ='Юнит 19-25.01'!R20 -> 0 | K21: =J21/J$26 -> 0 | L21: =K21+L20 -> 0.95238095 | M21: =_xlfn.IFS(L21<80%,"A",L21<=95%,"B",L21>95%,"C") -> C
B22: MR Р1886 черн глянец | C22: ='Юнит 19-25.01'!AE15 -> -93.54 | D22: =C22/C$26 -> -0.0093502906 | E22: =D22+E21 -> 1.08217 | F22: =IF(AND(E22<=0),"C",IF(E22<=0.8,"A",IF(E22<=0.95,"B","C"))) -> C | G22: =VLOOKUP(B$4:B$25,I$4:M$25,5,0) -> C | I22: lux5 | J22: ='Юнит 19-25.01'!R21 -> 0 | K22: =J22/J$26 -> 0 | L22: =K22+L21 -> 0.95238095 | M22: =_xlfn.IFS(L22<80%,"A",L22<=95%,"B",L22>95%,"C") -> C
B23: MR Р1886 корич | C23: ='Юнит 19-25.01'!AE16 -> -328.67 | D23: =C23/C$26 -> -0.032853966 | E23: =D23+E22 -> 1.049316 | F23: =IF(AND(E23<=0),"C",IF(E23<=0.8,"A",IF(E23<=0.95,"B","C"))) -> C | G23: =VLOOKUP(B$4:B$25,I$4:M$25,5,0) -> C | I23: lux6 | J23: ='Юнит 19-25.01'!R22 -> 0 | K23: =J23/J$26 -> 0 | L23: =K23+L22 -> 0.95238095 | M23: =_xlfn.IFS(L23<80%,"A",L23<=95%,"B",L23>95%,"C") -> C
B24: flip желтые Сул | C24: ='Юнит 19-25.01'!AE9 -> 72.94261 | D24: =C24/C$26 -> 0.0072913684 | E24: =D24+E23 -> 1.0566074 | F24: =IF(AND(E24<=0),"C",IF(E24<=0.8,"A",IF(E24<=0.95,"B","C"))) -> C | G24: =VLOOKUP(B$4:B$25,I$4:M$25,5,0) -> B | I24: lux7 | J24: ='Юнит 19-25.01'!R23 -> 0 | K24: =J24/J$26 -> 0 | L24: =K24+L23 -> 0.95238095 | M24: =_xlfn.IFS(L24<80%,"A",L24<=95%,"B",L24>95%,"C") -> C
B25: qs желтые | C25: ='Юнит 19-25.01'!AE6 -> -1308.5084 | D25: =C25/C$26 -> -0.13079895 | E25: =D25+E24 -> 0.92580843 | F25: =IF(AND(E25<=0),"C",IF(E25<=0.8,"A",IF(E25<=0.95,"B","C"))) -> B | G25: =VLOOKUP(B$4:B$25,I$4:M$25,5,0) -> B | I25: lux8 | J25: ='Юнит 19-25.01'!R24 -> 0 | K25: =J25/J$26 -> 0 | L25: =K25+L24 -> 0.95238095 | M25: =_xlfn.IFS(L25<80%,"A",L25<=95%,"B",L25>95%,"C") -> C
C26: =SUM(C4:C25) -> 10003.967 | D26: =SUM(D4:D25) -> 1 | J26: =SUM(J4:J25) -> 63 | K26: =SUM(K4:K25) -> 1
B28: ТУНИКИ
C29: Прибыль | D29: % прибыль | E29: Доля | F29: ABC прибыль | G29: ABC кол-во | J29: Кол-во | K29: % кол-во | L29: Доля | M29: ABC кол-во
B30: tunika15 кимоно песочная | C30: ='Юнит 19-25.01'!AE45 -> 6439.7034 | D30: =C30/C$50 -> 1.6022372 | E30: =D30 -> 1.6022372 | F30: =IF(AND(E30<=0),"C",IF(E30<=0.8,"A",IF(E30<=0.95,"B","C"))) -> C | G30: =VLOOKUP(B$30:B$50,I$30:M$50,5,0) -> A | I30: tunika15 кимоно песочная | J30: ='Юнит 19-25.01'!R45 -> 8 | K30: =J30/J$50 -> 0.57142857 | L30: =K30 -> 0.57142857 | M30: =_xlfn.IFS(L30<80%,"A",L30<=95%,"B",L30>95%,"C") -> A
B31: tunika09 кимоно | C31: ='Юнит 19-25.01'!AE37 -> 2688.14 | D31: =C31/C$50 -> 0.6688255 | E31: =D31+E30 -> 2.2710627 | F31: =IF(AND(E31<=0),"C",IF(E31<=0.8,"A",IF(E31<=0.95,"B","C"))) -> C | G31: =VLOOKUP(B$30:B$50,I$30:M$50,5,0) -> B | I31: tunika15 кимоно бирюза | J31: ='Юнит 19-25.01'!R44 -> 3 | K31: =J31/J$50 -> 0.21428571 | L31: =K31+L30 -> 0.78571429 | M31: =_xlfn.IFS(L31<80%,"A",L31<=95%,"B",L31>95%,"C") -> A
B32: tunika06 белая | C32: ='Юнит 19-25.01'!AE31 -> 1234.21 | D32: =C32/C$50 -> 0.30707892 | E32: =D32+E31 -> 2.5781416 | F32: =IF(AND(E32<=0),"C",IF(E32<=0.8,"A",IF(E32<=0.95,"B","C"))) -> C | G32: =VLOOKUP(B$30:B$50,I$30:M$50,5,0) -> C | I32: tunika09 кимоно | J32: ='Юнит 19-25.01'!R37 -> 2 | K32: =J32/J$50 -> 0.14285714 | L32: =K32+L31 -> 0.92857143 | M32: =_xlfn.IFS(L32<80%,"A",L32<=95%,"B",L32>95%,"C") -> B
B33: tunika07 кружево | C33: ='Юнит 19-25.01'!AE33 -> 848.44 | D33: =C33/C$50 -> 0.21109701 | E33: =D33+E32 -> 2.7892386 | F33: =IF(AND(E33<=0),"C",IF(E33<=0.8,"A",IF(E33<=0.95,"B","C"))) -> C | G33: =VLOOKUP(B$30:B$50,I$30:M$50,5,0) -> C | I33: tunika06 белая | J33: ='Юнит 19-25.01'!R31 -> 1 | K33: =J33/J$50 -> 0.071428571 | L33: =K33+L32 -> 1 | M33: =_xlfn.IFS(L33<80%,"A",L33<=95%,"B",L33>95%,"C") -> C
B34: tunika03 черная распашная | C34: ='Юнит 19-25.01'!AE29 -> 0 | D34: =C34/C$50 -> 0 | E34: =D34+E33 -> 2.7892386 | F34: =IF(AND(E34<=0),"C",IF(E34<=0.8,"A",IF(E34<=0.95,"B","C"))) -> C | G34: =VLOOKUP(B$30:B$50,I$30:M$50,5,0) -> C | I34: tunika07 кружево | J34: ='Юнит 19-25.01'!R33 -> 1 | K34: =J34/J$50 -> 0.071428571 | L34: =K34+L33 -> 1.0714286 | M34: =_xlfn.IFS(L34<80%,"A",L34<=95%,"B",L34>95%,"C") -> C
B35: tunika05 белая распашная | C35: ='Юнит 19-25.01'!AE30 -> 0 | D35: =C35/C$50 -> 0 | E35: =D35+E34 -> 2.7892386 | F35: =IF(AND(E35<=0),"C",IF(E35<=0.8,"A",IF(E35<=0.95,"B","C"))) -> C | G35: =VLOOKUP(B$30:B$50,I$30:M$50,5,0) -> C | I35: tunika02 оливковая с руч вышивкой | J35: ='Юнит 19-25.01'!R28 -> 0 | K35: =J35/J$50 -> 0 | L35: =K35+L34 -> 1.0714286 | M35: =_xlfn.IFS(L35<80%,"A",L35<=95%,"B",L35>95%,"C") -> C
B36: tunika06 черная | C36: ='Юнит 19-25.01'!AE32 -> 0 | D36: =C36/C$50 -> 0 | E36: =D36+E35 -> 2.7892386 | F36: =IF(AND(E36<=0),"C",IF(E36<=0.8,"A",IF(E36<=0.95,"B","C"))) -> C | G36: =VLOOKUP(B$30:B$50,I$30:M$50,5,0) -> C | I36: tunika03 черная распашная | J36: ='Юнит 19-25.01'!R29 -> 0 | K36: =J36/J$50 -> 0 | L36: =K36+L35 -> 1.0714286 | M36: =_xlfn.IFS(L36<80%,"A",L36<=95%,"B",L36>95%,"C") -> C
B37: tunika08 белая | C37: ='Юнит 19-25.01'!AE34 -> 0 | D37: =C37/C$50 -> 0 | E37: =D37+E36 -> 2.7892386 | F37: =IF(AND(E37<=0),"C",IF(E37<=0.8,"A",IF(E37<=0.95,"B","C"))) -> C | G37: =VLOOKUP(B$30:B$50,I$30:M$50,5,0) -> C | I37: tunika05 белая распашная | J37: ='Юнит 19-25.01'!R30 -> 0 | K37: =J37/J$50 -> 0 | L37: =K37+L36 -> 1.0714286 | M37: =_xlfn.IFS(L37<80%,"A",L37<=95%,"B",L37>95%,"C") -> C
B38: tunika08 черная | C38: ='Юнит 19-25.01'!AE35 -> 0 | D38: =C38/C$50 -> 0 | E38: =D38+E37 -> 2.7892386 | F38: =IF(AND(E38<=0),"C",IF(E38<=0.8,"A",IF(E38<=0.95,"B","C"))) -> C | G38: =VLOOKUP(B$30:B$50,I$30:M$50,5,0) -> C | I38: tunika06 черная | J38: ='Юнит 19-25.01'!R32 -> 0 | K38: =J38/J$50 -> 0 | L38: =K38+L37 -> 1.0714286 | M38: =_xlfn.IFS(L38<80%,"A",L38<=95%,"B",L38>95%,"C") -> C
B39: tunika11 халат зеленая | C39: ='Юнит 19-25.01'!AE39 -> 0 | D39: =C39/C$50 -> 0 | E39: =D39+E38 -> 2.7892386 | F39: =IF(AND(E39<=0),"C",IF(E39<=0.8,"A",IF(E39<=0.95,"B","C"))) -> C | G39: =VLOOKUP(B$30:B$50,I$30:M$50,5,0) -> C | I39: tunika08 белая | J39: ='Юнит 19-25.01'!R34 -> 0 | K39: =J39/J$50 -> 0 | L39: =K39+L38 -> 1.0714286 | M39: =_xlfn.IFS(L39<80%,"A",L39<=95%,"B",L39>95%,"C") -> C
B40: tunika12 халат белая | C40: ='Юнит 19-25.01'!AE40 -> 0 | D40: =C40/C$50 -> 0 | E40: =D40+E39 -> 2.7892386 | F40: =IF(AND(E40<=0),"C",IF(E40<=0.8,"A",IF(E40<=0.95,"B","C"))) -> C | G40: =VLOOKUP(B$30:B$50,I$30:M$50,5,0) -> C | I40: tunika08 черная | J40: ='Юнит 19-25.01'!R35 -> 0 | K40: =J40/J$50 -> 0 | L40: =K40+L39 -> 1.0714286 | M40: =_xlfn.IFS(L40<80%,"A",L40<=95%,"B",L40>95%,"C") -> C
B41: tunika13 халат черная | C41: ='Юнит 19-25.01'!AE41 -> 0 | D41: =C41/C$50 -> 0 | E41: =D41+E40 -> 2.7892386 | F41: =IF(AND(E41<=0),"C",IF(E41<=0.8,"A",IF(E41<=0.95,"B","C"))) -> C | G41: =VLOOKUP(B$30:B$50,I$30:M$50,5,0) -> C | I41: tunika08 зеленая | J41: ='Юнит 19-25.01'!R36 -> 0 | K41: =J41/J$50 -> 0 | L41: =K41+L40 -> 1.0714286 | M41: =_xlfn.IFS(L41<80%,"A",L41<=95%,"B",L41>95%,"C") -> C
B42: tunika14 халат с разрезами белая | C42: ='Юнит 19-25.01'!AE42 -> 0 | D42: =C42/C$50 -> 0 | E42: =D42+E41 -> 2.7892386 | F42: =IF(AND(E42<=0),"C",IF(E42<=0.8,"A",IF(E42<=0.95,"B","C"))) -> C | G42: =VLOOKUP(B$30:B$50,I$30:M$50,5,0) -> C | I42: tunika11 халат зеленая | J42: ='Юнит 19-25.01'!R39 -> 0 | K42: =J42/J$50 -> 0 | L42: =K42+L41 -> 1.0714286 | M42: =_xlfn.IFS(L42<80%,"A",L42<=95%,"B",L42>95%,"C") -> C
B43: tunika14 халат с разрезами черный | C43: ='Юнит 19-25.01'!AE43 -> 0 | D43: =C43/C$50 -> 0 | E43: =D43+E42 -> 2.7892386 | F43: =IF(AND(E43<=0),"C",IF(E43<=0.8,"A",IF(E43<=0.95,"B","C"))) -> C | G43: =VLOOKUP(B$30:B$50,I$30:M$50,5,0) -> C | I43: tunika12 халат белая | J43: ='Юнит 19-25.01'!R40 -> 0 | K43: =J43/J$50 -> 0 | L43: =K43+L42 -> 1.0714286 | M43: =_xlfn.IFS(L43<80%,"A",L43<=95%,"B",L43>95%,"C") -> C
B44: tunika16 сетка черная | C44: ='Юнит 19-25.01'!AE47 -> 0 | D44: =C44/C$50 -> 0 | E44: =D44+E43 -> 2.7892386 | F44: =IF(AND(E44<=0),"C",IF(E44<=0.8,"A",IF(E44<=0.95,"B","C"))) -> C | G44: =VLOOKUP(B$30:B$50,I$30:M$50,5,0) -> C | I44: tunika13 халат черная | J44: ='Юнит 19-25.01'!R41 -> 0 | K44: =J44/J$50 -> 0 | L44: =K44+L43 -> 1.0714286 | M44: =_xlfn.IFS(L44<80%,"A",L44<=95%,"B",L44>95%,"C") -> C
B45: tunika08 зеленая | C45: ='Юнит 19-25.01'!AE36 -> -113.88 | D45: =C45/C$50 -> -0.028334033 | E45: =D45+E44 -> 2.7609046 | F45: =IF(AND(E45<=0),"C",IF(E45<=0.8,"A",IF(E45<=0.95,"B","C"))) -> C | G45: =VLOOKUP(B$30:B$50,I$30:M$50,5,0) -> C | I45: tunika14 халат с разрезами белая | J45: ='Юнит 19-25.01'!R42 -> 0 | K45: =J45/J$50 -> 0 | L45: =K45+L44 -> 1.0714286 | M45: =_xlfn.IFS(L45<80%,"A",L45<=95%,"B",L45>95%,"C") -> C
B46: tunika02 оливковая с руч вышивкой | C46: ='Юнит 19-25.01'!AE28 -> -537.70695 | D46: =C46/C$50 -> -0.13378474 | E46: =D46+E45 -> 2.6271198 | F46: =IF(AND(E46<=0),"C",IF(E46<=0.8,"A",IF(E46<=0.95,"B","C"))) -> C | G46: =VLOOKUP(B$30:B$50,I$30:M$50,5,0) -> C | I46: tunika14 халат с разрезами черный | J46: ='Юнит 19-25.01'!R43 -> 0 | K46: =J46/J$50 -> 0 | L46: =K46+L45 -> 1.0714286 | M46: =_xlfn.IFS(L46<80%,"A",L46<=95%,"B",L46>95%,"C") -> C
B47: tunika16 сетка белая | C47: ='Юнит 19-25.01'!AE46 -> -810.57043 | D47: =C47/C$50 -> -0.20167483 | E47: =D47+E46 -> 2.425445 | F47: =IF(AND(E47<=0),"C",IF(E47<=0.8,"A",IF(E47<=0.95,"B","C"))) -> C | G47: =VLOOKUP(B$30:B$50,I$30:M$50,5,0) -> C | I47: tunika16 сетка белая | J47: ='Юнит 19-25.01'!R46 -> 0 | K47: =J47/J$50 -> 0 | L47: =K47+L46 -> 1.0714286 | M47: =_xlfn.IFS(L47<80%,"A",L47<=95%,"B",L47>95%,"C") -> C
B48: tunika10 кимоно ч/б | C48: ='Юнит 19-25.01'!AE38 -> -1412.64 | D48: =C48/C$50 -> -0.35147338 | E48: =D48+E47 -> 2.0739716 | F48: =IF(AND(E48<=0),"C",IF(E48<=0.8,"A",IF(E48<=0.95,"B","C"))) -> C | G48: =VLOOKUP(B$30:B$50,I$30:M$50,5,0) -> C | I48: tunika16 сетка черная | J48: ='Юнит 19-25.01'!R47 -> 0 | K48: =J48/J$50 -> 0 | L48: =K48+L47 -> 1.0714286 | M48: =_xlfn.IFS(L48<80%,"A",L48<=95%,"B",L48>95%,"C") -> C
B49: tunika15 кимоно бирюза | C49: ='Юнит 19-25.01'!AE44 -> -4316.5012 | D49: =C49/C$50 -> -1.0739716 | E49: =D49+E48 -> 1 | F49: =IF(AND(E49<=0),"C",IF(E49<=0.8,"A",IF(E49<=0.95,"B","C"))) -> C | G49: =VLOOKUP(B$30:B$50,I$30:M$50,5,0) -> A | I49: tunika10 кимоно ч/б | J49: ='Юнит 19-25.01'!R38 -> -1 | K49: =J49/J$50 -> -0.071428571 | L49: =K49+L48 -> 1 | M49: =_xlfn.IFS(L49<80%,"A",L49<=95%,"B",L49>95%,"C") -> C
C50: =SUM(C30:C49) -> 4019.1948 | D50: =SUM(D30:D49) -> 1 | J50: =SUM(J30:J49) -> 14 | K50: =SUM(K30:K49) -> 1

Sheet АВС 12-18.01
B2: ОЧКИ
C3: Прибыль | D3: % прибыль | E3: Доля | F3: ABC прибыль | G3: ABC кол-во | J3: Кол-во | K3: % кол-во | L3: Доля | M3: ABC кол-во
B4: черные с железкой классика | C4: ='Юнит 12-18.01'!AE3 -> 11137.395 | D4: =C4/C$26 -> 0.74671755 | E4: =D4 -> 0.74671755 | F4: =IF(AND(E4<=0),"C",IF(E4<=0.8,"A",IF(E4<=0.95,"B","C"))) -> A | G4: =VLOOKUP(B$4:B$25,I$4:M$25,5,0) -> A | I4: черные с железкой классика | J4: ='Юнит 12-18.01'!R3 -> 43 | K4: =J4/J$26 -> 0.76785714 | L4: =K4 -> 0.76785714 | M4: =_xlfn.IFS(L4<80%,"A",L4<=95%,"B",L4>95%,"C") -> A
B5: qs желтые | C5: ='Юнит 12-18.01'!AE6 -> 3561.2513 | D5: =C5/C$26 -> 0.23876757 | E5: =D5+E4 -> 0.98548513 | F5: =IF(AND(E5<=0),"C",IF(E5<=0.8,"A",IF(E5<=0.95,"B","C"))) -> C | G5: =VLOOKUP(B$4:B$25,I$4:M$25,5,0) -> B | I5: qs желтые | J5: ='Юнит 12-18.01'!R6 -> 7 | K5: =J5/J$26 -> 0.125 | L5: =K5+L4 -> 0.89285714 | M5: =_xlfn.IFS(L5<80%,"A",L5<=95%,"B",L5>95%,"C") -> B
B6: qs синие | C6: ='Юнит 12-18.01'!AE5 -> 881.45 | D6: =C6/C$26 -> 0.059097676 | E6: =D6+E5 -> 1.0445828 | F6: =IF(AND(E6<=0),"C",IF(E6<=0.8,"A",IF(E6<=0.95,"B","C"))) -> C | G6: =VLOOKUP(B$4:B$25,I$4:M$25,5,0) -> C | I6: qs черные | J6: ='Юнит 12-18.01'!R4 -> 2 | K6: =J6/J$26 -> 0.035714286 | L6: =K6+L5 -> 0.92857143 | M6: =_xlfn.IFS(L6<80%,"A",L6<=95%,"B",L6>95%,"C") -> B
B7: MR Р1886 корич | C7: ='Юнит 12-18.01'!AE16 -> 861.87 | D7: =C7/C$26 -> 0.057784916 | E7: =D7+E6 -> 1.1023677 | F7: =IF(AND(E7<=0),"C",IF(E7<=0.8,"A",IF(E7<=0.95,"B","C"))) -> C | G7: =VLOOKUP(B$4:B$25,I$4:M$25,5,0) -> C | I7: qs синие | J7: ='Юнит 12-18.01'!R5 -> 2 | K7: =J7/J$26 -> 0.035714286 | L7: =K7+L6 -> 0.96428571 | M7: =_xlfn.IFS(L7<80%,"A",L7<=95%,"B",L7>95%,"C") -> C
B8: qs коричневые | C8: ='Юнит 12-18.01'!AE7 -> 0 | D8: =C8/C$26 -> 0 | E8: =D8+E7 -> 1.1023677 | F8: =IF(AND(E8<=0),"C",IF(E8<=0.8,"A",IF(E8<=0.95,"B","C"))) -> C | G8: =VLOOKUP(B$4:B$25,I$4:M$25,5,0) -> C | I8: MR Р1886 корич | J8: ='Юнит 12-18.01'!R16 -> 2 | K8: =J8/J$26 -> 0.035714286 | L8: =K8+L7 -> 1 | M8: =_xlfn.IFS(L8<80%,"A",L8<=95%,"B",L8>95%,"C") -> C
B9: th желтый Сул | C9: ='Юнит 12-18.01'!AE8 -> 0 | D9: =C9/C$26 -> 0 | E9: =D9+E8 -> 1.1023677 | F9: =IF(AND(E9<=0),"C",IF(E9<=0.8,"A",IF(E9<=0.95,"B","C"))) -> C | G9: =VLOOKUP(B$4:B$25,I$4:M$25,5,0) -> C | I9: qs коричневые | J9: ='Юнит 12-18.01'!R7 -> 0 | K9: =J9/J$26 -> 0 | L9: =K9+L8 -> 1 | M9: =_xlfn.IFS(L9<80%,"A",L9<=95%,"B",L9>95%,"C") -> C
B10: MR 1819 черн | C10: ='Юнит 12-18.01'!AE11 -> 0 | D10: =C10/C$26 -> 0 | E10: =D10+E9 -> 1.1023677 | F10: =IF(AND(E10<=0),"C",IF(E10<=0.8,"A",IF(E10<=0.95,"B","C"))) -> C | G10: =VLOOKUP(B$4:B$25,I$4:M$25,5,0) -> C | I10: th желтый Сул | J10: ='Юнит 12-18.01'!R8 -> 0 | K10: =J10/J$26 -> 0 | L10: =K10+L9 -> 1 | M10: =_xlfn.IFS(L10<80%,"A",L10<=95%,"B",L10>95%,"C") -> C
B11: MR 1819 корич | C11: ='Юнит 12-18.01'!AE12 -> 0 | D11: =C11/C$26 -> 0 | E11: =D11+E8 -> 1.1023677 | F11: =IF(AND(E11<=0),"C",IF(E11<=0.8,"A",IF(E11<=0.95,"B","C"))) -> C | G11: =VLOOKUP(B$4:B$25,I$4:M$25,5,0) -> C | I11: flip желтые Сул | J11: ='Юнит 12-18.01'!R9 -> 0 | K11: =J11/J$26 -> 0 | L11: =K11+L8 -> 1 | M11: =_xlfn.IFS(L11<80%,"A",L11<=95%,"B",L11>95%,"C") -> C
B12: MR Р1874 корич | C12: ='Юнит 12-18.01'!AE14 -> 0 | D12: =C12/C$26 -> 0 | E12: =D12+E11 -> 1.1023677 | F12: =IF(AND(E12<=0),"C",IF(E12<=0.8,"A",IF(E12<=0.95,"B","C"))) -> C | G12: =VLOOKUP(B$4:B$25,I$4:M$25,5,0) -> C | I12: MR8854 C2 | J12: ='Юнит 12-18.01'!R10 -> 0 | K12: =J12/J$26 -> 0 | L12: =K12+L11 -> 1 | M12: =_xlfn.IFS(L12<80%,"A",L12<=95%,"B",L12>95%,"C") -> C
B13: MR Р1886 черн глянец | C13: ='Юнит 12-18.01'!AE15 -> 0 | D13: =C13/C$26 -> 0 | E13: =D13+E12 -> 1.1023677 | F13: =IF(AND(E13<=0),"C",IF(E13<=0.8,"A",IF(E13<=0.95,"B","C"))) -> C | G13: =VLOOKUP(B$4:B$25,I$4:M$25,5,0) -> C | I13: MR 1819 черн | J13: ='Юнит 12-18.01'!R11 -> 0 | K13: =J13/J$26 -> 0 | L13: =K13+L12 -> 1 | M13: =_xlfn.IFS(L13<80%,"A",L13<=95%,"B",L13>95%,"C") -> C | P13: A | Q13: 0.8
B14: lux1 | C14: ='Юнит 12-18.01'!AE17 -> 0 | D14: =C14/C$26 -> 0 | E14: =D14+E13 -> 1.1023677 | F14: =IF(AND(E14<=0),"C",IF(E14<=0.8,"A",IF(E14<=0.95,"B","C"))) -> C | G14: =VLOOKUP(B$4:B$25,I$4:M$25,5,0) -> C | I14: MR 1819 корич | J14: ='Юнит 12-18.01'!R12 -> 0 | K14: =J14/J$26 -> 0 | L14: =K14+L13 -> 1 | M14: =_xlfn.IFS(L14<80%,"A",L14<=95%,"B",L14>95%,"C") -> C | P14: B | Q14: 0.15
B15: lux2 | C15: ='Юнит 12-18.01'!AE18 -> 0 | D15: =C15/C$26 -> 0 | E15: =D15+E14 -> 1.1023677 | F15: =IF(AND(E15<=0),"C",IF(E15<=0.8,"A",IF(E15<=0.95,"B","C"))) -> C | G15: =VLOOKUP(B$4:B$25,I$4:M$25,5,0) -> C | I15: MR Р1874 черн | J15: ='Юнит 12-18.01'!R13 -> 0 | K15: =J15/J$26 -> 0 | L15: =K15+L14 -> 1 | M15: =_xlfn.IFS(L15<80%,"A",L15<=95%,"B",L15>95%,"C") -> C | P15: C | Q15: 0.05
B16: lux3 | C16: ='Юнит 12-18.01'!AE19 -> 0 | D16: =C16/C$26 -> 0 | E16: =D16+E15 -> 1.1023677 | F16: =IF(AND(E16<=0),"C",IF(E16<=0.8,"A",IF(E16<=0.95,"B","C"))) -> C | G16: =VLOOKUP(B$4:B$25,I$4:M$25,5,0) -> C | I16: MR Р1874 корич | J16: ='Юнит 12-18.01'!R14 -> 0 | K16: =J16/J$26 -> 0 | L16: =K16+L15 -> 1 | M16: =_xlfn.IFS(L16<80%,"A",L16<=95%,"B",L16>95%,"C") -> C
B17: lux4 | C17: ='Юнит 12-18.01'!AE20 -> 0 | D17: =C17/C$26 -> 0 | E17: =D17+E16 -> 1.1023677 | F17: =IF(AND(E17<=0),"C",IF(E17<=0.8,"A",IF(E17<=0.95,"B","C"))) -> C | G17: =VLOOKUP(B$4:B$25,I$4:M$25,5,0) -> C | I17: MR Р1886 черн глянец | J17: ='Юнит 12-18.01'!R15 -> 0 | K17: =J17/J$26 -> 0 | L17: =K17+L16 -> 1 | M17: =_xlfn.IFS(L17<80%,"A",L17<=95%,"B",L17>95%,"C") -> C
B18: lux5 | C18: ='Юнит 12-18.01'!AE21 -> 0 | D18: =C18/C$26 -> 0 | E18: =D18+E17 -> 1.1023677 | F18: =IF(AND(E18<=0),"C",IF(E18<=0.8,"A",IF(E18<=0.95,"B","C"))) -> C | G18: =VLOOKUP(B$4:B$25,I$4:M$25,5,0) -> C | I18: lux1 | J18: ='Юнит 12-18.01'!R17 -> 0 | K18: =J18/J$26 -> 0 | L18: =K18+L17 -> 1 | M18: =_xlfn.IFS(L18<80%,"A",L18<=95%,"B",L18>95%,"C") -> C
B19: lux6 | C19: ='Юнит 12-18.01'!AE22 -> 0 | D19: =C19/C$26 -> 0 | E19: =D19+E18 -> 1.1023677 | F19: =IF(AND(E19<=0),"C",IF(E19<=0.8,"A",IF(E19<=0.95,"B","C"))) -> C | G19: =VLOOKUP(B$4:B$25,I$4:M$25,5,0) -> C | I19: lux2 | J19: ='Юнит 12-18.01'!R18 -> 0 | K19: =J19/J$26 -> 0 | L19: =K19+L18 -> 1 | M19: =_xlfn.IFS(L19<80%,"A",L19<=95%,"B",L19>95%,"C") -> C
B20: lux7 | C20: ='Юнит 12-18.01'!AE23 -> 0 | D20: =C20/C$26 -> 0 | E20: =D20+E19 -> 1.1023677 | F20: =IF(AND(E20<=0),"C",IF(E20<=0.8,"A",IF(E20<=0.95,"B","C"))) -> C | G20: =VLOOKUP(B$4:B$25,I$4:M$25,5,0) -> C | I20: lux3 | J20: ='Юнит 12-18.01'!R19 -> 0 | K20: =J20/J$26 -> 0 | L20: =K20+L19 -> 1 | M20: =_xlfn.IFS(L20<80%,"A",L20<=95%,"B",L20>95%,"C") -> C
B21: lux8 | C21: ='Юнит 12-18.01'!AE24 -> 0 | D21: =C21/C$26 -> 0 | E21: =D21+E20 -> 1.1023677 | F21: =IF(AND(E21<=0),"C",IF(E21<=0.8,"A",IF(E21<=0.95,"B","C"))) -> C | G21: =VLOOKUP(B$4:B$25,I$4:M$25,5,0) -> C | I21: lux4 | J21: ='Юнит 12-18.01'!R20 -> 0 | K21: =J21/J$26 -> 0 | L21: =K21+L20 -> 1 | M21: =_xlfn.IFS(L21<80%,"A",L21<=95%,"B",L21>95%,"C") -> C
B22: MR8854 C2 | C22: ='Юнит 12-18.01'!AE10 -> -93.54 | D22: =C22/C$26 -> -0.0062714806 | E22: =D22+E21 -> 1.0960962 | F22: =IF(AND(E22<=0),"C",IF(E22<=0.8,"A",IF(E22<=0.95,"B","C"))) -> C | G22: =VLOOKUP(B$4:B$25,I$4:M$25,5,0) -> C | I22: lux5 | J22: ='Юнит 12-18.01'!R21 -> 0 | K22: =J22/J$26 -> 0 | L22: =K22+L21 -> 1 | M22: =_xlfn.IFS(L22<80%,"A",L22<=95%,"B",L22>95%,"C") -> C
B23: MR Р1874 черн | C23: ='Юнит 12-18.01'!AE13 -> -93.54 | D23: =C23/C$26 -> -0.0062714806 | E23: =D23+E22 -> 1.0898248 | F23: =IF(AND(E23<=0),"C",IF(E23<=0.8,"A",IF(E23<=0.95,"B","C"))) -> C | G23: =VLOOKUP(B$4:B$25,I$4:M$25,5,0) -> C | I23: lux6 | J23: ='Юнит 12-18.01'!R22 -> 0 | K23: =J23/J$26 -> 0 | L23: =K23+L22 -> 1 | M23: =_xlfn.IFS(L23<80%,"A",L23<=95%,"B",L23>95%,"C") -> C
B24: flip желтые Сул | C24: ='Юнит 12-18.01'!AE9 -> -429.25019 | D24: =C24/C$26 -> -0.028779498 | E24: =D24+E23 -> 1.0610453 | F24: =IF(AND(E24<=0),"C",IF(E24<=0.8,"A",IF(E24<=0.95,"B","C"))) -> C | G24: =VLOOKUP(B$4:B$25,I$4:M$25,5,0) -> C | I24: lux7 | J24: ='Юнит 12-18.01'!R23 -> 0 | K24: =J24/J$26 -> 0 | L24: =K24+L23 -> 1 | M24: =_xlfn.IFS(L24<80%,"A",L24<=95%,"B",L24>95%,"C") -> C
B25: qs черные | C25: ='Юнит 12-18.01'!AE4 -> -910.4985 | D25: =C25/C$26 -> -0.061045261 | E25: =D25+E24 -> 1 | F25: =IF(AND(E25<=0),"C",IF(E25<=0.8,"A",IF(E25<=0.95,"B","C"))) -> C | G25: =VLOOKUP(B$4:B$25,I$4:M$25,5,0) -> B | I25: lux8 | J25: ='Юнит 12-18.01'!R24 -> 0 | K25: =J25/J$26 -> 0 | L25: =K25+L24 -> 1 | M25: =_xlfn.IFS(L25<80%,"A",L25<=95%,"B",L25>95%,"C") -> C
C26: =SUM(C4:C25) -> 14915.138 | D26: =SUM(D4:D25) -> 1 | J26: =SUM(J4:J25) -> 56 | K26: =SUM(K4:K25) -> 1
B28: ТУНИКИ
C29: Прибыль | D29: % прибыль | E29: Доля | F29: ABC прибыль | G29: ABC кол-во | J29: Кол-во | K29: % кол-во | L29: Доля | M29: ABC кол-во
B30: tunika10 кимоно ч/б | C30: ='Юнит 12-18.01'!AE38 -> 1094.25 | D30: =C30/C$50 -> 1.0062694 | E30: =D30 -> 1.0062694 | F30: =IF(AND(E30<=0),"C",IF(E30<=0.8,"A",IF(E30<=0.95,"B","C"))) -> C | G30: =VLOOKUP(B$30:B$50,I$30:M$50,5,0) -> B | I30: tunika15 кимоно бирюза | J30: ='Юнит 12-18.01'!R44 -> 3 | K30: =J30/J$50 -> 0.6 | L30: =K30 -> 0.6 | M30: =_xlfn.IFS(L30<80%,"A",L30<=95%,"B",L30>95%,"C") -> A
B31: tunika15 кимоно бирюза | C31: ='Юнит 12-18.01'!AE44 -> 1366.2751 | D31: =C31/C$50 -> 1.256423 | E31: =D31+E30 -> 2.2626925 | F31: =IF(AND(E31<=0),"C",IF(E31<=0.8,"A",IF(E31<=0.95,"B","C"))) -> C | G31: =VLOOKUP(B$30:B$50,I$30:M$50,5,0) -> A | I31: tunika10 кимоно ч/б | J31: ='Юнит 12-18.01'!R38 -> 1 | K31: =J31/J$50 -> 0.2 | L31: =K31+L30 -> 0.8 | M31: =_xlfn.IFS(L31<80%,"A",L31<=95%,"B",L31>95%,"C") -> B
B32: tunika02 оливковая с руч вышивкой | C32: ='Юнит 12-18.01'!AE28 -> 0 | D32: =C32/C$50 -> 0 | E32: =D32+E31 -> 2.2626925 | F32: =IF(AND(E32<=0),"C",IF(E32<=0.8,"A",IF(E32<=0.95,"B","C"))) -> C | G32: =VLOOKUP(B$30:B$50,I$30:M$50,5,0) -> C | I32: tunika15 кимоно песочная | J32: ='Юнит 12-18.01'!R45 -> 1 | K32: =J32/J$50 -> 0.2 | L32: =K32+L31 -> 1 | M32: =_xlfn.IFS(L32<80%,"A",L32<=95%,"B",L32>95%,"C") -> C
B33: tunika03 черная распашная | C33: ='Юнит 12-18.01'!AE29 -> 0 | D33: =C33/C$50 -> 0 | E33: =D33+E32 -> 2.2626925 | F33: =IF(AND(E33<=0),"C",IF(E33<=0.8,"A",IF(E33<=0.95,"B","C"))) -> C | G33: =VLOOKUP(B$30:B$50,I$30:M$50,5,0) -> C | I33: tunika02 оливковая с руч вышивкой | J33: ='Юнит 12-18.01'!R28 -> 0 | K33: =J33/J$50 -> 0 | L33: =K33+L32 -> 1 | M33: =_xlfn.IFS(L33<80%,"A",L33<=95%,"B",L33>95%,"C") -> C
B34: tunika05 белая распашная | C34: ='Юнит 12-18.01'!AE30 -> 0 | D34: =C34/C$50 -> 0 | E34: =D34+E33 -> 2.2626925 | F34: =IF(AND(E34<=0),"C",IF(E34<=0.8,"A",IF(E34<=0.95,"B","C"))) -> C | G34: =VLOOKUP(B$30:B$50,I$30:M$50,5,0) -> C | I34: tunika03 черная распашная | J34: ='Юнит 12-18.01'!R29 -> 0 | K34: =J34/J$50 -> 0 | L34: =K34+L33 -> 1 | M34: =_xlfn.IFS(L34<80%,"A",L34<=95%,"B",L34>95%,"C") -> C
B35: tunika06 белая | C35: ='Юнит 12-18.01'!AE31 -> 0 | D35: =C35/C$50 -> 0 | E35: =D35+E34 -> 2.2626925 | F35: =IF(AND(E35<=0),"C",IF(E35<=0.8,"A",IF(E35<=0.95,"B","C"))) -> C | G35: =VLOOKUP(B$30:B$50,I$30:M$50,5,0) -> C | I35: tunika05 белая распашная | J35: ='Юнит 12-18.01'!R30 -> 0 | K35: =J35/J$50 -> 0 | L35: =K35+L34 -> 1 | M35: =_xlfn.IFS(L35<80%,"A",L35<=95%,"B",L35>95%,"C") -> C
B36: tunika06 черная | C36: ='Юнит 12-18.01'!AE32 -> 0 | D36: =C36/C$50 -> 0 | E36: =D36+E35 -> 2.2626925 | F36: =IF(AND(E36<=0),"C",IF(E36<=0.8,"A",IF(E36<=0.95,"B","C"))) -> C | G36: =VLOOKUP(B$30:B$50,I$30:M$50,5,0) -> C | I36: tunika06 белая | J36: ='Юнит 12-18.01'!R31 -> 0 | K36: =J36/J$50 -> 0 | L36: =K36+L35 -> 1 | M36: =_xlfn.IFS(L36<80%,"A",L36<=95%,"B",L36>95%,"C") -> C
B37: tunika07 кружево | C37: ='Юнит 12-18.01'!AE33 -> 0 | D37: =C37/C$50 -> 0 | E37: =D37+E36 -> 2.2626925 | F37: =IF(AND(E37<=0),"C",IF(E37<=0.8,"A",IF(E37<=0.95,"B","C"))) -> C | G37: =VLOOKUP(B$30:B$50,I$30:M$50,5,0) -> C | I37: tunika06 черная | J37: ='Юнит 12-18.01'!R32 -> 0 | K37: =J37/J$50 -> 0 | L37: =K37+L36 -> 1 | M37: =_xlfn.IFS(L37<80%,"A",L37<=95%,"B",L37>95%,"C") -> C
B38: tunika08 белая | C38: ='Юнит 12-18.01'!AE34 -> 0 | D38: =C38/C$50 -> 0 | E38: =D38+E37 -> 2.2626925 | F38: =IF(AND(E38<=0),"C",IF(E38<=0.8,"A",IF(E38<=0.95,"B","C"))) -> C | G38: =VLOOKUP(B$30:B$50,I$30:M$50,5,0) -> C | I38: tunika07 кружево | J38: ='Юнит 12-18.01'!R33 -> 0 | K38: =J38/J$50 -> 0 | L38: =K38+L37 -> 1 | M38: =_xlfn.IFS(L38<80%,"A",L38<=95%,"B",L38>95%,"C") -> C
B39: tunika08 черная | C39: ='Юнит 12-18.01'!AE35 -> 0 | D39: =C39/C$50 -> 0 | E39: =D39+E38 -> 2.2626925 | F39: =IF(AND(E39<=0),"C",IF(E39<=0.8,"A",IF(E39<=0.95,"B","C"))) -> C | G39: =VLOOKUP(B$30:B$50,I$30:M$50,5,0) -> C | I39: tunika08 белая | J39: ='Юнит 12-18.01'!R34 -> 0 | K39: =J39/J$50 -> 0 | L39: =K39+L38 -> 1 | M39: =_xlfn.IFS(L39<80%,"A",L39<=95%,"B",L39>95%,"C") -> C
B40: tunika08 зеленая | C40: ='Юнит 12-18.01'!AE36 -> 0 | D40: =C40/C$50 -> 0 | E40: =D40+E39 -> 2.2626925 | F40: =IF(AND(E40<=0),"C",IF(E40<=0.8,"A",IF(E40<=0.95,"B","C"))) -> C | G40: =VLOOKUP(B$30:B$50,I$30:M$50,5,0) -> C | I40: tunika08 черная | J40: ='Юнит 12-18.01'!R35 -> 0 | K40: =J40/J$50 -> 0 | L40: =K40+L39 -> 1 | M40: =_xlfn.IFS(L40<80%,"A",L40<=95%,"B",L40>95%,"C") -> C
B41: tunika09 кимоно | C41: ='Юнит 12-18.01'!AE37 -> 0 | D41: =C41/C$50 -> 0 | E41: =D41+E40 -> 2.2626925 | F41: =IF(AND(E41<=0),"C",IF(E41<=0.8,"A",IF(E41<=0.95,"B","C"))) -> C | G41: =VLOOKUP(B$30:B$50,I$30:M$50,5,0) -> C | I41: tunika08 зеленая | J41: ='Юнит 12-18.01'!R36 -> 0 | K41: =J41/J$50 -> 0 | L41: =K41+L40 -> 1 | M41: =_xlfn.IFS(L41<80%,"A",L41<=95%,"B",L41>95%,"C") -> C
B42: tunika11 халат зеленая | C42: ='Юнит 12-18.01'!AE39 -> 0 | D42: =C42/C$50 -> 0 | E42: =D42+E41 -> 2.2626925 | F42: =IF(AND(E42<=0),"C",IF(E42<=0.8,"A",IF(E42<=0.95,"B","C"))) -> C | G42: =VLOOKUP(B$30:B$50,I$30:M$50,5,0) -> C | I42: tunika09 кимоно | J42: ='Юнит 12-18.01'!R37 -> 0 | K42: =J42/J$50 -> 0 | L42: =K42+L41 -> 1 | M42: =_xlfn.IFS(L42<80%,"A",L42<=95%,"B",L42>95%,"C") -> C
B43: tunika12 халат белая | C43: ='Юнит 12-18.01'!AE40 -> 0 | D43: =C43/C$50 -> 0 | E43: =D43+E42 -> 2.2626925 | F43: =IF(AND(E43<=0),"C",IF(E43<=0.8,"A",IF(E43<=0.95,"B","C"))) -> C | G43: =VLOOKUP(B$30:B$50,I$30:M$50,5,0) -> C | I43: tunika11 халат зеленая | J43: ='Юнит 12-18.01'!R39 -> 0 | K43: =J43/J$50 -> 0 | L43: =K43+L42 -> 1 | M43: =_xlfn.IFS(L43<80%,"A",L43<=95%,"B",L43>95%,"C") -> C
B44: tunika13 халат черная | C44: ='Юнит 12-18.01'!AE41 -> 0 | D44: =C44/C$50 -> 0 | E44: =D44+E43 -> 2.2626925 | F44: =IF(AND(E44<=0),"C",IF(E44<=0.8,"A",IF(E44<=0.95,"B","C"))) -> C | G44: =VLOOKUP(B$30:B$50,I$30:M$50,5,0) -> C | I44: tunika12 халат белая | J44: ='Юнит 12-18.01'!R40 -> 0 | K44: =J44/J$50 -> 0 | L44: =K44+L43 -> 1 | M44: =_xlfn.IFS(L44<80%,"A",L44<=95%,"B",L44>95%,"C") -> C
B45: tunika14 халат с разрезами белая | C45: ='Юнит 12-18.01'!AE42 -> 0 | D45: =C45/C$50 -> 0 | E45: =D45+E44 -> 2.2626925 | F45: =IF(AND(E45<=0),"C",IF(E45<=0.8,"A",IF(E45<=0.95,"B","C"))) -> C | G45: =VLOOKUP(B$30:B$50,I$30:M$50,5,0) -> C | I45: tunika13 халат черная | J45: ='Юнит 12-18.01'!R41 -> 0 | K45: =J45/J$50 -> 0 | L45: =K45+L44 -> 1 | M45: =_xlfn.IFS(L45<80%,"A",L45<=95%,"B",L45>95%,"C") -> C
B46: tunika14 халат с разрезами черный | C46: ='Юнит 12-18.01'!AE43 -> 0 | D46: =C46/C$50 -> 0 | E46: =D46+E45 -> 2.2626925 | F46: =IF(AND(E46<=0),"C",IF(E46<=0.8,"A",IF(E46<=0.95,"B","C"))) -> C | G46: =VLOOKUP(B$30:B$50,I$30:M$50,5,0) -> C | I46: tunika14 халат с разрезами белая | J46: ='Юнит 12-18.01'!R42 -> 0 | K46: =J46/J$50 -> 0 | L46: =K46+L45 -> 1 | M46: =_xlfn.IFS(L46<80%,"A",L46<=95%,"B",L46>95%,"C") -> C
B47: tunika16 сетка белая | C47: ='Юнит 12-18.01'!AE46 -> 0 | D47: =C47/C$50 -> 0 | E47: =D47+E46 -> 2.2626925 | F47: =IF(AND(E47<=0),"C",IF(E47<=0.8,"A",IF(E47<=0.95,"B","C"))) -> C | G47: =VLOOKUP(B$30:B$50,I$30:M$50,5,0) -> C | I47: tunika14 халат с разрезами черный | J47: ='Юнит 12-18.01'!R43 -> 0 | K47: =J47/J$50 -> 0 | L47: =K47+L46 -> 1 | M47: =_xlfn.IFS(L47<80%,"A",L47<=95%,"B",L47>95%,"C") -> C
B48: tunika16 сетка черная | C48: ='Юнит 12-18.01'!AE47 -> 0 | D48: =C48/C$50 -> 0 | E48: =D48+E47 -> 2.2626925 | F48: =IF(AND(E48<=0),"C",IF(E48<=0.8,"A",IF(E48<=0.95,"B","C"))) -> C | G48: =VLOOKUP(B$30:B$50,I$30:M$50,5,0) -> C | I48: tunika16 сетка белая | J48: ='Юнит 12-18.01'!R46 -> 0 | K48: =J48/J$50 -> 0 | L48: =K48+L47 -> 1 | M48: =_xlfn.IFS(L48<80%,"A",L48<=95%,"B",L48>95%,"C") -> C
B49: tunika15 кимоно песочная | C49: ='Юнит 12-18.01'!AE45 -> -1373.0927 | D49: =C49/C$50 -> -1.2626925 | E49: =D49+E48 -> 1 | F49: =IF(AND(E49<=0),"C",IF(E49<=0.8,"A",IF(E49<=0.95,"B","C"))) -> C | G49: =VLOOKUP(B$30:B$50,I$30:M$50,5,0) -> C | I49: tunika16 сетка черная | J49: ='Юнит 12-18.01'!R47 -> 0 | K49: =J49/J$50 -> 0 | L49: =K49+L48 -> 1 | M49: =_xlfn.IFS(L49<80%,"A",L49<=95%,"B",L49>95%,"C") -> C
C50: =SUM(C30:C49) -> 1087.4324 | D50: =SUM(D30:D49) -> 1 | J50: =SUM(J30:J49) -> 5 | K50: =SUM(K30:K49) -> 1

Sheet АВС 05-11.01
B2: ОЧКИ
C3: Прибыль | D3: % прибыль | E3: Доля | F3: ABC прибыль | G3: ABC кол-во | J3: Кол-во | K3: % кол-во | L3: Доля | M3: ABC кол-во
B4: черные с железкой классика | C4: ='Юнит 05-11.01'!AE3 -> 6568.9867 | D4: =C4/C$26 -> 0.64827525 | E4: =D4 -> 0.64827525 | F4: =IF(AND(E4<=0),"C",IF(E4<=0.8,"A",IF(E4<=0.95,"B","C"))) -> A | G4: =VLOOKUP(B$4:B$25,I$4:M$25,5,0) -> A | I4: черные с железкой классика | J4: ='Юнит 05-11.01'!R3 -> 32 | K4: =J4/J$26 -> 0.59259259 | L4: =K4 -> 0.59259259 | M4: =_xlfn.IFS(L4<80%,"A",L4<=95%,"B",L4>95%,"C") -> A
B5: MR 1819 корич | C5: ='Юнит 05-11.01'!AE12 -> 698.36 | D5: =C5/C$26 -> 0.06891923 | E5: =D5+E4 -> 0.71719448 | F5: =IF(AND(E5<=0),"C",IF(E5<=0.8,"A",IF(E5<=0.95,"B","C"))) -> A | G5: =VLOOKUP(B$4:B$25,I$4:M$25,5,0) -> B | I5: qs желтые | J5: ='Юнит 05-11.01'!R6 -> 11 | K5: =J5/J$26 -> 0.2037037 | L5: =K5+L4 -> 0.7962963 | M5: =_xlfn.IFS(L5<80%,"A",L5<=95%,"B",L5>95%,"C") -> A
B6: qs желтые | C6: ='Юнит 05-11.01'!AE6 -> 1305.2943 | D6: =C6/C$26 -> 0.12881591 | E6: =D6+E5 -> 0.84601039 | F6: =IF(AND(E6<=0),"C",IF(E6<=0.8,"A",IF(E6<=0.95,"B","C"))) -> B | G6: =VLOOKUP(B$4:B$25,I$4:M$25,5,0) -> A | I6: MR 1819 корич | J6: ='Юнит 05-11.01'!R12 -> 2 | K6: =J6/J$26 -> 0.037037037 | L6: =K6+L5 -> 0.83333333 | M6: =_xlfn.IFS(L6<80%,"A",L6<=95%,"B",L6>95%,"C") -> B
B7: MR Р1886 корич | C7: ='Юнит 05-11.01'!AE16 -> 584.28 | D7: =C7/C$26 -> 0.057660988 | E7: =D7+E6 -> 0.90367138 | F7: =IF(AND(E7<=0),"C",IF(E7<=0.8,"A",IF(E7<=0.95,"B","C"))) -> B | G7: =VLOOKUP(B$4:B$25,I$4:M$25,5,0) -> B | I7: MR Р1886 черн глянец | J7: ='Юнит 05-11.01'!R15 -> 2 | K7: =J7/J$26 -> 0.037037037 | L7: =K7+L6 -> 0.87037037 | M7: =_xlfn.IFS(L7<80%,"A",L7<=95%,"B",L7>95%,"C") -> B
B8: MR Р1874 черн | C8: ='Юнит 05-11.01'!AE13 -> 497.35 | D8: =C8/C$26 -> 0.049082105 | E8: =D8+E7 -> 0.95275349 | F8: =IF(AND(E8<=0),"C",IF(E8<=0.8,"A",IF(E8<=0.95,"B","C"))) -> C | G8: =VLOOKUP(B$4:B$25,I$4:M$25,5,0) -> B | I8: MR Р1886 корич | J8: ='Юнит 05-11.01'!R16 -> 2 | K8: =J8/J$26 -> 0.037037037 | L8: =K8+L7 -> 0.90740741 | M8: =_xlfn.IFS(L8<80%,"A",L8<=95%,"B",L8>95%,"C") -> B
B9: qs синие | C9: ='Юнит 05-11.01'!AE5 -> 360.57 | D9: =C9/C$26 -> 0.035583663 | E9: =D9+E8 -> 0.98833715 | F9: =IF(AND(E9<=0),"C",IF(E9<=0.8,"A",IF(E9<=0.95,"B","C"))) -> C | G9: =VLOOKUP(B$4:B$25,I$4:M$25,5,0) -> B | I9: qs синие | J9: ='Юнит 05-11.01'!R5 -> 1 | K9: =J9/J$26 -> 0.018518519 | L9: =K9+L8 -> 0.92592593 | M9: =_xlfn.IFS(L9<80%,"A",L9<=95%,"B",L9>95%,"C") -> B
B10: MR Р1874 корич | C10: ='Юнит 05-11.01'!AE14 -> 280.86 | D10: =C10/C$26 -> 0.027717302 | E10: =D10+E9 -> 1.0160545 | F10: =IF(AND(E10<=0),"C",IF(E10<=0.8,"A",IF(E10<=0.95,"B","C"))) -> C | G10: =VLOOKUP(B$4:B$25,I$4:M$25,5,0) -> C | I10: qs коричневые | J10: ='Юнит 05-11.01'!R7 -> 1 | K10: =J10/J$26 -> 0.018518519 | L10: =K10+L9 -> 0.94444444 | M10: =_xlfn.IFS(L10<80%,"A",L10<=95%,"B",L10>95%,"C") -> B
B11: MR Р1886 черн глянец | C11: ='Юнит 05-11.01'!AE15 -> 132.94 | D11: =C11/C$26 -> 0.013119483 | E11: =D11+E8 -> 0.96587297 | F11: =IF(AND(E11<=0),"C",IF(E11<=0.8,"A",IF(E11<=0.95,"B","C"))) -> C | G11: =VLOOKUP(B$4:B$25,I$4:M$25,5,0) -> B | I11: flip желтые Сул | J11: ='Юнит 05-11.01'!R9 -> 1 | K11: =J11/J$26 -> 0.018518519 | L11: =K11+L8 -> 0.92592593 | M11: =_xlfn.IFS(L11<80%,"A",L11<=95%,"B",L11>95%,"C") -> B
B12: qs черные | C12: ='Юнит 05-11.01'!AE4 -> 0 | D12: =C12/C$26 -> 0 | E12: =D12+E11 -> 0.96587297 | F12: =IF(AND(E12<=0),"C",IF(E12<=0.8,"A",IF(E12<=0.95,"B","C"))) -> C | G12: =VLOOKUP(B$4:B$25,I$4:M$25,5,0) -> C | I12: MR Р1874 черн | J12: ='Юнит 05-11.01'!R13 -> 1 | K12: =J12/J$26 -> 0.018518519 | L12: =K12+L11 -> 0.94444444 | M12: =_xlfn.IFS(L12<80%,"A",L12<=95%,"B",L12>95%,"C") -> B
B13: th желтый Сул | C13: ='Юнит 05-11.01'!AE8 -> 0 | D13: =C13/C$26 -> 0 | E13: =D13+E12 -> 0.96587297 | F13: =IF(AND(E13<=0),"C",IF(E13<=0.8,"A",IF(E13<=0.95,"B","C"))) -> C | G13: =VLOOKUP(B$4:B$25,I$4:M$25,5,0) -> C | I13: MR Р1874 корич | J13: ='Юнит 05-11.01'!R14 -> 1 | K13: =J13/J$26 -> 0.018518519 | L13: =K13+L12 -> 0.96296296 | M13: =_xlfn.IFS(L13<80%,"A",L13<=95%,"B",L13>95%,"C") -> C | P13: A | Q13: 0.8
B14: MR 1819 черн | C14: ='Юнит 05-11.01'!AE11 -> 0 | D14: =C14/C$26 -> 0 | E14: =D14+E13 -> 0.96587297 | F14: =IF(AND(E14<=0),"C",IF(E14<=0.8,"A",IF(E14<=0.95,"B","C"))) -> C | G14: =VLOOKUP(B$4:B$25,I$4:M$25,5,0) -> C | I14: qs черные | J14: ='Юнит 05-11.01'!R4 -> 0 | K14: =J14/J$26 -> 0 | L14: =K14+L13 -> 0.96296296 | M14: =_xlfn.IFS(L14<80%,"A",L14<=95%,"B",L14>95%,"C") -> C | P14: B | Q14: 0.15
B15: lux1 | C15: ='Юнит 05-11.01'!AE17 -> 0 | D15: =C15/C$26 -> 0 | E15: =D15+E14 -> 0.96587297 | F15: =IF(AND(E15<=0),"C",IF(E15<=0.8,"A",IF(E15<=0.95,"B","C"))) -> C | G15: =VLOOKUP(B$4:B$25,I$4:M$25,5,0) -> C | I15: th желтый Сул | J15: ='Юнит 05-11.01'!R8 -> 0 | K15: =J15/J$26 -> 0 | L15: =K15+L14 -> 0.96296296 | M15: =_xlfn.IFS(L15<80%,"A",L15<=95%,"B",L15>95%,"C") -> C | P15: C | Q15: 0.05
B16: lux2 | C16: ='Юнит 05-11.01'!AE18 -> 0 | D16: =C16/C$26 -> 0 | E16: =D16+E15 -> 0.96587297 | F16: =IF(AND(E16<=0),"C",IF(E16<=0.8,"A",IF(E16<=0.95,"B","C"))) -> C | G16: =VLOOKUP(B$4:B$25,I$4:M$25,5,0) -> C | I16: MR8854 C2 | J16: ='Юнит 05-11.01'!R10 -> 0 | K16: =J16/J$26 -> 0 | L16: =K16+L15 -> 0.96296296 | M16: =_xlfn.IFS(L16<80%,"A",L16<=95%,"B",L16>95%,"C") -> C
B17: lux3 | C17: ='Юнит 05-11.01'!AE19 -> 0 | D17: =C17/C$26 -> 0 | E17: =D17+E16 -> 0.96587297 | F17: =IF(AND(E17<=0),"C",IF(E17<=0.8,"A",IF(E17<=0.95,"B","C"))) -> C | G17: =VLOOKUP(B$4:B$25,I$4:M$25,5,0) -> C | I17: MR 1819 черн | J17: ='Юнит 05-11.01'!R11 -> 0 | K17: =J17/J$26 -> 0 | L17: =K17+L16 -> 0.96296296 | M17: =_xlfn.IFS(L17<80%,"A",L17<=95%,"B",L17>95%,"C") -> C
B18: lux4 | C18: ='Юнит 05-11.01'!AE20 -> 0 | D18: =C18/C$26 -> 0 | E18: =D18+E17 -> 0.96587297 | F18: =IF(AND(E18<=0),"C",IF(E18<=0.8,"A",IF(E18<=0.95,"B","C"))) -> C | G18: =VLOOKUP(B$4:B$25,I$4:M$25,5,0) -> C | I18: lux1 | J18: ='Юнит 05-11.01'!R17 -> 0 | K18: =J18/J$26 -> 0 | L18: =K18+L17 -> 0.96296296 | M18: =_xlfn.IFS(L18<80%,"A",L18<=95%,"B",L18>95%,"C") -> C
B19: lux5 | C19: ='Юнит 05-11.01'!AE21 -> 0 | D19: =C19/C$26 -> 0 | E19: =D19+E18 -> 0.96587297 | F19: =IF(AND(E19<=0),"C",IF(E19<=0.8,"A",IF(E19<=0.95,"B","C"))) -> C | G19: =VLOOKUP(B$4:B$25,I$4:M$25,5,0) -> C | I19: lux2 | J19: ='Юнит 05-11.01'!R18 -> 0 | K19: =J19/J$26 -> 0 | L19: =K19+L18 -> 0.96296296 | M19: =_xlfn.IFS(L19<80%,"A",L19<=95%,"B",L19>95%,"C") -> C
B20: lux6 | C20: ='Юнит 05-11.01'!AE22 -> 0 | D20: =C20/C$26 -> 0 | E20: =D20+E19 -> 0.96587297 | F20: =IF(AND(E20<=0),"C",IF(E20<=0.8,"A",IF(E20<=0.95,"B","C"))) -> C | G20: =VLOOKUP(B$4:B$25,I$4:M$25,5,0) -> C | I20: lux3 | J20: ='Юнит 05-11.01'!R19 -> 0 | K20: =J20/J$26 -> 0 | L20: =K20+L19 -> 0.96296296 | M20: =_xlfn.IFS(L20<80%,"A",L20<=95%,"B",L20>95%,"C") -> C
B21: lux7 | C21: ='Юнит 05-11.01'!AE23 -> 0 | D21: =C21/C$26 -> 0 | E21: =D21+E20 -> 0.96587297 | F21: =IF(AND(E21<=0),"C",IF(E21<=0.8,"A",IF(E21<=0.95,"B","C"))) -> C | G21: =VLOOKUP(B$4:B$25,I$4:M$25,5,0) -> C | I21: lux4 | J21: ='Юнит 05-11.01'!R20 -> 0 | K21: =J21/J$26 -> 0 | L21: =K21+L20 -> 0.96296296 | M21: =_xlfn.IFS(L21<80%,"A",L21<=95%,"B",L21>95%,"C") -> C
B22: lux8 | C22: ='Юнит 05-11.01'!AE24 -> 0 | D22: =C22/C$26 -> 0 | E22: =D22+E21 -> 0.96587297 | F22: =IF(AND(E22<=0),"C",IF(E22<=0.8,"A",IF(E22<=0.95,"B","C"))) -> C | G22: =VLOOKUP(B$4:B$25,I$4:M$25,5,0) -> C | I22: lux5 | J22: ='Юнит 05-11.01'!R21 -> 0 | K22: =J22/J$26 -> 0 | L22: =K22+L21 -> 0.96296296 | M22: =_xlfn.IFS(L22<80%,"A",L22<=95%,"B",L22>95%,"C") -> C
B23: qs коричневые | C23: ='Юнит 05-11.01'!AE7 -> -11.197255 | D23: =C23/C$26 -> -0.0011050263 | E23: =D23+E22 -> 0.96476794 | F23: =IF(AND(E23<=0),"C",IF(E23<=0.8,"A",IF(E23<=0.95,"B","C"))) -> C | G23: =VLOOKUP(B$4:B$25,I$4:M$25,5,0) -> B | I23: lux6 | J23: ='Юнит 05-11.01'!R22 -> 0 | K23: =J23/J$26 -> 0 | L23: =K23+L22 -> 0.96296296 | M23: =_xlfn.IFS(L23<80%,"A",L23<=95%,"B",L23>95%,"C") -> C
B24: MR8854 C2 | C24: ='Юнит 05-11.01'!AE10 -> -93.54 | D24: =C24/C$26 -> -0.0092312057 | E24: =D24+E23 -> 0.95553674 | F24: =IF(AND(E24<=0),"C",IF(E24<=0.8,"A",IF(E24<=0.95,"B","C"))) -> C | G24: =VLOOKUP(B$4:B$25,I$4:M$25,5,0) -> C | I24: lux7 | J24: ='Юнит 05-11.01'!R23 -> 0 | K24: =J24/J$26 -> 0 | L24: =K24+L23 -> 0.96296296 | M24: =_xlfn.IFS(L24<80%,"A",L24<=95%,"B",L24>95%,"C") -> C
B25: flip желтые Сул | C25: ='Юнит 05-11.01'!AE9 -> -190.88285 | D25: =C25/C$26 -> -0.018837704 | E25: =D25+E24 -> 0.93669904 | F25: =IF(AND(E25<=0),"C",IF(E25<=0.8,"A",IF(E25<=0.95,"B","C"))) -> B | G25: =VLOOKUP(B$4:B$25,I$4:M$25,5,0) -> B | I25: lux8 | J25: ='Юнит 05-11.01'!R24 -> 0 | K25: =J25/J$26 -> 0 | L25: =K25+L24 -> 0.96296296 | M25: =_xlfn.IFS(L25<80%,"A",L25<=95%,"B",L25>95%,"C") -> C
C26: =SUM(C4:C25) -> 10133.021 | D26: =SUM(D4:D25) -> 1 | J26: =SUM(J4:J25) -> 54 | K26: =SUM(K4:K25) -> 1
B28: ТУНИКИ
C29: Прибыль | D29: % прибыль | E29: Доля | F29: ABC прибыль | G29: ABC кол-во | J29: Кол-во | K29: % кол-во | L29: Доля | M29: ABC кол-во
B30: tunika14 халат с разрезами белая | C30: ='Юнит 05-11.01'!AE42 -> 1422.85 | D30: =C30/C$50 -> 0.53163259 | E30: =D30 -> 0.53163259 | F30: =IF(AND(E30<=0),"C",IF(E30<=0.8,"A",IF(E30<=0.95,"B","C"))) -> A | G30: =VLOOKUP(B$30:B$50,I$30:M$50,5,0) -> A | I30: tunika14 халат с разрезами белая | J30: ='Юнит 05-11.01'!R42 -> 1 | K30: =J30/J$50 -> 0.5 | L30: =K30 -> 0.5 | M30: =_xlfn.IFS(L30<80%,"A",L30<=95%,"B",L30>95%,"C") -> A
B31: tunika15 кимоно песочная | C31: ='Юнит 05-11.01'!AE45 -> 1481.2884 | D31: =C31/C$50 -> 0.55346748 | E31: =D31+E30 -> 1.0851001 | F31: =IF(AND(E31<=0),"C",IF(E31<=0.8,"A",IF(E31<=0.95,"B","C"))) -> C | G31: =VLOOKUP(B$30:B$50,I$30:M$50,5,0) -> C | I31: tunika15 кимоно песочная | J31: ='Юнит 05-11.01'!R45 -> 1 | K31: =J31/J$50 -> 0.5 | L31: =K31+L30 -> 1 | M31: =_xlfn.IFS(L31<80%,"A",L31<=95%,"B",L31>95%,"C") -> C
B32: tunika02 оливковая с руч вышивкой | C32: ='Юнит 05-11.01'!AE28 -> 0 | D32: =C32/C$50 -> 0 | E32: =D32+E31 -> 1.0851001 | F32: =IF(AND(E32<=0),"C",IF(E32<=0.8,"A",IF(E32<=0.95,"B","C"))) -> C | G32: =VLOOKUP(B$30:B$50,I$30:M$50,5,0) -> C | I32: tunika02 оливковая с руч вышивкой | J32: ='Юнит 05-11.01'!R28 -> 0 | K32: =J32/J$50 -> 0 | L32: =K32+L31 -> 1 | M32: =_xlfn.IFS(L32<80%,"A",L32<=95%,"B",L32>95%,"C") -> C
B33: tunika03 черная распашная | C33: ='Юнит 05-11.01'!AE29 -> 0 | D33: =C33/C$50 -> 0 | E33: =D33+E32 -> 1.0851001 | F33: =IF(AND(E33<=0),"C",IF(E33<=0.8,"A",IF(E33<=0.95,"B","C"))) -> C | G33: =VLOOKUP(B$30:B$50,I$30:M$50,5,0) -> C | I33: tunika03 черная распашная | J33: ='Юнит 05-11.01'!R29 -> 0 | K33: =J33/J$50 -> 0 | L33: =K33+L32 -> 1 | M33: =_xlfn.IFS(L33<80%,"A",L33<=95%,"B",L33>95%,"C") -> C
B34: tunika05 белая распашная | C34: ='Юнит 05-11.01'!AE30 -> 0 | D34: =C34/C$50 -> 0 | E34: =D34+E33 -> 1.0851001 | F34: =IF(AND(E34<=0),"C",IF(E34<=0.8,"A",IF(E34<=0.95,"B","C"))) -> C | G34: =VLOOKUP(B$30:B$50,I$30:M$50,5,0) -> C | I34: tunika05 белая распашная | J34: ='Юнит 05-11.01'!R30 -> 0 | K34: =J34/J$50 -> 0 | L34: =K34+L33 -> 1 | M34: =_xlfn.IFS(L34<80%,"A",L34<=95%,"B",L34>95%,"C") -> C
B35: tunika06 белая | C35: ='Юнит 05-11.01'!AE31 -> 0 | D35: =C35/C$50 -> 0 | E35: =D35+E34 -> 1.0851001 | F35: =IF(AND(E35<=0),"C",IF(E35<=0.8,"A",IF(E35<=0.95,"B","C"))) -> C | G35: =VLOOKUP(B$30:B$50,I$30:M$50,5,0) -> C | I35: tunika06 белая | J35: ='Юнит 05-11.01'!R31 -> 0 | K35: =J35/J$50 -> 0 | L35: =K35+L34 -> 1 | M35: =_xlfn.IFS(L35<80%,"A",L35<=95%,"B",L35>95%,"C") -> C
B36: tunika06 черная | C36: ='Юнит 05-11.01'!AE32 -> 0 | D36: =C36/C$50 -> 0 | E36: =D36+E35 -> 1.0851001 | F36: =IF(AND(E36<=0),"C",IF(E36<=0.8,"A",IF(E36<=0.95,"B","C"))) -> C | G36: =VLOOKUP(B$30:B$50,I$30:M$50,5,0) -> C | I36: tunika06 черная | J36: ='Юнит 05-11.01'!R32 -> 0 | K36: =J36/J$50 -> 0 | L36: =K36+L35 -> 1 | M36: =_xlfn.IFS(L36<80%,"A",L36<=95%,"B",L36>95%,"C") -> C
B37: tunika07 кружево | C37: ='Юнит 05-11.01'!AE33 -> 0 | D37: =C37/C$50 -> 0 | E37: =D37+E36 -> 1.0851001 | F37: =IF(AND(E37<=0),"C",IF(E37<=0.8,"A",IF(E37<=0.95,"B","C"))) -> C | G37: =VLOOKUP(B$30:B$50,I$30:M$50,5,0) -> C | I37: tunika07 кружево | J37: ='Юнит 05-11.01'!R33 -> 0 | K37: =J37/J$50 -> 0 | L37: =K37+L36 -> 1 | M37: =_xlfn.IFS(L37<80%,"A",L37<=95%,"B",L37>95%,"C") -> C
B38: tunika08 белая | C38: ='Юнит 05-11.01'!AE34 -> 0 | D38: =C38/C$50 -> 0 | E38: =D38+E37 -> 1.0851001 | F38: =IF(AND(E38<=0),"C",IF(E38<=0.8,"A",IF(E38<=0.95,"B","C"))) -> C | G38: =VLOOKUP(B$30:B$50,I$30:M$50,5,0) -> C | I38: tunika08 белая | J38: ='Юнит 05-11.01'!R34 -> 0 | K38: =J38/J$50 -> 0 | L38: =K38+L37 -> 1 | M38: =_xlfn.IFS(L38<80%,"A",L38<=95%,"B",L38>95%,"C") -> C
B39: tunika08 черная | C39: ='Юнит 05-11.01'!AE35 -> 0 | D39: =C39/C$50 -> 0 | E39: =D39+E38 -> 1.0851001 | F39: =IF(AND(E39<=0),"C",IF(E39<=0.8,"A",IF(E39<=0.95,"B","C"))) -> C | G39: =VLOOKUP(B$30:B$50,I$30:M$50,5,0) -> C | I39: tunika08 черная | J39: ='Юнит 05-11.01'!R35 -> 0 | K39: =J39/J$50 -> 0 | L39: =K39+L38 -> 1 | M39: =_xlfn.IFS(L39<80%,"A",L39<=95%,"B",L39>95%,"C") -> C
B40: tunika08 зеленая | C40: ='Юнит 05-11.01'!AE36 -> 0 | D40: =C40/C$50 -> 0 | E40: =D40+E39 -> 1.0851001 | F40: =IF(AND(E40<=0),"C",IF(E40<=0.8,"A",IF(E40<=0.95,"B","C"))) -> C | G40: =VLOOKUP(B$30:B$50,I$30:M$50,5,0) -> C | I40: tunika08 зеленая | J40: ='Юнит 05-11.01'!R36 -> 0 | K40: =J40/J$50 -> 0 | L40: =K40+L39 -> 1 | M40: =_xlfn.IFS(L40<80%,"A",L40<=95%,"B",L40>95%,"C") -> C
B41: tunika10 кимоно ч/б | C41: ='Юнит 05-11.01'!AE38 -> 0 | D41: =C41/C$50 -> 0 | E41: =D41+E40 -> 1.0851001 | F41: =IF(AND(E41<=0),"C",IF(E41<=0.8,"A",IF(E41<=0.95,"B","C"))) -> C | G41: =VLOOKUP(B$30:B$50,I$30:M$50,5,0) -> C | I41: tunika09 кимоно | J41: ='Юнит 05-11.01'!R37 -> 0 | K41: =J41/J$50 -> 0 | L41: =K41+L40 -> 1 | M41: =_xlfn.IFS(L41<80%,"A",L41<=95%,"B",L41>95%,"C") -> C
B42: tunika11 халат зеленая | C42: ='Юнит 05-11.01'!AE39 -> 0 | D42: =C42/C$50 -> 0 | E42: =D42+E41 -> 1.0851001 | F42: =IF(AND(E42<=0),"C",IF(E42<=0.8,"A",IF(E42<=0.95,"B","C"))) -> C | G42: =VLOOKUP(B$30:B$50,I$30:M$50,5,0) -> C | I42: tunika10 кимоно ч/б | J42: ='Юнит 05-11.01'!R38 -> 0 | K42: =J42/J$50 -> 0 | L42: =K42+L41 -> 1 | M42: =_xlfn.IFS(L42<80%,"A",L42<=95%,"B",L42>95%,"C") -> C
B43: tunika12 халат белая | C43: ='Юнит 05-11.01'!AE40 -> 0 | D43: =C43/C$50 -> 0 | E43: =D43+E42 -> 1.0851001 | F43: =IF(AND(E43<=0),"C",IF(E43<=0.8,"A",IF(E43<=0.95,"B","C"))) -> C | G43: =VLOOKUP(B$30:B$50,I$30:M$50,5,0) -> C | I43: tunika11 халат зеленая | J43: ='Юнит 05-11.01'!R39 -> 0 | K43: =J43/J$50 -> 0 | L43: =K43+L42 -> 1 | M43: =_xlfn.IFS(L43<80%,"A",L43<=95%,"B",L43>95%,"C") -> C
B44: tunika13 халат черная | C44: ='Юнит 05-11.01'!AE41 -> 0 | D44: =C44/C$50 -> 0 | E44: =D44+E43 -> 1.0851001 | F44: =IF(AND(E44<=0),"C",IF(E44<=0.8,"A",IF(E44<=0.95,"B","C"))) -> C | G44: =VLOOKUP(B$30:B$50,I$30:M$50,5,0) -> C | I44: tunika12 халат белая | J44: ='Юнит 05-11.01'!R40 -> 0 | K44: =J44/J$50 -> 0 | L44: =K44+L43 -> 1 | M44: =_xlfn.IFS(L44<80%,"A",L44<=95%,"B",L44>95%,"C") -> C
B45: tunika14 халат с разрезами черный | C45: ='Юнит 05-11.01'!AE43 -> 0 | D45: =C45/C$50 -> 0 | E45: =D45+E44 -> 1.0851001 | F45: =IF(AND(E45<=0),"C",IF(E45<=0.8,"A",IF(E45<=0.95,"B","C"))) -> C | G45: =VLOOKUP(B$30:B$50,I$30:M$50,5,0) -> C | I45: tunika13 халат черная | J45: ='Юнит 05-11.01'!R41 -> 0 | K45: =J45/J$50 -> 0 | L45: =K45+L44 -> 1 | M45: =_xlfn.IFS(L45<80%,"A",L45<=95%,"B",L45>95%,"C") -> C
B46: tunika15 кимоно бирюза | C46: ='Юнит 05-11.01'!AE44 -> 0 | D46: =C46/C$50 -> 0 | E46: =D46+E45 -> 1.0851001 | F46: =IF(AND(E46<=0),"C",IF(E46<=0.8,"A",IF(E46<=0.95,"B","C"))) -> C | G46: =VLOOKUP(B$30:B$50,I$30:M$50,5,0) -> C | I46: tunika14 халат с разрезами черный | J46: ='Юнит 05-11.01'!R43 -> 0 | K46: =J46/J$50 -> 0 | L46: =K46+L45 -> 1 | M46: =_xlfn.IFS(L46<80%,"A",L46<=95%,"B",L46>95%,"C") -> C
B47: tunika16 сетка черная | C47: ='Юнит 05-11.01'!AE47 -> 0 | D47: =C47/C$50 -> 0 | E47: =D47+E46 -> 1.0851001 | F47: =IF(AND(E47<=0),"C",IF(E47<=0.8,"A",IF(E47<=0.95,"B","C"))) -> C | G47: =VLOOKUP(B$30:B$50,I$30:M$50,5,0) -> C | I47: tunika15 кимоно бирюза | J47: ='Юнит 05-11.01'!R44 -> 0 | K47: =J47/J$50 -> 0 | L47: =K47+L46 -> 1 | M47: =_xlfn.IFS(L47<80%,"A",L47<=95%,"B",L47>95%,"C") -> C
B48: tunika09 кимоно | C48: ='Юнит 05-11.01'!AE37 -> -113.88 | D48: =C48/C$50 -> -0.042550036 | E48: =D48+E47 -> 1.04255 | F48: =IF(AND(E48<=0),"C",IF(E48<=0.8,"A",IF(E48<=0.95,"B","C"))) -> C | G48: =VLOOKUP(B$30:B$50,I$30:M$50,5,0) -> C | I48: tunika16 сетка белая | J48: ='Юнит 05-11.01'!R46 -> 0 | K48: =J48/J$50 -> 0 | L48: =K48+L47 -> 1 | M48: =_xlfn.IFS(L48<80%,"A",L48<=95%,"B",L48>95%,"C") -> C
B49: tunika16 сетка белая | C49: ='Юнит 05-11.01'!AE46 -> -113.88 | D49: =C49/C$50 -> -0.042550036 | E49: =D49+E48 -> 1 | F49: =IF(AND(E49<=0),"C",IF(E49<=0.8,"A",IF(E49<=0.95,"B","C"))) -> C | G49: =VLOOKUP(B$30:B$50,I$30:M$50,5,0) -> C | I49: tunika16 сетка черная | J49: ='Юнит 05-11.01'!R47 -> 0 | K49: =J49/J$50 -> 0 | L49: =K49+L48 -> 1 | M49: =_xlfn.IFS(L49<80%,"A",L49<=95%,"B",L49>95%,"C") -> C
C50: =SUM(C30:C49) -> 2676.3784 | D50: =SUM(D30:D49) -> 1 | J50: =SUM(J30:J49) -> 2 | K50: =SUM(K30:K49) -> 1

Sheet АВС 01-04.01
B2: ОЧКИ
C3: Прибыль | D3: % прибыль | E3: Доля | F3: ABC прибыль | G3: ABC кол-во | J3: Кол-во | K3: % кол-во | L3: Доля | M3: ABC кол-во
B4: qs желтые | C4: ='Юнит 01-04.01'!AE6 -> 2714.1158 | D4: =C4/C$26 -> 0.52947686 | E4: =D4 -> 0.52947686 | F4: =IF(AND(E4<=0),"C",IF(E4<=0.8,"A",IF(E4<=0.95,"B","C"))) -> A | G4: =VLOOKUP(B$4:B$25,I$4:M$25,5,0) -> B | I4: черные с железкой классика | J4: ='Юнит 01-04.01'!R3 -> 14 | K4: =J4/J$26 -> 0.5 | L4: =K4 -> 0.5 | M4: =_xlfn.IFS(L4<80%,"A",L4<=95%,"B",L4>95%,"C") -> A
B5: lux4 | C5: ='Юнит 01-04.01'!AE20 -> 1644.69 | D5: =C5/C$26 -> 0.32085046 | E5: =D5+E4 -> 0.85032732 | F5: =IF(AND(E5<=0),"C",IF(E5<=0.8,"A",IF(E5<=0.95,"B","C"))) -> B | G5: =VLOOKUP(B$4:B$25,I$4:M$25,5,0) -> C | I5: qs желтые | J5: ='Юнит 01-04.01'!R6 -> 10 | K5: =J5/J$26 -> 0.35714286 | L5: =K5+L4 -> 0.85714286 | M5: =_xlfn.IFS(L5<80%,"A",L5<=95%,"B",L5>95%,"C") -> B
B6: qs коричневые | C6: ='Юнит 01-04.01'!AE7 -> 576.14 | D6: =C6/C$26 -> 0.11239491 | E6: =D6+E5 -> 0.96272223 | F6: =IF(AND(E6<=0),"C",IF(E6<=0.8,"A",IF(E6<=0.95,"B","C"))) -> C | G6: =VLOOKUP(B$4:B$25,I$4:M$25,5,0) -> C | I6: qs черные | J6: ='Юнит 01-04.01'!R4 -> 1 | K6: =J6/J$26 -> 0.035714286 | L6: =K6+L5 -> 0.89285714 | M6: =_xlfn.IFS(L6<80%,"A",L6<=95%,"B",L6>95%,"C") -> B
B7: qs синие | C7: ='Юнит 01-04.01'!AE5 -> 458.39 | D7: =C7/C$26 -> 0.089423928 | E7: =D7+E6 -> 1.0521462 | F7: =IF(AND(E7<=0),"C",IF(E7<=0.8,"A",IF(E7<=0.95,"B","C"))) -> C | G7: =VLOOKUP(B$4:B$25,I$4:M$25,5,0) -> B | I7: qs синие | J7: ='Юнит 01-04.01'!R5 -> 1 | K7: =J7/J$26 -> 0.035714286 | L7: =K7+L6 -> 0.92857143 | M7: =_xlfn.IFS(L7<80%,"A",L7<=95%,"B",L7>95%,"C") -> B
B8: qs черные | C8: ='Юнит 01-04.01'!AE4 -> 448.21 | D8: =C8/C$26 -> 0.087437987 | E8: =D8+E7 -> 1.1395841 | F8: =IF(AND(E8<=0),"C",IF(E8<=0.8,"A",IF(E8<=0.95,"B","C"))) -> C | G8: =VLOOKUP(B$4:B$25,I$4:M$25,5,0) -> B | I8: qs коричневые | J8: ='Юнит 01-04.01'!R7 -> 1 | K8: =J8/J$26 -> 0.035714286 | L8: =K8+L7 -> 0.96428571 | M8: =_xlfn.IFS(L8<80%,"A",L8<=95%,"B",L8>95%,"C") -> C
B9: th желтый Сул | C9: ='Юнит 01-04.01'!AE8 -> 0 | D9: =C9/C$26 -> 0 | E9: =D9+E8 -> 1.1395841 | F9: =IF(AND(E9<=0),"C",IF(E9<=0.8,"A",IF(E9<=0.95,"B","C"))) -> C | G9: =VLOOKUP(B$4:B$25,I$4:M$25,5,0) -> C | I9: lux4 | J9: ='Юнит 01-04.01'!R20 -> 1 | K9: =J9/J$26 -> 0.035714286 | L9: =K9+L8 -> 1 | M9: =_xlfn.IFS(L9<80%,"A",L9<=95%,"B",L9>95%,"C") -> C
B10: MR8854 C2 | C10: ='Юнит 01-04.01'!AE10 -> 0 | D10: =C10/C$26 -> 0 | E10: =D10+E9 -> 1.1395841 | F10: =IF(AND(E10<=0),"C",IF(E10<=0.8,"A",IF(E10<=0.95,"B","C"))) -> C | G10: =VLOOKUP(B$4:B$25,I$4:M$25,5,0) -> C | I10: th желтый Сул | J10: ='Юнит 01-04.01'!R8 -> 0 | K10: =J10/J$26 -> 0 | L10: =K10+L9 -> 1 | M10: =_xlfn.IFS(L10<80%,"A",L10<=95%,"B",L10>95%,"C") -> C
B11: MR 1819 черн | C11: ='Юнит 01-04.01'!AE11 -> 0 | D11: =C11/C$26 -> 0 | E11: =D11+E8 -> 1.1395841 | F11: =IF(AND(E11<=0),"C",IF(E11<=0.8,"A",IF(E11<=0.95,"B","C"))) -> C | G11: =VLOOKUP(B$4:B$25,I$4:M$25,5,0) -> C | I11: flip желтые Сул | J11: ='Юнит 01-04.01'!R9 -> 0 | K11: =J11/J$26 -> 0 | L11: =K11+L8 -> 0.96428571 | M11: =_xlfn.IFS(L11<80%,"A",L11<=95%,"B",L11>95%,"C") -> C
B12: MR 1819 корич | C12: ='Юнит 01-04.01'!AE12 -> 0 | D12: =C12/C$26 -> 0 | E12: =D12+E11 -> 1.1395841 | F12: =IF(AND(E12<=0),"C",IF(E12<=0.8,"A",IF(E12<=0.95,"B","C"))) -> C | G12: =VLOOKUP(B$4:B$25,I$4:M$25,5,0) -> C | I12: MR8854 C2 | J12: ='Юнит 01-04.01'!R10 -> 0 | K12: =J12/J$26 -> 0 | L12: =K12+L11 -> 0.96428571 | M12: =_xlfn.IFS(L12<80%,"A",L12<=95%,"B",L12>95%,"C") -> C
B13: MR Р1874 корич | C13: ='Юнит 01-04.01'!AE14 -> 0 | D13: =C13/C$26 -> 0 | E13: =D13+E12 -> 1.1395841 | F13: =IF(AND(E13<=0),"C",IF(E13<=0.8,"A",IF(E13<=0.95,"B","C"))) -> C | G13: =VLOOKUP(B$4:B$25,I$4:M$25,5,0) -> C | I13: MR 1819 черн | J13: ='Юнит 01-04.01'!R11 -> 0 | K13: =J13/J$26 -> 0 | L13: =K13+L12 -> 0.96428571 | M13: =_xlfn.IFS(L13<80%,"A",L13<=95%,"B",L13>95%,"C") -> C | P13: A | Q13: 0.8
B14: MR Р1886 корич | C14: ='Юнит 01-04.01'!AE16 -> 0 | D14: =C14/C$26 -> 0 | E14: =D14+E13 -> 1.1395841 | F14: =IF(AND(E14<=0),"C",IF(E14<=0.8,"A",IF(E14<=0.95,"B","C"))) -> C | G14: =VLOOKUP(B$4:B$25,I$4:M$25,5,0) -> C | I14: MR 1819 корич | J14: ='Юнит 01-04.01'!R12 -> 0 | K14: =J14/J$26 -> 0 | L14: =K14+L13 -> 0.96428571 | M14: =_xlfn.IFS(L14<80%,"A",L14<=95%,"B",L14>95%,"C") -> C | P14: B | Q14: 0.15
B15: lux1 | C15: ='Юнит 01-04.01'!AE17 -> 0 | D15: =C15/C$26 -> 0 | E15: =D15+E14 -> 1.1395841 | F15: =IF(AND(E15<=0),"C",IF(E15<=0.8,"A",IF(E15<=0.95,"B","C"))) -> C | G15: =VLOOKUP(B$4:B$25,I$4:M$25,5,0) -> C | I15: MR Р1874 черн | J15: ='Юнит 01-04.01'!R13 -> 0 | K15: =J15/J$26 -> 0 | L15: =K15+L14 -> 0.96428571 | M15: =_xlfn.IFS(L15<80%,"A",L15<=95%,"B",L15>95%,"C") -> C | P15: C | Q15: 0.05
B16: lux2 | C16: ='Юнит 01-04.01'!AE18 -> 0 | D16: =C16/C$26 -> 0 | E16: =D16+E15 -> 1.1395841 | F16: =IF(AND(E16<=0),"C",IF(E16<=0.8,"A",IF(E16<=0.95,"B","C"))) -> C | G16: =VLOOKUP(B$4:B$25,I$4:M$25,5,0) -> C | I16: MR Р1874 корич | J16: ='Юнит 01-04.01'!R14 -> 0 | K16: =J16/J$26 -> 0 | L16: =K16+L15 -> 0.96428571 | M16: =_xlfn.IFS(L16<80%,"A",L16<=95%,"B",L16>95%,"C") -> C
B17: lux3 | C17: ='Юнит 01-04.01'!AE19 -> 0 | D17: =C17/C$26 -> 0 | E17: =D17+E16 -> 1.1395841 | F17: =IF(AND(E17<=0),"C",IF(E17<=0.8,"A",IF(E17<=0.95,"B","C"))) -> C | G17: =VLOOKUP(B$4:B$25,I$4:M$25,5,0) -> C | I17: MR Р1886 черн глянец | J17: ='Юнит 01-04.01'!R15 -> 0 | K17: =J17/J$26 -> 0 | L17: =K17+L16 -> 0.96428571 | M17: =_xlfn.IFS(L17<80%,"A",L17<=95%,"B",L17>95%,"C") -> C
B18: lux5 | C18: ='Юнит 01-04.01'!AE21 -> 0 | D18: =C18/C$26 -> 0 | E18: =D18+E17 -> 1.1395841 | F18: =IF(AND(E18<=0),"C",IF(E18<=0.8,"A",IF(E18<=0.95,"B","C"))) -> C | G18: =VLOOKUP(B$4:B$25,I$4:M$25,5,0) -> C | I18: MR Р1886 корич | J18: ='Юнит 01-04.01'!R16 -> 0 | K18: =J18/J$26 -> 0 | L18: =K18+L17 -> 0.96428571 | M18: =_xlfn.IFS(L18<80%,"A",L18<=95%,"B",L18>95%,"C") -> C
B19: lux6 | C19: ='Юнит 01-04.01'!AE22 -> 0 | D19: =C19/C$26 -> 0 | E19: =D19+E18 -> 1.1395841 | F19: =IF(AND(E19<=0),"C",IF(E19<=0.8,"A",IF(E19<=0.95,"B","C"))) -> C | G19: =VLOOKUP(B$4:B$25,I$4:M$25,5,0) -> C | I19: lux1 | J19: ='Юнит 01-04.01'!R17 -> 0 | K19: =J19/J$26 -> 0 | L19: =K19+L18 -> 0.96428571 | M19: =_xlfn.IFS(L19<80%,"A",L19<=95%,"B",L19>95%,"C") -> C
B20: lux7 | C20: ='Юнит 01-04.01'!AE23 -> 0 | D20: =C20/C$26 -> 0 | E20: =D20+E19 -> 1.1395841 | F20: =IF(AND(E20<=0),"C",IF(E20<=0.8,"A",IF(E20<=0.95,"B","C"))) -> C | G20: =VLOOKUP(B$4:B$25,I$4:M$25,5,0) -> C | I20: lux2 | J20: ='Юнит 01-04.01'!R18 -> 0 | K20: =J20/J$26 -> 0 | L20: =K20+L19 -> 0.96428571 | M20: =_xlfn.IFS(L20<80%,"A",L20<=95%,"B",L20>95%,"C") -> C
B21: lux8 | C21: ='Юнит 01-04.01'!AE24 -> 0 | D21: =C21/C$26 -> 0 | E21: =D21+E20 -> 1.1395841 | F21: =IF(AND(E21<=0),"C",IF(E21<=0.8,"A",IF(E21<=0.95,"B","C"))) -> C | G21: =VLOOKUP(B$4:B$25,I$4:M$25,5,0) -> C | I21: lux3 | J21: ='Юнит 01-04.01'!R19 -> 0 | K21: =J21/J$26 -> 0 | L21: =K21+L20 -> 0.96428571 | M21: =_xlfn.IFS(L21<80%,"A",L21<=95%,"B",L21>95%,"C") -> C
B22: MR Р1874 черн | C22: ='Юнит 01-04.01'!AE13 -> -93.54 | D22: =C22/C$26 -> -0.018248029 | E22: =D22+E21 -> 1.1213361 | F22: =IF(AND(E22<=0),"C",IF(E22<=0.8,"A",IF(E22<=0.95,"B","C"))) -> C | G22: =VLOOKUP(B$4:B$25,I$4:M$25,5,0) -> C | I22: lux5 | J22: ='Юнит 01-04.01'!R21 -> 0 | K22: =J22/J$26 -> 0 | L22: =K22+L21 -> 0.96428571 | M22: =_xlfn.IFS(L22<80%,"A",L22<=95%,"B",L22>95%,"C") -> C
B23: MR Р1886 черн глянец | C23: ='Юнит 01-04.01'!AE15 -> -295.55 | D23: =C23/C$26 -> -0.057656672 | E23: =D23+E22 -> 1.0636794 | F23: =IF(AND(E23<=0),"C",IF(E23<=0.8,"A",IF(E23<=0.95,"B","C"))) -> C | G23: =VLOOKUP(B$4:B$25,I$4:M$25,5,0) -> C | I23: lux6 | J23: ='Юнит 01-04.01'!R22 -> 0 | K23: =J23/J$26 -> 0 | L23: =K23+L22 -> 0.96428571 | M23: =_xlfn.IFS(L23<80%,"A",L23<=95%,"B",L23>95%,"C") -> C
B24: flip желтые Сул | C24: ='Юнит 01-04.01'!AE9 -> -509.46505 | D24: =C24/C$26 -> -0.099387784 | E24: =D24+E23 -> 0.96429165 | F24: =IF(AND(E24<=0),"C",IF(E24<=0.8,"A",IF(E24<=0.95,"B","C"))) -> C | G24: =VLOOKUP(B$4:B$25,I$4:M$25,5,0) -> C | I24: lux7 | J24: ='Юнит 01-04.01'!R23 -> 0 | K24: =J24/J$26 -> 0 | L24: =K24+L23 -> 0.96428571 | M24: =_xlfn.IFS(L24<80%,"A",L24<=95%,"B",L24>95%,"C") -> C
B25: черные с железкой классика | C25: ='Юнит 01-04.01'!AE3 -> 183.04216 | D25: =C25/C$26 -> 0.035708346 | E25: =D25+E24 -> 1 | F25: =IF(AND(E25<=0),"C",IF(E25<=0.8,"A",IF(E25<=0.95,"B","C"))) -> C | G25: =VLOOKUP(B$4:B$25,I$4:M$25,5,0) -> A | I25: lux8 | J25: ='Юнит 01-04.01'!R24 -> 0 | K25: =J25/J$26 -> 0 | L25: =K25+L24 -> 0.96428571 | M25: =_xlfn.IFS(L25<80%,"A",L25<=95%,"B",L25>95%,"C") -> C
C26: =SUM(C4:C25) -> 5126.0329 | D26: =SUM(D4:D25) -> 1 | J26: =SUM(J4:J25) -> 28 | K26: =SUM(K4:K25) -> 1
B28: ТУНИКИ
C29: Прибыль | D29: % прибыль | E29: Доля | F29: ABC прибыль | G29: ABC кол-во | J29: Кол-во | K29: % кол-во | L29: Доля | M29: ABC кол-во
B30: tunika08 белая | C30: ='Юнит 01-04.01'!AE34 -> 1595.12 | D30: =C30/C$50 -> -1.7269284 | E30: =D30 -> -1.7269284 | F30: =IF(AND(E30<=0),"C",IF(E30<=0.8,"A",IF(E30<=0.95,"B","C"))) -> C | G30: =VLOOKUP(B$30:B$50,I$30:M$50,5,0) -> C | I30: tunika08 белая | J30: ='Юнит 01-04.01'!R34 -> 1 | K30: =J30/J$50 -> 1 | L30: =K30 -> 1 | M30: =_xlfn.IFS(L30<80%,"A",L30<=95%,"B",L30>95%,"C") -> C
B31: tunika02 оливковая с руч вышивкой | C31: ='Юнит 01-04.01'!AE28 -> 0 | D31: =C31/C$50 -> 0 | E31: =D31+E30 -> -1.7269284 | F31: =IF(AND(E31<=0),"C",IF(E31<=0.8,"A",IF(E31<=0.95,"B","C"))) -> C | G31: =VLOOKUP(B$30:B$50,I$30:M$50,5,0) -> C | I31: tunika02 оливковая с руч вышивкой | J31: ='Юнит 01-04.01'!R28 -> 0 | K31: =J31/J$50 -> 0 | L31: =K31+L30 -> 1 | M31: =_xlfn.IFS(L31<80%,"A",L31<=95%,"B",L31>95%,"C") -> C
B32: tunika03 черная распашная | C32: ='Юнит 01-04.01'!AE29 -> 0 | D32: =C32/C$50 -> 0 | E32: =D32+E31 -> -1.7269284 | F32: =IF(AND(E32<=0),"C",IF(E32<=0.8,"A",IF(E32<=0.95,"B","C"))) -> C | G32: =VLOOKUP(B$30:B$50,I$30:M$50,5,0) -> C | I32: tunika03 черная распашная | J32: ='Юнит 01-04.01'!R29 -> 0 | K32: =J32/J$50 -> 0 | L32: =K32+L31 -> 1 | M32: =_xlfn.IFS(L32<80%,"A",L32<=95%,"B",L32>95%,"C") -> C
B33: tunika05 белая распашная | C33: ='Юнит 01-04.01'!AE30 -> 0 | D33: =C33/C$50 -> 0 | E33: =D33+E32 -> -1.7269284 | F33: =IF(AND(E33<=0),"C",IF(E33<=0.8,"A",IF(E33<=0.95,"B","C"))) -> C | G33: =VLOOKUP(B$30:B$50,I$30:M$50,5,0) -> C | I33: tunika05 белая распашная | J33: ='Юнит 01-04.01'!R30 -> 0 | K33: =J33/J$50 -> 0 | L33: =K33+L32 -> 1 | M33: =_xlfn.IFS(L33<80%,"A",L33<=95%,"B",L33>95%,"C") -> C
B34: tunika06 белая | C34: ='Юнит 01-04.01'!AE31 -> 0 | D34: =C34/C$50 -> 0 | E34: =D34+E33 -> -1.7269284 | F34: =IF(AND(E34<=0),"C",IF(E34<=0.8,"A",IF(E34<=0.95,"B","C"))) -> C | G34: =VLOOKUP(B$30:B$50,I$30:M$50,5,0) -> C | I34: tunika06 белая | J34: ='Юнит 01-04.01'!R31 -> 0 | K34: =J34/J$50 -> 0 | L34: =K34+L33 -> 1 | M34: =_xlfn.IFS(L34<80%,"A",L34<=95%,"B",L34>95%,"C") -> C
B35: tunika06 черная | C35: ='Юнит 01-04.01'!AE32 -> 0 | D35: =C35/C$50 -> 0 | E35: =D35+E34 -> -1.7269284 | F35: =IF(AND(E35<=0),"C",IF(E35<=0.8,"A",IF(E35<=0.95,"B","C"))) -> C | G35: =VLOOKUP(B$30:B$50,I$30:M$50,5,0) -> C | I35: tunika06 черная | J35: ='Юнит 01-04.01'!R32 -> 0 | K35: =J35/J$50 -> 0 | L35: =K35+L34 -> 1 | M35: =_xlfn.IFS(L35<80%,"A",L35<=95%,"B",L35>95%,"C") -> C
B36: tunika07 кружево | C36: ='Юнит 01-04.01'!AE33 -> 0 | D36: =C36/C$50 -> 0 | E36: =D36+E35 -> -1.7269284 | F36: =IF(AND(E36<=0),"C",IF(E36<=0.8,"A",IF(E36<=0.95,"B","C"))) -> C | G36: =VLOOKUP(B$30:B$50,I$30:M$50,5,0) -> C | I36: tunika07 кружево | J36: ='Юнит 01-04.01'!R33 -> 0 | K36: =J36/J$50 -> 0 | L36: =K36+L35 -> 1 | M36: =_xlfn.IFS(L36<80%,"A",L36<=95%,"B",L36>95%,"C") -> C
B37: tunika08 черная | C37: ='Юнит 01-04.01'!AE35 -> 0 | D37: =C37/C$50 -> 0 | E37: =D37+E36 -> -1.7269284 | F37: =IF(AND(E37<=0),"C",IF(E37<=0.8,"A",IF(E37<=0.95,"B","C"))) -> C | G37: =VLOOKUP(B$30:B$50,I$30:M$50,5,0) -> C | I37: tunika08 черная | J37: ='Юнит 01-04.01'!R35 -> 0 | K37: =J37/J$50 -> 0 | L37: =K37+L36 -> 1 | M37: =_xlfn.IFS(L37<80%,"A",L37<=95%,"B",L37>95%,"C") -> C
B38: tunika08 зеленая | C38: ='Юнит 01-04.01'!AE36 -> 0 | D38: =C38/C$50 -> 0 | E38: =D38+E37 -> -1.7269284 | F38: =IF(AND(E38<=0),"C",IF(E38<=0.8,"A",IF(E38<=0.95,"B","C"))) -> C | G38: =VLOOKUP(B$30:B$50,I$30:M$50,5,0) -> C | I38: tunika08 зеленая | J38: ='Юнит 01-04.01'!R36 -> 0 | K38: =J38/J$50 -> 0 | L38: =K38+L37 -> 1 | M38: =_xlfn.IFS(L38<80%,"A",L38<=95%,"B",L38>95%,"C") -> C
B39: tunika09 кимоно | C39: ='Юнит 01-04.01'!AE37 -> 0 | D39: =C39/C$50 -> 0 | E39: =D39+E38 -> -1.7269284 | F39: =IF(AND(E39<=0),"C",IF(E39<=0.8,"A",IF(E39<=0.95,"B","C"))) -> C | G39: =VLOOKUP(B$30:B$50,I$30:M$50,5,0) -> C | I39: tunika09 кимоно | J39: ='Юнит 01-04.01'!R37 -> 0 | K39: =J39/J$50 -> 0 | L39: =K39+L38 -> 1 | M39: =_xlfn.IFS(L39<80%,"A",L39<=95%,"B",L39>95%,"C") -> C
B40: tunika10 кимоно ч/б | C40: ='Юнит 01-04.01'!AE38 -> 0 | D40: =C40/C$50 -> 0 | E40: =D40+E39 -> -1.7269284 | F40: =IF(AND(E40<=0),"C",IF(E40<=0.8,"A",IF(E40<=0.95,"B","C"))) -> C | G40: =VLOOKUP(B$30:B$50,I$30:M$50,5,0) -> C | I40: tunika10 кимоно ч/б | J40: ='Юнит 01-04.01'!R38 -> 0 | K40: =J40/J$50 -> 0 | L40: =K40+L39 -> 1 | M40: =_xlfn.IFS(L40<80%,"A",L40<=95%,"B",L40>95%,"C") -> C
B41: tunika11 халат зеленая | C41: ='Юнит 01-04.01'!AE39 -> 0 | D41: =C41/C$50 -> 0 | E41: =D41+E40 -> -1.7269284 | F41: =IF(AND(E41<=0),"C",IF(E41<=0.8,"A",IF(E41<=0.95,"B","C"))) -> C | G41: =VLOOKUP(B$30:B$50,I$30:M$50,5,0) -> C | I41: tunika11 халат зеленая | J41: ='Юнит 01-04.01'!R39 -> 0 | K41: =J41/J$50 -> 0 | L41: =K41+L40 -> 1 | M41: =_xlfn.IFS(L41<80%,"A",L41<=95%,"B",L41>95%,"C") -> C
B42: tunika12 халат белая | C42: ='Юнит 01-04.01'!AE40 -> 0 | D42: =C42/C$50 -> 0 | E42: =D42+E41 -> -1.7269284 | F42: =IF(AND(E42<=0),"C",IF(E42<=0.8,"A",IF(E42<=0.95,"B","C"))) -> C | G42: =VLOOKUP(B$30:B$50,I$30:M$50,5,0) -> C | I42: tunika12 халат белая | J42: ='Юнит 01-04.01'!R40 -> 0 | K42: =J42/J$50 -> 0 | L42: =K42+L41 -> 1 | M42: =_xlfn.IFS(L42<80%,"A",L42<=95%,"B",L42>95%,"C") -> C
B43: tunika13 халат черная | C43: ='Юнит 01-04.01'!AE41 -> 0 | D43: =C43/C$50 -> 0 | E43: =D43+E42 -> -1.7269284 | F43: =IF(AND(E43<=0),"C",IF(E43<=0.8,"A",IF(E43<=0.95,"B","C"))) -> C | G43: =VLOOKUP(B$30:B$50,I$30:M$50,5,0) -> C | I43: tunika13 халат черная | J43: ='Юнит 01-04.01'!R41 -> 0 | K43: =J43/J$50 -> 0 | L43: =K43+L42 -> 1 | M43: =_xlfn.IFS(L43<80%,"A",L43<=95%,"B",L43>95%,"C") -> C
B44: tunika14 халат с разрезами черный | C44: ='Юнит 01-04.01'!AE43 -> 0 | D44: =C44/C$50 -> 0 | E44: =D44+E43 -> -1.7269284 | F44: =IF(AND(E44<=0),"C",IF(E44<=0.8,"A",IF(E44<=0.95,"B","C"))) -> C | G44: =VLOOKUP(B$30:B$50,I$30:M$50,5,0) -> C | I44: tunika14 халат с разрезами белая | J44: ='Юнит 01-04.01'!R42 -> 0 | K44: =J44/J$50 -> 0 | L44: =K44+L43 -> 1 | M44: =_xlfn.IFS(L44<80%,"A",L44<=95%,"B",L44>95%,"C") -> C
B45: tunika16 сетка черная | C45: ='Юнит 01-04.01'!AE47 -> 0 | D45: =C45/C$50 -> 0 | E45: =D45+E44 -> -1.7269284 | F45: =IF(AND(E45<=0),"C",IF(E45<=0.8,"A",IF(E45<=0.95,"B","C"))) -> C | G45: =VLOOKUP(B$30:B$50,I$30:M$50,5,0) -> C | I45: tunika14 халат с разрезами черный | J45: ='Юнит 01-04.01'!R43 -> 0 | K45: =J45/J$50 -> 0 | L45: =K45+L44 -> 1 | M45: =_xlfn.IFS(L45<80%,"A",L45<=95%,"B",L45>95%,"C") -> C
B46: tunika16 сетка белая | C46: ='Юнит 01-04.01'!AE46 -> -124.26224 | D46: =C46/C$50 -> 0.13453031 | E46: =D46+E45 -> -1.5923981 | F46: =IF(AND(E46<=0),"C",IF(E46<=0.8,"A",IF(E46<=0.95,"B","C"))) -> C | G46: =VLOOKUP(B$30:B$50,I$30:M$50,5,0) -> C | I46: tunika15 кимоно бирюза | J46: ='Юнит 01-04.01'!R44 -> 0 | K46: =J46/J$50 -> 0 | L46: =K46+L45 -> 1 | M46: =_xlfn.IFS(L46<80%,"A",L46<=95%,"B",L46>95%,"C") -> C
B47: tunika15 кимоно бирюза | C47: ='Юнит 01-04.01'!AE44 -> -149.55252 | D47: =C47/C$50 -> 0.16191038 | E47: =D47+E46 -> -1.4304877 | F47: =IF(AND(E47<=0),"C",IF(E47<=0.8,"A",IF(E47<=0.95,"B","C"))) -> C | G47: =VLOOKUP(B$30:B$50,I$30:M$50,5,0) -> C | I47: tunika15 кимоно песочная | J47: ='Юнит 01-04.01'!R45 -> 0 | K47: =J47/J$50 -> 0 | L47: =K47+L46 -> 1 | M47: =_xlfn.IFS(L47<80%,"A",L47<=95%,"B",L47>95%,"C") -> C
B48: tunika14 халат с разрезами белая | C48: ='Юнит 01-04.01'!AE42 -> -976.81 | D48: =C48/C$50 -> 1.057526 | E48: =D48+E47 -> -0.37296166 | F48: =IF(AND(E48<=0),"C",IF(E48<=0.8,"A",IF(E48<=0.95,"B","C"))) -> C | G48: =VLOOKUP(B$30:B$50,I$30:M$50,5,0) -> C | I48: tunika16 сетка белая | J48: ='Юнит 01-04.01'!R46 -> 0 | K48: =J48/J$50 -> 0 | L48: =K48+L47 -> 1 | M48: =_xlfn.IFS(L48<80%,"A",L48<=95%,"B",L48>95%,"C") -> C
B49: tunika15 кимоно песочная | C49: ='Юнит 01-04.01'!AE45 -> -1268.1699 | D49: =C49/C$50 -> 1.3729617 | E49: =D49+E48 -> 1 | F49: =IF(AND(E49<=0),"C",IF(E49<=0.8,"A",IF(E49<=0.95,"B","C"))) -> C | G49: =VLOOKUP(B$30:B$50,I$30:M$50,5,0) -> C | I49: tunika16 сетка черная | J49: ='Юнит 01-04.01'!R47 -> 0 | K49: =J49/J$50 -> 0 | L49: =K49+L48 -> 1 | M49: =_xlfn.IFS(L49<80%,"A",L49<=95%,"B",L49>95%,"C") -> C
C50: =SUM(C30:C49) -> -923.67467 | D50: =SUM(D30:D49) -> 1 | J50: =SUM(J30:J49) -> 1 | K50: =SUM(K30:K49) -> 1

Sheet Юнит 01.02
B1: 01-31.01 | AG1: на 1 единицу проданного товара
B2: Артикул поставщика | C2: Остаток на Отчет 23 | D2: В пути до клиента | E2: В пути от клиента | F2: Итого по складам ВБ | G2: Остаток на нашем складе на 02.09 | H2: Себетоимость на 1 ед на 29.09.25 | I2: Себестоимость остатков | J2: Оборачиваемость, дн | K2: Заказы, шт 7 дней | L2: Средняя цена, руб (столбец 32, AG) | M2: % выкупа за 7 дней (столбец 23, X) | N2: Скорость заказов | O2: Скорость продаж | P2: Кол-во ПРОДАЖИ | Q2: Кол-во ВОЗВРАТЫ | R2: Кол-во ПРОДАЖИ-ВОЗВРАТЫ | S2: Выручка ПРОДАЖИ | T2: Выручка ВОЗВРАТЫ | U2: Выручка с учетом согласованной скидки ПРОДАЖИ - ВОЗВРАТЫ | V2: Доля выручки, % от общего объема | W2: Себестоимость продаж | X2: Комиссия, руб | Y2: Комиссия, % | Z2: Логистика | AA2: Реклама | AB2: Хранение | AC2: Штрафы | AD2: Налог 1% | AE2: Прибыль | AG2: Выручка на 1 ед (средняя цена продажи со скидкой) | AH2: Себестоимость на 1 ед | AI2: Комиссия на 1 ед | AJ2: Логистика на 1 ед | AK2: Реклама на 1 ед | AL2: Прибыль на 1 ед | AM2: Маржинальность, % | AN2: Рентабельность, % | AP2: Прибыль с остатков
A3: 2638219896 | B3: черные с железкой классика | H3: 142.98 | I3: =C3*H3 -> 0 | N3: =K3/7 -> 0 | O3: =R3/7 -> 4.5714286 | P3: =SUMIFS('Отчет 05-11.01'!H:H,'Отчет 05-11.01'!D:D,"Выручка",'Отчет 05-11.01'!E:E,B3) -> 35 | Q3: =SUMIFS('Отчет 05-11.01'!H:H,'Отчет 05-11.01'!D:D,"Возврат выручки",'Отчет 05-11.01'!E:E,B3) -> 3 | R3: =P3-Q3 -> 32 | S3: =SUMIFS('Отчет 05-11.01'!P:P,'Отчет 05-11.01'!C:C,"Продажи",'Отчет 05-11.01'!E:E,B3) -> 59640 | T3: =SUMIFS('Отчет 05-11.01'!P:P,'Отчет 05-11.01'!C:C,"Возвраты",'Отчет 05-11.01'!E:E,B3) -> -5112 | U3: =S3+T3 -> 54528 | V3: =U3/$U$49 -> 5.1812999 | W3: =R3*H3 -> 4575.36 | X3: =-SUMIFS('Отчет 05-11.01'!P:P,'Отчет 05-11.01'!C:C,"Вознаграждение Ozon",'Отчет 05-11.01'!E:E,B3) -> 23447.04 | Y3: =IF(U3=0,0,X3/U3) -> 0.43 | Z3: =-SUMIFS('Отчет 05-11.01'!P:P,'Отчет 05-11.01'!C:C,"Услуги доставки",'Отчет 05-11.01'!E:E,B3) -> 6296.89 | AD3: =U3*1% -> 545.28 | AE3: =U3-W3-X3-Z3-AA3-AB3-AC3-AD3 -> 19663.43 | AG3: =IF(R3=0,0,U3/R3) -> 1704 | AH3: =H3 -> 142.98 | AI3: =IF(R3=0,0,X3/R3) -> 732.72 | AJ3: =IF(P3=0,Z3/1,Z3/P3) -> 179.91114 | AK3: =IF(P3=0,0,AA3/P3) -> 0 | AL3: =_xlfn.IFS(R3=0,AE3,R3<0,AE3/-R3,R3>0,AE3/R3) -> 614.48219 | AM3: =IF(AG3=0,0,AL3/AG3) -> 0.36061161 | AN3: =IF(AH3=0,0,AL3/AH3) -> 4.2976793 | AP3: =AL3*C3 -> 0
A4: 2638638550 | B4: qs черные | H4: 123.09 | I4: =C4*H4 -> 0 | N4: =K4/7 -> 0 | O4: =R4/7 -> 0 | P4: =SUMIFS('Отчет 05-11.01'!H:H,'Отчет 05-11.01'!D:D,"Выручка",'Отчет 05-11.01'!E:E,B4) -> 0 | Q4: =SUMIFS('Отчет 05-11.01'!H:H,'Отчет 05-11.01'!D:D,"Возврат выручки",'Отчет 05-11.01'!E:E,B4) -> 0 | R4: =P4-Q4 -> 0 | S4: =SUMIFS('Отчет 05-11.01'!P:P,'Отчет 05-11.01'!C:C,"Продажи",'Отчет 05-11.01'!E:E,B4) -> 0 | T4: =SUMIFS('Отчет 05-11.01'!P:P,'Отчет 05-11.01'!C:C,"Возвраты",'Отчет 05-11.01'!E:E,B4) -> 0 | U4: =S4+T4 -> 0 | V4: =U4/$U$49 -> 0 | W4: =R4*H4 -> 0 | X4: =-SUMIFS('Отчет 05-11.01'!P:P,'Отчет 05-11.01'!C:C,"Вознаграждение Ozon",'Отчет 05-11.01'!E:E,B4) -> 0 | Y4: =IF(U4=0,0,X4/U4) -> 0 | Z4: =-SUMIFS('Отчет 05-11.01'!P:P,'Отчет 05-11.01'!C:C,"Услуги доставки",'Отчет 05-11.01'!E:E,B4) -> 0 | AD4: =U4*1% -> 0 | AE4: =U4-W4-X4-Z4-AA4-AB4-AC4-AD4 -> 0 | AG4: =IF(R4=0,0,U4/R4) -> 0 | AH4: =H4 -> 123.09 | AI4: =IF(R4=0,0,X4/R4) -> 0 | AJ4: =IF(P4=0,Z4/1,Z4/P4) -> 0 | AK4: =IF(P4=0,0,AA4/P4) -> 0 | AL4: {=_xlfn.IFS(R4=0,AE4,R4<0,AE4/-R4,R4>0,AE4/R4)} -> 0 | AM4: =IF(AG4=0,0,AL4/AG4) -> 0 | AN4: =IF(AH4=0,0,AL4/AH4) -> 0 | AP4: =AL4*C4 -> 0
A5: 2638691131 | B5: qs синие | H5: 123.09 | I5: =C5*H5 -> 0 | N5: =K5/7 -> 0 | O5: =R5/7 -> 0.14285714 | P5: =SUMIFS('Отчет 05-11.01'!H:H,'Отчет 05-11.01'!D:D,"Выручка",'Отчет 05-11.01'!E:E,B5) -> 1 | Q5: =SUMIFS('Отчет 05-11.01'!H:H,'Отчет 05-11.01'!D:D,"Возврат выручки",'Отчет 05-11.01'!E:E,B5) -> 0 | R5: =P5-Q5 -> 1 | S5: =SUMIFS('Отчет 05-11.01'!P:P,'Отчет 05-11.01'!C:C,"Продажи",'Отчет 05-11.01'!E:E,B5) -> 1206 | T5: =SUMIFS('Отчет 05-11.01'!P:P,'Отчет 05-11.01'!C:C,"Возвраты",'Отчет 05-11.01'!E:E,B5) -> 0 | U5: =S5+T5 -> 1206 | V5: =U5/$U$49 -> 0.11459521 | W5: =R5*H5 -> 123.09 | X5: =-SUMIFS('Отчет 05-11.01'!P:P,'Отчет 05-11.01'!C:C,"Вознаграждение Ozon",'Отчет 05-11.01'!E:E,B5) -> 518.58 | Y5: =IF(U5=0,0,X5/U5) -> 0.43 | Z5: =-SUMIFS('Отчет 05-11.01'!P:P,'Отчет 05-11.01'!C:C,"Услуги доставки",'Отчет 05-11.01'!E:E,B5) -> 191.7 | AD5: =U5*1% -> 12.06 | AE5: =U5-W5-X5-Z5-AA5-AB5-AC5-AD5 -> 360.57 | AG5: =IF(R5=0,0,U5/R5) -> 1206 | AH5: =H5 -> 123.09 | AI5: =IF(R5=0,0,X5/R5) -> 518.58 | AJ5: =IF(P5=0,Z5/1,Z5/P5) -> 191.7 | AK5: =IF(P5=0,0,AA5/P5) -> 0 | AL5: {=_xlfn.IFS(R5=0,AE5,R5<0,AE5/-R5,R5>0,AE5/R5)} -> 360.57 | AM5: =IF(AG5=0,0,AL5/AG5) -> 0.2989801 | AN5: =IF(AH5=0,0,AL5/AH5) -> 2.92932 | AP5: =AL5*C5 -> 0
A6: 2638382749 | B6: qs желтые | H6: 123.09 | I6: =C6*H6 -> 0 | N6: =K6/7 -> 0 | O6: =R6/7 -> 1.5714286 | P6: =SUMIFS('Отчет 05-11.01'!H:H,'Отчет 05-11.01'!D:D,"Выручка",'Отчет 05-11.01'!E:E,B6) -> 12 | Q6: =SUMIFS('Отчет 05-11.01'!H:H,'Отчет 05-11.01'!D:D,"Возврат выручки",'Отчет 05-11.01'!E:E,B6) -> 1 | R6: =P6-Q6 -> 11 | S6: =SUMIFS('Отчет 05-11.01'!P:P,'Отчет 05-11.01'!C:C,"Продажи",'Отчет 05-11.01'!E:E,B6) -> 17563 | T6: =SUMIFS('Отчет 05-11.01'!P:P,'Отчет 05-11.01'!C:C,"Возвраты",'Отчет 05-11.01'!E:E,B6) -> -1687 | U6: =S6+T6 -> 15876 | V6: =U6/$U$49 -> 1.5085519 | W6: =R6*H6 -> 1353.99 | X6: =-SUMIFS('Отчет 05-11.01'!P:P,'Отчет 05-11.01'!C:C,"Вознаграждение Ozon",'Отчет 05-11.01'!E:E,B6) -> 6826.68 | Y6: =IF(U6=0,0,X6/U6) -> 0.43 | Z6: =-SUMIFS('Отчет 05-11.01'!P:P,'Отчет 05-11.01'!C:C,"Услуги доставки",'Отчет 05-11.01'!E:E,B6) -> 1830.49 | AD6: =U6*1% -> 158.76 | AE6: =U6-W6-X6-Z6-AA6-AB6-AC6-AD6 -> 5706.08 | AG6: =IF(R6=0,0,U6/R6) -> 1443.2727 | AH6: =H6 -> 123.09 | AI6: =IF(R6=0,0,X6/R6) -> 620.60727 | AJ6: =IF(P6=0,Z6/1,Z6/P6) -> 152.54083 | AK6: =IF(P6=0,0,AA6/P6) -> 0 | AL6: {=_xlfn.IFS(R6=0,AE6,R6<0,AE6/-R6,R6>0,AE6/R6)} -> 518.73455 | AM6: =IF(AG6=0,0,AL6/AG6) -> 0.35941547 | AN6: =IF(AH6=0,0,AL6/AH6) -> 4.2142704 | AP6: =AL6*C6 -> 0
A7: 2638569317 | B7: qs коричневые | H7: 117.24 | I7: =C7*H7 -> 0 | N7: =K7/7 -> 0 | O7: =R7/7 -> 0.14285714 | P7: =SUMIFS('Отчет 05-11.01'!H:H,'Отчет 05-11.01'!D:D,"Выручка",'Отчет 05-11.01'!E:E,B7) -> 1 | Q7: =SUMIFS('Отчет 05-11.01'!H:H,'Отчет 05-11.01'!D:D,"Возврат выручки",'Отчет 05-11.01'!E:E,B7) -> 0 | R7: =P7-Q7 -> 1 | S7: =SUMIFS('Отчет 05-11.01'!P:P,'Отчет 05-11.01'!C:C,"Продажи",'Отчет 05-11.01'!E:E,B7) -> 1687 | T7: =SUMIFS('Отчет 05-11.01'!P:P,'Отчет 05-11.01'!C:C,"Возвраты",'Отчет 05-11.01'!E:E,B7) -> 0 | U7: =S7+T7 -> 1687 | V7: =U7/$U$49 -> 0.16030027 | W7: =R7*H7 -> 117.24 | X7: =-SUMIFS('Отчет 05-11.01'!P:P,'Отчет 05-11.01'!C:C,"Вознаграждение Ozon",'Отчет 05-11.01'!E:E,B7) -> 725.41 | Y7: =IF(U7=0,0,X7/U7) -> 0.43 | Z7: =-SUMIFS('Отчет 05-11.01'!P:P,'Отчет 05-11.01'!C:C,"Услуги доставки",'Отчет 05-11.01'!E:E,B7) -> 230.78 | AD7: =U7*1% -> 16.87 | AE7: =U7-W7-X7-Z7-AA7-AB7-AC7-AD7 -> 596.7 | AG7: =IF(R7=0,0,U7/R7) -> 1687 | AH7: =H7 -> 117.24 | AI7: =IF(R7=0,0,X7/R7) -> 725.41 | AJ7: =IF(P7=0,Z7/1,Z7/P7) -> 230.78 | AK7: =IF(P7=0,0,AA7/P7) -> 0 | AL7: {=_xlfn.IFS(R7=0,AE7,R7<0,AE7/-R7,R7>0,AE7/R7)} -> 596.7 | AM7: =IF(AG7=0,0,AL7/AG7) -> 0.3537048 | AN7: =IF(AH7=0,0,AL7/AH7) -> 5.0895599 | AP7: =AL7*C7 -> 0
A8: 3064334128 | B8: th желтый Сул | H8: 123 | I8: =C8*H8 -> 0 | N8: =K8/7 -> 0 | O8: =R8/7 -> 0 | P8: =SUMIFS('Отчет 05-11.01'!H:H,'Отчет 05-11.01'!D:D,"Выручка",'Отчет 05-11.01'!E:E,B8) -> 0 | Q8: =SUMIFS('Отчет 05-11.01'!H:H,'Отчет 05-11.01'!D:D,"Возврат выручки",'Отчет 05-11.01'!E:E,B8) -> 0 | R8: =P8-Q8 -> 0 | S8: =SUMIFS('Отчет 05-11.01'!P:P,'Отчет 05-11.01'!C:C,"Продажи",'Отчет 05-11.01'!E:E,B8) -> 0 | T8: =SUMIFS('Отчет 05-11.01'!P:P,'Отчет 05-11.01'!C:C,"Возвраты",'Отчет 05-11.01'!E:E,B8) -> 0 | U8: =S8+T8 -> 0 | V8: =U8/$U$49 -> 0 | W8: =R8*H8 -> 0 | X8: =-SUMIFS('Отчет 05-11.01'!P:P,'Отчет 05-11.01'!C:C,"Вознаграждение Ozon",'Отчет 05-11.01'!E:E,B8) -> 0 | Y8: =IF(U8=0,0,X8/U8) -> 0 | Z8: =-SUMIFS('Отчет 05-11.01'!P:P,'Отчет 05-11.01'!C:C,"Услуги доставки",'Отчет 05-11.01'!E:E,B8) -> 0 | AD8: =U8*1% -> 0 | AE8: =U8-W8-X8-Z8-AA8-AB8-AC8-AD8 -> 0 | AG8: =IF(R8=0,0,U8/R8) -> 0 | AH8: =H8 -> 123 | AI8: =IF(R8=0,0,X8/R8) -> 0 | AJ8: =IF(P8=0,Z8/1,Z8/P8) -> 0 | AK8: =IF(P8=0,0,AA8/P8) -> 0 | AL8: {=_xlfn.IFS(R8=0,AE8,R8<0,AE8/-R8,R8>0,AE8/R8)} -> 0 | AM8: =IF(AG8=0,0,AL8/AG8) -> 0 | AN8: =IF(AH8=0,0,AL8/AH8) -> 0 | AP8: =AL8*C8 -> 0
A9: 3064334311 | B9: flip желтые Сул | H9: 123 | I9: =C9*H9 -> 0 | N9: =K9/7 -> 0 | O9: =R9/7 -> 0.14285714 | P9: =SUMIFS('Отчет 05-11.01'!H:H,'Отчет 05-11.01'!D:D,"Выручка",'Отчет 05-11.01'!E:E,B9) -> 1 | Q9: =SUMIFS('Отчет 05-11.01'!H:H,'Отчет 05-11.01'!D:D,"Возврат выручки",'Отчет 05-11.01'!E:E,B9) -> 0 | R9: =P9-Q9 -> 1 | S9: =SUMIFS('Отчет 05-11.01'!P:P,'Отчет 05-11.01'!C:C,"Продажи",'Отчет 05-11.01'!E:E,B9) -> 1815 | T9: =SUMIFS('Отчет 05-11.01'!P:P,'Отчет 05-11.01'!C:C,"Возвраты",'Отчет 05-11.01'!E:E,B9) -> 0 | U9: =S9+T9 -> 1815 | V9: =U9/$U$49 -> 0.17246294 | W9: =R9*H9 -> 123 | X9: =-SUMIFS('Отчет 05-11.01'!P:P,'Отчет 05-11.01'!C:C,"Вознаграждение Ozon",'Отчет 05-11.01'!E:E,B9) -> 780.45 | Y9: =IF(U9=0,0,X9/U9) -> 0.43 | Z9: =-SUMIFS('Отчет 05-11.01'!P:P,'Отчет 05-11.01'!C:C,"Услуги доставки",'Отчет 05-11.01'!E:E,B9) -> 295.64 | AD9: =U9*1% -> 18.15 | AE9: =U9-W9-X9-Z9-AA9-AB9-AC9-AD9 -> 597.76 | AG9: =IF(R9=0,0,U9/R9) -> 1815 | AH9: =H9 -> 123 | AI9: =IF(R9=0,0,X9/R9) -> 780.45 | AJ9: =IF(P9=0,Z9/1,Z9/P9) -> 295.64 | AK9: =IF(P9=0,0,AA9/P9) -> 0 | AL9: {=_xlfn.IFS(R9=0,AE9,R9<0,AE9/-R9,R9>0,AE9/R9)} -> 597.76 | AM9: =IF(AG9=0,0,AL9/AG9) -> 0.32934435 | AN9: =IF(AH9=0,0,AL9/AH9) -> 4.8598374 | AP9: =AL9*C9 -> 0
A10: 2638291563 | B10: MR8854 C2 | H10: 169.89 | I10: =C10*H10 -> 0 | N10: =K10/7 -> 0 | O10: =R10/7 -> 0 | P10: =SUMIFS('Отчет 05-11.01'!H:H,'Отчет 05-11.01'!D:D,"Выручка",'Отчет 05-11.01'!E:E,B10) -> 0 | Q10: =SUMIFS('Отчет 05-11.01'!H:H,'Отчет 05-11.01'!D:D,"Возврат выручки",'Отчет 05-11.01'!E:E,B10) -> 0 | R10: =P10-Q10 -> 0 | S10: =SUMIFS('Отчет 05-11.01'!P:P,'Отчет 05-11.01'!C:C,"Продажи",'Отчет 05-11.01'!E:E,B10) -> 0 | T10: =SUMIFS('Отчет 05-11.01'!P:P,'Отчет 05-11.01'!C:C,"Возвраты",'Отчет 05-11.01'!E:E,B10) -> 0 | U10: =S10+T10 -> 0 | V10: =U10/$U$49 -> 0 | W10: =R10*H10 -> 0 | X10: =-SUMIFS('Отчет 05-11.01'!P:P,'Отчет 05-11.01'!C:C,"Вознаграждение Ozon",'Отчет 05-11.01'!E:E,B10) -> 0 | Y10: =IF(U10=0,0,X10/U10) -> 0 | Z10: =-SUMIFS('Отчет 05-11.01'!P:P,'Отчет 05-11.01'!C:C,"Услуги доставки",'Отчет 05-11.01'!E:E,B10) -> 93.54 | AD10: =U10*1% -> 0 | AE10: =U10-W10-X10-Z10-AA10-AB10-AC10-AD10 -> -93.54 | AG10: =IF(R10=0,0,U10/R10) -> 0 | AH10: =H10 -> 169.89 | AI10: =IF(R10=0,0,X10/R10) -> 0 | AJ10: =IF(P10=0,Z10/1,Z10/P10) -> 93.54 | AK10: =IF(P10=0,0,AA10/P10) -> 0 | AL10: {=_xlfn.IFS(R10=0,AE10,R10<0,AE10/-R10,R10>0,AE10/R10)} -> -93.54 | AM10: =IF(AG10=0,0,AL10/AG10) -> 0 | AN10: =IF(AH10=0,0,AL10/AH10) -> -0.55059156 | AP10: =AL10*C10 -> 0
A11: 2730130733 | B11: MR 1819 черн | H11: 169.89 | I11: =C11*H11 -> 0 | N11: =K11/7 -> 0 | O11: =R11/7 -> 0 | P11: =SUMIFS('Отчет 05-11.01'!H:H,'Отчет 05-11.01'!D:D,"Выручка",'Отчет 05-11.01'!E:E,B11) -> 0 | Q11: =SUMIFS('Отчет 05-11.01'!H:H,'Отчет 05-11.01'!D:D,"Возврат выручки",'Отчет 05-11.01'!E:E,B11) -> 0 | R11: =P11-Q11 -> 0 | S11: =SUMIFS('Отчет 05-11.01'!P:P,'Отчет 05-11.01'!C:C,"Продажи",'Отчет 05-11.01'!E:E,B11) -> 0 | T11: =SUMIFS('Отчет 05-11.01'!P:P,'Отчет 05-11.01'!C:C,"Возвраты",'Отчет 05-11.01'!E:E,B11) -> 0 | U11: =S11+T11 -> 0 | V11: =U11/$U$49 -> 0 | W11: =R11*H11 -> 0 | X11: =-SUMIFS('Отчет 05-11.01'!P:P,'Отчет 05-11.01'!C:C,"Вознаграждение Ozon",'Отчет 05-11.01'!E:E,B11) -> 0 | Y11: =IF(U11=0,0,X11/U11) -> 0 | Z11: =-SUMIFS('Отчет 05-11.01'!P:P,'Отчет 05-11.01'!C:C,"Услуги доставки",'Отчет 05-11.01'!E:E,B11) -> 0 | AD11: =U11*1% -> 0 | AE11: =U11-W11-X11-Z11-AA11-AB11-AC11-AD11 -> 0 | AG11: =IF(R11=0,0,U11/R11) -> 0 | AH11: =H11 -> 169.89 | AI11: =IF(R11=0,0,X11/R11) -> 0 | AJ11: =IF(P11=0,Z11/1,Z11/P11) -> 0 | AK11: =IF(P11=0,0,AA11/P11) -> 0 | AL11: {=_xlfn.IFS(R11=0,AE11,R11<0,AE11/-R11,R11>0,AE11/R11)} -> 0 | AM11: =IF(AG11=0,0,AL11/AG11) -> 0 | AN11: =IF(AH11=0,0,AL11/AH11) -> 0 | AP11: =AL11*C11 -> 0
A12: 2730131249 | B12: MR 1819 корич | H12: 169.89 | I12: =C12*H12 -> 0 | N12: =K12/7 -> 0 | O12: =R12/7 -> 0.28571429 | P12: =SUMIFS('Отчет 05-11.01'!H:H,'Отчет 05-11.01'!D:D,"Выручка",'Отчет 05-11.01'!E:E,B12) -> 2 | Q12: =SUMIFS('Отчет 05-11.01'!H:H,'Отчет 05-11.01'!D:D,"Возврат выручки",'Отчет 05-11.01'!E:E,B12) -> 0 | R12: =P12-Q12 -> 2 | S12: =SUMIFS('Отчет 05-11.01'!P:P,'Отчет 05-11.01'!C:C,"Продажи",'Отчет 05-11.01'!E:E,B12) -> 2180 | T12: =SUMIFS('Отчет 05-11.01'!P:P,'Отчет 05-11.01'!C:C,"Возвраты",'Отчет 05-11.01'!E:E,B12) -> 0 | U12: =S12+T12 -> 2180 | V12: =U12/$U$49 -> 0.20714557 | W12: =R12*H12 -> 339.78 | X12: =-SUMIFS('Отчет 05-11.01'!P:P,'Отчет 05-11.01'!C:C,"Вознаграждение Ozon",'Отчет 05-11.01'!E:E,B12) -> 937.4 | Y12: =IF(U12=0,0,X12/U12) -> 0.43 | Z12: =-SUMIFS('Отчет 05-11.01'!P:P,'Отчет 05-11.01'!C:C,"Услуги доставки",'Отчет 05-11.01'!E:E,B12) -> 182.66 | AD12: =U12*1% -> 21.8 | AE12: =U12-W12-X12-Z12-AA12-AB12-AC12-AD12 -> 698.36 | AG12: =IF(R12=0,0,U12/R12) -> 1090 | AH12: =H12 -> 169.89 | AI12: =IF(R12=0,0,X12/R12) -> 468.7 | AJ12: =IF(P12=0,Z12/1,Z12/P12) -> 91.33 | AK12: =IF(P12=0,0,AA12/P12) -> 0 | AL12: {=_xlfn.IFS(R12=0,AE12,R12<0,AE12/-R12,R12>0,AE12/R12)} -> 349.18 | AM12: =IF(AG12=0,0,AL12/AG12) -> 0.32034862 | AN12: =IF(AH12=0,0,AL12/AH12) -> 2.0553299 | AP12: =AL12*C12 -> 0
A13: 2730130553 | B13: MR Р1874 черн | H13: 169.89 | I13: =C13*H13 -> 0 | N13: =K13/7 -> 0 | O13: =R13/7 -> 0.14285714 | P13: =SUMIFS('Отчет 05-11.01'!H:H,'Отчет 05-11.01'!D:D,"Выручка",'Отчет 05-11.01'!E:E,B13) -> 1 | Q13: =SUMIFS('Отчет 05-11.01'!H:H,'Отчет 05-11.01'!D:D,"Возврат выручки",'Отчет 05-11.01'!E:E,B13) -> 0 | R13: =P13-Q13 -> 1 | S13: =SUMIFS('Отчет 05-11.01'!P:P,'Отчет 05-11.01'!C:C,"Продажи",'Отчет 05-11.01'!E:E,B13) -> 1387 | T13: =SUMIFS('Отчет 05-11.01'!P:P,'Отчет 05-11.01'!C:C,"Возвраты",'Отчет 05-11.01'!E:E,B13) -> 0 | U13: =S13+T13 -> 1387 | V13: =U13/$U$49 -> 0.13179399 | W13: =R13*H13 -> 169.89 | X13: =-SUMIFS('Отчет 05-11.01'!P:P,'Отчет 05-11.01'!C:C,"Вознаграждение Ozon",'Отчет 05-11.01'!E:E,B13) -> 596.41 | Y13: =IF(U13=0,0,X13/U13) -> 0.43 | Z13: =-SUMIFS('Отчет 05-11.01'!P:P,'Отчет 05-11.01'!C:C,"Услуги доставки",'Отчет 05-11.01'!E:E,B13) -> 109.48 | AD13: =U13*1% -> 13.87 | AE13: =U13-W13-X13-Z13-AA13-AB13-AC13-AD13 -> 497.35 | AG13: =IF(R13=0,0,U13/R13) -> 1387 | AH13: =H13 -> 169.89 | AI13: =IF(R13=0,0,X13/R13) -> 596.41 | AJ13: =IF(P13=0,Z13/1,Z13/P13) -> 109.48 | AK13: =IF(P13=0,0,AA13/P13) -> 0 | AL13: {=_xlfn.IFS(R13=0,AE13,R13<0,AE13/-R13,R13>0,AE13/R13)} -> 497.35 | AM13: =IF(AG13=0,0,AL13/AG13) -> 0.35857967 | AN13: =IF(AH13=0,0,AL13/AH13) -> 2.9274825 | AP13: =AL13*C13 -> 0
A14: 2730129638 | B14: MR Р1874 корич | H14: 169.89 | I14: =C14*H14 -> 0 | N14: =K14/7 -> 0 | O14: =R14/7 -> 0.14285714 | P14: =SUMIFS('Отчет 05-11.01'!H:H,'Отчет 05-11.01'!D:D,"Выручка",'Отчет 05-11.01'!E:E,B14) -> 1 | Q14: =SUMIFS('Отчет 05-11.01'!H:H,'Отчет 05-11.01'!D:D,"Возврат выручки",'Отчет 05-11.01'!E:E,B14) -> 0 | R14: =P14-Q14 -> 1 | S14: =SUMIFS('Отчет 05-11.01'!P:P,'Отчет 05-11.01'!C:C,"Продажи",'Отчет 05-11.01'!E:E,B14) -> 1429 | T14: =SUMIFS('Отчет 05-11.01'!P:P,'Отчет 05-11.01'!C:C,"Возвраты",'Отчет 05-11.01'!E:E,B14) -> 0 | U14: =S14+T14 -> 1429 | V14: =U14/$U$49 -> 0.13578487 | W14: =R14*H14 -> 169.89 | X14: =-SUMIFS('Отчет 05-11.01'!P:P,'Отчет 05-11.01'!C:C,"Вознаграждение Ozon",'Отчет 05-11.01'!E:E,B14) -> 614.47 | Y14: =IF(U14=0,0,X14/U14) -> 0.43 | Z14: =-SUMIFS('Отчет 05-11.01'!P:P,'Отчет 05-11.01'!C:C,"Услуги доставки",'Отчет 05-11.01'!E:E,B14) -> 98.79 | AD14: =U14*1% -> 14.29 | AE14: =U14-W14-X14-Z14-AA14-AB14-AC14-AD14 -> 531.56 | AG14: =IF(R14=0,0,U14/R14) -> 1429 | AH14: =H14 -> 169.89 | AI14: =IF(R14=0,0,X14/R14) -> 614.47 | AJ14: =IF(P14=0,Z14/1,Z14/P14) -> 98.79 | AK14: =IF(P14=0,0,AA14/P14) -> 0 | AL14: {=_xlfn.IFS(R14=0,AE14,R14<0,AE14/-R14,R14>0,AE14/R14)} -> 531.56 | AM14: =IF(AG14=0,0,AL14/AG14) -> 0.37198041 | AN14: =IF(AH14=0,0,AL14/AH14) -> 3.1288481 | AP14: =AL14*C14 -> 0
A15: 2730130141 | B15: MR Р1886 черн глянец | H15: 169.89 | I15: =C15*H15 -> 0 | N15: =K15/7 -> 0 | O15: =R15/7 -> 0.28571429 | P15: =SUMIFS('Отчет 05-11.01'!H:H,'Отчет 05-11.01'!D:D,"Выручка",'Отчет 05-11.01'!E:E,B15) -> 2 | Q15: =SUMIFS('Отчет 05-11.01'!H:H,'Отчет 05-11.01'!D:D,"Возврат выручки",'Отчет 05-11.01'!E:E,B15) -> 0 | R15: =P15-Q15 -> 2 | S15: =SUMIFS('Отчет 05-11.01'!P:P,'Отчет 05-11.01'!C:C,"Продажи",'Отчет 05-11.01'!E:E,B15) -> 2670 | T15: =SUMIFS('Отчет 05-11.01'!P:P,'Отчет 05-11.01'!C:C,"Возвраты",'Отчет 05-11.01'!E:E,B15) -> 0 | U15: =S15+T15 -> 2670 | V15: =U15/$U$49 -> 0.25370582 | W15: =R15*H15 -> 339.78 | X15: =-SUMIFS('Отчет 05-11.01'!P:P,'Отчет 05-11.01'!C:C,"Вознаграждение Ozon",'Отчет 05-11.01'!E:E,B15) -> 1148.1 | Y15: =IF(U15=0,0,X15/U15) -> 0.43 | Z15: =-SUMIFS('Отчет 05-11.01'!P:P,'Отчет 05-11.01'!C:C,"Услуги доставки",'Отчет 05-11.01'!E:E,B15) -> 396.42 | AD15: =U15*1% -> 26.7 | AE15: =U15-W15-X15-Z15-AA15-AB15-AC15-AD15 -> 759 | AG15: =IF(R15=0,0,U15/R15) -> 1335 | AH15: =H15 -> 169.89 | AI15: =IF(R15=0,0,X15/R15) -> 574.05 | AJ15: =IF(P15=0,Z15/1,Z15/P15) -> 198.21 | AK15: =IF(P15=0,0,AA15/P15) -> 0 | AL15: {=_xlfn.IFS(R15=0,AE15,R15<0,AE15/-R15,R15>0,AE15/R15)} -> 379.5 | AM15: =IF(AG15=0,0,AL15/AG15) -> 0.28426966 | AN15: =IF(AH15=0,0,AL15/AH15) -> 2.2337983 | AP15: =AL15*C15 -> 0
... A24: 2807226146 | B24: lux8 | H24: 991.12 | I24: =C24*H24 -> 0 | N24: =K24/7 -> 0 | O24: =R24/7 -> 0 | P24: =SUMIFS('Отчет 05-11.01'!H:H,'Отчет 05-11.01'!D:D,"Выручка",'Отчет 05-11.01'!E:E,B24) -> 0 | Q24: =SUMIFS('Отчет 05-11.01'!H:H,'Отчет 05-11.01'!D:D,"Возврат выручки",'Отчет 05-11.01'!E:E,B24) -> 0 | R24: =P24-Q24 -> 0 | S24: =SUMIFS('Отчет 05-11.01'!P:P,'Отчет 05-11.01'!C:C,"Продажи",'Отчет 05-11.01'!E:E,B24) -> 0 | T24: =SUMIFS('Отчет 05-11.01'!P:P,'Отчет 05-11.01'!C:C,"Возвраты",'Отчет 05-11.01'!E:E,B24) -> 0 | U24: =S24+T24 -> 0 | V24: =U24/$U$49 -> 0 | W24: =R24*H24 -> 0 | X24: =-SUMIFS('Отчет 05-11.01'!P:P,'Отчет 05-11.01'!C:C,"Вознаграждение Ozon",'Отчет 05-11.01'!E:E,B24) -> 0 | Y24: =IF(U24=0,0,X24/U24) -> 0 | Z24: =-SUMIFS('Отчет 05-11.01'!P:P,'Отчет 05-11.01'!C:C,"Услуги доставки",'Отчет 05-11.01'!E:E,B24) -> 0 | AD24: =U24*1% -> 0 | AE24: =U24-W24-X24-Z24-AA24-AB24-AC24-AD24 -> 0 | AG24: =IF(R24=0,0,U24/R24) -> 0 | AH24: =H24 -> 991.12 | AI24: =IF(R24=0,0,X24/R24) -> 0 | AJ24: =IF(P24=0,Z24/1,Z24/P24) -> 0 | AK24: =IF(P24=0,0,AA24/P24) -> 0 | AL24: {=_xlfn.IFS(R24=0,AE24,R24<0,AE24/-R24,R24>0,AE24/R24)} -> 0 | AM24: =IF(AG24=0,0,AL24/AG24) -> 0 | AN24: =IF(AH24=0,0,AL24/AH24) -> 0 | AP24: =AL24*C24 -> 0
AG25: =AVERAGEIF(AG3:AG24,"<>0",AG3:AG24) -> 1438.7773 | AH25: =AVERAGEIF(AH3:AH24,"<>0",AH3:AH24) -> 447.87636 | AI25: =AVERAGEIF(AI3:AI24,"<>0",AI3:AI24) -> 618.67423 | AJ25: =AVERAGEIF(AJ3:AJ24,"<>0",AJ3:AJ24) -> 159.442 | AK25: =AVERAGEIF(AK3:AK24,"<>0",AK3:AK24) -> #DIV/0! | AL25: =AVERAGEIF(AL3:AL24,"<>0",AL3:AL24) -> 435.79152 | AM25: =AVERAGEIF(AM3:AM24,"<>0",AM3:AM24) -> 0.33790156 | AN25: =AVERAGEIF(AN3:AN24,"<>0",AN3:AN24) -> 3.0712495
A26: Итого очки | C26: =SUM(C3:C24) -> 0 | E26: 108496 | F26: 597 | G26: 295 | I26: =SUM(I3:I24) -> 0 | K26: =SUM(K3:K24) -> 0 | P26: =SUM(P3:P24) -> 58 | Q26: =SUM(Q3:Q24) -> 4 | R26: =SUM(R3:R24) -> 54 | S26: =SUM(S3:S24) -> 92160 | T26: =SUM(T3:T24) -> -6799 | U26: =SUM(U3:U24) -> 85361 | V26: =SUM(V3:V24) -> 8.1110794 | W26: =SUM(W3:W24) -> 7651.8 | X26: =SUM(X3:X24) -> 36705.23 | Y26: =IF(U26=0,0,X26/U26) -> 0.43 | Z26: =SUM(Z3:Z24) -> 9950.27 | AA26: =IFERROR(P26*AA51/P51,0) -> 24016.688 | AB26: =SUM(AB3:AB24) -> 0 | AC26: =SUM(AC3:AC24) -> 0 | AD26: =SUM(AD3:AD24) -> 853.61 | AE26: =SUM(AE3:AE24) -> 30200.09 | AP26: =SUM(AP3:AP24) -> 0 | AZ26: 18592777
AA27: =SUM(AA3:AA24) -> 0
A28: 2774708536 | B28: tunika02 оливковая с руч вышивкой | H28: 672 | I28: =C28*H28 -> 0 | N28: =K28/7 -> 0 | O28: =R28/7 -> 0 | P28: =SUMIFS('Отчет 05-11.01'!H:H,'Отчет 05-11.01'!D:D,"Выручка",'Отчет 05-11.01'!E:E,B28) -> 0 | Q28: =SUMIFS('Отчет 05-11.01'!H:H,'Отчет 05-11.01'!D:D,"Возврат выручки",'Отчет 05-11.01'!E:E,B28) -> 0 | R28: =P28-Q28 -> 0 | S28: =SUMIFS('Отчет 05-11.01'!P:P,'Отчет 05-11.01'!C:C,"Продажи",'Отчет 05-11.01'!E:E,B28) -> 0 | T28: =SUMIFS('Отчет 05-11.01'!P:P,'Отчет 05-11.01'!C:C,"Возвраты",'Отчет 05-11.01'!E:E,B28) -> 0 | U28: =S28+T28 -> 0 | V28: =U28/$U$49 -> 0 | W28: =R28*H28 -> 0 | X28: =-SUMIFS('Отчет 05-11.01'!P:P,'Отчет 05-11.01'!C:C,"Вознаграждение Ozon",'Отчет 05-11.01'!E:E,B28) -> 0 | Y28: =IF(U28=0,0,X28/U28) -> 0 | Z28: =-SUMIFS('Отчет 05-11.01'!P:P,'Отчет 05-11.01'!C:C,"Услуги доставки",'Отчет 05-11.01'!E:E,B28) -> 0 | AD28: =U28*1% -> 0 | AE28: =U28-W28-X28-Z28-AA28-AB28-AC28-AD28 -> 0 | AG28: =IF(R28=0,0,U28/R28) -> 0 | AH28: =H28 -> 672 | AI28: =IF(R28=0,0,X28/R28) -> 0 | AJ28: =IF(P28=0,Z28/1,Z28/P28) -> 0 | AK28: =IF(P28=0,0,AA28/P28) -> 0 | AL28: {=_xlfn.IFS(R28=0,AE28,R28<0,AE28/-R28,R28>0,AE28/R28)} -> 0 | AM28: =IF(AG28=0,0,AL28/AG28) -> 0 | AN28: =IF(AH28=0,0,AL28/AH28) -> 0 | AP28: =AL28*C28 -> 0
A29: 2774708622 | B29: tunika03 черная распашная | H29: 627 | I29: =C29*H29 -> 0 | N29: =K29/7 -> 0 | O29: =R29/7 -> 0 | P29: =SUMIFS('Отчет 05-11.01'!H:H,'Отчет 05-11.01'!D:D,"Выручка",'Отчет 05-11.01'!E:E,B29) -> 0 | Q29: =SUMIFS('Отчет 05-11.01'!H:H,'Отчет 05-11.01'!D:D,"Возврат выручки",'Отчет 05-11.01'!E:E,B29) -> 0 | R29: =P29-Q29 -> 0 | S29: =SUMIFS('Отчет 05-11.01'!P:P,'Отчет 05-11.01'!C:C,"Продажи",'Отчет 05-11.01'!E:E,B29) -> 0 | T29: =SUMIFS('Отчет 05-11.01'!P:P,'Отчет 05-11.01'!C:C,"Возвраты",'Отчет 05-11.01'!E:E,B29) -> 0 | U29: =S29+T29 -> 0 | V29: =U29/$U$49 -> 0 | W29: =R29*H29 -> 0 | X29: =-SUMIFS('Отчет 05-11.01'!P:P,'Отчет 05-11.01'!C:C,"Вознаграждение Ozon",'Отчет 05-11.01'!E:E,B29) -> 0 | Y29: =IF(U29=0,0,X29/U29) -> 0 | Z29: =-SUMIFS('Отчет 05-11.01'!P:P,'Отчет 05-11.01'!C:C,"Услуги доставки",'Отчет 05-11.01'!E:E,B29) -> 0 | AD29: =U29*1% -> 0 | AE29: =U29-W29-X29-Z29-AA29-AB29-AC29-AD29 -> 0 | AG29: =IF(R29=0,0,U29/R29) -> 0 | AH29: =H29 -> 627 | AI29: =IF(R29=0,0,X29/R29) -> 0 | AJ29: =IF(P29=0,Z29/1,Z29/P29) -> 0 | AK29: =IF(P29=0,0,AA29/P29) -> 0 | AL29: {=_xlfn.IFS(R29=0,AE29,R29<0,AE29/-R29,R29>0,AE29/R29)} -> 0 | AM29: =IF(AG29=0,0,AL29/AG29) -> 0 | AN29: =IF(AH29=0,0,AL29/AH29) -> 0 | AP29: =AL29*C29 -> 0
A30: 2774709606 | B30: tunika05 белая распашная | H30: 627 | I30: =C30*H30 -> 0 | N30: =K30/7 -> 0 | O30: =R30/7 -> 0 | P30: =SUMIFS('Отчет 05-11.01'!H:H,'Отчет 05-11.01'!D:D,"Выручка",'Отчет 05-11.01'!E:E,B30) -> 0 | Q30: =SUMIFS('Отчет 05-11.01'!H:H,'Отчет 05-11.01'!D:D,"Возврат выручки",'Отчет 05-11.01'!E:E,B30) -> 0 | R30: =P30-Q30 -> 0 | S30: =SUMIFS('Отчет 05-11.01'!P:P,'Отчет 05-11.01'!C:C,"Продажи",'Отчет 05-11.01'!E:E,B30) -> 0 | T30: =SUMIFS('Отчет 05-11.01'!P:P,'Отчет 05-11.01'!C:C,"Возвраты",'Отчет 05-11.01'!E:E,B30) -> 0 | U30: =S30+T30 -> 0 | V30: =U30/$U$49 -> 0 | W30: =R30*H30 -> 0 | X30: =-SUMIFS('Отчет 05-11.01'!P:P,'Отчет 05-11.01'!C:C,"Вознаграждение Ozon",'Отчет 05-11.01'!E:E,B30) -> 0 | Y30: =IF(U30=0,0,X30/U30) -> 0 | Z30: =-SUMIFS('Отчет 05-11.01'!P:P,'Отчет 05-11.01'!C:C,"Услуги доставки",'Отчет 05-11.01'!E:E,B30) -> 0 | AD30: =U30*1% -> 0 | AE30: =U30-W30-X30-Z30-AA30-AB30-AC30-AD30 -> 0 | AG30: =IF(R30=0,0,U30/R30) -> 0 | AH30: =H30 -> 627 | AI30: =IF(R30=0,0,X30/R30) -> 0 | AJ30: =IF(P30=0,Z30/1,Z30/P30) -> 0 | AK30: =IF(P30=0,0,AA30/P30) -> 0 | AL30: {=_xlfn.IFS(R30=0,AE30,R30<0,AE30/-R30,R30>0,AE30/R30)} -> 0 | AM30: =IF(AG30=0,0,AL30/AG30) -> 0 | AN30: =IF(AH30=0,0,AL30/AH30) -> 0 | AP30: =AL30*C30 -> 0
A31: 2774720465 | B31: tunika06 белая | H31: 567 | I31: =C31*H31 -> 0 | N31: =K31/7 -> 0 | O31: =R31/7 -> 0 | P31: =SUMIFS('Отчет 05-11.01'!H:H,'Отчет 05-11.01'!D:D,"Выручка",'Отчет 05-11.01'!E:E,B31) -> 0 | Q31: =SUMIFS('Отчет 05-11.01'!H:H,'Отчет 05-11.01'!D:D,"Возврат выручки",'Отчет 05-11.01'!E:E,B31) -> 0 | R31: =P31-Q31 -> 0 | S31: =SUMIFS('Отчет 05-11.01'!P:P,'Отчет 05-11.01'!C:C,"Продажи",'Отчет 05-11.01'!E:E,B31) -> 0 | T31: =SUMIFS('Отчет 05-11.01'!P:P,'Отчет 05-11.01'!C:C,"Возвраты",'Отчет 05-11.01'!E:E,B31) -> 0 | U31: =S31+T31 -> 0 | V31: =U31/$U$49 -> 0 | W31: =R31*H31 -> 0 | X31: =-SUMIFS('Отчет 05-11.01'!P:P,'Отчет 05-11.01'!C:C,"Вознаграждение Ozon",'Отчет 05-11.01'!E:E,B31) -> 0 | Y31: =IF(U31=0,0,X31/U31) -> 0 | Z31: =-SUMIFS('Отчет 05-11.01'!P:P,'Отчет 05-11.01'!C:C,"Услуги доставки",'Отчет 05-11.01'!E:E,B31) -> 0 | AD31: =U31*1% -> 0 | AE31: =U31-W31-X31-Z31-AA31-AB31-AC31-AD31 -> 0 | AG31: =IF(R31=0,0,U31/R31) -> 0 | AH31: =H31 -> 567 | AI31: =IF(R31=0,0,X31/R31) -> 0 | AJ31: =IF(P31=0,Z31/1,Z31/P31) -> 0 | AK31: =IF(P31=0,0,AA31/P31) -> 0 | AL31: {=_xlfn.IFS(R31=0,AE31,R31<0,AE31/-R31,R31>0,AE31/R31)} -> 0 | AM31: =IF(AG31=0,0,AL31/AG31) -> 0 | AN31: =IF(AH31=0,0,AL31/AH31) -> 0 | AP31: =AL31*C31 -> 0
A32: 2774718470 | B32: tunika06 черная | H32: 567 | I32: =C32*H32 -> 0 | N32: =K32/7 -> 0 | O32: =R32/7 -> 0 | P32: =SUMIFS('Отчет 05-11.01'!H:H,'Отчет 05-11.01'!D:D,"Выручка",'Отчет 05-11.01'!E:E,B32) -> 0 | Q32: =SUMIFS('Отчет 05-11.01'!H:H,'Отчет 05-11.01'!D:D,"Возврат выручки",'Отчет 05-11.01'!E:E,B32) -> 0 | R32: =P32-Q32 -> 0 | S32: =SUMIFS('Отчет 05-11.01'!P:P,'Отчет 05-11.01'!C:C,"Продажи",'Отчет 05-11.01'!E:E,B32) -> 0 | T32: =SUMIFS('Отчет 05-11.01'!P:P,'Отчет 05-11.01'!C:C,"Возвраты",'Отчет 05-11.01'!E:E,B32) -> 0 | U32: =S32+T32 -> 0 | V32: =U32/$U$49 -> 0 | W32: =R32*H32 -> 0 | X32: =-SUMIFS('Отчет 05-11.01'!P:P,'Отчет 05-11.01'!C:C,"Вознаграждение Ozon",'Отчет 05-11.01'!E:E,B32) -> 0 | Y32: =IF(U32=0,0,X32/U32) -> 0 | Z32: =-SUMIFS('Отчет 05-11.01'!P:P,'Отчет 05-11.01'!C:C,"Услуги доставки",'Отчет 05-11.01'!E:E,B32) -> 0 | AD32: =U32*1% -> 0 | AE32: =U32-W32-X32-Z32-AA32-AB32-AC32-AD32 -> 0 | AG32: =IF(R32=0,0,U32/R32) -> 0 | AH32: =H32 -> 567 | AI32: =IF(R32=0,0,X32/R32) -> 0 | AJ32: =IF(P32=0,Z32/1,Z32/P32) -> 0 | AK32: =IF(P32=0,0,AA32/P32) -> 0 | AL32: {=_xlfn.IFS(R32=0,AE32,R32<0,AE32/-R32,R32>0,AE32/R32)} -> 0 | AM32: =IF(AG32=0,0,AL32/AG32) -> 0 | AN32: =IF(AH32=0,0,AL32/AH32) -> 0 | AP32: =AL32*C32 -> 0
A33: 2774719022 | B33: tunika07 кружево | H33: 657 | I33: =C33*H33 -> 0 | N33: =K33/7 -> 0 | O33: =R33/7 -> 0 | P33: =SUMIFS('Отчет 05-11.01'!H:H,'Отчет 05-11.01'!D:D,"Выручка",'Отчет 05-11.01'!E:E,B33) -> 0 | Q33: =SUMIFS('Отчет 05-11.01'!H:H,'Отчет 05-11.01'!D:D,"Возврат выручки",'Отчет 05-11.01'!E:E,B33) -> 0 | R33: =P33-Q33 -> 0 | S33: =SUMIFS('Отчет 05-11.01'!P:P,'Отчет 05-11.01'!C:C,"Продажи",'Отчет 05-11.01'!E:E,B33) -> 0 | T33: =SUMIFS('Отчет 05-11.01'!P:P,'Отчет 05-11.01'!C:C,"Возвраты",'Отчет 05-11.01'!E:E,B33) -> 0 | U33: =S33+T33 -> 0 | V33: =U33/$U$49 -> 0 | W33: =R33*H33 -> 0 | X33: =-SUMIFS('Отчет 05-11.01'!P:P,'Отчет 05-11.01'!C:C,"Вознаграждение Ozon",'Отчет 05-11.01'!E:E,B33) -> 0 | Y33: =IF(U33=0,0,X33/U33) -> 0 | Z33: =-SUMIFS('Отчет 05-11.01'!P:P,'Отчет 05-11.01'!C:C,"Услуги доставки",'Отчет 05-11.01'!E:E,B33) -> 0 | AD33: =U33*1% -> 0 | AE33: =U33-W33-X33-Z33-AA33-AB33-AC33-AD33 -> 0 | AG33: =IF(R33=0,0,U33/R33) -> 0 | AH33: =H33 -> 657 | AI33: =IF(R33=0,0,X33/R33) -> 0 | AJ33: =IF(P33=0,Z33/1,Z33/P33) -> 0 | AK33: =IF(P33=0,0,AA33/P33) -> 0 | AL33: {=_xlfn.IFS(R33=0,AE33,R33<0,AE33/-R33,R33>0,AE33/R33)} -> 0 | AM33: =IF(AG33=0,0,AL33/AG33) -> 0 | AN33: =IF(AH33=0,0,AL33/AH33) -> 0 | AP33: =AL33*C33 -> 0
A34: 2774719501 | B34: tunika08 белая | H34: 597 | I34: =C34*H34 -> 0 | N34: =K34/7 -> 0 | O34: =R34/7 -> 0 | P34: =SUMIFS('Отчет 05-11.01'!H:H,'Отчет 05-11.01'!D:D,"Выручка",'Отчет 05-11.01'!E:E,B34) -> 0 | Q34: =SUMIFS('Отчет 05-11.01'!H:H,'Отчет 05-11.01'!D:D,"Возврат выручки",'Отчет 05-11.01'!E:E,B34) -> 0 | R34: =P34-Q34 -> 0 | S34: =SUMIFS('Отчет 05-11.01'!P:P,'Отчет 05-11.01'!C:C,"Продажи",'Отчет 05-11.01'!E:E,B34) -> 0 | T34: =SUMIFS('Отчет 05-11.01'!P:P,'Отчет 05-11.01'!C:C,"Возвраты",'Отчет 05-11.01'!E:E,B34) -> 0 | U34: =S34+T34 -> 0 | V34: =U34/$U$49 -> 0 | W34: =R34*H34 -> 0 | X34: =-SUMIFS('Отчет 05-11.01'!P:P,'Отчет 05-11.01'!C:C,"Вознаграждение Ozon",'Отчет 05-11.01'!E:E,B34) -> 0 | Y34: =IF(U34=0,0,X34/U34) -> 0 | Z34: =-SUMIFS('Отчет 05-11.01'!P:P,'Отчет 05-11.01'!C:C,"Услуги доставки",'Отчет 05-11.01'!E:E,B34) -> 0 | AD34: =U34*1% -> 0 | AE34: =U34-W34-X34-Z34-AA34-AB34-AC34-AD34 -> 0 | AG34: =IF(R34=0,0,U34/R34) -> 0 | AH34: =H34 -> 597 | AI34: =IF(R34=0,0,X34/R34) -> 0 | AJ34: =IF(P34=0,Z34/1,Z34/P34) -> 0 | AK34: =IF(P34=0,0,AA34/P34) -> 0 | AL34: {=_xlfn.IFS(R34=0,AE34,R34<0,AE34/-R34,R34>0,AE34/R34)} -> 0 | AM34: =IF(AG34=0,0,AL34/AG34) -> 0 | AN34: =IF(AH34=0,0,AL34/AH34) -> 0 | AP34: =AL34*C34 -> 0
A35: 2774714412 | B35: tunika08 черная | H35: 552 | I35: =C35*H35 -> 0 | N35: =K35/7 -> 0 | O35: =R35/7 -> 0 | P35: =SUMIFS('Отчет 05-11.01'!H:H,'Отчет 05-11.01'!D:D,"Выручка",'Отчет 05-11.01'!E:E,B35) -> 0 | Q35: =SUMIFS('Отчет 05-11.01'!H:H,'Отчет 05-11.01'!D:D,"Возврат выручки",'Отчет 05-11.01'!E:E,B35) -> 0 | R35: =P35-Q35 -> 0 | S35: =SUMIFS('Отчет 05-11.01'!P:P,'Отчет 05-11.01'!C:C,"Продажи",'Отчет 05-11.01'!E:E,B35) -> 0 | T35: =SUMIFS('Отчет 05-11.01'!P:P,'Отчет 05-11.01'!C:C,"Возвраты",'Отчет 05-11.01'!E:E,B35) -> 0 | U35: =S35+T35 -> 0 | V35: =U35/$U$49 -> 0 | W35: =R35*H35 -> 0 | X35: =-SUMIFS('Отчет 05-11.01'!P:P,'Отчет 05-11.01'!C:C,"Вознаграждение Ozon",'Отчет 05-11.01'!E:E,B35) -> 0 | Y35: =IF(U35=0,0,X35/U35) -> 0 | Z35: =-SUMIFS('Отчет 05-11.01'!P:P,'Отчет 05-11.01'!C:C,"Услуги доставки",'Отчет 05-11.01'!E:E,B35) -> 0 | AD35: =U35*1% -> 0 | AE35: =U35-W35-X35-Z35-AA35-AB35-AC35-AD35 -> 0 | AG35: =IF(R35=0,0,U35/R35) -> 0 | AH35: =H35 -> 552 | AI35: =IF(R35=0,0,X35/R35) -> 0 | AJ35: =IF(P35=0,Z35/1,Z35/P35) -> 0 | AK35: =IF(P35=0,0,AA35/P35) -> 0 | AL35: {=_xlfn.IFS(R35=0,AE35,R35<0,AE35/-R35,R35>0,AE35/R35)} -> 0 | AM35: =IF(AG35=0,0,AL35/AG35) -> 0 | AN35: =IF(AH35=0,0,AL35/AH35) -> 0 | AP35: =AL35*C35 -> 0
A36: 2774710430 | B36: tunika08 зеленая | H36: 552 | I36: =C36*H36 -> 0 | N36: =K36/7 -> 0 | O36: =R36/7 -> 0 | P36: =SUMIFS('Отчет 05-11.01'!H:H,'Отчет 05-11.01'!D:D,"Выручка",'Отчет 05-11.01'!E:E,B36) -> 0 | Q36: =SUMIFS('Отчет 05-11.01'!H:H,'Отчет 05-11.01'!D:D,"Возврат выручки",'Отчет 05-11.01'!E:E,B36) -> 0 | R36: =P36-Q36 -> 0 | S36: =SUMIFS('Отчет 05-11.01'!P:P,'Отчет 05-11.01'!C:C,"Продажи",'Отчет 05-11.01'!E:E,B36) -> 0 | T36: =SUMIFS('Отчет 05-11.01'!P:P,'Отчет 05-11.01'!C:C,"Возвраты",'Отчет 05-11.01'!E:E,B36) -> 0 | U36: =S36+T36 -> 0 | V36: =U36/$U$49 -> 0 | W36: =R36*H36 -> 0 | X36: =-SUMIFS('Отчет 05-11.01'!P:P,'Отчет 05-11.01'!C:C,"Вознаграждение Ozon",'Отчет 05-11.01'!E:E,B36) -> 0 | Y36: =IF(U36=0,0,X36/U36) -> 0 | Z36: =-SUMIFS('Отчет 05-11.01'!P:P,'Отчет 05-11.01'!C:C,"Услуги доставки",'Отчет 05-11.01'!E:E,B36) -> 0 | AD36: =U36*1% -> 0 | AE36: =U36-W36-X36-Z36-AA36-AB36-AC36-AD36 -> 0 | AG36: =IF(R36=0,0,U36/R36) -> 0 | AH36: =H36 -> 552 | AI36: =IF(R36=0,0,X36/R36) -> 0 | AJ36: =IF(P36=0,Z36/1,Z36/P36) -> 0 | AK36: =IF(P36=0,0,AA36/P36) -> 0 | AL36: {=_xlfn.IFS(R36=0,AE36,R36<0,AE36/-R36,R36>0,AE36/R36)} -> 0 | AM36: =IF(AG36=0,0,AL36/AG36) -> 0 | AN36: =IF(AH36=0,0,AL36/AH36) -> 0 | AP36: =AL36*C36 -> 0
A37: 2774712116 | B37: tunika09 кимоно | H37: 687 | I37: =C37*H37 -> 0 | N37: =K37/7 -> 0 | O37: =R37/7 -> 0 | P37: =SUMIFS('Отчет 05-11.01'!H:H,'Отчет 05-11.01'!D:D,"Выручка",'Отчет 05-11.01'!E:E,B37) -> 0 | Q37: =SUMIFS('Отчет 05-11.01'!H:H,'Отчет 05-11.01'!D:D,"Возврат выручки",'Отчет 05-11.01'!E:E,B37) -> 0 | R37: =P37-Q37 -> 0 | S37: =SUMIFS('Отчет 05-11.01'!P:P,'Отчет 05-11.01'!C:C,"Продажи",'Отчет 05-11.01'!E:E,B37) -> 0 | T37: =SUMIFS('Отчет 05-11.01'!P:P,'Отчет 05-11.01'!C:C,"Возвраты",'Отчет 05-11.01'!E:E,B37) -> 0 | U37: =S37+T37 -> 0 | V37: =U37/$U$49 -> 0 | W37: =R37*H37 -> 0 | X37: =-SUMIFS('Отчет 05-11.01'!P:P,'Отчет 05-11.01'!C:C,"Вознаграждение Ozon",'Отчет 05-11.01'!E:E,B37) -> 0 | Y37: =IF(U37=0,0,X37/U37) -> 0 | Z37: =-SUMIFS('Отчет 05-11.01'!P:P,'Отчет 05-11.01'!C:C,"Услуги доставки",'Отчет 05-11.01'!E:E,B37) -> 113.88 | AD37: =U37*1% -> 0 | AE37: =U37-W37-X37-Z37-AA37-AB37-AC37-AD37 -> -113.88 | AG37: =IF(R37=0,0,U37/R37) -> 0 | AH37: =H37 -> 687 | AI37: =IF(R37=0,0,X37/R37) -> 0 | AJ37: =IF(P37=0,Z37/1,Z37/P37) -> 113.88 | AK37: =IF(P37=0,0,AA37/P37) -> 0 | AL37: {=_xlfn.IFS(R37=0,AE37,R37<0,AE37/-R37,R37>0,AE37/R37)} -> -113.88 | AM37: =IF(AG37=0,0,AL37/AG37) -> 0 | AN37: =IF(AH37=0,0,AL37/AH37) -> -0.16576419 | AP37: =AL37*C37 -> 0
A38: 2774719012 | B38: tunika10 кимоно ч/б | H38: 687 | I38: =C38*H38 -> 0 | N38: =K38/7 -> 0 | O38: =R38/7 -> 0 | P38: =SUMIFS('Отчет 05-11.01'!H:H,'Отчет 05-11.01'!D:D,"Выручка",'Отчет 05-11.01'!E:E,B38) -> 0 | Q38: =SUMIFS('Отчет 05-11.01'!H:H,'Отчет 05-11.01'!D:D,"Возврат выручки",'Отчет 05-11.01'!E:E,B38) -> 0 | R38: =P38-Q38 -> 0 | S38: =SUMIFS('Отчет 05-11.01'!P:P,'Отчет 05-11.01'!C:C,"Продажи",'Отчет 05-11.01'!E:E,B38) -> 0 | T38: =SUMIFS('Отчет 05-11.01'!P:P,'Отчет 05-11.01'!C:C,"Возвраты",'Отчет 05-11.01'!E:E,B38) -> 0 | U38: =S38+T38 -> 0 | V38: =U38/$U$49 -> 0 | W38: =R38*H38 -> 0 | X38: =-SUMIFS('Отчет 05-11.01'!P:P,'Отчет 05-11.01'!C:C,"Вознаграждение Ozon",'Отчет 05-11.01'!E:E,B38) -> 0 | Y38: =IF(U38=0,0,X38/U38) -> 0 | Z38: =-SUMIFS('Отчет 05-11.01'!P:P,'Отчет 05-11.01'!C:C,"Услуги доставки",'Отчет 05-11.01'!E:E,B38) -> 0 | AD38: =U38*1% -> 0 | AE38: =U38-W38-X38-Z38-AA38-AB38-AC38-AD38 -> 0 | AG38: =IF(R38=0,0,U38/R38) -> 0 | AH38: =H38 -> 687 | AI38: =IF(R38=0,0,X38/R38) -> 0 | AJ38: =IF(P38=0,Z38/1,Z38/P38) -> 0 | AK38: =IF(P38=0,0,AA38/P38) -> 0 | AL38: {=_xlfn.IFS(R38=0,AE38,R38<0,AE38/-R38,R38>0,AE38/R38)} -> 0 | AM38: =IF(AG38=0,0,AL38/AG38) -> 0 | AN38: =IF(AH38=0,0,AL38/AH38) -> 0 | AP38: =AL38*C38 -> 0
A39: 2774719433 | B39: tunika11 халат зеленая | H39: 597 | I39: =C39*H39 -> 0 | N39: =K39/7 -> 0 | O39: =R39/7 -> 0 | P39: =SUMIFS('Отчет 05-11.01'!H:H,'Отчет 05-11.01'!D:D,"Выручка",'Отчет 05-11.01'!E:E,B39) -> 0 | Q39: =SUMIFS('Отчет 05-11.01'!H:H,'Отчет 05-11.01'!D:D,"Возврат выручки",'Отчет 05-11.01'!E:E,B39) -> 0 | R39: =P39-Q39 -> 0 | S39: =SUMIFS('Отчет 05-11.01'!P:P,'Отчет 05-11.01'!C:C,"Продажи",'Отчет 05-11.01'!E:E,B39) -> 0 | T39: =SUMIFS('Отчет 05-11.01'!P:P,'Отчет 05-11.01'!C:C,"Возвраты",'Отчет 05-11.01'!E:E,B39) -> 0 | U39: =S39+T39 -> 0 | V39: =U39/$U$49 -> 0 | W39: =R39*H39 -> 0 | X39: =-SUMIFS('Отчет 05-11.01'!P:P,'Отчет 05-11.01'!C:C,"Вознаграждение Ozon",'Отчет 05-11.01'!E:E,B39) -> 0 | Y39: =IF(U39=0,0,X39/U39) -> 0 | Z39: =-SUMIFS('Отчет 05-11.01'!P:P,'Отчет 05-11.01'!C:C,"Услуги доставки",'Отчет 05-11.01'!E:E,B39) -> 0 | AD39: =U39*1% -> 0 | AE39: =U39-W39-X39-Z39-AA39-AB39-AC39-AD39 -> 0 | AG39: =IF(R39=0,0,U39/R39) -> 0 | AH39: =H39 -> 597 | AI39: =IF(R39=0,0,X39/R39) -> 0 | AJ39: =IF(P39=0,Z39/1,Z39/P39) -> 0 | AK39: =IF(P39=0,0,AA39/P39) -> 0 | AL39: {=_xlfn.IFS(R39=0,AE39,R39<0,AE39/-R39,R39>0,AE39/R39)} -> 0 | AM39: =IF(AG39=0,0,AL39/AG39) -> 0 | AN39: =IF(AH39=0,0,AL39/AH39) -> 0 | AP39: =AL39*C39 -> 0
... A47: 2774719500 | B47: tunika16 сетка черная | H47: 552 | I47: =C47*H47 -> 0 | N47: =K47/7 -> 0 | O47: =R47/7 -> 0 | P47: =SUMIFS('Отчет 05-11.01'!H:H,'Отчет 05-11.01'!D:D,"Выручка",'Отчет 05-11.01'!E:E,B47) -> 0 | Q47: =SUMIFS('Отчет 05-11.01'!H:H,'Отчет 05-11.01'!D:D,"Возврат выручки",'Отчет 05-11.01'!E:E,B47) -> 0 | R47: =P47-Q47 -> 0 | S47: =SUMIFS('Отчет 05-11.01'!P:P,'Отчет 05-11.01'!C:C,"Продажи",'Отчет 05-11.01'!E:E,B47) -> 0 | T47: =SUMIFS('Отчет 05-11.01'!P:P,'Отчет 05-11.01'!C:C,"Возвраты",'Отчет 05-11.01'!E:E,B47) -> 0 | U47: =S47+T47 -> 0 | V47: =U47/$U$49 -> 0 | W47: =R47*H47 -> 0 | X47: =-SUMIFS('Отчет 05-11.01'!P:P,'Отчет 05-11.01'!C:C,"Вознаграждение Ozon",'Отчет 05-11.01'!E:E,B47) -> 0 | Y47: =IF(U47=0,0,X47/U47) -> 0 | Z47: =-SUMIFS('Отчет 05-11.01'!P:P,'Отчет 05-11.01'!C:C,"Услуги доставки",'Отчет 05-11.01'!E:E,B47) -> 0 | AD47: =U47*1% -> 0 | AE47: =U47-W47-X47-Z47-AA47-AB47-AC47-AD47 -> 0 | AG47: =IF(R47=0,0,U47/R47) -> 0 | AH47: =H47 -> 552 | AI47: =IF(R47=0,0,X47/R47) -> 0 | AJ47: =IF(P47=0,Z47/1,Z47/P47) -> 0 | AK47: =IF(P47=0,0,AA47/P47) -> 0 | AL47: {=_xlfn.IFS(R47=0,AE47,R47<0,AE47/-R47,R47>0,AE47/R47)} -> 0 | AM47: =IF(AG47=0,0,AL47/AG47) -> 0 | AN47: =IF(AH47=0,0,AL47/AH47) -> 0 | AP47: =AL47*C47 -> 0
AG48: =AVERAGEIF(AG28:AG47,"<>0",AG28:AG47) -> 5262 | AH48: =AVERAGEIF(AH28:AH47,"<>0",AH28:AH47) -> 617.25 | AI48: =AVERAGEIF(AI28:AI47,"<>0",AI28:AI47) -> 2262.66 | AJ48: =AVERAGEIF(AJ28:AJ47,"<>0",AJ28:AJ47) -> 226.825 | AK48: =AVERAGEIF(AK28:AK47,"<>0",AK28:AK47) -> #DIV/0! | AL48: =AVERAGEIF(AL28:AL47,"<>0",AL28:AL47) -> 914.285 | AM48: =AVERAGEIF(AM28:AM47,"<>0",AM28:AM47) -> 0.36618394 | AN48: =AVERAGEIF(AN28:AN47,"<>0",AN28:AN47) -> 1.3569947
A49: Итого туники | C49: =SUM(C28:C47) -> 0 | I49: =SUM(I28:I47) -> 0 | K49: =SUM(K28:K47) -> 0 | P49: =SUM(P28:P47) -> 2 | Q49: =SUM(Q28:Q47) -> 0 | R49: =SUM(R28:R47) -> 2 | S49: =SUM(S28:S47) -> 10524 | T49: =SUM(T28:T47) -> 0 | U49: =SUM(U28:U47) -> 10524 | V49: =SUM(V28:V47) -> 1 | W49: =SUM(W28:W47) -> 1329 | X49: =SUM(X28:X47) -> 4525.32 | Y49: =IF(U49=0,0,X49/U49) -> 0.43 | Z49: =SUM(Z28:Z47) -> 907.3 | AA49: =IFERROR(P49*AA51/P51,0) -> 828.16167 | AB49: =SUM(AB28:AB47) -> 0 | AC49: =SUM(AC28:AC47) -> 0 | AD49: =SUM(AD28:AD47) -> 105.24 | AE49: =SUM(AE28:AE47) -> 3657.14 | AP49: =SUM(AP28:AP47) -> 0
AA50: =SUM(AA28:AA47) -> 0
A51: ИТОГО | C51: =C26+C49 -> 0 | D51: =SUM(D3:D47) -> 0 | E51: =SUM(E3:E47) -> 108496 | F51: =SUM(F3:F47) -> 597 | G51: =SUM(G3:G47) -> 295 | I51: =I26+I49 -> 0 | J51: =J26+J49 -> 0 | K51: =K26+K49 -> 0 | P51: =P26+P49 -> 60 | Q51: =Q26+Q49 -> 4 | R51: =R26-R49 -> 52 | S51: =S26+S49 -> 102684 | T51: =T26+T49 -> -6799 | U51: =U26+U49 -> 95885 | V51: =V26+V49 -> 9.1110794 | W51: =W26+W49 -> 8980.8 | X51: =X26+X49 -> 41230.55 | Y51: =X51/U51 -> 0.43 | Z51: =Z26+Z49 -> 10857.57 | AA51: 24844.85 | AC51: =SUM(AC3:AC47) -> 0 | AD51: =AD26+AD49 -> 958.85 | AE51: =AE26+AE49 -> 33857.23 | AK51: =AA52/P51 -> 414.08083 | AP51: =SUM(AP3:AP47) -> 0
AA52: =AA26+AA49 -> 24844.85
AA53: =AA27+AA50 -> 0
I56: Себестоимость остатков | K56: Прибыль с остатков | L56: Рентабельность товарных остатков
H58: до 60 дн | I58: =SUMIF(J3:J47,"<60",I3:I47) -> 0 | J58: =I58/I51 -> #DIV/0! | K58: =SUMIF(J3:J47,"<60",AP3:AP47) -> 0 | L58: =K58/I58 -> #DIV/0!
H59: 60-120 дн | I59: =I51-I60-I58 -> 0 | J59: =I59/I51 -> #DIV/0! | K59: =AP51-K58-K60 -> 0 | L59: =K59/I59 -> #DIV/0!
H60: > 120 дн | I60: =SUMIF(J3:J47,">120",I3:I47) -> 0 | J60: =I60/I51 -> #DIV/0! | K60: =SUMIF(J3:J47,">120",AP3:AP47) -> 0 | L60: =K60/I60 -> #DIV/0!
H62: Если товар на сайте менее 30 дней - оборачиваемость 0

Sheet ЯНВАРЬ
B1: 01-31.01 | AG1: на 1 единицу проданного товара
B2: Артикул поставщика | C2: Остаток на Отчет 23 | D2: В пути до клиента | E2: В пути от клиента | F2: Итого по складам ВБ | G2: Остаток на нашем складе на 02.09 | H2: Себетоимость на 1 ед на 29.09.25 | I2: Себестоимость остатков | J2: Оборачиваемость, дн | K2: Заказы, шт 31 день | L2: Средняя цена, руб (столбец 32, AG) | M2: % выкупа за 7 дней (столбец 23, X) | N2: Скорость заказов | O2: Скорость продаж | P2: Кол-во ПРОДАЖИ | Q2: Кол-во ВОЗВРАТЫ | R2: Кол-во ПРОДАЖИ-ВОЗВРАТЫ | S2: Выручка ПРОДАЖИ | T2: Выручка ВОЗВРАТЫ | U2: Выручка с учетом согласованной скидки ПРОДАЖИ - ВОЗВРАТЫ | V2: Доля выручки, % от общего объема | W2: Себестоимость продаж | X2: Комиссия, руб | Y2: Комиссия, % | Z2: Логистика | AA2: Реклама | AB2: Хранение | AC2: Штрафы | AD2: Налог 1% | AE2: Прибыль | AG2: Выручка на 1 ед (средняя цена продажи со скидкой) | AH2: Себестоимость на 1 ед | AI2: Комиссия на 1 ед | AJ2: Логистика на 1 ед | AK2: Реклама на 1 ед | AL2: Прибыль на 1 ед | AM2: Маржинальность, % | AN2: Рентабельность, % | AP2: Прибыль с остатков
A3: 2638219896 | B3: черные с железкой классика | H3: 142.98 | I3: =C3*H3 -> 0 | K3: ='Юнит 01-04.01'!K3+'Юнит 05-11.01'!K3+'Юнит 12-18.01'!K3+'Юнит 19-25.01'!K3+'Юнит 26-31.01'!K3 -> 230 | N3: =K3/7 -> 32.857143 | O3: =R3/7 -> 18.142857 | P3: ='Юнит 01-04.01'!P3+'Юнит 05-11.01'!P3+'Юнит 12-18.01'!P3+'Юнит 19-25.01'!P3+'Юнит 26-31.01'!P3 -> 131 | Q3: ='Юнит 01-04.01'!Q3+'Юнит 05-11.01'!Q3+'Юнит 12-18.01'!Q3+'Юнит 19-25.01'!Q3+'Юнит 26-31.01'!Q3 -> 4 | R3: =P3-Q3 -> 127 | S3: ='Юнит 01-04.01'!S3+'Юнит 05-11.01'!S3+'Юнит 12-18.01'!S3+'Юнит 19-25.01'!S3+'Юнит 26-31.01'!S3 -> 215922 | T3: ='Юнит 01-04.01'!T3+'Юнит 05-11.01'!T3+'Юнит 12-18.01'!T3+'Юнит 19-25.01'!T3+'Юнит 26-31.01'!T3 -> -6782 | U3: =S3+T3 -> 209140 | V3: =U3/$U$49 -> 2.1281749 | W3: =R3*H3 -> 18158.46 | X3: ='Юнит 01-04.01'!X3+'Юнит 05-11.01'!X3+'Юнит 12-18.01'!X3+'Юнит 19-25.01'!X3+'Юнит 26-31.01'!X3 -> 89930.2 | Y3: =IF(U3=0,0,X3/U3) -> 0.43 | Z3: ='Юнит 01-04.01'!Z3+'Юнит 05-11.01'!Z3+'Юнит 12-18.01'!Z3+'Юнит 19-25.01'!Z3+'Юнит 26-31.01'!Z3 -> 23614.87 | AA3: ='Юнит 01-04.01'!AA3+'Юнит 05-11.01'!AA3+'Юнит 12-18.01'!AA3+'Юнит 19-25.01'!AA3+'Юнит 26-31.01'!AA3 -> 51591.194 | AD3: =U3*1% -> 2091.4 | AE3: =U3-W3-X3-Z3-AA3-AB3-AC3-AD3 -> 23753.876 | AG3: =IF(R3=0,0,U3/R3) -> 1646.7717 | AH3: =H3 -> 142.98 | AI3: =IF(R3=0,0,X3/R3) -> 708.11181 | AJ3: =IF(P3=0,Z3/1,Z3/P3) -> 180.26618 | AK3: =IF(P3=0,0,AA3/P3) -> 393.82591 | AL3: =_xlfn.IFS(R3=0,AE3,R3<0,AE3/-R3,R3>0,AE3/R3) -> 187.03839 | AM3: =IF(AG3=0,0,AL3/AG3) -> 0.11357883 | AN3: =IF(AH3=0,0,AL3/AH3) -> 1.3081438 | AP3: =AL3*C3 -> 0
A4: 2638638550 | B4: qs черные | H4: 123.09 | I4: =C4*H4 -> 0 | K4: ='Юнит 01-04.01'!K4+'Юнит 05-11.01'!K4+'Юнит 12-18.01'!K4+'Юнит 19-25.01'!K4+'Юнит 26-31.01'!K4 -> 10 | N4: =K4/7 -> 1.4285714 | O4: =R4/7 -> 1.1428571 | P4: ='Юнит 01-04.01'!P4+'Юнит 05-11.01'!P4+'Юнит 12-18.01'!P4+'Юнит 19-25.01'!P4+'Юнит 26-31.01'!P4 -> 8 | Q4: ='Юнит 01-04.01'!Q4+'Юнит 05-11.01'!Q4+'Юнит 12-18.01'!Q4+'Юнит 19-25.01'!Q4+'Юнит 26-31.01'!Q4 -> 0 | R4: =P4-Q4 -> 8 | S4: ='Юнит 01-04.01'!S4+'Юнит 05-11.01'!S4+'Юнит 12-18.01'!S4+'Юнит 19-25.01'!S4+'Юнит 26-31.01'!S4 -> 12633 | T4: ='Юнит 01-04.01'!T4+'Юнит 05-11.01'!T4+'Юнит 12-18.01'!T4+'Юнит 19-25.01'!T4+'Юнит 26-31.01'!T4 -> 0 | U4: =S4+T4 -> 12633 | V4: =U4/$U$49 -> 0.12855137 | W4: =R4*H4 -> 984.72 | X4: ='Юнит 01-04.01'!X4+'Юнит 05-11.01'!X4+'Юнит 12-18.01'!X4+'Юнит 19-25.01'!X4+'Юнит 26-31.01'!X4 -> 5432.19 | Y4: =IF(U4=0,0,X4/U4) -> 0.43 | Z4: ='Юнит 01-04.01'!Z4+'Юнит 05-11.01'!Z4+'Юнит 12-18.01'!Z4+'Юнит 19-25.01'!Z4+'Юнит 26-31.01'!Z4 -> 1269.36 | AA4: ='Юнит 01-04.01'!AA4+'Юнит 05-11.01'!AA4+'Юнит 12-18.01'!AA4+'Юнит 19-25.01'!AA4+'Юнит 26-31.01'!AA4 -> 4690.7473 | AD4: =U4*1% -> 126.33 | AE4: =U4-W4-X4-Z4-AA4-AB4-AC4-AD4 -> 129.65268 | AG4: =IF(R4=0,0,U4/R4) -> 1579.125 | AH4: =H4 -> 123.09 | AI4: =IF(R4=0,0,X4/R4) -> 679.02375 | AJ4: =IF(P4=0,Z4/1,Z4/P4) -> 158.67 | AK4: =IF(P4=0,0,AA4/P4) -> 586.34342 | AL4: {=_xlfn.IFS(R4=0,AE4,R4<0,AE4/-R4,R4>0,AE4/R4)} -> 16.206584 | AM4: =IF(AG4=0,0,AL4/AG4) -> 0.010263016 | AN4: =IF(AH4=0,0,AL4/AH4) -> 0.13166451 | AP4: =AL4*C4 -> 0
A5: 2638691131 | B5: qs синие | H5: 123.09 | I5: =C5*H5 -> 0 | K5: ='Юнит 01-04.01'!K5+'Юнит 05-11.01'!K5+'Юнит 12-18.01'!K5+'Юнит 19-25.01'!K5+'Юнит 26-31.01'!K5 -> 3 | N5: =K5/7 -> 0.42857143 | O5: =R5/7 -> 0.57142857 | P5: ='Юнит 01-04.01'!P5+'Юнит 05-11.01'!P5+'Юнит 12-18.01'!P5+'Юнит 19-25.01'!P5+'Юнит 26-31.01'!P5 -> 4 | Q5: ='Юнит 01-04.01'!Q5+'Юнит 05-11.01'!Q5+'Юнит 12-18.01'!Q5+'Юнит 19-25.01'!Q5+'Юнит 26-31.01'!Q5 -> 0 | R5: =P5-Q5 -> 4 | S5: ='Юнит 01-04.01'!S5+'Юнит 05-11.01'!S5+'Юнит 12-18.01'!S5+'Юнит 19-25.01'!S5+'Юнит 26-31.01'!S5 -> 4824 | T5: ='Юнит 01-04.01'!T5+'Юнит 05-11.01'!T5+'Юнит 12-18.01'!T5+'Юнит 19-25.01'!T5+'Юнит 26-31.01'!T5 -> 0 | U5: =S5+T5 -> 4824 | V5: =U5/$U$49 -> 0.049088245 | W5: =R5*H5 -> 492.36 | X5: ='Юнит 01-04.01'!X5+'Юнит 05-11.01'!X5+'Юнит 12-18.01'!X5+'Юнит 19-25.01'!X5+'Юнит 26-31.01'!X5 -> 2074.32 | Y5: =IF(U5=0,0,X5/U5) -> 0.43 | Z5: ='Юнит 01-04.01'!Z5+'Юнит 05-11.01'!Z5+'Юнит 12-18.01'!Z5+'Юнит 19-25.01'!Z5+'Юнит 26-31.01'!Z5 -> 508.67 | AA5: ='Юнит 01-04.01'!AA5+'Юнит 05-11.01'!AA5+'Юнит 12-18.01'!AA5+'Юнит 19-25.01'!AA5+'Юнит 26-31.01'!AA5 -> 0 | AD5: =U5*1% -> 48.24 | AE5: =U5-W5-X5-Z5-AA5-AB5-AC5-AD5 -> 1700.41 | AG5: =IF(R5=0,0,U5/R5) -> 1206 | AH5: =H5 -> 123.09 | AI5: =IF(R5=0,0,X5/R5) -> 518.58 | AJ5: =IF(P5=0,Z5/1,Z5/P5) -> 127.1675 | AK5: =IF(P5=0,0,AA5/P5) -> 0 | AL5: {=_xlfn.IFS(R5=0,AE5,R5<0,AE5/-R5,R5>0,AE5/R5)} -> 425.1025 | AM5: =IF(AG5=0,0,AL5/AG5) -> 0.35248964 | AN5: =IF(AH5=0,0,AL5/AH5) -> 3.4535909 | AP5: =AL5*C5 -> 0
A6: 2638382749 | B6: qs желтые | H6: 123.09 | I6: =C6*H6 -> 0 | K6: ='Юнит 01-04.01'!K6+'Юнит 05-11.01'!K6+'Юнит 12-18.01'!K6+'Юнит 19-25.01'!K6+'Юнит 26-31.01'!K6 -> 26 | N6: =K6/7 -> 3.7142857 | O6: =R6/7 -> 4.2857143 | P6: ='Юнит 01-04.01'!P6+'Юнит 05-11.01'!P6+'Юнит 12-18.01'!P6+'Юнит 19-25.01'!P6+'Юнит 26-31.01'!P6 -> 31 | Q6: ='Юнит 01-04.01'!Q6+'Юнит 05-11.01'!Q6+'Юнит 12-18.01'!Q6+'Юнит 19-25.01'!Q6+'Юнит 26-31.01'!Q6 -> 1 | R6: =P6-Q6 -> 30 | S6: ='Юнит 01-04.01'!S6+'Юнит 05-11.01'!S6+'Юнит 12-18.01'!S6+'Юнит 19-25.01'!S6+'Юнит 26-31.01'!S6 -> 47318 | T6: ='Юнит 01-04.01'!T6+'Юнит 05-11.01'!T6+'Юнит 12-18.01'!T6+'Юнит 19-25.01'!T6+'Юнит 26-31.01'!T6 -> -1687 | U6: =S6+T6 -> 45631 | V6: =U6/$U$49 -> 0.46433369 | W6: =R6*H6 -> 3692.7 | X6: ='Юнит 01-04.01'!X6+'Юнит 05-11.01'!X6+'Юнит 12-18.01'!X6+'Юнит 19-25.01'!X6+'Юнит 26-31.01'!X6 -> 19621.33 | Y6: =IF(U6=0,0,X6/U6) -> 0.43 | Z6: ='Юнит 01-04.01'!Z6+'Юнит 05-11.01'!Z6+'Юнит 12-18.01'!Z6+'Юнит 19-25.01'!Z6+'Юнит 26-31.01'!Z6 -> 4860.29 | AA6: ='Юнит 01-04.01'!AA6+'Юнит 05-11.01'!AA6+'Юнит 12-18.01'!AA6+'Юнит 19-25.01'!AA6+'Юнит 26-31.01'!AA6 -> 10728.217 | AD6: =U6*1% -> 456.31 | AE6: =U6-W6-X6-Z6-AA6-AB6-AC6-AD6 -> 6272.1531 | AG6: =IF(R6=0,0,U6/R6) -> 1521.0333 | AH6: =H6 -> 123.09 | AI6: =IF(R6=0,0,X6/R6) -> 654.04433 | AJ6: =IF(P6=0,Z6/1,Z6/P6) -> 156.78355 | AK6: =IF(P6=0,0,AA6/P6) -> 346.07151 | AL6: {=_xlfn.IFS(R6=0,AE6,R6<0,AE6/-R6,R6>0,AE6/R6)} -> 209.07177 | AM6: =IF(AG6=0,0,AL6/AG6) -> 0.13745377 | AN6: =IF(AH6=0,0,AL6/AH6) -> 1.6985277 | AP6: =AL6*C6 -> 0
A7: 2638569317 | B7: qs коричневые | H7: 117.24 | I7: =C7*H7 -> 0 | K7: ='Юнит 01-04.01'!K7+'Юнит 05-11.01'!K7+'Юнит 12-18.01'!K7+'Юнит 19-25.01'!K7+'Юнит 26-31.01'!K7 -> 15 | N7: =K7/7 -> 2.1428571 | O7: =R7/7 -> 1.1428571 | P7: ='Юнит 01-04.01'!P7+'Юнит 05-11.01'!P7+'Юнит 12-18.01'!P7+'Юнит 19-25.01'!P7+'Юнит 26-31.01'!P7 -> 8 | Q7: ='Юнит 01-04.01'!Q7+'Юнит 05-11.01'!Q7+'Юнит 12-18.01'!Q7+'Юнит 19-25.01'!Q7+'Юнит 26-31.01'!Q7 -> 0 | R7: =P7-Q7 -> 8 | S7: ='Юнит 01-04.01'!S7+'Юнит 05-11.01'!S7+'Юнит 12-18.01'!S7+'Юнит 19-25.01'!S7+'Юнит 26-31.01'!S7 -> 13188 | T7: ='Юнит 01-04.01'!T7+'Юнит 05-11.01'!T7+'Юнит 12-18.01'!T7+'Юнит 19-25.01'!T7+'Юнит 26-31.01'!T7 -> 0 | U7: =S7+T7 -> 13188 | V7: =U7/$U$49 -> 0.13419896 | W7: =R7*H7 -> 937.92 | X7: ='Юнит 01-04.01'!X7+'Юнит 05-11.01'!X7+'Юнит 12-18.01'!X7+'Юнит 19-25.01'!X7+'Юнит 26-31.01'!X7 -> 5670.84 | Y7: =IF(U7=0,0,X7/U7) -> 0.43 | Z7: ='Юнит 01-04.01'!Z7+'Юнит 05-11.01'!Z7+'Юнит 12-18.01'!Z7+'Юнит 19-25.01'!Z7+'Юнит 26-31.01'!Z7 -> 1477.34 | AA7: ='Юнит 01-04.01'!AA7+'Юнит 05-11.01'!AA7+'Юнит 12-18.01'!AA7+'Юнит 19-25.01'!AA7+'Юнит 26-31.01'!AA7 -> 1767.0973 | AD7: =U7*1% -> 131.88 | AE7: =U7-W7-X7-Z7-AA7-AB7-AC7-AD7 -> 3202.9227 | AG7: =IF(R7=0,0,U7/R7) -> 1648.5 | AH7: =H7 -> 117.24 | AI7: =IF(R7=0,0,X7/R7) -> 708.855 | AJ7: =IF(P7=0,Z7/1,Z7/P7) -> 184.6675 | AK7: =IF(P7=0,0,AA7/P7) -> 220.88716 | AL7: {=_xlfn.IFS(R7=0,AE7,R7<0,AE7/-R7,R7>0,AE7/R7)} -> 400.36534 | AM7: =IF(AG7=0,0,AL7/AG7) -> 0.24286645 | AN7: =IF(AH7=0,0,AL7/AH7) -> 3.414921 | AP7: =AL7*C7 -> 0
A8: 3064334128 | B8: th желтый Сул | H8: 123 | I8: =C8*H8 -> 0 | K8: ='Юнит 01-04.01'!K8+'Юнит 05-11.01'!K8+'Юнит 12-18.01'!K8+'Юнит 19-25.01'!K8+'Юнит 26-31.01'!K8 -> 3 | N8: =K8/7 -> 0.42857143 | O8: =R8/7 -> 0.14285714 | P8: ='Юнит 01-04.01'!P8+'Юнит 05-11.01'!P8+'Юнит 12-18.01'!P8+'Юнит 19-25.01'!P8+'Юнит 26-31.01'!P8 -> 1 | Q8: ='Юнит 01-04.01'!Q8+'Юнит 05-11.01'!Q8+'Юнит 12-18.01'!Q8+'Юнит 19-25.01'!Q8+'Юнит 26-31.01'!Q8 -> 0 | R8: =P8-Q8 -> 1 | S8: ='Юнит 01-04.01'!S8+'Юнит 05-11.01'!S8+'Юнит 12-18.01'!S8+'Юнит 19-25.01'!S8+'Юнит 26-31.01'!S8 -> 1539 | T8: ='Юнит 01-04.01'!T8+'Юнит 05-11.01'!T8+'Юнит 12-18.01'!T8+'Юнит 19-25.01'!T8+'Юнит 26-31.01'!T8 -> 0 | U8: =S8+T8 -> 1539 | V8: =U8/$U$49 -> 0.015660615 | W8: =R8*H8 -> 123 | X8: ='Юнит 01-04.01'!X8+'Юнит 05-11.01'!X8+'Юнит 12-18.01'!X8+'Юнит 19-25.01'!X8+'Юнит 26-31.01'!X8 -> 661.77 | Y8: =IF(U8=0,0,X8/U8) -> 0.43 | Z8: ='Юнит 01-04.01'!Z8+'Юнит 05-11.01'!Z8+'Юнит 12-18.01'!Z8+'Юнит 19-25.01'!Z8+'Юнит 26-31.01'!Z8 -> 132.14 | AA8: ='Юнит 01-04.01'!AA8+'Юнит 05-11.01'!AA8+'Юнит 12-18.01'!AA8+'Юнит 19-25.01'!AA8+'Юнит 26-31.01'!AA8 -> 0 | AD8: =U8*1% -> 15.39 | AE8: =U8-W8-X8-Z8-AA8-AB8-AC8-AD8 -> 606.7 | AG8: =IF(R8=0,0,U8/R8) -> 1539 | AH8: =H8 -> 123 | AI8: =IF(R8=0,0,X8/R8) -> 661.77 | AJ8: =IF(P8=0,Z8/1,Z8/P8) -> 132.14 | AK8: =IF(P8=0,0,AA8/P8) -> 0 | AL8: {=_xlfn.IFS(R8=0,AE8,R8<0,AE8/-R8,R8>0,AE8/R8)} -> 606.7 | AM8: =IF(AG8=0,0,AL8/AG8) -> 0.39421702 | AN8: =IF(AH8=0,0,AL8/AH8) -> 4.9325203 | AP8: =AL8*C8 -> 0
A9: 3064334311 | B9: flip желтые Сул | H9: 123 | I9: =C9*H9 -> 0 | K9: ='Юнит 01-04.01'!K9+'Юнит 05-11.01'!K9+'Юнит 12-18.01'!K9+'Юнит 19-25.01'!K9+'Юнит 26-31.01'!K9 -> 14 | N9: =K9/7 -> 2 | O9: =R9/7 -> 0.85714286 | P9: ='Юнит 01-04.01'!P9+'Юнит 05-11.01'!P9+'Юнит 12-18.01'!P9+'Юнит 19-25.01'!P9+'Юнит 26-31.01'!P9 -> 6 | Q9: ='Юнит 01-04.01'!Q9+'Юнит 05-11.01'!Q9+'Юнит 12-18.01'!Q9+'Юнит 19-25.01'!Q9+'Юнит 26-31.01'!Q9 -> 0 | R9: =P9-Q9 -> 6 | S9: ='Юнит 01-04.01'!S9+'Юнит 05-11.01'!S9+'Юнит 12-18.01'!S9+'Юнит 19-25.01'!S9+'Юнит 26-31.01'!S9 -> 10890 | T9: ='Юнит 01-04.01'!T9+'Юнит 05-11.01'!T9+'Юнит 12-18.01'!T9+'Юнит 19-25.01'!T9+'Юнит 26-31.01'!T9 -> 0 | U9: =S9+T9 -> 10890 | V9: =U9/$U$49 -> 0.11081488 | W9: =R9*H9 -> 738 | X9: ='Юнит 01-04.01'!X9+'Юнит 05-11.01'!X9+'Юнит 12-18.01'!X9+'Юнит 19-25.01'!X9+'Юнит 26-31.01'!X9 -> 4682.7 | Y9: =IF(U9=0,0,X9/U9) -> 0.43 | Z9: ='Юнит 01-04.01'!Z9+'Юнит 05-11.01'!Z9+'Юнит 12-18.01'!Z9+'Юнит 19-25.01'!Z9+'Юнит 26-31.01'!Z9 -> 1257 | AA9: ='Юнит 01-04.01'!AA9+'Юнит 05-11.01'!AA9+'Юнит 12-18.01'!AA9+'Юнит 19-25.01'!AA9+'Юнит 26-31.01'!AA9 -> 5160.0555 | AD9: =U9*1% -> 108.9 | AE9: =U9-W9-X9-Z9-AA9-AB9-AC9-AD9 -> -1056.6555 | AG9: =IF(R9=0,0,U9/R9) -> 1815 | AH9: =H9 -> 123 | AI9: =IF(R9=0,0,X9/R9) -> 780.45 | AJ9: =IF(P9=0,Z9/1,Z9/P9) -> 209.5 | AK9: =IF(P9=0,0,AA9/P9) -> 860.00925 | AL9: {=_xlfn.IFS(R9=0,AE9,R9<0,AE9/-R9,R9>0,AE9/R9)} -> -176.10925 | AM9: =IF(AG9=0,0,AL9/AG9) -> -0.097029888 | AN9: =IF(AH9=0,0,AL9/AH9) -> -1.4317825 | AP9: =AL9*C9 -> 0
A10: 2638291563 | B10: MR8854 C2 | H10: 169.89 | I10: =C10*H10 -> 0 | K10: ='Юнит 01-04.01'!K10+'Юнит 05-11.01'!K10+'Юнит 12-18.01'!K10+'Юнит 19-25.01'!K10+'Юнит 26-31.01'!K10 -> 5 | N10: =K10/7 -> 0.71428571 | O10: =R10/7 -> 0 | P10: ='Юнит 01-04.01'!P10+'Юнит 05-11.01'!P10+'Юнит 12-18.01'!P10+'Юнит 19-25.01'!P10+'Юнит 26-31.01'!P10 -> 0 | Q10: ='Юнит 01-04.01'!Q10+'Юнит 05-11.01'!Q10+'Юнит 12-18.01'!Q10+'Юнит 19-25.01'!Q10+'Юнит 26-31.01'!Q10 -> 0 | R10: =P10-Q10 -> 0 | S10: ='Юнит 01-04.01'!S10+'Юнит 05-11.01'!S10+'Юнит 12-18.01'!S10+'Юнит 19-25.01'!S10+'Юнит 26-31.01'!S10 -> 0 | T10: ='Юнит 01-04.01'!T10+'Юнит 05-11.01'!T10+'Юнит 12-18.01'!T10+'Юнит 19-25.01'!T10+'Юнит 26-31.01'!T10 -> 0 | U10: =S10+T10 -> 0 | V10: =U10/$U$49 -> 0 | W10: =R10*H10 -> 0 | X10: ='Юнит 01-04.01'!X10+'Юнит 05-11.01'!X10+'Юнит 12-18.01'!X10+'Юнит 19-25.01'!X10+'Юнит 26-31.01'!X10 -> 0 | Y10: =IF(U10=0,0,X10/U10) -> 0 | Z10: ='Юнит 01-04.01'!Z10+'Юнит 05-11.01'!Z10+'Юнит 12-18.01'!Z10+'Юнит 19-25.01'!Z10+'Юнит 26-31.01'!Z10 -> 280.62 | AA10: ='Юнит 01-04.01'!AA10+'Юнит 05-11.01'!AA10+'Юнит 12-18.01'!AA10+'Юнит 19-25.01'!AA10+'Юнит 26-31.01'!AA10 -> 0 | AD10: =U10*1% -> 0 | AE10: =U10-W10-X10-Z10-AA10-AB10-AC10-AD10 -> -280.62 | AG10: =IF(R10=0,0,U10/R10) -> 0 | AH10: =H10 -> 169.89 | AI10: =IF(R10=0,0,X10/R10) -> 0 | AJ10: =IF(P10=0,Z10/1,Z10/P10) -> 280.62 | AK10: =IF(P10=0,0,AA10/P10) -> 0 | AL10: {=_xlfn.IFS(R10=0,AE10,R10<0,AE10/-R10,R10>0,AE10/R10)} -> -280.62 | AM10: =IF(AG10=0,0,AL10/AG10) -> 0 | AN10: =IF(AH10=0,0,AL10/AH10) -> -1.6517747 | AP10: =AL10*C10 -> 0
A11: 2730130733 | B11: MR 1819 черн | H11: 169.89 | I11: =C11*H11 -> 0 | K11: ='Юнит 01-04.01'!K11+'Юнит 05-11.01'!K11+'Юнит 12-18.01'!K11+'Юнит 19-25.01'!K11+'Юнит 26-31.01'!K11 -> 1 | N11: =K11/7 -> 0.14285714 | O11: =R11/7 -> 0 | P11: ='Юнит 01-04.01'!P11+'Юнит 05-11.01'!P11+'Юнит 12-18.01'!P11+'Юнит 19-25.01'!P11+'Юнит 26-31.01'!P11 -> 0 | Q11: ='Юнит 01-04.01'!Q11+'Юнит 05-11.01'!Q11+'Юнит 12-18.01'!Q11+'Юнит 19-25.01'!Q11+'Юнит 26-31.01'!Q11 -> 0 | R11: =P11-Q11 -> 0 | S11: ='Юнит 01-04.01'!S11+'Юнит 05-11.01'!S11+'Юнит 12-18.01'!S11+'Юнит 19-25.01'!S11+'Юнит 26-31.01'!S11 -> 0 | T11: ='Юнит 01-04.01'!T11+'Юнит 05-11.01'!T11+'Юнит 12-18.01'!T11+'Юнит 19-25.01'!T11+'Юнит 26-31.01'!T11 -> 0 | U11: =S11+T11 -> 0 | V11: =U11/$U$49 -> 0 | W11: =R11*H11 -> 0 | X11: ='Юнит 01-04.01'!X11+'Юнит 05-11.01'!X11+'Юнит 12-18.01'!X11+'Юнит 19-25.01'!X11+'Юнит 26-31.01'!X11 -> 0 | Y11: =IF(U11=0,0,X11/U11) -> 0 | Z11: ='Юнит 01-04.01'!Z11+'Юнит 05-11.01'!Z11+'Юнит 12-18.01'!Z11+'Юнит 19-25.01'!Z11+'Юнит 26-31.01'!Z11 -> 93.54 | AA11: ='Юнит 01-04.01'!AA11+'Юнит 05-11.01'!AA11+'Юнит 12-18.01'!AA11+'Юнит 19-25.01'!AA11+'Юнит 26-31.01'!AA11 -> 0 | AD11: =U11*1% -> 0 | AE11: =U11-W11-X11-Z11-AA11-AB11-AC11-AD11 -> -93.54 | AG11: =IF(R11=0,0,U11/R11) -> 0 | AH11: =H11 -> 169.89 | AI11: =IF(R11=0,0,X11/R11) -> 0 | AJ11: =IF(P11=0,Z11/1,Z11/P11) -> 93.54 | AK11: =IF(P11=0,0,AA11/P11) -> 0 | AL11: {=_xlfn.IFS(R11=0,AE11,R11<0,AE11/-R11,R11>0,AE11/R11)} -> -93.54 | AM11: =IF(AG11=0,0,AL11/AG11) -> 0 | AN11: =IF(AH11=0,0,AL11/AH11) -> -0.55059156 | AP11: =AL11*C11 -> 0
A12: 2730131249 | B12: MR 1819 корич | H12: 169.89 | I12: =C12*H12 -> 0 | K12: ='Юнит 01-04.01'!K12+'Юнит 05-11.01'!K12+'Юнит 12-18.01'!K12+'Юнит 19-25.01'!K12+'Юнит 26-31.01'!K12 -> 3 | N12: =K12/7 -> 0.42857143 | O12: =R12/7 -> 0.42857143 | P12: ='Юнит 01-04.01'!P12+'Юнит 05-11.01'!P12+'Юнит 12-18.01'!P12+'Юнит 19-25.01'!P12+'Юнит 26-31.01'!P12 -> 3 | Q12: ='Юнит 01-04.01'!Q12+'Юнит 05-11.01'!Q12+'Юнит 12-18.01'!Q12+'Юнит 19-25.01'!Q12+'Юнит 26-31.01'!Q12 -> 0 | R12: =P12-Q12 -> 3 | S12: ='Юнит 01-04.01'!S12+'Юнит 05-11.01'!S12+'Юнит 12-18.01'!S12+'Юнит 19-25.01'!S12+'Юнит 26-31.01'!S12 -> 3282 | T12: ='Юнит 01-04.01'!T12+'Юнит 05-11.01'!T12+'Юнит 12-18.01'!T12+'Юнит 19-25.01'!T12+'Юнит 26-31.01'!T12 -> 0 | U12: =S12+T12 -> 3282 | V12: =U12/$U$49 -> 0.033397102 | W12: =R12*H12 -> 509.67 | X12: ='Юнит 01-04.01'!X12+'Юнит 05-11.01'!X12+'Юнит 12-18.01'!X12+'Юнит 19-25.01'!X12+'Юнит 26-31.01'!X12 -> 1411.26 | Y12: =IF(U12=0,0,X12/U12) -> 0.43 | Z12: ='Юнит 01-04.01'!Z12+'Юнит 05-11.01'!Z12+'Юнит 12-18.01'!Z12+'Юнит 19-25.01'!Z12+'Юнит 26-31.01'!Z12 -> 307.87 | AA12: ='Юнит 01-04.01'!AA12+'Юнит 05-11.01'!AA12+'Юнит 12-18.01'!AA12+'Юнит 19-25.01'!AA12+'Юнит 26-31.01'!AA12 -> 0 | AD12: =U12*1% -> 32.82 | AE12: =U12-W12-X12-Z12-AA12-AB12-AC12-AD12 -> 1020.38 | AG12: =IF(R12=0,0,U12/R12) -> 1094 | AH12: =H12 -> 169.89 | AI12: =IF(R12=0,0,X12/R12) -> 470.42 | AJ12: =IF(P12=0,Z12/1,Z12/P12) -> 102.62333 | AK12: =IF(P12=0,0,AA12/P12) -> 0 | AL12: {=_xlfn.IFS(R12=0,AE12,R12<0,AE12/-R12,R12>0,AE12/R12)} -> 340.12667 | AM12: =IF(AG12=0,0,AL12/AG12) -> 0.31090189 | AN12: =IF(AH12=0,0,AL12/AH12) -> 2.0020405 | AP12: =AL12*C12 -> 0
A13: 2730130553 | B13: MR Р1874 черн | H13: 169.89 | I13: =C13*H13 -> 0 | K13: ='Юнит 01-04.01'!K13+'Юнит 05-11.01'!K13+'Юнит 12-18.01'!K13+'Юнит 19-25.01'!K13+'Юнит 26-31.01'!K13 -> 7 | N13: =K13/7 -> 1 | O13: =R13/7 -> 0.57142857 | P13: ='Юнит 01-04.01'!P13+'Юнит 05-11.01'!P13+'Юнит 12-18.01'!P13+'Юнит 19-25.01'!P13+'Юнит 26-31.01'!P13 -> 4 | Q13: ='Юнит 01-04.01'!Q13+'Юнит 05-11.01'!Q13+'Юнит 12-18.01'!Q13+'Юнит 19-25.01'!Q13+'Юнит 26-31.01'!Q13 -> 0 | R13: =P13-Q13 -> 4 | S13: ='Юнит 01-04.01'!S13+'Юнит 05-11.01'!S13+'Юнит 12-18.01'!S13+'Юнит 19-25.01'!S13+'Юнит 26-31.01'!S13 -> 5520 | T13: ='Юнит 01-04.01'!T13+'Юнит 05-11.01'!T13+'Юнит 12-18.01'!T13+'Юнит 19-25.01'!T13+'Юнит 26-31.01'!T13 -> 0 | U13: =S13+T13 -> 5520 | V13: =U13/$U$49 -> 0.056170628 | W13: =R13*H13 -> 679.56 | X13: ='Юнит 01-04.01'!X13+'Юнит 05-11.01'!X13+'Юнит 12-18.01'!X13+'Юнит 19-25.01'!X13+'Юнит 26-31.01'!X13 -> 2373.6 | Y13: =IF(U13=0,0,X13/U13) -> 0.43 | Z13: ='Юнит 01-04.01'!Z13+'Юнит 05-11.01'!Z13+'Юнит 12-18.01'!Z13+'Юнит 19-25.01'!Z13+'Юнит 26-31.01'!Z13 -> 885.38 | AA13: ='Юнит 01-04.01'!AA13+'Юнит 05-11.01'!AA13+'Юнит 12-18.01'!AA13+'Юнит 19-25.01'!AA13+'Юнит 26-31.01'!AA13 -> 795.8 | AD13: =U13*1% -> 55.2 | AE13: =U13-W13-X13-Z13-AA13-AB13-AC13-AD13 -> 730.46 | AG13: =IF(R13=0,0,U13/R13) -> 1380 | AH13: =H13 -> 169.89 | AI13: =IF(R13=0,0,X13/R13) -> 593.4 | AJ13: =IF(P13=0,Z13/1,Z13/P13) -> 221.345 | AK13: =IF(P13=0,0,AA13/P13) -> 198.95 | AL13: {=_xlfn.IFS(R13=0,AE13,R13<0,AE13/-R13,R13>0,AE13/R13)} -> 182.615 | AM13: =IF(AG13=0,0,AL13/AG13) -> 0.13232971 | AN13: =IF(AH13=0,0,AL13/AH13) -> 1.0749014 | AP13: =AL13*C13 -> 0
A14: 2730129638 | B14: MR Р1874 корич | H14: 169.89 | I14: =C14*H14 -> 0 | K14: ='Юнит 01-04.01'!K14+'Юнит 05-11.01'!K14+'Юнит 12-18.01'!K14+'Юнит 19-25.01'!K14+'Юнит 26-31.01'!K14 -> 3 | N14: =K14/7 -> 0.42857143 | O14: =R14/7 -> 0.28571429 | P14: ='Юнит 01-04.01'!P14+'Юнит 05-11.01'!P14+'Юнит 12-18.01'!P14+'Юнит 19-25.01'!P14+'Юнит 26-31.01'!P14 -> 2 | Q14: ='Юнит 01-04.01'!Q14+'Юнит 05-11.01'!Q14+'Юнит 12-18.01'!Q14+'Юнит 19-25.01'!Q14+'Юнит 26-31.01'!Q14 -> 0 | R14: =P14-Q14 -> 2 | S14: ='Юнит 01-04.01'!S14+'Юнит 05-11.01'!S14+'Юнит 12-18.01'!S14+'Юнит 19-25.01'!S14+'Юнит 26-31.01'!S14 -> 2858 | T14: ='Юнит 01-04.01'!T14+'Юнит 05-11.01'!T14+'Юнит 12-18.01'!T14+'Юнит 19-25.01'!T14+'Юнит 26-31.01'!T14 -> 0 | U14: =S14+T14 -> 2858 | V14: =U14/$U$49 -> 0.029082546 | W14: =R14*H14 -> 339.78 | X14: ='Юнит 01-04.01'!X14+'Юнит 05-11.01'!X14+'Юнит 12-18.01'!X14+'Юнит 19-25.01'!X14+'Юнит 26-31.01'!X14 -> 1228.94 | Y14: =IF(U14=0,0,X14/U14) -> 0.43 | Z14: ='Юнит 01-04.01'!Z14+'Юнит 05-11.01'!Z14+'Юнит 12-18.01'!Z14+'Юнит 19-25.01'!Z14+'Юнит 26-31.01'!Z14 -> 238.25 | AA14: ='Юнит 01-04.01'!AA14+'Юнит 05-11.01'!AA14+'Юнит 12-18.01'!AA14+'Юнит 19-25.01'!AA14+'Юнит 26-31.01'!AA14 -> 250.7 | AD14: =U14*1% -> 28.58 | AE14: =U14-W14-X14-Z14-AA14-AB14-AC14-AD14 -> 771.75 | AG14: =IF(R14=0,0,U14/R14) -> 1429 | AH14: =H14 -> 169.89 | AI14: =IF(R14=0,0,X14/R14) -> 614.47 | AJ14: =IF(P14=0,Z14/1,Z14/P14) -> 119.125 | AK14: =IF(P14=0,0,AA14/P14) -> 125.35 | AL14: {=_xlfn.IFS(R14=0,AE14,R14<0,AE14/-R14,R14>0,AE14/R14)} -> 385.875 | AM14: =IF(AG14=0,0,AL14/AG14) -> 0.27003149 | AN14: =IF(AH14=0,0,AL14/AH14) -> 2.2713226 | AP14: =AL14*C14 -> 0
A15: 2730130141 | B15: MR Р1886 черн глянец | H15: 169.89 | I15: =C15*H15 -> 0 | K15: ='Юнит 01-04.01'!K15+'Юнит 05-11.01'!K15+'Юнит 12-18.01'!K15+'Юнит 19-25.01'!K15+'Юнит 26-31.01'!K15 -> 4 | N15: =K15/7 -> 0.57142857 | O15: =R15/7 -> 0.28571429 | P15: ='Юнит 01-04.01'!P15+'Юнит 05-11.01'!P15+'Юнит 12-18.01'!P15+'Юнит 19-25.01'!P15+'Юнит 26-31.01'!P15 -> 2 | Q15: ='Юнит 01-04.01'!Q15+'Юнит 05-11.01'!Q15+'Юнит 12-18.01'!Q15+'Юнит 19-25.01'!Q15+'Юнит 26-31.01'!Q15 -> 0 | R15: =P15-Q15 -> 2 | S15: ='Юнит 01-04.01'!S15+'Юнит 05-11.01'!S15+'Юнит 12-18.01'!S15+'Юнит 19-25.01'!S15+'Юнит 26-31.01'!S15 -> 2670 | T15: ='Юнит 01-04.01'!T15+'Юнит 05-11.01'!T15+'Юнит 12-18.01'!T15+'Юнит 19-25.01'!T15+'Юнит 26-31.01'!T15 -> 0 | U15: =S15+T15 -> 2670 | V15: =U15/$U$49 -> 0.027169489 | W15: =R15*H15 -> 339.78 | X15: ='Юнит 01-04.01'!X15+'Юнит 05-11.01'!X15+'Юнит 12-18.01'!X15+'Юнит 19-25.01'!X15+'Юнит 26-31.01'!X15 -> 1148.1 | Y15: =IF(U15=0,0,X15/U15) -> 0.43 | Z15: ='Юнит 01-04.01'!Z15+'Юнит 05-11.01'!Z15+'Юнит 12-18.01'!Z15+'Юнит 19-25.01'!Z15+'Юнит 26-31.01'!Z15 -> 489.96 | AA15: ='Юнит 01-04.01'!AA15+'Юнит 05-11.01'!AA15+'Юнит 12-18.01'!AA15+'Юнит 19-25.01'!AA15+'Юнит 26-31.01'!AA15 -> 921.61 | AD15: =U15*1% -> 26.7 | AE15: =U15-W15-X15-Z15-AA15-AB15-AC15-AD15 -> -256.15 | AG15: =IF(R15=0,0,U15/R15) -> 1335 | AH15: =H15 -> 169.89 | AI15: =IF(R15=0,0,X15/R15) -> 574.05 | AJ15: =IF(P15=0,Z15/1,Z15/P15) -> 244.98 | AK15: =IF(P15=0,0,AA15/P15) -> 460.805 | AL15: {=_xlfn.IFS(R15=0,AE15,R15<0,AE15/-R15,R15>0,AE15/R15)} -> -128.075 | AM15: =IF(AG15=0,0,AL15/AG15) -> -0.09593633 | AN15: =IF(AH15=0,0,AL15/AH15) -> -0.75387015 | AP15: =AL15*C15 -> 0
... A24: 2807226146 | B24: lux8 | H24: 991.12 | I24: =C24*H24 -> 0 | K24: ='Юнит 01-04.01'!K24+'Юнит 05-11.01'!K24+'Юнит 12-18.01'!K24+'Юнит 19-25.01'!K24+'Юнит 26-31.01'!K24 -> 0 | N24: =K24/7 -> 0 | O24: =R24/7 -> 0 | P24: ='Юнит 01-04.01'!P24+'Юнит 05-11.01'!P24+'Юнит 12-18.01'!P24+'Юнит 19-25.01'!P24+'Юнит 26-31.01'!P24 -> 0 | Q24: ='Юнит 01-04.01'!Q24+'Юнит 05-11.01'!Q24+'Юнит 12-18.01'!Q24+'Юнит 19-25.01'!Q24+'Юнит 26-31.01'!Q24 -> 0 | R24: =P24-Q24 -> 0 | S24: ='Юнит 01-04.01'!S24+'Юнит 05-11.01'!S24+'Юнит 12-18.01'!S24+'Юнит 19-25.01'!S24+'Юнит 26-31.01'!S24 -> 0 | T24: ='Юнит 01-04.01'!T24+'Юнит 05-11.01'!T24+'Юнит 12-18.01'!T24+'Юнит 19-25.01'!T24+'Юнит 26-31.01'!T24 -> 0 | U24: =S24+T24 -> 0 | V24: =U24/$U$49 -> 0 | W24: =R24*H24 -> 0 | X24: ='Юнит 01-04.01'!X24+'Юнит 05-11.01'!X24+'Юнит 12-18.01'!X24+'Юнит 19-25.01'!X24+'Юнит 26-31.01'!X24 -> 0 | Y24: =IF(U24=0,0,X24/U24) -> 0 | Z24: ='Юнит 01-04.01'!Z24+'Юнит 05-11.01'!Z24+'Юнит 12-18.01'!Z24+'Юнит 19-25.01'!Z24+'Юнит 26-31.01'!Z24 -> 0 | AA24: ='Юнит 01-04.01'!AA24+'Юнит 05-11.01'!AA24+'Юнит 12-18.01'!AA24+'Юнит 19-25.01'!AA24+'Юнит 26-31.01'!AA24 -> 0 | AD24: =U24*1% -> 0 | AE24: =U24-W24-X24-Z24-AA24-AB24-AC24-AD24 -> 0 | AG24: =IF(R24=0,0,U24/R24) -> 0 | AH24: =H24 -> 991.12 | AI24: =IF(R24=0,0,X24/R24) -> 0 | AJ24: =IF(P24=0,Z24/1,Z24/P24) -> 0 | AK24: =IF(P24=0,0,AA24/P24) -> 0 | AL24: {=_xlfn.IFS(R24=0,AE24,R24<0,AE24/-R24,R24>0,AE24/R24)} -> 0 | AM24: =IF(AG24=0,0,AL24/AG24) -> 0 | AN24: =IF(AH24=0,0,AL24/AH24) -> 0 | AP24: =AL24*C24 -> 0
AG25: =AVERAGEIF(AG3:AG24,"<>0",AG3:AG24) -> 1867.9414 | AH25: =AVERAGEIF(AH3:AH24,"<>0",AH3:AH24) -> 447.87636 | AI25: =AVERAGEIF(AI3:AI24,"<>0",AI3:AI24) -> 803.21481 | AJ25: =AVERAGEIF(AJ3:AJ24,"<>0",AJ3:AJ24) -> 173.78285 | AK25: =AVERAGEIF(AK3:AK24,"<>0",AK3:AK24) -> 372.11608 | AL25: =AVERAGEIF(AL3:AL24,"<>0",AL3:AL24) -> 307.09169 | AM25: =AVERAGEIF(AM3:AM24,"<>0",AM3:AM24) -> 0.18325533 | AN25: =AVERAGEIF(AN3:AN24,"<>0",AN3:AN24) -> 1.2695949
A26: Итого очки | C26: =SUM(C3:C24) -> 0 | E26: 108496 | F26: 597 | G26: 295 | I26: =SUM(I3:I24) -> 0 | K26: =SUM(K3:K24) -> 333 | P26: =SUM(P3:P24) -> 206 | Q26: =SUM(Q3:Q24) -> 5 | R26: =SUM(R3:R24) -> 201 | S26: =SUM(S3:S24) -> 334486 | T26: =SUM(T3:T24) -> -8469 | U26: =SUM(U3:U24) -> 326017 | V26: =SUM(V3:V24) -> 3.3174963 | W26: =SUM(W3:W24) -> 29517.35 | X26: =SUM(X3:X24) -> 140187.31 | Y26: =IF(U26=0,0,X26/U26) -> 0.43 | Z26: =SUM(Z3:Z24) -> 36341.38 | AA26: =SUM(AA3:AA24) -> 76532.631 | AB26: =SUM(AB3:AB24) -> 0 | AC26: =SUM(AC3:AC24) -> 0 | AD26: =SUM(AD3:AD24) -> 3260.17 | AE26: =SUM(AE3:AE24) -> 40178.159 | AP26: =SUM(AP3:AP24) -> 0 | AZ26: 18592777
AA27: ='Юнит 01-04.01'!AA27+'Юнит 05-11.01'!AA27+'Юнит 12-18.01'!AA27+'Юнит 19-25.01'!AA27+'Юнит 26-31.01'!AA27 -> 76532.631
A28: 2774708536 | B28: tunika02 оливковая с руч вышивкой | H28: 672 | I28: =C28*H28 -> 0 | K28: ='Юнит 01-04.01'!K28+'Юнит 05-11.01'!K28+'Юнит 12-18.01'!K28+'Юнит 19-25.01'!K28+'Юнит 26-31.01'!K28 -> 2 | N28: =K28/7 -> 0.28571429 | O28: =R28/7 -> 0 | P28: ='Юнит 01-04.01'!P28+'Юнит 05-11.01'!P28+'Юнит 12-18.01'!P28+'Юнит 19-25.01'!P28+'Юнит 26-31.01'!P28 -> 0 | Q28: ='Юнит 01-04.01'!Q28+'Юнит 05-11.01'!Q28+'Юнит 12-18.01'!Q28+'Юнит 19-25.01'!Q28+'Юнит 26-31.01'!Q28 -> 0 | R28: =P28-Q28 -> 0 | S28: ='Юнит 01-04.01'!S28+'Юнит 05-11.01'!S28+'Юнит 12-18.01'!S28+'Юнит 19-25.01'!S28+'Юнит 26-31.01'!S28 -> 0 | T28: ='Юнит 01-04.01'!T28+'Юнит 05-11.01'!T28+'Юнит 12-18.01'!T28+'Юнит 19-25.01'!T28+'Юнит 26-31.01'!T28 -> 0 | U28: =S28+T28 -> 0 | V28: =U28/$U$49 -> 0 | W28: =R28*H28 -> 0 | X28: ='Юнит 01-04.01'!X28+'Юнит 05-11.01'!X28+'Юнит 12-18.01'!X28+'Юнит 19-25.01'!X28+'Юнит 26-31.01'!X28 -> 0 | Y28: =IF(U28=0,0,X28/U28) -> 0 | Z28: ='Юнит 01-04.01'!Z28+'Юнит 05-11.01'!Z28+'Юнит 12-18.01'!Z28+'Юнит 19-25.01'!Z28+'Юнит 26-31.01'!Z28 -> 0 | AA28: ='Юнит 01-04.01'!AA28+'Юнит 05-11.01'!AA28+'Юнит 12-18.01'!AA28+'Юнит 19-25.01'!AA28+'Юнит 26-31.01'!AA28 -> 537.70695 | AD28: =U28*1% -> 0 | AE28: =U28-W28-X28-Z28-AA28-AB28-AC28-AD28 -> -537.70695 | AG28: =IF(R28=0,0,U28/R28) -> 0 | AH28: =H28 -> 672 | AI28: =IF(R28=0,0,X28/R28) -> 0 | AJ28: =IF(P28=0,Z28/1,Z28/P28) -> 0 | AK28: =IF(P28=0,0,AA28/P28) -> 0 | AL28: {=_xlfn.IFS(R28=0,AE28,R28<0,AE28/-R28,R28>0,AE28/R28)} -> -537.70695 | AM28: =IF(AG28=0,0,AL28/AG28) -> 0 | AN28: =IF(AH28=0,0,AL28/AH28) -> -0.80015915 | AP28: =AL28*C28 -> 0
A29: 2774708622 | B29: tunika03 черная распашная | H29: 627 | I29: =C29*H29 -> 0 | K29: ='Юнит 01-04.01'!K29+'Юнит 05-11.01'!K29+'Юнит 12-18.01'!K29+'Юнит 19-25.01'!K29+'Юнит 26-31.01'!K29 -> 1 | N29: =K29/7 -> 0.14285714 | O29: =R29/7 -> 0 | P29: ='Юнит 01-04.01'!P29+'Юнит 05-11.01'!P29+'Юнит 12-18.01'!P29+'Юнит 19-25.01'!P29+'Юнит 26-31.01'!P29 -> 0 | Q29: ='Юнит 01-04.01'!Q29+'Юнит 05-11.01'!Q29+'Юнит 12-18.01'!Q29+'Юнит 19-25.01'!Q29+'Юнит 26-31.01'!Q29 -> 0 | R29: =P29-Q29 -> 0 | S29: ='Юнит 01-04.01'!S29+'Юнит 05-11.01'!S29+'Юнит 12-18.01'!S29+'Юнит 19-25.01'!S29+'Юнит 26-31.01'!S29 -> 0 | T29: ='Юнит 01-04.01'!T29+'Юнит 05-11.01'!T29+'Юнит 12-18.01'!T29+'Юнит 19-25.01'!T29+'Юнит 26-31.01'!T29 -> 0 | U29: =S29+T29 -> 0 | V29: =U29/$U$49 -> 0 | W29: =R29*H29 -> 0 | X29: ='Юнит 01-04.01'!X29+'Юнит 05-11.01'!X29+'Юнит 12-18.01'!X29+'Юнит 19-25.01'!X29+'Юнит 26-31.01'!X29 -> 0 | Y29: =IF(U29=0,0,X29/U29) -> 0 | Z29: ='Юнит 01-04.01'!Z29+'Юнит 05-11.01'!Z29+'Юнит 12-18.01'!Z29+'Юнит 19-25.01'!Z29+'Юнит 26-31.01'!Z29 -> 0 | AA29: ='Юнит 01-04.01'!AA29+'Юнит 05-11.01'!AA29+'Юнит 12-18.01'!AA29+'Юнит 19-25.01'!AA29+'Юнит 26-31.01'!AA29 -> 0 | AD29: =U29*1% -> 0 | AE29: =U29-W29-X29-Z29-AA29-AB29-AC29-AD29 -> 0 | AG29: =IF(R29=0,0,U29/R29) -> 0 | AH29: =H29 -> 627 | AI29: =IF(R29=0,0,X29/R29) -> 0 | AJ29: =IF(P29=0,Z29/1,Z29/P29) -> 0 | AK29: =IF(P29=0,0,AA29/P29) -> 0 | AL29: {=_xlfn.IFS(R29=0,AE29,R29<0,AE29/-R29,R29>0,AE29/R29)} -> 0 | AM29: =IF(AG29=0,0,AL29/AG29) -> 0 | AN29: =IF(AH29=0,0,AL29/AH29) -> 0 | AP29: =AL29*C29 -> 0
A30: 2774709606 | B30: tunika05 белая распашная | H30: 627 | I30: =C30*H30 -> 0 | K30: ='Юнит 01-04.01'!K30+'Юнит 05-11.01'!K30+'Юнит 12-18.01'!K30+'Юнит 19-25.01'!K30+'Юнит 26-31.01'!K30 -> 1 | N30: =K30/7 -> 0.14285714 | O30: =R30/7 -> 0 | P30: ='Юнит 01-04.01'!P30+'Юнит 05-11.01'!P30+'Юнит 12-18.01'!P30+'Юнит 19-25.01'!P30+'Юнит 26-31.01'!P30 -> 0 | Q30: ='Юнит 01-04.01'!Q30+'Юнит 05-11.01'!Q30+'Юнит 12-18.01'!Q30+'Юнит 19-25.01'!Q30+'Юнит 26-31.01'!Q30 -> 0 | R30: =P30-Q30 -> 0 | S30: ='Юнит 01-04.01'!S30+'Юнит 05-11.01'!S30+'Юнит 12-18.01'!S30+'Юнит 19-25.01'!S30+'Юнит 26-31.01'!S30 -> 0 | T30: ='Юнит 01-04.01'!T30+'Юнит 05-11.01'!T30+'Юнит 12-18.01'!T30+'Юнит 19-25.01'!T30+'Юнит 26-31.01'!T30 -> 0 | U30: =S30+T30 -> 0 | V30: =U30/$U$49 -> 0 | W30: =R30*H30 -> 0 | X30: ='Юнит 01-04.01'!X30+'Юнит 05-11.01'!X30+'Юнит 12-18.01'!X30+'Юнит 19-25.01'!X30+'Юнит 26-31.01'!X30 -> 0 | Y30: =IF(U30=0,0,X30/U30) -> 0 | Z30: ='Юнит 01-04.01'!Z30+'Юнит 05-11.01'!Z30+'Юнит 12-18.01'!Z30+'Юнит 19-25.01'!Z30+'Юнит 26-31.01'!Z30 -> 0 | AA30: ='Юнит 01-04.01'!AA30+'Юнит 05-11.01'!AA30+'Юнит 12-18.01'!AA30+'Юнит 19-25.01'!AA30+'Юнит 26-31.01'!AA30 -> 0 | AD30: =U30*1% -> 0 | AE30: =U30-W30-X30-Z30-AA30-AB30-AC30-AD30 -> 0 | AG30: =IF(R30=0,0,U30/R30) -> 0 | AH30: =H30 -> 627 | AI30: =IF(R30=0,0,X30/R30) -> 0 | AJ30: =IF(P30=0,Z30/1,Z30/P30) -> 0 | AK30: =IF(P30=0,0,AA30/P30) -> 0 | AL30: {=_xlfn.IFS(R30=0,AE30,R30<0,AE30/-R30,R30>0,AE30/R30)} -> 0 | AM30: =IF(AG30=0,0,AL30/AG30) -> 0 | AN30: =IF(AH30=0,0,AL30/AH30) -> 0 | AP30: =AL30*C30 -> 0
A31: 2774720465 | B31: tunika06 белая | H31: 567 | I31: =C31*H31 -> 0 | K31: ='Юнит 01-04.01'!K31+'Юнит 05-11.01'!K31+'Юнит 12-18.01'!K31+'Юнит 19-25.01'!K31+'Юнит 26-31.01'!K31 -> 1 | N31: =K31/7 -> 0.14285714 | O31: =R31/7 -> 0.14285714 | P31: ='Юнит 01-04.01'!P31+'Юнит 05-11.01'!P31+'Юнит 12-18.01'!P31+'Юнит 19-25.01'!P31+'Юнит 26-31.01'!P31 -> 1 | Q31: ='Юнит 01-04.01'!Q31+'Юнит 05-11.01'!Q31+'Юнит 12-18.01'!Q31+'Юнит 19-25.01'!Q31+'Юнит 26-31.01'!Q31 -> 0 | R31: =P31-Q31 -> 1 | S31: ='Юнит 01-04.01'!S31+'Юнит 05-11.01'!S31+'Юнит 12-18.01'!S31+'Юнит 19-25.01'!S31+'Юнит 26-31.01'!S31 -> 3649 | T31: ='Юнит 01-04.01'!T31+'Юнит 05-11.01'!T31+'Юнит 12-18.01'!T31+'Юнит 19-25.01'!T31+'Юнит 26-31.01'!T31 -> 0 | U31: =S31+T31 -> 3649 | V31: =U31/$U$49 -> 0.037131635 | W31: =R31*H31 -> 567 | X31: ='Юнит 01-04.01'!X31+'Юнит 05-11.01'!X31+'Юнит 12-18.01'!X31+'Юнит 19-25.01'!X31+'Юнит 26-31.01'!X31 -> 1569.07 | Y31: =IF(U31=0,0,X31/U31) -> 0.43 | Z31: ='Юнит 01-04.01'!Z31+'Юнит 05-11.01'!Z31+'Юнит 12-18.01'!Z31+'Юнит 19-25.01'!Z31+'Юнит 26-31.01'!Z31 -> 242.23 | AA31: ='Юнит 01-04.01'!AA31+'Юнит 05-11.01'!AA31+'Юнит 12-18.01'!AA31+'Юнит 19-25.01'!AA31+'Юнит 26-31.01'!AA31 -> 0 | AD31: =U31*1% -> 36.49 | AE31: =U31-W31-X31-Z31-AA31-AB31-AC31-AD31 -> 1234.21 | AG31: =IF(R31=0,0,U31/R31) -> 3649 | AH31: =H31 -> 567 | AI31: =IF(R31=0,0,X31/R31) -> 1569.07 | AJ31: =IF(P31=0,Z31/1,Z31/P31) -> 242.23 | AK31: =IF(P31=0,0,AA31/P31) -> 0 | AL31: {=_xlfn.IFS(R31=0,AE31,R31<0,AE31/-R31,R31>0,AE31/R31)} -> 1234.21 | AM31: =IF(AG31=0,0,AL31/AG31) -> 0.33823239 | AN31: =IF(AH31=0,0,AL31/AH31) -> 2.1767372 | AP31: =AL31*C31 -> 0
A32: 2774718470 | B32: tunika06 черная | H32: 567 | I32: =C32*H32 -> 0 | K32: ='Юнит 01-04.01'!K32+'Юнит 05-11.01'!K32+'Юнит 12-18.01'!K32+'Юнит 19-25.01'!K32+'Юнит 26-31.01'!K32 -> 0 | N32: =K32/7 -> 0 | O32: =R32/7 -> 0 | P32: ='Юнит 01-04.01'!P32+'Юнит 05-11.01'!P32+'Юнит 12-18.01'!P32+'Юнит 19-25.01'!P32+'Юнит 26-31.01'!P32 -> 0 | Q32: ='Юнит 01-04.01'!Q32+'Юнит 05-11.01'!Q32+'Юнит 12-18.01'!Q32+'Юнит 19-25.01'!Q32+'Юнит 26-31.01'!Q32 -> 0 | R32: =P32-Q32 -> 0 | S32: ='Юнит 01-04.01'!S32+'Юнит 05-11.01'!S32+'Юнит 12-18.01'!S32+'Юнит 19-25.01'!S32+'Юнит 26-31.01'!S32 -> 0 | T32: ='Юнит 01-04.01'!T32+'Юнит 05-11.01'!T32+'Юнит 12-18.01'!T32+'Юнит 19-25.01'!T32+'Юнит 26-31.01'!T32 -> 0 | U32: =S32+T32 -> 0 | V32: =U32/$U$49 -> 0 | W32: =R32*H32 -> 0 | X32: ='Юнит 01-04.01'!X32+'Юнит 05-11.01'!X32+'Юнит 12-18.01'!X32+'Юнит 19-25.01'!X32+'Юнит 26-31.01'!X32 -> 0 | Y32: =IF(U32=0,0,X32/U32) -> 0 | Z32: ='Юнит 01-04.01'!Z32+'Юнит 05-11.01'!Z32+'Юнит 12-18.01'!Z32+'Юнит 19-25.01'!Z32+'Юнит 26-31.01'!Z32 -> 0 | AA32: ='Юнит 01-04.01'!AA32+'Юнит 05-11.01'!AA32+'Юнит 12-18.01'!AA32+'Юнит 19-25.01'!AA32+'Юнит 26-31.01'!AA32 -> 0 | AD32: =U32*1% -> 0 | AE32: =U32-W32-X32-Z32-AA32-AB32-AC32-AD32 -> 0 | AG32: =IF(R32=0,0,U32/R32) -> 0 | AH32: =H32 -> 567 | AI32: =IF(R32=0,0,X32/R32) -> 0 | AJ32: =IF(P32=0,Z32/1,Z32/P32) -> 0 | AK32: =IF(P32=0,0,AA32/P32) -> 0 | AL32: {=_xlfn.IFS(R32=0,AE32,R32<0,AE32/-R32,R32>0,AE32/R32)} -> 0 | AM32: =IF(AG32=0,0,AL32/AG32) -> 0 | AN32: =IF(AH32=0,0,AL32/AH32) -> 0 | AP32: =AL32*C32 -> 0
A33: 2774719022 | B33: tunika07 кружево | H33: 657 | I33: =C33*H33 -> 0 | K33: ='Юнит 01-04.01'!K33+'Юнит 05-11.01'!K33+'Юнит 12-18.01'!K33+'Юнит 19-25.01'!K33+'Юнит 26-31.01'!K33 -> 1 | N33: =K33/7 -> 0.14285714 | O33: =R33/7 -> 0.14285714 | P33: ='Юнит 01-04.01'!P33+'Юнит 05-11.01'!P33+'Юнит 12-18.01'!P33+'Юнит 19-25.01'!P33+'Юнит 26-31.01'!P33 -> 1 | Q33: ='Юнит 01-04.01'!Q33+'Юнит 05-11.01'!Q33+'Юнит 12-18.01'!Q33+'Юнит 19-25.01'!Q33+'Юнит 26-31.01'!Q33 -> 0 | R33: =P33-Q33 -> 1 | S33: ='Юнит 01-04.01'!S33+'Юнит 05-11.01'!S33+'Юнит 12-18.01'!S33+'Юнит 19-25.01'!S33+'Юнит 26-31.01'!S33 -> 3080 | T33: ='Юнит 01-04.01'!T33+'Юнит 05-11.01'!T33+'Юнит 12-18.01'!T33+'Юнит 19-25.01'!T33+'Юнит 26-31.01'!T33 -> 0 | U33: =S33+T33 -> 3080 | V33: =U33/$U$49 -> 0.031341583 | W33: =R33*H33 -> 657 | X33: ='Юнит 01-04.01'!X33+'Юнит 05-11.01'!X33+'Юнит 12-18.01'!X33+'Юнит 19-25.01'!X33+'Юнит 26-31.01'!X33 -> 1324.4 | Y33: =IF(U33=0,0,X33/U33) -> 0.43 | Z33: ='Юнит 01-04.01'!Z33+'Юнит 05-11.01'!Z33+'Юнит 12-18.01'!Z33+'Юнит 19-25.01'!Z33+'Юнит 26-31.01'!Z33 -> 219.36 | AA33: ='Юнит 01-04.01'!AA33+'Юнит 05-11.01'!AA33+'Юнит 12-18.01'!AA33+'Юнит 19-25.01'!AA33+'Юнит 26-31.01'!AA33 -> 0 | AD33: =U33*1% -> 30.8 | AE33: =U33-W33-X33-Z33-AA33-AB33-AC33-AD33 -> 848.44 | AG33: =IF(R33=0,0,U33/R33) -> 3080 | AH33: =H33 -> 657 | AI33: =IF(R33=0,0,X33/R33) -> 1324.4 | AJ33: =IF(P33=0,Z33/1,Z33/P33) -> 219.36 | AK33: =IF(P33=0,0,AA33/P33) -> 0 | AL33: {=_xlfn.IFS(R33=0,AE33,R33<0,AE33/-R33,R33>0,AE33/R33)} -> 848.44 | AM33: =IF(AG33=0,0,AL33/AG33) -> 0.27546753 | AN33: =IF(AH33=0,0,AL33/AH33) -> 1.2913851 | AP33: =AL33*C33 -> 0
A34: 2774719501 | B34: tunika08 белая | H34: 597 | I34: =C34*H34 -> 0 | K34: ='Юнит 01-04.01'!K34+'Юнит 05-11.01'!K34+'Юнит 12-18.01'!K34+'Юнит 19-25.01'!K34+'Юнит 26-31.01'!K34 -> 1 | N34: =K34/7 -> 0.14285714 | O34: =R34/7 -> 0.14285714 | P34: ='Юнит 01-04.01'!P34+'Юнит 05-11.01'!P34+'Юнит 12-18.01'!P34+'Юнит 19-25.01'!P34+'Юнит 26-31.01'!P34 -> 1 | Q34: ='Юнит 01-04.01'!Q34+'Юнит 05-11.01'!Q34+'Юнит 12-18.01'!Q34+'Юнит 19-25.01'!Q34+'Юнит 26-31.01'!Q34 -> 0 | R34: =P34-Q34 -> 1 | S34: ='Юнит 01-04.01'!S34+'Юнит 05-11.01'!S34+'Юнит 12-18.01'!S34+'Юнит 19-25.01'!S34+'Юнит 26-31.01'!S34 -> 4247 | T34: ='Юнит 01-04.01'!T34+'Юнит 05-11.01'!T34+'Юнит 12-18.01'!T34+'Юнит 19-25.01'!T34+'Юнит 26-31.01'!T34 -> 0 | U34: =S34+T34 -> 4247 | V34: =U34/$U$49 -> 0.043216786 | W34: =R34*H34 -> 597 | X34: ='Юнит 01-04.01'!X34+'Юнит 05-11.01'!X34+'Юнит 12-18.01'!X34+'Юнит 19-25.01'!X34+'Юнит 26-31.01'!X34 -> 1826.21 | Y34: =IF(U34=0,0,X34/U34) -> 0.43 | Z34: ='Юнит 01-04.01'!Z34+'Юнит 05-11.01'!Z34+'Юнит 12-18.01'!Z34+'Юнит 19-25.01'!Z34+'Юнит 26-31.01'!Z34 -> 186.2 | AA34: ='Юнит 01-04.01'!AA34+'Юнит 05-11.01'!AA34+'Юнит 12-18.01'!AA34+'Юнит 19-25.01'!AA34+'Юнит 26-31.01'!AA34 -> 0 | AD34: =U34*1% -> 42.47 | AE34: =U34-W34-X34-Z34-AA34-AB34-AC34-AD34 -> 1595.12 | AG34: =IF(R34=0,0,U34/R34) -> 4247 | AH34: =H34 -> 597 | AI34: =IF(R34=0,0,X34/R34) -> 1826.21 | AJ34: =IF(P34=0,Z34/1,Z34/P34) -> 186.2 | AK34: =IF(P34=0,0,AA34/P34) -> 0 | AL34: {=_xlfn.IFS(R34=0,AE34,R34<0,AE34/-R34,R34>0,AE34/R34)} -> 1595.12 | AM34: =IF(AG34=0,0,AL34/AG34) -> 0.37558747 | AN34: =IF(AH34=0,0,AL34/AH34) -> 2.6718928 | AP34: =AL34*C34 -> 0
A35: 2774714412 | B35: tunika08 черная | H35: 552 | I35: =C35*H35 -> 0 | K35: ='Юнит 01-04.01'!K35+'Юнит 05-11.01'!K35+'Юнит 12-18.01'!K35+'Юнит 19-25.01'!K35+'Юнит 26-31.01'!K35 -> 3 | N35: =K35/7 -> 0.42857143 | O35: =R35/7 -> 0 | P35: ='Юнит 01-04.01'!P35+'Юнит 05-11.01'!P35+'Юнит 12-18.01'!P35+'Юнит 19-25.01'!P35+'Юнит 26-31.01'!P35 -> 0 | Q35: ='Юнит 01-04.01'!Q35+'Юнит 05-11.01'!Q35+'Юнит 12-18.01'!Q35+'Юнит 19-25.01'!Q35+'Юнит 26-31.01'!Q35 -> 0 | R35: =P35-Q35 -> 0 | S35: ='Юнит 01-04.01'!S35+'Юнит 05-11.01'!S35+'Юнит 12-18.01'!S35+'Юнит 19-25.01'!S35+'Юнит 26-31.01'!S35 -> 0 | T35: ='Юнит 01-04.01'!T35+'Юнит 05-11.01'!T35+'Юнит 12-18.01'!T35+'Юнит 19-25.01'!T35+'Юнит 26-31.01'!T35 -> 0 | U35: =S35+T35 -> 0 | V35: =U35/$U$49 -> 0 | W35: =R35*H35 -> 0 | X35: ='Юнит 01-04.01'!X35+'Юнит 05-11.01'!X35+'Юнит 12-18.01'!X35+'Юнит 19-25.01'!X35+'Юнит 26-31.01'!X35 -> 0 | Y35: =IF(U35=0,0,X35/U35) -> 0 | Z35: ='Юнит 01-04.01'!Z35+'Юнит 05-11.01'!Z35+'Юнит 12-18.01'!Z35+'Юнит 19-25.01'!Z35+'Юнит 26-31.01'!Z35 -> 0 | AA35: ='Юнит 01-04.01'!AA35+'Юнит 05-11.01'!AA35+'Юнит 12-18.01'!AA35+'Юнит 19-25.01'!AA35+'Юнит 26-31.01'!AA35 -> 0 | AD35: =U35*1% -> 0 | AE35: =U35-W35-X35-Z35-AA35-AB35-AC35-AD35 -> 0 | AG35: =IF(R35=0,0,U35/R35) -> 0 | AH35: =H35 -> 552 | AI35: =IF(R35=0,0,X35/R35) -> 0 | AJ35: =IF(P35=0,Z35/1,Z35/P35) -> 0 | AK35: =IF(P35=0,0,AA35/P35) -> 0 | AL35: {=_xlfn.IFS(R35=0,AE35,R35<0,AE35/-R35,R35>0,AE35/R35)} -> 0 | AM35: =IF(AG35=0,0,AL35/AG35) -> 0 | AN35: =IF(AH35=0,0,AL35/AH35) -> 0 | AP35: =AL35*C35 -> 0
A36: 2774710430 | B36: tunika08 зеленая | H36: 552 | I36: =C36*H36 -> 0 | K36: ='Юнит 01-04.01'!K36+'Юнит 05-11.01'!K36+'Юнит 12-18.01'!K36+'Юнит 19-25.01'!K36+'Юнит 26-31.01'!K36 -> 4 | N36: =K36/7 -> 0.57142857 | O36: =R36/7 -> 0 | P36: ='Юнит 01-04.01'!P36+'Юнит 05-11.01'!P36+'Юнит 12-18.01'!P36+'Юнит 19-25.01'!P36+'Юнит 26-31.01'!P36 -> 0 | Q36: ='Юнит 01-04.01'!Q36+'Юнит 05-11.01'!Q36+'Юнит 12-18.01'!Q36+'Юнит 19-25.01'!Q36+'Юнит 26-31.01'!Q36 -> 0 | R36: =P36-Q36 -> 0 | S36: ='Юнит 01-04.01'!S36+'Юнит 05-11.01'!S36+'Юнит 12-18.01'!S36+'Юнит 19-25.01'!S36+'Юнит 26-31.01'!S36 -> 0 | T36: ='Юнит 01-04.01'!T36+'Юнит 05-11.01'!T36+'Юнит 12-18.01'!T36+'Юнит 19-25.01'!T36+'Юнит 26-31.01'!T36 -> 0 | U36: =S36+T36 -> 0 | V36: =U36/$U$49 -> 0 | W36: =R36*H36 -> 0 | X36: ='Юнит 01-04.01'!X36+'Юнит 05-11.01'!X36+'Юнит 12-18.01'!X36+'Юнит 19-25.01'!X36+'Юнит 26-31.01'!X36 -> 0 | Y36: =IF(U36=0,0,X36/U36) -> 0 | Z36: ='Юнит 01-04.01'!Z36+'Юнит 05-11.01'!Z36+'Юнит 12-18.01'!Z36+'Юнит 19-25.01'!Z36+'Юнит 26-31.01'!Z36 -> 113.88 | AA36: ='Юнит 01-04.01'!AA36+'Юнит 05-11.01'!AA36+'Юнит 12-18.01'!AA36+'Юнит 19-25.01'!AA36+'Юнит 26-31.01'!AA36 -> 0 | AD36: =U36*1% -> 0 | AE36: =U36-W36-X36-Z36-AA36-AB36-AC36-AD36 -> -113.88 | AG36: =IF(R36=0,0,U36/R36) -> 0 | AH36: =H36 -> 552 | AI36: =IF(R36=0,0,X36/R36) -> 0 | AJ36: =IF(P36=0,Z36/1,Z36/P36) -> 113.88 | AK36: =IF(P36=0,0,AA36/P36) -> 0 | AL36: {=_xlfn.IFS(R36=0,AE36,R36<0,AE36/-R36,R36>0,AE36/R36)} -> -113.88 | AM36: =IF(AG36=0,0,AL36/AG36) -> 0 | AN36: =IF(AH36=0,0,AL36/AH36) -> -0.20630435 | AP36: =AL36*C36 -> 0
A37: 2774712116 | B37: tunika09 кимоно | H37: 687 | I37: =C37*H37 -> 0 | K37: ='Юнит 01-04.01'!K37+'Юнит 05-11.01'!K37+'Юнит 12-18.01'!K37+'Юнит 19-25.01'!K37+'Юнит 26-31.01'!K37 -> 7 | N37: =K37/7 -> 1 | O37: =R37/7 -> 0.28571429 | P37: ='Юнит 01-04.01'!P37+'Юнит 05-11.01'!P37+'Юнит 12-18.01'!P37+'Юнит 19-25.01'!P37+'Юнит 26-31.01'!P37 -> 3 | Q37: ='Юнит 01-04.01'!Q37+'Юнит 05-11.01'!Q37+'Юнит 12-18.01'!Q37+'Юнит 19-25.01'!Q37+'Юнит 26-31.01'!Q37 -> 1 | R37: =P37-Q37 -> 2 | S37: ='Юнит 01-04.01'!S37+'Юнит 05-11.01'!S37+'Юнит 12-18.01'!S37+'Юнит 19-25.01'!S37+'Юнит 26-31.01'!S37 -> 13518 | T37: ='Юнит 01-04.01'!T37+'Юнит 05-11.01'!T37+'Юнит 12-18.01'!T37+'Юнит 19-25.01'!T37+'Юнит 26-31.01'!T37 -> -4506 | U37: =S37+T37 -> 9012 | V37: =U37/$U$49 -> 0.091704656 | W37: =R37*H37 -> 1374 | X37: ='Юнит 01-04.01'!X37+'Юнит 05-11.01'!X37+'Юнит 12-18.01'!X37+'Юнит 19-25.01'!X37+'Юнит 26-31.01'!X37 -> 3875.16 | Y37: =IF(U37=0,0,X37/U37) -> 0.43 | Z37: ='Юнит 01-04.01'!Z37+'Юнит 05-11.01'!Z37+'Юнит 12-18.01'!Z37+'Юнит 19-25.01'!Z37+'Юнит 26-31.01'!Z37 -> 1098.46 | AA37: ='Юнит 01-04.01'!AA37+'Юнит 05-11.01'!AA37+'Юнит 12-18.01'!AA37+'Юнит 19-25.01'!AA37+'Юнит 26-31.01'!AA37 -> 0 | AD37: =U37*1% -> 90.12 | AE37: =U37-W37-X37-Z37-AA37-AB37-AC37-AD37 -> 2574.26 | AG37: =IF(R37=0,0,U37/R37) -> 4506 | AH37: =H37 -> 687 | AI37: =IF(R37=0,0,X37/R37) -> 1937.58 | AJ37: =IF(P37=0,Z37/1,Z37/P37) -> 366.15333 | AK37: =IF(P37=0,0,AA37/P37) -> 0 | AL37: {=_xlfn.IFS(R37=0,AE37,R37<0,AE37/-R37,R37>0,AE37/R37)} -> 1287.13 | AM37: =IF(AG37=0,0,AL37/AG37) -> 0.28564802 | AN37: =IF(AH37=0,0,AL37/AH37) -> 1.8735517 | AP37: =AL37*C37 -> 0
A38: 2774719012 | B38: tunika10 кимоно ч/б | H38: 687 | I38: =C38*H38 -> 0 | K38: ='Юнит 01-04.01'!K38+'Юнит 05-11.01'!K38+'Юнит 12-18.01'!K38+'Юнит 19-25.01'!K38+'Юнит 26-31.01'!K38 -> 5 | N38: =K38/7 -> 0.71428571 | O38: =R38/7 -> 0 | P38: ='Юнит 01-04.01'!P38+'Юнит 05-11.01'!P38+'Юнит 12-18.01'!P38+'Юнит 19-25.01'!P38+'Юнит 26-31.01'!P38 -> 1 | Q38: ='Юнит 01-04.01'!Q38+'Юнит 05-11.01'!Q38+'Юнит 12-18.01'!Q38+'Юнит 19-25.01'!Q38+'Юнит 26-31.01'!Q38 -> 1 | R38: =P38-Q38 -> 0 | S38: ='Юнит 01-04.01'!S38+'Юнит 05-11.01'!S38+'Юнит 12-18.01'!S38+'Юнит 19-25.01'!S38+'Юнит 26-31.01'!S38 -> 3546 | T38: ='Юнит 01-04.01'!T38+'Юнит 05-11.01'!T38+'Юнит 12-18.01'!T38+'Юнит 19-25.01'!T38+'Юнит 26-31.01'!T38 -> -3546 | U38: =S38+T38 -> 0 | V38: =U38/$U$49 -> 0 | W38: =R38*H38 -> 0 | X38: ='Юнит 01-04.01'!X38+'Юнит 05-11.01'!X38+'Юнит 12-18.01'!X38+'Юнит 19-25.01'!X38+'Юнит 26-31.01'!X38 -> 0 | Y38: =IF(U38=0,0,X38/U38) -> 0 | Z38: ='Юнит 01-04.01'!Z38+'Юнит 05-11.01'!Z38+'Юнит 12-18.01'!Z38+'Юнит 19-25.01'!Z38+'Юнит 26-31.01'!Z38 -> 318.39 | AA38: ='Юнит 01-04.01'!AA38+'Юнит 05-11.01'!AA38+'Юнит 12-18.01'!AA38+'Юнит 19-25.01'!AA38+'Юнит 26-31.01'!AA38 -> 0 | AD38: =U38*1% -> 0 | AE38: =U38-W38-X38-Z38-AA38-AB38-AC38-AD38 -> -318.39 | AG38: =IF(R38=0,0,U38/R38) -> 0 | AH38: =H38 -> 687 | AI38: =IF(R38=0,0,X38/R38) -> 0 | AJ38: =IF(P38=0,Z38/1,Z38/P38) -> 318.39 | AK38: =IF(P38=0,0,AA38/P38) -> 0 | AL38: {=_xlfn.IFS(R38=0,AE38,R38<0,AE38/-R38,R38>0,AE38/R38)} -> -318.39 | AM38: =IF(AG38=0,0,AL38/AG38) -> 0 | AN38: =IF(AH38=0,0,AL38/AH38) -> -0.46344978 | AP38: =AL38*C38 -> 0
A39: 2774719433 | B39: tunika11 халат зеленая | H39: 597 | I39: =C39*H39 -> 0 | K39: ='Юнит 01-04.01'!K39+'Юнит 05-11.01'!K39+'Юнит 12-18.01'!K39+'Юнит 19-25.01'!K39+'Юнит 26-31.01'!K39 -> 1 | N39: =K39/7 -> 0.14285714 | O39: =R39/7 -> 0 | P39: ='Юнит 01-04.01'!P39+'Юнит 05-11.01'!P39+'Юнит 12-18.01'!P39+'Юнит 19-25.01'!P39+'Юнит 26-31.01'!P39 -> 0 | Q39: ='Юнит 01-04.01'!Q39+'Юнит 05-11.01'!Q39+'Юнит 12-18.01'!Q39+'Юнит 19-25.01'!Q39+'Юнит 26-31.01'!Q39 -> 0 | R39: =P39-Q39 -> 0 | S39: ='Юнит 01-04.01'!S39+'Юнит 05-11.01'!S39+'Юнит 12-18.01'!S39+'Юнит 19-25.01'!S39+'Юнит 26-31.01'!S39 -> 0 | T39: ='Юнит 01-04.01'!T39+'Юнит 05-11.01'!T39+'Юнит 12-18.01'!T39+'Юнит 19-25.01'!T39+'Юнит 26-31.01'!T39 -> 0 | U39: =S39+T39 -> 0 | V39: =U39/$U$49 -> 0 | W39: =R39*H39 -> 0 | X39: ='Юнит 01-04.01'!X39+'Юнит 05-11.01'!X39+'Юнит 12-18.01'!X39+'Юнит 19-25.01'!X39+'Юнит 26-31.01'!X39 -> 0 | Y39: =IF(U39=0,0,X39/U39) -> 0 | Z39: ='Юнит 01-04.01'!Z39+'Юнит 05-11.01'!Z39+'Юнит 12-18.01'!Z39+'Юнит 19-25.01'!Z39+'Юнит 26-31.01'!Z39 -> 0 | AA39: ='Юнит 01-04.01'!AA39+'Юнит 05-11.01'!AA39+'Юнит 12-18.01'!AA39+'Юнит 19-25.01'!AA39+'Юнит 26-31.01'!AA39 -> 0 | AD39: =U39*1% -> 0 | AE39: =U39-W39-X39-Z39-AA39-AB39-AC39-AD39 -> 0 | AG39: =IF(R39=0,0,U39/R39) -> 0 | AH39: =H39 -> 597 | AI39: =IF(R39=0,0,X39/R39) -> 0 | AJ39: =IF(P39=0,Z39/1,Z39/P39) -> 0 | AK39: =IF(P39=0,0,AA39/P39) -> 0 | AL39: {=_xlfn.IFS(R39=0,AE39,R39<0,AE39/-R39,R39>0,AE39/R39)} -> 0 | AM39: =IF(AG39=0,0,AL39/AG39) -> 0 | AN39: =IF(AH39=0,0,AL39/AH39) -> 0 | AP39: =AL39*C39 -> 0
... A47: 2774719500 | B47: tunika16 сетка черная | H47: 552 | I47: =C47*H47 -> 0 | K47: ='Юнит 01-04.01'!K47+'Юнит 05-11.01'!K47+'Юнит 12-18.01'!K47+'Юнит 19-25.01'!K47+'Юнит 26-31.01'!K47 -> 0 | N47: =K47/7 -> 0 | O47: =R47/7 -> 0 | P47: ='Юнит 01-04.01'!P47+'Юнит 05-11.01'!P47+'Юнит 12-18.01'!P47+'Юнит 19-25.01'!P47+'Юнит 26-31.01'!P47 -> 0 | Q47: ='Юнит 01-04.01'!Q47+'Юнит 05-11.01'!Q47+'Юнит 12-18.01'!Q47+'Юнит 19-25.01'!Q47+'Юнит 26-31.01'!Q47 -> 0 | R47: =P47-Q47 -> 0 | S47: ='Юнит 01-04.01'!S47+'Юнит 05-11.01'!S47+'Юнит 12-18.01'!S47+'Юнит 19-25.01'!S47+'Юнит 26-31.01'!S47 -> 0 | T47: ='Юнит 01-04.01'!T47+'Юнит 05-11.01'!T47+'Юнит 12-18.01'!T47+'Юнит 19-25.01'!T47+'Юнит 26-31.01'!T47 -> 0 | U47: =S47+T47 -> 0 | V47: =U47/$U$49 -> 0 | W47: =R47*H47 -> 0 | X47: ='Юнит 01-04.01'!X47+'Юнит 05-11.01'!X47+'Юнит 12-18.01'!X47+'Юнит 19-25.01'!X47+'Юнит 26-31.01'!X47 -> 0 | Y47: =IF(U47=0,0,X47/U47) -> 0 | Z47: ='Юнит 01-04.01'!Z47+'Юнит 05-11.01'!Z47+'Юнит 12-18.01'!Z47+'Юнит 19-25.01'!Z47+'Юнит 26-31.01'!Z47 -> 0 | AA47: ='Юнит 01-04.01'!AA47+'Юнит 05-11.01'!AA47+'Юнит 12-18.01'!AA47+'Юнит 19-25.01'!AA47+'Юнит 26-31.01'!AA47 -> 0 | AD47: =U47*1% -> 0 | AE47: =U47-W47-X47-Z47-AA47-AB47-AC47-AD47 -> 0 | AG47: =IF(R47=0,0,U47/R47) -> 0 | AH47: =H47 -> 552 | AI47: =IF(R47=0,0,X47/R47) -> 0 | AJ47: =IF(P47=0,Z47/1,Z47/P47) -> 0 | AK47: =IF(P47=0,0,AA47/P47) -> 0 | AL47: {=_xlfn.IFS(R47=0,AE47,R47<0,AE47/-R47,R47>0,AE47/R47)} -> 0 | AM47: =IF(AG47=0,0,AL47/AG47) -> 0 | AN47: =IF(AH47=0,0,AL47/AH47) -> 0 | AP47: =AL47*C47 -> 0
AG48: =AVERAGEIF(AG28:AG47,"<>0",AG28:AG47) -> 4086.1714 | AH48: =AVERAGEIF(AH28:AH47,"<>0",AH28:AH47) -> 617.25 | AI48: =AVERAGEIF(AI28:AI47,"<>0",AI28:AI47) -> 1757.0537 | AJ48: =AVERAGEIF(AJ28:AJ47,"<>0",AJ28:AJ47) -> 246.37392 | AK48: =AVERAGEIF(AK28:AK47,"<>0",AK28:AK47) -> 1238.0711 | AL48: =AVERAGEIF(AL28:AL47,"<>0",AL28:AL47) -> 309.41759 | AM48: =AVERAGEIF(AM28:AM47,"<>0",AM28:AM47) -> 0.19563637 | AN48: =AVERAGEIF(AN28:AN47,"<>0",AN28:AN47) -> 0.48682629
A49: Итого туники | C49: =SUM(C28:C47) -> 0 | I49: =SUM(I28:I47) -> 0 | K49: =SUM(K28:K47) -> 105 | P49: =SUM(P28:P47) -> 26 | Q49: =SUM(Q28:Q47) -> 4 | R49: =SUM(R28:R47) -> 22 | S49: =SUM(S28:S47) -> 116204 | T49: =SUM(T28:T47) -> -17932 | U49: =SUM(U28:U47) -> 98272 | V49: =SUM(V28:V47) -> 1 | W49: =SUM(W28:W47) -> 14829 | X49: =SUM(X28:X47) -> 42256.96 | Y49: =IF(U49=0,0,X49/U49) -> 0.43 | Z49: =SUM(Z28:Z47) -> 9013.36 | AA49: =SUM(AA28:AA47) -> 24330.629 | AB49: =SUM(AB28:AB47) -> 0 | AC49: =SUM(AC28:AC47) -> 0 | AD49: =SUM(AD28:AD47) -> 982.72 | AE49: =SUM(AE28:AE47) -> 6859.331 | AP49: =SUM(AP28:AP47) -> 0
AA50: ='Юнит 01-04.01'!AA50+'Юнит 05-11.01'!AA50+'Юнит 12-18.01'!AA50+'Юнит 19-25.01'!AA50+'Юнит 26-31.01'!AA50 -> 24330.629
