Workbook

Sheet Реклама
B2: ПЕРИОД | C2: БАЛАНС | F2: СЧЕТ | I2: Неделя
C3: Номер документа | D3: Сумма | E3: Даты | F3: Номер документа | G3: Сумма | H3: Даты
B4: 01-04.01 | F4: 277607349 | G4: 4738 | H4: 01-04.01 | I4: 1
B5: 04-11.01 | F5: 279228154 | G5: 6535 | H5: 04-11.01 | I5: 2
B6: 11-18.01 | C6: 280305485 | D6: 2922 | E6: 14-18.01 | F6: 280297200 | G6: 3464 | H6: 11-17.01 | I6: 3
B7: 18-25.01 | C7: 281290485 | D7: 5916 | E7: 18-23.01 | F7: 281290488 | G7: 2033 | H7: 18-25.01 | I7: 4
B8: 25.01-01.02 | C8: 282283796 | D8: 12613 | E8: 27-31.01 | F8: 282343451 | G8: 9553 | H8: 25-31.01 | I8: 5
C9: 282375547 | D9: 1000 | E9: 01.02 | F9: 282385566 | G9: 79 | H9: 01.02
B10: 01-08.02 | C10: 283356234 | D10: 9526 | E10: 01-04.02 | F10: 283392061 | G10: 17308 | H10: 01-08.02 | I10: 6
B11: 08-15.02 | C11: 284419876 | D11: 16968 | E11: 09-12.02 | F11: 284354982 | G11: 25029 | H11: 08-15.02 | I11: 7
B12: 15-22.02 | C12: 285375130 | D12: 19000 | E12: 16-21.02 | F12: 285375131 | G12: 43359 | H12: 16-22.02 | I12: 8
B13: 22.02-01.03 | C13: 286365345 | D13: 20188 | E13: 23-28.02 | F13: 286438626 | G13: 41519 | H13: 22-28.02 | I13: 9
F14: 286502032 | G14: 8252 | H14: 01.03
B15: 01-08.03 | C15: 287719816 | D15: 55356 | E15: 01.03-08.03 | F15: 287759820 | G15: 14284 | H15: 01.03-05.03 | I15: 10
B16: 08-15.03 | C16: 288712526 | D16: 117662 | E16: 08-15.03 | I16: 11
B17: 15-22.03 | C17: 289759802 | D17: 121051 | E17: 15-22.03 | I17: 12
B18: 22-29.03 | C18: 290725778 | D18: 128912 | E18: 22-29.03 | I18: 13
B19: 29.03-05.04 | C19: 291768435 | D19: 65325 | E19: 29-31.03 | I19: 14
C20: 291883504 | D20: 80610 | E20: 01-05.04 | F20: 291847775 | G20: 788 | H20: 04.02
B21: 05-12.04 | C21: 292907640 | D21: 104265 | E21: 06-12.04 | I21: 15
B22: 12-19.04 | C22: 293900151 | D22: 127217 | E22: 12-19.04 | I22: 16
B23: 19-26.04 | C23: 294920472 | D23: =112470+12849 -> 125319 | E23: 19-26.04 | I23: 17
B24: 26.04-03.05 | C24: 295903378 | D24: 38906 | E24: 26-30.04 | I24: 18
C25: 296043480 | D25: 53077 | E25: 01.05-03.05
B26: 03-10.05 | C26: 296996503 | D26: 150375 | E26: 03.05-10.05 | F26: 297017628 | G26: 8172 | H26: 09.05-10.05 | I26: 19
H33: .

Sheet Сводная_план
B2: Период | E2: Дата поступления дс | F2: Итого к перечислению на счет, руб | G2: шт. | J2: ВБ реализовал товар (выручка с СПП) | M2: Выручка до вычета комиссии ВБ | P2: Себестоимость продаж | Q2: Логистика WB | R2: Комиссия WB | S2: Хранение WB | T2: Платная приемка WB | U2: Штрафы WB | V2: Прочие удержания WB | W2: Реклама БАЛАНС | X2: Реклама СЧЕТ | Y2: Блогеры | Z2: Налог | AA2: Прочие поступления WB | AB2: Прибыль до вычета налогов | AC2: Прибыль после вычета налогов | AD2: Итог месяц | AE2: % Cебестоимости | AF2: Маржинальность, % | AG2: Рентабельность, % | AH2: Доля рекламы, %
B3: Месяц | C3: Даты | D3: Нед | G3: Заказы | H3: Продажи | I3: Возвраты | J3: Продажи | K3: Возвраты | L3: Общая | M3: Продажи | N3: Возвраты | O3: Общая
B4: Январь 1 | C4: 29-31.12 | D4: 1 | AD4: =SUM(AC4:AC9) -> 0 | AE4: =P4/O4 -> #DIV/0! | AF4: =AC4/P4 -> #DIV/0! | AG4: =AC4/O4 -> #DIV/0! | AH4: =(W4+X4+Y4)/O4 -> #DIV/0!
C5: 01-04.01 | D5: 1
B6: Январь 2 | C6: 05-11.01 | D6: 2 | AE6: =P6/O6 -> #DIV/0! | AF6: =AC6/P6 -> #DIV/0! | AG6: =AC6/O6 -> #DIV/0! | AH6: =(W6+X6+Y6)/O6 -> #DIV/0!
B7: Январь 3 | C7: 12-18.01 | D7: 3 | AE7: =P7/O7 -> #DIV/0! | AF7: =AC7/P7 -> #DIV/0! | AG7: =AC7/O7 -> #DIV/0! | AH7: =(W7+X7+Y7)/O7 -> #DIV/0!
B8: Январь 4 | C8: 19-25.01 | D8: 4 | AE8: =P8/O8 -> #DIV/0! | AF8: =AC8/P8 -> #DIV/0! | AG8: =AC8/O8 -> #DIV/0! | AH8: =(W8+X8+Y8)/O8 -> #DIV/0!
B9: Январь 5 | C9: 26.01-01.02 | D9: 5 | AE9: =P9/O9 -> #DIV/0! | AF9: =AC9/P9 -> #DIV/0! | AG9: =AC9/O9 -> #DIV/0! | AH9: =(W9+X9+Y9)/O9 -> #DIV/0!
B10: Февраль 1 | C10: 02-08.02 | D10: 6 | AD10: =SUM(AC10:AC13) -> 0 | AE10: =P10/O10 -> #DIV/0! | AF10: =AC10/P10 -> #DIV/0! | AG10: =AC10/O10 -> #DIV/0! | AH10: =(W10+X10+Y10)/O10 -> #DIV/0!
B11: Февраль 2 | C11: 09-15.02 | D11: 7 | AE11: =P11/O11 -> #DIV/0! | AF11: =AC11/P11 -> #DIV/0! | AG11: =AC11/O11 -> #DIV/0! | AH11: =(W11+X11+Y11)/O11 -> #DIV/0!
B12: Февраль 3 | C12: 16-22.02 | D12: 8 | AE12: =P12/O12 -> #DIV/0! | AF12: =AC12/P12 -> #DIV/0! | AG12: =AC12/O12 -> #DIV/0! | AH12: =(W12+X12+Y12)/O12 -> #DIV/0!
B13: Февраль 4 | C13: 23.02-01.03 | D13: 9 | AE13: =P13/O13 -> #DIV/0! | AF13: =AC13/P13 -> #DIV/0! | AG13: =AC13/O13 -> #DIV/0! | AH13: =(W13+X13+Y13)/O13 -> #DIV/0!
B14: Март 1 очки | C14: 02-08.03 | D14: 10 | AD14: =SUM(AC14:AC21) -> 0 | AE14: =P14/O14 -> #DIV/0! | AF14: =AC14/P14 -> #DIV/0! | AG14: =AC14/O14 -> #DIV/0! | AH14: =(W14+X14+Y14)/O14 -> #DIV/0!
B15: Март 1 шапки | C15: 02-08.03 | D15: 10 | AE15: =P15/O15 -> #DIV/0! | AF15: =AC15/P15 -> #DIV/0! | AG15: =AC15/O15 -> #DIV/0! | AH15: =(W15+X15+Y15)/O15 -> #DIV/0!
B16: Март 2 очки | C16: 09-15.03 | D16: 11 | AE16: =P16/O16 -> #DIV/0! | AF16: =AC16/P16 -> #DIV/0! | AG16: =AC16/O16 -> #DIV/0! | AH16: =(W16+X16+Y16)/O16 -> #DIV/0!
B17: Март 2 шапки | C17: 09-15.03 | D17: 11 | AE17: =P17/O17 -> #DIV/0! | AF17: =AC17/P17 -> #DIV/0! | AG17: =AC17/O17 -> #DIV/0! | AH17: =(W17+X17+Y17)/O17 -> #DIV/0!
B18: Март 3 очки | C18: 16-22.03 | D18: 12 | AE18: =P18/O18 -> #DIV/0! | AF18: =AC18/P18 -> #DIV/0! | AG18: =AC18/O18 -> #DIV/0! | AH18: =(W18+X18+Y18)/O18 -> #DIV/0!
B19: Март 3 шапки | C19: 16-22.03 | D19: 12 | AE19: =P19/O19 -> #DIV/0! | AF19: =AC19/P19 -> #DIV/0! | AG19: =AC19/O19 -> #DIV/0! | AH19: =(W19+X19+Y19)/O19 -> #DIV/0!
B20: Март 4 очки | C20: 23-29.03 | D20: 13 | AE20: =P20/O20 -> #DIV/0! | AF20: =AC20/P20 -> #DIV/0! | AG20: =AC20/O20 -> #DIV/0! | AH20: =(W20+X20+Y20)/O20 -> #DIV/0!
B21: Март 4 шапки | C21: 23-29.03 | D21: 13 | AE21: =P21/O21 -> #DIV/0! | AF21: =AC21/P21 -> #DIV/0! | AG21: =AC21/O21 -> #DIV/0! | AH21: =(W21+X21+Y21)/O21 -> #DIV/0!
B22: Апрель 1 очки | C22: 30.03-05.04 | D22: 14 | F22: =IFERROR(O22-SUM(Q22:W22)+AA22,0) -> 367394.67 | G22: ='Юнит 14'!L$59 -> 1070 | H22: ='Юнит 14'!Q$59 -> 738 | I22: ='Юнит 14'!R$59 -> -18 | J22: ='Юнит 14'!T$59 -> 627842.82 | K22: ='Юнит 14'!U$59 -> -15191 | L22: =IFERROR(J22+K22,0) -> 612651.82 | M22: ='Юнит 14'!W$59 -> 950855.45 | N22: ='Юнит 14'!X$59 -> -23538 | O22: =IFERROR(M22+N22,0) -> 927317.45 | P22: ='Юнит 14'!AB$59 -> 91170.72 | Q22: ='Юнит 14'!AE$59 -> 96960.75 | R22: ='Юнит 14'!AC$59 -> 349571.93 | S22: ='Юнит 14'!AI$59 -> 6078.0973 | U22: ='Юнит 14'!AJ$59 -> 100 | W22: ='Юнит 14'!AF$59 -> 107212 | X22: ='Юнит 14'!AG$59 -> 788 | Y22: ='Юнит 14'!AH142 -> 0 | Z22: =IFERROR((L22)*0.01,0) -> 6126.5182 | AB22: =O22-SUM(P22:Y22)+AA22 -> 275435.95 | AC22: =O22-SUM(P22:Z22)+AA22 -> 269309.43 | AD22: =SUM(AC22:AC31) -> 778623.14 | AE22: =P22/O22 -> 0.098316623 | AF22: =AC22/P22 -> 2.9539027 | AG22: =AC22/O22 -> 0.29041774 | AH22: =(W22+X22+Y22)/O22 -> 0.11646497
B23: Апрель 1 шапки | C23: 30.03-05.04 | D23: 14 | AE23: =P23/O23 -> #DIV/0! | AF23: =AC23/P23 -> #DIV/0! | AG23: =AC23/O23 -> #DIV/0! | AH23: =(W23+X23+Y23)/O23 -> #DIV/0!
B24: Апрель 2 очки | C24: 06-12.04 | D24: 15 | F24: =IFERROR(O24-SUM(Q24:W24)+AA24,0) -> 239463.88 | G24: ='Юнит 15'!L$59 -> 712 | H24: ='Юнит 15'!Q$59 -> 475 | I24: ='Юнит 15'!R$59 -> -10 | J24: ='Юнит 15'!T$59 -> 410987.97 | K24: ='Юнит 15'!U$59 -> -8507 | L24: =IFERROR(J24+K24,0) -> 402480.97 | M24: ='Юнит 15'!W$59 -> 615994.65 | N24: ='Юнит 15'!X$59 -> -12994 | O24: =IFERROR(M24+N24,0) -> 603000.65 | P24: ='Юнит 15'!AB$59 -> 58987.17 | Q24: ='Юнит 15'!AE$59 -> 63078.87 | R24: ='Юнит 15'!AC$59 -> 228321.03 | S24: ='Юнит 15'!AI$59 -> 5840.8701 | U24: ='Юнит 15'!AJ$59 -> 30 | W24: ='Юнит 15'!AF$59 -> 66266 | X24: ='Юнит 15'!AG$59 -> 0 | Y24: ='Юнит 15'!AH144 -> 0 | Z24: =IFERROR((L24)*0.01,0) -> 4024.8097 | AB24: =O24-SUM(P24:Y24)+AA24 -> 180476.71 | AC24: =O24-SUM(P24:Z24)+AA24 -> 176451.9 | AE24: =P24/O24 -> 0.09782273 | AF24: =AC24/P24 -> 2.9913607 | AG24: =AC24/O24 -> 0.29262307 | AH24: =(W24+X24+Y24)/O24 -> 0.10989375
B25: Апрель 2 шапки | C25: 06-12.04 | D25: 15 | AE25: =P25/O25 -> #DIV/0! | AF25: =AC25/P25 -> #DIV/0! | AG25: =AC25/O25 -> #DIV/0! | AH25: =(W25+X25+Y25)/O25 -> #DIV/0!
B26: Апрель 3 очки | C26: 13-19.04 | D26: 16 | F26: =IFERROR(O26-SUM(Q26:W26)+AA26,0) -> 205868.01 | G26: ='Юнит 16'!L$59 -> 843 | H26: ='Юнит 16'!Q$59 -> 491 | I26: ='Юнит 16'!R$59 -> -6 | J26: ='Юнит 16'!T$59 -> 422194.48 | K26: ='Юнит 16'!U$59 -> -5004.64 | L26: =IFERROR(J26+K26,0) -> 417189.84 | M26: ='Юнит 16'!W$59 -> 631051.64 | N26: ='Юнит 16'!X$59 -> -7401.77 | O26: =IFERROR(M26+N26,0) -> 623649.87 | P26: ='Юнит 16'!AB$59 -> 62105.34 | Q26: ='Юнит 16'!AE$59 -> 69407.72 | R26: ='Юнит 16'!AC$59 -> 235781.61 | S26: ='Юнит 16'!AI$59 -> 5403.531 | U26: ='Юнит 16'!AJ$59 -> 200 | W26: ='Юнит 16'!AF$59 -> 106989 | X26: ='Юнит 16'!AG$59 -> 0 | Y26: ='Юнит 16'!AH146 -> 0 | Z26: =IFERROR((L26)*0.01,0) -> 4171.8984 | AB26: =O26-SUM(P26:Y26)+AA26 -> 143762.67 | AC26: =O26-SUM(P26:Z26)+AA26 -> 139590.77 | AE26: =P26/O26 -> 0.099583665 | AF26: =AC26/P26 -> 2.2476452 | AG26: =AC26/O26 -> 0.22382875 | AH26: =(W26+X26+Y26)/O26 -> 0.17155299
B27: Апрель 3 шапки | C27: 13-19.04 | D27: 16 | AE27: =P27/O27 -> #DIV/0! | AF27: =AC27/P27 -> #DIV/0! | AG27: =AC27/O27 -> #DIV/0! | AH27: =(W27+X27+Y27)/O27 -> #DIV/0!
B28: Апрель 4 очки | C28: 20-26.04 | D28: 17 | F28: =IFERROR(O28-SUM(Q28:W28)+AA28,0) -> 159366.79 | G28: ='Юнит 17'!L$59 -> 614 | H28: ='Юнит 17'!Q$59 -> 419 | I28: ='Юнит 17'!R$59 -> -3 | J28: ='Юнит 17'!T$59 -> 367593.75 | K28: ='Юнит 17'!U$59 -> -2608 | L28: =IFERROR(J28+K28,0) -> 364985.75 | M28: ='Юнит 17'!W$59 -> 538871.83 | N28: ='Юнит 17'!X$59 -> -3900 | O28: =IFERROR(M28+N28,0) -> 534971.83 | P28: ='Юнит 17'!AB$59 -> 53094.99 | Q28: ='Юнит 17'!AE$59 -> 54950.82 | R28: ='Юнит 17'!AC$59 -> 202367.99 | S28: ='Юнит 17'!AI$59 -> 5036.2292 | U28: ='Юнит 17'!AJ$59 -> 150 | W28: ='Юнит 17'!AF$59 -> 113100 | X28: ='Юнит 17'!AG$59 -> 0 | Y28: ='Юнит 17'!AH148 -> 0 | Z28: =IFERROR((L28)*0.01,0) -> 3649.8575 | AB28: =O28-SUM(P28:Y28)+AA28 -> 106271.8 | AC28: =O28-SUM(P28:Z28)+AA28 -> 102621.94 | AE28: =P28/O28 -> 0.099248198 | AF28: =AC28/P28 -> 1.932799 | AG28: =AC28/O28 -> 0.19182682 | AH28: =(W28+X28+Y28)/O28 -> 0.211413
B29: Апрель 4 шапки | C29: 20-26.04 | D29: 17 | AE29: =P29/O29 -> #DIV/0! | AF29: =AC29/P29 -> #DIV/0! | AG29: =AC29/O29 -> #DIV/0! | AH29: =(W29+X29+Y29)/O29 -> #DIV/0!
B30: Апрель 5 очки | C30: 27.04-03.05 | D30: 18 | F30: =IFERROR(O30-SUM(Q30:W30)+AA30,0) -> 142132.84 | G30: ='Юнит 18'!L$59 -> 675 | H30: ='Юнит 18'!Q$59 -> 385 | I30: ='Юнит 18'!R$59 -> -8 | J30: ='Юнит 18'!T$59 -> 337964.2 | K30: ='Юнит 18'!U$59 -> -7103.85 | L30: =IFERROR(J30+K30,0) -> 330860.35 | M30: ='Юнит 18'!W$59 -> 474292.2 | N30: ='Юнит 18'!X$59 -> -10016.93 | O30: =IFERROR(M30+N30,0) -> 464275.27 | P30: ='Юнит 18'!AB$59 -> 48175.14 | Q30: ='Юнит 18'!AE$59 -> 49084.94 | R30: ='Юнит 18'!AC$59 -> 175905.37 | S30: ='Юнит 18'!AI$59 -> 4681.1243 | U30: ='Юнит 18'!AJ$59 -> 827 | W30: ='Юнит 18'!AF$59 -> 91644 | X30: ='Юнит 18'!AG$59 -> 0 | Y30: ='Юнит 18'!AH150 -> 0 | Z30: =IFERROR((L30)*0.01,0) -> 3308.6035 | AB30: =O30-SUM(P30:Y30)+AA30 -> 93957.696 | AC30: =O30-SUM(P30:Z30)+AA30 -> 90649.092 | AE30: =P30/O30 -> 0.10376417 | AF30: =AC30/P30 -> 1.8816571 | AG30: =AC30/O30 -> 0.19524859 | AH30: =(W30+X30+Y30)/O30 -> 0.19739152
B31: Апрель 5 шапки | C31: 27.04-03.05 | D31: 18 | AE31: =P31/O31 -> #DIV/0! | AF31: =AC31/P31 -> #DIV/0! | AG31: =AC31/O31 -> #DIV/0! | AH31: =(W31+X31+Y31)/O31 -> #DIV/0!
AB33: =O33-SUM(P33:Y33)+AA33 -> 0 | AC33: =O33-SUM(P33:Z33)+AA33 -> 0 | AE33: =P33/O33 -> #DIV/0! | AF33: =AC33/P33 -> #DIV/0! | AG33: =AC33/O33 -> #DIV/0! | AH33: =(W33+X33+Y33)/O33 -> #DIV/0!
B34: Итого | F34: =SUM(F4:F33) -> 1114226.2 | G34: =SUM(G4:G33) -> 3914 | H34: =SUM(H4:H33) -> 2508 | I34: =SUM(I4:I33) -> -45 | J34: =SUM(J4:J33) -> 2166583.2 | K34: =SUM(K4:K33) -> -38414.49 | L34: =SUM(L4:L33) -> 2128168.7 | M34: =SUM(M4:M33) -> 3211065.8 | ... AD34: =SUM(AD4:AD33) -> 778623.14 | AE34: =P34/O34 -> 0.099432913 | AF34: =AC34/P34 -> 2.4833821 | AG34: =AC34/O34 -> 0.24692992 | AH34: =(W34+X34+Y34)/O34 -> 0.15412808
M35: % от выручки за весь период
N36: =-N34/M34 -> 0.018016043 | P36: =P34/$O$34 -> 0.099432913 | Q36: =Q34/$O$34 -> 0.10575971 | R36: =R34/$O$34 -> 0.37801035 | S36: =S34/$O$34 -> 0.0085753275 | T36: =T34/$O$34 -> 0 | U36: =U34/$O$34 -> 0.00041449758 | V36: =V34/$O$34 -> 0 | W36: =W34/$O$34 -> 0.15387818 | ... Z36: =Z34/$O$34 -> 0.0067492026 | AD36: =AC34/P34 -> 2.4833821 | AE36: Маржинальность, %
W37: =(W34+X34)/O34 -> 0.15412808 | AD37: =AC34/O34 -> 0.24692992 | AE37: Рентабельность, %
B39: 14 нед | W39: =W22/O22 -> 0.11561521 | X39: =X22/O22 -> 0.00084976294
B40: 15 нед | W40: =W24/O24 -> 0.10989375 | X40: =X24/O24 -> 0
B41: 16 нед | W41: =W26/O26 -> 0.17155299 | X41: =X26/O26 -> 0
B42: 17 нед | W42: =W28/O28 -> 0.211413 | X42: =X28/O28 -> 0
B43: 18 нед | W43: =W30/O30 -> 0.19739152 | X43: =X30/O30 -> 0
B44: АПРЕЛЬ | W44: =(W22+W24+W26+W28+W30)/(O22+O24+O26+O28+O30) -> 0.15387818 | X44: =(X22+X24+X26+X28+X30)/(O22+O24+O26+O28+O30) -> 0.00024990366

Sheet Сводная
B2: Период | E2: Дата поступления дс | F2: Итого к перечислению на счет, руб | G2: шт. | J2: ВБ реализовал товар (выручка с СПП) | M2: Выручка до вычета комиссии ВБ | P2: Себестоимость продаж | Q2: Логистика WB | R2: Комиссия WB | S2: Хранение WB | T2: Платная приемка WB | U2: Штрафы WB | V2: Прочие удержания WB | W2: Реклама БАЛАНС | X2: Реклама СЧЕТ | Y2: Блогеры | Z2: Налог | AA2: Прочие поступления WB | AB2: Прибыль до вычета налогов | AC2: Прибыль после вычета налогов | AD2: Итог месяц | AE2: % Cебестоимости | AF2: Маржинальность, % | AG2: Рентабельность, % | AH2: Доля рекламы, %
B3: Месяц | C3: Даты | D3: Нед | G3: Заказы | H3: Продажи | I3: Возвраты | J3: Продажи | K3: Возвраты | L3: Общая | M3: Продажи | N3: Возвраты | O3: Общая
B4: Январь 1 | C4: 29-31.12 | D4: 1 | F4: =IFERROR(O4-SUM(Q4:W4)+AA4,0) -> 21116.17 | G4: ='Юнит 1 29-31.12'!L$17 -> 29 | H4: ='Юнит 1 29-31.12'!Q$17 -> 31 | I4: ='Юнит 1 29-31.12'!R$17 -> 0 | J4: ='Юнит 1 29-31.12'!T$74 -> 31859.55 | K4: ='Юнит 1 29-31.12'!U$74 -> 0 | L4: =IFERROR(J4+K4,0) -> 31859.55 | M4: ='Юнит 1 29-31.12'!W$74 -> 37862.85 | N4: ='Юнит 1 29-31.12'!X$74 -> 0 | O4: =IFERROR(M4+N4,0) -> 37862.85 | P4: ='Юнит 1 29-31.12'!AB$74 -> 3949.17 | Q4: ='Юнит 1 29-31.12'!AE$74 -> 2587.3 | R4: ='Юнит 1 29-31.12'!AC$74 -> 13659.08 | S4: ='Юнит 1 29-31.12'!AI$74 -> 413.9 | U4: ='Юнит 1 29-31.12'!AJ$74 -> 0 | V4: 86.4 | W4: ='Юнит 1 29-31.12'!AF$74 -> 0 | X4: ='Юнит 1 29-31.12'!AG$74 -> 0 | Y4: ='Юнит 1 29-31.12'!AH84 -> 0 | Z4: 313.33 | AB4: =O4-SUM(P4:Y4)+AA4 -> 17167 | AC4: =O4-SUM(P4:Z4)+AA4 -> 16853.67 | AD4: =SUM(AC4:AC9) -> 67154.08 | AE4: =P4/O4 -> 0.10430197 | AF4: =AC4/P4 -> 4.2676486 | AG4: =AC4/O4 -> 0.44512418 | AH4: =(W4+X4+Y4)/O4 -> 0
C5: 01-04.01 | D5: 1 | F5: =IFERROR(O5-SUM(Q5:W5)+AA5,0) -> 8163.47 | G5: ='Юнит 1 01-04.01'!L$17 -> 37 | H5: ='Юнит 1 01-04.01'!Q$17 -> 14 | I5: ='Юнит 1 01-04.01'!R$17 -> 0 | J5: ='Юнит 1 01-04.01'!T$74 -> 14286.08 | K5: ='Юнит 1 01-04.01'!U$74 -> 0 | L5: =IFERROR(J5+K5,0) -> 14286.08 | M5: ='Юнит 1 01-04.01'!W$74 -> 17125.77 | N5: ='Юнит 1 01-04.01'!X$74 -> 0 | O5: =IFERROR(M5+N5,0) -> 17125.77 | P5: ='Юнит 1 01-04.01'!AB$74 -> 1763.04 | Q5: ='Юнит 1 01-04.01'!AE$74 -> 1955.75 | R5: ='Юнит 1 01-04.01'!AC$74 -> 6195.14 | S5: ='Юнит 1 01-04.01'!AI$74 -> 635.73 | U5: ='Юнит 1 01-04.01'!AJ$74 -> 0 | V5: 175.68 | W5: ='Юнит 1 01-04.01'!AF$74 -> 0 | X5: ='Юнит 1 01-04.01'!AG$74 -> 4738 | Y5: ='Юнит 1 01-04.01'!AH85 -> 0 | Z5: 144.56 | AB5: =O5-SUM(P5:Y5)+AA5 -> 1662.43 | AC5: =O5-SUM(P5:Z5)+AA5 -> 1517.87
B6: Январь 2 | C6: 05-11.01 | D6: 2 | F6: =IFERROR(O6-SUM(Q6:W6)+AA6,0) -> 25524.23 | G6: ='Юнит 2'!L$17 -> 86 | H6: ='Юнит 2'!Q$17 -> 43 | I6: ='Юнит 2'!R$17 -> -1 | J6: ='Юнит 2'!T$74 -> 43245.32 | K6: ='Юнит 2'!U$74 -> -931 | L6: =IFERROR(J6+K6,0) -> 42314.32 | M6: ='Юнит 2'!W$74 -> 52197.86 | N6: ='Юнит 2'!X$74 -> -1199 | O6: =IFERROR(M6+N6,0) -> 50998.86 | P6: ='Юнит 2'!AB$74 -> 5562.9 | Q6: ='Юнит 2'!AE$74 -> 5752.8 | R6: ='Юнит 2'!AC$74 -> 18463.04 | S6: ='Юнит 2'!AI$74 -> 1083.11 | U6: ='Юнит 2'!AJ$74 -> 0 | V6: 175.68 | W6: ='Юнит 2'!AF$74 -> 0 | X6: ='Юнит 2'!AG$74 -> 6535 | Y6: ='Юнит 2'!AH85 -> 0 | Z6: 416.28 | AB6: =O6-SUM(P6:Y6)+AA6 -> 13426.33 | AC6: =O6-SUM(P6:Z6)+AA6 -> 13010.05 | AE6: =P6/O6 -> 0.10907891 | AF6: =AC6/P6 -> 2.3387172 | AG6: =AC6/O6 -> 0.25510472 | AH6: =(W6+X6+Y6)/O6 -> 0.12814012
B7: Январь 3 | C7: 12-18.01 | D7: 3 | F7: =IFERROR(O7-SUM(Q7:W7)+AA7,0) -> 25982.83 | G7: ='Юнит 3'!L$17 -> 62 | H7: ='Юнит 3'!Q$17 -> 49 | I7: ='Юнит 3'!R$17 -> -1 | J7: ='Юнит 3'!T$74 -> 45785.47 | K7: ='Юнит 3'!U$74 -> -948 | L7: =IFERROR(J7+K7,0) -> 44837.47 | M7: ='Юнит 3'!W$74 -> 56919.74 | N7: ='Юнит 3'!X$74 -> -1174 | O7: =IFERROR(M7+N7,0) -> 55745.74 | P7: ='Юнит 3'!AB$74 -> 6528.42 | Q7: ='Юнит 3'!AE$74 -> 6055.25 | R7: ='Юнит 3'!AC$74 -> 19306.86 | S7: ='Юнит 3'!AI$74 -> 1361.68 | U7: ='Юнит 3'!AJ$74 -> 0 | V7: 117.12 | W7: ='Юнит 3'!AF$74 -> 2922 | X7: ='Юнит 3'!AG$74 -> 3464 | Y7: ='Юнит 3'!AH86 -> 0 | Z7: 467.24 | AB7: =O7-SUM(P7:Y7)+AA7 -> 15990.41 | AC7: =O7-SUM(P7:Z7)+AA7 -> 15523.17 | AE7: =P7/O7 -> 0.11711065 | AF7: =AC7/P7 -> 2.3777836 | AG7: =AC7/O7 -> 0.27846379 | AH7: =(W7+X7+Y7)/O7 -> 0.11455584
B8: Январь 4 | C8: 19-25.01 | D8: 4 | F8: =IFERROR(O8-SUM(Q8:W8)+AA8,0) -> 22836.85 | G8: ='Юнит 4'!L$17 -> 86 | H8: ='Юнит 4'!Q$17 -> 49 | I8: ='Юнит 4'!R$17 -> -2 | J8: ='Юнит 4'!T$74 -> 44338.88 | K8: ='Юнит 4'!U$74 -> -1888 | L8: =IFERROR(J8+K8,0) -> 42450.88 | M8: ='Юнит 4'!W$74 -> 59321.67 | N8: ='Юнит 4'!X$74 -> -2412 | O8: =IFERROR(M8+N8,0) -> 56909.67 | P8: ='Юнит 4'!AB$74 -> 6764.52 | Q8: ='Юнит 4'!AE$74 -> 6115.35 | R8: ='Юнит 4'!AC$74 -> 20543.92 | S8: ='Юнит 4'!AI$74 -> 1438.99 | U8: ='Юнит 4'!AJ$74 -> 0 | V8: 58.56 | W8: ='Юнит 4'!AF$74 -> 5916 | X8: ='Юнит 4'!AG$74 -> 2033 | Y8: ='Юнит 4'!AH87 -> 0 | Z8: 456.13 | AB8: =O8-SUM(P8:Y8)+AA8 -> 14039.33 | AC8: =O8-SUM(P8:Z8)+AA8 -> 13583.2 | AE8: =P8/O8 -> 0.11886416 | AF8: =AC8/P8 -> 2.0080065 | AG8: =AC8/O8 -> 0.23868 | AH8: =(W8+X8+Y8)/O8 -> 0.13967749
B9: Январь 5 | C9: 26.01-01.02 | D9: 5 | F9: =IFERROR(O9-SUM(Q9:W9)+AA9,0) -> 26541.81 | G9: ='Юнит 5'!L$17 -> 157 | H9: ='Юнит 5'!Q$17 -> 70 | I9: ='Юнит 5'!R$17 -> -1 | J9: ='Юнит 5'!T$74 -> 53707.42 | K9: ='Юнит 5'!U$74 -> -813 | L9: =IFERROR(J9+K9,0) -> 52894.42 | M9: ='Юнит 5'!W$74 -> 80352 | N9: ='Юнит 5'!X$74 -> -1238 | O9: =IFERROR(M9+N9,0) -> 79114 | P9: ='Юнит 5'!AB$74 -> 9760.32 | Q9: ='Юнит 5'!AE$74 -> 8509.6 | R9: ='Юнит 5'!AC$74 -> 28720.66 | S9: ='Юнит 5'!AI$74 -> 1377.57 | U9: ='Юнит 5'!AJ$74 -> 0 | V9: 351.36 | W9: ='Юнит 5'!AF$74 -> 13613 | X9: ='Юнит 5'!AG$74 -> 9632 | Y9: ='Юнит 5'!AH88 -> 0 | Z9: 483.37 | AB9: =O9-SUM(P9:Y9)+AA9 -> 7149.49 | AC9: =O9-SUM(P9:Z9)+AA9 -> 6666.12 | AE9: =P9/O9 -> 0.12337033 | AF9: =AC9/P9 -> 0.68298171 | AG9: =AC9/O9 -> 0.084259676 | AH9: =(W9+X9+Y9)/O9 -> 0.29381652
B10: Февраль 1 | C10: 02-08.02 | D10: 6 | F10: =IFERROR(O10-SUM(Q10:W10)+AA10,0) -> 59865 | G10: ='Юнит 6'!L$45 -> 286 | H10: ='Юнит 6'!Q$45 -> 118 | I10: ='Юнит 6'!R$45 -> -1 | J10: ='Юнит 6'!T$102 -> 85982.96 | K10: ='Юнит 6'!U$102 -> -777 | L10: =IFERROR(J10+K10,0) -> 85205.96 | M10: ='Юнит 6'!W$102 -> 132376.93 | N10: ='Юнит 6'!X$102 -> -1238 | O10: =IFERROR(M10+N10,0) -> 131138.93 | P10: ='Юнит 6'!AB$102 -> 15974.01 | Q10: ='Юнит 6'!AE$102 -> 12544.65 | R10: ='Юнит 6'!AC$102 -> 47795.47 | S10: ='Юнит 6'!AI$102 -> 1261.41 | U10: ='Юнит 6'!AJ$102 -> 0 | V10: 146.4 | W10: ='Юнит 6'!AF$102 -> 9526 | X10: ='Юнит 6'!AG$102 -> 17308 | Y10: ='Юнит 6'!AH117 -> 0 | Z10: 922.79 | AB10: =O10-SUM(P10:Y10)+AA10 -> 26582.99 | AC10: =O10-SUM(P10:Z10)+AA10 -> 25660.2 | AD10: =SUM(AC10:AC13) -> 265557.06 | AE10: =P10/O10 -> 0.12180982 | AF10: =AC10/P10 -> 1.6063719 | AG10: =AC10/O10 -> 0.19567187 | AH10: =(W10+X10+Y10)/O10 -> 0.20462269
B11: Февраль 2 | C11: 09-15.02 | D11: 7 | F11: =IFERROR(O11-SUM(Q11:W11)+AA11,0) -> 105982.04 | G11: ='Юнит 7'!L$45 -> 388 | H11: ='Юнит 7'!Q$45 -> 212 | I11: ='Юнит 7'!R$45 -> -2 | J11: ='Юнит 7'!T$102 -> 149383.2 | K11: ='Юнит 7'!U$102 -> -1458 | L11: =IFERROR(J11+K11,0) -> 147925.2 | M11: ='Юнит 7'!W$102 -> 234275.74 | N11: ='Юнит 7'!X$102 -> -2388 | O11: =IFERROR(M11+N11,0) -> 231887.74 | P11: ='Юнит 7'!AB$102 -> 27919.8 | Q11: ='Юнит 7'!AE$102 -> 22767.8 | R11: ='Юнит 7'!AC$102 -> 84374.68 | S11: ='Юнит 7'!AI$102 -> 1132.46 | T11: 165 | U11: ='Юнит 7'!AJ$102 -> 0 | V11: 497.76 | W11: ='Юнит 7'!AF$102 -> 16968 | X11: ='Юнит 7'!AG$102 -> 25029 | Y11: ='Юнит 7'!AH118 -> 0 | Z11: 1478.16 | AB11: =O11-SUM(P11:Y11)+AA11 -> 53033.24 | AC11: =O11-SUM(P11:Z11)+AA11 -> 51555.08 | AE11: =P11/O11 -> 0.12040223 | AF11: =AC11/P11 -> 1.8465419 | AG11: =AC11/O11 -> 0.22232775 | AH11: =(W11+X11+Y11)/O11 -> 0.18110919
B12: Февраль 3 | C12: 16-22.02 | D12: 8 | F12: =IFERROR(O12-SUM(Q12:W12)+AA12,0) -> 168699.24 | G12: ='Юнит 8'!L$45 -> 640 | H12: ='Юнит 8'!Q$45 -> 332 | I12: ='Юнит 8'!R$45 -> -3 | J12: ='Юнит 8'!T$102 -> 231517.83 | K12: ='Юнит 8'!U$102 -> -2178 | L12: =IFERROR(J12+K12,0) -> 229339.83 | M12: ='Юнит 8'!W$102 -> 360665.46 | N12: ='Юнит 8'!X$102 -> -3466 | O12: =IFERROR(M12+N12,0) -> 357199.46 | P12: ='Юнит 8'!AB$102 -> 44360.03 | Q12: ='Юнит 8'!AE$102 -> 32716.08 | R12: ='Юнит 8'!AC$102 -> 132861.28 | S12: ='Юнит 8'!AI$102 -> 1284.66 | T12: 1905 | U12: ='Юнит 8'!AJ$102 -> 294 | V12: 439.2 | W12: ='Юнит 8'!AF$102 -> 19000 | X12: ='Юнит 8'!AG$102 -> 43359 | Y12: ='Юнит 8'!AH119 -> 0 | Z12: 2261.26 | AB12: =O12-SUM(P12:Y12)+AA12 -> 80980.21 | AC12: =O12-SUM(P12:Z12)+AA12 -> 78718.95 | AE12: =P12/O12 -> 0.1241884 | AF12: =AC12/P12 -> 1.7745468 | AG12: =AC12/O12 -> 0.22037813 | AH12: =(W12+X12+Y12)/O12 -> 0.17457753
B13: Февраль 4 | C13: 23.02-01.03 | D13: 9 | F13: =IFERROR(O13-SUM(Q13:W13)+AA13,0) -> 214108.03 | G13: ='Юнит 9'!L$45 -> 632 | H13: ='Юнит 9'!Q$45 -> 399 | I13: ='Юнит 9'!R$45 -> -9 | J13: ='Юнит 9'!T$102 -> 296481.4 | K13: ='Юнит 9'!U$102 -> -6522 | L13: =IFERROR(J13+K13,0) -> 289959.4 | M13: ='Юнит 9'!W$102 -> 464446.44 | N13: ='Юнит 9'!X$102 -> -10316 | O13: =IFERROR(M13+N13,0) -> 454130.44 | P13: ='Юнит 9'!AB$102 -> 51789.51 | Q13: ='Юнит 9'!AE$102 -> 45998.58 | R13: ='Юнит 9'!AC$102 -> 171766.49 | S13: ='Юнит 9'!AI$102 -> 1545.78 | T13: 465 | U13: ='Юнит 9'!AJ$102 -> 0 | V13: 58.56 | W13: ='Юнит 9'!AF$102 -> 20188 | X13: ='Юнит 9'!AG$102 -> 49771 | Y13: ='Юнит 9'!AH120 -> 0 | Z13: 2924.69 | AB13: =O13-SUM(P13:Y13)+AA13 -> 112547.52 | AC13: =O13-SUM(P13:Z13)+AA13 -> 109622.83 | AE13: =P13/O13 -> 0.11404105 | AF13: =AC13/P13 -> 2.1166995 | AG13: =AC13/O13 -> 0.24139062 | AH13: =(W13+X13+Y13)/O13 -> 0.15405045
B14: Март 1 очки | C14: 02-08.03 | D14: 10 | F14: =IFERROR(O14-SUM(Q14:W14)+AA14,0) -> 183388.28 | G14: ='Юнит 10'!L$58 -> 833 | H14: ='Юнит 10'!Q$58 -> 382 | I14: ='Юнит 10'!R$58 -> -8 | J14: ='Юнит 10'!T$58 -> 300005.62 | K14: ='Юнит 10'!U$58 -> -6272.41 | L14: =IFERROR(J14+K14,0) -> 293733.21 | M14: ='Юнит 10'!W$58 -> 466843.39 | N14: ='Юнит 10'!X$58 -> -9947.95 | O14: =IFERROR(M14+N14,0) -> 456895.44 | P14: ='Юнит 10'!AB$58 -> 49184.92 | Q14: ='Юнит 10'!AE$58 -> 46676.69 | R14: ='Юнит 10'!AC$58 -> 172521.44 | S14: ='Юнит 10'!AI$58 -> 2108.03 | T14: 735 | U14: ='Юнит 10'!AJ$58 -> 30 | W14: ='Юнит 10'!AF$58 -> 51436 | X14: ='Юнит 10'!AG$58 -> 14284 | Y14: ='Юнит 10'!AH134 -> 0 | Z14: 3000.76 | AB14: =O14-SUM(P14:Y14)+AA14 -> 119919.36 | AC14: =O14-SUM(P14:Z14)+AA14 -> 116918.6 | AD14: =SUM(AC14:AC21) -> 1089861.5 | AE14: =P14/O14 -> 0.10765028 | AF14: =AC14/P14 -> 2.3771229 | AG14: =AC14/O14 -> 0.25589794 | AH14: =(W14+X14+Y14)/O14 -> 0.14384035
B15: Март 1 шапки | C15: 02-08.03 | D15: 10 | F15: =IFERROR(O15-SUM(Q15:W15)+AA15,0) -> -3920 | G15: ='Юнит 10'!L$68 -> 2 | H15: ='Юнит 10'!Q$68 -> 0 | I15: ='Юнит 10'!R$68 -> 0 | J15: ='Юнит 10'!T$68 -> 0 | K15: ='Юнит 10'!U$68 -> 0 | L15: =IFERROR(J15+K15,0) -> 0 | M15: ='Юнит 10'!W$68 -> 0 | N15: ='Юнит 10'!X$68 -> 0 | O15: =IFERROR(M15+N15,0) -> 0 | P15: ='Юнит 10'!AB$68 -> 0 | Q15: ='Юнит 10'!AE$68 -> 0 | R15: ='Юнит 10'!AC$68 -> 0 | S15: ='Юнит 10'!AI$68 -> 0 | U15: ='Юнит 10'!AJ$68 -> 0 | W15: ='Юнит 10'!AF$68 -> 3920 | X15: ='Юнит 10'!AG$68 -> 0 | Y15: ='Юнит 10'!AH135 -> 0 | Z15: =IFERROR((L15)*0.01,0) -> 0 | AB15: =O15-SUM(P15:Y15)+AA15 -> -3920 | AC15: =O15-SUM(P15:Z15)+AA15 -> -3920 | AE15: =P15/O15 -> #DIV/0! | AF15: =AC15/P15 -> #DIV/0! | AG15: =AC15/O15 -> #DIV/0! | AH15: =(W15+X15+Y15)/O15 -> #DIV/0!
B16: Март 2 очки | C16: 09-15.03 | D16: 11 | F16: =IFERROR(O16-SUM(Q16:W16)+AA16,0) -> 370668.61 | G16: ='Юнит 11'!L$58 -> 1503 | H16: ='Юнит 11'!Q$58 -> 797 | I16: ='Юнит 11'!R$58 -> -13 | J16: ='Юнит 11'!T$58 -> 612594.65 | K16: ='Юнит 11'!U$58 -> -10314 | L16: =IFERROR(J16+K16,0) -> 602280.65 | M16: ='Юнит 11'!W$58 -> 943118.99 | N16: ='Юнит 11'!X$58 -> -15997 | O16: =IFERROR(M16+N16,0) -> 927121.99 | P16: ='Юнит 11'!AB$58 -> 103751.9 | Q16: ='Юнит 11'!AE$58 -> 97317.48 | R16: ='Юнит 11'!AC$58 -> 349180.58 | S16: ='Юнит 11'!AI$58 -> 1851.28 | T16: 165 | U16: ='Юнит 11'!AJ$58 -> 0 | V16: 2357.04 | W16: ='Юнит 11'!AF$58 -> 105582 | X16: ='Юнит 11'!AG$58 -> 0 | Y16: ='Юнит 11'!AH136 -> 0 | Z16: 5817.33 | AB16: =O16-SUM(P16:Y16)+AA16 -> 266916.71 | AC16: =O16-SUM(P16:Z16)+AA16 -> 261099.38 | AE16: =P16/O16 -> 0.1119075 | AF16: =AC16/P16 -> 2.5165744 | AG16: =AC16/O16 -> 0.28162354 | AH16: =(W16+X16+Y16)/O16 -> 0.11388145
B17: Март 2 шапки | C17: 09-15.03 | D17: 11 | F17: =IFERROR(O17-SUM(Q17:W17)+AA17,0) -> -12473.82 | G17: ='Юнит 11'!L$68 -> 16 | H17: ='Юнит 11'!Q$68 -> 0 | I17: ='Юнит 11'!R$68 -> 0 | J17: ='Юнит 11'!T$68 -> 0 | K17: ='Юнит 11'!U$68 -> 0 | L17: =IFERROR(J17+K17,0) -> 0 | M17: ='Юнит 11'!W$68 -> 0 | N17: ='Юнит 11'!X$68 -> 0 | O17: =IFERROR(M17+N17,0) -> 0 | P17: ='Юнит 11'!AB$68 -> 0 | Q17: ='Юнит 11'!AE$68 -> 198.82 | R17: ='Юнит 11'!AC$68 -> 0 | S17: ='Юнит 11'!AI$68 -> 0 | T17: 195 | U17: ='Юнит 11'!AJ$68 -> 0 | W17: ='Юнит 11'!AF$68 -> 12080 | X17: ='Юнит 11'!AG$68 -> 0 | Y17: ='Юнит 11'!AH137 -> 0 | Z17: =IFERROR((L17)*0.01,0) -> 0 | AB17: =O17-SUM(P17:Y17)+AA17 -> -12473.82 | AC17: =O17-SUM(P17:Z17)+AA17 -> -12473.82 | AE17: =P17/O17 -> #DIV/0! | AF17: =AC17/P17 -> #DIV/0! | AG17: =AC17/O17 -> #DIV/0! | AH17: =(W17+X17+Y17)/O17 -> #DIV/0!
B18: Март 3 очки | C18: 16-22.03 | D18: 12 | F18: =IFERROR(O18-SUM(Q18:W18)+AA18,0) -> 460743.49 | G18: ='Юнит 12'!L$58 -> 1912 | H18: ='Юнит 12'!Q$58 -> 947 | I18: ='Юнит 12'!R$58 -> -22 | J18: ='Юнит 12'!T$58 -> 770335.74 | K18: ='Юнит 12'!U$58 -> -17585.11 | L18: =IFERROR(J18+K18,0) -> 752750.63 | M18: ='Юнит 12'!W$58 -> 1160661.8 | N18: ='Юнит 12'!X$58 -> -26564.08 | O18: =IFERROR(M18+N18,0) -> 1134097.7 | P18: ='Юнит 12'!AB$58 -> 122764.06 | Q18: ='Юнит 12'!AE$58 -> 116519.87 | R18: ='Юнит 12'!AC$58 -> 428981.74 | S18: ='Юнит 12'!AI$58 -> 2973.3315 | T18: 300 | U18: ='Юнит 12'!AJ$58 -> 0 | V18: 3528.24 | W18: ='Юнит 12'!AF$58 -> 121051 | X18: ='Юнит 12'!AG$58 -> 0 | Y18: ='Юнит 12'!AH138 -> 0 | Z18: =7525.32*O18/(O18+O19) -> 7481.2543 | AB18: =O18-SUM(P18:Y18)+AA18 -> 337979.43 | AC18: =O18-SUM(P18:Z18)+AA18 -> 330498.17 | AE18: =P18/O18 -> 0.10824823 | AF18: =AC18/P18 -> 2.6921411 | AG18: =AC18/O18 -> 0.2914195 | AH18: =(W18+X18+Y18)/O18 -> 0.10673772
B19: Март 3 шапки | C19: 16-22.03 | D19: 12 | F19: =IFERROR(O19-SUM(Q19:W19)+AA19,0) -> -2556.9685 | G19: ='Юнит 12'!L$68 -> 4 | H19: ='Юнит 12'!Q$68 -> 3 | I19: ='Юнит 12'!R$68 -> 0 | J19: ='Юнит 12'!T$68 -> 4468 | K19: ='Юнит 12'!U$68 -> 0 | L19: =IFERROR(J19+K19,0) -> 4468 | M19: ='Юнит 12'!W$68 -> 6680 | N19: ='Юнит 12'!X$68 -> 0 | O19: =IFERROR(M19+N19,0) -> 6680 | P19: ='Юнит 12'!AB$68 -> 1187.34 | Q19: ='Юнит 12'!AE$68 -> 2459.75 | R19: ='Юнит 12'!AC$68 -> 2953.15 | S19: ='Юнит 12'!AI$68 -> 3.7884878 | T19: 75 | U19: ='Юнит 12'!AJ$68 -> 3745.28 | W19: ='Юнит 12'!AF$68 -> 0 | X19: ='Юнит 12'!AG$68 -> 0 | Y19: ='Юнит 12'!AH139 -> 0 | Z19: =7525.32*O19/(O18+O19) -> 44.065675 | AB19: =O19-SUM(P19:Y19)+AA19 -> -3744.3085 | AC19: =O19-SUM(P19:Z19)+AA19 -> -3788.3742 | AE19: =P19/O19 -> 0.17774551 | AF19: =AC19/P19 -> -3.1906397 | AG19: =AC19/O19 -> -0.56712188 | AH19: =(W19+X19+Y19)/O19 -> 0
B20: Март 4 очки | C20: 23-29.03 | D20: 13 | F20: =IFERROR(O20-SUM(Q20:W20)+AA20,0) -> 545173.78 | G20: ='Юнит 13'!L$58 -> 1741 | H20: ='Юнит 13'!Q$58 -> 1033 | I20: ='Юнит 13'!R$58 -> -22 | J20: ='Юнит 13'!T$58 -> 894331.41 | K20: ='Юнит 13'!U$58 -> -18419.39 | L20: =IFERROR(J20+K20,0) -> 875912.02 | M20: ='Юнит 13'!W$58 -> 1343124.6 | N20: ='Юнит 13'!X$58 -> -28012.89 | O20: =IFERROR(M20+N20,0) -> 1315111.7 | P20: ='Юнит 13'!AB$58 -> 133965.07 | Q20: ='Юнит 13'!AE$58 -> 138495.53 | R20: ='Юнит 13'!AC$58 -> 495515.23 | S20: ='Юнит 13'!AI$58 -> 5304.7482 | T20: 30 | U20: ='Юнит 13'!AJ$58 -> 70 | V20: 1610.4 | W20: ='Юнит 13'!AF$58 -> 128912 | X20: ='Юнит 13'!AG$58 -> 0 | Y20: ='Юнит 13'!AH140 -> 0 | Z20: 8476.9 | AB20: =O20-SUM(P20:Y20)+AA20 -> 411208.71 | AC20: =O20-SUM(P20:Z20)+AA20 -> 402731.81 | AE20: =P20/O20 -> 0.10186593 | AF20: =AC20/P20 -> 3.0062449 | AG20: =AC20/O20 -> 0.30623392 | AH20: =(W20+X20+Y20)/O20 -> 0.098023613
B21: Март 4 шапки | C21: 23-29.03 | D21: 13 | F21: =IFERROR(O21-SUM(Q21:W21)+AA21,0) -> -1204.2518 | G21: ='Юнит 13'!L$68 -> 0 | H21: ='Юнит 13'!Q$68 -> 0 | I21: ='Юнит 13'!R$68 -> 0 | J21: ='Юнит 13'!T$68 -> 0 | K21: ='Юнит 13'!U$68 -> 0 | L21: =IFERROR(J21+K21,0) -> 0 | M21: ='Юнит 13'!W$68 -> 0 | N21: ='Юнит 13'!X$68 -> 0 | O21: =IFERROR(M21+N21,0) -> 0 | P21: ='Юнит 13'!AB$68 -> 0 | Q21: ='Юнит 13'!AE$68 -> 1195.55 | R21: ='Юнит 13'!AC$68 -> 0 | S21: ='Юнит 13'!AI$68 -> 8.7017952 | U21: ='Юнит 13'!AJ$68 -> 0 | W21: ='Юнит 13'!AF$68 -> 0 | X21: ='Юнит 13'!AG$68 -> 0 | Y21: ='Юнит 13'!AH141 -> 0 | Z21: =IFERROR((L21)*0.01,0) -> 0 | AB21: =O21-SUM(P21:Y21)+AA21 -> -1204.2518 | AC21: =O21-SUM(P21:Z21)+AA21 -> -1204.2518 | AE21: =P21/O21 -> #DIV/0! | AF21: =AC21/P21 -> #DIV/0! | AG21: =AC21/O21 -> #DIV/0! | AH21: =(W21+X21+Y21)/O21 -> #DIV/0!
B22: Апрель 1 очки | C22: 30.03-05.04 | D22: 14 | F22: =IFERROR(O22-SUM(Q22:W22)+AA22,0) -> 458789.03 | G22: ='Юнит 14'!L$58 -> 1458 | H22: ='Юнит 14'!Q$58 -> 957 | I22: ='Юнит 14'!R$58 -> -29 | J22: ='Юнит 14'!T$58 -> 818298.19 | K22: ='Юнит 14'!U$58 -> -24782 | L22: =IFERROR(J22+K22,0) -> 793516.19 | M22: ='Юнит 14'!W$58 -> 1234216.1 | N22: ='Юнит 14'!X$58 -> -37862 | O22: =IFERROR(M22+N22,0) -> 1196354.1 | P22: ='Юнит 14'!AB$58 -> 123010.15 | Q22: ='Юнит 14'!AE$58 -> 131915.07 | R22: ='Юнит 14'!AC$58 -> 450831.19 | S22: ='Юнит 14'!AI$58 -> 7319.828 | U22: ='Юнит 14'!AJ$58 -> 100 | V22: 1464 | W22: ='Юнит 14'!AF$58 -> 145935 | X22: ='Юнит 14'!AG$58 -> 788 | Y22: ='Юнит 14'!AH142 -> 0 | Z22: =IFERROR((L22)*0.01,0) -> 7935.1619 | AB22: =O22-SUM(P22:Y22)+AA22 -> 334990.88 | AC22: =O22-SUM(P22:Z22)+AA22 -> 327055.72 | AD22: =SUM(AC22:AC31) -> 992641.16 | AE22: =P22/O22 -> 0.10282085 | AF22: =AC22/P22 -> 2.6587702 | AG22: =AC22/O22 -> 0.27337702 | AH22: =(W22+X22+Y22)/O22 -> 0.12264178
B23: Апрель 1 шапки | C23: 30.03-05.04 | D23: 14 | F23: =IFERROR(O23-SUM(Q23:W23)+AA23,0) -> -211.39204 | G23: ='Юнит 14'!L$68 -> 1 | H23: ='Юнит 14'!Q$68 -> 0 | I23: ='Юнит 14'!R$68 -> 0 | J23: ='Юнит 14'!T$68 -> 0 | K23: ='Юнит 14'!U$68 -> 0 | L23: =IFERROR(J23+K23,0) -> 0 | M23: ='Юнит 14'!W$68 -> 0 | N23: ='Юнит 14'!X$68 -> 0 | O23: =IFERROR(M23+N23,0) -> 0 | P23: ='Юнит 14'!AB$68 -> 0 | Q23: ='Юнит 14'!AE$68 -> 198.82 | R23: ='Юнит 14'!AC$68 -> 0 | S23: ='Юнит 14'!AI$68 -> 12.572039 | U23: ='Юнит 14'!AJ$68 -> 0 | W23: ='Юнит 14'!AF$68 -> 0 | X23: ='Юнит 14'!AG$68 -> 0 | Y23: ='Юнит 14'!AH143 -> 0 | Z23: =IFERROR((L23)*0.01,0) -> 0 | AB23: =O23-SUM(P23:Y23)+AA23 -> -211.39204 | AC23: =O23-SUM(P23:Z23)+AA23 -> -211.39204 | AE23: =P23/O23 -> #DIV/0! | AF23: =AC23/P23 -> #DIV/0! | AG23: =AC23/O23 -> #DIV/0! | AH23: =(W23+X23+Y23)/O23 -> #DIV/0!
B24: Апрель 2 очки | C24: 06-12.04 | D24: 15 | F24: =IFERROR(O24-SUM(Q24:W24)+AA24,0) -> 308596.97 | G24: ='Юнит 15'!L$58 -> 1031 | H24: ='Юнит 15'!Q$58 -> 649 | I24: ='Юнит 15'!R$58 -> -15 | J24: ='Юнит 15'!T$58 -> 565037.61 | K24: ='Юнит 15'!U$58 -> -13075 | L24: =IFERROR(J24+K24,0) -> 551962.61 | M24: ='Юнит 15'!W$58 -> 842036.95 | N24: ='Юнит 15'!X$58 -> -19867 | O24: =IFERROR(M24+N24,0) -> 822169.95 | P24: ='Юнит 15'!AB$58 -> 84927.51 | Q24: ='Юнит 15'!AE$58 -> 91879.1 | R24: ='Юнит 15'!AC$58 -> 310403.9 | S24: ='Юнит 15'!AI$58 -> 6994.9839 | U24: ='Юнит 15'!AJ$58 -> 30 | W24: ='Юнит 15'!AF$58 -> 104265 | X24: ='Юнит 15'!AG$58 -> 0 | Y24: ='Юнит 15'!AH144 -> 0 | Z24: =IFERROR((L24)*0.01,0) -> 5519.6261 | AB24: =O24-SUM(P24:Y24)+AA24 -> 223669.46 | AC24: =O24-SUM(P24:Z24)+AA24 -> 218149.83 | AE24: =P24/O24 -> 0.10329678 | AF24: =AC24/P24 -> 2.5686592 | AG24: =AC24/O24 -> 0.26533423 | AH24: =(W24+X24+Y24)/O24 -> 0.12681685
B25: Апрель 2 шапки | C25: 06-12.04 | D25: 15 | F25: =IFERROR(O25-SUM(Q25:W25)+AA25,0) -> -163.32611 | G25: ='Юнит 15'!L$68 -> 0 | H25: ='Юнит 15'!Q$68 -> 0 | I25: ='Юнит 15'!R$68 -> 0 | J25: ='Юнит 15'!T$68 -> 0 | K25: ='Юнит 15'!U$68 -> 0 | L25: =IFERROR(J25+K25,0) -> 0 | M25: ='Юнит 15'!W$68 -> 0 | N25: ='Юнит 15'!X$68 -> 0 | O25: =IFERROR(M25+N25,0) -> 0 | P25: ='Юнит 15'!AB$68 -> 0 | Q25: ='Юнит 15'!AE$68 -> 148.68 | R25: ='Юнит 15'!AC$68 -> 0 | S25: ='Юнит 15'!AI$68 -> 14.646114 | U25: ='Юнит 15'!AJ$68 -> 0 | W25: ='Юнит 15'!AF$68 -> 0 | X25: ='Юнит 15'!AG$68 -> 0 | Y25: ='Юнит 15'!AH145 -> 0 | Z25: =IFERROR((L25)*0.01,0) -> 0 | AB25: =O25-SUM(P25:Y25)+AA25 -> -163.32611 | AC25: =O25-SUM(P25:Z25)+AA25 -> -163.32611 | AE25: =P25/O25 -> #DIV/0! | AF25: =AC25/P25 -> #DIV/0! | AG25: =AC25/O25 -> #DIV/0! | AH25: =(W25+X25+Y25)/O25 -> #DIV/0!
B26: Апрель 3 очки | C26: 13-19.04 | D26: 16 | F26: =IFERROR(O26-SUM(Q26:W26)+AA26,0) -> 274995.95 | G26: ='Юнит 16'!L$58 -> 1081 | H26: ='Юнит 16'!Q$58 -> 638 | I26: ='Юнит 16'!R$58 -> -9 | J26: ='Юнит 16'!T$58 -> 548435.46 | K26: ='Юнит 16'!U$58 -> -7418.64 | L26: =IFERROR(J26+K26,0) -> 541016.82 | M26: ='Юнит 16'!W$58 -> 817854.85 | N26: ='Юнит 16'!X$58 -> -11109.77 | O26: =IFERROR(M26+N26,0) -> 806745.08 | P26: ='Юнит 16'!AB$58 -> 85073.03 | Q26: ='Юнит 16'!AE$58 -> 97296.2 | R26: ='Юнит 16'!AC$58 -> 303420.29 | S26: ='Юнит 16'!AI$58 -> 6515.645 | U26: ='Юнит 16'!AJ$58 -> 300 | W26: ='Юнит 16'!AF$58 -> 124217 | X26: ='Юнит 16'!AG$58 -> 0 | Y26: ='Юнит 16'!AH146 -> 0 | Z26: =IFERROR((L26)*0.01,0) -> 5410.1682 | AB26: =O26-SUM(P26:Y26)+AA26 -> 189922.92 | AC26: =O26-SUM(P26:Z26)+AA26 -> 184512.75 | AE26: =P26/O26 -> 0.10545218 | AF26: =AC26/P26 -> 2.1688748 | AG26: =AC26/O26 -> 0.22871258 | AH26: =(W26+X26+Y26)/O26 -> 0.15397305
B27: Апрель 3 шапки | C27: 13-19.04 | D27: 16 | F27: =IFERROR(O27-SUM(Q27:W27)+AA27,0) -> -14.815018 | G27: ='Юнит 16'!L$68 -> 0 | H27: ='Юнит 16'!Q$68 -> 0 | I27: ='Юнит 16'!R$68 -> 0 | J27: ='Юнит 16'!T$68 -> 0 | K27: ='Юнит 16'!U$68 -> 0 | L27: =IFERROR(J27+K27,0) -> 0 | M27: ='Юнит 16'!W$68 -> 0 | N27: ='Юнит 16'!X$68 -> 0 | O27: =IFERROR(M27+N27,0) -> 0 | P27: ='Юнит 16'!AB$68 -> 0 | Q27: ='Юнит 16'!AE$68 -> 0 | R27: ='Юнит 16'!AC$68 -> 0 | S27: ='Юнит 16'!AI$68 -> 14.815018 | U27: ='Юнит 16'!AJ$68 -> 0 | W27: ='Юнит 16'!AF$68 -> 0 | X27: ='Юнит 16'!AG$68 -> 0 | Y27: ='Юнит 16'!AH147 -> 0 | Z27: =IFERROR((L27)*0.01,0) -> 0 | AB27: =O27-SUM(P27:Y27)+AA27 -> -14.815018 | AC27: =O27-SUM(P27:Z27)+AA27 -> -14.815018 | AE27: =P27/O27 -> #DIV/0! | AF27: =AC27/P27 -> #DIV/0! | AG27: =AC27/O27 -> #DIV/0! | AH27: =(W27+X27+Y27)/O27 -> #DIV/0!
B28: Апрель 4 очки | C28: 20-26.04 | D28: 17 | F28: =IFERROR(O28-SUM(Q28:W28)+AA28,0) -> 208993.55 | G28: ='Юнит 17'!L$58 -> 765 | H28: ='Юнит 17'!Q$58 -> 508 | I28: ='Юнит 17'!R$58 -> -5 | J28: ='Юнит 17'!T$58 -> 446671.25 | K28: ='Юнит 17'!U$58 -> -4383 | L28: =IFERROR(J28+K28,0) -> 442288.25 | M28: ='Юнит 17'!W$58 -> 653283.95 | N28: ='Юнит 17'!X$58 -> -6573 | O28: =IFERROR(M28+N28,0) -> 646710.95 | P28: ='Юнит 17'!AB$58 -> 66479.62 | Q28: ='Юнит 17'!AE$58 -> 71227.13 | R28: ='Юнит 17'!AC$58 -> 244596.21 | S28: ='Юнит 17'!AI$58 -> 6101.0598 | U28: ='Юнит 17'!AJ$58 -> 260 | W28: ='Юнит 17'!AF$58 -> 115533 | X28: ='Юнит 17'!AG$58 -> 0 | Y28: ='Юнит 17'!AH148 -> 0 | Z28: =IFERROR((L28)*0.01,0) -> 4422.8825 | AB28: =O28-SUM(P28:Y28)+AA28 -> 142513.93 | AC28: =O28-SUM(P28:Z28)+AA28 -> 138091.05 | AE28: =P28/O28 -> 0.1027965 | AF28: =AC28/P28 -> 2.0771937 | AG28: =AC28/O28 -> 0.21352823 | AH28: =(W28+X28+Y28)/O28 -> 0.17864704
B29: Апрель 4 шапки | C29: 20-26.04 | D29: 17 | F29: =IFERROR(O29-SUM(Q29:W29)+AA29,0) -> -14.640201 | G29: ='Юнит 17'!L$68 -> 0 | H29: ='Юнит 17'!Q$68 -> 0 | I29: ='Юнит 17'!R$68 -> 0 | J29: ='Юнит 17'!T$68 -> 0 | K29: ='Юнит 17'!U$68 -> 0 | L29: =IFERROR(J29+K29,0) -> 0 | M29: ='Юнит 17'!W$68 -> 0 | N29: ='Юнит 17'!X$68 -> 0 | O29: =IFERROR(M29+N29,0) -> 0 | P29: ='Юнит 17'!AB$68 -> 0 | Q29: ='Юнит 17'!AE$68 -> 0 | R29: ='Юнит 17'!AC$68 -> 0 | S29: ='Юнит 17'!AI$68 -> 14.640201 | U29: ='Юнит 17'!AJ$68 -> 0 | W29: ='Юнит 17'!AF$68 -> 0 | X29: ='Юнит 17'!AG$68 -> 0 | Y29: ='Юнит 17'!AH149 -> 0 | Z29: =IFERROR((L29)*0.01,0) -> 0 | AB29: =O29-SUM(P29:Y29)+AA29 -> -14.640201 | AC29: =O29-SUM(P29:Z29)+AA29 -> -14.640201 | AE29: =P29/O29 -> #DIV/0! | AF29: =AC29/P29 -> #DIV/0! | AG29: =AC29/O29 -> #DIV/0! | AH29: =(W29+X29+Y29)/O29 -> #DIV/0!
B30: Апрель 5 очки | C30: 27.04-03.05 | D30: 18 | F30: =IFERROR(O30-SUM(Q30:W30)+AA30,0) -> 189562.38 | G30: ='Юнит 18'!L$58 -> 792 | H30: ='Юнит 18'!Q$58 -> 468 | I30: ='Юнит 18'!R$58 -> -10 | J30: ='Юнит 18'!T$58 -> 410333.48 | K30: ='Юнит 18'!U$58 -> -8792.85 | L30: =IFERROR(J30+K30,0) -> 401540.63 | M30: ='Юнит 18'!W$58 -> 576307.26 | N30: ='Юнит 18'!X$58 -> -12539.93 | O30: =IFERROR(M30+N30,0) -> 563767.33 | P30: ='Юнит 18'!AB$58 -> 60278.12 | Q30: ='Юнит 18'!AE$58 -> 62131.89 | R30: ='Юнит 18'!AC$58 -> 213539.48 | S30: ='Юнит 18'!AI$58 -> 5723.5761 | U30: ='Юнит 18'!AJ$58 -> 827 | W30: ='Юнит 18'!AF$58 -> 91983 | X30: ='Юнит 18'!AG$58 -> 0 | Y30: ='Юнит 18'!AH150 -> 0 | Z30: =IFERROR((L30)*0.01,0) -> 4015.4063 | AB30: =O30-SUM(P30:Y30)+AA30 -> 129284.26 | AC30: =O30-SUM(P30:Z30)+AA30 -> 125268.86 | AE30: =P30/O30 -> 0.10692021 | AF30: =AC30/P30 -> 2.0781812 | AG30: =AC30/O30 -> 0.22219957 | AH30: =(W30+X30+Y30)/O30 -> 0.16315773
B31: Апрель 5 шапки | C31: 27.04-03.05 | D31: 18 | F31: =IFERROR(O31-SUM(Q31:W31)+AA31,0) -> -32.863858 | G31: ='Юнит 18'!L$68 -> 0 | H31: ='Юнит 18'!Q$68 -> 0 | I31: ='Юнит 18'!R$68 -> 0 | J31: ='Юнит 18'!T$68 -> 0 | K31: ='Юнит 18'!U$68 -> 0 | L31: =IFERROR(J31+K31,0) -> 0 | M31: ='Юнит 18'!W$68 -> 0 | N31: ='Юнит 18'!X$68 -> 0 | O31: =IFERROR(M31+N31,0) -> 0 | P31: ='Юнит 18'!AB$68 -> 0 | Q31: ='Юнит 18'!AE$68 -> 18 | R31: ='Юнит 18'!AC$68 -> 0 | S31: ='Юнит 18'!AI$68 -> 14.863858 | U31: ='Юнит 18'!AJ$68 -> 0 | W31: ='Юнит 18'!AF$68 -> 0 | X31: ='Юнит 18'!AG$68 -> 0 | Y31: ='Юнит 18'!AH151 -> 0 | Z31: =IFERROR((L31)*0.01,0) -> 0 | AB31: =O31-SUM(P31:Y31)+AA31 -> -32.863858 | AC31: =O31-SUM(P31:Z31)+AA31 -> -32.863858 | AE31: =P31/O31 -> #DIV/0! | AF31: =AC31/P31 -> #DIV/0! | AG31: =AC31/O31 -> #DIV/0! | AH31: =(W31+X31+Y31)/O31 -> #DIV/0!
B32: Май 1 очки | C32: 04-10.05 | D32: 19 | F32: =IFERROR(O32-SUM(Q32:W32)+AA32,0) -> 294239.53 | G32: ='Юнит 19'!L$64 -> 1366 | H32: ='Юнит 19'!Q$64 -> 712 | I32: ='Юнит 19'!R$64 -> -12 | J32: ='Юнит 19'!T$64 -> 623893.13 | K32: ='Юнит 19'!U$64 -> -10793 | L32: =IFERROR(J32+K32,0) -> 613100.13 | M32: ='Юнит 19'!W$64 -> 864482.03 | N32: ='Юнит 19'!X$64 -> -14966 | O32: =IFERROR(M32+N32,0) -> 849516.03 | P32: ='Юнит 19'!AB$64 -> 90756.23 | Q32: ='Юнит 19'!AE$64 -> 77440.42 | R32: ='Юнит 19'!AC$64 -> 321797.17 | S32: ='Юнит 19'!AI$64 -> 5038.9143 | T32: 435 | U32: ='Юнит 19'!AJ$64 -> 190 | W32: ='Юнит 19'!AF$64 -> 150375 | X32: ='Юнит 19'!AG$64 -> 8172 | Y32: ='Юнит 19'!AH152 -> 0 | Z32: =IFERROR((L32)*0.01,0) -> 6131.0013 | AB32: =O32-SUM(P32:Y32)+AA32 -> 195311.3 | AC32: =O32-SUM(P32:Z32)+AA32 -> 189180.29 | AE32: =P32/O32 -> 0.10683286 | AF32: =AC32/P32 -> 2.0844882 | AG32: =AC32/O32 -> 0.22269185 | AH32: =(W32+X32+Y32)/O32 -> 0.18663215
B33: Май 1 шапки | C33: 04-10.05 | D33: 19 | F33: =IFERROR(O33-SUM(Q33:W33)+AA33,0) -> -15.835683 | G33: ='Юнит 19'!L$74 -> 0 | H33: ='Юнит 19'!Q$74 -> 0 | I33: ='Юнит 19'!R$74 -> 0 | J33: ='Юнит 19'!T$74 -> 0 | K33: ='Юнит 19'!U$74 -> 0 | L33: =IFERROR(J33+K33,0) -> 0 | M33: ='Юнит 19'!W$74 -> 0 | N33: ='Юнит 19'!X$74 -> 0 | O33: =IFERROR(M33+N33,0) -> 0 | P33: ='Юнит 19'!AB$74 -> 0 | Q33: ='Юнит 19'!AE$74 -> 0 | R33: ='Юнит 19'!AC$74 -> 0 | S33: ='Юнит 19'!AI$74 -> 15.835683 | U33: ='Юнит 19'!AJ$74 -> 0 | W33: ='Юнит 19'!AF$74 -> 0 | X33: ='Юнит 19'!AG$74 -> 0 | Y33: ='Юнит 19'!AH153 -> 0 | Z33: =IFERROR((L33)*0.01,0) -> 0 | AB33: =O33-SUM(P33:Y33)+AA33 -> -15.835683 | AC33: =O33-SUM(P33:Z33)+AA33 -> -15.835683 | AE33: =P33/O33 -> #DIV/0! | AF33: =AC33/P33 -> #DIV/0! | AG33: =AC33/O33 -> #DIV/0! | AH33: =(W33+X33+Y33)/O33 -> #DIV/0!
AB39: =O39-SUM(P39:Y39)+AA39 -> 0 | AC39: =O39-SUM(P39:Z39)+AA39 -> 0 | AE39: =P39/O39 -> #DIV/0! | AF39: =AC39/P39 -> #DIV/0! | AG39: =AC39/O39 -> #DIV/0! | AH39: =(W39+X39+Y39)/O39 -> #DIV/0!
B40: Итого | F40: =SUM(F4:F39) -> 3953363.3 | G40: =SUM(G4:G39) -> 14908 | H40: =SUM(H4:H39) -> 8411 | I40: =SUM(I4:I39) -> -165 | J40: =SUM(J4:J39) -> 6990992.7 | K40: =SUM(K4:K39) -> -137350.4 | L40: =SUM(L4:L39) -> 6853642.3 | M40: =SUM(M4:M39) -> 10404154 | ... AD40: =SUM(AD4:AD39) -> 2415213.8 | AE40: =P40/O40 -> 0.10745505 | AF40: =AC40/P40 -> 2.3768004 | AG40: =AC40/O40 -> 0.25539922 | AH40: =(W40+X40+Y40)/O40 -> 0.14008976
M41: % от выручки за весь период
N42: =-N40/M40 -> 0.019883463 | P42: =P40/$O$40 -> 0.10745505 | Q42: =Q40/$O$40 -> 0.10592254 | R42: =R40/$O$40 -> 0.37631855 | S42: =S40/$O$40 -> 0.0060375441 | T42: =T40/$O$40 -> 0.00043835203 | U42: =U40/$O$40 -> 0.00057331738 | V42: =V40/$O$40 -> 0.0010852302 | W42: =W40/$O$40 -> 0.12193659 | ... Z42: =Z40/$O$40 -> 0.0066804424 | AD42: =AC40/P40 -> 2.3768004 | AE42: Маржинальность, %
W43: =(W40+X40)/O40 -> 0.14008976 | AD43: =AC40/O40 -> 0.25539922 | AE43: Рентабельность, %
B45: ЯНВАРЬ | G45: =SUM(G4:G9) -> 457 | H45: =SUM(H4:H9) -> 256 | I45: =SUM(I4:I9) -> -5 | J45: =SUM(J4:J9) -> 233222.72 | K45: =SUM(K4:K9) -> -4580 | L45: =SUM(L4:L9) -> 228642.72 | M45: =SUM(M4:M9) -> 303779.89 | N45: =SUM(N4:N9) -> -6023 | ... AA45: =SUM(AA4:AA9) -> 0 | AC45: =SUM(AC4:AC9) -> 67154.08 | AD45: =AC45/P45 -> 1.9562269
N46: =-N45/M45 -> 0.019826856 | P46: =P45/$O$45 -> 0.11528993 | Q46: =Q45/$O$45 -> 0.10403135 | R46: =R45/$O$45 -> 0.35897977 | S46: =S45/$O$45 -> 0.021195076 | T46: =T45/$O$45 -> 0 | U46: =U45/$O$45 -> 0 | V46: =V45/$O$45 -> 0.0032402273 | W46: =W45/$O$45 -> 0.075400438 | ... AA46: =AA45/$O$45 -> 0 | AC46: =AC45/O45 -> 0.22553325 | AD46: =AC45/O45 -> 0.22553325
B48: ФЕВРАЛЬ | G48: =SUM(G10:G13) -> 1946 | H48: =SUM(H10:H13) -> 1061 | I48: =SUM(I10:I13) -> -15 | J48: =SUM(J10:J13) -> 763365.39 | K48: =SUM(K10:K13) -> -10935 | L48: =SUM(L10:L13) -> 752430.39 | M48: =SUM(M10:M13) -> 1191764.6 | N48: =SUM(N10:N13) -> -17408 | ... AC48: =SUM(AC10:AC13) -> 265557.06 | AD48: =AC48/P48 -> 1.896249
N49: =-N48/M48 -> 0.014606912 | P49: =P48/$O$48 -> 0.11925113 | Q49: =Q48/$O$48 -> 0.09709752 | R49: =R48/$O$48 -> 0.37194659 | S49: =S48/$O$48 -> 0.0044486574 | T49: =T48/$O$48 -> 0.0021586289 | U49: =U48/$O$48 -> 0.00025034986 | V49: =V48/$O$48 -> 0.00097237928 | W49: =W48/$O$48 -> 0.055930202 | ... AA49: =AA48/$O$48 -> 0 | AC49: =AC48/O48 -> 0.22612984 | AD49: =AC48/O48 -> 0.22612984
B51: 11 нед очки | G51: =G16 -> 1503 | H51: =H16 -> 797 | I51: =I16 -> -13 | J51: =J16 -> 612594.65 | K51: =K16 -> -10314 | L51: =L16 -> 602280.65 | M51: =M16 -> 943118.99 | N51: =N16 -> -15997 | ... AC51: =AC16 -> 261099.38 | AD51: =AC16/P16 -> 2.5165744
N52: =-N51/$M$51 -> 0.016961805 | P52: =P51/$O$51 -> 0.1119075 | Q52: =Q51/$O$51 -> 0.10496729 | R52: =R51/$O$51 -> 0.37662852 | S52: =S51/$O$51 -> 0.001996803 | T52: =T51/$O$51 -> 0.00017797011 | U52: =U51/$O$51 -> 0 | V52: =V51/$O$51 -> 0.0025423192 | W52: =W51/$O$51 -> 0.11388145 | ... AC52: =AC51/$O$51 -> 0.28162354 | AD52: =AC16/O16 -> 0.28162354
B54: 12 нед очки | G54: =G18 -> 1912 | H54: =H18 -> 947 | I54: =I18 -> -22 | J54: =J18 -> 770335.74 | K54: =K18 -> -17585.11 | L54: =L18 -> 752750.63 | M54: =M18 -> 1160661.8 | N54: =N18 -> -26564.08 | ... AC54: =AC18 -> 330498.17 | AD54: =AC18/P18 -> 2.6921411
N55: =-N54/$M$54 -> 0.022887013 | P55: =P54/$O$54 -> 0.10824823 | Q55: =Q54/$O$54 -> 0.10274236 | R55: =R54/$O$54 -> 0.3782582 | S55: =S54/$O$54 -> 0.0026217597 | T55: =T54/$O$54 -> 0.00026452748 | U55: =U54/$O$54 -> 0 | V55: =V54/$O$54 -> 0.0031110548 | W55: =W54/$O$54 -> 0.10673772 | ... AC55: =AC54/$O$54 -> 0.2914195 | AD55: =AC18/O18 -> 0.2914195
B57: 13 нед очки | G57: =G20 -> 1741 | H57: =H20 -> 1033 | I57: =I20 -> -22 | J57: =J20 -> 894331.41 | K57: =K20 -> -18419.39 | L57: =L20 -> 875912.02 | M57: =M20 -> 1343124.6 | N57: =N20 -> -28012.89 | ... AC57: =AC20 -> 402731.81 | AD57: =AC20/P20 -> 3.0062449
N58: =-N57/$M$57 -> 0.020856509 | P58: =P57/$O$57 -> 0.10186593 | Q58: =Q57/$O$57 -> 0.10531085 | R58: =R57/$O$57 -> 0.37678566 | S58: =S57/$O$57 -> 0.0040336865 | T58: =T57/$O$57 -> 2.2811751e-05 | U58: =U57/$O$57 -> 5.3227418e-05 | V58: =V57/$O$57 -> 0.0012245348 | W58: =W57/$O$57 -> 0.098023613 | ... AC58: =AC57/$O$57 -> 0.30623392 | AD58: =AC20/O20 -> 0.30623392
B60: МАРТ очки | G60: =G14+G16+G18+G20 -> 5989 | H60: =H14+H16+H18+H20 -> 3159 | I60: =I14+I16+I18+I20 -> -65 | J60: =J14+J16+J18+J20 -> 2577267.4 | K60: =K14+K16+K18+K20 -> -52590.91 | L60: =L14+L16+L18+L20 -> 2524676.5 | M60: =M14+M16+M18+M20 -> 3913748.7 | N60: =N14+N16+N18+N20 -> -80521.92 | ... AC60: =AC14+AC16+AC18+AC20 -> 1111248 | AD60: =AC60/P60 -> 2.712571
N61: =-N60/M60 -> 0.020574116 | P61: =P60/$O60 -> 0.10687235 | Q61: =Q60/$O60 -> 0.10409235 | R61: =R60/$O60 -> 0.37727979 | S61: =S60/$O60 -> 0.0031924513 | T61: =T60/$O60 -> 0.00032087848 | U61: =U60/$O60 -> 2.6087682e-05 | V61: =V60/$O60 -> 0.0019554491 | W61: =W60/$O60 -> 0.10617191 | ... AA61: =AA60/$O60 -> 0 | AC61: =AC60/O60 -> 0.28989883 | AD61: =AC60/O60 -> 0.28989883
B63: МАРТ шапки | G63: =G15+G17+G19+G21 -> 22 | H63: =H15+H17+H19+H21 -> 3 | I63: =I15+I17+I19+I21 -> 0 | J63: =J15+J17+J19+J21 -> 4468 | K63: =K15+K17+K19+K21 -> 0 | L63: =L15+L17+L19+L21 -> 4468 | M63: =M15+M17+M19+M21 -> 6680 | N63: =N15+N17+N19+N21 -> 0 | ... AC63: =AC15+AC17+AC19+AC21 -> -21386.446 | AD63: =AC63/P63 -> -18.012066
N64: =-N63/M63 -> 0 | P64: =P63/$O63 -> 0.17774551 | Q64: =Q63/$O63 -> 0.57696407 | R64: =R63/$O63 -> 0.44208832 | S64: =S63/$O63 -> 0.0018698028 | T64: =T63/$O63 -> 0.040419162 | U64: =U63/$O63 -> 0.56067066 | V64: =V63/$O63 -> 0 | W64: =W63/$O63 -> 2.3952096 | ... AA64: =AA63/$O63 -> 0 | AC64: =AC63/O63 -> -3.2015638 | AD64: =AC63/O63 -> -3.2015638
B66: МАРТ | G66: =SUM(G14:G21) -> 6011 | H66: =SUM(H14:H21) -> 3162 | I66: =SUM(I14:I21) -> -65 | J66: =SUM(J14:J21) -> 2581735.4 | K66: =SUM(K14:K21) -> -52590.91 | L66: =SUM(L14:L21) -> 2529144.5 | M66: =SUM(M14:M21) -> 3920428.7 | N66: =SUM(N14:N21) -> -80521.92 | ... AC66: =SUM(AC14:AC21) -> 1089861.5 | AD66: =AC66/P66 -> 2.6526781
N67: =-N66/M66 -> 0.02053906 | P67: =P66/$O66 -> 0.10699564 | Q67: =Q66/$O66 -> 0.10491497 | R67: =R66/$O66 -> 0.37739253 | S67: =S66/$O66 -> 0.0031901504 | T67: =T66/$O66 -> 0.00039063448 | U67: =U66/$O66 -> 0.0010013993 | V67: =V66/$O66 -> 0.0019520474 | W67: =W66/$O66 -> 0.11015398 | ... AA67: =AA66/$O66 -> 0 | AC67: =AC66/O66 -> 0.28382499 | AD67: =AC66/O66 -> 0.28382499
B69: 14 нед очки | G69: =G22 -> 1458 | H69: =H22 -> 957 | I69: =I22 -> -29 | J69: =J22 -> 818298.19 | K69: =K22 -> -24782 | L69: =L22 -> 793516.19 | M69: =M22 -> 1234216.1 | N69: =N22 -> -37862 | ... AC69: =AC22 -> 327055.72 | AD69: =AC22/P22 -> 2.6587702
N70: =-N69/M69 -> 0.030676961 | P70: =P69/O69 -> 0.10282085 | Q70: =Q69/O69 -> 0.11026423 | R70: =R69/O69 -> 0.37683758 | S70: =S69/O69 -> 0.0061184459 | T70: =T69/O69 -> 0 | U70: =U69/O69 -> 8.3587291e-05 | V70: =V69/O69 -> 0.0012237179 | W70: =W69/O69 -> 0.12198311 | X70: =X69/O69 -> 0.00065866785 | Y70: =Y69/O69 -> 0 | Z70: =Z69/O69 -> 0.0066327869 | AA70: =AA69/O69 -> 0 | AB70: =AB69/O69 -> 0.2800098 | AC70: =AC69/O69 -> 0.27337702 | AD70: =AC22/O22 -> 0.27337702
B72: 15 нед очки | G72: =G24 -> 1031 | H72: =H24 -> 649 | I72: =I24 -> -15 | J72: =J24 -> 565037.61 | K72: =K24 -> -13075 | L72: =L24 -> 551962.61 | M72: =M24 -> 842036.95 | N72: =N24 -> -19867 | ... AC72: =AC24 -> 218149.83 | AD72: =AC24/P24 -> 2.5686592
N73: =-N72/M72 -> 0.023593976 | P73: =P72/O72 -> 0.10329678 | Q73: =Q72/O72 -> 0.11175196 | R73: =R72/O72 -> 0.37754226 | S73: =S72/O72 -> 0.0085079537 | T73: =T72/O72 -> 0 | U73: =U72/O72 -> 3.6488806e-05 | V73: =V72/O72 -> 0 | W73: =W72/O72 -> 0.12681685 | X73: =X72/O72 -> 0 | Y73: =Y72/O72 -> 0 | Z73: =Z72/O72 -> 0.0067134856 | AA73: =AA72/O72 -> 0 | AB73: =AB72/O72 -> 0.27204771 | AC73: =AC72/O72 -> 0.26533423 | AD73: =AC24/O24 -> 0.26533423
B75: 16 нед очки | G75: =G26 -> 1081 | H75: =H26 -> 638 | I75: =I26 -> -9 | J75: =J26 -> 548435.46 | K75: =K26 -> -7418.64 | L75: =L26 -> 541016.82 | M75: =M26 -> 817854.85 | N75: =N26 -> -11109.77 | ... AC75: =AC26 -> 184512.75 | AD75: =AC26/P26 -> 2.1688748
N76: =-N75/M75 -> 0.013584036 | P76: =P75/O75 -> 0.10545218 | Q76: =Q75/O75 -> 0.1206034 | R76: =R75/O75 -> 0.3761043 | S76: =S75/O75 -> 0.0080764608 | T76: =T75/O75 -> 0 | U76: =U75/O75 -> 0.00037186468 | V76: =V75/O75 -> 0 | W76: =W75/O75 -> 0.15397305 | X76: =X75/O75 -> 0 | Y76: =Y75/O75 -> 0 | Z76: =Z75/O75 -> 0.0067061682 | AA76: =AA75/O75 -> 0 | AB76: =AB75/O75 -> 0.23541875 | AC76: =AC75/O75 -> 0.22871258 | AD76: =AC26/O26 -> 0.22871258
B78: 17 нед очки | G78: =G28 -> 765 | H78: =H28 -> 508 | I78: =I28 -> -5 | J78: =J28 -> 446671.25 | K78: =K28 -> -4383 | L78: =L28 -> 442288.25 | M78: =M28 -> 653283.95 | N78: =N28 -> -6573 | ... AC78: =AC28 -> 138091.05 | AD78: =AC28/P28 -> 2.0771937
N79: =-N78/M78 -> 0.010061475 | P79: =P78/O78 -> 0.1027965 | Q79: =Q78/O78 -> 0.1101375 | R79: =R78/O78 -> 0.37821566 | S79: =S78/O78 -> 0.0094339825 | T79: =T78/O78 -> 0 | U79: =U78/O78 -> 0.00040203432 | V79: =V78/O78 -> 0 | W79: =W78/O78 -> 0.17864704 | X79: =X78/O78 -> 0 | Y79: =Y78/O78 -> 0 | Z79: =Z78/O78 -> 0.0068390407 | AA79: =AA78/O78 -> 0 | AB79: =AB78/O78 -> 0.22036728 | AC79: =AC78/O78 -> 0.21352823 | AD79: =AC28/O28 -> 0.21352823
B81: 18 нед очки | G81: =G30 -> 792 | H81: =H30 -> 468 | I81: =I30 -> -10 | J81: =J30 -> 410333.48 | K81: =K30 -> -8792.85 | L81: =L30 -> 401540.63 | M81: =M30 -> 576307.26 | N81: =N30 -> -12539.93 | ... AC81: =AC30 -> 125268.86 | AD81: =AC30/P30 -> 2.0781812
N82: =-N81/M81 -> 0.021759105 | P82: =P81/O81 -> 0.10692021 | Q82: =Q81/O81 -> 0.11020839 | R82: =R81/O81 -> 0.37877236 | S82: =S81/O81 -> 0.010152373 | T82: =T81/O81 -> 0 | U82: =U81/O81 -> 0.0014669172 | V82: =V81/O81 -> 0 | W82: =W81/O81 -> 0.16315773 | X82: =X81/O81 -> 0 | Y82: =Y81/O81 -> 0 | Z82: =Z81/O81 -> 0.007122453 | AA82: =AA81/O81 -> 0 | AB82: =AB81/O81 -> 0.22932202 | AC82: =AC81/O81 -> 0.22219957 | AD82: =AC30/O30 -> 0.22219957
B84: АПРЕЛЬ очки | G84: =G22+G24+G26+G28+G30 -> 5127 | H84: =H22+H24+H26+H28+H30 -> 3220 | I84: =I22+I24+I26+I28+I30 -> -68 | J84: =J22+J24+J26+J28+J30 -> 2788776 | K84: =K22+K24+K26+K28+K30 -> -58451.49 | L84: =L22+L24+L26+L28+L30 -> 2730324.5 | M84: =M22+M24+M26+M28+M30 -> 4123699.1 | N84: =N22+N24+N26+N28+N30 -> -87951.7 | ... AC84: =AC22+AC24+AC26+AC28+AC30 -> 993078.2 | AD84: =AC84/P84 -> 2.3657763
N85: =-N84/M84 -> 0.02132835 | P85: =P84/$O84 -> 0.10401256 | Q85: =Q84/$O84 -> 0.112606 | R85: =R84/$O84 -> 0.37732566 | S85: =S84/$O84 -> 0.008091461 | T85: =T84/$O84 -> 0 | U85: =U84/$O84 -> 0.00037589072 | V85: =V84/$O84 -> 0.00036275808 | W85: =W84/$O84 -> 0.1441946 | ... AA85: =AA84/$O84 -> 0 | AC85: =AC84/O84 -> 0.24607045 | AD85: =AC84/O84 -> 0.24607045
B87: АПРЕЛЬ шапки | G87: =G23+G25+G27+G29+G31 -> 1 | H87: =H23+H25+H27+H29+H31 -> 0 | I87: =I23+I25+I27+I29+I31 -> 0 | J87: =J23+J25+J27+J29+J31 -> 0 | K87: =K23+K25+K27+K29+K31 -> 0 | L87: =L23+L25+L27+L29+L31 -> 0 | M87: =M23+M25+M27+M29+M31 -> 0 | N87: =N23+N25+N27+N29+N31 -> 0 | ... AC87: =AC23+AC25+AC27+AC29+AC31 -> -437.03723 | AD87: =AC87/P87 -> #DIV/0!
N88: =-N87/M87 -> #DIV/0! | P88: =P87/$O87 -> #DIV/0! | Q88: =Q87/$O87 -> #DIV/0! | R88: =R87/$O87 -> #DIV/0! | S88: =S87/$O87 -> #DIV/0! | T88: =T87/$O87 -> #DIV/0! | U88: =U87/$O87 -> #DIV/0! | V88: =V87/$O87 -> #DIV/0! | W88: =W87/$O87 -> #DIV/0! | ... AA88: =AA87/$O87 -> #DIV/0! | AC88: =AC87/O87 -> #DIV/0! | AD88: =AC87/O87 -> #DIV/0!
B90: АПРЕЛЬ | G90: =SUM(G22:G31) -> 5128 | H90: =SUM(H22:H31) -> 3220 | I90: =SUM(I22:I31) -> -68 | J90: =SUM(J22:J31) -> 2788776 | K90: =SUM(K22:K31) -> -58451.49 | L90: =SUM(L22:L31) -> 2730324.5 | M90: =SUM(M22:M31) -> 4123699.1 | N90: =SUM(N22:N31) -> -87951.7 | ... AC90: =SUM(AC22:AC31) -> 992641.16 | AD90: =AC90/P90 -> 2.3647352
N91: =-N90/M90 -> 0.02132835 | P91: =P90/$O90 -> 0.10401256 | Q91: =Q90/$O90 -> 0.11269657 | R91: =R90/$O90 -> 0.37732566 | S91: =S90/$O90 -> 0.0081091869 | T91: =T90/$O90 -> 0 | U91: =U90/$O90 -> 0.00037589072 | V91: =V90/$O90 -> 0.00036275808 | W91: =W90/$O90 -> 0.1441946 | ... AA91: =AA90/$O90 -> 0 | AC91: =AC90/O90 -> 0.24596216 | AD91: =AC90/O90 -> 0.24596216
B93: 19 нед очки | G93: =G32 -> 1366 | H93: =H32 -> 712 | I93: =I32 -> -12 | J93: =J32 -> 623893.13 | K93: =K32 -> -10793 | L93: =L32 -> 613100.13 | M93: =M32 -> 864482.03 | N93: =N32 -> -14966 | ... AC93: =AC32 -> 189180.29 | AD93: =AC32/P32 -> 2.0844882
N94: =-N93/M93 -> 0.017312101 | P94: =P93/O93 -> 0.10683286 | Q94: =Q93/O93 -> 0.09115828 | R94: =R93/O93 -> 0.37880059 | S94: =S93/O93 -> 0.0059315118 | T94: =T93/O93 -> 0.00051205626 | U94: =U93/O93 -> 0.00022365676 | V94: =V93/O93 -> 0 | W94: =W93/O93 -> 0.17701255 | X94: =X93/O93 -> 0.0096195948 | Y94: =Y93/O93 -> 0 | Z94: =Z93/O93 -> 0.0072170519 | AA94: =AA93/O93 -> 0 | AB94: =AB93/O93 -> 0.2299089 | AC94: =AC93/O93 -> 0.22269185 | AD94: =AC32/O32 -> 0.22269185

Sheet АВС 20
B2: ОЧКИ
C3: Прибыль | D3: % прибыль | E3: Доля | F3: ABC прибыль | G3: ABC кол-во | J3: Кол-во | K3: % кол-во | L3: Доля | M3: ABC кол-во
B4: Черные с железкой Сул | D4: =C4/C$64 -> #DIV/0! | E4: =D4 -> #DIV/0! | F4: =IF(AND(E4<=0),"C",IF(E4<=0.8,"A",IF(E4<=0.95,"B","C"))) -> #DIV/0! | G4: =VLOOKUP(B$4:B$57,I$4:M$57,5,0) -> #DIV/0! | I4: Черные с железкой Сул | K4: =J4/J$64 -> #DIV/0! | L4: =K4 -> #DIV/0! | M4: =_xlfn.IFS(L4<80%,"A",L4<=95%,"B",L4>95%,"C") -> #DIV/0! | P4: A | Q4: 0.8
B5: Qs черн Сул | D5: =C5/C$64 -> #DIV/0! | E5: =E4+D5 -> #DIV/0! | F5: =IF(AND(E5<=0),"C",IF(E5<=0.8,"A",IF(E5<=0.95,"B","C"))) -> #DIV/0! | G5: =VLOOKUP(B$4:B$57,I$4:M$57,5,0) -> #DIV/0! | I5: Qs черн Сул | K5: =J5/J$64 -> #DIV/0! | L5: =L4+K5 -> #DIV/0! | M5: =_xlfn.IFS(L5<80%,"A",L5<=95%,"B",L5>95%,"C") -> #DIV/0! | P5: B | Q5: 0.15
B6: Qs син Сул | D6: =C6/C$64 -> #DIV/0! | E6: =E5+D6 -> #DIV/0! | F6: =IF(AND(E6<=0),"C",IF(E6<=0.8,"A",IF(E6<=0.95,"B","C"))) -> #DIV/0! | G6: =VLOOKUP(B$4:B$57,I$4:M$57,5,0) -> #DIV/0! | I6: Qs син Сул | K6: =J6/J$64 -> #DIV/0! | L6: =L5+K6 -> #DIV/0! | M6: =_xlfn.IFS(L6<80%,"A",L6<=95%,"B",L6>95%,"C") -> #DIV/0! | P6: C | Q6: 0.05
B7: Qs желт Сул | D7: =C7/C$64 -> #DIV/0! | E7: =E6+D7 -> #DIV/0! | F7: =IF(AND(E7<=0),"C",IF(E7<=0.8,"A",IF(E7<=0.95,"B","C"))) -> #DIV/0! | G7: =VLOOKUP(B$4:B$57,I$4:M$57,5,0) -> #DIV/0! | I7: Qs желт Сул | K7: =J7/J$64 -> #DIV/0! | L7: =L6+K7 -> #DIV/0! | M7: =_xlfn.IFS(L7<80%,"A",L7<=95%,"B",L7>95%,"C") -> #DIV/0!
B8: flip черные Сул | D8: =C8/C$64 -> #DIV/0! | E8: =E7+D8 -> #DIV/0! | F8: =IF(AND(E8<=0),"C",IF(E8<=0.8,"A",IF(E8<=0.95,"B","C"))) -> #DIV/0! | G8: =VLOOKUP(B$4:B$57,I$4:M$57,5,0) -> #DIV/0! | I8: flip черные Сул | K8: =J8/J$64 -> #DIV/0! | L8: =L7+K8 -> #DIV/0! | M8: =_xlfn.IFS(L8<80%,"A",L8<=95%,"B",L8>95%,"C") -> #DIV/0!
B9: flip желтые Сул | D9: =C9/C$64 -> #DIV/0! | E9: =E8+D9 -> #DIV/0! | F9: =IF(AND(E9<=0),"C",IF(E9<=0.8,"A",IF(E9<=0.95,"B","C"))) -> #DIV/0! | G9: =VLOOKUP(B$4:B$57,I$4:M$57,5,0) -> #DIV/0! | I9: flip желтые Сул | K9: =J9/J$64 -> #DIV/0! | L9: =L8+K9 -> #DIV/0! | M9: =_xlfn.IFS(L9<80%,"A",L9<=95%,"B",L9>95%,"C") -> #DIV/0!
B10: MR8854 C2 Сул | D10: =C10/C$64 -> #DIV/0! | E10: =E9+D10 -> #DIV/0! | F10: =IF(AND(E10<=0),"C",IF(E10<=0.8,"A",IF(E10<=0.95,"B","C"))) -> #DIV/0! | G10: =VLOOKUP(B$4:B$57,I$4:M$57,5,0) -> #DIV/0! | I10: MR8854 C2 Сул | K10: =J10/J$64 -> #DIV/0! | L10: =L9+K10 -> #DIV/0! | M10: =_xlfn.IFS(L10<80%,"A",L10<=95%,"B",L10>95%,"C") -> #DIV/0!
B11: MR 1819 черн | D11: =C11/C$64 -> #DIV/0! | E11: =E10+D11 -> #DIV/0! | F11: =IF(AND(E11<=0),"C",IF(E11<=0.8,"A",IF(E11<=0.95,"B","C"))) -> #DIV/0! | G11: =VLOOKUP(B$4:B$57,I$4:M$57,5,0) -> #DIV/0! | I11: MR 1819 черн | K11: =J11/J$64 -> #DIV/0! | L11: =L10+K11 -> #DIV/0! | M11: =_xlfn.IFS(L11<80%,"A",L11<=95%,"B",L11>95%,"C") -> #DIV/0!
B12: MR 1819 корич | D12: =C12/C$64 -> #DIV/0! | E12: =E11+D12 -> #DIV/0! | F12: =IF(AND(E12<=0),"C",IF(E12<=0.8,"A",IF(E12<=0.95,"B","C"))) -> #DIV/0! | G12: =VLOOKUP(B$4:B$57,I$4:M$57,5,0) -> #DIV/0! | I12: MR 1819 корич | K12: =J12/J$64 -> #DIV/0! | L12: =L11+K12 -> #DIV/0! | M12: =_xlfn.IFS(L12<80%,"A",L12<=95%,"B",L12>95%,"C") -> #DIV/0!
B13: MR Р1874 черн | D13: =C13/C$64 -> #DIV/0! | E13: =E12+D13 -> #DIV/0! | F13: =IF(AND(E13<=0),"C",IF(E13<=0.8,"A",IF(E13<=0.95,"B","C"))) -> #DIV/0! | G13: =VLOOKUP(B$4:B$57,I$4:M$57,5,0) -> #DIV/0! | I13: MR Р1874 черн | K13: =J13/J$64 -> #DIV/0! | L13: =L12+K13 -> #DIV/0! | M13: =_xlfn.IFS(L13<80%,"A",L13<=95%,"B",L13>95%,"C") -> #DIV/0!
B14: MR Р1874 корич | D14: =C14/C$64 -> #DIV/0! | E14: =E13+D14 -> #DIV/0! | F14: =IF(AND(E14<=0),"C",IF(E14<=0.8,"A",IF(E14<=0.95,"B","C"))) -> #DIV/0! | G14: =VLOOKUP(B$4:B$57,I$4:M$57,5,0) -> #DIV/0! | I14: MR Р1874 корич | K14: =J14/J$64 -> #DIV/0! | L14: =L13+K14 -> #DIV/0! | M14: =_xlfn.IFS(L14<80%,"A",L14<=95%,"B",L14>95%,"C") -> #DIV/0!
B15: MR Р1886 черн | D15: =C15/C$64 -> #DIV/0! | E15: =E14+D15 -> #DIV/0! | F15: =IF(AND(E15<=0),"C",IF(E15<=0.8,"A",IF(E15<=0.95,"B","C"))) -> #DIV/0! | G15: =VLOOKUP(B$4:B$57,I$4:M$57,5,0) -> #DIV/0! | I15: MR Р1886 черн | K15: =J15/J$64 -> #DIV/0! | L15: =L14+K15 -> #DIV/0! | M15: =_xlfn.IFS(L15<80%,"A",L15<=95%,"B",L15>95%,"C") -> #DIV/0!
B16: MR Р1886 корич | D16: =C16/C$64 -> #DIV/0! | E16: =E15+D16 -> #DIV/0! | F16: =IF(AND(E16<=0),"C",IF(E16<=0.8,"A",IF(E16<=0.95,"B","C"))) -> #DIV/0! | G16: =VLOOKUP(B$4:B$57,I$4:M$57,5,0) -> #DIV/0! | I16: MR Р1886 корич | K16: =J16/J$64 -> #DIV/0! | L16: =L15+K16 -> #DIV/0! | M16: =_xlfn.IFS(L16<80%,"A",L16<=95%,"B",L16>95%,"C") -> #DIV/0!
B17: MR 1890 черн | D17: =C17/C$64 -> #DIV/0! | E17: =E16+D17 -> #DIV/0! | F17: =IF(AND(E17<=0),"C",IF(E17<=0.8,"A",IF(E17<=0.95,"B","C"))) -> #DIV/0! | G17: =VLOOKUP(B$4:B$57,I$4:M$57,5,0) -> #DIV/0! | I17: MR 1890 черн | K17: =J17/J$64 -> #DIV/0! | L17: =L16+K17 -> #DIV/0! | M17: =_xlfn.IFS(L17<80%,"A",L17<=95%,"B",L17>95%,"C") -> #DIV/0!
B18: MR 1890 желт | D18: =C18/C$64 -> #DIV/0! | E18: =E17+D18 -> #DIV/0! | F18: =IF(AND(E18<=0),"C",IF(E18<=0.8,"A",IF(E18<=0.95,"B","C"))) -> #DIV/0! | G18: =VLOOKUP(B$4:B$57,I$4:M$57,5,0) -> #DIV/0! | I18: MR 1890 желт | K18: =J18/J$64 -> #DIV/0! | L18: =L17+K18 -> #DIV/0! | M18: =_xlfn.IFS(L18<80%,"A",L18<=95%,"B",L18>95%,"C") -> #DIV/0!
... B27: qs009 | D27: =C27/C$64 -> #DIV/0! | E27: =E26+D27 -> #DIV/0! | F27: =IF(AND(E27<=0),"C",IF(E27<=0.8,"A",IF(E27<=0.95,"B","C"))) -> #DIV/0! | G27: =VLOOKUP(B$4:B$57,I$4:M$57,5,0) -> #DIV/0! | I27: qs009 | K27: =J27/J$64 -> #DIV/0! | L27: =L26+K27 -> #DIV/0! | M27: =_xlfn.IFS(L27<80%,"A",L27<=95%,"B",L27>95%,"C") -> #DIV/0!
B28: qs010 | D28: =C28/C$64 -> #DIV/0! | E28: =E24+D28 -> #DIV/0! | F28: =IF(AND(E28<=0),"C",IF(E28<=0.8,"A",IF(E28<=0.95,"B","C"))) -> #DIV/0! | G28: =VLOOKUP(B$4:B$57,I$4:M$57,5,0) -> #DIV/0! | I28: qs010 | K28: =J28/J$64 -> #DIV/0! | L28: =L24+K28 -> #DIV/0! | M28: =_xlfn.IFS(L28<80%,"A",L28<=95%,"B",L28>95%,"C") -> #DIV/0!
B29: qs011 | D29: =C29/C$64 -> #DIV/0! | E29: =E28+D29 -> #DIV/0! | F29: =IF(AND(E29<=0),"C",IF(E29<=0.8,"A",IF(E29<=0.95,"B","C"))) -> #DIV/0! | G29: =VLOOKUP(B$4:B$57,I$4:M$57,5,0) -> #DIV/0! | I29: qs011 | K29: =J29/J$64 -> #DIV/0! | L29: =L28+K29 -> #DIV/0! | M29: =_xlfn.IFS(L29<80%,"A",L29<=95%,"B",L29>95%,"C") -> #DIV/0!
B30: qs012 | D30: =C30/C$64 -> #DIV/0! | E30: =E29+D30 -> #DIV/0! | F30: =IF(AND(E30<=0),"C",IF(E30<=0.8,"A",IF(E30<=0.95,"B","C"))) -> #DIV/0! | G30: =VLOOKUP(B$4:B$57,I$4:M$57,5,0) -> #DIV/0! | I30: qs012 | K30: =J30/J$64 -> #DIV/0! | L30: =L29+K30 -> #DIV/0! | M30: =_xlfn.IFS(L30<80%,"A",L30<=95%,"B",L30>95%,"C") -> #DIV/0!
B31: qs013 | D31: =C31/C$64 -> #DIV/0! | E31: =E30+D31 -> #DIV/0! | F31: =IF(AND(E31<=0),"C",IF(E31<=0.8,"A",IF(E31<=0.95,"B","C"))) -> #DIV/0! | G31: =VLOOKUP(B$4:B$57,I$4:M$57,5,0) -> #DIV/0! | I31: qs013 | K31: =J31/J$64 -> #DIV/0! | L31: =L30+K31 -> #DIV/0! | M31: =_xlfn.IFS(L31<80%,"A",L31<=95%,"B",L31>95%,"C") -> #DIV/0!
B32: qs014 | D32: =C32/C$64 -> #DIV/0! | E32: =E31+D32 -> #DIV/0! | F32: =IF(AND(E32<=0),"C",IF(E32<=0.8,"A",IF(E32<=0.95,"B","C"))) -> #DIV/0! | G32: =VLOOKUP(B$4:B$57,I$4:M$57,5,0) -> #DIV/0! | I32: qs014 | K32: =J32/J$64 -> #DIV/0! | L32: =L31+K32 -> #DIV/0! | M32: =_xlfn.IFS(L32<80%,"A",L32<=95%,"B",L32>95%,"C") -> #DIV/0!
B33: qs015 | D33: =C33/C$64 -> #DIV/0! | E33: =E32+D33 -> #DIV/0! | F33: =IF(AND(E33<=0),"C",IF(E33<=0.8,"A",IF(E33<=0.95,"B","C"))) -> #DIV/0! | G33: =VLOOKUP(B$4:B$57,I$4:M$57,5,0) -> #DIV/0! | I33: qs015 | K33: =J33/J$64 -> #DIV/0! | L33: =L32+K33 -> #DIV/0! | M33: =_xlfn.IFS(L33<80%,"A",L33<=95%,"B",L33>95%,"C") -> #DIV/0!
B34: qs001 Ж | D34: =C34/C$64 -> #DIV/0! | E34: =E33+D34 -> #DIV/0! | F34: =IF(AND(E34<=0),"C",IF(E34<=0.8,"A",IF(E34<=0.95,"B","C"))) -> #DIV/0! | G34: =VLOOKUP(B$4:B$57,I$4:M$57,5,0) -> #DIV/0! | I34: qs001 Ж | K34: =J34/J$64 -> #DIV/0! | L34: =L33+K34 -> #DIV/0! | M34: =_xlfn.IFS(L34<80%,"A",L34<=95%,"B",L34>95%,"C") -> #DIV/0!
B35: qs010ж | D35: =C35/C$64 -> #DIV/0! | E35: =E34+D35 -> #DIV/0! | F35: =IF(AND(E35<=0),"C",IF(E35<=0.8,"A",IF(E35<=0.95,"B","C"))) -> #DIV/0! | G35: =VLOOKUP(B$4:B$57,I$4:M$57,5,0) -> #DIV/0! | I35: qs010ж | K35: =J35/J$64 -> #DIV/0! | L35: =L34+K35 -> #DIV/0! | M35: =_xlfn.IFS(L35<80%,"A",L35<=95%,"B",L35>95%,"C") -> #DIV/0!
B36: qs011ж | D36: =C36/C$64 -> #DIV/0! | E36: =E35+D36 -> #DIV/0! | F36: =IF(AND(E36<=0),"C",IF(E36<=0.8,"A",IF(E36<=0.95,"B","C"))) -> #DIV/0! | G36: =VLOOKUP(B$4:B$57,I$4:M$57,5,0) -> #DIV/0! | I36: qs011ж | K36: =J36/J$64 -> #DIV/0! | L36: =L35+K36 -> #DIV/0! | M36: =_xlfn.IFS(L36<80%,"A",L36<=95%,"B",L36>95%,"C") -> #DIV/0!
B37: qs012ж | D37: =C37/C$64 -> #DIV/0! | E37: =E36+D37 -> #DIV/0! | F37: =IF(AND(E37<=0),"C",IF(E37<=0.8,"A",IF(E37<=0.95,"B","C"))) -> #DIV/0! | G37: =VLOOKUP(B$4:B$57,I$4:M$57,5,0) -> #DIV/0! | I37: qs012ж | K37: =J37/J$64 -> #DIV/0! | L37: =L36+K37 -> #DIV/0! | M37: =_xlfn.IFS(L37<80%,"A",L37<=95%,"B",L37>95%,"C") -> #DIV/0!
B38: 2038ч/б | D38: =C38/C$64 -> #DIV/0! | E38: =E37+D38 -> #DIV/0! | F38: =IF(AND(E38<=0),"C",IF(E38<=0.8,"A",IF(E38<=0.95,"B","C"))) -> #DIV/0! | G38: =VLOOKUP(B$4:B$57,I$4:M$57,5,0) -> #DIV/0! | I38: 2038ч/б | K38: =J38/J$64 -> #DIV/0! | L38: =L37+K38 -> #DIV/0! | M38: =_xlfn.IFS(L38<80%,"A",L38<=95%,"B",L38>95%,"C") -> #DIV/0!
B39: 2038красный | D39: =C39/C$64 -> #DIV/0! | E39: =E38+D39 -> #DIV/0! | F39: =IF(AND(E39<=0),"C",IF(E39<=0.8,"A",IF(E39<=0.95,"B","C"))) -> #DIV/0! | G39: =VLOOKUP(B$4:B$57,I$4:M$57,5,0) -> #DIV/0! | I39: 2038красный | K39: =J39/J$64 -> #DIV/0! | L39: =L38+K39 -> #DIV/0! | M39: =_xlfn.IFS(L39<80%,"A",L39<=95%,"B",L39>95%,"C") -> #DIV/0!
B40: 2100черный | D40: =C40/C$64 -> #DIV/0! | E40: =E39+D40 -> #DIV/0! | F40: =IF(AND(E40<=0),"C",IF(E40<=0.8,"A",IF(E40<=0.95,"B","C"))) -> #DIV/0! | G40: =VLOOKUP(B$4:B$57,I$4:M$57,5,0) -> #DIV/0! | I40: 2100черный | K40: =J40/J$64 -> #DIV/0! | L40: =L39+K40 -> #DIV/0! | M40: =_xlfn.IFS(L40<80%,"A",L40<=95%,"B",L40>95%,"C") -> #DIV/0!
... B57: 8852 | D57: =C57/C$64 -> #DIV/0! | E57: =E56+D57 -> #DIV/0! | F57: =IF(AND(E57<=0),"C",IF(E57<=0.8,"A",IF(E57<=0.95,"B","C"))) -> #DIV/0! | G57: =VLOOKUP(B$4:B$57,I$4:M$57,5,0) -> #DIV/0! | I57: 8852 | K57: =J57/J$64 -> #DIV/0! | L57: =L56+K57 -> #DIV/0! | M57: =_xlfn.IFS(L57<80%,"A",L57<=95%,"B",L57>95%,"C") -> #DIV/0!
B58: 2801 | D58: =C58/C$64 -> #DIV/0! | E58: =E57+D58 -> #DIV/0! | F58: =IF(AND(E58<=0),"C",IF(E58<=0.8,"A",IF(E58<=0.95,"B","C"))) -> #DIV/0! | G58: =VLOOKUP(B$4:B$57,I$4:M$57,5,0) -> #VALUE! | I58: 2801 | K58: =J58/J$64 -> #DIV/0! | L58: =L57+K58 -> #DIV/0! | M58: =_xlfn.IFS(L58<80%,"A",L58<=95%,"B",L58>95%,"C") -> #DIV/0!
B59: 2811 С3 | D59: =C59/C$64 -> #DIV/0! | E59: =E58+D59 -> #DIV/0! | F59: =IF(AND(E59<=0),"C",IF(E59<=0.8,"A",IF(E59<=0.95,"B","C"))) -> #DIV/0! | G59: =VLOOKUP(B$4:B$57,I$4:M$57,5,0) -> #VALUE! | I59: 2811 С3 | K59: =J59/J$64 -> #DIV/0! | L59: =L58+K59 -> #DIV/0! | M59: =_xlfn.IFS(L59<80%,"A",L59<=95%,"B",L59>95%,"C") -> #DIV/0!
B60: 03004 С8-02 | D60: =C60/C$64 -> #DIV/0! | E60: =E59+D60 -> #DIV/0! | F60: =IF(AND(E60<=0),"C",IF(E60<=0.8,"A",IF(E60<=0.95,"B","C"))) -> #DIV/0! | G60: =VLOOKUP(B$4:B$57,I$4:M$57,5,0) -> #VALUE! | I60: 03004 С8-02 | K60: =J60/J$64 -> #DIV/0! | L60: =L59+K60 -> #DIV/0! | M60: =_xlfn.IFS(L60<80%,"A",L60<=95%,"B",L60>95%,"C") -> #DIV/0!
B61: 03004 С9-08 | D61: =C61/C$64 -> #DIV/0! | E61: =E60+D61 -> #DIV/0! | F61: =IF(AND(E61<=0),"C",IF(E61<=0.8,"A",IF(E61<=0.95,"B","C"))) -> #DIV/0! | G61: =VLOOKUP(B$4:B$57,I$4:M$57,5,0) -> #VALUE! | I61: 03004 С9-08 | K61: =J61/J$64 -> #DIV/0! | L61: =L60+K61 -> #DIV/0! | M61: =_xlfn.IFS(L61<80%,"A",L61<=95%,"B",L61>95%,"C") -> #DIV/0!
B62: 03977 С9-08 | D62: =C62/C$64 -> #DIV/0! | E62: =E61+D62 -> #DIV/0! | F62: =IF(AND(E62<=0),"C",IF(E62<=0.8,"A",IF(E62<=0.95,"B","C"))) -> #DIV/0! | G62: =VLOOKUP(B$4:B$57,I$4:M$57,5,0) -> #VALUE! | I62: 03977 С9-08 | K62: =J62/J$64 -> #DIV/0! | L62: =L61+K62 -> #DIV/0! | M62: =_xlfn.IFS(L62<80%,"A",L62<=95%,"B",L62>95%,"C") -> #DIV/0!
B63: 03985 С9-124 | D63: =C63/C$64 -> #DIV/0! | E63: =E62+D63 -> #DIV/0! | F63: =IF(AND(E63<=0),"C",IF(E63<=0.8,"A",IF(E63<=0.95,"B","C"))) -> #DIV/0! | G63: =VLOOKUP(B$4:B$57,I$4:M$57,5,0) -> #VALUE! | I63: 03985 С9-124 | K63: =J63/J$64 -> #DIV/0! | L63: =L62+K63 -> #DIV/0! | M63: =_xlfn.IFS(L63<80%,"A",L63<=95%,"B",L63>95%,"C") -> #DIV/0!
C64: =SUM(C4:C63) -> 0 | D64: =SUM(D4:D44) -> #DIV/0! | J64: =SUM(J4:J63) -> 0 | K64: =SUM(K4:K44) -> #DIV/0!
C67: Прибыль | D67: % прибыль | E67: Доля | F67: ABC прибыль | G67: ABC кол-во | J67: Кол-во | K67: % кол-во | L67: Доля | M67: ABC кол-во
D68: =C68/C$120 -> #DIV/0! | E68: =D68 -> #DIV/0! | F68: =IF(AND(E68<=0),"C",IF(E68<=0.8,"A",IF(E68<=0.95,"B","C"))) -> #DIV/0! | G68: =VLOOKUP(B68:B119,I$68:M$119,5,0) -> #N/A | K68: =J68/J$120 -> #DIV/0! | L68: =K68 -> #DIV/0! | M68: =_xlfn.IFS(L68<80%,"A",L68<=95%,"B",L68>95%,"C") -> #DIV/0!
D69: =C69/C$120 -> #DIV/0! | E69: =D69+E68 -> #DIV/0! | F69: =IF(AND(E69<=0),"C",IF(E69<=0.8,"A",IF(E69<=0.95,"B","C"))) -> #DIV/0! | G69: =VLOOKUP(B69:B120,I$68:M$119,5,0) -> #N/A | K69: =J69/J$120 -> #DIV/0! | L69: =K69+L68 -> #DIV/0! | M69: =_xlfn.IFS(L69<80%,"A",L69<=95%,"B",L69>95%,"C") -> #DIV/0!
D70: =C70/C$120 -> #DIV/0! | E70: =D70+E69 -> #DIV/0! | F70: =IF(AND(E70<=0),"C",IF(E70<=0.8,"A",IF(E70<=0.95,"B","C"))) -> #DIV/0! | G70: =VLOOKUP(B70:B121,I$68:M$119,5,0) -> #N/A | K70: =J70/J$120 -> #DIV/0! | L70: =K70+L69 -> #DIV/0! | M70: =_xlfn.IFS(L70<80%,"A",L70<=95%,"B",L70>95%,"C") -> #DIV/0!
D71: =C71/C$120 -> #DIV/0! | E71: =D71+E70 -> #DIV/0! | F71: =IF(AND(E71<=0),"C",IF(E71<=0.8,"A",IF(E71<=0.95,"B","C"))) -> #DIV/0! | G71: =VLOOKUP(B71:B122,I$68:M$119,5,0) -> #N/A | K71: =J71/J$120 -> #DIV/0! | L71: =K71+L70 -> #DIV/0! | M71: =_xlfn.IFS(L71<80%,"A",L71<=95%,"B",L71>95%,"C") -> #DIV/0!
D72: =C72/C$120 -> #DIV/0! | E72: =D72+E71 -> #DIV/0! | F72: =IF(AND(E72<=0),"C",IF(E72<=0.8,"A",IF(E72<=0.95,"B","C"))) -> #DIV/0! | G72: =VLOOKUP(B72:B123,I$68:M$119,5,0) -> #N/A | K72: =J72/J$120 -> #DIV/0! | L72: =K72+L71 -> #DIV/0! | M72: =_xlfn.IFS(L72<80%,"A",L72<=95%,"B",L72>95%,"C") -> #DIV/0!
D73: =C73/C$120 -> #DIV/0! | E73: =D73+E72 -> #DIV/0! | F73: =IF(AND(E73<=0),"C",IF(E73<=0.8,"A",IF(E73<=0.95,"B","C"))) -> #DIV/0! | G73: =VLOOKUP(B73:B124,I$68:M$119,5,0) -> #N/A | K73: =J73/J$120 -> #DIV/0! | L73: =K73+L72 -> #DIV/0! | M73: =_xlfn.IFS(L73<80%,"A",L73<=95%,"B",L73>95%,"C") -> #DIV/0!
D74: =C74/C$120 -> #DIV/0! | E74: =D74+E73 -> #DIV/0! | F74: =IF(AND(E74<=0),"C",IF(E74<=0.8,"A",IF(E74<=0.95,"B","C"))) -> #DIV/0! | G74: =VLOOKUP(B74:B125,I$68:M$119,5,0) -> #N/A | K74: =J74/J$120 -> #DIV/0! | L74: =K74+L73 -> #DIV/0! | M74: =_xlfn.IFS(L74<80%,"A",L74<=95%,"B",L74>95%,"C") -> #DIV/0!
D75: =C75/C$120 -> #DIV/0! | E75: =D75+E74 -> #DIV/0! | F75: =IF(AND(E75<=0),"C",IF(E75<=0.8,"A",IF(E75<=0.95,"B","C"))) -> #DIV/0! | G75: =VLOOKUP(B75:B126,I$68:M$119,5,0) -> #N/A | K75: =J75/J$120 -> #DIV/0! | L75: =K75+L74 -> #DIV/0! | M75: =_xlfn.IFS(L75<80%,"A",L75<=95%,"B",L75>95%,"C") -> #DIV/0!
D76: =C76/C$120 -> #DIV/0! | E76: =D76+E75 -> #DIV/0! | F76: =IF(AND(E76<=0),"C",IF(E76<=0.8,"A",IF(E76<=0.95,"B","C"))) -> #DIV/0! | G76: =VLOOKUP(B76:B127,I$68:M$119,5,0) -> #N/A | K76: =J76/J$120 -> #DIV/0! | L76: =K76+L75 -> #DIV/0! | M76: =_xlfn.IFS(L76<80%,"A",L76<=95%,"B",L76>95%,"C") -> #DIV/0!
D77: =C77/C$120 -> #DIV/0! | E77: =D77+E76 -> #DIV/0! | F77: =IF(AND(E77<=0),"C",IF(E77<=0.8,"A",IF(E77<=0.95,"B","C"))) -> #DIV/0! | G77: =VLOOKUP(B77:B128,I$68:M$119,5,0) -> #N/A | K77: =J77/J$120 -> #DIV/0! | L77: =K77+L76 -> #DIV/0! | M77: =_xlfn.IFS(L77<80%,"A",L77<=95%,"B",L77>95%,"C") -> #DIV/0!
D78: =C78/C$120 -> #DIV/0! | E78: =D78+E77 -> #DIV/0! | F78: =IF(AND(E78<=0),"C",IF(E78<=0.8,"A",IF(E78<=0.95,"B","C"))) -> #DIV/0! | G78: =VLOOKUP(B78:B129,I$68:M$119,5,0) -> #N/A | K78: =J78/J$120 -> #DIV/0! | L78: =K78+L77 -> #DIV/0! | M78: =_xlfn.IFS(L78<80%,"A",L78<=95%,"B",L78>95%,"C") -> #DIV/0!
D79: =C79/C$120 -> #DIV/0! | E79: =D79+E78 -> #DIV/0! | F79: =IF(AND(E79<=0),"C",IF(E79<=0.8,"A",IF(E79<=0.95,"B","C"))) -> #DIV/0! | G79: =VLOOKUP(B79:B130,I$68:M$119,5,0) -> #N/A | K79: =J79/J$120 -> #DIV/0! | L79: =K79+L78 -> #DIV/0! | M79: =_xlfn.IFS(L79<80%,"A",L79<=95%,"B",L79>95%,"C") -> #DIV/0!
D80: =C80/C$120 -> #DIV/0! | E80: =D80+E79 -> #DIV/0! | F80: =IF(AND(E80<=0),"C",IF(E80<=0.8,"A",IF(E80<=0.95,"B","C"))) -> #DIV/0! | G80: =VLOOKUP(B80:B131,I$68:M$119,5,0) -> #N/A | K80: =J80/J$120 -> #DIV/0! | L80: =K80+L79 -> #DIV/0! | M80: =_xlfn.IFS(L80<80%,"A",L80<=95%,"B",L80>95%,"C") -> #DIV/0!
... D119: =C119/C$120 -> #DIV/0! | E119: =D119+E118 -> #DIV/0! | F119: =IF(AND(E119<=0),"C",IF(E119<=0.8,"A",IF(E119<=0.95,"B","C"))) -> #DIV/0! | G119: =VLOOKUP(B119:B170,I$68:M$119,5,0) -> #N/A | K119: =J119/J$120 -> #DIV/0! | L119: =K119+L118 -> #DIV/0! | M119: =_xlfn.IFS(L119<80%,"A",L119<=95%,"B",L119>95%,"C") -> #DIV/0!
C120: =SUM(C68:C119) -> 0 | D120: =SUM(D68:D119) -> #DIV/0! | J120: =SUM(J68:J119) -> 0 | K120: =SUM(K68:K119) -> #DIV/0!

Sheet АВС 19
B2: ОЧКИ
C3: Прибыль | D3: % прибыль | E3: Доля | F3: ABC прибыль | G3: ABC кол-во | J3: Кол-во | K3: % кол-во | L3: Доля | M3: ABC кол-во
B4: Qs черн Сул | C4: ='Юнит 19'!AL4 -> 111708.02 | D4: =C4/C$64 -> 0.58807534 | E4: =D4 -> 0.58807534 | F4: =IF(AND(E4<=0),"C",IF(E4<=0.8,"A",IF(E4<=0.95,"B","C"))) -> A | G4: =VLOOKUP(B$4:B$63,I$4:M$63,5,0) -> A | I4: Qs черн Сул | J4: ='Юнит 19'!S4 -> 322 | K4: =J4/J$64 -> 0.46 | L4: =K4 -> 0.46 | M4: =_xlfn.IFS(L4<80%,"A",L4<=95%,"B",L4>95%,"C") -> A | P4: A | Q4: 0.8
B5: Черные с железкой Сул | C5: ='Юнит 19'!AL3 -> 43040.11 | D5: =C5/C$64 -> 0.22658021 | E5: =E4+D5 -> 0.81465554 | F5: =IF(AND(E5<=0),"C",IF(E5<=0.8,"A",IF(E5<=0.95,"B","C"))) -> B | G5: =VLOOKUP(B$4:B$63,I$4:M$63,5,0) -> A | I5: Черные с железкой Сул | J5: ='Юнит 19'!S3 -> 118 | K5: =J5/J$64 -> 0.16857143 | L5: =L4+K5 -> 0.62857143 | M5: =_xlfn.IFS(L5<80%,"A",L5<=95%,"B",L5>95%,"C") -> A | P5: B | Q5: 0.15
B6: flip желтые Сул | C6: ='Юнит 19'!AL8 -> 20857.187 | D6: =C6/C$64 -> 0.1098005 | E6: =E5+D6 -> 0.92445605 | F6: =IF(AND(E6<=0),"C",IF(E6<=0.8,"A",IF(E6<=0.95,"B","C"))) -> B | G6: =VLOOKUP(B$4:B$63,I$4:M$63,5,0) -> A | I6: flip желтые Сул | J6: ='Юнит 19'!S8 -> 62 | K6: =J6/J$64 -> 0.088571429 | L6: =L5+K6 -> 0.71714286 | M6: =_xlfn.IFS(L6<80%,"A",L6<=95%,"B",L6>95%,"C") -> A | P6: C | Q6: 0.05
B7: Qs желт Сул | C7: ='Юнит 19'!AL6 -> 9730.1643 | D7: =C7/C$64 -> 0.051223444 | E7: =E6+D7 -> 0.97567949 | F7: =IF(AND(E7<=0),"C",IF(E7<=0.8,"A",IF(E7<=0.95,"B","C"))) -> C | G7: =VLOOKUP(B$4:B$63,I$4:M$63,5,0) -> B | I7: Qs син Сул | J7: ='Юнит 19'!S5 -> 51 | K7: =J7/J$64 -> 0.072857143 | L7: =L6+K7 -> 0.79 | M7: =_xlfn.IFS(L7<80%,"A",L7<=95%,"B",L7>95%,"C") -> A
B8: flip черные Сул | C8: ='Юнит 19'!AL7 -> 5426.7534 | D8: =C8/C$64 -> 0.028568582 | E8: =E7+D8 -> 1.0042481 | F8: =IF(AND(E8<=0),"C",IF(E8<=0.8,"A",IF(E8<=0.95,"B","C"))) -> C | G8: =VLOOKUP(B$4:B$63,I$4:M$63,5,0) -> B | I8: flip черные Сул | J8: ='Юнит 19'!S7 -> 29 | K8: =J8/J$64 -> 0.041428571 | L8: =L7+K8 -> 0.83142857 | M8: =_xlfn.IFS(L8<80%,"A",L8<=95%,"B",L8>95%,"C") -> B
B9: Qs син Сул | C9: ='Юнит 19'!AL5 -> 3708.9954 | D9: =C9/C$64 -> 0.019525623 | E9: =E8+D9 -> 1.0237737 | F9: =IF(AND(E9<=0),"C",IF(E9<=0.8,"A",IF(E9<=0.95,"B","C"))) -> C | G9: =VLOOKUP(B$4:B$63,I$4:M$63,5,0) -> A | I9: Qs желт Сул | J9: ='Юнит 19'!S6 -> 28 | K9: =J9/J$64 -> 0.04 | L9: =L8+K9 -> 0.87142857 | M9: =_xlfn.IFS(L9<80%,"A",L9<=95%,"B",L9>95%,"C") -> B
B10: qs015 | C10: ='Юнит 19'!AL32 -> 3671.9772 | D10: =C10/C$64 -> 0.019330744 | E10: =E9+D10 -> 1.0431044 | F10: =IF(AND(E10<=0),"C",IF(E10<=0.8,"A",IF(E10<=0.95,"B","C"))) -> C | G10: =VLOOKUP(B$4:B$63,I$4:M$63,5,0) -> B | I10: MR 1890 корич | J10: ='Юнит 19'!S18 -> 10 | K10: =J10/J$64 -> 0.014285714 | L10: =L9+K10 -> 0.88571429 | M10: =_xlfn.IFS(L10<80%,"A",L10<=95%,"B",L10>95%,"C") -> B
B11: qs007 | C11: ='Юнит 19'!AL24 -> 2760.2195 | D11: =C11/C$64 -> 0.01453089 | E11: =E10+D11 -> 1.0576353 | F11: =IF(AND(E11<=0),"C",IF(E11<=0.8,"A",IF(E11<=0.95,"B","C"))) -> C | G11: =VLOOKUP(B$4:B$63,I$4:M$63,5,0) -> B | I11: MR 1890 черн | J11: ='Юнит 19'!S16 -> 9 | K11: =J11/J$64 -> 0.012857143 | L11: =L10+K11 -> 0.89857143 | M11: =_xlfn.IFS(L11<80%,"A",L11<=95%,"B",L11>95%,"C") -> B
B12: qs006 | C12: ='Юнит 19'!AL23 -> 2450.28 | D12: =C12/C$64 -> 0.012899246 | E12: =E11+D12 -> 1.0705346 | F12: =IF(AND(E12<=0),"C",IF(E12<=0.8,"A",IF(E12<=0.95,"B","C"))) -> C | G12: =VLOOKUP(B$4:B$63,I$4:M$63,5,0) -> C | I12: MR 1890 желт | J12: ='Юнит 19'!S17 -> 8 | K12: =J12/J$64 -> 0.011428571 | L12: =L11+K12 -> 0.91 | M12: =_xlfn.IFS(L12<80%,"A",L12<=95%,"B",L12>95%,"C") -> B
B13: qs005 | C13: ='Юнит 19'!AL22 -> 2261.443 | D13: =C13/C$64 -> 0.011905133 | E13: =E12+D13 -> 1.0824397 | F13: =IF(AND(E13<=0),"C",IF(E13<=0.8,"A",IF(E13<=0.95,"B","C"))) -> C | G13: =VLOOKUP(B$4:B$63,I$4:M$63,5,0) -> B | I13: qs015 | J13: ='Юнит 19'!S32 -> 8 | K13: =J13/J$64 -> 0.011428571 | L13: =L12+K13 -> 0.92142857 | M13: =_xlfn.IFS(L13<80%,"A",L13<=95%,"B",L13>95%,"C") -> B
B14: qs014 | C14: ='Юнит 19'!AL31 -> 2072.55 | D14: =C14/C$64 -> 0.010910725 | E14: =E13+D14 -> 1.0933504 | F14: =IF(AND(E14<=0),"C",IF(E14<=0.8,"A",IF(E14<=0.95,"B","C"))) -> C | G14: =VLOOKUP(B$4:B$63,I$4:M$63,5,0) -> C | I14: qs005 | J14: ='Юнит 19'!S22 -> 7 | K14: =J14/J$64 -> 0.01 | L14: =L13+K14 -> 0.93142857 | M14: =_xlfn.IFS(L14<80%,"A",L14<=95%,"B",L14>95%,"C") -> B
B15: MR 1890 черн | C15: ='Юнит 19'!AL16 -> 1970.1401 | D15: =C15/C$64 -> 0.010371599 | E15: =E14+D15 -> 1.103722 | F15: =IF(AND(E15<=0),"C",IF(E15<=0.8,"A",IF(E15<=0.95,"B","C"))) -> C | G15: =VLOOKUP(B$4:B$63,I$4:M$63,5,0) -> B | I15: qs007 | J15: ='Юнит 19'!S24 -> 6 | K15: =J15/J$64 -> 0.0085714286 | L15: =L14+K15 -> 0.94 | M15: =_xlfn.IFS(L15<80%,"A",L15<=95%,"B",L15>95%,"C") -> B
B16: qs003 | C16: ='Юнит 19'!AL21 -> 1830.1529 | D16: =C16/C$64 -> 0.0096346508 | E16: =E15+D16 -> 1.1133567 | F16: =IF(AND(E16<=0),"C",IF(E16<=0.8,"A",IF(E16<=0.95,"B","C"))) -> C | G16: =VLOOKUP(B$4:B$63,I$4:M$63,5,0) -> C | I16: qs010ж | J16: ='Юнит 19'!S34 -> 6 | K16: =J16/J$64 -> 0.0085714286 | L16: =L15+K16 -> 0.94857143 | M16: =_xlfn.IFS(L16<80%,"A",L16<=95%,"B",L16>95%,"C") -> B
B17: qs002 | C17: ='Юнит 19'!AL20 -> 1739.8715 | D17: =C17/C$64 -> 0.0091593736 | E17: =E16+D17 -> 1.1225161 | F17: =IF(AND(E17<=0),"C",IF(E17<=0.8,"A",IF(E17<=0.95,"B","C"))) -> C | G17: =VLOOKUP(B$4:B$63,I$4:M$63,5,0) -> C | I17: qs006 | J17: ='Юнит 19'!S23 -> 5 | K17: =J17/J$64 -> 0.0071428571 | L17: =L16+K17 -> 0.95571429 | M17: =_xlfn.IFS(L17<80%,"A",L17<=95%,"B",L17>95%,"C") -> C
B18: MR8854 C2 Сул | C18: ='Юнит 19'!AL9 -> 1000.38 | D18: =C18/C$64 -> 0.005266397 | E18: =E17+D18 -> 1.1277825 | F18: =IF(AND(E18<=0),"C",IF(E18<=0.8,"A",IF(E18<=0.95,"B","C"))) -> C | G18: =VLOOKUP(B$4:B$63,I$4:M$63,5,0) -> C | I18: qs009 | J18: ='Юнит 19'!S26 -> 5 | K18: =J18/J$64 -> 0.0071428571 | L18: =L17+K18 -> 0.96285714 | M18: =_xlfn.IFS(L18<80%,"A",L18<=95%,"B",L18>95%,"C") -> C
B19: MR 1890 корич | C19: ='Юнит 19'!AL18 -> 840.54915 | D19: =C19/C$64 -> 0.004424984 | E19: =E18+D19 -> 1.1322074 | F19: =IF(AND(E19<=0),"C",IF(E19<=0.8,"A",IF(E19<=0.95,"B","C"))) -> C | G19: =VLOOKUP(B$4:B$63,I$4:M$63,5,0) -> B | I19: qs002 | J19: ='Юнит 19'!S20 -> 4 | K19: =J19/J$64 -> 0.0057142857 | L19: =L18+K19 -> 0.96857143 | M19: =_xlfn.IFS(L19<80%,"A",L19<=95%,"B",L19>95%,"C") -> C
B20: qs013 | C20: ='Юнит 19'!AL30 -> 581.21 | D20: =C20/C$64 -> 0.0030597199 | E20: =E19+D20 -> 1.1352672 | F20: =IF(AND(E20<=0),"C",IF(E20<=0.8,"A",IF(E20<=0.95,"B","C"))) -> C | G20: =VLOOKUP(B$4:B$63,I$4:M$63,5,0) -> C | I20: qs003 | J20: ='Юнит 19'!S21 -> 4 | K20: =J20/J$64 -> 0.0057142857 | L20: =L19+K20 -> 0.97428571 | M20: =_xlfn.IFS(L20<80%,"A",L20<=95%,"B",L20>95%,"C") -> C
B21: qs012ж | C21: ='Юнит 19'!AL36 -> 434.5315 | D21: =C21/C$64 -> 0.0022875461 | E21: =E20+D21 -> 1.1375547 | F21: =IF(AND(E21<=0),"C",IF(E21<=0.8,"A",IF(E21<=0.95,"B","C"))) -> C | G21: =VLOOKUP(B$4:B$63,I$4:M$63,5,0) -> C | I21: qs014 | J21: ='Юнит 19'!S31 -> 4 | K21: =J21/J$64 -> 0.0057142857 | L21: =L20+K21 -> 0.98 | M21: =_xlfn.IFS(L21<80%,"A",L21<=95%,"B",L21>95%,"C") -> C
B22: qs011ж | C22: ='Юнит 19'!AL35 -> 353.39721 | D22: =C22/C$64 -> 0.0018604231 | E22: =E21+D22 -> 1.1394151 | F22: =IF(AND(E22<=0),"C",IF(E22<=0.8,"A",IF(E22<=0.95,"B","C"))) -> C | G22: =VLOOKUP(B$4:B$63,I$4:M$63,5,0) -> C | I22: qs008 | J22: ='Юнит 19'!S25 -> 3 | K22: =J22/J$64 -> 0.0042857143 | L22: =L21+K22 -> 0.98428571 | M22: =_xlfn.IFS(L22<80%,"A",L22<=95%,"B",L22>95%,"C") -> C
B23: 2084 (+1.75) | C23: ='Юнит 19'!AL55 -> 194.84003 | D23: =C23/C$64 -> 0.0010257152 | E23: =E22+D23 -> 1.1404408 | F23: =IF(AND(E23<=0),"C",IF(E23<=0.8,"A",IF(E23<=0.95,"B","C"))) -> C | G23: =VLOOKUP(B$4:B$63,I$4:M$63,5,0) -> C | I23: MR8854 C2 Сул | J23: ='Юнит 19'!S9 -> 2 | K23: =J23/J$64 -> 0.0028571429 | L23: =L22+K23 -> 0.98714286 | M23: =_xlfn.IFS(L23<80%,"A",L23<=95%,"B",L23>95%,"C") -> C
B24: MR 1819 корич | C24: ='Юнит 19'!AL11 -> 0 | D24: =C24/C$64 -> 0 | E24: =E23+D24 -> 1.1404408 | F24: =IF(AND(E24<=0),"C",IF(E24<=0.8,"A",IF(E24<=0.95,"B","C"))) -> C | G24: =VLOOKUP(B$4:B$63,I$4:M$63,5,0) -> C | I24: 2064ч/б | J24: ='Юнит 19'!S50 -> 2 | K24: =J24/J$64 -> 0.0028571429 | L24: =L23+K24 -> 0.99 | M24: =_xlfn.IFS(L24<80%,"A",L24<=95%,"B",L24>95%,"C") -> C
B25: MR Р1874 черн | C25: ='Юнит 19'!AL12 -> 0 | D25: =C25/C$64 -> 0 | E25: =E24+D25 -> 1.1404408 | F25: =IF(AND(E25<=0),"C",IF(E25<=0.8,"A",IF(E25<=0.95,"B","C"))) -> C | G25: =VLOOKUP(B$4:B$63,I$4:M$63,5,0) -> C | I25: 2084 (+1.75) | J25: ='Юнит 19'!S55 -> 2 | K25: =J25/J$64 -> 0.0028571429 | L25: =L24+K25 -> 0.99285714 | M25: =_xlfn.IFS(L25<80%,"A",L25<=95%,"B",L25>95%,"C") -> C
B26: MR Р1874 корич | C26: ='Юнит 19'!AL13 -> 0 | D26: =C26/C$64 -> 0 | E26: =E25+D26 -> 1.1404408 | F26: =IF(AND(E26<=0),"C",IF(E26<=0.8,"A",IF(E26<=0.95,"B","C"))) -> C | G26: =VLOOKUP(B$4:B$63,I$4:M$63,5,0) -> C | I26: qs013 | J26: ='Юнит 19'!S30 -> 1 | K26: =J26/J$64 -> 0.0014285714 | L26: =L25+K26 -> 0.99428571 | M26: =_xlfn.IFS(L26<80%,"A",L26<=95%,"B",L26>95%,"C") -> C
B27: MR Р1886 корич | C27: ='Юнит 19'!AL15 -> 0 | D27: =C27/C$64 -> 0 | E27: =E26+D27 -> 1.1404408 | F27: =IF(AND(E27<=0),"C",IF(E27<=0.8,"A",IF(E27<=0.95,"B","C"))) -> C | G27: =VLOOKUP(B$4:B$63,I$4:M$63,5,0) -> C | I27: qs011ж | J27: ='Юнит 19'!S35 -> 1 | K27: =J27/J$64 -> 0.0014285714 | L27: =L26+K27 -> 0.99571429 | M27: =_xlfn.IFS(L27<80%,"A",L27<=95%,"B",L27>95%,"C") -> C
B28: qs010 | C28: ='Юнит 19'!AL27 -> 0 | D28: =C28/C$64 -> 0 | E28: =E24+D28 -> 1.1404408 | F28: =IF(AND(E28<=0),"C",IF(E28<=0.8,"A",IF(E28<=0.95,"B","C"))) -> C | G28: =VLOOKUP(B$4:B$63,I$4:M$63,5,0) -> C | I28: qs012ж | J28: ='Юнит 19'!S36 -> 1 | K28: =J28/J$64 -> 0.0014285714 | L28: =L24+K28 -> 0.99142857 | M28: =_xlfn.IFS(L28<80%,"A",L28<=95%,"B",L28>95%,"C") -> C
B29: qs011 | C29: ='Юнит 19'!AL28 -> 0 | D29: =C29/C$64 -> 0 | E29: =E28+D29 -> 1.1404408 | F29: =IF(AND(E29<=0),"C",IF(E29<=0.8,"A",IF(E29<=0.95,"B","C"))) -> C | G29: =VLOOKUP(B$4:B$63,I$4:M$63,5,0) -> C | I29: 2100черный | J29: ='Юнит 19'!S39 -> 1 | K29: =J29/J$64 -> 0.0014285714 | L29: =L28+K29 -> 0.99285714 | M29: =_xlfn.IFS(L29<80%,"A",L29<=95%,"B",L29>95%,"C") -> C
B30: qs001 Ж | C30: ='Юнит 19'!AL33 -> 0 | D30: =C30/C$64 -> 0 | E30: =E29+D30 -> 1.1404408 | F30: =IF(AND(E30<=0),"C",IF(E30<=0.8,"A",IF(E30<=0.95,"B","C"))) -> C | G30: =VLOOKUP(B$4:B$63,I$4:M$63,5,0) -> C | I30: 2081 | J30: ='Юнит 19'!S53 -> 1 | K30: =J30/J$64 -> 0.0014285714 | L30: =L29+K30 -> 0.99428571 | M30: =_xlfn.IFS(L30<80%,"A",L30<=95%,"B",L30>95%,"C") -> C
B31: 03977 С9-08 | C31: ='Юнит 19'!AL61 -> 0 | D31: =C31/C$64 -> 0 | E31: =E30+D31 -> 1.1404408 | F31: =IF(AND(E31<=0),"C",IF(E31<=0.8,"A",IF(E31<=0.95,"B","C"))) -> C | G31: =VLOOKUP(B$4:B$63,I$4:M$63,5,0) -> C | I31: 03004 С8-02 | J31: ='Юнит 19'!S59 -> 1 | K31: =J31/J$64 -> 0.0014285714 | L31: =L30+K31 -> 0.99571429 | M31: =_xlfn.IFS(L31<80%,"A",L31<=95%,"B",L31>95%,"C") -> C
B32: 03985 С9-124 | C32: ='Юнит 19'!AL62 -> 0 | D32: =C32/C$64 -> 0 | E32: =E31+D32 -> 1.1404408 | F32: =IF(AND(E32<=0),"C",IF(E32<=0.8,"A",IF(E32<=0.95,"B","C"))) -> C | G32: =VLOOKUP(B$4:B$63,I$4:M$63,5,0) -> C | I32: MR 1819 черн | J32: ='Юнит 19'!S10 -> 0 | K32: =J32/J$64 -> 0 | L32: =L31+K32 -> 0.99571429 | M32: =_xlfn.IFS(L32<80%,"A",L32<=95%,"B",L32>95%,"C") -> C
B33: 2100фиолетовый | C33: ='Юнит 19'!AL41 -> -3.1671366 | D33: =C33/C$64 -> -1.6673063e-05 | E33: =E32+D33 -> 1.1404242 | F33: =IF(AND(E33<=0),"C",IF(E33<=0.8,"A",IF(E33<=0.95,"B","C"))) -> C | G33: =VLOOKUP(B$4:B$63,I$4:M$63,5,0) -> C | I33: MR 1819 корич | J33: ='Юнит 19'!S11 -> 0 | K33: =J33/J$64 -> 0 | L33: =L32+K33 -> 0.99571429 | M33: =_xlfn.IFS(L33<80%,"A",L33<=95%,"B",L33>95%,"C") -> C
B34: MR 1819 черн | C34: ='Юнит 19'!AL10 -> -6.3342732 | D34: =C34/C$64 -> -3.3346126e-05 | E34: =E33+D34 -> 1.1403908 | F34: =IF(AND(E34<=0),"C",IF(E34<=0.8,"A",IF(E34<=0.95,"B","C"))) -> C | G34: =VLOOKUP(B$4:B$63,I$4:M$63,5,0) -> C | I34: MR Р1874 черн | J34: ='Юнит 19'!S12 -> 0 | K34: =J34/J$64 -> 0 | L34: =L33+K34 -> 0.99571429 | M34: =_xlfn.IFS(L34<80%,"A",L34<=95%,"B",L34>95%,"C") -> C
B35: 2100красный | C35: ='Юнит 19'!AL40 -> -8.4456976 | D35: =C35/C$64 -> -4.4461501e-05 | E35: =E34+D35 -> 1.1403464 | F35: =IF(AND(E35<=0),"C",IF(E35<=0.8,"A",IF(E35<=0.95,"B","C"))) -> C | G35: =VLOOKUP(B$4:B$63,I$4:M$63,5,0) -> C | I35: MR Р1874 корич | J35: ='Юнит 19'!S13 -> 0 | K35: =J35/J$64 -> 0 | L35: =L34+K35 -> 0.99571429 | M35: =_xlfn.IFS(L35<80%,"A",L35<=95%,"B",L35>95%,"C") -> C
B36: 2104 | C36: ='Юнит 19'!AL42 -> -8.4456976 | D36: =C36/C$64 -> -4.4461501e-05 | E36: =E35+D36 -> 1.1403019 | F36: =IF(AND(E36<=0),"C",IF(E36<=0.8,"A",IF(E36<=0.95,"B","C"))) -> C | G36: =VLOOKUP(B$4:B$63,I$4:M$63,5,0) -> C | I36: MR Р1886 корич | J36: ='Юнит 19'!S15 -> 0 | K36: =J36/J$64 -> 0 | L36: =L35+K36 -> 0.99571429 | M36: =_xlfn.IFS(L36<80%,"A",L36<=95%,"B",L36>95%,"C") -> C
B37: 2084 | C37: ='Юнит 19'!AL54 -> -14.779971 | D37: =C37/C$64 -> -7.7807627e-05 | E37: =E36+D37 -> 1.1402241 | F37: =IF(AND(E37<=0),"C",IF(E37<=0.8,"A",IF(E37<=0.95,"B","C"))) -> C | G37: =VLOOKUP(B$4:B$63,I$4:M$63,5,0) -> C | I37: qs001 | J37: ='Юнит 19'!S19 -> 0 | K37: =J37/J$64 -> 0 | L37: =L36+K37 -> 0.99571429 | M37: =_xlfn.IFS(L37<80%,"A",L37<=95%,"B",L37>95%,"C") -> C
B38: 6008 | C38: ='Юнит 19'!AL43 -> -23.225668 | D38: =C38/C$64 -> -0.00012226913 | E38: =E37+D38 -> 1.1401018 | F38: =IF(AND(E38<=0),"C",IF(E38<=0.8,"A",IF(E38<=0.95,"B","C"))) -> C | G38: =VLOOKUP(B$4:B$63,I$4:M$63,5,0) -> C | I38: qs010 | J38: ='Юнит 19'!S27 -> 0 | K38: =J38/J$64 -> 0 | L38: =L37+K38 -> 0.99571429 | M38: =_xlfn.IFS(L38<80%,"A",L38<=95%,"B",L38>95%,"C") -> C
B39: 2038красный | C39: ='Юнит 19'!AL38 -> -93.847122 | D39: =C39/C$64 -> -0.00049404847 | E39: =E38+D39 -> 1.1396078 | F39: =IF(AND(E39<=0),"C",IF(E39<=0.8,"A",IF(E39<=0.95,"B","C"))) -> C | G39: =VLOOKUP(B$4:B$63,I$4:M$63,5,0) -> C | I39: qs011 | J39: ='Юнит 19'!S28 -> 0 | K39: =J39/J$64 -> 0 | L39: =L38+K39 -> 0.99571429 | M39: =_xlfn.IFS(L39<80%,"A",L39<=95%,"B",L39>95%,"C") -> C
B40: 2038ч/б | C40: ='Юнит 19'!AL37 -> -95.41141 | D40: =C40/C$64 -> -0.0005022835 | E40: =E39+D40 -> 1.1391055 | F40: =IF(AND(E40<=0),"C",IF(E40<=0.8,"A",IF(E40<=0.95,"B","C"))) -> C | G40: =VLOOKUP(B$4:B$63,I$4:M$63,5,0) -> C | I40: qs012 | J40: ='Юнит 19'!S29 -> 0 | K40: =J40/J$64 -> 0 | L40: =L39+K40 -> 0.99571429 | M40: =_xlfn.IFS(L40<80%,"A",L40<=95%,"B",L40>95%,"C") -> C
B41: qs012 | C41: ='Юнит 19'!AL29 -> -101.62142 | D41: =C41/C$64 -> -0.00053497548 | E41: =E40+D41 -> 1.1385705 | F41: =IF(AND(E41<=0),"C",IF(E41<=0.8,"A",IF(E41<=0.95,"B","C"))) -> C | G41: =VLOOKUP(B$4:B$63,I$4:M$63,5,0) -> C | I41: qs001 Ж | J41: ='Юнит 19'!S33 -> 0 | K41: =J41/J$64 -> 0 | L41: =L40+K41 -> 0.99571429 | M41: =_xlfn.IFS(L41<80%,"A",L41<=95%,"B",L41>95%,"C") -> C
B42: qs001 | C42: ='Юнит 19'!AL19 -> -190.11 | D42: =C42/C$64 -> -0.0010008144 | E42: =E41+D42 -> 1.1375697 | F42: =IF(AND(E42<=0),"C",IF(E42<=0.8,"A",IF(E42<=0.95,"B","C"))) -> C | G42: =VLOOKUP(B$4:B$63,I$4:M$63,5,0) -> C | I42: 2038ч/б | J42: ='Юнит 19'!S37 -> 0 | K42: =J42/J$64 -> 0 | L42: =L41+K42 -> 0.99571429 | M42: =_xlfn.IFS(L42<80%,"A",L42<=95%,"B",L42>95%,"C") -> C
B43: MR 1890 желт | C43: ='Юнит 19'!AL17 -> -193.15706 | D43: =C43/C$64 -> -0.0010168554 | E43: =E42+D43 -> 1.1365528 | F43: =IF(AND(E43<=0),"C",IF(E43<=0.8,"A",IF(E43<=0.95,"B","C"))) -> C | G43: =VLOOKUP(B$4:B$63,I$4:M$63,5,0) -> B | I43: 2038красный | J43: ='Юнит 19'!S38 -> 0 | K43: =J43/J$64 -> 0 | L43: =L42+K43 -> 0.99571429 | M43: =_xlfn.IFS(L43<80%,"A",L43<=95%,"B",L43>95%,"C") -> C
B44: 2100черный | C44: ='Юнит 19'!AL39 -> -561.97855 | D44: =C44/C$64 -> -0.0029584779 | E44: =E43+D44 -> 1.1335944 | F44: =IF(AND(E44<=0),"C",IF(E44<=0.8,"A",IF(E44<=0.95,"B","C"))) -> C | G44: =VLOOKUP(B$4:B$63,I$4:M$63,5,0) -> C | I44: 2100красный | J44: ='Юнит 19'!S40 -> 0 | K44: =J44/J$64 -> 0 | L44: =L43+K44 -> 0.99571429 | M44: =_xlfn.IFS(L44<80%,"A",L44<=95%,"B",L44>95%,"C") -> C
B45: 2081 | C45: ='Юнит 19'!AL53 -> -582.84564 | D45: =C45/C$64 -> -0.0030683306 | E45: =E44+D45 -> 1.130526 | F45: =IF(AND(E45<=0),"C",IF(E45<=0.8,"A",IF(E45<=0.95,"B","C"))) -> C | G45: =VLOOKUP(B$4:B$63,I$4:M$63,5,0) -> C | I45: 2100фиолетовый | J45: ='Юнит 19'!S41 -> 0 | K45: =J45/J$64 -> 0 | L45: =L44+K45 -> 0.99571429 | M45: =_xlfn.IFS(L45<80%,"A",L45<=95%,"B",L45>95%,"C") -> C
B46: 580черный | C46: ='Юнит 19'!AL48 -> -634.00564 | D46: =C46/C$64 -> -0.0033376571 | E46: =E45+D46 -> 1.1271884 | F46: =IF(AND(E46<=0),"C",IF(E46<=0.8,"A",IF(E46<=0.95,"B","C"))) -> C | G46: =VLOOKUP(B$4:B$63,I$4:M$63,5,0) -> C | I46: 2104 | J46: ='Юнит 19'!S42 -> 0 | K46: =J46/J$64 -> 0 | L46: =L45+K46 -> 0.99571429 | M46: =_xlfn.IFS(L46<80%,"A",L46<=95%,"B",L46>95%,"C") -> C
B47: 2064коричневые | C47: ='Юнит 19'!AL51 -> -729.61135 | D47: =C47/C$64 -> -0.0038409635 | E47: =E46+D47 -> 1.1233474 | F47: =IF(AND(E47<=0),"C",IF(E47<=0.8,"A",IF(E47<=0.95,"B","C"))) -> C | G47: =VLOOKUP(B$4:B$63,I$4:M$63,5,0) -> C | I47: 6008 | J47: ='Юнит 19'!S43 -> 0 | K47: =J47/J$64 -> 0 | L47: =L46+K47 -> 0.99571429 | M47: =_xlfn.IFS(L47<80%,"A",L47<=95%,"B",L47>95%,"C") -> C
B48: MR Р1886 черн | C48: ='Юнит 19'!AL14 -> -861.62426 | D48: =C48/C$64 -> -0.0045359318 | E48: =E47+D48 -> 1.1188115 | F48: =IF(AND(E48<=0),"C",IF(E48<=0.8,"A",IF(E48<=0.95,"B","C"))) -> C | G48: =VLOOKUP(B$4:B$63,I$4:M$63,5,0) -> C | I48: 123черный | J48: ='Юнит 19'!S44 -> 0 | K48: =J48/J$64 -> 0 | L48: =L47+K48 -> 0.99571429 | M48: =_xlfn.IFS(L48<80%,"A",L48<=95%,"B",L48>95%,"C") -> C
B49: 2801 | C49: ='Юнит 19'!AL57 -> -1000 | D49: =C49/C$64 -> -0.0052643966 | E49: =E48+D49 -> 1.1135471 | F49: =IF(AND(E49<=0),"C",IF(E49<=0.8,"A",IF(E49<=0.95,"B","C"))) -> C | G49: =VLOOKUP(B$4:B$63,I$4:M$63,5,0) -> C | I49: 123метал | J49: ='Юнит 19'!S45 -> 0 | K49: =J49/J$64 -> 0 | L49: =L48+K49 -> 0.99571429 | M49: =_xlfn.IFS(L49<80%,"A",L49<=95%,"B",L49>95%,"C") -> C
B50: 03004 С9-08 | C50: ='Юнит 19'!AL60 -> -1000 | D50: =C50/C$64 -> -0.0052643966 | E50: =E49+D50 -> 1.1082827 | F50: =IF(AND(E50<=0),"C",IF(E50<=0.8,"A",IF(E50<=0.95,"B","C"))) -> C | G50: =VLOOKUP(B$4:B$63,I$4:M$63,5,0) -> C | I50: 180ч/б | J50: ='Юнит 19'!S46 -> 0 | K50: =J50/J$64 -> 0 | L50: =L49+K50 -> 0.99571429 | M50: =_xlfn.IFS(L50<80%,"A",L50<=95%,"B",L50>95%,"C") -> C
B51: 123метал | C51: ='Юнит 19'!AL45 -> -1036.9499 | D51: =C51/C$64 -> -0.0054589156 | E51: =E50+D51 -> 1.1028238 | F51: =IF(AND(E51<=0),"C",IF(E51<=0.8,"A",IF(E51<=0.95,"B","C"))) -> C | G51: =VLOOKUP(B$4:B$63,I$4:M$63,5,0) -> C | I51: 180узор | J51: ='Юнит 19'!S47 -> 0 | K51: =J51/J$64 -> 0 | L51: =L50+K51 -> 0.99571429 | M51: =_xlfn.IFS(L51<80%,"A",L51<=95%,"B",L51>95%,"C") -> C
B52: 180узор | C52: ='Юнит 19'!AL47 -> -1038.0056 | D52: =C52/C$64 -> -0.0054644733 | E52: =E51+D52 -> 1.0973593 | F52: =IF(AND(E52<=0),"C",IF(E52<=0.8,"A",IF(E52<=0.95,"B","C"))) -> C | G52: =VLOOKUP(B$4:B$63,I$4:M$63,5,0) -> C | I52: 580черный | J52: ='Юнит 19'!S48 -> 0 | K52: =J52/J$64 -> 0 | L52: =L51+K52 -> 0.99571429 | M52: =_xlfn.IFS(L52<80%,"A",L52<=95%,"B",L52>95%,"C") -> C
B53: 8852 | C53: ='Юнит 19'!AL56 -> -1041.1728 | D53: =C53/C$64 -> -0.0054811464 | E53: =E52+D53 -> 1.0918782 | F53: =IF(AND(E53<=0),"C",IF(E53<=0.8,"A",IF(E53<=0.95,"B","C"))) -> C | G53: =VLOOKUP(B$4:B$63,I$4:M$63,5,0) -> C | I53: 580метал | J53: ='Юнит 19'!S49 -> 0 | K53: =J53/J$64 -> 0 | L53: =L52+K53 -> 0.99571429 | M53: =_xlfn.IFS(L53<80%,"A",L53<=95%,"B",L53>95%,"C") -> C
B54: 580метал | C54: ='Юнит 19'!AL49 -> -1118.7971 | D54: =C54/C$64 -> -0.0058897915 | E54: =E53+D54 -> 1.0859884 | F54: =IF(AND(E54<=0),"C",IF(E54<=0.8,"A",IF(E54<=0.95,"B","C"))) -> C | G54: =VLOOKUP(B$4:B$63,I$4:M$63,5,0) -> C | I54: 2064коричневые | J54: ='Юнит 19'!S51 -> 0 | K54: =J54/J$64 -> 0 | L54: =L53+K54 -> 0.99571429 | M54: =_xlfn.IFS(L54<80%,"A",L54<=95%,"B",L54>95%,"C") -> C
B55: 123черный | C55: ='Юнит 19'!AL44 -> -1122.6114 | D55: =C55/C$64 -> -0.0059098713 | E55: =E54+D55 -> 1.0800785 | F55: =IF(AND(E55<=0),"C",IF(E55<=0.8,"A",IF(E55<=0.95,"B","C"))) -> C | G55: =VLOOKUP(B$4:B$63,I$4:M$63,5,0) -> C | I55: 2064фиолетовые | J55: ='Юнит 19'!S52 -> 0 | K55: =J55/J$64 -> 0 | L55: =L54+K55 -> 0.99571429 | M55: =_xlfn.IFS(L55<80%,"A",L55<=95%,"B",L55>95%,"C") -> C
B56: qs010ж | C56: ='Юнит 19'!AL34 -> -1126.9357 | D56: =C56/C$64 -> -0.0059326364 | E56: =E55+D56 -> 1.0741459 | F56: =IF(AND(E56<=0),"C",IF(E56<=0.8,"A",IF(E56<=0.95,"B","C"))) -> C | G56: =VLOOKUP(B$4:B$63,I$4:M$63,5,0) -> B | I56: 2084 | J56: ='Юнит 19'!S54 -> 0 | K56: =J56/J$64 -> 0 | L56: =L55+K56 -> 0.99571429 | M56: =_xlfn.IFS(L56<80%,"A",L56<=95%,"B",L56>95%,"C") -> C
B57: 2064фиолетовые | C57: ='Юнит 19'!AL52 -> -1127.8899 | D57: =C57/C$64 -> -0.0059376598 | E57: =E56+D57 -> 1.0682082 | F57: =IF(AND(E57<=0),"C",IF(E57<=0.8,"A",IF(E57<=0.95,"B","C"))) -> C | G57: =VLOOKUP(B$4:B$63,I$4:M$63,5,0) -> C | I57: 8852 | J57: ='Юнит 19'!S56 -> 0 | K57: =J57/J$64 -> 0 | L57: =L56+K57 -> 0.99571429 | M57: =_xlfn.IFS(L57<80%,"A",L57<=95%,"B",L57>95%,"C") -> C
B58: 180ч/б | C58: ='Юнит 19'!AL46 -> -1201.6185 | D58: =C58/C$64 -> -0.0063257963 | E58: =E57+D58 -> 1.0618824 | F58: =IF(AND(E58<=0),"C",IF(E58<=0.8,"A",IF(E58<=0.95,"B","C"))) -> C | G58: =VLOOKUP(B$4:B$63,I$4:M$63,5,0) -> C | I58: 2801 | J58: ='Юнит 19'!S57 -> 0 | K58: =J58/J$64 -> 0 | L58: =L57+K58 -> 0.99571429 | M58: =_xlfn.IFS(L58<80%,"A",L58<=95%,"B",L58>95%,"C") -> C
B59: 2064ч/б | C59: ='Юнит 19'!AL50 -> -1334.8414 | D59: =C59/C$64 -> -0.0070271345 | E59: =E58+D59 -> 1.0548553 | F59: =IF(AND(E59<=0),"C",IF(E59<=0.8,"A",IF(E59<=0.95,"B","C"))) -> C | G59: =VLOOKUP(B$4:B$63,I$4:M$63,5,0) -> C | I59: 2811 С3 | J59: ='Юнит 19'!S58 -> 0 | K59: =J59/J$64 -> 0 | L59: =L58+K59 -> 0.99571429 | M59: =_xlfn.IFS(L59<80%,"A",L59<=95%,"B",L59>95%,"C") -> C
B60: 2811 С3 | C60: ='Юнит 19'!AL58 -> -2000 | D60: =C60/C$64 -> -0.010528793 | E60: =E59+D60 -> 1.0443265 | F60: =IF(AND(E60<=0),"C",IF(E60<=0.8,"A",IF(E60<=0.95,"B","C"))) -> C | G60: =VLOOKUP(B$4:B$63,I$4:M$63,5,0) -> C | I60: 03004 С9-08 | J60: ='Юнит 19'!S60 -> 0 | K60: =J60/J$64 -> 0 | L60: =L59+K60 -> 0.99571429 | M60: =_xlfn.IFS(L60<80%,"A",L60<=95%,"B",L60>95%,"C") -> C
B61: qs008 | C61: ='Юнит 19'!AL25 -> -2045.6027 | D61: =C61/C$64 -> -0.010768864 | E61: =E60+D61 -> 1.0335576 | F61: =IF(AND(E61<=0),"C",IF(E61<=0.8,"A",IF(E61<=0.95,"B","C"))) -> C | G61: =VLOOKUP(B$4:B$63,I$4:M$63,5,0) -> C | I61: 03977 С9-08 | J61: ='Юнит 19'!S61 -> 0 | K61: =J61/J$64 -> 0 | L61: =L60+K61 -> 0.99571429 | M61: =_xlfn.IFS(L61<80%,"A",L61<=95%,"B",L61>95%,"C") -> C
B62: 03004 С8-02 | C62: ='Юнит 19'!AL59 -> -2714.03 | D62: =C62/C$64 -> -0.01428773 | E62: =E61+D62 -> 1.0192699 | F62: =IF(AND(E62<=0),"C",IF(E62<=0.8,"A",IF(E62<=0.95,"B","C"))) -> C | G62: =VLOOKUP(B$4:B$63,I$4:M$63,5,0) -> C | I62: 03985 С9-124 | J62: ='Юнит 19'!S62 -> 0 | K62: =J62/J$64 -> 0 | L62: =L61+K62 -> 0.99571429 | M62: =_xlfn.IFS(L62<80%,"A",L62<=95%,"B",L62>95%,"C") -> C
B63: qs009 | C63: ='Юнит 19'!AL26 -> -3660.4158 | D63: =C63/C$64 -> -0.01926988 | E63: =E62+D63 -> 1 | F63: =IF(AND(E63<=0),"C",IF(E63<=0.8,"A",IF(E63<=0.95,"B","C"))) -> C | G63: =VLOOKUP(B$4:B$63,I$4:M$63,5,0) -> C | I63: MR Р1886 черн | J63: ='Юнит 19'!S14 -> -1 | K63: =J63/J$64 -> -0.0014285714 | L63: =L62+K63 -> 0.99428571 | M63: =_xlfn.IFS(L63<80%,"A",L63<=95%,"B",L63>95%,"C") -> C
C64: =SUM(C4:C63) -> 189955.29 | D64: =SUM(D4:D44) -> 1.1335944 | J64: =SUM(J4:J63) -> 700 | K64: =SUM(K4:K44) -> 1.0014286
C67: Прибыль | D67: % прибыль | E67: Доля | F67: ABC прибыль | G67: ABC кол-во | J67: Кол-во | K67: % кол-во | L67: Доля | M67: ABC кол-во
D68: =C68/C$120 -> #DIV/0! | E68: =D68 -> #DIV/0! | F68: =IF(AND(E68<=0),"C",IF(E68<=0.8,"A",IF(E68<=0.95,"B","C"))) -> #DIV/0! | G68: =VLOOKUP(B68:B119,I$68:M$119,5,0) -> #N/A | K68: =J68/J$120 -> #DIV/0! | L68: =K68 -> #DIV/0! | M68: =_xlfn.IFS(L68<80%,"A",L68<=95%,"B",L68>95%,"C") -> #DIV/0!
D69: =C69/C$120 -> #DIV/0! | E69: =D69+E68 -> #DIV/0! | F69: =IF(AND(E69<=0),"C",IF(E69<=0.8,"A",IF(E69<=0.95,"B","C"))) -> #DIV/0! | G69: =VLOOKUP(B69:B120,I$68:M$119,5,0) -> #N/A | K69: =J69/J$120 -> #DIV/0! | L69: =K69+L68 -> #DIV/0! | M69: =_xlfn.IFS(L69<80%,"A",L69<=95%,"B",L69>95%,"C") -> #DIV/0!
D70: =C70/C$120 -> #DIV/0! | E70: =D70+E69 -> #DIV/0! | F70: =IF(AND(E70<=0),"C",IF(E70<=0.8,"A",IF(E70<=0.95,"B","C"))) -> #DIV/0! | G70: =VLOOKUP(B70:B121,I$68:M$119,5,0) -> #N/A | K70: =J70/J$120 -> #DIV/0! | L70: =K70+L69 -> #DIV/0! | M70: =_xlfn.IFS(L70<80%,"A",L70<=95%,"B",L70>95%,"C") -> #DIV/0!
D71: =C71/C$120 -> #DIV/0! | E71: =D71+E70 -> #DIV/0! | F71: =IF(AND(E71<=0),"C",IF(E71<=0.8,"A",IF(E71<=0.95,"B","C"))) -> #DIV/0! | G71: =VLOOKUP(B71:B122,I$68:M$119,5,0) -> #N/A | K71: =J71/J$120 -> #DIV/0! | L71: =K71+L70 -> #DIV/0! | M71: =_xlfn.IFS(L71<80%,"A",L71<=95%,"B",L71>95%,"C") -> #DIV/0!
D72: =C72/C$120 -> #DIV/0! | E72: =D72+E71 -> #DIV/0! | F72: =IF(AND(E72<=0),"C",IF(E72<=0.8,"A",IF(E72<=0.95,"B","C"))) -> #DIV/0! | G72: =VLOOKUP(B72:B123,I$68:M$119,5,0) -> #N/A | K72: =J72/J$120 -> #DIV/0! | L72: =K72+L71 -> #DIV/0! | M72: =_xlfn.IFS(L72<80%,"A",L72<=95%,"B",L72>95%,"C") -> #DIV/0!
D73: =C73/C$120 -> #DIV/0! | E73: =D73+E72 -> #DIV/0! | F73: =IF(AND(E73<=0),"C",IF(E73<=0.8,"A",IF(E73<=0.95,"B","C"))) -> #DIV/0! | G73: =VLOOKUP(B73:B124,I$68:M$119,5,0) -> #N/A | K73: =J73/J$120 -> #DIV/0! | L73: =K73+L72 -> #DIV/0! | M73: =_xlfn.IFS(L73<80%,"A",L73<=95%,"B",L73>95%,"C") -> #DIV/0!
D74: =C74/C$120 -> #DIV/0! | E74: =D74+E73 -> #DIV/0! | F74: =IF(AND(E74<=0),"C",IF(E74<=0.8,"A",IF(E74<=0.95,"B","C"))) -> #DIV/0! | G74: =VLOOKUP(B74:B125,I$68:M$119,5,0) -> #N/A | K74: =J74/J$120 -> #DIV/0! | L74: =K74+L73 -> #DIV/0! | M74: =_xlfn.IFS(L74<80%,"A",L74<=95%,"B",L74>95%,"C") -> #DIV/0!
D75: =C75/C$120 -> #DIV/0! | E75: =D75+E74 -> #DIV/0! | F75: =IF(AND(E75<=0),"C",IF(E75<=0.8,"A",IF(E75<=0.95,"B","C"))) -> #DIV/0! | G75: =VLOOKUP(B75:B126,I$68:M$119,5,0) -> #N/A | K75: =J75/J$120 -> #DIV/0! | L75: =K75+L74 -> #DIV/0! | M75: =_xlfn.IFS(L75<80%,"A",L75<=95%,"B",L75>95%,"C") -> #DIV/0!
D76: =C76/C$120 -> #DIV/0! | E76: =D76+E75 -> #DIV/0! | F76: =IF(AND(E76<=0),"C",IF(E76<=0.8,"A",IF(E76<=0.95,"B","C"))) -> #DIV/0! | G76: =VLOOKUP(B76:B127,I$68:M$119,5,0) -> #N/A | K76: =J76/J$120 -> #DIV/0! | L76: =K76+L75 -> #DIV/0! | M76: =_xlfn.IFS(L76<80%,"A",L76<=95%,"B",L76>95%,"C") -> #DIV/0!
D77: =C77/C$120 -> #DIV/0! | E77: =D77+E76 -> #DIV/0! | F77: =IF(AND(E77<=0),"C",IF(E77<=0.8,"A",IF(E77<=0.95,"B","C"))) -> #DIV/0! | G77: =VLOOKUP(B77:B128,I$68:M$119,5,0) -> #N/A | K77: =J77/J$120 -> #DIV/0! | L77: =K77+L76 -> #DIV/0! | M77: =_xlfn.IFS(L77<80%,"A",L77<=95%,"B",L77>95%,"C") -> #DIV/0!
D78: =C78/C$120 -> #DIV/0! | E78: =D78+E77 -> #DIV/0! | F78: =IF(AND(E78<=0),"C",IF(E78<=0.8,"A",IF(E78<=0.95,"B","C"))) -> #DIV/0! | G78: =VLOOKUP(B78:B129,I$68:M$119,5,0) -> #N/A | K78: =J78/J$120 -> #DIV/0! | L78: =K78+L77 -> #DIV/0! | M78: =_xlfn.IFS(L78<80%,"A",L78<=95%,"B",L78>95%,"C") -> #DIV/0!
D79: =C79/C$120 -> #DIV/0! | E79: =D79+E78 -> #DIV/0! | F79: =IF(AND(E79<=0),"C",IF(E79<=0.8,"A",IF(E79<=0.95,"B","C"))) -> #DIV/0! | G79: =VLOOKUP(B79:B130,I$68:M$119,5,0) -> #N/A | K79: =J79/J$120 -> #DIV/0! | L79: =K79+L78 -> #DIV/0! | M79: =_xlfn.IFS(L79<80%,"A",L79<=95%,"B",L79>95%,"C") -> #DIV/0!
D80: =C80/C$120 -> #DIV/0! | E80: =D80+E79 -> #DIV/0! | F80: =IF(AND(E80<=0),"C",IF(E80<=0.8,"A",IF(E80<=0.95,"B","C"))) -> #DIV/0! | G80: =VLOOKUP(B80:B131,I$68:M$119,5,0) -> #N/A | K80: =J80/J$120 -> #DIV/0! | L80: =K80+L79 -> #DIV/0! | M80: =_xlfn.IFS(L80<80%,"A",L80<=95%,"B",L80>95%,"C") -> #DIV/0!
... D119: =C119/C$120 -> #DIV/0! | E119: =D119+E118 -> #DIV/0! | F119: =IF(AND(E119<=0),"C",IF(E119<=0.8,"A",IF(E119<=0.95,"B","C"))) -> #DIV/0! | G119: =VLOOKUP(B119:B170,I$68:M$119,5,0) -> #N/A | K119: =J119/J$120 -> #DIV/0! | L119: =K119+L118 -> #DIV/0! | M119: =_xlfn.IFS(L119<80%,"A",L119<=95%,"B",L119>95%,"C") -> #DIV/0!
C120: =SUM(C68:C119) -> 0 | D120: =SUM(D68:D119) -> #DIV/0! | J120: =SUM(J68:J119) -> 0 | K120: =SUM(K68:K119) -> #DIV/0!

Sheet АВС АПРЕЛЬ
B2: ОЧКИ
C3: Прибыль | D3: % прибыль | E3: Доля | F3: ABC прибыль | G3: ABC кол-во | J3: Кол-во | K3: % кол-во | L3: Доля | M3: ABC кол-во
B4: Qs черн Сул | C4: =АПРЕЛЬ!AL4 -> 468765.56 | D4: =C4/C$58 -> 0.47133803 | E4: =D4 -> 0.47133803 | F4: =IF(AND(E4<=0),"C",IF(E4<=0.8,"A",IF(E4<=0.95,"B","C"))) -> A | G4: =VLOOKUP(B$4:B$57,I$4:M$57,5,0) -> A | I4: Qs черн Сул | J4: =АПРЕЛЬ!S4 -> 1330 | K4: =J4/J$58 -> 0.42195431 | L4: =K4 -> 0.42195431 | M4: =_xlfn.IFS(L4<80%,"A",L4<=95%,"B",L4>95%,"C") -> A | P4: A | Q4: 0.8
B5: Черные с железкой Сул | C5: =АПРЕЛЬ!AL3 -> 167973.74 | D5: =C5/C$58 -> 0.16889554 | E5: =E4+D5 -> 0.64023356 | F5: =IF(AND(E5<=0),"C",IF(E5<=0.8,"A",IF(E5<=0.95,"B","C"))) -> A | G5: =VLOOKUP(B$4:B$57,I$4:M$57,5,0) -> A | I5: Черные с железкой Сул | J5: =АПРЕЛЬ!S3 -> 521 | K5: =J5/J$58 -> 0.16529188 | L5: =L4+K5 -> 0.58724619 | M5: =_xlfn.IFS(L5<80%,"A",L5<=95%,"B",L5>95%,"C") -> A | P5: B | Q5: 0.15
B6: flip желтые Сул | C6: =АПРЕЛЬ!AL8 -> 72657.211 | D6: =C6/C$58 -> 0.073055935 | E6: =E5+D6 -> 0.7132895 | F6: =IF(AND(E6<=0),"C",IF(E6<=0.8,"A",IF(E6<=0.95,"B","C"))) -> A | G6: =VLOOKUP(B$4:B$57,I$4:M$57,5,0) -> A | I6: flip желтые Сул | J6: =АПРЕЛЬ!S8 -> 222 | K6: =J6/J$58 -> 0.070431472 | L6: =L5+K6 -> 0.65767766 | M6: =_xlfn.IFS(L6<80%,"A",L6<=95%,"B",L6>95%,"C") -> A | P6: C | Q6: 0.05
B7: Qs желт Сул | C7: =АПРЕЛЬ!AL6 -> 39205.563 | D7: =C7/C$58 -> 0.039420713 | E7: =E6+D7 -> 0.75271021 | F7: =IF(AND(E7<=0),"C",IF(E7<=0.8,"A",IF(E7<=0.95,"B","C"))) -> A | G7: =VLOOKUP(B$4:B$57,I$4:M$57,5,0) -> A | I7: Qs син Сул | J7: =АПРЕЛЬ!S5 -> 159 | K7: =J7/J$58 -> 0.050444162 | L7: =L6+K7 -> 0.70812183 | M7: =_xlfn.IFS(L7<80%,"A",L7<=95%,"B",L7>95%,"C") -> A
B8: MR8854 C2 Сул | C8: =АПРЕЛЬ!AL9 -> 32884.319 | D8: =C8/C$58 -> 0.033064779 | E8: =E7+D8 -> 0.78577499 | F8: =IF(AND(E8<=0),"C",IF(E8<=0.8,"A",IF(E8<=0.95,"B","C"))) -> A | G8: =VLOOKUP(B$4:B$57,I$4:M$57,5,0) -> B | I8: Qs желт Сул | J8: =АПРЕЛЬ!S6 -> 140 | K8: =J8/J$58 -> 0.044416244 | L8: =L7+K8 -> 0.75253807 | M8: =_xlfn.IFS(L8<80%,"A",L8<=95%,"B",L8>95%,"C") -> A
B9: MR 1890 черн | C9: =АПРЕЛЬ!AL16 -> 27024.387 | D9: =C9/C$58 -> 0.02717269 | E9: =E8+D9 -> 0.81294768 | F9: =IF(AND(E9<=0),"C",IF(E9<=0.8,"A",IF(E9<=0.95,"B","C"))) -> B | G9: =VLOOKUP(B$4:B$57,I$4:M$57,5,0) -> B | I9: flip черные Сул | J9: =АПРЕЛЬ!S7 -> 91 | K9: =J9/J$58 -> 0.028870558 | L9: =L8+K9 -> 0.78140863 | M9: =_xlfn.IFS(L9<80%,"A",L9<=95%,"B",L9>95%,"C") -> A
B10: MR 1890 желт | C10: =АПРЕЛЬ!AL17 -> 22685.49 | D10: =C10/C$58 -> 0.022809982 | E10: =E9+D10 -> 0.83575766 | F10: =IF(AND(E10<=0),"C",IF(E10<=0.8,"A",IF(E10<=0.95,"B","C"))) -> B | G10: =VLOOKUP(B$4:B$57,I$4:M$57,5,0) -> B | I10: MR 1890 желт | J10: =АПРЕЛЬ!S17 -> 85 | K10: =J10/J$58 -> 0.026967005 | L10: =L9+K10 -> 0.80837563 | M10: =_xlfn.IFS(L10<80%,"A",L10<=95%,"B",L10>95%,"C") -> B
B11: MR 1890 корич | C11: =АПРЕЛЬ!AL18 -> 21578.072 | D11: =C11/C$58 -> 0.021696487 | E11: =E10+D11 -> 0.85745415 | F11: =IF(AND(E11<=0),"C",IF(E11<=0.8,"A",IF(E11<=0.95,"B","C"))) -> B | G11: =VLOOKUP(B$4:B$57,I$4:M$57,5,0) -> B | I11: MR 1890 черн | J11: =АПРЕЛЬ!S16 -> 73 | K11: =J11/J$58 -> 0.023159898 | L11: =L10+K11 -> 0.83153553 | M11: =_xlfn.IFS(L11<80%,"A",L11<=95%,"B",L11>95%,"C") -> B
B12: qs002 | C12: =АПРЕЛЬ!AL20 -> 21384.736 | D12: =C12/C$58 -> 0.02150209 | E12: =E11+D12 -> 0.87895624 | F12: =IF(AND(E12<=0),"C",IF(E12<=0.8,"A",IF(E12<=0.95,"B","C"))) -> B | G12: =VLOOKUP(B$4:B$57,I$4:M$57,5,0) -> B | I12: MR 1890 корич | J12: =АПРЕЛЬ!S18 -> 70 | K12: =J12/J$58 -> 0.022208122 | L12: =L11+K12 -> 0.85374365 | M12: =_xlfn.IFS(L12<80%,"A",L12<=95%,"B",L12>95%,"C") -> B
B13: qs006 | C13: =АПРЕЛЬ!AL23 -> 19462.443 | D13: =C13/C$58 -> 0.019569248 | E13: =E12+D13 -> 0.89852549 | F13: =IF(AND(E13<=0),"C",IF(E13<=0.8,"A",IF(E13<=0.95,"B","C"))) -> B | G13: =VLOOKUP(B$4:B$57,I$4:M$57,5,0) -> B | I13: MR8854 C2 Сул | J13: =АПРЕЛЬ!S9 -> 59 | K13: =J13/J$58 -> 0.018718274 | L13: =L12+K13 -> 0.87246193 | M13: =_xlfn.IFS(L13<80%,"A",L13<=95%,"B",L13>95%,"C") -> B
B14: qs015 | C14: =АПРЕЛЬ!AL32 -> 16401.804 | D14: =C14/C$58 -> 0.016491813 | E14: =E13+D14 -> 0.9150173 | F14: =IF(AND(E14<=0),"C",IF(E14<=0.8,"A",IF(E14<=0.95,"B","C"))) -> B | G14: =VLOOKUP(B$4:B$57,I$4:M$57,5,0) -> B | I14: qs006 | J14: =АПРЕЛЬ!S23 -> 44 | K14: =J14/J$58 -> 0.013959391 | L14: =L13+K14 -> 0.88642132 | M14: =_xlfn.IFS(L14<80%,"A",L14<=95%,"B",L14>95%,"C") -> B
B15: Qs син Сул | C15: =АПРЕЛЬ!AL5 -> 15674.011 | D15: =C15/C$58 -> 0.015760026 | E15: =E14+D15 -> 0.93077733 | F15: =IF(AND(E15<=0),"C",IF(E15<=0.8,"A",IF(E15<=0.95,"B","C"))) -> B | G15: =VLOOKUP(B$4:B$57,I$4:M$57,5,0) -> A | I15: qs002 | J15: =АПРЕЛЬ!S20 -> 43 | K15: =J15/J$58 -> 0.013642132 | L15: =L14+K15 -> 0.90006345 | M15: =_xlfn.IFS(L15<80%,"A",L15<=95%,"B",L15>95%,"C") -> B
B16: qs007 | C16: =АПРЕЛЬ!AL24 -> 14437.356 | D16: =C16/C$58 -> 0.014516584 | E16: =E15+D16 -> 0.94529391 | F16: =IF(AND(E16<=0),"C",IF(E16<=0.8,"A",IF(E16<=0.95,"B","C"))) -> B | G16: =VLOOKUP(B$4:B$57,I$4:M$57,5,0) -> B | I16: qs007 | J16: =АПРЕЛЬ!S24 -> 36 | K16: =J16/J$58 -> 0.01142132 | L16: =L15+K16 -> 0.91148477 | M16: =_xlfn.IFS(L16<80%,"A",L16<=95%,"B",L16>95%,"C") -> B
B17: flip черные Сул | C17: =АПРЕЛЬ!AL7 -> 14347.059 | D17: =C17/C$58 -> 0.014425792 | E17: =E16+D17 -> 0.9597197 | F17: =IF(AND(E17<=0),"C",IF(E17<=0.8,"A",IF(E17<=0.95,"B","C"))) -> C | G17: =VLOOKUP(B$4:B$57,I$4:M$57,5,0) -> A | I17: qs015 | J17: =АПРЕЛЬ!S32 -> 34 | K17: =J17/J$58 -> 0.010786802 | L17: =L16+K17 -> 0.92227157 | M17: =_xlfn.IFS(L17<80%,"A",L17<=95%,"B",L17>95%,"C") -> B
B18: qs014 | C18: =АПРЕЛЬ!AL31 -> 8657.8239 | D18: =C18/C$58 -> 0.0087053358 | E18: =E17+D18 -> 0.96842504 | F18: =IF(AND(E18<=0),"C",IF(E18<=0.8,"A",IF(E18<=0.95,"B","C"))) -> C | G18: =VLOOKUP(B$4:B$57,I$4:M$57,5,0) -> B | I18: qs010ж | J18: =АПРЕЛЬ!S34 -> 20 | K18: =J18/J$58 -> 0.0063451777 | L18: =L17+K18 -> 0.92861675 | M18: =_xlfn.IFS(L18<80%,"A",L18<=95%,"B",L18>95%,"C") -> B
B19: qs010ж | C19: =АПРЕЛЬ!AL34 -> 7870.1033 | D19: =C19/C$58 -> 0.0079132925 | E19: =E18+D19 -> 0.97633833 | F19: =IF(AND(E19<=0),"C",IF(E19<=0.8,"A",IF(E19<=0.95,"B","C"))) -> C | G19: =VLOOKUP(B$4:B$57,I$4:M$57,5,0) -> B | I19: qs014 | J19: =АПРЕЛЬ!S31 -> 18 | K19: =J19/J$58 -> 0.0057106599 | L19: =L18+K19 -> 0.93432741 | M19: =_xlfn.IFS(L19<80%,"A",L19<=95%,"B",L19>95%,"C") -> B
B20: qs013 | C20: =АПРЕЛЬ!AL30 -> 7029.7651 | D20: =C20/C$58 -> 0.0070683427 | E20: =E19+D20 -> 0.98340667 | F20: =IF(AND(E20<=0),"C",IF(E20<=0.8,"A",IF(E20<=0.95,"B","C"))) -> C | G20: =VLOOKUP(B$4:B$57,I$4:M$57,5,0) -> B | I20: MR Р1886 черн | J20: =АПРЕЛЬ!S14 -> 16 | K20: =J20/J$58 -> 0.0050761421 | L20: =L19+K20 -> 0.93940355 | M20: =_xlfn.IFS(L20<80%,"A",L20<=95%,"B",L20>95%,"C") -> B
B21: MR Р1886 черн | C21: =АПРЕЛЬ!AL14 -> 6149.1269 | D21: =C21/C$58 -> 0.0061828718 | E21: =E20+D21 -> 0.98958955 | F21: =IF(AND(E21<=0),"C",IF(E21<=0.8,"A",IF(E21<=0.95,"B","C"))) -> C | G21: =VLOOKUP(B$4:B$57,I$4:M$57,5,0) -> B | I21: MR 1819 корич | J21: =АПРЕЛЬ!S11 -> 15 | K21: =J21/J$58 -> 0.0047588832 | L21: =L20+K21 -> 0.94416244 | M21: =_xlfn.IFS(L21<80%,"A",L21<=95%,"B",L21>95%,"C") -> B
B22: qs003 | C22: =АПРЕЛЬ!AL21 -> 5396.6955 | D22: =C22/C$58 -> 0.0054263112 | E22: =E21+D22 -> 0.99501586 | F22: =IF(AND(E22<=0),"C",IF(E22<=0.8,"A",IF(E22<=0.95,"B","C"))) -> C | G22: =VLOOKUP(B$4:B$57,I$4:M$57,5,0) -> C | I22: qs013 | J22: =АПРЕЛЬ!S30 -> 15 | K22: =J22/J$58 -> 0.0047588832 | L22: =L21+K22 -> 0.94892132 | M22: =_xlfn.IFS(L22<80%,"A",L22<=95%,"B",L22>95%,"C") -> B
B23: MR 1819 корич | C23: =АПРЕЛЬ!AL11 -> 4568.8753 | D23: =C23/C$58 -> 0.0045939481 | E23: =E22+D23 -> 0.99960981 | F23: =IF(AND(E23<=0),"C",IF(E23<=0.8,"A",IF(E23<=0.95,"B","C"))) -> C | G23: =VLOOKUP(B$4:B$57,I$4:M$57,5,0) -> B | I23: qs009 | J23: =АПРЕЛЬ!S26 -> 14 | K23: =J23/J$58 -> 0.0044416244 | L23: =L22+K23 -> 0.95336294 | M23: =_xlfn.IFS(L23<80%,"A",L23<=95%,"B",L23>95%,"C") -> C
B24: qs001 | C24: =АПРЕЛЬ!AL19 -> 3879.6929 | D24: =C24/C$58 -> 0.0039009837 | E24: =E23+D24 -> 1.0035108 | F24: =IF(AND(E24<=0),"C",IF(E24<=0.8,"A",IF(E24<=0.95,"B","C"))) -> C | G24: =VLOOKUP(B$4:B$57,I$4:M$57,5,0) -> C | I24: qs003 | J24: =АПРЕЛЬ!S21 -> 13 | K24: =J24/J$58 -> 0.0041243655 | L24: =L23+K24 -> 0.95748731 | M24: =_xlfn.IFS(L24<80%,"A",L24<=95%,"B",L24>95%,"C") -> C
B25: MR Р1886 корич | C25: =АПРЕЛЬ!AL15 -> 3724.5249 | D25: =C25/C$58 -> 0.0037449642 | E25: =E24+D25 -> 1.0072558 | F25: =IF(AND(E25<=0),"C",IF(E25<=0.8,"A",IF(E25<=0.95,"B","C"))) -> C | G25: =VLOOKUP(B$4:B$57,I$4:M$57,5,0) -> C | I25: qs005 | J25: =АПРЕЛЬ!S22 -> 13 | K25: =J25/J$58 -> 0.0041243655 | L25: =L24+K25 -> 0.96161168 | M25: =_xlfn.IFS(L25<80%,"A",L25<=95%,"B",L25>95%,"C") -> C
B26: qs005 | C26: =АПРЕЛЬ!AL22 -> 3064.4581 | D26: =C26/C$58 -> 0.0030812751 | E26: =E25+D26 -> 1.010337 | F26: =IF(AND(E26<=0),"C",IF(E26<=0.8,"A",IF(E26<=0.95,"B","C"))) -> C | G26: =VLOOKUP(B$4:B$57,I$4:M$57,5,0) -> C | I26: qs008 | J26: =АПРЕЛЬ!S25 -> 13 | K26: =J26/J$58 -> 0.0041243655 | L26: =L25+K26 -> 0.96573604 | M26: =_xlfn.IFS(L26<80%,"A",L26<=95%,"B",L26>95%,"C") -> C
B27: MR 1819 черн | C27: =АПРЕЛЬ!AL10 -> 2800.7244 | D27: =C27/C$58 -> 0.0028160941 | E27: =E26+D27 -> 1.0131531 | F27: =IF(AND(E27<=0),"C",IF(E27<=0.8,"A",IF(E27<=0.95,"B","C"))) -> C | G27: =VLOOKUP(B$4:B$57,I$4:M$57,5,0) -> C | I27: 2100черный | J27: =АПРЕЛЬ!S39 -> 12 | K27: =J27/J$58 -> 0.0038071066 | L27: =L26+K27 -> 0.96954315 | M27: =_xlfn.IFS(L27<80%,"A",L27<=95%,"B",L27>95%,"C") -> C
B28: qs008 | C28: =АПРЕЛЬ!AL25 -> 2630.5391 | D28: =C28/C$58 -> 0.0026449748 | E28: =E24+D28 -> 1.0061558 | F28: =IF(AND(E28<=0),"C",IF(E28<=0.8,"A",IF(E28<=0.95,"B","C"))) -> C | G28: =VLOOKUP(B$4:B$57,I$4:M$57,5,0) -> C | I28: MR 1819 черн | J28: =АПРЕЛЬ!S10 -> 10 | K28: =J28/J$58 -> 0.0031725888 | L28: =L24+K28 -> 0.9606599 | M28: =_xlfn.IFS(L28<80%,"A",L28<=95%,"B",L28>95%,"C") -> C
B29: qs011ж | C29: =АПРЕЛЬ!AL35 -> 1936.0932 | D29: =C29/C$58 -> 0.0019467179 | E29: =E28+D29 -> 1.0081025 | F29: =IF(AND(E29<=0),"C",IF(E29<=0.8,"A",IF(E29<=0.95,"B","C"))) -> C | G29: =VLOOKUP(B$4:B$57,I$4:M$57,5,0) -> C | I29: MR Р1886 корич | J29: =АПРЕЛЬ!S15 -> 9 | K29: =J29/J$58 -> 0.0028553299 | L29: =L28+K29 -> 0.96351523 | M29: =_xlfn.IFS(L29<80%,"A",L29<=95%,"B",L29>95%,"C") -> C
B30: qs012ж | C30: =АПРЕЛЬ!AL36 -> 1832.511 | D30: =C30/C$58 -> 0.0018425674 | E30: =E29+D30 -> 1.009945 | F30: =IF(AND(E30<=0),"C",IF(E30<=0.8,"A",IF(E30<=0.95,"B","C"))) -> C | G30: =VLOOKUP(B$4:B$57,I$4:M$57,5,0) -> C | I30: qs001 | J30: =АПРЕЛЬ!S19 -> 7 | K30: =J30/J$58 -> 0.0022208122 | L30: =L29+K30 -> 0.96573604 | M30: =_xlfn.IFS(L30<80%,"A",L30<=95%,"B",L30>95%,"C") -> C
B31: qs009 | C31: =АПРЕЛЬ!AL26 -> 1273.0468 | D31: =C31/C$58 -> 0.001280033 | E31: =E30+D31 -> 1.0112251 | F31: =IF(AND(E31<=0),"C",IF(E31<=0.8,"A",IF(E31<=0.95,"B","C"))) -> C | G31: =VLOOKUP(B$4:B$57,I$4:M$57,5,0) -> C | I31: 2038ч/б | J31: =АПРЕЛЬ!S37 -> 7 | K31: =J31/J$58 -> 0.0022208122 | L31: =L30+K31 -> 0.96795685 | M31: =_xlfn.IFS(L31<80%,"A",L31<=95%,"B",L31>95%,"C") -> C
B32: qs011 | C32: =АПРЕЛЬ!AL28 -> 1235.3465 | D32: =C32/C$58 -> 0.0012421258 | E32: =E31+D32 -> 1.0124672 | F32: =IF(AND(E32<=0),"C",IF(E32<=0.8,"A",IF(E32<=0.95,"B","C"))) -> C | G32: =VLOOKUP(B$4:B$57,I$4:M$57,5,0) -> C | I32: qs011ж | J32: =АПРЕЛЬ!S35 -> 6 | K32: =J32/J$58 -> 0.0019035533 | L32: =L31+K32 -> 0.96986041 | M32: =_xlfn.IFS(L32<80%,"A",L32<=95%,"B",L32>95%,"C") -> C
B33: qs010 | C33: =АПРЕЛЬ!AL27 -> 1018.2508 | D33: =C33/C$58 -> 0.0010238387 | E33: =E32+D33 -> 1.013491 | F33: =IF(AND(E33<=0),"C",IF(E33<=0.8,"A",IF(E33<=0.95,"B","C"))) -> C | G33: =VLOOKUP(B$4:B$57,I$4:M$57,5,0) -> C | I33: 580метал | J33: =АПРЕЛЬ!S49 -> 6 | K33: =J33/J$58 -> 0.0019035533 | L33: =L32+K33 -> 0.97176396 | M33: =_xlfn.IFS(L33<80%,"A",L33<=95%,"B",L33>95%,"C") -> C
B34: MR Р1874 черн | C34: =АПРЕЛЬ!AL12 -> 791.70592 | D34: =C34/C$58 -> 0.00079605061 | E34: =E33+D34 -> 1.0142871 | F34: =IF(AND(E34<=0),"C",IF(E34<=0.8,"A",IF(E34<=0.95,"B","C"))) -> C | G34: =VLOOKUP(B$4:B$57,I$4:M$57,5,0) -> C | I34: 2084 (+1.75) | J34: =АПРЕЛЬ!S55 -> 6 | K34: =J34/J$58 -> 0.0019035533 | L34: =L33+K34 -> 0.97366751 | M34: =_xlfn.IFS(L34<80%,"A",L34<=95%,"B",L34>95%,"C") -> C
B35: 2100фиолетовый | C35: =АПРЕЛЬ!AL41 -> 638.40481 | D35: =C35/C$58 -> 0.00064190822 | E35: =E34+D35 -> 1.014929 | F35: =IF(AND(E35<=0),"C",IF(E35<=0.8,"A",IF(E35<=0.95,"B","C"))) -> C | G35: =VLOOKUP(B$4:B$57,I$4:M$57,5,0) -> C | I35: qs012ж | J35: =АПРЕЛЬ!S36 -> 5 | K35: =J35/J$58 -> 0.0015862944 | L35: =L34+K35 -> 0.97525381 | M35: =_xlfn.IFS(L35<80%,"A",L35<=95%,"B",L35>95%,"C") -> C
B36: 580черный | C36: =АПРЕЛЬ!AL48 -> 213.74709 | D36: =C36/C$58 -> 0.00021492008 | E36: =E35+D36 -> 1.0151439 | F36: =IF(AND(E36<=0),"C",IF(E36<=0.8,"A",IF(E36<=0.95,"B","C"))) -> C | G36: =VLOOKUP(B$4:B$57,I$4:M$57,5,0) -> C | I36: 180ч/б | J36: =АПРЕЛЬ!S46 -> 5 | K36: =J36/J$58 -> 0.0015862944 | L36: =L35+K36 -> 0.9768401 | M36: =_xlfn.IFS(L36<80%,"A",L36<=95%,"B",L36>95%,"C") -> C
B37: 2064ч/б | C37: =АПРЕЛЬ!AL50 -> 190.74793 | D37: =C37/C$58 -> 0.0001917947 | E37: =E36+D37 -> 1.0153357 | F37: =IF(AND(E37<=0),"C",IF(E37<=0.8,"A",IF(E37<=0.95,"B","C"))) -> C | G37: =VLOOKUP(B$4:B$57,I$4:M$57,5,0) -> C | I37: 2064коричневые | J37: =АПРЕЛЬ!S51 -> 5 | K37: =J37/J$58 -> 0.0015862944 | L37: =L36+K37 -> 0.9784264 | M37: =_xlfn.IFS(L37<80%,"A",L37<=95%,"B",L37>95%,"C") -> C
B38: MR Р1874 корич | C38: =АПРЕЛЬ!AL13 -> 0 | D38: =C38/C$58 -> 0 | E38: =E37+D38 -> 1.0153357 | F38: =IF(AND(E38<=0),"C",IF(E38<=0.8,"A",IF(E38<=0.95,"B","C"))) -> C | G38: =VLOOKUP(B$4:B$57,I$4:M$57,5,0) -> C | I38: qs011 | J38: =АПРЕЛЬ!S28 -> 4 | K38: =J38/J$58 -> 0.0012690355 | L38: =L37+K38 -> 0.97969543 | M38: =_xlfn.IFS(L38<80%,"A",L38<=95%,"B",L38>95%,"C") -> C
B39: qs001 Ж | C39: =АПРЕЛЬ!AL33 -> 0 | D39: =C39/C$58 -> 0 | E39: =E38+D39 -> 1.0153357 | F39: =IF(AND(E39<=0),"C",IF(E39<=0.8,"A",IF(E39<=0.95,"B","C"))) -> C | G39: =VLOOKUP(B$4:B$57,I$4:M$57,5,0) -> C | I39: 123метал | J39: =АПРЕЛЬ!S45 -> 4 | K39: =J39/J$58 -> 0.0012690355 | L39: =L38+K39 -> 0.98096447 | M39: =_xlfn.IFS(L39<80%,"A",L39<=95%,"B",L39>95%,"C") -> C
B40: 2084 | C40: =АПРЕЛЬ!AL54 -> -68.573297 | D40: =C40/C$58 -> -6.894961e-05 | E40: =E39+D40 -> 1.0152668 | F40: =IF(AND(E40<=0),"C",IF(E40<=0.8,"A",IF(E40<=0.95,"B","C"))) -> C | G40: =VLOOKUP(B$4:B$57,I$4:M$57,5,0) -> C | I40: 2064фиолетовые | J40: =АПРЕЛЬ!S52 -> 4 | K40: =J40/J$58 -> 0.0012690355 | L40: =L39+K40 -> 0.9822335 | M40: =_xlfn.IFS(L40<80%,"A",L40<=95%,"B",L40>95%,"C") -> C
B41: 8852 | C41: =АПРЕЛЬ!AL56 -> -191.02561 | D41: =C41/C$58 -> -0.00019207391 | E41: =E40+D41 -> 1.0150747 | F41: =IF(AND(E41<=0),"C",IF(E41<=0.8,"A",IF(E41<=0.95,"B","C"))) -> C | G41: =VLOOKUP(B$4:B$57,I$4:M$57,5,0) -> C | I41: MR Р1874 черн | J41: =АПРЕЛЬ!S12 -> 3 | K41: =J41/J$58 -> 0.00095177665 | L41: =L40+K41 -> 0.98318528 | M41: =_xlfn.IFS(L41<80%,"A",L41<=95%,"B",L41>95%,"C") -> C
B42: 2038ч/б | C42: =АПРЕЛЬ!AL37 -> -202.87666 | D42: =C42/C$58 -> -0.00020398999 | E42: =E41+D42 -> 1.0148707 | F42: =IF(AND(E42<=0),"C",IF(E42<=0.8,"A",IF(E42<=0.95,"B","C"))) -> C | G42: =VLOOKUP(B$4:B$57,I$4:M$57,5,0) -> C | I42: qs010 | J42: =АПРЕЛЬ!S27 -> 3 | K42: =J42/J$58 -> 0.00095177665 | L42: =L41+K42 -> 0.98413706 | M42: =_xlfn.IFS(L42<80%,"A",L42<=95%,"B",L42>95%,"C") -> C
B43: 2100красный | C43: =АПРЕЛЬ!AL40 -> -237.51109 | D43: =C43/C$58 -> -0.00023881449 | E43: =E42+D43 -> 1.0146319 | F43: =IF(AND(E43<=0),"C",IF(E43<=0.8,"A",IF(E43<=0.95,"B","C"))) -> C | G43: =VLOOKUP(B$4:B$57,I$4:M$57,5,0) -> C | I43: 2038красный | J43: =АПРЕЛЬ!S38 -> 2 | K43: =J43/J$58 -> 0.00063451777 | L43: =L42+K43 -> 0.98477157 | M43: =_xlfn.IFS(L43<80%,"A",L43<=95%,"B",L43>95%,"C") -> C
B44: qs012 | C44: =АПРЕЛЬ!AL29 -> -269.57959 | D44: =C44/C$58 -> -0.00027105897 | E44: =E43+D44 -> 1.0143608 | F44: =IF(AND(E44<=0),"C",IF(E44<=0.8,"A",IF(E44<=0.95,"B","C"))) -> C | G44: =VLOOKUP(B$4:B$57,I$4:M$57,5,0) -> C | I44: 2100красный | J44: =АПРЕЛЬ!S40 -> 2 | K44: =J44/J$58 -> 0.00063451777 | L44: =L43+K44 -> 0.98540609 | M44: =_xlfn.IFS(L44<80%,"A",L44<=95%,"B",L44>95%,"C") -> C
B45: 2038красный | C45: =АПРЕЛЬ!AL38 -> -374.23801 | D45: =C45/C$58 -> -0.00037629173 | E45: =E44+D45 -> 1.0139845 | F45: =IF(AND(E45<=0),"C",IF(E45<=0.8,"A",IF(E45<=0.95,"B","C"))) -> C | G45: =VLOOKUP(B$4:B$57,I$4:M$57,5,0) -> C | I45: 2100фиолетовый | J45: =АПРЕЛЬ!S41 -> 2 | K45: =J45/J$58 -> 0.00063451777 | L45: =L44+K45 -> 0.98604061 | M45: =_xlfn.IFS(L45<80%,"A",L45<=95%,"B",L45>95%,"C") -> C
B46: 2104 | C46: =АПРЕЛЬ!AL42 -> -498.02474 | D46: =C46/C$58 -> -0.00050075778 | E46: =E45+D46 -> 1.0134838 | F46: =IF(AND(E46<=0),"C",IF(E46<=0.8,"A",IF(E46<=0.95,"B","C"))) -> C | G46: =VLOOKUP(B$4:B$57,I$4:M$57,5,0) -> C | I46: 6008 | J46: =АПРЕЛЬ!S43 -> 2 | K46: =J46/J$58 -> 0.00063451777 | L46: =L45+K46 -> 0.98667513 | M46: =_xlfn.IFS(L46<80%,"A",L46<=95%,"B",L46>95%,"C") -> C
B47: 180узор | C47: =АПРЕЛЬ!AL47 -> -1103.0501 | D47: =C47/C$58 -> -0.0011091034 | E47: =E46+D47 -> 1.0123747 | F47: =IF(AND(E47<=0),"C",IF(E47<=0.8,"A",IF(E47<=0.95,"B","C"))) -> C | G47: =VLOOKUP(B$4:B$57,I$4:M$57,5,0) -> C | I47: 2104 | J47: =АПРЕЛЬ!S42 -> 1 | K47: =J47/J$58 -> 0.00031725888 | L47: =L46+K47 -> 0.98699239 | M47: =_xlfn.IFS(L47<80%,"A",L47<=95%,"B",L47>95%,"C") -> C
B48: 123черный | C48: =АПРЕЛЬ!AL44 -> -1286.8085 | D48: =C48/C$58 -> -0.0012938702 | E48: =E47+D48 -> 1.0110808 | F48: =IF(AND(E48<=0),"C",IF(E48<=0.8,"A",IF(E48<=0.95,"B","C"))) -> C | G48: =VLOOKUP(B$4:B$57,I$4:M$57,5,0) -> C | I48: 180узор | J48: =АПРЕЛЬ!S47 -> 1 | K48: =J48/J$58 -> 0.00031725888 | L48: =L47+K48 -> 0.98730964 | M48: =_xlfn.IFS(L48<80%,"A",L48<=95%,"B",L48>95%,"C") -> C
B49: 6008 | C49: =АПРЕЛЬ!AL43 -> -1365.9453 | D49: =C49/C$58 -> -0.0013734413 | E49: =E48+D49 -> 1.0097074 | F49: =IF(AND(E49<=0),"C",IF(E49<=0.8,"A",IF(E49<=0.95,"B","C"))) -> C | G49: =VLOOKUP(B$4:B$57,I$4:M$57,5,0) -> C | I49: 580черный | J49: =АПРЕЛЬ!S48 -> 1 | K49: =J49/J$58 -> 0.00031725888 | L49: =L48+K49 -> 0.9876269 | M49: =_xlfn.IFS(L49<80%,"A",L49<=95%,"B",L49>95%,"C") -> C
B50: 2100черный | C50: =АПРЕЛЬ!AL39 -> -1431.4247 | D50: =C50/C$58 -> -0.00143928 | E50: =E49+D50 -> 1.0082681 | F50: =IF(AND(E50<=0),"C",IF(E50<=0.8,"A",IF(E50<=0.95,"B","C"))) -> C | G50: =VLOOKUP(B$4:B$57,I$4:M$57,5,0) -> C | I50: 2064ч/б | J50: =АПРЕЛЬ!S50 -> 1 | K50: =J50/J$58 -> 0.00031725888 | L50: =L49+K50 -> 0.98794416 | M50: =_xlfn.IFS(L50<80%,"A",L50<=95%,"B",L50>95%,"C") -> C
B51: 2081 | C51: =АПРЕЛЬ!AL53 -> -1453.6793 | D51: =C51/C$58 -> -0.0014616567 | E51: =E50+D51 -> 1.0068064 | F51: =IF(AND(E51<=0),"C",IF(E51<=0.8,"A",IF(E51<=0.95,"B","C"))) -> C | G51: =VLOOKUP(B$4:B$57,I$4:M$57,5,0) -> C | I51: MR Р1874 корич | J51: =АПРЕЛЬ!S13 -> 0 | K51: =J51/J$58 -> 0 | L51: =L50+K51 -> 0.98794416 | M51: =_xlfn.IFS(L51<80%,"A",L51<=95%,"B",L51>95%,"C") -> C
B52: 2084 (+1.75) | C52: =АПРЕЛЬ!AL55 -> -1604.3954 | D52: =C52/C$58 -> -0.0016131999 | E52: =E51+D52 -> 1.0051932 | F52: =IF(AND(E52<=0),"C",IF(E52<=0.8,"A",IF(E52<=0.95,"B","C"))) -> C | G52: =VLOOKUP(B$4:B$57,I$4:M$57,5,0) -> C | I52: qs012 | J52: =АПРЕЛЬ!S29 -> 0 | K52: =J52/J$58 -> 0 | L52: =L51+K52 -> 0.98794416 | M52: =_xlfn.IFS(L52<80%,"A",L52<=95%,"B",L52>95%,"C") -> C
B53: 2064коричневые | C53: =АПРЕЛЬ!AL51 -> -1696.4741 | D53: =C53/C$58 -> -0.001705784 | E53: =E52+D53 -> 1.0034874 | F53: =IF(AND(E53<=0),"C",IF(E53<=0.8,"A",IF(E53<=0.95,"B","C"))) -> C | G53: =VLOOKUP(B$4:B$57,I$4:M$57,5,0) -> C | I53: qs001 Ж | J53: =АПРЕЛЬ!S33 -> 0 | K53: =J53/J$58 -> 0 | L53: =L52+K53 -> 0.98794416 | M53: =_xlfn.IFS(L53<80%,"A",L53<=95%,"B",L53>95%,"C") -> C
B54: 123метал | C54: =АПРЕЛЬ!AL45 -> -2884.9276 | D54: =C54/C$58 -> -0.0029007594 | E54: =E53+D54 -> 1.0005867 | F54: =IF(AND(E54<=0),"C",IF(E54<=0.8,"A",IF(E54<=0.95,"B","C"))) -> C | G54: =VLOOKUP(B$4:B$57,I$4:M$57,5,0) -> C | I54: 123черный | J54: =АПРЕЛЬ!S44 -> 0 | K54: =J54/J$58 -> 0 | L54: =L53+K54 -> 0.98794416 | M54: =_xlfn.IFS(L54<80%,"A",L54<=95%,"B",L54>95%,"C") -> C
B55: 180ч/б | C55: =АПРЕЛЬ!AL46 -> -3201.3706 | D55: =C55/C$58 -> -0.0032189389 | E55: =E54+D55 -> 0.99736775 | F55: =IF(AND(E55<=0),"C",IF(E55<=0.8,"A",IF(E55<=0.95,"B","C"))) -> C | G55: =VLOOKUP(B$4:B$57,I$4:M$57,5,0) -> C | I55: 2081 | J55: =АПРЕЛЬ!S53 -> 0 | K55: =J55/J$58 -> 0 | L55: =L54+K55 -> 0.98794416 | M55: =_xlfn.IFS(L55<80%,"A",L55<=95%,"B",L55>95%,"C") -> C
B56: 2064фиолетовые | C56: =АПРЕЛЬ!AL52 -> -3474.0158 | D56: =C56/C$58 -> -0.0034930804 | E56: =E55+D56 -> 0.99387467 | F56: =IF(AND(E56<=0),"C",IF(E56<=0.8,"A",IF(E56<=0.95,"B","C"))) -> C | G56: =VLOOKUP(B$4:B$57,I$4:M$57,5,0) -> C | I56: 2084 | J56: =АПРЕЛЬ!S54 -> 0 | K56: =J56/J$58 -> 0 | L56: =L55+K56 -> 0.98794416 | M56: =_xlfn.IFS(L56<80%,"A",L56<=95%,"B",L56>95%,"C") -> C
B57: 580метал | C57: =АПРЕЛЬ!AL49 -> -3497.8076 | D57: =C57/C$58 -> -0.0035170027 | E57: =E56+D57 -> 0.99035767 | F57: =IF(AND(E57<=0),"C",IF(E57<=0.8,"A",IF(E57<=0.95,"B","C"))) -> C | G57: =VLOOKUP(B$4:B$57,I$4:M$57,5,0) -> C | I57: 8852 | J57: =АПРЕЛЬ!S56 -> 0 | K57: =J57/J$58 -> 0 | L57: =L56+K57 -> 0.98794416 | M57: =_xlfn.IFS(L57<80%,"A",L57<=95%,"B",L57>95%,"C") -> C
C58: =SUM(C4:C57) -> 994542.2 | D58: =SUM(D4:D44) -> 1.0240032 | J58: =SUM(J4:J57) -> 3152 | K58: =SUM(K4:K44) -> 0.99746193
C61: Прибыль | D61: % прибыль | E61: Доля | F61: ABC прибыль | G61: ABC кол-во | J61: Кол-во | K61: % кол-во | L61: Доля | M61: ABC кол-во
D62: =C62/C$114 -> #DIV/0! | E62: =D62 -> #DIV/0! | F62: =IF(AND(E62<=0),"C",IF(E62<=0.8,"A",IF(E62<=0.95,"B","C"))) -> #DIV/0! | G62: =VLOOKUP(B62:B113,I$62:M$113,5,0) -> #N/A | K62: =J62/J$114 -> #DIV/0! | L62: =K62 -> #DIV/0! | M62: =_xlfn.IFS(L62<80%,"A",L62<=95%,"B",L62>95%,"C") -> #DIV/0!
D63: =C63/C$114 -> #DIV/0! | E63: =D63+E62 -> #DIV/0! | F63: =IF(AND(E63<=0),"C",IF(E63<=0.8,"A",IF(E63<=0.95,"B","C"))) -> #DIV/0! | G63: =VLOOKUP(B63:B114,I$62:M$113,5,0) -> #N/A | K63: =J63/J$114 -> #DIV/0! | L63: =K63+L62 -> #DIV/0! | M63: =_xlfn.IFS(L63<80%,"A",L63<=95%,"B",L63>95%,"C") -> #DIV/0!
D64: =C64/C$114 -> #DIV/0! | E64: =D64+E63 -> #DIV/0! | F64: =IF(AND(E64<=0),"C",IF(E64<=0.8,"A",IF(E64<=0.95,"B","C"))) -> #DIV/0! | G64: =VLOOKUP(B64:B115,I$62:M$113,5,0) -> #N/A | K64: =J64/J$114 -> #DIV/0! | L64: =K64+L63 -> #DIV/0! | M64: =_xlfn.IFS(L64<80%,"A",L64<=95%,"B",L64>95%,"C") -> #DIV/0!
D65: =C65/C$114 -> #DIV/0! | E65: =D65+E64 -> #DIV/0! | F65: =IF(AND(E65<=0),"C",IF(E65<=0.8,"A",IF(E65<=0.95,"B","C"))) -> #DIV/0! | G65: =VLOOKUP(B65:B116,I$62:M$113,5,0) -> #N/A | K65: =J65/J$114 -> #DIV/0! | L65: =K65+L64 -> #DIV/0! | M65: =_xlfn.IFS(L65<80%,"A",L65<=95%,"B",L65>95%,"C") -> #DIV/0!
D66: =C66/C$114 -> #DIV/0! | E66: =D66+E65 -> #DIV/0! | F66: =IF(AND(E66<=0),"C",IF(E66<=0.8,"A",IF(E66<=0.95,"B","C"))) -> #DIV/0! | G66: =VLOOKUP(B66:B117,I$62:M$113,5,0) -> #N/A | K66: =J66/J$114 -> #DIV/0! | L66: =K66+L65 -> #DIV/0! | M66: =_xlfn.IFS(L66<80%,"A",L66<=95%,"B",L66>95%,"C") -> #DIV/0!
D67: =C67/C$114 -> #DIV/0! | E67: =D67+E66 -> #DIV/0! | F67: =IF(AND(E67<=0),"C",IF(E67<=0.8,"A",IF(E67<=0.95,"B","C"))) -> #DIV/0! | G67: =VLOOKUP(B67:B118,I$62:M$113,5,0) -> #N/A | K67: =J67/J$114 -> #DIV/0! | L67: =K67+L66 -> #DIV/0! | M67: =_xlfn.IFS(L67<80%,"A",L67<=95%,"B",L67>95%,"C") -> #DIV/0!
D68: =C68/C$114 -> #DIV/0! | E68: =D68+E67 -> #DIV/0! | F68: =IF(AND(E68<=0),"C",IF(E68<=0.8,"A",IF(E68<=0.95,"B","C"))) -> #DIV/0! | G68: =VLOOKUP(B68:B119,I$62:M$113,5,0) -> #N/A | K68: =J68/J$114 -> #DIV/0! | L68: =K68+L67 -> #DIV/0! | M68: =_xlfn.IFS(L68<80%,"A",L68<=95%,"B",L68>95%,"C") -> #DIV/0!
D69: =C69/C$114 -> #DIV/0! | E69: =D69+E68 -> #DIV/0! | F69: =IF(AND(E69<=0),"C",IF(E69<=0.8,"A",IF(E69<=0.95,"B","C"))) -> #DIV/0! | G69: =VLOOKUP(B69:B120,I$62:M$113,5,0) -> #N/A | K69: =J69/J$114 -> #DIV/0! | L69: =K69+L68 -> #DIV/0! | M69: =_xlfn.IFS(L69<80%,"A",L69<=95%,"B",L69>95%,"C") -> #DIV/0!
D70: =C70/C$114 -> #DIV/0! | E70: =D70+E69 -> #DIV/0! | F70: =IF(AND(E70<=0),"C",IF(E70<=0.8,"A",IF(E70<=0.95,"B","C"))) -> #DIV/0! | G70: =VLOOKUP(B70:B121,I$62:M$113,5,0) -> #N/A | K70: =J70/J$114 -> #DIV/0! | L70: =K70+L69 -> #DIV/0! | M70: =_xlfn.IFS(L70<80%,"A",L70<=95%,"B",L70>95%,"C") -> #DIV/0!
D71: =C71/C$114 -> #DIV/0! | E71: =D71+E70 -> #DIV/0! | F71: =IF(AND(E71<=0),"C",IF(E71<=0.8,"A",IF(E71<=0.95,"B","C"))) -> #DIV/0! | G71: =VLOOKUP(B71:B122,I$62:M$113,5,0) -> #N/A | K71: =J71/J$114 -> #DIV/0! | L71: =K71+L70 -> #DIV/0! | M71: =_xlfn.IFS(L71<80%,"A",L71<=95%,"B",L71>95%,"C") -> #DIV/0!
D72: =C72/C$114 -> #DIV/0! | E72: =D72+E71 -> #DIV/0! | F72: =IF(AND(E72<=0),"C",IF(E72<=0.8,"A",IF(E72<=0.95,"B","C"))) -> #DIV/0! | G72: =VLOOKUP(B72:B123,I$62:M$113,5,0) -> #N/A | K72: =J72/J$114 -> #DIV/0! | L72: =K72+L71 -> #DIV/0! | M72: =_xlfn.IFS(L72<80%,"A",L72<=95%,"B",L72>95%,"C") -> #DIV/0!
D73: =C73/C$114 -> #DIV/0! | E73: =D73+E72 -> #DIV/0! | F73: =IF(AND(E73<=0),"C",IF(E73<=0.8,"A",IF(E73<=0.95,"B","C"))) -> #DIV/0! | G73: =VLOOKUP(B73:B124,I$62:M$113,5,0) -> #N/A | K73: =J73/J$114 -> #DIV/0! | L73: =K73+L72 -> #DIV/0! | M73: =_xlfn.IFS(L73<80%,"A",L73<=95%,"B",L73>95%,"C") -> #DIV/0!
D74: =C74/C$114 -> #DIV/0! | E74: =D74+E73 -> #DIV/0! | F74: =IF(AND(E74<=0),"C",IF(E74<=0.8,"A",IF(E74<=0.95,"B","C"))) -> #DIV/0! | G74: =VLOOKUP(B74:B125,I$62:M$113,5,0) -> #N/A | K74: =J74/J$114 -> #DIV/0! | L74: =K74+L73 -> #DIV/0! | M74: =_xlfn.IFS(L74<80%,"A",L74<=95%,"B",L74>95%,"C") -> #DIV/0!
... D113: =C113/C$114 -> #DIV/0! | E113: =D113+E112 -> #DIV/0! | F113: =IF(AND(E113<=0),"C",IF(E113<=0.8,"A",IF(E113<=0.95,"B","C"))) -> #DIV/0! | G113: =VLOOKUP(B113:B164,I$62:M$113,5,0) -> #N/A | K113: =J113/J$114 -> #DIV/0! | L113: =K113+L112 -> #DIV/0! | M113: =_xlfn.IFS(L113<80%,"A",L113<=95%,"B",L113>95%,"C") -> #DIV/0!
C114: =SUM(C62:C113) -> 0 | D114: =SUM(D62:D113) -> #DIV/0! | J114: =SUM(J62:J113) -> 0 | K114: =SUM(K62:K113) -> #DIV/0!

Sheet АВС 18
B2: ОЧКИ
C3: Прибыль | D3: % прибыль | E3: Доля | F3: ABC прибыль | G3: ABC кол-во | J3: Кол-во | K3: % кол-во | L3: Доля | M3: ABC кол-во
B4: Qs черн Сул | C4: ='Юнит 18'!AL4 -> 48649.204 | D4: =C4/C$58 -> 0.38835833 | E4: =D4 -> 0.38835833 | F4: =IF(AND(E4<=0),"C",IF(E4<=0.8,"A",IF(E4<=0.95,"B","C"))) -> A | G4: =VLOOKUP(B$4:B$57,I$4:M$57,5,0) -> A | I4: Qs черн Сул | J4: ='Юнит 18'!S4 -> 181 | K4: =J4/J$58 -> 0.39519651 | L4: =K4 -> 0.39519651 | M4: =_xlfn.IFS(L4<80%,"A",L4<=95%,"B",L4>95%,"C") -> A | P4: A | Q4: 0.8
B5: Черные с железкой Сул | C5: ='Юнит 18'!AL3 -> 37401.985 | D5: =C5/C$58 -> 0.29857369 | E5: =E4+D5 -> 0.68693201 | F5: =IF(AND(E5<=0),"C",IF(E5<=0.8,"A",IF(E5<=0.95,"B","C"))) -> A | G5: =VLOOKUP(B$4:B$57,I$4:M$57,5,0) -> A | I5: Черные с железкой Сул | J5: ='Юнит 18'!S3 -> 89 | K5: =J5/J$58 -> 0.19432314 | L5: =L4+K5 -> 0.58951965 | M5: =_xlfn.IFS(L5<80%,"A",L5<=95%,"B",L5>95%,"C") -> A | P5: B | Q5: 0.15
B6: flip желтые Сул | C6: ='Юнит 18'!AL8 -> 10515.49 | D6: =C6/C$58 -> 0.083943372 | E6: =E5+D6 -> 0.77087539 | F6: =IF(AND(E6<=0),"C",IF(E6<=0.8,"A",IF(E6<=0.95,"B","C"))) -> A | G6: =VLOOKUP(B$4:B$57,I$4:M$57,5,0) -> A | I6: flip желтые Сул | J6: ='Юнит 18'!S8 -> 42 | K6: =J6/J$58 -> 0.091703057 | L6: =L5+K6 -> 0.68122271 | M6: =_xlfn.IFS(L6<80%,"A",L6<=95%,"B",L6>95%,"C") -> A | P6: C | Q6: 0.05
B7: qs015 | C7: ='Юнит 18'!AL32 -> 5173.0693 | D7: =C7/C$58 -> 0.041295733 | E7: =E6+D7 -> 0.81217112 | F7: =IF(AND(E7<=0),"C",IF(E7<=0.8,"A",IF(E7<=0.95,"B","C"))) -> B | G7: =VLOOKUP(B$4:B$57,I$4:M$57,5,0) -> B | I7: Qs син Сул | J7: ='Юнит 18'!S5 -> 26 | K7: =J7/J$58 -> 0.056768559 | L7: =L6+K7 -> 0.73799127 | M7: =_xlfn.IFS(L7<80%,"A",L7<=95%,"B",L7>95%,"C") -> A
B8: MR 1890 черн | C8: ='Юнит 18'!AL16 -> 4540.7465 | D8: =C8/C$58 -> 0.036248008 | E8: =E7+D8 -> 0.84841913 | F8: =IF(AND(E8<=0),"C",IF(E8<=0.8,"A",IF(E8<=0.95,"B","C"))) -> B | G8: =VLOOKUP(B$4:B$57,I$4:M$57,5,0) -> B | I8: Qs желт Сул | J8: ='Юнит 18'!S6 -> 20 | K8: =J8/J$58 -> 0.043668122 | L8: =L7+K8 -> 0.78165939 | M8: =_xlfn.IFS(L8<80%,"A",L8<=95%,"B",L8>95%,"C") -> A
B9: MR 1890 корич | C9: ='Юнит 18'!AL18 -> 4254.3768 | D9: =C9/C$58 -> 0.033961967 | E9: =E8+D9 -> 0.88238109 | F9: =IF(AND(E9<=0),"C",IF(E9<=0.8,"A",IF(E9<=0.95,"B","C"))) -> B | G9: =VLOOKUP(B$4:B$57,I$4:M$57,5,0) -> B | I9: flip черные Сул | J9: ='Юнит 18'!S7 -> 19 | K9: =J9/J$58 -> 0.041484716 | L9: =L8+K9 -> 0.8231441 | M9: =_xlfn.IFS(L9<80%,"A",L9<=95%,"B",L9>95%,"C") -> B
B10: MR 1890 желт | C10: ='Юнит 18'!AL17 -> 3472.261 | D10: =C10/C$58 -> 0.02771847 | E10: =E9+D10 -> 0.91009956 | F10: =IF(AND(E10<=0),"C",IF(E10<=0.8,"A",IF(E10<=0.95,"B","C"))) -> B | G10: =VLOOKUP(B$4:B$57,I$4:M$57,5,0) -> B | I10: qs015 | J10: ='Юнит 18'!S32 -> 10 | K10: =J10/J$58 -> 0.021834061 | L10: =L9+K10 -> 0.84497817 | M10: =_xlfn.IFS(L10<80%,"A",L10<=95%,"B",L10>95%,"C") -> B
B11: qs005 | C11: ='Юнит 18'!AL22 -> 2906.6601 | D11: =C11/C$58 -> 0.023203374 | E11: =E10+D11 -> 0.93330294 | F11: =IF(AND(E11<=0),"C",IF(E11<=0.8,"A",IF(E11<=0.95,"B","C"))) -> B | G11: =VLOOKUP(B$4:B$57,I$4:M$57,5,0) -> B | I11: MR 1890 черн | J11: ='Юнит 18'!S16 -> 9 | K11: =J11/J$58 -> 0.019650655 | L11: =L10+K11 -> 0.86462882 | M11: =_xlfn.IFS(L11<80%,"A",L11<=95%,"B",L11>95%,"C") -> B
B12: qs002 | C12: ='Юнит 18'!AL20 -> 1822.5491 | D12: =C12/C$58 -> 0.0145491 | E12: =E11+D12 -> 0.94785204 | F12: =IF(AND(E12<=0),"C",IF(E12<=0.8,"A",IF(E12<=0.95,"B","C"))) -> B | G12: =VLOOKUP(B$4:B$57,I$4:M$57,5,0) -> B | I12: MR 1890 корич | J12: ='Юнит 18'!S18 -> 9 | K12: =J12/J$58 -> 0.019650655 | L12: =L11+K12 -> 0.88427948 | M12: =_xlfn.IFS(L12<80%,"A",L12<=95%,"B",L12>95%,"C") -> B
B13: MR8854 C2 Сул | C13: ='Юнит 18'!AL9 -> 1649.7163 | D13: =C13/C$58 -> 0.013169405 | E13: =E12+D13 -> 0.96102144 | F13: =IF(AND(E13<=0),"C",IF(E13<=0.8,"A",IF(E13<=0.95,"B","C"))) -> C | G13: =VLOOKUP(B$4:B$57,I$4:M$57,5,0) -> B | I13: MR 1890 желт | J13: ='Юнит 18'!S17 -> 8 | K13: =J13/J$58 -> 0.017467249 | L13: =L12+K13 -> 0.90174672 | M13: =_xlfn.IFS(L13<80%,"A",L13<=95%,"B",L13>95%,"C") -> B
B14: qs007 | C14: ='Юнит 18'!AL24 -> 1108.1998 | D14: =C14/C$58 -> 0.008846571 | E14: =E13+D14 -> 0.96986801 | F14: =IF(AND(E14<=0),"C",IF(E14<=0.8,"A",IF(E14<=0.95,"B","C"))) -> C | G14: =VLOOKUP(B$4:B$57,I$4:M$57,5,0) -> B | I14: qs005 | J14: ='Юнит 18'!S22 -> 6 | K14: =J14/J$58 -> 0.013100437 | L14: =L13+K14 -> 0.91484716 | M14: =_xlfn.IFS(L14<80%,"A",L14<=95%,"B",L14>95%,"C") -> B
B15: qs014 | C15: ='Юнит 18'!AL31 -> 1066.3691 | D15: =C15/C$58 -> 0.0085126431 | E15: =E14+D15 -> 0.97838065 | F15: =IF(AND(E15<=0),"C",IF(E15<=0.8,"A",IF(E15<=0.95,"B","C"))) -> C | G15: =VLOOKUP(B$4:B$57,I$4:M$57,5,0) -> C | I15: qs002 | J15: ='Юнит 18'!S20 -> 4 | K15: =J15/J$58 -> 0.0087336245 | L15: =L14+K15 -> 0.92358079 | M15: =_xlfn.IFS(L15<80%,"A",L15<=95%,"B",L15>95%,"C") -> B
B16: qs006 | C16: ='Юнит 18'!AL23 -> 1060.8607 | D16: =C16/C$58 -> 0.0084686705 | E16: =E15+D16 -> 0.98684933 | F16: =IF(AND(E16<=0),"C",IF(E16<=0.8,"A",IF(E16<=0.95,"B","C"))) -> C | G16: =VLOOKUP(B$4:B$57,I$4:M$57,5,0) -> C | I16: qs007 | J16: ='Юнит 18'!S24 -> 4 | K16: =J16/J$58 -> 0.0087336245 | L16: =L15+K16 -> 0.93231441 | M16: =_xlfn.IFS(L16<80%,"A",L16<=95%,"B",L16>95%,"C") -> B
B17: MR 1819 корич | C17: ='Юнит 18'!AL11 -> 992.09 | D17: =C17/C$58 -> 0.0079196859 | E17: =E16+D17 -> 0.99476901 | F17: =IF(AND(E17<=0),"C",IF(E17<=0.8,"A",IF(E17<=0.95,"B","C"))) -> C | G17: =VLOOKUP(B$4:B$57,I$4:M$57,5,0) -> B | I17: MR8854 C2 Сул | J17: ='Юнит 18'!S9 -> 3 | K17: =J17/J$58 -> 0.0065502183 | L17: =L16+K17 -> 0.93886463 | M17: =_xlfn.IFS(L17<80%,"A",L17<=95%,"B",L17>95%,"C") -> B
B18: qs003 | C18: ='Юнит 18'!AL21 -> 974.00212 | D18: =C18/C$58 -> 0.0077752934 | E18: =E17+D18 -> 1.0025443 | F18: =IF(AND(E18<=0),"C",IF(E18<=0.8,"A",IF(E18<=0.95,"B","C"))) -> C | G18: =VLOOKUP(B$4:B$57,I$4:M$57,5,0) -> C | I18: MR 1819 корич | J18: ='Юнит 18'!S11 -> 3 | K18: =J18/J$58 -> 0.0065502183 | L18: =L17+K18 -> 0.94541485 | M18: =_xlfn.IFS(L18<80%,"A",L18<=95%,"B",L18>95%,"C") -> B
B19: qs009 | C19: ='Юнит 18'!AL26 -> 928.07457 | D19: =C19/C$58 -> 0.0074086616 | E19: =E18+D19 -> 1.009953 | F19: =IF(AND(E19<=0),"C",IF(E19<=0.8,"A",IF(E19<=0.95,"B","C"))) -> C | G19: =VLOOKUP(B$4:B$57,I$4:M$57,5,0) -> C | I19: qs006 | J19: ='Юнит 18'!S23 -> 3 | K19: =J19/J$58 -> 0.0065502183 | L19: =L18+K19 -> 0.95196507 | M19: =_xlfn.IFS(L19<80%,"A",L19<=95%,"B",L19>95%,"C") -> C
B20: qs011ж | C20: ='Юнит 18'!AL35 -> 912.96674 | D20: =C20/C$58 -> 0.0072880583 | E20: =E19+D20 -> 1.017241 | F20: =IF(AND(E20<=0),"C",IF(E20<=0.8,"A",IF(E20<=0.95,"B","C"))) -> C | G20: =VLOOKUP(B$4:B$57,I$4:M$57,5,0) -> C | I20: qs009 | J20: ='Юнит 18'!S26 -> 3 | K20: =J20/J$58 -> 0.0065502183 | L20: =L19+K20 -> 0.95851528 | M20: =_xlfn.IFS(L20<80%,"A",L20<=95%,"B",L20>95%,"C") -> C
B21: qs010ж | C21: ='Юнит 18'!AL34 -> 793.42245 | D21: =C21/C$58 -> 0.0063337565 | E21: =E20+D21 -> 1.0235748 | F21: =IF(AND(E21<=0),"C",IF(E21<=0.8,"A",IF(E21<=0.95,"B","C"))) -> C | G21: =VLOOKUP(B$4:B$57,I$4:M$57,5,0) -> C | I21: MR 1819 черн | J21: ='Юнит 18'!S10 -> 2 | K21: =J21/J$58 -> 0.0043668122 | L21: =L20+K21 -> 0.9628821 | M21: =_xlfn.IFS(L21<80%,"A",L21<=95%,"B",L21>95%,"C") -> C
B22: qs001 | C22: ='Юнит 18'!AL19 -> 645.5 | D22: =C22/C$58 -> 0.0051529168 | E22: =E21+D22 -> 1.0287277 | F22: =IF(AND(E22<=0),"C",IF(E22<=0.8,"A",IF(E22<=0.95,"B","C"))) -> C | G22: =VLOOKUP(B$4:B$57,I$4:M$57,5,0) -> C | I22: qs003 | J22: ='Юнит 18'!S21 -> 2 | K22: =J22/J$58 -> 0.0043668122 | L22: =L21+K22 -> 0.96724891 | M22: =_xlfn.IFS(L22<80%,"A",L22<=95%,"B",L22>95%,"C") -> C
B23: MR 1819 черн | C23: ='Юнит 18'!AL10 -> 482.92353 | D23: =C23/C$58 -> 0.0038550965 | E23: =E22+D23 -> 1.0325828 | F23: =IF(AND(E23<=0),"C",IF(E23<=0.8,"A",IF(E23<=0.95,"B","C"))) -> C | G23: =VLOOKUP(B$4:B$57,I$4:M$57,5,0) -> C | I23: qs014 | J23: ='Юнит 18'!S31 -> 2 | K23: =J23/J$58 -> 0.0043668122 | L23: =L22+K23 -> 0.97161572 | M23: =_xlfn.IFS(L23<80%,"A",L23<=95%,"B",L23>95%,"C") -> C
B24: 6008 | C24: ='Юнит 18'!AL43 -> 466.72968 | D24: =C24/C$58 -> 0.0037258237 | E24: =E23+D24 -> 1.0363086 | F24: =IF(AND(E24<=0),"C",IF(E24<=0.8,"A",IF(E24<=0.95,"B","C"))) -> C | G24: =VLOOKUP(B$4:B$57,I$4:M$57,5,0) -> C | I24: qs010ж | J24: ='Юнит 18'!S34 -> 2 | K24: =J24/J$58 -> 0.0043668122 | L24: =L23+K24 -> 0.97598253 | M24: =_xlfn.IFS(L24<80%,"A",L24<=95%,"B",L24>95%,"C") -> C
B25: 580черный | C25: ='Юнит 18'!AL48 -> 444.97582 | D25: =C25/C$58 -> 0.0035521663 | E25: =E24+D25 -> 1.0398608 | F25: =IF(AND(E25<=0),"C",IF(E25<=0.8,"A",IF(E25<=0.95,"B","C"))) -> C | G25: =VLOOKUP(B$4:B$57,I$4:M$57,5,0) -> C | I25: qs011ж | J25: ='Юнит 18'!S35 -> 2 | K25: =J25/J$58 -> 0.0043668122 | L25: =L24+K25 -> 0.98034934 | M25: =_xlfn.IFS(L25<80%,"A",L25<=95%,"B",L25>95%,"C") -> C
B26: MR Р1886 черн | C26: ='Юнит 18'!AL14 -> 398.09614 | D26: =C26/C$58 -> 0.0031779338 | E26: =E25+D26 -> 1.0430387 | F26: =IF(AND(E26<=0),"C",IF(E26<=0.8,"A",IF(E26<=0.95,"B","C"))) -> C | G26: =VLOOKUP(B$4:B$57,I$4:M$57,5,0) -> C | I26: MR Р1886 черн | J26: ='Юнит 18'!S14 -> 1 | K26: =J26/J$58 -> 0.0021834061 | L26: =L25+K26 -> 0.98253275 | M26: =_xlfn.IFS(L26<80%,"A",L26<=95%,"B",L26>95%,"C") -> C
B27: 2038ч/б | C27: ='Юнит 18'!AL37 -> 391.59169 | D27: =C27/C$58 -> 0.0031260099 | E27: =E26+D27 -> 1.0461647 | F27: =IF(AND(E27<=0),"C",IF(E27<=0.8,"A",IF(E27<=0.95,"B","C"))) -> C | G27: =VLOOKUP(B$4:B$57,I$4:M$57,5,0) -> C | I27: qs001 | J27: ='Юнит 18'!S19 -> 1 | K27: =J27/J$58 -> 0.0021834061 | L27: =L26+K27 -> 0.98471616 | M27: =_xlfn.IFS(L27<80%,"A",L27<=95%,"B",L27>95%,"C") -> C
B28: 2064коричневые | C28: ='Юнит 18'!AL51 -> 383.60397 | D28: =C28/C$58 -> 0.0030622453 | E28: =E24+D28 -> 1.0393709 | F28: =IF(AND(E28<=0),"C",IF(E28<=0.8,"A",IF(E28<=0.95,"B","C"))) -> C | G28: =VLOOKUP(B$4:B$57,I$4:M$57,5,0) -> C | I28: qs008 | J28: ='Юнит 18'!S25 -> 1 | K28: =J28/J$58 -> 0.0021834061 | L28: =L24+K28 -> 0.97816594 | M28: =_xlfn.IFS(L28<80%,"A",L28<=95%,"B",L28>95%,"C") -> C
B29: qs013 | C29: ='Юнит 18'!AL30 -> 374.21908 | D29: =C29/C$58 -> 0.0029873273 | E29: =E28+D29 -> 1.0423582 | F29: =IF(AND(E29<=0),"C",IF(E29<=0.8,"A",IF(E29<=0.95,"B","C"))) -> C | G29: =VLOOKUP(B$4:B$57,I$4:M$57,5,0) -> C | I29: qs011 | J29: ='Юнит 18'!S28 -> 1 | K29: =J29/J$58 -> 0.0021834061 | L29: =L28+K29 -> 0.98034934 | M29: =_xlfn.IFS(L29<80%,"A",L29<=95%,"B",L29>95%,"C") -> C
B30: qs011 | C30: ='Юнит 18'!AL28 -> 360.91 | D30: =C30/C$58 -> 0.0028810832 | E30: =E29+D30 -> 1.0452393 | F30: =IF(AND(E30<=0),"C",IF(E30<=0.8,"A",IF(E30<=0.95,"B","C"))) -> C | G30: =VLOOKUP(B$4:B$57,I$4:M$57,5,0) -> C | I30: qs013 | J30: ='Юнит 18'!S30 -> 1 | K30: =J30/J$58 -> 0.0021834061 | L30: =L29+K30 -> 0.98253275 | M30: =_xlfn.IFS(L30<80%,"A",L30<=95%,"B",L30>95%,"C") -> C
B31: qs008 | C31: ='Юнит 18'!AL25 -> 45.108102 | D31: =C31/C$58 -> 0.00036009031 | E31: =E30+D31 -> 1.0455994 | F31: =IF(AND(E31<=0),"C",IF(E31<=0.8,"A",IF(E31<=0.95,"B","C"))) -> C | G31: =VLOOKUP(B$4:B$57,I$4:M$57,5,0) -> C | I31: 2038ч/б | J31: ='Юнит 18'!S37 -> 1 | K31: =J31/J$58 -> 0.0021834061 | L31: =L30+K31 -> 0.98471616 | M31: =_xlfn.IFS(L31<80%,"A",L31<=95%,"B",L31>95%,"C") -> C
B32: MR Р1874 корич | C32: ='Юнит 18'!AL13 -> 0 | D32: =C32/C$58 -> 0 | E32: =E31+D32 -> 1.0455994 | F32: =IF(AND(E32<=0),"C",IF(E32<=0.8,"A",IF(E32<=0.95,"B","C"))) -> C | G32: =VLOOKUP(B$4:B$57,I$4:M$57,5,0) -> C | I32: 6008 | J32: ='Юнит 18'!S43 -> 1 | K32: =J32/J$58 -> 0.0021834061 | L32: =L31+K32 -> 0.98689956 | M32: =_xlfn.IFS(L32<80%,"A",L32<=95%,"B",L32>95%,"C") -> C
B33: qs001 Ж | C33: ='Юнит 18'!AL33 -> 0 | D33: =C33/C$58 -> 0 | E33: =E32+D33 -> 1.0455994 | F33: =IF(AND(E33<=0),"C",IF(E33<=0.8,"A",IF(E33<=0.95,"B","C"))) -> C | G33: =VLOOKUP(B$4:B$57,I$4:M$57,5,0) -> C | I33: 580черный | J33: ='Юнит 18'!S48 -> 1 | K33: =J33/J$58 -> 0.0021834061 | L33: =L32+K33 -> 0.98908297 | M33: =_xlfn.IFS(L33<80%,"A",L33<=95%,"B",L33>95%,"C") -> C
B34: 2104 | C34: ='Юнит 18'!AL42 -> -7.9273908 | D34: =C34/C$58 -> -6.3283013e-05 | E34: =E33+D34 -> 1.0455361 | F34: =IF(AND(E34<=0),"C",IF(E34<=0.8,"A",IF(E34<=0.95,"B","C"))) -> C | G34: =VLOOKUP(B$4:B$57,I$4:M$57,5,0) -> C | I34: 2064коричневые | J34: ='Юнит 18'!S51 -> 1 | K34: =J34/J$58 -> 0.0021834061 | L34: =L33+K34 -> 0.99126638 | M34: =_xlfn.IFS(L34<80%,"A",L34<=95%,"B",L34>95%,"C") -> C
B35: 2100красный | C35: ='Юнит 18'!AL40 -> -8.9183146 | D35: =C35/C$58 -> -7.119339e-05 | E35: =E34+D35 -> 1.0454649 | F35: =IF(AND(E35<=0),"C",IF(E35<=0.8,"A",IF(E35<=0.95,"B","C"))) -> C | G35: =VLOOKUP(B$4:B$57,I$4:M$57,5,0) -> C | I35: MR Р1874 черн | J35: ='Юнит 18'!S12 -> 0 | K35: =J35/J$58 -> 0 | L35: =L34+K35 -> 0.99126638 | M35: =_xlfn.IFS(L35<80%,"A",L35<=95%,"B",L35>95%,"C") -> C
B36: 2038красный | C36: ='Юнит 18'!AL38 -> -9.9092385 | D36: =C36/C$58 -> -7.9103767e-05 | E36: =E35+D36 -> 1.0453858 | F36: =IF(AND(E36<=0),"C",IF(E36<=0.8,"A",IF(E36<=0.95,"B","C"))) -> C | G36: =VLOOKUP(B$4:B$57,I$4:M$57,5,0) -> C | I36: MR Р1874 корич | J36: ='Юнит 18'!S13 -> 0 | K36: =J36/J$58 -> 0 | L36: =L35+K36 -> 0.99126638 | M36: =_xlfn.IFS(L36<80%,"A",L36<=95%,"B",L36>95%,"C") -> C
B37: MR Р1874 черн | C37: ='Юнит 18'!AL12 -> -12.66 | D37: =C37/C$58 -> -0.00010106263 | E37: =E36+D37 -> 1.0452847 | F37: =IF(AND(E37<=0),"C",IF(E37<=0.8,"A",IF(E37<=0.95,"B","C"))) -> C | G37: =VLOOKUP(B$4:B$57,I$4:M$57,5,0) -> C | I37: MR Р1886 корич | J37: ='Юнит 18'!S15 -> 0 | K37: =J37/J$58 -> 0 | L37: =L36+K37 -> 0.99126638 | M37: =_xlfn.IFS(L37<80%,"A",L37<=95%,"B",L37>95%,"C") -> C
B38: MR Р1886 корич | C38: ='Юнит 18'!AL15 -> -12.76 | D38: =C38/C$58 -> -0.00010186091 | E38: =E37+D38 -> 1.0451829 | F38: =IF(AND(E38<=0),"C",IF(E38<=0.8,"A",IF(E38<=0.95,"B","C"))) -> C | G38: =VLOOKUP(B$4:B$57,I$4:M$57,5,0) -> C | I38: qs010 | J38: ='Юнит 18'!S27 -> 0 | K38: =J38/J$58 -> 0 | L38: =L37+K38 -> 0.99126638 | M38: =_xlfn.IFS(L38<80%,"A",L38<=95%,"B",L38>95%,"C") -> C
B39: 2100черный | C39: ='Юнит 18'!AL39 -> -13.872934 | D39: =C39/C$58 -> -0.00011074527 | E39: =E38+D39 -> 1.0450721 | F39: =IF(AND(E39<=0),"C",IF(E39<=0.8,"A",IF(E39<=0.95,"B","C"))) -> C | G39: =VLOOKUP(B$4:B$57,I$4:M$57,5,0) -> C | I39: qs012 | J39: ='Юнит 18'!S29 -> 0 | K39: =J39/J$58 -> 0 | L39: =L38+K39 -> 0.99126638 | M39: =_xlfn.IFS(L39<80%,"A",L39<=95%,"B",L39>95%,"C") -> C
B40: 2084 | C40: ='Юнит 18'!AL54 -> -13.872934 | D40: =C40/C$58 -> -0.00011074527 | E40: =E39+D40 -> 1.0449614 | F40: =IF(AND(E40<=0),"C",IF(E40<=0.8,"A",IF(E40<=0.95,"B","C"))) -> C | G40: =VLOOKUP(B$4:B$57,I$4:M$57,5,0) -> C | I40: qs001 Ж | J40: ='Юнит 18'!S33 -> 0 | K40: =J40/J$58 -> 0 | L40: =L39+K40 -> 0.99126638 | M40: =_xlfn.IFS(L40<80%,"A",L40<=95%,"B",L40>95%,"C") -> C
B41: 2084 (+1.75) | C41: ='Юнит 18'!AL55 -> -17.836629 | D41: =C41/C$58 -> -0.00014238678 | E41: =E40+D41 -> 1.044819 | F41: =IF(AND(E41<=0),"C",IF(E41<=0.8,"A",IF(E41<=0.95,"B","C"))) -> C | G41: =VLOOKUP(B$4:B$57,I$4:M$57,5,0) -> C | I41: qs012ж | J41: ='Юнит 18'!S36 -> 0 | K41: =J41/J$58 -> 0 | L41: =L40+K41 -> 0.99126638 | M41: =_xlfn.IFS(L41<80%,"A",L41<=95%,"B",L41>95%,"C") -> C
B42: 180ч/б | C42: ='Юнит 18'!AL46 -> -33.691411 | D42: =C42/C$58 -> -0.00026895281 | E42: =E41+D42 -> 1.04455 | F42: =IF(AND(E42<=0),"C",IF(E42<=0.8,"A",IF(E42<=0.95,"B","C"))) -> C | G42: =VLOOKUP(B$4:B$57,I$4:M$57,5,0) -> C | I42: 2038красный | J42: ='Юнит 18'!S38 -> 0 | K42: =J42/J$58 -> 0 | L42: =L41+K42 -> 0.99126638 | M42: =_xlfn.IFS(L42<80%,"A",L42<=95%,"B",L42>95%,"C") -> C
B43: 2100фиолетовый | C43: ='Юнит 18'!AL41 -> -33.723695 | D43: =C43/C$58 -> -0.00026921053 | E43: =E42+D43 -> 1.0442808 | F43: =IF(AND(E43<=0),"C",IF(E43<=0.8,"A",IF(E43<=0.95,"B","C"))) -> C | G43: =VLOOKUP(B$4:B$57,I$4:M$57,5,0) -> C | I43: 2100черный | J43: ='Юнит 18'!S39 -> 0 | K43: =J43/J$58 -> 0 | L43: =L42+K43 -> 0.99126638 | M43: =_xlfn.IFS(L43<80%,"A",L43<=95%,"B",L43>95%,"C") -> C
B44: 2064ч/б | C44: ='Юнит 18'!AL50 -> -35.476629 | D44: =C44/C$58 -> -0.0002832039 | E44: =E43+D44 -> 1.0439976 | F44: =IF(AND(E44<=0),"C",IF(E44<=0.8,"A",IF(E44<=0.95,"B","C"))) -> C | G44: =VLOOKUP(B$4:B$57,I$4:M$57,5,0) -> C | I44: 2100красный | J44: ='Юнит 18'!S40 -> 0 | K44: =J44/J$58 -> 0 | L44: =L43+K44 -> 0.99126638 | M44: =_xlfn.IFS(L44<80%,"A",L44<=95%,"B",L44>95%,"C") -> C
B45: 8852 | C45: ='Юнит 18'!AL56 -> -38.64603 | D45: =C45/C$58 -> -0.00030850469 | E45: =E44+D45 -> 1.0436891 | F45: =IF(AND(E45<=0),"C",IF(E45<=0.8,"A",IF(E45<=0.95,"B","C"))) -> C | G45: =VLOOKUP(B$4:B$57,I$4:M$57,5,0) -> C | I45: 2100фиолетовый | J45: ='Юнит 18'!S41 -> 0 | K45: =J45/J$58 -> 0 | L45: =L44+K45 -> 0.99126638 | M45: =_xlfn.IFS(L45<80%,"A",L45<=95%,"B",L45>95%,"C") -> C
B46: 180узор | C46: ='Юнит 18'!AL47 -> -54.304182 | D46: =C46/C$58 -> -0.00043350106 | E46: =E45+D46 -> 1.0432556 | F46: =IF(AND(E46<=0),"C",IF(E46<=0.8,"A",IF(E46<=0.95,"B","C"))) -> C | G46: =VLOOKUP(B$4:B$57,I$4:M$57,5,0) -> C | I46: 2104 | J46: ='Юнит 18'!S42 -> 0 | K46: =J46/J$58 -> 0 | L46: =L45+K46 -> 0.99126638 | M46: =_xlfn.IFS(L46<80%,"A",L46<=95%,"B",L46>95%,"C") -> C
B47: 123черный | C47: ='Юнит 18'!AL44 -> -56.28603 | D47: =C47/C$58 -> -0.00044932181 | E47: =E46+D47 -> 1.0428063 | F47: =IF(AND(E47<=0),"C",IF(E47<=0.8,"A",IF(E47<=0.95,"B","C"))) -> C | G47: =VLOOKUP(B$4:B$57,I$4:M$57,5,0) -> C | I47: 123черный | J47: ='Юнит 18'!S44 -> 0 | K47: =J47/J$58 -> 0 | L47: =L46+K47 -> 0.99126638 | M47: =_xlfn.IFS(L47<80%,"A",L47<=95%,"B",L47>95%,"C") -> C
B48: 2081 | C48: ='Юнит 18'!AL53 -> -56.28603 | D48: =C48/C$58 -> -0.00044932181 | E48: =E47+D48 -> 1.042357 | F48: =IF(AND(E48<=0),"C",IF(E48<=0.8,"A",IF(E48<=0.95,"B","C"))) -> C | G48: =VLOOKUP(B$4:B$57,I$4:M$57,5,0) -> C | I48: 123метал | J48: ='Юнит 18'!S45 -> 0 | K48: =J48/J$58 -> 0 | L48: =L47+K48 -> 0.99126638 | M48: =_xlfn.IFS(L48<80%,"A",L48<=95%,"B",L48>95%,"C") -> C
B49: 2064фиолетовые | C49: ='Юнит 18'!AL52 -> -68.919725 | D49: =C49/C$58 -> -0.00055017446 | E49: =E48+D49 -> 1.0418068 | F49: =IF(AND(E49<=0),"C",IF(E49<=0.8,"A",IF(E49<=0.95,"B","C"))) -> C | G49: =VLOOKUP(B$4:B$57,I$4:M$57,5,0) -> C | I49: 180ч/б | J49: ='Юнит 18'!S46 -> 0 | K49: =J49/J$58 -> 0 | L49: =L48+K49 -> 0.99126638 | M49: =_xlfn.IFS(L49<80%,"A",L49<=95%,"B",L49>95%,"C") -> C
B50: qs012 | C50: ='Юнит 18'!AL29 -> -81.39 | D50: =C50/C$58 -> -0.00064972254 | E50: =E49+D50 -> 1.0411571 | F50: =IF(AND(E50<=0),"C",IF(E50<=0.8,"A",IF(E50<=0.95,"B","C"))) -> C | G50: =VLOOKUP(B$4:B$57,I$4:M$57,5,0) -> C | I50: 180узор | J50: ='Юнит 18'!S47 -> 0 | K50: =J50/J$58 -> 0 | L50: =L49+K50 -> 0.99126638 | M50: =_xlfn.IFS(L50<80%,"A",L50<=95%,"B",L50>95%,"C") -> C
B51: 123метал | C51: ='Юнит 18'!AL45 -> -87.602335 | D51: =C51/C$58 -> -0.00069931455 | E51: =E50+D51 -> 1.0404578 | F51: =IF(AND(E51<=0),"C",IF(E51<=0.8,"A",IF(E51<=0.95,"B","C"))) -> C | G51: =VLOOKUP(B$4:B$57,I$4:M$57,5,0) -> C | I51: 580метал | J51: ='Юнит 18'!S49 -> 0 | K51: =J51/J$58 -> 0 | L51: =L50+K51 -> 0.99126638 | M51: =_xlfn.IFS(L51<80%,"A",L51<=95%,"B",L51>95%,"C") -> C
B52: qs010 | C52: ='Юнит 18'!AL27 -> -119.99092 | D52: =C52/C$58 -> -0.00095786715 | E52: =E51+D52 -> 1.0394999 | F52: =IF(AND(E52<=0),"C",IF(E52<=0.8,"A",IF(E52<=0.95,"B","C"))) -> C | G52: =VLOOKUP(B$4:B$57,I$4:M$57,5,0) -> C | I52: 2064ч/б | J52: ='Юнит 18'!S50 -> 0 | K52: =J52/J$58 -> 0 | L52: =L51+K52 -> 0.99126638 | M52: =_xlfn.IFS(L52<80%,"A",L52<=95%,"B",L52>95%,"C") -> C
B53: 580метал | C53: ='Юнит 18'!AL49 -> -120.12049 | D53: =C53/C$58 -> -0.00095890143 | E53: =E52+D53 -> 1.038541 | F53: =IF(AND(E53<=0),"C",IF(E53<=0.8,"A",IF(E53<=0.95,"B","C"))) -> C | G53: =VLOOKUP(B$4:B$57,I$4:M$57,5,0) -> C | I53: 2064фиолетовые | J53: ='Юнит 18'!S52 -> 0 | K53: =J53/J$58 -> 0 | L53: =L52+K53 -> 0.99126638 | M53: =_xlfn.IFS(L53<80%,"A",L53<=95%,"B",L53>95%,"C") -> C
B54: qs012ж | C54: ='Юнит 18'!AL36 -> -145.06233 | D54: =C54/C$58 -> -0.001158008 | E54: =E53+D54 -> 1.037383 | F54: =IF(AND(E54<=0),"C",IF(E54<=0.8,"A",IF(E54<=0.95,"B","C"))) -> C | G54: =VLOOKUP(B$4:B$57,I$4:M$57,5,0) -> C | I54: 2081 | J54: ='Юнит 18'!S53 -> 0 | K54: =J54/J$58 -> 0 | L54: =L53+K54 -> 0.99126638 | M54: =_xlfn.IFS(L54<80%,"A",L54<=95%,"B",L54>95%,"C") -> C
B55: Qs син Сул | C55: ='Юнит 18'!AL5 -> -818.87078 | D55: =C55/C$58 -> -0.0065369063 | E55: =E54+D55 -> 1.0308461 | F55: =IF(AND(E55<=0),"C",IF(E55<=0.8,"A",IF(E55<=0.95,"B","C"))) -> C | G55: =VLOOKUP(B$4:B$57,I$4:M$57,5,0) -> A | I55: 2084 | J55: ='Юнит 18'!S54 -> 0 | K55: =J55/J$58 -> 0 | L55: =L54+K55 -> 0.99126638 | M55: =_xlfn.IFS(L55<80%,"A",L55<=95%,"B",L55>95%,"C") -> C
B56: flip черные Сул | C56: ='Юнит 18'!AL7 -> -1373.0154 | D56: =C56/C$58 -> -0.010960549 | E56: =E55+D56 -> 1.0198855 | F56: =IF(AND(E56<=0),"C",IF(E56<=0.8,"A",IF(E56<=0.95,"B","C"))) -> C | G56: =VLOOKUP(B$4:B$57,I$4:M$57,5,0) -> B | I56: 2084 (+1.75) | J56: ='Юнит 18'!S55 -> 0 | K56: =J56/J$58 -> 0 | L56: =L55+K56 -> 0.99126638 | M56: =_xlfn.IFS(L56<80%,"A",L56<=95%,"B",L56>95%,"C") -> C
B57: Qs желт Сул | C57: ='Юнит 18'!AL6 -> -3725.7004 | D57: =C57/C$58 -> -0.029741633 | E57: =E56+D57 -> 0.99014389 | F57: =IF(AND(E57<=0),"C",IF(E57<=0.8,"A",IF(E57<=0.95,"B","C"))) -> C | G57: =VLOOKUP(B$4:B$57,I$4:M$57,5,0) -> A | I57: 8852 | J57: ='Юнит 18'!S56 -> 0 | K57: =J57/J$58 -> 0 | L57: =L56+K57 -> 0.99126638 | M57: =_xlfn.IFS(L57<80%,"A",L57<=95%,"B",L57>95%,"C") -> C
C58: =SUM(C4:C57) -> 125268.86 | D58: =SUM(D4:D44) -> 1.0538537 | J58: =SUM(J4:J57) -> 458 | K58: =SUM(K4:K44) -> 1
C61: Прибыль | D61: % прибыль | E61: Доля | F61: ABC прибыль | G61: ABC кол-во | J61: Кол-во | K61: % кол-во | L61: Доля | M61: ABC кол-во
D62: =C62/C$114 -> #DIV/0! | E62: =D62 -> #DIV/0! | F62: =IF(AND(E62<=0),"C",IF(E62<=0.8,"A",IF(E62<=0.95,"B","C"))) -> #DIV/0! | G62: =VLOOKUP(B62:B113,I$62:M$113,5,0) -> #N/A | K62: =J62/J$114 -> #DIV/0! | L62: =K62 -> #DIV/0! | M62: =_xlfn.IFS(L62<80%,"A",L62<=95%,"B",L62>95%,"C") -> #DIV/0!
D63: =C63/C$114 -> #DIV/0! | E63: =D63+E62 -> #DIV/0! | F63: =IF(AND(E63<=0),"C",IF(E63<=0.8,"A",IF(E63<=0.95,"B","C"))) -> #DIV/0! | G63: =VLOOKUP(B63:B114,I$62:M$113,5,0) -> #N/A | K63: =J63/J$114 -> #DIV/0! | L63: =K63+L62 -> #DIV/0! | M63: =_xlfn.IFS(L63<80%,"A",L63<=95%,"B",L63>95%,"C") -> #DIV/0!
D64: =C64/C$114 -> #DIV/0! | E64: =D64+E63 -> #DIV/0! | F64: =IF(AND(E64<=0),"C",IF(E64<=0.8,"A",IF(E64<=0.95,"B","C"))) -> #DIV/0! | G64: =VLOOKUP(B64:B115,I$62:M$113,5,0) -> #N/A | K64: =J64/J$114 -> #DIV/0! | L64: =K64+L63 -> #DIV/0! | M64: =_xlfn.IFS(L64<80%,"A",L64<=95%,"B",L64>95%,"C") -> #DIV/0!
D65: =C65/C$114 -> #DIV/0! | E65: =D65+E64 -> #DIV/0! | F65: =IF(AND(E65<=0),"C",IF(E65<=0.8,"A",IF(E65<=0.95,"B","C"))) -> #DIV/0! | G65: =VLOOKUP(B65:B116,I$62:M$113,5,0) -> #N/A | K65: =J65/J$114 -> #DIV/0! | L65: =K65+L64 -> #DIV/0! | M65: =_xlfn.IFS(L65<80%,"A",L65<=95%,"B",L65>95%,"C") -> #DIV/0!
D66: =C66/C$114 -> #DIV/0! | E66: =D66+E65 -> #DIV/0! | F66: =IF(AND(E66<=0),"C",IF(E66<=0.8,"A",IF(E66<=0.95,"B","C"))) -> #DIV/0! | G66: =VLOOKUP(B66:B117,I$62:M$113,5,0) -> #N/A | K66: =J66/J$114 -> #DIV/0! | L66: =K66+L65 -> #DIV/0! | M66: =_xlfn.IFS(L66<80%,"A",L66<=95%,"B",L66>95%,"C") -> #DIV/0!
D67: =C67/C$114 -> #DIV/0! | E67: =D67+E66 -> #DIV/0! | F67: =IF(AND(E67<=0),"C",IF(E67<=0.8,"A",IF(E67<=0.95,"B","C"))) -> #DIV/0! | G67: =VLOOKUP(B67:B118,I$62:M$113,5,0) -> #N/A | K67: =J67/J$114 -> #DIV/0! | L67: =K67+L66 -> #DIV/0! | M67: =_xlfn.IFS(L67<80%,"A",L67<=95%,"B",L67>95%,"C") -> #DIV/0!
D68: =C68/C$114 -> #DIV/0! | E68: =D68+E67 -> #DIV/0! | F68: =IF(AND(E68<=0),"C",IF(E68<=0.8,"A",IF(E68<=0.95,"B","C"))) -> #DIV/0! | G68: =VLOOKUP(B68:B119,I$62:M$113,5,0) -> #N/A | K68: =J68/J$114 -> #DIV/0! | L68: =K68+L67 -> #DIV/0! | M68: =_xlfn.IFS(L68<80%,"A",L68<=95%,"B",L68>95%,"C") -> #DIV/0!
D69: =C69/C$114 -> #DIV/0! | E69: =D69+E68 -> #DIV/0! | F69: =IF(AND(E69<=0),"C",IF(E69<=0.8,"A",IF(E69<=0.95,"B","C"))) -> #DIV/0! | G69: =VLOOKUP(B69:B120,I$62:M$113,5,0) -> #N/A | K69: =J69/J$114 -> #DIV/0! | L69: =K69+L68 -> #DIV/0! | M69: =_xlfn.IFS(L69<80%,"A",L69<=95%,"B",L69>95%,"C") -> #DIV/0!
D70: =C70/C$114 -> #DIV/0! | E70: =D70+E69 -> #DIV/0! | F70: =IF(AND(E70<=0),"C",IF(E70<=0.8,"A",IF(E70<=0.95,"B","C"))) -> #DIV/0! | G70: =VLOOKUP(B70:B121,I$62:M$113,5,0) -> #N/A | K70: =J70/J$114 -> #DIV/0! | L70: =K70+L69 -> #DIV/0! | M70: =_xlfn.IFS(L70<80%,"A",L70<=95%,"B",L70>95%,"C") -> #DIV/0!
D71: =C71/C$114 -> #DIV/0! | E71: =D71+E70 -> #DIV/0! | F71: =IF(AND(E71<=0),"C",IF(E71<=0.8,"A",IF(E71<=0.95,"B","C"))) -> #DIV/0! | G71: =VLOOKUP(B71:B122,I$62:M$113,5,0) -> #N/A | K71: =J71/J$114 -> #DIV/0! | L71: =K71+L70 -> #DIV/0! | M71: =_xlfn.IFS(L71<80%,"A",L71<=95%,"B",L71>95%,"C") -> #DIV/0!
D72: =C72/C$114 -> #DIV/0! | E72: =D72+E71 -> #DIV/0! | F72: =IF(AND(E72<=0),"C",IF(E72<=0.8,"A",IF(E72<=0.95,"B","C"))) -> #DIV/0! | G72: =VLOOKUP(B72:B123,I$62:M$113,5,0) -> #N/A | K72: =J72/J$114 -> #DIV/0! | L72: =K72+L71 -> #DIV/0! | M72: =_xlfn.IFS(L72<80%,"A",L72<=95%,"B",L72>95%,"C") -> #DIV/0!
D73: =C73/C$114 -> #DIV/0! | E73: =D73+E72 -> #DIV/0! | F73: =IF(AND(E73<=0),"C",IF(E73<=0.8,"A",IF(E73<=0.95,"B","C"))) -> #DIV/0! | G73: =VLOOKUP(B73:B124,I$62:M$113,5,0) -> #N/A | K73: =J73/J$114 -> #DIV/0! | L73: =K73+L72 -> #DIV/0! | M73: =_xlfn.IFS(L73<80%,"A",L73<=95%,"B",L73>95%,"C") -> #DIV/0!
D74: =C74/C$114 -> #DIV/0! | E74: =D74+E73 -> #DIV/0! | F74: =IF(AND(E74<=0),"C",IF(E74<=0.8,"A",IF(E74<=0.95,"B","C"))) -> #DIV/0! | G74: =VLOOKUP(B74:B125,I$62:M$113,5,0) -> #N/A | K74: =J74/J$114 -> #DIV/0! | L74: =K74+L73 -> #DIV/0! | M74: =_xlfn.IFS(L74<80%,"A",L74<=95%,"B",L74>95%,"C") -> #DIV/0!
... D113: =C113/C$114 -> #DIV/0! | E113: =D113+E112 -> #DIV/0! | F113: =IF(AND(E113<=0),"C",IF(E113<=0.8,"A",IF(E113<=0.95,"B","C"))) -> #DIV/0! | G113: =VLOOKUP(B113:B164,I$62:M$113,5,0) -> #N/A | K113: =J113/J$114 -> #DIV/0! | L113: =K113+L112 -> #DIV/0! | M113: =_xlfn.IFS(L113<80%,"A",L113<=95%,"B",L113>95%,"C") -> #DIV/0!
C114: =SUM(C62:C113) -> 0 | D114: =SUM(D62:D113) -> #DIV/0! | J114: =SUM(J62:J113) -> 0 | K114: =SUM(K62:K113) -> #DIV/0!

Sheet АВС 17
B2: ОЧКИ
C3: Прибыль | D3: % прибыль | E3: Доля | F3: ABC прибыль | G3: ABC кол-во | J3: Кол-во | K3: % кол-во | L3: Доля | M3: ABC кол-во
B4: Qs черн Сул | C4: ='Юнит 17'!AL4 -> 73673.399 | D4: =C4/C$58 -> 0.53351322 | E4: =D4 -> 0.53351322 | F4: =IF(AND(E4<=0),"C",IF(E4<=0.8,"A",IF(E4<=0.95,"B","C"))) -> A | G4: =VLOOKUP(B$4:B$57,I$4:M$57,5,0) -> A | I4: Qs черн Сул | J4: ='Юнит 17'!S4 -> 242 | K4: =J4/J$58 -> 0.48111332 | L4: =K4 -> 0.48111332 | M4: =_xlfn.IFS(L4<80%,"A",L4<=95%,"B",L4>95%,"C") -> A | P4: A | Q4: 0.8
B5: Черные с железкой Сул | C5: ='Юнит 17'!AL3 -> 29431.715 | D5: =C5/C$58 -> 0.21313268 | E5: =E4+D5 -> 0.7466459 | F5: =IF(AND(E5<=0),"C",IF(E5<=0.8,"A",IF(E5<=0.95,"B","C"))) -> A | G5: =VLOOKUP(B$4:B$57,I$4:M$57,5,0) -> A | I5: Черные с железкой Сул | J5: ='Юнит 17'!S3 -> 95 | K5: =J5/J$58 -> 0.1888668 | L5: =L4+K5 -> 0.66998012 | M5: =_xlfn.IFS(L5<80%,"A",L5<=95%,"B",L5>95%,"C") -> A | P5: B | Q5: 0.15
B6: flip желтые Сул | C6: ='Юнит 17'!AL8 -> 7900.7181 | D6: =C6/C$58 -> 0.057213833 | E6: =E5+D6 -> 0.80385973 | F6: =IF(AND(E6<=0),"C",IF(E6<=0.8,"A",IF(E6<=0.95,"B","C"))) -> B | G6: =VLOOKUP(B$4:B$57,I$4:M$57,5,0) -> A | I6: flip желтые Сул | J6: ='Юнит 17'!S8 -> 34 | K6: =J6/J$58 -> 0.067594433 | L6: =L5+K6 -> 0.73757455 | M6: =_xlfn.IFS(L6<80%,"A",L6<=95%,"B",L6>95%,"C") -> A | P6: C | Q6: 0.05
B7: MR 1890 желт | C7: ='Юнит 17'!AL17 -> 7175.8414 | D7: =C7/C$58 -> 0.051964566 | E7: =E6+D7 -> 0.8558243 | F7: =IF(AND(E7<=0),"C",IF(E7<=0.8,"A",IF(E7<=0.95,"B","C"))) -> B | G7: =VLOOKUP(B$4:B$57,I$4:M$57,5,0) -> B | I7: Qs желт Сул | J7: ='Юнит 17'!S6 -> 19 | K7: =J7/J$58 -> 0.03777336 | L7: =L6+K7 -> 0.77534791 | M7: =_xlfn.IFS(L7<80%,"A",L7<=95%,"B",L7>95%,"C") -> A
B8: MR 1890 черн | C8: ='Юнит 17'!AL16 -> 6162.7645 | D8: =C8/C$58 -> 0.04462827 | E8: =E7+D8 -> 0.90045257 | F8: =IF(AND(E8<=0),"C",IF(E8<=0.8,"A",IF(E8<=0.95,"B","C"))) -> B | G8: =VLOOKUP(B$4:B$57,I$4:M$57,5,0) -> B | I8: MR 1890 желт | J8: ='Юнит 17'!S17 -> 17 | K8: =J8/J$58 -> 0.033797217 | L8: =L7+K8 -> 0.80914513 | M8: =_xlfn.IFS(L8<80%,"A",L8<=95%,"B",L8>95%,"C") -> B
B9: qs015 | C9: ='Юнит 17'!AL32 -> 3893.368 | D9: =C9/C$58 -> 0.02819421 | E9: =E8+D9 -> 0.92864678 | F9: =IF(AND(E9<=0),"C",IF(E9<=0.8,"A",IF(E9<=0.95,"B","C"))) -> B | G9: =VLOOKUP(B$4:B$57,I$4:M$57,5,0) -> B | I9: Qs син Сул | J9: ='Юнит 17'!S5 -> 14 | K9: =J9/J$58 -> 0.027833002 | L9: =L8+K9 -> 0.83697813 | M9: =_xlfn.IFS(L9<80%,"A",L9<=95%,"B",L9>95%,"C") -> B
B10: MR 1890 корич | C10: ='Юнит 17'!AL18 -> 3540.775 | D10: =C10/C$58 -> 0.025640873 | E10: =E9+D10 -> 0.95428765 | F10: =IF(AND(E10<=0),"C",IF(E10<=0.8,"A",IF(E10<=0.95,"B","C"))) -> C | G10: =VLOOKUP(B$4:B$57,I$4:M$57,5,0) -> B | I10: flip черные Сул | J10: ='Юнит 17'!S7 -> 12 | K10: =J10/J$58 -> 0.023856859 | L10: =L9+K10 -> 0.86083499 | M10: =_xlfn.IFS(L10<80%,"A",L10<=95%,"B",L10>95%,"C") -> B
B11: MR8854 C2 Сул | C11: ='Юнит 17'!AL9 -> 2688.74 | D11: =C11/C$58 -> 0.019470777 | E11: =E10+D11 -> 0.97375843 | F11: =IF(AND(E11<=0),"C",IF(E11<=0.8,"A",IF(E11<=0.95,"B","C"))) -> C | G11: =VLOOKUP(B$4:B$57,I$4:M$57,5,0) -> B | I11: MR 1890 черн | J11: ='Юнит 17'!S16 -> 12 | K11: =J11/J$58 -> 0.023856859 | L11: =L10+K11 -> 0.88469185 | M11: =_xlfn.IFS(L11<80%,"A",L11<=95%,"B",L11>95%,"C") -> B
B12: qs007 | C12: ='Юнит 17'!AL24 -> 2499.2985 | D12: =C12/C$58 -> 0.018098918 | E12: =E11+D12 -> 0.99185734 | F12: =IF(AND(E12<=0),"C",IF(E12<=0.8,"A",IF(E12<=0.95,"B","C"))) -> C | G12: =VLOOKUP(B$4:B$57,I$4:M$57,5,0) -> B | I12: MR 1890 корич | J12: ='Юнит 17'!S18 -> 10 | K12: =J12/J$58 -> 0.019880716 | L12: =L11+K12 -> 0.90457256 | M12: =_xlfn.IFS(L12<80%,"A",L12<=95%,"B",L12>95%,"C") -> B
B13: qs003 | C13: ='Юнит 17'!AL21 -> 1907.8494 | D13: =C13/C$58 -> 0.01381588 | E13: =E12+D13 -> 1.0056732 | F13: =IF(AND(E13<=0),"C",IF(E13<=0.8,"A",IF(E13<=0.95,"B","C"))) -> C | G13: =VLOOKUP(B$4:B$57,I$4:M$57,5,0) -> C | I13: qs015 | J13: ='Юнит 17'!S32 -> 7 | K13: =J13/J$58 -> 0.013916501 | L13: =L12+K13 -> 0.91848907 | M13: =_xlfn.IFS(L13<80%,"A",L13<=95%,"B",L13>95%,"C") -> B
B14: qs008 | C14: ='Юнит 17'!AL25 -> 1685.1667 | D14: =C14/C$58 -> 0.012203301 | E14: =E13+D14 -> 1.0178765 | F14: =IF(AND(E14<=0),"C",IF(E14<=0.8,"A",IF(E14<=0.95,"B","C"))) -> C | G14: =VLOOKUP(B$4:B$57,I$4:M$57,5,0) -> C | I14: qs007 | J14: ='Юнит 17'!S24 -> 6 | K14: =J14/J$58 -> 0.011928429 | L14: =L13+K14 -> 0.9304175 | M14: =_xlfn.IFS(L14<80%,"A",L14<=95%,"B",L14>95%,"C") -> B
B15: qs014 | C15: ='Юнит 17'!AL31 -> 1552.1608 | D15: =C15/C$58 -> 0.011240127 | E15: =E14+D15 -> 1.0291167 | F15: =IF(AND(E15<=0),"C",IF(E15<=0.8,"A",IF(E15<=0.95,"B","C"))) -> C | G15: =VLOOKUP(B$4:B$57,I$4:M$57,5,0) -> C | I15: MR8854 C2 Сул | J15: ='Юнит 17'!S9 -> 5 | K15: =J15/J$58 -> 0.0099403579 | L15: =L14+K15 -> 0.94035785 | M15: =_xlfn.IFS(L15<80%,"A",L15<=95%,"B",L15>95%,"C") -> B
B16: qs002 | C16: ='Юнит 17'!AL20 -> 1458.8409 | D16: =C16/C$58 -> 0.010564341 | E16: =E15+D16 -> 1.039681 | F16: =IF(AND(E16<=0),"C",IF(E16<=0.8,"A",IF(E16<=0.95,"B","C"))) -> C | G16: =VLOOKUP(B$4:B$57,I$4:M$57,5,0) -> B | I16: qs002 | J16: ='Юнит 17'!S20 -> 4 | K16: =J16/J$58 -> 0.0079522863 | L16: =L15+K16 -> 0.94831014 | M16: =_xlfn.IFS(L16<80%,"A",L16<=95%,"B",L16>95%,"C") -> B
B17: qs010ж | C17: ='Юнит 17'!AL34 -> 1448.3536 | D17: =C17/C$58 -> 0.010488396 | E17: =E16+D17 -> 1.0501694 | F17: =IF(AND(E17<=0),"C",IF(E17<=0.8,"A",IF(E17<=0.95,"B","C"))) -> C | G17: =VLOOKUP(B$4:B$57,I$4:M$57,5,0) -> C | I17: qs003 | J17: ='Юнит 17'!S21 -> 4 | K17: =J17/J$58 -> 0.0079522863 | L17: =L16+K17 -> 0.95626243 | M17: =_xlfn.IFS(L17<80%,"A",L17<=95%,"B",L17>95%,"C") -> C
B18: MR Р1886 корич | C18: ='Юнит 17'!AL15 -> 979.59 | D18: =C18/C$58 -> 0.007093798 | E18: =E17+D18 -> 1.0572632 | F18: =IF(AND(E18<=0),"C",IF(E18<=0.8,"A",IF(E18<=0.95,"B","C"))) -> C | G18: =VLOOKUP(B$4:B$57,I$4:M$57,5,0) -> C | I18: qs008 | J18: ='Юнит 17'!S25 -> 4 | K18: =J18/J$58 -> 0.0079522863 | L18: =L17+K18 -> 0.96421471 | M18: =_xlfn.IFS(L18<80%,"A",L18<=95%,"B",L18>95%,"C") -> C
B19: MR Р1886 черн | C19: ='Юнит 17'!AL14 -> 937.61379 | D19: =C19/C$58 -> 0.0067898231 | E19: =E18+D19 -> 1.064053 | F19: =IF(AND(E19<=0),"C",IF(E19<=0.8,"A",IF(E19<=0.95,"B","C"))) -> C | G19: =VLOOKUP(B$4:B$57,I$4:M$57,5,0) -> C | I19: qs014 | J19: ='Юнит 17'!S31 -> 3 | K19: =J19/J$58 -> 0.0059642147 | L19: =L18+K19 -> 0.97017893 | M19: =_xlfn.IFS(L19<80%,"A",L19<=95%,"B",L19>95%,"C") -> C
B20: qs005 | C20: ='Юнит 17'!AL22 -> 809.18122 | D20: =C20/C$58 -> 0.005859766 | E20: =E19+D20 -> 1.0699128 | F20: =IF(AND(E20<=0),"C",IF(E20<=0.8,"A",IF(E20<=0.95,"B","C"))) -> C | G20: =VLOOKUP(B$4:B$57,I$4:M$57,5,0) -> C | I20: qs010ж | J20: ='Юнит 17'!S34 -> 3 | K20: =J20/J$58 -> 0.0059642147 | L20: =L19+K20 -> 0.97614314 | M20: =_xlfn.IFS(L20<80%,"A",L20<=95%,"B",L20>95%,"C") -> C
B21: 2100фиолетовый | C21: ='Юнит 17'!AL41 -> 440.50595 | D21: =C21/C$58 -> 0.0031899674 | E21: =E20+D21 -> 1.0731027 | F21: =IF(AND(E21<=0),"C",IF(E21<=0.8,"A",IF(E21<=0.95,"B","C"))) -> C | G21: =VLOOKUP(B$4:B$57,I$4:M$57,5,0) -> C | I21: MR Р1886 черн | J21: ='Юнит 17'!S14 -> 2 | K21: =J21/J$58 -> 0.0039761431 | L21: =L20+K21 -> 0.98011928 | M21: =_xlfn.IFS(L21<80%,"A",L21<=95%,"B",L21>95%,"C") -> C
B22: 2084 (+1.75) | C22: ='Юнит 17'!AL55 -> 403.00575 | D22: =C22/C$58 -> 0.002918406 | E22: =E21+D22 -> 1.0760211 | F22: =IF(AND(E22<=0),"C",IF(E22<=0.8,"A",IF(E22<=0.95,"B","C"))) -> C | G22: =VLOOKUP(B$4:B$57,I$4:M$57,5,0) -> C | I22: MR Р1886 корич | J22: ='Юнит 17'!S15 -> 2 | K22: =J22/J$58 -> 0.0039761431 | L22: =L21+K22 -> 0.98409543 | M22: =_xlfn.IFS(L22<80%,"A",L22<=95%,"B",L22>95%,"C") -> C
B23: MR Р1874 черн | C23: ='Юнит 17'!AL12 -> 379.34 | D23: =C23/C$58 -> 0.0027470282 | E23: =E22+D23 -> 1.0787682 | F23: =IF(AND(E23<=0),"C",IF(E23<=0.8,"A",IF(E23<=0.95,"B","C"))) -> C | G23: =VLOOKUP(B$4:B$57,I$4:M$57,5,0) -> C | I23: qs005 | J23: ='Юнит 17'!S22 -> 2 | K23: =J23/J$58 -> 0.0039761431 | L23: =L22+K23 -> 0.98807157 | M23: =_xlfn.IFS(L23<80%,"A",L23<=95%,"B",L23>95%,"C") -> C
B24: flip черные Сул | C24: ='Юнит 17'!AL7 -> 377.39187 | D24: =C24/C$58 -> 0.0027329206 | E24: =E23+D24 -> 1.0815011 | F24: =IF(AND(E24<=0),"C",IF(E24<=0.8,"A",IF(E24<=0.95,"B","C"))) -> C | G24: =VLOOKUP(B$4:B$57,I$4:M$57,5,0) -> B | I24: MR Р1874 черн | J24: ='Юнит 17'!S12 -> 1 | K24: =J24/J$58 -> 0.0019880716 | L24: =L23+K24 -> 0.99005964 | M24: =_xlfn.IFS(L24<80%,"A",L24<=95%,"B",L24>95%,"C") -> C
B25: 2064ч/б | C25: ='Юнит 17'!AL50 -> 359.07176 | D25: =C25/C$58 -> 0.0026002537 | E25: =E24+D25 -> 1.0841014 | F25: =IF(AND(E25<=0),"C",IF(E25<=0.8,"A",IF(E25<=0.95,"B","C"))) -> C | G25: =VLOOKUP(B$4:B$57,I$4:M$57,5,0) -> C | I25: qs006 | J25: ='Юнит 17'!S23 -> 1 | K25: =J25/J$58 -> 0.0019880716 | L25: =L24+K25 -> 0.99204771 | M25: =_xlfn.IFS(L25<80%,"A",L25<=95%,"B",L25>95%,"C") -> C
B26: MR Р1874 корич | C26: ='Юнит 17'!AL13 -> 0 | D26: =C26/C$58 -> 0 | E26: =E25+D26 -> 1.0841014 | F26: =IF(AND(E26<=0),"C",IF(E26<=0.8,"A",IF(E26<=0.95,"B","C"))) -> C | G26: =VLOOKUP(B$4:B$57,I$4:M$57,5,0) -> C | I26: qs009 | J26: ='Юнит 17'!S26 -> 1 | K26: =J26/J$58 -> 0.0019880716 | L26: =L25+K26 -> 0.99403579 | M26: =_xlfn.IFS(L26<80%,"A",L26<=95%,"B",L26>95%,"C") -> C
B27: qs011 | C27: ='Юнит 17'!AL28 -> 0 | D27: =C27/C$58 -> 0 | E27: =E26+D27 -> 1.0841014 | F27: =IF(AND(E27<=0),"C",IF(E27<=0.8,"A",IF(E27<=0.95,"B","C"))) -> C | G27: =VLOOKUP(B$4:B$57,I$4:M$57,5,0) -> C | I27: 2100фиолетовый | J27: ='Юнит 17'!S41 -> 1 | K27: =J27/J$58 -> 0.0019880716 | L27: =L26+K27 -> 0.99602386 | M27: =_xlfn.IFS(L27<80%,"A",L27<=95%,"B",L27>95%,"C") -> C
B28: qs001 Ж | C28: ='Юнит 17'!AL33 -> 0 | D28: =C28/C$58 -> 0 | E28: =E24+D28 -> 1.0815011 | F28: =IF(AND(E28<=0),"C",IF(E28<=0.8,"A",IF(E28<=0.95,"B","C"))) -> C | G28: =VLOOKUP(B$4:B$57,I$4:M$57,5,0) -> C | I28: 2064ч/б | J28: ='Юнит 17'!S50 -> 1 | K28: =J28/J$58 -> 0.0019880716 | L28: =L24+K28 -> 0.99204771 | M28: =_xlfn.IFS(L28<80%,"A",L28<=95%,"B",L28>95%,"C") -> C
B29: 2104 | C29: ='Юнит 17'!AL42 -> -7.8081072 | D29: =C29/C$58 -> -5.6543182e-05 | E29: =E28+D29 -> 1.0814446 | F29: =IF(AND(E29<=0),"C",IF(E29<=0.8,"A",IF(E29<=0.95,"B","C"))) -> C | G29: =VLOOKUP(B$4:B$57,I$4:M$57,5,0) -> C | I29: 2084 (+1.75) | J29: ='Юнит 17'!S55 -> 1 | K29: =J29/J$58 -> 0.0019880716 | L29: =L28+K29 -> 0.99403579 | M29: =_xlfn.IFS(L29<80%,"A",L29<=95%,"B",L29>95%,"C") -> C
B30: 2038красный | C30: ='Юнит 17'!AL38 -> -9.7601341 | D30: =C30/C$58 -> -7.0678978e-05 | E30: =E29+D30 -> 1.0813739 | F30: =IF(AND(E30<=0),"C",IF(E30<=0.8,"A",IF(E30<=0.95,"B","C"))) -> C | G30: =VLOOKUP(B$4:B$57,I$4:M$57,5,0) -> C | I30: MR 1819 черн | J30: ='Юнит 17'!S10 -> 0 | K30: =J30/J$58 -> 0 | L30: =L29+K30 -> 0.99403579 | M30: =_xlfn.IFS(L30<80%,"A",L30<=95%,"B",L30>95%,"C") -> C
B31: 2084 | C31: ='Юнит 17'!AL54 -> -13.664188 | D31: =C31/C$58 -> -9.8950569e-05 | E31: =E30+D31 -> 1.0812749 | F31: =IF(AND(E31<=0),"C",IF(E31<=0.8,"A",IF(E31<=0.95,"B","C"))) -> C | G31: =VLOOKUP(B$4:B$57,I$4:M$57,5,0) -> C | I31: MR 1819 корич | J31: ='Юнит 17'!S11 -> 0 | K31: =J31/J$58 -> 0 | L31: =L30+K31 -> 0.99403579 | M31: =_xlfn.IFS(L31<80%,"A",L31<=95%,"B",L31>95%,"C") -> C
B32: 123метал | C32: ='Юнит 17'!AL45 -> -34.160469 | D32: =C32/C$58 -> -0.00024737642 | E32: =E31+D32 -> 1.0810275 | F32: =IF(AND(E32<=0),"C",IF(E32<=0.8,"A",IF(E32<=0.95,"B","C"))) -> C | G32: =VLOOKUP(B$4:B$57,I$4:M$57,5,0) -> C | I32: MR Р1874 корич | J32: ='Юнит 17'!S13 -> 0 | K32: =J32/J$58 -> 0 | L32: =L31+K32 -> 0.99403579 | M32: =_xlfn.IFS(L32<80%,"A",L32<=95%,"B",L32>95%,"C") -> C
B33: qs011ж | C33: ='Юнит 17'!AL35 -> -36.112496 | D33: =C33/C$58 -> -0.00026151222 | E33: =E32+D33 -> 1.080766 | F33: =IF(AND(E33<=0),"C",IF(E33<=0.8,"A",IF(E33<=0.95,"B","C"))) -> C | G33: =VLOOKUP(B$4:B$57,I$4:M$57,5,0) -> C | I33: qs001 | J33: ='Юнит 17'!S19 -> 0 | K33: =J33/J$58 -> 0 | L33: =L32+K33 -> 0.99403579 | M33: =_xlfn.IFS(L33<80%,"A",L33<=95%,"B",L33>95%,"C") -> C
B34: 580черный | C34: ='Юнит 17'!AL48 -> -36.112496 | D34: =C34/C$58 -> -0.00026151222 | E34: =E33+D34 -> 1.0805045 | F34: =IF(AND(E34<=0),"C",IF(E34<=0.8,"A",IF(E34<=0.95,"B","C"))) -> C | G34: =VLOOKUP(B$4:B$57,I$4:M$57,5,0) -> C | I34: qs010 | J34: ='Юнит 17'!S27 -> 0 | K34: =J34/J$58 -> 0 | L34: =L33+K34 -> 0.99403579 | M34: =_xlfn.IFS(L34<80%,"A",L34<=95%,"B",L34>95%,"C") -> C
B35: 123черный | C35: ='Юнит 17'!AL44 -> -38.064523 | D35: =C35/C$58 -> -0.00027564801 | E35: =E34+D35 -> 1.0802289 | F35: =IF(AND(E35<=0),"C",IF(E35<=0.8,"A",IF(E35<=0.95,"B","C"))) -> C | G35: =VLOOKUP(B$4:B$57,I$4:M$57,5,0) -> C | I35: qs011 | J35: ='Юнит 17'!S28 -> 0 | K35: =J35/J$58 -> 0 | L35: =L34+K35 -> 0.99403579 | M35: =_xlfn.IFS(L35<80%,"A",L35<=95%,"B",L35>95%,"C") -> C
B36: 2081 | C36: ='Юнит 17'!AL53 -> -38.064523 | D36: =C36/C$58 -> -0.00027564801 | E36: =E35+D36 -> 1.0799532 | F36: =IF(AND(E36<=0),"C",IF(E36<=0.8,"A",IF(E36<=0.95,"B","C"))) -> C | G36: =VLOOKUP(B$4:B$57,I$4:M$57,5,0) -> C | I36: qs012 | J36: ='Юнит 17'!S29 -> 0 | K36: =J36/J$58 -> 0 | L36: =L35+K36 -> 0.99403579 | M36: =_xlfn.IFS(L36<80%,"A",L36<=95%,"B",L36>95%,"C") -> C
B37: 8852 | C37: ='Юнит 17'!AL56 -> -38.064523 | D37: =C37/C$58 -> -0.00027564801 | E37: =E36+D37 -> 1.0796776 | F37: =IF(AND(E37<=0),"C",IF(E37<=0.8,"A",IF(E37<=0.95,"B","C"))) -> C | G37: =VLOOKUP(B$4:B$57,I$4:M$57,5,0) -> C | I37: qs013 | J37: ='Юнит 17'!S30 -> 0 | K37: =J37/J$58 -> 0 | L37: =L36+K37 -> 0.99403579 | M37: =_xlfn.IFS(L37<80%,"A",L37<=95%,"B",L37>95%,"C") -> C
B38: 6008 | C38: ='Юнит 17'!AL43 -> -38.168308 | D38: =C38/C$58 -> -0.00027639959 | E38: =E37+D38 -> 1.0794012 | F38: =IF(AND(E38<=0),"C",IF(E38<=0.8,"A",IF(E38<=0.95,"B","C"))) -> C | G38: =VLOOKUP(B$4:B$57,I$4:M$57,5,0) -> C | I38: qs001 Ж | J38: ='Юнит 17'!S33 -> 0 | K38: =J38/J$58 -> 0 | L38: =L37+K38 -> 0.99403579 | M38: =_xlfn.IFS(L38<80%,"A",L38<=95%,"B",L38>95%,"C") -> C
B39: 2064фиолетовые | C39: ='Юнит 17'!AL52 -> -41.968576 | D39: =C39/C$58 -> -0.0003039196 | E39: =E38+D39 -> 1.0790973 | F39: =IF(AND(E39<=0),"C",IF(E39<=0.8,"A",IF(E39<=0.95,"B","C"))) -> C | G39: =VLOOKUP(B$4:B$57,I$4:M$57,5,0) -> C | I39: qs011ж | J39: ='Юнит 17'!S35 -> 0 | K39: =J39/J$58 -> 0 | L39: =L38+K39 -> 0.99403579 | M39: =_xlfn.IFS(L39<80%,"A",L39<=95%,"B",L39>95%,"C") -> C
B40: MR 1819 черн | C40: ='Юнит 17'!AL10 -> -50.194121 | D40: =C40/C$58 -> -0.0003634857 | E40: =E39+D40 -> 1.0787338 | F40: =IF(AND(E40<=0),"C",IF(E40<=0.8,"A",IF(E40<=0.95,"B","C"))) -> C | G40: =VLOOKUP(B$4:B$57,I$4:M$57,5,0) -> C | I40: qs012ж | J40: ='Юнит 17'!S36 -> 0 | K40: =J40/J$58 -> 0 | L40: =L39+K40 -> 0.99403579 | M40: =_xlfn.IFS(L40<80%,"A",L40<=95%,"B",L40>95%,"C") -> C
B41: qs012 | C41: ='Юнит 17'!AL29 -> -74.452027 | D41: =C41/C$58 -> -0.00053915173 | E41: =E40+D41 -> 1.0781946 | F41: =IF(AND(E41<=0),"C",IF(E41<=0.8,"A",IF(E41<=0.95,"B","C"))) -> C | G41: =VLOOKUP(B$4:B$57,I$4:M$57,5,0) -> C | I41: 2038ч/б | J41: ='Юнит 17'!S37 -> 0 | K41: =J41/J$58 -> 0 | L41: =L40+K41 -> 0.99403579 | M41: =_xlfn.IFS(L41<80%,"A",L41<=95%,"B",L41>95%,"C") -> C
B42: 2064коричневые | C42: ='Юнит 17'!AL51 -> -75.040536 | D42: =C42/C$58 -> -0.00054341348 | E42: =E41+D42 -> 1.0776512 | F42: =IF(AND(E42<=0),"C",IF(E42<=0.8,"A",IF(E42<=0.95,"B","C"))) -> C | G42: =VLOOKUP(B$4:B$57,I$4:M$57,5,0) -> C | I42: 2038красный | J42: ='Юнит 17'!S38 -> 0 | K42: =J42/J$58 -> 0 | L42: =L41+K42 -> 0.99403579 | M42: =_xlfn.IFS(L42<80%,"A",L42<=95%,"B",L42>95%,"C") -> C
B43: 2038ч/б | C43: ='Юнит 17'!AL37 -> -94.694121 | D43: =C43/C$58 -> -0.00068573685 | E43: =E42+D43 -> 1.0769655 | F43: =IF(AND(E43<=0),"C",IF(E43<=0.8,"A",IF(E43<=0.95,"B","C"))) -> C | G43: =VLOOKUP(B$4:B$57,I$4:M$57,5,0) -> C | I43: 2100черный | J43: ='Юнит 17'!S39 -> 0 | K43: =J43/J$58 -> 0 | L43: =L42+K43 -> 0.99403579 | M43: =_xlfn.IFS(L43<80%,"A",L43<=95%,"B",L43>95%,"C") -> C
B44: 2100красный | C44: ='Юнит 17'!AL40 -> -94.694121 | D44: =C44/C$58 -> -0.00068573685 | E44: =E43+D44 -> 1.0762797 | F44: =IF(AND(E44<=0),"C",IF(E44<=0.8,"A",IF(E44<=0.95,"B","C"))) -> C | G44: =VLOOKUP(B$4:B$57,I$4:M$57,5,0) -> C | I44: 2100красный | J44: ='Юнит 17'!S40 -> 0 | K44: =J44/J$58 -> 0 | L44: =L43+K44 -> 0.99403579 | M44: =_xlfn.IFS(L44<80%,"A",L44<=95%,"B",L44>95%,"C") -> C
B45: qs001 | C45: ='Юнит 17'!AL19 -> -101.32 | D45: =C45/C$58 -> -0.00073371882 | E45: =E44+D45 -> 1.075546 | F45: =IF(AND(E45<=0),"C",IF(E45<=0.8,"A",IF(E45<=0.95,"B","C"))) -> C | G45: =VLOOKUP(B$4:B$57,I$4:M$57,5,0) -> C | I45: 2104 | J45: ='Юнит 17'!S42 -> 0 | K45: =J45/J$58 -> 0 | L45: =L44+K45 -> 0.99403579 | M45: =_xlfn.IFS(L45<80%,"A",L45<=95%,"B",L45>95%,"C") -> C
B46: 580метал | C46: ='Юнит 17'!AL49 -> -119.80642 | D46: =C46/C$58 -> -0.00086759003 | E46: =E45+D46 -> 1.0746784 | F46: =IF(AND(E46<=0),"C",IF(E46<=0.8,"A",IF(E46<=0.95,"B","C"))) -> C | G46: =VLOOKUP(B$4:B$57,I$4:M$57,5,0) -> C | I46: 6008 | J46: ='Юнит 17'!S43 -> 0 | K46: =J46/J$58 -> 0 | L46: =L45+K46 -> 0.99403579 | M46: =_xlfn.IFS(L46<80%,"A",L46<=95%,"B",L46>95%,"C") -> C
B47: 2100черный | C47: ='Юнит 17'!AL39 -> -129.01419 | D47: =C47/C$58 -> -0.00093426902 | E47: =E46+D47 -> 1.0737442 | F47: =IF(AND(E47<=0),"C",IF(E47<=0.8,"A",IF(E47<=0.95,"B","C"))) -> C | G47: =VLOOKUP(B$4:B$57,I$4:M$57,5,0) -> C | I47: 123черный | J47: ='Юнит 17'!S44 -> 0 | K47: =J47/J$58 -> 0 | L47: =L46+K47 -> 0.99403579 | M47: =_xlfn.IFS(L47<80%,"A",L47<=95%,"B",L47>95%,"C") -> C
B48: qs010 | C48: ='Юнит 17'!AL27 -> -132.02601 | D48: =C48/C$58 -> -0.00095607945 | E48: =E47+D48 -> 1.0727881 | F48: =IF(AND(E48<=0),"C",IF(E48<=0.8,"A",IF(E48<=0.95,"B","C"))) -> C | G48: =VLOOKUP(B$4:B$57,I$4:M$57,5,0) -> C | I48: 123метал | J48: ='Юнит 17'!S45 -> 0 | K48: =J48/J$58 -> 0 | L48: =L47+K48 -> 0.99403579 | M48: =_xlfn.IFS(L48<80%,"A",L48<=95%,"B",L48>95%,"C") -> C
B49: qs012ж | C49: ='Юнит 17'!AL36 -> -133.53648 | D49: =C49/C$58 -> -0.00096701767 | E49: =E48+D49 -> 1.0718211 | F49: =IF(AND(E49<=0),"C",IF(E49<=0.8,"A",IF(E49<=0.95,"B","C"))) -> C | G49: =VLOOKUP(B$4:B$57,I$4:M$57,5,0) -> C | I49: 180ч/б | J49: ='Юнит 17'!S46 -> 0 | K49: =J49/J$58 -> 0 | L49: =L48+K49 -> 0.99403579 | M49: =_xlfn.IFS(L49<80%,"A",L49<=95%,"B",L49>95%,"C") -> C
B50: 180узор | C50: ='Юнит 17'!AL47 -> -156.1125 | D50: =C50/C$58 -> -0.0011305041 | E50: =E49+D50 -> 1.0706906 | F50: =IF(AND(E50<=0),"C",IF(E50<=0.8,"A",IF(E50<=0.95,"B","C"))) -> C | G50: =VLOOKUP(B$4:B$57,I$4:M$57,5,0) -> C | I50: 180узор | J50: ='Юнит 17'!S47 -> 0 | K50: =J50/J$58 -> 0 | L50: =L49+K50 -> 0.99403579 | M50: =_xlfn.IFS(L50<80%,"A",L50<=95%,"B",L50>95%,"C") -> C
B51: qs006 | C51: ='Юнит 17'!AL23 -> -170.57461 | D51: =C51/C$58 -> -0.001235233 | E51: =E50+D51 -> 1.0694553 | F51: =IF(AND(E51<=0),"C",IF(E51<=0.8,"A",IF(E51<=0.95,"B","C"))) -> C | G51: =VLOOKUP(B$4:B$57,I$4:M$57,5,0) -> C | I51: 580черный | J51: ='Юнит 17'!S48 -> 0 | K51: =J51/J$58 -> 0 | L51: =L50+K51 -> 0.99403579 | M51: =_xlfn.IFS(L51<80%,"A",L51<=95%,"B",L51>95%,"C") -> C
B52: 180ч/б | C52: ='Юнит 17'!AL46 -> -204.75446 | D52: =C52/C$58 -> -0.0014827497 | E52: =E51+D52 -> 1.0679726 | F52: =IF(AND(E52<=0),"C",IF(E52<=0.8,"A",IF(E52<=0.95,"B","C"))) -> C | G52: =VLOOKUP(B$4:B$57,I$4:M$57,5,0) -> C | I52: 580метал | J52: ='Юнит 17'!S49 -> 0 | K52: =J52/J$58 -> 0 | L52: =L51+K52 -> 0.99403579 | M52: =_xlfn.IFS(L52<80%,"A",L52<=95%,"B",L52>95%,"C") -> C
B53: MR 1819 корич | C53: ='Юнит 17'!AL11 -> -238.11 | D53: =C53/C$58 -> -0.0017242972 | E53: =E52+D53 -> 1.0662483 | F53: =IF(AND(E53<=0),"C",IF(E53<=0.8,"A",IF(E53<=0.95,"B","C"))) -> C | G53: =VLOOKUP(B$4:B$57,I$4:M$57,5,0) -> C | I53: 2064коричневые | J53: ='Юнит 17'!S51 -> 0 | K53: =J53/J$58 -> 0 | L53: =L52+K53 -> 0.99403579 | M53: =_xlfn.IFS(L53<80%,"A",L53<=95%,"B",L53>95%,"C") -> C
B54: qs013 | C54: ='Юнит 17'!AL30 -> -260.12 | D54: =C54/C$58 -> -0.0018836847 | E54: =E53+D54 -> 1.0643646 | F54: =IF(AND(E54<=0),"C",IF(E54<=0.8,"A",IF(E54<=0.95,"B","C"))) -> C | G54: =VLOOKUP(B$4:B$57,I$4:M$57,5,0) -> C | I54: 2064фиолетовые | J54: ='Юнит 17'!S52 -> 0 | K54: =J54/J$58 -> 0 | L54: =L53+K54 -> 0.99403579 | M54: =_xlfn.IFS(L54<80%,"A",L54<=95%,"B",L54>95%,"C") -> C
B55: qs009 | C55: ='Юнит 17'!AL26 -> -485.96486 | D55: =C55/C$58 -> -0.0035191627 | E55: =E54+D55 -> 1.0608454 | F55: =IF(AND(E55<=0),"C",IF(E55<=0.8,"A",IF(E55<=0.95,"B","C"))) -> C | G55: =VLOOKUP(B$4:B$57,I$4:M$57,5,0) -> C | I55: 2081 | J55: ='Юнит 17'!S53 -> 0 | K55: =J55/J$58 -> 0 | L55: =L54+K55 -> 0.99403579 | M55: =_xlfn.IFS(L55<80%,"A",L55<=95%,"B",L55>95%,"C") -> C
B56: Qs желт Сул | C56: ='Юнит 17'!AL6 -> -2316.6606 | D56: =C56/C$58 -> -0.016776327 | E56: =E55+D56 -> 1.0440691 | F56: =IF(AND(E56<=0),"C",IF(E56<=0.8,"A",IF(E56<=0.95,"B","C"))) -> C | G56: =VLOOKUP(B$4:B$57,I$4:M$57,5,0) -> A | I56: 2084 | J56: ='Юнит 17'!S54 -> 0 | K56: =J56/J$58 -> 0 | L56: =L55+K56 -> 0.99403579 | M56: =_xlfn.IFS(L56<80%,"A",L56<=95%,"B",L56>95%,"C") -> C
B57: Qs син Сул | C57: ='Юнит 17'!AL5 -> -6444.6203 | D57: =C57/C$58 -> -0.046669356 | E57: =E56+D57 -> 0.99739975 | F57: =IF(AND(E57<=0),"C",IF(E57<=0.8,"A",IF(E57<=0.95,"B","C"))) -> C | G57: =VLOOKUP(B$4:B$57,I$4:M$57,5,0) -> B | I57: 8852 | J57: ='Юнит 17'!S56 -> 0 | K57: =J57/J$58 -> 0 | L57: =L56+K57 -> 0.99403579 | M57: =_xlfn.IFS(L57<80%,"A",L57<=95%,"B",L57>95%,"C") -> C
C58: =SUM(C4:C57) -> 138091.05 | D58: =SUM(D4:D44) -> 1.07888 | J58: =SUM(J4:J57) -> 503 | K58: =SUM(K4:K44) -> 1
C61: Прибыль | D61: % прибыль | E61: Доля | F61: ABC прибыль | G61: ABC кол-во | J61: Кол-во | K61: % кол-во | L61: Доля | M61: ABC кол-во
D62: =C62/C$114 -> #DIV/0! | E62: =D62 -> #DIV/0! | F62: =IF(AND(E62<=0),"C",IF(E62<=0.8,"A",IF(E62<=0.95,"B","C"))) -> #DIV/0! | G62: =VLOOKUP(B62:B113,I$62:M$113,5,0) -> #N/A | K62: =J62/J$114 -> #DIV/0! | L62: =K62 -> #DIV/0! | M62: =_xlfn.IFS(L62<80%,"A",L62<=95%,"B",L62>95%,"C") -> #DIV/0!
D63: =C63/C$114 -> #DIV/0! | E63: =D63+E62 -> #DIV/0! | F63: =IF(AND(E63<=0),"C",IF(E63<=0.8,"A",IF(E63<=0.95,"B","C"))) -> #DIV/0! | G63: =VLOOKUP(B63:B114,I$62:M$113,5,0) -> #N/A | K63: =J63/J$114 -> #DIV/0! | L63: =K63+L62 -> #DIV/0! | M63: =_xlfn.IFS(L63<80%,"A",L63<=95%,"B",L63>95%,"C") -> #DIV/0!
D64: =C64/C$114 -> #DIV/0! | E64: =D64+E63 -> #DIV/0! | F64: =IF(AND(E64<=0),"C",IF(E64<=0.8,"A",IF(E64<=0.95,"B","C"))) -> #DIV/0! | G64: =VLOOKUP(B64:B115,I$62:M$113,5,0) -> #N/A | K64: =J64/J$114 -> #DIV/0! | L64: =K64+L63 -> #DIV/0! | M64: =_xlfn.IFS(L64<80%,"A",L64<=95%,"B",L64>95%,"C") -> #DIV/0!
D65: =C65/C$114 -> #DIV/0! | E65: =D65+E64 -> #DIV/0! | F65: =IF(AND(E65<=0),"C",IF(E65<=0.8,"A",IF(E65<=0.95,"B","C"))) -> #DIV/0! | G65: =VLOOKUP(B65:B116,I$62:M$113,5,0) -> #N/A | K65: =J65/J$114 -> #DIV/0! | L65: =K65+L64 -> #DIV/0! | M65: =_xlfn.IFS(L65<80%,"A",L65<=95%,"B",L65>95%,"C") -> #DIV/0!
D66: =C66/C$114 -> #DIV/0! | E66: =D66+E65 -> #DIV/0! | F66: =IF(AND(E66<=0),"C",IF(E66<=0.8,"A",IF(E66<=0.95,"B","C"))) -> #DIV/0! | G66: =VLOOKUP(B66:B117,I$62:M$113,5,0) -> #N/A | K66: =J66/J$114 -> #DIV/0! | L66: =K66+L65 -> #DIV/0! | M66: =_xlfn.IFS(L66<80%,"A",L66<=95%,"B",L66>95%,"C") -> #DIV/0!
D67: =C67/C$114 -> #DIV/0! | E67: =D67+E66 -> #DIV/0! | F67: =IF(AND(E67<=0),"C",IF(E67<=0.8,"A",IF(E67<=0.95,"B","C"))) -> #DIV/0! | G67: =VLOOKUP(B67:B118,I$62:M$113,5,0) -> #N/A | K67: =J67/J$114 -> #DIV/0! | L67: =K67+L66 -> #DIV/0! | M67: =_xlfn.IFS(L67<80%,"A",L67<=95%,"B",L67>95%,"C") -> #DIV/0!
D68: =C68/C$114 -> #DIV/0! | E68: =D68+E67 -> #DIV/0! | F68: =IF(AND(E68<=0),"C",IF(E68<=0.8,"A",IF(E68<=0.95,"B","C"))) -> #DIV/0! | G68: =VLOOKUP(B68:B119,I$62:M$113,5,0) -> #N/A | K68: =J68/J$114 -> #DIV/0! | L68: =K68+L67 -> #DIV/0! | M68: =_xlfn.IFS(L68<80%,"A",L68<=95%,"B",L68>95%,"C") -> #DIV/0!
D69: =C69/C$114 -> #DIV/0! | E69: =D69+E68 -> #DIV/0! | F69: =IF(AND(E69<=0),"C",IF(E69<=0.8,"A",IF(E69<=0.95,"B","C"))) -> #DIV/0! | G69: =VLOOKUP(B69:B120,I$62:M$113,5,0) -> #N/A | K69: =J69/J$114 -> #DIV/0! | L69: =K69+L68 -> #DIV/0! | M69: =_xlfn.IFS(L69<80%,"A",L69<=95%,"B",L69>95%,"C") -> #DIV/0!
D70: =C70/C$114 -> #DIV/0! | E70: =D70+E69 -> #DIV/0! | F70: =IF(AND(E70<=0),"C",IF(E70<=0.8,"A",IF(E70<=0.95,"B","C"))) -> #DIV/0! | G70: =VLOOKUP(B70:B121,I$62:M$113,5,0) -> #N/A | K70: =J70/J$114 -> #DIV/0! | L70: =K70+L69 -> #DIV/0! | M70: =_xlfn.IFS(L70<80%,"A",L70<=95%,"B",L70>95%,"C") -> #DIV/0!
D71: =C71/C$114 -> #DIV/0! | E71: =D71+E70 -> #DIV/0! | F71: =IF(AND(E71<=0),"C",IF(E71<=0.8,"A",IF(E71<=0.95,"B","C"))) -> #DIV/0! | G71: =VLOOKUP(B71:B122,I$62:M$113,5,0) -> #N/A | K71: =J71/J$114 -> #DIV/0! | L71: =K71+L70 -> #DIV/0! | M71: =_xlfn.IFS(L71<80%,"A",L71<=95%,"B",L71>95%,"C") -> #DIV/0!
D72: =C72/C$114 -> #DIV/0! | E72: =D72+E71 -> #DIV/0! | F72: =IF(AND(E72<=0),"C",IF(E72<=0.8,"A",IF(E72<=0.95,"B","C"))) -> #DIV/0! | G72: =VLOOKUP(B72:B123,I$62:M$113,5,0) -> #N/A | K72: =J72/J$114 -> #DIV/0! | L72: =K72+L71 -> #DIV/0! | M72: =_xlfn.IFS(L72<80%,"A",L72<=95%,"B",L72>95%,"C") -> #DIV/0!
D73: =C73/C$114 -> #DIV/0! | E73: =D73+E72 -> #DIV/0! | F73: =IF(AND(E73<=0),"C",IF(E73<=0.8,"A",IF(E73<=0.95,"B","C"))) -> #DIV/0! | G73: =VLOOKUP(B73:B124,I$62:M$113,5,0) -> #N/A | K73: =J73/J$114 -> #DIV/0! | L73: =K73+L72 -> #DIV/0! | M73: =_xlfn.IFS(L73<80%,"A",L73<=95%,"B",L73>95%,"C") -> #DIV/0!
D74: =C74/C$114 -> #DIV/0! | E74: =D74+E73 -> #DIV/0! | F74: =IF(AND(E74<=0),"C",IF(E74<=0.8,"A",IF(E74<=0.95,"B","C"))) -> #DIV/0! | G74: =VLOOKUP(B74:B125,I$62:M$113,5,0) -> #N/A | K74: =J74/J$114 -> #DIV/0! | L74: =K74+L73 -> #DIV/0! | M74: =_xlfn.IFS(L74<80%,"A",L74<=95%,"B",L74>95%,"C") -> #DIV/0!
... D113: =C113/C$114 -> #DIV/0! | E113: =D113+E112 -> #DIV/0! | F113: =IF(AND(E113<=0),"C",IF(E113<=0.8,"A",IF(E113<=0.95,"B","C"))) -> #DIV/0! | G113: =VLOOKUP(B113:B164,I$62:M$113,5,0) -> #N/A | K113: =J113/J$114 -> #DIV/0! | L113: =K113+L112 -> #DIV/0! | M113: =_xlfn.IFS(L113<80%,"A",L113<=95%,"B",L113>95%,"C") -> #DIV/0!
C114: =SUM(C62:C113) -> 0 | D114: =SUM(D62:D113) -> #DIV/0! | J114: =SUM(J62:J113) -> 0 | K114: =SUM(K62:K113) -> #DIV/0!

Sheet АВС 16
B2: ОЧКИ
C3: Прибыль | D3: % прибыль | E3: Доля | F3: ABC прибыль | G3: ABC кол-во | J3: Кол-во | K3: % кол-во | L3: Доля | M3: ABC кол-во
B4: Qs черн Сул | C4: ='Юнит 16'!AL4 -> 69347.354 | D4: =C4/C$58 -> 0.37584045 | E4: =D4 -> 0.37584045 | F4: =IF(AND(E4<=0),"C",IF(E4<=0.8,"A",IF(E4<=0.95,"B","C"))) -> A | G4: =VLOOKUP(B$4:B$57,I$4:M$57,5,0) -> A | I4: Qs черн Сул | J4: ='Юнит 16'!S4 -> 257 | K4: =J4/J$58 -> 0.40858506 | L4: =K4 -> 0.40858506 | M4: =_xlfn.IFS(L4<80%,"A",L4<=95%,"B",L4>95%,"C") -> A | P4: A | Q4: 0.8
B5: Черные с железкой Сул | C5: ='Юнит 16'!AL3 -> 39632.068 | D5: =C5/C$58 -> 0.21479311 | E5: =E4+D5 -> 0.59063357 | F5: =IF(AND(E5<=0),"C",IF(E5<=0.8,"A",IF(E5<=0.95,"B","C"))) -> A | G5: =VLOOKUP(B$4:B$57,I$4:M$57,5,0) -> A | I5: Черные с железкой Сул | J5: ='Юнит 16'!S3 -> 121 | K5: =J5/J$58 -> 0.19236884 | L5: =L4+K5 -> 0.6009539 | M5: =_xlfn.IFS(L5<80%,"A",L5<=95%,"B",L5>95%,"C") -> A | P5: B | Q5: 0.15
B6: flip желтые Сул | C6: ='Юнит 16'!AL8 -> 13088.703 | D6: =C6/C$58 -> 0.070936581 | E6: =E5+D6 -> 0.66157015 | F6: =IF(AND(E6<=0),"C",IF(E6<=0.8,"A",IF(E6<=0.95,"B","C"))) -> A | G6: =VLOOKUP(B$4:B$57,I$4:M$57,5,0) -> A | I6: flip желтые Сул | J6: ='Юнит 16'!S8 -> 35 | K6: =J6/J$58 -> 0.055643879 | L6: =L5+K6 -> 0.65659777 | M6: =_xlfn.IFS(L6<80%,"A",L6<=95%,"B",L6>95%,"C") -> A | P6: C | Q6: 0.05
B7: Qs желт Сул | C7: ='Юнит 16'!AL6 -> 10718.667 | D7: =C7/C$58 -> 0.058091743 | E7: =E6+D7 -> 0.71966189 | F7: =IF(AND(E7<=0),"C",IF(E7<=0.8,"A",IF(E7<=0.95,"B","C"))) -> A | G7: =VLOOKUP(B$4:B$57,I$4:M$57,5,0) -> A | I7: Qs син Сул | J7: ='Юнит 16'!S5 -> 34 | K7: =J7/J$58 -> 0.054054054 | L7: =L6+K7 -> 0.71065183 | M7: =_xlfn.IFS(L7<80%,"A",L7<=95%,"B",L7>95%,"C") -> A
B8: qs002 | C8: ='Юнит 16'!AL20 -> 7152.7839 | D8: =C8/C$58 -> 0.038765798 | E8: =E7+D8 -> 0.75842769 | F8: =IF(AND(E8<=0),"C",IF(E8<=0.8,"A",IF(E8<=0.95,"B","C"))) -> A | G8: =VLOOKUP(B$4:B$57,I$4:M$57,5,0) -> B | I8: Qs желт Сул | J8: ='Юнит 16'!S6 -> 27 | K8: =J8/J$58 -> 0.042925278 | L8: =L7+K8 -> 0.75357711 | M8: =_xlfn.IFS(L8<80%,"A",L8<=95%,"B",L8>95%,"C") -> A
B9: MR8854 C2 Сул | C9: ='Юнит 16'!AL9 -> 5884.2321 | D9: =C9/C$58 -> 0.031890654 | E9: =E8+D9 -> 0.79031834 | F9: =IF(AND(E9<=0),"C",IF(E9<=0.8,"A",IF(E9<=0.95,"B","C"))) -> A | G9: =VLOOKUP(B$4:B$57,I$4:M$57,5,0) -> B | I9: MR 1890 желт | J9: ='Юнит 16'!S17 -> 18 | K9: =J9/J$58 -> 0.028616852 | L9: =L8+K9 -> 0.78219396 | M9: =_xlfn.IFS(L9<80%,"A",L9<=95%,"B",L9>95%,"C") -> A
B10: Qs син Сул | C10: ='Юнит 16'!AL5 -> 5206.7614 | D10: =C10/C$58 -> 0.028218979 | E10: =E9+D10 -> 0.81853732 | F10: =IF(AND(E10<=0),"C",IF(E10<=0.8,"A",IF(E10<=0.95,"B","C"))) -> B | G10: =VLOOKUP(B$4:B$57,I$4:M$57,5,0) -> A | I10: MR 1890 черн | J10: ='Юнит 16'!S16 -> 15 | K10: =J10/J$58 -> 0.023847377 | L10: =L9+K10 -> 0.80604134 | M10: =_xlfn.IFS(L10<80%,"A",L10<=95%,"B",L10>95%,"C") -> B
B11: MR 1890 корич | C11: ='Юнит 16'!AL18 -> 4543.0409 | D11: =C11/C$58 -> 0.024621827 | E11: =E10+D11 -> 0.84315915 | F11: =IF(AND(E11<=0),"C",IF(E11<=0.8,"A",IF(E11<=0.95,"B","C"))) -> B | G11: =VLOOKUP(B$4:B$57,I$4:M$57,5,0) -> B | I11: MR 1890 корич | J11: ='Юнит 16'!S18 -> 12 | K11: =J11/J$58 -> 0.019077901 | L11: =L10+K11 -> 0.82511924 | M11: =_xlfn.IFS(L11<80%,"A",L11<=95%,"B",L11>95%,"C") -> B
B12: MR 1890 черн | C12: ='Юнит 16'!AL16 -> 4466.6602 | D12: =C12/C$58 -> 0.024207868 | E12: =E11+D12 -> 0.86736702 | F12: =IF(AND(E12<=0),"C",IF(E12<=0.8,"A",IF(E12<=0.95,"B","C"))) -> B | G12: =VLOOKUP(B$4:B$57,I$4:M$57,5,0) -> B | I12: qs002 | J12: ='Юнит 16'!S20 -> 12 | K12: =J12/J$58 -> 0.019077901 | L12: =L11+K12 -> 0.84419714 | M12: =_xlfn.IFS(L12<80%,"A",L12<=95%,"B",L12>95%,"C") -> B
B13: qs006 | C13: ='Юнит 16'!AL23 -> 3416.98 | D13: =C13/C$58 -> 0.018518937 | E13: =E12+D13 -> 0.88588595 | F13: =IF(AND(E13<=0),"C",IF(E13<=0.8,"A",IF(E13<=0.95,"B","C"))) -> B | G13: =VLOOKUP(B$4:B$57,I$4:M$57,5,0) -> B | I13: flip черные Сул | J13: ='Юнит 16'!S7 -> 11 | K13: =J13/J$58 -> 0.017488076 | L13: =L12+K13 -> 0.86168521 | M13: =_xlfn.IFS(L13<80%,"A",L13<=95%,"B",L13>95%,"C") -> B
B14: qs007 | C14: ='Юнит 16'!AL24 -> 3385.4726 | D14: =C14/C$58 -> 0.018348178 | E14: =E13+D14 -> 0.90423413 | F14: =IF(AND(E14<=0),"C",IF(E14<=0.8,"A",IF(E14<=0.95,"B","C"))) -> B | G14: =VLOOKUP(B$4:B$57,I$4:M$57,5,0) -> B | I14: MR8854 C2 Сул | J14: ='Юнит 16'!S9 -> 11 | K14: =J14/J$58 -> 0.017488076 | L14: =L13+K14 -> 0.87917329 | M14: =_xlfn.IFS(L14<80%,"A",L14<=95%,"B",L14>95%,"C") -> B
B15: MR 1890 желт | C15: ='Юнит 16'!AL17 -> 2822.2115 | D15: =C15/C$58 -> 0.015295482 | E15: =E14+D15 -> 0.91952961 | F15: =IF(AND(E15<=0),"C",IF(E15<=0.8,"A",IF(E15<=0.95,"B","C"))) -> B | G15: =VLOOKUP(B$4:B$57,I$4:M$57,5,0) -> A | I15: qs007 | J15: ='Юнит 16'!S24 -> 9 | K15: =J15/J$58 -> 0.014308426 | L15: =L14+K15 -> 0.89348172 | M15: =_xlfn.IFS(L15<80%,"A",L15<=95%,"B",L15>95%,"C") -> B
B16: qs013 | C16: ='Юнит 16'!AL30 -> 2780.7624 | D16: =C16/C$58 -> 0.015070842 | E16: =E15+D16 -> 0.93460046 | F16: =IF(AND(E16<=0),"C",IF(E16<=0.8,"A",IF(E16<=0.95,"B","C"))) -> B | G16: =VLOOKUP(B$4:B$57,I$4:M$57,5,0) -> B | I16: qs006 | J16: ='Юнит 16'!S23 -> 8 | K16: =J16/J$58 -> 0.012718601 | L16: =L15+K16 -> 0.90620032 | M16: =_xlfn.IFS(L16<80%,"A",L16<=95%,"B",L16>95%,"C") -> B
B17: 2100черный | C17: ='Юнит 16'!AL39 -> 2749.068 | D17: =C17/C$58 -> 0.014899068 | E17: =E16+D17 -> 0.94949952 | F17: =IF(AND(E17<=0),"C",IF(E17<=0.8,"A",IF(E17<=0.95,"B","C"))) -> B | G17: =VLOOKUP(B$4:B$57,I$4:M$57,5,0) -> B | I17: MR Р1886 черн | J17: ='Юнит 16'!S14 -> 6 | K17: =J17/J$58 -> 0.0095389507 | L17: =L16+K17 -> 0.91573927 | M17: =_xlfn.IFS(L17<80%,"A",L17<=95%,"B",L17>95%,"C") -> B
B18: MR Р1886 черн | C18: ='Юнит 16'!AL14 -> 2397.7496 | D18: =C18/C$58 -> 0.012995035 | E18: =E17+D18 -> 0.96249456 | F18: =IF(AND(E18<=0),"C",IF(E18<=0.8,"A",IF(E18<=0.95,"B","C"))) -> C | G18: =VLOOKUP(B$4:B$57,I$4:M$57,5,0) -> B | I18: 2100черный | J18: ='Юнит 16'!S39 -> 6 | K18: =J18/J$58 -> 0.0095389507 | L18: =L17+K18 -> 0.92527822 | M18: =_xlfn.IFS(L18<80%,"A",L18<=95%,"B",L18>95%,"C") -> B
B19: 180ч/б | C19: ='Юнит 16'!AL46 -> 1766.8723 | D19: =C19/C$58 -> 0.009575882 | E19: =E18+D19 -> 0.97207044 | F19: =IF(AND(E19<=0),"C",IF(E19<=0.8,"A",IF(E19<=0.95,"B","C"))) -> C | G19: =VLOOKUP(B$4:B$57,I$4:M$57,5,0) -> C | I19: qs013 | J19: ='Юнит 16'!S30 -> 5 | K19: =J19/J$58 -> 0.0079491256 | L19: =L18+K19 -> 0.93322734 | M19: =_xlfn.IFS(L19<80%,"A",L19<=95%,"B",L19>95%,"C") -> B
B20: flip черные Сул | C20: ='Юнит 16'!AL7 -> 1597.217 | D20: =C20/C$58 -> 0.0086564046 | E20: =E19+D20 -> 0.98072685 | F20: =IF(AND(E20<=0),"C",IF(E20<=0.8,"A",IF(E20<=0.95,"B","C"))) -> C | G20: =VLOOKUP(B$4:B$57,I$4:M$57,5,0) -> B | I20: 580метал | J20: ='Юнит 16'!S49 -> 5 | K20: =J20/J$58 -> 0.0079491256 | L20: =L19+K20 -> 0.94117647 | M20: =_xlfn.IFS(L20<80%,"A",L20<=95%,"B",L20>95%,"C") -> B
B21: 2038ч/б | C21: ='Юнит 16'!AL37 -> 1513.211 | D21: =C21/C$58 -> 0.008201119 | E21: =E20+D21 -> 0.98892797 | F21: =IF(AND(E21<=0),"C",IF(E21<=0.8,"A",IF(E21<=0.95,"B","C"))) -> C | G21: =VLOOKUP(B$4:B$57,I$4:M$57,5,0) -> C | I21: qs009 | J21: ='Юнит 16'!S26 -> 4 | K21: =J21/J$58 -> 0.0063593005 | L21: =L20+K21 -> 0.94753577 | M21: =_xlfn.IFS(L21<80%,"A",L21<=95%,"B",L21>95%,"C") -> B
B22: 2064фиолетовые | C22: ='Юнит 16'!AL52 -> 812.64028 | D22: =C22/C$58 -> 0.0044042501 | E22: =E21+D22 -> 0.99333222 | F22: =IF(AND(E22<=0),"C",IF(E22<=0.8,"A",IF(E22<=0.95,"B","C"))) -> C | G22: =VLOOKUP(B$4:B$57,I$4:M$57,5,0) -> C | I22: 2038ч/б | J22: ='Юнит 16'!S37 -> 4 | K22: =J22/J$58 -> 0.0063593005 | L22: =L21+K22 -> 0.95389507 | M22: =_xlfn.IFS(L22<80%,"A",L22<=95%,"B",L22>95%,"C") -> C
B23: qs011ж | C23: ='Юнит 16'!AL35 -> 642.71862 | D23: =C23/C$58 -> 0.0034833291 | E23: =E22+D23 -> 0.99681554 | F23: =IF(AND(E23<=0),"C",IF(E23<=0.8,"A",IF(E23<=0.95,"B","C"))) -> C | G23: =VLOOKUP(B$4:B$57,I$4:M$57,5,0) -> C | I23: 180ч/б | J23: ='Юнит 16'!S46 -> 3 | K23: =J23/J$58 -> 0.0047694754 | L23: =L22+K23 -> 0.95866455 | M23: =_xlfn.IFS(L23<80%,"A",L23<=95%,"B",L23>95%,"C") -> C
B24: MR 1819 черн | C24: ='Юнит 16'!AL10 -> 622.28332 | D24: =C24/C$58 -> 0.0033725763 | E24: =E23+D24 -> 1.0001881 | F24: =IF(AND(E24<=0),"C",IF(E24<=0.8,"A",IF(E24<=0.95,"B","C"))) -> C | G24: =VLOOKUP(B$4:B$57,I$4:M$57,5,0) -> C | I24: 2084 (+1.75) | J24: ='Юнит 16'!S55 -> 3 | K24: =J24/J$58 -> 0.0047694754 | L24: =L23+K24 -> 0.96343402 | M24: =_xlfn.IFS(L24<80%,"A",L24<=95%,"B",L24>95%,"C") -> C
B25: 2064коричневые | C25: ='Юнит 16'!AL51 -> 457.70328 | D25: =C25/C$58 -> 0.0024806052 | E25: =E24+D25 -> 1.0026687 | F25: =IF(AND(E25<=0),"C",IF(E25<=0.8,"A",IF(E25<=0.95,"B","C"))) -> C | G25: =VLOOKUP(B$4:B$57,I$4:M$57,5,0) -> C | I25: MR 1819 черн | J25: ='Юнит 16'!S10 -> 2 | K25: =J25/J$58 -> 0.0031796502 | L25: =L24+K25 -> 0.96661367 | M25: =_xlfn.IFS(L25<80%,"A",L25<=95%,"B",L25>95%,"C") -> C
B26: qs008 | C26: ='Юнит 16'!AL25 -> 425.98025 | D26: =C26/C$58 -> 0.0023086765 | E26: =E25+D26 -> 1.0049774 | F26: =IF(AND(E26<=0),"C",IF(E26<=0.8,"A",IF(E26<=0.95,"B","C"))) -> C | G26: =VLOOKUP(B$4:B$57,I$4:M$57,5,0) -> C | I26: qs008 | J26: ='Юнит 16'!S25 -> 2 | K26: =J26/J$58 -> 0.0031796502 | L26: =L25+K26 -> 0.96979332 | M26: =_xlfn.IFS(L26<80%,"A",L26<=95%,"B",L26>95%,"C") -> C
B27: MR Р1886 корич | C27: ='Юнит 16'!AL15 -> 412.53 | D27: =C27/C$58 -> 0.0022357805 | E27: =E26+D27 -> 1.0072132 | F27: =IF(AND(E27<=0),"C",IF(E27<=0.8,"A",IF(E27<=0.95,"B","C"))) -> C | G27: =VLOOKUP(B$4:B$57,I$4:M$57,5,0) -> C | I27: qs010ж | J27: ='Юнит 16'!S34 -> 2 | K27: =J27/J$58 -> 0.0031796502 | L27: =L26+K27 -> 0.97297297 | M27: =_xlfn.IFS(L27<80%,"A",L27<=95%,"B",L27>95%,"C") -> C
B28: 2100фиолетовый | C28: ='Юнит 16'!AL41 -> 400.49933 | D28: =C28/C$58 -> 0.0021705781 | E28: =E24+D28 -> 1.0023587 | F28: =IF(AND(E28<=0),"C",IF(E28<=0.8,"A",IF(E28<=0.95,"B","C"))) -> C | G28: =VLOOKUP(B$4:B$57,I$4:M$57,5,0) -> C | I28: qs011ж | J28: ='Юнит 16'!S35 -> 2 | K28: =J28/J$58 -> 0.0031796502 | L28: =L24+K28 -> 0.96661367 | M28: =_xlfn.IFS(L28<80%,"A",L28<=95%,"B",L28>95%,"C") -> C
B29: qs011 | C29: ='Юнит 16'!AL28 -> 400.42 | D29: =C29/C$58 -> 0.0021701482 | E29: =E28+D29 -> 1.0045288 | F29: =IF(AND(E29<=0),"C",IF(E29<=0.8,"A",IF(E29<=0.95,"B","C"))) -> C | G29: =VLOOKUP(B$4:B$57,I$4:M$57,5,0) -> C | I29: 2064фиолетовые | J29: ='Юнит 16'!S52 -> 2 | K29: =J29/J$58 -> 0.0031796502 | L29: =L28+K29 -> 0.96979332 | M29: =_xlfn.IFS(L29<80%,"A",L29<=95%,"B",L29>95%,"C") -> C
B30: qs012ж | C30: ='Юнит 16'!AL36 -> 337.90162 | D30: =C30/C$58 -> 0.0018313186 | E30: =E29+D30 -> 1.0063602 | F30: =IF(AND(E30<=0),"C",IF(E30<=0.8,"A",IF(E30<=0.95,"B","C"))) -> C | G30: =VLOOKUP(B$4:B$57,I$4:M$57,5,0) -> C | I30: MR 1819 корич | J30: ='Юнит 16'!S11 -> 1 | K30: =J30/J$58 -> 0.0015898251 | L30: =L29+K30 -> 0.97138315 | M30: =_xlfn.IFS(L30<80%,"A",L30<=95%,"B",L30>95%,"C") -> C
B31: 2038красный | C31: ='Юнит 16'!AL38 -> 278.54332 | D31: =C31/C$58 -> 0.0015096156 | E31: =E30+D31 -> 1.0078698 | F31: =IF(AND(E31<=0),"C",IF(E31<=0.8,"A",IF(E31<=0.95,"B","C"))) -> C | G31: =VLOOKUP(B$4:B$57,I$4:M$57,5,0) -> C | I31: MR Р1874 черн | J31: ='Юнит 16'!S12 -> 1 | K31: =J31/J$58 -> 0.0015898251 | L31: =L30+K31 -> 0.97297297 | M31: =_xlfn.IFS(L31<80%,"A",L31<=95%,"B",L31>95%,"C") -> C
B32: 180узор | C32: ='Юнит 16'!AL47 -> 261.10629 | D32: =C32/C$58 -> 0.0014151125 | E32: =E31+D32 -> 1.0092849 | F32: =IF(AND(E32<=0),"C",IF(E32<=0.8,"A",IF(E32<=0.95,"B","C"))) -> C | G32: =VLOOKUP(B$4:B$57,I$4:M$57,5,0) -> C | I32: MR Р1886 корич | J32: ='Юнит 16'!S15 -> 1 | K32: =J32/J$58 -> 0.0015898251 | L32: =L31+K32 -> 0.9745628 | M32: =_xlfn.IFS(L32<80%,"A",L32<=95%,"B",L32>95%,"C") -> C
B33: qs009 | C33: ='Юнит 16'!AL26 -> 231.73092 | D33: =C33/C$58 -> 0.0012559074 | E33: =E32+D33 -> 1.0105408 | F33: =IF(AND(E33<=0),"C",IF(E33<=0.8,"A",IF(E33<=0.95,"B","C"))) -> C | G33: =VLOOKUP(B$4:B$57,I$4:M$57,5,0) -> B | I33: qs005 | J33: ='Юнит 16'!S22 -> 1 | K33: =J33/J$58 -> 0.0015898251 | L33: =L32+K33 -> 0.97615262 | M33: =_xlfn.IFS(L33<80%,"A",L33<=95%,"B",L33>95%,"C") -> C
B34: MR Р1874 черн | C34: ='Юнит 16'!AL12 -> 219.37233 | D34: =C34/C$58 -> 0.0011889278 | E34: =E33+D34 -> 1.0117297 | F34: =IF(AND(E34<=0),"C",IF(E34<=0.8,"A",IF(E34<=0.95,"B","C"))) -> C | G34: =VLOOKUP(B$4:B$57,I$4:M$57,5,0) -> C | I34: qs011 | J34: ='Юнит 16'!S28 -> 1 | K34: =J34/J$58 -> 0.0015898251 | L34: =L33+K34 -> 0.97774245 | M34: =_xlfn.IFS(L34<80%,"A",L34<=95%,"B",L34>95%,"C") -> C
B35: qs014 | C35: ='Юнит 16'!AL31 -> 199.29933 | D35: =C35/C$58 -> 0.0010801385 | E35: =E34+D35 -> 1.0128099 | F35: =IF(AND(E35<=0),"C",IF(E35<=0.8,"A",IF(E35<=0.95,"B","C"))) -> C | G35: =VLOOKUP(B$4:B$57,I$4:M$57,5,0) -> C | I35: qs014 | J35: ='Юнит 16'!S31 -> 1 | K35: =J35/J$58 -> 0.0015898251 | L35: =L34+K35 -> 0.97933227 | M35: =_xlfn.IFS(L35<80%,"A",L35<=95%,"B",L35>95%,"C") -> C
B36: MR 1819 корич | C36: ='Юнит 16'!AL11 -> 143.75233 | D36: =C36/C$58 -> 0.00077909161 | E36: =E35+D36 -> 1.013589 | F36: =IF(AND(E36<=0),"C",IF(E36<=0.8,"A",IF(E36<=0.95,"B","C"))) -> C | G36: =VLOOKUP(B$4:B$57,I$4:M$57,5,0) -> C | I36: qs015 | J36: ='Юнит 16'!S32 -> 1 | K36: =J36/J$58 -> 0.0015898251 | L36: =L35+K36 -> 0.9809221 | M36: =_xlfn.IFS(L36<80%,"A",L36<=95%,"B",L36>95%,"C") -> C
B37: qs005 | C37: ='Юнит 16'!AL22 -> 61.494592 | D37: =C37/C$58 -> 0.00033328099 | E37: =E36+D37 -> 1.0139222 | F37: =IF(AND(E37<=0),"C",IF(E37<=0.8,"A",IF(E37<=0.95,"B","C"))) -> C | G37: =VLOOKUP(B$4:B$57,I$4:M$57,5,0) -> C | I37: qs012ж | J37: ='Юнит 16'!S36 -> 1 | K37: =J37/J$58 -> 0.0015898251 | L37: =L36+K37 -> 0.98251192 | M37: =_xlfn.IFS(L37<80%,"A",L37<=95%,"B",L37>95%,"C") -> C
B38: MR Р1874 корич | C38: ='Юнит 16'!AL13 -> 0 | D38: =C38/C$58 -> 0 | E38: =E37+D38 -> 1.0139222 | F38: =IF(AND(E38<=0),"C",IF(E38<=0.8,"A",IF(E38<=0.95,"B","C"))) -> C | G38: =VLOOKUP(B$4:B$57,I$4:M$57,5,0) -> C | I38: 2038красный | J38: ='Юнит 16'!S38 -> 1 | K38: =J38/J$58 -> 0.0015898251 | L38: =L37+K38 -> 0.98410175 | M38: =_xlfn.IFS(L38<80%,"A",L38<=95%,"B",L38>95%,"C") -> C
B39: qs001 Ж | C39: ='Юнит 16'!AL33 -> 0 | D39: =C39/C$58 -> 0 | E39: =E38+D39 -> 1.0139222 | F39: =IF(AND(E39<=0),"C",IF(E39<=0.8,"A",IF(E39<=0.95,"B","C"))) -> C | G39: =VLOOKUP(B$4:B$57,I$4:M$57,5,0) -> C | I39: 2100фиолетовый | J39: ='Юнит 16'!S41 -> 1 | K39: =J39/J$58 -> 0.0015898251 | L39: =L38+K39 -> 0.98569157 | M39: =_xlfn.IFS(L39<80%,"A",L39<=95%,"B",L39>95%,"C") -> C
B40: qs012 | C40: ='Юнит 16'!AL29 -> -0.98766788 | D40: =C40/C$58 -> -5.3528436e-06 | E40: =E39+D40 -> 1.0139169 | F40: =IF(AND(E40<=0),"C",IF(E40<=0.8,"A",IF(E40<=0.95,"B","C"))) -> C | G40: =VLOOKUP(B$4:B$57,I$4:M$57,5,0) -> C | I40: 123метал | J40: ='Юнит 16'!S45 -> 1 | K40: =J40/J$58 -> 0.0015898251 | L40: =L39+K40 -> 0.9872814 | M40: =_xlfn.IFS(L40<80%,"A",L40<=95%,"B",L40>95%,"C") -> C
B41: 2104 | C41: ='Юнит 16'!AL42 -> -7.901343 | D41: =C41/C$58 -> -4.2822749e-05 | E41: =E40+D41 -> 1.0138741 | F41: =IF(AND(E41<=0),"C",IF(E41<=0.8,"A",IF(E41<=0.95,"B","C"))) -> C | G41: =VLOOKUP(B$4:B$57,I$4:M$57,5,0) -> C | I41: 180узор | J41: ='Юнит 16'!S47 -> 1 | K41: =J41/J$58 -> 0.0015898251 | L41: =L40+K41 -> 0.98887122 | M41: =_xlfn.IFS(L41<80%,"A",L41<=95%,"B",L41>95%,"C") -> C
B42: 2084 | C42: ='Юнит 16'!AL54 -> -13.82735 | D42: =C42/C$58 -> -7.493981e-05 | E42: =E41+D42 -> 1.0137991 | F42: =IF(AND(E42<=0),"C",IF(E42<=0.8,"A",IF(E42<=0.95,"B","C"))) -> C | G42: =VLOOKUP(B$4:B$57,I$4:M$57,5,0) -> C | I42: 2064коричневые | J42: ='Юнит 16'!S51 -> 1 | K42: =J42/J$58 -> 0.0015898251 | L42: =L41+K42 -> 0.99046105 | M42: =_xlfn.IFS(L42<80%,"A",L42<=95%,"B",L42>95%,"C") -> C
B43: 2064ч/б | C43: ='Юнит 16'!AL50 -> -17.778022 | D43: =C43/C$58 -> -9.6351185e-05 | E43: =E42+D43 -> 1.0137028 | F43: =IF(AND(E43<=0),"C",IF(E43<=0.8,"A",IF(E43<=0.95,"B","C"))) -> C | G43: =VLOOKUP(B$4:B$57,I$4:M$57,5,0) -> C | I43: MR Р1874 корич | J43: ='Юнит 16'!S13 -> 0 | K43: =J43/J$58 -> 0 | L43: =L42+K43 -> 0.99046105 | M43: =_xlfn.IFS(L43<80%,"A",L43<=95%,"B",L43>95%,"C") -> C
B44: qs010ж | C44: ='Юнит 16'!AL34 -> -23.665465 | D44: =C44/C$58 -> -0.00012825924 | E44: =E43+D44 -> 1.0135745 | F44: =IF(AND(E44<=0),"C",IF(E44<=0.8,"A",IF(E44<=0.95,"B","C"))) -> C | G44: =VLOOKUP(B$4:B$57,I$4:M$57,5,0) -> C | I44: qs001 | J44: ='Юнит 16'!S19 -> 0 | K44: =J44/J$58 -> 0 | L44: =L43+K44 -> 0.99046105 | M44: =_xlfn.IFS(L44<80%,"A",L44<=95%,"B",L44>95%,"C") -> C
B45: 123метал | C45: ='Юнит 16'!AL45 -> -33.418376 | D45: =C45/C$58 -> -0.00018111689 | E45: =E44+D45 -> 1.0133934 | F45: =IF(AND(E45<=0),"C",IF(E45<=0.8,"A",IF(E45<=0.95,"B","C"))) -> C | G45: =VLOOKUP(B$4:B$57,I$4:M$57,5,0) -> C | I45: qs003 | J45: ='Юнит 16'!S21 -> 0 | K45: =J45/J$58 -> 0 | L45: =L44+K45 -> 0.99046105 | M45: =_xlfn.IFS(L45<80%,"A",L45<=95%,"B",L45>95%,"C") -> C
B46: 123черный | C46: ='Юнит 16'!AL44 -> -38.519047 | D46: =C46/C$58 -> -0.0002087609 | E46: =E45+D46 -> 1.0131846 | F46: =IF(AND(E46<=0),"C",IF(E46<=0.8,"A",IF(E46<=0.95,"B","C"))) -> C | G46: =VLOOKUP(B$4:B$57,I$4:M$57,5,0) -> C | I46: qs010 | J46: ='Юнит 16'!S27 -> 0 | K46: =J46/J$58 -> 0 | L46: =L45+K46 -> 0.99046105 | M46: =_xlfn.IFS(L46<80%,"A",L46<=95%,"B",L46>95%,"C") -> C
B47: 8852 | C47: ='Юнит 16'!AL56 -> -38.519047 | D47: =C47/C$58 -> -0.0002087609 | E47: =E46+D47 -> 1.0129759 | F47: =IF(AND(E47<=0),"C",IF(E47<=0.8,"A",IF(E47<=0.95,"B","C"))) -> C | G47: =VLOOKUP(B$4:B$57,I$4:M$57,5,0) -> C | I47: qs012 | J47: ='Юнит 16'!S29 -> 0 | K47: =J47/J$58 -> 0 | L47: =L46+K47 -> 0.99046105 | M47: =_xlfn.IFS(L47<80%,"A",L47<=95%,"B",L47>95%,"C") -> C
B48: 2100красный | C48: ='Юнит 16'!AL40 -> -108.93368 | D48: =C48/C$58 -> -0.00059038563 | E48: =E47+D48 -> 1.0123855 | F48: =IF(AND(E48<=0),"C",IF(E48<=0.8,"A",IF(E48<=0.95,"B","C"))) -> C | G48: =VLOOKUP(B$4:B$57,I$4:M$57,5,0) -> C | I48: qs001 Ж | J48: ='Юнит 16'!S33 -> 0 | K48: =J48/J$58 -> 0 | L48: =L47+K48 -> 0.99046105 | M48: =_xlfn.IFS(L48<80%,"A",L48<=95%,"B",L48>95%,"C") -> C
B49: 580черный | C49: ='Юнит 16'!AL48 -> -121.26371 | D49: =C49/C$58 -> -0.00065721048 | E49: =E48+D49 -> 1.0117283 | F49: =IF(AND(E49<=0),"C",IF(E49<=0.8,"A",IF(E49<=0.95,"B","C"))) -> C | G49: =VLOOKUP(B$4:B$57,I$4:M$57,5,0) -> C | I49: 2100красный | J49: ='Юнит 16'!S40 -> 0 | K49: =J49/J$58 -> 0 | L49: =L48+K49 -> 0.99046105 | M49: =_xlfn.IFS(L49<80%,"A",L49<=95%,"B",L49>95%,"C") -> C
B50: qs010 | C50: ='Юнит 16'!AL27 -> -171.12767 | D50: =C50/C$58 -> -0.00092745716 | E50: =E49+D50 -> 1.0108008 | F50: =IF(AND(E50<=0),"C",IF(E50<=0.8,"A",IF(E50<=0.95,"B","C"))) -> C | G50: =VLOOKUP(B$4:B$57,I$4:M$57,5,0) -> C | I50: 2104 | J50: ='Юнит 16'!S42 -> 0 | K50: =J50/J$58 -> 0 | L50: =L49+K50 -> 0.99046105 | M50: =_xlfn.IFS(L50<80%,"A",L50<=95%,"B",L50>95%,"C") -> C
B51: qs001 | C51: ='Юнит 16'!AL19 -> -192.62 | D51: =C51/C$58 -> -0.0010439387 | E51: =E50+D51 -> 1.0097569 | F51: =IF(AND(E51<=0),"C",IF(E51<=0.8,"A",IF(E51<=0.95,"B","C"))) -> C | G51: =VLOOKUP(B$4:B$57,I$4:M$57,5,0) -> C | I51: 6008 | J51: ='Юнит 16'!S43 -> 0 | K51: =J51/J$58 -> 0 | L51: =L50+K51 -> 0.99046105 | M51: =_xlfn.IFS(L51<80%,"A",L51<=95%,"B",L51>95%,"C") -> C
B52: 6008 | C52: ='Юнит 16'!AL43 -> -203.48636 | D52: =C52/C$58 -> -0.0011028309 | E52: =E51+D52 -> 1.0086541 | F52: =IF(AND(E52<=0),"C",IF(E52<=0.8,"A",IF(E52<=0.95,"B","C"))) -> C | G52: =VLOOKUP(B$4:B$57,I$4:M$57,5,0) -> C | I52: 123черный | J52: ='Юнит 16'!S44 -> 0 | K52: =J52/J$58 -> 0 | L52: =L51+K52 -> 0.99046105 | M52: =_xlfn.IFS(L52<80%,"A",L52<=95%,"B",L52>95%,"C") -> C
B53: 2081 | C53: ='Юнит 16'!AL53 -> -208.31905 | D53: =C53/C$58 -> -0.0011290225 | E53: =E52+D53 -> 1.007525 | F53: =IF(AND(E53<=0),"C",IF(E53<=0.8,"A",IF(E53<=0.95,"B","C"))) -> C | G53: =VLOOKUP(B$4:B$57,I$4:M$57,5,0) -> C | I53: 580черный | J53: ='Юнит 16'!S48 -> 0 | K53: =J53/J$58 -> 0 | L53: =L52+K53 -> 0.99046105 | M53: =_xlfn.IFS(L53<80%,"A",L53<=95%,"B",L53>95%,"C") -> C
B54: qs003 | C54: ='Юнит 16'!AL21 -> -239.83806 | D54: =C54/C$58 -> -0.0012998455 | E54: =E53+D54 -> 1.0062252 | F54: =IF(AND(E54<=0),"C",IF(E54<=0.8,"A",IF(E54<=0.95,"B","C"))) -> C | G54: =VLOOKUP(B$4:B$57,I$4:M$57,5,0) -> C | I54: 2064ч/б | J54: ='Юнит 16'!S50 -> 0 | K54: =J54/J$58 -> 0 | L54: =L53+K54 -> 0.99046105 | M54: =_xlfn.IFS(L54<80%,"A",L54<=95%,"B",L54>95%,"C") -> C
B55: 580метал | C55: ='Юнит 16'!AL49 -> -721.88237 | D55: =C55/C$58 -> -0.0039123713 | E55: =E54+D55 -> 1.0023128 | F55: =IF(AND(E55<=0),"C",IF(E55<=0.8,"A",IF(E55<=0.95,"B","C"))) -> C | G55: =VLOOKUP(B$4:B$57,I$4:M$57,5,0) -> B | I55: 2081 | J55: ='Юнит 16'!S53 -> 0 | K55: =J55/J$58 -> 0 | L55: =L54+K55 -> 0.99046105 | M55: =_xlfn.IFS(L55<80%,"A",L55<=95%,"B",L55>95%,"C") -> C
B56: qs015 | C56: ='Юнит 16'!AL32 -> -736.45138 | D56: =C56/C$58 -> -0.0039913306 | E56: =E55+D56 -> 0.99832148 | F56: =IF(AND(E56<=0),"C",IF(E56<=0.8,"A",IF(E56<=0.95,"B","C"))) -> C | G56: =VLOOKUP(B$4:B$57,I$4:M$57,5,0) -> C | I56: 2084 | J56: ='Юнит 16'!S54 -> 0 | K56: =J56/J$58 -> 0 | L56: =L55+K56 -> 0.99046105 | M56: =_xlfn.IFS(L56<80%,"A",L56<=95%,"B",L56>95%,"C") -> C
B57: 2084 (+1.75) | C57: ='Юнит 16'!AL55 -> -986.50569 | D57: =C57/C$58 -> -0.0053465449 | E57: =E56+D57 -> 0.99297494 | F57: =IF(AND(E57<=0),"C",IF(E57<=0.8,"A",IF(E57<=0.95,"B","C"))) -> C | G57: =VLOOKUP(B$4:B$57,I$4:M$57,5,0) -> C | I57: 8852 | J57: ='Юнит 16'!S56 -> 0 | K57: =J57/J$58 -> 0 | L57: =L56+K57 -> 0.99046105 | M57: =_xlfn.IFS(L57<80%,"A",L57<=95%,"B",L57>95%,"C") -> C
C58: =SUM(C4:C57) -> 184512.75 | D58: =SUM(D4:D44) -> 1.0205996 | J58: =SUM(J4:J57) -> 629 | K58: =SUM(K4:K44) -> 1
C61: Прибыль | D61: % прибыль | E61: Доля | F61: ABC прибыль | G61: ABC кол-во | J61: Кол-во | K61: % кол-во | L61: Доля | M61: ABC кол-во
D62: =C62/C$114 -> #DIV/0! | E62: =D62 -> #DIV/0! | F62: =IF(AND(E62<=0),"C",IF(E62<=0.8,"A",IF(E62<=0.95,"B","C"))) -> #DIV/0! | G62: =VLOOKUP(B62:B113,I$62:M$113,5,0) -> #N/A | K62: =J62/J$114 -> #DIV/0! | L62: =K62 -> #DIV/0! | M62: =_xlfn.IFS(L62<80%,"A",L62<=95%,"B",L62>95%,"C") -> #DIV/0!
D63: =C63/C$114 -> #DIV/0! | E63: =D63+E62 -> #DIV/0! | F63: =IF(AND(E63<=0),"C",IF(E63<=0.8,"A",IF(E63<=0.95,"B","C"))) -> #DIV/0! | G63: =VLOOKUP(B63:B114,I$62:M$113,5,0) -> #N/A | K63: =J63/J$114 -> #DIV/0! | L63: =K63+L62 -> #DIV/0! | M63: =_xlfn.IFS(L63<80%,"A",L63<=95%,"B",L63>95%,"C") -> #DIV/0!
D64: =C64/C$114 -> #DIV/0! | E64: =D64+E63 -> #DIV/0! | F64: =IF(AND(E64<=0),"C",IF(E64<=0.8,"A",IF(E64<=0.95,"B","C"))) -> #DIV/0! | G64: =VLOOKUP(B64:B115,I$62:M$113,5,0) -> #N/A | K64: =J64/J$114 -> #DIV/0! | L64: =K64+L63 -> #DIV/0! | M64: =_xlfn.IFS(L64<80%,"A",L64<=95%,"B",L64>95%,"C") -> #DIV/0!
D65: =C65/C$114 -> #DIV/0! | E65: =D65+E64 -> #DIV/0! | F65: =IF(AND(E65<=0),"C",IF(E65<=0.8,"A",IF(E65<=0.95,"B","C"))) -> #DIV/0! | G65: =VLOOKUP(B65:B116,I$62:M$113,5,0) -> #N/A | K65: =J65/J$114 -> #DIV/0! | L65: =K65+L64 -> #DIV/0! | M65: =_xlfn.IFS(L65<80%,"A",L65<=95%,"B",L65>95%,"C") -> #DIV/0!
D66: =C66/C$114 -> #DIV/0! | E66: =D66+E65 -> #DIV/0! | F66: =IF(AND(E66<=0),"C",IF(E66<=0.8,"A",IF(E66<=0.95,"B","C"))) -> #DIV/0! | G66: =VLOOKUP(B66:B117,I$62:M$113,5,0) -> #N/A | K66: =J66/J$114 -> #DIV/0! | L66: =K66+L65 -> #DIV/0! | M66: =_xlfn.IFS(L66<80%,"A",L66<=95%,"B",L66>95%,"C") -> #DIV/0!
D67: =C67/C$114 -> #DIV/0! | E67: =D67+E66 -> #DIV/0! | F67: =IF(AND(E67<=0),"C",IF(E67<=0.8,"A",IF(E67<=0.95,"B","C"))) -> #DIV/0! | G67: =VLOOKUP(B67:B118,I$62:M$113,5,0) -> #N/A | K67: =J67/J$114 -> #DIV/0! | L67: =K67+L66 -> #DIV/0! | M67: =_xlfn.IFS(L67<80%,"A",L67<=95%,"B",L67>95%,"C") -> #DIV/0!
D68: =C68/C$114 -> #DIV/0! | E68: =D68+E67 -> #DIV/0! | F68: =IF(AND(E68<=0),"C",IF(E68<=0.8,"A",IF(E68<=0.95,"B","C"))) -> #DIV/0! | G68: =VLOOKUP(B68:B119,I$62:M$113,5,0) -> #N/A | K68: =J68/J$114 -> #DIV/0! | L68: =K68+L67 -> #DIV/0! | M68: =_xlfn.IFS(L68<80%,"A",L68<=95%,"B",L68>95%,"C") -> #DIV/0!
D69: =C69/C$114 -> #DIV/0! | E69: =D69+E68 -> #DIV/0! | F69: =IF(AND(E69<=0),"C",IF(E69<=0.8,"A",IF(E69<=0.95,"B","C"))) -> #DIV/0! | G69: =VLOOKUP(B69:B120,I$62:M$113,5,0) -> #N/A | K69: =J69/J$114 -> #DIV/0! | L69: =K69+L68 -> #DIV/0! | M69: =_xlfn.IFS(L69<80%,"A",L69<=95%,"B",L69>95%,"C") -> #DIV/0!
