Workbook

Sheet Сводная
A1: Период | D1: Итого к перечислению на счет, руб | E1: шт. | H1: Выручка | K1: Себестоимость продаж | L1: Логистика | M1: Комиссия | N1: Хранение | O1: Платная приемка | P1: Штрафы | Q1: Реклама Ozon | R1: Другие услуги и штрафы | S1: Услуги партнёров | T1: Услуги FBO | U1: Компенсировано | V1: Пополнение рекламного кабинета | W1: ЕАЭС | X1: Налог | Y1: Прибыль до вычета налогов | Z1: Прибыль после вычета налогов | AA1: Итог месяц | AB1: % Cебестоимости | AC1: Маржинальность, % | AD1: Рентабельность, % | AE1: Доля рекламы, % | AG1: Данные для построения диаграмм
A2: Месяц | B2: Даты | C2: Нед | E2: Заказы | F2: Продажи | G2: Возвраты | H2: Продажи | I2: Возвраты | J2: Общая | AG2: Нед | AH2: По магазину | AI2: По очкам | AJ2: По туникам
A3: Январь | B3: 01-04.01 очки | D3: =J3-SUM(L3:T3)+U3+V3 -> 8693.5829 | E3: ='Юнит 01-04.01'!K$26 -> 44 | F3: ='Юнит 01-04.01'!P$26 -> 28 | G3: ='Юнит 01-04.01'!Q$26 -> 0 | H3: ='Юнит 01-04.01'!S$26 -> 45978 | I3: ='Юнит 01-04.01'!T$26 -> 0 | J3: =H3+I3 -> 45978 | K3: ='Юнит 01-04.01'!W$26 -> 4528.66 | L3: ='Юнит 01-04.01'!Z$26 -> 3709.34 | M3: ='Юнит 01-04.01'!X$26 -> 19770.54 | Q3: ='Юнит 01-04.01'!AA$26 -> 12383.647 | S3: 808.39 | T3: 612.5 | W3: 2545 | X3: =2656.15*J3/SUM($J$3:$J$12) -> 193.86959 | Y3: =J3-SUM(L3:T3)-K3-V3+U3+W3 -> 6709.9229 | Z3: =Y3-X3 -> 6516.0533 | AA3: =SUM(Z3:Z12) -> 53230.01 | AB3: =K3/J3 -> 0.098496237 | AC3: =Z3/K3 -> 1.438848 | AD3: =Z3/J3 -> 0.14172111 | AE3: =Q3/J3 -> 0.26933853
B4: 01-04.01 туники | D4: =J4-SUM(L4:T4)+U4+V4+W4 -> -283.08293 | E4: ='Юнит 01-04.01'!K$49 -> 5 | F4: ='Юнит 01-04.01'!P$49 -> 1 | G4: ='Юнит 01-04.01'!Q$49 -> 0 | H4: ='Юнит 01-04.01'!S$49 -> 4247 | I4: ='Юнит 01-04.01'!T$49 -> 0 | J4: =H4+I4 -> 4247 | K4: ='Юнит 01-04.01'!W$49 -> 597 | L4: ='Юнит 01-04.01'!Z$49 -> 186.2 | M4: ='Юнит 01-04.01'!X$49 -> 1826.21 | Q4: ='Юнит 01-04.01'!AA$49 -> 2517.6729 | X4: =2656.15*J4/SUM($J$3:$J$12) -> 17.907785 | Y4: =J4-SUM(L4:T4)-K4-V4+U4+W4 -> -880.08293 | Z4: =Y4-X4 -> -897.99072 | AB4: =K4/J4 -> 0.14056981 | AC4: =Z4/K4 -> -1.5041721 | AD4: =Z4/J4 -> -0.21144119 | AE4: =Q4/J4 -> 0.59281209
B5: 05-11.01 очки | D5: =J5-SUM(L5:T5)+U5+V5+W5 -> 15399.171 | E5: ='Юнит 05-11.01'!K$26 -> 74 | F5: ='Юнит 05-11.01'!P$26 -> 58 | G5: ='Юнит 05-11.01'!Q$26 -> 4 | H5: ='Юнит 05-11.01'!S$26 -> 92160 | I5: ='Юнит 05-11.01'!T$26 -> -6799 | J5: =H5+I5 -> 85361 | K5: ='Юнит 05-11.01'!W$26 -> 7651.8 | L5: ='Юнит 05-11.01'!Z$26 -> 9950.27 | M5: ='Юнит 05-11.01'!X$26 -> 36705.23 | Q5: ='Юнит 05-11.01'!AA$26 -> 20067.069 | R5: 5 | S5: 1918.46 | T5: 1315.8 | X5: =2656.15*J5/SUM($J$3:$J$12) -> 359.93088 | Y5: =J5-SUM(L5:T5)-K5-V5+U5+W5 -> 7747.3709 | Z5: =Y5-X5 -> 7387.44 | AB5: =K5/J5 -> 0.089640468 | AC5: =Z5/K5 -> 0.96545127 | AD5: =Z5/J5 -> 0.086543504 | AE5: =Q5/J5 -> 0.23508475
B6: 05-11.01 туники | D6: =J6-SUM(L6:T6)+U6+V6+W6 -> 4110.6391 | E6: ='Юнит 05-11.01'!K$49 -> 4 | F6: ='Юнит 05-11.01'!P$49 -> 2 | G6: ='Юнит 05-11.01'!Q$49 -> 0 | H6: ='Юнит 05-11.01'!S$49 -> 10524 | I6: ='Юнит 05-11.01'!T$49 -> 0 | J6: =H6+I6 -> 10524 | K6: ='Юнит 05-11.01'!W$49 -> 1329 | L6: ='Юнит 05-11.01'!Z$49 -> 907.3 | M6: ='Юнит 05-11.01'!X$49 -> 4525.32 | Q6: ='Юнит 05-11.01'!AA$49 -> 980.7409 | X6: =2656.15*J6/SUM($J$3:$J$12) -> 44.375213 | Y6: =J6-SUM(L6:T6)-K6-V6+U6+W6 -> 2781.6391 | Z6: =Y6-X6 -> 2737.2639 | AB6: =K6/J6 -> 0.12628278 | AC6: =Z6/K6 -> 2.0596417 | AD6: =Z6/J6 -> 0.26009729 | AE6: =Q6/J6 -> 0.093190888
B7: 12-18.01 очки | D7: =J7-SUM(L7:T7)+U7+V7+W7 -> 29545.798 | E7: ='Юнит 12-18.01'!K$26 -> 96 | F7: ='Юнит 12-18.01'!P$26 -> 56 | G7: ='Юнит 12-18.01'!Q$26 -> 0 | H7: ='Юнит 12-18.01'!S$26 -> 91762 | I7: ='Юнит 12-18.01'!T$26 -> 0 | J7: =H7+I7 -> 91762 | K7: ='Юнит 12-18.01'!W$26 -> 7841.91 | L7: ='Юнит 12-18.01'!Z$26 -> 9811.64 | M7: ='Юнит 12-18.01'!X$26 -> 39457.66 | Q7: ='Юнит 12-18.01'!AA$26 -> 18818.032 | S7: 2168.87 | T7: 800 | V7: 7000 | W7: 1840 | X7: =2656.15*J7/SUM($J$3:$J$12) -> 386.92116 | Y7: =J7-SUM(L7:T7)-K7-V7+U7+W7 -> 7703.8881 | Z7: =Y7-X7 -> 7316.967 | AB7: =K7/J7 -> 0.085459231 | AC7: =Z7/K7 -> 0.93305929 | AD7: =Z7/J7 -> 0.07973853 | AE7: =Q7/J7 -> 0.20507434
B8: 12-18.01 туники | D8: =J8-SUM(L8:T8)+U8+V8+W8 -> 4732.6119 | E8: ='Юнит 12-18.01'!K$49 -> 30 | F8: ='Юнит 12-18.01'!P$49 -> 5 | G8: ='Юнит 12-18.01'!Q$49 -> 0 | H8: ='Юнит 12-18.01'!S$49 -> 21020 | I8: ='Юнит 12-18.01'!T$49 -> 0 | J8: =H8+I8 -> 21020 | K8: ='Юнит 12-18.01'!W$49 -> 3435 | L8: ='Юнит 12-18.01'!Z$49 -> 1528.99 | M8: ='Юнит 12-18.01'!X$49 -> 9038.6 | Q8: ='Юнит 12-18.01'!AA$49 -> 5719.7981 | X8: =2656.15*J8/SUM($J$3:$J$12) -> 88.632363 | Y8: =J8-SUM(L8:T8)-K8-V8+U8+W8 -> 1297.6119 | Z8: =Y8-X8 -> 1208.9795 | AB8: =K8/J8 -> 0.16341579 | AC8: =Z8/K8 -> 0.3519591 | AD8: =Z8/J8 -> 0.057515676 | AE8: =Q8/J8 -> 0.27211219
B9: 19-25.01 очки | D9: =J9-SUM(L9:T9)+U9+V9+W9 -> 21740.787 | E9: ='Юнит 19-25.01'!K$26 -> 119 | F9: ='Юнит 19-25.01'!P$26 -> 64 | G9: ='Юнит 19-25.01'!Q$26 -> 1 | H9: ='Юнит 19-25.01'!S$26 -> 104586 | I9: ='Юнит 19-25.01'!T$26 -> -1670 | J9: =H9+I9 -> 102916 | K9: ='Юнит 19-25.01'!W$26 -> 9494.98 | L9: ='Юнит 19-25.01'!Z$26 -> 12870.13 | M9: ='Юнит 19-25.01'!X$26 -> 44253.88 | Q9: ='Юнит 19-25.01'!AA$26 -> 25263.883 | R9: 15 | S9: 3536.42 | T9: 2235.9 | V9: 7000 | X9: =2656.15*J9/SUM($J$3:$J$12) -> 433.95282 | Y9: =J9-SUM(L9:T9)-K9-V9+U9+W9 -> -1754.1928 | Z9: =Y9-X9 -> -2188.1456 | AB9: =K9/J9 -> 0.092259513 | AC9: =Z9/K9 -> -0.23045289 | AD9: =Z9/J9 -> -0.021261472 | AE9: =Q9/J9 -> 0.24548061
B10: 19-25.01 туники | D10: =J10-SUM(L10:T10)+U10+V10+W10 -> 13844.323 | E10: ='Юнит 19-25.01'!K$49 -> 66 | F10: ='Юнит 19-25.01'!P$49 -> 18 | G10: ='Юнит 19-25.01'!Q$49 -> 4 | H10: ='Юнит 19-25.01'!S$49 -> 80413 | I10: ='Юнит 19-25.01'!T$49 -> -17932 | J10: =H10+I10 -> 62481 | K10: ='Юнит 19-25.01'!W$49 -> 9468 | L10: ='Юнит 19-25.01'!Z$49 -> 6390.87 | M10: ='Юнит 19-25.01'!X$49 -> 26866.83 | Q10: ='Юнит 19-25.01'!AA$49 -> 15378.977 | X10: =2656.15*J10/SUM($J$3:$J$12) -> 263.45569 | Y10: =J10-SUM(L10:T10)-K10-V10+U10+W10 -> 4376.3228 | Z10: =Y10-X10 -> 4112.8671 | AB10: =K10/J10 -> 0.15153407 | AC10: =Z10/K10 -> 0.43439661 | AD10: =Z10/J10 -> 0.065825885 | AE10: =Q10/J10 -> 0.24613846
B11: 26-31.01 очки | D11: =J11-SUM(L11:T11)+U11+V11+W11 -> 23967.429 | E11: ='Юнит 26-31.01'!K$26 -> 100 | F11: ='Юнит 26-31.01'!P$26 -> 72 | G11: ='Юнит 26-31.01'!Q$26 -> 3 | H11: ='Юнит 26-31.01'!S$26 -> 120331 | I11: ='Юнит 26-31.01'!T$26 -> -4419 | J11: =H11+I11 -> 115912 | K11: ='Юнит 26-31.01'!W$26 -> 10470.94 | L11: ='Юнит 26-31.01'!Z$26 -> 13196.61 | M11: ='Юнит 26-31.01'!X$26 -> 49842.16 | Q11: ='Юнит 26-31.01'!AA$26 -> 19493.871 | R11: 25 | S11: 2141.43 | T11: 7245.5 | X11: =2656.15*J11/SUM($J$3:$J$12) -> 488.7514 | Y11: =J11-SUM(L11:T11)-K11-V11+U11+W11 -> 13496.489 | Z11: =Y11-X11 -> 13007.738 | AB11: =K11/J11 -> 0.090335254 | AC11: =Z11/K11 -> 1.2422703 | AD11: =Z11/J11 -> 0.1122208 | AE11: =Q11/J11 -> 0.16817819
B12: 26-31.01 туники | D12: =J12-SUM(L12:T12)+U12+V12+W12 -> 27742.191 | E12: ='Юнит 26-31.01'!K$49 -> 60 | F12: ='Юнит 26-31.01'!P$49 -> 20 | G12: ='Юнит 26-31.01'!Q$49 -> 0 | H12: ='Юнит 26-31.01'!S$49 -> 89730 | I12: ='Юнит 26-31.01'!T$49 -> 0 | J12: =H12+I12 -> 89730 | K12: ='Юнит 26-31.01'!W$49 -> 13335 | L12: ='Юнит 26-31.01'!Z$49 -> 8653.99 | M12: ='Юнит 26-31.01'!X$49 -> 38583.9 | Q12: ='Юнит 26-31.01'!AA$49 -> 13258.459 | S12: 1491.46 | X12: =2656.15*J12/SUM($J$3:$J$12) -> 378.35309 | Y12: =J12-SUM(L12:T12)-K12-V12+U12+W12 -> 14407.191 | Z12: =Y12-X12 -> 14028.838 | AB12: =K12/J12 -> 0.1486125 | AC12: =Z12/K12 -> 1.0520313 | AD12: =Z12/J12 -> 0.15634501 | AE12: =Q12/J12 -> 0.14775949
A13: Февраль | B13: 01.02 очки | D13: =J13-SUM(L13:T13)+U13+V13 -> 1221.3769 | E13: ='Юнит 01.02'!K$26 -> 19 | F13: ='Юнит 01.02'!P$26 -> 8 | G13: ='Юнит 01.02'!Q$26 -> 1 | H13: ='Юнит 01.02'!S$26 -> 13169 | I13: ='Юнит 01.02'!T$26 -> -1655 | J13: =H13+I13 -> 11514 | K13: ='Юнит 01.02'!W$26 -> 1054.68 | L13: ='Юнит 01.02'!Z$26 -> 1614.84 | M13: ='Юнит 01.02'!X$26 -> 4951.02 | Q13: ='Юнит 01.02'!AA$26 -> 3338.9931 | S13: 387.77 | W13: 902 | X13: =4921.38*J13/SUM($J$13:$J$22) -> 52.083983 | Y13: =J13-SUM(L13:T13)-K13-V13+U13+W13 -> 1068.6969 | Z13: =J13-SUM(L13:T13)-K13-X13+U13+W13-V13 -> 1016.6129 | AA13: =SUM(Z13:Z22) -> 147164.97 | AB13: =K13/J13 -> 0.091599792 | AC13: =Z13/K13 -> 0.9639065 | AD13: =Z13/J13 -> 0.088293634 | AE13: =Q13/J13 -> 0.28999419
B14: 01.02 туники | D14: =J14-SUM(L14:T14)+U14+V14+W14 -> -3647.3769 | E14: ='Юнит 01.02'!K$49 -> 7 | F14: ='Юнит 01.02'!P$49 -> 1 | G14: ='Юнит 01.02'!Q$49 -> 0 | H14: ='Юнит 01.02'!S$49 -> 4940 | I14: ='Юнит 01.02'!T$49 -> 0 | J14: =H14+I14 -> 4940 | K14: ='Юнит 01.02'!W$49 -> 687 | L14: ='Юнит 01.02'!Z$49 -> 1483.67 | M14: ='Юнит 01.02'!X$49 -> 2124.2 | Q14: ='Юнит 01.02'!AA$49 -> 4567.9469 | R14: 5 | S14: 406.56 | X14: =4921.38*J14/SUM($J$13:$J$22) -> 22.346263 | Y14: =J14-SUM(L14:T14)-K14-V14+U14+W14 -> -4334.3769 | Z14: =J14-SUM(L14:T14)-K14-X14+U14+W14-V14 -> -4356.7232 | AB14: =K14/J14 -> 0.13906883 | AC14: =Z14/K14 -> -6.341664 | AD14: =Z14/J14 -> -0.88192776 | AE14: =Q14/J14 -> 0.92468561
B15: 02-08.02 очки | D15: =J15-SUM(L15:T15)+U15+V15 -> 19261.798 | E15: ='Юнит 02-08.02'!K$26 -> 131 | F15: ='Юнит 02-08.02'!P$26 -> 65 | G15: ='Юнит 02-08.02'!Q$26 -> 5 | H15: ='Юнит 02-08.02'!S$26 -> 119818 | I15: ='Юнит 02-08.02'!T$26 -> -9187 | J15: =H15+I15 -> 110631 | K15: ='Юнит 02-08.02'!W$26 -> 9043.72 | L15: ='Юнит 02-08.02'!Z$26 -> 13862.81 | M15: ='Юнит 02-08.02'!X$26 -> 47571.33 | Q15: ='Юнит 02-08.02'!AA$26 -> 26854.642 | S15: 3080.42 | X15: =4921.38*J15/SUM($J$13:$J$22) -> 500.44321 | Y15: =J15-SUM(L15:T15)-K15-V15+U15+W15 -> 10218.078 | Z15: =J15-SUM(L15:T15)-K15-X15+U15+W15-V15 -> 9717.6347 | AB15: =K15/J15 -> 0.081746708 | AC15: =Z15/K15 -> 1.0745174 | AD15: =Z15/J15 -> 0.087838262 | AE15: =Q15/J15 -> 0.24274066
B16: 02-08.02 туники | D16: =J16-SUM(L16:T16)+U16+V16+W16 -> 28854.102 | E16: ='Юнит 02-08.02'!K$49 -> 68 | F16: ='Юнит 02-08.02'!P$49 -> 24 | G16: ='Юнит 02-08.02'!Q$49 -> 1 | H16: ='Юнит 02-08.02'!S$49 -> 114048 | I16: ='Юнит 02-08.02'!T$49 -> -4178 | J16: =H16+I16 -> 109870 | K16: ='Юнит 02-08.02'!W$49 -> 14496 | L16: ='Юнит 02-08.02'!Z$49 -> 11481.36 | M16: ='Юнит 02-08.02'!X$49 -> 47244.1 | Q16: ='Юнит 02-08.02'!AA$49 -> 20002.458 | R16: 20 | S16: 2267.98 | X16: =4921.38*J16/SUM($J$13:$J$22) -> 497.0008 | Y16: =J16-SUM(L16:T16)-K16-V16+U16+W16 -> 14358.102 | Z16: =J16-SUM(L16:T16)-K16-X16+U16+W16-V16 -> 13861.101 | AB16: =K16/J16 -> 0.13193774 | AC16: =Z16/K16 -> 0.9562018 | AD16: =Z16/J16 -> 0.12615911 | AE16: =Q16/J16 -> 0.18205568
B17: 09-15.02 очки | D17: =J17-SUM(L17:T17)+U17+V17 -> 22441.752 | E17: ='Юнит 09-15.02'!K$26 -> 121 | F17: ='Юнит 09-15.02'!P$26 -> 60 | G17: ='Юнит 09-15.02'!Q$26 -> 2 | H17: ='Юнит 09-15.02'!S$26 -> 125456 | I17: ='Юнит 09-15.02'!T$26 -> -4877 | J17: =H17+I17 -> 120579 | K17: ='Юнит 09-15.02'!W$26 -> 7423.19 | L17: ='Юнит 09-15.02'!Z$26 -> 13659.9 | M17: ='Юнит 09-15.02'!X$26 -> 51848.97 | Q17: ='Юнит 09-15.02'!AA$26 -> 26940.334 | S17: 3309.41 | T17: =3250.8*F17/(F17+F18) -> 2378.6341 | X17: =4921.38*J17/SUM($J$13:$J$22) -> 545.44334 | Y17: =J17-SUM(L17:T17)-K17-V17+U17+W17 -> 15018.562 | Z17: =J17-SUM(L17:T17)-K17-X17+U17+W17-V17 -> 14473.119 | AB17: =K17/J17 -> 0.061562876 | AC17: =Z17/K17 -> 1.9497169 | AD17: =Z17/J17 -> 0.12003018 | AE17: =Q17/J17 -> 0.22342476
B18: 09-15.02 туники | D18: =J18-SUM(L18:T18)+U18+V18+W18 -> 28836.778 | E18: ='Юнит 09-15.02'!K$49 -> 54 | F18: ='Юнит 09-15.02'!P$49 -> 22 | G18: ='Юнит 09-15.02'!Q$49 -> 2 | H18: ='Юнит 09-15.02'!S$49 -> 110799 | I18: ='Юнит 09-15.02'!T$49 -> -9047 | J18: =H18+I18 -> 101752 | K18: ='Юнит 09-15.02'!W$49 -> 13275 | L18: ='Юнит 09-15.02'!Z$49 -> 8720.99 | M18: ='Юнит 09-15.02'!X$49 -> 43753.36 | Q18: ='Юнит 09-15.02'!AA$49 -> 17681.836 | R18: 25 | S18: 1861.87 | T18: =3250.8*F18/(F17+F18) -> 872.16585 | X18: =4921.38*J18/SUM($J$13:$J$22) -> 460.27874 | Y18: =J18-SUM(L18:T18)-K18-V18+U18+W18 -> 15561.778 | Z18: =J18-SUM(L18:T18)-K18-X18+U18+W18-V18 -> 15101.499 | AB18: =K18/J18 -> 0.13046427 | AC18: =Z18/K18 -> 1.1375894 | AD18: =Z18/J18 -> 0.14841476 | AE18: =Q18/J18 -> 0.17377385
B19: 16-22.02 очки | D19: =J19-SUM(L19:T19)+U19+V19 -> 37691.629 | E19: ='Юнит 16-22.02'!K$26 -> 172 | F19: ='Юнит 16-22.02'!P$26 -> 79 | G19: ='Юнит 16-22.02'!Q$26 -> 2 | H19: ='Юнит 16-22.02'!S$26 -> 173410 | I19: ='Юнит 16-22.02'!T$26 -> -4800 | J19: =H19+I19 -> 168610 | K19: ='Юнит 16-22.02'!W$26 -> 11163.54 | L19: ='Юнит 16-22.02'!Z$26 -> 17063.86 | M19: ='Юнит 16-22.02'!X$26 -> 72502.3 | Q19: ='Юнит 16-22.02'!AA$26 -> 37347.301 | S19: 4004.91 | W19: 972 | X19: =4921.38*J19/SUM($J$13:$J$22) -> 762.71325 | Y19: =J19-SUM(L19:T19)-K19-V19+U19+W19 -> 27500.089 | Z19: =J19-SUM(L19:T19)-K19-X19+U19+W19-V19 -> 26737.376 | AB19: =K19/J19 -> 0.06620924 | AC19: =Z19/K19 -> 2.3950625 | AD19: =Z19/J19 -> 0.15857527 | AE19: =Q19/J19 -> 0.2215011
B20: 16-22.02 туники | D20: =J20-SUM(L20:T20)+U20+V20+W20 -> 43858.251 | E20: ='Юнит 16-22.02'!K$49 -> 78 | F20: ='Юнит 16-22.02'!P$49 -> 27 | G20: ='Юнит 16-22.02'!Q$49 -> 2 | H20: ='Юнит 16-22.02'!S$49 -> 141378 | I20: ='Юнит 16-22.02'!T$49 -> -10000 | J20: =H20+I20 -> 131378 | K20: ='Юнит 16-22.02'!W$49 -> 15420 | L20: ='Юнит 16-22.02'!Z$49 -> 10936.38 | M20: ='Юнит 16-22.02'!X$49 -> 56492.54 | Q20: ='Юнит 16-22.02'!AA$49 -> 21117.479 | R20: 20 | S20: 2139.35 | W20: 3186 | X20: =4921.38*J20/SUM($J$13:$J$22) -> 594.29299 | Y20: =J20-SUM(L20:T20)-K20-V20+U20+W20 -> 28438.251 | Z20: =J20-SUM(L20:T20)-K20-X20+U20+W20-V20 -> 27843.958 | AB20: =K20/J20 -> 0.11737125 | AC20: =Z20/K20 -> 1.8057041 | AD20: =Z20/J20 -> 0.21193775 | AE20: =Q20/J20 -> 0.16073832
B21: 23-28.02 очки | D21: =J21-SUM(L21:T21)+U21+V21 -> 51268.243 | E21: ='Юнит 23-28.02'!K$26 -> 200 | F21: ='Юнит 23-28.02'!P$26 -> 104 | G21: ='Юнит 23-28.02'!Q$26 -> 6 | H21: ='Юнит 23-28.02'!S$26 -> 230456 | I21: ='Юнит 23-28.02'!T$26 -> -14068 | J21: =H21+I21 -> 216388 | K21: ='Юнит 23-28.02'!W$26 -> 14285.64 | L21: ='Юнит 23-28.02'!Z$26 -> 18630.99 | M21: ='Юнит 23-28.02'!X$26 -> 93046.84 | Q21: ='Юнит 23-28.02'!AA$26 -> 49038.397 | S21: 4403.53 | X21: =4921.38*J21/SUM($J$13:$J$22) -> 978.83871 | Y21: =J21-SUM(L21:T21)-K21-V21+U21+W21 -> 36982.603 | Z21: =J21-SUM(L21:T21)-K21-X21+U21+W21-V21 -> 36003.764 | AB21: =K21/J21 -> 0.066018633 | AC21: =Z21/K21 -> 2.5202766 | AD21: =Z21/J21 -> 0.16638522 | AE21: =Q21/J21 -> 0.22662253
B22: 23-28.02 туники | D22: =J22-SUM(L22:T22)+U22+V22+W22 -> 20741.567 | E22: ='Юнит 23-28.02'!K$49 -> 73 | F22: ='Юнит 23-28.02'!P$49 -> 22 | G22: ='Юнит 23-28.02'!Q$49 -> 1 | H22: ='Юнит 23-28.02'!S$49 -> 118788 | I22: ='Юнит 23-28.02'!T$49 -> -6500 | J22: =H22+I22 -> 112288 | K22: ='Юнит 23-28.02'!W$49 -> 13467 | L22: ='Юнит 23-28.02'!Z$49 -> 9725.32 | M22: ='Юнит 23-28.02'!X$49 -> 48283.84 | Q22: ='Юнит 23-28.02'!AA$49 -> 30882.493 | R22: 10 | S22: 2644.78 | X22: =4921.38*J22/SUM($J$13:$J$22) -> 507.93871 | Y22: =J22-SUM(L22:T22)-K22-V22+U22+W22 -> 7274.5671 | Z22: =J22-SUM(L22:T22)-K22-X22+U22+W22-V22 -> 6766.6284 | AB22: =K22/J22 -> 0.11993267 | AC22: =Z22/K22 -> 0.50245997 | AD22: =Z22/J22 -> 0.060261367 | AE22: =Q22/J22 -> 0.27502933
A23: Март | B23: 01.03 очки | C23: 9 | D23: =J23-SUM(L23:T23)+U23+V23 -> 9573.6928 | E23: ='Юнит 01.03'!K$26 -> 33 | F23: ='Юнит 01.03'!P$26 -> 19 | G23: ='Юнит 01.03'!Q$26 -> 0 | H23: ='Юнит 01.03'!S$26 -> 40846 | I23: ='Юнит 01.03'!T$26 -> 0 | J23: =H23+I23 -> 40846 | K23: ='Юнит 01.03'!W$26 -> 2795.01 | L23: ='Юнит 01.03'!Z$26 -> 4137.97 | M23: ='Юнит 01.03'!X$26 -> 17563.78 | Q23: ='Юнит 01.03'!AA$26 -> 8589.2572 | S23: 981.3 | W23: 2592 | X23: ='Юнит 01.03'!AD$26 -> 174.8667 | Y23: =J23-SUM(L23:T23)-K23-V23+U23+W23 -> 9370.6828 | Z23: =J23-SUM(L23:T23)-K23-X23+U23+W23-V23 -> 9195.8161 | AA23: =SUM(Z23:Z38) -> 330669.81 | AB23: =K23/J23 -> 0.068427998 | AC23: =Z23/K23 -> 3.2900834 | AD23: =Z23/J23 -> 0.22513382 | AE23: =Q23/J23 -> 0.21028393
B24: 01.03 туники | C24: 9 | D24: =J24-SUM(L24:T24)+U24+V24+W24 -> 11464.637 | E24: ='Юнит 01.03'!K$49 -> 10 | F24: ='Юнит 01.03'!P$49 -> 5 | G24: ='Юнит 01.03'!Q$49 -> 0 | H24: ='Юнит 01.03'!S$49 -> 27900 | I24: ='Юнит 01.03'!T$49 -> 0 | J24: =H24+I24 -> 27900 | K24: ='Юнит 01.03'!W$49 -> 3240 | L24: ='Юнит 01.03'!Z$49 -> 1772.61 | M24: ='Юнит 01.03'!X$49 -> 11997 | Q24: ='Юнит 01.03'!AA$49 -> 2452.0328 | S24: 213.72 | X24: ='Юнит 01.03'!AD$49 -> 119.4433 | Y24: =J24-SUM(L24:T24)-K24-V24+U24+W24 -> 8224.6372 | Z24: =J24-SUM(L24:T24)-K24-X24+U24+W24-V24 -> 8105.1939 | AB24: =K24/J24 -> 0.11612903 | AC24: =Z24/K24 -> 2.5016031 | AD24: =Z24/J24 -> 0.29050874 | AE24: =Q24/J24 -> 0.08788648
B25: 02-08.03 очки | C25: 10 | D25: =J25-SUM(L25:T25)+U25+V25 -> 43006.268 | E25: ='Юнит 02-08.03'!K$26 -> 197 | F25: ='Юнит 02-08.03'!P$26 -> 103 | G25: ='Юнит 02-08.03'!Q$26 -> 9 | H25: ='Юнит 02-08.03'!S$26 -> 247424 | I25: ='Юнит 02-08.03'!T$26 -> -18379 | J25: =H25+I25 -> 229045 | K25: ='Юнит 02-08.03'!W$26 -> 13689.96 | L25: ='Юнит 02-08.03'!Z$26 -> 23987.37 | M25: ='Юнит 02-08.03'!X$26 -> 98489.35 | Q25: ='Юнит 02-08.03'!AA$26 -> 55823.055 | R25: 40 | S25: 5595.07 | T25: =2818.8*F25/(F25+F26) -> 2103.887 | X25: ='Юнит 02-08.03'!AD$26 -> 946.88488 | Y25: =J25-SUM(L25:T25)-K25-V25+U25+W25 -> 29316.308 | Z25: =J25-SUM(L25:T25)-K25-X25+U25+W25-V25 -> 28369.423 | AB25: =K25/J25 -> 0.05976974 | AC25: =Z25/K25 -> 2.0722795 | AD25: =Z25/J25 -> 0.12385961 | AE25: =Q25/J25 -> 0.24372091
B26: 02-08.03 туники | C26: 10 | D26: =J26-SUM(L26:T26)+U26+V26+W26 -> 11946.392 | E26: ='Юнит 02-08.03'!K$49 -> 64 | F26: ='Юнит 02-08.03'!P$49 -> 35 | G26: ='Юнит 02-08.03'!Q$49 -> 11 | H26: ='Юнит 02-08.03'!S$49 -> 173194 | I26: ='Юнит 02-08.03'!T$49 -> -55802 | J26: =H26+I26 -> 117392 | K26: ='Юнит 02-08.03'!W$49 -> 14478 | L26: ='Юнит 02-08.03'!Z$49 -> 12952.31 | M26: ='Юнит 02-08.03'!X$49 -> 50478.56 | Q26: ='Юнит 02-08.03'!AA$49 -> 39094.165 | R26: 45 | S26: 2160.66 | T26: =2818.8*F26/(F25+F26) -> 714.91304 | X26: ='Юнит 02-08.03'!AD$49 -> 485.30512 | Y26: =J26-SUM(L26:T26)-K26-V26+U26+W26 -> -2531.6083 | Z26: =J26-SUM(L26:T26)-K26-X26+U26+W26-V26 -> -3016.9135 | AB26: =K26/J26 -> 0.12333038 | AC26: =Z26/K26 -> -0.20837916 | AD26: =Z26/J26 -> -0.025699481 | AE26: =Q26/J26 -> 0.3330224
B27: 09-15.03 очки | C27: 11 | D27: =J27-SUM(L27:T27)+U27+V27 -> 105076.48 | E27: ='Юнит 09-15.03'!K$26 -> 349 | F27: ='Юнит 09-15.03'!P$26 -> 151 | G27: ='Юнит 09-15.03'!Q$26 -> 7 | H27: ='Юнит 09-15.03'!S$26 -> 390195 | I27: ='Юнит 09-15.03'!T$26 -> -18400 | J27: =H27+I27 -> 371795 | K27: ='Юнит 09-15.03'!W$26 -> 20433.06 | L27: ='Юнит 09-15.03'!Z$26 -> 31144.36 | M27: ='Юнит 09-15.03'!X$26 -> 159871.85 | Q27: ='Юнит 09-15.03'!AA$26 -> 66464.463 | R27: 55 | S27: 7274.73 | T27: =2350.4*F27/(F27+F28) -> 1908.1204 | X27: ='Юнит 09-15.03'!AD$26 -> 1429.6569 | Y27: =J27-SUM(L27:T27)-K27-V27+U27+W27 -> 84643.417 | Z27: =J27-SUM(L27:T27)-K27-X27+U27+W27-V27 -> 83213.76 | AB27: =K27/J27 -> 0.054957867 | AC27: =Z27/K27 -> 4.072506 | AD27: =Z27/J27 -> 0.22381624 | AE27: =Q27/J27 -> 0.17876642
B28: 09-15.03 туники | C28: 11 | D28: =J28-SUM(L28:T28)+U28+V28+W28 -> 30545.503 | E28: ='Юнит 09-15.03'!K$49 -> 81 | F28: ='Юнит 09-15.03'!P$49 -> 35 | G28: ='Юнит 09-15.03'!Q$49 -> 3 | H28: ='Юнит 09-15.03'!S$49 -> 165276 | I28: ='Юнит 09-15.03'!T$49 -> -15138 | J28: =H28+I28 -> 150138 | K28: ='Юнит 09-15.03'!W$49 -> 20184 | L28: ='Юнит 09-15.03'!Z$49 -> 13386.34 | M28: ='Юнит 09-15.03'!X$49 -> 64559.34 | Q28: ='Юнит 09-15.03'!AA$49 -> 38590.547 | R28: 25 | S28: 2588.99 | T28: =2350.4*F28/(F27+F28) -> 442.27957 | X28: ='Юнит 09-15.03'!AD$49 -> 577.32307 | Y28: =J28-SUM(L28:T28)-K28-V28+U28+W28 -> 10361.503 | Z28: =J28-SUM(L28:T28)-K28-X28+U28+W28-V28 -> 9784.1801 | AB28: =K28/J28 -> 0.13443632 | AC28: =Z28/K28 -> 0.48474931 | AD28: =Z28/J28 -> 0.065167913 | AE28: =Q28/J28 -> 0.25703384
B29: 16-22.03 очки | C29: 12 | D29: =J29-SUM(L29:T29)+U29+V29 -> 140853.44 | E29: ='Юнит 16-22.03'!K$26 -> 335 | F29: ='Юнит 16-22.03'!P$26 -> 174 | G29: ='Юнит 16-22.03'!Q$26 -> 3 | H29: ='Юнит 16-22.03'!S$26 -> 466726 | I29: ='Юнит 16-22.03'!T$26 -> -8150 | J29: =H29+I29 -> 458576 | K29: ='Юнит 16-22.03'!W$26 -> 24482.7 | L29: ='Юнит 16-22.03'!Z$26 -> 38820.12 | M29: ='Юнит 16-22.03'!X$26 -> 197187.68 | Q29: ='Юнит 16-22.03'!AA$26 -> 72779.225 | R29: 230 | S29: 8705.53 | W29: 1431 | X29: ='Юнит 16-22.03'!AD$26 -> 1891.4078 | Y29: =J29-SUM(L29:T29)-K29-V29+U29+W29 -> 117801.74 | Z29: =J29-SUM(L29:T29)-K29-X29+U29+W29-V29 -> 115910.34 | AB29: =K29/J29 -> 0.053388533 | AC29: =Z29/K29 -> 4.7343772 | AD29: =Z29/J29 -> 0.25276145 | AE29: =Q29/J29 -> 0.15870701
B30: 16-22.03 туники | C30: 12 | D30: =J30-SUM(L30:T30)+U30+V30+W30 -> 19370.855 | E30: ='Юнит 16-22.03'!K$49 -> 46 | F30: ='Юнит 16-22.03'!P$49 -> 27 | G30: ='Юнит 16-22.03'!Q$49 -> 6 | H30: ='Юнит 16-22.03'!S$49 -> 109484 | I30: ='Юнит 16-22.03'!T$49 -> -29016 | J30: =H30+I30 -> 80468 | K30: ='Юнит 16-22.03'!W$49 -> 12897 | L30: ='Юнит 16-22.03'!Z$49 -> 9001.49 | M30: ='Юнит 16-22.03'!X$49 -> 34601.24 | Q30: ='Юнит 16-22.03'!AA$49 -> 16067.285 | R30: 30 | S30: 1397.13 | X30: ='Юнит 16-22.03'!AD$49 -> 331.89221 | Y30: =J30-SUM(L30:T30)-K30-V30+U30+W30 -> 6473.8555 | Z30: =J30-SUM(L30:T30)-K30-X30+U30+W30-V30 -> 6141.9633 | AB30: =K30/J30 -> 0.16027489 | AC30: =Z30/K30 -> 0.47623193 | AD30: =Z30/J30 -> 0.076328022 | AE30: =Q30/J30 -> 0.19967297
B31: 23-29.03 очки | C31: 13 | D31: =J31-SUM(L31:T31)+U31+V31 -> 96137.006 | E31: ='Юнит 23-29.03'!K$26 -> 301 | F31: ='Юнит 23-29.03'!P$26 -> 135 | G31: ='Юнит 23-29.03'!Q$26 -> 4 | H31: ='Юнит 23-29.03'!S$26 -> 367961 | I31: ='Юнит 23-29.03'!T$26 -> -10800 | J31: =H31+I31 -> 357161 | K31: ='Юнит 23-29.03'!W$26 -> 18526.35 | L31: ='Юнит 23-29.03'!Z$26 -> 34591.78 | M31: ='Юнит 23-29.03'!X$26 -> 153579.23 | Q31: ='Юнит 23-29.03'!AA$26 -> 64198.067 | R31: 65 | S31: 7549.42 | T31: =1148.4*F31/(F31+F32) -> 1040.4966 | X31: ='Юнит 23-29.03'!AD$26 -> 1665.1657 | Y31: =J31-SUM(L31:T31)-K31-V31+U31+W31 -> 77610.656 | Z31: =J31-SUM(L31:T31)-K31-X31+U31+W31-V31 -> 75945.491 | AB31: =K31/J31 -> 0.051871145 | AC31: =Z31/K31 -> 4.0993229 | AD31: =Z31/J31 -> 0.21263657 | AE31: =Q31/J31 -> 0.17974546
B32: 23-29.03 туники | C32: 13 | D32: =J32-SUM(L32:T32)+U32+V32+W32 -> 5243.0235 | E32: ='Юнит 23-29.03'!K$49 -> 37 | F32: ='Юнит 23-29.03'!P$49 -> 14 | G32: ='Юнит 23-29.03'!Q$49 -> 2 | H32: ='Юнит 23-29.03'!S$49 -> 54641 | I32: ='Юнит 23-29.03'!T$49 -> -11000 | J32: =H32+I32 -> 43641 | K32: ='Юнит 23-29.03'!W$49 -> 8019 | L32: ='Юнит 23-29.03'!Z$49 -> 6060.65 | M32: ='Юнит 23-29.03'!X$49 -> 18765.63 | Q32: ='Юнит 23-29.03'!AA$49 -> 12301.373 | R32: 25 | S32: 1137.42 | T32: =1148.4*F32/(F31+F32) -> 107.90336 | X32: ='Юнит 23-29.03'!AD$49 -> 203.46426 | Y32: =J32-SUM(L32:T32)-K32-V32+U32+W32 -> -2775.9765 | Z32: =J32-SUM(L32:T32)-K32-X32+U32+W32-V32 -> -2979.4407 | AB32: =K32/J32 -> 0.18374923 | AC32: =Z32/K32 -> -0.37154767 | AD32: =Z32/J32 -> -0.068271596 | AE32: =Q32/J32 -> 0.28187652
B33: 30-31.03 очки | C33: 14 | D33: =J33-SUM(L33:T33)+U33+V33 -> 0 | E33: ='Юнит 30-31.03'!K$26 -> 0 | F33: ='Юнит 30-31.03'!P$26 -> 0 | G33: ='Юнит 30-31.03'!Q$26 -> 0 | H33: ='Юнит 30-31.03'!S$26 -> 0 | I33: ='Юнит 30-31.03'!T$26 -> 0 | J33: =H33+I33 -> 0 | K33: ='Юнит 30-31.03'!W$26 -> 0 | L33: ='Юнит 30-31.03'!Z$26 -> 0 | M33: ='Юнит 30-31.03'!X$26 -> 0 | Q33: ='Юнит 30-31.03'!AA$26 -> 0 | X33: ='Юнит 30-31.03'!AD$26 -> 0 | Y33: =J33-SUM(L33:T33)-K33-V33+U33+W33 -> 0 | Z33: =J33-SUM(L33:T33)-K33-X33+U33+W33-V33 -> 0 | AB33: =K33/J33 -> #DIV/0! | AC33: =Z33/K33 -> #DIV/0! | AD33: =Z33/J33 -> #DIV/0! | AE33: =Q33/J33 -> #DIV/0!
B34: 30-31.03 туники | C34: 14 | D34: =J34-SUM(L34:T34)+U34+V34+W34 -> 0 | E34: ='Юнит 30-31.03'!K$49 -> 0 | F34: ='Юнит 30-31.03'!P$49 -> 0 | G34: ='Юнит 30-31.03'!Q$49 -> 0 | H34: ='Юнит 30-31.03'!S$49 -> 0 | I34: ='Юнит 30-31.03'!T$49 -> 0 | J34: =H34+I34 -> 0 | K34: ='Юнит 30-31.03'!W$49 -> 0 | L34: ='Юнит 30-31.03'!Z$49 -> 0 | M34: ='Юнит 30-31.03'!X$49 -> 0 | Q34: ='Юнит 30-31.03'!AA$49 -> 0 | X34: ='Юнит 30-31.03'!AD$49 -> 0 | Y34: =J34-SUM(L34:T34)-K34-V34+U34+W34 -> 0 | Z34: =J34-SUM(L34:T34)-K34-X34+U34+W34-V34 -> 0 | AB34: =K34/J34 -> #DIV/0! | AC34: =Z34/K34 -> #DIV/0! | AD34: =Z34/J34 -> #DIV/0! | AE34: =Q34/J34 -> #DIV/0!
B35: 01-05.04 очки | C35: 15 | D35: =J35-SUM(L35:T35)+U35+V35 -> 0 | E35: ='Юнит 01-05.04'!K$26 -> 0 | F35: ='Юнит 01-05.04'!P$26 -> 0 | G35: ='Юнит 01-05.04'!Q$26 -> 0 | H35: ='Юнит 01-05.04'!S$26 -> 0 | I35: ='Юнит 01-05.04'!T$26 -> 0 | J35: =H35+I35 -> 0 | K35: ='Юнит 01-05.04'!W$26 -> 0 | L35: ='Юнит 01-05.04'!Z$26 -> 0 | M35: ='Юнит 01-05.04'!X$26 -> 0 | Q35: ='Юнит 01-05.04'!AA$26 -> 0 | X35: ='Юнит 01-05.04'!AD$26 -> 0 | Y35: =J35-SUM(L35:T35)-K35-V35+U35+W35 -> 0 | Z35: =J35-SUM(L35:T35)-K35-X35+U35+W35-V35 -> 0
B36: 01-05.04 туники | C36: 15 | D36: =J36-SUM(L36:T36)+U36+V36+W36 -> 0 | E36: ='Юнит 01-05.04'!K$49 -> 0 | F36: ='Юнит 01-05.04'!P$49 -> 0 | G36: ='Юнит 01-05.04'!Q$49 -> 0 | H36: ='Юнит 01-05.04'!S$49 -> 0 | I36: ='Юнит 01-05.04'!T$49 -> 0 | J36: =H36+I36 -> 0 | K36: ='Юнит 01-05.04'!W$49 -> 0 | L36: ='Юнит 01-05.04'!Z$49 -> 0 | M36: ='Юнит 01-05.04'!X$49 -> 0 | Q36: ='Юнит 01-05.04'!AA$49 -> 0 | X36: ='Юнит 01-05.04'!AD$49 -> 0 | Y36: =J36-SUM(L36:T36)-K36-V36+U36+W36 -> 0 | Z36: =J36-SUM(L36:T36)-K36-X36+U36+W36-V36 -> 0
A39: Итого | D39: =SUM(D3:D38) -> 873238.87 | E39: =SUM(E3:E38) -> 2974 | F39: =SUM(F3:F38) -> 1434 | G39: =SUM(G3:G38) -> 79 | H39: =SUM(H3:H38) -> 3856660 | I39: =SUM(I3:I38) -> -261817 | J39: =SUM(J3:J38) -> 3594843 | K39: =SUM(K3:K38) -> 307213.14 | ... AA39: =SUM(AA3:AA38) -> 531064.79 | AB39: =K39/J39 -> 0.085459404 | AC39: =Z39/K39 -> 1.7286526 | AD39: =Z39/J39 -> 0.14772962 | AE39: =Q39/J39 -> 0.2080796
H40: % от выручки за весь период | AA40: Маржинальность, % | AB40: Рентабельность, %
I41: =-I39/H39 -> 0.06788698 | J41: 0 | K41: =K39/$J$39 -> 0.085459404 | L41: =L39/$J$39 -> 0.097428583 | M41: =M39/$J$39 -> 0.43 | Q41: =Q39/$J$39 -> 0.2080796 | R41: =R39/$J$39 -> 0.00017803281 | S41: =S39/$J$39 -> 0.020633886 | T41: =T39/$J$39 -> 0.0060581505 | U41: =U39/$J$39 -> 0 | V41: =V39/$J$39 -> 0.0038944677 | X41: =X39/$J$39 -> 0.0042847323 | AA41: =Z39/K39 -> 1.7286526 | AB41: =Z39/J39 -> 0.14772962
A43: январь очки | D43: =D3+D5+D7+D9+D11 -> 99346.768 | E43: =E3+E5+E7+E9+E11 -> 433 | F43: =F3+F5+F7+F9+F11 -> 278 | G43: =G3+G5+G7+G9+G11 -> 8 | H43: =H3+H5+H7+H9+H11 -> 454817 | I43: =I3+I5+I7+I9+I11 -> -12888 | J43: =J3+J5+J7+J9+J11 -> 441929 | K43: =K3+K5+K7+K9+K11 -> 39988.29 | ... Z43: =Z3+Z5+Z7+Z9+Z11 -> 32040.052 | AA43: =Z43/K43 -> 0.80123587 | AB43: =Z43/J43 -> 0.072500452
K44: =K43/$J$43 -> 0.090485779 | L44: =L43/$J$43 -> 0.11209491 | M44: =M43/$J$43 -> 0.43 | Q44: =Q43/$J$43 -> 0.21728943 | R44: =R43/$J$43 -> 0.00010182631 | S44: =S43/$J$43 -> 0.023925947 | T44: =T43/$J$43 -> 0.027628194 | U44: =U43/$J$43 -> 0 | V44: =V43/$J$43 -> 0.031679297 | X44: =X43/$J$43 -> 0.0042165729
A45: январь туники | D45: =D4+D6+D8+D10+D12 -> 50146.682 | E45: =E4+E6+E8+E10+E12 -> 165 | F45: =F4+F6+F8+F10+F12 -> 46 | G45: =G4+G6+G8+G10+G12 -> 4 | H45: =H4+H6+H8+H10+H12 -> 205934 | I45: =I4+I6+I8+I10+I12 -> -17932 | J45: =J4+J6+J8+J10+J12 -> 188002 | K45: =K4+K6+K8+K10+K12 -> 28164 | ... Z45: =Z4+Z6+Z8+Z10+Z12 -> 21189.958
A46: январь итого | D46: =D43+D45 -> 149493.45 | E46: =E43+E45 -> 598 | F46: =F43+F45 -> 324 | G46: =G43+G45 -> 12 | H46: =H43+H45 -> 660751 | I46: =I43+I45 -> -30820 | J46: =J43+J45 -> 629931 | K46: =K43+K45 -> 68152.29 | ... Z46: =Z43+Z45 -> 53230.01
A48: февраль очки | D48: =D13+D15+D17+D19+D21 -> 131884.8 | E48: =E13+E15+E17+E19+E21 -> 643 | F48: =F13+F15+F17+F19+F21 -> 316 | G48: =G13+G15+G17+G19+G21 -> 16 | H48: =H13+H15+H17+H19+H21 -> 662309 | I48: =I13+I15+I17+I19+I21 -> -34587 | J48: =J13+J15+J17+J19+J21 -> 627722 | K48: =K13+K15+K17+K19+K21 -> 42970.77 | ... Z48: =Z13+Z15+Z17+Z19+Z21 -> 87948.507 | AA48: =Z48/K48 -> 2.0467054 | AB48: =Z48/J48 -> 0.14010741
K49: =K48/$J$48 -> 0.068455096 | L49: =L48/$J$48 -> 0.10328203 | M49: =M48/$J$48 -> 0.43 | Q49: =Q48/$J$48 -> 0.22863571 | R49: =R48/$J$48 -> 0 | S49: =S48/$J$48 -> 0.024192302 | T49: =T48/$J$48 -> 0.0037893114 | U49: =U48/$J$48 -> 0 | V49: =V48/$J$48 -> 0 | X49: =X48/$J$48 -> 0.0045235351 | Z49: =Z48/K48 -> 2.0467054
A50: февраль туники | D50: =D14+D16+D18+D20+D22 -> 118643.32 | E50: =E14+E16+E18+E20+E22 -> 280 | F50: =F14+F16+F18+F20+F22 -> 96 | G50: =G14+G16+G18+G20+G22 -> 6 | H50: =H14+H16+H18+H20+H22 -> 489953 | I50: =I14+I16+I18+I20+I22 -> -29725 | J50: =J14+J16+J18+J20+J22 -> 460228 | K50: =K14+K16+K18+K20+K22 -> 57345 | ... Z50: =Z14+Z16+Z18+Z20+Z22 -> 59216.463
A51: февраль итого | D51: =D48+D50 -> 250528.12 | E51: =E48+E50 -> 923 | F51: =F48+F50 -> 412 | G51: =G48+G50 -> 22 | H51: =H48+H50 -> 1152262 | I51: =I48+I50 -> -64312 | J51: =J48+J50 -> 1087950 | K51: =K48+K50 -> 100315.77 | ... Z51: =Z48+Z50 -> 147164.97
A53: 5 неделя очки | K53: =(K11+K13)/($J$11+$J$13) -> 0.090449516 | L53: =(L11+L13)/($J$11+$J$13) -> 0.1162357 | M53: =(M11+M13)/($J$11+$J$13) -> 0.43 | N53: =(N11+N13)/($J$11+$J$13) -> 0 | O53: =(O11+O13)/($J$11+$J$13) -> 0 | P53: =(P11+P13)/($J$11+$J$13) -> 0 | Q53: =(Q11+Q13)/($J$11+$J$13) -> 0.17918528 | R53: =(R11+S11+T11+R13+S13+T13)/($J$11+$J$13) -> 0.076905027 | U53: =(U11+U13)/($J$11+$J$13) -> 0 | V53: =(V11+V13)/($J$11+$J$13) -> 0 | W53: =(W11+W13)/($J$11+$J$13) -> 0.0070786182 | X53: =(X11+X13)/($J$11+$J$13) -> 0.0042443095 | Y53: =(Y11+Y13)/($J$11+$J$13) -> 0.11430309 | AA53: =(Z11+Z13)/($J$11+$J$13) -> 0.11005878
A54: 6 неделя очки | K54: =K15/$J$15 -> 0.081746708 | L54: =L15/$J$15 -> 0.12530674 | M54: =M15/$J$15 -> 0.43 | Q54: =Q15/$J$15 -> 0.24274066 | R54: =(R15+S15+T15)/$J$15 -> 0.027844094 | U54: =U15/$J$15 -> 0 | V54: =V15/$J$15 -> 0 | X54: =X15/$J$15 -> 0.0045235351 | AA54: =Z15/K15 -> 1.0745174
A55: 7 неделя очки | K55: =K17/$J$17 -> 0.061562876 | L55: =L17/$J$17 -> 0.1132859 | M55: =M17/$J$17 -> 0.43 | Q55: =Q17/$J$17 -> 0.22342476 | R55: =(R17+S17+T17)/$J$17 -> 0.047172759 | U55: =U17/$J$17 -> 0 | V55: =V17/$J$17 -> 0 | X55: =X17/$J$17 -> 0.0045235351 | AA55: =Z17/K17 -> 1.9497169
A56: 8 неделя очки | K56: =K19/$J$19 -> 0.06620924 | L56: =L19/$J$19 -> 0.10120313 | M56: =M19/$J$19 -> 0.43 | Q56: =Q19/$J$19 -> 0.2215011 | R56: =(R19+S19+T19)/$J$19 -> 0.023752506 | U56: =U19/$J$19 -> 0 | V56: =V19/$J$19 -> 0 | X56: =X19/$J$19 -> 0.0045235351 | AA56: =Z19/K19 -> 2.3950625
A57: 9 неделя очки | K57: =(K21+K23)/($J$21+$J$23) -> 0.066401214 | L57: =(L21+L23)/($J$21+$J$23) -> 0.088514582 | M57: =(M21+M23)/($J$21+$J$23) -> 0.43 | N57: =(N21+N23)/($J$21+$J$23) -> 0 | O57: =(O21+O23)/($J$21+$J$23) -> 0 | P57: =(P21+P23)/($J$21+$J$23) -> 0 | Q57: =(Q21+Q23)/($J$21+$J$23) -> 0.22402814 | R57: =(R21+S21+T21+R23+S23+T23)/($J$21+$J$23) -> 0.020933586 | U57: =(U21+U23)/($J$21+$J$23) -> 0 | V57: =(V21+V23)/($J$21+$J$23) -> 0 | X57: =(X21+X23)/($J$21+$J$23) -> 0.0044850425 | AA57: =(Z21+Z23)/(K21+K23) -> 2.6462447 | AB57: =(Z21+Z23)/(J21+J23) -> 0.17571386
A58: 10 неделя очки | K58: =(K25)/($J$25) -> 0.05976974 | L58: =(L25)/($J$25) -> 0.10472776 | M58: =(M25)/($J$25) -> 0.43 | N58: =(N25)/($J$25) -> 0 | O58: =(O25)/($J$25) -> 0 | P58: =(P25)/($J$25) -> 0 | Q58: =(Q25)/($J$25) -> 0.24372091 | R58: =(R25+S25+T25)/($J$25) -> 0.033787932 | U58: =(U25)/($J$25) -> 0 | V58: =(V25)/($J$25) -> 0 | X58: =(X25)/($J$25) -> 0.0041340561 | AA58: =(Z25)/(K25) -> 2.0722795 | AB58: =(Z25)/(J25) -> 0.12385961
A59: 11 неделя очки | K59: =(K27)/($J$27) -> 0.054957867 | L59: =(L27)/($J$27) -> 0.08376756 | M59: =(M27)/($J$27) -> 0.43 | N59: =(N27)/($J$27) -> 0 | O59: =(O27)/($J$27) -> 0 | P59: =(P27)/($J$27) -> 0 | Q59: =(Q27)/($J$27) -> 0.17876642 | R59: =(R27+S27+T27)/($J$27) -> 0.024846624 | U59: =(U27)/($J$27) -> 0 | V59: =(V27)/($J$27) -> 0 | X59: =(X27)/($J$27) -> 0.0038452828 | AA59: =(Z27)/(K27) -> 4.072506 | AB59: =(Z27)/(J27) -> 0.22381624
A60: 12 неделя очки | K60: =(K29)/($J$29) -> 0.053388533 | L60: =(L29)/($J$29) -> 0.084653623 | M60: =(M29)/($J$29) -> 0.43 | N60: =(N29)/($J$29) -> 0 | O60: =(O29)/($J$29) -> 0 | P60: =(P29)/($J$29) -> 0 | Q60: =(Q29)/($J$29) -> 0.15870701 | R60: =(R29+S29+T29)/($J$29) -> 0.019485385 | U60: =(U29)/($J$29) -> 0 | V60: =(V29)/($J$29) -> 0 | X60: =(X29)/($J$29) -> 0.0041245242 | AA60: =(Z29)/(K29) -> 4.7343772 | AB60: =(Z29)/(J29) -> 0.25276145
A61: 13 неделя очки | K61: =(K31)/($J31) -> 0.051871145 | L61: =(L31)/($J31) -> 0.096852064 | M61: =(M31)/($J31) -> 0.43 | N61: =(N31)/($J31) -> 0 | O61: =(O31)/($J31) -> 0 | P61: =(P31)/($J31) -> 0 | Q61: =(Q31)/($J31) -> 0.17974546 | R61: =(R31+S31+T31)/($J31) -> 0.024232536 | U61: =(U31)/($J31) -> 0 | V61: =(V31)/($J31) -> 0 | X61: =(X31)/($J31) -> 0.0046622272 | AA61: =(Z31)/(K31) -> 4.0993229 | AB61: =(Z31)/(J31) -> 0.21263657
A63: март очки | D63: =D23+D25+D27+D29+D31+D33 -> 394646.89 | E63: =E23+E25+E27+E29+E31+E33 -> 1215 | F63: =F23+F25+F27+F29+F31+F33 -> 582 | G63: =G23+G25+G27+G29+G31+G33 -> 23 | H63: =H23+H25+H27+H29+H31+H33 -> 1513152 | I63: =I23+I25+I27+I29+I31+I33 -> -55729 | J63: =J23+J25+J27+J29+J31+J33 -> 1457423 | K63: =K23+K25+K27+K29+K31+K33 -> 79927.08 | ... Z63: =Z23+Z25+Z27+Z29+Z31+Z33 -> 312634.83 | AA63: =Z63/K63 -> 3.9115007 | AB63: =Z63/J63 -> 0.21451207
K64: =K63/$J$63 -> 0.054841374 | L64: =L63/$J$63 -> 0.091038497 | M64: =M63/$J$63 -> 0.43 | Q64: =Q63/$J$63 -> 0.18378608 | R64: =R63/$J$63 -> 0.00026759561 | S64: =S63/$J$63 -> 0.020657043 | T64: =T63/$J$63 -> 0.0034667382 | U64: =U63/$J$63 -> 0 | V64: =V63/$J$63 -> 0 | X64: =X63/$J$63 -> 0.0041909467 | Z64: =Z63/K63 -> 3.9115007
A65: март туники | D65: =D24+D26+D28+D30+D32+D34 -> 78570.411 | E65: =E24+E26+E28+E30+E32+E34 -> 238 | F65: =F24+F26+F28+F30+F32+F34 -> 116 | G65: =G24+G26+G28+G30+G32+G34 -> 22 | H65: =H24+H26+H28+H30+H32+H34 -> 530495 | I65: =I24+I26+I28+I30+I32+I34 -> -110956 | J65: =J24+J26+J28+J30+J32+J34 -> 419539 | K65: =K24+K26+K28+K30+K32+K34 -> 58818 | ... Z65: =Z24+Z26+Z28+Z30+Z32+Z34 -> 18034.983
A66: март итого | D66: =D63+D65 -> 473217.3 | E66: =E63+E65 -> 1453 | F66: =F63+F65 -> 698 | G66: =G63+G65 -> 45 | H66: =H63+H65 -> 2043647 | I66: =I63+I65 -> -166685 | J66: =J63+J65 -> 1876962 | K66: =K63+K65 -> 138745.08 | ... Z66: =Z63+Z65 -> 330669.81

Sheet АВС МАРТ
B2: ОЧКИ
C3: Прибыль | D3: % прибыль | E3: Доля | F3: ABC прибыль | G3: ABC кол-во | J3: Кол-во | K3: % кол-во | L3: Доля | M3: ABC кол-во
B4: черные с железкой классика | D4: =C4/C$26 -> #DIV/0! | E4: =D4 -> #DIV/0! | F4: =IF(AND(E4<=0),"C",IF(E4<=0.8,"A",IF(E4<=0.95,"B","C"))) -> #DIV/0! | G4: =VLOOKUP(B$4:B$25,I$4:M$25,5,0) -> #DIV/0! | I4: черные с железкой классика | K4: =J4/J$26 -> #DIV/0! | L4: =K4 -> #DIV/0! | M4: =_xlfn.IFS(L4<80%,"A",L4<=95%,"B",L4>95%,"C") -> #DIV/0!
B5: qs черные | D5: =C5/C$26 -> #DIV/0! | E5: =D5+E4 -> #DIV/0! | F5: =IF(AND(E5<=0),"C",IF(E5<=0.8,"A",IF(E5<=0.95,"B","C"))) -> #DIV/0! | G5: =VLOOKUP(B$4:B$25,I$4:M$25,5,0) -> #DIV/0! | I5: qs черные | K5: =J5/J$26 -> #DIV/0! | L5: =K5+L4 -> #DIV/0! | M5: =_xlfn.IFS(L5<80%,"A",L5<=95%,"B",L5>95%,"C") -> #DIV/0!
B6: qs синие | D6: =C6/C$26 -> #DIV/0! | E6: =D6+E5 -> #DIV/0! | F6: =IF(AND(E6<=0),"C",IF(E6<=0.8,"A",IF(E6<=0.95,"B","C"))) -> #DIV/0! | G6: =VLOOKUP(B$4:B$25,I$4:M$25,5,0) -> #DIV/0! | I6: qs синие | K6: =J6/J$26 -> #DIV/0! | L6: =K6+L5 -> #DIV/0! | M6: =_xlfn.IFS(L6<80%,"A",L6<=95%,"B",L6>95%,"C") -> #DIV/0!
B7: qs желтые | D7: =C7/C$26 -> #DIV/0! | E7: =D7+E6 -> #DIV/0! | F7: =IF(AND(E7<=0),"C",IF(E7<=0.8,"A",IF(E7<=0.95,"B","C"))) -> #DIV/0! | G7: =VLOOKUP(B$4:B$25,I$4:M$25,5,0) -> #DIV/0! | I7: qs желтые | K7: =J7/J$26 -> #DIV/0! | L7: =K7+L6 -> #DIV/0! | M7: =_xlfn.IFS(L7<80%,"A",L7<=95%,"B",L7>95%,"C") -> #DIV/0!
B8: qs коричневые | D8: =C8/C$26 -> #DIV/0! | E8: =D8+E7 -> #DIV/0! | F8: =IF(AND(E8<=0),"C",IF(E8<=0.8,"A",IF(E8<=0.95,"B","C"))) -> #DIV/0! | G8: =VLOOKUP(B$4:B$25,I$4:M$25,5,0) -> #DIV/0! | I8: qs коричневые | K8: =J8/J$26 -> #DIV/0! | L8: =K8+L7 -> #DIV/0! | M8: =_xlfn.IFS(L8<80%,"A",L8<=95%,"B",L8>95%,"C") -> #DIV/0!
B9: th желтый Сул | D9: =C9/C$26 -> #DIV/0! | E9: =D9+E8 -> #DIV/0! | F9: =IF(AND(E9<=0),"C",IF(E9<=0.8,"A",IF(E9<=0.95,"B","C"))) -> #DIV/0! | G9: =VLOOKUP(B$4:B$25,I$4:M$25,5,0) -> #DIV/0! | I9: th желтый Сул | K9: =J9/J$26 -> #DIV/0! | L9: =K9+L8 -> #DIV/0! | M9: =_xlfn.IFS(L9<80%,"A",L9<=95%,"B",L9>95%,"C") -> #DIV/0!
B10: flip желтые Сул | D10: =C10/C$26 -> #DIV/0! | E10: =D10+E9 -> #DIV/0! | F10: =IF(AND(E10<=0),"C",IF(E10<=0.8,"A",IF(E10<=0.95,"B","C"))) -> #DIV/0! | G10: =VLOOKUP(B$4:B$25,I$4:M$25,5,0) -> #DIV/0! | I10: flip желтые Сул | K10: =J10/J$26 -> #DIV/0! | L10: =K10+L9 -> #DIV/0! | M10: =_xlfn.IFS(L10<80%,"A",L10<=95%,"B",L10>95%,"C") -> #DIV/0!
B11: MR8854 C2 | D11: =C11/C$26 -> #DIV/0! | E11: =D11+E8 -> #DIV/0! | F11: =IF(AND(E11<=0),"C",IF(E11<=0.8,"A",IF(E11<=0.95,"B","C"))) -> #DIV/0! | G11: =VLOOKUP(B$4:B$25,I$4:M$25,5,0) -> #DIV/0! | I11: MR8854 C2 | K11: =J11/J$26 -> #DIV/0! | L11: =K11+L8 -> #DIV/0! | M11: =_xlfn.IFS(L11<80%,"A",L11<=95%,"B",L11>95%,"C") -> #DIV/0!
B12: MR 1819 черн | D12: =C12/C$26 -> #DIV/0! | E12: =D12+E11 -> #DIV/0! | F12: =IF(AND(E12<=0),"C",IF(E12<=0.8,"A",IF(E12<=0.95,"B","C"))) -> #DIV/0! | G12: =VLOOKUP(B$4:B$25,I$4:M$25,5,0) -> #DIV/0! | I12: MR 1819 черн | K12: =J12/J$26 -> #DIV/0! | L12: =K12+L11 -> #DIV/0! | M12: =_xlfn.IFS(L12<80%,"A",L12<=95%,"B",L12>95%,"C") -> #DIV/0!
B13: MR 1819 корич | D13: =C13/C$26 -> #DIV/0! | E13: =D13+E12 -> #DIV/0! | F13: =IF(AND(E13<=0),"C",IF(E13<=0.8,"A",IF(E13<=0.95,"B","C"))) -> #DIV/0! | G13: =VLOOKUP(B$4:B$25,I$4:M$25,5,0) -> #DIV/0! | I13: MR 1819 корич | K13: =J13/J$26 -> #DIV/0! | L13: =K13+L12 -> #DIV/0! | M13: =_xlfn.IFS(L13<80%,"A",L13<=95%,"B",L13>95%,"C") -> #DIV/0! | P13: A | Q13: 0.8
B14: MR Р1874 черн | D14: =C14/C$26 -> #DIV/0! | E14: =D14+E13 -> #DIV/0! | F14: =IF(AND(E14<=0),"C",IF(E14<=0.8,"A",IF(E14<=0.95,"B","C"))) -> #DIV/0! | G14: =VLOOKUP(B$4:B$25,I$4:M$25,5,0) -> #DIV/0! | I14: MR Р1874 черн | K14: =J14/J$26 -> #DIV/0! | L14: =K14+L13 -> #DIV/0! | M14: =_xlfn.IFS(L14<80%,"A",L14<=95%,"B",L14>95%,"C") -> #DIV/0! | P14: B | Q14: 0.15
B15: MR Р1874 корич | D15: =C15/C$26 -> #DIV/0! | E15: =D15+E14 -> #DIV/0! | F15: =IF(AND(E15<=0),"C",IF(E15<=0.8,"A",IF(E15<=0.95,"B","C"))) -> #DIV/0! | G15: =VLOOKUP(B$4:B$25,I$4:M$25,5,0) -> #DIV/0! | I15: MR Р1874 корич | K15: =J15/J$26 -> #DIV/0! | L15: =K15+L14 -> #DIV/0! | M15: =_xlfn.IFS(L15<80%,"A",L15<=95%,"B",L15>95%,"C") -> #DIV/0! | P15: C | Q15: 0.05
B16: MR Р1886 черн глянец | D16: =C16/C$26 -> #DIV/0! | E16: =D16+E15 -> #DIV/0! | F16: =IF(AND(E16<=0),"C",IF(E16<=0.8,"A",IF(E16<=0.95,"B","C"))) -> #DIV/0! | G16: =VLOOKUP(B$4:B$25,I$4:M$25,5,0) -> #DIV/0! | I16: MR Р1886 черн глянец | K16: =J16/J$26 -> #DIV/0! | L16: =K16+L15 -> #DIV/0! | M16: =_xlfn.IFS(L16<80%,"A",L16<=95%,"B",L16>95%,"C") -> #DIV/0!
B17: MR Р1886 корич | D17: =C17/C$26 -> #DIV/0! | E17: =D17+E16 -> #DIV/0! | F17: =IF(AND(E17<=0),"C",IF(E17<=0.8,"A",IF(E17<=0.95,"B","C"))) -> #DIV/0! | G17: =VLOOKUP(B$4:B$25,I$4:M$25,5,0) -> #DIV/0! | I17: MR Р1886 корич | K17: =J17/J$26 -> #DIV/0! | L17: =K17+L16 -> #DIV/0! | M17: =_xlfn.IFS(L17<80%,"A",L17<=95%,"B",L17>95%,"C") -> #DIV/0!
B18: lux1 | D18: =C18/C$26 -> #DIV/0! | E18: =D18+E17 -> #DIV/0! | F18: =IF(AND(E18<=0),"C",IF(E18<=0.8,"A",IF(E18<=0.95,"B","C"))) -> #DIV/0! | G18: =VLOOKUP(B$4:B$25,I$4:M$25,5,0) -> #DIV/0! | I18: lux1 | K18: =J18/J$26 -> #DIV/0! | L18: =K18+L17 -> #DIV/0! | M18: =_xlfn.IFS(L18<80%,"A",L18<=95%,"B",L18>95%,"C") -> #DIV/0!
B19: lux2 | D19: =C19/C$26 -> #DIV/0! | E19: =D19+E18 -> #DIV/0! | F19: =IF(AND(E19<=0),"C",IF(E19<=0.8,"A",IF(E19<=0.95,"B","C"))) -> #DIV/0! | G19: =VLOOKUP(B$4:B$25,I$4:M$25,5,0) -> #DIV/0! | I19: lux2 | K19: =J19/J$26 -> #DIV/0! | L19: =K19+L18 -> #DIV/0! | M19: =_xlfn.IFS(L19<80%,"A",L19<=95%,"B",L19>95%,"C") -> #DIV/0!
B20: lux3 | D20: =C20/C$26 -> #DIV/0! | E20: =D20+E19 -> #DIV/0! | F20: =IF(AND(E20<=0),"C",IF(E20<=0.8,"A",IF(E20<=0.95,"B","C"))) -> #DIV/0! | G20: =VLOOKUP(B$4:B$25,I$4:M$25,5,0) -> #DIV/0! | I20: lux3 | K20: =J20/J$26 -> #DIV/0! | L20: =K20+L19 -> #DIV/0! | M20: =_xlfn.IFS(L20<80%,"A",L20<=95%,"B",L20>95%,"C") -> #DIV/0!
B21: lux4 | D21: =C21/C$26 -> #DIV/0! | E21: =D21+E20 -> #DIV/0! | F21: =IF(AND(E21<=0),"C",IF(E21<=0.8,"A",IF(E21<=0.95,"B","C"))) -> #DIV/0! | G21: =VLOOKUP(B$4:B$25,I$4:M$25,5,0) -> #DIV/0! | I21: lux4 | K21: =J21/J$26 -> #DIV/0! | L21: =K21+L20 -> #DIV/0! | M21: =_xlfn.IFS(L21<80%,"A",L21<=95%,"B",L21>95%,"C") -> #DIV/0!
B22: lux5 | D22: =C22/C$26 -> #DIV/0! | E22: =D22+E21 -> #DIV/0! | F22: =IF(AND(E22<=0),"C",IF(E22<=0.8,"A",IF(E22<=0.95,"B","C"))) -> #DIV/0! | G22: =VLOOKUP(B$4:B$25,I$4:M$25,5,0) -> #DIV/0! | I22: lux5 | K22: =J22/J$26 -> #DIV/0! | L22: =K22+L21 -> #DIV/0! | M22: =_xlfn.IFS(L22<80%,"A",L22<=95%,"B",L22>95%,"C") -> #DIV/0!
B23: lux6 | D23: =C23/C$26 -> #DIV/0! | E23: =D23+E22 -> #DIV/0! | F23: =IF(AND(E23<=0),"C",IF(E23<=0.8,"A",IF(E23<=0.95,"B","C"))) -> #DIV/0! | G23: =VLOOKUP(B$4:B$25,I$4:M$25,5,0) -> #DIV/0! | I23: lux6 | K23: =J23/J$26 -> #DIV/0! | L23: =K23+L22 -> #DIV/0! | M23: =_xlfn.IFS(L23<80%,"A",L23<=95%,"B",L23>95%,"C") -> #DIV/0!
B24: lux7 | D24: =C24/C$26 -> #DIV/0! | E24: =D24+E23 -> #DIV/0! | F24: =IF(AND(E24<=0),"C",IF(E24<=0.8,"A",IF(E24<=0.95,"B","C"))) -> #DIV/0! | G24: =VLOOKUP(B$4:B$25,I$4:M$25,5,0) -> #DIV/0! | I24: lux7 | K24: =J24/J$26 -> #DIV/0! | L24: =K24+L23 -> #DIV/0! | M24: =_xlfn.IFS(L24<80%,"A",L24<=95%,"B",L24>95%,"C") -> #DIV/0!
B25: lux8 | D25: =C25/C$26 -> #DIV/0! | E25: =D25+E24 -> #DIV/0! | F25: =IF(AND(E25<=0),"C",IF(E25<=0.8,"A",IF(E25<=0.95,"B","C"))) -> #DIV/0! | G25: =VLOOKUP(B$4:B$25,I$4:M$25,5,0) -> #DIV/0! | I25: lux8 | K25: =J25/J$26 -> #DIV/0! | L25: =K25+L24 -> #DIV/0! | M25: =_xlfn.IFS(L25<80%,"A",L25<=95%,"B",L25>95%,"C") -> #DIV/0!
C26: =SUM(C4:C25) -> 0 | D26: =SUM(D4:D25) -> #DIV/0! | J26: =SUM(J4:J25) -> 0 | K26: =SUM(K4:K25) -> #DIV/0!
B28: ТУНИКИ
C29: Прибыль | D29: % прибыль | E29: Доля | F29: ABC прибыль | G29: ABC кол-во | J29: Кол-во | K29: % кол-во | L29: Доля | M29: ABC кол-во
B30: tunika02 оливковая с руч вышивкой | D30: =C30/C$50 -> #DIV/0! | E30: =D30 -> #DIV/0! | F30: =IF(AND(E30<=0),"C",IF(E30<=0.8,"A",IF(E30<=0.95,"B","C"))) -> #DIV/0! | G30: =VLOOKUP(B$30:B$50,I$30:M$50,5,0) -> #DIV/0! | I30: tunika02 оливковая с руч вышивкой | K30: =J30/J$50 -> #DIV/0! | L30: =K30 -> #DIV/0! | M30: =_xlfn.IFS(L30<80%,"A",L30<=95%,"B",L30>95%,"C") -> #DIV/0!
B31: tunika03 черная распашная | D31: =C31/C$50 -> #DIV/0! | E31: =D31+E30 -> #DIV/0! | F31: =IF(AND(E31<=0),"C",IF(E31<=0.8,"A",IF(E31<=0.95,"B","C"))) -> #DIV/0! | G31: =VLOOKUP(B$30:B$50,I$30:M$50,5,0) -> #DIV/0! | I31: tunika03 черная распашная | K31: =J31/J$50 -> #DIV/0! | L31: =K31+L30 -> #DIV/0! | M31: =_xlfn.IFS(L31<80%,"A",L31<=95%,"B",L31>95%,"C") -> #DIV/0!
B32: tunika05 белая распашная | D32: =C32/C$50 -> #DIV/0! | E32: =D32+E31 -> #DIV/0! | F32: =IF(AND(E32<=0),"C",IF(E32<=0.8,"A",IF(E32<=0.95,"B","C"))) -> #DIV/0! | G32: =VLOOKUP(B$30:B$50,I$30:M$50,5,0) -> #DIV/0! | I32: tunika05 белая распашная | K32: =J32/J$50 -> #DIV/0! | L32: =K32+L31 -> #DIV/0! | M32: =_xlfn.IFS(L32<80%,"A",L32<=95%,"B",L32>95%,"C") -> #DIV/0!
B33: tunika06 белая | D33: =C33/C$50 -> #DIV/0! | E33: =D33+E32 -> #DIV/0! | F33: =IF(AND(E33<=0),"C",IF(E33<=0.8,"A",IF(E33<=0.95,"B","C"))) -> #DIV/0! | G33: =VLOOKUP(B$30:B$50,I$30:M$50,5,0) -> #DIV/0! | I33: tunika06 белая | K33: =J33/J$50 -> #DIV/0! | L33: =K33+L32 -> #DIV/0! | M33: =_xlfn.IFS(L33<80%,"A",L33<=95%,"B",L33>95%,"C") -> #DIV/0!
B34: tunika06 черная | D34: =C34/C$50 -> #DIV/0! | E34: =D34+E33 -> #DIV/0! | F34: =IF(AND(E34<=0),"C",IF(E34<=0.8,"A",IF(E34<=0.95,"B","C"))) -> #DIV/0! | G34: =VLOOKUP(B$30:B$50,I$30:M$50,5,0) -> #DIV/0! | I34: tunika06 черная | K34: =J34/J$50 -> #DIV/0! | L34: =K34+L33 -> #DIV/0! | M34: =_xlfn.IFS(L34<80%,"A",L34<=95%,"B",L34>95%,"C") -> #DIV/0!
B35: tunika07 кружево | D35: =C35/C$50 -> #DIV/0! | E35: =D35+E34 -> #DIV/0! | F35: =IF(AND(E35<=0),"C",IF(E35<=0.8,"A",IF(E35<=0.95,"B","C"))) -> #DIV/0! | G35: =VLOOKUP(B$30:B$50,I$30:M$50,5,0) -> #DIV/0! | I35: tunika07 кружево | K35: =J35/J$50 -> #DIV/0! | L35: =K35+L34 -> #DIV/0! | M35: =_xlfn.IFS(L35<80%,"A",L35<=95%,"B",L35>95%,"C") -> #DIV/0!
B36: tunika08 белая | D36: =C36/C$50 -> #DIV/0! | E36: =D36+E35 -> #DIV/0! | F36: =IF(AND(E36<=0),"C",IF(E36<=0.8,"A",IF(E36<=0.95,"B","C"))) -> #DIV/0! | G36: =VLOOKUP(B$30:B$50,I$30:M$50,5,0) -> #DIV/0! | I36: tunika08 белая | K36: =J36/J$50 -> #DIV/0! | L36: =K36+L35 -> #DIV/0! | M36: =_xlfn.IFS(L36<80%,"A",L36<=95%,"B",L36>95%,"C") -> #DIV/0!
B37: tunika08 черная | D37: =C37/C$50 -> #DIV/0! | E37: =D37+E36 -> #DIV/0! | F37: =IF(AND(E37<=0),"C",IF(E37<=0.8,"A",IF(E37<=0.95,"B","C"))) -> #DIV/0! | G37: =VLOOKUP(B$30:B$50,I$30:M$50,5,0) -> #DIV/0! | I37: tunika08 черная | K37: =J37/J$50 -> #DIV/0! | L37: =K37+L36 -> #DIV/0! | M37: =_xlfn.IFS(L37<80%,"A",L37<=95%,"B",L37>95%,"C") -> #DIV/0!
B38: tunika08 зеленая | D38: =C38/C$50 -> #DIV/0! | E38: =D38+E37 -> #DIV/0! | F38: =IF(AND(E38<=0),"C",IF(E38<=0.8,"A",IF(E38<=0.95,"B","C"))) -> #DIV/0! | G38: =VLOOKUP(B$30:B$50,I$30:M$50,5,0) -> #DIV/0! | I38: tunika08 зеленая | K38: =J38/J$50 -> #DIV/0! | L38: =K38+L37 -> #DIV/0! | M38: =_xlfn.IFS(L38<80%,"A",L38<=95%,"B",L38>95%,"C") -> #DIV/0!
B39: tunika09 кимоно | D39: =C39/C$50 -> #DIV/0! | E39: =D39+E38 -> #DIV/0! | F39: =IF(AND(E39<=0),"C",IF(E39<=0.8,"A",IF(E39<=0.95,"B","C"))) -> #DIV/0! | G39: =VLOOKUP(B$30:B$50,I$30:M$50,5,0) -> #DIV/0! | I39: tunika09 кимоно | K39: =J39/J$50 -> #DIV/0! | L39: =K39+L38 -> #DIV/0! | M39: =_xlfn.IFS(L39<80%,"A",L39<=95%,"B",L39>95%,"C") -> #DIV/0!
B40: tunika10 кимоно ч/б | D40: =C40/C$50 -> #DIV/0! | E40: =D40+E39 -> #DIV/0! | F40: =IF(AND(E40<=0),"C",IF(E40<=0.8,"A",IF(E40<=0.95,"B","C"))) -> #DIV/0! | G40: =VLOOKUP(B$30:B$50,I$30:M$50,5,0) -> #DIV/0! | I40: tunika10 кимоно ч/б | K40: =J40/J$50 -> #DIV/0! | L40: =K40+L39 -> #DIV/0! | M40: =_xlfn.IFS(L40<80%,"A",L40<=95%,"B",L40>95%,"C") -> #DIV/0!
B41: tunika11 халат зеленая | D41: =C41/C$50 -> #DIV/0! | E41: =D41+E40 -> #DIV/0! | F41: =IF(AND(E41<=0),"C",IF(E41<=0.8,"A",IF(E41<=0.95,"B","C"))) -> #DIV/0! | G41: =VLOOKUP(B$30:B$50,I$30:M$50,5,0) -> #DIV/0! | I41: tunika11 халат зеленая | K41: =J41/J$50 -> #DIV/0! | L41: =K41+L40 -> #DIV/0! | M41: =_xlfn.IFS(L41<80%,"A",L41<=95%,"B",L41>95%,"C") -> #DIV/0!
B42: tunika12 халат белая | D42: =C42/C$50 -> #DIV/0! | E42: =D42+E41 -> #DIV/0! | F42: =IF(AND(E42<=0),"C",IF(E42<=0.8,"A",IF(E42<=0.95,"B","C"))) -> #DIV/0! | G42: =VLOOKUP(B$30:B$50,I$30:M$50,5,0) -> #DIV/0! | I42: tunika12 халат белая | K42: =J42/J$50 -> #DIV/0! | L42: =K42+L41 -> #DIV/0! | M42: =_xlfn.IFS(L42<80%,"A",L42<=95%,"B",L42>95%,"C") -> #DIV/0!
... B49: tunika16 сетка черная | D49: =C49/C$50 -> #DIV/0! | E49: =D49+E48 -> #DIV/0! | F49: =IF(AND(E49<=0),"C",IF(E49<=0.8,"A",IF(E49<=0.95,"B","C"))) -> #DIV/0! | G49: =VLOOKUP(B$30:B$50,I$30:M$50,5,0) -> #DIV/0! | I49: tunika16 сетка черная | K49: =J49/J$50 -> #DIV/0! | L49: =K49+L48 -> #DIV/0! | M49: =_xlfn.IFS(L49<80%,"A",L49<=95%,"B",L49>95%,"C") -> #DIV/0!
C50: =SUM(C30:C49) -> 0 | D50: =SUM(D30:D49) -> #DIV/0! | J50: =SUM(J30:J49) -> 0 | K50: =SUM(K30:K49) -> #DIV/0!

Sheet АВС 30-31.03
B2: ОЧКИ
C3: Прибыль | D3: % прибыль | E3: Доля | F3: ABC прибыль | G3: ABC кол-во | J3: Кол-во | K3: % кол-во | L3: Доля | M3: ABC кол-во
B4: черные с железкой классика | D4: =C4/C$26 -> #DIV/0! | E4: =D4 -> #DIV/0! | F4: =IF(AND(E4<=0),"C",IF(E4<=0.8,"A",IF(E4<=0.95,"B","C"))) -> #DIV/0! | G4: =VLOOKUP(B$4:B$25,I$4:M$25,5,0) -> #DIV/0! | I4: черные с железкой классика | K4: =J4/J$26 -> #DIV/0! | L4: =K4 -> #DIV/0! | M4: =_xlfn.IFS(L4<80%,"A",L4<=95%,"B",L4>95%,"C") -> #DIV/0!
B5: qs черные | D5: =C5/C$26 -> #DIV/0! | E5: =D5+E4 -> #DIV/0! | F5: =IF(AND(E5<=0),"C",IF(E5<=0.8,"A",IF(E5<=0.95,"B","C"))) -> #DIV/0! | G5: =VLOOKUP(B$4:B$25,I$4:M$25,5,0) -> #DIV/0! | I5: qs черные | K5: =J5/J$26 -> #DIV/0! | L5: =K5+L4 -> #DIV/0! | M5: =_xlfn.IFS(L5<80%,"A",L5<=95%,"B",L5>95%,"C") -> #DIV/0!
B6: qs синие | D6: =C6/C$26 -> #DIV/0! | E6: =D6+E5 -> #DIV/0! | F6: =IF(AND(E6<=0),"C",IF(E6<=0.8,"A",IF(E6<=0.95,"B","C"))) -> #DIV/0! | G6: =VLOOKUP(B$4:B$25,I$4:M$25,5,0) -> #DIV/0! | I6: qs синие | K6: =J6/J$26 -> #DIV/0! | L6: =K6+L5 -> #DIV/0! | M6: =_xlfn.IFS(L6<80%,"A",L6<=95%,"B",L6>95%,"C") -> #DIV/0!
B7: qs желтые | D7: =C7/C$26 -> #DIV/0! | E7: =D7+E6 -> #DIV/0! | F7: =IF(AND(E7<=0),"C",IF(E7<=0.8,"A",IF(E7<=0.95,"B","C"))) -> #DIV/0! | G7: =VLOOKUP(B$4:B$25,I$4:M$25,5,0) -> #DIV/0! | I7: qs желтые | K7: =J7/J$26 -> #DIV/0! | L7: =K7+L6 -> #DIV/0! | M7: =_xlfn.IFS(L7<80%,"A",L7<=95%,"B",L7>95%,"C") -> #DIV/0!
B8: qs коричневые | D8: =C8/C$26 -> #DIV/0! | E8: =D8+E7 -> #DIV/0! | F8: =IF(AND(E8<=0),"C",IF(E8<=0.8,"A",IF(E8<=0.95,"B","C"))) -> #DIV/0! | G8: =VLOOKUP(B$4:B$25,I$4:M$25,5,0) -> #DIV/0! | I8: qs коричневые | K8: =J8/J$26 -> #DIV/0! | L8: =K8+L7 -> #DIV/0! | M8: =_xlfn.IFS(L8<80%,"A",L8<=95%,"B",L8>95%,"C") -> #DIV/0!
B9: th желтый Сул | D9: =C9/C$26 -> #DIV/0! | E9: =D9+E8 -> #DIV/0! | F9: =IF(AND(E9<=0),"C",IF(E9<=0.8,"A",IF(E9<=0.95,"B","C"))) -> #DIV/0! | G9: =VLOOKUP(B$4:B$25,I$4:M$25,5,0) -> #DIV/0! | I9: th желтый Сул | K9: =J9/J$26 -> #DIV/0! | L9: =K9+L8 -> #DIV/0! | M9: =_xlfn.IFS(L9<80%,"A",L9<=95%,"B",L9>95%,"C") -> #DIV/0!
B10: flip желтые Сул | D10: =C10/C$26 -> #DIV/0! | E10: =D10+E9 -> #DIV/0! | F10: =IF(AND(E10<=0),"C",IF(E10<=0.8,"A",IF(E10<=0.95,"B","C"))) -> #DIV/0! | G10: =VLOOKUP(B$4:B$25,I$4:M$25,5,0) -> #DIV/0! | I10: flip желтые Сул | K10: =J10/J$26 -> #DIV/0! | L10: =K10+L9 -> #DIV/0! | M10: =_xlfn.IFS(L10<80%,"A",L10<=95%,"B",L10>95%,"C") -> #DIV/0!
B11: MR8854 C2 | D11: =C11/C$26 -> #DIV/0! | E11: =D11+E8 -> #DIV/0! | F11: =IF(AND(E11<=0),"C",IF(E11<=0.8,"A",IF(E11<=0.95,"B","C"))) -> #DIV/0! | G11: =VLOOKUP(B$4:B$25,I$4:M$25,5,0) -> #DIV/0! | I11: MR8854 C2 | K11: =J11/J$26 -> #DIV/0! | L11: =K11+L8 -> #DIV/0! | M11: =_xlfn.IFS(L11<80%,"A",L11<=95%,"B",L11>95%,"C") -> #DIV/0!
B12: MR 1819 черн | D12: =C12/C$26 -> #DIV/0! | E12: =D12+E11 -> #DIV/0! | F12: =IF(AND(E12<=0),"C",IF(E12<=0.8,"A",IF(E12<=0.95,"B","C"))) -> #DIV/0! | G12: =VLOOKUP(B$4:B$25,I$4:M$25,5,0) -> #DIV/0! | I12: MR 1819 черн | K12: =J12/J$26 -> #DIV/0! | L12: =K12+L11 -> #DIV/0! | M12: =_xlfn.IFS(L12<80%,"A",L12<=95%,"B",L12>95%,"C") -> #DIV/0!
B13: MR 1819 корич | D13: =C13/C$26 -> #DIV/0! | E13: =D13+E12 -> #DIV/0! | F13: =IF(AND(E13<=0),"C",IF(E13<=0.8,"A",IF(E13<=0.95,"B","C"))) -> #DIV/0! | G13: =VLOOKUP(B$4:B$25,I$4:M$25,5,0) -> #DIV/0! | I13: MR 1819 корич | K13: =J13/J$26 -> #DIV/0! | L13: =K13+L12 -> #DIV/0! | M13: =_xlfn.IFS(L13<80%,"A",L13<=95%,"B",L13>95%,"C") -> #DIV/0! | P13: A | Q13: 0.8
B14: MR Р1874 черн | D14: =C14/C$26 -> #DIV/0! | E14: =D14+E13 -> #DIV/0! | F14: =IF(AND(E14<=0),"C",IF(E14<=0.8,"A",IF(E14<=0.95,"B","C"))) -> #DIV/0! | G14: =VLOOKUP(B$4:B$25,I$4:M$25,5,0) -> #DIV/0! | I14: MR Р1874 черн | K14: =J14/J$26 -> #DIV/0! | L14: =K14+L13 -> #DIV/0! | M14: =_xlfn.IFS(L14<80%,"A",L14<=95%,"B",L14>95%,"C") -> #DIV/0! | P14: B | Q14: 0.15
B15: MR Р1874 корич | D15: =C15/C$26 -> #DIV/0! | E15: =D15+E14 -> #DIV/0! | F15: =IF(AND(E15<=0),"C",IF(E15<=0.8,"A",IF(E15<=0.95,"B","C"))) -> #DIV/0! | G15: =VLOOKUP(B$4:B$25,I$4:M$25,5,0) -> #DIV/0! | I15: MR Р1874 корич | K15: =J15/J$26 -> #DIV/0! | L15: =K15+L14 -> #DIV/0! | M15: =_xlfn.IFS(L15<80%,"A",L15<=95%,"B",L15>95%,"C") -> #DIV/0! | P15: C | Q15: 0.05
B16: MR Р1886 черн глянец | D16: =C16/C$26 -> #DIV/0! | E16: =D16+E15 -> #DIV/0! | F16: =IF(AND(E16<=0),"C",IF(E16<=0.8,"A",IF(E16<=0.95,"B","C"))) -> #DIV/0! | G16: =VLOOKUP(B$4:B$25,I$4:M$25,5,0) -> #DIV/0! | I16: MR Р1886 черн глянец | K16: =J16/J$26 -> #DIV/0! | L16: =K16+L15 -> #DIV/0! | M16: =_xlfn.IFS(L16<80%,"A",L16<=95%,"B",L16>95%,"C") -> #DIV/0!
B17: MR Р1886 корич | D17: =C17/C$26 -> #DIV/0! | E17: =D17+E16 -> #DIV/0! | F17: =IF(AND(E17<=0),"C",IF(E17<=0.8,"A",IF(E17<=0.95,"B","C"))) -> #DIV/0! | G17: =VLOOKUP(B$4:B$25,I$4:M$25,5,0) -> #DIV/0! | I17: MR Р1886 корич | K17: =J17/J$26 -> #DIV/0! | L17: =K17+L16 -> #DIV/0! | M17: =_xlfn.IFS(L17<80%,"A",L17<=95%,"B",L17>95%,"C") -> #DIV/0!
B18: lux1 | D18: =C18/C$26 -> #DIV/0! | E18: =D18+E17 -> #DIV/0! | F18: =IF(AND(E18<=0),"C",IF(E18<=0.8,"A",IF(E18<=0.95,"B","C"))) -> #DIV/0! | G18: =VLOOKUP(B$4:B$25,I$4:M$25,5,0) -> #DIV/0! | I18: lux1 | K18: =J18/J$26 -> #DIV/0! | L18: =K18+L17 -> #DIV/0! | M18: =_xlfn.IFS(L18<80%,"A",L18<=95%,"B",L18>95%,"C") -> #DIV/0!
B19: lux2 | D19: =C19/C$26 -> #DIV/0! | E19: =D19+E18 -> #DIV/0! | F19: =IF(AND(E19<=0),"C",IF(E19<=0.8,"A",IF(E19<=0.95,"B","C"))) -> #DIV/0! | G19: =VLOOKUP(B$4:B$25,I$4:M$25,5,0) -> #DIV/0! | I19: lux2 | K19: =J19/J$26 -> #DIV/0! | L19: =K19+L18 -> #DIV/0! | M19: =_xlfn.IFS(L19<80%,"A",L19<=95%,"B",L19>95%,"C") -> #DIV/0!
B20: lux3 | D20: =C20/C$26 -> #DIV/0! | E20: =D20+E19 -> #DIV/0! | F20: =IF(AND(E20<=0),"C",IF(E20<=0.8,"A",IF(E20<=0.95,"B","C"))) -> #DIV/0! | G20: =VLOOKUP(B$4:B$25,I$4:M$25,5,0) -> #DIV/0! | I20: lux3 | K20: =J20/J$26 -> #DIV/0! | L20: =K20+L19 -> #DIV/0! | M20: =_xlfn.IFS(L20<80%,"A",L20<=95%,"B",L20>95%,"C") -> #DIV/0!
B21: lux4 | D21: =C21/C$26 -> #DIV/0! | E21: =D21+E20 -> #DIV/0! | F21: =IF(AND(E21<=0),"C",IF(E21<=0.8,"A",IF(E21<=0.95,"B","C"))) -> #DIV/0! | G21: =VLOOKUP(B$4:B$25,I$4:M$25,5,0) -> #DIV/0! | I21: lux4 | K21: =J21/J$26 -> #DIV/0! | L21: =K21+L20 -> #DIV/0! | M21: =_xlfn.IFS(L21<80%,"A",L21<=95%,"B",L21>95%,"C") -> #DIV/0!
B22: lux5 | D22: =C22/C$26 -> #DIV/0! | E22: =D22+E21 -> #DIV/0! | F22: =IF(AND(E22<=0),"C",IF(E22<=0.8,"A",IF(E22<=0.95,"B","C"))) -> #DIV/0! | G22: =VLOOKUP(B$4:B$25,I$4:M$25,5,0) -> #DIV/0! | I22: lux5 | K22: =J22/J$26 -> #DIV/0! | L22: =K22+L21 -> #DIV/0! | M22: =_xlfn.IFS(L22<80%,"A",L22<=95%,"B",L22>95%,"C") -> #DIV/0!
B23: lux6 | D23: =C23/C$26 -> #DIV/0! | E23: =D23+E22 -> #DIV/0! | F23: =IF(AND(E23<=0),"C",IF(E23<=0.8,"A",IF(E23<=0.95,"B","C"))) -> #DIV/0! | G23: =VLOOKUP(B$4:B$25,I$4:M$25,5,0) -> #DIV/0! | I23: lux6 | K23: =J23/J$26 -> #DIV/0! | L23: =K23+L22 -> #DIV/0! | M23: =_xlfn.IFS(L23<80%,"A",L23<=95%,"B",L23>95%,"C") -> #DIV/0!
B24: lux7 | D24: =C24/C$26 -> #DIV/0! | E24: =D24+E23 -> #DIV/0! | F24: =IF(AND(E24<=0),"C",IF(E24<=0.8,"A",IF(E24<=0.95,"B","C"))) -> #DIV/0! | G24: =VLOOKUP(B$4:B$25,I$4:M$25,5,0) -> #DIV/0! | I24: lux7 | K24: =J24/J$26 -> #DIV/0! | L24: =K24+L23 -> #DIV/0! | M24: =_xlfn.IFS(L24<80%,"A",L24<=95%,"B",L24>95%,"C") -> #DIV/0!
B25: lux8 | D25: =C25/C$26 -> #DIV/0! | E25: =D25+E24 -> #DIV/0! | F25: =IF(AND(E25<=0),"C",IF(E25<=0.8,"A",IF(E25<=0.95,"B","C"))) -> #DIV/0! | G25: =VLOOKUP(B$4:B$25,I$4:M$25,5,0) -> #DIV/0! | I25: lux8 | K25: =J25/J$26 -> #DIV/0! | L25: =K25+L24 -> #DIV/0! | M25: =_xlfn.IFS(L25<80%,"A",L25<=95%,"B",L25>95%,"C") -> #DIV/0!
C26: =SUM(C4:C25) -> 0 | D26: =SUM(D4:D25) -> #DIV/0! | J26: =SUM(J4:J25) -> 0 | K26: =SUM(K4:K25) -> #DIV/0!
B28: ТУНИКИ
C29: Прибыль | D29: % прибыль | E29: Доля | F29: ABC прибыль | G29: ABC кол-во | J29: Кол-во | K29: % кол-во | L29: Доля | M29: ABC кол-во
B30: tunika02 оливковая с руч вышивкой | D30: =C30/C$50 -> #DIV/0! | E30: =D30 -> #DIV/0! | F30: =IF(AND(E30<=0),"C",IF(E30<=0.8,"A",IF(E30<=0.95,"B","C"))) -> #DIV/0! | G30: =VLOOKUP(B$30:B$50,I$30:M$50,5,0) -> #DIV/0! | I30: tunika02 оливковая с руч вышивкой | K30: =J30/J$50 -> #DIV/0! | L30: =K30 -> #DIV/0! | M30: =_xlfn.IFS(L30<80%,"A",L30<=95%,"B",L30>95%,"C") -> #DIV/0!
B31: tunika03 черная распашная | D31: =C31/C$50 -> #DIV/0! | E31: =D31+E30 -> #DIV/0! | F31: =IF(AND(E31<=0),"C",IF(E31<=0.8,"A",IF(E31<=0.95,"B","C"))) -> #DIV/0! | G31: =VLOOKUP(B$30:B$50,I$30:M$50,5,0) -> #DIV/0! | I31: tunika03 черная распашная | K31: =J31/J$50 -> #DIV/0! | L31: =K31+L30 -> #DIV/0! | M31: =_xlfn.IFS(L31<80%,"A",L31<=95%,"B",L31>95%,"C") -> #DIV/0!
B32: tunika05 белая распашная | D32: =C32/C$50 -> #DIV/0! | E32: =D32+E31 -> #DIV/0! | F32: =IF(AND(E32<=0),"C",IF(E32<=0.8,"A",IF(E32<=0.95,"B","C"))) -> #DIV/0! | G32: =VLOOKUP(B$30:B$50,I$30:M$50,5,0) -> #DIV/0! | I32: tunika05 белая распашная | K32: =J32/J$50 -> #DIV/0! | L32: =K32+L31 -> #DIV/0! | M32: =_xlfn.IFS(L32<80%,"A",L32<=95%,"B",L32>95%,"C") -> #DIV/0!
B33: tunika06 белая | D33: =C33/C$50 -> #DIV/0! | E33: =D33+E32 -> #DIV/0! | F33: =IF(AND(E33<=0),"C",IF(E33<=0.8,"A",IF(E33<=0.95,"B","C"))) -> #DIV/0! | G33: =VLOOKUP(B$30:B$50,I$30:M$50,5,0) -> #DIV/0! | I33: tunika06 белая | K33: =J33/J$50 -> #DIV/0! | L33: =K33+L32 -> #DIV/0! | M33: =_xlfn.IFS(L33<80%,"A",L33<=95%,"B",L33>95%,"C") -> #DIV/0!
B34: tunika06 черная | D34: =C34/C$50 -> #DIV/0! | E34: =D34+E33 -> #DIV/0! | F34: =IF(AND(E34<=0),"C",IF(E34<=0.8,"A",IF(E34<=0.95,"B","C"))) -> #DIV/0! | G34: =VLOOKUP(B$30:B$50,I$30:M$50,5,0) -> #DIV/0! | I34: tunika06 черная | K34: =J34/J$50 -> #DIV/0! | L34: =K34+L33 -> #DIV/0! | M34: =_xlfn.IFS(L34<80%,"A",L34<=95%,"B",L34>95%,"C") -> #DIV/0!
B35: tunika07 кружево | D35: =C35/C$50 -> #DIV/0! | E35: =D35+E34 -> #DIV/0! | F35: =IF(AND(E35<=0),"C",IF(E35<=0.8,"A",IF(E35<=0.95,"B","C"))) -> #DIV/0! | G35: =VLOOKUP(B$30:B$50,I$30:M$50,5,0) -> #DIV/0! | I35: tunika07 кружево | K35: =J35/J$50 -> #DIV/0! | L35: =K35+L34 -> #DIV/0! | M35: =_xlfn.IFS(L35<80%,"A",L35<=95%,"B",L35>95%,"C") -> #DIV/0!
B36: tunika08 белая | D36: =C36/C$50 -> #DIV/0! | E36: =D36+E35 -> #DIV/0! | F36: =IF(AND(E36<=0),"C",IF(E36<=0.8,"A",IF(E36<=0.95,"B","C"))) -> #DIV/0! | G36: =VLOOKUP(B$30:B$50,I$30:M$50,5,0) -> #DIV/0! | I36: tunika08 белая | K36: =J36/J$50 -> #DIV/0! | L36: =K36+L35 -> #DIV/0! | M36: =_xlfn.IFS(L36<80%,"A",L36<=95%,"B",L36>95%,"C") -> #DIV/0!
B37: tunika08 черная | D37: =C37/C$50 -> #DIV/0! | E37: =D37+E36 -> #DIV/0! | F37: =IF(AND(E37<=0),"C",IF(E37<=0.8,"A",IF(E37<=0.95,"B","C"))) -> #DIV/0! | G37: =VLOOKUP(B$30:B$50,I$30:M$50,5,0) -> #DIV/0! | I37: tunika08 черная | K37: =J37/J$50 -> #DIV/0! | L37: =K37+L36 -> #DIV/0! | M37: =_xlfn.IFS(L37<80%,"A",L37<=95%,"B",L37>95%,"C") -> #DIV/0!
B38: tunika08 зеленая | D38: =C38/C$50 -> #DIV/0! | E38: =D38+E37 -> #DIV/0! | F38: =IF(AND(E38<=0),"C",IF(E38<=0.8,"A",IF(E38<=0.95,"B","C"))) -> #DIV/0! | G38: =VLOOKUP(B$30:B$50,I$30:M$50,5,0) -> #DIV/0! | I38: tunika08 зеленая | K38: =J38/J$50 -> #DIV/0! | L38: =K38+L37 -> #DIV/0! | M38: =_xlfn.IFS(L38<80%,"A",L38<=95%,"B",L38>95%,"C") -> #DIV/0!
B39: tunika09 кимоно | D39: =C39/C$50 -> #DIV/0! | E39: =D39+E38 -> #DIV/0! | F39: =IF(AND(E39<=0),"C",IF(E39<=0.8,"A",IF(E39<=0.95,"B","C"))) -> #DIV/0! | G39: =VLOOKUP(B$30:B$50,I$30:M$50,5,0) -> #DIV/0! | I39: tunika09 кимоно | K39: =J39/J$50 -> #DIV/0! | L39: =K39+L38 -> #DIV/0! | M39: =_xlfn.IFS(L39<80%,"A",L39<=95%,"B",L39>95%,"C") -> #DIV/0!
B40: tunika10 кимоно ч/б | D40: =C40/C$50 -> #DIV/0! | E40: =D40+E39 -> #DIV/0! | F40: =IF(AND(E40<=0),"C",IF(E40<=0.8,"A",IF(E40<=0.95,"B","C"))) -> #DIV/0! | G40: =VLOOKUP(B$30:B$50,I$30:M$50,5,0) -> #DIV/0! | I40: tunika10 кимоно ч/б | K40: =J40/J$50 -> #DIV/0! | L40: =K40+L39 -> #DIV/0! | M40: =_xlfn.IFS(L40<80%,"A",L40<=95%,"B",L40>95%,"C") -> #DIV/0!
B41: tunika11 халат зеленая | D41: =C41/C$50 -> #DIV/0! | E41: =D41+E40 -> #DIV/0! | F41: =IF(AND(E41<=0),"C",IF(E41<=0.8,"A",IF(E41<=0.95,"B","C"))) -> #DIV/0! | G41: =VLOOKUP(B$30:B$50,I$30:M$50,5,0) -> #DIV/0! | I41: tunika11 халат зеленая | K41: =J41/J$50 -> #DIV/0! | L41: =K41+L40 -> #DIV/0! | M41: =_xlfn.IFS(L41<80%,"A",L41<=95%,"B",L41>95%,"C") -> #DIV/0!
B42: tunika12 халат белая | D42: =C42/C$50 -> #DIV/0! | E42: =D42+E41 -> #DIV/0! | F42: =IF(AND(E42<=0),"C",IF(E42<=0.8,"A",IF(E42<=0.95,"B","C"))) -> #DIV/0! | G42: =VLOOKUP(B$30:B$50,I$30:M$50,5,0) -> #DIV/0! | I42: tunika12 халат белая | K42: =J42/J$50 -> #DIV/0! | L42: =K42+L41 -> #DIV/0! | M42: =_xlfn.IFS(L42<80%,"A",L42<=95%,"B",L42>95%,"C") -> #DIV/0!
... B49: tunika16 сетка черная | D49: =C49/C$50 -> #DIV/0! | E49: =D49+E48 -> #DIV/0! | F49: =IF(AND(E49<=0),"C",IF(E49<=0.8,"A",IF(E49<=0.95,"B","C"))) -> #DIV/0! | G49: =VLOOKUP(B$30:B$50,I$30:M$50,5,0) -> #DIV/0! | I49: tunika16 сетка черная | K49: =J49/J$50 -> #DIV/0! | L49: =K49+L48 -> #DIV/0! | M49: =_xlfn.IFS(L49<80%,"A",L49<=95%,"B",L49>95%,"C") -> #DIV/0!
C50: =SUM(C30:C49) -> 0 | D50: =SUM(D30:D49) -> #DIV/0! | J50: =SUM(J30:J49) -> 0 | K50: =SUM(K30:K49) -> #DIV/0!

Sheet АВС 23-29.03
B2: ОЧКИ
C3: Прибыль | D3: % прибыль | E3: Доля | F3: ABC прибыль | G3: ABC кол-во | J3: Кол-во | K3: % кол-во | L3: Доля | M3: ABC кол-во
B4: черные с железкой классика | C4: ='Юнит 23-29.03'!AE3 -> 64086.083 | D4: =C4/C$26 -> 0.75751507 | E4: =D4 -> 0.75751507 | F4: =IF(AND(E4<=0),"C",IF(E4<=0.8,"A",IF(E4<=0.95,"B","C"))) -> A | G4: =VLOOKUP(B$4:B$25,I$4:M$25,5,0) -> A | I4: черные с железкой классика | J4: ='Юнит 23-29.03'!R3 -> 84 | K4: =J4/J$26 -> 0.64122137 | L4: =K4 -> 0.64122137 | M4: =_xlfn.IFS(L4<80%,"A",L4<=95%,"B",L4>95%,"C") -> A
B5: qs желтые | C5: ='Юнит 23-29.03'!AE6 -> 6828.646 | D5: =C5/C$26 -> 0.080716467 | E5: =D5+E4 -> 0.83823153 | F5: =IF(AND(E5<=0),"C",IF(E5<=0.8,"A",IF(E5<=0.95,"B","C"))) -> B | G5: =VLOOKUP(B$4:B$25,I$4:M$25,5,0) -> A | I5: qs желтые | J5: ='Юнит 23-29.03'!R6 -> 13 | K5: =J5/J$26 -> 0.099236641 | L5: =K5+L4 -> 0.74045802 | M5: =_xlfn.IFS(L5<80%,"A",L5<=95%,"B",L5>95%,"C") -> A
B6: qs черные | C6: ='Юнит 23-29.03'!AE4 -> 5334.3972 | D6: =C6/C$26 -> 0.063054037 | E6: =D6+E5 -> 0.90128557 | F6: =IF(AND(E6<=0),"C",IF(E6<=0.8,"A",IF(E6<=0.95,"B","C"))) -> B | G6: =VLOOKUP(B$4:B$25,I$4:M$25,5,0) -> B | I6: MR8854 C2 | J6: ='Юнит 23-29.03'!R10 -> 11 | K6: =J6/J$26 -> 0.083969466 | L6: =K6+L5 -> 0.82442748 | M6: =_xlfn.IFS(L6<80%,"A",L6<=95%,"B",L6>95%,"C") -> B
B7: flip желтые Сул | C7: ='Юнит 23-29.03'!AE9 -> 2559.7759 | D7: =C7/C$26 -> 0.030257252 | E7: =D7+E6 -> 0.93154282 | F7: =IF(AND(E7<=0),"C",IF(E7<=0.8,"A",IF(E7<=0.95,"B","C"))) -> B | G7: =VLOOKUP(B$4:B$25,I$4:M$25,5,0) -> B | I7: qs черные | J7: ='Юнит 23-29.03'!R4 -> 6 | K7: =J7/J$26 -> 0.045801527 | L7: =K7+L6 -> 0.87022901 | M7: =_xlfn.IFS(L7<80%,"A",L7<=95%,"B",L7>95%,"C") -> B
B8: MR8854 C2 | C8: ='Юнит 23-29.03'!AE10 -> 1936.3808 | D8: =C8/C$26 -> 0.022888552 | E8: =D8+E7 -> 0.95443137 | F8: =IF(AND(E8<=0),"C",IF(E8<=0.8,"A",IF(E8<=0.95,"B","C"))) -> C | G8: =VLOOKUP(B$4:B$25,I$4:M$25,5,0) -> B | I8: flip желтые Сул | J8: ='Юнит 23-29.03'!R9 -> 5 | K8: =J8/J$26 -> 0.038167939 | L8: =K8+L7 -> 0.90839695 | M8: =_xlfn.IFS(L8<80%,"A",L8<=95%,"B",L8>95%,"C") -> B
B9: qs синие | C9: ='Юнит 23-29.03'!AE5 -> 1688.0937 | D9: =C9/C$26 -> 0.01995373 | E9: =D9+E8 -> 0.9743851 | F9: =IF(AND(E9<=0),"C",IF(E9<=0.8,"A",IF(E9<=0.95,"B","C"))) -> C | G9: =VLOOKUP(B$4:B$25,I$4:M$25,5,0) -> B | I9: qs синие | J9: ='Юнит 23-29.03'!R5 -> 4 | K9: =J9/J$26 -> 0.030534351 | L9: =K9+L8 -> 0.9389313 | M9: =_xlfn.IFS(L9<80%,"A",L9<=95%,"B",L9>95%,"C") -> B
B10: MR 1819 черн | C10: ='Юнит 23-29.03'!AE11 -> 982.06837 | D10: =C10/C$26 -> 0.011608317 | E10: =D10+E9 -> 0.98599342 | F10: =IF(AND(E10<=0),"C",IF(E10<=0.8,"A",IF(E10<=0.95,"B","C"))) -> C | G10: =VLOOKUP(B$4:B$25,I$4:M$25,5,0) -> B | I10: qs коричневые | J10: ='Юнит 23-29.03'!R7 -> 3 | K10: =J10/J$26 -> 0.022900763 | L10: =K10+L9 -> 0.96183206 | M10: =_xlfn.IFS(L10<80%,"A",L10<=95%,"B",L10>95%,"C") -> C
B11: MR Р1874 черн | C11: ='Юнит 23-29.03'!AE13 -> 687.38177 | D11: =C11/C$26 -> 0.0081250409 | E11: =D11+E8 -> 0.96255642 | F11: =IF(AND(E11<=0),"C",IF(E11<=0.8,"A",IF(E11<=0.95,"B","C"))) -> C | G11: =VLOOKUP(B$4:B$25,I$4:M$25,5,0) -> B | I11: MR 1819 черн | J11: ='Юнит 23-29.03'!R11 -> 2 | K11: =J11/J$26 -> 0.015267176 | L11: =K11+L8 -> 0.92366412 | M11: =_xlfn.IFS(L11<80%,"A",L11<=95%,"B",L11>95%,"C") -> B
B12: MR Р1886 черн глянец | C12: ='Юнит 23-29.03'!AE15 -> 645.62876 | D12: =C12/C$26 -> 0.0076315089 | E12: =D12+E11 -> 0.97018792 | F12: =IF(AND(E12<=0),"C",IF(E12<=0.8,"A",IF(E12<=0.95,"B","C"))) -> C | G12: =VLOOKUP(B$4:B$25,I$4:M$25,5,0) -> B | I12: MR Р1874 черн | J12: ='Юнит 23-29.03'!R13 -> 1 | K12: =J12/J$26 -> 0.0076335878 | L12: =K12+L11 -> 0.93129771 | M12: =_xlfn.IFS(L12<80%,"A",L12<=95%,"B",L12>95%,"C") -> B
B13: qs коричневые | C13: ='Юнит 23-29.03'!AE7 -> 527.04446 | D13: =C13/C$26 -> 0.00622981 | E13: =D13+E12 -> 0.97641773 | F13: =IF(AND(E13<=0),"C",IF(E13<=0.8,"A",IF(E13<=0.95,"B","C"))) -> C | G13: =VLOOKUP(B$4:B$25,I$4:M$25,5,0) -> C | I13: MR Р1886 черн глянец | J13: ='Юнит 23-29.03'!R15 -> 1 | K13: =J13/J$26 -> 0.0076335878 | L13: =K13+L12 -> 0.9389313 | M13: =_xlfn.IFS(L13<80%,"A",L13<=95%,"B",L13>95%,"C") -> B | P13: A | Q13: 0.8
B14: MR Р1874 корич | C14: ='Юнит 23-29.03'!AE14 -> 0 | D14: =C14/C$26 -> 0 | E14: =D14+E13 -> 0.97641773 | F14: =IF(AND(E14<=0),"C",IF(E14<=0.8,"A",IF(E14<=0.95,"B","C"))) -> C | G14: =VLOOKUP(B$4:B$25,I$4:M$25,5,0) -> B | I14: MR Р1886 корич | J14: ='Юнит 23-29.03'!R16 -> 1 | K14: =J14/J$26 -> 0.0076335878 | L14: =K14+L13 -> 0.94656489 | M14: =_xlfn.IFS(L14<80%,"A",L14<=95%,"B",L14>95%,"C") -> B | P14: B | Q14: 0.15
B15: lux1 | C15: ='Юнит 23-29.03'!AE17 -> 0 | D15: =C15/C$26 -> 0 | E15: =D15+E14 -> 0.97641773 | F15: =IF(AND(E15<=0),"C",IF(E15<=0.8,"A",IF(E15<=0.95,"B","C"))) -> C | G15: =VLOOKUP(B$4:B$25,I$4:M$25,5,0) -> B | I15: th желтый Сул | J15: ='Юнит 23-29.03'!R8 -> 0 | K15: =J15/J$26 -> 0 | L15: =K15+L14 -> 0.94656489 | M15: =_xlfn.IFS(L15<80%,"A",L15<=95%,"B",L15>95%,"C") -> B | P15: C | Q15: 0.05
B16: lux2 | C16: ='Юнит 23-29.03'!AE18 -> 0 | D16: =C16/C$26 -> 0 | E16: =D16+E15 -> 0.97641773 | F16: =IF(AND(E16<=0),"C",IF(E16<=0.8,"A",IF(E16<=0.95,"B","C"))) -> C | G16: =VLOOKUP(B$4:B$25,I$4:M$25,5,0) -> B | I16: MR 1819 корич | J16: ='Юнит 23-29.03'!R12 -> 0 | K16: =J16/J$26 -> 0 | L16: =K16+L15 -> 0.94656489 | M16: =_xlfn.IFS(L16<80%,"A",L16<=95%,"B",L16>95%,"C") -> B
B17: lux4 | C17: ='Юнит 23-29.03'!AE20 -> 0 | D17: =C17/C$26 -> 0 | E17: =D17+E16 -> 0.97641773 | F17: =IF(AND(E17<=0),"C",IF(E17<=0.8,"A",IF(E17<=0.95,"B","C"))) -> C | G17: =VLOOKUP(B$4:B$25,I$4:M$25,5,0) -> B | I17: MR Р1874 корич | J17: ='Юнит 23-29.03'!R14 -> 0 | K17: =J17/J$26 -> 0 | L17: =K17+L16 -> 0.94656489 | M17: =_xlfn.IFS(L17<80%,"A",L17<=95%,"B",L17>95%,"C") -> B
B18: lux5 | C18: ='Юнит 23-29.03'!AE21 -> 0 | D18: =C18/C$26 -> 0 | E18: =D18+E17 -> 0.97641773 | F18: =IF(AND(E18<=0),"C",IF(E18<=0.8,"A",IF(E18<=0.95,"B","C"))) -> C | G18: =VLOOKUP(B$4:B$25,I$4:M$25,5,0) -> B | I18: lux1 | J18: ='Юнит 23-29.03'!R17 -> 0 | K18: =J18/J$26 -> 0 | L18: =K18+L17 -> 0.94656489 | M18: =_xlfn.IFS(L18<80%,"A",L18<=95%,"B",L18>95%,"C") -> B
B19: lux6 | C19: ='Юнит 23-29.03'!AE22 -> 0 | D19: =C19/C$26 -> 0 | E19: =D19+E18 -> 0.97641773 | F19: =IF(AND(E19<=0),"C",IF(E19<=0.8,"A",IF(E19<=0.95,"B","C"))) -> C | G19: =VLOOKUP(B$4:B$25,I$4:M$25,5,0) -> B | I19: lux2 | J19: ='Юнит 23-29.03'!R18 -> 0 | K19: =J19/J$26 -> 0 | L19: =K19+L18 -> 0.94656489 | M19: =_xlfn.IFS(L19<80%,"A",L19<=95%,"B",L19>95%,"C") -> B
B20: lux7 | C20: ='Юнит 23-29.03'!AE23 -> 0 | D20: =C20/C$26 -> 0 | E20: =D20+E19 -> 0.97641773 | F20: =IF(AND(E20<=0),"C",IF(E20<=0.8,"A",IF(E20<=0.95,"B","C"))) -> C | G20: =VLOOKUP(B$4:B$25,I$4:M$25,5,0) -> B | I20: lux3 | J20: ='Юнит 23-29.03'!R19 -> 0 | K20: =J20/J$26 -> 0 | L20: =K20+L19 -> 0.94656489 | M20: =_xlfn.IFS(L20<80%,"A",L20<=95%,"B",L20>95%,"C") -> B
B21: lux8 | C21: ='Юнит 23-29.03'!AE24 -> 0 | D21: =C21/C$26 -> 0 | E21: =D21+E20 -> 0.97641773 | F21: =IF(AND(E21<=0),"C",IF(E21<=0.8,"A",IF(E21<=0.95,"B","C"))) -> C | G21: =VLOOKUP(B$4:B$25,I$4:M$25,5,0) -> B | I21: lux4 | J21: ='Юнит 23-29.03'!R20 -> 0 | K21: =J21/J$26 -> 0 | L21: =K21+L20 -> 0.94656489 | M21: =_xlfn.IFS(L21<80%,"A",L21<=95%,"B",L21>95%,"C") -> B
B22: th желтый Сул | C22: ='Юнит 23-29.03'!AE8 -> -65.683221 | D22: =C22/C$26 -> -0.00077639367 | E22: =D22+E21 -> 0.97564134 | F22: =IF(AND(E22<=0),"C",IF(E22<=0.8,"A",IF(E22<=0.95,"B","C"))) -> C | G22: =VLOOKUP(B$4:B$25,I$4:M$25,5,0) -> B | I22: lux5 | J22: ='Юнит 23-29.03'!R21 -> 0 | K22: =J22/J$26 -> 0 | L22: =K22+L21 -> 0.94656489 | M22: =_xlfn.IFS(L22<80%,"A",L22<=95%,"B",L22>95%,"C") -> B
B23: lux3 | C23: ='Юнит 23-29.03'!AE19 -> -113.88 | D23: =C23/C$26 -> -0.0013460928 | E23: =D23+E22 -> 0.97429525 | F23: =IF(AND(E23<=0),"C",IF(E23<=0.8,"A",IF(E23<=0.95,"B","C"))) -> C | G23: =VLOOKUP(B$4:B$25,I$4:M$25,5,0) -> B | I23: lux6 | J23: ='Юнит 23-29.03'!R22 -> 0 | K23: =J23/J$26 -> 0 | L23: =K23+L22 -> 0.94656489 | M23: =_xlfn.IFS(L23<80%,"A",L23<=95%,"B",L23>95%,"C") -> B
B24: MR 1819 корич | C24: ='Юнит 23-29.03'!AE12 -> -187.08 | D24: =C24/C$26 -> -0.0022113369 | E24: =D24+E23 -> 0.97208391 | F24: =IF(AND(E24<=0),"C",IF(E24<=0.8,"A",IF(E24<=0.95,"B","C"))) -> C | G24: =VLOOKUP(B$4:B$25,I$4:M$25,5,0) -> B | I24: lux7 | J24: ='Юнит 23-29.03'!R23 -> 0 | K24: =J24/J$26 -> 0 | L24: =K24+L23 -> 0.94656489 | M24: =_xlfn.IFS(L24<80%,"A",L24<=95%,"B",L24>95%,"C") -> B
B25: MR Р1886 корич | C25: ='Юнит 23-29.03'!AE16 -> -308.44956 | D25: =C25/C$26 -> -0.0036459584 | E25: =D25+E24 -> 0.96843795 | F25: =IF(AND(E25<=0),"C",IF(E25<=0.8,"A",IF(E25<=0.95,"B","C"))) -> C | G25: =VLOOKUP(B$4:B$25,I$4:M$25,5,0) -> B | I25: lux8 | J25: ='Юнит 23-29.03'!R24 -> 0 | K25: =J25/J$26 -> 0 | L25: =K25+L24 -> 0.94656489 | M25: =_xlfn.IFS(L25<80%,"A",L25<=95%,"B",L25>95%,"C") -> B
C26: =SUM(C4:C25) -> 84600.407 | D26: =SUM(D4:D25) -> 1 | J26: =SUM(J4:J25) -> 131 | K26: =SUM(K4:K25) -> 1
B28: ТУНИКИ
C29: Прибыль | D29: % прибыль | E29: Доля | F29: ABC прибыль | G29: ABC кол-во | J29: Кол-во | K29: % кол-во | L29: Доля | M29: ABC кол-во
B30: tunika09 кимоно | C30: ='Юнит 23-29.03'!AE37 -> 2735.9655 | D30: =C30/C$50 -> -2.0991565 | E30: =D30 -> -2.0991565 | F30: =IF(AND(E30<=0),"C",IF(E30<=0.8,"A",IF(E30<=0.95,"B","C"))) -> C | G30: =VLOOKUP(B$30:B$50,I$30:M$50,5,0) -> B | I30: tunika02 оливковая с руч вышивкой | J30: ='Юнит 23-29.03'!R28 -> 7 | K30: =J30/J$50 -> 0.58333333 | L30: =K30 -> 0.58333333 | M30: =_xlfn.IFS(L30<80%,"A",L30<=95%,"B",L30>95%,"C") -> A
B31: tunika07 кружево | C31: ='Юнит 23-29.03'!AE33 -> 1391.45 | D31: =C31/C$50 -> -1.0675833 | E31: =D31+E30 -> -3.1667398 | F31: =IF(AND(E31<=0),"C",IF(E31<=0.8,"A",IF(E31<=0.95,"B","C"))) -> C | G31: =VLOOKUP(B$30:B$50,I$30:M$50,5,0) -> B | I31: tunika03 черная распашная | J31: ='Юнит 23-29.03'!R29 -> 0 | K31: =J31/J$50 -> 0 | L31: =K31+L30 -> 0.58333333 | M31: =_xlfn.IFS(L31<80%,"A",L31<=95%,"B",L31>95%,"C") -> A
B32: tunika05 белая распашная | C32: ='Юнит 23-29.03'!AE30 -> 922.10844 | D32: =C32/C$50 -> -0.70748329 | E32: =D32+E31 -> -3.8742231 | F32: =IF(AND(E32<=0),"C",IF(E32<=0.8,"A",IF(E32<=0.95,"B","C"))) -> C | G32: =VLOOKUP(B$30:B$50,I$30:M$50,5,0) -> A | I32: tunika05 белая распашная | J32: ='Юнит 23-29.03'!R30 -> 1 | K32: =J32/J$50 -> 0.083333333 | L32: =K32+L31 -> 0.66666667 | M32: =_xlfn.IFS(L32<80%,"A",L32<=95%,"B",L32>95%,"C") -> A
B33: tunika02 оливковая с руч вышивкой | C33: ='Юнит 23-29.03'!AE28 -> 349.1069 | D33: =C33/C$50 -> -0.2678506 | E33: =D33+E32 -> -4.1420737 | F33: =IF(AND(E33<=0),"C",IF(E33<=0.8,"A",IF(E33<=0.95,"B","C"))) -> C | G33: =VLOOKUP(B$30:B$50,I$30:M$50,5,0) -> A | I33: tunika06 белая | J33: ='Юнит 23-29.03'!R31 -> 0 | K33: =J33/J$50 -> 0 | L33: =K33+L32 -> 0.66666667 | M33: =_xlfn.IFS(L33<80%,"A",L33<=95%,"B",L33>95%,"C") -> A
B34: tunika03 черная распашная | C34: ='Юнит 23-29.03'!AE29 -> 0 | D34: =C34/C$50 -> 0 | E34: =D34+E33 -> -4.1420737 | F34: =IF(AND(E34<=0),"C",IF(E34<=0.8,"A",IF(E34<=0.95,"B","C"))) -> C | G34: =VLOOKUP(B$30:B$50,I$30:M$50,5,0) -> A | I34: tunika06 черная | J34: ='Юнит 23-29.03'!R32 -> 0 | K34: =J34/J$50 -> 0 | L34: =K34+L33 -> 0.66666667 | M34: =_xlfn.IFS(L34<80%,"A",L34<=95%,"B",L34>95%,"C") -> A
B35: tunika06 белая | C35: ='Юнит 23-29.03'!AE31 -> 0 | D35: =C35/C$50 -> 0 | E35: =D35+E34 -> -4.1420737 | F35: =IF(AND(E35<=0),"C",IF(E35<=0.8,"A",IF(E35<=0.95,"B","C"))) -> C | G35: =VLOOKUP(B$30:B$50,I$30:M$50,5,0) -> A | I35: tunika07 кружево | J35: ='Юнит 23-29.03'!R33 -> 2 | K35: =J35/J$50 -> 0.16666667 | L35: =K35+L34 -> 0.83333333 | M35: =_xlfn.IFS(L35<80%,"A",L35<=95%,"B",L35>95%,"C") -> B
B36: tunika06 черная | C36: ='Юнит 23-29.03'!AE32 -> 0 | D36: =C36/C$50 -> 0 | E36: =D36+E35 -> -4.1420737 | F36: =IF(AND(E36<=0),"C",IF(E36<=0.8,"A",IF(E36<=0.95,"B","C"))) -> C | G36: =VLOOKUP(B$30:B$50,I$30:M$50,5,0) -> A | I36: tunika08 белая | J36: ='Юнит 23-29.03'!R34 -> 0 | K36: =J36/J$50 -> 0 | L36: =K36+L35 -> 0.83333333 | M36: =_xlfn.IFS(L36<80%,"A",L36<=95%,"B",L36>95%,"C") -> B
B37: tunika08 белая | C37: ='Юнит 23-29.03'!AE34 -> 0 | D37: =C37/C$50 -> 0 | E37: =D37+E36 -> -4.1420737 | F37: =IF(AND(E37<=0),"C",IF(E37<=0.8,"A",IF(E37<=0.95,"B","C"))) -> C | G37: =VLOOKUP(B$30:B$50,I$30:M$50,5,0) -> B | I37: tunika08 черная | J37: ='Юнит 23-29.03'!R35 -> 0 | K37: =J37/J$50 -> 0 | L37: =K37+L36 -> 0.83333333 | M37: =_xlfn.IFS(L37<80%,"A",L37<=95%,"B",L37>95%,"C") -> B
B38: tunika08 черная | C38: ='Юнит 23-29.03'!AE35 -> 0 | D38: =C38/C$50 -> 0 | E38: =D38+E37 -> -4.1420737 | F38: =IF(AND(E38<=0),"C",IF(E38<=0.8,"A",IF(E38<=0.95,"B","C"))) -> C | G38: =VLOOKUP(B$30:B$50,I$30:M$50,5,0) -> B | I38: tunika08 зеленая | J38: ='Юнит 23-29.03'!R36 -> 0 | K38: =J38/J$50 -> 0 | L38: =K38+L37 -> 0.83333333 | M38: =_xlfn.IFS(L38<80%,"A",L38<=95%,"B",L38>95%,"C") -> B
B39: tunika08 зеленая | C39: ='Юнит 23-29.03'!AE36 -> 0 | D39: =C39/C$50 -> 0 | E39: =D39+E38 -> -4.1420737 | F39: =IF(AND(E39<=0),"C",IF(E39<=0.8,"A",IF(E39<=0.95,"B","C"))) -> C | G39: =VLOOKUP(B$30:B$50,I$30:M$50,5,0) -> B | I39: tunika09 кимоно | J39: ='Юнит 23-29.03'!R37 -> 1 | K39: =J39/J$50 -> 0.083333333 | L39: =K39+L38 -> 0.91666667 | M39: =_xlfn.IFS(L39<80%,"A",L39<=95%,"B",L39>95%,"C") -> B
B40: tunika10 кимоно ч/б | C40: ='Юнит 23-29.03'!AE38 -> 0 | D40: =C40/C$50 -> 0 | E40: =D40+E39 -> -4.1420737 | F40: =IF(AND(E40<=0),"C",IF(E40<=0.8,"A",IF(E40<=0.95,"B","C"))) -> C | G40: =VLOOKUP(B$30:B$50,I$30:M$50,5,0) -> B | I40: tunika10 кимоно ч/б | J40: ='Юнит 23-29.03'!R38 -> 0 | K40: =J40/J$50 -> 0 | L40: =K40+L39 -> 0.91666667 | M40: =_xlfn.IFS(L40<80%,"A",L40<=95%,"B",L40>95%,"C") -> B
B41: tunika11 халат зеленая | C41: ='Юнит 23-29.03'!AE39 -> 0 | D41: =C41/C$50 -> 0 | E41: =D41+E40 -> -4.1420737 | F41: =IF(AND(E41<=0),"C",IF(E41<=0.8,"A",IF(E41<=0.95,"B","C"))) -> C | G41: =VLOOKUP(B$30:B$50,I$30:M$50,5,0) -> B | I41: tunika11 халат зеленая | J41: ='Юнит 23-29.03'!R39 -> 0 | K41: =J41/J$50 -> 0 | L41: =K41+L40 -> 0.91666667 | M41: =_xlfn.IFS(L41<80%,"A",L41<=95%,"B",L41>95%,"C") -> B
B42: tunika13 халат черная | C42: ='Юнит 23-29.03'!AE41 -> 0 | D42: =C42/C$50 -> 0 | E42: =D42+E41 -> -4.1420737 | F42: =IF(AND(E42<=0),"C",IF(E42<=0.8,"A",IF(E42<=0.95,"B","C"))) -> C | G42: =VLOOKUP(B$30:B$50,I$30:M$50,5,0) -> B | I42: tunika12 халат белая | J42: ='Юнит 23-29.03'!R40 -> 0 | K42: =J42/J$50 -> 0 | L42: =K42+L41 -> 0.91666667 | M42: =_xlfn.IFS(L42<80%,"A",L42<=95%,"B",L42>95%,"C") -> B
B43: tunika14 халат с разрезами белая | C43: ='Юнит 23-29.03'!AE42 -> 0 | D43: =C43/C$50 -> 0 | E43: =D43+E42 -> -4.1420737 | F43: =IF(AND(E43<=0),"C",IF(E43<=0.8,"A",IF(E43<=0.95,"B","C"))) -> C | G43: =VLOOKUP(B$30:B$50,I$30:M$50,5,0) -> B | I43: tunika13 халат черная | J43: ='Юнит 23-29.03'!R41 -> 0 | K43: =J43/J$50 -> 0 | L43: =K43+L42 -> 0.91666667 | M43: =_xlfn.IFS(L43<80%,"A",L43<=95%,"B",L43>95%,"C") -> B
B44: tunika12 халат белая | C44: ='Юнит 23-29.03'!AE40 -> -113.88 | D44: =C44/C$50 -> 0.087373886 | E44: =D44+E43 -> -4.0546998 | F44: =IF(AND(E44<=0),"C",IF(E44<=0.8,"A",IF(E44<=0.95,"B","C"))) -> C | G44: =VLOOKUP(B$30:B$50,I$30:M$50,5,0) -> B | I44: tunika14 халат с разрезами белая | J44: ='Юнит 23-29.03'!R42 -> 0 | K44: =J44/J$50 -> 0 | L44: =K44+L43 -> 0.91666667 | M44: =_xlfn.IFS(L44<80%,"A",L44<=95%,"B",L44>95%,"C") -> B
B45: tunika14 халат с разрезами черный | C45: ='Юнит 23-29.03'!AE43 -> -113.88 | D45: =C45/C$50 -> 0.087373886 | E45: =D45+E44 -> -3.9673259 | F45: =IF(AND(E45<=0),"C",IF(E45<=0.8,"A",IF(E45<=0.95,"B","C"))) -> C | G45: =VLOOKUP(B$30:B$50,I$30:M$50,5,0) -> B | I45: tunika14 халат с разрезами черный | J45: ='Юнит 23-29.03'!R43 -> 0 | K45: =J45/J$50 -> 0 | L45: =K45+L44 -> 0.91666667 | M45: =_xlfn.IFS(L45<80%,"A",L45<=95%,"B",L45>95%,"C") -> B
B46: tunika16 сетка черная | C46: ='Юнит 23-29.03'!AE47 -> -113.88 | D46: =C46/C$50 -> 0.087373886 | E46: =D46+E45 -> -3.8799521 | F46: =IF(AND(E46<=0),"C",IF(E46<=0.8,"A",IF(E46<=0.95,"B","C"))) -> C | G46: =VLOOKUP(B$30:B$50,I$30:M$50,5,0) -> C | I46: tunika15 кимоно бирюза | J46: ='Юнит 23-29.03'!R44 -> 0 | K46: =J46/J$50 -> 0 | L46: =K46+L45 -> 0.91666667 | M46: =_xlfn.IFS(L46<80%,"A",L46<=95%,"B",L46>95%,"C") -> B
B47: tunika15 кимоно бирюза | C47: ='Юнит 23-29.03'!AE44 -> -227.76 | D47: =C47/C$50 -> 0.17474777 | E47: =D47+E46 -> -3.7052043 | F47: =IF(AND(E47<=0),"C",IF(E47<=0.8,"A",IF(E47<=0.95,"B","C"))) -> C | G47: =VLOOKUP(B$30:B$50,I$30:M$50,5,0) -> B | I47: tunika15 кимоно песочная | J47: ='Юнит 23-29.03'!R45 -> 1 | K47: =J47/J$50 -> 0.083333333 | L47: =K47+L46 -> 1 | M47: =_xlfn.IFS(L47<80%,"A",L47<=95%,"B",L47>95%,"C") -> C
B48: tunika16 сетка белая | C48: ='Юнит 23-29.03'!AE46 -> -2980.8306 | D48: =C48/C$50 -> 2.287028 | E48: =D48+E47 -> -1.4181762 | F48: =IF(AND(E48<=0),"C",IF(E48<=0.8,"A",IF(E48<=0.95,"B","C"))) -> C | G48: =VLOOKUP(B$30:B$50,I$30:M$50,5,0) -> C | I48: tunika16 сетка белая | J48: ='Юнит 23-29.03'!R46 -> 0 | K48: =J48/J$50 -> 0 | L48: =K48+L47 -> 1 | M48: =_xlfn.IFS(L48<80%,"A",L48<=95%,"B",L48>95%,"C") -> C
B49: tunika15 кимоно песочная | C49: ='Юнит 23-29.03'!AE45 -> -3151.7645 | D49: =C49/C$50 -> 2.4181762 | E49: =D49+E48 -> 1 | F49: =IF(AND(E49<=0),"C",IF(E49<=0.8,"A",IF(E49<=0.95,"B","C"))) -> C | G49: =VLOOKUP(B$30:B$50,I$30:M$50,5,0) -> C | I49: tunika16 сетка черная | J49: ='Юнит 23-29.03'!R47 -> 0 | K49: =J49/J$50 -> 0 | L49: =K49+L48 -> 1 | M49: =_xlfn.IFS(L49<80%,"A",L49<=95%,"B",L49>95%,"C") -> C
C50: =SUM(C30:C49) -> -1303.3643 | D50: =SUM(D30:D49) -> 1 | J50: =SUM(J30:J49) -> 12 | K50: =SUM(K30:K49) -> 1

Sheet АВС 16-22.03
B2: ОЧКИ
C3: Прибыль | D3: % прибыль | E3: Доля | F3: ABC прибыль | G3: ABC кол-во | J3: Кол-во | K3: % кол-во | L3: Доля | M3: ABC кол-во
B4: черные с железкой классика | C4: ='Юнит 16-22.03'!AE3 -> 92693.636 | D4: =C4/C$26 -> 0.7510735 | E4: =D4 -> 0.7510735 | F4: =IF(AND(E4<=0),"C",IF(E4<=0.8,"A",IF(E4<=0.95,"B","C"))) -> A | G4: =VLOOKUP(B$4:B$25,I$4:M$25,5,0) -> A | I4: черные с железкой классика | J4: ='Юнит 16-22.03'!R3 -> 108 | K4: =J4/J$26 -> 0.63157895 | L4: =K4 -> 0.63157895 | M4: =_xlfn.IFS(L4<80%,"A",L4<=95%,"B",L4>95%,"C") -> A
B5: MR8854 C2 | C5: ='Юнит 16-22.03'!AE10 -> 15462.812 | D5: =C5/C$26 -> 0.12529132 | E5: =D5+E4 -> 0.87636482 | F5: =IF(AND(E5<=0),"C",IF(E5<=0.8,"A",IF(E5<=0.95,"B","C"))) -> B | G5: =VLOOKUP(B$4:B$25,I$4:M$25,5,0) -> A | I5: MR8854 C2 | J5: ='Юнит 16-22.03'!R10 -> 22 | K5: =J5/J$26 -> 0.12865497 | L5: =K5+L4 -> 0.76023392 | M5: =_xlfn.IFS(L5<80%,"A",L5<=95%,"B",L5>95%,"C") -> A
B6: qs черные | C6: ='Юнит 16-22.03'!AE4 -> 4508.4354 | D6: =C6/C$26 -> 0.036530731 | E6: =D6+E5 -> 0.91289555 | F6: =IF(AND(E6<=0),"C",IF(E6<=0.8,"A",IF(E6<=0.95,"B","C"))) -> B | G6: =VLOOKUP(B$4:B$25,I$4:M$25,5,0) -> B | I6: qs желтые | J6: ='Юнит 16-22.03'!R6 -> 9 | K6: =J6/J$26 -> 0.052631579 | L6: =K6+L5 -> 0.8128655 | M6: =_xlfn.IFS(L6<80%,"A",L6<=95%,"B",L6>95%,"C") -> B
B7: flip желтые Сул | C7: ='Юнит 16-22.03'!AE9 -> 4098.1221 | D7: =C7/C$26 -> 0.033206065 | E7: =D7+E6 -> 0.94610162 | F7: =IF(AND(E7<=0),"C",IF(E7<=0.8,"A",IF(E7<=0.95,"B","C"))) -> B | G7: =VLOOKUP(B$4:B$25,I$4:M$25,5,0) -> B | I7: qs синие | J7: ='Юнит 16-22.03'!R5 -> 7 | K7: =J7/J$26 -> 0.040935673 | L7: =K7+L6 -> 0.85380117 | M7: =_xlfn.IFS(L7<80%,"A",L7<=95%,"B",L7>95%,"C") -> B
B8: qs коричневые | C8: ='Юнит 16-22.03'!AE7 -> 1997.17 | D8: =C8/C$26 -> 0.016182573 | E8: =D8+E7 -> 0.96228419 | F8: =IF(AND(E8<=0),"C",IF(E8<=0.8,"A",IF(E8<=0.95,"B","C"))) -> C | G8: =VLOOKUP(B$4:B$25,I$4:M$25,5,0) -> B | I8: qs черные | J8: ='Юнит 16-22.03'!R4 -> 6 | K8: =J8/J$26 -> 0.035087719 | L8: =K8+L7 -> 0.88888889 | M8: =_xlfn.IFS(L8<80%,"A",L8<=95%,"B",L8>95%,"C") -> B
B9: qs синие | C9: ='Юнит 16-22.03'!AE5 -> 1367.9697 | D9: =C9/C$26 -> 0.011084319 | E9: =D9+E8 -> 0.97336851 | F9: =IF(AND(E9<=0),"C",IF(E9<=0.8,"A",IF(E9<=0.95,"B","C"))) -> C | G9: =VLOOKUP(B$4:B$25,I$4:M$25,5,0) -> B | I9: flip желтые Сул | J9: ='Юнит 16-22.03'!R9 -> 6 | K9: =J9/J$26 -> 0.035087719 | L9: =K9+L8 -> 0.92397661 | M9: =_xlfn.IFS(L9<80%,"A",L9<=95%,"B",L9>95%,"C") -> B
B10: qs желтые | C10: ='Юнит 16-22.03'!AE6 -> 1301.9201 | D10: =C10/C$26 -> 0.010549135 | E10: =D10+E9 -> 0.98391764 | F10: =IF(AND(E10<=0),"C",IF(E10<=0.8,"A",IF(E10<=0.95,"B","C"))) -> C | G10: =VLOOKUP(B$4:B$25,I$4:M$25,5,0) -> B | I10: qs коричневые | J10: ='Юнит 16-22.03'!R7 -> 4 | K10: =J10/J$26 -> 0.023391813 | L10: =K10+L9 -> 0.94736842 | M10: =_xlfn.IFS(L10<80%,"A",L10<=95%,"B",L10>95%,"C") -> B
B11: MR 1819 черн | C11: ='Юнит 16-22.03'!AE11 -> 1124.0484 | D11: =C11/C$26 -> 0.0091078849 | E11: =D11+E8 -> 0.97139207 | F11: =IF(AND(E11<=0),"C",IF(E11<=0.8,"A",IF(E11<=0.95,"B","C"))) -> C | G11: =VLOOKUP(B$4:B$25,I$4:M$25,5,0) -> B | I11: th желтый Сул | J11: ='Юнит 16-22.03'!R8 -> 3 | K11: =J11/J$26 -> 0.01754386 | L11: =K11+L8 -> 0.90643275 | M11: =_xlfn.IFS(L11<80%,"A",L11<=95%,"B",L11>95%,"C") -> B
B12: MR 1819 корич | C12: ='Юнит 16-22.03'!AE12 -> 894.46476 | D12: =C12/C$26 -> 0.0072476257 | E12: =D12+E11 -> 0.9786397 | F12: =IF(AND(E12<=0),"C",IF(E12<=0.8,"A",IF(E12<=0.95,"B","C"))) -> C | G12: =VLOOKUP(B$4:B$25,I$4:M$25,5,0) -> B | I12: MR 1819 черн | J12: ='Юнит 16-22.03'!R11 -> 2 | K12: =J12/J$26 -> 0.011695906 | L12: =K12+L11 -> 0.91812865 | M12: =_xlfn.IFS(L12<80%,"A",L12<=95%,"B",L12>95%,"C") -> B
B13: MR Р1886 черн глянец | C13: ='Юнит 16-22.03'!AE15 -> 154.11699 | D13: =C13/C$26 -> 0.0012487717 | E13: =D13+E12 -> 0.97988847 | F13: =IF(AND(E13<=0),"C",IF(E13<=0.8,"A",IF(E13<=0.95,"B","C"))) -> C | G13: =VLOOKUP(B$4:B$25,I$4:M$25,5,0) -> B | I13: MR 1819 корич | J13: ='Юнит 16-22.03'!R12 -> 2 | K13: =J13/J$26 -> 0.011695906 | L13: =K13+L12 -> 0.92982456 | M13: =_xlfn.IFS(L13<80%,"A",L13<=95%,"B",L13>95%,"C") -> B | P13: A | Q13: 0.8
B14: th желтый Сул | C14: ='Юнит 16-22.03'!AE8 -> 23.780968 | D14: =C14/C$26 -> 0.00019269127 | E14: =D14+E13 -> 0.98008116 | F14: =IF(AND(E14<=0),"C",IF(E14<=0.8,"A",IF(E14<=0.95,"B","C"))) -> C | G14: =VLOOKUP(B$4:B$25,I$4:M$25,5,0) -> B | I14: MR Р1886 черн глянец | J14: ='Юнит 16-22.03'!R15 -> 1 | K14: =J14/J$26 -> 0.0058479532 | L14: =K14+L13 -> 0.93567251 | M14: =_xlfn.IFS(L14<80%,"A",L14<=95%,"B",L14>95%,"C") -> B | P14: B | Q14: 0.15
B15: MR Р1874 корич | C15: ='Юнит 16-22.03'!AE14 -> 0 | D15: =C15/C$26 -> 0 | E15: =D15+E14 -> 0.98008116 | F15: =IF(AND(E15<=0),"C",IF(E15<=0.8,"A",IF(E15<=0.95,"B","C"))) -> C | G15: =VLOOKUP(B$4:B$25,I$4:M$25,5,0) -> B | I15: MR Р1886 корич | J15: ='Юнит 16-22.03'!R16 -> 1 | K15: =J15/J$26 -> 0.0058479532 | L15: =K15+L14 -> 0.94152047 | M15: =_xlfn.IFS(L15<80%,"A",L15<=95%,"B",L15>95%,"C") -> B | P15: C | Q15: 0.05
B16: lux1 | C16: ='Юнит 16-22.03'!AE17 -> 0 | D16: =C16/C$26 -> 0 | E16: =D16+E15 -> 0.98008116 | F16: =IF(AND(E16<=0),"C",IF(E16<=0.8,"A",IF(E16<=0.95,"B","C"))) -> C | G16: =VLOOKUP(B$4:B$25,I$4:M$25,5,0) -> B | I16: MR Р1874 черн | J16: ='Юнит 16-22.03'!R13 -> 0 | K16: =J16/J$26 -> 0 | L16: =K16+L15 -> 0.94152047 | M16: =_xlfn.IFS(L16<80%,"A",L16<=95%,"B",L16>95%,"C") -> B
B17: lux2 | C17: ='Юнит 16-22.03'!AE18 -> 0 | D17: =C17/C$26 -> 0 | E17: =D17+E16 -> 0.98008116 | F17: =IF(AND(E17<=0),"C",IF(E17<=0.8,"A",IF(E17<=0.95,"B","C"))) -> C | G17: =VLOOKUP(B$4:B$25,I$4:M$25,5,0) -> B | I17: MR Р1874 корич | J17: ='Юнит 16-22.03'!R14 -> 0 | K17: =J17/J$26 -> 0 | L17: =K17+L16 -> 0.94152047 | M17: =_xlfn.IFS(L17<80%,"A",L17<=95%,"B",L17>95%,"C") -> B
B18: lux3 | C18: ='Юнит 16-22.03'!AE19 -> 0 | D18: =C18/C$26 -> 0 | E18: =D18+E17 -> 0.98008116 | F18: =IF(AND(E18<=0),"C",IF(E18<=0.8,"A",IF(E18<=0.95,"B","C"))) -> C | G18: =VLOOKUP(B$4:B$25,I$4:M$25,5,0) -> B | I18: lux1 | J18: ='Юнит 16-22.03'!R17 -> 0 | K18: =J18/J$26 -> 0 | L18: =K18+L17 -> 0.94152047 | M18: =_xlfn.IFS(L18<80%,"A",L18<=95%,"B",L18>95%,"C") -> B
B19: lux4 | C19: ='Юнит 16-22.03'!AE20 -> 0 | D19: =C19/C$26 -> 0 | E19: =D19+E18 -> 0.98008116 | F19: =IF(AND(E19<=0),"C",IF(E19<=0.8,"A",IF(E19<=0.95,"B","C"))) -> C | G19: =VLOOKUP(B$4:B$25,I$4:M$25,5,0) -> B | I19: lux2 | J19: ='Юнит 16-22.03'!R18 -> 0 | K19: =J19/J$26 -> 0 | L19: =K19+L18 -> 0.94152047 | M19: =_xlfn.IFS(L19<80%,"A",L19<=95%,"B",L19>95%,"C") -> B
B20: lux5 | C20: ='Юнит 16-22.03'!AE21 -> 0 | D20: =C20/C$26 -> 0 | E20: =D20+E19 -> 0.98008116 | F20: =IF(AND(E20<=0),"C",IF(E20<=0.8,"A",IF(E20<=0.95,"B","C"))) -> C | G20: =VLOOKUP(B$4:B$25,I$4:M$25,5,0) -> B | I20: lux3 | J20: ='Юнит 16-22.03'!R19 -> 0 | K20: =J20/J$26 -> 0 | L20: =K20+L19 -> 0.94152047 | M20: =_xlfn.IFS(L20<80%,"A",L20<=95%,"B",L20>95%,"C") -> B
B21: lux6 | C21: ='Юнит 16-22.03'!AE22 -> 0 | D21: =C21/C$26 -> 0 | E21: =D21+E20 -> 0.98008116 | F21: =IF(AND(E21<=0),"C",IF(E21<=0.8,"A",IF(E21<=0.95,"B","C"))) -> C | G21: =VLOOKUP(B$4:B$25,I$4:M$25,5,0) -> B | I21: lux4 | J21: ='Юнит 16-22.03'!R20 -> 0 | K21: =J21/J$26 -> 0 | L21: =K21+L20 -> 0.94152047 | M21: =_xlfn.IFS(L21<80%,"A",L21<=95%,"B",L21>95%,"C") -> B
B22: lux7 | C22: ='Юнит 16-22.03'!AE23 -> 0 | D22: =C22/C$26 -> 0 | E22: =D22+E21 -> 0.98008116 | F22: =IF(AND(E22<=0),"C",IF(E22<=0.8,"A",IF(E22<=0.95,"B","C"))) -> C | G22: =VLOOKUP(B$4:B$25,I$4:M$25,5,0) -> B | I22: lux5 | J22: ='Юнит 16-22.03'!R21 -> 0 | K22: =J22/J$26 -> 0 | L22: =K22+L21 -> 0.94152047 | M22: =_xlfn.IFS(L22<80%,"A",L22<=95%,"B",L22>95%,"C") -> B
B23: lux8 | C23: ='Юнит 16-22.03'!AE24 -> 0 | D23: =C23/C$26 -> 0 | E23: =D23+E22 -> 0.98008116 | F23: =IF(AND(E23<=0),"C",IF(E23<=0.8,"A",IF(E23<=0.95,"B","C"))) -> C | G23: =VLOOKUP(B$4:B$25,I$4:M$25,5,0) -> B | I23: lux6 | J23: ='Юнит 16-22.03'!R22 -> 0 | K23: =J23/J$26 -> 0 | L23: =K23+L22 -> 0.94152047 | M23: =_xlfn.IFS(L23<80%,"A",L23<=95%,"B",L23>95%,"C") -> B
B24: MR Р1874 черн | C24: ='Юнит 16-22.03'!AE13 -> -93.54 | D24: =C24/C$26 -> -0.00075793138 | E24: =D24+E23 -> 0.97932323 | F24: =IF(AND(E24<=0),"C",IF(E24<=0.8,"A",IF(E24<=0.95,"B","C"))) -> C | G24: =VLOOKUP(B$4:B$25,I$4:M$25,5,0) -> B | I24: lux7 | J24: ='Юнит 16-22.03'!R23 -> 0 | K24: =J24/J$26 -> 0 | L24: =K24+L23 -> 0.94152047 | M24: =_xlfn.IFS(L24<80%,"A",L24<=95%,"B",L24>95%,"C") -> B
B25: MR Р1886 корич | C25: ='Юнит 16-22.03'!AE16 -> -118.06924 | D25: =C25/C$26 -> -0.0009566857 | E25: =D25+E24 -> 0.97836655 | F25: =IF(AND(E25<=0),"C",IF(E25<=0.8,"A",IF(E25<=0.95,"B","C"))) -> C | G25: =VLOOKUP(B$4:B$25,I$4:M$25,5,0) -> B | I25: lux8 | J25: ='Юнит 16-22.03'!R24 -> 0 | K25: =J25/J$26 -> 0 | L25: =K25+L24 -> 0.94152047 | M25: =_xlfn.IFS(L25<80%,"A",L25<=95%,"B",L25>95%,"C") -> B
C26: =SUM(C4:C25) -> 123414.87 | D26: =SUM(D4:D25) -> 1 | J26: =SUM(J4:J25) -> 171 | K26: =SUM(K4:K25) -> 1
B28: ТУНИКИ
C29: Прибыль | D29: % прибыль | E29: Доля | F29: ABC прибыль | G29: ABC кол-во | J29: Кол-во | K29: % кол-во | L29: Доля | M29: ABC кол-во
B30: tunika16 сетка белая | C30: ='Юнит 16-22.03'!AE46 -> 10251.027 | D30: =C30/C$50 -> 1.2348957 | E30: =D30 -> 1.2348957 | F30: =IF(AND(E30<=0),"C",IF(E30<=0.8,"A",IF(E30<=0.95,"B","C"))) -> C | G30: =VLOOKUP(B$30:B$50,I$30:M$50,5,0) -> A | I30: tunika16 сетка белая | J30: ='Юнит 16-22.03'!R46 -> 11 | K30: =J30/J$50 -> 0.52380952 | L30: =K30 -> 0.52380952 | M30: =_xlfn.IFS(L30<80%,"A",L30<=95%,"B",L30>95%,"C") -> A
B31: tunika15 кимоно песочная | C31: ='Юнит 16-22.03'!AE45 -> 4203.3312 | D31: =C31/C$50 -> 0.50635664 | E31: =D31+E30 -> 1.7412523 | F31: =IF(AND(E31<=0),"C",IF(E31<=0.8,"A",IF(E31<=0.95,"B","C"))) -> C | G31: =VLOOKUP(B$30:B$50,I$30:M$50,5,0) -> C | I31: tunika02 оливковая с руч вышивкой | J31: ='Юнит 16-22.03'!R28 -> 7 | K31: =J31/J$50 -> 0.33333333 | L31: =K31+L30 -> 0.85714286 | M31: =_xlfn.IFS(L31<80%,"A",L31<=95%,"B",L31>95%,"C") -> B
B32: tunika02 оливковая с руч вышивкой | C32: ='Юнит 16-22.03'!AE28 -> 2146.8647 | D32: =C32/C$50 -> 0.25862325 | E32: =D32+E31 -> 1.9998756 | F32: =IF(AND(E32<=0),"C",IF(E32<=0.8,"A",IF(E32<=0.95,"B","C"))) -> C | G32: =VLOOKUP(B$30:B$50,I$30:M$50,5,0) -> B | I32: tunika15 кимоно песочная | J32: ='Юнит 16-22.03'!R45 -> 2 | K32: =J32/J$50 -> 0.095238095 | L32: =K32+L31 -> 0.95238095 | M32: =_xlfn.IFS(L32<80%,"A",L32<=95%,"B",L32>95%,"C") -> C
B33: tunika06 белая | C33: ='Юнит 16-22.03'!AE31 -> 1559.657 | D33: =C33/C$50 -> 0.18788495 | E33: =D33+E32 -> 2.1877605 | F33: =IF(AND(E33<=0),"C",IF(E33<=0.8,"A",IF(E33<=0.95,"B","C"))) -> C | G33: =VLOOKUP(B$30:B$50,I$30:M$50,5,0) -> C | I33: tunika05 белая распашная | J33: ='Юнит 16-22.03'!R30 -> 1 | K33: =J33/J$50 -> 0.047619048 | L33: =K33+L32 -> 1 | M33: =_xlfn.IFS(L33<80%,"A",L33<=95%,"B",L33>95%,"C") -> C
B34: tunika05 белая распашная | C34: ='Юнит 16-22.03'!AE30 -> 1340.4468 | D34: =C34/C$50 -> 0.16147767 | E34: =D34+E33 -> 2.3492382 | F34: =IF(AND(E34<=0),"C",IF(E34<=0.8,"A",IF(E34<=0.95,"B","C"))) -> C | G34: =VLOOKUP(B$30:B$50,I$30:M$50,5,0) -> C | I34: tunika06 белая | J34: ='Юнит 16-22.03'!R31 -> 1 | K34: =J34/J$50 -> 0.047619048 | L34: =K34+L33 -> 1.047619 | M34: =_xlfn.IFS(L34<80%,"A",L34<=95%,"B",L34>95%,"C") -> C
B35: tunika07 кружево | C35: ='Юнит 16-22.03'!AE33 -> 954.80024 | D35: =C35/C$50 -> 0.11502054 | E35: =D35+E34 -> 2.4642587 | F35: =IF(AND(E35<=0),"C",IF(E35<=0.8,"A",IF(E35<=0.95,"B","C"))) -> C | G35: =VLOOKUP(B$30:B$50,I$30:M$50,5,0) -> C | I35: tunika07 кружево | J35: ='Юнит 16-22.03'!R33 -> 1 | K35: =J35/J$50 -> 0.047619048 | L35: =K35+L34 -> 1.0952381 | M35: =_xlfn.IFS(L35<80%,"A",L35<=95%,"B",L35>95%,"C") -> C
B36: tunika06 черная | C36: ='Юнит 16-22.03'!AE32 -> 0 | D36: =C36/C$50 -> 0 | E36: =D36+E35 -> 2.4642587 | F36: =IF(AND(E36<=0),"C",IF(E36<=0.8,"A",IF(E36<=0.95,"B","C"))) -> C | G36: =VLOOKUP(B$30:B$50,I$30:M$50,5,0) -> C | I36: tunika15 кимоно бирюза | J36: ='Юнит 16-22.03'!R44 -> 1 | K36: =J36/J$50 -> 0.047619048 | L36: =K36+L35 -> 1.1428571 | M36: =_xlfn.IFS(L36<80%,"A",L36<=95%,"B",L36>95%,"C") -> C
B37: tunika08 белая | C37: ='Юнит 16-22.03'!AE34 -> 0 | D37: =C37/C$50 -> 0 | E37: =D37+E36 -> 2.4642587 | F37: =IF(AND(E37<=0),"C",IF(E37<=0.8,"A",IF(E37<=0.95,"B","C"))) -> C | G37: =VLOOKUP(B$30:B$50,I$30:M$50,5,0) -> C | I37: tunika03 черная распашная | J37: ='Юнит 16-22.03'!R29 -> 0 | K37: =J37/J$50 -> 0 | L37: =K37+L36 -> 1.1428571 | M37: =_xlfn.IFS(L37<80%,"A",L37<=95%,"B",L37>95%,"C") -> C
B38: tunika08 черная | C38: ='Юнит 16-22.03'!AE35 -> 0 | D38: =C38/C$50 -> 0 | E38: =D38+E37 -> 2.4642587 | F38: =IF(AND(E38<=0),"C",IF(E38<=0.8,"A",IF(E38<=0.95,"B","C"))) -> C | G38: =VLOOKUP(B$30:B$50,I$30:M$50,5,0) -> C | I38: tunika06 черная | J38: ='Юнит 16-22.03'!R32 -> 0 | K38: =J38/J$50 -> 0 | L38: =K38+L37 -> 1.1428571 | M38: =_xlfn.IFS(L38<80%,"A",L38<=95%,"B",L38>95%,"C") -> C
B39: tunika11 халат зеленая | C39: ='Юнит 16-22.03'!AE39 -> 0 | D39: =C39/C$50 -> 0 | E39: =D39+E38 -> 2.4642587 | F39: =IF(AND(E39<=0),"C",IF(E39<=0.8,"A",IF(E39<=0.95,"B","C"))) -> C | G39: =VLOOKUP(B$30:B$50,I$30:M$50,5,0) -> C | I39: tunika08 белая | J39: ='Юнит 16-22.03'!R34 -> 0 | K39: =J39/J$50 -> 0 | L39: =K39+L38 -> 1.1428571 | M39: =_xlfn.IFS(L39<80%,"A",L39<=95%,"B",L39>95%,"C") -> C
B40: tunika12 халат белая | C40: ='Юнит 16-22.03'!AE40 -> 0 | D40: =C40/C$50 -> 0 | E40: =D40+E39 -> 2.4642587 | F40: =IF(AND(E40<=0),"C",IF(E40<=0.8,"A",IF(E40<=0.95,"B","C"))) -> C | G40: =VLOOKUP(B$30:B$50,I$30:M$50,5,0) -> C | I40: tunika08 черная | J40: ='Юнит 16-22.03'!R35 -> 0 | K40: =J40/J$50 -> 0 | L40: =K40+L39 -> 1.1428571 | M40: =_xlfn.IFS(L40<80%,"A",L40<=95%,"B",L40>95%,"C") -> C
B41: tunika13 халат черная | C41: ='Юнит 16-22.03'!AE41 -> 0 | D41: =C41/C$50 -> 0 | E41: =D41+E40 -> 2.4642587 | F41: =IF(AND(E41<=0),"C",IF(E41<=0.8,"A",IF(E41<=0.95,"B","C"))) -> C | G41: =VLOOKUP(B$30:B$50,I$30:M$50,5,0) -> C | I41: tunika09 кимоно | J41: ='Юнит 16-22.03'!R37 -> 0 | K41: =J41/J$50 -> 0 | L41: =K41+L40 -> 1.1428571 | M41: =_xlfn.IFS(L41<80%,"A",L41<=95%,"B",L41>95%,"C") -> C
B42: tunika16 сетка черная | C42: ='Юнит 16-22.03'!AE47 -> 0 | D42: =C42/C$50 -> 0 | E42: =D42+E41 -> 2.4642587 | F42: =IF(AND(E42<=0),"C",IF(E42<=0.8,"A",IF(E42<=0.95,"B","C"))) -> C | G42: =VLOOKUP(B$30:B$50,I$30:M$50,5,0) -> C | I42: tunika11 халат зеленая | J42: ='Юнит 16-22.03'!R39 -> 0 | K42: =J42/J$50 -> 0 | L42: =K42+L41 -> 1.1428571 | M42: =_xlfn.IFS(L42<80%,"A",L42<=95%,"B",L42>95%,"C") -> C
B43: tunika03 черная распашная | C43: ='Юнит 16-22.03'!AE29 -> -113.88 | D43: =C43/C$50 -> -0.013718618 | E43: =D43+E42 -> 2.4505401 | F43: =IF(AND(E43<=0),"C",IF(E43<=0.8,"A",IF(E43<=0.95,"B","C"))) -> C | G43: =VLOOKUP(B$30:B$50,I$30:M$50,5,0) -> C | I43: tunika12 халат белая | J43: ='Юнит 16-22.03'!R40 -> 0 | K43: =J43/J$50 -> 0 | L43: =K43+L42 -> 1.1428571 | M43: =_xlfn.IFS(L43<80%,"A",L43<=95%,"B",L43>95%,"C") -> C
B44: tunika14 халат с разрезами белая | C44: ='Юнит 16-22.03'!AE42 -> -113.88 | D44: =C44/C$50 -> -0.013718618 | E44: =D44+E43 -> 2.4368215 | F44: =IF(AND(E44<=0),"C",IF(E44<=0.8,"A",IF(E44<=0.95,"B","C"))) -> C | G44: =VLOOKUP(B$30:B$50,I$30:M$50,5,0) -> C | I44: tunika13 халат черная | J44: ='Юнит 16-22.03'!R41 -> 0 | K44: =J44/J$50 -> 0 | L44: =K44+L43 -> 1.1428571 | M44: =_xlfn.IFS(L44<80%,"A",L44<=95%,"B",L44>95%,"C") -> C
B45: tunika14 халат с разрезами черный | C45: ='Юнит 16-22.03'!AE43 -> -113.88 | D45: =C45/C$50 -> -0.013718618 | E45: =D45+E44 -> 2.4231029 | F45: =IF(AND(E45<=0),"C",IF(E45<=0.8,"A",IF(E45<=0.95,"B","C"))) -> C | G45: =VLOOKUP(B$30:B$50,I$30:M$50,5,0) -> C | I45: tunika14 халат с разрезами белая | J45: ='Юнит 16-22.03'!R42 -> 0 | K45: =J45/J$50 -> 0 | L45: =K45+L44 -> 1.1428571 | M45: =_xlfn.IFS(L45<80%,"A",L45<=95%,"B",L45>95%,"C") -> C
B46: tunika09 кимоно | C46: ='Юнит 16-22.03'!AE37 -> -227.76 | D46: =C46/C$50 -> -0.027437236 | E46: =D46+E45 -> 2.3956657 | F46: =IF(AND(E46<=0),"C",IF(E46<=0.8,"A",IF(E46<=0.95,"B","C"))) -> C | G46: =VLOOKUP(B$30:B$50,I$30:M$50,5,0) -> C | I46: tunika14 халат с разрезами черный | J46: ='Юнит 16-22.03'!R43 -> 0 | K46: =J46/J$50 -> 0 | L46: =K46+L45 -> 1.1428571 | M46: =_xlfn.IFS(L46<80%,"A",L46<=95%,"B",L46>95%,"C") -> C
B47: tunika10 кимоно ч/б | C47: ='Юнит 16-22.03'!AE38 -> -3162.0106 | D47: =C47/C$50 -> -0.38091337 | E47: =D47+E46 -> 2.0147523 | F47: =IF(AND(E47<=0),"C",IF(E47<=0.8,"A",IF(E47<=0.95,"B","C"))) -> C | G47: =VLOOKUP(B$30:B$50,I$30:M$50,5,0) -> C | I47: tunika16 сетка черная | J47: ='Юнит 16-22.03'!R47 -> 0 | K47: =J47/J$50 -> 0 | L47: =K47+L46 -> 1.1428571 | M47: =_xlfn.IFS(L47<80%,"A",L47<=95%,"B",L47>95%,"C") -> C
B48: tunika08 зеленая | C48: ='Юнит 16-22.03'!AE36 -> -3773.6978 | D48: =C48/C$50 -> -0.45460062 | E48: =D48+E47 -> 1.5601517 | F48: =IF(AND(E48<=0),"C",IF(E48<=0.8,"A",IF(E48<=0.95,"B","C"))) -> C | G48: =VLOOKUP(B$30:B$50,I$30:M$50,5,0) -> C | I48: tunika10 кимоно ч/б | J48: ='Юнит 16-22.03'!R38 -> -1 | K48: =J48/J$50 -> -0.047619048 | L48: =K48+L47 -> 1.0952381 | M48: =_xlfn.IFS(L48<80%,"A",L48<=95%,"B",L48>95%,"C") -> C
B49: tunika15 кимоно бирюза | C49: ='Юнит 16-22.03'!AE44 -> -4649.8906 | D49: =C49/C$50 -> -0.56015167 | E49: =D49+E48 -> 1 | F49: =IF(AND(E49<=0),"C",IF(E49<=0.8,"A",IF(E49<=0.95,"B","C"))) -> C | G49: =VLOOKUP(B$30:B$50,I$30:M$50,5,0) -> C | I49: tunika08 зеленая | J49: ='Юнит 16-22.03'!R36 -> -2 | K49: =J49/J$50 -> -0.095238095 | L49: =K49+L48 -> 1 | M49: =_xlfn.IFS(L49<80%,"A",L49<=95%,"B",L49>95%,"C") -> C
C50: =SUM(C30:C49) -> 8301.1278 | D50: =SUM(D30:D49) -> 1 | J50: =SUM(J30:J49) -> 21 | K50: =SUM(K30:K49) -> 1

Sheet АВС 09-15.03
B2: ОЧКИ
C3: Прибыль | D3: % прибыль | E3: Доля | F3: ABC прибыль | G3: ABC кол-во | J3: Кол-во | K3: % кол-во | L3: Доля | M3: ABC кол-во
B4: черные с железкой классика | C4: ='Юнит 09-15.03'!AE3 -> 57490.095 | D4: =C4/C$26 -> 0.62183985 | E4: =D4 -> 0.62183985 | F4: =IF(AND(E4<=0),"C",IF(E4<=0.8,"A",IF(E4<=0.95,"B","C"))) -> A | G4: =VLOOKUP(B$4:B$25,I$4:M$25,5,0) -> A | I4: черные с железкой классика | J4: ='Юнит 09-15.03'!R3 -> 75 | K4: =J4/J$26 -> 0.52083333 | L4: =K4 -> 0.52083333 | M4: =_xlfn.IFS(L4<80%,"A",L4<=95%,"B",L4>95%,"C") -> A
B5: qs желтые | C5: ='Юнит 09-15.03'!AE6 -> 8977.45 | D5: =C5/C$26 -> 0.097104312 | E5: =D5+E4 -> 0.71894416 | F5: =IF(AND(E5<=0),"C",IF(E5<=0.8,"A",IF(E5<=0.95,"B","C"))) -> A | G5: =VLOOKUP(B$4:B$25,I$4:M$25,5,0) -> A | I5: qs желтые | J5: ='Юнит 09-15.03'!R6 -> 16 | K5: =J5/J$26 -> 0.11111111 | L5: =K5+L4 -> 0.63194444 | M5: =_xlfn.IFS(L5<80%,"A",L5<=95%,"B",L5>95%,"C") -> A
B6: MR8854 C2 | C6: ='Юнит 09-15.03'!AE10 -> 7824.7691 | D6: =C6/C$26 -> 0.084636374 | E6: =D6+E5 -> 0.80358053 | F6: =IF(AND(E6<=0),"C",IF(E6<=0.8,"A",IF(E6<=0.95,"B","C"))) -> B | G6: =VLOOKUP(B$4:B$25,I$4:M$25,5,0) -> A | I6: MR8854 C2 | J6: ='Юнит 09-15.03'!R10 -> 14 | K6: =J6/J$26 -> 0.097222222 | L6: =K6+L5 -> 0.72916667 | M6: =_xlfn.IFS(L6<80%,"A",L6<=95%,"B",L6>95%,"C") -> A
B7: qs коричневые | C7: ='Юнит 09-15.03'!AE7 -> 5985.5 | D7: =C7/C$26 -> 0.064741977 | E7: =D7+E6 -> 0.86832251 | F7: =IF(AND(E7<=0),"C",IF(E7<=0.8,"A",IF(E7<=0.95,"B","C"))) -> B | G7: =VLOOKUP(B$4:B$25,I$4:M$25,5,0) -> A | I7: qs коричневые | J7: ='Юнит 09-15.03'!R7 -> 8 | K7: =J7/J$26 -> 0.055555556 | L7: =K7+L6 -> 0.78472222 | M7: =_xlfn.IFS(L7<80%,"A",L7<=95%,"B",L7>95%,"C") -> A
B8: qs черные | C8: ='Юнит 09-15.03'!AE4 -> 5267.1913 | D8: =C8/C$26 -> 0.056972413 | E8: =D8+E7 -> 0.92529492 | F8: =IF(AND(E8<=0),"C",IF(E8<=0.8,"A",IF(E8<=0.95,"B","C"))) -> B | G8: =VLOOKUP(B$4:B$25,I$4:M$25,5,0) -> B | I8: qs черные | J8: ='Юнит 09-15.03'!R4 -> 7 | K8: =J8/J$26 -> 0.048611111 | L8: =K8+L7 -> 0.83333333 | M8: =_xlfn.IFS(L8<80%,"A",L8<=95%,"B",L8>95%,"C") -> B
B9: flip желтые Сул | C9: ='Юнит 09-15.03'!AE9 -> 2105.1583 | D9: =C9/C$26 -> 0.02277038 | E9: =D9+E8 -> 0.9480653 | F9: =IF(AND(E9<=0),"C",IF(E9<=0.8,"A",IF(E9<=0.95,"B","C"))) -> B | G9: =VLOOKUP(B$4:B$25,I$4:M$25,5,0) -> B | I9: qs синие | J9: ='Юнит 09-15.03'!R5 -> 6 | K9: =J9/J$26 -> 0.041666667 | L9: =K9+L8 -> 0.875 | M9: =_xlfn.IFS(L9<80%,"A",L9<=95%,"B",L9>95%,"C") -> B
B10: qs синие | C10: ='Юнит 09-15.03'!AE5 -> 1912.8229 | D10: =C10/C$26 -> 0.02068999 | E10: =D10+E9 -> 0.96875529 | F10: =IF(AND(E10<=0),"C",IF(E10<=0.8,"A",IF(E10<=0.95,"B","C"))) -> C | G10: =VLOOKUP(B$4:B$25,I$4:M$25,5,0) -> B | I10: MR Р1886 корич | J10: ='Юнит 09-15.03'!R16 -> 5 | K10: =J10/J$26 -> 0.034722222 | L10: =K10+L9 -> 0.90972222 | M10: =_xlfn.IFS(L10<80%,"A",L10<=95%,"B",L10>95%,"C") -> B
B11: MR Р1886 черн глянец | C11: ='Юнит 09-15.03'!AE15 -> 1189.9334 | D11: =C11/C$26 -> 0.012870878 | E11: =D11+E8 -> 0.9381658 | F11: =IF(AND(E11<=0),"C",IF(E11<=0.8,"A",IF(E11<=0.95,"B","C"))) -> B | G11: =VLOOKUP(B$4:B$25,I$4:M$25,5,0) -> B | I11: MR Р1886 черн глянец | J11: ='Юнит 09-15.03'!R15 -> 4 | K11: =J11/J$26 -> 0.027777778 | L11: =K11+L8 -> 0.86111111 | M11: =_xlfn.IFS(L11<80%,"A",L11<=95%,"B",L11>95%,"C") -> B
B12: MR 1819 корич | C12: ='Юнит 09-15.03'!AE12 -> 1133.998 | D12: =C12/C$26 -> 0.012265854 | E12: =D12+E11 -> 0.95043165 | F12: =IF(AND(E12<=0),"C",IF(E12<=0.8,"A",IF(E12<=0.95,"B","C"))) -> C | G12: =VLOOKUP(B$4:B$25,I$4:M$25,5,0) -> B | I12: flip желтые Сул | J12: ='Юнит 09-15.03'!R9 -> 3 | K12: =J12/J$26 -> 0.020833333 | L12: =K12+L11 -> 0.88194444 | M12: =_xlfn.IFS(L12<80%,"A",L12<=95%,"B",L12>95%,"C") -> B
B13: MR 1819 черн | C13: ='Юнит 09-15.03'!AE11 -> 1114.5018 | D13: =C13/C$26 -> 0.012054975 | E13: =D13+E12 -> 0.96248663 | F13: =IF(AND(E13<=0),"C",IF(E13<=0.8,"A",IF(E13<=0.95,"B","C"))) -> C | G13: =VLOOKUP(B$4:B$25,I$4:M$25,5,0) -> B | I13: th желтый Сул | J13: ='Юнит 09-15.03'!R8 -> 2 | K13: =J13/J$26 -> 0.013888889 | L13: =K13+L12 -> 0.89583333 | M13: =_xlfn.IFS(L13<80%,"A",L13<=95%,"B",L13>95%,"C") -> B | P13: A | Q13: 0.8
B14: MR Р1886 корич | C14: ='Юнит 09-15.03'!AE16 -> 837.23394 | D14: =C14/C$26 -> 0.0090559152 | E14: =D14+E13 -> 0.97154254 | F14: =IF(AND(E14<=0),"C",IF(E14<=0.8,"A",IF(E14<=0.95,"B","C"))) -> C | G14: =VLOOKUP(B$4:B$25,I$4:M$25,5,0) -> B | I14: MR 1819 черн | J14: ='Юнит 09-15.03'!R11 -> 2 | K14: =J14/J$26 -> 0.013888889 | L14: =K14+L13 -> 0.90972222 | M14: =_xlfn.IFS(L14<80%,"A",L14<=95%,"B",L14>95%,"C") -> B | P14: B | Q14: 0.15
B15: MR Р1874 корич | C15: ='Юнит 09-15.03'!AE14 -> 0 | D15: =C15/C$26 -> 0 | E15: =D15+E14 -> 0.97154254 | F15: =IF(AND(E15<=0),"C",IF(E15<=0.8,"A",IF(E15<=0.95,"B","C"))) -> C | G15: =VLOOKUP(B$4:B$25,I$4:M$25,5,0) -> B | I15: MR 1819 корич | J15: ='Юнит 09-15.03'!R12 -> 2 | K15: =J15/J$26 -> 0.013888889 | L15: =K15+L14 -> 0.92361111 | M15: =_xlfn.IFS(L15<80%,"A",L15<=95%,"B",L15>95%,"C") -> B | P15: C | Q15: 0.05
B16: lux1 | C16: ='Юнит 09-15.03'!AE17 -> 0 | D16: =C16/C$26 -> 0 | E16: =D16+E15 -> 0.97154254 | F16: =IF(AND(E16<=0),"C",IF(E16<=0.8,"A",IF(E16<=0.95,"B","C"))) -> C | G16: =VLOOKUP(B$4:B$25,I$4:M$25,5,0) -> B | I16: MR Р1874 черн | J16: ='Юнит 09-15.03'!R13 -> 0 | K16: =J16/J$26 -> 0 | L16: =K16+L15 -> 0.92361111 | M16: =_xlfn.IFS(L16<80%,"A",L16<=95%,"B",L16>95%,"C") -> B
B17: lux2 | C17: ='Юнит 09-15.03'!AE18 -> 0 | D17: =C17/C$26 -> 0 | E17: =D17+E16 -> 0.97154254 | F17: =IF(AND(E17<=0),"C",IF(E17<=0.8,"A",IF(E17<=0.95,"B","C"))) -> C | G17: =VLOOKUP(B$4:B$25,I$4:M$25,5,0) -> B | I17: MR Р1874 корич | J17: ='Юнит 09-15.03'!R14 -> 0 | K17: =J17/J$26 -> 0 | L17: =K17+L16 -> 0.92361111 | M17: =_xlfn.IFS(L17<80%,"A",L17<=95%,"B",L17>95%,"C") -> B
B18: lux3 | C18: ='Юнит 09-15.03'!AE19 -> 0 | D18: =C18/C$26 -> 0 | E18: =D18+E17 -> 0.97154254 | F18: =IF(AND(E18<=0),"C",IF(E18<=0.8,"A",IF(E18<=0.95,"B","C"))) -> C | G18: =VLOOKUP(B$4:B$25,I$4:M$25,5,0) -> B | I18: lux1 | J18: ='Юнит 09-15.03'!R17 -> 0 | K18: =J18/J$26 -> 0 | L18: =K18+L17 -> 0.92361111 | M18: =_xlfn.IFS(L18<80%,"A",L18<=95%,"B",L18>95%,"C") -> B
B19: lux4 | C19: ='Юнит 09-15.03'!AE20 -> 0 | D19: =C19/C$26 -> 0 | E19: =D19+E18 -> 0.97154254 | F19: =IF(AND(E19<=0),"C",IF(E19<=0.8,"A",IF(E19<=0.95,"B","C"))) -> C | G19: =VLOOKUP(B$4:B$25,I$4:M$25,5,0) -> B | I19: lux2 | J19: ='Юнит 09-15.03'!R18 -> 0 | K19: =J19/J$26 -> 0 | L19: =K19+L18 -> 0.92361111 | M19: =_xlfn.IFS(L19<80%,"A",L19<=95%,"B",L19>95%,"C") -> B
B20: lux5 | C20: ='Юнит 09-15.03'!AE21 -> 0 | D20: =C20/C$26 -> 0 | E20: =D20+E19 -> 0.97154254 | F20: =IF(AND(E20<=0),"C",IF(E20<=0.8,"A",IF(E20<=0.95,"B","C"))) -> C | G20: =VLOOKUP(B$4:B$25,I$4:M$25,5,0) -> B | I20: lux3 | J20: ='Юнит 09-15.03'!R19 -> 0 | K20: =J20/J$26 -> 0 | L20: =K20+L19 -> 0.92361111 | M20: =_xlfn.IFS(L20<80%,"A",L20<=95%,"B",L20>95%,"C") -> B
B21: lux6 | C21: ='Юнит 09-15.03'!AE22 -> 0 | D21: =C21/C$26 -> 0 | E21: =D21+E20 -> 0.97154254 | F21: =IF(AND(E21<=0),"C",IF(E21<=0.8,"A",IF(E21<=0.95,"B","C"))) -> C | G21: =VLOOKUP(B$4:B$25,I$4:M$25,5,0) -> B | I21: lux4 | J21: ='Юнит 09-15.03'!R20 -> 0 | K21: =J21/J$26 -> 0 | L21: =K21+L20 -> 0.92361111 | M21: =_xlfn.IFS(L21<80%,"A",L21<=95%,"B",L21>95%,"C") -> B
B22: lux7 | C22: ='Юнит 09-15.03'!AE23 -> 0 | D22: =C22/C$26 -> 0 | E22: =D22+E21 -> 0.97154254 | F22: =IF(AND(E22<=0),"C",IF(E22<=0.8,"A",IF(E22<=0.95,"B","C"))) -> C | G22: =VLOOKUP(B$4:B$25,I$4:M$25,5,0) -> B | I22: lux5 | J22: ='Юнит 09-15.03'!R21 -> 0 | K22: =J22/J$26 -> 0 | L22: =K22+L21 -> 0.92361111 | M22: =_xlfn.IFS(L22<80%,"A",L22<=95%,"B",L22>95%,"C") -> B
B23: lux8 | C23: ='Юнит 09-15.03'!AE24 -> 0 | D23: =C23/C$26 -> 0 | E23: =D23+E22 -> 0.97154254 | F23: =IF(AND(E23<=0),"C",IF(E23<=0.8,"A",IF(E23<=0.95,"B","C"))) -> C | G23: =VLOOKUP(B$4:B$25,I$4:M$25,5,0) -> B | I23: lux6 | J23: ='Юнит 09-15.03'!R22 -> 0 | K23: =J23/J$26 -> 0 | L23: =K23+L22 -> 0.92361111 | M23: =_xlfn.IFS(L23<80%,"A",L23<=95%,"B",L23>95%,"C") -> B
B24: th желтый Сул | C24: ='Юнит 09-15.03'!AE8 -> -673.88369 | D24: =C24/C$26 -> -0.0072890422 | E24: =D24+E23 -> 0.9642535 | F24: =IF(AND(E24<=0),"C",IF(E24<=0.8,"A",IF(E24<=0.95,"B","C"))) -> C | G24: =VLOOKUP(B$4:B$25,I$4:M$25,5,0) -> B | I24: lux7 | J24: ='Юнит 09-15.03'!R23 -> 0 | K24: =J24/J$26 -> 0 | L24: =K24+L23 -> 0.92361111 | M24: =_xlfn.IFS(L24<80%,"A",L24<=95%,"B",L24>95%,"C") -> B
B25: MR Р1874 черн | C25: ='Юнит 09-15.03'!AE13 -> -713.16 | D25: =C25/C$26 -> -0.0077138732 | E25: =D25+E24 -> 0.95653963 | F25: =IF(AND(E25<=0),"C",IF(E25<=0.8,"A",IF(E25<=0.95,"B","C"))) -> C | G25: =VLOOKUP(B$4:B$25,I$4:M$25,5,0) -> B | I25: lux8 | J25: ='Юнит 09-15.03'!R24 -> 0 | K25: =J25/J$26 -> 0 | L25: =K25+L24 -> 0.92361111 | M25: =_xlfn.IFS(L25<80%,"A",L25<=95%,"B",L25>95%,"C") -> B
C26: =SUM(C4:C25) -> 92451.61 | D26: =SUM(D4:D25) -> 1 | J26: =SUM(J4:J25) -> 144 | K26: =SUM(K4:K25) -> 1
B28: ТУНИКИ
C29: Прибыль | D29: % прибыль | E29: Доля | F29: ABC прибыль | G29: ABC кол-во | J29: Кол-во | K29: % кол-во | L29: Доля | M29: ABC кол-во
B30: tunika16 сетка белая | C30: ='Юнит 09-15.03'!AE46 -> 6748.0047 | D30: =C30/C$50 -> 0.48668548 | E30: =D30 -> 0.48668548 | F30: =IF(AND(E30<=0),"C",IF(E30<=0.8,"A",IF(E30<=0.95,"B","C"))) -> A | G30: =VLOOKUP(B$30:B$50,I$30:M$50,5,0) -> A | I30: tunika16 сетка белая | J30: ='Юнит 09-15.03'!R46 -> 10 | K30: =J30/J$50 -> 0.3125 | L30: =K30 -> 0.3125 | M30: =_xlfn.IFS(L30<80%,"A",L30<=95%,"B",L30>95%,"C") -> A
B31: tunika07 кружево | C31: ='Юнит 09-15.03'!AE33 -> 4772.6028 | D31: =C31/C$50 -> 0.34421383 | E31: =D31+E30 -> 0.83089931 | F31: =IF(AND(E31<=0),"C",IF(E31<=0.8,"A",IF(E31<=0.95,"B","C"))) -> B | G31: =VLOOKUP(B$30:B$50,I$30:M$50,5,0) -> B | I31: tunika15 кимоно песочная | J31: ='Юнит 09-15.03'!R45 -> 8 | K31: =J31/J$50 -> 0.25 | L31: =K31+L30 -> 0.5625 | M31: =_xlfn.IFS(L31<80%,"A",L31<=95%,"B",L31>95%,"C") -> A
B32: tunika08 зеленая | C32: ='Юнит 09-15.03'!AE36 -> 2807.6962 | D32: =C32/C$50 -> 0.20249912 | E32: =D32+E31 -> 1.0333984 | F32: =IF(AND(E32<=0),"C",IF(E32<=0.8,"A",IF(E32<=0.95,"B","C"))) -> C | G32: =VLOOKUP(B$30:B$50,I$30:M$50,5,0) -> C | I32: tunika02 оливковая с руч вышивкой | J32: ='Юнит 09-15.03'!R28 -> 6 | K32: =J32/J$50 -> 0.1875 | L32: =K32+L31 -> 0.75 | M32: =_xlfn.IFS(L32<80%,"A",L32<=95%,"B",L32>95%,"C") -> A
B33: tunika10 кимоно ч/б | C33: ='Юнит 09-15.03'!AE38 -> 2706.9057 | D33: =C33/C$50 -> 0.19522981 | E33: =D33+E32 -> 1.2286282 | F33: =IF(AND(E33<=0),"C",IF(E33<=0.8,"A",IF(E33<=0.95,"B","C"))) -> C | G33: =VLOOKUP(B$30:B$50,I$30:M$50,5,0) -> C | I33: tunika07 кружево | J33: ='Юнит 09-15.03'!R33 -> 5 | K33: =J33/J$50 -> 0.15625 | L33: =K33+L32 -> 0.90625 | M33: =_xlfn.IFS(L33<80%,"A",L33<=95%,"B",L33>95%,"C") -> B
B34: tunika15 кимоно песочная | C34: ='Юнит 09-15.03'!AE45 -> 1973.4553 | D34: =C34/C$50 -> 0.14233127 | E34: =D34+E33 -> 1.3709595 | F34: =IF(AND(E34<=0),"C",IF(E34<=0.8,"A",IF(E34<=0.95,"B","C"))) -> C | G34: =VLOOKUP(B$30:B$50,I$30:M$50,5,0) -> A | I34: tunika08 зеленая | J34: ='Юнит 09-15.03'!R36 -> 2 | K34: =J34/J$50 -> 0.0625 | L34: =K34+L33 -> 0.96875 | M34: =_xlfn.IFS(L34<80%,"A",L34<=95%,"B",L34>95%,"C") -> C
B35: tunika05 белая распашная | C35: ='Юнит 09-15.03'!AE30 -> 1255.6989 | D35: =C35/C$50 -> 0.09056461 | E35: =D35+E34 -> 1.4615241 | F35: =IF(AND(E35<=0),"C",IF(E35<=0.8,"A",IF(E35<=0.95,"B","C"))) -> C | G35: =VLOOKUP(B$30:B$50,I$30:M$50,5,0) -> C | I35: tunika05 белая распашная | J35: ='Юнит 09-15.03'!R30 -> 1 | K35: =J35/J$50 -> 0.03125 | L35: =K35+L34 -> 1 | M35: =_xlfn.IFS(L35<80%,"A",L35<=95%,"B",L35>95%,"C") -> C
B36: tunika03 черная распашная | C36: ='Юнит 09-15.03'!AE29 -> 0 | D36: =C36/C$50 -> 0 | E36: =D36+E35 -> 1.4615241 | F36: =IF(AND(E36<=0),"C",IF(E36<=0.8,"A",IF(E36<=0.95,"B","C"))) -> C | G36: =VLOOKUP(B$30:B$50,I$30:M$50,5,0) -> C | I36: tunika10 кимоно ч/б | J36: ='Юнит 09-15.03'!R38 -> 1 | K36: =J36/J$50 -> 0.03125 | L36: =K36+L35 -> 1.03125 | M36: =_xlfn.IFS(L36<80%,"A",L36<=95%,"B",L36>95%,"C") -> C
B37: tunika06 черная | C37: ='Юнит 09-15.03'!AE32 -> 0 | D37: =C37/C$50 -> 0 | E37: =D37+E36 -> 1.4615241 | F37: =IF(AND(E37<=0),"C",IF(E37<=0.8,"A",IF(E37<=0.95,"B","C"))) -> C | G37: =VLOOKUP(B$30:B$50,I$30:M$50,5,0) -> C | I37: tunika03 черная распашная | J37: ='Юнит 09-15.03'!R29 -> 0 | K37: =J37/J$50 -> 0 | L37: =K37+L36 -> 1.03125 | M37: =_xlfn.IFS(L37<80%,"A",L37<=95%,"B",L37>95%,"C") -> C
B38: tunika08 черная | C38: ='Юнит 09-15.03'!AE35 -> 0 | D38: =C38/C$50 -> 0 | E38: =D38+E37 -> 1.4615241 | F38: =IF(AND(E38<=0),"C",IF(E38<=0.8,"A",IF(E38<=0.95,"B","C"))) -> C | G38: =VLOOKUP(B$30:B$50,I$30:M$50,5,0) -> C | I38: tunika06 черная | J38: ='Юнит 09-15.03'!R32 -> 0 | K38: =J38/J$50 -> 0 | L38: =K38+L37 -> 1.03125 | M38: =_xlfn.IFS(L38<80%,"A",L38<=95%,"B",L38>95%,"C") -> C
B39: tunika12 халат белая | C39: ='Юнит 09-15.03'!AE40 -> 0 | D39: =C39/C$50 -> 0 | E39: =D39+E38 -> 1.4615241 | F39: =IF(AND(E39<=0),"C",IF(E39<=0.8,"A",IF(E39<=0.95,"B","C"))) -> C | G39: =VLOOKUP(B$30:B$50,I$30:M$50,5,0) -> C | I39: tunika08 белая | J39: ='Юнит 09-15.03'!R34 -> 0 | K39: =J39/J$50 -> 0 | L39: =K39+L38 -> 1.03125 | M39: =_xlfn.IFS(L39<80%,"A",L39<=95%,"B",L39>95%,"C") -> C
B40: tunika13 халат черная | C40: ='Юнит 09-15.03'!AE41 -> 0 | D40: =C40/C$50 -> 0 | E40: =D40+E39 -> 1.4615241 | F40: =IF(AND(E40<=0),"C",IF(E40<=0.8,"A",IF(E40<=0.95,"B","C"))) -> C | G40: =VLOOKUP(B$30:B$50,I$30:M$50,5,0) -> C | I40: tunika08 черная | J40: ='Юнит 09-15.03'!R35 -> 0 | K40: =J40/J$50 -> 0 | L40: =K40+L39 -> 1.03125 | M40: =_xlfn.IFS(L40<80%,"A",L40<=95%,"B",L40>95%,"C") -> C
B41: tunika14 халат с разрезами черный | C41: ='Юнит 09-15.03'!AE43 -> -56.94 | D41: =C41/C$50 -> -0.0041066764 | E41: =D41+E40 -> 1.4574174 | F41: =IF(AND(E41<=0),"C",IF(E41<=0.8,"A",IF(E41<=0.95,"B","C"))) -> C | G41: =VLOOKUP(B$30:B$50,I$30:M$50,5,0) -> C | I41: tunika09 кимоно | J41: ='Юнит 09-15.03'!R37 -> 0 | K41: =J41/J$50 -> 0 | L41: =K41+L40 -> 1.03125 | M41: =_xlfn.IFS(L41<80%,"A",L41<=95%,"B",L41>95%,"C") -> C
B42: tunika09 кимоно | C42: ='Юнит 09-15.03'!AE37 -> -113.88 | D42: =C42/C$50 -> -0.0082133528 | E42: =D42+E41 -> 1.4492041 | F42: =IF(AND(E42<=0),"C",IF(E42<=0.8,"A",IF(E42<=0.95,"B","C"))) -> C | G42: =VLOOKUP(B$30:B$50,I$30:M$50,5,0) -> C | I42: tunika11 халат зеленая | J42: ='Юнит 09-15.03'!R39 -> 0 | K42: =J42/J$50 -> 0 | L42: =K42+L41 -> 1.03125 | M42: =_xlfn.IFS(L42<80%,"A",L42<=95%,"B",L42>95%,"C") -> C
B43: tunika14 халат с разрезами белая | C43: ='Юнит 09-15.03'!AE42 -> -170.82 | D43: =C43/C$50 -> -0.012320029 | E43: =D43+E42 -> 1.4368841 | F43: =IF(AND(E43<=0),"C",IF(E43<=0.8,"A",IF(E43<=0.95,"B","C"))) -> C | G43: =VLOOKUP(B$30:B$50,I$30:M$50,5,0) -> C | I43: tunika12 халат белая | J43: ='Юнит 09-15.03'!R40 -> 0 | K43: =J43/J$50 -> 0 | L43: =K43+L42 -> 1.03125 | M43: =_xlfn.IFS(L43<80%,"A",L43<=95%,"B",L43>95%,"C") -> C
B44: tunika16 сетка черная | C44: ='Юнит 09-15.03'!AE47 -> -227.76 | D44: =C44/C$50 -> -0.016426706 | E44: =D44+E43 -> 1.4204574 | F44: =IF(AND(E44<=0),"C",IF(E44<=0.8,"A",IF(E44<=0.95,"B","C"))) -> C | G44: =VLOOKUP(B$30:B$50,I$30:M$50,5,0) -> C | I44: tunika13 халат черная | J44: ='Юнит 09-15.03'!R41 -> 0 | K44: =J44/J$50 -> 0 | L44: =K44+L43 -> 1.03125 | M44: =_xlfn.IFS(L44<80%,"A",L44<=95%,"B",L44>95%,"C") -> C
B45: tunika08 белая | C45: ='Юнит 09-15.03'!AE34 -> -284.7 | D45: =C45/C$50 -> -0.020533382 | E45: =D45+E44 -> 1.399924 | F45: =IF(AND(E45<=0),"C",IF(E45<=0.8,"A",IF(E45<=0.95,"B","C"))) -> C | G45: =VLOOKUP(B$30:B$50,I$30:M$50,5,0) -> C | I45: tunika14 халат с разрезами белая | J45: ='Юнит 09-15.03'!R42 -> 0 | K45: =J45/J$50 -> 0 | L45: =K45+L44 -> 1.03125 | M45: =_xlfn.IFS(L45<80%,"A",L45<=95%,"B",L45>95%,"C") -> C
B46: tunika11 халат зеленая | C46: ='Юнит 09-15.03'!AE39 -> -338.12 | D46: =C46/C$50 -> -0.024386186 | E46: =D46+E45 -> 1.3755378 | F46: =IF(AND(E46<=0),"C",IF(E46<=0.8,"A",IF(E46<=0.95,"B","C"))) -> C | G46: =VLOOKUP(B$30:B$50,I$30:M$50,5,0) -> C | I46: tunika14 халат с разрезами черный | J46: ='Юнит 09-15.03'!R43 -> 0 | K46: =J46/J$50 -> 0 | L46: =K46+L45 -> 1.03125 | M46: =_xlfn.IFS(L46<80%,"A",L46<=95%,"B",L46>95%,"C") -> C
B47: tunika15 кимоно бирюза | C47: ='Юнит 09-15.03'!AE44 -> -912.44 | D47: =C47/C$50 -> -0.065807794 | E47: =D47+E46 -> 1.30973 | F47: =IF(AND(E47<=0),"C",IF(E47<=0.8,"A",IF(E47<=0.95,"B","C"))) -> C | G47: =VLOOKUP(B$30:B$50,I$30:M$50,5,0) -> C | I47: tunika15 кимоно бирюза | J47: ='Юнит 09-15.03'!R44 -> 0 | K47: =J47/J$50 -> 0 | L47: =K47+L46 -> 1.03125 | M47: =_xlfn.IFS(L47<80%,"A",L47<=95%,"B",L47>95%,"C") -> C
B48: tunika06 белая | C48: ='Юнит 09-15.03'!AE31 -> -1810.8498 | D48: =C48/C$50 -> -0.13060369 | E48: =D48+E47 -> 1.1791263 | F48: =IF(AND(E48<=0),"C",IF(E48<=0.8,"A",IF(E48<=0.95,"B","C"))) -> C | G48: =VLOOKUP(B$30:B$50,I$30:M$50,5,0) -> C | I48: tunika16 сетка черная | J48: ='Юнит 09-15.03'!R47 -> 0 | K48: =J48/J$50 -> 0 | L48: =K48+L47 -> 1.03125 | M48: =_xlfn.IFS(L48<80%,"A",L48<=95%,"B",L48>95%,"C") -> C
B49: tunika02 оливковая с руч вышивкой | C49: ='Юнит 09-15.03'!AE28 -> -2483.6268 | D49: =C49/C$50 -> -0.1791263 | E49: =D49+E48 -> 1 | F49: =IF(AND(E49<=0),"C",IF(E49<=0.8,"A",IF(E49<=0.95,"B","C"))) -> C | G49: =VLOOKUP(B$30:B$50,I$30:M$50,5,0) -> A | I49: tunika06 белая | J49: ='Юнит 09-15.03'!R31 -> -1 | K49: =J49/J$50 -> -0.03125 | L49: =K49+L48 -> 1 | M49: =_xlfn.IFS(L49<80%,"A",L49<=95%,"B",L49>95%,"C") -> C
C50: =SUM(C30:C49) -> 13865.227 | D50: =SUM(D30:D49) -> 1 | J50: =SUM(J30:J49) -> 32 | K50: =SUM(K30:K49) -> 1

Sheet АВС 02-08.03
B2: ОЧКИ
C3: Прибыль | D3: % прибыль | E3: Доля | F3: ABC прибыль | G3: ABC кол-во | J3: Кол-во | K3: % кол-во | L3: Доля | M3: ABC кол-во
B4: черные с железкой классика | C4: ='Юнит 02-08.03'!AE3 -> 18536.642 | D4: =C4/C$26 -> 0.51336122 | E4: =D4 -> 0.51336122 | F4: =IF(AND(E4<=0),"C",IF(E4<=0.8,"A",IF(E4<=0.95,"B","C"))) -> A | G4: =VLOOKUP(B$4:B$25,I$4:M$25,5,0) -> A | I4: черные с железкой классика | J4: ='Юнит 02-08.03'!R3 -> 36 | K4: =J4/J$26 -> 0.38297872 | L4: =K4 -> 0.38297872 | M4: =_xlfn.IFS(L4<80%,"A",L4<=95%,"B",L4>95%,"C") -> A
B5: MR8854 C2 | C5: ='Юнит 02-08.03'!AE10 -> 10703.858 | D5: =C5/C$26 -> 0.29643694 | E5: =D5+E4 -> 0.80979816 | F5: =IF(AND(E5<=0),"C",IF(E5<=0.8,"A",IF(E5<=0.95,"B","C"))) -> B | G5: =VLOOKUP(B$4:B$25,I$4:M$25,5,0) -> A | I5: MR8854 C2 | J5: ='Юнит 02-08.03'!R10 -> 19 | K5: =J5/J$26 -> 0.20212766 | L5: =K5+L4 -> 0.58510638 | M5: =_xlfn.IFS(L5<80%,"A",L5<=95%,"B",L5>95%,"C") -> A
B6: qs коричневые | C6: ='Юнит 02-08.03'!AE7 -> 4005.3458 | D6: =C6/C$26 -> 0.11092566 | E6: =D6+E5 -> 0.92072381 | F6: =IF(AND(E6<=0),"C",IF(E6<=0.8,"A",IF(E6<=0.95,"B","C"))) -> B | G6: =VLOOKUP(B$4:B$25,I$4:M$25,5,0) -> A | I6: qs желтые | J6: ='Юнит 02-08.03'!R6 -> 9 | K6: =J6/J$26 -> 0.095744681 | L6: =K6+L5 -> 0.68085106 | M6: =_xlfn.IFS(L6<80%,"A",L6<=95%,"B",L6>95%,"C") -> A
B7: qs желтые | C7: ='Юнит 02-08.03'!AE6 -> 3461.4598 | D7: =C7/C$26 -> 0.095863059 | E7: =D7+E6 -> 1.0165869 | F7: =IF(AND(E7<=0),"C",IF(E7<=0.8,"A",IF(E7<=0.95,"B","C"))) -> C | G7: =VLOOKUP(B$4:B$25,I$4:M$25,5,0) -> A | I7: qs коричневые | J7: ='Юнит 02-08.03'!R7 -> 8 | K7: =J7/J$26 -> 0.085106383 | L7: =K7+L6 -> 0.76595745 | M7: =_xlfn.IFS(L7<80%,"A",L7<=95%,"B",L7>95%,"C") -> A
B8: MR Р1874 черн | C8: ='Юнит 02-08.03'!AE13 -> 1242.7288 | D8: =C8/C$26 -> 0.03441663 | E8: =D8+E7 -> 1.0510035 | F8: =IF(AND(E8<=0),"C",IF(E8<=0.8,"A",IF(E8<=0.95,"B","C"))) -> C | G8: =VLOOKUP(B$4:B$25,I$4:M$25,5,0) -> B | I8: flip желтые Сул | J8: ='Юнит 02-08.03'!R9 -> 4 | K8: =J8/J$26 -> 0.042553191 | L8: =K8+L7 -> 0.80851064 | M8: =_xlfn.IFS(L8<80%,"A",L8<=95%,"B",L8>95%,"C") -> B
B9: MR Р1886 корич | C9: ='Юнит 02-08.03'!AE16 -> 1234.1401 | D9: =C9/C$26 -> 0.034178773 | E9: =D9+E8 -> 1.0851823 | F9: =IF(AND(E9<=0),"C",IF(E9<=0.8,"A",IF(E9<=0.95,"B","C"))) -> C | G9: =VLOOKUP(B$4:B$25,I$4:M$25,5,0) -> B | I9: MR Р1886 черн глянец | J9: ='Юнит 02-08.03'!R15 -> 4 | K9: =J9/J$26 -> 0.042553191 | L9: =K9+L8 -> 0.85106383 | M9: =_xlfn.IFS(L9<80%,"A",L9<=95%,"B",L9>95%,"C") -> B
B10: flip желтые Сул | C10: ='Юнит 02-08.03'!AE9 -> 1048.3384 | D10: =C10/C$26 -> 0.029033106 | E10: =D10+E9 -> 1.1142154 | F10: =IF(AND(E10<=0),"C",IF(E10<=0.8,"A",IF(E10<=0.95,"B","C"))) -> C | G10: =VLOOKUP(B$4:B$25,I$4:M$25,5,0) -> B | I10: MR Р1886 корич | J10: ='Юнит 02-08.03'!R16 -> 4 | K10: =J10/J$26 -> 0.042553191 | L10: =K10+L9 -> 0.89361702 | M10: =_xlfn.IFS(L10<80%,"A",L10<=95%,"B",L10>95%,"C") -> B
B11: MR 1819 черн | C11: ='Юнит 02-08.03'!AE11 -> 475.1554 | D11: =C11/C$26 -> 0.013159145 | E11: =D11+E8 -> 1.0641626 | F11: =IF(AND(E11<=0),"C",IF(E11<=0.8,"A",IF(E11<=0.95,"B","C"))) -> C | G11: =VLOOKUP(B$4:B$25,I$4:M$25,5,0) -> B | I11: qs черные | J11: ='Юнит 02-08.03'!R4 -> 3 | K11: =J11/J$26 -> 0.031914894 | L11: =K11+L8 -> 0.84042553 | M11: =_xlfn.IFS(L11<80%,"A",L11<=95%,"B",L11>95%,"C") -> B
B12: th желтый Сул | C12: ='Юнит 02-08.03'!AE8 -> 463.8088 | D12: =C12/C$26 -> 0.012844907 | E12: =D12+E11 -> 1.0770076 | F12: =IF(AND(E12<=0),"C",IF(E12<=0.8,"A",IF(E12<=0.95,"B","C"))) -> C | G12: =VLOOKUP(B$4:B$25,I$4:M$25,5,0) -> B | I12: MR Р1874 черн | J12: ='Юнит 02-08.03'!R13 -> 3 | K12: =J12/J$26 -> 0.031914894 | L12: =K12+L11 -> 0.87234043 | M12: =_xlfn.IFS(L12<80%,"A",L12<=95%,"B",L12>95%,"C") -> B
B13: MR Р1874 корич | C13: ='Юнит 02-08.03'!AE14 -> 0 | D13: =C13/C$26 -> 0 | E13: =D13+E12 -> 1.0770076 | F13: =IF(AND(E13<=0),"C",IF(E13<=0.8,"A",IF(E13<=0.95,"B","C"))) -> C | G13: =VLOOKUP(B$4:B$25,I$4:M$25,5,0) -> B | I13: th желтый Сул | J13: ='Юнит 02-08.03'!R8 -> 2 | K13: =J13/J$26 -> 0.021276596 | L13: =K13+L12 -> 0.89361702 | M13: =_xlfn.IFS(L13<80%,"A",L13<=95%,"B",L13>95%,"C") -> B | P13: A | Q13: 0.8
B14: lux1 | C14: ='Юнит 02-08.03'!AE17 -> 0 | D14: =C14/C$26 -> 0 | E14: =D14+E13 -> 1.0770076 | F14: =IF(AND(E14<=0),"C",IF(E14<=0.8,"A",IF(E14<=0.95,"B","C"))) -> C | G14: =VLOOKUP(B$4:B$25,I$4:M$25,5,0) -> B | I14: qs синие | J14: ='Юнит 02-08.03'!R5 -> 1 | K14: =J14/J$26 -> 0.010638298 | L14: =K14+L13 -> 0.90425532 | M14: =_xlfn.IFS(L14<80%,"A",L14<=95%,"B",L14>95%,"C") -> B | P14: B | Q14: 0.15
B15: lux2 | C15: ='Юнит 02-08.03'!AE18 -> 0 | D15: =C15/C$26 -> 0 | E15: =D15+E14 -> 1.0770076 | F15: =IF(AND(E15<=0),"C",IF(E15<=0.8,"A",IF(E15<=0.95,"B","C"))) -> C | G15: =VLOOKUP(B$4:B$25,I$4:M$25,5,0) -> B | I15: MR 1819 черн | J15: ='Юнит 02-08.03'!R11 -> 1 | K15: =J15/J$26 -> 0.010638298 | L15: =K15+L14 -> 0.91489362 | M15: =_xlfn.IFS(L15<80%,"A",L15<=95%,"B",L15>95%,"C") -> B | P15: C | Q15: 0.05
B16: lux3 | C16: ='Юнит 02-08.03'!AE19 -> 0 | D16: =C16/C$26 -> 0 | E16: =D16+E15 -> 1.0770076 | F16: =IF(AND(E16<=0),"C",IF(E16<=0.8,"A",IF(E16<=0.95,"B","C"))) -> C | G16: =VLOOKUP(B$4:B$25,I$4:M$25,5,0) -> B | I16: MR 1819 корич | J16: ='Юнит 02-08.03'!R12 -> 0 | K16: =J16/J$26 -> 0 | L16: =K16+L15 -> 0.91489362 | M16: =_xlfn.IFS(L16<80%,"A",L16<=95%,"B",L16>95%,"C") -> B
B17: lux4 | C17: ='Юнит 02-08.03'!AE20 -> 0 | D17: =C17/C$26 -> 0 | E17: =D17+E16 -> 1.0770076 | F17: =IF(AND(E17<=0),"C",IF(E17<=0.8,"A",IF(E17<=0.95,"B","C"))) -> C | G17: =VLOOKUP(B$4:B$25,I$4:M$25,5,0) -> B | I17: MR Р1874 корич | J17: ='Юнит 02-08.03'!R14 -> 0 | K17: =J17/J$26 -> 0 | L17: =K17+L16 -> 0.91489362 | M17: =_xlfn.IFS(L17<80%,"A",L17<=95%,"B",L17>95%,"C") -> B
B18: lux5 | C18: ='Юнит 02-08.03'!AE21 -> 0 | D18: =C18/C$26 -> 0 | E18: =D18+E17 -> 1.0770076 | F18: =IF(AND(E18<=0),"C",IF(E18<=0.8,"A",IF(E18<=0.95,"B","C"))) -> C | G18: =VLOOKUP(B$4:B$25,I$4:M$25,5,0) -> B | I18: lux1 | J18: ='Юнит 02-08.03'!R17 -> 0 | K18: =J18/J$26 -> 0 | L18: =K18+L17 -> 0.91489362 | M18: =_xlfn.IFS(L18<80%,"A",L18<=95%,"B",L18>95%,"C") -> B
B19: lux6 | C19: ='Юнит 02-08.03'!AE22 -> 0 | D19: =C19/C$26 -> 0 | E19: =D19+E18 -> 1.0770076 | F19: =IF(AND(E19<=0),"C",IF(E19<=0.8,"A",IF(E19<=0.95,"B","C"))) -> C | G19: =VLOOKUP(B$4:B$25,I$4:M$25,5,0) -> B | I19: lux2 | J19: ='Юнит 02-08.03'!R18 -> 0 | K19: =J19/J$26 -> 0 | L19: =K19+L18 -> 0.91489362 | M19: =_xlfn.IFS(L19<80%,"A",L19<=95%,"B",L19>95%,"C") -> B
B20: lux7 | C20: ='Юнит 02-08.03'!AE23 -> 0 | D20: =C20/C$26 -> 0 | E20: =D20+E19 -> 1.0770076 | F20: =IF(AND(E20<=0),"C",IF(E20<=0.8,"A",IF(E20<=0.95,"B","C"))) -> C | G20: =VLOOKUP(B$4:B$25,I$4:M$25,5,0) -> B | I20: lux3 | J20: ='Юнит 02-08.03'!R19 -> 0 | K20: =J20/J$26 -> 0 | L20: =K20+L19 -> 0.91489362 | M20: =_xlfn.IFS(L20<80%,"A",L20<=95%,"B",L20>95%,"C") -> B
B21: lux8 | C21: ='Юнит 02-08.03'!AE24 -> 0 | D21: =C21/C$26 -> 0 | E21: =D21+E20 -> 1.0770076 | F21: =IF(AND(E21<=0),"C",IF(E21<=0.8,"A",IF(E21<=0.95,"B","C"))) -> C | G21: =VLOOKUP(B$4:B$25,I$4:M$25,5,0) -> B | I21: lux4 | J21: ='Юнит 02-08.03'!R20 -> 0 | K21: =J21/J$26 -> 0 | L21: =K21+L20 -> 0.91489362 | M21: =_xlfn.IFS(L21<80%,"A",L21<=95%,"B",L21>95%,"C") -> B
B22: MR 1819 корич | C22: ='Юнит 02-08.03'!AE12 -> -93.54 | D22: =C22/C$26 -> -0.0025905344 | E22: =D22+E21 -> 1.074417 | F22: =IF(AND(E22<=0),"C",IF(E22<=0.8,"A",IF(E22<=0.95,"B","C"))) -> C | G22: =VLOOKUP(B$4:B$25,I$4:M$25,5,0) -> B | I22: lux5 | J22: ='Юнит 02-08.03'!R21 -> 0 | K22: =J22/J$26 -> 0 | L22: =K22+L21 -> 0.91489362 | M22: =_xlfn.IFS(L22<80%,"A",L22<=95%,"B",L22>95%,"C") -> B
B23: qs черные | C23: ='Юнит 02-08.03'!AE4 -> -300.06912 | D23: =C23/C$26 -> -0.0083102349 | E23: =D23+E22 -> 1.0661068 | F23: =IF(AND(E23<=0),"C",IF(E23<=0.8,"A",IF(E23<=0.95,"B","C"))) -> C | G23: =VLOOKUP(B$4:B$25,I$4:M$25,5,0) -> B | I23: lux6 | J23: ='Юнит 02-08.03'!R22 -> 0 | K23: =J23/J$26 -> 0 | L23: =K23+L22 -> 0.91489362 | M23: =_xlfn.IFS(L23<80%,"A",L23<=95%,"B",L23>95%,"C") -> B
B24: qs синие | C24: ='Юнит 02-08.03'!AE5 -> -2117.2945 | D24: =C24/C$26 -> -0.058637205 | E24: =D24+E23 -> 1.0074696 | F24: =IF(AND(E24<=0),"C",IF(E24<=0.8,"A",IF(E24<=0.95,"B","C"))) -> C | G24: =VLOOKUP(B$4:B$25,I$4:M$25,5,0) -> B | I24: lux7 | J24: ='Юнит 02-08.03'!R23 -> 0 | K24: =J24/J$26 -> 0 | L24: =K24+L23 -> 0.91489362 | M24: =_xlfn.IFS(L24<80%,"A",L24<=95%,"B",L24>95%,"C") -> B
B25: MR Р1886 черн глянец | C25: ='Юнит 02-08.03'!AE15 -> -2552.193 | D25: =C25/C$26 -> -0.070681459 | E25: =D25+E24 -> 0.93678812 | F25: =IF(AND(E25<=0),"C",IF(E25<=0.8,"A",IF(E25<=0.95,"B","C"))) -> B | G25: =VLOOKUP(B$4:B$25,I$4:M$25,5,0) -> B | I25: lux8 | J25: ='Юнит 02-08.03'!R24 -> 0 | K25: =J25/J$26 -> 0 | L25: =K25+L24 -> 0.91489362 | M25: =_xlfn.IFS(L25<80%,"A",L25<=95%,"B",L25>95%,"C") -> B
C26: =SUM(C4:C25) -> 36108.38 | D26: =SUM(D4:D25) -> 1 | J26: =SUM(J4:J25) -> 94 | K26: =SUM(K4:K25) -> 1
B28: ТУНИКИ
C29: Прибыль | D29: % прибыль | E29: Доля | F29: ABC прибыль | G29: ABC кол-во | J29: Кол-во | K29: % кол-во | L29: Доля | M29: ABC кол-во
B30: tunika15 кимоно бирюза | C30: ='Юнит 02-08.03'!AE44 -> 5772.0559 | D30: =C30/C$50 -> 17.577106 | E30: =D30 -> 17.577106 | F30: =IF(AND(E30<=0),"C",IF(E30<=0.8,"A",IF(E30<=0.95,"B","C"))) -> C | G30: =VLOOKUP(B$30:B$50,I$30:M$50,5,0) -> A | I30: tunika16 сетка белая | J30: ='Юнит 02-08.03'!R46 -> 8 | K30: =J30/J$50 -> 0.33333333 | L30: =K30 -> 0.33333333 | M30: =_xlfn.IFS(L30<80%,"A",L30<=95%,"B",L30>95%,"C") -> A
B31: tunika08 зеленая | C31: ='Юнит 02-08.03'!AE36 -> 4453.3782 | D31: =C31/C$50 -> 13.561459 | E31: =D31+E30 -> 31.138565 | F31: =IF(AND(E31<=0),"C",IF(E31<=0.8,"A",IF(E31<=0.95,"B","C"))) -> C | G31: =VLOOKUP(B$30:B$50,I$30:M$50,5,0) -> A | I31: tunika08 зеленая | J31: ='Юнит 02-08.03'!R36 -> 3 | K31: =J31/J$50 -> 0.125 | L31: =K31+L30 -> 0.45833333 | M31: =_xlfn.IFS(L31<80%,"A",L31<=95%,"B",L31>95%,"C") -> A
B32: tunika06 белая | C32: ='Юнит 02-08.03'!AE31 -> 3270.9805 | D32: =C32/C$50 -> 9.9608133 | E32: =D32+E31 -> 41.099378 | F32: =IF(AND(E32<=0),"C",IF(E32<=0.8,"A",IF(E32<=0.95,"B","C"))) -> C | G32: =VLOOKUP(B$30:B$50,I$30:M$50,5,0) -> A | I32: tunika15 кимоно бирюза | J32: ='Юнит 02-08.03'!R44 -> 3 | K32: =J32/J$50 -> 0.125 | L32: =K32+L31 -> 0.58333333 | M32: =_xlfn.IFS(L32<80%,"A",L32<=95%,"B",L32>95%,"C") -> A
B33: tunika07 кружево | C33: ='Юнит 02-08.03'!AE33 -> 2015.4944 | D33: =C33/C$50 -> 6.137598 | E33: =D33+E32 -> 47.236976 | F33: =IF(AND(E33<=0),"C",IF(E33<=0.8,"A",IF(E33<=0.95,"B","C"))) -> C | G33: =VLOOKUP(B$30:B$50,I$30:M$50,5,0) -> B | I33: tunika02 оливковая с руч вышивкой | J33: ='Юнит 02-08.03'!R28 -> 2 | K33: =J33/J$50 -> 0.083333333 | L33: =K33+L32 -> 0.66666667 | M33: =_xlfn.IFS(L33<80%,"A",L33<=95%,"B",L33>95%,"C") -> A
B34: tunika16 сетка черная | C34: ='Юнит 02-08.03'!AE47 -> 1703.7897 | D34: =C34/C$50 -> 5.1883927 | E34: =D34+E33 -> 52.425369 | F34: =IF(AND(E34<=0),"C",IF(E34<=0.8,"A",IF(E34<=0.95,"B","C"))) -> C | G34: =VLOOKUP(B$30:B$50,I$30:M$50,5,0) -> C | I34: tunika06 белая | J34: ='Юнит 02-08.03'!R31 -> 2 | K34: =J34/J$50 -> 0.083333333 | L34: =K34+L33 -> 0.75 | M34: =_xlfn.IFS(L34<80%,"A",L34<=95%,"B",L34>95%,"C") -> A
B35: tunika05 белая распашная | C35: ='Юнит 02-08.03'!AE30 -> 979.84378 | D35: =C35/C$50 -> 2.9838273 | E35: =D35+E34 -> 55.409196 | F35: =IF(AND(E35<=0),"C",IF(E35<=0.8,"A",IF(E35<=0.95,"B","C"))) -> C | G35: =VLOOKUP(B$30:B$50,I$30:M$50,5,0) -> C | I35: tunika07 кружево | J35: ='Юнит 02-08.03'!R33 -> 2 | K35: =J35/J$50 -> 0.083333333 | L35: =K35+L34 -> 0.83333333 | M35: =_xlfn.IFS(L35<80%,"A",L35<=95%,"B",L35>95%,"C") -> B
B36: tunika03 черная распашная | C36: ='Юнит 02-08.03'!AE29 -> 0 | D36: =C36/C$50 -> 0 | E36: =D36+E35 -> 55.409196 | F36: =IF(AND(E36<=0),"C",IF(E36<=0.8,"A",IF(E36<=0.95,"B","C"))) -> C | G36: =VLOOKUP(B$30:B$50,I$30:M$50,5,0) -> C | I36: tunika15 кимоно песочная | J36: ='Юнит 02-08.03'!R45 -> 2 | K36: =J36/J$50 -> 0.083333333 | L36: =K36+L35 -> 0.91666667 | M36: =_xlfn.IFS(L36<80%,"A",L36<=95%,"B",L36>95%,"C") -> B
B37: tunika06 черная | C37: ='Юнит 02-08.03'!AE32 -> 0 | D37: =C37/C$50 -> 0 | E37: =D37+E36 -> 55.409196 | F37: =IF(AND(E37<=0),"C",IF(E37<=0.8,"A",IF(E37<=0.95,"B","C"))) -> C | G37: =VLOOKUP(B$30:B$50,I$30:M$50,5,0) -> C | I37: tunika05 белая распашная | J37: ='Юнит 02-08.03'!R30 -> 1 | K37: =J37/J$50 -> 0.041666667 | L37: =K37+L36 -> 0.95833333 | M37: =_xlfn.IFS(L37<80%,"A",L37<=95%,"B",L37>95%,"C") -> C
B38: tunika08 черная | C38: ='Юнит 02-08.03'!AE35 -> 0 | D38: =C38/C$50 -> 0 | E38: =D38+E37 -> 55.409196 | F38: =IF(AND(E38<=0),"C",IF(E38<=0.8,"A",IF(E38<=0.95,"B","C"))) -> C | G38: =VLOOKUP(B$30:B$50,I$30:M$50,5,0) -> C | I38: tunika16 сетка черная | J38: ='Юнит 02-08.03'!R47 -> 1 | K38: =J38/J$50 -> 0.041666667 | L38: =K38+L37 -> 1 | M38: =_xlfn.IFS(L38<80%,"A",L38<=95%,"B",L38>95%,"C") -> C
B39: tunika13 халат черная | C39: ='Юнит 02-08.03'!AE41 -> 0 | D39: =C39/C$50 -> 0 | E39: =D39+E38 -> 55.409196 | F39: =IF(AND(E39<=0),"C",IF(E39<=0.8,"A",IF(E39<=0.95,"B","C"))) -> C | G39: =VLOOKUP(B$30:B$50,I$30:M$50,5,0) -> C | I39: tunika03 черная распашная | J39: ='Юнит 02-08.03'!R29 -> 0 | K39: =J39/J$50 -> 0 | L39: =K39+L38 -> 1 | M39: =_xlfn.IFS(L39<80%,"A",L39<=95%,"B",L39>95%,"C") -> C
B40: tunika09 кимоно | C40: ='Юнит 02-08.03'!AE37 -> -113.88 | D40: =C40/C$50 -> -0.34678819 | E40: =D40+E39 -> 55.062408 | F40: =IF(AND(E40<=0),"C",IF(E40<=0.8,"A",IF(E40<=0.95,"B","C"))) -> C | G40: =VLOOKUP(B$30:B$50,I$30:M$50,5,0) -> C | I40: tunika06 черная | J40: ='Юнит 02-08.03'!R32 -> 0 | K40: =J40/J$50 -> 0 | L40: =K40+L39 -> 1 | M40: =_xlfn.IFS(L40<80%,"A",L40<=95%,"B",L40>95%,"C") -> C
B41: tunika10 кимоно ч/б | C41: ='Юнит 02-08.03'!AE38 -> -113.88 | D41: =C41/C$50 -> -0.34678819 | E41: =D41+E40 -> 54.71562 | F41: =IF(AND(E41<=0),"C",IF(E41<=0.8,"A",IF(E41<=0.95,"B","C"))) -> C | G41: =VLOOKUP(B$30:B$50,I$30:M$50,5,0) -> C | I41: tunika08 белая | J41: ='Юнит 02-08.03'!R34 -> 0 | K41: =J41/J$50 -> 0 | L41: =K41+L40 -> 1 | M41: =_xlfn.IFS(L41<80%,"A",L41<=95%,"B",L41>95%,"C") -> C
B42: tunika08 белая | C42: ='Юнит 02-08.03'!AE34 -> -196.34 | D42: =C42/C$50 -> -0.59789597 | E42: =D42+E41 -> 54.117724 | F42: =IF(AND(E42<=0),"C",IF(E42<=0.8,"A",IF(E42<=0.95,"B","C"))) -> C | G42: =VLOOKUP(B$30:B$50,I$30:M$50,5,0) -> C | I42: tunika08 черная | J42: ='Юнит 02-08.03'!R35 -> 0 | K42: =J42/J$50 -> 0 | L42: =K42+L41 -> 1 | M42: =_xlfn.IFS(L42<80%,"A",L42<=95%,"B",L42>95%,"C") -> C
B43: tunika14 халат с разрезами черный | C43: ='Юнит 02-08.03'!AE43 -> -214.1 | D43: =C43/C$50 -> -0.65197885 | E43: =D43+E42 -> 53.465745 | F43: =IF(AND(E43<=0),"C",IF(E43<=0.8,"A",IF(E43<=0.95,"B","C"))) -> C | G43: =VLOOKUP(B$30:B$50,I$30:M$50,5,0) -> C | I43: tunika09 кимоно | J43: ='Юнит 02-08.03'!R37 -> 0 | K43: =J43/J$50 -> 0 | L43: =K43+L42 -> 1 | M43: =_xlfn.IFS(L43<80%,"A",L43<=95%,"B",L43>95%,"C") -> C
B44: tunika12 халат белая | C44: ='Юнит 02-08.03'!AE40 -> -227.76 | D44: =C44/C$50 -> -0.69357638 | E44: =D44+E43 -> 52.772169 | F44: =IF(AND(E44<=0),"C",IF(E44<=0.8,"A",IF(E44<=0.95,"B","C"))) -> C | G44: =VLOOKUP(B$30:B$50,I$30:M$50,5,0) -> C | I44: tunika10 кимоно ч/б | J44: ='Юнит 02-08.03'!R38 -> 0 | K44: =J44/J$50 -> 0 | L44: =K44+L43 -> 1 | M44: =_xlfn.IFS(L44<80%,"A",L44<=95%,"B",L44>95%,"C") -> C
B45: tunika11 халат зеленая | C45: ='Юнит 02-08.03'!AE39 -> -246.15 | D45: =C45/C$50 -> -0.74957774 | E45: =D45+E44 -> 52.022591 | F45: =IF(AND(E45<=0),"C",IF(E45<=0.8,"A",IF(E45<=0.95,"B","C"))) -> C | G45: =VLOOKUP(B$30:B$50,I$30:M$50,5,0) -> C | I45: tunika11 халат зеленая | J45: ='Юнит 02-08.03'!R39 -> 0 | K45: =J45/J$50 -> 0 | L45: =K45+L44 -> 1 | M45: =_xlfn.IFS(L45<80%,"A",L45<=95%,"B",L45>95%,"C") -> C
B46: tunika02 оливковая с руч вышивкой | C46: ='Юнит 02-08.03'!AE28 -> -452.73198 | D46: =C46/C$50 -> -1.3786627 | E46: =D46+E45 -> 50.643928 | F46: =IF(AND(E46<=0),"C",IF(E46<=0.8,"A",IF(E46<=0.95,"B","C"))) -> C | G46: =VLOOKUP(B$30:B$50,I$30:M$50,5,0) -> A | I46: tunika12 халат белая | J46: ='Юнит 02-08.03'!R40 -> 0 | K46: =J46/J$50 -> 0 | L46: =K46+L45 -> 1 | M46: =_xlfn.IFS(L46<80%,"A",L46<=95%,"B",L46>95%,"C") -> C
B47: tunika14 халат с разрезами белая | C47: ='Юнит 02-08.03'!AE42 -> -1438.44 | D47: =C47/C$50 -> -4.3803478 | E47: =D47+E46 -> 46.263581 | F47: =IF(AND(E47<=0),"C",IF(E47<=0.8,"A",IF(E47<=0.95,"B","C"))) -> C | G47: =VLOOKUP(B$30:B$50,I$30:M$50,5,0) -> C | I47: tunika13 халат черная | J47: ='Юнит 02-08.03'!R41 -> 0 | K47: =J47/J$50 -> 0 | L47: =K47+L46 -> 1 | M47: =_xlfn.IFS(L47<80%,"A",L47<=95%,"B",L47>95%,"C") -> C
B48: tunika16 сетка белая | C48: ='Юнит 02-08.03'!AE46 -> -3741.6329 | D48: =C48/C$50 -> -11.394047 | E48: =D48+E47 -> 34.869533 | F48: =IF(AND(E48<=0),"C",IF(E48<=0.8,"A",IF(E48<=0.95,"B","C"))) -> C | G48: =VLOOKUP(B$30:B$50,I$30:M$50,5,0) -> A | I48: tunika14 халат с разрезами белая | J48: ='Юнит 02-08.03'!R42 -> 0 | K48: =J48/J$50 -> 0 | L48: =K48+L47 -> 1 | M48: =_xlfn.IFS(L48<80%,"A",L48<=95%,"B",L48>95%,"C") -> C
B49: tunika15 кимоно песочная | C49: ='Юнит 02-08.03'!AE45 -> -11122.243 | D49: =C49/C$50 -> -33.869533 | E49: =D49+E48 -> 1 | F49: =IF(AND(E49<=0),"C",IF(E49<=0.8,"A",IF(E49<=0.95,"B","C"))) -> C | G49: =VLOOKUP(B$30:B$50,I$30:M$50,5,0) -> B | I49: tunika14 халат с разрезами черный | J49: ='Юнит 02-08.03'!R43 -> 0 | K49: =J49/J$50 -> 0 | L49: =K49+L48 -> 1 | M49: =_xlfn.IFS(L49<80%,"A",L49<=95%,"B",L49>95%,"C") -> C
C50: =SUM(C30:C49) -> 328.38488 | D50: =SUM(D30:D49) -> 1 | J50: =SUM(J30:J49) -> 24 | K50: =SUM(K30:K49) -> 1

Sheet АВС ФЕВРАЛЬ
B2: ОЧКИ
C3: Прибыль | D3: % прибыль | E3: Доля | F3: ABC прибыль | G3: ABC кол-во | J3: Кол-во | K3: % кол-во | L3: Доля | M3: ABC кол-во
B4: черные с железкой классика | C4: =ФЕВРАЛЬ!AE3 -> 77109.923 | D4: =C4/C$26 -> 0.74402289 | E4: =D4 -> 0.74402289 | F4: =IF(AND(E4<=0),"C",IF(E4<=0.8,"A",IF(E4<=0.95,"B","C"))) -> A | G4: =VLOOKUP(B$4:B$25,I$4:M$25,5,0) -> A | I4: черные с железкой классика | J4: =ФЕВРАЛЬ!R3 -> 166 | K4: =J4/J$26 -> 0.55333333 | L4: =K4 -> 0.55333333 | M4: =_xlfn.IFS(L4<80%,"A",L4<=95%,"B",L4>95%,"C") -> A
B5: qs желтые | C5: =ФЕВРАЛЬ!AE6 -> 6375.9128 | D5: =C5/C$26 -> 0.061520293 | E5: =D5+E4 -> 0.80554318 | F5: =IF(AND(E5<=0),"C",IF(E5<=0.8,"A",IF(E5<=0.95,"B","C"))) -> B | G5: =VLOOKUP(B$4:B$25,I$4:M$25,5,0) -> A | I5: qs коричневые | J5: =ФЕВРАЛЬ!R7 -> 27 | K5: =J5/J$26 -> 0.09 | L5: =K5+L4 -> 0.64333333 | M5: =_xlfn.IFS(L5<80%,"A",L5<=95%,"B",L5>95%,"C") -> A
B6: MR8854 C2 | C6: =ФЕВРАЛЬ!AE10 -> 5819.3539 | D6: =C6/C$26 -> 0.056150134 | E6: =D6+E5 -> 0.86169332 | F6: =IF(AND(E6<=0),"C",IF(E6<=0.8,"A",IF(E6<=0.95,"B","C"))) -> B | G6: =VLOOKUP(B$4:B$25,I$4:M$25,5,0) -> B | I6: qs желтые | J6: =ФЕВРАЛЬ!R6 -> 19 | K6: =J6/J$26 -> 0.063333333 | L6: =K6+L5 -> 0.70666667 | M6: =_xlfn.IFS(L6<80%,"A",L6<=95%,"B",L6>95%,"C") -> A
B7: MR Р1874 черн | C7: =ФЕВРАЛЬ!AE13 -> 5492.0895 | D7: =C7/C$26 -> 0.052992406 | E7: =D7+E6 -> 0.91468572 | F7: =IF(AND(E7<=0),"C",IF(E7<=0.8,"A",IF(E7<=0.95,"B","C"))) -> B | G7: =VLOOKUP(B$4:B$25,I$4:M$25,5,0) -> A | I7: MR Р1874 черн | J7: =ФЕВРАЛЬ!R13 -> 19 | K7: =J7/J$26 -> 0.063333333 | L7: =K7+L6 -> 0.77 | M7: =_xlfn.IFS(L7<80%,"A",L7<=95%,"B",L7>95%,"C") -> A
B8: qs коричневые | C8: =ФЕВРАЛЬ!AE7 -> 3286.1568 | D8: =C8/C$26 -> 0.031707669 | E8: =D8+E7 -> 0.94639339 | F8: =IF(AND(E8<=0),"C",IF(E8<=0.8,"A",IF(E8<=0.95,"B","C"))) -> B | G8: =VLOOKUP(B$4:B$25,I$4:M$25,5,0) -> A | I8: MR8854 C2 | J8: =ФЕВРАЛЬ!R10 -> 18 | K8: =J8/J$26 -> 0.06 | L8: =K8+L7 -> 0.83 | M8: =_xlfn.IFS(L8<80%,"A",L8<=95%,"B",L8>95%,"C") -> B
B9: flip желтые Сул | C9: =ФЕВРАЛЬ!AE9 -> 2483.91 | D9: =C9/C$26 -> 0.023966901 | E9: =D9+E8 -> 0.97036029 | F9: =IF(AND(E9<=0),"C",IF(E9<=0.8,"A",IF(E9<=0.95,"B","C"))) -> C | G9: =VLOOKUP(B$4:B$25,I$4:M$25,5,0) -> B | I9: MR Р1886 черн глянец | J9: =ФЕВРАЛЬ!R15 -> 16 | K9: =J9/J$26 -> 0.053333333 | L9: =K9+L8 -> 0.88333333 | M9: =_xlfn.IFS(L9<80%,"A",L9<=95%,"B",L9>95%,"C") -> B
B10: MR 1819 корич | C10: =ФЕВРАЛЬ!AE12 -> 1757.6519 | D10: =C10/C$26 -> 0.016959338 | E10: =D10+E9 -> 0.98731963 | F10: =IF(AND(E10<=0),"C",IF(E10<=0.8,"A",IF(E10<=0.95,"B","C"))) -> C | G10: =VLOOKUP(B$4:B$25,I$4:M$25,5,0) -> B | I10: flip желтые Сул | J10: =ФЕВРАЛЬ!R9 -> 12 | K10: =J10/J$26 -> 0.04 | L10: =K10+L9 -> 0.92333333 | M10: =_xlfn.IFS(L10<80%,"A",L10<=95%,"B",L10>95%,"C") -> B
B11: th желтый Сул | C11: =ФЕВРАЛЬ!AE8 -> 1379.9613 | D11: =C11/C$26 -> 0.013315055 | E11: =D11+E8 -> 0.95970845 | F11: =IF(AND(E11<=0),"C",IF(E11<=0.8,"A",IF(E11<=0.95,"B","C"))) -> C | G11: =VLOOKUP(B$4:B$25,I$4:M$25,5,0) -> B | I11: th желтый Сул | J11: =ФЕВРАЛЬ!R8 -> 6 | K11: =J11/J$26 -> 0.02 | L11: =K11+L8 -> 0.85 | M11: =_xlfn.IFS(L11<80%,"A",L11<=95%,"B",L11>95%,"C") -> B
B12: qs черные | C12: =ФЕВРАЛЬ!AE4 -> 440.38589 | D12: =C12/C$26 -> 0.0042492221 | E12: =D12+E11 -> 0.96395767 | F12: =IF(AND(E12<=0),"C",IF(E12<=0.8,"A",IF(E12<=0.95,"B","C"))) -> C | G12: =VLOOKUP(B$4:B$25,I$4:M$25,5,0) -> B | I12: qs черные | J12: =ФЕВРАЛЬ!R4 -> 5 | K12: =J12/J$26 -> 0.016666667 | L12: =K12+L11 -> 0.86666667 | M12: =_xlfn.IFS(L12<80%,"A",L12<=95%,"B",L12>95%,"C") -> B
B13: MR Р1886 корич | C13: =ФЕВРАЛЬ!AE16 -> 243.27566 | D13: =C13/C$26 -> 0.0023473329 | E13: =D13+E12 -> 0.966305 | F13: =IF(AND(E13<=0),"C",IF(E13<=0.8,"A",IF(E13<=0.95,"B","C"))) -> C | G13: =VLOOKUP(B$4:B$25,I$4:M$25,5,0) -> B | I13: MR 1819 корич | J13: =ФЕВРАЛЬ!R12 -> 4 | K13: =J13/J$26 -> 0.013333333 | L13: =K13+L12 -> 0.88 | M13: =_xlfn.IFS(L13<80%,"A",L13<=95%,"B",L13>95%,"C") -> B | P13: A | Q13: 0.8
B14: MR Р1886 черн глянец | C14: =ФЕВРАЛЬ!AE15 -> 18.334962 | D14: =C14/C$26 -> 0.00017691149 | E14: =D14+E13 -> 0.96648191 | F14: =IF(AND(E14<=0),"C",IF(E14<=0.8,"A",IF(E14<=0.95,"B","C"))) -> C | G14: =VLOOKUP(B$4:B$25,I$4:M$25,5,0) -> B | I14: qs синие | J14: =ФЕВРАЛЬ!R5 -> 3 | K14: =J14/J$26 -> 0.01 | L14: =K14+L13 -> 0.89 | M14: =_xlfn.IFS(L14<80%,"A",L14<=95%,"B",L14>95%,"C") -> B | P14: B | Q14: 0.15
B15: MR 1819 черн | C15: =ФЕВРАЛЬ!AE11 -> 9.5568904 | D15: =C15/C$26 -> 9.2213103e-05 | E15: =D15+E14 -> 0.96657412 | F15: =IF(AND(E15<=0),"C",IF(E15<=0.8,"A",IF(E15<=0.95,"B","C"))) -> C | G15: =VLOOKUP(B$4:B$25,I$4:M$25,5,0) -> B | I15: MR Р1874 корич | J15: =ФЕВРАЛЬ!R14 -> 2 | K15: =J15/J$26 -> 0.0066666667 | L15: =K15+L14 -> 0.89666667 | M15: =_xlfn.IFS(L15<80%,"A",L15<=95%,"B",L15>95%,"C") -> B | P15: C | Q15: 0.05
B16: lux1 | C16: =ФЕВРАЛЬ!AE17 -> 0 | D16: =C16/C$26 -> 0 | E16: =D16+E15 -> 0.96657412 | F16: =IF(AND(E16<=0),"C",IF(E16<=0.8,"A",IF(E16<=0.95,"B","C"))) -> C | G16: =VLOOKUP(B$4:B$25,I$4:M$25,5,0) -> B | I16: MR Р1886 корич | J16: =ФЕВРАЛЬ!R16 -> 2 | K16: =J16/J$26 -> 0.0066666667 | L16: =K16+L15 -> 0.90333333 | M16: =_xlfn.IFS(L16<80%,"A",L16<=95%,"B",L16>95%,"C") -> B
B17: lux2 | C17: =ФЕВРАЛЬ!AE18 -> 0 | D17: =C17/C$26 -> 0 | E17: =D17+E16 -> 0.96657412 | F17: =IF(AND(E17<=0),"C",IF(E17<=0.8,"A",IF(E17<=0.95,"B","C"))) -> C | G17: =VLOOKUP(B$4:B$25,I$4:M$25,5,0) -> B | I17: MR 1819 черн | J17: =ФЕВРАЛЬ!R11 -> 1 | K17: =J17/J$26 -> 0.0033333333 | L17: =K17+L16 -> 0.90666667 | M17: =_xlfn.IFS(L17<80%,"A",L17<=95%,"B",L17>95%,"C") -> B
B18: lux5 | C18: =ФЕВРАЛЬ!AE21 -> 0 | D18: =C18/C$26 -> 0 | E18: =D18+E17 -> 0.96657412 | F18: =IF(AND(E18<=0),"C",IF(E18<=0.8,"A",IF(E18<=0.95,"B","C"))) -> C | G18: =VLOOKUP(B$4:B$25,I$4:M$25,5,0) -> B | I18: lux1 | J18: =ФЕВРАЛЬ!R17 -> 0 | K18: =J18/J$26 -> 0 | L18: =K18+L17 -> 0.90666667 | M18: =_xlfn.IFS(L18<80%,"A",L18<=95%,"B",L18>95%,"C") -> B
B19: lux6 | C19: =ФЕВРАЛЬ!AE22 -> 0 | D19: =C19/C$26 -> 0 | E19: =D19+E18 -> 0.96657412 | F19: =IF(AND(E19<=0),"C",IF(E19<=0.8,"A",IF(E19<=0.95,"B","C"))) -> C | G19: =VLOOKUP(B$4:B$25,I$4:M$25,5,0) -> B | I19: lux2 | J19: =ФЕВРАЛЬ!R18 -> 0 | K19: =J19/J$26 -> 0 | L19: =K19+L18 -> 0.90666667 | M19: =_xlfn.IFS(L19<80%,"A",L19<=95%,"B",L19>95%,"C") -> B
B20: lux7 | C20: =ФЕВРАЛЬ!AE23 -> 0 | D20: =C20/C$26 -> 0 | E20: =D20+E19 -> 0.96657412 | F20: =IF(AND(E20<=0),"C",IF(E20<=0.8,"A",IF(E20<=0.95,"B","C"))) -> C | G20: =VLOOKUP(B$4:B$25,I$4:M$25,5,0) -> B | I20: lux3 | J20: =ФЕВРАЛЬ!R19 -> 0 | K20: =J20/J$26 -> 0 | L20: =K20+L19 -> 0.90666667 | M20: =_xlfn.IFS(L20<80%,"A",L20<=95%,"B",L20>95%,"C") -> B
B21: lux8 | C21: =ФЕВРАЛЬ!AE24 -> 0 | D21: =C21/C$26 -> 0 | E21: =D21+E20 -> 0.96657412 | F21: =IF(AND(E21<=0),"C",IF(E21<=0.8,"A",IF(E21<=0.95,"B","C"))) -> C | G21: =VLOOKUP(B$4:B$25,I$4:M$25,5,0) -> B | I21: lux4 | J21: =ФЕВРАЛЬ!R20 -> 0 | K21: =J21/J$26 -> 0 | L21: =K21+L20 -> 0.90666667 | M21: =_xlfn.IFS(L21<80%,"A",L21<=95%,"B",L21>95%,"C") -> B
B22: qs синие | C22: =ФЕВРАЛЬ!AE5 -> -35.446901 | D22: =C22/C$26 -> -0.00034202221 | E22: =D22+E21 -> 0.9662321 | F22: =IF(AND(E22<=0),"C",IF(E22<=0.8,"A",IF(E22<=0.95,"B","C"))) -> C | G22: =VLOOKUP(B$4:B$25,I$4:M$25,5,0) -> B | I22: lux5 | J22: =ФЕВРАЛЬ!R21 -> 0 | K22: =J22/J$26 -> 0 | L22: =K22+L21 -> 0.90666667 | M22: =_xlfn.IFS(L22<80%,"A",L22<=95%,"B",L22>95%,"C") -> B
B23: lux3 | C23: =ФЕВРАЛЬ!AE19 -> -227.76 | D23: =C23/C$26 -> -0.0021976245 | E23: =D23+E22 -> 0.96403448 | F23: =IF(AND(E23<=0),"C",IF(E23<=0.8,"A",IF(E23<=0.95,"B","C"))) -> C | G23: =VLOOKUP(B$4:B$25,I$4:M$25,5,0) -> B | I23: lux6 | J23: =ФЕВРАЛЬ!R22 -> 0 | K23: =J23/J$26 -> 0 | L23: =K23+L22 -> 0.90666667 | M23: =_xlfn.IFS(L23<80%,"A",L23<=95%,"B",L23>95%,"C") -> B
B24: MR Р1874 корич | C24: =ФЕВРАЛЬ!AE14 -> -235.94473 | D24: =C24/C$26 -> -0.0022765978 | E24: =D24+E23 -> 0.96175788 | F24: =IF(AND(E24<=0),"C",IF(E24<=0.8,"A",IF(E24<=0.95,"B","C"))) -> C | G24: =VLOOKUP(B$4:B$25,I$4:M$25,5,0) -> B | I24: lux7 | J24: =ФЕВРАЛЬ!R23 -> 0 | K24: =J24/J$26 -> 0 | L24: =K24+L23 -> 0.90666667 | M24: =_xlfn.IFS(L24<80%,"A",L24<=95%,"B",L24>95%,"C") -> B
B25: lux4 | C25: =ФЕВРАЛЬ!AE20 -> -278.18 | D25: =C25/C$26 -> -0.00268412 | E25: =D25+E24 -> 0.95907376 | F25: =IF(AND(E25<=0),"C",IF(E25<=0.8,"A",IF(E25<=0.95,"B","C"))) -> C | G25: =VLOOKUP(B$4:B$25,I$4:M$25,5,0) -> B | I25: lux8 | J25: =ФЕВРАЛЬ!R24 -> 0 | K25: =J25/J$26 -> 0 | L25: =K25+L24 -> 0.90666667 | M25: =_xlfn.IFS(L25<80%,"A",L25<=95%,"B",L25>95%,"C") -> B
C26: =SUM(C4:C25) -> 103639.18 | D26: =SUM(D4:D25) -> 1 | J26: =SUM(J4:J25) -> 300 | K26: =SUM(K4:K25) -> 1
B28: ТУНИКИ
C29: Прибыль | D29: % прибыль | E29: Доля | F29: ABC прибыль | G29: ABC кол-во | J29: Кол-во | K29: % кол-во | L29: Доля | M29: ABC кол-во
B30: tunika15 кимоно бирюза | C30: =ФЕВРАЛЬ!AE44 -> 16175.416 | D30: =C30/C$50 -> 0.24404337 | E30: =D30 -> 0.24404337 | F30: =IF(AND(E30<=0),"C",IF(E30<=0.8,"A",IF(E30<=0.95,"B","C"))) -> A | G30: =VLOOKUP(B$30:B$50,I$30:M$50,5,0) -> A | I30: tunika16 сетка белая | J30: =ФЕВРАЛЬ!R46 -> 22 | K30: =J30/J$50 -> 0.24444444 | L30: =K30 -> 0.24444444 | M30: =_xlfn.IFS(L30<80%,"A",L30<=95%,"B",L30>95%,"C") -> A
B31: tunika09 кимоно | C31: =ФЕВРАЛЬ!AE37 -> 14757.09 | D31: =C31/C$50 -> 0.22264465 | E31: =D31+E30 -> 0.46668802 | F31: =IF(AND(E31<=0),"C",IF(E31<=0.8,"A",IF(E31<=0.95,"B","C"))) -> A | G31: =VLOOKUP(B$30:B$50,I$30:M$50,5,0) -> A | I31: tunika15 кимоно песочная | J31: =ФЕВРАЛЬ!R45 -> 20 | K31: =J31/J$50 -> 0.22222222 | L31: =K31+L30 -> 0.46666667 | M31: =_xlfn.IFS(L31<80%,"A",L31<=95%,"B",L31>95%,"C") -> A
B32: tunika15 кимоно песочная | C32: =ФЕВРАЛЬ!AE45 -> 8328.6119 | D32: =C32/C$50 -> 0.12565627 | E32: =D32+E31 -> 0.59234429 | F32: =IF(AND(E32<=0),"C",IF(E32<=0.8,"A",IF(E32<=0.95,"B","C"))) -> A | G32: =VLOOKUP(B$30:B$50,I$30:M$50,5,0) -> A | I32: tunika15 кимоно бирюза | J32: =ФЕВРАЛЬ!R44 -> 18 | K32: =J32/J$50 -> 0.2 | L32: =K32+L31 -> 0.66666667 | M32: =_xlfn.IFS(L32<80%,"A",L32<=95%,"B",L32>95%,"C") -> A
B33: tunika16 сетка белая | C33: =ФЕВРАЛЬ!AE46 -> 7626.6201 | D33: =C33/C$50 -> 0.11506511 | E33: =D33+E32 -> 0.7074094 | F33: =IF(AND(E33<=0),"C",IF(E33<=0.8,"A",IF(E33<=0.95,"B","C"))) -> A | G33: =VLOOKUP(B$30:B$50,I$30:M$50,5,0) -> A | I33: tunika09 кимоно | J33: =ФЕВРАЛЬ!R37 -> 8 | K33: =J33/J$50 -> 0.088888889 | L33: =K33+L32 -> 0.75555556 | M33: =_xlfn.IFS(L33<80%,"A",L33<=95%,"B",L33>95%,"C") -> A
B34: tunika14 халат с разрезами черный | C34: =ФЕВРАЛЬ!AE43 -> 3895.327 | D34: =C34/C$50 -> 0.058769969 | E34: =D34+E33 -> 0.76617937 | F34: =IF(AND(E34<=0),"C",IF(E34<=0.8,"A",IF(E34<=0.95,"B","C"))) -> A | G34: =VLOOKUP(B$30:B$50,I$30:M$50,5,0) -> B | I34: tunika14 халат с разрезами белая | J34: =ФЕВРАЛЬ!R42 -> 4 | K34: =J34/J$50 -> 0.044444444 | L34: =K34+L33 -> 0.8 | M34: =_xlfn.IFS(L34<80%,"A",L34<=95%,"B",L34>95%,"C") -> B
B35: tunika08 белая | C35: =ФЕВРАЛЬ!AE34 -> 3165.6391 | D35: =C35/C$50 -> 0.047760949 | E35: =D35+E34 -> 0.81394031 | F35: =IF(AND(E35<=0),"C",IF(E35<=0.8,"A",IF(E35<=0.95,"B","C"))) -> B | G35: =VLOOKUP(B$30:B$50,I$30:M$50,5,0) -> B | I35: tunika07 кружево | J35: =ФЕВРАЛЬ!R33 -> 3 | K35: =J35/J$50 -> 0.033333333 | L35: =K35+L34 -> 0.83333333 | M35: =_xlfn.IFS(L35<80%,"A",L35<=95%,"B",L35>95%,"C") -> B
B36: tunika12 халат белая | C36: =ФЕВРАЛЬ!AE40 -> 3105.376 | D36: =C36/C$50 -> 0.046851741 | E36: =D36+E35 -> 0.86079206 | F36: =IF(AND(E36<=0),"C",IF(E36<=0.8,"A",IF(E36<=0.95,"B","C"))) -> B | G36: =VLOOKUP(B$30:B$50,I$30:M$50,5,0) -> B | I36: tunika14 халат с разрезами черный | J36: =ФЕВРАЛЬ!R43 -> 3 | K36: =J36/J$50 -> 0.033333333 | L36: =K36+L35 -> 0.86666667 | M36: =_xlfn.IFS(L36<80%,"A",L36<=95%,"B",L36>95%,"C") -> B
B37: tunika07 кружево | C37: =ФЕВРАЛЬ!AE33 -> 2753.2231 | D37: =C37/C$50 -> 0.041538704 | E37: =D37+E36 -> 0.90233076 | F37: =IF(AND(E37<=0),"C",IF(E37<=0.8,"A",IF(E37<=0.95,"B","C"))) -> B | G37: =VLOOKUP(B$30:B$50,I$30:M$50,5,0) -> B | I37: tunika05 белая распашная | J37: =ФЕВРАЛЬ!R30 -> 2 | K37: =J37/J$50 -> 0.022222222 | L37: =K37+L36 -> 0.88888889 | M37: =_xlfn.IFS(L37<80%,"A",L37<=95%,"B",L37>95%,"C") -> B
B38: tunika08 черная | C38: =ФЕВРАЛЬ!AE35 -> 2632.647 | D38: =C38/C$50 -> 0.039719537 | E38: =D38+E37 -> 0.9420503 | F38: =IF(AND(E38<=0),"C",IF(E38<=0.8,"A",IF(E38<=0.95,"B","C"))) -> B | G38: =VLOOKUP(B$30:B$50,I$30:M$50,5,0) -> C | I38: tunika08 белая | J38: =ФЕВРАЛЬ!R34 -> 2 | K38: =J38/J$50 -> 0.022222222 | L38: =K38+L37 -> 0.91111111 | M38: =_xlfn.IFS(L38<80%,"A",L38<=95%,"B",L38>95%,"C") -> B
B39: tunika05 белая распашная | C39: =ФЕВРАЛЬ!AE30 -> 2144.7046 | D39: =C39/C$50 -> 0.032357803 | E39: =D39+E38 -> 0.9744081 | F39: =IF(AND(E39<=0),"C",IF(E39<=0.8,"A",IF(E39<=0.95,"B","C"))) -> C | G39: =VLOOKUP(B$30:B$50,I$30:M$50,5,0) -> B | I39: tunika12 халат белая | J39: =ФЕВРАЛЬ!R40 -> 2 | K39: =J39/J$50 -> 0.022222222 | L39: =K39+L38 -> 0.93333333 | M39: =_xlfn.IFS(L39<80%,"A",L39<=95%,"B",L39>95%,"C") -> B
B40: tunika06 белая | C40: =ФЕВРАЛЬ!AE31 -> 1514.2488 | D40: =C40/C$50 -> 0.022845927 | E40: =D40+E39 -> 0.99725403 | F40: =IF(AND(E40<=0),"C",IF(E40<=0.8,"A",IF(E40<=0.95,"B","C"))) -> C | G40: =VLOOKUP(B$30:B$50,I$30:M$50,5,0) -> C | I40: tunika16 сетка черная | J40: =ФЕВРАЛЬ!R47 -> 2 | K40: =J40/J$50 -> 0.022222222 | L40: =K40+L39 -> 0.95555556 | M40: =_xlfn.IFS(L40<80%,"A",L40<=95%,"B",L40>95%,"C") -> C
B41: tunika16 сетка черная | C41: =ФЕВРАЛЬ!AE47 -> 1147.5467 | D41: =C41/C$50 -> 0.017313382 | E41: =D41+E40 -> 1.0145674 | F41: =IF(AND(E41<=0),"C",IF(E41<=0.8,"A",IF(E41<=0.95,"B","C"))) -> C | G41: =VLOOKUP(B$30:B$50,I$30:M$50,5,0) -> C | I41: tunika02 оливковая с руч вышивкой | J41: =ФЕВРАЛЬ!R28 -> 1 | K41: =J41/J$50 -> 0.011111111 | L41: =K41+L40 -> 0.96666667 | M41: =_xlfn.IFS(L41<80%,"A",L41<=95%,"B",L41>95%,"C") -> C
B42: tunika11 халат зеленая | C42: =ФЕВРАЛЬ!AE39 -> 917.42215 | D42: =C42/C$50 -> 0.013841424 | E42: =D42+E41 -> 1.0284088 | F42: =IF(AND(E42<=0),"C",IF(E42<=0.8,"A",IF(E42<=0.95,"B","C"))) -> C | G42: =VLOOKUP(B$30:B$50,I$30:M$50,5,0) -> C | I42: tunika06 белая | J42: =ФЕВРАЛЬ!R31 -> 1 | K42: =J42/J$50 -> 0.011111111 | L42: =K42+L41 -> 0.97777778 | M42: =_xlfn.IFS(L42<80%,"A",L42<=95%,"B",L42>95%,"C") -> C
B43: tunika02 оливковая с руч вышивкой | C43: =ФЕВРАЛЬ!AE28 -> 881.81159 | D43: =C43/C$50 -> 0.013304156 | E43: =D43+E42 -> 1.041713 | F43: =IF(AND(E43<=0),"C",IF(E43<=0.8,"A",IF(E43<=0.95,"B","C"))) -> C | G43: =VLOOKUP(B$30:B$50,I$30:M$50,5,0) -> C | I43: tunika08 черная | J43: =ФЕВРАЛЬ!R35 -> 1 | K43: =J43/J$50 -> 0.011111111 | L43: =K43+L42 -> 0.98888889 | M43: =_xlfn.IFS(L43<80%,"A",L43<=95%,"B",L43>95%,"C") -> C
B44: tunika06 черная | C44: =ФЕВРАЛЬ!AE32 -> 0 | D44: =C44/C$50 -> 0 | E44: =D44+E43 -> 1.041713 | F44: =IF(AND(E44<=0),"C",IF(E44<=0.8,"A",IF(E44<=0.95,"B","C"))) -> C | G44: =VLOOKUP(B$30:B$50,I$30:M$50,5,0) -> C | I44: tunika11 халат зеленая | J44: =ФЕВРАЛЬ!R39 -> 1 | K44: =J44/J$50 -> 0.011111111 | L44: =K44+L43 -> 1 | M44: =_xlfn.IFS(L44<80%,"A",L44<=95%,"B",L44>95%,"C") -> C
B45: tunika13 халат черная | C45: =ФЕВРАЛЬ!AE41 -> 0 | D45: =C45/C$50 -> 0 | E45: =D45+E44 -> 1.041713 | F45: =IF(AND(E45<=0),"C",IF(E45<=0.8,"A",IF(E45<=0.95,"B","C"))) -> C | G45: =VLOOKUP(B$30:B$50,I$30:M$50,5,0) -> C | I45: tunika03 черная распашная | J45: =ФЕВРАЛЬ!R29 -> 0 | K45: =J45/J$50 -> 0 | L45: =K45+L44 -> 1 | M45: =_xlfn.IFS(L45<80%,"A",L45<=95%,"B",L45>95%,"C") -> C
B46: tunika03 черная распашная | C46: =ФЕВРАЛЬ!AE29 -> -535.01 | D46: =C46/C$50 -> -0.0080718567 | E46: =D46+E45 -> 1.0336411 | F46: =IF(AND(E46<=0),"C",IF(E46<=0.8,"A",IF(E46<=0.95,"B","C"))) -> C | G46: =VLOOKUP(B$30:B$50,I$30:M$50,5,0) -> C | I46: tunika06 черная | J46: =ФЕВРАЛЬ!R32 -> 0 | K46: =J46/J$50 -> 0 | L46: =K46+L45 -> 1 | M46: =_xlfn.IFS(L46<80%,"A",L46<=95%,"B",L46>95%,"C") -> C
B47: tunika08 зеленая | C47: =ФЕВРАЛЬ!AE36 -> -683.28 | D47: =C47/C$50 -> -0.010308851 | E47: =D47+E46 -> 1.0233323 | F47: =IF(AND(E47<=0),"C",IF(E47<=0.8,"A",IF(E47<=0.95,"B","C"))) -> C | G47: =VLOOKUP(B$30:B$50,I$30:M$50,5,0) -> C | I47: tunika08 зеленая | J47: =ФЕВРАЛЬ!R36 -> 0 | K47: =J47/J$50 -> 0 | L47: =K47+L46 -> 1 | M47: =_xlfn.IFS(L47<80%,"A",L47<=95%,"B",L47>95%,"C") -> C
B48: tunika10 кимоно ч/б | C48: =ФЕВРАЛЬ!AE38 -> -762.4 | D48: =C48/C$50 -> -0.011502558 | E48: =D48+E47 -> 1.0118297 | F48: =IF(AND(E48<=0),"C",IF(E48<=0.8,"A",IF(E48<=0.95,"B","C"))) -> C | G48: =VLOOKUP(B$30:B$50,I$30:M$50,5,0) -> C | I48: tunika10 кимоно ч/б | J48: =ФЕВРАЛЬ!R38 -> 0 | K48: =J48/J$50 -> 0 | L48: =K48+L47 -> 1 | M48: =_xlfn.IFS(L48<80%,"A",L48<=95%,"B",L48>95%,"C") -> C
B49: tunika14 халат с разрезами белая | C49: =ФЕВРАЛЬ!AE42 -> -784.0848 | D49: =C49/C$50 -> -0.011829723 | E49: =D49+E48 -> 1 | F49: =IF(AND(E49<=0),"C",IF(E49<=0.8,"A",IF(E49<=0.95,"B","C"))) -> C | G49: =VLOOKUP(B$30:B$50,I$30:M$50,5,0) -> B | I49: tunika13 халат черная | J49: =ФЕВРАЛЬ!R41 -> 0 | K49: =J49/J$50 -> 0 | L49: =K49+L48 -> 1 | M49: =_xlfn.IFS(L49<80%,"A",L49<=95%,"B",L49>95%,"C") -> C
C50: =SUM(C30:C49) -> 66280.909 | D50: =SUM(D30:D49) -> 1 | J50: =SUM(J30:J49) -> 90 | K50: =SUM(K30:K49) -> 1

Sheet АВС 23.02-01.03
B2: ОЧКИ
C3: Прибыль | D3: % прибыль | E3: Доля | F3: ABC прибыль | G3: ABC кол-во | J3: Кол-во | K3: % кол-во | L3: Доля | M3: ABC кол-во
B4: черные с железкой классика | C4: ='Юнит 23.02-01.03'!AE3 -> 33017.893 | D4: =C4/C$26 -> 0.6879919 | E4: =D4 -> 0.6879919 | F4: =IF(AND(E4<=0),"C",IF(E4<=0.8,"A",IF(E4<=0.95,"B","C"))) -> A | G4: =VLOOKUP(B$4:B$25,I$4:M$25,5,0) -> A | I4: черные с железкой классика | J4: ='Юнит 23.02-01.03'!R3 -> 55 | K4: =J4/J$26 -> 0.47008547 | L4: =K4 -> 0.47008547 | M4: =_xlfn.IFS(L4<80%,"A",L4<=95%,"B",L4>95%,"C") -> A
B5: qs желтые | C5: ='Юнит 23.02-01.03'!AE6 -> 5714.258 | D5: =C5/C$26 -> 0.11906766 | E5: =D5+E4 -> 0.80705956 | F5: =IF(AND(E5<=0),"C",IF(E5<=0.8,"A",IF(E5<=0.95,"B","C"))) -> B | G5: =VLOOKUP(B$4:B$25,I$4:M$25,5,0) -> A | I5: qs желтые | J5: ='Юнит 23.02-01.03'!R6 -> 12 | K5: =J5/J$26 -> 0.1025641 | L5: =K5+L4 -> 0.57264957 | M5: =_xlfn.IFS(L5<80%,"A",L5<=95%,"B",L5>95%,"C") -> A
B6: MR8854 C2 | C6: ='Юнит 23.02-01.03'!AE10 -> 4422.0429 | D6: =C6/C$26 -> 0.09214185 | E6: =D6+E5 -> 0.89920141 | F6: =IF(AND(E6<=0),"C",IF(E6<=0.8,"A",IF(E6<=0.95,"B","C"))) -> B | G6: =VLOOKUP(B$4:B$25,I$4:M$25,5,0) -> A | I6: MR8854 C2 | J6: ='Юнит 23.02-01.03'!R10 -> 11 | K6: =J6/J$26 -> 0.094017094 | L6: =K6+L5 -> 0.66666667 | M6: =_xlfn.IFS(L6<80%,"A",L6<=95%,"B",L6>95%,"C") -> A
B7: MR Р1874 черн | C7: ='Юнит 23.02-01.03'!AE13 -> 2403.0929 | D7: =C7/C$26 -> 0.050073107 | E7: =D7+E6 -> 0.94927452 | F7: =IF(AND(E7<=0),"C",IF(E7<=0.8,"A",IF(E7<=0.95,"B","C"))) -> B | G7: =VLOOKUP(B$4:B$25,I$4:M$25,5,0) -> B | I7: MR Р1886 черн глянец | J7: ='Юнит 23.02-01.03'!R15 -> 11 | K7: =J7/J$26 -> 0.094017094 | L7: =K7+L6 -> 0.76068376 | M7: =_xlfn.IFS(L7<80%,"A",L7<=95%,"B",L7>95%,"C") -> A
B8: qs коричневые | C8: ='Юнит 23.02-01.03'!AE7 -> 1638.1117 | D8: =C8/C$26 -> 0.034133238 | E8: =D8+E7 -> 0.98340776 | F8: =IF(AND(E8<=0),"C",IF(E8<=0.8,"A",IF(E8<=0.95,"B","C"))) -> C | G8: =VLOOKUP(B$4:B$25,I$4:M$25,5,0) -> B | I8: qs коричневые | J8: ='Юнит 23.02-01.03'!R7 -> 9 | K8: =J8/J$26 -> 0.076923077 | L8: =K8+L7 -> 0.83760684 | M8: =_xlfn.IFS(L8<80%,"A",L8<=95%,"B",L8>95%,"C") -> B
B9: qs черные | C9: ='Юнит 23.02-01.03'!AE4 -> 1601.8791 | D9: =C9/C$26 -> 0.033378261 | E9: =D9+E8 -> 1.016786 | F9: =IF(AND(E9<=0),"C",IF(E9<=0.8,"A",IF(E9<=0.95,"B","C"))) -> C | G9: =VLOOKUP(B$4:B$25,I$4:M$25,5,0) -> B | I9: MR Р1874 черн | J9: ='Юнит 23.02-01.03'!R13 -> 9 | K9: =J9/J$26 -> 0.076923077 | L9: =K9+L8 -> 0.91452991 | M9: =_xlfn.IFS(L9<80%,"A",L9<=95%,"B",L9>95%,"C") -> B
B10: MR 1819 корич | C10: ='Юнит 23.02-01.03'!AE12 -> 1428.7372 | D10: =C10/C$26 -> 0.029770513 | E10: =D10+E9 -> 1.0465565 | F10: =IF(AND(E10<=0),"C",IF(E10<=0.8,"A",IF(E10<=0.95,"B","C"))) -> C | G10: =VLOOKUP(B$4:B$25,I$4:M$25,5,0) -> B | I10: qs черные | J10: ='Юнит 23.02-01.03'!R4 -> 4 | K10: =J10/J$26 -> 0.034188034 | L10: =K10+L9 -> 0.94871795 | M10: =_xlfn.IFS(L10<80%,"A",L10<=95%,"B",L10>95%,"C") -> B
B11: th желтый Сул | C11: ='Юнит 23.02-01.03'!AE8 -> 375.86234 | D11: =C11/C$26 -> 0.0078318216 | E11: =D11+E8 -> 0.99123958 | F11: =IF(AND(E11<=0),"C",IF(E11<=0.8,"A",IF(E11<=0.95,"B","C"))) -> C | G11: =VLOOKUP(B$4:B$25,I$4:M$25,5,0) -> B | I11: MR 1819 корич | J11: ='Юнит 23.02-01.03'!R12 -> 3 | K11: =J11/J$26 -> 0.025641026 | L11: =K11+L8 -> 0.86324786 | M11: =_xlfn.IFS(L11<80%,"A",L11<=95%,"B",L11>95%,"C") -> B
B12: MR Р1874 корич | C12: ='Юнит 23.02-01.03'!AE14 -> 0 | D12: =C12/C$26 -> 0 | E12: =D12+E11 -> 0.99123958 | F12: =IF(AND(E12<=0),"C",IF(E12<=0.8,"A",IF(E12<=0.95,"B","C"))) -> C | G12: =VLOOKUP(B$4:B$25,I$4:M$25,5,0) -> B | I12: th желтый Сул | J12: ='Юнит 23.02-01.03'!R8 -> 1 | K12: =J12/J$26 -> 0.0085470085 | L12: =K12+L11 -> 0.87179487 | M12: =_xlfn.IFS(L12<80%,"A",L12<=95%,"B",L12>95%,"C") -> B
B13: lux1 | C13: ='Юнит 23.02-01.03'!AE17 -> 0 | D13: =C13/C$26 -> 0 | E13: =D13+E12 -> 0.99123958 | F13: =IF(AND(E13<=0),"C",IF(E13<=0.8,"A",IF(E13<=0.95,"B","C"))) -> C | G13: =VLOOKUP(B$4:B$25,I$4:M$25,5,0) -> B | I13: flip желтые Сул | J13: ='Юнит 23.02-01.03'!R9 -> 1 | K13: =J13/J$26 -> 0.0085470085 | L13: =K13+L12 -> 0.88034188 | M13: =_xlfn.IFS(L13<80%,"A",L13<=95%,"B",L13>95%,"C") -> B | P13: A | Q13: 0.8
B14: lux2 | C14: ='Юнит 23.02-01.03'!AE18 -> 0 | D14: =C14/C$26 -> 0 | E14: =D14+E13 -> 0.99123958 | F14: =IF(AND(E14<=0),"C",IF(E14<=0.8,"A",IF(E14<=0.95,"B","C"))) -> C | G14: =VLOOKUP(B$4:B$25,I$4:M$25,5,0) -> B | I14: MR Р1886 корич | J14: ='Юнит 23.02-01.03'!R16 -> 1 | K14: =J14/J$26 -> 0.0085470085 | L14: =K14+L13 -> 0.88888889 | M14: =_xlfn.IFS(L14<80%,"A",L14<=95%,"B",L14>95%,"C") -> B | P14: B | Q14: 0.15
B15: lux4 | C15: ='Юнит 23.02-01.03'!AE20 -> 0 | D15: =C15/C$26 -> 0 | E15: =D15+E14 -> 0.99123958 | F15: =IF(AND(E15<=0),"C",IF(E15<=0.8,"A",IF(E15<=0.95,"B","C"))) -> C | G15: =VLOOKUP(B$4:B$25,I$4:M$25,5,0) -> B | I15: qs синие | J15: ='Юнит 23.02-01.03'!R5 -> 0 | K15: =J15/J$26 -> 0 | L15: =K15+L14 -> 0.88888889 | M15: =_xlfn.IFS(L15<80%,"A",L15<=95%,"B",L15>95%,"C") -> B | P15: C | Q15: 0.05
B16: lux5 | C16: ='Юнит 23.02-01.03'!AE21 -> 0 | D16: =C16/C$26 -> 0 | E16: =D16+E15 -> 0.99123958 | F16: =IF(AND(E16<=0),"C",IF(E16<=0.8,"A",IF(E16<=0.95,"B","C"))) -> C | G16: =VLOOKUP(B$4:B$25,I$4:M$25,5,0) -> B | I16: MR 1819 черн | J16: ='Юнит 23.02-01.03'!R11 -> 0 | K16: =J16/J$26 -> 0 | L16: =K16+L15 -> 0.88888889 | M16: =_xlfn.IFS(L16<80%,"A",L16<=95%,"B",L16>95%,"C") -> B
B17: lux6 | C17: ='Юнит 23.02-01.03'!AE22 -> 0 | D17: =C17/C$26 -> 0 | E17: =D17+E16 -> 0.99123958 | F17: =IF(AND(E17<=0),"C",IF(E17<=0.8,"A",IF(E17<=0.95,"B","C"))) -> C | G17: =VLOOKUP(B$4:B$25,I$4:M$25,5,0) -> B | I17: MR Р1874 корич | J17: ='Юнит 23.02-01.03'!R14 -> 0 | K17: =J17/J$26 -> 0 | L17: =K17+L16 -> 0.88888889 | M17: =_xlfn.IFS(L17<80%,"A",L17<=95%,"B",L17>95%,"C") -> B
B18: lux7 | C18: ='Юнит 23.02-01.03'!AE23 -> 0 | D18: =C18/C$26 -> 0 | E18: =D18+E17 -> 0.99123958 | F18: =IF(AND(E18<=0),"C",IF(E18<=0.8,"A",IF(E18<=0.95,"B","C"))) -> C | G18: =VLOOKUP(B$4:B$25,I$4:M$25,5,0) -> B | I18: lux1 | J18: ='Юнит 23.02-01.03'!R17 -> 0 | K18: =J18/J$26 -> 0 | L18: =K18+L17 -> 0.88888889 | M18: =_xlfn.IFS(L18<80%,"A",L18<=95%,"B",L18>95%,"C") -> B
B19: lux8 | C19: ='Юнит 23.02-01.03'!AE24 -> 0 | D19: =C19/C$26 -> 0 | E19: =D19+E18 -> 0.99123958 | F19: =IF(AND(E19<=0),"C",IF(E19<=0.8,"A",IF(E19<=0.95,"B","C"))) -> C | G19: =VLOOKUP(B$4:B$25,I$4:M$25,5,0) -> B | I19: lux2 | J19: ='Юнит 23.02-01.03'!R18 -> 0 | K19: =J19/J$26 -> 0 | L19: =K19+L18 -> 0.88888889 | M19: =_xlfn.IFS(L19<80%,"A",L19<=95%,"B",L19>95%,"C") -> B
B20: flip желтые Сул | C20: ='Юнит 23.02-01.03'!AE9 -> -22.464127 | D20: =C20/C$26 -> -0.00046808369 | E20: =D20+E19 -> 0.99077149 | F20: =IF(AND(E20<=0),"C",IF(E20<=0.8,"A",IF(E20<=0.95,"B","C"))) -> C | G20: =VLOOKUP(B$4:B$25,I$4:M$25,5,0) -> B | I20: lux3 | J20: ='Юнит 23.02-01.03'!R19 -> 0 | K20: =J20/J$26 -> 0 | L20: =K20+L19 -> 0.88888889 | M20: =_xlfn.IFS(L20<80%,"A",L20<=95%,"B",L20>95%,"C") -> B
B21: lux3 | C21: ='Юнит 23.02-01.03'!AE19 -> -113.88 | D21: =C21/C$26 -> -0.0023729109 | E21: =D21+E20 -> 0.98839858 | F21: =IF(AND(E21<=0),"C",IF(E21<=0.8,"A",IF(E21<=0.95,"B","C"))) -> C | G21: =VLOOKUP(B$4:B$25,I$4:M$25,5,0) -> B | I21: lux4 | J21: ='Юнит 23.02-01.03'!R20 -> 0 | K21: =J21/J$26 -> 0 | L21: =K21+L20 -> 0.88888889 | M21: =_xlfn.IFS(L21<80%,"A",L21<=95%,"B",L21>95%,"C") -> B
B22: MR Р1886 корич | C22: ='Юнит 23.02-01.03'!AE16 -> -142.52354 | D22: =C22/C$26 -> -0.0029697546 | E22: =D22+E21 -> 0.98542883 | F22: =IF(AND(E22<=0),"C",IF(E22<=0.8,"A",IF(E22<=0.95,"B","C"))) -> C | G22: =VLOOKUP(B$4:B$25,I$4:M$25,5,0) -> B | I22: lux5 | J22: ='Юнит 23.02-01.03'!R21 -> 0 | K22: =J22/J$26 -> 0 | L22: =K22+L21 -> 0.88888889 | M22: =_xlfn.IFS(L22<80%,"A",L22<=95%,"B",L22>95%,"C") -> B
B23: MR 1819 черн | C23: ='Юнит 23.02-01.03'!AE11 -> -187.08 | D23: =C23/C$26 -> -0.003898175 | E23: =D23+E22 -> 0.98153065 | F23: =IF(AND(E23<=0),"C",IF(E23<=0.8,"A",IF(E23<=0.95,"B","C"))) -> C | G23: =VLOOKUP(B$4:B$25,I$4:M$25,5,0) -> B | I23: lux6 | J23: ='Юнит 23.02-01.03'!R22 -> 0 | K23: =J23/J$26 -> 0 | L23: =K23+L22 -> 0.88888889 | M23: =_xlfn.IFS(L23<80%,"A",L23<=95%,"B",L23>95%,"C") -> B
B24: qs синие | C24: ='Юнит 23.02-01.03'!AE5 -> -935.41696 | D24: =C24/C$26 -> -0.019491228 | E24: =D24+E23 -> 0.96203942 | F24: =IF(AND(E24<=0),"C",IF(E24<=0.8,"A",IF(E24<=0.95,"B","C"))) -> C | G24: =VLOOKUP(B$4:B$25,I$4:M$25,5,0) -> B | I24: lux7 | J24: ='Юнит 23.02-01.03'!R23 -> 0 | K24: =J24/J$26 -> 0 | L24: =K24+L23 -> 0.88888889 | M24: =_xlfn.IFS(L24<80%,"A",L24<=95%,"B",L24>95%,"C") -> B
B25: MR Р1886 черн глянец | C25: ='Юнит 23.02-01.03'!AE15 -> -1208.8242 | D25: =C25/C$26 -> -0.025188198 | E25: =D25+E24 -> 0.93685123 | F25: =IF(AND(E25<=0),"C",IF(E25<=0.8,"A",IF(E25<=0.95,"B","C"))) -> B | G25: =VLOOKUP(B$4:B$25,I$4:M$25,5,0) -> A | I25: lux8 | J25: ='Юнит 23.02-01.03'!R24 -> 0 | K25: =J25/J$26 -> 0 | L25: =K25+L24 -> 0.88888889 | M25: =_xlfn.IFS(L25<80%,"A",L25<=95%,"B",L25>95%,"C") -> B
C26: =SUM(C4:C25) -> 47991.688 | D26: =SUM(D4:D25) -> 1 | J26: =SUM(J4:J25) -> 117 | K26: =SUM(K4:K25) -> 1
B28: ТУНИКИ
C29: Прибыль | D29: % прибыль | E29: Доля | F29: ABC прибыль | G29: ABC кол-во | J29: Кол-во | K29: % кол-во | L29: Доля | M29: ABC кол-во
B30: tunika15 кимоно бирюза | C30: ='Юнит 23.02-01.03'!AE44 -> 4779.458 | D30: =C30/C$50 -> 0.26977565 | E30: =D30 -> 0.26977565 | F30: =IF(AND(E30<=0),"C",IF(E30<=0.8,"A",IF(E30<=0.95,"B","C"))) -> A | G30: =VLOOKUP(B$30:B$50,I$30:M$50,5,0) -> B | I30: tunika15 кимоно песочная | J30: ='Юнит 23.02-01.03'!R45 -> 9 | K30: =J30/J$50 -> 0.34615385 | L30: =K30 -> 0.34615385 | M30: =_xlfn.IFS(L30<80%,"A",L30<=95%,"B",L30>95%,"C") -> A
B31: tunika05 белая распашная | C31: ='Юнит 23.02-01.03'!AE30 -> 3307.6535 | D31: =C31/C$50 -> 0.18669991 | E31: =D31+E30 -> 0.45647555 | F31: =IF(AND(E31<=0),"C",IF(E31<=0.8,"A",IF(E31<=0.95,"B","C"))) -> A | G31: =VLOOKUP(B$30:B$50,I$30:M$50,5,0) -> A | I31: tunika16 сетка белая | J31: ='Юнит 23.02-01.03'!R46 -> 5 | K31: =J31/J$50 -> 0.19230769 | L31: =K31+L30 -> 0.53846154 | M31: =_xlfn.IFS(L31<80%,"A",L31<=95%,"B",L31>95%,"C") -> A
B32: tunika12 халат белая | C32: ='Юнит 23.02-01.03'!AE40 -> 3219.5676 | D32: =C32/C$50 -> 0.18172792 | E32: =D32+E31 -> 0.63820347 | F32: =IF(AND(E32<=0),"C",IF(E32<=0.8,"A",IF(E32<=0.95,"B","C"))) -> A | G32: =VLOOKUP(B$30:B$50,I$30:M$50,5,0) -> A | I32: tunika05 белая распашная | J32: ='Юнит 23.02-01.03'!R30 -> 2 | K32: =J32/J$50 -> 0.076923077 | L32: =K32+L31 -> 0.61538462 | M32: =_xlfn.IFS(L32<80%,"A",L32<=95%,"B",L32>95%,"C") -> A
B33: tunika09 кимоно | C33: ='Юнит 23.02-01.03'!AE37 -> 2623.219 | D33: =C33/C$50 -> 0.14806712 | E33: =D33+E32 -> 0.78627059 | F33: =IF(AND(E33<=0),"C",IF(E33<=0.8,"A",IF(E33<=0.95,"B","C"))) -> A | G33: =VLOOKUP(B$30:B$50,I$30:M$50,5,0) -> C | I33: tunika12 халат белая | J33: ='Юнит 23.02-01.03'!R40 -> 2 | K33: =J33/J$50 -> 0.076923077 | L33: =K33+L32 -> 0.69230769 | M33: =_xlfn.IFS(L33<80%,"A",L33<=95%,"B",L33>95%,"C") -> A
B34: tunika14 халат с разрезами черный | C34: ='Юнит 23.02-01.03'!AE43 -> 2553.9268 | D34: =C34/C$50 -> 0.14415594 | E34: =D34+E33 -> 0.93042653 | F34: =IF(AND(E34<=0),"C",IF(E34<=0.8,"A",IF(E34<=0.95,"B","C"))) -> B | G34: =VLOOKUP(B$30:B$50,I$30:M$50,5,0) -> A | I34: tunika14 халат с разрезами черный | J34: ='Юнит 23.02-01.03'!R43 -> 2 | K34: =J34/J$50 -> 0.076923077 | L34: =K34+L33 -> 0.76923077 | M34: =_xlfn.IFS(L34<80%,"A",L34<=95%,"B",L34>95%,"C") -> A
B35: tunika14 халат с разрезами белая | C35: ='Юнит 23.02-01.03'!AE42 -> 1585.9122 | D35: =C35/C$50 -> 0.089516532 | E35: =D35+E34 -> 1.0199431 | F35: =IF(AND(E35<=0),"C",IF(E35<=0.8,"A",IF(E35<=0.95,"B","C"))) -> C | G35: =VLOOKUP(B$30:B$50,I$30:M$50,5,0) -> C | I35: tunika15 кимоно бирюза | J35: ='Юнит 23.02-01.03'!R44 -> 2 | K35: =J35/J$50 -> 0.076923077 | L35: =K35+L34 -> 0.84615385 | M35: =_xlfn.IFS(L35<80%,"A",L35<=95%,"B",L35>95%,"C") -> B
B36: tunika07 кружево | C36: ='Юнит 23.02-01.03'!AE33 -> 1468.5949 | D36: =C36/C$50 -> 0.082894578 | E36: =D36+E35 -> 1.1028376 | F36: =IF(AND(E36<=0),"C",IF(E36<=0.8,"A",IF(E36<=0.95,"B","C"))) -> C | G36: =VLOOKUP(B$30:B$50,I$30:M$50,5,0) -> B | I36: tunika02 оливковая с руч вышивкой | J36: ='Юнит 23.02-01.03'!R28 -> 1 | K36: =J36/J$50 -> 0.038461538 | L36: =K36+L35 -> 0.88461538 | M36: =_xlfn.IFS(L36<80%,"A",L36<=95%,"B",L36>95%,"C") -> B
B37: tunika02 оливковая с руч вышивкой | C37: ='Юнит 23.02-01.03'!AE28 -> 1423.4363 | D37: =C37/C$50 -> 0.080345604 | E37: =D37+E36 -> 1.1831832 | F37: =IF(AND(E37<=0),"C",IF(E37<=0.8,"A",IF(E37<=0.95,"B","C"))) -> C | G37: =VLOOKUP(B$30:B$50,I$30:M$50,5,0) -> B | I37: tunika07 кружево | J37: ='Юнит 23.02-01.03'!R33 -> 1 | K37: =J37/J$50 -> 0.038461538 | L37: =K37+L36 -> 0.92307692 | M37: =_xlfn.IFS(L37<80%,"A",L37<=95%,"B",L37>95%,"C") -> B
B38: tunika16 сетка белая | C38: ='Юнит 23.02-01.03'!AE46 -> 17.618356 | D38: =C38/C$50 -> 0.00099446493 | E38: =D38+E37 -> 1.1841777 | F38: =IF(AND(E38<=0),"C",IF(E38<=0.8,"A",IF(E38<=0.95,"B","C"))) -> C | G38: =VLOOKUP(B$30:B$50,I$30:M$50,5,0) -> A | I38: tunika09 кимоно | J38: ='Юнит 23.02-01.03'!R37 -> 1 | K38: =J38/J$50 -> 0.038461538 | L38: =K38+L37 -> 0.96153846 | M38: =_xlfn.IFS(L38<80%,"A",L38<=95%,"B",L38>95%,"C") -> C
B39: tunika03 черная распашная | C39: ='Юнит 23.02-01.03'!AE29 -> 0 | D39: =C39/C$50 -> 0 | E39: =D39+E38 -> 1.1841777 | F39: =IF(AND(E39<=0),"C",IF(E39<=0.8,"A",IF(E39<=0.95,"B","C"))) -> C | G39: =VLOOKUP(B$30:B$50,I$30:M$50,5,0) -> C | I39: tunika14 халат с разрезами белая | J39: ='Юнит 23.02-01.03'!R42 -> 1 | K39: =J39/J$50 -> 0.038461538 | L39: =K39+L38 -> 1 | M39: =_xlfn.IFS(L39<80%,"A",L39<=95%,"B",L39>95%,"C") -> C
B40: tunika06 белая | C40: ='Юнит 23.02-01.03'!AE31 -> 0 | D40: =C40/C$50 -> 0 | E40: =D40+E39 -> 1.1841777 | F40: =IF(AND(E40<=0),"C",IF(E40<=0.8,"A",IF(E40<=0.95,"B","C"))) -> C | G40: =VLOOKUP(B$30:B$50,I$30:M$50,5,0) -> C | I40: tunika03 черная распашная | J40: ='Юнит 23.02-01.03'!R29 -> 0 | K40: =J40/J$50 -> 0 | L40: =K40+L39 -> 1 | M40: =_xlfn.IFS(L40<80%,"A",L40<=95%,"B",L40>95%,"C") -> C
B41: tunika06 черная | C41: ='Юнит 23.02-01.03'!AE32 -> 0 | D41: =C41/C$50 -> 0 | E41: =D41+E40 -> 1.1841777 | F41: =IF(AND(E41<=0),"C",IF(E41<=0.8,"A",IF(E41<=0.95,"B","C"))) -> C | G41: =VLOOKUP(B$30:B$50,I$30:M$50,5,0) -> C | I41: tunika06 белая | J41: ='Юнит 23.02-01.03'!R31 -> 0 | K41: =J41/J$50 -> 0 | L41: =K41+L40 -> 1 | M41: =_xlfn.IFS(L41<80%,"A",L41<=95%,"B",L41>95%,"C") -> C
B42: tunika08 белая | C42: ='Юнит 23.02-01.03'!AE34 -> 0 | D42: =C42/C$50 -> 0 | E42: =D42+E41 -> 1.1841777 | F42: =IF(AND(E42<=0),"C",IF(E42<=0.8,"A",IF(E42<=0.95,"B","C"))) -> C | G42: =VLOOKUP(B$30:B$50,I$30:M$50,5,0) -> C | I42: tunika06 черная | J42: ='Юнит 23.02-01.03'!R32 -> 0 | K42: =J42/J$50 -> 0 | L42: =K42+L41 -> 1 | M42: =_xlfn.IFS(L42<80%,"A",L42<=95%,"B",L42>95%,"C") -> C
B43: tunika10 кимоно ч/б | C43: ='Юнит 23.02-01.03'!AE38 -> 0 | D43: =C43/C$50 -> 0 | E43: =D43+E42 -> 1.1841777 | F43: =IF(AND(E43<=0),"C",IF(E43<=0.8,"A",IF(E43<=0.95,"B","C"))) -> C | G43: =VLOOKUP(B$30:B$50,I$30:M$50,5,0) -> C | I43: tunika08 белая | J43: ='Юнит 23.02-01.03'!R34 -> 0 | K43: =J43/J$50 -> 0 | L43: =K43+L42 -> 1 | M43: =_xlfn.IFS(L43<80%,"A",L43<=95%,"B",L43>95%,"C") -> C
B44: tunika11 халат зеленая | C44: ='Юнит 23.02-01.03'!AE39 -> 0 | D44: =C44/C$50 -> 0 | E44: =D44+E43 -> 1.1841777 | F44: =IF(AND(E44<=0),"C",IF(E44<=0.8,"A",IF(E44<=0.95,"B","C"))) -> C | G44: =VLOOKUP(B$30:B$50,I$30:M$50,5,0) -> C | I44: tunika08 черная | J44: ='Юнит 23.02-01.03'!R35 -> 0 | K44: =J44/J$50 -> 0 | L44: =K44+L43 -> 1 | M44: =_xlfn.IFS(L44<80%,"A",L44<=95%,"B",L44>95%,"C") -> C
B45: tunika13 халат черная | C45: ='Юнит 23.02-01.03'!AE41 -> 0 | D45: =C45/C$50 -> 0 | E45: =D45+E44 -> 1.1841777 | F45: =IF(AND(E45<=0),"C",IF(E45<=0.8,"A",IF(E45<=0.95,"B","C"))) -> C | G45: =VLOOKUP(B$30:B$50,I$30:M$50,5,0) -> C | I45: tunika08 зеленая | J45: ='Юнит 23.02-01.03'!R36 -> 0 | K45: =J45/J$50 -> 0 | L45: =K45+L44 -> 1 | M45: =_xlfn.IFS(L45<80%,"A",L45<=95%,"B",L45>95%,"C") -> C
B46: tunika08 черная | C46: ='Юнит 23.02-01.03'!AE35 -> -113.88 | D46: =C46/C$50 -> -0.0064279362 | E46: =D46+E45 -> 1.1777498 | F46: =IF(AND(E46<=0),"C",IF(E46<=0.8,"A",IF(E46<=0.95,"B","C"))) -> C | G46: =VLOOKUP(B$30:B$50,I$30:M$50,5,0) -> C | I46: tunika10 кимоно ч/б | J46: ='Юнит 23.02-01.03'!R38 -> 0 | K46: =J46/J$50 -> 0 | L46: =K46+L45 -> 1 | M46: =_xlfn.IFS(L46<80%,"A",L46<=95%,"B",L46>95%,"C") -> C
B47: tunika08 зеленая | C47: ='Юнит 23.02-01.03'!AE36 -> -113.88 | D47: =C47/C$50 -> -0.0064279362 | E47: =D47+E46 -> 1.1713218 | F47: =IF(AND(E47<=0),"C",IF(E47<=0.8,"A",IF(E47<=0.95,"B","C"))) -> C | G47: =VLOOKUP(B$30:B$50,I$30:M$50,5,0) -> C | I47: tunika11 халат зеленая | J47: ='Юнит 23.02-01.03'!R39 -> 0 | K47: =J47/J$50 -> 0 | L47: =K47+L46 -> 1 | M47: =_xlfn.IFS(L47<80%,"A",L47<=95%,"B",L47>95%,"C") -> C
B48: tunika16 сетка черная | C48: ='Юнит 23.02-01.03'!AE47 -> -227.76 | D48: =C48/C$50 -> -0.012855872 | E48: =D48+E47 -> 1.158466 | F48: =IF(AND(E48<=0),"C",IF(E48<=0.8,"A",IF(E48<=0.95,"B","C"))) -> C | G48: =VLOOKUP(B$30:B$50,I$30:M$50,5,0) -> C | I48: tunika13 халат черная | J48: ='Юнит 23.02-01.03'!R41 -> 0 | K48: =J48/J$50 -> 0 | L48: =K48+L47 -> 1 | M48: =_xlfn.IFS(L48<80%,"A",L48<=95%,"B",L48>95%,"C") -> C
B49: tunika15 кимоно песочная | C49: ='Юнит 23.02-01.03'!AE45 -> -2807.4492 | D49: =C49/C$50 -> -0.15846596 | E49: =D49+E48 -> 1 | F49: =IF(AND(E49<=0),"C",IF(E49<=0.8,"A",IF(E49<=0.95,"B","C"))) -> C | G49: =VLOOKUP(B$30:B$50,I$30:M$50,5,0) -> A | I49: tunika16 сетка черная | J49: ='Юнит 23.02-01.03'!R47 -> 0 | K49: =J49/J$50 -> 0 | L49: =K49+L48 -> 1 | M49: =_xlfn.IFS(L49<80%,"A",L49<=95%,"B",L49>95%,"C") -> C
C50: =SUM(C30:C49) -> 17716.417 | D50: =SUM(D30:D49) -> 1 | J50: =SUM(J30:J49) -> 26 | K50: =SUM(K30:K49) -> 1

Sheet АВС 16-22.02
B2: ОЧКИ
C3: Прибыль | D3: % прибыль | E3: Доля | F3: ABC прибыль | G3: ABC кол-во | J3: Кол-во | K3: % кол-во | L3: Доля | M3: ABC кол-во
B4: черные с железкой классика | C4: ='Юнит 16-22.02'!AE3 -> 17253.917 | D4: =C4/C$26 -> 0.57923097 | E4: =D4 -> 0.57923097 | F4: =IF(AND(E4<=0),"C",IF(E4<=0.8,"A",IF(E4<=0.95,"B","C"))) -> A | G4: =VLOOKUP(B$4:B$25,I$4:M$25,5,0) -> A | I4: черные с железкой классика | J4: ='Юнит 16-22.02'!R3 -> 33 | K4: =J4/J$26 -> 0.42857143 | L4: =K4 -> 0.42857143 | M4: =_xlfn.IFS(L4<80%,"A",L4<=95%,"B",L4>95%,"C") -> A
B5: qs желтые | C5: ='Юнит 16-22.02'!AE6 -> 4516.8356 | D5: =C5/C$26 -> 0.15163462 | E5: =D5+E4 -> 0.73086558 | F5: =IF(AND(E5<=0),"C",IF(E5<=0.8,"A",IF(E5<=0.95,"B","C"))) -> A | G5: =VLOOKUP(B$4:B$25,I$4:M$25,5,0) -> A | I5: qs желтые | J5: ='Юнит 16-22.02'!R6 -> 9 | K5: =J5/J$26 -> 0.11688312 | L5: =K5+L4 -> 0.54545455 | M5: =_xlfn.IFS(L5<80%,"A",L5<=95%,"B",L5>95%,"C") -> A
B6: MR Р1874 черн | C6: ='Юнит 16-22.02'!AE13 -> 3110.4793 | D6: =C6/C$26 -> 0.10442185 | E6: =D6+E5 -> 0.83528743 | F6: =IF(AND(E6<=0),"C",IF(E6<=0.8,"A",IF(E6<=0.95,"B","C"))) -> B | G6: =VLOOKUP(B$4:B$25,I$4:M$25,5,0) -> A | I6: qs коричневые | J6: ='Юнит 16-22.02'!R7 -> 8 | K6: =J6/J$26 -> 0.1038961 | L6: =K6+L5 -> 0.64935065 | M6: =_xlfn.IFS(L6<80%,"A",L6<=95%,"B",L6>95%,"C") -> A
B7: qs коричневые | C7: ='Юнит 16-22.02'!AE7 -> 2066.9719 | D7: =C7/C$26 -> 0.06939028 | E7: =D7+E6 -> 0.90467771 | F7: =IF(AND(E7<=0),"C",IF(E7<=0.8,"A",IF(E7<=0.95,"B","C"))) -> B | G7: =VLOOKUP(B$4:B$25,I$4:M$25,5,0) -> A | I7: MR Р1874 черн | J7: ='Юнит 16-22.02'!R13 -> 7 | K7: =J7/J$26 -> 0.090909091 | L7: =K7+L6 -> 0.74025974 | M7: =_xlfn.IFS(L7<80%,"A",L7<=95%,"B",L7>95%,"C") -> A
B8: MR8854 C2 | C8: ='Юнит 16-22.02'!AE10 -> 1739.7317 | D8: =C8/C$26 -> 0.058404505 | E8: =D8+E7 -> 0.96308222 | F8: =IF(AND(E8<=0),"C",IF(E8<=0.8,"A",IF(E8<=0.95,"B","C"))) -> C | G8: =VLOOKUP(B$4:B$25,I$4:M$25,5,0) -> B | I8: MR Р1886 черн глянец | J8: ='Юнит 16-22.02'!R15 -> 7 | K8: =J8/J$26 -> 0.090909091 | L8: =K8+L7 -> 0.83116883 | M8: =_xlfn.IFS(L8<80%,"A",L8<=95%,"B",L8>95%,"C") -> B
B9: th желтый Сул | C9: ='Юнит 16-22.02'!AE8 -> 1310.2365 | D9: =C9/C$26 -> 0.04398593 | E9: =D9+E8 -> 1.0070681 | F9: =IF(AND(E9<=0),"C",IF(E9<=0.8,"A",IF(E9<=0.95,"B","C"))) -> C | G9: =VLOOKUP(B$4:B$25,I$4:M$25,5,0) -> B | I9: MR8854 C2 | J9: ='Юнит 16-22.02'!R10 -> 5 | K9: =J9/J$26 -> 0.064935065 | L9: =K9+L8 -> 0.8961039 | M9: =_xlfn.IFS(L9<80%,"A",L9<=95%,"B",L9>95%,"C") -> B
B10: MR Р1886 черн глянец | C10: ='Юнит 16-22.02'!AE15 -> 1080.6849 | D10: =C10/C$26 -> 0.036279655 | E10: =D10+E9 -> 1.0433478 | F10: =IF(AND(E10<=0),"C",IF(E10<=0.8,"A",IF(E10<=0.95,"B","C"))) -> C | G10: =VLOOKUP(B$4:B$25,I$4:M$25,5,0) -> B | I10: th желтый Сул | J10: ='Юнит 16-22.02'!R8 -> 3 | K10: =J10/J$26 -> 0.038961039 | L10: =K10+L9 -> 0.93506494 | M10: =_xlfn.IFS(L10<80%,"A",L10<=95%,"B",L10>95%,"C") -> B
B11: MR Р1886 корич | C11: ='Юнит 16-22.02'!AE16 -> 631.36683 | D11: =C11/C$26 -> 0.021195605 | E11: =D11+E8 -> 0.98427782 | F11: =IF(AND(E11<=0),"C",IF(E11<=0.8,"A",IF(E11<=0.95,"B","C"))) -> C | G11: =VLOOKUP(B$4:B$25,I$4:M$25,5,0) -> B | I11: MR Р1874 корич | J11: ='Юнит 16-22.02'!R14 -> 2 | K11: =J11/J$26 -> 0.025974026 | L11: =K11+L8 -> 0.85714286 | M11: =_xlfn.IFS(L11<80%,"A",L11<=95%,"B",L11>95%,"C") -> B
B12: MR 1819 черн | C12: ='Юнит 16-22.02'!AE11 -> 383.89 | D12: =C12/C$26 -> 0.012887565 | E12: =D12+E11 -> 0.99716539 | F12: =IF(AND(E12<=0),"C",IF(E12<=0.8,"A",IF(E12<=0.95,"B","C"))) -> C | G12: =VLOOKUP(B$4:B$25,I$4:M$25,5,0) -> B | I12: flip желтые Сул | J12: ='Юнит 16-22.02'!R9 -> 1 | K12: =J12/J$26 -> 0.012987013 | L12: =K12+L11 -> 0.87012987 | M12: =_xlfn.IFS(L12<80%,"A",L12<=95%,"B",L12>95%,"C") -> B
B13: MR Р1874 корич | C13: ='Юнит 16-22.02'!AE14 -> 245.05556 | D13: =C13/C$26 -> 0.0082267563 | E13: =D13+E12 -> 1.0053921 | F13: =IF(AND(E13<=0),"C",IF(E13<=0.8,"A",IF(E13<=0.95,"B","C"))) -> C | G13: =VLOOKUP(B$4:B$25,I$4:M$25,5,0) -> B | I13: MR 1819 черн | J13: ='Юнит 16-22.02'!R11 -> 1 | K13: =J13/J$26 -> 0.012987013 | L13: =K13+L12 -> 0.88311688 | M13: =_xlfn.IFS(L13<80%,"A",L13<=95%,"B",L13>95%,"C") -> B | P13: A | Q13: 0.8
B14: MR 1819 корич | C14: ='Юнит 16-22.02'!AE12 -> 0 | D14: =C14/C$26 -> 0 | E14: =D14+E13 -> 1.0053921 | F14: =IF(AND(E14<=0),"C",IF(E14<=0.8,"A",IF(E14<=0.95,"B","C"))) -> C | G14: =VLOOKUP(B$4:B$25,I$4:M$25,5,0) -> B | I14: MR Р1886 корич | J14: ='Юнит 16-22.02'!R16 -> 1 | K14: =J14/J$26 -> 0.012987013 | L14: =K14+L13 -> 0.8961039 | M14: =_xlfn.IFS(L14<80%,"A",L14<=95%,"B",L14>95%,"C") -> B | P14: B | Q14: 0.15
B15: lux1 | C15: ='Юнит 16-22.02'!AE17 -> 0 | D15: =C15/C$26 -> 0 | E15: =D15+E14 -> 1.0053921 | F15: =IF(AND(E15<=0),"C",IF(E15<=0.8,"A",IF(E15<=0.95,"B","C"))) -> C | G15: =VLOOKUP(B$4:B$25,I$4:M$25,5,0) -> B | I15: qs черные | J15: ='Юнит 16-22.02'!R4 -> 0 | K15: =J15/J$26 -> 0 | L15: =K15+L14 -> 0.8961039 | M15: =_xlfn.IFS(L15<80%,"A",L15<=95%,"B",L15>95%,"C") -> B | P15: C | Q15: 0.05
B16: lux2 | C16: ='Юнит 16-22.02'!AE18 -> 0 | D16: =C16/C$26 -> 0 | E16: =D16+E15 -> 1.0053921 | F16: =IF(AND(E16<=0),"C",IF(E16<=0.8,"A",IF(E16<=0.95,"B","C"))) -> C | G16: =VLOOKUP(B$4:B$25,I$4:M$25,5,0) -> B | I16: qs синие | J16: ='Юнит 16-22.02'!R5 -> 0 | K16: =J16/J$26 -> 0 | L16: =K16+L15 -> 0.8961039 | M16: =_xlfn.IFS(L16<80%,"A",L16<=95%,"B",L16>95%,"C") -> B
B17: lux3 | C17: ='Юнит 16-22.02'!AE19 -> 0 | D17: =C17/C$26 -> 0 | E17: =D17+E16 -> 1.0053921 | F17: =IF(AND(E17<=0),"C",IF(E17<=0.8,"A",IF(E17<=0.95,"B","C"))) -> C | G17: =VLOOKUP(B$4:B$25,I$4:M$25,5,0) -> B | I17: MR 1819 корич | J17: ='Юнит 16-22.02'!R12 -> 0 | K17: =J17/J$26 -> 0 | L17: =K17+L16 -> 0.8961039 | M17: =_xlfn.IFS(L17<80%,"A",L17<=95%,"B",L17>95%,"C") -> B
B18: lux4 | C18: ='Юнит 16-22.02'!AE20 -> 0 | D18: =C18/C$26 -> 0 | E18: =D18+E17 -> 1.0053921 | F18: =IF(AND(E18<=0),"C",IF(E18<=0.8,"A",IF(E18<=0.95,"B","C"))) -> C | G18: =VLOOKUP(B$4:B$25,I$4:M$25,5,0) -> B | I18: lux1 | J18: ='Юнит 16-22.02'!R17 -> 0 | K18: =J18/J$26 -> 0 | L18: =K18+L17 -> 0.8961039 | M18: =_xlfn.IFS(L18<80%,"A",L18<=95%,"B",L18>95%,"C") -> B
B19: lux5 | C19: ='Юнит 16-22.02'!AE21 -> 0 | D19: =C19/C$26 -> 0 | E19: =D19+E18 -> 1.0053921 | F19: =IF(AND(E19<=0),"C",IF(E19<=0.8,"A",IF(E19<=0.95,"B","C"))) -> C | G19: =VLOOKUP(B$4:B$25,I$4:M$25,5,0) -> B | I19: lux2 | J19: ='Юнит 16-22.02'!R18 -> 0 | K19: =J19/J$26 -> 0 | L19: =K19+L18 -> 0.8961039 | M19: =_xlfn.IFS(L19<80%,"A",L19<=95%,"B",L19>95%,"C") -> B
B20: lux6 | C20: ='Юнит 16-22.02'!AE22 -> 0 | D20: =C20/C$26 -> 0 | E20: =D20+E19 -> 1.0053921 | F20: =IF(AND(E20<=0),"C",IF(E20<=0.8,"A",IF(E20<=0.95,"B","C"))) -> C | G20: =VLOOKUP(B$4:B$25,I$4:M$25,5,0) -> B | I20: lux3 | J20: ='Юнит 16-22.02'!R19 -> 0 | K20: =J20/J$26 -> 0 | L20: =K20+L19 -> 0.8961039 | M20: =_xlfn.IFS(L20<80%,"A",L20<=95%,"B",L20>95%,"C") -> B
B21: lux7 | C21: ='Юнит 16-22.02'!AE23 -> 0 | D21: =C21/C$26 -> 0 | E21: =D21+E20 -> 1.0053921 | F21: =IF(AND(E21<=0),"C",IF(E21<=0.8,"A",IF(E21<=0.95,"B","C"))) -> C | G21: =VLOOKUP(B$4:B$25,I$4:M$25,5,0) -> B | I21: lux4 | J21: ='Юнит 16-22.02'!R20 -> 0 | K21: =J21/J$26 -> 0 | L21: =K21+L20 -> 0.8961039 | M21: =_xlfn.IFS(L21<80%,"A",L21<=95%,"B",L21>95%,"C") -> B
B22: lux8 | C22: ='Юнит 16-22.02'!AE24 -> 0 | D22: =C22/C$26 -> 0 | E22: =D22+E21 -> 1.0053921 | F22: =IF(AND(E22<=0),"C",IF(E22<=0.8,"A",IF(E22<=0.95,"B","C"))) -> C | G22: =VLOOKUP(B$4:B$25,I$4:M$25,5,0) -> B | I22: lux5 | J22: ='Юнит 16-22.02'!R21 -> 0 | K22: =J22/J$26 -> 0 | L22: =K22+L21 -> 0.8961039 | M22: =_xlfn.IFS(L22<80%,"A",L22<=95%,"B",L22>95%,"C") -> B
B23: qs синие | C23: ='Юнит 16-22.02'!AE5 -> -93.54 | D23: =C23/C$26 -> -0.0031402298 | E23: =D23+E22 -> 1.0022519 | F23: =IF(AND(E23<=0),"C",IF(E23<=0.8,"A",IF(E23<=0.95,"B","C"))) -> C | G23: =VLOOKUP(B$4:B$25,I$4:M$25,5,0) -> B | I23: lux6 | J23: ='Юнит 16-22.02'!R22 -> 0 | K23: =J23/J$26 -> 0 | L23: =K23+L22 -> 0.8961039 | M23: =_xlfn.IFS(L23<80%,"A",L23<=95%,"B",L23>95%,"C") -> B
B24: flip желтые Сул | C24: ='Юнит 16-22.02'!AE9 -> -577.67962 | D24: =C24/C$26 -> -0.019393273 | E24: =D24+E23 -> 0.98285864 | F24: =IF(AND(E24<=0),"C",IF(E24<=0.8,"A",IF(E24<=0.95,"B","C"))) -> C | G24: =VLOOKUP(B$4:B$25,I$4:M$25,5,0) -> B | I24: lux7 | J24: ='Юнит 16-22.02'!R23 -> 0 | K24: =J24/J$26 -> 0 | L24: =K24+L23 -> 0.8961039 | M24: =_xlfn.IFS(L24<80%,"A",L24<=95%,"B",L24>95%,"C") -> B
B25: qs черные | C25: ='Юнит 16-22.02'!AE4 -> -1880.321 | D25: =C25/C$26 -> -0.063124226 | E25: =D25+E24 -> 0.91973442 | F25: =IF(AND(E25<=0),"C",IF(E25<=0.8,"A",IF(E25<=0.95,"B","C"))) -> B | G25: =VLOOKUP(B$4:B$25,I$4:M$25,5,0) -> B | I25: lux8 | J25: ='Юнит 16-22.02'!R24 -> 0 | K25: =J25/J$26 -> 0 | L25: =K25+L24 -> 0.8961039 | M25: =_xlfn.IFS(L25<80%,"A",L25<=95%,"B",L25>95%,"C") -> B
C26: =SUM(C4:C25) -> 29787.629 | D26: =SUM(D4:D25) -> 1 | J26: =SUM(J4:J25) -> 77 | K26: =SUM(K4:K25) -> 1
B28: ТУНИКИ
C29: Прибыль | D29: % прибыль | E29: Доля | F29: ABC прибыль | G29: ABC кол-во | J29: Кол-во | K29: % кол-во | L29: Доля | M29: ABC кол-во
B30: tunika15 кимоно песочная | C30: ='Юнит 16-22.02'!AE45 -> 8204.5166 | D30: =C30/C$50 -> 0.30578667 | E30: =D30 -> 0.30578667 | F30: =IF(AND(E30<=0),"C",IF(E30<=0.8,"A",IF(E30<=0.95,"B","C"))) -> A | G30: =VLOOKUP(B$30:B$50,I$30:M$50,5,0) -> A | I30: tunika16 сетка белая | J30: ='Юнит 16-22.02'!R46 -> 10 | K30: =J30/J$50 -> 0.4 | L30: =K30 -> 0.4 | M30: =_xlfn.IFS(L30<80%,"A",L30<=95%,"B",L30>95%,"C") -> A
B31: tunika15 кимоно бирюза | C31: ='Юнит 16-22.02'!AE44 -> 6982.6542 | D31: =C31/C$50 -> 0.26024722 | E31: =D31+E30 -> 0.56603389 | F31: =IF(AND(E31<=0),"C",IF(E31<=0.8,"A",IF(E31<=0.95,"B","C"))) -> A | G31: =VLOOKUP(B$30:B$50,I$30:M$50,5,0) -> B | I31: tunika15 кимоно песочная | J31: ='Юнит 16-22.02'!R45 -> 6 | K31: =J31/J$50 -> 0.24 | L31: =K31+L30 -> 0.64 | M31: =_xlfn.IFS(L31<80%,"A",L31<=95%,"B",L31>95%,"C") -> A
B32: tunika16 сетка белая | C32: ='Юнит 16-22.02'!AE46 -> 6481.0262 | D32: =C32/C$50 -> 0.24155128 | E32: =D32+E31 -> 0.80758517 | F32: =IF(AND(E32<=0),"C",IF(E32<=0.8,"A",IF(E32<=0.95,"B","C"))) -> B | G32: =VLOOKUP(B$30:B$50,I$30:M$50,5,0) -> A | I32: tunika15 кимоно бирюза | J32: ='Юнит 16-22.02'!R44 -> 4 | K32: =J32/J$50 -> 0.16 | L32: =K32+L31 -> 0.8 | M32: =_xlfn.IFS(L32<80%,"A",L32<=95%,"B",L32>95%,"C") -> B
B33: tunika09 кимоно | C33: ='Юнит 16-22.02'!AE37 -> 3432.3642 | D33: =C33/C$50 -> 0.12792603 | E33: =D33+E32 -> 0.9355112 | F33: =IF(AND(E33<=0),"C",IF(E33<=0.8,"A",IF(E33<=0.95,"B","C"))) -> B | G33: =VLOOKUP(B$30:B$50,I$30:M$50,5,0) -> B | I33: tunika09 кимоно | J33: ='Юнит 16-22.02'!R37 -> 2 | K33: =J33/J$50 -> 0.08 | L33: =K33+L32 -> 0.88 | M33: =_xlfn.IFS(L33<80%,"A",L33<=95%,"B",L33>95%,"C") -> B
B34: tunika08 черная | C34: ='Юнит 16-22.02'!AE35 -> 2861.0756 | D34: =C34/C$50 -> 0.1066338 | E34: =D34+E33 -> 1.042145 | F34: =IF(AND(E34<=0),"C",IF(E34<=0.8,"A",IF(E34<=0.95,"B","C"))) -> C | G34: =VLOOKUP(B$30:B$50,I$30:M$50,5,0) -> C | I34: tunika16 сетка черная | J34: ='Юнит 16-22.02'!R47 -> 2 | K34: =J34/J$50 -> 0.08 | L34: =K34+L33 -> 0.96 | M34: =_xlfn.IFS(L34<80%,"A",L34<=95%,"B",L34>95%,"C") -> C
B35: tunika16 сетка черная | C35: ='Юнит 16-22.02'!AE47 -> 1717.5882 | D35: =C35/C$50 -> 0.064015423 | E35: =D35+E34 -> 1.1061604 | F35: =IF(AND(E35<=0),"C",IF(E35<=0.8,"A",IF(E35<=0.95,"B","C"))) -> C | G35: =VLOOKUP(B$30:B$50,I$30:M$50,5,0) -> C | I35: tunika05 белая распашная | J35: ='Юнит 16-22.02'!R30 -> 1 | K35: =J35/J$50 -> 0.04 | L35: =K35+L34 -> 1 | M35: =_xlfn.IFS(L35<80%,"A",L35<=95%,"B",L35>95%,"C") -> C
B36: tunika05 белая распашная | C36: ='Юнит 16-22.02'!AE30 -> 662.14219 | D36: =C36/C$50 -> 0.02467839 | E36: =D36+E35 -> 1.1308388 | F36: =IF(AND(E36<=0),"C",IF(E36<=0.8,"A",IF(E36<=0.95,"B","C"))) -> C | G36: =VLOOKUP(B$30:B$50,I$30:M$50,5,0) -> C | I36: tunika08 черная | J36: ='Юнит 16-22.02'!R35 -> 1 | K36: =J36/J$50 -> 0.04 | L36: =K36+L35 -> 1.04 | M36: =_xlfn.IFS(L36<80%,"A",L36<=95%,"B",L36>95%,"C") -> C
B37: tunika02 оливковая с руч вышивкой | C37: ='Юнит 16-22.02'!AE28 -> 0 | D37: =C37/C$50 -> 0 | E37: =D37+E36 -> 1.1308388 | F37: =IF(AND(E37<=0),"C",IF(E37<=0.8,"A",IF(E37<=0.95,"B","C"))) -> C | G37: =VLOOKUP(B$30:B$50,I$30:M$50,5,0) -> C | I37: tunika02 оливковая с руч вышивкой | J37: ='Юнит 16-22.02'!R28 -> 0 | K37: =J37/J$50 -> 0 | L37: =K37+L36 -> 1.04 | M37: =_xlfn.IFS(L37<80%,"A",L37<=95%,"B",L37>95%,"C") -> C
B38: tunika06 черная | C38: ='Юнит 16-22.02'!AE32 -> 0 | D38: =C38/C$50 -> 0 | E38: =D38+E37 -> 1.1308388 | F38: =IF(AND(E38<=0),"C",IF(E38<=0.8,"A",IF(E38<=0.95,"B","C"))) -> C | G38: =VLOOKUP(B$30:B$50,I$30:M$50,5,0) -> C | I38: tunika06 белая | J38: ='Юнит 16-22.02'!R31 -> 0 | K38: =J38/J$50 -> 0 | L38: =K38+L37 -> 1.04 | M38: =_xlfn.IFS(L38<80%,"A",L38<=95%,"B",L38>95%,"C") -> C
B39: tunika08 белая | C39: ='Юнит 16-22.02'!AE34 -> 0 | D39: =C39/C$50 -> 0 | E39: =D39+E38 -> 1.1308388 | F39: =IF(AND(E39<=0),"C",IF(E39<=0.8,"A",IF(E39<=0.95,"B","C"))) -> C | G39: =VLOOKUP(B$30:B$50,I$30:M$50,5,0) -> C | I39: tunika06 черная | J39: ='Юнит 16-22.02'!R32 -> 0 | K39: =J39/J$50 -> 0 | L39: =K39+L38 -> 1.04 | M39: =_xlfn.IFS(L39<80%,"A",L39<=95%,"B",L39>95%,"C") -> C
B40: tunika12 халат белая | C40: ='Юнит 16-22.02'!AE40 -> 0 | D40: =C40/C$50 -> 0 | E40: =D40+E39 -> 1.1308388 | F40: =IF(AND(E40<=0),"C",IF(E40<=0.8,"A",IF(E40<=0.95,"B","C"))) -> C | G40: =VLOOKUP(B$30:B$50,I$30:M$50,5,0) -> C | I40: tunika07 кружево | J40: ='Юнит 16-22.02'!R33 -> 0 | K40: =J40/J$50 -> 0 | L40: =K40+L39 -> 1.04 | M40: =_xlfn.IFS(L40<80%,"A",L40<=95%,"B",L40>95%,"C") -> C
B41: tunika13 халат черная | C41: ='Юнит 16-22.02'!AE41 -> 0 | D41: =C41/C$50 -> 0 | E41: =D41+E40 -> 1.1308388 | F41: =IF(AND(E41<=0),"C",IF(E41<=0.8,"A",IF(E41<=0.95,"B","C"))) -> C | G41: =VLOOKUP(B$30:B$50,I$30:M$50,5,0) -> C | I41: tunika08 белая | J41: ='Юнит 16-22.02'!R34 -> 0 | K41: =J41/J$50 -> 0 | L41: =K41+L40 -> 1.04 | M41: =_xlfn.IFS(L41<80%,"A",L41<=95%,"B",L41>95%,"C") -> C
B42: tunika14 халат с разрезами черный | C42: ='Юнит 16-22.02'!AE43 -> 0 | D42: =C42/C$50 -> 0 | E42: =D42+E41 -> 1.1308388 | F42: =IF(AND(E42<=0),"C",IF(E42<=0.8,"A",IF(E42<=0.95,"B","C"))) -> C | G42: =VLOOKUP(B$30:B$50,I$30:M$50,5,0) -> C | I42: tunika08 зеленая | J42: ='Юнит 16-22.02'!R36 -> 0 | K42: =J42/J$50 -> 0 | L42: =K42+L41 -> 1.04 | M42: =_xlfn.IFS(L42<80%,"A",L42<=95%,"B",L42>95%,"C") -> C
B43: tunika06 белая | C43: ='Юнит 16-22.02'!AE31 -> -113.88 | D43: =C43/C$50 -> -0.0042443679 | E43: =D43+E42 -> 1.1265944 | F43: =IF(AND(E43<=0),"C",IF(E43<=0.8,"A",IF(E43<=0.95,"B","C"))) -> C | G43: =VLOOKUP(B$30:B$50,I$30:M$50,5,0) -> C | I43: tunika10 кимоно ч/б | J43: ='Юнит 16-22.02'!R38 -> 0 | K43: =J43/J$50 -> 0 | L43: =K43+L42 -> 1.04 | M43: =_xlfn.IFS(L43<80%,"A",L43<=95%,"B",L43>95%,"C") -> C
B44: tunika08 зеленая | C44: ='Юнит 16-22.02'!AE36 -> -113.88 | D44: =C44/C$50 -> -0.0042443679 | E44: =D44+E43 -> 1.1223501 | F44: =IF(AND(E44<=0),"C",IF(E44<=0.8,"A",IF(E44<=0.95,"B","C"))) -> C | G44: =VLOOKUP(B$30:B$50,I$30:M$50,5,0) -> C | I44: tunika11 халат зеленая | J44: ='Юнит 16-22.02'!R39 -> 0 | K44: =J44/J$50 -> 0 | L44: =K44+L43 -> 1.04 | M44: =_xlfn.IFS(L44<80%,"A",L44<=95%,"B",L44>95%,"C") -> C
B45: tunika10 кимоно ч/б | C45: ='Юнит 16-22.02'!AE38 -> -113.88 | D45: =C45/C$50 -> -0.0042443679 | E45: =D45+E44 -> 1.1181057 | F45: =IF(AND(E45<=0),"C",IF(E45<=0.8,"A",IF(E45<=0.95,"B","C"))) -> C | G45: =VLOOKUP(B$30:B$50,I$30:M$50,5,0) -> C | I45: tunika12 халат белая | J45: ='Юнит 16-22.02'!R40 -> 0 | K45: =J45/J$50 -> 0 | L45: =K45+L44 -> 1.04 | M45: =_xlfn.IFS(L45<80%,"A",L45<=95%,"B",L45>95%,"C") -> C
B46: tunika11 халат зеленая | C46: ='Юнит 16-22.02'!AE39 -> -113.88 | D46: =C46/C$50 -> -0.0042443679 | E46: =D46+E45 -> 1.1138613 | F46: =IF(AND(E46<=0),"C",IF(E46<=0.8,"A",IF(E46<=0.95,"B","C"))) -> C | G46: =VLOOKUP(B$30:B$50,I$30:M$50,5,0) -> C | I46: tunika13 халат черная | J46: ='Юнит 16-22.02'!R41 -> 0 | K46: =J46/J$50 -> 0 | L46: =K46+L45 -> 1.04 | M46: =_xlfn.IFS(L46<80%,"A",L46<=95%,"B",L46>95%,"C") -> C
B47: tunika07 кружево | C47: ='Юнит 16-22.02'!AE33 -> -227.76 | D47: =C47/C$50 -> -0.0084887357 | E47: =D47+E46 -> 1.1053726 | F47: =IF(AND(E47<=0),"C",IF(E47<=0.8,"A",IF(E47<=0.95,"B","C"))) -> C | G47: =VLOOKUP(B$30:B$50,I$30:M$50,5,0) -> C | I47: tunika14 халат с разрезами белая | J47: ='Юнит 16-22.02'!R42 -> 0 | K47: =J47/J$50 -> 0 | L47: =K47+L46 -> 1.04 | M47: =_xlfn.IFS(L47<80%,"A",L47<=95%,"B",L47>95%,"C") -> C
B48: tunika14 халат с разрезами белая | C48: ='Юнит 16-22.02'!AE42 -> -455.52 | D48: =C48/C$50 -> -0.016977471 | E48: =D48+E47 -> 1.0883951 | F48: =IF(AND(E48<=0),"C",IF(E48<=0.8,"A",IF(E48<=0.95,"B","C"))) -> C | G48: =VLOOKUP(B$30:B$50,I$30:M$50,5,0) -> C | I48: tunika14 халат с разрезами черный | J48: ='Юнит 16-22.02'!R43 -> 0 | K48: =J48/J$50 -> 0 | L48: =K48+L47 -> 1.04 | M48: =_xlfn.IFS(L48<80%,"A",L48<=95%,"B",L48>95%,"C") -> C
B49: tunika03 черная распашная | C49: ='Юнит 16-22.02'!AE29 -> -2371.7166 | D49: =C49/C$50 -> -0.088395134 | E49: =D49+E48 -> 1 | F49: =IF(AND(E49<=0),"C",IF(E49<=0.8,"A",IF(E49<=0.95,"B","C"))) -> C | G49: =VLOOKUP(B$30:B$50,I$30:M$50,5,0) -> C | I49: tunika03 черная распашная | J49: ='Юнит 16-22.02'!R29 -> -1 | K49: =J49/J$50 -> -0.04 | L49: =K49+L48 -> 1 | M49: =_xlfn.IFS(L49<80%,"A",L49<=95%,"B",L49>95%,"C") -> C
C50: =SUM(C30:C49) -> 26830.851 | D50: =SUM(D30:D49) -> 1 | J50: =SUM(J30:J49) -> 25 | K50: =SUM(K30:K49) -> 1

Sheet АВС 09-15.02
B2: ОЧКИ
C3: Прибыль | D3: % прибыль | E3: Доля | F3: ABC прибыль | G3: ABC кол-во | J3: Кол-во | K3: % кол-во | L3: Доля | M3: ABC кол-во
B4: черные с железкой классика | C4: ='Юнит 09-15.02'!AE3 -> 18261.877 | D4: =C4/C$26 -> 0.9050678 | E4: =D4 -> 0.9050678 | F4: =IF(AND(E4<=0),"C",IF(E4<=0.8,"A",IF(E4<=0.95,"B","C"))) -> B | G4: =VLOOKUP(B$4:B$25,I$4:M$25,5,0) -> A | I4: черные с железкой классика | J4: ='Юнит 09-15.02'!R3 -> 40 | K4: =J4/J$26 -> 0.68965517 | L4: =K4 -> 0.68965517 | M4: =_xlfn.IFS(L4<80%,"A",L4<=95%,"B",L4>95%,"C") -> A
B5: qs коричневые | C5: ='Юнит 09-15.02'!AE7 -> 2261.0319 | D5: =C5/C$26 -> 0.11205787 | E5: =D5+E4 -> 1.0171257 | F5: =IF(AND(E5<=0),"C",IF(E5<=0.8,"A",IF(E5<=0.95,"B","C"))) -> C | G5: =VLOOKUP(B$4:B$25,I$4:M$25,5,0) -> A | I5: qs коричневые | J5: ='Юнит 09-15.02'!R7 -> 5 | K5: =J5/J$26 -> 0.086206897 | L5: =K5+L4 -> 0.77586207 | M5: =_xlfn.IFS(L5<80%,"A",L5<=95%,"B",L5>95%,"C") -> A
B6: flip желтые Сул | C6: ='Юнит 09-15.02'!AE9 -> 1236.572 | D6: =C6/C$26 -> 0.061285126 | E6: =D6+E5 -> 1.0784108 | F6: =IF(AND(E6<=0),"C",IF(E6<=0.8,"A",IF(E6<=0.95,"B","C"))) -> C | G6: =VLOOKUP(B$4:B$25,I$4:M$25,5,0) -> B | I6: flip желтые Сул | J6: ='Юнит 09-15.02'!R9 -> 5 | K6: =J6/J$26 -> 0.086206897 | L6: =K6+L5 -> 0.86206897 | M6: =_xlfn.IFS(L6<80%,"A",L6<=95%,"B",L6>95%,"C") -> B
B7: qs черные | C7: ='Юнит 09-15.02'!AE4 -> 873.30156 | D7: =C7/C$26 -> 0.043281263 | E7: =D7+E6 -> 1.1216921 | F7: =IF(AND(E7<=0),"C",IF(E7<=0.8,"A",IF(E7<=0.95,"B","C"))) -> C | G7: =VLOOKUP(B$4:B$25,I$4:M$25,5,0) -> B | I7: MR8854 C2 | J7: ='Юнит 09-15.02'!R10 -> 4 | K7: =J7/J$26 -> 0.068965517 | L7: =K7+L6 -> 0.93103448 | M7: =_xlfn.IFS(L7<80%,"A",L7<=95%,"B",L7>95%,"C") -> B
B8: MR8854 C2 | C8: ='Юнит 09-15.02'!AE10 -> 827.0756 | D8: =C8/C$26 -> 0.040990281 | E8: =D8+E7 -> 1.1626823 | F8: =IF(AND(E8<=0),"C",IF(E8<=0.8,"A",IF(E8<=0.95,"B","C"))) -> C | G8: =VLOOKUP(B$4:B$25,I$4:M$25,5,0) -> B | I8: qs черные | J8: ='Юнит 09-15.02'!R4 -> 1 | K8: =J8/J$26 -> 0.017241379 | L8: =K8+L7 -> 0.94827586 | M8: =_xlfn.IFS(L8<80%,"A",L8<=95%,"B",L8>95%,"C") -> B
B9: MR 1819 корич | C9: ='Юнит 09-15.02'!AE12 -> 329.21308 | D9: =C9/C$26 -> 0.016315965 | E9: =D9+E8 -> 1.1789983 | F9: =IF(AND(E9<=0),"C",IF(E9<=0.8,"A",IF(E9<=0.95,"B","C"))) -> C | G9: =VLOOKUP(B$4:B$25,I$4:M$25,5,0) -> C | I9: qs синие | J9: ='Юнит 09-15.02'!R5 -> 1 | K9: =J9/J$26 -> 0.017241379 | L9: =K9+L8 -> 0.96551724 | M9: =_xlfn.IFS(L9<80%,"A",L9<=95%,"B",L9>95%,"C") -> C
B10: qs синие | C10: ='Юнит 09-15.02'!AE5 -> 310.95156 | D10: =C10/C$26 -> 0.015410915 | E10: =D10+E9 -> 1.1944092 | F10: =IF(AND(E10<=0),"C",IF(E10<=0.8,"A",IF(E10<=0.95,"B","C"))) -> C | G10: =VLOOKUP(B$4:B$25,I$4:M$25,5,0) -> C | I10: MR 1819 корич | J10: ='Юнит 09-15.02'!R12 -> 1 | K10: =J10/J$26 -> 0.017241379 | L10: =K10+L9 -> 0.98275862 | M10: =_xlfn.IFS(L10<80%,"A",L10<=95%,"B",L10>95%,"C") -> C
B11: MR Р1874 черн | C11: ='Юнит 09-15.02'!AE13 -> 142.4794 | D11: =C11/C$26 -> 0.0070613505 | E11: =D11+E8 -> 1.1697437 | F11: =IF(AND(E11<=0),"C",IF(E11<=0.8,"A",IF(E11<=0.95,"B","C"))) -> C | G11: =VLOOKUP(B$4:B$25,I$4:M$25,5,0) -> C | I11: MR Р1874 черн | J11: ='Юнит 09-15.02'!R13 -> 1 | K11: =J11/J$26 -> 0.017241379 | L11: =K11+L8 -> 0.96551724 | M11: =_xlfn.IFS(L11<80%,"A",L11<=95%,"B",L11>95%,"C") -> C
B12: lux1 | C12: ='Юнит 09-15.02'!AE17 -> 0 | D12: =C12/C$26 -> 0 | E12: =D12+E11 -> 1.1697437 | F12: =IF(AND(E12<=0),"C",IF(E12<=0.8,"A",IF(E12<=0.95,"B","C"))) -> C | G12: =VLOOKUP(B$4:B$25,I$4:M$25,5,0) -> C | I12: MR Р1886 черн глянец | J12: ='Юнит 09-15.02'!R15 -> 1 | K12: =J12/J$26 -> 0.017241379 | L12: =K12+L11 -> 0.98275862 | M12: =_xlfn.IFS(L12<80%,"A",L12<=95%,"B",L12>95%,"C") -> C
B13: lux2 | C13: ='Юнит 09-15.02'!AE18 -> 0 | D13: =C13/C$26 -> 0 | E13: =D13+E12 -> 1.1697437 | F13: =IF(AND(E13<=0),"C",IF(E13<=0.8,"A",IF(E13<=0.95,"B","C"))) -> C | G13: =VLOOKUP(B$4:B$25,I$4:M$25,5,0) -> C | I13: qs желтые | J13: ='Юнит 09-15.02'!R6 -> 0 | K13: =J13/J$26 -> 0 | L13: =K13+L12 -> 0.98275862 | M13: =_xlfn.IFS(L13<80%,"A",L13<=95%,"B",L13>95%,"C") -> C | P13: A | Q13: 0.8
B14: lux3 | C14: ='Юнит 09-15.02'!AE19 -> 0 | D14: =C14/C$26 -> 0 | E14: =D14+E13 -> 1.1697437 | F14: =IF(AND(E14<=0),"C",IF(E14<=0.8,"A",IF(E14<=0.95,"B","C"))) -> C | G14: =VLOOKUP(B$4:B$25,I$4:M$25,5,0) -> C | I14: th желтый Сул | J14: ='Юнит 09-15.02'!R8 -> 0 | K14: =J14/J$26 -> 0 | L14: =K14+L13 -> 0.98275862 | M14: =_xlfn.IFS(L14<80%,"A",L14<=95%,"B",L14>95%,"C") -> C | P14: B | Q14: 0.15
B15: lux5 | C15: ='Юнит 09-15.02'!AE21 -> 0 | D15: =C15/C$26 -> 0 | E15: =D15+E14 -> 1.1697437 | F15: =IF(AND(E15<=0),"C",IF(E15<=0.8,"A",IF(E15<=0.95,"B","C"))) -> C | G15: =VLOOKUP(B$4:B$25,I$4:M$25,5,0) -> C | I15: MR 1819 черн | J15: ='Юнит 09-15.02'!R11 -> 0 | K15: =J15/J$26 -> 0 | L15: =K15+L14 -> 0.98275862 | M15: =_xlfn.IFS(L15<80%,"A",L15<=95%,"B",L15>95%,"C") -> C | P15: C | Q15: 0.05
B16: lux6 | C16: ='Юнит 09-15.02'!AE22 -> 0 | D16: =C16/C$26 -> 0 | E16: =D16+E15 -> 1.1697437 | F16: =IF(AND(E16<=0),"C",IF(E16<=0.8,"A",IF(E16<=0.95,"B","C"))) -> C | G16: =VLOOKUP(B$4:B$25,I$4:M$25,5,0) -> C | I16: MR Р1874 корич | J16: ='Юнит 09-15.02'!R14 -> 0 | K16: =J16/J$26 -> 0 | L16: =K16+L15 -> 0.98275862 | M16: =_xlfn.IFS(L16<80%,"A",L16<=95%,"B",L16>95%,"C") -> C
B17: lux7 | C17: ='Юнит 09-15.02'!AE23 -> 0 | D17: =C17/C$26 -> 0 | E17: =D17+E16 -> 1.1697437 | F17: =IF(AND(E17<=0),"C",IF(E17<=0.8,"A",IF(E17<=0.95,"B","C"))) -> C | G17: =VLOOKUP(B$4:B$25,I$4:M$25,5,0) -> C | I17: MR Р1886 корич | J17: ='Юнит 09-15.02'!R16 -> 0 | K17: =J17/J$26 -> 0 | L17: =K17+L16 -> 0.98275862 | M17: =_xlfn.IFS(L17<80%,"A",L17<=95%,"B",L17>95%,"C") -> C
B18: lux8 | C18: ='Юнит 09-15.02'!AE24 -> 0 | D18: =C18/C$26 -> 0 | E18: =D18+E17 -> 1.1697437 | F18: =IF(AND(E18<=0),"C",IF(E18<=0.8,"A",IF(E18<=0.95,"B","C"))) -> C | G18: =VLOOKUP(B$4:B$25,I$4:M$25,5,0) -> C | I18: lux1 | J18: ='Юнит 09-15.02'!R17 -> 0 | K18: =J18/J$26 -> 0 | L18: =K18+L17 -> 0.98275862 | M18: =_xlfn.IFS(L18<80%,"A",L18<=95%,"B",L18>95%,"C") -> C
B19: MR Р1886 черн глянец | C19: ='Юнит 09-15.02'!AE15 -> -119.58737 | D19: =C19/C$26 -> -0.0059268098 | E19: =D19+E18 -> 1.1638169 | F19: =IF(AND(E19<=0),"C",IF(E19<=0.8,"A",IF(E19<=0.95,"B","C"))) -> C | G19: =VLOOKUP(B$4:B$25,I$4:M$25,5,0) -> C | I19: lux2 | J19: ='Юнит 09-15.02'!R18 -> 0 | K19: =J19/J$26 -> 0 | L19: =K19+L18 -> 0.98275862 | M19: =_xlfn.IFS(L19<80%,"A",L19<=95%,"B",L19>95%,"C") -> C
B20: MR 1819 черн | C20: ='Юнит 09-15.02'!AE11 -> -187.08 | D20: =C20/C$26 -> -0.0092717786 | E20: =D20+E19 -> 1.1545451 | F20: =IF(AND(E20<=0),"C",IF(E20<=0.8,"A",IF(E20<=0.95,"B","C"))) -> C | G20: =VLOOKUP(B$4:B$25,I$4:M$25,5,0) -> C | I20: lux3 | J20: ='Юнит 09-15.02'!R19 -> 0 | K20: =J20/J$26 -> 0 | L20: =K20+L19 -> 0.98275862 | M20: =_xlfn.IFS(L20<80%,"A",L20<=95%,"B",L20>95%,"C") -> C
B21: MR Р1874 корич | C21: ='Юнит 09-15.02'!AE14 -> -387.09 | D21: =C21/C$26 -> -0.019184374 | E21: =D21+E20 -> 1.1353607 | F21: =IF(AND(E21<=0),"C",IF(E21<=0.8,"A",IF(E21<=0.95,"B","C"))) -> C | G21: =VLOOKUP(B$4:B$25,I$4:M$25,5,0) -> C | I21: lux5 | J21: ='Юнит 09-15.02'!R21 -> 0 | K21: =J21/J$26 -> 0 | L21: =K21+L20 -> 0.98275862 | M21: =_xlfn.IFS(L21<80%,"A",L21<=95%,"B",L21>95%,"C") -> C
B22: th желтый Сул | C22: ='Юнит 09-15.02'!AE8 -> -425.04 | D22: =C22/C$26 -> -0.021065195 | E22: =D22+E21 -> 1.1142955 | F22: =IF(AND(E22<=0),"C",IF(E22<=0.8,"A",IF(E22<=0.95,"B","C"))) -> C | G22: =VLOOKUP(B$4:B$25,I$4:M$25,5,0) -> C | I22: lux6 | J22: ='Юнит 09-15.02'!R22 -> 0 | K22: =J22/J$26 -> 0 | L22: =K22+L21 -> 0.98275862 | M22: =_xlfn.IFS(L22<80%,"A",L22<=95%,"B",L22>95%,"C") -> C
B23: MR Р1886 корич | C23: ='Юнит 09-15.02'!AE16 -> -569.18 | D23: =C23/C$26 -> -0.028208846 | E23: =D23+E22 -> 1.0860867 | F23: =IF(AND(E23<=0),"C",IF(E23<=0.8,"A",IF(E23<=0.95,"B","C"))) -> C | G23: =VLOOKUP(B$4:B$25,I$4:M$25,5,0) -> C | I23: lux7 | J23: ='Юнит 09-15.02'!R23 -> 0 | K23: =J23/J$26 -> 0 | L23: =K23+L22 -> 0.98275862 | M23: =_xlfn.IFS(L23<80%,"A",L23<=95%,"B",L23>95%,"C") -> C
B24: lux4 | C24: ='Юнит 09-15.02'!AE20 -> -925.79033 | D24: =C24/C$26 -> -0.045882633 | E24: =D24+E23 -> 1.0402041 | F24: =IF(AND(E24<=0),"C",IF(E24<=0.8,"A",IF(E24<=0.95,"B","C"))) -> C | G24: =VLOOKUP(B$4:B$25,I$4:M$25,5,0) -> C | I24: lux8 | J24: ='Юнит 09-15.02'!R24 -> 0 | K24: =J24/J$26 -> 0 | L24: =K24+L23 -> 0.98275862 | M24: =_xlfn.IFS(L24<80%,"A",L24<=95%,"B",L24>95%,"C") -> C
B25: qs желтые | C25: ='Юнит 09-15.02'!AE6 -> -1451.3763 | D25: =C25/C$26 -> -0.071930937 | E25: =D25+E24 -> 0.96827312 | F25: =IF(AND(E25<=0),"C",IF(E25<=0.8,"A",IF(E25<=0.95,"B","C"))) -> C | G25: =VLOOKUP(B$4:B$25,I$4:M$25,5,0) -> C | I25: lux4 | J25: ='Юнит 09-15.02'!R20 -> -1 | K25: =J25/J$26 -> -0.017241379 | L25: =K25+L24 -> 0.96551724 | M25: =_xlfn.IFS(L25<80%,"A",L25<=95%,"B",L25>95%,"C") -> C
C26: =SUM(C4:C25) -> 20177.358 | D26: =SUM(D4:D25) -> 1 | J26: =SUM(J4:J25) -> 58 | K26: =SUM(K4:K25) -> 1
B28: ТУНИКИ
C29: Прибыль | D29: % прибыль | E29: Доля | F29: ABC прибыль | G29: ABC кол-во | J29: Кол-во | K29: % кол-во | L29: Доля | M29: ABC кол-во
B30: tunika15 кимоно бирюза | C30: ='Юнит 09-15.02'!AE44 -> 7055.3882 | D30: =C30/C$50 -> 0.39472445 | E30: =D30 -> 0.39472445 | F30: =IF(AND(E30<=0),"C",IF(E30<=0.8,"A",IF(E30<=0.95,"B","C"))) -> A | G30: =VLOOKUP(B$30:B$50,I$30:M$50,5,0) -> A | I30: tunika15 кимоно бирюза | J30: ='Юнит 09-15.02'!R44 -> 7 | K30: =J30/J$50 -> 0.35 | L30: =K30 -> 0.35 | M30: =_xlfn.IFS(L30<80%,"A",L30<=95%,"B",L30>95%,"C") -> A
B31: tunika09 кимоно | C31: ='Юнит 09-15.02'!AE37 -> 5645.122 | D31: =C31/C$50 -> 0.31582495 | E31: =D31+E30 -> 0.7105494 | F31: =IF(AND(E31<=0),"C",IF(E31<=0.8,"A",IF(E31<=0.95,"B","C"))) -> A | G31: =VLOOKUP(B$30:B$50,I$30:M$50,5,0) -> A | I31: tunika15 кимоно песочная | J31: ='Юнит 09-15.02'!R45 -> 4 | K31: =J31/J$50 -> 0.2 | L31: =K31+L30 -> 0.55 | M31: =_xlfn.IFS(L31<80%,"A",L31<=95%,"B",L31>95%,"C") -> A
B32: tunika15 кимоно песочная | C32: ='Юнит 09-15.02'!AE45 -> 4691.1462 | D32: =C32/C$50 -> 0.26245332 | E32: =D32+E31 -> 0.97300272 | F32: =IF(AND(E32<=0),"C",IF(E32<=0.8,"A",IF(E32<=0.95,"B","C"))) -> C | G32: =VLOOKUP(B$30:B$50,I$30:M$50,5,0) -> A | I32: tunika09 кимоно | J32: ='Юнит 09-15.02'!R37 -> 3 | K32: =J32/J$50 -> 0.15 | L32: =K32+L31 -> 0.7 | M32: =_xlfn.IFS(L32<80%,"A",L32<=95%,"B",L32>95%,"C") -> A
B33: tunika03 черная распашная | C33: ='Юнит 09-15.02'!AE29 -> 1950.7439 | D33: =C33/C$50 -> 0.10913734 | E33: =D33+E32 -> 1.0821401 | F33: =IF(AND(E33<=0),"C",IF(E33<=0.8,"A",IF(E33<=0.95,"B","C"))) -> C | G33: =VLOOKUP(B$30:B$50,I$30:M$50,5,0) -> B | I33: tunika07 кружево | J33: ='Юнит 09-15.02'!R33 -> 2 | K33: =J33/J$50 -> 0.1 | L33: =K33+L32 -> 0.8 | M33: =_xlfn.IFS(L33<80%,"A",L33<=95%,"B",L33>95%,"C") -> B
B34: tunika07 кружево | C34: ='Юнит 09-15.02'!AE33 -> 1741.132 | D34: =C34/C$50 -> 0.097410283 | E34: =D34+E33 -> 1.1795503 | F34: =IF(AND(E34<=0),"C",IF(E34<=0.8,"A",IF(E34<=0.95,"B","C"))) -> C | G34: =VLOOKUP(B$30:B$50,I$30:M$50,5,0) -> B | I34: tunika14 халат с разрезами белая | J34: ='Юнит 09-15.02'!R42 -> 2 | K34: =J34/J$50 -> 0.1 | L34: =K34+L33 -> 0.9 | M34: =_xlfn.IFS(L34<80%,"A",L34<=95%,"B",L34>95%,"C") -> B
B35: tunika06 белая | C35: ='Юнит 09-15.02'!AE31 -> 1628.7063 | D35: =C35/C$50 -> 0.091120459 | E35: =D35+E34 -> 1.2706708 | F35: =IF(AND(E35<=0),"C",IF(E35<=0.8,"A",IF(E35<=0.95,"B","C"))) -> C | G35: =VLOOKUP(B$30:B$50,I$30:M$50,5,0) -> C | I35: tunika03 черная распашная | J35: ='Юнит 09-15.02'!R29 -> 1 | K35: =J35/J$50 -> 0.05 | L35: =K35+L34 -> 0.95 | M35: =_xlfn.IFS(L35<80%,"A",L35<=95%,"B",L35>95%,"C") -> B
B36: tunika14 халат с разрезами белая | C36: ='Юнит 09-15.02'!AE42 -> 1576.2627 | D36: =C36/C$50 -> 0.088186419 | E36: =D36+E35 -> 1.3588572 | F36: =IF(AND(E36<=0),"C",IF(E36<=0.8,"A",IF(E36<=0.95,"B","C"))) -> C | G36: =VLOOKUP(B$30:B$50,I$30:M$50,5,0) -> B | I36: tunika06 белая | J36: ='Юнит 09-15.02'!R31 -> 1 | K36: =J36/J$50 -> 0.05 | L36: =K36+L35 -> 1 | M36: =_xlfn.IFS(L36<80%,"A",L36<=95%,"B",L36>95%,"C") -> C
B37: tunika02 оливковая с руч вышивкой | C37: ='Юнит 09-15.02'!AE28 -> 0 | D37: =C37/C$50 -> 0 | E37: =D37+E36 -> 1.3588572 | F37: =IF(AND(E37<=0),"C",IF(E37<=0.8,"A",IF(E37<=0.95,"B","C"))) -> C | G37: =VLOOKUP(B$30:B$50,I$30:M$50,5,0) -> C | I37: tunika16 сетка белая | J37: ='Юнит 09-15.02'!R46 -> 1 | K37: =J37/J$50 -> 0.05 | L37: =K37+L36 -> 1.05 | M37: =_xlfn.IFS(L37<80%,"A",L37<=95%,"B",L37>95%,"C") -> C
B38: tunika06 черная | C38: ='Юнит 09-15.02'!AE32 -> 0 | D38: =C38/C$50 -> 0 | E38: =D38+E37 -> 1.3588572 | F38: =IF(AND(E38<=0),"C",IF(E38<=0.8,"A",IF(E38<=0.95,"B","C"))) -> C | G38: =VLOOKUP(B$30:B$50,I$30:M$50,5,0) -> C | I38: tunika02 оливковая с руч вышивкой | J38: ='Юнит 09-15.02'!R28 -> 0 | K38: =J38/J$50 -> 0 | L38: =K38+L37 -> 1.05 | M38: =_xlfn.IFS(L38<80%,"A",L38<=95%,"B",L38>95%,"C") -> C
B39: tunika08 белая | C39: ='Юнит 09-15.02'!AE34 -> 0 | D39: =C39/C$50 -> 0 | E39: =D39+E38 -> 1.3588572 | F39: =IF(AND(E39<=0),"C",IF(E39<=0.8,"A",IF(E39<=0.95,"B","C"))) -> C | G39: =VLOOKUP(B$30:B$50,I$30:M$50,5,0) -> C | I39: tunika05 белая распашная | J39: ='Юнит 09-15.02'!R30 -> 0 | K39: =J39/J$50 -> 0 | L39: =K39+L38 -> 1.05 | M39: =_xlfn.IFS(L39<80%,"A",L39<=95%,"B",L39>95%,"C") -> C
B40: tunika08 черная | C40: ='Юнит 09-15.02'!AE35 -> 0 | D40: =C40/C$50 -> 0 | E40: =D40+E39 -> 1.3588572 | F40: =IF(AND(E40<=0),"C",IF(E40<=0.8,"A",IF(E40<=0.95,"B","C"))) -> C | G40: =VLOOKUP(B$30:B$50,I$30:M$50,5,0) -> C | I40: tunika06 черная | J40: ='Юнит 09-15.02'!R32 -> 0 | K40: =J40/J$50 -> 0 | L40: =K40+L39 -> 1.05 | M40: =_xlfn.IFS(L40<80%,"A",L40<=95%,"B",L40>95%,"C") -> C
B41: tunika11 халат зеленая | C41: ='Юнит 09-15.02'!AE39 -> 0 | D41: =C41/C$50 -> 0 | E41: =D41+E40 -> 1.3588572 | F41: =IF(AND(E41<=0),"C",IF(E41<=0.8,"A",IF(E41<=0.95,"B","C"))) -> C | G41: =VLOOKUP(B$30:B$50,I$30:M$50,5,0) -> C | I41: tunika08 белая | J41: ='Юнит 09-15.02'!R34 -> 0 | K41: =J41/J$50 -> 0 | L41: =K41+L40 -> 1.05 | M41: =_xlfn.IFS(L41<80%,"A",L41<=95%,"B",L41>95%,"C") -> C
B42: tunika12 халат белая | C42: ='Юнит 09-15.02'!AE40 -> 0 | D42: =C42/C$50 -> 0 | E42: =D42+E41 -> 1.3588572 | F42: =IF(AND(E42<=0),"C",IF(E42<=0.8,"A",IF(E42<=0.95,"B","C"))) -> C | G42: =VLOOKUP(B$30:B$50,I$30:M$50,5,0) -> C | I42: tunika08 черная | J42: ='Юнит 09-15.02'!R35 -> 0 | K42: =J42/J$50 -> 0 | L42: =K42+L41 -> 1.05 | M42: =_xlfn.IFS(L42<80%,"A",L42<=95%,"B",L42>95%,"C") -> C
B43: tunika13 халат черная | C43: ='Юнит 09-15.02'!AE41 -> 0 | D43: =C43/C$50 -> 0 | E43: =D43+E42 -> 1.3588572 | F43: =IF(AND(E43<=0),"C",IF(E43<=0.8,"A",IF(E43<=0.95,"B","C"))) -> C | G43: =VLOOKUP(B$30:B$50,I$30:M$50,5,0) -> C | I43: tunika08 зеленая | J43: ='Юнит 09-15.02'!R36 -> 0 | K43: =J43/J$50 -> 0 | L43: =K43+L42 -> 1.05 | M43: =_xlfn.IFS(L43<80%,"A",L43<=95%,"B",L43>95%,"C") -> C
B44: tunika05 белая распашная | C44: ='Юнит 09-15.02'!AE30 -> -113.88 | D44: =C44/C$50 -> -0.0063711902 | E44: =D44+E43 -> 1.352486 | F44: =IF(AND(E44<=0),"C",IF(E44<=0.8,"A",IF(E44<=0.95,"B","C"))) -> C | G44: =VLOOKUP(B$30:B$50,I$30:M$50,5,0) -> C | I44: tunika11 халат зеленая | J44: ='Юнит 09-15.02'!R39 -> 0 | K44: =J44/J$50 -> 0 | L44: =K44+L43 -> 1.05 | M44: =_xlfn.IFS(L44<80%,"A",L44<=95%,"B",L44>95%,"C") -> C
B45: tunika14 халат с разрезами черный | C45: ='Юнит 09-15.02'!AE43 -> -113.88 | D45: =C45/C$50 -> -0.0063711902 | E45: =D45+E44 -> 1.3461148 | F45: =IF(AND(E45<=0),"C",IF(E45<=0.8,"A",IF(E45<=0.95,"B","C"))) -> C | G45: =VLOOKUP(B$30:B$50,I$30:M$50,5,0) -> C | I45: tunika12 халат белая | J45: ='Юнит 09-15.02'!R40 -> 0 | K45: =J45/J$50 -> 0 | L45: =K45+L44 -> 1.05 | M45: =_xlfn.IFS(L45<80%,"A",L45<=95%,"B",L45>95%,"C") -> C
B46: tunika08 зеленая | C46: ='Юнит 09-15.02'!AE36 -> -227.76 | D46: =C46/C$50 -> -0.01274238 | E46: =D46+E45 -> 1.3333725 | F46: =IF(AND(E46<=0),"C",IF(E46<=0.8,"A",IF(E46<=0.95,"B","C"))) -> C | G46: =VLOOKUP(B$30:B$50,I$30:M$50,5,0) -> C | I46: tunika13 халат черная | J46: ='Юнит 09-15.02'!R41 -> 0 | K46: =J46/J$50 -> 0 | L46: =K46+L45 -> 1.05 | M46: =_xlfn.IFS(L46<80%,"A",L46<=95%,"B",L46>95%,"C") -> C
B47: tunika16 сетка черная | C47: ='Юнит 09-15.02'!AE47 -> -227.76 | D47: =C47/C$50 -> -0.01274238 | E47: =D47+E46 -> 1.3206301 | F47: =IF(AND(E47<=0),"C",IF(E47<=0.8,"A",IF(E47<=0.95,"B","C"))) -> C | G47: =VLOOKUP(B$30:B$50,I$30:M$50,5,0) -> C | I47: tunika14 халат с разрезами черный | J47: ='Юнит 09-15.02'!R43 -> 0 | K47: =J47/J$50 -> 0 | L47: =K47+L46 -> 1.05 | M47: =_xlfn.IFS(L47<80%,"A",L47<=95%,"B",L47>95%,"C") -> C
B48: tunika10 кимоно ч/б | C48: ='Юнит 09-15.02'!AE38 -> -1425.9352 | D48: =C48/C$50 -> -0.079776117 | E48: =D48+E47 -> 1.240854 | F48: =IF(AND(E48<=0),"C",IF(E48<=0.8,"A",IF(E48<=0.95,"B","C"))) -> C | G48: =VLOOKUP(B$30:B$50,I$30:M$50,5,0) -> C | I48: tunika16 сетка черная | J48: ='Юнит 09-15.02'!R47 -> 0 | K48: =J48/J$50 -> 0 | L48: =K48+L47 -> 1.05 | M48: =_xlfn.IFS(L48<80%,"A",L48<=95%,"B",L48>95%,"C") -> C
B49: tunika16 сетка белая | C49: ='Юнит 09-15.02'!AE46 -> -4305.0747 | D49: =C49/C$50 -> -0.24085396 | E49: =D49+E48 -> 1 | F49: =IF(AND(E49<=0),"C",IF(E49<=0.8,"A",IF(E49<=0.95,"B","C"))) -> C | G49: =VLOOKUP(B$30:B$50,I$30:M$50,5,0) -> C | I49: tunika10 кимоно ч/б | J49: ='Юнит 09-15.02'!R38 -> -1 | K49: =J49/J$50 -> -0.05 | L49: =K49+L48 -> 1 | M49: =_xlfn.IFS(L49<80%,"A",L49<=95%,"B",L49>95%,"C") -> C
C50: =SUM(C30:C49) -> 17874.211 | D50: =SUM(D30:D49) -> 1 | J50: =SUM(J30:J49) -> 20 | K50: =SUM(K30:K49) -> 1

Sheet АВС 02-08.02
B2: ОЧКИ
C3: Прибыль | D3: % прибыль | E3: Доля | F3: ABC прибыль | G3: ABC кол-во | J3: Кол-во | K3: % кол-во | L3: Доля | M3: ABC кол-во
