Workbook

Sheet Динамика показатели
B1: Неделя | C1: 52 | D1: 51 | E1: 50 | F1: 49 | G1: 48 | H1: 47 | I1: 46 | J1: 45 | K1: 44 | L1: 43 | M1: 42 | N1: 41 | O1: 40
B2: ОЧКИ
B3: Логистика | C3: ='Дашборд 22-31.12'!$G$19 -> 0.099636126 | D3: ='Дашборд 15-21.12'!$G$19 -> 0.12768273 | E3: ='Дашборд 08-14.12'!$G$19 -> 0.11649218 | F3: ='Дашборд 01-07.12'!$G$19 -> 0.10242165 | G3: ='Дашборд 24-30.11'!$G$19 -> 0.11386342 | H3: ='Дашборд 17-23.11'!$G$19 -> 0.11274964 | I3: ='Дашборд 10-16.11'!$G$19 -> 0.073365321 | J3: ='Дашборд 03-09.11'!$G$19 -> 0.084928063 | K3: ='Дашборд 27.10-02.11'!$G$19 -> 0.064888889 | L3: ='Дашборд 20-26.10'!$G$17 -> 0.12556256 | M3: ='Дашборд 13-19.10'!$G$17 -> 0.15547938 | N3: ='Дашборд 06-12.10'!G17 -> 0.089603283 | O3: ='Дашборд 01-05.10'!G17 -> 0.086414947
B4: Реклама | C4: ='Дашборд 22-31.12'!$G$20 -> 0.32953964 | D4: ='Дашборд 15-21.12'!$G$20 -> 0.34210081 | E4: ='Дашборд 08-14.12'!$G$20 -> 0.18201157 | F4: ='Дашборд 01-07.12'!$G$20 -> 0.15322395 | G4: ='Дашборд 24-30.11'!$G$20 -> 0.4273338 | H4: ='Дашборд 17-23.11'!$G$20 -> 0.56864193 | I4: ='Дашборд 10-16.11'!$G$20 -> 0.63833041 | J4: ='Дашборд 03-09.11'!$G$20 -> 0.74072085 | K4: ='Дашборд 27.10-02.11'!$G$20 -> 0.69204075 | L4: ='Дашборд 20-26.10'!$G$18 -> 0.69204481 | M4: ='Дашборд 13-19.10'!$G$18 -> 0.55619483 | N4: ='Дашборд 06-12.10'!G18 -> 1.0468865 | O4: ='Дашборд 01-05.10'!G18 -> 0.64043644
B5: Возвраты | C5: ='Дашборд 22-31.12'!$G$22 -> 0.039055874 | D5: ='Дашборд 15-21.12'!$G$22 -> 0.055486468 | E5: ='Дашборд 08-14.12'!$G$22 -> 0.067593769 | F5: ='Дашборд 01-07.12'!$G$22 -> 0 | G5: ='Дашборд 24-30.11'!$G$22 -> 0.10751985 | H5: ='Дашборд 17-23.11'!$G$22 -> 0.058502071 | I5: ='Дашборд 10-16.11'!$G$22 -> 0.033727313 | J5: ='Дашборд 03-09.11'!$G$22 -> 0 | K5: ='Дашборд 27.10-02.11'!$G$22 -> 0 | L5: ='Дашборд 20-26.10'!$G$20 -> 0 | M5: ='Дашборд 13-19.10'!$G$20 -> 0 | N5: ='Дашборд 06-12.10'!G20 -> 0.048796357 | O5: ='Дашборд 01-05.10'!G20 -> 0.13485795
B6: Комиссия | C6: ='Дашборд 22-31.12'!$G$23 -> 0.43 | D6: ='Дашборд 15-21.12'!$G$23 -> 0.43 | E6: ='Дашборд 08-14.12'!$G$23 -> 0.43 | F6: ='Дашборд 01-07.12'!$G$23 -> 0.43 | G6: ='Дашборд 24-30.11'!$G$23 -> 0.43 | H6: ='Дашборд 17-23.11'!$G$23 -> 0.42795259 | I6: ='Дашборд 10-16.11'!$G$23 -> 0.41578228 | J6: ='Дашборд 03-09.11'!$G$23 -> 0.38 | K6: ='Дашборд 27.10-02.11'!$G$23 -> 0.35771457 | L6: ='Дашборд 20-26.10'!$G$21 -> 0.33486049 | M6: ='Дашборд 13-19.10'!$G$21 -> 0.29973018 | N6: ='Дашборд 06-12.10'!G21 -> 0.26126582 | O6: ='Дашборд 01-05.10'!G21 -> 0.25220142
B7: Маржинальность | C7: ='Дашборд 22-31.12'!$G$25 -> -0.11642303 | D7: ='Дашборд 15-21.12'!$G$25 -> -1.0579162 | E7: ='Дашборд 08-14.12'!$G$25 -> 0.24679927 | F7: ='Дашборд 01-07.12'!$G$25 -> 2.0890589 | G7: ='Дашборд 24-30.11'!$G$25 -> -1.0637454 | H7: ='Дашборд 17-23.11'!$G$25 -> -2.7480703 | I7: ='Дашборд 10-16.11'!$G$25 -> -3.8926561 | J7: ='Дашборд 03-09.11'!$G$25 -> -5.0291455 | K7: ='Дашборд 27.10-02.11'!$G$25 -> -0.65630134 | L7: ='Дашборд 20-26.10'!$G$23 -> -2.5798194 | M7: ='Дашборд 13-19.10'!$G$23 -> 4.0584498 | N7: ='Дашборд 06-12.10'!G23 -> 0.29139814 | O7: ='Дашборд 01-05.10'!G23 -> -1.1880959
B8: Рентабельность | C8: ='Дашборд 22-31.12'!$G$26 -> -0.011163575 | D8: ='Дашборд 15-21.12'!$G$26 -> -0.10426806 | E8: ='Дашборд 08-14.12'!$G$26 -> 0.022814908 | F8: ='Дашборд 01-07.12'!$G$26 -> 0.1855935 | G8: ='Дашборд 24-30.11'!$G$26 -> -0.090846166 | H8: ='Дашборд 17-23.11'!$G$26 -> -0.23673668 | I8: ='Дашборд 10-16.11'!$G$26 -> -0.35667142 | J8: ='Дашборд 03-09.11'!$G$26 -> -0.49810247 | K8: ='Дашборд 27.10-02.11'!$G$26 -> -0.13668589 | L8: ='Дашборд 20-26.10'!$G$24 -> -0.38894231 | M8: ='Дашборд 13-19.10'!$G$24 -> 0.61004204 | N8: ='Дашборд 06-12.10'!G24 -> 0.044814921 | O8: ='Дашборд 01-05.10'!G24 -> -0.23230452
B9: Прибыль | C9: ='Дашборд 22-31.12'!$E$16 -> -1492.57 | D9: ='Дашборд 15-21.12'!$E$16 -> -6018.6652 | E9: ='Дашборд 08-14.12'!$E$16 -> 1272.7068 | F9: ='Дашборд 01-07.12'!$E$16 -> 16113.413 | G9: ='Дашборд 24-30.11'!$E$16 -> -4585.5511 | H9: ='Дашборд 17-23.11'!$E$16 -> -11624.008 | I9: ='Дашборд 10-16.11'!$E$16 -> -13938.006 | J9: ='Дашборд 03-09.11'!$E$16 -> -7131.8312 | K9: ='Дашборд 27.10-02.11'!$E$16 -> -7332.4751 | L9: ='Дашборд 20-26.10'!$E$14 -> -6913.8386 | M9: ='Дашборд 13-19.10'!$E$14 -> 11033.22 | N9: ='Дашборд 06-12.10'!E14 -> 1048.3106 | O9: ='Дашборд 01-05.10'!E14 -> -6564.6933
B10: ТУНИКИ
B11: Логистика | C11: ='Дашборд 22-31.12'!$M$19 -> #DIV/0! | D11: ='Дашборд 15-21.12'!$M$19 -> 0.093010769 | E11: ='Дашборд 08-14.12'!$M$19 -> 0.094414944 | F11: ='Дашборд 01-07.12'!$M$19 -> -0.17600545 | G11: ='Дашборд 24-30.11'!$M$19 -> 0.15342 | H11: ='Дашборд 17-23.11'!$M$19 -> 0.19407336 | I11: ='Дашборд 10-16.11'!$M$19 -> 0.085996663 | J11: ='Дашборд 03-09.11'!$M$19 -> 0.091958599 | K11: ='Дашборд 27.10-02.11'!$M$19 -> 0.047370828 | L11: ='Дашборд 20-26.10'!$M$17 -> 0.069799063 | M11: ='Дашборд 13-19.10'!$M$17 -> 0.062033314 | N11: ='Дашборд 06-12.10'!M17 -> 0.076712329 | O11: ='Дашборд 01-05.10'!M17 -> 0.034773969
B12: Реклама | C12: ='Дашборд 22-31.12'!$M$20 -> #DIV/0! | D12: ='Дашборд 15-21.12'!$M$20 -> 0.13809151 | E12: ='Дашборд 08-14.12'!$M$20 -> 0.087279936 | F12: ='Дашборд 01-07.12'!$M$20 -> -0.041702373 | G12: ='Дашборд 24-30.11'!$M$20 -> 0.19972316 | H12: ='Дашборд 17-23.11'!$M$20 -> 0.32442005 | I12: ='Дашборд 10-16.11'!$M$20 -> 0.23358537 | J12: ='Дашборд 03-09.11'!$M$20 -> 0.3694242 | K12: ='Дашборд 27.10-02.11'!$M$20 -> 0.24762288 | L12: ='Дашборд 20-26.10'!$M$18 -> 0.28593184 | M12: ='Дашборд 13-19.10'!$M$18 -> 0.23810065 | N12: ='Дашборд 06-12.10'!M18 -> 0.42773008 | O12: ='Дашборд 01-05.10'!M18 -> 0.22476519
B13: Возвраты | C13: ='Дашборд 22-31.12'!$M$22 -> #DIV/0! | D13: ='Дашборд 15-21.12'!$M$22 -> 0.32150313 | E13: ='Дашборд 08-14.12'!$M$22 -> 0 | F13: ='Дашборд 01-07.12'!$M$22 -> 1.8461538 | G13: ='Дашборд 24-30.11'!$M$22 -> 0.5 | H13: ='Дашборд 17-23.11'!$M$22 -> 0.41278895 | I13: ='Дашборд 10-16.11'!$M$22 -> 0.21759772 | J13: ='Дашборд 03-09.11'!$M$22 -> 0.43621826 | K13: ='Дашборд 27.10-02.11'!$M$22 -> 0.10258515 | L13: ='Дашборд 20-26.10'!$M$20 -> 0.26504553 | M13: ='Дашборд 13-19.10'!$M$20 -> 0.16951174 | N13: ='Дашборд 06-12.10'!M20 -> 0.076524264 | O13: ='Дашборд 01-05.10'!M20 -> 0.083959044
B14: Комиссия | C14: ='Дашборд 22-31.12'!$M$23 -> #DIV/0! | D14: ='Дашборд 15-21.12'!$M$23 -> 0.43 | E14: ='Дашборд 08-14.12'!$M$23 -> 0.43 | F14: ='Дашборд 01-07.12'!$M$23 -> 0.43 | G14: ='Дашборд 24-30.11'!$M$23 -> 0.43 | H14: ='Дашборд 17-23.11'!$M$23 -> 0.46514826 | I14: ='Дашборд 10-16.11'!$M$23 -> 0.43 | J14: ='Дашборд 03-09.11'!$M$23 -> 0.38 | K14: ='Дашборд 27.10-02.11'!$M$23 -> 0.36710928 | L14: ='Дашборд 20-26.10'!$M$21 -> 0.3121257 | M14: ='Дашборд 13-19.10'!$M$21 -> 0.26984328 | N14: ='Дашборд 06-12.10'!M21 -> 0.24 | O14: ='Дашборд 01-05.10'!M21 -> 0.24
B15: Маржинальность | C15: ='Дашборд 22-31.12'!$M$25 -> #DIV/0! | D15: ='Дашборд 15-21.12'!$M$25 -> 2.1118417 | E15: ='Дашборд 08-14.12'!$M$25 -> 0.68505138 | F15: ='Дашборд 01-07.12'!$M$25 -> 6.1648125 | G15: ='Дашборд 24-30.11'!$M$25 -> 0.97949131 | H15: ='Дашборд 17-23.11'!$M$25 -> -0.95935662 | I15: ='Дашборд 10-16.11'!$M$25 -> 0.87332767 | J15: ='Дашборд 03-09.11'!$M$25 -> 0.08683085 | K15: ='Дашборд 27.10-02.11'!$M$25 -> 1.2618752 | L15: ='Дашборд 20-26.10'!$M$23 -> 0.37676652 | M15: ='Дашборд 13-19.10'!$M$23 -> 0.78107774 | N15: ='Дашборд 06-12.10'!M23 -> 0.151625 | O15: ='Дашборд 01-05.10'!M23 -> 1.1157134
B16: Рентабельность | C16: ='Дашборд 22-31.12'!$M$26 -> #DIV/0! | D16: ='Дашборд 15-21.12'!$M$26 -> 0.22320542 | E16: ='Дашборд 08-14.12'!$M$26 -> 0.15379854 | F16: ='Дашборд 01-07.12'!$M$26 -> 0.66916237 | G16: ='Дашборд 24-30.11'!$M$26 -> 0.10235684 | H16: ='Дашборд 17-23.11'!$M$26 -> -0.1500834 | I16: ='Дашборд 10-16.11'!$M$26 -> 0.11208058 | J16: ='Дашборд 03-09.11'!$M$26 -> 0.011873566 | K16: ='Дашборд 27.10-02.11'!$M$26 -> 0.17365982 | L16: ='Дашборд 20-26.10'!$M$24 -> 0.0881579 | M16: ='Дашборд 13-19.10'!$M$24 -> 0.1841977 | N16: ='Дашборд 06-12.10'!M24 -> 0.03233055 | O16: ='Дашборд 01-05.10'!M24 -> 0.25864266
B17: Прибыль | C17: ='Дашборд 22-31.12'!$K$16 -> -284.7 | D17: ='Дашборд 15-21.12'!$K$16 -> 1450.8352 | E17: ='Дашборд 08-14.12'!$K$16 -> 1309.1332 | F17: ='Дашборд 01-07.12'!$K$16 -> -3680.3931 | G17: ='Дашборд 24-30.11'!$K$16 -> 614.14105 | H17: ='Дашборд 17-23.11'!$K$16 -> -1174.2525 | I17: ='Дашборд 10-16.11'!$K$16 -> 2216.5056 | J17: ='Дашборд 03-09.11'!$K$16 -> 238.61118 | K17: ='Дашборд 27.10-02.11'!$K$16 -> 7220.2151 | L17: ='Дашборд 20-26.10'!$K$14 -> 2334.0686 | M17: ='Дашборд 13-19.10'!$K$14 -> 8979.2696 | N17: ='Дашборд 06-12.10'!K14 -> 1439.6794 | O17: ='Дашборд 01-05.10'!K14 -> 10412.953

Sheet Динамика финансы
A1: Период | D1: Дата поступления дс | E1: Итого к перечислению на счет, руб | F1: шт. | I1: Выручка | L1: Себестоимость продаж | M1: Логистика | N1: Комиссия | O1: Хранение | P1: Платная приемка | Q1: Штрафы | R1: Реклама Ozon | S1: Прочее | T1: Доп. услуги | U1: Услуги FBO | V1: Компенсировано | W1: Прочие начисления | X1: Налог | Y1: Итого | Z1: Итог месяц | AA1: % Cебестоимости | AB1: Маржинальность, % | AC1: Рентабельность, % | AD1: Доля рекламы, % | AF1: Данные для построения диаграмм
A2: Месяц | B2: Даты | C2: Нед | F2: Заказы | G2: Продажи | H2: Возвраты | I2: Продажи | J2: Возвраты | K2: Общая | AF2: Нед | AG2: По магазину | AH2: По очкам | AI2: По туникам
A3: Август | B3: 01-31.08 очки | E3: =K3-SUM(M3:U3)+V3+W3 -> 1314.45 | F3: =АВГУСТ!K$24 -> 19 | G3: =АВГУСТ!P$24 -> 5 | H3: =АВГУСТ!Q$24 -> 0 | I3: =АВГУСТ!S$24 -> 8513 | J3: =АВГУСТ!T$24 -> 0 | K3: =I3+J3 -> 8513 | L3: =АВГУСТ!W$24 -> 649.38 | M3: =АВГУСТ!Z$24 -> 506 | N3: =АВГУСТ!X$24 -> 1702.6 | R3: =АВГУСТ!AA$24 -> 15668.72 | S3: 0 | T3: 284.73 | U3: 15426.5 | W3: 26390 | X3: =(K3)*0.01 -> 85.13 | Y3: =K3-SUM(M3:U3)-L3-X3+V3+W3 -> 579.94 | Z3: =SUM(Y3:Y4) -> 579.94 | AA3: =L3/K3 -> 0.076280982 | AB3: =Y3/L3 -> 0.89306723 | AC3: =Y3/K3 -> 0.068124046 | AD3: =R3/K3 -> 1.8405638 | AF3: август | AG3: =(K3+K4)/1000 -> 8.513 | AH3: =K3/1000 -> 8.513 | AI3: =K4/1000 -> 0
B4: 01-31.08 туники | E4: =K4-SUM(M4:U4)+V4+W4 -> 0 | F4: =АВГУСТ!K$47 -> 0 | G4: =АВГУСТ!P$47 -> 0 | H4: =АВГУСТ!Q$47 -> 0 | I4: =АВГУСТ!S$47 -> 0 | J4: =АВГУСТ!T$47 -> 0 | K4: =I4+J4 -> 0 | L4: =АВГУСТ!W$47 -> 0 | M4: =АВГУСТ!Z$47 -> 0 | N4: =АВГУСТ!X$47 -> 0 | R4: =АВГУСТ!AA$47 -> 0 | X4: =(K4)*0.01 -> 0 | Y4: =K4-SUM(M4:U4)-L4-X4+V4+W4 -> 0 | AA4: =L4/K4 -> #DIV/0! | AB4: =Y4/L4 -> #DIV/0! | AC4: =Y4/K4 -> #DIV/0! | AD4: =R4/K4 -> #DIV/0! | AF4: сентябрь | AG4: =(K5+K6)/1000 -> 164.682 | AH4: =K5/1000 -> 133.332 | AI4: =K6/1000 -> 31.35
A5: Сентябрь | B5: 01-30.09 очки | E5: =K5-SUM(M5:U5)+V5+W5 -> 59471.661 | F5: =СЕНТЯБРЬ!K$24 -> 197 | G5: =СЕНТЯБРЬ!P$24 -> 108 | H5: =СЕНТЯБРЬ!Q$24 -> 5 | I5: =СЕНТЯБРЬ!S$24 -> 140000 | J5: =СЕНТЯБРЬ!T$24 -> -6668 | K5: =I5+J5 -> 133332 | L5: =СЕНТЯБРЬ!W$24 -> 17238.88 | M5: =СЕНТЯБРЬ!Z$24 -> 10852 | N5: =СЕНТЯБРЬ!X$24 -> 28418.52 | R5: =СЕНТЯБРЬ!AA$24 -> 94178.709 | S5: 10 | T5: 3767.91 | U5: 14633.2 | W5: 78000 | X5: =(K5)*0.01 -> 1333.32 | Y5: =K5-SUM(M5:U5)-L5-X5+V5+W5 -> 40899.461 | Z5: =SUM(Y5:Y6) -> 47356.31 | AA5: =L5/K5 -> 0.12929289 | AB5: =Y5/L5 -> 2.3725126 | AC5: =Y5/K5 -> 0.30674902 | AD5: =R5/K5 -> 0.70634738 | AF5: 40 | AG5: =(K7+K8)/1000 -> 68.519 | AH5: =K7/1000 -> 28.259 | AI5: =K8/1000 -> 40.26
B6: 01-30.09 туники | E6: =K6-SUM(M6:U6)+V6+W6 -> 13757.349 | F6: =СЕНТЯБРЬ!K$47 -> 42 | G6: =СЕНТЯБРЬ!P$47 -> 10 | H6: =СЕНТЯБРЬ!Q$47 -> 1 | I6: =СЕНТЯБРЬ!S$47 -> 35040 | J6: =СЕНТЯБРЬ!T$47 -> -3690 | K6: =I6+J6 -> 31350 | L6: =СЕНТЯБРЬ!W$47 -> 6987 | M6: =СЕНТЯБРЬ!Z$47 -> 2408 | N6: =СЕНТЯБРЬ!X$47 -> 6464.4 | R6: =СЕНТЯБРЬ!AA$47 -> 8720.2508 | X6: =(K6)*0.01 -> 313.5 | Y6: =K6-SUM(M6:U6)-L6-X6+V6+W6 -> 6456.8492 | AA6: =L6/K6 -> 0.22287081 | AB6: =Y6/L6 -> 0.92412325 | AC6: =Y6/K6 -> 0.2059601 | AD6: =R6/K6 -> 0.27815792 | AF6: 41 | AG6: =(K9+K10)/1000 -> 67.922 | AH6: =K9/1000 -> 23.392 | AI6: =K10/1000 -> 44.53
A7: Октябрь | B7: 01-05.10 очки | E7: =K7-SUM(M7:U7)+V7+W7 -> -756.71333 | F7: ='Юнит 01-05.10'!K$24 -> 25 | G7: ='Юнит 01-05.10'!P$24 -> 26 | H7: ='Юнит 01-05.10'!Q$24 -> 2 | I7: ='Юнит 01-05.10'!S$24 -> 32664 | J7: ='Юнит 01-05.10'!T$24 -> -4405 | K7: =I7+J7 -> 28259 | L7: ='Юнит 01-05.10'!W$24 -> 5525.39 | M7: ='Юнит 01-05.10'!Z$24 -> 2442 | N7: ='Юнит 01-05.10'!X$24 -> 7126.96 | R7: ='Юнит 01-05.10'!AA$24 -> 18098.093 | S7: 10 | T7: 1338.66 | U7: 0 | X7: =(K7)*0.01 -> 282.59 | Y7: =K7-SUM(M7:U7)-L7-X7+V7+W7 -> -6564.6933 | Z7: =SUM(Y7:Y16) -> 20856.72 | AA7: =L7/K7 -> 0.19552673 | AB7: =Y7/L7 -> -1.1880959 | AC7: =Y7/K7 -> -0.23230452 | AD7: =R7/K7 -> 0.64043644 | AF7: 42 | AG7: =(K11+K12)/1000 -> 66.834 | AH7: =K11/1000 -> 18.086 | AI7: =K12/1000 -> 48.748
B8: 01-05.10 туники | E8: =K8-SUM(M8:U8)+V8+W8 -> 20148.553 | F8: ='Юнит 01-05.10'!K$47 -> 44 | G8: ='Юнит 01-05.10'!P$47 -> 13 | H8: ='Юнит 01-05.10'!Q$47 -> 1 | I8: ='Юнит 01-05.10'!S$47 -> 43950 | J8: ='Юнит 01-05.10'!T$47 -> -3690 | K8: =I8+J8 -> 40260 | L8: ='Юнит 01-05.10'!W$47 -> 9333 | M8: ='Юнит 01-05.10'!Z$47 -> 1400 | N8: ='Юнит 01-05.10'!X$47 -> 9662.4 | R8: ='Юнит 01-05.10'!AA$47 -> 9049.0467 | X8: =(K8)*0.01 -> 402.6 | Y8: =K8-SUM(M8:U8)-L8-X8+V8+W8 -> 10412.953 | AA8: =L8/K8 -> 0.23181818 | AB8: =Y8/L8 -> 1.1157134 | AC8: =Y8/K8 -> 0.25864266 | AD8: =R8/K8 -> 0.22476519 | AF8: 43 | AG8: =(K13+K14)/1000 -> 44.252 | AH8: =K13/1000 -> 17.776 | AI8: =K14/1000 -> 26.476
B9: 06-12.10 очки | E9: =K9-SUM(M9:U9)+V9+W9 -> 4879.7506 | F9: ='Юнит 06-12.10'!K$24 -> 41 | G9: ='Юнит 06-12.10'!P$24 -> 18 | H9: ='Юнит 06-12.10'!Q$24 -> 1 | I9: ='Юнит 06-12.10'!S$24 -> 24592 | J9: ='Юнит 06-12.10'!T$24 -> -1200 | K9: =I9+J9 -> 23392 | L9: ='Юнит 06-12.10'!W$24 -> 3597.52 | M9: ='Юнит 06-12.10'!Z$24 -> 2096 | N9: ='Юнит 06-12.10'!X$24 -> 6111.53 | R9: ='Юнит 06-12.10'!AA$24 -> 24488.769 | S9: 10 | T9: 1805.95 | U9: 0 | W9: 16000 | X9: =(K9)*0.01 -> 233.92 | Y9: =K9-SUM(M9:U9)-L9-X9+V9+W9 -> 1048.3106 | AA9: =L9/K9 -> 0.15379275 | AB9: =Y9/L9 -> 0.29139814 | AC9: =Y9/K9 -> 0.044814921 | AD9: =R9/K9 -> 1.0468865 | AF9: 44 | AG9: =(K15+K16+K17+K18)/1000 -> 63.99 | AH9: =(K15+K17)/1000 -> 20.25 | AI9: =(K16+K18)/1000 -> 43.74
B10: 06-12.10 туники | E10: =K10-SUM(M10:U10)+V10+W10 -> 11379.979 | F10: ='Юнит 06-12.10'!K$47 -> 32 | G10: ='Юнит 06-12.10'!P$47 -> 14 | H10: ='Юнит 06-12.10'!Q$47 -> 1 | I10: ='Юнит 06-12.10'!S$47 -> 48220 | J10: ='Юнит 06-12.10'!T$47 -> -3690 | K10: =I10+J10 -> 44530 | L10: ='Юнит 06-12.10'!W$47 -> 9495 | M10: ='Юнит 06-12.10'!Z$47 -> 3416 | N10: ='Юнит 06-12.10'!X$47 -> 10687.2 | R10: ='Юнит 06-12.10'!AA$47 -> 19046.821 | X10: =(K10)*0.01 -> 445.3 | Y10: =K10-SUM(M10:U10)-L10-X10+V10+W10 -> 1439.6794 | AA10: =L10/K10 -> 0.21322704 | AB10: =Y10/L10 -> 0.151625 | AC10: =Y10/K10 -> 0.03233055 | AD10: =R10/K10 -> 0.42773008 | AF10: 45 | AG10: =(K19+K20)/1000 -> 34.414 | AH10: =(K19)/1000 -> 14.318 | AI10: =(K20)/1000 -> 20.096
B11: 13-19.10 очки | E11: =K11-SUM(M11:U11)+V11+W11 -> 13932.66 | F11: ='Юнит 13-19.10'!K$24 -> 26 | G11: ='Юнит 13-19.10'!P$24 -> 13 | H11: ='Юнит 13-19.10'!Q$24 -> 0 | I11: ='Юнит 13-19.10'!S$24 -> 18086 | J11: ='Юнит 13-19.10'!T$24 -> 0 | K11: =I11+J11 -> 18086 | L11: ='Юнит 13-19.10'!W$24 -> 2718.58 | M11: ='Юнит 13-19.10'!Z$24 -> 2812 | N11: ='Юнит 13-19.10'!X$24 -> 5420.92 | R11: ='Юнит 13-19.10'!AA$24 -> 10059.34 | S11: 174 | T11: 1687.08 | U11: 0 | W11: 16000 | X11: =(K11)*0.01 -> 180.86 | Y11: =K11-SUM(M11:U11)-L11-X11+V11+W11 -> 11033.22 | AA11: =L11/K11 -> 0.15031406 | AB11: =Y11/L11 -> 4.0584498 | AC11: =Y11/K11 -> 0.61004204 | AD11: =R11/K11 -> 0.55619483 | AF11: 46 | AG11: =(K21+K22)/1000 -> 58.854 | AH11: =(K21)/1000 -> 39.078 | AI11: =(K22)/1000 -> 19.776
B12: 13-19.10 туники | E12: =K12-SUM(M12:U12)+V12+W12 -> 20962.75 | F12: ='Юнит 13-19.10'!K$47 -> 17 | G12: ='Юнит 13-19.10'!P$47 -> 15 | H12: ='Юнит 13-19.10'!Q$47 -> 3 | I12: ='Юнит 13-19.10'!S$47 -> 58698 | J12: ='Юнит 13-19.10'!T$47 -> -9950 | K12: =I12+J12 -> 48748 | L12: ='Юнит 13-19.10'!W$47 -> 11496 | M12: ='Юнит 13-19.10'!Z$47 -> 3024 | N12: ='Юнит 13-19.10'!X$47 -> 13154.32 | R12: ='Юнит 13-19.10'!AA$47 -> 11606.93 | X12: =(K12)*0.01 -> 487.48 | Y12: =K12-SUM(M12:U12)-L12-X12+V12+W12 -> 8979.2696 | AA12: =L12/K12 -> 0.23582506 | AB12: =Y12/L12 -> 0.78107774 | AC12: =Y12/K12 -> 0.1841977 | AD12: =R12/K12 -> 0.23810065 | AF12: 47 | AG12: =(K23+K24)/1000 -> 56.925 | AH12: =(K23)/1000 -> 49.101 | AI12: =(K24)/1000 -> 7.824
B13: 20-26.10 очки | E13: =K13-SUM(M13:U13)+V13+W13 -> -4056.1086 | F13: ='Юнит 20-26.10'!K$24 -> 20 | G13: ='Юнит 20-26.10'!P$24 -> 13 | H13: ='Юнит 20-26.10'!Q$24 -> 0 | I13: ='Юнит 20-26.10'!S$24 -> 17776 | J13: ='Юнит 20-26.10'!T$24 -> 0 | K13: =I13+J13 -> 17776 | L13: ='Юнит 20-26.10'!W$24 -> 2679.97 | M13: ='Юнит 20-26.10'!Z$24 -> 2232 | N13: ='Юнит 20-26.10'!X$24 -> 5952.48 | R13: ='Юнит 20-26.10'!AA$24 -> 12301.789 | S13: 20 | T13: 1325.84 | U13: 0 | X13: =(K13)*0.01 -> 177.76 | Y13: =K13-SUM(M13:U13)-L13-X13+V13+W13 -> -6913.8386 | AA13: =L13/K13 -> 0.15076339 | AB13: =Y13/L13 -> -2.5798194 | AC13: =Y13/K13 -> -0.38894231 | AD13: =R13/K13 -> 0.69204481 | AF13: 48 | AG13: =(K25+K26)/1000 -> 56.476 | AH13: =(K25)/1000 -> 50.476 | AI13: =(K26)/1000 -> 6
B14: 20-26.10 туники | E14: =K14-SUM(M14:U14)+V14+W14 -> 8793.8286 | F14: ='Юнит 20-26.10'!K$47 -> 0 | G14: ='Юнит 20-26.10'!P$47 -> 8 | H14: ='Юнит 20-26.10'!Q$47 -> 2 | I14: ='Юнит 20-26.10'!S$47 -> 36024 | J14: ='Юнит 20-26.10'!T$47 -> -9548 | K14: =I14+J14 -> 26476 | L14: ='Юнит 20-26.10'!W$47 -> 6195 | M14: ='Юнит 20-26.10'!Z$47 -> 1848 | N14: ='Юнит 20-26.10'!X$47 -> 8263.84 | R14: ='Юнит 20-26.10'!AA$47 -> 7570.3314 | X14: =(K14)*0.01 -> 264.76 | Y14: =K14-SUM(M14:U14)-L14-X14+V14+W14 -> 2334.0686 | AA14: =L14/K14 -> 0.2339855 | AB14: =Y14/L14 -> 0.37676652 | AC14: =Y14/K14 -> 0.0881579 | AD14: =R14/K14 -> 0.28593184 | AF14: 49 | AG14: =(K27+K28)/1000 -> 81.321 | AH14: =(K27)/1000 -> 86.821 | AI14: =(K28)/1000 -> -5.5
B15: 27-31.10 очки | E15: =K15-SUM(M15:U15)+V15+W15 -> -4016.9211 | F15: ='Юнит 27-31.10'!K$24 -> 13 | G15: ='Юнит 27-31.10'!P$24 -> 10 | H15: ='Юнит 27-31.10'!Q$24 -> 0 | I15: ='Юнит 27-31.10'!S$24 -> 13972 | J15: ='Юнит 27-31.10'!T$24 -> 0 | K15: =I15+J15 -> 13972 | L15: ='Юнит 27-31.10'!W$24 -> 2317.72 | M15: ='Юнит 27-31.10'!Z$24 -> 1074 | N15: ='Юнит 27-31.10'!X$24 -> 4858.08 | R15: ='Юнит 27-31.10'!AA$24 -> 11163.561 | S15: 5 | T15: 888.28 | U15: 0 | X15: =(K15)*0.01 -> 139.72 | Y15: =K15-SUM(M15:U15)-L15-X15+V15+W15 -> -6474.3611 | AA15: =L15/K15 -> 0.16588319 | AB15: =Y15/L15 -> -2.7934181 | AC15: =Y15/K15 -> -0.46338113 | AD15: =R15/K15 -> 0.79899521 | AF15: 50 | AG15: =(K29+K30)/1000 -> 64.296 | AH15: =(K29)/1000 -> 55.784 | AI15: =(K30)/1000 -> 8.512
B16: 27-31.10 туники | E16: =K16-SUM(M16:U16)+V16+W16 -> 11712.031 | F16: ='Юнит 27-31.10'!K$47 -> 24 | G16: ='Юнит 27-31.10'!P$47 -> 8 | H16: ='Юнит 27-31.10'!Q$47 -> 1 | I16: ='Юнит 27-31.10'!S$47 -> 39192 | J16: ='Юнит 27-31.10'!T$47 -> -5000 | K16: =I16+J16 -> 34192 | L16: ='Юнит 27-31.10'!W$47 -> 5808 | M16: ='Юнит 27-31.10'!Z$47 -> 1120 | N16: ='Юнит 27-31.10'!X$47 -> 12429.12 | R16: ='Юнит 27-31.10'!AA$47 -> 8930.8489 | X16: =(K16)*0.01 -> 341.92 | Y16: =K16-SUM(M16:U16)-L16-X16+V16+W16 -> 5562.1111 | AA16: =L16/K16 -> 0.1698643 | AB16: =Y16/L16 -> 0.95766376 | AC16: =Y16/K16 -> 0.16267288 | AD16: =R16/K16 -> 0.26119703 | AF16: 51 | AG16: =(K31+K32)/1000 -> 64.223 | AH16: =(K31)/1000 -> 57.723 | AI16: =(K32)/1000 -> 6.5
A17: Ноябрь | B17: 01-02.11 очки | E17: =K17-SUM(M17:U17)+V17+W17 -> 512.166 | F17: ='Юнит 01-02.11'!K$24 -> 4 | G17: ='Юнит 01-02.11'!P$24 -> 3 | H17: ='Юнит 01-02.11'!Q$24 -> 0 | I17: ='Юнит 01-02.11'!S$24 -> 6278 | J17: ='Юнит 01-02.11'!T$24 -> 0 | K17: =I17+J17 -> 6278 | L17: ='Юнит 01-02.11'!W$24 -> 1307.5 | M17: ='Юнит 01-02.11'!Z$24 -> 240 | N17: ='Юнит 01-02.11'!X$24 -> 2385.64 | R17: ='Юнит 01-02.11'!AA$24 -> 2850.264 | S17: 0 | T17: 289.93 | U17: 0 | X17: =(K17)*0.01 -> 62.78 | Y17: =K17-SUM(M17:U17)-L17-X17+V17+W17 -> -858.114 | Z17: =SUM(Y17:Y26) -> -34584.4 | AA17: =L17/K17 -> 0.20826696 | AB17: =Y17/L17 -> -0.65630134 | AC17: =Y17/K17 -> -0.13668589 | AD17: =R17/K17 -> 0.45400828 | AF17: 52 | AG17: =(K33+K34)/1000 -> 133.7 | AH17: =(K33)/1000 -> 133.7 | AI17: =(K34)/1000 -> 0
B18: 01-02.11 туники | E18: =K18-SUM(M18:U18)+V18+W18 -> 3067.584 | F18: ='Юнит 01-02.11'!K$47 -> 3 | G18: ='Юнит 01-02.11'!P$47 -> 2 | H18: ='Юнит 01-02.11'!Q$47 -> 0 | I18: ='Юнит 01-02.11'!S$47 -> 9548 | J18: ='Юнит 01-02.11'!T$47 -> 0 | K18: =I18+J18 -> 9548 | L18: ='Юнит 01-02.11'!W$47 -> 1314 | M18: ='Юнит 01-02.11'!Z$47 -> 952 | N18: ='Юнит 01-02.11'!X$47 -> 3628.24 | R18: ='Юнит 01-02.11'!AA$47 -> 1900.176 | X18: =(K18)*0.01 -> 95.48 | Y18: =K18-SUM(M18:U18)-L18-X18+V18+W18 -> 1658.104 | AA18: =L18/K18 -> 0.13762044 | AB18: =Y18/L18 -> 1.2618752 | AC18: =Y18/K18 -> 0.17365982 | AD18: =R18/K18 -> 0.19901299
B19: 03-09.11 очки | E19: =K19-SUM(M19:U19)+V19+W19 -> -5570.5512 | F19: ='Юнит 03-09.11'!K$26 -> 20 | G19: ='Юнит 03-09.11'!P$26 -> 10 | H19: ='Юнит 03-09.11'!Q$26 -> 0 | I19: ='Юнит 03-09.11'!S$26 -> 14318 | J19: ='Юнит 03-09.11'!T$26 -> 0 | K19: =I19+J19 -> 14318 | L19: ='Юнит 03-09.11'!W$26 -> 1418.1 | M19: ='Юнит 03-09.11'!Z$26 -> 1216 | N19: ='Юнит 03-09.11'!X$26 -> 5440.84 | R19: ='Юнит 03-09.11'!AA$26 -> 10605.641 | S19: 5 | T19: 924.97 | U19: 1696.1 | X19: =(K19)*0.01 -> 143.18 | Y19: =K19-SUM(M19:U19)-L19-X19+V19+W19 -> -7131.8312 | AA19: =L19/K19 -> 0.099043162 | AB19: =Y19/L19 -> -5.0291455 | AC19: =Y19/K19 -> -0.49810247 | AD19: =R19/K19 -> 0.74072085
B20: 03-09.11 туники | E20: =K20-SUM(M20:U20)+V20+W20 -> 3187.5712 | F20: ='Юнит 03-09.11'!K$49 -> 16 | G20: ='Юнит 03-09.11'!P$49 -> 7 | H20: ='Юнит 03-09.11'!Q$49 -> 3 | I20: ='Юнит 03-09.11'!S$49 -> 35645 | J20: ='Юнит 03-09.11'!T$49 -> -15549 | K20: =I20+J20 -> 20096 | L20: ='Юнит 03-09.11'!W$49 -> 2748 | M20: ='Юнит 03-09.11'!Z$49 -> 1848 | N20: ='Юнит 03-09.11'!X$49 -> 7636.48 | R20: ='Юнит 03-09.11'!AA$49 -> 7423.9488 | X20: =(K20)*0.01 -> 200.96 | Y20: =K20-SUM(M20:U20)-L20-X20+V20+W20 -> 238.61118 | AA20: =L20/K20 -> 0.13674363 | AB20: =Y20/L20 -> 0.08683085 | AC20: =Y20/K20 -> 0.011873566 | AD20: =R20/K20 -> 0.3694242
B21: 10-16.11 очки | E21: =K21-SUM(M21:U21)+V21+W21 -> -9966.6356 | F21: ='Юнит 10-16.11'!K$26 -> 53 | G21: ='Юнит 10-16.11'!P$26 -> 27 | H21: ='Юнит 10-16.11'!Q$26 -> 1 | I21: ='Юнит 10-16.11'!S$26 -> 40442 | J21: ='Юнит 10-16.11'!T$26 -> -1364 | K21: =I21+J21 -> 39078 | L21: ='Юнит 10-16.11'!W$26 -> 3580.59 | M21: ='Юнит 10-16.11'!Z$26 -> 2866.97 | N21: ='Юнит 10-16.11'!X$26 -> 16247.94 | R21: ='Юнит 10-16.11'!AA$26 -> 24944.676 | S21: 5 | T21: 1416.75 | U21: 3563.3 | X21: =(K21)*0.01 -> 390.78 | Y21: =K21-SUM(M21:U21)-L21-X21+V21+W21 -> -13938.006 | AA21: =L21/K21 -> 0.091626747 | AB21: =Y21/L21 -> -3.8926561 | AC21: =Y21/K21 -> -0.35667142 | AD21: =R21/K21 -> 0.63833041
B22: 10-16.11 туники | E22: =K22-SUM(M22:U22)+V22+W22 -> 4952.2656 | F22: ='Юнит 10-16.11'!K$49 -> 18 | G22: ='Юнит 10-16.11'!P$49 -> 5 | H22: ='Юнит 10-16.11'!Q$49 -> 1 | I22: ='Юнит 10-16.11'!S$49 -> 25276 | J22: ='Юнит 10-16.11'!T$49 -> -5500 | K22: =I22+J22 -> 19776 | L22: ='Юнит 10-16.11'!W$49 -> 2538 | M22: ='Юнит 10-16.11'!Z$49 -> 1700.67 | N22: ='Юнит 10-16.11'!X$49 -> 8503.68 | R22: ='Юнит 10-16.11'!AA$49 -> 4619.3844 | X22: =(K22)*0.01 -> 197.76 | Y22: =K22-SUM(M22:U22)-L22-X22+V22+W22 -> 2216.5056 | AA22: =L22/K22 -> 0.12833738 | AB22: =Y22/L22 -> 0.87332767 | AC22: =Y22/K22 -> 0.11208058 | AD22: =R22/K22 -> 0.23358537
B23: 17-23.11 очки | E23: =K23-SUM(M23:U23)+V23+W23 -> -6903.1175 | F23: ='Юнит 17-23.11'!K$26 -> 68 | G23: ='Юнит 17-23.11'!P$26 -> 33 | H23: ='Юнит 17-23.11'!Q$26 -> 2 | I23: ='Юнит 17-23.11'!S$26 -> 52152 | J23: ='Юнит 17-23.11'!T$26 -> -3051 | K23: =I23+J23 -> 49101 | L23: ='Юнит 17-23.11'!W$26 -> 4229.88 | M23: ='Юнит 17-23.11'!Z$26 -> 5536.12 | N23: ='Юнит 17-23.11'!X$26 -> 21012.9 | R23: ='Юнит 17-23.11'!AA$26 -> 27920.888 | S23: 5 | T23: 1529.21 | U23: 0 | X23: =(K23)*0.01 -> 491.01 | Y23: =K23-SUM(M23:U23)-L23-X23+V23+W23 -> -11624.008 | AA23: =L23/K23 -> 0.086146514 | AB23: =Y23/L23 -> -2.7480703 | AC23: =Y23/K23 -> -0.23673668 | AD23: =R23/K23 -> 0.56864193
B24: 17-23.11 туники | E24: =K24-SUM(M24:U24)+V24+W24 -> 127.9875 | F24: ='Юнит 17-23.11'!K$49 -> 5 | G24: ='Юнит 17-23.11'!P$49 -> 3 | H24: ='Юнит 17-23.11'!Q$49 -> 1 | I24: ='Юнит 17-23.11'!S$49 -> 13324 | J24: ='Юнит 17-23.11'!T$49 -> -5500 | K24: =I24+J24 -> 7824 | L24: ='Юнит 17-23.11'!W$49 -> 1224 | M24: ='Юнит 17-23.11'!Z$49 -> 1518.43 | N24: ='Юнит 17-23.11'!X$49 -> 3639.32 | R24: ='Юнит 17-23.11'!AA$49 -> 2538.2625 | X24: =(K24)*0.01 -> 78.24 | Y24: =K24-SUM(M24:U24)-L24-X24+V24+W24 -> -1174.2525 | AA24: =L24/K24 -> 0.15644172 | AB24: =Y24/L24 -> -0.95935662 | AC24: =Y24/K24 -> -0.1500834 | AD24: =R24/K24 -> 0.32442005
B25: 24-30.11 очки | E25: =K25-SUM(M25:U25)+V25+W25 -> 229.96895 | F25: ='Юнит 24-30.11'!K$26 -> 69 | G25: ='Юнит 24-30.11'!P$26 -> 36 | H25: ='Юнит 24-30.11'!Q$26 -> 4 | I25: ='Юнит 24-30.11'!S$26 -> 56557 | J25: ='Юнит 24-30.11'!T$26 -> -6081 | K25: =I25+J25 -> 50476 | L25: ='Юнит 24-30.11'!W$26 -> 4310.76 | M25: ='Юнит 24-30.11'!Z$26 -> 5747.37 | N25: ='Юнит 24-30.11'!X$26 -> 21704.68 | R25: ='Юнит 24-30.11'!AA$26 -> 21570.101 | S25: 5 | T25: 1218.88 | U25: 0 | X25: =(K25)*0.01 -> 504.76 | Y25: =K25-SUM(M25:U25)-L25-X25+V25+W25 -> -4585.5511 | AA25: =L25/K25 -> 0.085402171 | AB25: =Y25/L25 -> -1.0637454 | AC25: =Y25/K25 -> -0.090846166 | AD25: =R25/K25 -> 0.4273338
B26: 24-30.11 туники | E26: =K26-SUM(M26:U26)+V26+W26 -> 1301.1411 | F26: ='Юнит 24-30.11'!K$49 -> 7 | G26: ='Юнит 24-30.11'!P$49 -> 2 | H26: ='Юнит 24-30.11'!Q$49 -> 1 | I26: ='Юнит 24-30.11'!S$49 -> 12000 | J26: ='Юнит 24-30.11'!T$49 -> -6000 | K26: =I26+J26 -> 6000 | L26: ='Юнит 24-30.11'!W$49 -> 627 | M26: ='Юнит 24-30.11'!Z$49 -> 920.52 | N26: ='Юнит 24-30.11'!X$49 -> 2580 | R26: ='Юнит 24-30.11'!AA$49 -> 1198.3389 | X26: =(K26)*0.01 -> 60 | Y26: =K26-SUM(M26:U26)-L26-X26+V26+W26 -> 614.14105 | AA26: =L26/K26 -> 0.1045 | AB26: =Y26/L26 -> 0.97949131 | AC26: =Y26/K26 -> 0.10235684 | AD26: =R26/K26 -> 0.19972316
A27: Декабрь | B27: 01-07.12 очки | E27: =K27-SUM(M27:U27)+V27+W27 -> 24694.863 | F27: ='Юнит 01-07.12'!K$26 -> 79 | G27: ='Юнит 01-07.12'!P$26 -> 58 | H27: ='Юнит 01-07.12'!Q$26 -> 0 | I27: ='Юнит 01-07.12'!S$26 -> 86821 | J27: ='Юнит 01-07.12'!T$26 -> 0 | K27: =I27+J27 -> 86821 | L27: ='Юнит 01-07.12'!W$26 -> 7713.24 | M27: ='Юнит 01-07.12'!Z$26 -> 8892.35 | N27: ='Юнит 01-07.12'!X$26 -> 37333.03 | R27: ='Юнит 01-07.12'!AA$26 -> 13303.057 | S27: 10 | T27: 1682.9 | U27: 904.8 | X27: =(K27)*0.01 -> 868.21 | Y27: =K27-SUM(M27:U27)-L27-X27+V27+W27 -> 16113.413 | Z27: =SUM(Y27:Y34) -> 8669.76 | AA27: =L27/K27 -> 0.088840718 | AB27: =Y27/L27 -> 2.0890589 | AC27: =Y27/K27 -> 0.1855935 | AD27: =R27/K27 -> 0.15322395
B28: 01-07.12 туники | E28: =K28-SUM(M28:U28)+V28+W28 -> -4332.3931 | F28: ='Юнит 01-07.12'!K$49 -> 1 | G28: ='Юнит 01-07.12'!P$49 -> 1 | H28: ='Юнит 01-07.12'!Q$49 -> 2 | I28: ='Юнит 01-07.12'!S$49 -> 6500 | J28: ='Юнит 01-07.12'!T$49 -> -12000 | K28: =I28+J28 -> -5500 | L28: ='Юнит 01-07.12'!W$49 -> -597 | M28: ='Юнит 01-07.12'!Z$49 -> 968.03 | N28: ='Юнит 01-07.12'!X$49 -> -2365 | R28: ='Юнит 01-07.12'!AA$49 -> 229.36305 | X28: =(K28)*0.01 -> -55 | Y28: =K28-SUM(M28:U28)-L28-X28+V28+W28 -> -3680.3931 | AA28: =L28/K28 -> 0.10854545 | AB28: =Y28/L28 -> 6.1648125 | AC28: =Y28/K28 -> 0.66916237 | AD28: =R28/K28 -> -0.041702373
B29: 08-14.12 очки | E29: =K29-SUM(M29:U29)+V29+W29 -> 6987.3968 | F29: ='Юнит 08-14.12'!K$26 -> 58 | G29: ='Юнит 08-14.12'!P$26 -> 41 | H29: ='Юнит 08-14.12'!Q$26 -> 3 | I29: ='Юнит 08-14.12'!S$26 -> 59828 | J29: ='Юнит 08-14.12'!T$26 -> -4044 | K29: =I29+J29 -> 55784 | L29: ='Юнит 08-14.12'!W$26 -> 5156.85 | M29: ='Юнит 08-14.12'!Z$26 -> 6498.4 | N29: ='Юнит 08-14.12'!X$26 -> 23987.12 | R29: ='Юнит 08-14.12'!AA$26 -> 10153.333 | S29: 0 | T29: 1409.05 | U29: 6748.7 | X29: =(K29)*0.01 -> 557.84 | Y29: =K29-SUM(M29:U29)-L29-X29+V29+W29 -> 1272.7068 | AA29: =L29/K29 -> 0.092443174 | AB29: =Y29/L29 -> 0.24679927 | AC29: =Y29/K29 -> 0.022814908 | AD29: =R29/K29 -> 0.18201157
B30: 08-14.12 туники | E30: =K30-SUM(M30:U30)+V30+W30 -> 3305.2532 | F30: ='Юнит 08-14.12'!K$49 -> 6 | G30: ='Юнит 08-14.12'!P$49 -> 3 | H30: ='Юнит 08-14.12'!Q$49 -> 0 | I30: ='Юнит 08-14.12'!S$49 -> 8512 | J30: ='Юнит 08-14.12'!T$49 -> 0 | K30: =I30+J30 -> 8512 | L30: ='Юнит 08-14.12'!W$49 -> 1911 | M30: ='Юнит 08-14.12'!Z$49 -> 803.66 | N30: ='Юнит 08-14.12'!X$49 -> 3660.16 | R30: ='Юнит 08-14.12'!AA$49 -> 742.92682 | X30: =(K30)*0.01 -> 85.12 | Y30: =K30-SUM(M30:U30)-L30-X30+V30+W30 -> 1309.1332 | AA30: =L30/K30 -> 0.22450658 | AB30: =Y30/L30 -> 0.68505138 | AC30: =Y30/K30 -> 0.15379854 | AD30: =R30/K30 -> 0.087279936
B31: 15-21.12 очки | E31: =K31-SUM(M31:U31)+V31+W31 -> 247.73478 | F31: ='Юнит 15-21.12'!K$26 -> 95 | G31: ='Юнит 15-21.12'!P$26 -> 44 | H31: ='Юнит 15-21.12'!Q$26 -> 2 | I31: ='Юнит 15-21.12'!S$26 -> 61114 | J31: ='Юнит 15-21.12'!T$26 -> -3391 | K31: =I31+J31 -> 57723 | L31: ='Юнит 15-21.12'!W$26 -> 5689.17 | M31: ='Юнит 15-21.12'!Z$26 -> 7370.23 | N31: ='Юнит 15-21.12'!X$26 -> 24820.89 | R31: ='Юнит 15-21.12'!AA$26 -> 19747.085 | S31: 0 | T31: 1553.66 | U31: 3983.4 | X31: =(K31)*0.01 -> 577.23 | Y31: =K31-SUM(M31:U31)-L31-X31+V31+W31 -> -6018.6652 | AA31: =L31/K31 -> 0.098559846 | AB31: =Y31/L31 -> -1.0579162 | AC31: =Y31/K31 -> -0.10426806 | AD31: =R31/K31 -> 0.34210081
B32: 15-21.12 туники | E32: =K32-SUM(M32:U32)+V32+W32 -> 2202.8352 | F32: ='Юнит 15-21.12'!K$49 -> 2 | G32: ='Юнит 15-21.12'!P$49 -> 2 | H32: ='Юнит 15-21.12'!Q$49 -> 1 | I32: ='Юнит 15-21.12'!S$49 -> 9580 | J32: ='Юнит 15-21.12'!T$49 -> -3080 | K32: =I32+J32 -> 6500 | L32: ='Юнит 15-21.12'!W$49 -> 687 | M32: ='Юнит 15-21.12'!Z$49 -> 604.57 | N32: ='Юнит 15-21.12'!X$49 -> 2795 | R32: ='Юнит 15-21.12'!AA$49 -> 897.59478 | X32: =(K32)*0.01 -> 65 | Y32: =K32-SUM(M32:U32)-L32-X32+V32+W32 -> 1450.8352 | AA32: =L32/K32 -> 0.10569231 | AB32: =Y32/L32 -> 2.1118417 | AC32: =Y32/K32 -> 0.22320542 | AD32: =R32/K32 -> 0.13809151
B33: 22-31.12 очки | E33: =K33-SUM(M33:U33)+V33+W33 -> 12664.66 | F33: ='Юнит 22-31.12'!K$26 -> 152 | G33: ='Юнит 22-31.12'!P$26 -> 94 | H33: ='Юнит 22-31.12'!Q$26 -> 4 | I33: ='Юнит 22-31.12'!S$26 -> 139134 | J33: ='Юнит 22-31.12'!T$26 -> -5434 | K33: =I33+J33 -> 133700 | L33: ='Юнит 22-31.12'!W$26 -> 12820.23 | M33: ='Юнит 22-31.12'!Z$26 -> 13321.35 | N33: ='Юнит 22-31.12'!X$26 -> 57491 | R33: ='Юнит 22-31.12'!AA$26 -> 44059.45 | S33: 25 | T33: 2416.34 | U33: 3722.2 | X33: =(K33)*0.01 -> 1337 | Y33: =K33-SUM(M33:U33)-L33-X33+V33+W33 -> -1492.57 | AA33: =L33/K33 -> 0.095888033 | AB33: =Y33/L33 -> -0.11642303 | AC33: =Y33/K33 -> -0.011163575 | AD33: =R33/K33 -> 0.32953964
B34: 22-31.12 туники | E34: =K34-SUM(M34:U34)+V34+W34 -> -284.7 | F34: ='Юнит 22-31.12'!K$49 -> 3 | G34: ='Юнит 22-31.12'!P$49 -> 0 | H34: ='Юнит 22-31.12'!Q$49 -> 0 | I34: ='Юнит 22-31.12'!S$49 -> 0 | J34: ='Юнит 22-31.12'!T$49 -> 0 | K34: =I34+J34 -> 0 | L34: ='Юнит 22-31.12'!W$49 -> 0 | M34: ='Юнит 22-31.12'!Z$49 -> 284.7 | N34: ='Юнит 22-31.12'!X$49 -> 0 | R34: ='Юнит 22-31.12'!AA$49 -> 0 | X34: =(K34)*0.01 -> 0 | Y34: =K34-SUM(M34:U34)-L34-X34+V34+W34 -> -284.7 | AA34: =L34/K34 -> #DIV/0! | AB34: =Y34/L34 -> #DIV/0! | AC34: =Y34/K34 -> #DIV/0! | AD34: =R34/K34 -> #DIV/0!
A35: Итого | E35: =SUM(E3:E34) -> 193947.3 | F35: =SUM(F3:F34) -> 1159 | G35: =SUM(G3:G34) -> 632 | H35: =SUM(H3:H34) -> 42 | I35: =SUM(I3:I34) -> 1153756 | J35: =SUM(J3:J34) -> -118835 | K35: =SUM(K3:K34) -> 1034921 | L35: =SUM(L3:L34) -> 140719.76 | ... Z35: =SUM(Z3:Z34) -> 42878.33 | AA35: =L35/K35 -> 0.1359715 | AB35: =Y35/L35 -> 0.30470724 | AC35: =Y35/K35 -> 0.041431501 | AD35: =R35/K35 -> 0.43055238
I36: % от выручки за весь период
J37: =-J35/I35 -> 0.10299838 | K37: 0 | L37: =L35/$K$35 -> 0.1359715 | M37: =M35/$K$35 -> 0.093262549 | N37: =N35/$K$35 -> 0.34858148 | R37: =R35/$K$35 -> 0.43055238 | X37: =X35/$K$35 -> 0.01 | Y37: =Y35/L35 -> 0.30470724 | Z37: Маржинальность, %
Y38: =Y35/$K$35 -> 0.041431501 | Z38: Рентабельность, %
I39: 22-31.12
I40: % от выручки за последнюю неделю
I41: очки | J41: =-(J33)/(I33) -> 0.039055874 | L41: =(L33)/($K$33) -> 0.095888033 | M41: =(M33)/($K$33) -> 0.099636126 | N41: =(N33)/($K$33) -> 0.43 | O41: =(O33)/($K$33) -> 0 | P41: =(P33)/($K$33) -> 0 | Q41: =(Q33)/($K$33) -> 0 | R41: =(R33)/($K$33) -> 0.32953964 | S41: =(S33)/($K$33) -> 0.00018698579 | ... X41: =(X33)/($K$33) -> 0.01
I42: туники | J42: =-(J34)/(I34) -> #DIV/0! | L42: =(L34)/($K$34) -> #DIV/0! | M42: =(M34)/($K$34) -> #DIV/0! | N42: =(N34)/($K$34) -> #DIV/0! | O42: =(O34)/($K$34) -> #DIV/0! | P42: =(P34)/($K$34) -> #DIV/0! | Q42: =(Q34)/($K$34) -> #DIV/0! | R42: =(R34)/($K$34) -> #DIV/0! | S42: =(S34)/($K$34) -> #DIV/0! | ... X42: =(X34)/($K$34) -> #DIV/0!
I43: Изменение относительно прошлой недели
I44: очки | J44: =-(J33)/(I33)+(J31)/(I31) -> -0.016430594 | K44: =(K33)/(K31)-1 -> 1.3162344 | L44: =(L33)/(L31)-1 -> 1.2534447 | M44: =(M33)/(M31)-1 -> 0.80745377 | N44: =(N33)/(N31)-1 -> 1.3162344 | O44: =(O33)/(O31)-1 -> #DIV/0! | P44: =(P33)/(P31)-1 -> #DIV/0! | Q44: =(Q33)/(Q31)-1 -> #DIV/0! | R44: =(R33)/(R31)-1 -> 1.2311875 | ... X44: =(X33)/(X31)-1 -> 1.3162344 | Y44: =-((Y33)/(Y31)-1) -> 0.7520098
I45: туники | J45: =-(J34)/(I34)+(J32)/(I32) -> #DIV/0! | K45: =(K34)/(K32)-1 -> -1 | L45: =(L34)/(L32)-1 -> -1 | M45: =(M34)/(M32)-1 -> -0.52908679 | N45: =(N34)/(N32)-1 -> -1 | O45: =(O34)/(O32)-1 -> #DIV/0! | P45: =(P34)/(P32)-1 -> #DIV/0! | Q45: =(Q34)/(Q32)-1 -> #DIV/0! | R45: =(R34)/(R32)-1 -> -1 | ... Y45: =(Y34)/(Y32)-1 -> -1.1962318 | Z45: Изменение прибыли за неделю
I46: 15-21.12
I47: % от выручки за последнюю неделю
I48: очки | J48: =-(J31)/(I31) -> 0.055486468 | L48: =(L31)/($K$31) -> 0.098559846 | M48: =(M31)/($K$31) -> 0.12768273 | N48: =(N31)/($K$31) -> 0.43 | O48: =(O31)/($K$31) -> 0 | P48: =(P31)/($K$31) -> 0 | Q48: =(Q31)/($K$31) -> 0 | R48: =(R31)/($K$31) -> 0.34210081 | S48: =(S31)/($K$31) -> 0 | ... X48: =(X31)/($K$31) -> 0.01
I49: туники | J49: =-(J32)/(I32) -> 0.32150313 | L49: =(L32)/($K$32) -> 0.10569231 | M49: =(M32)/($K$32) -> 0.093010769 | N49: =(N32)/($K$32) -> 0.43 | O49: =(O32)/($K$32) -> 0 | P49: =(P32)/($K$32) -> 0 | Q49: =(Q32)/($K$32) -> 0 | R49: =(R32)/($K$32) -> 0.13809151 | S49: =(S32)/($K$32) -> 0 | ... X49: =(X32)/($K$32) -> 0.01
I50: Изменение относительно прошлой недели
I51: очки | J51: =-(J31)/(I31)+(J29)/(I29) -> -0.012107301 | K51: =(K31)/(K29)-1 -> 0.034759071 | L51: =(L31)/(L29)-1 -> 0.10322581 | M51: =(M31)/(M29)-1 -> 0.13416072 | N51: =(N31)/(N29)-1 -> 0.034759071 | O51: =(O31)/(O29)-1 -> #DIV/0! | P51: =(P31)/(P29)-1 -> #DIV/0! | Q51: =(Q31)/(Q29)-1 -> #DIV/0! | R51: =(R31)/(R29)-1 -> 0.94488695 | ... Y51: =(Y31)/(Y29)-1 -> -5.7290272
I52: туники | J52: =-(J32)/(I32)+(J30)/(I30) -> 0.32150313 | K52: =(K32)/(K30)-1 -> -0.23637218 | L52: =(L32)/(L30)-1 -> -0.64050235 | M52: =(M32)/(M30)-1 -> -0.24772914 | N52: =(N32)/(N30)-1 -> -0.23637218 | O52: =(O32)/(O30)-1 -> #DIV/0! | P52: =(P32)/(P30)-1 -> #DIV/0! | Q52: =(Q32)/(Q30)-1 -> #DIV/0! | R52: =(R32)/(R30)-1 -> 0.20818735 | ... Y52: =(Y32)/(Y30)-1 -> 0.10824112 | Z52: Изменение прибыли за неделю
I53: 08-14.12
I54: % от выручки за последнюю неделю
I55: очки | J55: =-(J29)/(I29) -> 0.067593769 | L55: =(L29)/($K$29) -> 0.092443174 | M55: =(M29)/($K$29) -> 0.11649218 | N55: =(N29)/($K$29) -> 0.43 | O55: =(O29)/($K$29) -> 0 | P55: =(P29)/($K$29) -> 0 | Q55: =(Q29)/($K$29) -> 0 | R55: =(R29)/($K$29) -> 0.18201157 | S55: =(S29)/($K$29) -> 0 | ... X55: =(X29)/($K$29) -> 0.01
I56: туники | J56: =-(J30)/(I30) -> 0 | L56: =(L30)/($K$30) -> 0.22450658 | M56: =(M30)/($K$30) -> 0.094414944 | N56: =(N30)/($K$30) -> 0.43 | O56: =(O30)/($K$30) -> 0 | P56: =(P30)/($K$30) -> 0 | Q56: =(Q30)/($K$30) -> 0 | R56: =(R30)/($K$30) -> 0.087279936 | S56: =(S30)/($K$30) -> 0 | ... X56: =(X30)/($K$30) -> 0.01
I57: Изменение относительно прошлой недели
I58: очки | J58: =-(J29)/(I29)+(J27)/(I27) -> 0.067593769 | K58: =(K29)/(K27)-1 -> -0.35748264 | L58: =(L29)/(L27)-1 -> -0.33142882 | M58: =(M29)/(M27)-1 -> -0.26921455 | N58: =(N29)/(N27)-1 -> -0.35748264 | O58: =(O29)/(O27)-1 -> #DIV/0! | P58: =(P29)/(P27)-1 -> #DIV/0! | Q58: =(Q29)/(Q27)-1 -> #DIV/0! | R58: =(R29)/(R27)-1 -> -0.23676692 | ... Y58: =(Y29)/(Y27)-1 -> -0.92101569
I59: туники | J59: =-(J30)/(I30)+(J28)/(I28) -> -1.8461538 | K59: =(K30)/(K28)-1 -> -2.5476364 | L59: =(L30)/(L28)-1 -> -4.201005 | M59: =(M30)/(M28)-1 -> -0.16979846 | N59: =(N30)/(N28)-1 -> -2.5476364 | O59: =(O30)/(O28)-1 -> #DIV/0! | P59: =(P30)/(P28)-1 -> #DIV/0! | Q59: =(Q30)/(Q28)-1 -> #DIV/0! | R59: =(R30)/(R28)-1 -> 2.2390867 | ... X59: =(X30)/(X28)-1 -> -2.5476364 | Y59: =-((Y30)/(Y28)-1) -> 1.3557047 | Z59: Изменение прибыли за неделю
I60: 01-07.12
I61: % от выручки за последнюю неделю
I62: очки | J62: =-(J27)/(I27) -> 0 | L62: =(L27)/($K$27) -> 0.088840718 | M62: =(M27)/($K$27) -> 0.10242165 | N62: =(N27)/($K$27) -> 0.43 | O62: =(O27)/($K$27) -> 0 | P62: =(P27)/($K$27) -> 0 | Q62: =(Q27)/($K$27) -> 0 | R62: =(R27)/($K$27) -> 0.15322395 | S62: =(S27)/($K$27) -> 0.00011517951 | ... X62: =(X27)/($K$27) -> 0.01
I63: туники | J63: =-(J28)/(I28) -> 1.8461538 | L63: =(L28)/($K$28) -> 0.10854545 | M63: =(M28)/($K$28) -> -0.17600545 | N63: =(N28)/($K$28) -> 0.43 | O63: =(O28)/($K$28) -> 0 | P63: =(P28)/($K$28) -> 0 | Q63: =(Q28)/($K$28) -> 0 | R63: =(R28)/($K$28) -> -0.041702373 | S63: =(S28)/($K$28) -> 0 | ... X63: =(X28)/($K$28) -> 0.01
I64: Изменение относительно прошлой недели
I65: очки | J65: =-(J27)/(I27)+(J25)/(I25) -> -0.10751985 | K65: =(K27)/(K25)-1 -> 0.72004517 | L65: =(L27)/(L25)-1 -> 0.78929933 | M65: =(M27)/(M25)-1 -> 0.54720333 | N65: =(N27)/(N25)-1 -> 0.72004517 | O65: =(O27)/(O25)-1 -> #DIV/0! | P65: =(P27)/(P25)-1 -> #DIV/0! | Q65: =(Q27)/(Q25)-1 -> #DIV/0! | R65: =(R27)/(R25)-1 -> -0.38326404 | ... X65: =(X27)/(X25)-1 -> 0.72004517 | Y65: =-((Y27)/(Y25)-1) -> 4.5139535
I66: туники | J66: =-(J28)/(I28)+(J26)/(I26) -> 1.3461538 | K66: =(K28)/(K26)-1 -> -1.9166667 | L66: =(L28)/(L26)-1 -> -1.9521531 | M66: =(M28)/(M26)-1 -> 0.051612132 | N66: =(N28)/(N26)-1 -> -1.9166667 | O66: =(O28)/(O26)-1 -> #DIV/0! | P66: =(P28)/(P26)-1 -> #DIV/0! | Q66: =(Q28)/(Q26)-1 -> #DIV/0! | R66: =(R28)/(R26)-1 -> -0.80859919 | ... Y66: =(Y28)/(Y26)-1 -> -6.9927488 | Z66: Изменение прибыли за неделю
I67: 24-30.11
I68: % от выручки за последнюю неделю
I69: очки | J69: =-(J25)/(I25) -> 0.10751985 | L69: =(L25)/($K$25) -> 0.085402171 | M69: =(M25)/($K$25) -> 0.11386342 | N69: =(N25)/($K$25) -> 0.43 | O69: =(O25)/($K$25) -> 0 | P69: =(P25)/($K$25) -> 0 | Q69: =(Q25)/($K$25) -> 0 | R69: =(R25)/($K$25) -> 0.4273338 | S69: =(S25)/($K$25) -> 9.9056978e-05 | ... X69: =(X25)/($K$25) -> 0.01
I70: туники | J70: =-(J26)/(I26) -> 0.5 | L70: =(L26)/($K$26) -> 0.1045 | M70: =(M26)/($K$26) -> 0.15342 | N70: =(N26)/($K$26) -> 0.43 | O70: =(O26)/($K$26) -> 0 | P70: =(P26)/($K$26) -> 0 | Q70: =(Q26)/($K$26) -> 0 | R70: =(R26)/($K$26) -> 0.19972316 | S70: =(S26)/($K$26) -> 0 | ... X70: =(X26)/($K$26) -> 0.01
I71: Изменение относительно прошлой недели
I72: очки | J72: =-(J25)/(I25)+(J23)/(I23) -> 0.049017776 | K72: =(K25)/(K23)-1 -> 0.028003503 | L72: =(L25)/(L23)-1 -> 0.01912111 | M72: =(M25)/(M23)-1 -> 0.038158494 | N72: =(N25)/(N23)-1 -> 0.032921681 | O72: =(O25)/(O23)-1 -> #DIV/0! | P72: =(P25)/(P23)-1 -> #DIV/0! | Q72: =(Q25)/(Q23)-1 -> #DIV/0! | R72: =(R25)/(R23)-1 -> -0.22745647 | ... X72: =(X25)/(X23)-1 -> 0.028003503 | Y72: =-((Y25)/(Y23)-1) -> 0.60551032
I73: туники | J73: =-(J26)/(I26)+(J24)/(I24) -> 0.087211048 | K73: =(K26)/(K24)-1 -> -0.23312883 | L73: =(L26)/(L24)-1 -> -0.4877451 | M73: =(M26)/(M24)-1 -> -0.39376856 | N73: =(N26)/(N24)-1 -> -0.29107635 | O73: =(O26)/(O24)-1 -> #DIV/0! | P73: =(P26)/(P24)-1 -> #DIV/0! | Q73: =(Q26)/(Q24)-1 -> #DIV/0! | R73: =(R26)/(R24)-1 -> -0.52789006 | ... X73: =(X26)/(X24)-1 -> -0.23312883 | Y73: =-((Y26)/(Y24)-1) -> 1.523006 | Z73: Изменение прибыли за неделю
I74: 17-23.11
I75: % от выручки за последнюю неделю
I76: очки | J76: =-(J23)/(I23) -> 0.058502071 | L76: =(L23)/($K$23) -> 0.086146514 | M76: =(M23)/($K$23) -> 0.11274964 | N76: =(N23)/($K$23) -> 0.42795259 | O76: =(O23)/($K$23) -> 0 | P76: =(P23)/($K$23) -> 0 | Q76: =(Q23)/($K$23) -> 0 | R76: =(R23)/($K$23) -> 0.56864193 | S76: =(S23)/($K$23) -> 0.00010183092 | ... X76: =(X23)/($K$23) -> 0.01
I77: туники | J77: =-(J24)/(I24) -> 0.41278895 | L77: =(L24)/($K$24) -> 0.15644172 | M77: =(M24)/($K$24) -> 0.19407336 | N77: =(N24)/($K$24) -> 0.46514826 | O77: =(O24)/($K$24) -> 0 | P77: =(P24)/($K$24) -> 0 | Q77: =(Q24)/($K$24) -> 0 | R77: =(R24)/($K$24) -> 0.32442005 | S77: =(S24)/($K$24) -> 0 | ... X77: =(X24)/($K$24) -> 0.01
I78: Изменение относительно прошлой недели
I79: очки | J79: =-(J23)/(I23)+(J21)/(I21) -> 0.024774758 | K79: =(K23)/(K21)-1 -> 0.25648703 | L79: =(L23)/(L21)-1 -> 0.18133604 | M79: =(M23)/(M21)-1 -> 0.93100032 | N79: =(N23)/(N21)-1 -> 0.29326548 | O79: =(O23)/(O21)-1 -> #DIV/0! | P79: =(P23)/(P21)-1 -> #DIV/0! | Q79: =(Q23)/(Q21)-1 -> #DIV/0! | R79: =(R23)/(R21)-1 -> 0.11931251 | ... X79: =(X23)/(X21)-1 -> 0.25648703 | Y79: =-((Y23)/(Y21)-1) -> 0.16602075
I80: туники | J80: =-(J24)/(I24)+(J22)/(I22) -> 0.19519123 | K80: =(K24)/(K22)-1 -> -0.60436893 | L80: =(L24)/(L22)-1 -> -0.5177305 | M80: =(M24)/(M22)-1 -> -0.10715777 | N80: =(N24)/(N22)-1 -> -0.57202999 | O80: =(O24)/(O22)-1 -> #DIV/0! | P80: =(P24)/(P22)-1 -> #DIV/0! | Q80: =(Q24)/(Q22)-1 -> #DIV/0! | R80: =(R24)/(R22)-1 -> -0.45051931 | ... X80: =(X24)/(X22)-1 -> -0.60436893 | Y80: =-((Y24)/(Y22)-1) -> 1.5297765 | Z80: Изменение прибыли за неделю
I81: 10-16.11
I82: % от выручки за последнюю неделю
I83: очки | J83: =-(J21)/(I21) -> 0.033727313 | L83: =(L21)/($K$21) -> 0.091626747 | M83: =(M21)/($K$21) -> 0.073365321 | N83: =(N21)/($K$21) -> 0.41578228 | O83: =(O21)/($K$21) -> 0 | P83: =(P21)/($K$21) -> 0 | Q83: =(Q21)/($K$21) -> 0 | R83: =(R21)/($K$21) -> 0.63833041 | S83: =(S21)/($K$21) -> 0.00012794923 | ... X83: =(X21)/($K$21) -> 0.01
I84: туники | J84: =-(J22)/(I22) -> 0.21759772 | L84: =(L22)/($K$22) -> 0.12833738 | M84: =(M22)/($K$22) -> 0.085996663 | N84: =(N22)/($K$22) -> 0.43 | O84: =(O22)/($K$22) -> 0 | P84: =(P22)/($K$22) -> 0 | Q84: =(Q22)/($K$22) -> 0 | R84: =(R22)/($K$22) -> 0.23358537 | S84: =(S22)/($K$22) -> 0 | ... X84: =(X22)/($K$22) -> 0.01
I85: Изменение относительно прошлой недели
I86: очки | J86: =-(J21)/(I21)+(J19)/(I19) -> 0.033727313 | K86: =(K21)/(K19)-1 -> 1.7292918 | L86: =(L21)/(L19)-1 -> 1.5249207 | M86: =(M21)/(M19)-1 -> 1.3577056 | N86: =(N21)/(N19)-1 -> 1.9862926 | O86: =(O21)/(O19)-1 -> #DIV/0! | P86: =(P21)/(P19)-1 -> #DIV/0! | Q86: =(Q21)/(Q19)-1 -> #DIV/0! | R86: =(R21)/(R19)-1 -> 1.3520196 | ... X86: =(X21)/(X19)-1 -> 1.7292918 | Y86: =-((Y21)/(Y19)-1) -> -0.95433757
I87: туники | J87: =-(J22)/(I22)+(J20)/(I20) -> -0.21862054 | K87: =(K22)/(K20)-1 -> -0.015923567 | L87: =(L22)/(L20)-1 -> -0.076419214 | M87: =(M22)/(M20)-1 -> -0.079724026 | N87: =(N22)/(N20)-1 -> 0.11356017 | O87: =(O22)/(O20)-1 -> #DIV/0! | P87: =(P22)/(P20)-1 -> #DIV/0! | Q87: =(Q22)/(Q20)-1 -> #DIV/0! | R87: =(R22)/(R20)-1 -> -0.3777726 | ... X87: =(X22)/(X20)-1 -> -0.015923567 | Y87: =-((Y22)/(Y20)-1) -> -8.2891945 | Z87: Изменение прибыли за неделю
I88: 03-09.11
I89: % от выручки за последнюю неделю
I90: очки | J90: =-(J19)/(I19) -> 0 | L90: =(L19)/($K$19) -> 0.099043162 | M90: =(M19)/($K$19) -> 0.084928063 | N90: =(N19)/($K$19) -> 0.38 | O90: =(O19)/($K$19) -> 0 | P90: =(P19)/($K$19) -> 0 | Q90: =(Q19)/($K$19) -> 0 | R90: =(R19)/($K$19) -> 0.74072085 | S90: =(S19)/($K$19) -> 0.00034921078 | ... X90: =(X19)/($K$19) -> 0.01
I91: туники | J91: =-(J20)/(I20) -> 0.43621826 | L91: =(L20)/($K$20) -> 0.13674363 | M91: =(M20)/($K$20) -> 0.091958599 | N91: =(N20)/($K$20) -> 0.38 | O91: =(O20)/($K$20) -> 0 | P91: =(P20)/($K$20) -> 0 | Q91: =(Q20)/($K$20) -> 0 | R91: =(R20)/($K$20) -> 0.3694242 | S91: =(S20)/($K$20) -> 0 | ... X91: =(X20)/($K$20) -> 0.01
I92: Изменение относительно прошлой недели
I93: очки | J93: =-(J19)/(I19)+(J17+J15)/(I17+I15) -> 0 | K93: =(K19)/(K17+K15)-1 -> -0.29293827 | L93: =(L19)/(L17+L15)-1 -> -0.60882374 | M93: =(M19)/(M17+M15)-1 -> -0.074581431 | N93: =(N19)/(N17+N15)-1 -> -0.24888869 | O93: =(O19)/(O17+O15)-1 -> #DIV/0! | P93: =(P19)/(P17+P15)-1 -> #DIV/0! | Q93: =(Q19)/(Q17+Q15)-1 -> #DIV/0! | R93: =(R19)/(R17+R15)-1 -> -0.24320155 | ... Y93: =(Y19)/(Y17+Y15)-1 -> -0.027363739
I94: туники | J94: =-(J20)/(I20)+(J18+J16)/(I18+I16) -> 0.33363312 | K94: =(K20)/(K18+K16)-1 -> -0.54055784 | L94: =(L20)/(L18+L16)-1 -> -0.61415333 | M94: =(M20)/(M18+M16)-1 -> -0.10810811 | N94: =(N20)/(N18+N16)-1 -> -0.52442494 | O94: =(O20)/(O18+O16)-1 -> #DIV/0! | P94: =(P20)/(P18+P16)-1 -> #DIV/0! | Q94: =(Q20)/(Q18+Q16)-1 -> #DIV/0! | R94: =(R20)/(R18+R16)-1 -> -0.31456636 | ... Y94: =(Y20)/(Y18+Y16)-1 -> -0.96695235 | Z94: Изменение прибыли за неделю
I95: 27.10-02.11
I96: % от выручки за последнюю неделю
I97: очки | J97: =-(J17+J15)/(I17+I15) -> 0 | L97: =(L17+L15)/($K$17+$K$15) -> 0.17902321 | M97: =(M17+M15)/($K$17+$K$15) -> 0.064888889 | N97: =(N17+N15)/($K$17+$K$15) -> 0.35771457 | O97: =(O17+O15)/($K$17+$K$15) -> 0 | P97: =(P17+P15)/($K$17+$K$15) -> 0 | Q97: =(Q17+Q15)/($K$17+$K$15) -> 0 | R97: =(R17+R15)/($K$17+$K$15) -> 0.69204075 | S97: =(S17+S15)/($K$17+$K$15) -> 0.00024691358 | ... X97: =(X17+X15)/($K$17+$K$15) -> 0.01
I98: туники | J98: =-(J18+J16)/(I18+I16) -> 0.10258515 | L98: =(L18+L16)/($K$18+$K$16) -> 0.16282579 | M98: =(M18+M16)/($K$18+$K$16) -> 0.047370828 | N98: =(N18+N16)/($K$18+$K$16) -> 0.36710928 | O98: =(O18+O16)/($K$18+$K$16) -> 0 | P98: =(P18+P16)/($K$18+$K$16) -> 0 | Q98: =(Q18+Q16)/($K$18+$K$16) -> 0 | R98: =(R18+R16)/($K$18+$K$16) -> 0.24762288 | S98: =(S18+S16)/($K$18+$K$16) -> 0 | ... X98: =(X18+X16)/($K$18+$K$16) -> 0.01
I99: Изменение относительно прошлой недели
I100: очки | J100: =-(J17+J15)/(I17+I15)+(J13)/(I13) -> 0 | K100: =(K17+K15)/(K13)-1 -> 0.13917642 | L100: =(L17+L15)/(L13)-1 -> 0.35270917 | M100: =(M17+M15)/(M13)-1 -> -0.41129032 | N100: =(N17+N15)/(N13)-1 -> 0.21692471 | O100: =(O17+O15)/(O13)-1 -> #DIV/0! | P100: =(P17+P15)/(P13)-1 -> #DIV/0! | Q100: =(Q17+Q15)/(Q13)-1 -> #DIV/0! | R100: =(R17+R15)/(R13)-1 -> 0.13916973 | ... Y100: =(Y17+Y15)/(Y13)-1 -> 0.060550523
...

Sheet Дашборд 22-31.12
B2: Период | E2: Дата поступления дс | F2: Итого к перечислению на счет, руб | G2: Выручка | J2: Себестоимость продаж | K2: Логистика | L2: Комиссия | M2: Хранение | N2: Платная приемка | O2: Штрафы | P2: Реклама Ozon | Q2: Прочее | R2: Доп. услуги | S2: Услуги FBO | T2: Компенсировано | U2: Прочие начисления | V2: Налог | W2: Итого | Y2: % Cебестоимости | Z2: Маржинальность, % | AA2: Рентабельность, % | AB2: Доля рекламы, %
B3: Месяц | C3: Даты | D3: Нед | G3: Продажи | H3: Возвраты | I3: Общая
C4: ='Динамика финансы'!B33 -> 22-31.12 очки | D4: ='Динамика финансы'!C33 -> 0 | E4: ='Динамика финансы'!D33 -> 0 | F4: ='Динамика финансы'!E33 -> 12664.66 | G4: ='Динамика финансы'!I33 -> 139134 | H4: ='Динамика финансы'!J33 -> -5434 | I4: ='Динамика финансы'!K33 -> 133700 | J4: ='Динамика финансы'!L33 -> 12820.23 | K4: ='Динамика финансы'!M33 -> 13321.35 | L4: ='Динамика финансы'!N33 -> 57491 | M4: ='Динамика финансы'!O33 -> 0 | N4: ='Динамика финансы'!P33 -> 0 | ... W4: ='Динамика финансы'!Y33 -> -1492.57 | Y4: ='Динамика финансы'!AA33 -> 0.095888033 | Z4: ='Динамика финансы'!AB33 -> -0.11642303 | AA4: ='Динамика финансы'!AC33 -> -0.011163575 | AB4: ='Динамика финансы'!AD33 -> 0.32953964
C5: ='Динамика финансы'!B34 -> 22-31.12 туники | D5: ='Динамика финансы'!C34 -> 0 | E5: ='Динамика финансы'!D34 -> 0 | F5: ='Динамика финансы'!E34 -> -284.7 | G5: ='Динамика финансы'!I34 -> 0 | H5: ='Динамика финансы'!J34 -> 0 | I5: ='Динамика финансы'!K34 -> 0 | J5: ='Динамика финансы'!L34 -> 0 | K5: ='Динамика финансы'!M34 -> 284.7 | L5: ='Динамика финансы'!N34 -> 0 | M5: ='Динамика финансы'!O34 -> 0 | N5: ='Динамика финансы'!P34 -> 0 | ... W5: ='Динамика финансы'!Y34 -> -284.7 | Y5: ='Динамика финансы'!AA34 -> #DIV/0! | Z5: ='Динамика финансы'!AB34 -> #DIV/0! | AA5: ='Динамика финансы'!AC34 -> #DIV/0! | AB5: ='Динамика финансы'!AD34 -> #DIV/0!
F8: =F4+F5+F6+F7 -> 12379.96 | G8: =G4+G5+G6+G7 -> 139134 | H8: =H4+H5+H6+H7 -> -5434 | I8: =I4+I5+I6+I7 -> 133700 | J8: =J4+J5+J6+J7 -> 12820.23 | K8: =K4+K5+K6+K7 -> 13606.05 | L8: =L4+L5+L6+L7 -> 57491 | M8: =M4+M5+M6+M7 -> 0 | ... W8: =W4+W5+W6+W7 -> -1777.27
C11: АНАЛИЗ ФИНАНСОВЫХ ПОКАЗАТЕЛЕЙ ЗА | G11: 22-31.12
C13: ОЧКИ | I13: ТУНИКИ
C15: Выручка | E15: =I4 -> 133700 | F15: руб. | G15: ='Динамика финансы'!K44 -> 1.3162344 | I15: Выручка | K15: =I5 -> 0 | L15: руб. | M15: ='Динамика финансы'!K45 -> -1
C16: Прибыль | E16: =W4 -> -1492.57 | F16: руб. | G16: ='Динамика финансы'!Y44 -> 0.7520098 | I16: Прибыль | K16: =W5 -> -284.7 | L16: руб. | M16: ='Динамика финансы'!Y45 -> -1.1962318
C17: Себестоимость продаж | E17: =J4 -> 12820.23 | F17: руб. | G17: ='Динамика финансы'!L44 -> 1.2534447 | I17: Себестоимость продаж | K17: =J5 -> 0 | L17: руб. | M17: ='Динамика финансы'!L45 -> -1
G18: % от выручки | M18: % от выручки
C19: Логистика | E19: =K4 -> 13321.35 | F19: руб. | G19: ='Динамика финансы'!M41 -> 0.099636126 | I19: Логистика | K19: =K5 -> 284.7 | L19: руб. | M19: ='Динамика финансы'!M42 -> #DIV/0!
C20: Реклама | E20: =P4 -> 44059.45 | F20: руб. | G20: ='Динамика финансы'!R41 -> 0.32953964 | I20: Реклама | K20: =P5 -> 0 | L20: руб. | M20: ='Динамика финансы'!R42 -> #DIV/0!
C22: Возвраты | E22: =H4 -> -5434 | F22: руб. | G22: ='Динамика финансы'!J41 -> 0.039055874 | I22: Возвраты | K22: =H5 -> 0 | L22: руб. | M22: ='Динамика финансы'!J42 -> #DIV/0!
C23: Комиссия | E23: =L4 -> 57491 | F23: руб. | G23: ='Динамика финансы'!N41 -> 0.43 | I23: Комиссия | K23: =L5 -> 0 | L23: руб. | M23: ='Динамика финансы'!N42 -> #DIV/0!
E25: Маржинальность | G25: =Z4 -> -0.11642303 | K25: Маржинальность | M25: =Z5 -> #DIV/0!
E26: Рентабельность | G26: =AA4 -> -0.011163575 | K26: Рентабельность | M26: =AA5 -> #DIV/0!
E27: % себестоимости | G27: =Y4 -> 0.095888033 | K27: % себестоимости | M27: =Y5 -> #DIV/0!
F29: На остатках товара на | I29: руб.

Sheet Дашборд 15-21.12
B2: Период | E2: Дата поступления дс | F2: Итого к перечислению на счет, руб | G2: Выручка | J2: Себестоимость продаж | K2: Логистика | L2: Комиссия | M2: Хранение | N2: Платная приемка | O2: Штрафы | P2: Реклама Ozon | Q2: Прочее | R2: Доп. услуги | S2: Услуги FBO | T2: Компенсировано | U2: Прочие начисления | V2: Налог | W2: Итого | Y2: % Cебестоимости | Z2: Маржинальность, % | AA2: Рентабельность, % | AB2: Доля рекламы, %
B3: Месяц | C3: Даты | D3: Нед | G3: Продажи | H3: Возвраты | I3: Общая
C4: ='Динамика финансы'!B31 -> 15-21.12 очки | D4: ='Динамика финансы'!C31 -> 0 | E4: ='Динамика финансы'!D31 -> 0 | F4: ='Динамика финансы'!E31 -> 247.73478 | G4: ='Динамика финансы'!I31 -> 61114 | H4: ='Динамика финансы'!J31 -> -3391 | I4: ='Динамика финансы'!K31 -> 57723 | J4: ='Динамика финансы'!L31 -> 5689.17 | K4: ='Динамика финансы'!M31 -> 7370.23 | L4: ='Динамика финансы'!N31 -> 24820.89 | M4: ='Динамика финансы'!O31 -> 0 | N4: ='Динамика финансы'!P31 -> 0 | ... W4: ='Динамика финансы'!Y31 -> -6018.6652 | Y4: ='Динамика финансы'!AA31 -> 0.098559846 | Z4: ='Динамика финансы'!AB31 -> -1.0579162 | AA4: ='Динамика финансы'!AC31 -> -0.10426806 | AB4: ='Динамика финансы'!AD31 -> 0.34210081
C5: ='Динамика финансы'!B32 -> 15-21.12 туники | D5: ='Динамика финансы'!C32 -> 0 | E5: ='Динамика финансы'!D32 -> 0 | F5: ='Динамика финансы'!E32 -> 2202.8352 | G5: ='Динамика финансы'!I32 -> 9580 | H5: ='Динамика финансы'!J32 -> -3080 | I5: ='Динамика финансы'!K32 -> 6500 | J5: ='Динамика финансы'!L32 -> 687 | K5: ='Динамика финансы'!M32 -> 604.57 | L5: ='Динамика финансы'!N32 -> 2795 | M5: ='Динамика финансы'!O32 -> 0 | N5: ='Динамика финансы'!P32 -> 0 | ... W5: ='Динамика финансы'!Y32 -> 1450.8352 | Y5: ='Динамика финансы'!AA32 -> 0.10569231 | Z5: ='Динамика финансы'!AB32 -> 2.1118417 | AA5: ='Динамика финансы'!AC32 -> 0.22320542 | AB5: ='Динамика финансы'!AD32 -> 0.13809151
F8: =F4+F5+F6+F7 -> 2450.57 | G8: =G4+G5+G6+G7 -> 70694 | H8: =H4+H5+H6+H7 -> -6471 | I8: =I4+I5+I6+I7 -> 64223 | J8: =J4+J5+J6+J7 -> 6376.17 | K8: =K4+K5+K6+K7 -> 7974.8 | L8: =L4+L5+L6+L7 -> 27615.89 | M8: =M4+M5+M6+M7 -> 0 | ... W8: =W4+W5+W6+W7 -> -4567.83
C11: АНАЛИЗ ФИНАНСОВЫХ ПОКАЗАТЕЛЕЙ ЗА | G11: 15-21.12
C13: ОЧКИ | I13: ТУНИКИ
C15: Выручка | E15: =I4 -> 57723 | F15: руб. | G15: ='Динамика финансы'!K51 -> 0.034759071 | I15: Выручка | K15: =I5 -> 6500 | L15: руб. | M15: ='Динамика финансы'!K52 -> -0.23637218
C16: Прибыль | E16: =W4 -> -6018.6652 | F16: руб. | G16: ='Динамика финансы'!Y51 -> -5.7290272 | I16: Прибыль | K16: =W5 -> 1450.8352 | L16: руб. | M16: ='Динамика финансы'!Y52 -> 0.10824112
C17: Себестоимость продаж | E17: =J4 -> 5689.17 | F17: руб. | G17: ='Динамика финансы'!L51 -> 0.10322581 | I17: Себестоимость продаж | K17: =J5 -> 687 | L17: руб. | M17: ='Динамика финансы'!L52 -> -0.64050235
G18: % от выручки | M18: % от выручки
C19: Логистика | E19: =K4 -> 7370.23 | F19: руб. | G19: ='Динамика финансы'!M48 -> 0.12768273 | I19: Логистика | K19: =K5 -> 604.57 | L19: руб. | M19: ='Динамика финансы'!M49 -> 0.093010769
C20: Реклама | E20: =P4 -> 19747.085 | F20: руб. | G20: ='Динамика финансы'!R48 -> 0.34210081 | I20: Реклама | K20: =P5 -> 897.59478 | L20: руб. | M20: ='Динамика финансы'!R49 -> 0.13809151
C22: Возвраты | E22: =H4 -> -3391 | F22: руб. | G22: ='Динамика финансы'!J48 -> 0.055486468 | I22: Возвраты | K22: =H5 -> -3080 | L22: руб. | M22: ='Динамика финансы'!J49 -> 0.32150313
C23: Комиссия | E23: =L4 -> 24820.89 | F23: руб. | G23: ='Динамика финансы'!N48 -> 0.43 | I23: Комиссия | K23: =L5 -> 2795 | L23: руб. | M23: ='Динамика финансы'!N49 -> 0.43
E25: Маржинальность | G25: =Z4 -> -1.0579162 | K25: Маржинальность | M25: =Z5 -> 2.1118417
E26: Рентабельность | G26: =AA4 -> -0.10426806 | K26: Рентабельность | M26: =AA5 -> 0.22320542
E27: % себестоимости | G27: =Y4 -> 0.098559846 | K27: % себестоимости | M27: =Y5 -> 0.10569231
F29: На остатках товара на | H29: ='Юнит 15-21.12'!I51 -> 808739.01 | I29: руб.

Sheet Дашборд 08-14.12
B2: Период | E2: Дата поступления дс | F2: Итого к перечислению на счет, руб | G2: Выручка | J2: Себестоимость продаж | K2: Логистика | L2: Комиссия | M2: Хранение | N2: Платная приемка | O2: Штрафы | P2: Реклама Ozon | Q2: Прочее | R2: Доп. услуги | S2: Услуги FBO | T2: Компенсировано | U2: Прочие начисления | V2: Налог | W2: Итого | Y2: % Cебестоимости | Z2: Маржинальность, % | AA2: Рентабельность, % | AB2: Доля рекламы, %
B3: Месяц | C3: Даты | D3: Нед | G3: Продажи | H3: Возвраты | I3: Общая
C4: ='Динамика финансы'!B29 -> 08-14.12 очки | D4: ='Динамика финансы'!C29 -> 0 | E4: ='Динамика финансы'!D29 -> 0 | F4: ='Динамика финансы'!E29 -> 6987.3968 | G4: ='Динамика финансы'!I29 -> 59828 | H4: ='Динамика финансы'!J29 -> -4044 | I4: ='Динамика финансы'!K29 -> 55784 | J4: ='Динамика финансы'!L29 -> 5156.85 | K4: ='Динамика финансы'!M29 -> 6498.4 | L4: ='Динамика финансы'!N29 -> 23987.12 | M4: ='Динамика финансы'!O29 -> 0 | N4: ='Динамика финансы'!P29 -> 0 | ... W4: ='Динамика финансы'!Y29 -> 1272.7068 | Y4: ='Динамика финансы'!AA29 -> 0.092443174 | Z4: ='Динамика финансы'!AB29 -> 0.24679927 | AA4: ='Динамика финансы'!AC29 -> 0.022814908 | AB4: ='Динамика финансы'!AD29 -> 0.18201157
C5: ='Динамика финансы'!B30 -> 08-14.12 туники | D5: ='Динамика финансы'!C30 -> 0 | E5: ='Динамика финансы'!D30 -> 0 | F5: ='Динамика финансы'!E30 -> 3305.2532 | G5: ='Динамика финансы'!I30 -> 8512 | H5: ='Динамика финансы'!J30 -> 0 | I5: ='Динамика финансы'!K30 -> 8512 | J5: ='Динамика финансы'!L30 -> 1911 | K5: ='Динамика финансы'!M30 -> 803.66 | L5: ='Динамика финансы'!N30 -> 3660.16 | M5: ='Динамика финансы'!O30 -> 0 | N5: ='Динамика финансы'!P30 -> 0 | ... W5: ='Динамика финансы'!Y30 -> 1309.1332 | Y5: ='Динамика финансы'!AA30 -> 0.22450658 | Z5: ='Динамика финансы'!AB30 -> 0.68505138 | AA5: ='Динамика финансы'!AC30 -> 0.15379854 | AB5: ='Динамика финансы'!AD30 -> 0.087279936
F8: =F4+F5+F6+F7 -> 10292.65 | G8: =G4+G5+G6+G7 -> 68340 | H8: =H4+H5+H6+H7 -> -4044 | I8: =I4+I5+I6+I7 -> 64296 | J8: =J4+J5+J6+J7 -> 7067.85 | K8: =K4+K5+K6+K7 -> 7302.06 | L8: =L4+L5+L6+L7 -> 27647.28 | M8: =M4+M5+M6+M7 -> 0 | ... W8: =W4+W5+W6+W7 -> 2581.84
C11: АНАЛИЗ ФИНАНСОВЫХ ПОКАЗАТЕЛЕЙ ЗА | G11: 08-14.12
C13: ОЧКИ | I13: ТУНИКИ
C15: Выручка | E15: =I4 -> 55784 | F15: руб. | G15: ='Динамика финансы'!K58 -> -0.35748264 | I15: Выручка | K15: =I5 -> 8512 | L15: руб. | M15: ='Динамика финансы'!K59 -> -2.5476364
C16: Прибыль | E16: =W4 -> 1272.7068 | F16: руб. | G16: ='Динамика финансы'!Y58 -> -0.92101569 | I16: Прибыль | K16: =W5 -> 1309.1332 | L16: руб. | M16: ='Динамика финансы'!Y59 -> 1.3557047
C17: Себестоимость продаж | E17: =J4 -> 5156.85 | F17: руб. | G17: ='Динамика финансы'!L58 -> -0.33142882 | I17: Себестоимость продаж | K17: =J5 -> 1911 | L17: руб. | M17: ='Динамика финансы'!L59 -> -4.201005
G18: % от выручки | M18: % от выручки
C19: Логистика | E19: =K4 -> 6498.4 | F19: руб. | G19: ='Динамика финансы'!M55 -> 0.11649218 | I19: Логистика | K19: =K5 -> 803.66 | L19: руб. | M19: ='Динамика финансы'!M56 -> 0.094414944
C20: Реклама | E20: =P4 -> 10153.333 | F20: руб. | G20: ='Динамика финансы'!R55 -> 0.18201157 | I20: Реклама | K20: =P5 -> 742.92682 | L20: руб. | M20: ='Динамика финансы'!R56 -> 0.087279936
C22: Возвраты | E22: =H4 -> -4044 | F22: руб. | G22: ='Динамика финансы'!J55 -> 0.067593769 | I22: Возвраты | K22: =H5 -> 0 | L22: руб. | M22: ='Динамика финансы'!J56 -> 0
C23: Комиссия | E23: =L4 -> 23987.12 | F23: руб. | G23: ='Динамика финансы'!N55 -> 0.43 | I23: Комиссия | K23: =L5 -> 3660.16 | L23: руб. | M23: ='Динамика финансы'!N56 -> 0.43
E25: Маржинальность | G25: =Z4 -> 0.24679927 | K25: Маржинальность | M25: =Z5 -> 0.68505138
E26: Рентабельность | G26: =AA4 -> 0.022814908 | K26: Рентабельность | M26: =AA5 -> 0.15379854
E27: % себестоимости | G27: =Y4 -> 0.092443174 | K27: % себестоимости | M27: =Y5 -> 0.22450658
F29: На остатках товара на | H29: ='Юнит 24-30.11'!I51 -> 728189.41 | I29: руб.

Sheet Дашборд 01-07.12
B2: Период | E2: Дата поступления дс | F2: Итого к перечислению на счет, руб | G2: Выручка | J2: Себестоимость продаж | K2: Логистика | L2: Комиссия | M2: Хранение | N2: Платная приемка | O2: Штрафы | P2: Реклама Ozon | Q2: Прочее | R2: Доп. услуги | S2: Услуги FBO | T2: Компенсировано | U2: Прочие начисления | V2: Налог | W2: Итого | Y2: % Cебестоимости | Z2: Маржинальность, % | AA2: Рентабельность, % | AB2: Доля рекламы, %
B3: Месяц | C3: Даты | D3: Нед | G3: Продажи | H3: Возвраты | I3: Общая
C4: ='Динамика финансы'!B27 -> 01-07.12 очки | D4: ='Динамика финансы'!C27 -> 0 | E4: ='Динамика финансы'!D27 -> 0 | F4: ='Динамика финансы'!E27 -> 24694.863 | G4: ='Динамика финансы'!I27 -> 86821 | H4: ='Динамика финансы'!J27 -> 0 | I4: ='Динамика финансы'!K27 -> 86821 | J4: ='Динамика финансы'!L27 -> 7713.24 | K4: ='Динамика финансы'!M27 -> 8892.35 | L4: ='Динамика финансы'!N27 -> 37333.03 | M4: ='Динамика финансы'!O27 -> 0 | N4: ='Динамика финансы'!P27 -> 0 | ... W4: ='Динамика финансы'!Y27 -> 16113.413 | Y4: ='Динамика финансы'!AA27 -> 0.088840718 | Z4: ='Динамика финансы'!AB27 -> 2.0890589 | AA4: ='Динамика финансы'!AC27 -> 0.1855935 | AB4: ='Динамика финансы'!AD27 -> 0.15322395
C5: ='Динамика финансы'!B28 -> 01-07.12 туники | D5: ='Динамика финансы'!C28 -> 0 | E5: ='Динамика финансы'!D28 -> 0 | F5: ='Динамика финансы'!E28 -> -4332.3931 | G5: ='Динамика финансы'!I28 -> 6500 | H5: ='Динамика финансы'!J28 -> -12000 | I5: ='Динамика финансы'!K28 -> -5500 | J5: ='Динамика финансы'!L28 -> -597 | K5: ='Динамика финансы'!M28 -> 968.03 | L5: ='Динамика финансы'!N28 -> -2365 | M5: ='Динамика финансы'!O28 -> 0 | N5: ='Динамика финансы'!P28 -> 0 | ... W5: ='Динамика финансы'!Y28 -> -3680.3931 | Y5: ='Динамика финансы'!AA28 -> 0.10854545 | Z5: ='Динамика финансы'!AB28 -> 6.1648125 | AA5: ='Динамика финансы'!AC28 -> 0.66916237 | AB5: ='Динамика финансы'!AD28 -> -0.041702373
F8: =F4+F5+F6+F7 -> 20362.47 | G8: =G4+G5+G6+G7 -> 93321 | H8: =H4+H5+H6+H7 -> -12000 | I8: =I4+I5+I6+I7 -> 81321 | J8: =J4+J5+J6+J7 -> 7116.24 | K8: =K4+K5+K6+K7 -> 9860.38 | L8: =L4+L5+L6+L7 -> 34968.03 | M8: =M4+M5+M6+M7 -> 0 | ... W8: =W4+W5+W6+W7 -> 12433.02
C11: АНАЛИЗ ФИНАНСОВЫХ ПОКАЗАТЕЛЕЙ ЗА | G11: 01-07.12
C13: ОЧКИ | I13: ТУНИКИ
C15: Выручка | E15: =I4 -> 86821 | F15: руб. | G15: ='Динамика финансы'!K65 -> 0.72004517 | I15: Выручка | K15: =I5 -> -5500 | L15: руб. | M15: ='Динамика финансы'!K66 -> -1.9166667
C16: Прибыль | E16: =W4 -> 16113.413 | F16: руб. | G16: ='Динамика финансы'!Y65 -> 4.5139535 | I16: Прибыль | K16: =W5 -> -3680.3931 | L16: руб. | M16: ='Динамика финансы'!Y66 -> -6.9927488
C17: Себестоимость продаж | E17: =J4 -> 7713.24 | F17: руб. | G17: ='Динамика финансы'!L65 -> 0.78929933 | I17: Себестоимость продаж | K17: =J5 -> -597 | L17: руб. | M17: ='Динамика финансы'!L66 -> -1.9521531
G18: % от выручки | M18: % от выручки
C19: Логистика | E19: =K4 -> 8892.35 | F19: руб. | G19: ='Динамика финансы'!M62 -> 0.10242165 | I19: Логистика | K19: =K5 -> 968.03 | L19: руб. | M19: ='Динамика финансы'!M63 -> -0.17600545
C20: Реклама | E20: =P4 -> 13303.057 | F20: руб. | G20: ='Динамика финансы'!R62 -> 0.15322395 | I20: Реклама | K20: =P5 -> 229.36305 | L20: руб. | M20: ='Динамика финансы'!R63 -> -0.041702373
C22: Возвраты | E22: =H4 -> 0 | F22: руб. | G22: ='Динамика финансы'!J62 -> 0 | I22: Возвраты | K22: =H5 -> -12000 | L22: руб. | M22: ='Динамика финансы'!J63 -> 1.8461538
C23: Комиссия | E23: =L4 -> 37333.03 | F23: руб. | G23: ='Динамика финансы'!N62 -> 0.43 | I23: Комиссия | K23: =L5 -> -2365 | L23: руб. | M23: ='Динамика финансы'!N63 -> 0.43
E25: Маржинальность | G25: =Z4 -> 2.0890589 | K25: Маржинальность | M25: =Z5 -> 6.1648125
E26: Рентабельность | G26: =AA4 -> 0.1855935 | K26: Рентабельность | M26: =AA5 -> 0.66916237
E27: % себестоимости | G27: =Y4 -> 0.088840718 | K27: % себестоимости | M27: =Y5 -> 0.10854545
F29: На остатках товара на | H29: ='Юнит 24-30.11'!I51 -> 728189.41 | I29: руб.

Sheet Дашборд 24-30.11
B2: Период | E2: Дата поступления дс | F2: Итого к перечислению на счет, руб | G2: Выручка | J2: Себестоимость продаж | K2: Логистика | L2: Комиссия | M2: Хранение | N2: Платная приемка | O2: Штрафы | P2: Реклама Ozon | Q2: Прочее | R2: Доп. услуги | S2: Услуги FBO | T2: Компенсировано | U2: Прочие начисления | V2: Налог | W2: Итого | Y2: % Cебестоимости | Z2: Маржинальность, % | AA2: Рентабельность, % | AB2: Доля рекламы, %
B3: Месяц | C3: Даты | D3: Нед | G3: Продажи | H3: Возвраты | I3: Общая
C4: ='Динамика финансы'!B25 -> 24-30.11 очки | D4: ='Динамика финансы'!C25 -> 0 | E4: ='Динамика финансы'!D25 -> 0 | F4: ='Динамика финансы'!E25 -> 229.96895 | G4: ='Динамика финансы'!I25 -> 56557 | H4: ='Динамика финансы'!J25 -> -6081 | I4: ='Динамика финансы'!K25 -> 50476 | J4: ='Динамика финансы'!L25 -> 4310.76 | K4: ='Динамика финансы'!M25 -> 5747.37 | L4: ='Динамика финансы'!N25 -> 21704.68 | M4: ='Динамика финансы'!O25 -> 0 | N4: ='Динамика финансы'!P25 -> 0 | ... W4: ='Динамика финансы'!Y25 -> -4585.5511 | Y4: ='Динамика финансы'!AA25 -> 0.085402171 | Z4: ='Динамика финансы'!AB25 -> -1.0637454 | AA4: ='Динамика финансы'!AC25 -> -0.090846166 | AB4: ='Динамика финансы'!AD25 -> 0.4273338
C5: ='Динамика финансы'!B26 -> 24-30.11 туники | D5: ='Динамика финансы'!C26 -> 0 | E5: ='Динамика финансы'!D26 -> 0 | F5: ='Динамика финансы'!E26 -> 1301.1411 | G5: ='Динамика финансы'!I26 -> 12000 | H5: ='Динамика финансы'!J26 -> -6000 | I5: ='Динамика финансы'!K26 -> 6000 | J5: ='Динамика финансы'!L26 -> 627 | K5: ='Динамика финансы'!M26 -> 920.52 | L5: ='Динамика финансы'!N26 -> 2580 | M5: ='Динамика финансы'!O26 -> 0 | N5: ='Динамика финансы'!P26 -> 0 | ... W5: ='Динамика финансы'!Y26 -> 614.14105 | Y5: ='Динамика финансы'!AA26 -> 0.1045 | Z5: ='Динамика финансы'!AB26 -> 0.97949131 | AA5: ='Динамика финансы'!AC26 -> 0.10235684 | AB5: ='Динамика финансы'!AD26 -> 0.19972316
F8: =F4+F5+F6+F7 -> 1531.11 | G8: =G4+G5+G6+G7 -> 68557 | H8: =H4+H5+H6+H7 -> -12081 | I8: =I4+I5+I6+I7 -> 56476 | J8: =J4+J5+J6+J7 -> 4937.76 | K8: =K4+K5+K6+K7 -> 6667.89 | L8: =L4+L5+L6+L7 -> 24284.68 | M8: =M4+M5+M6+M7 -> 0 | ... W8: =W4+W5+W6+W7 -> -3971.41
C11: АНАЛИЗ ФИНАНСОВЫХ ПОКАЗАТЕЛЕЙ ЗА | G11: 24-30.11
C13: ОЧКИ | I13: ТУНИКИ
C15: Выручка | E15: =I4 -> 50476 | F15: руб. | G15: ='Динамика финансы'!K72 -> 0.028003503 | I15: Выручка | K15: =I5 -> 6000 | L15: руб. | M15: ='Динамика финансы'!K73 -> -0.23312883
C16: Прибыль | E16: =W4 -> -4585.5511 | F16: руб. | G16: ='Динамика финансы'!Y72 -> 0.60551032 | I16: Прибыль | K16: =W5 -> 614.14105 | L16: руб. | M16: ='Динамика финансы'!Y73 -> 1.523006
C17: Себестоимость продаж | E17: =J4 -> 4310.76 | F17: руб. | G17: ='Динамика финансы'!L72 -> 0.01912111 | I17: Себестоимость продаж | K17: =J5 -> 627 | L17: руб. | M17: ='Динамика финансы'!L73 -> -0.4877451
G18: % от выручки | M18: % от выручки
C19: Логистика | E19: =K4 -> 5747.37 | F19: руб. | G19: ='Динамика финансы'!M69 -> 0.11386342 | I19: Логистика | K19: =K5 -> 920.52 | L19: руб. | M19: ='Динамика финансы'!M70 -> 0.15342
C20: Реклама | E20: =P4 -> 21570.101 | F20: руб. | G20: ='Динамика финансы'!R69 -> 0.4273338 | I20: Реклама | K20: =P5 -> 1198.3389 | L20: руб. | M20: ='Динамика финансы'!R70 -> 0.19972316
C22: Возвраты | E22: =H4 -> -6081 | F22: руб. | G22: ='Динамика финансы'!J69 -> 0.10751985 | I22: Возвраты | K22: =H5 -> -6000 | L22: руб. | M22: ='Динамика финансы'!J70 -> 0.5
C23: Комиссия | E23: =L4 -> 21704.68 | F23: руб. | G23: ='Динамика финансы'!N69 -> 0.43 | I23: Комиссия | K23: =L5 -> 2580 | L23: руб. | M23: ='Динамика финансы'!N70 -> 0.43
E25: Маржинальность | G25: =Z4 -> -1.0637454 | K25: Маржинальность | M25: =Z5 -> 0.97949131
E26: Рентабельность | G26: =AA4 -> -0.090846166 | K26: Рентабельность | M26: =AA5 -> 0.10235684
E27: % себестоимости | G27: =Y4 -> 0.085402171 | K27: % себестоимости | M27: =Y5 -> 0.1045
F29: На остатках товара на | H29: ='Юнит 24-30.11'!I51 -> 728189.41 | I29: руб.

Sheet Дашборд 17-23.11
B2: Период | E2: Дата поступления дс | F2: Итого к перечислению на счет, руб | G2: Выручка | J2: Себестоимость продаж | K2: Логистика | L2: Комиссия | M2: Хранение | N2: Платная приемка | O2: Штрафы | P2: Реклама Ozon | Q2: Прочее | R2: Доп. услуги | S2: Услуги FBO | T2: Компенсировано | U2: Прочие начисления | V2: Налог | W2: Итого | Y2: % Cебестоимости | Z2: Маржинальность, % | AA2: Рентабельность, % | AB2: Доля рекламы, %
B3: Месяц | C3: Даты | D3: Нед | G3: Продажи | H3: Возвраты | I3: Общая
C4: ='Динамика финансы'!B23 -> 17-23.11 очки | D4: ='Динамика финансы'!C23 -> 0 | E4: ='Динамика финансы'!D23 -> 0 | F4: ='Динамика финансы'!E23 -> -6903.1175 | G4: ='Динамика финансы'!I23 -> 52152 | H4: ='Динамика финансы'!J23 -> -3051 | I4: ='Динамика финансы'!K23 -> 49101 | J4: ='Динамика финансы'!L23 -> 4229.88 | K4: ='Динамика финансы'!M23 -> 5536.12 | L4: ='Динамика финансы'!N23 -> 21012.9 | M4: ='Динамика финансы'!O23 -> 0 | N4: ='Динамика финансы'!P23 -> 0 | ... W4: ='Динамика финансы'!Y23 -> -11624.008 | Y4: ='Динамика финансы'!AA23 -> 0.086146514 | Z4: ='Динамика финансы'!AB23 -> -2.7480703 | AA4: ='Динамика финансы'!AC23 -> -0.23673668 | AB4: ='Динамика финансы'!AD23 -> 0.56864193
C5: ='Динамика финансы'!B24 -> 17-23.11 туники | D5: ='Динамика финансы'!C24 -> 0 | E5: ='Динамика финансы'!D24 -> 0 | F5: ='Динамика финансы'!E24 -> 127.9875 | G5: ='Динамика финансы'!I24 -> 13324 | H5: ='Динамика финансы'!J24 -> -5500 | I5: ='Динамика финансы'!K24 -> 7824 | J5: ='Динамика финансы'!L24 -> 1224 | K5: ='Динамика финансы'!M24 -> 1518.43 | L5: ='Динамика финансы'!N24 -> 3639.32 | M5: ='Динамика финансы'!O24 -> 0 | N5: ='Динамика финансы'!P24 -> 0 | ... W5: ='Динамика финансы'!Y24 -> -1174.2525 | Y5: ='Динамика финансы'!AA24 -> 0.15644172 | Z5: ='Динамика финансы'!AB24 -> -0.95935662 | AA5: ='Динамика финансы'!AC24 -> -0.1500834 | AB5: ='Динамика финансы'!AD24 -> 0.32442005
F8: =F4+F5+F6+F7 -> -6775.13 | G8: =G4+G5+G6+G7 -> 65476 | H8: =H4+H5+H6+H7 -> -8551 | I8: =I4+I5+I6+I7 -> 56925 | J8: =J4+J5+J6+J7 -> 5453.88 | K8: =K4+K5+K6+K7 -> 7054.55 | L8: =L4+L5+L6+L7 -> 24652.22 | M8: =M4+M5+M6+M7 -> 0 | ... W8: =W4+W5+W6+W7 -> -12798.26
C11: АНАЛИЗ ФИНАНСОВЫХ ПОКАЗАТЕЛЕЙ ЗА | G11: 10-16.11
C13: ОЧКИ | I13: ТУНИКИ
C15: Выручка | E15: =I4 -> 49101 | F15: руб. | G15: ='Динамика финансы'!K79 -> 0.25648703 | I15: Выручка | K15: =I5 -> 7824 | L15: руб. | M15: ='Динамика финансы'!K80 -> -0.60436893
C16: Прибыль | E16: =W4 -> -11624.008 | F16: руб. | G16: ='Динамика финансы'!Y79 -> 0.16602075 | I16: Прибыль | K16: =W5 -> -1174.2525 | L16: руб. | M16: ='Динамика финансы'!Y80 -> 1.5297765
C17: Себестоимость продаж | E17: =J4 -> 4229.88 | F17: руб. | G17: ='Динамика финансы'!L79 -> 0.18133604 | I17: Себестоимость продаж | K17: =J5 -> 1224 | L17: руб. | M17: ='Динамика финансы'!L80 -> -0.5177305
G18: % от выручки | M18: % от выручки
C19: Логистика | E19: =K4 -> 5536.12 | F19: руб. | G19: ='Динамика финансы'!M76 -> 0.11274964 | I19: Логистика | K19: =K5 -> 1518.43 | L19: руб. | M19: ='Динамика финансы'!M77 -> 0.19407336
C20: Реклама | E20: =P4 -> 27920.888 | F20: руб. | G20: ='Динамика финансы'!R76 -> 0.56864193 | I20: Реклама | K20: =P5 -> 2538.2625 | L20: руб. | M20: ='Динамика финансы'!R77 -> 0.32442005
C22: Возвраты | E22: =H4 -> -3051 | F22: руб. | G22: ='Динамика финансы'!J76 -> 0.058502071 | I22: Возвраты | K22: =H5 -> -5500 | L22: руб. | M22: ='Динамика финансы'!J77 -> 0.41278895
C23: Комиссия | E23: =L4 -> 21012.9 | F23: руб. | G23: ='Динамика финансы'!N76 -> 0.42795259 | I23: Комиссия | K23: =L5 -> 3639.32 | L23: руб. | M23: ='Динамика финансы'!N77 -> 0.46514826
E25: Маржинальность | G25: =Z4 -> -2.7480703 | K25: Маржинальность | M25: =Z5 -> -0.95935662
E26: Рентабельность | G26: =AA4 -> -0.23673668 | K26: Рентабельность | M26: =AA5 -> -0.1500834
E27: % себестоимости | G27: =Y4 -> 0.086146514 | K27: % себестоимости | M27: =Y5 -> 0.15644172
F29: На остатках товара на | H29: ='Юнит 17-23.11'!I51 -> 736264.3 | I29: руб.

Sheet Дашборд 10-16.11
B2: Период | E2: Дата поступления дс | F2: Итого к перечислению на счет, руб | G2: Выручка | J2: Себестоимость продаж | K2: Логистика | L2: Комиссия | M2: Хранение | N2: Платная приемка | O2: Штрафы | P2: Реклама Ozon | Q2: Прочее | R2: Доп. услуги | S2: Услуги FBO | T2: Компенсировано | U2: Прочие начисления | V2: Налог | W2: Итого | Y2: % Cебестоимости | Z2: Маржинальность, % | AA2: Рентабельность, % | AB2: Доля рекламы, %
B3: Месяц | C3: Даты | D3: Нед | G3: Продажи | H3: Возвраты | I3: Общая
C4: ='Динамика финансы'!B21 -> 10-16.11 очки | D4: ='Динамика финансы'!C21 -> 0 | E4: ='Динамика финансы'!D21 -> 0 | F4: ='Динамика финансы'!E21 -> -9966.6356 | G4: ='Динамика финансы'!I21 -> 40442 | H4: ='Динамика финансы'!J21 -> -1364 | I4: ='Динамика финансы'!K21 -> 39078 | J4: ='Динамика финансы'!L21 -> 3580.59 | K4: ='Динамика финансы'!M21 -> 2866.97 | L4: ='Динамика финансы'!N21 -> 16247.94 | M4: ='Динамика финансы'!O21 -> 0 | N4: ='Динамика финансы'!P21 -> 0 | ... W4: ='Динамика финансы'!Y21 -> -13938.006 | Y4: ='Динамика финансы'!AA21 -> 0.091626747 | Z4: ='Динамика финансы'!AB21 -> -3.8926561 | AA4: ='Динамика финансы'!AC21 -> -0.35667142 | AB4: ='Динамика финансы'!AD21 -> 0.63833041
C5: ='Динамика финансы'!B22 -> 10-16.11 туники | D5: ='Динамика финансы'!C22 -> 0 | E5: ='Динамика финансы'!D22 -> 0 | F5: ='Динамика финансы'!E22 -> 4952.2656 | G5: ='Динамика финансы'!I22 -> 25276 | H5: ='Динамика финансы'!J22 -> -5500 | I5: ='Динамика финансы'!K22 -> 19776 | J5: ='Динамика финансы'!L22 -> 2538 | K5: ='Динамика финансы'!M22 -> 1700.67 | L5: ='Динамика финансы'!N22 -> 8503.68 | M5: ='Динамика финансы'!O22 -> 0 | N5: ='Динамика финансы'!P22 -> 0 | ... W5: ='Динамика финансы'!Y22 -> 2216.5056 | Y5: ='Динамика финансы'!AA22 -> 0.12833738 | Z5: ='Динамика финансы'!AB22 -> 0.87332767 | AA5: ='Динамика финансы'!AC22 -> 0.11208058 | AB5: ='Динамика финансы'!AD22 -> 0.23358537
F8: =F4+F5+F6+F7 -> -5014.37 | G8: =G4+G5+G6+G7 -> 65718 | H8: =H4+H5+H6+H7 -> -6864 | I8: =I4+I5+I6+I7 -> 58854 | J8: =J4+J5+J6+J7 -> 6118.59 | K8: =K4+K5+K6+K7 -> 4567.64 | L8: =L4+L5+L6+L7 -> 24751.62 | M8: =M4+M5+M6+M7 -> 0 | ... W8: =W4+W5+W6+W7 -> -11721.5
C11: АНАЛИЗ ФИНАНСОВЫХ ПОКАЗАТЕЛЕЙ ЗА | G11: 10-16.11
C13: ОЧКИ | I13: ТУНИКИ
C15: Выручка | E15: =I4 -> 39078 | F15: руб. | G15: ='Динамика финансы'!K86 -> 1.7292918 | I15: Выручка | K15: =I5 -> 19776 | L15: руб. | M15: ='Динамика финансы'!K87 -> -0.015923567
C16: Прибыль | E16: =W4 -> -13938.006 | F16: руб. | G16: ='Динамика финансы'!Y86 -> -0.95433757 | I16: Прибыль | K16: =W5 -> 2216.5056 | L16: руб. | M16: ='Динамика финансы'!Y87 -> -8.2891945
C17: Себестоимость продаж | E17: =J4 -> 3580.59 | F17: руб. | G17: ='Динамика финансы'!L86 -> 1.5249207 | I17: Себестоимость продаж | K17: =J5 -> 2538 | L17: руб. | M17: ='Динамика финансы'!L87 -> -0.076419214
G18: % от выручки | M18: % от выручки
C19: Логистика | E19: =K4 -> 2866.97 | F19: руб. | G19: ='Динамика финансы'!M83 -> 0.073365321 | I19: Логистика | K19: =K5 -> 1700.67 | L19: руб. | M19: ='Динамика финансы'!M84 -> 0.085996663
C20: Реклама | E20: =P4 -> 24944.676 | F20: руб. | G20: ='Динамика финансы'!R83 -> 0.63833041 | I20: Реклама | K20: =P5 -> 4619.3844 | L20: руб. | M20: ='Динамика финансы'!R84 -> 0.23358537
C22: Возвраты | E22: =H4 -> -1364 | F22: руб. | G22: ='Динамика финансы'!J83 -> 0.033727313 | I22: Возвраты | K22: =H5 -> -5500 | L22: руб. | M22: ='Динамика финансы'!J84 -> 0.21759772
C23: Комиссия | E23: =L4 -> 16247.94 | F23: руб. | G23: ='Динамика финансы'!N83 -> 0.41578228 | I23: Комиссия | K23: =L5 -> 8503.68 | L23: руб. | M23: ='Динамика финансы'!N84 -> 0.43
E25: Маржинальность | G25: =Z4 -> -3.8926561 | K25: Маржинальность | M25: =Z5 -> 0.87332767
E26: Рентабельность | G26: =AA4 -> -0.35667142 | K26: Рентабельность | M26: =AA5 -> 0.11208058
E27: % себестоимости | G27: =Y4 -> 0.091626747 | K27: % себестоимости | M27: =Y5 -> 0.12833738
F29: На остатках товара на | H29: ='Юнит 10-16.11'!I51 -> 740327.11 | I29: руб.

Sheet Дашборд 03-09.11
B2: Период | E2: Дата поступления дс | F2: Итого к перечислению на счет, руб | G2: Выручка | J2: Себестоимость продаж | K2: Логистика | L2: Комиссия | M2: Хранение | N2: Платная приемка | O2: Штрафы | P2: Реклама Ozon | Q2: Прочее | R2: Доп. услуги | S2: Услуги FBO | T2: Компенсировано | U2: Прочие начисления | V2: Налог | W2: Итого | Y2: % Cебестоимости | Z2: Маржинальность, % | AA2: Рентабельность, % | AB2: Доля рекламы, %
B3: Месяц | C3: Даты | D3: Нед | G3: Продажи | H3: Возвраты | I3: Общая
C4: ='Динамика финансы'!B19 -> 03-09.11 очки | D4: ='Динамика финансы'!C19 -> 0 | E4: ='Динамика финансы'!D19 -> 0 | F4: ='Динамика финансы'!E19 -> -5570.5512 | G4: ='Динамика финансы'!I19 -> 14318 | H4: ='Динамика финансы'!J19 -> 0 | I4: ='Динамика финансы'!K19 -> 14318 | J4: ='Динамика финансы'!L19 -> 1418.1 | K4: ='Динамика финансы'!M19 -> 1216 | L4: ='Динамика финансы'!N19 -> 5440.84 | M4: ='Динамика финансы'!O19 -> 0 | N4: ='Динамика финансы'!P19 -> 0 | ... W4: ='Динамика финансы'!Y19 -> -7131.8312 | Y4: ='Динамика финансы'!AA19 -> 0.099043162 | Z4: ='Динамика финансы'!AB19 -> -5.0291455 | AA4: ='Динамика финансы'!AC19 -> -0.49810247 | AB4: ='Динамика финансы'!AD19 -> 0.74072085
C5: ='Динамика финансы'!B20 -> 03-09.11 туники | D5: ='Динамика финансы'!C20 -> 0 | E5: ='Динамика финансы'!D20 -> 0 | F5: ='Динамика финансы'!E20 -> 3187.5712 | G5: ='Динамика финансы'!I20 -> 35645 | H5: ='Динамика финансы'!J20 -> -15549 | I5: ='Динамика финансы'!K20 -> 20096 | J5: ='Динамика финансы'!L20 -> 2748 | K5: ='Динамика финансы'!M20 -> 1848 | L5: ='Динамика финансы'!N20 -> 7636.48 | M5: ='Динамика финансы'!O20 -> 0 | N5: ='Динамика финансы'!P20 -> 0 | ... W5: ='Динамика финансы'!Y20 -> 238.61118 | Y5: ='Динамика финансы'!AA20 -> 0.13674363 | Z5: ='Динамика финансы'!AB20 -> 0.08683085 | AA5: ='Динамика финансы'!AC20 -> 0.011873566 | AB5: ='Динамика финансы'!AD20 -> 0.3694242
F8: =F4+F5+F6+F7 -> -2382.98 | G8: =G4+G5+G6+G7 -> 49963 | H8: =H4+H5+H6+H7 -> -15549 | I8: =I4+I5+I6+I7 -> 34414 | J8: =J4+J5+J6+J7 -> 4166.1 | K8: =K4+K5+K6+K7 -> 3064 | L8: =L4+L5+L6+L7 -> 13077.32 | M8: =M4+M5+M6+M7 -> 0 | ... W8: =W4+W5+W6+W7 -> -6893.22
C11: АНАЛИЗ ФИНАНСОВЫХ ПОКАЗАТЕЛЕЙ ЗА | G11: 03-09.11
C13: ОЧКИ | I13: ТУНИКИ
C15: Выручка | E15: =I4 -> 14318 | F15: руб. | G15: ='Динамика финансы'!K93 -> -0.29293827 | I15: Выручка | K15: =I5 -> 20096 | L15: руб. | M15: ='Динамика финансы'!K94 -> -0.54055784
C16: Прибыль | E16: =W4 -> -7131.8312 | F16: руб. | G16: ='Динамика финансы'!Y93 -> -0.027363739 | I16: Прибыль | K16: =W5 -> 238.61118 | L16: руб. | M16: ='Динамика финансы'!Y94 -> -0.96695235
C17: Себестоимость продаж | E17: =J4 -> 1418.1 | F17: руб. | G17: ='Динамика финансы'!L93 -> -0.60882374 | I17: Себестоимость продаж | K17: =J5 -> 2748 | L17: руб. | M17: ='Динамика финансы'!L94 -> -0.61415333
G18: % от выручки | M18: % от выручки
C19: Логистика | E19: =K4 -> 1216 | F19: руб. | G19: ='Динамика финансы'!M90 -> 0.084928063 | I19: Логистика | K19: =K5 -> 1848 | L19: руб. | M19: ='Динамика финансы'!M91 -> 0.091958599
C20: Реклама | E20: =P4 -> 10605.641 | F20: руб. | G20: ='Динамика финансы'!R90 -> 0.74072085 | I20: Реклама | K20: =P5 -> 7423.9488 | L20: руб. | M20: ='Динамика финансы'!R91 -> 0.3694242
C22: Возвраты | E22: =H4 -> 0 | F22: руб. | G22: ='Динамика финансы'!J90 -> 0 | I22: Возвраты | K22: =H5 -> -15549 | L22: руб. | M22: ='Динамика финансы'!J91 -> 0.43621826
C23: Комиссия | E23: =L4 -> 5440.84 | F23: руб. | G23: ='Динамика финансы'!N90 -> 0.38 | I23: Комиссия | K23: =L5 -> 7636.48 | L23: руб. | M23: ='Динамика финансы'!N91 -> 0.38
E25: Маржинальность | G25: =Z4 -> -5.0291455 | K25: Маржинальность | M25: =Z5 -> 0.08683085
E26: Рентабельность | G26: =AA4 -> -0.49810247 | K26: Рентабельность | M26: =AA5 -> 0.011873566
E27: % себестоимости | G27: =Y4 -> 0.099043162 | K27: % себестоимости | M27: =Y5 -> 0.13674363
F29: На остатках товара на | H29: ='Юнит 03-09.11'!I51 -> 708211.59 | I29: руб.

Sheet Дашборд 27.10-02.11
B2: Период | E2: Дата поступления дс | F2: Итого к перечислению на счет, руб | G2: Выручка | J2: Себестоимость продаж | K2: Логистика | L2: Комиссия | M2: Хранение | N2: Платная приемка | O2: Штрафы | P2: Реклама Ozon | Q2: Прочее | R2: Доп. услуги | S2: Услуги FBO | T2: Компенсировано | U2: Прочие начисления | V2: Налог | W2: Итого | Y2: % Cебестоимости | Z2: Маржинальность, % | AA2: Рентабельность, % | AB2: Доля рекламы, %
B3: Месяц | C3: Даты | D3: Нед | G3: Продажи | H3: Возвраты | I3: Общая
C4: ='Динамика финансы'!B15 -> 27-31.10 очки | D4: ='Динамика финансы'!C15 -> 0 | E4: ='Динамика финансы'!D15 -> 0 | F4: ='Динамика финансы'!E15 -> -4016.9211 | G4: ='Динамика финансы'!I15 -> 13972 | H4: ='Динамика финансы'!J15 -> 0 | I4: ='Динамика финансы'!K15 -> 13972 | J4: ='Динамика финансы'!L15 -> 2317.72 | K4: ='Динамика финансы'!M15 -> 1074 | L4: ='Динамика финансы'!N15 -> 4858.08 | M4: ='Динамика финансы'!O15 -> 0 | N4: ='Динамика финансы'!P15 -> 0 | ... W4: ='Динамика финансы'!Y15 -> -6474.3611 | Y4: ='Динамика финансы'!AA15 -> 0.16588319 | Z4: ='Динамика финансы'!AB15 -> -2.7934181 | AA4: ='Динамика финансы'!AC15 -> -0.46338113 | AB4: ='Динамика финансы'!AD15 -> 0.79899521
C5: ='Динамика финансы'!B16 -> 27-31.10 туники | D5: ='Динамика финансы'!C16 -> 0 | E5: ='Динамика финансы'!D16 -> 0 | F5: ='Динамика финансы'!E16 -> 11712.031 | G5: ='Динамика финансы'!I16 -> 39192 | H5: ='Динамика финансы'!J16 -> -5000 | I5: ='Динамика финансы'!K16 -> 34192 | J5: ='Динамика финансы'!L16 -> 5808 | K5: ='Динамика финансы'!M16 -> 1120 | L5: ='Динамика финансы'!N16 -> 12429.12 | M5: ='Динамика финансы'!O16 -> 0 | N5: ='Динамика финансы'!P16 -> 0 | ... W5: ='Динамика финансы'!Y16 -> 5562.1111 | Y5: ='Динамика финансы'!AA16 -> 0.1698643 | Z5: ='Динамика финансы'!AB16 -> 0.95766376 | AA5: ='Динамика финансы'!AC16 -> 0.16267288 | AB5: ='Динамика финансы'!AD16 -> 0.26119703
C6: ='Динамика финансы'!B17 -> 01-02.11 очки | D6: ='Динамика финансы'!C17 -> 0 | E6: ='Динамика финансы'!D17 -> 0 | F6: ='Динамика финансы'!E17 -> 512.166 | G6: ='Динамика финансы'!I17 -> 6278 | H6: ='Динамика финансы'!J17 -> 0 | I6: ='Динамика финансы'!K17 -> 6278 | J6: ='Динамика финансы'!L17 -> 1307.5 | K6: ='Динамика финансы'!M17 -> 240 | L6: ='Динамика финансы'!N17 -> 2385.64 | M6: ='Динамика финансы'!O17 -> 0 | N6: ='Динамика финансы'!P17 -> 0 | ... W6: ='Динамика финансы'!Y17 -> -858.114 | Y6: ='Динамика финансы'!AA17 -> 0.20826696 | Z6: ='Динамика финансы'!AB17 -> -0.65630134 | AA6: ='Динамика финансы'!AC17 -> -0.13668589 | AB6: ='Динамика финансы'!AD17 -> 0.45400828
C7: ='Динамика финансы'!B18 -> 01-02.11 туники | D7: ='Динамика финансы'!C18 -> 0 | E7: ='Динамика финансы'!D18 -> 0 | F7: ='Динамика финансы'!E18 -> 3067.584 | G7: ='Динамика финансы'!I18 -> 9548 | H7: ='Динамика финансы'!J18 -> 0 | I7: ='Динамика финансы'!K18 -> 9548 | J7: ='Динамика финансы'!L18 -> 1314 | K7: ='Динамика финансы'!M18 -> 952 | L7: ='Динамика финансы'!N18 -> 3628.24 | M7: ='Динамика финансы'!O18 -> 0 | N7: ='Динамика финансы'!P18 -> 0 | ... W7: ='Динамика финансы'!Y18 -> 1658.104 | Y7: ='Динамика финансы'!AA18 -> 0.13762044 | Z7: ='Динамика финансы'!AB18 -> 1.2618752 | AA7: ='Динамика финансы'!AC18 -> 0.17365982 | AB7: ='Динамика финансы'!AD18 -> 0.19901299
F8: =F4+F5+F6+F7 -> 11274.86 | G8: =G4+G5+G6+G7 -> 68990 | H8: =H4+H5+H6+H7 -> -5000 | I8: =I4+I5+I6+I7 -> 63990 | J8: =J4+J5+J6+J7 -> 10747.22 | K8: =K4+K5+K6+K7 -> 3386 | L8: =L4+L5+L6+L7 -> 23301.08 | M8: =M4+M5+M6+M7 -> 0 | ... W8: =W4+W5+W6+W7 -> -112.26
C11: АНАЛИЗ ФИНАНСОВЫХ ПОКАЗАТЕЛЕЙ ЗА | G11: 06-12.10
C13: ОЧКИ | I13: ТУНИКИ
C15: Выручка | E15: =I4+I6 -> 20250 | F15: руб. | G15: ='Динамика финансы'!K100 -> 0.13917642 | I15: Выручка | K15: =I5+I7 -> 43740 | L15: руб. | M15: ='Динамика финансы'!K101 -> 0.65206225
C16: Прибыль | E16: =W4+W6 -> -7332.4751 | F16: руб. | G16: ='Динамика финансы'!Y100 -> 0.060550523 | I16: Прибыль | K16: =W5+W7 -> 7220.2151 | L16: руб. | M16: ='Динамика финансы'!Y101 -> 2.0934032
C17: Себестоимость продаж | E17: =J4+J6 -> 3625.22 | F17: руб. | G17: ='Динамика финансы'!L100 -> 0.35270917 | I17: Себестоимость продаж | K17: =J5+J7 -> 7122 | L17: руб. | M17: ='Динамика финансы'!L101 -> 0.1496368
G18: % от выручки | M18: % от выручки
C19: Логистика | E19: =K4+K6 -> 1314 | F19: руб. | G19: ='Динамика финансы'!M97 -> 0.064888889 | I19: Логистика | K19: =K5+K7 -> 2072 | L19: руб. | M19: ='Динамика финансы'!M98 -> 0.047370828
C20: Реклама | E20: =P4+P6 -> 14013.825 | F20: руб. | G20: ='Динамика финансы'!R97 -> 0.69204075 | I20: Реклама | K20: =P5+P7 -> 10831.025 | L20: руб. | M20: ='Динамика финансы'!R98 -> 0.24762288
C22: Возвраты | E22: =H4+H6 -> 0 | F22: руб. | G22: ='Динамика финансы'!J97 -> 0 | I22: Возвраты | K22: =H5+H7 -> -5000 | L22: руб. | M22: ='Динамика финансы'!J98 -> 0.10258515
C23: Комиссия | E23: =L4+L6 -> 7243.72 | F23: руб. | G23: ='Динамика финансы'!N97 -> 0.35771457 | I23: Комиссия | K23: =L5+L7 -> 16057.36 | L23: руб. | M23: ='Динамика финансы'!N98 -> 0.36710928
E25: Маржинальность | G25: =Z6 -> -0.65630134 | K25: Маржинальность | M25: =Z7 -> 1.2618752
E26: Рентабельность | G26: =AA6 -> -0.13668589 | K26: Рентабельность | M26: =AA7 -> 0.17365982
E27: % себестоимости | G27: =Y6 -> 0.20826696 | K27: % себестоимости | M27: =Y7 -> 0.13762044
F29: На остатках товара на | H29: ='Юнит 27.10-02.11'!I49 -> 654379.2 | I29: руб.

Sheet Дашборд 20-26.10
B2: Период | E2: Дата поступления дс | F2: Итого к перечислению на счет, руб | G2: Выручка | J2: Себестоимость продаж | K2: Логистика | L2: Комиссия | M2: Хранение | N2: Платная приемка | O2: Штрафы | P2: Реклама Ozon | Q2: Прочее | R2: Доп. услуги | S2: Услуги FBO | T2: Компенсировано | U2: Прочие начисления | V2: Налог | W2: Итого | Y2: % Cебестоимости | Z2: Маржинальность, % | AA2: Рентабельность, % | AB2: Доля рекламы, %
B3: Месяц | C3: Даты | D3: Нед | G3: Продажи | H3: Возвраты | I3: Общая
C4: ='Динамика финансы'!B13 -> 20-26.10 очки | D4: ='Динамика финансы'!C13 -> 0 | E4: ='Динамика финансы'!D13 -> 0 | F4: ='Динамика финансы'!E13 -> -4056.1086 | G4: ='Динамика финансы'!I13 -> 17776 | H4: ='Динамика финансы'!J13 -> 0 | I4: ='Динамика финансы'!K13 -> 17776 | J4: ='Динамика финансы'!L13 -> 2679.97 | K4: ='Динамика финансы'!M13 -> 2232 | L4: ='Динамика финансы'!N13 -> 5952.48 | M4: ='Динамика финансы'!O13 -> 0 | N4: ='Динамика финансы'!P13 -> 0 | ... W4: ='Динамика финансы'!Y13 -> -6913.8386 | Y4: ='Динамика финансы'!AA13 -> 0.15076339 | Z4: ='Динамика финансы'!AB13 -> -2.5798194 | AA4: ='Динамика финансы'!AC13 -> -0.38894231 | AB4: ='Динамика финансы'!AD13 -> 0.69204481
C5: ='Динамика финансы'!B14 -> 20-26.10 туники | D5: ='Динамика финансы'!C14 -> 0 | E5: ='Динамика финансы'!D14 -> 0 | F5: ='Динамика финансы'!E14 -> 8793.8286 | G5: ='Динамика финансы'!I14 -> 36024 | H5: ='Динамика финансы'!J14 -> -9548 | I5: ='Динамика финансы'!K14 -> 26476 | J5: ='Динамика финансы'!L14 -> 6195 | K5: ='Динамика финансы'!M14 -> 1848 | L5: ='Динамика финансы'!N14 -> 8263.84 | M5: ='Динамика финансы'!O14 -> 0 | N5: ='Динамика финансы'!P14 -> 0 | ... W5: ='Динамика финансы'!Y14 -> 2334.0686 | Y5: ='Динамика финансы'!AA14 -> 0.2339855 | Z5: ='Динамика финансы'!AB14 -> 0.37676652 | AA5: ='Динамика финансы'!AC14 -> 0.0881579 | AB5: ='Динамика финансы'!AD14 -> 0.28593184
F6: =F4+F5 -> 4737.72 | G6: =G4+G5 -> 53800 | H6: =H4+H5 -> -9548 | I6: =I4+I5 -> 44252 | J6: =J4+J5 -> 8874.97 | K6: =K4+K5 -> 4080 | L6: =L4+L5 -> 14216.32 | M6: =M4+M5 -> 0 | ... W6: =W4+W5 -> -4579.77
C9: АНАЛИЗ ФИНАНСОВЫХ ПОКАЗАТЕЛЕЙ ЗА | G9: 06-12.10
C11: ОЧКИ | I11: ТУНИКИ
C13: Выручка | E13: =I4 -> 17776 | F13: руб. | G13: ='Динамика финансы'!K107 -> -0.01714033 | I13: Выручка | K13: =I4 -> 17776 | L13: руб. | M13: ='Динамика финансы'!K108 -> -0.45688028
C14: Прибыль | E14: =W4 -> -6913.8386 | F14: руб. | G14: ='Динамика финансы'!Y107 -> -1.6266383 | I14: Прибыль | K14: =W5 -> 2334.0686 | L14: руб. | M14: ='Динамика финансы'!Y108 -> -0.74006031
C15: Себестоимость продаж | E15: =J4 -> 2679.97 | F15: руб. | G15: ='Динамика финансы'!L107 -> -0.014202267 | I15: Себестоимость продаж | K15: =J5 -> 6195 | L15: руб. | M15: ='Динамика финансы'!L108 -> -0.46111691
G16: % от выручки | M16: % от выручки
C17: Логистика | E17: =K4 -> 2232 | F17: руб. | G17: ='Динамика финансы'!M104 -> 0.12556256 | I17: Логистика | K17: =K5 -> 1848 | L17: руб. | M17: ='Динамика финансы'!M105 -> 0.069799063
C18: Реклама | E18: =P4 -> 12301.789 | F18: руб. | G18: ='Динамика финансы'!R104 -> 0.69204481 | I18: Реклама | K18: =P5 -> 7570.3314 | L18: руб. | M18: ='Динамика финансы'!R105 -> 0.28593184
C20: Возвраты | E20: =H4 -> 0 | F20: руб. | G20: ='Динамика финансы'!J104 -> 0 | I20: Возвраты | K20: =H5 -> -9548 | L20: руб. | M20: ='Динамика финансы'!J105 -> 0.26504553
C21: Комиссия | E21: =L4 -> 5952.48 | F21: руб. | G21: ='Динамика финансы'!N104 -> 0.33486049 | I21: Комиссия | K21: =L5 -> 8263.84 | L21: руб. | M21: ='Динамика финансы'!N105 -> 0.3121257
E23: Маржинальность | G23: =Z4 -> -2.5798194 | K23: Маржинальность | M23: =Z5 -> 0.37676652
E24: Рентабельность | G24: =AA4 -> -0.38894231 | K24: Рентабельность | M24: =AA5 -> 0.0881579
E25: % себестоимости | G25: =Y4 -> 0.15076339 | K25: % себестоимости | M25: =Y5 -> 0.2339855
F27: На остатках товара на | H27: ='Юнит 20-26.10'!I49 -> 660765.73 | I27: руб.

Sheet Дашборд 13-19.10
B2: Период | E2: Дата поступления дс | F2: Итого к перечислению на счет, руб | G2: Выручка | J2: Себестоимость продаж | K2: Логистика | L2: Комиссия | M2: Хранение | N2: Платная приемка | O2: Штрафы | P2: Реклама Ozon | Q2: Прочее | R2: Доп. услуги | S2: Услуги FBO | T2: Компенсировано | U2: Прочие начисления | V2: Налог | W2: Итого | Y2: % Cебестоимости | Z2: Маржинальность, % | AA2: Рентабельность, % | AB2: Доля рекламы, %
B3: Месяц | C3: Даты | D3: Нед | G3: Продажи | H3: Возвраты | I3: Общая
C4: ='Динамика финансы'!B11 -> 13-19.10 очки | D4: ='Динамика финансы'!C11 -> 0 | E4: ='Динамика финансы'!D11 -> 0 | F4: ='Динамика финансы'!E11 -> 13932.66 | G4: ='Динамика финансы'!I11 -> 18086 | H4: ='Динамика финансы'!J11 -> 0 | I4: ='Динамика финансы'!K11 -> 18086 | J4: ='Динамика финансы'!L11 -> 2718.58 | K4: ='Динамика финансы'!M11 -> 2812 | L4: ='Динамика финансы'!N11 -> 5420.92 | M4: ='Динамика финансы'!O11 -> 0 | N4: ='Динамика финансы'!P11 -> 0 | ... W4: ='Динамика финансы'!Y11 -> 11033.22 | Y4: ='Динамика финансы'!AA11 -> 0.15031406 | Z4: ='Динамика финансы'!AB11 -> 4.0584498 | AA4: ='Динамика финансы'!AC11 -> 0.61004204 | AB4: ='Динамика финансы'!AD11 -> 0.55619483
C5: ='Динамика финансы'!B12 -> 13-19.10 туники | D5: ='Динамика финансы'!C12 -> 0 | E5: ='Динамика финансы'!D12 -> 0 | F5: ='Динамика финансы'!E12 -> 20962.75 | G5: ='Динамика финансы'!I12 -> 58698 | H5: ='Динамика финансы'!J12 -> -9950 | I5: ='Динамика финансы'!K12 -> 48748 | J5: ='Динамика финансы'!L12 -> 11496 | K5: ='Динамика финансы'!M12 -> 3024 | L5: ='Динамика финансы'!N12 -> 13154.32 | M5: ='Динамика финансы'!O12 -> 0 | N5: ='Динамика финансы'!P12 -> 0 | ... W5: ='Динамика финансы'!Y12 -> 8979.2696 | Y5: ='Динамика финансы'!AA12 -> 0.23582506 | Z5: ='Динамика финансы'!AB12 -> 0.78107774 | AA5: ='Динамика финансы'!AC12 -> 0.1841977 | AB5: ='Динамика финансы'!AD12 -> 0.23810065
F6: =F4+F5 -> 34895.41 | G6: =G4+G5 -> 76784 | H6: =H4+H5 -> -9950 | I6: =I4+I5 -> 66834 | J6: =J4+J5 -> 14214.58 | K6: =K4+K5 -> 5836 | L6: =L4+L5 -> 18575.24 | M6: =M4+M5 -> 0 | ... W6: =W4+W5 -> 20012.49
C9: АНАЛИЗ ФИНАНСОВЫХ ПОКАЗАТЕЛЕЙ ЗА | G9: 06-12.10
C11: ОЧКИ | I11: ТУНИКИ
C13: Выручка | E13: =I4 -> 18086 | F13: руб. | G13: ='Динамика финансы'!K114 -> -0.22682969 | I13: Выручка | K13: =I4 -> 18086 | L13: руб. | M13: ='Динамика финансы'!K115 -> 0.094722659
C14: Прибыль | E14: =W4 -> 11033.22 | F14: руб. | G14: ='Динамика финансы'!Y114 -> -9.5247625 | I14: Прибыль | K14: =W5 -> 8979.2696 | L14: руб. | M14: ='Динамика финансы'!Y115 -> -5.2369926
C15: Себестоимость продаж | E15: =J4 -> 2718.58 | F15: руб. | G15: ='Динамика финансы'!L114 -> -0.24431831 | I15: Себестоимость продаж | K15: =J5 -> 11496 | L15: руб. | M15: ='Динамика финансы'!L115 -> 0.2107425
G16: % от выручки | M16: % от выручки
C17: Логистика | E17: =K4 -> 2812 | F17: руб. | G17: ='Динамика финансы'!M111 -> 0.15547938 | I17: Логистика | K17: =K5 -> 3024 | L17: руб. | M17: ='Динамика финансы'!M112 -> 0.062033314
C18: Реклама | E18: =P4 -> 10059.34 | F18: руб. | G18: ='Динамика финансы'!R111 -> 0.55619483 | I18: Реклама | K18: =P5 -> 11606.93 | L18: руб. | M18: ='Динамика финансы'!R112 -> 0.23810065
C20: Возвраты | E20: =H4 -> 0 | F20: руб. | G20: ='Динамика финансы'!J111 -> 0 | I20: Возвраты | K20: =H5 -> -9950 | L20: руб. | M20: ='Динамика финансы'!J112 -> 0.16951174
C21: Комиссия | E21: =L4 -> 5420.92 | F21: руб. | G21: ='Динамика финансы'!N111 -> 0.29973018 | I21: Комиссия | K21: =L5 -> 13154.32 | L21: руб. | M21: ='Динамика финансы'!N112 -> 0.26984328
E23: Маржинальность | G23: =Z4 -> 4.0584498 | K23: Маржинальность | M23: =Z5 -> 0.78107774
E24: Рентабельность | G24: =AA4 -> 0.61004204 | K24: Рентабельность | M24: =AA5 -> 0.1841977
E25: % себестоимости | G25: =Y4 -> 0.15031406 | K25: % себестоимости | M25: =Y5 -> 0.23582506
F27: На остатках товара на | H27: ='Юнит 13-19.10'!I49 -> 664455.27 | I27: руб.

Sheet Дашборд 06-12.10
B2: Период | E2: Дата поступления дс | F2: Итого к перечислению на счет, руб | G2: Выручка | J2: Себестоимость продаж | K2: Логистика | L2: Комиссия | M2: Хранение | N2: Платная приемка | O2: Штрафы | P2: Реклама Ozon | Q2: Прочее | R2: Доп. услуги | S2: Услуги FBO | T2: Компенсировано | U2: Прочие начисления | V2: Налог | W2: Итого | Y2: % Cебестоимости | Z2: Маржинальность, % | AA2: Рентабельность, % | AB2: Доля рекламы, %
B3: Месяц | C3: Даты | D3: Нед | G3: Продажи | H3: Возвраты | I3: Общая
C4: ='Динамика финансы'!B9 -> 06-12.10 очки | D4: ='Динамика финансы'!C9 -> 0 | E4: ='Динамика финансы'!D9 -> 0 | F4: ='Динамика финансы'!E9 -> 4879.7506 | G4: ='Динамика финансы'!I9 -> 24592 | H4: ='Динамика финансы'!J9 -> -1200 | I4: ='Динамика финансы'!K9 -> 23392 | J4: ='Динамика финансы'!L9 -> 3597.52 | K4: ='Динамика финансы'!M9 -> 2096 | L4: ='Динамика финансы'!N9 -> 6111.53 | M4: ='Динамика финансы'!O9 -> 0 | N4: ='Динамика финансы'!P9 -> 0 | ... W4: ='Динамика финансы'!Y9 -> 1048.3106 | Y4: ='Динамика финансы'!AA9 -> 0.15379275 | Z4: ='Динамика финансы'!AB9 -> 0.29139814 | AA4: ='Динамика финансы'!AC9 -> 0.044814921 | AB4: ='Динамика финансы'!AD9 -> 1.0468865
C5: ='Динамика финансы'!B10 -> 06-12.10 туники | D5: ='Динамика финансы'!C10 -> 0 | E5: ='Динамика финансы'!D10 -> 0 | F5: ='Динамика финансы'!E10 -> 11379.979 | G5: ='Динамика финансы'!I10 -> 48220 | H5: ='Динамика финансы'!J10 -> -3690 | I5: ='Динамика финансы'!K10 -> 44530 | J5: ='Динамика финансы'!L10 -> 9495 | K5: ='Динамика финансы'!M10 -> 3416 | L5: ='Динамика финансы'!N10 -> 10687.2 | M5: ='Динамика финансы'!O10 -> 0 | N5: ='Динамика финансы'!P10 -> 0 | ... W5: ='Динамика финансы'!Y10 -> 1439.6794 | Y5: ='Динамика финансы'!AA10 -> 0.21322704 | Z5: ='Динамика финансы'!AB10 -> 0.151625 | AA5: ='Динамика финансы'!AC10 -> 0.03233055 | AB5: ='Динамика финансы'!AD10 -> 0.42773008
F6: =F4+F5 -> 16259.73 | G6: =G4+G5 -> 72812 | H6: =H4+H5 -> -4890 | I6: =I4+I5 -> 67922 | J6: =J4+J5 -> 13092.52 | K6: =K4+K5 -> 5512 | L6: =L4+L5 -> 16798.73 | M6: =M4+M5 -> 0 | ... W6: =W4+W5 -> 2487.99
C9: АНАЛИЗ ФИНАНСОВЫХ ПОКАЗАТЕЛЕЙ ЗА | G9: 06-12.10
C11: ОЧКИ | I11: ТУНИКИ
C13: Выручка | E13: =I4 -> 23392 | F13: руб. | G13: ='Динамика финансы'!K121 -> -0.17222832 | I13: Выручка | K13: =I4 -> 23392 | L13: руб. | M13: ='Динамика финансы'!K122 -> 0.10606061
C14: Прибыль | E14: =W4 -> 1048.3106 | F14: руб. | G14: ='Динамика финансы'!Y121 -> 1.1596892 | I14: Прибыль | K14: =W5 -> 1439.6794 | L14: руб. | M14: ='Динамика финансы'!Y122 -> -0.86174149
C15: Себестоимость продаж | E15: =J4 -> 3597.52 | F15: руб. | G15: ='Динамика финансы'!L121 -> -0.34891112 | I15: Себестоимость продаж | K15: =J5 -> 9495 | L15: руб. | M15: ='Динамика финансы'!L122 -> 0.017357763
G16: % от выручки | M16: % от выручки
C17: Логистика | E17: =K4 -> 2096 | F17: руб. | G17: ='Динамика финансы'!M118 -> 0.089603283 | I17: Логистика | K17: =K5 -> 3416 | L17: руб. | M17: ='Динамика финансы'!M119 -> 0.076712329
C18: Реклама | E18: =P4 -> 24488.769 | F18: руб. | G18: ='Динамика финансы'!R118 -> 1.0468865 | I18: Реклама | K18: =P5 -> 19046.821 | L18: руб. | M18: ='Динамика финансы'!R119 -> 0.42773008
C20: Возвраты | E20: =H4 -> -1200 | F20: руб. | G20: ='Динамика финансы'!J118 -> 0.048796357 | I20: Возвраты | K20: =H5 -> -3690 | L20: руб. | M20: ='Динамика финансы'!J119 -> 0.076524264
C21: Комиссия | E21: =L4 -> 6111.53 | F21: руб. | G21: ='Динамика финансы'!N118 -> 0.26126582 | I21: Комиссия | K21: =L5 -> 10687.2 | L21: руб. | M21: ='Динамика финансы'!N119 -> 0.24
E23: Маржинальность | G23: =Z4 -> 0.29139814 | K23: Маржинальность | M23: =Z5 -> 0.151625
E24: Рентабельность | G24: =AA4 -> 0.044814921 | K24: Рентабельность | M24: =AA5 -> 0.03233055
E25: % себестоимости | G25: =Y4 -> 0.15379275 | K25: % себестоимости | M25: =Y5 -> 0.21322704
F27: На остатках товара на | H27: ='Юнит 06-12.10'!I49 -> 658278.98 | I27: руб.

Sheet Дашборд 01-05.10
B2: Период | E2: Дата поступления дс | F2: Итого к перечислению на счет, руб | G2: Выручка | J2: Себестоимость продаж | K2: Логистика | L2: Комиссия | M2: Хранение | N2: Платная приемка | O2: Штрафы | P2: Реклама Ozon | Q2: Прочее | R2: Доп. услуги | S2: Услуги FBO | T2: Компенсировано | U2: Прочие начисления | V2: Налог | W2: Итого | Y2: % Cебестоимости | Z2: Маржинальность, % | AA2: Рентабельность, % | AB2: Доля рекламы, %
B3: Месяц | C3: Даты | D3: Нед | G3: Продажи | H3: Возвраты | I3: Общая
C4: ='Динамика финансы'!B7 -> 01-05.10 очки | D4: ='Динамика финансы'!C7 -> 0 | E4: ='Динамика финансы'!D7 -> 0 | F4: ='Динамика финансы'!E7 -> -756.71333 | G4: ='Динамика финансы'!I7 -> 32664 | H4: ='Динамика финансы'!J7 -> -4405 | I4: ='Динамика финансы'!K7 -> 28259 | J4: ='Динамика финансы'!L7 -> 5525.39 | K4: ='Динамика финансы'!M7 -> 2442 | L4: ='Динамика финансы'!N7 -> 7126.96 | M4: ='Динамика финансы'!O7 -> 0 | N4: ='Динамика финансы'!P7 -> 0 | ... W4: ='Динамика финансы'!Y7 -> -6564.6933 | Y4: ='Динамика финансы'!AA7 -> 0.19552673 | Z4: ='Динамика финансы'!AB7 -> -1.1880959 | AA4: ='Динамика финансы'!AC7 -> -0.23230452 | AB4: ='Динамика финансы'!AD7 -> 0.64043644
C5: ='Динамика финансы'!B8 -> 01-05.10 туники | D5: ='Динамика финансы'!C8 -> 0 | E5: ='Динамика финансы'!D8 -> 0 | F5: ='Динамика финансы'!E8 -> 20148.553 | G5: ='Динамика финансы'!I8 -> 43950 | H5: ='Динамика финансы'!J8 -> -3690 | I5: ='Динамика финансы'!K8 -> 40260 | J5: ='Динамика финансы'!L8 -> 9333 | K5: ='Динамика финансы'!M8 -> 1400 | L5: ='Динамика финансы'!N8 -> 9662.4 | M5: ='Динамика финансы'!O8 -> 0 | N5: ='Динамика финансы'!P8 -> 0 | ... W5: ='Динамика финансы'!Y8 -> 10412.953 | Y5: ='Динамика финансы'!AA8 -> 0.23181818 | Z5: ='Динамика финансы'!AB8 -> 1.1157134 | AA5: ='Динамика финансы'!AC8 -> 0.25864266 | AB5: ='Динамика финансы'!AD8 -> 0.22476519
F6: =F4+F5 -> 19391.84 | G6: =G4+G5 -> 76614 | H6: =H4+H5 -> -8095 | I6: =I4+I5 -> 68519 | J6: =J4+J5 -> 14858.39 | K6: =K4+K5 -> 3842 | L6: =L4+L5 -> 16789.36 | M6: =M4+M5 -> 0 | ... W6: =W4+W5 -> 3848.26
C9: АНАЛИЗ ФИНАНСОВЫХ ПОКАЗАТЕЛЕЙ ЗА | G9: 01-05.10
C11: ОЧКИ | I11: ТУНИКИ
C13: Выручка | E13: =I4 -> 28259 | F13: руб. | I13: Выручка | K13: =I4 -> 28259 | L13: руб.
C14: Прибыль | E14: =W4 -> -6564.6933 | F14: руб. | I14: Прибыль | K14: =W5 -> 10412.953 | L14: руб.
C15: Себестоимость продаж | E15: =J4 -> 5525.39 | F15: руб. | I15: Себестоимость продаж | K15: =J5 -> 9333 | L15: руб.
G16: % от выручки | M16: % от выручки
C17: Логистика | E17: =K4 -> 2442 | F17: руб. | G17: ='Динамика финансы'!M125 -> 0.086414947 | I17: Логистика | K17: =K5 -> 1400 | L17: руб. | M17: ='Динамика финансы'!M126 -> 0.034773969
C18: Реклама | E18: =P4 -> 18098.093 | F18: руб. | G18: ='Динамика финансы'!R125 -> 0.64043644 | I18: Реклама | K18: =P5 -> 9049.0467 | L18: руб. | M18: ='Динамика финансы'!R126 -> 0.22476519
C20: Возвраты | E20: =H4 -> -4405 | F20: руб. | G20: ='Динамика финансы'!J125 -> 0.13485795 | I20: Возвраты | K20: =H5 -> -3690 | L20: руб. | M20: ='Динамика финансы'!J126 -> 0.083959044
C21: Комиссия | E21: =L4 -> 7126.96 | F21: руб. | G21: ='Динамика финансы'!N125 -> 0.25220142 | I21: Комиссия | K21: =L5 -> 9662.4 | L21: руб. | M21: ='Динамика финансы'!N126 -> 0.24
E23: Маржинальность | G23: =Z4 -> -1.1880959 | K23: Маржинальность | M23: =Z5 -> 1.1157134
E24: Рентабельность | G24: =AA4 -> -0.23230452 | K24: Рентабельность | M24: =AA5 -> 0.25864266
E25: % себестоимости | G25: =Y4 -> 0.19552673 | K25: % себестоимости | M25: =Y5 -> 0.23181818
F27: На остатках товара на | H27: ='Юнит 06-12.10'!I49 -> 658278.98 | I27: руб.

Sheet АВС 2025
B2: ОЧКИ
C3: Прибыль | D3: % прибыль | E3: Доля | F3: ABC прибыль | G3: ABC кол-во | J3: Кол-во | K3: % кол-во | L3: Доля | M3: ABC кол-во
B4: черные с железкой классика | C4: ='2025'!AE3 -> 30922.462 | D4: =C4/C$26 -> -14.345226 | E4: =D4 -> -14.345226 | F4: =IF(AND(E4<=0),"C",IF(E4<=0.8,"A",IF(E4<=0.95,"B","C"))) -> C | G4: =VLOOKUP(B$4:B$25,I$4:M$25,5,0) -> A | I4: черные с железкой классика | J4: ='2025'!R3 -> 267 | K4: =J4/J$26 -> 0.47424512 | L4: =K4 -> 0.47424512 | M4: =_xlfn.IFS(L4<80%,"A",L4<=95%,"B",L4>95%,"C") -> A
B5: qs коричневые | C5: ='2025'!AE7 -> 11793.927 | D5: =C5/C$26 -> -5.4713155 | E5: =D5+E4 -> -19.816541 | F5: =IF(AND(E5<=0),"C",IF(E5<=0.8,"A",IF(E5<=0.95,"B","C"))) -> C | G5: =VLOOKUP(B$4:B$25,I$4:M$25,5,0) -> A | I5: qs желтые | J5: ='2025'!R6 -> 134 | K5: =J5/J$26 -> 0.23801066 | L5: =K5+L4 -> 0.71225577 | M5: =_xlfn.IFS(L5<80%,"A",L5<=95%,"B",L5>95%,"C") -> A
B6: MR Р1874 черн | C6: ='2025'!AE13 -> 7595.9747 | D6: =C6/C$26 -> -3.5238453 | E6: =D6+E5 -> -23.340387 | F6: =IF(AND(E6<=0),"C",IF(E6<=0.8,"A",IF(E6<=0.95,"B","C"))) -> C | G6: =VLOOKUP(B$4:B$25,I$4:M$25,5,0) -> B | I6: qs коричневые | J6: ='2025'!R7 -> 20 | K6: =J6/J$26 -> 0.035523979 | L6: =K6+L5 -> 0.74777975 | M6: =_xlfn.IFS(L6<80%,"A",L6<=95%,"B",L6>95%,"C") -> A
B7: MR 1819 корич | C7: ='2025'!AE12 -> 3149.39 | D7: =C7/C$26 -> -1.4610322 | E7: =D7+E6 -> -24.801419 | F7: =IF(AND(E7<=0),"C",IF(E7<=0.8,"A",IF(E7<=0.95,"B","C"))) -> C | G7: =VLOOKUP(B$4:B$25,I$4:M$25,5,0) -> B | I7: qs черные | J7: ='2025'!R4 -> 19 | K7: =J7/J$26 -> 0.03374778 | L7: =K7+L6 -> 0.78152753 | M7: =_xlfn.IFS(L7<80%,"A",L7<=95%,"B",L7>95%,"C") -> A
B8: qs черные | C8: ='2025'!AE4 -> 3882.7407 | D8: =C8/C$26 -> -1.8012406 | E8: =D8+E7 -> -26.60266 | F8: =IF(AND(E8<=0),"C",IF(E8<=0.8,"A",IF(E8<=0.95,"B","C"))) -> C | G8: =VLOOKUP(B$4:B$25,I$4:M$25,5,0) -> A | I8: MR Р1874 черн | J8: ='2025'!R13 -> 18 | K8: =J8/J$26 -> 0.031971581 | L8: =K8+L7 -> 0.81349911 | M8: =_xlfn.IFS(L8<80%,"A",L8<=95%,"B",L8>95%,"C") -> B
B9: MR 1819 черн | C9: ='2025'!AE11 -> 1733.22 | D9: =C9/C$26 -> -0.80405734 | E9: =D9+E8 -> -27.406717 | F9: =IF(AND(E9<=0),"C",IF(E9<=0.8,"A",IF(E9<=0.95,"B","C"))) -> C | G9: =VLOOKUP(B$4:B$25,I$4:M$25,5,0) -> B | I9: MR Р1886 корич | J9: ='2025'!R16 -> 16 | K9: =J9/J$26 -> 0.028419183 | L9: =K9+L8 -> 0.84191829 | M9: =_xlfn.IFS(L9<80%,"A",L9<=95%,"B",L9>95%,"C") -> B
B10: MR8854 C2 | C10: ='2025'!AE10 -> 1021.6763 | D10: =C10/C$26 -> -0.47396539 | E10: =D10+E9 -> -27.880682 | F10: =IF(AND(E10<=0),"C",IF(E10<=0.8,"A",IF(E10<=0.95,"B","C"))) -> C | G10: =VLOOKUP(B$4:B$25,I$4:M$25,5,0) -> B | I10: MR8854 C2 | J10: ='2025'!R10 -> 15 | K10: =J10/J$26 -> 0.026642984 | L10: =K10+L9 -> 0.86856128 | M10: =_xlfn.IFS(L10<80%,"A",L10<=95%,"B",L10>95%,"C") -> B
B11: qs синие | C11: ='2025'!AE5 -> 517.09594 | D11: =C11/C$26 -> -0.23988575 | E11: =D11+E8 -> -26.842545 | F11: =IF(AND(E11<=0),"C",IF(E11<=0.8,"A",IF(E11<=0.95,"B","C"))) -> C | G11: =VLOOKUP(B$4:B$25,I$4:M$25,5,0) -> B | I11: MR Р1886 черн глянец | J11: ='2025'!R15 -> 15 | K11: =J11/J$26 -> 0.026642984 | L11: =K11+L8 -> 0.8401421 | M11: =_xlfn.IFS(L11<80%,"A",L11<=95%,"B",L11>95%,"C") -> B
B12: lux6 | C12: ='2025'!AE22 -> 94.039378 | D12: =C12/C$26 -> -0.043625767 | E12: =D12+E11 -> -26.886171 | F12: =IF(AND(E12<=0),"C",IF(E12<=0.8,"A",IF(E12<=0.95,"B","C"))) -> C | G12: =VLOOKUP(B$4:B$25,I$4:M$25,5,0) -> B | I12: qs синие | J12: ='2025'!R5 -> 14 | K12: =J12/J$26 -> 0.024866785 | L12: =K12+L11 -> 0.86500888 | M12: =_xlfn.IFS(L12<80%,"A",L12<=95%,"B",L12>95%,"C") -> B
B13: lux8 | C13: ='2025'!AE24 -> -435.98338 | D13: =C13/C$26 -> 0.20225686 | E13: =D13+E12 -> -26.683914 | F13: =IF(AND(E13<=0),"C",IF(E13<=0.8,"A",IF(E13<=0.95,"B","C"))) -> C | G13: =VLOOKUP(B$4:B$25,I$4:M$25,5,0) -> B | I13: MR Р1874 корич | J13: ='2025'!R14 -> 12 | K13: =J13/J$26 -> 0.021314387 | L13: =K13+L12 -> 0.88632327 | M13: =_xlfn.IFS(L13<80%,"A",L13<=95%,"B",L13>95%,"C") -> B | P13: A | Q13: 0.8
B14: lux7 | C14: ='2025'!AE23 -> -798.21564 | D14: =C14/C$26 -> 0.37029987 | E14: =D14+E13 -> -26.313614 | F14: =IF(AND(E14<=0),"C",IF(E14<=0.8,"A",IF(E14<=0.95,"B","C"))) -> C | G14: =VLOOKUP(B$4:B$25,I$4:M$25,5,0) -> B | I14: flip желтые Сул | J14: ='2025'!R9 -> 8 | K14: =J14/J$26 -> 0.014209591 | L14: =K14+L13 -> 0.90053286 | M14: =_xlfn.IFS(L14<80%,"A",L14<=95%,"B",L14>95%,"C") -> B | P14: B | Q14: 0.15
B15: lux2 | C15: ='2025'!AE18 -> -799.89007 | D15: =C15/C$26 -> 0.37107665 | E15: =D15+E14 -> -25.942538 | F15: =IF(AND(E15<=0),"C",IF(E15<=0.8,"A",IF(E15<=0.95,"B","C"))) -> C | G15: =VLOOKUP(B$4:B$25,I$4:M$25,5,0) -> B | I15: th желтый Сул | J15: ='2025'!R8 -> 6 | K15: =J15/J$26 -> 0.010657194 | L15: =K15+L14 -> 0.91119005 | M15: =_xlfn.IFS(L15<80%,"A",L15<=95%,"B",L15>95%,"C") -> B | P15: C | Q15: 0.05
B16: lux5 | C16: ='2025'!AE21 -> -1564.469 | D16: =C16/C$26 -> 0.72577213 | E16: =D16+E15 -> -25.216766 | F16: =IF(AND(E16<=0),"C",IF(E16<=0.8,"A",IF(E16<=0.95,"B","C"))) -> C | G16: =VLOOKUP(B$4:B$25,I$4:M$25,5,0) -> B | I16: MR 1819 черн | J16: ='2025'!R11 -> 6 | K16: =J16/J$26 -> 0.010657194 | L16: =K16+L15 -> 0.92184725 | M16: =_xlfn.IFS(L16<80%,"A",L16<=95%,"B",L16>95%,"C") -> B
B17: th желтый Сул | C17: ='2025'!AE8 -> -2770.9243 | D17: =C17/C$26 -> 1.2854583 | E17: =D17+E16 -> -23.931307 | F17: =IF(AND(E17<=0),"C",IF(E17<=0.8,"A",IF(E17<=0.95,"B","C"))) -> C | G17: =VLOOKUP(B$4:B$25,I$4:M$25,5,0) -> B | I17: MR 1819 корич | J17: ='2025'!R12 -> 5 | K17: =J17/J$26 -> 0.0088809947 | L17: =K17+L16 -> 0.93072824 | M17: =_xlfn.IFS(L17<80%,"A",L17<=95%,"B",L17>95%,"C") -> B
B18: qs желтые | C18: ='2025'!AE6 -> 4088.2923 | D18: =C18/C$26 -> -1.8965979 | E18: =D18+E17 -> -25.827905 | F18: =IF(AND(E18<=0),"C",IF(E18<=0.8,"A",IF(E18<=0.95,"B","C"))) -> C | G18: =VLOOKUP(B$4:B$25,I$4:M$25,5,0) -> A | I18: lux4 | J18: ='2025'!R20 -> 3 | K18: =J18/J$26 -> 0.0053285968 | L18: =K18+L17 -> 0.93605684 | M18: =_xlfn.IFS(L18<80%,"A",L18<=95%,"B",L18>95%,"C") -> B
B19: lux3 | C19: ='2025'!AE19 -> -4941.9668 | D19: =C19/C$26 -> 2.2926257 | E19: =D19+E18 -> -23.535279 | F19: =IF(AND(E19<=0),"C",IF(E19<=0.8,"A",IF(E19<=0.95,"B","C"))) -> C | G19: =VLOOKUP(B$4:B$25,I$4:M$25,5,0) -> B | I19: lux6 | J19: ='2025'!R22 -> 2 | K19: =J19/J$26 -> 0.0035523979 | L19: =K19+L18 -> 0.93960924 | M19: =_xlfn.IFS(L19<80%,"A",L19<=95%,"B",L19>95%,"C") -> B
B20: MR Р1886 черн глянец | C20: ='2025'!AE15 -> -5867.6056 | D20: =C20/C$26 -> 2.7220384 | E20: =D20+E19 -> -20.813241 | F20: =IF(AND(E20<=0),"C",IF(E20<=0.8,"A",IF(E20<=0.95,"B","C"))) -> C | G20: =VLOOKUP(B$4:B$25,I$4:M$25,5,0) -> B | I20: lux1 | J20: ='2025'!R17 -> 1 | K20: =J20/J$26 -> 0.0017761989 | L20: =K20+L19 -> 0.94138544 | M20: =_xlfn.IFS(L20<80%,"A",L20<=95%,"B",L20>95%,"C") -> B
B21: flip желтые Сул | C21: ='2025'!AE9 -> -6282.8522 | D21: =C21/C$26 -> 2.9146753 | E21: =D21+E20 -> -17.898566 | F21: =IF(AND(E21<=0),"C",IF(E21<=0.8,"A",IF(E21<=0.95,"B","C"))) -> C | G21: =VLOOKUP(B$4:B$25,I$4:M$25,5,0) -> B | I21: lux3 | J21: ='2025'!R19 -> 1 | K21: =J21/J$26 -> 0.0017761989 | L21: =K21+L20 -> 0.94316163 | M21: =_xlfn.IFS(L21<80%,"A",L21<=95%,"B",L21>95%,"C") -> B
B22: lux4 | C22: ='2025'!AE20 -> -8026.5188 | D22: =C22/C$26 -> 3.7235789 | E22: =D22+E21 -> -14.174987 | F22: =IF(AND(E22<=0),"C",IF(E22<=0.8,"A",IF(E22<=0.95,"B","C"))) -> C | G22: =VLOOKUP(B$4:B$25,I$4:M$25,5,0) -> B | I22: lux5 | J22: ='2025'!R21 -> 1 | K22: =J22/J$26 -> 0.0017761989 | L22: =K22+L21 -> 0.94493783 | M22: =_xlfn.IFS(L22<80%,"A",L22<=95%,"B",L22>95%,"C") -> B
B23: MR Р1886 корич | C23: ='2025'!AE16 -> -8368.2073 | D23: =C23/C$26 -> 3.8820914 | E23: =D23+E22 -> -10.292895 | F23: =IF(AND(E23<=0),"C",IF(E23<=0.8,"A",IF(E23<=0.95,"B","C"))) -> C | G23: =VLOOKUP(B$4:B$25,I$4:M$25,5,0) -> B | I23: lux2 | J23: ='2025'!R18 -> 0 | K23: =J23/J$26 -> 0 | L23: =K23+L22 -> 0.94493783 | M23: =_xlfn.IFS(L23<80%,"A",L23<=95%,"B",L23>95%,"C") -> B
B24: lux1 | C24: ='2025'!AE17 -> -12557.207 | D24: =C24/C$26 -> 5.8254085 | E24: =D24+E23 -> -4.467487 | F24: =IF(AND(E24<=0),"C",IF(E24<=0.8,"A",IF(E24<=0.95,"B","C"))) -> C | G24: =VLOOKUP(B$4:B$25,I$4:M$25,5,0) -> B | I24: lux7 | J24: ='2025'!R23 -> 0 | K24: =J24/J$26 -> 0 | L24: =K24+L23 -> 0.94493783 | M24: =_xlfn.IFS(L24<80%,"A",L24<=95%,"B",L24>95%,"C") -> B
B25: MR Р1874 корич | C25: ='2025'!AE14 -> -14540.57 | D25: =C25/C$26 -> 6.7455097 | E25: =D25+E24 -> 2.2780227 | F25: =IF(AND(E25<=0),"C",IF(E25<=0.8,"A",IF(E25<=0.95,"B","C"))) -> C | G25: =VLOOKUP(B$4:B$25,I$4:M$25,5,0) -> B | I25: lux8 | J25: ='2025'!R24 -> 0 | K25: =J25/J$26 -> 0 | L25: =K25+L24 -> 0.94493783 | M25: =_xlfn.IFS(L25<80%,"A",L25<=95%,"B",L25>95%,"C") -> B
C26: =SUM(C4:C25) -> -2155.5925 | D26: =SUM(D4:D25) -> 1 | J26: =SUM(J4:J25) -> 563 | K26: =SUM(K4:K25) -> 1
B28: ТУНИКИ
C29: Прибыль | D29: % прибыль | E29: Доля | F29: ABC прибыль | G29: ABC кол-во | J29: Кол-во | K29: % кол-во | L29: Доля | M29: ABC кол-во
B30: tunika16 сетка белая | C30: ='2025'!AE46 -> 7058.8108 | D30: =C30/C$50 -> -1.4839137 | E30: =D30 -> -1.4839137 | F30: =IF(AND(E30<=0),"C",IF(E30<=0.8,"A",IF(E30<=0.95,"B","C"))) -> C | G30: =VLOOKUP(B$30:B$50,I$30:M$50,5,0) -> A | I30: tunika15 кимоно песочная | J30: ='2025'!R45 -> 16 | K30: =J30/J$50 -> 0.14414414 | L30: =K30 -> 0.14414414 | M30: =_xlfn.IFS(L30<80%,"A",L30<=95%,"B",L30>95%,"C") -> A
B31: tunika15 кимоно песочная | C31: ='2025'!AE45 -> 6934.6843 | D31: =C31/C$50 -> -1.4578197 | E31: =D31+E30 -> -2.9417334 | F31: =IF(AND(E31<=0),"C",IF(E31<=0.8,"A",IF(E31<=0.95,"B","C"))) -> C | G31: =VLOOKUP(B$30:B$50,I$30:M$50,5,0) -> A | I31: tunika15 кимоно бирюза | J31: ='2025'!R44 -> 15 | K31: =J31/J$50 -> 0.13513514 | L31: =K31+L30 -> 0.27927928 | M31: =_xlfn.IFS(L31<80%,"A",L31<=95%,"B",L31>95%,"C") -> A
B32: tunika08 черная | C32: ='2025'!AE35 -> 4397 | D32: =C32/C$50 -> -0.92434391 | E32: =D32+E31 -> -3.8660773 | F32: =IF(AND(E32<=0),"C",IF(E32<=0.8,"A",IF(E32<=0.95,"B","C"))) -> C | G32: =VLOOKUP(B$30:B$50,I$30:M$50,5,0) -> C | I32: tunika16 сетка белая | J32: ='2025'!R46 -> 15 | K32: =J32/J$50 -> 0.13513514 | L32: =K32+L31 -> 0.41441441 | M32: =_xlfn.IFS(L32<80%,"A",L32<=95%,"B",L32>95%,"C") -> A
B33: tunika07 кружево | C33: ='2025'!AE33 -> 3631.23 | D33: =C33/C$50 -> -0.7633626 | E33: =D33+E32 -> -4.6294399 | F33: =IF(AND(E33<=0),"C",IF(E33<=0.8,"A",IF(E33<=0.95,"B","C"))) -> C | G33: =VLOOKUP(B$30:B$50,I$30:M$50,5,0) -> B | I33: tunika10 кимоно ч/б | J33: ='2025'!R38 -> 14 | K33: =J33/J$50 -> 0.12612613 | L33: =K33+L32 -> 0.54054054 | M33: =_xlfn.IFS(L33<80%,"A",L33<=95%,"B",L33>95%,"C") -> A
B34: tunika15 кимоно бирюза | C34: ='2025'!AE44 -> 3388.509 | D34: =C34/C$50 -> -0.71233742 | E34: =D34+E33 -> -5.3417774 | F34: =IF(AND(E34<=0),"C",IF(E34<=0.8,"A",IF(E34<=0.95,"B","C"))) -> C | G34: =VLOOKUP(B$30:B$50,I$30:M$50,5,0) -> A | I34: tunika03 черная распашная | J34: ='2025'!R29 -> 10 | K34: =J34/J$50 -> 0.09009009 | L34: =K34+L33 -> 0.63063063 | M34: =_xlfn.IFS(L34<80%,"A",L34<=95%,"B",L34>95%,"C") -> A
B35: tunika08 белая | C35: ='2025'!AE34 -> 1499.84 | D35: =C35/C$50 -> -0.31529861 | E35: =D35+E34 -> -5.657076 | F35: =IF(AND(E35<=0),"C",IF(E35<=0.8,"A",IF(E35<=0.95,"B","C"))) -> C | G35: =VLOOKUP(B$30:B$50,I$30:M$50,5,0) -> C | I35: tunika02 оливковая с руч вышивкой | J35: ='2025'!R28 -> 7 | K35: =J35/J$50 -> 0.063063063 | L35: =K35+L34 -> 0.69369369 | M35: =_xlfn.IFS(L35<80%,"A",L35<=95%,"B",L35>95%,"C") -> A
B36: tunika08 зеленая | C36: ='2025'!AE36 -> 527.14433 | D36: =C36/C$50 -> -0.11081707 | E36: =D36+E35 -> -5.767893 | F36: =IF(AND(E36<=0),"C",IF(E36<=0.8,"A",IF(E36<=0.95,"B","C"))) -> C | G36: =VLOOKUP(B$30:B$50,I$30:M$50,5,0) -> C | I36: tunika05 белая распашная | J36: ='2025'!R30 -> 7 | K36: =J36/J$50 -> 0.063063063 | L36: =K36+L35 -> 0.75675676 | M36: =_xlfn.IFS(L36<80%,"A",L36<=95%,"B",L36>95%,"C") -> A
B37: tunika13 халат черная | C37: ='2025'!AE41 -> 324.16 | D37: =C37/C$50 -> -0.0681454 | E37: =D37+E36 -> -5.8360384 | F37: =IF(AND(E37<=0),"C",IF(E37<=0.8,"A",IF(E37<=0.95,"B","C"))) -> C | G37: =VLOOKUP(B$30:B$50,I$30:M$50,5,0) -> B | I37: tunika07 кружево | J37: ='2025'!R33 -> 6 | K37: =J37/J$50 -> 0.054054054 | L37: =K37+L36 -> 0.81081081 | M37: =_xlfn.IFS(L37<80%,"A",L37<=95%,"B",L37>95%,"C") -> B
B38: tunika14 халат с разрезами черный | C38: ='2025'!AE43 -> -224 | D38: =C38/C$50 -> 0.047089615 | E38: =D38+E37 -> -5.7889488 | F38: =IF(AND(E38<=0),"C",IF(E38<=0.8,"A",IF(E38<=0.95,"B","C"))) -> C | G38: =VLOOKUP(B$30:B$50,I$30:M$50,5,0) -> C | I38: tunika09 кимоно | J38: ='2025'!R37 -> 6 | K38: =J38/J$50 -> 0.054054054 | L38: =K38+L37 -> 0.86486486 | M38: =_xlfn.IFS(L38<80%,"A",L38<=95%,"B",L38>95%,"C") -> B
B39: tunika06 черная | C39: ='2025'!AE32 -> -336 | D39: =C39/C$50 -> 0.070634422 | E39: =D39+E38 -> -5.7183144 | F39: =IF(AND(E39<=0),"C",IF(E39<=0.8,"A",IF(E39<=0.95,"B","C"))) -> C | G39: =VLOOKUP(B$30:B$50,I$30:M$50,5,0) -> C | I39: tunika11 халат зеленая | J39: ='2025'!R39 -> 5 | K39: =J39/J$50 -> 0.045045045 | L39: =K39+L38 -> 0.90990991 | M39: =_xlfn.IFS(L39<80%,"A",L39<=95%,"B",L39>95%,"C") -> B
B40: tunika12 халат белая | C40: ='2025'!AE40 -> -448 | D40: =C40/C$50 -> 0.094179229 | E40: =D40+E39 -> -5.6241352 | F40: =IF(AND(E40<=0),"C",IF(E40<=0.8,"A",IF(E40<=0.95,"B","C"))) -> C | G40: =VLOOKUP(B$30:B$50,I$30:M$50,5,0) -> C | I40: tunika13 халат черная | J40: ='2025'!R41 -> 3 | K40: =J40/J$50 -> 0.027027027 | L40: =K40+L39 -> 0.93693694 | M40: =_xlfn.IFS(L40<80%,"A",L40<=95%,"B",L40>95%,"C") -> B
B41: tunika10 кимоно ч/б | C41: ='2025'!AE38 -> 1612.9842 | D41: =C41/C$50 -> -0.33908395 | E41: =D41+E40 -> -5.9632191 | F41: =IF(AND(E41<=0),"C",IF(E41<=0.8,"A",IF(E41<=0.95,"B","C"))) -> C | G41: =VLOOKUP(B$30:B$50,I$30:M$50,5,0) -> A | I41: tunika08 черная | J41: ='2025'!R35 -> 2 | K41: =J41/J$50 -> 0.018018018 | L41: =K41+L40 -> 0.95495495 | M41: =_xlfn.IFS(L41<80%,"A",L41<=95%,"B",L41>95%,"C") -> C
B42: tunika11 халат зеленая | C42: ='2025'!AE39 -> -949.92467 | D42: =C42/C$50 -> 0.19969458 | E42: =D42+E41 -> -5.7635245 | F42: =IF(AND(E42<=0),"C",IF(E42<=0.8,"A",IF(E42<=0.95,"B","C"))) -> C | G42: =VLOOKUP(B$30:B$50,I$30:M$50,5,0) -> B | I42: tunika16 сетка черная | J42: ='2025'!R47 -> 2 | K42: =J42/J$50 -> 0.018018018 | L42: =K42+L41 -> 0.97297297 | M42: =_xlfn.IFS(L42<80%,"A",L42<=95%,"B",L42>95%,"C") -> C
B43: tunika05 белая распашная | C43: ='2025'!AE30 -> -1246.7747 | D43: =C43/C$50 -> 0.26209885 | E43: =D43+E42 -> -5.5014257 | F43: =IF(AND(E43<=0),"C",IF(E43<=0.8,"A",IF(E43<=0.95,"B","C"))) -> C | G43: =VLOOKUP(B$30:B$50,I$30:M$50,5,0) -> A | I43: tunika06 белая | J43: ='2025'!R31 -> 1 | K43: =J43/J$50 -> 0.009009009 | L43: =K43+L42 -> 0.98198198 | M43: =_xlfn.IFS(L43<80%,"A",L43<=95%,"B",L43>95%,"C") -> C
B44: tunika06 белая | C44: ='2025'!AE31 -> -2464.2461 | D44: =C44/C$50 -> 0.5180375 | E44: =D44+E43 -> -4.9833882 | F44: =IF(AND(E44<=0),"C",IF(E44<=0.8,"A",IF(E44<=0.95,"B","C"))) -> C | G44: =VLOOKUP(B$30:B$50,I$30:M$50,5,0) -> C | I44: tunika08 белая | J44: ='2025'!R34 -> 1 | K44: =J44/J$50 -> 0.009009009 | L44: =K44+L43 -> 0.99099099 | M44: =_xlfn.IFS(L44<80%,"A",L44<=95%,"B",L44>95%,"C") -> C
B45: tunika16 сетка черная | C45: ='2025'!AE47 -> -2697.8935 | D45: =C45/C$50 -> 0.5671552 | E45: =D45+E44 -> -4.416233 | F45: =IF(AND(E45<=0),"C",IF(E45<=0.8,"A",IF(E45<=0.95,"B","C"))) -> C | G45: =VLOOKUP(B$30:B$50,I$30:M$50,5,0) -> C | I45: tunika08 зеленая | J45: ='2025'!R36 -> 1 | K45: =J45/J$50 -> 0.009009009 | L45: =K45+L44 -> 1 | M45: =_xlfn.IFS(L45<80%,"A",L45<=95%,"B",L45>95%,"C") -> C
B46: tunika14 халат с разрезами белая | C46: ='2025'!AE42 -> -4441.3457 | D46: =C46/C$50 -> 0.93366632 | E46: =D46+E45 -> -3.4825667 | F46: =IF(AND(E46<=0),"C",IF(E46<=0.8,"A",IF(E46<=0.95,"B","C"))) -> C | G46: =VLOOKUP(B$30:B$50,I$30:M$50,5,0) -> C | I46: tunika06 черная | J46: ='2025'!R32 -> 0 | K46: =J46/J$50 -> 0 | L46: =K46+L45 -> 1 | M46: =_xlfn.IFS(L46<80%,"A",L46<=95%,"B",L46>95%,"C") -> C
B47: tunika09 кимоно | C47: ='2025'!AE37 -> -4051.4625 | D47: =C47/C$50 -> 0.8517045 | E47: =D47+E46 -> -2.6308622 | F47: =IF(AND(E47<=0),"C",IF(E47<=0.8,"A",IF(E47<=0.95,"B","C"))) -> C | G47: =VLOOKUP(B$30:B$50,I$30:M$50,5,0) -> B | I47: tunika12 халат белая | J47: ='2025'!R40 -> 0 | K47: =J47/J$50 -> 0 | L47: =K47+L46 -> 1 | M47: =_xlfn.IFS(L47<80%,"A",L47<=95%,"B",L47>95%,"C") -> C
B48: tunika02 оливковая с руч вышивкой | C48: ='2025'!AE28 -> -4737.1133 | D48: =C48/C$50 -> 0.99584303 | E48: =D48+E47 -> -1.6350191 | F48: =IF(AND(E48<=0),"C",IF(E48<=0.8,"A",IF(E48<=0.95,"B","C"))) -> C | G48: =VLOOKUP(B$30:B$50,I$30:M$50,5,0) -> A | I48: tunika14 халат с разрезами белая | J48: ='2025'!R42 -> 0 | K48: =J48/J$50 -> 0 | L48: =K48+L47 -> 1 | M48: =_xlfn.IFS(L48<80%,"A",L48<=95%,"B",L48>95%,"C") -> C
B49: tunika03 черная распашная | C49: ='2025'!AE29 -> -12534.49 | D49: =C49/C$50 -> 2.6350191 | E49: =D49+E48 -> 1 | F49: =IF(AND(E49<=0),"C",IF(E49<=0.8,"A",IF(E49<=0.95,"B","C"))) -> C | G49: =VLOOKUP(B$30:B$50,I$30:M$50,5,0) -> A | I49: tunika14 халат с разрезами черный | J49: ='2025'!R43 -> 0 | K49: =J49/J$50 -> 0 | L49: =K49+L48 -> 1 | M49: =_xlfn.IFS(L49<80%,"A",L49<=95%,"B",L49>95%,"C") -> C
C50: =SUM(C30:C49) -> -4756.8875 | D50: =SUM(D30:D49) -> 1 | J50: =SUM(J30:J49) -> 111 | K50: =SUM(K30:K49) -> 1

Sheet АВС ДЕКАБРЬ
B2: ОЧКИ
C3: Прибыль | D3: % прибыль | E3: Доля | F3: ABC прибыль | G3: ABC кол-во | J3: Кол-во | K3: % кол-во | L3: Доля | M3: ABC кол-во
B4: черные с железкой классика | C4: =ДЕКАБРЬ!AE3 -> 13038.755 | D4: =C4/C$26 -> 0.41207159 | E4: =D4 -> 0.41207159 | F4: =IF(AND(E4<=0),"C",IF(E4<=0.8,"A",IF(E4<=0.95,"B","C"))) -> A | G4: =VLOOKUP(B$4:B$25,I$4:M$25,5,0) -> A | I4: черные с железкой классика | J4: =ДЕКАБРЬ!R3 -> 112 | K4: =J4/J$26 -> 0.49122807 | L4: =K4 -> 0.49122807 | M4: =_xlfn.IFS(L4<80%,"A",L4<=95%,"B",L4>95%,"C") -> A
B5: qs коричневые | C5: =ДЕКАБРЬ!AE7 -> 3790.9 | D5: =C5/C$26 -> 0.11980609 | E5: =D5+E4 -> 0.53187768 | F5: =IF(AND(E5<=0),"C",IF(E5<=0.8,"A",IF(E5<=0.95,"B","C"))) -> A | G5: =VLOOKUP(B$4:B$25,I$4:M$25,5,0) -> B | I5: qs желтые | J5: =ДЕКАБРЬ!R6 -> 66 | K5: =J5/J$26 -> 0.28947368 | L5: =K5+L4 -> 0.78070175 | M5: =_xlfn.IFS(L5<80%,"A",L5<=95%,"B",L5>95%,"C") -> A
B6: MR Р1874 черн | C6: =ДЕКАБРЬ!AE13 -> 2939.06 | D6: =C6/C$26 -> 0.092884875 | E6: =D6+E5 -> 0.62476255 | F6: =IF(AND(E6<=0),"C",IF(E6<=0.8,"A",IF(E6<=0.95,"B","C"))) -> A | G6: =VLOOKUP(B$4:B$25,I$4:M$25,5,0) -> B | I6: qs черные | J6: =ДЕКАБРЬ!R4 -> 6 | K6: =J6/J$26 -> 0.026315789 | L6: =K6+L5 -> 0.80701754 | M6: =_xlfn.IFS(L6<80%,"A",L6<=95%,"B",L6>95%,"C") -> B
B7: qs черные | C7: =ДЕКАБРЬ!AE4 -> 2153.4 | D7: =C7/C$26 -> 0.068055191 | E7: =D7+E6 -> 0.69281774 | F7: =IF(AND(E7<=0),"C",IF(E7<=0.8,"A",IF(E7<=0.95,"B","C"))) -> A | G7: =VLOOKUP(B$4:B$25,I$4:M$25,5,0) -> B | I7: qs коричневые | J7: =ДЕКАБРЬ!R7 -> 6 | K7: =J7/J$26 -> 0.026315789 | L7: =K7+L6 -> 0.83333333 | M7: =_xlfn.IFS(L7<80%,"A",L7<=95%,"B",L7>95%,"C") -> B
B8: MR8854 C2 | C8: =ДЕКАБРЬ!AE10 -> 1789.98 | D8: =C8/C$26 -> 0.056569811 | E8: =D8+E7 -> 0.74938755 | F8: =IF(AND(E8<=0),"C",IF(E8<=0.8,"A",IF(E8<=0.95,"B","C"))) -> A | G8: =VLOOKUP(B$4:B$25,I$4:M$25,5,0) -> B | I8: MR Р1886 черн глянец | J8: =ДЕКАБРЬ!R15 -> 6 | K8: =J8/J$26 -> 0.026315789 | L8: =K8+L7 -> 0.85964912 | M8: =_xlfn.IFS(L8<80%,"A",L8<=95%,"B",L8>95%,"C") -> B
B9: MR Р1874 корич | C9: =ДЕКАБРЬ!AE14 -> 1464.08 | D9: =C9/C$26 -> 0.046270198 | E9: =D9+E8 -> 0.79565775 | F9: =IF(AND(E9<=0),"C",IF(E9<=0.8,"A",IF(E9<=0.95,"B","C"))) -> A | G9: =VLOOKUP(B$4:B$25,I$4:M$25,5,0) -> B | I9: qs синие | J9: =ДЕКАБРЬ!R5 -> 5 | K9: =J9/J$26 -> 0.021929825 | L9: =K9+L8 -> 0.88157895 | M9: =_xlfn.IFS(L9<80%,"A",L9<=95%,"B",L9>95%,"C") -> B
B10: qs синие | C10: =ДЕКАБРЬ!AE5 -> 1412.92 | D10: =C10/C$26 -> 0.044653358 | E10: =D10+E9 -> 0.84031111 | F10: =IF(AND(E10<=0),"C",IF(E10<=0.8,"A",IF(E10<=0.95,"B","C"))) -> B | G10: =VLOOKUP(B$4:B$25,I$4:M$25,5,0) -> B | I10: flip желтые Сул | J10: =ДЕКАБРЬ!R9 -> 5 | K10: =J10/J$26 -> 0.021929825 | L10: =K10+L9 -> 0.90350877 | M10: =_xlfn.IFS(L10<80%,"A",L10<=95%,"B",L10>95%,"C") -> B
B11: MR 1819 черн | C11: =ДЕКАБРЬ!AE11 -> 866.58 | D11: =C11/C$26 -> 0.027387047 | E11: =D11+E8 -> 0.7767746 | F11: =IF(AND(E11<=0),"C",IF(E11<=0.8,"A",IF(E11<=0.95,"B","C"))) -> A | G11: =VLOOKUP(B$4:B$25,I$4:M$25,5,0) -> B | I11: MR Р1874 черн | J11: =ДЕКАБРЬ!R13 -> 5 | K11: =J11/J$26 -> 0.021929825 | L11: =K11+L8 -> 0.88157895 | M11: =_xlfn.IFS(L11<80%,"A",L11<=95%,"B",L11>95%,"C") -> B
B12: MR 1819 корич | C12: =ДЕКАБРЬ!AE12 -> 613.66 | D12: =C12/C$26 -> 0.019393865 | E12: =D12+E11 -> 0.79616847 | F12: =IF(AND(E12<=0),"C",IF(E12<=0.8,"A",IF(E12<=0.95,"B","C"))) -> A | G12: =VLOOKUP(B$4:B$25,I$4:M$25,5,0) -> C | I12: th желтый Сул | J12: =ДЕКАБРЬ!R8 -> 4 | K12: =J12/J$26 -> 0.01754386 | L12: =K12+L11 -> 0.89912281 | M12: =_xlfn.IFS(L12<80%,"A",L12<=95%,"B",L12>95%,"C") -> B
B13: lux1 | C13: =ДЕКАБРЬ!AE17 -> 0 | D13: =C13/C$26 -> 0 | E13: =D13+E12 -> 0.79616847 | F13: =IF(AND(E13<=0),"C",IF(E13<=0.8,"A",IF(E13<=0.95,"B","C"))) -> A | G13: =VLOOKUP(B$4:B$25,I$4:M$25,5,0) -> C | I13: MR8854 C2 | J13: =ДЕКАБРЬ!R10 -> 4 | K13: =J13/J$26 -> 0.01754386 | L13: =K13+L12 -> 0.91666667 | M13: =_xlfn.IFS(L13<80%,"A",L13<=95%,"B",L13>95%,"C") -> B | P13: A | Q13: 0.8
B14: lux2 | C14: =ДЕКАБРЬ!AE18 -> 0 | D14: =C14/C$26 -> 0 | E14: =D14+E13 -> 0.79616847 | F14: =IF(AND(E14<=0),"C",IF(E14<=0.8,"A",IF(E14<=0.95,"B","C"))) -> A | G14: =VLOOKUP(B$4:B$25,I$4:M$25,5,0) -> C | I14: MR Р1874 корич | J14: =ДЕКАБРЬ!R14 -> 4 | K14: =J14/J$26 -> 0.01754386 | L14: =K14+L13 -> 0.93421053 | M14: =_xlfn.IFS(L14<80%,"A",L14<=95%,"B",L14>95%,"C") -> B | P14: B | Q14: 0.15
B15: lux3 | C15: =ДЕКАБРЬ!AE19 -> 0 | D15: =C15/C$26 -> 0 | E15: =D15+E14 -> 0.79616847 | F15: =IF(AND(E15<=0),"C",IF(E15<=0.8,"A",IF(E15<=0.95,"B","C"))) -> A | G15: =VLOOKUP(B$4:B$25,I$4:M$25,5,0) -> C | I15: MR 1819 черн | J15: =ДЕКАБРЬ!R11 -> 2 | K15: =J15/J$26 -> 0.0087719298 | L15: =K15+L14 -> 0.94298246 | M15: =_xlfn.IFS(L15<80%,"A",L15<=95%,"B",L15>95%,"C") -> B | P15: C | Q15: 0.05
B16: lux5 | C16: =ДЕКАБРЬ!AE21 -> 0 | D16: =C16/C$26 -> 0 | E16: =D16+E15 -> 0.79616847 | F16: =IF(AND(E16<=0),"C",IF(E16<=0.8,"A",IF(E16<=0.95,"B","C"))) -> A | G16: =VLOOKUP(B$4:B$25,I$4:M$25,5,0) -> C | I16: MR 1819 корич | J16: =ДЕКАБРЬ!R12 -> 2 | K16: =J16/J$26 -> 0.0087719298 | L16: =K16+L15 -> 0.95175439 | M16: =_xlfn.IFS(L16<80%,"A",L16<=95%,"B",L16>95%,"C") -> C
B17: lux6 | C17: =ДЕКАБРЬ!AE22 -> 0 | D17: =C17/C$26 -> 0 | E17: =D17+E16 -> 0.79616847 | F17: =IF(AND(E17<=0),"C",IF(E17<=0.8,"A",IF(E17<=0.95,"B","C"))) -> A | G17: =VLOOKUP(B$4:B$25,I$4:M$25,5,0) -> C | I17: MR Р1886 корич | J17: =ДЕКАБРЬ!R16 -> 1 | K17: =J17/J$26 -> 0.0043859649 | L17: =K17+L16 -> 0.95614035 | M17: =_xlfn.IFS(L17<80%,"A",L17<=95%,"B",L17>95%,"C") -> C
B18: lux7 | C18: =ДЕКАБРЬ!AE23 -> 0 | D18: =C18/C$26 -> 0 | E18: =D18+E17 -> 0.79616847 | F18: =IF(AND(E18<=0),"C",IF(E18<=0.8,"A",IF(E18<=0.95,"B","C"))) -> A | G18: =VLOOKUP(B$4:B$25,I$4:M$25,5,0) -> C | I18: lux1 | J18: =ДЕКАБРЬ!R17 -> 0 | K18: =J18/J$26 -> 0 | L18: =K18+L17 -> 0.95614035 | M18: =_xlfn.IFS(L18<80%,"A",L18<=95%,"B",L18>95%,"C") -> C
B19: lux8 | C19: =ДЕКАБРЬ!AE24 -> 0 | D19: =C19/C$26 -> 0 | E19: =D19+E18 -> 0.79616847 | F19: =IF(AND(E19<=0),"C",IF(E19<=0.8,"A",IF(E19<=0.95,"B","C"))) -> A | G19: =VLOOKUP(B$4:B$25,I$4:M$25,5,0) -> C | I19: lux2 | J19: =ДЕКАБРЬ!R18 -> 0 | K19: =J19/J$26 -> 0 | L19: =K19+L18 -> 0.95614035 | M19: =_xlfn.IFS(L19<80%,"A",L19<=95%,"B",L19>95%,"C") -> C
B20: MR Р1886 черн глянец | C20: =ДЕКАБРЬ!AE15 -> 298.59 | D20: =C20/C$26 -> 0.0094365188 | E20: =D20+E19 -> 0.80560498 | F20: =IF(AND(E20<=0),"C",IF(E20<=0.8,"A",IF(E20<=0.95,"B","C"))) -> B | G20: =VLOOKUP(B$4:B$25,I$4:M$25,5,0) -> B | I20: lux3 | J20: =ДЕКАБРЬ!R19 -> 0 | K20: =J20/J$26 -> 0 | L20: =K20+L19 -> 0.95614035 | M20: =_xlfn.IFS(L20<80%,"A",L20<=95%,"B",L20>95%,"C") -> C
B21: lux4 | C21: =ДЕКАБРЬ!AE20 -> -113.88 | D21: =C21/C$26 -> -0.0035990179 | E21: =D21+E20 -> 0.80200597 | F21: =IF(AND(E21<=0),"C",IF(E21<=0.8,"A",IF(E21<=0.95,"B","C"))) -> B | G21: =VLOOKUP(B$4:B$25,I$4:M$25,5,0) -> C | I21: lux4 | J21: =ДЕКАБРЬ!R20 -> 0 | K21: =J21/J$26 -> 0 | L21: =K21+L20 -> 0.95614035 | M21: =_xlfn.IFS(L21<80%,"A",L21<=95%,"B",L21>95%,"C") -> C
B22: qs желтые | C22: =ДЕКАБРЬ!AE6 -> 5749.0587 | D22: =C22/C$26 -> 0.18169095 | E22: =D22+E21 -> 0.98369692 | F22: =IF(AND(E22<=0),"C",IF(E22<=0.8,"A",IF(E22<=0.95,"B","C"))) -> C | G22: =VLOOKUP(B$4:B$25,I$4:M$25,5,0) -> A | I22: lux5 | J22: =ДЕКАБРЬ!R21 -> 0 | K22: =J22/J$26 -> 0 | L22: =K22+L21 -> 0.95614035 | M22: =_xlfn.IFS(L22<80%,"A",L22<=95%,"B",L22>95%,"C") -> C
B23: MR Р1886 корич | C23: =ДЕКАБРЬ!AE16 -> -246.17 | D23: =C23/C$26 -> -0.0077798581 | E23: =D23+E22 -> 0.97591706 | F23: =IF(AND(E23<=0),"C",IF(E23<=0.8,"A",IF(E23<=0.95,"B","C"))) -> C | G23: =VLOOKUP(B$4:B$25,I$4:M$25,5,0) -> C | I23: lux6 | J23: =ДЕКАБРЬ!R22 -> 0 | K23: =J23/J$26 -> 0 | L23: =K23+L22 -> 0.95614035 | M23: =_xlfn.IFS(L23<80%,"A",L23<=95%,"B",L23>95%,"C") -> C
B24: th желтый Сул | C24: =ДЕКАБРЬ!AE8 -> -501.47252 | D24: =C24/C$26 -> -0.015848337 | E24: =D24+E23 -> 0.96006872 | F24: =IF(AND(E24<=0),"C",IF(E24<=0.8,"A",IF(E24<=0.95,"B","C"))) -> C | G24: =VLOOKUP(B$4:B$25,I$4:M$25,5,0) -> B | I24: lux7 | J24: =ДЕКАБРЬ!R23 -> 0 | K24: =J24/J$26 -> 0 | L24: =K24+L23 -> 0.95614035 | M24: =_xlfn.IFS(L24<80%,"A",L24<=95%,"B",L24>95%,"C") -> C
B25: flip желтые Сул | C25: =ДЕКАБРЬ!AE9 -> -1613.4959 | D25: =C25/C$26 -> -0.050992277 | E25: =D25+E24 -> 0.90907644 | F25: =IF(AND(E25<=0),"C",IF(E25<=0.8,"A",IF(E25<=0.95,"B","C"))) -> B | G25: =VLOOKUP(B$4:B$25,I$4:M$25,5,0) -> B | I25: lux8 | J25: =ДЕКАБРЬ!R24 -> 0 | K25: =J25/J$26 -> 0 | L25: =K25+L24 -> 0.95614035 | M25: =_xlfn.IFS(L25<80%,"A",L25<=95%,"B",L25>95%,"C") -> C
C26: =SUM(C4:C25) -> 31641.965 | D26: =SUM(D4:D25) -> 1 | J26: =SUM(J4:J25) -> 228 | K26: =SUM(K4:K25) -> 1
B28: ТУНИКИ
C29: Прибыль | D29: % прибыль | E29: Доля | F29: ABC прибыль | G29: ABC кол-во | J29: Кол-во | K29: % кол-во | L29: Доля | M29: ABC кол-во
B30: tunika13 халат черная | C30: =ДЕКАБРЬ!AE41 -> 548.16 | D30: =C30/C$50 -> -0.073086293 | E30: =D30 -> -0.073086293 | F30: =IF(AND(E30<=0),"C",IF(E30<=0.8,"A",IF(E30<=0.95,"B","C"))) -> C | G30: =VLOOKUP(B$30:B$50,I$30:M$50,5,0) -> A | I30: tunika07 кружево | J30: =ДЕКАБРЬ!R33 -> 2 | K30: =J30/J$50 -> 0.66666667 | L30: =K30 -> 0.66666667 | M30: =_xlfn.IFS(L30<80%,"A",L30<=95%,"B",L30>95%,"C") -> A
B31: tunika03 черная распашная | C31: =ДЕКАБРЬ!AE29 -> 0 | D31: =C31/C$50 -> 0 | E31: =D31+E30 -> -0.073086293 | F31: =IF(AND(E31<=0),"C",IF(E31<=0.8,"A",IF(E31<=0.95,"B","C"))) -> C | G31: =VLOOKUP(B$30:B$50,I$30:M$50,5,0) -> C | I31: tunika02 оливковая с руч вышивкой | J31: =ДЕКАБРЬ!R28 -> 0 | K31: =J31/J$50 -> 0 | L31: =K31+L30 -> 0.66666667 | M31: =_xlfn.IFS(L31<80%,"A",L31<=95%,"B",L31>95%,"C") -> A
B32: tunika05 белая распашная | C32: =ДЕКАБРЬ!AE30 -> 0 | D32: =C32/C$50 -> 0 | E32: =D32+E31 -> -0.073086293 | F32: =IF(AND(E32<=0),"C",IF(E32<=0.8,"A",IF(E32<=0.95,"B","C"))) -> C | G32: =VLOOKUP(B$30:B$50,I$30:M$50,5,0) -> C | I32: tunika11 халат зеленая | J32: =ДЕКАБРЬ!R39 -> -1 | K32: =J32/J$50 -> -0.33333333 | L32: =K32+L31 -> 0.33333333 | M32: =_xlfn.IFS(L32<80%,"A",L32<=95%,"B",L32>95%,"C") -> A
B33: tunika06 черная | C33: =ДЕКАБРЬ!AE32 -> 0 | D33: =C33/C$50 -> 0 | E33: =D33+E32 -> -0.073086293 | F33: =IF(AND(E33<=0),"C",IF(E33<=0.8,"A",IF(E33<=0.95,"B","C"))) -> C | G33: =VLOOKUP(B$30:B$50,I$30:M$50,5,0) -> C | I33: tunika13 халат черная | J33: =ДЕКАБРЬ!R41 -> 1 | K33: =J33/J$50 -> 0.33333333 | L33: =K33+L32 -> 0.66666667 | M33: =_xlfn.IFS(L33<80%,"A",L33<=95%,"B",L33>95%,"C") -> A
B34: tunika08 белая | C34: =ДЕКАБРЬ!AE34 -> 0 | D34: =C34/C$50 -> 0 | E34: =D34+E33 -> -0.073086293 | F34: =IF(AND(E34<=0),"C",IF(E34<=0.8,"A",IF(E34<=0.95,"B","C"))) -> C | G34: =VLOOKUP(B$30:B$50,I$30:M$50,5,0) -> C | I34: tunika15 кимоно песочная | J34: =ДЕКАБРЬ!R45 -> 1 | K34: =J34/J$50 -> 0.33333333 | L34: =K34+L33 -> 1 | M34: =_xlfn.IFS(L34<80%,"A",L34<=95%,"B",L34>95%,"C") -> C
B35: tunika08 черная | C35: =ДЕКАБРЬ!AE35 -> 0 | D35: =C35/C$50 -> 0 | E35: =D35+E34 -> -0.073086293 | F35: =IF(AND(E35<=0),"C",IF(E35<=0.8,"A",IF(E35<=0.95,"B","C"))) -> C | G35: =VLOOKUP(B$30:B$50,I$30:M$50,5,0) -> C | I35: tunika03 черная распашная | J35: =ДЕКАБРЬ!R29 -> 0 | K35: =J35/J$50 -> 0 | L35: =K35+L34 -> 1 | M35: =_xlfn.IFS(L35<80%,"A",L35<=95%,"B",L35>95%,"C") -> C
B36: tunika09 кимоно | C36: =ДЕКАБРЬ!AE37 -> 0 | D36: =C36/C$50 -> 0 | E36: =D36+E35 -> -0.073086293 | F36: =IF(AND(E36<=0),"C",IF(E36<=0.8,"A",IF(E36<=0.95,"B","C"))) -> C | G36: =VLOOKUP(B$30:B$50,I$30:M$50,5,0) -> C | I36: tunika05 белая распашная | J36: =ДЕКАБРЬ!R30 -> 0 | K36: =J36/J$50 -> 0 | L36: =K36+L35 -> 1 | M36: =_xlfn.IFS(L36<80%,"A",L36<=95%,"B",L36>95%,"C") -> C
B37: tunika12 халат белая | C37: =ДЕКАБРЬ!AE40 -> 0 | D37: =C37/C$50 -> 0 | E37: =D37+E36 -> -0.073086293 | F37: =IF(AND(E37<=0),"C",IF(E37<=0.8,"A",IF(E37<=0.95,"B","C"))) -> C | G37: =VLOOKUP(B$30:B$50,I$30:M$50,5,0) -> C | I37: tunika06 белая | J37: =ДЕКАБРЬ!R31 -> 0 | K37: =J37/J$50 -> 0 | L37: =K37+L36 -> 1 | M37: =_xlfn.IFS(L37<80%,"A",L37<=95%,"B",L37>95%,"C") -> C
B38: tunika14 халат с разрезами черный | C38: =ДЕКАБРЬ!AE43 -> 0 | D38: =C38/C$50 -> 0 | E38: =D38+E37 -> -0.073086293 | F38: =IF(AND(E38<=0),"C",IF(E38<=0.8,"A",IF(E38<=0.95,"B","C"))) -> C | G38: =VLOOKUP(B$30:B$50,I$30:M$50,5,0) -> C | I38: tunika06 черная | J38: =ДЕКАБРЬ!R32 -> 0 | K38: =J38/J$50 -> 0 | L38: =K38+L37 -> 1 | M38: =_xlfn.IFS(L38<80%,"A",L38<=95%,"B",L38>95%,"C") -> C
B39: tunika16 сетка черная | C39: =ДЕКАБРЬ!AE47 -> 0 | D39: =C39/C$50 -> 0 | E39: =D39+E38 -> -0.073086293 | F39: =IF(AND(E39<=0),"C",IF(E39<=0.8,"A",IF(E39<=0.95,"B","C"))) -> C | G39: =VLOOKUP(B$30:B$50,I$30:M$50,5,0) -> C | I39: tunika08 белая | J39: =ДЕКАБРЬ!R34 -> 0 | K39: =J39/J$50 -> 0 | L39: =K39+L38 -> 1 | M39: =_xlfn.IFS(L39<80%,"A",L39<=95%,"B",L39>95%,"C") -> C
B40: tunika08 зеленая | C40: =ДЕКАБРЬ!AE36 -> -112 | D40: =C40/C$50 -> 0.014932985 | E40: =D40+E39 -> -0.058153309 | F40: =IF(AND(E40<=0),"C",IF(E40<=0.8,"A",IF(E40<=0.95,"B","C"))) -> C | G40: =VLOOKUP(B$30:B$50,I$30:M$50,5,0) -> C | I40: tunika08 черная | J40: =ДЕКАБРЬ!R35 -> 0 | K40: =J40/J$50 -> 0 | L40: =K40+L39 -> 1 | M40: =_xlfn.IFS(L40<80%,"A",L40<=95%,"B",L40>95%,"C") -> C
B41: tunika06 белая | C41: =ДЕКАБРЬ!AE31 -> -113.88 | D41: =C41/C$50 -> 0.015183645 | E41: =D41+E40 -> -0.042969663 | F41: =IF(AND(E41<=0),"C",IF(E41<=0.8,"A",IF(E41<=0.95,"B","C"))) -> C | G41: =VLOOKUP(B$30:B$50,I$30:M$50,5,0) -> C | I41: tunika08 зеленая | J41: =ДЕКАБРЬ!R36 -> 0 | K41: =J41/J$50 -> 0 | L41: =K41+L40 -> 1 | M41: =_xlfn.IFS(L41<80%,"A",L41<=95%,"B",L41>95%,"C") -> C
B42: tunika10 кимоно ч/б | C42: =ДЕКАБРЬ!AE38 -> -113.88 | D42: =C42/C$50 -> 0.015183645 | E42: =D42+E41 -> -0.027786018 | F42: =IF(AND(E42<=0),"C",IF(E42<=0.8,"A",IF(E42<=0.95,"B","C"))) -> C | G42: =VLOOKUP(B$30:B$50,I$30:M$50,5,0) -> C | I42: tunika09 кимоно | J42: =ДЕКАБРЬ!R37 -> 0 | K42: =J42/J$50 -> 0 | L42: =K42+L41 -> 1 | M42: =_xlfn.IFS(L42<80%,"A",L42<=95%,"B",L42>95%,"C") -> C
B43: tunika07 кружево | C43: =ДЕКАБРЬ!AE33 -> 1500.11 | D43: =C43/C$50 -> -0.20001 | E43: =D43+E42 -> -0.22779601 | F43: =IF(AND(E43<=0),"C",IF(E43<=0.8,"A",IF(E43<=0.95,"B","C"))) -> C | G43: =VLOOKUP(B$30:B$50,I$30:M$50,5,0) -> A | I43: tunika10 кимоно ч/б | J43: =ДЕКАБРЬ!R38 -> 0 | K43: =J43/J$50 -> 0 | L43: =K43+L42 -> 1 | M43: =_xlfn.IFS(L43<80%,"A",L43<=95%,"B",L43>95%,"C") -> C
B44: tunika15 кимоно песочная | C44: =ДЕКАБРЬ!AE45 -> -146.03766 | D44: =C44/C$50 -> 0.019471234 | E44: =D44+E43 -> -0.20832478 | F44: =IF(AND(E44<=0),"C",IF(E44<=0.8,"A",IF(E44<=0.95,"B","C"))) -> C | G44: =VLOOKUP(B$30:B$50,I$30:M$50,5,0) -> C | I44: tunika12 халат белая | J44: =ДЕКАБРЬ!R40 -> 0 | K44: =J44/J$50 -> 0 | L44: =K44+L43 -> 1 | M44: =_xlfn.IFS(L44<80%,"A",L44<=95%,"B",L44>95%,"C") -> C
B45: tunika16 сетка белая | C45: =ДЕКАБРЬ!AE46 -> -1233.8363 | D45: =C45/C$50 -> 0.16450767 | E45: =D45+E44 -> -0.043817111 | F45: =IF(AND(E45<=0),"C",IF(E45<=0.8,"A",IF(E45<=0.95,"B","C"))) -> C | G45: =VLOOKUP(B$30:B$50,I$30:M$50,5,0) -> C | I45: tunika14 халат с разрезами белая | J45: =ДЕКАБРЬ!R42 -> 0 | K45: =J45/J$50 -> 0 | L45: =K45+L44 -> 1 | M45: =_xlfn.IFS(L45<80%,"A",L45<=95%,"B",L45>95%,"C") -> C
B46: tunika15 кимоно бирюза | C46: =ДЕКАБРЬ!AE44 -> -1360.8611 | D46: =C46/C$50 -> 0.18144391 | E46: =D46+E45 -> 0.1376268 | F46: =IF(AND(E46<=0),"C",IF(E46<=0.8,"A",IF(E46<=0.95,"B","C"))) -> A | G46: =VLOOKUP(B$30:B$50,I$30:M$50,5,0) -> C | I46: tunika14 халат с разрезами черный | J46: =ДЕКАБРЬ!R43 -> 0 | K46: =J46/J$50 -> 0 | L46: =K46+L45 -> 1 | M46: =_xlfn.IFS(L46<80%,"A",L46<=95%,"B",L46>95%,"C") -> C
B47: tunika02 оливковая с руч вышивкой | C47: =ДЕКАБРЬ!AE28 -> -352.03 | D47: =C47/C$50 -> 0.046936237 | E47: =D47+E46 -> 0.18456304 | F47: =IF(AND(E47<=0),"C",IF(E47<=0.8,"A",IF(E47<=0.95,"B","C"))) -> A | G47: =VLOOKUP(B$30:B$50,I$30:M$50,5,0) -> A | I47: tunika15 кимоно бирюза | J47: =ДЕКАБРЬ!R44 -> 0 | K47: =J47/J$50 -> 0 | L47: =K47+L46 -> 1 | M47: =_xlfn.IFS(L47<80%,"A",L47<=95%,"B",L47>95%,"C") -> C
B48: tunika14 халат с разрезами белая | C48: =ДЕКАБРЬ!AE42 -> -3352.92 | D48: =C48/C$50 -> 0.44704556 | E48: =D48+E47 -> 0.6316086 | F48: =IF(AND(E48<=0),"C",IF(E48<=0.8,"A",IF(E48<=0.95,"B","C"))) -> A | G48: =VLOOKUP(B$30:B$50,I$30:M$50,5,0) -> C | I48: tunika16 сетка белая | J48: =ДЕКАБРЬ!R46 -> 0 | K48: =J48/J$50 -> 0 | L48: =K48+L47 -> 1 | M48: =_xlfn.IFS(L48<80%,"A",L48<=95%,"B",L48>95%,"C") -> C
B49: tunika11 халат зеленая | C49: =ДЕКАБРЬ!AE39 -> -2763 | D49: =C49/C$50 -> 0.3683914 | E49: =D49+E48 -> 1 | F49: =IF(AND(E49<=0),"C",IF(E49<=0.8,"A",IF(E49<=0.95,"B","C"))) -> C | G49: =VLOOKUP(B$30:B$50,I$30:M$50,5,0) -> A | I49: tunika16 сетка черная | J49: =ДЕКАБРЬ!R47 -> 0 | K49: =J49/J$50 -> 0 | L49: =K49+L48 -> 1 | M49: =_xlfn.IFS(L49<80%,"A",L49<=95%,"B",L49>95%,"C") -> C
C50: =SUM(C30:C49) -> -7500.1751 | D50: =SUM(D30:D49) -> 1 | J50: =SUM(J30:J49) -> 3 | K50: =SUM(K30:K49) -> 1

Sheet АВС 22-31.12
B2: ОЧКИ
C3: Прибыль | D3: % прибыль | E3: Доля | F3: ABC прибыль | G3: ABC кол-во | J3: Кол-во | K3: % кол-во | L3: Доля | M3: ABC кол-во
B4: черные с железкой классика | C4: ='Юнит 22-31.12'!AE3 -> 4910.3405 | D4: =C4/C$26 -> 1.0670071 | E4: =D4 -> 1.0670071 | F4: =IF(AND(E4<=0),"C",IF(E4<=0.8,"A",IF(E4<=0.95,"B","C"))) -> C | G4: =VLOOKUP(B$4:B$25,I$4:M$25,5,0) -> A | I4: черные с железкой классика | J4: ='Юнит 22-31.12'!R3 -> 57 | K4: =J4/J$26 -> 0.63333333 | L4: =K4 -> 0.63333333 | M4: =_xlfn.IFS(L4<80%,"A",L4<=95%,"B",L4>95%,"C") -> A
B5: MR Р1874 черн | C5: ='Юнит 22-31.12'!AE13 -> 1386.43 | D5: =C5/C$26 -> 0.30126846 | E5: =D5+E4 -> 1.3682756 | F5: =IF(AND(E5<=0),"C",IF(E5<=0.8,"A",IF(E5<=0.95,"B","C"))) -> C | G5: =VLOOKUP(B$4:B$25,I$4:M$25,5,0) -> B | I5: qs желтые | J5: ='Юнит 22-31.12'!R6 -> 15 | K5: =J5/J$26 -> 0.16666667 | L5: =K5+L4 -> 0.8 | M5: =_xlfn.IFS(L5<80%,"A",L5<=95%,"B",L5>95%,"C") -> B
B6: MR8854 C2 | C6: ='Юнит 22-31.12'!AE10 -> 1157.26 | D6: =C6/C$26 -> 0.25147028 | E6: =D6+E5 -> 1.6197459 | F6: =IF(AND(E6<=0),"C",IF(E6<=0.8,"A",IF(E6<=0.95,"B","C"))) -> C | G6: =VLOOKUP(B$4:B$25,I$4:M$25,5,0) -> B | I6: qs черные | J6: ='Юнит 22-31.12'!R4 -> 3 | K6: =J6/J$26 -> 0.033333333 | L6: =K6+L5 -> 0.83333333 | M6: =_xlfn.IFS(L6<80%,"A",L6<=95%,"B",L6>95%,"C") -> B
B7: qs черные | C7: ='Юнит 22-31.12'!AE4 -> 1039.02 | D7: =C7/C$26 -> 0.22577696 | E7: =D7+E6 -> 1.8455228 | F7: =IF(AND(E7<=0),"C",IF(E7<=0.8,"A",IF(E7<=0.95,"B","C"))) -> C | G7: =VLOOKUP(B$4:B$25,I$4:M$25,5,0) -> B | I7: MR8854 C2 | J7: ='Юнит 22-31.12'!R10 -> 3 | K7: =J7/J$26 -> 0.033333333 | L7: =K7+L6 -> 0.86666667 | M7: =_xlfn.IFS(L7<80%,"A",L7<=95%,"B",L7>95%,"C") -> B
B8: MR 1819 черн | C8: ='Юнит 22-31.12'!AE11 -> 723.68 | D8: =C8/C$26 -> 0.15725421 | E8: =D8+E7 -> 2.0027771 | F8: =IF(AND(E8<=0),"C",IF(E8<=0.8,"A",IF(E8<=0.95,"B","C"))) -> C | G8: =VLOOKUP(B$4:B$25,I$4:M$25,5,0) -> B | I8: MR Р1874 черн | J8: ='Юнит 22-31.12'!R13 -> 3 | K8: =J8/J$26 -> 0.033333333 | L8: =K8+L7 -> 0.9 | M8: =_xlfn.IFS(L8<80%,"A",L8<=95%,"B",L8>95%,"C") -> B
B9: qs синие | C9: ='Юнит 22-31.12'!AE5 -> 636.39 | D9: =C9/C$26 -> 0.13828627 | E9: =D9+E8 -> 2.1410633 | F9: =IF(AND(E9<=0),"C",IF(E9<=0.8,"A",IF(E9<=0.95,"B","C"))) -> C | G9: =VLOOKUP(B$4:B$25,I$4:M$25,5,0) -> B | I9: qs синие | J9: ='Юнит 22-31.12'!R5 -> 2 | K9: =J9/J$26 -> 0.022222222 | L9: =K9+L8 -> 0.92222222 | M9: =_xlfn.IFS(L9<80%,"A",L9<=95%,"B",L9>95%,"C") -> B
B10: MR Р1874 корич | C10: ='Юнит 22-31.12'!AE14 -> 412.55 | D10: =C10/C$26 -> 0.089646288 | E10: =D10+E9 -> 2.2307096 | F10: =IF(AND(E10<=0),"C",IF(E10<=0.8,"A",IF(E10<=0.95,"B","C"))) -> C | G10: =VLOOKUP(B$4:B$25,I$4:M$25,5,0) -> B | I10: MR 1819 черн | J10: ='Юнит 22-31.12'!R11 -> 2 | K10: =J10/J$26 -> 0.022222222 | L10: =K10+L9 -> 0.94444444 | M10: =_xlfn.IFS(L10<80%,"A",L10<=95%,"B",L10>95%,"C") -> B
B11: MR 1819 корич | C11: ='Юнит 22-31.12'!AE12 -> 202.92 | D11: =C11/C$26 -> 0.044094109 | E11: =D11+E8 -> 2.0468712 | F11: =IF(AND(E11<=0),"C",IF(E11<=0.8,"A",IF(E11<=0.95,"B","C"))) -> C | G11: =VLOOKUP(B$4:B$25,I$4:M$25,5,0) -> C | I11: MR Р1874 корич | J11: ='Юнит 22-31.12'!R14 -> 2 | K11: =J11/J$26 -> 0.022222222 | L11: =K11+L8 -> 0.92222222 | M11: =_xlfn.IFS(L11<80%,"A",L11<=95%,"B",L11>95%,"C") -> B
B12: qs коричневые | C12: ='Юнит 22-31.12'!AE7 -> 0 | D12: =C12/C$26 -> 0 | E12: =D12+E11 -> 2.0468712 | F12: =IF(AND(E12<=0),"C",IF(E12<=0.8,"A",IF(E12<=0.95,"B","C"))) -> C | G12: =VLOOKUP(B$4:B$25,I$4:M$25,5,0) -> C | I12: MR Р1886 черн глянец | J12: ='Юнит 22-31.12'!R15 -> 2 | K12: =J12/J$26 -> 0.022222222 | L12: =K12+L11 -> 0.94444444 | M12: =_xlfn.IFS(L12<80%,"A",L12<=95%,"B",L12>95%,"C") -> B
B13: lux1 | C13: ='Юнит 22-31.12'!AE17 -> 0 | D13: =C13/C$26 -> 0 | E13: =D13+E12 -> 2.0468712 | F13: =IF(AND(E13<=0),"C",IF(E13<=0.8,"A",IF(E13<=0.95,"B","C"))) -> C | G13: =VLOOKUP(B$4:B$25,I$4:M$25,5,0) -> C | I13: MR 1819 корич | J13: ='Юнит 22-31.12'!R12 -> 1 | K13: =J13/J$26 -> 0.011111111 | L13: =K13+L12 -> 0.95555556 | M13: =_xlfn.IFS(L13<80%,"A",L13<=95%,"B",L13>95%,"C") -> C | P13: A | Q13: 0.8
B14: lux2 | C14: ='Юнит 22-31.12'!AE18 -> 0 | D14: =C14/C$26 -> 0 | E14: =D14+E13 -> 2.0468712 | F14: =IF(AND(E14<=0),"C",IF(E14<=0.8,"A",IF(E14<=0.95,"B","C"))) -> C | G14: =VLOOKUP(B$4:B$25,I$4:M$25,5,0) -> C | I14: qs коричневые | J14: ='Юнит 22-31.12'!R7 -> 0 | K14: =J14/J$26 -> 0 | L14: =K14+L13 -> 0.95555556 | M14: =_xlfn.IFS(L14<80%,"A",L14<=95%,"B",L14>95%,"C") -> C | P14: B | Q14: 0.15
B15: lux3 | C15: ='Юнит 22-31.12'!AE19 -> 0 | D15: =C15/C$26 -> 0 | E15: =D15+E14 -> 2.0468712 | F15: =IF(AND(E15<=0),"C",IF(E15<=0.8,"A",IF(E15<=0.95,"B","C"))) -> C | G15: =VLOOKUP(B$4:B$25,I$4:M$25,5,0) -> C | I15: th желтый Сул | J15: ='Юнит 22-31.12'!R8 -> 0 | K15: =J15/J$26 -> 0 | L15: =K15+L14 -> 0.95555556 | M15: =_xlfn.IFS(L15<80%,"A",L15<=95%,"B",L15>95%,"C") -> C | P15: C | Q15: 0.05
B16: lux5 | C16: ='Юнит 22-31.12'!AE21 -> 0 | D16: =C16/C$26 -> 0 | E16: =D16+E15 -> 2.0468712 | F16: =IF(AND(E16<=0),"C",IF(E16<=0.8,"A",IF(E16<=0.95,"B","C"))) -> C | G16: =VLOOKUP(B$4:B$25,I$4:M$25,5,0) -> C | I16: flip желтые Сул | J16: ='Юнит 22-31.12'!R9 -> 0 | K16: =J16/J$26 -> 0 | L16: =K16+L15 -> 0.95555556 | M16: =_xlfn.IFS(L16<80%,"A",L16<=95%,"B",L16>95%,"C") -> C
B17: lux6 | C17: ='Юнит 22-31.12'!AE22 -> 0 | D17: =C17/C$26 -> 0 | E17: =D17+E16 -> 2.0468712 | F17: =IF(AND(E17<=0),"C",IF(E17<=0.8,"A",IF(E17<=0.95,"B","C"))) -> C | G17: =VLOOKUP(B$4:B$25,I$4:M$25,5,0) -> C | I17: MR Р1886 корич | J17: ='Юнит 22-31.12'!R16 -> 0 | K17: =J17/J$26 -> 0 | L17: =K17+L16 -> 0.95555556 | M17: =_xlfn.IFS(L17<80%,"A",L17<=95%,"B",L17>95%,"C") -> C
B18: lux7 | C18: ='Юнит 22-31.12'!AE23 -> 0 | D18: =C18/C$26 -> 0 | E18: =D18+E17 -> 2.0468712 | F18: =IF(AND(E18<=0),"C",IF(E18<=0.8,"A",IF(E18<=0.95,"B","C"))) -> C | G18: =VLOOKUP(B$4:B$25,I$4:M$25,5,0) -> C | I18: lux1 | J18: ='Юнит 22-31.12'!R17 -> 0 | K18: =J18/J$26 -> 0 | L18: =K18+L17 -> 0.95555556 | M18: =_xlfn.IFS(L18<80%,"A",L18<=95%,"B",L18>95%,"C") -> C
B19: lux8 | C19: ='Юнит 22-31.12'!AE24 -> 0 | D19: =C19/C$26 -> 0 | E19: =D19+E18 -> 2.0468712 | F19: =IF(AND(E19<=0),"C",IF(E19<=0.8,"A",IF(E19<=0.95,"B","C"))) -> C | G19: =VLOOKUP(B$4:B$25,I$4:M$25,5,0) -> C | I19: lux2 | J19: ='Юнит 22-31.12'!R18 -> 0 | K19: =J19/J$26 -> 0 | L19: =K19+L18 -> 0.95555556 | M19: =_xlfn.IFS(L19<80%,"A",L19<=95%,"B",L19>95%,"C") -> C
B20: th желтый Сул | C20: ='Юнит 22-31.12'!AE8 -> -92 | D20: =C20/C$26 -> -0.019991415 | E20: =D20+E19 -> 2.0268797 | F20: =IF(AND(E20<=0),"C",IF(E20<=0.8,"A",IF(E20<=0.95,"B","C"))) -> C | G20: =VLOOKUP(B$4:B$25,I$4:M$25,5,0) -> C | I20: lux3 | J20: ='Юнит 22-31.12'!R19 -> 0 | K20: =J20/J$26 -> 0 | L20: =K20+L19 -> 0.95555556 | M20: =_xlfn.IFS(L20<80%,"A",L20<=95%,"B",L20>95%,"C") -> C
B21: lux4 | C21: ='Юнит 22-31.12'!AE20 -> -113.88 | D21: =C21/C$26 -> -0.024745896 | E21: =D21+E20 -> 2.0021339 | F21: =IF(AND(E21<=0),"C",IF(E21<=0.8,"A",IF(E21<=0.95,"B","C"))) -> C | G21: =VLOOKUP(B$4:B$25,I$4:M$25,5,0) -> C | I21: lux4 | J21: ='Юнит 22-31.12'!R20 -> 0 | K21: =J21/J$26 -> 0 | L21: =K21+L20 -> 0.95555556 | M21: =_xlfn.IFS(L21<80%,"A",L21<=95%,"B",L21>95%,"C") -> C
B22: MR Р1886 черн глянец | C22: ='Юнит 22-31.12'!AE15 -> -307.59 | D22: =C22/C$26 -> -0.06683869 | E22: =D22+E21 -> 1.9352952 | F22: =IF(AND(E22<=0),"C",IF(E22<=0.8,"A",IF(E22<=0.95,"B","C"))) -> C | G22: =VLOOKUP(B$4:B$25,I$4:M$25,5,0) -> B | I22: lux5 | J22: ='Юнит 22-31.12'!R21 -> 0 | K22: =J22/J$26 -> 0 | L22: =K22+L21 -> 0.95555556 | M22: =_xlfn.IFS(L22<80%,"A",L22<=95%,"B",L22>95%,"C") -> C
B23: MR Р1886 корич | C23: ='Юнит 22-31.12'!AE16 -> -664.7 | D23: =C23/C$26 -> -0.14443798 | E23: =D23+E22 -> 1.7908572 | F23: =IF(AND(E23<=0),"C",IF(E23<=0.8,"A",IF(E23<=0.95,"B","C"))) -> C | G23: =VLOOKUP(B$4:B$25,I$4:M$25,5,0) -> C | I23: lux6 | J23: ='Юнит 22-31.12'!R22 -> 0 | K23: =J23/J$26 -> 0 | L23: =K23+L22 -> 0.95555556 | M23: =_xlfn.IFS(L23<80%,"A",L23<=95%,"B",L23>95%,"C") -> C
B24: flip желтые Сул | C24: ='Юнит 22-31.12'!AE9 -> -2274.0265 | D24: =C24/C$26 -> -0.49414139 | E24: =D24+E23 -> 1.2967158 | F24: =IF(AND(E24<=0),"C",IF(E24<=0.8,"A",IF(E24<=0.95,"B","C"))) -> C | G24: =VLOOKUP(B$4:B$25,I$4:M$25,5,0) -> C | I24: lux7 | J24: ='Юнит 22-31.12'!R23 -> 0 | K24: =J24/J$26 -> 0 | L24: =K24+L23 -> 0.95555556 | M24: =_xlfn.IFS(L24<80%,"A",L24<=95%,"B",L24>95%,"C") -> C
B25: qs желтые | C25: ='Юнит 22-31.12'!AE6 -> -2414.4187 | D25: =C25/C$26 -> -0.52464835 | E25: =D25+E24 -> 0.77206744 | F25: =IF(AND(E25<=0),"C",IF(E25<=0.8,"A",IF(E25<=0.95,"B","C"))) -> A | G25: =VLOOKUP(B$4:B$25,I$4:M$25,5,0) -> B | I25: lux8 | J25: ='Юнит 22-31.12'!R24 -> 0 | K25: =J25/J$26 -> 0 | L25: =K25+L24 -> 0.95555556 | M25: =_xlfn.IFS(L25<80%,"A",L25<=95%,"B",L25>95%,"C") -> C
C26: =SUM(C4:C25) -> 4601.9753 | D26: =SUM(D4:D25) -> 1 | J26: =SUM(J4:J25) -> 90 | K26: =SUM(K4:K25) -> 1
B28: ТУНИКИ
C29: Прибыль | D29: % прибыль | E29: Доля | F29: ABC прибыль | G29: ABC кол-во | J29: Кол-во | K29: % кол-во | L29: Доля | M29: ABC кол-во
B30: tunika02 оливковая с руч вышивкой | C30: ='Юнит 22-31.12'!AE28 -> 0 | D30: =C30/C$50 -> 0 | E30: =D30 -> 0 | F30: =IF(AND(E30<=0),"C",IF(E30<=0.8,"A",IF(E30<=0.95,"B","C"))) -> C | G30: =VLOOKUP(B$30:B$50,I$30:M$50,5,0) -> #DIV/0! | I30: tunika02 оливковая с руч вышивкой | J30: ='Юнит 22-31.12'!R28 -> 0 | K30: =J30/J$50 -> #DIV/0! | L30: =K30 -> #DIV/0! | M30: =_xlfn.IFS(L30<80%,"A",L30<=95%,"B",L30>95%,"C") -> #DIV/0!
B31: tunika03 черная распашная | C31: ='Юнит 22-31.12'!AE29 -> 0 | D31: =C31/C$50 -> 0 | E31: =D31+E30 -> 0 | F31: =IF(AND(E31<=0),"C",IF(E31<=0.8,"A",IF(E31<=0.95,"B","C"))) -> C | G31: =VLOOKUP(B$30:B$50,I$30:M$50,5,0) -> #DIV/0! | I31: tunika03 черная распашная | J31: ='Юнит 22-31.12'!R29 -> 0 | K31: =J31/J$50 -> #DIV/0! | L31: =K31+L30 -> #DIV/0! | M31: =_xlfn.IFS(L31<80%,"A",L31<=95%,"B",L31>95%,"C") -> #DIV/0!
B32: tunika05 белая распашная | C32: ='Юнит 22-31.12'!AE30 -> 0 | D32: =C32/C$50 -> 0 | E32: =D32+E31 -> 0 | F32: =IF(AND(E32<=0),"C",IF(E32<=0.8,"A",IF(E32<=0.95,"B","C"))) -> C | G32: =VLOOKUP(B$30:B$50,I$30:M$50,5,0) -> #DIV/0! | I32: tunika05 белая распашная | J32: ='Юнит 22-31.12'!R30 -> 0 | K32: =J32/J$50 -> #DIV/0! | L32: =K32+L31 -> #DIV/0! | M32: =_xlfn.IFS(L32<80%,"A",L32<=95%,"B",L32>95%,"C") -> #DIV/0!
B33: tunika06 черная | C33: ='Юнит 22-31.12'!AE32 -> 0 | D33: =C33/C$50 -> 0 | E33: =D33+E32 -> 0 | F33: =IF(AND(E33<=0),"C",IF(E33<=0.8,"A",IF(E33<=0.95,"B","C"))) -> C | G33: =VLOOKUP(B$30:B$50,I$30:M$50,5,0) -> #DIV/0! | I33: tunika06 белая | J33: ='Юнит 22-31.12'!R31 -> 0 | K33: =J33/J$50 -> #DIV/0! | L33: =K33+L32 -> #DIV/0! | M33: =_xlfn.IFS(L33<80%,"A",L33<=95%,"B",L33>95%,"C") -> #DIV/0!
B34: tunika08 белая | C34: ='Юнит 22-31.12'!AE34 -> 0 | D34: =C34/C$50 -> 0 | E34: =D34+E33 -> 0 | F34: =IF(AND(E34<=0),"C",IF(E34<=0.8,"A",IF(E34<=0.95,"B","C"))) -> C | G34: =VLOOKUP(B$30:B$50,I$30:M$50,5,0) -> #DIV/0! | I34: tunika06 черная | J34: ='Юнит 22-31.12'!R32 -> 0 | K34: =J34/J$50 -> #DIV/0! | L34: =K34+L33 -> #DIV/0! | M34: =_xlfn.IFS(L34<80%,"A",L34<=95%,"B",L34>95%,"C") -> #DIV/0!
B35: tunika08 черная | C35: ='Юнит 22-31.12'!AE35 -> 0 | D35: =C35/C$50 -> 0 | E35: =D35+E34 -> 0 | F35: =IF(AND(E35<=0),"C",IF(E35<=0.8,"A",IF(E35<=0.95,"B","C"))) -> C | G35: =VLOOKUP(B$30:B$50,I$30:M$50,5,0) -> #DIV/0! | I35: tunika07 кружево | J35: ='Юнит 22-31.12'!R33 -> 0 | K35: =J35/J$50 -> #DIV/0! | L35: =K35+L34 -> #DIV/0! | M35: =_xlfn.IFS(L35<80%,"A",L35<=95%,"B",L35>95%,"C") -> #DIV/0!
B36: tunika08 зеленая | C36: ='Юнит 22-31.12'!AE36 -> 0 | D36: =C36/C$50 -> 0 | E36: =D36+E35 -> 0 | F36: =IF(AND(E36<=0),"C",IF(E36<=0.8,"A",IF(E36<=0.95,"B","C"))) -> C | G36: =VLOOKUP(B$30:B$50,I$30:M$50,5,0) -> #DIV/0! | I36: tunika08 белая | J36: ='Юнит 22-31.12'!R34 -> 0 | K36: =J36/J$50 -> #DIV/0! | L36: =K36+L35 -> #DIV/0! | M36: =_xlfn.IFS(L36<80%,"A",L36<=95%,"B",L36>95%,"C") -> #DIV/0!
B37: tunika09 кимоно | C37: ='Юнит 22-31.12'!AE37 -> 0 | D37: =C37/C$50 -> 0 | E37: =D37+E36 -> 0 | F37: =IF(AND(E37<=0),"C",IF(E37<=0.8,"A",IF(E37<=0.95,"B","C"))) -> C | G37: =VLOOKUP(B$30:B$50,I$30:M$50,5,0) -> #DIV/0! | I37: tunika08 черная | J37: ='Юнит 22-31.12'!R35 -> 0 | K37: =J37/J$50 -> #DIV/0! | L37: =K37+L36 -> #DIV/0! | M37: =_xlfn.IFS(L37<80%,"A",L37<=95%,"B",L37>95%,"C") -> #DIV/0!
B38: tunika11 халат зеленая | C38: ='Юнит 22-31.12'!AE39 -> 0 | D38: =C38/C$50 -> 0 | E38: =D38+E37 -> 0 | F38: =IF(AND(E38<=0),"C",IF(E38<=0.8,"A",IF(E38<=0.95,"B","C"))) -> C | G38: =VLOOKUP(B$30:B$50,I$30:M$50,5,0) -> #DIV/0! | I38: tunika08 зеленая | J38: ='Юнит 22-31.12'!R36 -> 0 | K38: =J38/J$50 -> #DIV/0! | L38: =K38+L37 -> #DIV/0! | M38: =_xlfn.IFS(L38<80%,"A",L38<=95%,"B",L38>95%,"C") -> #DIV/0!
B39: tunika12 халат белая | C39: ='Юнит 22-31.12'!AE40 -> 0 | D39: =C39/C$50 -> 0 | E39: =D39+E38 -> 0 | F39: =IF(AND(E39<=0),"C",IF(E39<=0.8,"A",IF(E39<=0.95,"B","C"))) -> C | G39: =VLOOKUP(B$30:B$50,I$30:M$50,5,0) -> #DIV/0! | I39: tunika09 кимоно | J39: ='Юнит 22-31.12'!R37 -> 0 | K39: =J39/J$50 -> #DIV/0! | L39: =K39+L38 -> #DIV/0! | M39: =_xlfn.IFS(L39<80%,"A",L39<=95%,"B",L39>95%,"C") -> #DIV/0!
B40: tunika13 халат черная | C40: ='Юнит 22-31.12'!AE41 -> 0 | D40: =C40/C$50 -> 0 | E40: =D40+E39 -> 0 | F40: =IF(AND(E40<=0),"C",IF(E40<=0.8,"A",IF(E40<=0.95,"B","C"))) -> C | G40: =VLOOKUP(B$30:B$50,I$30:M$50,5,0) -> #DIV/0! | I40: tunika10 кимоно ч/б | J40: ='Юнит 22-31.12'!R38 -> 0 | K40: =J40/J$50 -> #DIV/0! | L40: =K40+L39 -> #DIV/0! | M40: =_xlfn.IFS(L40<80%,"A",L40<=95%,"B",L40>95%,"C") -> #DIV/0!
B41: tunika14 халат с разрезами черный | C41: ='Юнит 22-31.12'!AE43 -> 0 | D41: =C41/C$50 -> 0 | E41: =D41+E40 -> 0 | F41: =IF(AND(E41<=0),"C",IF(E41<=0.8,"A",IF(E41<=0.95,"B","C"))) -> C | G41: =VLOOKUP(B$30:B$50,I$30:M$50,5,0) -> #DIV/0! | I41: tunika11 халат зеленая | J41: ='Юнит 22-31.12'!R39 -> 0 | K41: =J41/J$50 -> #DIV/0! | L41: =K41+L40 -> #DIV/0! | M41: =_xlfn.IFS(L41<80%,"A",L41<=95%,"B",L41>95%,"C") -> #DIV/0!
B42: tunika16 сетка черная | C42: ='Юнит 22-31.12'!AE47 -> 0 | D42: =C42/C$50 -> 0 | E42: =D42+E41 -> 0 | F42: =IF(AND(E42<=0),"C",IF(E42<=0.8,"A",IF(E42<=0.95,"B","C"))) -> C | G42: =VLOOKUP(B$30:B$50,I$30:M$50,5,0) -> #DIV/0! | I42: tunika12 халат белая | J42: ='Юнит 22-31.12'!R40 -> 0 | K42: =J42/J$50 -> #DIV/0! | L42: =K42+L41 -> #DIV/0! | M42: =_xlfn.IFS(L42<80%,"A",L42<=95%,"B",L42>95%,"C") -> #DIV/0!
B43: tunika07 кружево | C43: ='Юнит 22-31.12'!AE33 -> -56.94 | D43: =C43/C$50 -> 0.010258138 | E43: =D43+E42 -> 0.010258138 | F43: =IF(AND(E43<=0),"C",IF(E43<=0.8,"A",IF(E43<=0.95,"B","C"))) -> A | G43: =VLOOKUP(B$30:B$50,I$30:M$50,5,0) -> #DIV/0! | I43: tunika13 халат черная | J43: ='Юнит 22-31.12'!R41 -> 0 | K43: =J43/J$50 -> #DIV/0! | L43: =K43+L42 -> #DIV/0! | M43: =_xlfn.IFS(L43<80%,"A",L43<=95%,"B",L43>95%,"C") -> #DIV/0!
B44: tunika06 белая | C44: ='Юнит 22-31.12'!AE31 -> -113.88 | D44: =C44/C$50 -> 0.020516275 | E44: =D44+E43 -> 0.030774413 | F44: =IF(AND(E44<=0),"C",IF(E44<=0.8,"A",IF(E44<=0.95,"B","C"))) -> A | G44: =VLOOKUP(B$30:B$50,I$30:M$50,5,0) -> #DIV/0! | I44: tunika14 халат с разрезами белая | J44: ='Юнит 22-31.12'!R42 -> 0 | K44: =J44/J$50 -> #DIV/0! | L44: =K44+L43 -> #DIV/0! | M44: =_xlfn.IFS(L44<80%,"A",L44<=95%,"B",L44>95%,"C") -> #DIV/0!
B45: tunika10 кимоно ч/б | C45: ='Юнит 22-31.12'!AE38 -> -113.88 | D45: =C45/C$50 -> 0.020516275 | E45: =D45+E44 -> 0.051290688 | F45: =IF(AND(E45<=0),"C",IF(E45<=0.8,"A",IF(E45<=0.95,"B","C"))) -> A | G45: =VLOOKUP(B$30:B$50,I$30:M$50,5,0) -> #DIV/0! | I45: tunika14 халат с разрезами черный | J45: ='Юнит 22-31.12'!R43 -> 0 | K45: =J45/J$50 -> #DIV/0! | L45: =K45+L44 -> #DIV/0! | M45: =_xlfn.IFS(L45<80%,"A",L45<=95%,"B",L45>95%,"C") -> #DIV/0!
B46: tunika16 сетка белая | C46: ='Юнит 22-31.12'!AE46 -> -1233.8363 | D46: =C46/C$50 -> 0.22228421 | E46: =D46+E45 -> 0.2735749 | F46: =IF(AND(E46<=0),"C",IF(E46<=0.8,"A",IF(E46<=0.95,"B","C"))) -> A | G46: =VLOOKUP(B$30:B$50,I$30:M$50,5,0) -> #DIV/0! | I46: tunika15 кимоно бирюза | J46: ='Юнит 22-31.12'!R44 -> 0 | K46: =J46/J$50 -> #DIV/0! | L46: =K46+L45 -> #DIV/0! | M46: =_xlfn.IFS(L46<80%,"A",L46<=95%,"B",L46>95%,"C") -> #DIV/0!
B47: tunika15 кимоно бирюза | C47: ='Юнит 22-31.12'!AE44 -> -1248.8611 | D47: =C47/C$50 -> 0.22499103 | E47: =D47+E46 -> 0.49856593 | F47: =IF(AND(E47<=0),"C",IF(E47<=0.8,"A",IF(E47<=0.95,"B","C"))) -> A | G47: =VLOOKUP(B$30:B$50,I$30:M$50,5,0) -> #DIV/0! | I47: tunika15 кимоно песочная | J47: ='Юнит 22-31.12'!R45 -> 0 | K47: =J47/J$50 -> #DIV/0! | L47: =K47+L46 -> #DIV/0! | M47: =_xlfn.IFS(L47<80%,"A",L47<=95%,"B",L47>95%,"C") -> #DIV/0!
B48: tunika15 кимоно песочная | C48: ='Юнит 22-31.12'!AE45 -> -1288.3177 | D48: =C48/C$50 -> 0.2320994 | E48: =D48+E47 -> 0.73066533 | F48: =IF(AND(E48<=0),"C",IF(E48<=0.8,"A",IF(E48<=0.95,"B","C"))) -> A | G48: =VLOOKUP(B$30:B$50,I$30:M$50,5,0) -> #DIV/0! | I48: tunika16 сетка белая | J48: ='Юнит 22-31.12'!R46 -> 0 | K48: =J48/J$50 -> #DIV/0! | L48: =K48+L47 -> #DIV/0! | M48: =_xlfn.IFS(L48<80%,"A",L48<=95%,"B",L48>95%,"C") -> #DIV/0!
B49: tunika14 халат с разрезами белая | C49: ='Юнит 22-31.12'!AE42 -> -1495 | D49: =C49/C$50 -> 0.26933467 | E49: =D49+E48 -> 1 | F49: =IF(AND(E49<=0),"C",IF(E49<=0.8,"A",IF(E49<=0.95,"B","C"))) -> C | G49: =VLOOKUP(B$30:B$50,I$30:M$50,5,0) -> #DIV/0! | I49: tunika16 сетка черная | J49: ='Юнит 22-31.12'!R47 -> 0 | K49: =J49/J$50 -> #DIV/0! | L49: =K49+L48 -> #DIV/0! | M49: =_xlfn.IFS(L49<80%,"A",L49<=95%,"B",L49>95%,"C") -> #DIV/0!
C50: =SUM(C30:C49) -> -5550.7151 | D50: =SUM(D30:D49) -> 1 | J50: =SUM(J30:J49) -> 0 | K50: =SUM(K30:K49) -> #DIV/0!

Sheet АВС 15-21.12
B2: ОЧКИ
C3: Прибыль | D3: % прибыль | E3: Доля | F3: ABC прибыль | G3: ABC кол-во | J3: Кол-во | K3: % кол-во | L3: Доля | M3: ABC кол-во
B4: qs коричневые | C4: ='Юнит 15-21.12'!AE7 -> 569.92 | D4: =C4/C$26 -> -1.4004686 | E4: =D4 -> -1.4004686 | F4: =IF(AND(E4<=0),"C",IF(E4<=0.8,"A",IF(E4<=0.95,"B","C"))) -> C | G4: =VLOOKUP(B$4:B$25,I$4:M$25,5,0) -> B | I4: черные с железкой классика | J4: ='Юнит 15-21.12'!R3 -> 17 | K4: =J4/J$26 -> 0.4047619 | L4: =K4 -> 0.4047619 | M4: =_xlfn.IFS(L4<80%,"A",L4<=95%,"B",L4>95%,"C") -> A
B5: qs желтые | C5: ='Юнит 15-21.12'!AE6 -> 494.53307 | D5: =C5/C$26 -> -1.2152198 | E5: =D5+E4 -> -2.6156884 | F5: =IF(AND(E5<=0),"C",IF(E5<=0.8,"A",IF(E5<=0.95,"B","C"))) -> C | G5: =VLOOKUP(B$4:B$25,I$4:M$25,5,0) -> A | I5: qs желтые | J5: ='Юнит 15-21.12'!R6 -> 16 | K5: =J5/J$26 -> 0.38095238 | L5: =K5+L4 -> 0.78571429 | M5: =_xlfn.IFS(L5<80%,"A",L5<=95%,"B",L5>95%,"C") -> A
B6: qs синие | C6: ='Юнит 15-21.12'!AE5 -> 460.99 | D6: =C6/C$26 -> -1.1327941 | E6: =D6+E5 -> -3.7484826 | F6: =IF(AND(E6<=0),"C",IF(E6<=0.8,"A",IF(E6<=0.95,"B","C"))) -> C | G6: =VLOOKUP(B$4:B$25,I$4:M$25,5,0) -> B | I6: qs синие | J6: ='Юнит 15-21.12'!R5 -> 2 | K6: =J6/J$26 -> 0.047619048 | L6: =K6+L5 -> 0.83333333 | M6: =_xlfn.IFS(L6<80%,"A",L6<=95%,"B",L6>95%,"C") -> B
B7: MR Р1874 корич | C7: ='Юнит 15-21.12'!AE14 -> 395.12 | D7: =C7/C$26 -> -0.97093131 | E7: =D7+E6 -> -4.7194139 | F7: =IF(AND(E7<=0),"C",IF(E7<=0.8,"A",IF(E7<=0.95,"B","C"))) -> C | G7: =VLOOKUP(B$4:B$25,I$4:M$25,5,0) -> C | I7: MR Р1886 черн глянец | J7: ='Юнит 15-21.12'!R15 -> 2 | K7: =J7/J$26 -> 0.047619048 | L7: =K7+L6 -> 0.88095238 | M7: =_xlfn.IFS(L7<80%,"A",L7<=95%,"B",L7>95%,"C") -> B
B8: th желтый Сул | C8: ='Юнит 15-21.12'!AE8 -> 373.60913 | D8: =C8/C$26 -> -0.91807248 | E8: =D8+E7 -> -5.6374864 | F8: =IF(AND(E8<=0),"C",IF(E8<=0.8,"A",IF(E8<=0.95,"B","C"))) -> C | G8: =VLOOKUP(B$4:B$25,I$4:M$25,5,0) -> C | I8: qs черные | J8: ='Юнит 15-21.12'!R4 -> 1 | K8: =J8/J$26 -> 0.023809524 | L8: =K8+L7 -> 0.9047619 | M8: =_xlfn.IFS(L8<80%,"A",L8<=95%,"B",L8>95%,"C") -> B
B9: MR Р1886 черн глянец | C9: ='Юнит 15-21.12'!AE15 -> 373.6 | D9: =C9/C$26 -> -0.91805005 | E9: =D9+E8 -> -6.5555364 | F9: =IF(AND(E9<=0),"C",IF(E9<=0.8,"A",IF(E9<=0.95,"B","C"))) -> C | G9: =VLOOKUP(B$4:B$25,I$4:M$25,5,0) -> B | I9: qs коричневые | J9: ='Юнит 15-21.12'!R7 -> 1 | K9: =J9/J$26 -> 0.023809524 | L9: =K9+L8 -> 0.92857143 | M9: =_xlfn.IFS(L9<80%,"A",L9<=95%,"B",L9>95%,"C") -> B
B10: MR 1819 корич | C10: ='Юнит 15-21.12'!AE12 -> 300.54 | D10: =C10/C$26 -> -0.73851917 | E10: =D10+E9 -> -7.2940556 | F10: =IF(AND(E10<=0),"C",IF(E10<=0.8,"A",IF(E10<=0.95,"B","C"))) -> C | G10: =VLOOKUP(B$4:B$25,I$4:M$25,5,0) -> B | I10: th желтый Сул | J10: ='Юнит 15-21.12'!R8 -> 1 | K10: =J10/J$26 -> 0.023809524 | L10: =K10+L9 -> 0.95238095 | M10: =_xlfn.IFS(L10<80%,"A",L10<=95%,"B",L10>95%,"C") -> C
B11: qs черные | C11: ='Юнит 15-21.12'!AE4 -> 254.85 | D11: =C11/C$26 -> -0.6262448 | E11: =D11+E8 -> -6.2637312 | F11: =IF(AND(E11<=0),"C",IF(E11<=0.8,"A",IF(E11<=0.95,"B","C"))) -> C | G11: =VLOOKUP(B$4:B$25,I$4:M$25,5,0) -> B | I11: MR 1819 корич | J11: ='Юнит 15-21.12'!R12 -> 1 | K11: =J11/J$26 -> 0.023809524 | L11: =K11+L8 -> 0.92857143 | M11: =_xlfn.IFS(L11<80%,"A",L11<=95%,"B",L11>95%,"C") -> B
B12: MR8854 C2 | C12: ='Юнит 15-21.12'!AE10 -> 0 | D12: =C12/C$26 -> 0 | E12: =D12+E11 -> -6.2637312 | F12: =IF(AND(E12<=0),"C",IF(E12<=0.8,"A",IF(E12<=0.95,"B","C"))) -> C | G12: =VLOOKUP(B$4:B$25,I$4:M$25,5,0) -> C | I12: MR Р1874 корич | J12: ='Юнит 15-21.12'!R14 -> 1 | K12: =J12/J$26 -> 0.023809524 | L12: =K12+L11 -> 0.95238095 | M12: =_xlfn.IFS(L12<80%,"A",L12<=95%,"B",L12>95%,"C") -> C
B13: MR 1819 черн | C13: ='Юнит 15-21.12'!AE11 -> 0 | D13: =C13/C$26 -> 0 | E13: =D13+E12 -> -6.2637312 | F13: =IF(AND(E13<=0),"C",IF(E13<=0.8,"A",IF(E13<=0.95,"B","C"))) -> C | G13: =VLOOKUP(B$4:B$25,I$4:M$25,5,0) -> C | I13: flip желтые Сул | J13: ='Юнит 15-21.12'!R9 -> 0 | K13: =J13/J$26 -> 0 | L13: =K13+L12 -> 0.95238095 | M13: =_xlfn.IFS(L13<80%,"A",L13<=95%,"B",L13>95%,"C") -> C | P13: A | Q13: 0.8
B14: MR Р1874 черн | C14: ='Юнит 15-21.12'!AE13 -> 0 | D14: =C14/C$26 -> 0 | E14: =D14+E13 -> -6.2637312 | F14: =IF(AND(E14<=0),"C",IF(E14<=0.8,"A",IF(E14<=0.95,"B","C"))) -> C | G14: =VLOOKUP(B$4:B$25,I$4:M$25,5,0) -> C | I14: MR8854 C2 | J14: ='Юнит 15-21.12'!R10 -> 0 | K14: =J14/J$26 -> 0 | L14: =K14+L13 -> 0.95238095 | M14: =_xlfn.IFS(L14<80%,"A",L14<=95%,"B",L14>95%,"C") -> C | P14: B | Q14: 0.15
B15: MR Р1886 корич | C15: ='Юнит 15-21.12'!AE16 -> 0 | D15: =C15/C$26 -> 0 | E15: =D15+E14 -> -6.2637312 | F15: =IF(AND(E15<=0),"C",IF(E15<=0.8,"A",IF(E15<=0.95,"B","C"))) -> C | G15: =VLOOKUP(B$4:B$25,I$4:M$25,5,0) -> C | I15: MR 1819 черн | J15: ='Юнит 15-21.12'!R11 -> 0 | K15: =J15/J$26 -> 0 | L15: =K15+L14 -> 0.95238095 | M15: =_xlfn.IFS(L15<80%,"A",L15<=95%,"B",L15>95%,"C") -> C | P15: C | Q15: 0.05
B16: lux1 | C16: ='Юнит 15-21.12'!AE17 -> 0 | D16: =C16/C$26 -> 0 | E16: =D16+E15 -> -6.2637312 | F16: =IF(AND(E16<=0),"C",IF(E16<=0.8,"A",IF(E16<=0.95,"B","C"))) -> C | G16: =VLOOKUP(B$4:B$25,I$4:M$25,5,0) -> C | I16: MR Р1874 черн | J16: ='Юнит 15-21.12'!R13 -> 0 | K16: =J16/J$26 -> 0 | L16: =K16+L15 -> 0.95238095 | M16: =_xlfn.IFS(L16<80%,"A",L16<=95%,"B",L16>95%,"C") -> C
B17: lux2 | C17: ='Юнит 15-21.12'!AE18 -> 0 | D17: =C17/C$26 -> 0 | E17: =D17+E16 -> -6.2637312 | F17: =IF(AND(E17<=0),"C",IF(E17<=0.8,"A",IF(E17<=0.95,"B","C"))) -> C | G17: =VLOOKUP(B$4:B$25,I$4:M$25,5,0) -> C | I17: MR Р1886 корич | J17: ='Юнит 15-21.12'!R16 -> 0 | K17: =J17/J$26 -> 0 | L17: =K17+L16 -> 0.95238095 | M17: =_xlfn.IFS(L17<80%,"A",L17<=95%,"B",L17>95%,"C") -> C
B18: lux3 | C18: ='Юнит 15-21.12'!AE19 -> 0 | D18: =C18/C$26 -> 0 | E18: =D18+E17 -> -6.2637312 | F18: =IF(AND(E18<=0),"C",IF(E18<=0.8,"A",IF(E18<=0.95,"B","C"))) -> C | G18: =VLOOKUP(B$4:B$25,I$4:M$25,5,0) -> C | I18: lux1 | J18: ='Юнит 15-21.12'!R17 -> 0 | K18: =J18/J$26 -> 0 | L18: =K18+L17 -> 0.95238095 | M18: =_xlfn.IFS(L18<80%,"A",L18<=95%,"B",L18>95%,"C") -> C
B19: lux4 | C19: ='Юнит 15-21.12'!AE20 -> 0 | D19: =C19/C$26 -> 0 | E19: =D19+E18 -> -6.2637312 | F19: =IF(AND(E19<=0),"C",IF(E19<=0.8,"A",IF(E19<=0.95,"B","C"))) -> C | G19: =VLOOKUP(B$4:B$25,I$4:M$25,5,0) -> C | I19: lux2 | J19: ='Юнит 15-21.12'!R18 -> 0 | K19: =J19/J$26 -> 0 | L19: =K19+L18 -> 0.95238095 | M19: =_xlfn.IFS(L19<80%,"A",L19<=95%,"B",L19>95%,"C") -> C
B20: lux5 | C20: ='Юнит 15-21.12'!AE21 -> 0 | D20: =C20/C$26 -> 0 | E20: =D20+E19 -> -6.2637312 | F20: =IF(AND(E20<=0),"C",IF(E20<=0.8,"A",IF(E20<=0.95,"B","C"))) -> C | G20: =VLOOKUP(B$4:B$25,I$4:M$25,5,0) -> C | I20: lux3 | J20: ='Юнит 15-21.12'!R19 -> 0 | K20: =J20/J$26 -> 0 | L20: =K20+L19 -> 0.95238095 | M20: =_xlfn.IFS(L20<80%,"A",L20<=95%,"B",L20>95%,"C") -> C
B21: lux6 | C21: ='Юнит 15-21.12'!AE22 -> 0 | D21: =C21/C$26 -> 0 | E21: =D21+E20 -> -6.2637312 | F21: =IF(AND(E21<=0),"C",IF(E21<=0.8,"A",IF(E21<=0.95,"B","C"))) -> C | G21: =VLOOKUP(B$4:B$25,I$4:M$25,5,0) -> C | I21: lux4 | J21: ='Юнит 15-21.12'!R20 -> 0 | K21: =J21/J$26 -> 0 | L21: =K21+L20 -> 0.95238095 | M21: =_xlfn.IFS(L21<80%,"A",L21<=95%,"B",L21>95%,"C") -> C
B22: lux7 | C22: ='Юнит 15-21.12'!AE23 -> 0 | D22: =C22/C$26 -> 0 | E22: =D22+E21 -> -6.2637312 | F22: =IF(AND(E22<=0),"C",IF(E22<=0.8,"A",IF(E22<=0.95,"B","C"))) -> C | G22: =VLOOKUP(B$4:B$25,I$4:M$25,5,0) -> C | I22: lux5 | J22: ='Юнит 15-21.12'!R21 -> 0 | K22: =J22/J$26 -> 0 | L22: =K22+L21 -> 0.95238095 | M22: =_xlfn.IFS(L22<80%,"A",L22<=95%,"B",L22>95%,"C") -> C
B23: lux8 | C23: ='Юнит 15-21.12'!AE24 -> 0 | D23: =C23/C$26 -> 0 | E23: =D23+E22 -> -6.2637312 | F23: =IF(AND(E23<=0),"C",IF(E23<=0.8,"A",IF(E23<=0.95,"B","C"))) -> C | G23: =VLOOKUP(B$4:B$25,I$4:M$25,5,0) -> C | I23: lux6 | J23: ='Юнит 15-21.12'!R22 -> 0 | K23: =J23/J$26 -> 0 | L23: =K23+L22 -> 0.95238095 | M23: =_xlfn.IFS(L23<80%,"A",L23<=95%,"B",L23>95%,"C") -> C
B24: flip желтые Сул | C24: ='Юнит 15-21.12'!AE9 -> -92 | D24: =C24/C$26 -> 0.22607228 | E24: =D24+E23 -> -6.0376589 | F24: =IF(AND(E24<=0),"C",IF(E24<=0.8,"A",IF(E24<=0.95,"B","C"))) -> C | G24: =VLOOKUP(B$4:B$25,I$4:M$25,5,0) -> C | I24: lux7 | J24: ='Юнит 15-21.12'!R23 -> 0 | K24: =J24/J$26 -> 0 | L24: =K24+L23 -> 0.95238095 | M24: =_xlfn.IFS(L24<80%,"A",L24<=95%,"B",L24>95%,"C") -> C
B25: черные с железкой классика | C25: ='Юнит 15-21.12'!AE3 -> -3538.1117 | D25: =C25/C$26 -> 8.6942281 | E25: =D25+E24 -> 2.6565692 | F25: =IF(AND(E25<=0),"C",IF(E25<=0.8,"A",IF(E25<=0.95,"B","C"))) -> C | G25: =VLOOKUP(B$4:B$25,I$4:M$25,5,0) -> A | I25: lux8 | J25: ='Юнит 15-21.12'!R24 -> 0 | K25: =J25/J$26 -> 0 | L25: =K25+L24 -> 0.95238095 | M25: =_xlfn.IFS(L25<80%,"A",L25<=95%,"B",L25>95%,"C") -> C
C26: =SUM(C4:C25) -> -406.94949 | D26: =SUM(D4:D25) -> 1 | J26: =SUM(J4:J25) -> 42 | K26: =SUM(K4:K25) -> 1
B28: ТУНИКИ
C29: Прибыль | D29: % прибыль | E29: Доля | F29: ABC прибыль | G29: ABC кол-во | J29: Кол-во | K29: % кол-во | L29: Доля | M29: ABC кол-во
B30: tunika02 оливковая с руч вышивкой | C30: ='Юнит 15-21.12'!AE28 -> 0 | D30: =C30/C$50 -> 0 | E30: =D30 -> 0 | F30: =IF(AND(E30<=0),"C",IF(E30<=0.8,"A",IF(E30<=0.95,"B","C"))) -> C | G30: =VLOOKUP(B$30:B$50,I$30:M$50,5,0) -> A | I30: tunika02 оливковая с руч вышивкой | J30: ='Юнит 15-21.12'!R28 -> 0 | K30: =J30/J$50 -> 0 | L30: =K30 -> 0 | M30: =_xlfn.IFS(L30<80%,"A",L30<=95%,"B",L30>95%,"C") -> A
B31: tunika03 черная распашная | C31: ='Юнит 15-21.12'!AE29 -> 0 | D31: =C31/C$50 -> 0 | E31: =D31+E30 -> 0 | F31: =IF(AND(E31<=0),"C",IF(E31<=0.8,"A",IF(E31<=0.95,"B","C"))) -> C | G31: =VLOOKUP(B$30:B$50,I$30:M$50,5,0) -> A | I31: tunika03 черная распашная | J31: ='Юнит 15-21.12'!R29 -> 0 | K31: =J31/J$50 -> 0 | L31: =K31+L30 -> 0 | M31: =_xlfn.IFS(L31<80%,"A",L31<=95%,"B",L31>95%,"C") -> A
B32: tunika05 белая распашная | C32: ='Юнит 15-21.12'!AE30 -> 0 | D32: =C32/C$50 -> 0 | E32: =D32+E31 -> 0 | F32: =IF(AND(E32<=0),"C",IF(E32<=0.8,"A",IF(E32<=0.95,"B","C"))) -> C | G32: =VLOOKUP(B$30:B$50,I$30:M$50,5,0) -> A | I32: tunika05 белая распашная | J32: ='Юнит 15-21.12'!R30 -> 0 | K32: =J32/J$50 -> 0 | L32: =K32+L31 -> 0 | M32: =_xlfn.IFS(L32<80%,"A",L32<=95%,"B",L32>95%,"C") -> A
B33: tunika06 белая | C33: ='Юнит 15-21.12'!AE31 -> 0 | D33: =C33/C$50 -> 0 | E33: =D33+E32 -> 0 | F33: =IF(AND(E33<=0),"C",IF(E33<=0.8,"A",IF(E33<=0.95,"B","C"))) -> C | G33: =VLOOKUP(B$30:B$50,I$30:M$50,5,0) -> A | I33: tunika06 белая | J33: ='Юнит 15-21.12'!R31 -> 0 | K33: =J33/J$50 -> 0 | L33: =K33+L32 -> 0 | M33: =_xlfn.IFS(L33<80%,"A",L33<=95%,"B",L33>95%,"C") -> A
B34: tunika06 черная | C34: ='Юнит 15-21.12'!AE32 -> 0 | D34: =C34/C$50 -> 0 | E34: =D34+E33 -> 0 | F34: =IF(AND(E34<=0),"C",IF(E34<=0.8,"A",IF(E34<=0.95,"B","C"))) -> C | G34: =VLOOKUP(B$30:B$50,I$30:M$50,5,0) -> A | I34: tunika06 черная | J34: ='Юнит 15-21.12'!R32 -> 0 | K34: =J34/J$50 -> 0 | L34: =K34+L33 -> 0 | M34: =_xlfn.IFS(L34<80%,"A",L34<=95%,"B",L34>95%,"C") -> A
B35: tunika07 кружево | C35: ='Юнит 15-21.12'!AE33 -> -170.85 | D35: =C35/C$50 -> -0.12992099 | E35: =D35+E34 -> -0.12992099 | F35: =IF(AND(E35<=0),"C",IF(E35<=0.8,"A",IF(E35<=0.95,"B","C"))) -> C | G35: =VLOOKUP(B$30:B$50,I$30:M$50,5,0) -> A | I35: tunika07 кружево | J35: ='Юнит 15-21.12'!R33 -> 0 | K35: =J35/J$50 -> 0 | L35: =K35+L34 -> 0 | M35: =_xlfn.IFS(L35<80%,"A",L35<=95%,"B",L35>95%,"C") -> A
B36: tunika08 белая | C36: ='Юнит 15-21.12'!AE34 -> 0 | D36: =C36/C$50 -> 0 | E36: =D36+E35 -> -0.12992099 | F36: =IF(AND(E36<=0),"C",IF(E36<=0.8,"A",IF(E36<=0.95,"B","C"))) -> C | G36: =VLOOKUP(B$30:B$50,I$30:M$50,5,0) -> A | I36: tunika08 белая | J36: ='Юнит 15-21.12'!R34 -> 0 | K36: =J36/J$50 -> 0 | L36: =K36+L35 -> 0 | M36: =_xlfn.IFS(L36<80%,"A",L36<=95%,"B",L36>95%,"C") -> A
B37: tunika08 черная | C37: ='Юнит 15-21.12'!AE35 -> 0 | D37: =C37/C$50 -> 0 | E37: =D37+E36 -> -0.12992099 | F37: =IF(AND(E37<=0),"C",IF(E37<=0.8,"A",IF(E37<=0.95,"B","C"))) -> C | G37: =VLOOKUP(B$30:B$50,I$30:M$50,5,0) -> A | I37: tunika08 черная | J37: ='Юнит 15-21.12'!R35 -> 0 | K37: =J37/J$50 -> 0 | L37: =K37+L36 -> 0 | M37: =_xlfn.IFS(L37<80%,"A",L37<=95%,"B",L37>95%,"C") -> A
B38: tunika08 зеленая | C38: ='Юнит 15-21.12'!AE36 -> -112 | D38: =C38/C$50 -> -0.08516916 | E38: =D38+E37 -> -0.21509015 | F38: =IF(AND(E38<=0),"C",IF(E38<=0.8,"A",IF(E38<=0.95,"B","C"))) -> C | G38: =VLOOKUP(B$30:B$50,I$30:M$50,5,0) -> A | I38: tunika08 зеленая | J38: ='Юнит 15-21.12'!R36 -> 0 | K38: =J38/J$50 -> 0 | L38: =K38+L37 -> 0 | M38: =_xlfn.IFS(L38<80%,"A",L38<=95%,"B",L38>95%,"C") -> A
B39: tunika09 кимоно | C39: ='Юнит 15-21.12'!AE37 -> 0 | D39: =C39/C$50 -> 0 | E39: =D39+E38 -> -0.21509015 | F39: =IF(AND(E39<=0),"C",IF(E39<=0.8,"A",IF(E39<=0.95,"B","C"))) -> C | G39: =VLOOKUP(B$30:B$50,I$30:M$50,5,0) -> A | I39: tunika09 кимоно | J39: ='Юнит 15-21.12'!R37 -> 0 | K39: =J39/J$50 -> 0 | L39: =K39+L38 -> 0 | M39: =_xlfn.IFS(L39<80%,"A",L39<=95%,"B",L39>95%,"C") -> A
B40: tunika10 кимоно ч/б | C40: ='Юнит 15-21.12'!AE38 -> 0 | D40: =C40/C$50 -> 0 | E40: =D40+E39 -> -0.21509015 | F40: =IF(AND(E40<=0),"C",IF(E40<=0.8,"A",IF(E40<=0.95,"B","C"))) -> C | G40: =VLOOKUP(B$30:B$50,I$30:M$50,5,0) -> A | I40: tunika10 кимоно ч/б | J40: ='Юнит 15-21.12'!R38 -> 0 | K40: =J40/J$50 -> 0 | L40: =K40+L39 -> 0 | M40: =_xlfn.IFS(L40<80%,"A",L40<=95%,"B",L40>95%,"C") -> A
B41: tunika11 халат зеленая | C41: ='Юнит 15-21.12'!AE39 -> 0 | D41: =C41/C$50 -> 0 | E41: =D41+E40 -> -0.21509015 | F41: =IF(AND(E41<=0),"C",IF(E41<=0.8,"A",IF(E41<=0.95,"B","C"))) -> C | G41: =VLOOKUP(B$30:B$50,I$30:M$50,5,0) -> A | I41: tunika11 халат зеленая | J41: ='Юнит 15-21.12'!R39 -> 0 | K41: =J41/J$50 -> 0 | L41: =K41+L40 -> 0 | M41: =_xlfn.IFS(L41<80%,"A",L41<=95%,"B",L41>95%,"C") -> A
B42: tunika12 халат белая | C42: ='Юнит 15-21.12'!AE40 -> 0 | D42: =C42/C$50 -> 0 | E42: =D42+E41 -> -0.21509015 | F42: =IF(AND(E42<=0),"C",IF(E42<=0.8,"A",IF(E42<=0.95,"B","C"))) -> C | G42: =VLOOKUP(B$30:B$50,I$30:M$50,5,0) -> A | I42: tunika12 халат белая | J42: ='Юнит 15-21.12'!R40 -> 0 | K42: =J42/J$50 -> 0 | L42: =K42+L41 -> 0 | M42: =_xlfn.IFS(L42<80%,"A",L42<=95%,"B",L42>95%,"C") -> A
... B49: tunika16 сетка черная | C49: ='Юнит 15-21.12'!AE47 -> 0 | D49: =C49/C$50 -> 0 | E49: =D49+E48 -> 1 | F49: =IF(AND(E49<=0),"C",IF(E49<=0.8,"A",IF(E49<=0.95,"B","C"))) -> C | G49: =VLOOKUP(B$30:B$50,I$30:M$50,5,0) -> C | I49: tunika16 сетка черная | J49: ='Юнит 15-21.12'!R47 -> 0 | K49: =J49/J$50 -> 0 | L49: =K49+L48 -> 1 | M49: =_xlfn.IFS(L49<80%,"A",L49<=95%,"B",L49>95%,"C") -> C
C50: =SUM(C30:C49) -> 1315.03 | D50: =SUM(D30:D49) -> 1 | J50: =SUM(J30:J49) -> 1 | K50: =SUM(K30:K49) -> 1

Sheet АВС 08-14.12
B2: ОЧКИ
C3: Прибыль | D3: % прибыль | E3: Доля | F3: ABC прибыль | G3: ABC кол-во | J3: Кол-во | K3: % кол-во | L3: Доля | M3: ABC кол-во
B4: черные с железкой классика | C4: ='Юнит 08-14.12'!AE3 -> 1208.5003 | D4: =C4/C$26 -> 0.49416995 | E4: =D4 -> 0.49416995 | F4: =IF(AND(E4<=0),"C",IF(E4<=0.8,"A",IF(E4<=0.95,"B","C"))) -> A | G4: =VLOOKUP(B$4:B$25,I$4:M$25,5,0) -> A | I4: черные с железкой классика | J4: ='Юнит 08-14.12'!R3 -> 15 | K4: =J4/J$26 -> 0.39473684 | L4: =K4 -> 0.39473684 | M4: =_xlfn.IFS(L4<80%,"A",L4<=95%,"B",L4>95%,"C") -> A
B5: qs желтые | C5: ='Юнит 08-14.12'!AE6 -> 603.40604 | D5: =C5/C$26 -> 0.2467398 | E5: =D5+E4 -> 0.74090974 | F5: =IF(AND(E5<=0),"C",IF(E5<=0.8,"A",IF(E5<=0.95,"B","C"))) -> A | G5: =VLOOKUP(B$4:B$25,I$4:M$25,5,0) -> A | I5: qs желтые | J5: ='Юнит 08-14.12'!R6 -> 13 | K5: =J5/J$26 -> 0.34210526 | L5: =K5+L4 -> 0.73684211 | M5: =_xlfn.IFS(L5<80%,"A",L5<=95%,"B",L5>95%,"C") -> A
B6: qs коричневые | C6: ='Юнит 08-14.12'!AE7 -> 556.33 | D6: =C6/C$26 -> 0.22748985 | E6: =D6+E5 -> 0.9683996 | F6: =IF(AND(E6<=0),"C",IF(E6<=0.8,"A",IF(E6<=0.95,"B","C"))) -> C | G6: =VLOOKUP(B$4:B$25,I$4:M$25,5,0) -> B | I6: th желтый Сул | J6: ='Юнит 08-14.12'!R8 -> 2 | K6: =J6/J$26 -> 0.052631579 | L6: =K6+L5 -> 0.78947368 | M6: =_xlfn.IFS(L6<80%,"A",L6<=95%,"B",L6>95%,"C") -> A
B7: MR Р1874 черн | C7: ='Юнит 08-14.12'!AE13 -> 528.51 | D7: =C7/C$26 -> 0.21611393 | E7: =D7+E6 -> 1.1845135 | F7: =IF(AND(E7<=0),"C",IF(E7<=0.8,"A",IF(E7<=0.95,"B","C"))) -> C | G7: =VLOOKUP(B$4:B$25,I$4:M$25,5,0) -> B | I7: qs черные | J7: ='Юнит 08-14.12'!R4 -> 1 | K7: =J7/J$26 -> 0.026315789 | L7: =K7+L6 -> 0.81578947 | M7: =_xlfn.IFS(L7<80%,"A",L7<=95%,"B",L7>95%,"C") -> B
B8: MR8854 C2 | C8: ='Юнит 08-14.12'!AE10 -> 374.32 | D8: =C8/C$26 -> 0.15306383 | E8: =D8+E7 -> 1.3375774 | F8: =IF(AND(E8<=0),"C",IF(E8<=0.8,"A",IF(E8<=0.95,"B","C"))) -> C | G8: =VLOOKUP(B$4:B$25,I$4:M$25,5,0) -> B | I8: qs синие | J8: ='Юнит 08-14.12'!R5 -> 1 | K8: =J8/J$26 -> 0.026315789 | L8: =K8+L7 -> 0.84210526 | M8: =_xlfn.IFS(L8<80%,"A",L8<=95%,"B",L8>95%,"C") -> B
B9: MR Р1886 корич | C9: ='Юнит 08-14.12'!AE16 -> 356.88 | D9: =C9/C$26 -> 0.14593241 | E9: =D9+E8 -> 1.4835098 | F9: =IF(AND(E9<=0),"C",IF(E9<=0.8,"A",IF(E9<=0.95,"B","C"))) -> C | G9: =VLOOKUP(B$4:B$25,I$4:M$25,5,0) -> B | I9: qs коричневые | J9: ='Юнит 08-14.12'!R7 -> 1 | K9: =J9/J$26 -> 0.026315789 | L9: =K9+L8 -> 0.86842105 | M9: =_xlfn.IFS(L9<80%,"A",L9<=95%,"B",L9>95%,"C") -> B
B10: MR Р1874 корич | C10: ='Юнит 08-14.12'!AE14 -> 340.66 | D10: =C10/C$26 -> 0.13929986 | E10: =D10+E9 -> 1.6228096 | F10: =IF(AND(E10<=0),"C",IF(E10<=0.8,"A",IF(E10<=0.95,"B","C"))) -> C | G10: =VLOOKUP(B$4:B$25,I$4:M$25,5,0) -> B | I10: flip желтые Сул | J10: ='Юнит 08-14.12'!R9 -> 1 | K10: =J10/J$26 -> 0.026315789 | L10: =K10+L9 -> 0.89473684 | M10: =_xlfn.IFS(L10<80%,"A",L10<=95%,"B",L10>95%,"C") -> B
B11: qs черные | C11: ='Юнит 08-14.12'!AE4 -> 339.72 | D11: =C11/C$26 -> 0.13891549 | E11: =D11+E8 -> 1.4764928 | F11: =IF(AND(E11<=0),"C",IF(E11<=0.8,"A",IF(E11<=0.95,"B","C"))) -> C | G11: =VLOOKUP(B$4:B$25,I$4:M$25,5,0) -> B | I11: MR8854 C2 | J11: ='Юнит 08-14.12'!R10 -> 1 | K11: =J11/J$26 -> 0.026315789 | L11: =K11+L8 -> 0.86842105 | M11: =_xlfn.IFS(L11<80%,"A",L11<=95%,"B",L11>95%,"C") -> B
B12: qs синие | C12: ='Юнит 08-14.12'!AE5 -> 43.04 | D12: =C12/C$26 -> 0.01759956 | E12: =D12+E11 -> 1.4940924 | F12: =IF(AND(E12<=0),"C",IF(E12<=0.8,"A",IF(E12<=0.95,"B","C"))) -> C | G12: =VLOOKUP(B$4:B$25,I$4:M$25,5,0) -> B | I12: MR Р1874 черн | J12: ='Юнит 08-14.12'!R13 -> 1 | K12: =J12/J$26 -> 0.026315789 | L12: =K12+L11 -> 0.89473684 | M12: =_xlfn.IFS(L12<80%,"A",L12<=95%,"B",L12>95%,"C") -> B
B13: MR 1819 черн | C13: ='Юнит 08-14.12'!AE11 -> 0 | D13: =C13/C$26 -> 0 | E13: =D13+E12 -> 1.4940924 | F13: =IF(AND(E13<=0),"C",IF(E13<=0.8,"A",IF(E13<=0.95,"B","C"))) -> C | G13: =VLOOKUP(B$4:B$25,I$4:M$25,5,0) -> B | I13: MR Р1874 корич | J13: ='Юнит 08-14.12'!R14 -> 1 | K13: =J13/J$26 -> 0.026315789 | L13: =K13+L12 -> 0.92105263 | M13: =_xlfn.IFS(L13<80%,"A",L13<=95%,"B",L13>95%,"C") -> B | P13: A | Q13: 0.8
B14: MR 1819 корич | C14: ='Юнит 08-14.12'!AE12 -> 0 | D14: =C14/C$26 -> 0 | E14: =D14+E13 -> 1.4940924 | F14: =IF(AND(E14<=0),"C",IF(E14<=0.8,"A",IF(E14<=0.95,"B","C"))) -> C | G14: =VLOOKUP(B$4:B$25,I$4:M$25,5,0) -> B | I14: MR Р1886 корич | J14: ='Юнит 08-14.12'!R16 -> 1 | K14: =J14/J$26 -> 0.026315789 | L14: =K14+L13 -> 0.94736842 | M14: =_xlfn.IFS(L14<80%,"A",L14<=95%,"B",L14>95%,"C") -> B | P14: B | Q14: 0.15
B15: lux1 | C15: ='Юнит 08-14.12'!AE17 -> 0 | D15: =C15/C$26 -> 0 | E15: =D15+E14 -> 1.4940924 | F15: =IF(AND(E15<=0),"C",IF(E15<=0.8,"A",IF(E15<=0.95,"B","C"))) -> C | G15: =VLOOKUP(B$4:B$25,I$4:M$25,5,0) -> B | I15: MR 1819 черн | J15: ='Юнит 08-14.12'!R11 -> 0 | K15: =J15/J$26 -> 0 | L15: =K15+L14 -> 0.94736842 | M15: =_xlfn.IFS(L15<80%,"A",L15<=95%,"B",L15>95%,"C") -> B | P15: C | Q15: 0.05
B16: lux2 | C16: ='Юнит 08-14.12'!AE18 -> 0 | D16: =C16/C$26 -> 0 | E16: =D16+E15 -> 1.4940924 | F16: =IF(AND(E16<=0),"C",IF(E16<=0.8,"A",IF(E16<=0.95,"B","C"))) -> C | G16: =VLOOKUP(B$4:B$25,I$4:M$25,5,0) -> B | I16: MR 1819 корич | J16: ='Юнит 08-14.12'!R12 -> 0 | K16: =J16/J$26 -> 0 | L16: =K16+L15 -> 0.94736842 | M16: =_xlfn.IFS(L16<80%,"A",L16<=95%,"B",L16>95%,"C") -> B
B17: lux3 | C17: ='Юнит 08-14.12'!AE19 -> 0 | D17: =C17/C$26 -> 0 | E17: =D17+E16 -> 1.4940924 | F17: =IF(AND(E17<=0),"C",IF(E17<=0.8,"A",IF(E17<=0.95,"B","C"))) -> C | G17: =VLOOKUP(B$4:B$25,I$4:M$25,5,0) -> B | I17: MR Р1886 черн глянец | J17: ='Юнит 08-14.12'!R15 -> 0 | K17: =J17/J$26 -> 0 | L17: =K17+L16 -> 0.94736842 | M17: =_xlfn.IFS(L17<80%,"A",L17<=95%,"B",L17>95%,"C") -> B
B18: lux4 | C18: ='Юнит 08-14.12'!AE20 -> 0 | D18: =C18/C$26 -> 0 | E18: =D18+E17 -> 1.4940924 | F18: =IF(AND(E18<=0),"C",IF(E18<=0.8,"A",IF(E18<=0.95,"B","C"))) -> C | G18: =VLOOKUP(B$4:B$25,I$4:M$25,5,0) -> B | I18: lux1 | J18: ='Юнит 08-14.12'!R17 -> 0 | K18: =J18/J$26 -> 0 | L18: =K18+L17 -> 0.94736842 | M18: =_xlfn.IFS(L18<80%,"A",L18<=95%,"B",L18>95%,"C") -> B
B19: lux5 | C19: ='Юнит 08-14.12'!AE21 -> 0 | D19: =C19/C$26 -> 0 | E19: =D19+E18 -> 1.4940924 | F19: =IF(AND(E19<=0),"C",IF(E19<=0.8,"A",IF(E19<=0.95,"B","C"))) -> C | G19: =VLOOKUP(B$4:B$25,I$4:M$25,5,0) -> B | I19: lux2 | J19: ='Юнит 08-14.12'!R18 -> 0 | K19: =J19/J$26 -> 0 | L19: =K19+L18 -> 0.94736842 | M19: =_xlfn.IFS(L19<80%,"A",L19<=95%,"B",L19>95%,"C") -> B
B20: lux6 | C20: ='Юнит 08-14.12'!AE22 -> 0 | D20: =C20/C$26 -> 0 | E20: =D20+E19 -> 1.4940924 | F20: =IF(AND(E20<=0),"C",IF(E20<=0.8,"A",IF(E20<=0.95,"B","C"))) -> C | G20: =VLOOKUP(B$4:B$25,I$4:M$25,5,0) -> B | I20: lux3 | J20: ='Юнит 08-14.12'!R19 -> 0 | K20: =J20/J$26 -> 0 | L20: =K20+L19 -> 0.94736842 | M20: =_xlfn.IFS(L20<80%,"A",L20<=95%,"B",L20>95%,"C") -> B
B21: lux7 | C21: ='Юнит 08-14.12'!AE23 -> 0 | D21: =C21/C$26 -> 0 | E21: =D21+E20 -> 1.4940924 | F21: =IF(AND(E21<=0),"C",IF(E21<=0.8,"A",IF(E21<=0.95,"B","C"))) -> C | G21: =VLOOKUP(B$4:B$25,I$4:M$25,5,0) -> B | I21: lux4 | J21: ='Юнит 08-14.12'!R20 -> 0 | K21: =J21/J$26 -> 0 | L21: =K21+L20 -> 0.94736842 | M21: =_xlfn.IFS(L21<80%,"A",L21<=95%,"B",L21>95%,"C") -> B
B22: lux8 | C22: ='Юнит 08-14.12'!AE24 -> 0 | D22: =C22/C$26 -> 0 | E22: =D22+E21 -> 1.4940924 | F22: =IF(AND(E22<=0),"C",IF(E22<=0.8,"A",IF(E22<=0.95,"B","C"))) -> C | G22: =VLOOKUP(B$4:B$25,I$4:M$25,5,0) -> B | I22: lux5 | J22: ='Юнит 08-14.12'!R21 -> 0 | K22: =J22/J$26 -> 0 | L22: =K22+L21 -> 0.94736842 | M22: =_xlfn.IFS(L22<80%,"A",L22<=95%,"B",L22>95%,"C") -> B
B23: MR Р1886 черн глянец | C23: ='Юнит 08-14.12'!AE15 -> -559.59 | D23: =C23/C$26 -> -0.22882291 | E23: =D23+E22 -> 1.2652695 | F23: =IF(AND(E23<=0),"C",IF(E23<=0.8,"A",IF(E23<=0.95,"B","C"))) -> C | G23: =VLOOKUP(B$4:B$25,I$4:M$25,5,0) -> B | I23: lux6 | J23: ='Юнит 08-14.12'!R22 -> 0 | K23: =J23/J$26 -> 0 | L23: =K23+L22 -> 0.94736842 | M23: =_xlfn.IFS(L23<80%,"A",L23<=95%,"B",L23>95%,"C") -> B
B24: flip желтые Сул | C24: ='Юнит 08-14.12'!AE9 -> -660.01 | D24: =C24/C$26 -> -0.26988582 | E24: =D24+E23 -> 0.99538368 | F24: =IF(AND(E24<=0),"C",IF(E24<=0.8,"A",IF(E24<=0.95,"B","C"))) -> C | G24: =VLOOKUP(B$4:B$25,I$4:M$25,5,0) -> B | I24: lux7 | J24: ='Юнит 08-14.12'!R23 -> 0 | K24: =J24/J$26 -> 0 | L24: =K24+L23 -> 0.94736842 | M24: =_xlfn.IFS(L24<80%,"A",L24<=95%,"B",L24>95%,"C") -> B
B25: th желтый Сул | C25: ='Юнит 08-14.12'!AE8 -> -686.25072 | D25: =C25/C$26 -> -0.28061596 | E25: =D25+E24 -> 0.71476772 | F25: =IF(AND(E25<=0),"C",IF(E25<=0.8,"A",IF(E25<=0.95,"B","C"))) -> A | G25: =VLOOKUP(B$4:B$25,I$4:M$25,5,0) -> A | I25: lux8 | J25: ='Юнит 08-14.12'!R24 -> 0 | K25: =J25/J$26 -> 0 | L25: =K25+L24 -> 0.94736842 | M25: =_xlfn.IFS(L25<80%,"A",L25<=95%,"B",L25>95%,"C") -> B
C26: =SUM(C4:C25) -> 2445.5157 | D26: =SUM(D4:D25) -> 1 | J26: =SUM(J4:J25) -> 38 | K26: =SUM(K4:K25) -> 1
B28: ТУНИКИ
C29: Прибыль | D29: % прибыль | E29: Доля | F29: ABC прибыль | G29: ABC кол-во | J29: Кол-во | K29: % кол-во | L29: Доля | M29: ABC кол-во
B30: tunika07 кружево | C30: ='Юнит 08-14.12'!AE33 -> 1418.3 | D30: =C30/C$50 -> 2.0234257 | E30: =D30 -> 2.0234257 | F30: =IF(AND(E30<=0),"C",IF(E30<=0.8,"A",IF(E30<=0.95,"B","C"))) -> C | G30: =VLOOKUP(B$30:B$50,I$30:M$50,5,0) -> A | I30: tunika07 кружево | J30: ='Юнит 08-14.12'!R33 -> 2 | K30: =J30/J$50 -> 0.66666667 | L30: =K30 -> 0.66666667 | M30: =_xlfn.IFS(L30<80%,"A",L30<=95%,"B",L30>95%,"C") -> A
B31: tunika13 халат черная | C31: ='Юнит 08-14.12'!AE41 -> 432.16 | D31: =C31/C$50 -> 0.6165435 | E31: =D31+E30 -> 2.6399692 | F31: =IF(AND(E31<=0),"C",IF(E31<=0.8,"A",IF(E31<=0.95,"B","C"))) -> C | G31: =VLOOKUP(B$30:B$50,I$30:M$50,5,0) -> C | I31: tunika13 халат черная | J31: ='Юнит 08-14.12'!R41 -> 1 | K31: =J31/J$50 -> 0.33333333 | L31: =K31+L30 -> 1 | M31: =_xlfn.IFS(L31<80%,"A",L31<=95%,"B",L31>95%,"C") -> C
B32: tunika02 оливковая с руч вышивкой | C32: ='Юнит 08-14.12'!AE28 -> 0 | D32: =C32/C$50 -> 0 | E32: =D32+E31 -> 2.6399692 | F32: =IF(AND(E32<=0),"C",IF(E32<=0.8,"A",IF(E32<=0.95,"B","C"))) -> C | G32: =VLOOKUP(B$30:B$50,I$30:M$50,5,0) -> C | I32: tunika02 оливковая с руч вышивкой | J32: ='Юнит 08-14.12'!R28 -> 0 | K32: =J32/J$50 -> 0 | L32: =K32+L31 -> 1 | M32: =_xlfn.IFS(L32<80%,"A",L32<=95%,"B",L32>95%,"C") -> C
B33: tunika03 черная распашная | C33: ='Юнит 08-14.12'!AE29 -> 0 | D33: =C33/C$50 -> 0 | E33: =D33+E32 -> 2.6399692 | F33: =IF(AND(E33<=0),"C",IF(E33<=0.8,"A",IF(E33<=0.95,"B","C"))) -> C | G33: =VLOOKUP(B$30:B$50,I$30:M$50,5,0) -> C | I33: tunika03 черная распашная | J33: ='Юнит 08-14.12'!R29 -> 0 | K33: =J33/J$50 -> 0 | L33: =K33+L32 -> 1 | M33: =_xlfn.IFS(L33<80%,"A",L33<=95%,"B",L33>95%,"C") -> C
B34: tunika05 белая распашная | C34: ='Юнит 08-14.12'!AE30 -> 0 | D34: =C34/C$50 -> 0 | E34: =D34+E33 -> 2.6399692 | F34: =IF(AND(E34<=0),"C",IF(E34<=0.8,"A",IF(E34<=0.95,"B","C"))) -> C | G34: =VLOOKUP(B$30:B$50,I$30:M$50,5,0) -> C | I34: tunika05 белая распашная | J34: ='Юнит 08-14.12'!R30 -> 0 | K34: =J34/J$50 -> 0 | L34: =K34+L33 -> 1 | M34: =_xlfn.IFS(L34<80%,"A",L34<=95%,"B",L34>95%,"C") -> C
B35: tunika06 белая | C35: ='Юнит 08-14.12'!AE31 -> 0 | D35: =C35/C$50 -> 0 | E35: =D35+E34 -> 2.6399692 | F35: =IF(AND(E35<=0),"C",IF(E35<=0.8,"A",IF(E35<=0.95,"B","C"))) -> C | G35: =VLOOKUP(B$30:B$50,I$30:M$50,5,0) -> C | I35: tunika06 белая | J35: ='Юнит 08-14.12'!R31 -> 0 | K35: =J35/J$50 -> 0 | L35: =K35+L34 -> 1 | M35: =_xlfn.IFS(L35<80%,"A",L35<=95%,"B",L35>95%,"C") -> C
B36: tunika06 черная | C36: ='Юнит 08-14.12'!AE32 -> 0 | D36: =C36/C$50 -> 0 | E36: =D36+E35 -> 2.6399692 | F36: =IF(AND(E36<=0),"C",IF(E36<=0.8,"A",IF(E36<=0.95,"B","C"))) -> C | G36: =VLOOKUP(B$30:B$50,I$30:M$50,5,0) -> C | I36: tunika06 черная | J36: ='Юнит 08-14.12'!R32 -> 0 | K36: =J36/J$50 -> 0 | L36: =K36+L35 -> 1 | M36: =_xlfn.IFS(L36<80%,"A",L36<=95%,"B",L36>95%,"C") -> C
B37: tunika08 белая | C37: ='Юнит 08-14.12'!AE34 -> 0 | D37: =C37/C$50 -> 0 | E37: =D37+E36 -> 2.6399692 | F37: =IF(AND(E37<=0),"C",IF(E37<=0.8,"A",IF(E37<=0.95,"B","C"))) -> C | G37: =VLOOKUP(B$30:B$50,I$30:M$50,5,0) -> C | I37: tunika08 белая | J37: ='Юнит 08-14.12'!R34 -> 0 | K37: =J37/J$50 -> 0 | L37: =K37+L36 -> 1 | M37: =_xlfn.IFS(L37<80%,"A",L37<=95%,"B",L37>95%,"C") -> C
B38: tunika08 черная | C38: ='Юнит 08-14.12'!AE35 -> 0 | D38: =C38/C$50 -> 0 | E38: =D38+E37 -> 2.6399692 | F38: =IF(AND(E38<=0),"C",IF(E38<=0.8,"A",IF(E38<=0.95,"B","C"))) -> C | G38: =VLOOKUP(B$30:B$50,I$30:M$50,5,0) -> C | I38: tunika08 черная | J38: ='Юнит 08-14.12'!R35 -> 0 | K38: =J38/J$50 -> 0 | L38: =K38+L37 -> 1 | M38: =_xlfn.IFS(L38<80%,"A",L38<=95%,"B",L38>95%,"C") -> C
B39: tunika08 зеленая | C39: ='Юнит 08-14.12'!AE36 -> 0 | D39: =C39/C$50 -> 0 | E39: =D39+E38 -> 2.6399692 | F39: =IF(AND(E39<=0),"C",IF(E39<=0.8,"A",IF(E39<=0.95,"B","C"))) -> C | G39: =VLOOKUP(B$30:B$50,I$30:M$50,5,0) -> C | I39: tunika08 зеленая | J39: ='Юнит 08-14.12'!R36 -> 0 | K39: =J39/J$50 -> 0 | L39: =K39+L38 -> 1 | M39: =_xlfn.IFS(L39<80%,"A",L39<=95%,"B",L39>95%,"C") -> C
B40: tunika09 кимоно | C40: ='Юнит 08-14.12'!AE37 -> 0 | D40: =C40/C$50 -> 0 | E40: =D40+E39 -> 2.6399692 | F40: =IF(AND(E40<=0),"C",IF(E40<=0.8,"A",IF(E40<=0.95,"B","C"))) -> C | G40: =VLOOKUP(B$30:B$50,I$30:M$50,5,0) -> C | I40: tunika09 кимоно | J40: ='Юнит 08-14.12'!R37 -> 0 | K40: =J40/J$50 -> 0 | L40: =K40+L39 -> 1 | M40: =_xlfn.IFS(L40<80%,"A",L40<=95%,"B",L40>95%,"C") -> C
B41: tunika10 кимоно ч/б | C41: ='Юнит 08-14.12'!AE38 -> 0 | D41: =C41/C$50 -> 0 | E41: =D41+E40 -> 2.6399692 | F41: =IF(AND(E41<=0),"C",IF(E41<=0.8,"A",IF(E41<=0.95,"B","C"))) -> C | G41: =VLOOKUP(B$30:B$50,I$30:M$50,5,0) -> C | I41: tunika10 кимоно ч/б | J41: ='Юнит 08-14.12'!R38 -> 0 | K41: =J41/J$50 -> 0 | L41: =K41+L40 -> 1 | M41: =_xlfn.IFS(L41<80%,"A",L41<=95%,"B",L41>95%,"C") -> C
B42: tunika12 халат белая | C42: ='Юнит 08-14.12'!AE40 -> 0 | D42: =C42/C$50 -> 0 | E42: =D42+E41 -> 2.6399692 | F42: =IF(AND(E42<=0),"C",IF(E42<=0.8,"A",IF(E42<=0.95,"B","C"))) -> C | G42: =VLOOKUP(B$30:B$50,I$30:M$50,5,0) -> C | I42: tunika11 халат зеленая | J42: ='Юнит 08-14.12'!R39 -> 0 | K42: =J42/J$50 -> 0 | L42: =K42+L41 -> 1 | M42: =_xlfn.IFS(L42<80%,"A",L42<=95%,"B",L42>95%,"C") -> C
B43: tunika14 халат с разрезами черный | C43: ='Юнит 08-14.12'!AE43 -> 0 | D43: =C43/C$50 -> 0 | E43: =D43+E42 -> 2.6399692 | F43: =IF(AND(E43<=0),"C",IF(E43<=0.8,"A",IF(E43<=0.95,"B","C"))) -> C | G43: =VLOOKUP(B$30:B$50,I$30:M$50,5,0) -> C | I43: tunika12 халат белая | J43: ='Юнит 08-14.12'!R40 -> 0 | K43: =J43/J$50 -> 0 | L43: =K43+L42 -> 1 | M43: =_xlfn.IFS(L43<80%,"A",L43<=95%,"B",L43>95%,"C") -> C
B44: tunika15 кимоно бирюза | C44: ='Юнит 08-14.12'!AE44 -> 0 | D44: =C44/C$50 -> 0 | E44: =D44+E43 -> 2.6399692 | F44: =IF(AND(E44<=0),"C",IF(E44<=0.8,"A",IF(E44<=0.95,"B","C"))) -> C | G44: =VLOOKUP(B$30:B$50,I$30:M$50,5,0) -> C | I44: tunika14 халат с разрезами белая | J44: ='Юнит 08-14.12'!R42 -> 0 | K44: =J44/J$50 -> 0 | L44: =K44+L43 -> 1 | M44: =_xlfn.IFS(L44<80%,"A",L44<=95%,"B",L44>95%,"C") -> C
B45: tunika16 сетка белая | C45: ='Юнит 08-14.12'!AE46 -> 0 | D45: =C45/C$50 -> 0 | E45: =D45+E44 -> 2.6399692 | F45: =IF(AND(E45<=0),"C",IF(E45<=0.8,"A",IF(E45<=0.95,"B","C"))) -> C | G45: =VLOOKUP(B$30:B$50,I$30:M$50,5,0) -> C | I45: tunika14 халат с разрезами черный | J45: ='Юнит 08-14.12'!R43 -> 0 | K45: =J45/J$50 -> 0 | L45: =K45+L44 -> 1 | M45: =_xlfn.IFS(L45<80%,"A",L45<=95%,"B",L45>95%,"C") -> C
B46: tunika16 сетка черная | C46: ='Юнит 08-14.12'!AE47 -> 0 | D46: =C46/C$50 -> 0 | E46: =D46+E45 -> 2.6399692 | F46: =IF(AND(E46<=0),"C",IF(E46<=0.8,"A",IF(E46<=0.95,"B","C"))) -> C | G46: =VLOOKUP(B$30:B$50,I$30:M$50,5,0) -> C | I46: tunika15 кимоно бирюза | J46: ='Юнит 08-14.12'!R44 -> 0 | K46: =J46/J$50 -> 0 | L46: =K46+L45 -> 1 | M46: =_xlfn.IFS(L46<80%,"A",L46<=95%,"B",L46>95%,"C") -> C
B47: tunika11 халат зеленая | C47: ='Юнит 08-14.12'!AE39 -> -112 | D47: =C47/C$50 -> -0.15978543 | E47: =D47+E46 -> 2.4801838 | F47: =IF(AND(E47<=0),"C",IF(E47<=0.8,"A",IF(E47<=0.95,"B","C"))) -> C | G47: =VLOOKUP(B$30:B$50,I$30:M$50,5,0) -> C | I47: tunika15 кимоно песочная | J47: ='Юнит 08-14.12'!R45 -> 0 | K47: =J47/J$50 -> 0 | L47: =K47+L46 -> 1 | M47: =_xlfn.IFS(L47<80%,"A",L47<=95%,"B",L47>95%,"C") -> C
B48: tunika15 кимоно песочная | C48: ='Юнит 08-14.12'!AE45 -> -112 | D48: =C48/C$50 -> -0.15978543 | E48: =D48+E47 -> 2.3203983 | F48: =IF(AND(E48<=0),"C",IF(E48<=0.8,"A",IF(E48<=0.95,"B","C"))) -> C | G48: =VLOOKUP(B$30:B$50,I$30:M$50,5,0) -> C | I48: tunika16 сетка белая | J48: ='Юнит 08-14.12'!R46 -> 0 | K48: =J48/J$50 -> 0 | L48: =K48+L47 -> 1 | M48: =_xlfn.IFS(L48<80%,"A",L48<=95%,"B",L48>95%,"C") -> C
B49: tunika14 халат с разрезами белая | C49: ='Юнит 08-14.12'!AE42 -> -925.52 | D49: =C49/C$50 -> -1.3203983 | E49: =D49+E48 -> 1 | F49: =IF(AND(E49<=0),"C",IF(E49<=0.8,"A",IF(E49<=0.95,"B","C"))) -> C | G49: =VLOOKUP(B$30:B$50,I$30:M$50,5,0) -> C | I49: tunika16 сетка черная | J49: ='Юнит 08-14.12'!R47 -> 0 | K49: =J49/J$50 -> 0 | L49: =K49+L48 -> 1 | M49: =_xlfn.IFS(L49<80%,"A",L49<=95%,"B",L49>95%,"C") -> C
C50: =SUM(C30:C49) -> 700.94 | D50: =SUM(D30:D49) -> 1 | J50: =SUM(J30:J49) -> 3 | K50: =SUM(K30:K49) -> 1

Sheet АВС 01-07.12
B2: ОЧКИ
C3: Прибыль | D3: % прибыль | E3: Доля | F3: ABC прибыль | G3: ABC кол-во | J3: Кол-во | K3: % кол-во | L3: Доля | M3: ABC кол-во
B4: qs желтые | C4: ='Юнит 01-07.12'!AE6 -> 2281.5884 | D4: =C4/C$26 -> 0.27488937 | E4: =D4 -> 0.27488937 | F4: =IF(AND(E4<=0),"C",IF(E4<=0.8,"A",IF(E4<=0.95,"B","C"))) -> A | G4: =VLOOKUP(B$4:B$25,I$4:M$25,5,0) -> A | I4: черные с железкой классика | J4: ='Юнит 01-07.12'!R3 -> 23 | K4: =J4/J$26 -> 0.39655172 | L4: =K4 -> 0.39655172 | M4: =_xlfn.IFS(L4<80%,"A",L4<=95%,"B",L4>95%,"C") -> A
B5: qs коричневые | C5: ='Юнит 01-07.12'!AE7 -> 2197.45 | D5: =C5/C$26 -> 0.26475225 | E5: =D5+E4 -> 0.53964162 | F5: =IF(AND(E5<=0),"C",IF(E5<=0.8,"A",IF(E5<=0.95,"B","C"))) -> A | G5: =VLOOKUP(B$4:B$25,I$4:M$25,5,0) -> B | I5: qs желтые | J5: ='Юнит 01-07.12'!R6 -> 22 | K5: =J5/J$26 -> 0.37931034 | L5: =K5+L4 -> 0.77586207 | M5: =_xlfn.IFS(L5<80%,"A",L5<=95%,"B",L5>95%,"C") -> A
B6: черные с железкой классика | C6: ='Юнит 01-07.12'!AE3 -> 2154.0259 | D6: =C6/C$26 -> 0.25952044 | E6: =D6+E5 -> 0.79916206 | F6: =IF(AND(E6<=0),"C",IF(E6<=0.8,"A",IF(E6<=0.95,"B","C"))) -> A | G6: =VLOOKUP(B$4:B$25,I$4:M$25,5,0) -> A | I6: qs коричневые | J6: ='Юнит 01-07.12'!R7 -> 4 | K6: =J6/J$26 -> 0.068965517 | L6: =K6+L5 -> 0.84482759 | M6: =_xlfn.IFS(L6<80%,"A",L6<=95%,"B",L6>95%,"C") -> B
B7: flip желтые Сул | C7: ='Юнит 01-07.12'!AE9 -> 901.79062 | D7: =C7/C$26 -> 0.10864916 | E7: =D7+E6 -> 0.90781122 | F7: =IF(AND(E7<=0),"C",IF(E7<=0.8,"A",IF(E7<=0.95,"B","C"))) -> B | G7: =VLOOKUP(B$4:B$25,I$4:M$25,5,0) -> B | I7: flip желтые Сул | J7: ='Юнит 01-07.12'!R9 -> 4 | K7: =J7/J$26 -> 0.068965517 | L7: =K7+L6 -> 0.9137931 | M7: =_xlfn.IFS(L7<80%,"A",L7<=95%,"B",L7>95%,"C") -> B
B8: MR Р1874 черн | C8: ='Юнит 01-07.12'!AE13 -> 628.67 | D8: =C8/C$26 -> 0.075743155 | E8: =D8+E7 -> 0.98355438 | F8: =IF(AND(E8<=0),"C",IF(E8<=0.8,"A",IF(E8<=0.95,"B","C"))) -> C | G8: =VLOOKUP(B$4:B$25,I$4:M$25,5,0) -> C | I8: MR Р1886 черн глянец | J8: ='Юнит 01-07.12'!R15 -> 2 | K8: =J8/J$26 -> 0.034482759 | L8: =K8+L7 -> 0.94827586 | M8: =_xlfn.IFS(L8<80%,"A",L8<=95%,"B",L8>95%,"C") -> B
B9: MR Р1886 черн глянец | C9: ='Юнит 01-07.12'!AE15 -> 383.17 | D9: =C9/C$26 -> 0.046164927 | E9: =D9+E8 -> 1.0297193 | F9: =IF(AND(E9<=0),"C",IF(E9<=0.8,"A",IF(E9<=0.95,"B","C"))) -> C | G9: =VLOOKUP(B$4:B$25,I$4:M$25,5,0) -> B | I9: qs черные | J9: ='Юнит 01-07.12'!R4 -> 1 | K9: =J9/J$26 -> 0.017241379 | L9: =K9+L8 -> 0.96551724 | M9: =_xlfn.IFS(L9<80%,"A",L9<=95%,"B",L9>95%,"C") -> C
B10: qs черные | C10: ='Юнит 01-07.12'!AE4 -> 185.01 | D10: =C10/C$26 -> 0.022290297 | E10: =D10+E9 -> 1.0520096 | F10: =IF(AND(E10<=0),"C",IF(E10<=0.8,"A",IF(E10<=0.95,"B","C"))) -> C | G10: =VLOOKUP(B$4:B$25,I$4:M$25,5,0) -> C | I10: th желтый Сул | J10: ='Юнит 01-07.12'!R8 -> 1 | K10: =J10/J$26 -> 0.017241379 | L10: =K10+L9 -> 0.98275862 | M10: =_xlfn.IFS(L10<80%,"A",L10<=95%,"B",L10>95%,"C") -> C
B11: qs синие | C11: ='Юнит 01-07.12'!AE5 -> 0 | D11: =C11/C$26 -> 0 | E11: =D11+E8 -> 0.98355438 | F11: =IF(AND(E11<=0),"C",IF(E11<=0.8,"A",IF(E11<=0.95,"B","C"))) -> C | G11: =VLOOKUP(B$4:B$25,I$4:M$25,5,0) -> C | I11: MR Р1874 черн | J11: ='Юнит 01-07.12'!R13 -> 1 | K11: =J11/J$26 -> 0.017241379 | L11: =K11+L8 -> 0.96551724 | M11: =_xlfn.IFS(L11<80%,"A",L11<=95%,"B",L11>95%,"C") -> C
B12: MR8854 C2 | C12: ='Юнит 01-07.12'!AE10 -> 0 | D12: =C12/C$26 -> 0 | E12: =D12+E11 -> 0.98355438 | F12: =IF(AND(E12<=0),"C",IF(E12<=0.8,"A",IF(E12<=0.95,"B","C"))) -> C | G12: =VLOOKUP(B$4:B$25,I$4:M$25,5,0) -> C | I12: qs синие | J12: ='Юнит 01-07.12'!R5 -> 0 | K12: =J12/J$26 -> 0 | L12: =K12+L11 -> 0.96551724 | M12: =_xlfn.IFS(L12<80%,"A",L12<=95%,"B",L12>95%,"C") -> C
B13: MR 1819 черн | C13: ='Юнит 01-07.12'!AE11 -> 0 | D13: =C13/C$26 -> 0 | E13: =D13+E12 -> 0.98355438 | F13: =IF(AND(E13<=0),"C",IF(E13<=0.8,"A",IF(E13<=0.95,"B","C"))) -> C | G13: =VLOOKUP(B$4:B$25,I$4:M$25,5,0) -> C | I13: MR8854 C2 | J13: ='Юнит 01-07.12'!R10 -> 0 | K13: =J13/J$26 -> 0 | L13: =K13+L12 -> 0.96551724 | M13: =_xlfn.IFS(L13<80%,"A",L13<=95%,"B",L13>95%,"C") -> C | P13: A | Q13: 0.8
B14: MR 1819 корич | C14: ='Юнит 01-07.12'!AE12 -> 0 | D14: =C14/C$26 -> 0 | E14: =D14+E13 -> 0.98355438 | F14: =IF(AND(E14<=0),"C",IF(E14<=0.8,"A",IF(E14<=0.95,"B","C"))) -> C | G14: =VLOOKUP(B$4:B$25,I$4:M$25,5,0) -> C | I14: MR 1819 черн | J14: ='Юнит 01-07.12'!R11 -> 0 | K14: =J14/J$26 -> 0 | L14: =K14+L13 -> 0.96551724 | M14: =_xlfn.IFS(L14<80%,"A",L14<=95%,"B",L14>95%,"C") -> C | P14: B | Q14: 0.15
B15: MR Р1874 корич | C15: ='Юнит 01-07.12'!AE14 -> 0 | D15: =C15/C$26 -> 0 | E15: =D15+E14 -> 0.98355438 | F15: =IF(AND(E15<=0),"C",IF(E15<=0.8,"A",IF(E15<=0.95,"B","C"))) -> C | G15: =VLOOKUP(B$4:B$25,I$4:M$25,5,0) -> C | I15: MR 1819 корич | J15: ='Юнит 01-07.12'!R12 -> 0 | K15: =J15/J$26 -> 0 | L15: =K15+L14 -> 0.96551724 | M15: =_xlfn.IFS(L15<80%,"A",L15<=95%,"B",L15>95%,"C") -> C | P15: C | Q15: 0.05
B16: MR Р1886 корич | C16: ='Юнит 01-07.12'!AE16 -> 0 | D16: =C16/C$26 -> 0 | E16: =D16+E15 -> 0.98355438 | F16: =IF(AND(E16<=0),"C",IF(E16<=0.8,"A",IF(E16<=0.95,"B","C"))) -> C | G16: =VLOOKUP(B$4:B$25,I$4:M$25,5,0) -> C | I16: MR Р1874 корич | J16: ='Юнит 01-07.12'!R14 -> 0 | K16: =J16/J$26 -> 0 | L16: =K16+L15 -> 0.96551724 | M16: =_xlfn.IFS(L16<80%,"A",L16<=95%,"B",L16>95%,"C") -> C
B17: lux1 | C17: ='Юнит 01-07.12'!AE17 -> 0 | D17: =C17/C$26 -> 0 | E17: =D17+E16 -> 0.98355438 | F17: =IF(AND(E17<=0),"C",IF(E17<=0.8,"A",IF(E17<=0.95,"B","C"))) -> C | G17: =VLOOKUP(B$4:B$25,I$4:M$25,5,0) -> C | I17: MR Р1886 корич | J17: ='Юнит 01-07.12'!R16 -> 0 | K17: =J17/J$26 -> 0 | L17: =K17+L16 -> 0.96551724 | M17: =_xlfn.IFS(L17<80%,"A",L17<=95%,"B",L17>95%,"C") -> C
B18: lux2 | C18: ='Юнит 01-07.12'!AE18 -> 0 | D18: =C18/C$26 -> 0 | E18: =D18+E17 -> 0.98355438 | F18: =IF(AND(E18<=0),"C",IF(E18<=0.8,"A",IF(E18<=0.95,"B","C"))) -> C | G18: =VLOOKUP(B$4:B$25,I$4:M$25,5,0) -> C | I18: lux1 | J18: ='Юнит 01-07.12'!R17 -> 0 | K18: =J18/J$26 -> 0 | L18: =K18+L17 -> 0.96551724 | M18: =_xlfn.IFS(L18<80%,"A",L18<=95%,"B",L18>95%,"C") -> C
B19: lux3 | C19: ='Юнит 01-07.12'!AE19 -> 0 | D19: =C19/C$26 -> 0 | E19: =D19+E18 -> 0.98355438 | F19: =IF(AND(E19<=0),"C",IF(E19<=0.8,"A",IF(E19<=0.95,"B","C"))) -> C | G19: =VLOOKUP(B$4:B$25,I$4:M$25,5,0) -> C | I19: lux2 | J19: ='Юнит 01-07.12'!R18 -> 0 | K19: =J19/J$26 -> 0 | L19: =K19+L18 -> 0.96551724 | M19: =_xlfn.IFS(L19<80%,"A",L19<=95%,"B",L19>95%,"C") -> C
B20: lux4 | C20: ='Юнит 01-07.12'!AE20 -> 0 | D20: =C20/C$26 -> 0 | E20: =D20+E19 -> 0.98355438 | F20: =IF(AND(E20<=0),"C",IF(E20<=0.8,"A",IF(E20<=0.95,"B","C"))) -> C | G20: =VLOOKUP(B$4:B$25,I$4:M$25,5,0) -> C | I20: lux3 | J20: ='Юнит 01-07.12'!R19 -> 0 | K20: =J20/J$26 -> 0 | L20: =K20+L19 -> 0.96551724 | M20: =_xlfn.IFS(L20<80%,"A",L20<=95%,"B",L20>95%,"C") -> C
B21: lux5 | C21: ='Юнит 01-07.12'!AE21 -> 0 | D21: =C21/C$26 -> 0 | E21: =D21+E20 -> 0.98355438 | F21: =IF(AND(E21<=0),"C",IF(E21<=0.8,"A",IF(E21<=0.95,"B","C"))) -> C | G21: =VLOOKUP(B$4:B$25,I$4:M$25,5,0) -> C | I21: lux4 | J21: ='Юнит 01-07.12'!R20 -> 0 | K21: =J21/J$26 -> 0 | L21: =K21+L20 -> 0.96551724 | M21: =_xlfn.IFS(L21<80%,"A",L21<=95%,"B",L21>95%,"C") -> C
B22: lux6 | C22: ='Юнит 01-07.12'!AE22 -> 0 | D22: =C22/C$26 -> 0 | E22: =D22+E21 -> 0.98355438 | F22: =IF(AND(E22<=0),"C",IF(E22<=0.8,"A",IF(E22<=0.95,"B","C"))) -> C | G22: =VLOOKUP(B$4:B$25,I$4:M$25,5,0) -> C | I22: lux5 | J22: ='Юнит 01-07.12'!R21 -> 0 | K22: =J22/J$26 -> 0 | L22: =K22+L21 -> 0.96551724 | M22: =_xlfn.IFS(L22<80%,"A",L22<=95%,"B",L22>95%,"C") -> C
B23: lux7 | C23: ='Юнит 01-07.12'!AE23 -> 0 | D23: =C23/C$26 -> 0 | E23: =D23+E22 -> 0.98355438 | F23: =IF(AND(E23<=0),"C",IF(E23<=0.8,"A",IF(E23<=0.95,"B","C"))) -> C | G23: =VLOOKUP(B$4:B$25,I$4:M$25,5,0) -> C | I23: lux6 | J23: ='Юнит 01-07.12'!R22 -> 0 | K23: =J23/J$26 -> 0 | L23: =K23+L22 -> 0.96551724 | M23: =_xlfn.IFS(L23<80%,"A",L23<=95%,"B",L23>95%,"C") -> C
B24: lux8 | C24: ='Юнит 01-07.12'!AE24 -> 0 | D24: =C24/C$26 -> 0 | E24: =D24+E23 -> 0.98355438 | F24: =IF(AND(E24<=0),"C",IF(E24<=0.8,"A",IF(E24<=0.95,"B","C"))) -> C | G24: =VLOOKUP(B$4:B$25,I$4:M$25,5,0) -> C | I24: lux7 | J24: ='Юнит 01-07.12'!R23 -> 0 | K24: =J24/J$26 -> 0 | L24: =K24+L23 -> 0.96551724 | M24: =_xlfn.IFS(L24<80%,"A",L24<=95%,"B",L24>95%,"C") -> C
B25: th желтый Сул | C25: ='Юнит 01-07.12'!AE8 -> -431.68093 | D25: =C25/C$26 -> -0.052009601 | E25: =D25+E24 -> 0.93154478 | F25: =IF(AND(E25<=0),"C",IF(E25<=0.8,"A",IF(E25<=0.95,"B","C"))) -> B | G25: =VLOOKUP(B$4:B$25,I$4:M$25,5,0) -> C | I25: lux8 | J25: ='Юнит 01-07.12'!R24 -> 0 | K25: =J25/J$26 -> 0 | L25: =K25+L24 -> 0.96551724 | M25: =_xlfn.IFS(L25<80%,"A",L25<=95%,"B",L25>95%,"C") -> C
C26: =SUM(C4:C25) -> 8300.0239 | D26: =SUM(D4:D25) -> 1 | J26: =SUM(J4:J25) -> 58 | K26: =SUM(K4:K25) -> 1
B28: ТУНИКИ
C29: Прибыль | D29: % прибыль | E29: Доля | F29: ABC прибыль | G29: ABC кол-во | J29: Кол-во | K29: % кол-во | L29: Доля | M29: ABC кол-во
B30: tunika03 черная распашная | C30: ='Юнит 01-07.12'!AE29 -> 0 | D30: =C30/C$50 -> 0 | E30: =D30 -> 0 | F30: =IF(AND(E30<=0),"C",IF(E30<=0.8,"A",IF(E30<=0.95,"B","C"))) -> C | G30: =VLOOKUP(B$30:B$50,I$30:M$50,5,0) -> A | I30: tunika02 оливковая с руч вышивкой | J30: ='Юнит 01-07.12'!R28 -> 0 | K30: =J30/J$50 -> 0 | L30: =K30 -> 0 | M30: =_xlfn.IFS(L30<80%,"A",L30<=95%,"B",L30>95%,"C") -> A
B31: tunika05 белая распашная | C31: ='Юнит 01-07.12'!AE30 -> 0 | D31: =C31/C$50 -> 0 | E31: =D31+E30 -> 0 | F31: =IF(AND(E31<=0),"C",IF(E31<=0.8,"A",IF(E31<=0.95,"B","C"))) -> C | G31: =VLOOKUP(B$30:B$50,I$30:M$50,5,0) -> A | I31: tunika03 черная распашная | J31: ='Юнит 01-07.12'!R29 -> 0 | K31: =J31/J$50 -> 0 | L31: =K31+L30 -> 0 | M31: =_xlfn.IFS(L31<80%,"A",L31<=95%,"B",L31>95%,"C") -> A
B32: tunika06 белая | C32: ='Юнит 01-07.12'!AE31 -> 0 | D32: =C32/C$50 -> 0 | E32: =D32+E31 -> 0 | F32: =IF(AND(E32<=0),"C",IF(E32<=0.8,"A",IF(E32<=0.95,"B","C"))) -> C | G32: =VLOOKUP(B$30:B$50,I$30:M$50,5,0) -> A | I32: tunika05 белая распашная | J32: ='Юнит 01-07.12'!R30 -> 0 | K32: =J32/J$50 -> 0 | L32: =K32+L31 -> 0 | M32: =_xlfn.IFS(L32<80%,"A",L32<=95%,"B",L32>95%,"C") -> A
B33: tunika06 черная | C33: ='Юнит 01-07.12'!AE32 -> 0 | D33: =C33/C$50 -> 0 | E33: =D33+E32 -> 0 | F33: =IF(AND(E33<=0),"C",IF(E33<=0.8,"A",IF(E33<=0.95,"B","C"))) -> C | G33: =VLOOKUP(B$30:B$50,I$30:M$50,5,0) -> A | I33: tunika06 белая | J33: ='Юнит 01-07.12'!R31 -> 0 | K33: =J33/J$50 -> 0 | L33: =K33+L32 -> 0 | M33: =_xlfn.IFS(L33<80%,"A",L33<=95%,"B",L33>95%,"C") -> A
B34: tunika07 кружево | C34: ='Юнит 01-07.12'!AE33 -> 0 | D34: =C34/C$50 -> 0 | E34: =D34+E33 -> 0 | F34: =IF(AND(E34<=0),"C",IF(E34<=0.8,"A",IF(E34<=0.95,"B","C"))) -> C | G34: =VLOOKUP(B$30:B$50,I$30:M$50,5,0) -> A | I34: tunika06 черная | J34: ='Юнит 01-07.12'!R32 -> 0 | K34: =J34/J$50 -> 0 | L34: =K34+L33 -> 0 | M34: =_xlfn.IFS(L34<80%,"A",L34<=95%,"B",L34>95%,"C") -> A
B35: tunika08 белая | C35: ='Юнит 01-07.12'!AE34 -> 0 | D35: =C35/C$50 -> 0 | E35: =D35+E34 -> 0 | F35: =IF(AND(E35<=0),"C",IF(E35<=0.8,"A",IF(E35<=0.95,"B","C"))) -> C | G35: =VLOOKUP(B$30:B$50,I$30:M$50,5,0) -> A | I35: tunika07 кружево | J35: ='Юнит 01-07.12'!R33 -> 0 | K35: =J35/J$50 -> 0 | L35: =K35+L34 -> 0 | M35: =_xlfn.IFS(L35<80%,"A",L35<=95%,"B",L35>95%,"C") -> A
B36: tunika08 черная | C36: ='Юнит 01-07.12'!AE35 -> 0 | D36: =C36/C$50 -> 0 | E36: =D36+E35 -> 0 | F36: =IF(AND(E36<=0),"C",IF(E36<=0.8,"A",IF(E36<=0.95,"B","C"))) -> C | G36: =VLOOKUP(B$30:B$50,I$30:M$50,5,0) -> A | I36: tunika08 белая | J36: ='Юнит 01-07.12'!R34 -> 0 | K36: =J36/J$50 -> 0 | L36: =K36+L35 -> 0 | M36: =_xlfn.IFS(L36<80%,"A",L36<=95%,"B",L36>95%,"C") -> A
B37: tunika08 зеленая | C37: ='Юнит 01-07.12'!AE36 -> 0 | D37: =C37/C$50 -> 0 | E37: =D37+E36 -> 0 | F37: =IF(AND(E37<=0),"C",IF(E37<=0.8,"A",IF(E37<=0.95,"B","C"))) -> C | G37: =VLOOKUP(B$30:B$50,I$30:M$50,5,0) -> A | I37: tunika08 черная | J37: ='Юнит 01-07.12'!R35 -> 0 | K37: =J37/J$50 -> 0 | L37: =K37+L36 -> 0 | M37: =_xlfn.IFS(L37<80%,"A",L37<=95%,"B",L37>95%,"C") -> A
B38: tunika09 кимоно | C38: ='Юнит 01-07.12'!AE37 -> 0 | D38: =C38/C$50 -> 0 | E38: =D38+E37 -> 0 | F38: =IF(AND(E38<=0),"C",IF(E38<=0.8,"A",IF(E38<=0.95,"B","C"))) -> C | G38: =VLOOKUP(B$30:B$50,I$30:M$50,5,0) -> A | I38: tunika08 зеленая | J38: ='Юнит 01-07.12'!R36 -> 0 | K38: =J38/J$50 -> 0 | L38: =K38+L37 -> 0 | M38: =_xlfn.IFS(L38<80%,"A",L38<=95%,"B",L38>95%,"C") -> A
B39: tunika10 кимоно ч/б | C39: ='Юнит 01-07.12'!AE38 -> 0 | D39: =C39/C$50 -> 0 | E39: =D39+E38 -> 0 | F39: =IF(AND(E39<=0),"C",IF(E39<=0.8,"A",IF(E39<=0.95,"B","C"))) -> C | G39: =VLOOKUP(B$30:B$50,I$30:M$50,5,0) -> A | I39: tunika09 кимоно | J39: ='Юнит 01-07.12'!R37 -> 0 | K39: =J39/J$50 -> 0 | L39: =K39+L38 -> 0 | M39: =_xlfn.IFS(L39<80%,"A",L39<=95%,"B",L39>95%,"C") -> A
B40: tunika12 халат белая | C40: ='Юнит 01-07.12'!AE40 -> 0 | D40: =C40/C$50 -> 0 | E40: =D40+E39 -> 0 | F40: =IF(AND(E40<=0),"C",IF(E40<=0.8,"A",IF(E40<=0.95,"B","C"))) -> C | G40: =VLOOKUP(B$30:B$50,I$30:M$50,5,0) -> A | I40: tunika10 кимоно ч/б | J40: ='Юнит 01-07.12'!R38 -> 0 | K40: =J40/J$50 -> 0 | L40: =K40+L39 -> 0 | M40: =_xlfn.IFS(L40<80%,"A",L40<=95%,"B",L40>95%,"C") -> A
B41: tunika13 халат черная | C41: ='Юнит 01-07.12'!AE41 -> 0 | D41: =C41/C$50 -> 0 | E41: =D41+E40 -> 0 | F41: =IF(AND(E41<=0),"C",IF(E41<=0.8,"A",IF(E41<=0.95,"B","C"))) -> C | G41: =VLOOKUP(B$30:B$50,I$30:M$50,5,0) -> A | I41: tunika12 халат белая | J41: ='Юнит 01-07.12'!R40 -> 0 | K41: =J41/J$50 -> 0 | L41: =K41+L40 -> 0 | M41: =_xlfn.IFS(L41<80%,"A",L41<=95%,"B",L41>95%,"C") -> A
B42: tunika14 халат с разрезами черный | C42: ='Юнит 01-07.12'!AE43 -> 0 | D42: =C42/C$50 -> 0 | E42: =D42+E41 -> 0 | F42: =IF(AND(E42<=0),"C",IF(E42<=0.8,"A",IF(E42<=0.95,"B","C"))) -> C | G42: =VLOOKUP(B$30:B$50,I$30:M$50,5,0) -> A | I42: tunika13 халат черная | J42: ='Юнит 01-07.12'!R41 -> 0 | K42: =J42/J$50 -> 0 | L42: =K42+L41 -> 0 | M42: =_xlfn.IFS(L42<80%,"A",L42<=95%,"B",L42>95%,"C") -> A
B43: tunika16 сетка белая | C43: ='Юнит 01-07.12'!AE46 -> 0 | D43: =C43/C$50 -> 0 | E43: =D43+E42 -> 0 | F43: =IF(AND(E43<=0),"C",IF(E43<=0.8,"A",IF(E43<=0.95,"B","C"))) -> C | G43: =VLOOKUP(B$30:B$50,I$30:M$50,5,0) -> A | I43: tunika14 халат с разрезами белая | J43: ='Юнит 01-07.12'!R42 -> 0 | K43: =J43/J$50 -> 0 | L43: =K43+L42 -> 0 | M43: =_xlfn.IFS(L43<80%,"A",L43<=95%,"B",L43>95%,"C") -> A
B44: tunika16 сетка черная | C44: ='Юнит 01-07.12'!AE47 -> 0 | D44: =C44/C$50 -> 0 | E44: =D44+E43 -> 0 | F44: =IF(AND(E44<=0),"C",IF(E44<=0.8,"A",IF(E44<=0.95,"B","C"))) -> C | G44: =VLOOKUP(B$30:B$50,I$30:M$50,5,0) -> A | I44: tunika14 халат с разрезами черный | J44: ='Юнит 01-07.12'!R43 -> 0 | K44: =J44/J$50 -> 0 | L44: =K44+L43 -> 0 | M44: =_xlfn.IFS(L44<80%,"A",L44<=95%,"B",L44>95%,"C") -> A
B45: tunika14 халат с разрезами белая | C45: ='Юнит 01-07.12'!AE42 -> -112 | D45: =C45/C$50 -> 0.025219375 | E45: =D45+E44 -> 0.025219375 | F45: =IF(AND(E45<=0),"C",IF(E45<=0.8,"A",IF(E45<=0.95,"B","C"))) -> A | G45: =VLOOKUP(B$30:B$50,I$30:M$50,5,0) -> A | I45: tunika15 кимоно бирюза | J45: ='Юнит 01-07.12'!R44 -> 0 | K45: =J45/J$50 -> 0 | L45: =K45+L44 -> 0 | M45: =_xlfn.IFS(L45<80%,"A",L45<=95%,"B",L45>95%,"C") -> A
B46: tunika15 кимоно бирюза | C46: ='Юнит 01-07.12'!AE44 -> -112 | D46: =C46/C$50 -> 0.025219375 | E46: =D46+E45 -> 0.05043875 | F46: =IF(AND(E46<=0),"C",IF(E46<=0.8,"A",IF(E46<=0.95,"B","C"))) -> A | G46: =VLOOKUP(B$30:B$50,I$30:M$50,5,0) -> A | I46: tunika15 кимоно песочная | J46: ='Юнит 01-07.12'!R45 -> 0 | K46: =J46/J$50 -> 0 | L46: =K46+L45 -> 0 | M46: =_xlfn.IFS(L46<80%,"A",L46<=95%,"B",L46>95%,"C") -> A
B47: tunika02 оливковая с руч вышивкой | C47: ='Юнит 01-07.12'!AE28 -> -352.03 | D47: =C47/C$50 -> 0.079267647 | E47: =D47+E46 -> 0.1297064 | F47: =IF(AND(E47<=0),"C",IF(E47<=0.8,"A",IF(E47<=0.95,"B","C"))) -> A | G47: =VLOOKUP(B$30:B$50,I$30:M$50,5,0) -> A | I47: tunika16 сетка белая | J47: ='Юнит 01-07.12'!R46 -> 0 | K47: =J47/J$50 -> 0 | L47: =K47+L46 -> 0 | M47: =_xlfn.IFS(L47<80%,"A",L47<=95%,"B",L47>95%,"C") -> A
B48: tunika15 кимоно песочная | C48: ='Юнит 01-07.12'!AE45 -> -1489 | D48: =C48/C$50 -> 0.33528258 | E48: =D48+E47 -> 0.46498898 | F48: =IF(AND(E48<=0),"C",IF(E48<=0.8,"A",IF(E48<=0.95,"B","C"))) -> A | G48: =VLOOKUP(B$30:B$50,I$30:M$50,5,0) -> A | I48: tunika16 сетка черная | J48: ='Юнит 01-07.12'!R47 -> 0 | K48: =J48/J$50 -> 0 | L48: =K48+L47 -> 0 | M48: =_xlfn.IFS(L48<80%,"A",L48<=95%,"B",L48>95%,"C") -> A
B49: tunika11 халат зеленая | C49: ='Юнит 01-07.12'!AE39 -> -2376 | D49: =C49/C$50 -> 0.53501102 | E49: =D49+E48 -> 1 | F49: =IF(AND(E49<=0),"C",IF(E49<=0.8,"A",IF(E49<=0.95,"B","C"))) -> C | G49: =VLOOKUP(B$30:B$50,I$30:M$50,5,0) -> C | I49: tunika11 халат зеленая | J49: ='Юнит 01-07.12'!R39 -> -1 | K49: =J49/J$50 -> 1 | L49: =K49+L48 -> 1 | M49: =_xlfn.IFS(L49<80%,"A",L49<=95%,"B",L49>95%,"C") -> C
C50: =SUM(C30:C49) -> -4441.03 | D50: =SUM(D30:D49) -> 1 | J50: =SUM(J30:J49) -> -1 | K50: =SUM(K30:K49) -> 1

Sheet АВС НОЯБРЬ
B2: ОЧКИ
C3: Прибыль | D3: % прибыль | E3: Доля | F3: ABC прибыль | G3: ABC кол-во | J3: Кол-во | K3: % кол-во | L3: Доля | M3: ABC кол-во
B4: MR Р1874 черн | C4: =НОЯБРЬ!AE13 -> 2399.52 | D4: =C4/C$26 -> -0.45057988 | E4: =D4 -> -0.45057988 | F4: =IF(AND(E4<=0),"C",IF(E4<=0.8,"A",IF(E4<=0.95,"B","C"))) -> C | G4: =VLOOKUP(B$4:B$25,I$4:M$25,5,0) -> B | I4: qs желтые | J4: =НОЯБРЬ!R6 -> 51 | K4: =J4/J$26 -> 0.5 | L4: =K4 -> 0.5 | M4: =_xlfn.IFS(L4<80%,"A",L4<=95%,"B",L4>95%,"C") -> A
B5: lux6 | C5: =НОЯБРЬ!AE22 -> 1369.48 | D5: =C5/C$26 -> -0.25715982 | E5: =D5+E4 -> -0.7077397 | F5: =IF(AND(E5<=0),"C",IF(E5<=0.8,"A",IF(E5<=0.95,"B","C"))) -> C | G5: =VLOOKUP(B$4:B$25,I$4:M$25,5,0) -> B | I5: черные с железкой классика | J5: =НОЯБРЬ!R3 -> 26 | K5: =J5/J$26 -> 0.25490196 | L5: =K5+L4 -> 0.75490196 | M5: =_xlfn.IFS(L5<80%,"A",L5<=95%,"B",L5>95%,"C") -> A
B6: MR 1819 черн | C6: =НОЯБРЬ!AE11 -> 792.11 | D6: =C6/C$26 -> -0.14874176 | E6: =D6+E5 -> -0.85648146 | F6: =IF(AND(E6<=0),"C",IF(E6<=0.8,"A",IF(E6<=0.95,"B","C"))) -> C | G6: =VLOOKUP(B$4:B$25,I$4:M$25,5,0) -> B | I6: MR Р1874 черн | J6: =НОЯБРЬ!R13 -> 5 | K6: =J6/J$26 -> 0.049019608 | L6: =K6+L5 -> 0.80392157 | M6: =_xlfn.IFS(L6<80%,"A",L6<=95%,"B",L6>95%,"C") -> B
